Workbook

Sheet 1
A2: Гончарова Марина Алексеевна | B2: Группа отчетности по заработной плате | C2: Руководитель группы
A3: Макаенко Анастасия Леонидовна | B3: Отдел специальной оценки условий труда и оценки профессиональных | C3: Начальник отдела
A5: 0.3 | B5: основной единый тариф страховых взносов
A6: 0.037 | B6: НС, без скидки
B7: страховые взносы по дополнительному тарифу:
A8: 0.04 | B8: оценка труда, 3.2
A9: 0.02 | B9: оценка труда, 3.1
A12: Власенко Светлана Леонидовна | B12: Дирекция по экономике и финансам | C12: Старший бизнес-партнер
A14: Давыденко Сергей Александрович | B14: Дирекция по персоналу | C14: Бизнес-партнер по управлению персоналом

Sheet Версии
B1: 1
B2: 1 | C2: Данные для расчета по варианту "Производство"
B3: 1
B4: 1 | C4: Модель | D4: г/п, т | E4: КИГ | F4: Вес, т | G4: Погрузка, мин | H4: Разгрузка, мин | I4: Норма топлива, г/ткм | J4: Пробег шин, тыс. км | K4: Эксплуатация, лет | L4: Техн скорость, км/час
B5: =IF(C5=0,0,1) -> 1 | C5: =Производительность_1!C24 -> NHL NTE 240 | D5: =Производительность_1!E24 -> 227.8 | E5: =Производительность_1!E40 -> 0.98371378 | F5: =Производительность_1!E24 -> 227.8 | G5: =Простои!AA9 -> 3.5 | H5: =Простои!AC9 -> 0.8 | I5: ='ФОТ, МТР, макро'!O5 -> 90 | J5: ='ФОТ, МТР, макро'!Y5 -> 80 | K5: =Производительность_1!Y56 -> 20 | L5: =Производительность_1!E152 -> 22.46
B6: =IF(C6=0,0,1) -> 1 | C6: =Производительность_1!C25 -> Estar ESDE240 (ГПБ К) | D6: =Производительность_1!E25 -> 211.392 | E6: =Производительность_1!E41 -> 0.98371378 | F6: =Производительность_1!E25 -> 211.392 | G6: =Простои!AA10 -> 3.5 | H6: =Простои!AC10 -> 0.8 | I6: ='ФОТ, МТР, макро'!O6 -> 90 | J6: ='ФОТ, МТР, макро'!Y6 -> 80 | K6: =Производительность_1!Y57 -> 10 | L6: =Производительность_1!E153 -> 22.46
B7: =IF(C7=0,0,1) -> 1 | C7: =Производительность_1!C26 -> SANY SET240S | D7: =Производительность_1!E26 -> 216.362 | E7: =Производительность_1!E42 -> 0.98371378 | F7: =Производительность_1!E26 -> 216.362 | G7: =Простои!AA11 -> 3.5 | H7: =Простои!AC11 -> 0.8 | I7: ='ФОТ, МТР, макро'!O7 -> 90 | J7: ='ФОТ, МТР, макро'!Y7 -> 80 | K7: =Производительность_1!Y58 -> 12 | L7: =Производительность_1!E154 -> 22.46
B8: =IF(C8=0,0,1) -> 1 | C8: =Производительность_1!C27 -> TZCO TZE240 | D8: =Производительность_1!E27 -> 222 | E8: =Производительность_1!E43 -> 0.98371378 | F8: =Производительность_1!E27 -> 222 | G8: =Простои!AA12 -> 3.5 | H8: =Простои!AC12 -> 0.8 | I8: ='ФОТ, МТР, макро'!O8 -> 90 | J8: ='ФОТ, МТР, макро'!Y8 -> 80 | K8: =Производительность_1!Y59 -> 8 | L8: =Производительность_1!E155 -> 22.46
B9: =IF(C9=0,0,1) -> 1 | C9: =Производительность_1!C28 -> БелАЗ 7531 (ГПФК) | D9: =Производительность_1!E28 -> 231 | E9: =Производительность_1!E44 -> 0.98371378 | F9: =Производительность_1!E28 -> 231 | G9: =Простои!AA13 -> 3.5 | H9: =Простои!AC13 -> 0.8 | I9: ='ФОТ, МТР, макро'!O9 -> 90 | J9: ='ФОТ, МТР, макро'!Y9 -> 90 | K9: =Производительность_1!Y60 -> 10 | L9: =Производительность_1!E156 -> 22.46
B10: =IF(C10=0,0,1) -> 1 | C10: =Производительность_1!C29 -> XCMG 240 | D10: =Производительность_1!E29 -> 211.392 | E10: =Производительность_1!E45 -> 0.98371378 | F10: =Производительность_1!E29 -> 211.392 | G10: =Простои!AA14 -> 3.5 | H10: =Простои!AC14 -> 0.8 | I10: ='ФОТ, МТР, макро'!O10 -> 90 | J10: ='ФОТ, МТР, макро'!Y10 -> 80 | K10: =Производительность_1!Y61 -> 0 | L10: =Производительность_1!E157 -> 22.46
B11: =IF(C11=0,0,1) -> 1 | C11: =Производительность_1!C30 -> БелАЗ 7531 (БТЛ) | D11: =Производительность_1!E30 -> 231 | E11: =Производительность_1!E46 -> 0.98371378 | F11: =Производительность_1!E30 -> 231 | G11: =Простои!AA15 -> 3.5 | H11: =Простои!AC15 -> 0.8 | I11: ='ФОТ, МТР, макро'!O11 -> 90 | J11: ='ФОТ, МТР, макро'!Y11 -> 80 | K11: =Производительность_1!Y62 -> 10 | L11: =Производительность_1!E158 -> 22.46
B12: =IF(C12=0,0,1) -> 0 | C12: =Производительность_1!C31 -> 0 | D12: =Производительность_1!E31 -> 0 | E12: =Производительность_1!E47 -> 0 | F12: =Производительность_1!E31 -> 0 | G12: =Простои!AA16 -> 0 | H12: =Простои!AC16 -> 0 | I12: ='ФОТ, МТР, макро'!O12 -> 0 | J12: ='ФОТ, МТР, макро'!Y12 -> 0 | K12: =Производительность_1!Y63 -> 0 | L12: =Производительность_1!E159 -> 0
B13: =IF(C13=0,0,1) -> 0 | C13: =Производительность_1!C32 -> 0 | D13: =Производительность_1!E32 -> 0 | E13: =Производительность_1!E48 -> 0 | F13: =Производительность_1!E32 -> 0 | G13: =Простои!AA17 -> 0 | H13: =Простои!AC17 -> 0 | I13: ='ФОТ, МТР, макро'!O13 -> 0 | J13: ='ФОТ, МТР, макро'!Y13 -> 0 | K13: =Производительность_1!Y64 -> 0 | L13: =Производительность_1!E160 -> 0
B14: =IF(C14=0,0,1) -> 0 | C14: =Производительность_1!C33 -> 0 | D14: =Производительность_1!E33 -> 0 | E14: =Производительность_1!E49 -> 0 | F14: =Производительность_1!E33 -> 0 | G14: =Простои!AA18 -> 0 | H14: =Простои!AC18 -> 0 | I14: ='ФОТ, МТР, макро'!O14 -> 0 | J14: ='ФОТ, МТР, макро'!Y14 -> 0 | K14: =Производительность_1!Y65 -> 0 | L14: =Производительность_1!E161 -> 0
B15: =IF(C15=0,0,1) -> 0 | C15: =Производительность_1!C34 -> 0 | D15: =Производительность_1!E34 -> 0 | E15: =Производительность_1!E50 -> 0 | F15: =Производительность_1!E34 -> 0 | G15: =Простои!AA19 -> 0 | H15: =Простои!AC19 -> 0 | I15: ='ФОТ, МТР, макро'!O15 -> 0 | J15: ='ФОТ, МТР, макро'!Y15 -> 0 | K15: =Производительность_1!Y66 -> 0 | L15: =Производительность_1!E162 -> 0
B16: =IF(C16=0,0,1) -> 0 | C16: =Производительность_1!C35 -> 0 | D16: =Производительность_1!E35 -> 0 | E16: =Производительность_1!E51 -> 0 | F16: =Производительность_1!E35 -> 0 | G16: =Простои!AA20 -> 0 | H16: =Простои!AC20 -> 0 | I16: ='ФОТ, МТР, макро'!O16 -> 0 | J16: ='ФОТ, МТР, макро'!Y16 -> 0 | K16: =Производительность_1!Y67 -> 0 | L16: =Производительность_1!E163 -> 0
... B19: =IF(C19=0,0,1) -> 0 | C19: =Производительность_1!C38 -> 0 | D19: =Производительность_1!E38 -> 0 | E19: =Производительность_1!E54 -> 0 | F19: =Производительность_1!E38 -> 0 | G19: =Простои!AA23 -> 0 | H19: =Простои!AC23 -> 0 | I19: ='ФОТ, МТР, макро'!O19 -> 0 | J19: ='ФОТ, МТР, макро'!Y19 -> 0 | K19: =Производительность_1!Y70 -> 0 | L19: =Производительность_1!E166 -> 0
B20: 1
B21: 1
B22: 1
B23: 1 | C23: КТГ
B24: 1
B25: 1 | C25: КТГ по годам старения в расчете | D25: =Производительность_1!D4 -> Ед. изм. | E25: =Производительность_1!E4 -> 1 | F25: =Производительность_1!F4 -> 2 | G25: =Производительность_1!G4 -> 3 | H25: =Производительность_1!H4 -> 4 | I25: =Производительность_1!I4 -> 5 | J25: =Производительность_1!J4 -> 6 | K25: =Производительность_1!K4 -> 7 | ... X25: =Производительность_1!X4 -> 20 | Y25: Средний
B26: =B5 -> 1 | C26: =C5 -> NHL NTE 240 | D26: =Производительность_1!D56 -> коэфф. | E26: =Производительность_1!E56 -> 0.93755029 | F26: =Производительность_1!F56 -> 0.93038071 | G26: =Производительность_1!G56 -> 0.92090265 | H26: =Производительность_1!H56 -> 0.90840582 | I26: =Производительность_1!I56 -> 0.93333289 | J26: =Производительность_1!J56 -> 0.92172393 | K26: =Производительность_1!K56 -> 0.93126858 | ... X26: =Производительность_1!X56 -> 0.92201249 | Y26: =Производительность_1!Z56 -> 0.92288816 | Z26: =Производительность_1!AA56 -> 0
B27: =B6 -> 1 | C27: =C6 -> Estar ESDE240 (ГПБ К) | D27: =Производительность_1!D57 -> коэфф. | E27: =Производительность_1!E57 -> 0.91162481 | F27: =Производительность_1!F57 -> 0.89608701 | G27: =Производительность_1!G57 -> 0.84869673 | H27: =Производительность_1!H57 -> 0.80563483 | I27: =Производительность_1!I57 -> 0.89852867 | J27: =Производительность_1!J57 -> 0.8220605 | K27: =Производительность_1!K57 -> 0.88942796 | ... X27: =Производительность_1!X57 -> 0 | Y27: =Производительность_1!Z57 -> 0.8573313 | Z27: =Производительность_1!AA57 -> 0
B28: =B7 -> 1 | C28: =C7 -> SANY SET240S | D28: =Производительность_1!D58 -> коэфф. | E28: =Производительность_1!E58 -> 0.9357084 | F28: =Производительность_1!F58 -> 0.90263508 | G28: =Производительность_1!G58 -> 0.86578831 | H28: =Производительность_1!H58 -> 0.90352296 | I28: =Производительность_1!I58 -> 0.85025051 | J28: =Производительность_1!J58 -> 0.90352296 | K28: =Производительность_1!K58 -> 0.86578831 | ... X28: =Производительность_1!X58 -> 0 | Y28: =Производительность_1!Z58 -> 0.88337931 | Z28: =Производительность_1!AA58 -> 0
B29: =B8 -> 1 | C29: =C8 -> TZCO TZE240 | D29: =Производительность_1!D59 -> коэфф. | E29: =Производительность_1!E59 -> 0.90962709 | F29: =Производительность_1!F59 -> 0.88376776 | G29: =Производительность_1!G59 -> 0.77400431 | H29: =Производительность_1!H59 -> 0.88376776 | I29: =Производительность_1!I59 -> 0.90962709 | J29: =Производительность_1!J59 -> 0.74814498 | K29: =Производительность_1!K59 -> 0.90962709 | ... X29: =Производительность_1!X59 -> 0 | Y29: =Производительность_1!Z59 -> 0.86279173 | Z29: =Производительность_1!AA59 -> 0
B30: =B9 -> 1 | C30: =C9 -> БелАЗ 7531 (ГПФК) | D30: =Производительность_1!D60 -> коэфф. | E30: =Производительность_1!E60 -> 0.90830416 | F30: =Производительность_1!F60 -> 0.88577435 | G30: =Производительность_1!G60 -> 0.86468734 | H30: =Производительность_1!H60 -> 0.87460194 | I30: =Производительность_1!I60 -> 0.88129799 | J30: =Производительность_1!J60 -> 0.84567204 | K30: =Производительность_1!K60 -> 0.89713174 | ... X30: =Производительность_1!X60 -> 0 | Y30: =Производительность_1!Z60 -> 0.87156467 | Z30: =Производительность_1!AA60 -> 0
B31: =B10 -> 1 | C31: =C10 -> XCMG 240 | D31: =Производительность_1!D61 -> коэфф. | E31: =Производительность_1!E61 -> 0 | F31: =Производительность_1!F61 -> 0 | G31: =Производительность_1!G61 -> 0 | H31: =Производительность_1!H61 -> 0 | I31: =Производительность_1!I61 -> 0 | J31: =Производительность_1!J61 -> 0 | K31: =Производительность_1!K61 -> 0 | ... X31: =Производительность_1!X61 -> 0 | Y31: =Производительность_1!Z61 -> #DIV/0! | Z31: =Производительность_1!AA61 -> 0
B32: =B11 -> 1 | C32: =C11 -> БелАЗ 7531 (БТЛ) | D32: =Производительность_1!D62 -> коэфф. | E32: =Производительность_1!E62 -> 0.92956037 | F32: =Производительность_1!F62 -> 0.90792065 | G32: =Производительность_1!G62 -> 0.89941186 | H32: =Производительность_1!H62 -> 0.88050754 | I32: =Производительность_1!I62 -> 0.90115061 | J32: =Производительность_1!J62 -> 0.87025999 | K32: =Производительность_1!K62 -> 0.85058935 | ... X32: =Производительность_1!X62 -> 0 | Y32: =Производительность_1!Z62 -> 0.88411536 | Z32: =Производительность_1!AA62 -> 0
B33: =B12 -> 0 | C33: =C12 -> 0 | D33: =Производительность_1!D63 -> коэфф. | E33: =Производительность_1!E63 -> 0 | F33: =Производительность_1!F63 -> 0 | G33: =Производительность_1!G63 -> 0 | H33: =Производительность_1!H63 -> 0 | I33: =Производительность_1!I63 -> 0 | J33: =Производительность_1!J63 -> 0 | K33: =Производительность_1!K63 -> 0 | ... X33: =Производительность_1!X63 -> 0 | Y33: =Производительность_1!Z63 -> #DIV/0! | Z33: =Производительность_1!AA63 -> 0
B34: =B13 -> 0 | C34: =C13 -> 0 | D34: =Производительность_1!D64 -> коэфф. | E34: =Производительность_1!E64 -> 0 | F34: =Производительность_1!F64 -> 0 | G34: =Производительность_1!G64 -> 0 | H34: =Производительность_1!H64 -> 0 | I34: =Производительность_1!I64 -> 0 | J34: =Производительность_1!J64 -> 0 | K34: =Производительность_1!K64 -> 0 | ... X34: =Производительность_1!X64 -> 0 | Y34: =Производительность_1!Z64 -> #DIV/0! | Z34: =Производительность_1!AA64 -> 0
B35: =B14 -> 0 | C35: =C14 -> 0 | D35: =Производительность_1!D65 -> коэфф. | E35: =Производительность_1!E65 -> 0 | F35: =Производительность_1!F65 -> 0 | G35: =Производительность_1!G65 -> 0 | H35: =Производительность_1!H65 -> 0 | I35: =Производительность_1!I65 -> 0 | J35: =Производительность_1!J65 -> 0 | K35: =Производительность_1!K65 -> 0 | ... X35: =Производительность_1!X65 -> 0 | Y35: =Производительность_1!Z65 -> #DIV/0! | Z35: =Производительность_1!AA65 -> 0
B36: =B15 -> 0 | C36: =C15 -> 0 | D36: =Производительность_1!D66 -> коэфф. | E36: =Производительность_1!E66 -> 0 | F36: =Производительность_1!F66 -> 0 | G36: =Производительность_1!G66 -> 0 | H36: =Производительность_1!H66 -> 0 | I36: =Производительность_1!I66 -> 0 | J36: =Производительность_1!J66 -> 0 | K36: =Производительность_1!K66 -> 0 | ... X36: =Производительность_1!X66 -> 0 | Y36: =Производительность_1!Z66 -> #DIV/0! | Z36: =Производительность_1!AA66 -> 0
B37: =B16 -> 0 | C37: =C16 -> 0 | D37: =Производительность_1!D67 -> коэфф. | E37: =Производительность_1!E67 -> 0 | F37: =Производительность_1!F67 -> 0 | G37: =Производительность_1!G67 -> 0 | H37: =Производительность_1!H67 -> 0 | I37: =Производительность_1!I67 -> 0 | J37: =Производительность_1!J67 -> 0 | K37: =Производительность_1!K67 -> 0 | ... X37: =Производительность_1!X67 -> 0 | Y37: =Производительность_1!Z67 -> #DIV/0! | Z37: =Производительность_1!AA67 -> 0
... B40: =B19 -> 0 | C40: =C19 -> 0 | D40: =Производительность_1!D70 -> коэфф. | E40: =Производительность_1!E70 -> 0 | F40: =Производительность_1!F70 -> 0 | G40: =Производительность_1!G70 -> 0 | H40: =Производительность_1!H70 -> 0 | I40: =Производительность_1!I70 -> 0 | J40: =Производительность_1!J70 -> 0 | K40: =Производительность_1!K70 -> 0 | ... X40: =Производительность_1!X70 -> 0 | Y40: =Производительность_1!Z70 -> #DIV/0! | Z40: =Производительность_1!AA70 -> 0
B41: =B20 -> 1
B42: 1
B43: 1 | C43: КТГ поставщиков (текущий тендер) | D43: =D25 -> Ед. изм. | E43: =E25 -> 1 | F43: =F25 -> 2 | G43: =G25 -> 3 | H43: =H25 -> 4 | I43: =I25 -> 5 | J43: =J25 -> 6 | K43: =K25 -> 7 | ... Y43: =Y25 -> Средний
B44: =B26 -> 1 | C44: =C26 -> NHL NTE 240 | D44: =D26 -> коэфф. | E44: =Производительность!E56 -> 0.93755029 | F44: =Производительность!F56 -> 0.93038071 | G44: =Производительность!G56 -> 0.92090265 | H44: =Производительность!H56 -> 0.90840582 | I44: =Производительность!I56 -> 0.93333289 | J44: =Производительность!J56 -> 0.92172393 | K44: =Производительность!K56 -> 0.93126858 | L44: =Производительность!L56 -> 0.91113604 | ... X44: =Производительность!X56 -> 0.92201249 | Y44: =Производительность!Z56 -> 0.92288816 | Z44: =Производительность!AA56 -> данные поставщика от 27.07.2026
B45: =B27 -> 1 | C45: =C27 -> Estar ESDE240 (ГПБ К) | D45: =D27 -> коэфф. | E45: =Производительность!E57 -> 0.91162481 | F45: =Производительность!F57 -> 0.89608701 | G45: =Производительность!G57 -> 0.84869673 | H45: =Производительность!H57 -> 0.80563483 | I45: =Производительность!I57 -> 0.89852867 | J45: =Производительность!J57 -> 0.8220605 | K45: =Производительность!K57 -> 0.88942796 | L45: =Производительность!L57 -> 0.81118404 | ... X45: =Производительность!X57 -> 0 | Y45: =Производительность!Z57 -> 0.8573313 | Z45: =Производительность!AA57 -> данные поставщика от 24.07.2026
B46: =B28 -> 1 | C46: =C28 -> SANY SET240S | D46: =D28 -> коэфф. | E46: =Производительность!E58 -> 0.9357084 | F46: =Производительность!F58 -> 0.90263508 | G46: =Производительность!G58 -> 0.86578831 | H46: =Производительность!H58 -> 0.90352296 | I46: =Производительность!I58 -> 0.85025051 | J46: =Производительность!J58 -> 0.90352296 | K46: =Производительность!K58 -> 0.86578831 | L46: =Производительность!L58 -> 0.90352296 | ... X46: =Производительность!X58 -> 0 | Y46: =Производительность!Z58 -> 0.88337931 | Z46: =Производительность!AA58 -> данные поставщика от 16.07.2026
B47: =B29 -> 1 | C47: =C29 -> TZCO TZE240 | D47: =D29 -> коэфф. | E47: =Производительность!E59 -> 0.90962709 | F47: =Производительность!F59 -> 0.88376776 | G47: =Производительность!G59 -> 0.77400431 | H47: =Производительность!H59 -> 0.88376776 | I47: =Производительность!I59 -> 0.90962709 | J47: =Производительность!J59 -> 0.74814498 | K47: =Производительность!K59 -> 0.90962709 | L47: =Производительность!L59 -> 0.88376776 | ... X47: =Производительность!X59 -> 0 | Y47: =Производительность!Z59 -> 0.86279173 | Z47: =Производительность!AA59 -> данные поставщика от 15.07.2026
B48: =B30 -> 1 | C48: =C30 -> БелАЗ 7531 (ГПФК) | D48: =D30 -> коэфф. | E48: =Производительность!E60 -> 0.90830416 | F48: =Производительность!F60 -> 0.88577435 | G48: =Производительность!G60 -> 0.86468734 | H48: =Производительность!H60 -> 0.87460194 | I48: =Производительность!I60 -> 0.88129799 | J48: =Производительность!J60 -> 0.84567204 | K48: =Производительность!K60 -> 0.89713174 | L48: =Производительность!L60 -> 0.85462477 | ... X48: =Производительность!X60 -> 0 | Y48: =Производительность!Z60 -> 0.87156467 | Z48: =Производительность!AA60 -> данные поставщика от 09.07.2026
B49: =B31 -> 1 | C49: =C31 -> XCMG 240 | D49: =D31 -> коэфф. | E49: =Производительность!E61 -> 0 | F49: =Производительность!F61 -> 0 | G49: =Производительность!G61 -> 0 | H49: =Производительность!H61 -> 0 | I49: =Производительность!I61 -> 0 | J49: =Производительность!J61 -> 0 | K49: =Производительность!K61 -> 0 | L49: =Производительность!L61 -> 0 | ... X49: =Производительность!X61 -> 0 | Y49: =Производительность!Z61 -> #DIV/0! | Z49: =Производительность!AA61 -> нет данных
B50: =B32 -> 1 | C50: =C32 -> БелАЗ 7531 (БТЛ) | D50: =D32 -> коэфф. | E50: =Производительность!E62 -> 0.92956037 | F50: =Производительность!F62 -> 0.90792065 | G50: =Производительность!G62 -> 0.89941186 | H50: =Производительность!H62 -> 0.88050754 | I50: =Производительность!I62 -> 0.90115061 | J50: =Производительность!J62 -> 0.87025999 | K50: =Производительность!K62 -> 0.85058935 | L50: =Производительность!L62 -> 0.89171695 | ... X50: =Производительность!X62 -> 0 | Y50: =Производительность!Z62 -> 0.88411536 | Z50: =Производительность!AA62 -> данные поставщика от 22.07.2026
B51: =B33 -> 0 | C51: =C33 -> 0 | D51: =D33 -> коэфф. | E51: =Производительность!E63 -> 0 | F51: =Производительность!F63 -> 0 | G51: =Производительность!G63 -> 0 | H51: =Производительность!H63 -> 0 | I51: =Производительность!I63 -> 0 | J51: =Производительность!J63 -> 0 | K51: =Производительность!K63 -> 0 | L51: =Производительность!L63 -> 0 | ... X51: =Производительность!X63 -> 0 | Y51: =Производительность!Z63 -> #DIV/0! | Z51: =Производительность!AA63 -> 0
B52: =B34 -> 0 | C52: =C34 -> 0 | D52: =D34 -> коэфф. | E52: =Производительность!E64 -> 0 | F52: =Производительность!F64 -> 0 | G52: =Производительность!G64 -> 0 | H52: =Производительность!H64 -> 0 | I52: =Производительность!I64 -> 0 | J52: =Производительность!J64 -> 0 | K52: =Производительность!K64 -> 0 | L52: =Производительность!L64 -> 0 | ... X52: =Производительность!X64 -> 0 | Y52: =Производительность!Z64 -> #DIV/0! | Z52: =Производительность!AA64 -> 0
B53: =B35 -> 0 | C53: =C35 -> 0 | D53: =D35 -> коэфф. | E53: =Производительность!E65 -> 0 | F53: =Производительность!F65 -> 0 | G53: =Производительность!G65 -> 0 | H53: =Производительность!H65 -> 0 | I53: =Производительность!I65 -> 0 | J53: =Производительность!J65 -> 0 | K53: =Производительность!K65 -> 0 | L53: =Производительность!L65 -> 0 | ... X53: =Производительность!X65 -> 0 | Y53: =Производительность!Z65 -> #DIV/0! | Z53: =Производительность!AA65 -> 0
B54: =B36 -> 0 | C54: =C36 -> 0 | D54: =D36 -> коэфф. | E54: =Производительность!E66 -> 0 | F54: =Производительность!F66 -> 0 | G54: =Производительность!G66 -> 0 | H54: =Производительность!H66 -> 0 | I54: =Производительность!I66 -> 0 | J54: =Производительность!J66 -> 0 | K54: =Производительность!K66 -> 0 | L54: =Производительность!L66 -> 0 | ... X54: =Производительность!X66 -> 0 | Y54: =Производительность!Z66 -> #DIV/0! | Z54: =Производительность!AA66 -> 0
B55: =B37 -> 0 | C55: =C37 -> 0 | D55: =D37 -> коэфф. | E55: =Производительность!E67 -> 0 | F55: =Производительность!F67 -> 0 | G55: =Производительность!G67 -> 0 | H55: =Производительность!H67 -> 0 | I55: =Производительность!I67 -> 0 | J55: =Производительность!J67 -> 0 | K55: =Производительность!K67 -> 0 | L55: =Производительность!L67 -> 0 | ... X55: =Производительность!X67 -> 0 | Y55: =Производительность!Z67 -> #DIV/0! | Z55: =Производительность!AA67 -> 0
... B58: =B40 -> 0 | C58: =C40 -> 0 | D58: =D40 -> коэфф. | E58: =Производительность!E70 -> 0 | F58: =Производительность!F70 -> 0 | G58: =Производительность!G70 -> 0 | H58: =Производительность!H70 -> 0 | I58: =Производительность!I70 -> 0 | J58: =Производительность!J70 -> 0 | K58: =Производительность!K70 -> 0 | L58: =Производительность!L70 -> 0 | ... X58: =Производительность!X70 -> 0 | Y58: =Производительность!Z70 -> #DIV/0! | Z58: =Производительность!AA70 -> 0
B59: =B41 -> 1
B60: 1
B61: 1 | C61: КТГ тендер дек. 2024 | D61: =D43 -> Ед. изм. | E61: =E43 -> 1 | F61: =F43 -> 2 | G61: =G43 -> 3 | H61: =H43 -> 4 | I61: =I43 -> 5 | J61: =J43 -> 6 | K61: =K43 -> 7 | ... Y61: =Y43 -> Средний
B62: 1 | C62: NHL NTE 240 | D62: =D44 -> коэфф. | E62: 0.9210477 | F62: 0.90366926 | G62: 0.83779555 | H62: 0.86443487 | I62: 0.89167487 | J62: 0.88808059 | K62: 0.86356059 | L62: 0.88910345 | M62: 0.88895487 | N62: 0.86370345 | Y62: 0.88120252 | Z62: Первые 4 года - среднесрок, далее - на динамике от поставщика
B63: 1 | C63: ESTAR ESDE240 | D63: =D62 -> коэфф. | E63: 0.9210477 | F63: 0.90366926 | G63: 0.83779555 | H63: 0.86443487 | I63: 0.89167487 | J63: 0.88808059 | K63: 0.86356059 | L63: 0.88910345 | M63: 0.88895487 | N63: 0.86370345 | Y63: 0.88120252 | Z63: равно NTE 240
B64: 1 | C64: БелАЗ-7531H привод Силовые Маш | D64: =D63 -> коэфф. | E64: 0.77 | F64: 0.74735921 | G64: 0.70762684 | H64: 0.75483215 | I64: 0.74288284 | J64: 0.68861153 | K64: 0.7587166 | L64: 0.73485498 | M64: 0.68513403 | N64: 0.72294267 | Y64: 0.73129608 | Z64: 1-ый год - факт Карельского Окатыша (30 ед. БелАЗ-7531H, введенные 2023-2024), далее - динамика поставщика
B65: 1
B66: 1
B67: 1
B68: 1 | C68: Затраты на ТО и Ремонты | E68: ='ФОТ, МТР, макро'!AK7 -> 94.0485 | F68: ='ФОТ, МТР, макро'!AL7 -> 94.0485 | G68: ='ФОТ, МТР, макро'!AM7 -> 94.0485 | H68: ='ФОТ, МТР, макро'!AN7 -> 94.0485 | I68: ='ФОТ, МТР, макро'!AO7 -> 94.0485 | J68: ='ФОТ, МТР, макро'!AP7 -> 94.0485 | K68: ='ФОТ, МТР, макро'!AQ7 -> 94.0485 | L68: ='ФОТ, МТР, макро'!AR7 -> 94.0485 | ... X68: ='ФОТ, МТР, макро'!BD7 -> 94.0485 | Y68: руб/долл
B69: 1 | C69: включая смазочные и трудозатраты
B70: 1 | C70: Затраты в расчете | D70: =D25 -> Ед. изм. | E70: =E25 -> 1 | F70: =F25 -> 2 | G70: =G25 -> 3 | H70: =H25 -> 4 | I70: =I25 -> 5 | J70: =J25 -> 6 | K70: =K25 -> 7 | ... X70: =X25 -> 20 | Y70: Всего | Z70: Среднее | AA70: Производство/Поставщик
A71: ТО, ТР, ППР | B71: =B5 -> 1 | C71: =C5 -> NHL NTE 240 | D71: тыс. долл. | E71: =SUMIFS(ТСО_1!G:G,ТСО_1!$A:$A,$C71,ТСО_1!$C:$C,$A$71)/E$68 -> 63.91384 | F71: =SUMIFS(ТСО_1!H:H,ТСО_1!$A:$A,$C71,ТСО_1!$C:$C,$A$71)/F$68 -> 88.815489 | G71: =SUMIFS(ТСО_1!I:I,ТСО_1!$A:$A,$C71,ТСО_1!$C:$C,$A$71)/G$68 -> 526.21505 | H71: =SUMIFS(ТСО_1!J:J,ТСО_1!$A:$A,$C71,ТСО_1!$C:$C,$A$71)/H$68 -> 279.8431 | I71: =SUMIFS(ТСО_1!K:K,ТСО_1!$A:$A,$C71,ТСО_1!$C:$C,$A$71)/I$68 -> 93.326115 | J71: =SUMIFS(ТСО_1!L:L,ТСО_1!$A:$A,$C71,ТСО_1!$C:$C,$A$71)/J$68 -> 513.88141 | K71: =SUMIFS(ТСО_1!M:M,ТСО_1!$A:$A,$C71,ТСО_1!$C:$C,$A$71)/K$68 -> 86.516048 | L71: =SUMIFS(ТСО_1!N:N,ТСО_1!$A:$A,$C71,ТСО_1!$C:$C,$A$71)/L$68 -> 296.58055 | M71: =SUMIFS(ТСО_1!O:O,ТСО_1!$A:$A,$C71,ТСО_1!$C:$C,$A$71)/M$68 -> 958.65982 | N71: =SUMIFS(ТСО_1!P:P,ТСО_1!$A:$A,$C71,ТСО_1!$C:$C,$A$71)/N$68 -> 73.522262 | O71: =SUMIFS(ТСО_1!Q:Q,ТСО_1!$A:$A,$C71,ТСО_1!$C:$C,$A$71)/O$68 -> 2113.8489 | P71: =SUMIFS(ТСО_1!R:R,ТСО_1!$A:$A,$C71,ТСО_1!$C:$C,$A$71)/P$68 -> 515.23001 | Q71: =SUMIFS(ТСО_1!S:S,ТСО_1!$A:$A,$C71,ТСО_1!$C:$C,$A$71)/Q$68 -> 80.169897 | R71: =SUMIFS(ТСО_1!T:T,ТСО_1!$A:$A,$C71,ТСО_1!$C:$C,$A$71)/R$68 -> 81.530805 | S71: =SUMIFS(ТСО_1!U:U,ТСО_1!$A:$A,$C71,ТСО_1!$C:$C,$A$71)/S$68 -> 733.18369 | T71: =SUMIFS(ТСО_1!V:V,ТСО_1!$A:$A,$C71,ТСО_1!$C:$C,$A$71)/T$68 -> 81.693954 | U71: =SUMIFS(ТСО_1!W:W,ТСО_1!$A:$A,$C71,ТСО_1!$C:$C,$A$71)/U$68 -> 80.59716 | V71: =SUMIFS(ТСО_1!X:X,ТСО_1!$A:$A,$C71,ТСО_1!$C:$C,$A$71)/V$68 -> 1170.2928 | W71: =SUMIFS(ТСО_1!Y:Y,ТСО_1!$A:$A,$C71,ТСО_1!$C:$C,$A$71)/W$68 -> 83.014317 | X71: =SUMIFS(ТСО_1!Z:Z,ТСО_1!$A:$A,$C71,ТСО_1!$C:$C,$A$71)/X$68 -> 101.43293 | Y71: =SUM(E71:X71) -> 8022.2681 | Z71: =Y71/K5 -> 401.11341 | AA71: =IF(Y71=0,"-",Y71/Y89-1) -> 0
B72: =B6 -> 1 | C72: =C6 -> Estar ESDE240 (ГПБ К) | D72: =D71 -> тыс. долл. | E72: =SUMIFS(ТСО_1!G:G,ТСО_1!$A:$A,$C72,ТСО_1!$C:$C,$A$71)/E$68 -> 180.53003 | F72: =SUMIFS(ТСО_1!H:H,ТСО_1!$A:$A,$C72,ТСО_1!$C:$C,$A$71)/F$68 -> 276.72926 | G72: =SUMIFS(ТСО_1!I:I,ТСО_1!$A:$A,$C72,ТСО_1!$C:$C,$A$71)/G$68 -> 928.14011 | H72: =SUMIFS(ТСО_1!J:J,ТСО_1!$A:$A,$C72,ТСО_1!$C:$C,$A$71)/H$68 -> 2751.3389 | I72: =SUMIFS(ТСО_1!K:K,ТСО_1!$A:$A,$C72,ТСО_1!$C:$C,$A$71)/I$68 -> 184.23303 | J72: =SUMIFS(ТСО_1!L:L,ТСО_1!$A:$A,$C72,ТСО_1!$C:$C,$A$71)/J$68 -> 1024.3393 | K72: =SUMIFS(ТСО_1!M:M,ТСО_1!$A:$A,$C72,ТСО_1!$C:$C,$A$71)/K$68 -> 180.53003 | L72: =SUMIFS(ТСО_1!N:N,ТСО_1!$A:$A,$C72,ТСО_1!$C:$C,$A$71)/L$68 -> 2751.3389 | M72: =SUMIFS(ТСО_1!O:O,ТСО_1!$A:$A,$C72,ТСО_1!$C:$C,$A$71)/M$68 -> 180.53003 | N72: =SUMIFS(ТСО_1!P:P,ТСО_1!$A:$A,$C72,ТСО_1!$C:$C,$A$71)/N$68 -> 180.53003 | O72: =SUMIFS(ТСО_1!Q:Q,ТСО_1!$A:$A,$C72,ТСО_1!$C:$C,$A$71)/O$68 -> 0 | P72: =SUMIFS(ТСО_1!R:R,ТСО_1!$A:$A,$C72,ТСО_1!$C:$C,$A$71)/P$68 -> 0 | Q72: =SUMIFS(ТСО_1!S:S,ТСО_1!$A:$A,$C72,ТСО_1!$C:$C,$A$71)/Q$68 -> 0 | R72: =SUMIFS(ТСО_1!T:T,ТСО_1!$A:$A,$C72,ТСО_1!$C:$C,$A$71)/R$68 -> 0 | S72: =SUMIFS(ТСО_1!U:U,ТСО_1!$A:$A,$C72,ТСО_1!$C:$C,$A$71)/S$68 -> 0 | T72: =SUMIFS(ТСО_1!V:V,ТСО_1!$A:$A,$C72,ТСО_1!$C:$C,$A$71)/T$68 -> 0 | U72: =SUMIFS(ТСО_1!W:W,ТСО_1!$A:$A,$C72,ТСО_1!$C:$C,$A$71)/U$68 -> 0 | V72: =SUMIFS(ТСО_1!X:X,ТСО_1!$A:$A,$C72,ТСО_1!$C:$C,$A$71)/V$68 -> 0 | W72: =SUMIFS(ТСО_1!Y:Y,ТСО_1!$A:$A,$C72,ТСО_1!$C:$C,$A$71)/W$68 -> 0 | X72: =SUMIFS(ТСО_1!Z:Z,ТСО_1!$A:$A,$C72,ТСО_1!$C:$C,$A$71)/X$68 -> 0 | Y72: =SUM(E72:X72) -> 8638.2397 | Z72: =Y72/K6 -> 863.82397 | AA72: =IF(Y72=0,"-",Y72/Y90-1) -> 0
B73: =B7 -> 1 | C73: =C7 -> SANY SET240S | D73: =D72 -> тыс. долл. | E73: =SUMIFS(ТСО_1!G:G,ТСО_1!$A:$A,$C73,ТСО_1!$C:$C,$A$71)/E$68 -> 135.34771 | F73: =SUMIFS(ТСО_1!H:H,ТСО_1!$A:$A,$C73,ТСО_1!$C:$C,$A$71)/F$68 -> 211.26698 | G73: =SUMIFS(ТСО_1!I:I,ТСО_1!$A:$A,$C73,ТСО_1!$C:$C,$A$71)/G$68 -> 597.96064 | H73: =SUMIFS(ТСО_1!J:J,ТСО_1!$A:$A,$C73,ТСО_1!$C:$C,$A$71)/H$68 -> 305.14198 | I73: =SUMIFS(ТСО_1!K:K,ТСО_1!$A:$A,$C73,ТСО_1!$C:$C,$A$71)/I$68 -> 973.93701 | J73: =SUMIFS(ТСО_1!L:L,ТСО_1!$A:$A,$C73,ТСО_1!$C:$C,$A$71)/J$68 -> 741.2592 | K73: =SUMIFS(ТСО_1!M:M,ТСО_1!$A:$A,$C73,ТСО_1!$C:$C,$A$71)/K$68 -> 267.37571 | L73: =SUMIFS(ТСО_1!N:N,ТСО_1!$A:$A,$C73,ТСО_1!$C:$C,$A$71)/L$68 -> 268.93298 | M73: =SUMIFS(ТСО_1!O:O,ТСО_1!$A:$A,$C73,ТСО_1!$C:$C,$A$71)/M$68 -> 1349.3409 | N73: =SUMIFS(ТСО_1!P:P,ТСО_1!$A:$A,$C73,ТСО_1!$C:$C,$A$71)/N$68 -> 196.00098 | O73: =SUMIFS(ТСО_1!Q:Q,ТСО_1!$A:$A,$C73,ТСО_1!$C:$C,$A$71)/O$68 -> 258.79771 | P73: =SUMIFS(ТСО_1!R:R,ТСО_1!$A:$A,$C73,ТСО_1!$C:$C,$A$71)/P$68 -> 282.98871 | Q73: =SUMIFS(ТСО_1!S:S,ТСО_1!$A:$A,$C73,ТСО_1!$C:$C,$A$71)/Q$68 -> 0 | R73: =SUMIFS(ТСО_1!T:T,ТСО_1!$A:$A,$C73,ТСО_1!$C:$C,$A$71)/R$68 -> 0 | S73: =SUMIFS(ТСО_1!U:U,ТСО_1!$A:$A,$C73,ТСО_1!$C:$C,$A$71)/S$68 -> 0 | T73: =SUMIFS(ТСО_1!V:V,ТСО_1!$A:$A,$C73,ТСО_1!$C:$C,$A$71)/T$68 -> 0 | U73: =SUMIFS(ТСО_1!W:W,ТСО_1!$A:$A,$C73,ТСО_1!$C:$C,$A$71)/U$68 -> 0 | V73: =SUMIFS(ТСО_1!X:X,ТСО_1!$A:$A,$C73,ТСО_1!$C:$C,$A$71)/V$68 -> 0 | W73: =SUMIFS(ТСО_1!Y:Y,ТСО_1!$A:$A,$C73,ТСО_1!$C:$C,$A$71)/W$68 -> 0 | X73: =SUMIFS(ТСО_1!Z:Z,ТСО_1!$A:$A,$C73,ТСО_1!$C:$C,$A$71)/X$68 -> 0 | Y73: =SUM(E73:X73) -> 5588.3505 | Z73: =Y73/K7 -> 465.69588 | AA73: =IF(Y73=0,"-",Y73/Y91-1) -> 0
B74: =B8 -> 1 | C74: =C8 -> TZCO TZE240 | D74: =D73 -> тыс. долл. | E74: =SUMIFS(ТСО_1!G:G,ТСО_1!$A:$A,$C74,ТСО_1!$C:$C,$A$71)/E$68 -> 299.33592 | F74: =SUMIFS(ТСО_1!H:H,ТСО_1!$A:$A,$C74,ТСО_1!$C:$C,$A$71)/F$68 -> 629.57257 | G74: =SUMIFS(ТСО_1!I:I,ТСО_1!$A:$A,$C74,ТСО_1!$C:$C,$A$71)/G$68 -> 1881.2035 | H74: =SUMIFS(ТСО_1!J:J,ТСО_1!$A:$A,$C74,ТСО_1!$C:$C,$A$71)/H$68 -> 629.57257 | I74: =SUMIFS(ТСО_1!K:K,ТСО_1!$A:$A,$C74,ТСО_1!$C:$C,$A$71)/I$68 -> 299.33592 | J74: =SUMIFS(ТСО_1!L:L,ТСО_1!$A:$A,$C74,ТСО_1!$C:$C,$A$71)/J$68 -> 2211.4401 | K74: =SUMIFS(ТСО_1!M:M,ТСО_1!$A:$A,$C74,ТСО_1!$C:$C,$A$71)/K$68 -> 299.33592 | L74: =SUMIFS(ТСО_1!N:N,ТСО_1!$A:$A,$C74,ТСО_1!$C:$C,$A$71)/L$68 -> 629.57257 | M74: =SUMIFS(ТСО_1!O:O,ТСО_1!$A:$A,$C74,ТСО_1!$C:$C,$A$71)/M$68 -> 0 | N74: =SUMIFS(ТСО_1!P:P,ТСО_1!$A:$A,$C74,ТСО_1!$C:$C,$A$71)/N$68 -> 0 | O74: =SUMIFS(ТСО_1!Q:Q,ТСО_1!$A:$A,$C74,ТСО_1!$C:$C,$A$71)/O$68 -> 0 | P74: =SUMIFS(ТСО_1!R:R,ТСО_1!$A:$A,$C74,ТСО_1!$C:$C,$A$71)/P$68 -> 0 | Q74: =SUMIFS(ТСО_1!S:S,ТСО_1!$A:$A,$C74,ТСО_1!$C:$C,$A$71)/Q$68 -> 0 | R74: =SUMIFS(ТСО_1!T:T,ТСО_1!$A:$A,$C74,ТСО_1!$C:$C,$A$71)/R$68 -> 0 | S74: =SUMIFS(ТСО_1!U:U,ТСО_1!$A:$A,$C74,ТСО_1!$C:$C,$A$71)/S$68 -> 0 | T74: =SUMIFS(ТСО_1!V:V,ТСО_1!$A:$A,$C74,ТСО_1!$C:$C,$A$71)/T$68 -> 0 | U74: =SUMIFS(ТСО_1!W:W,ТСО_1!$A:$A,$C74,ТСО_1!$C:$C,$A$71)/U$68 -> 0 | V74: =SUMIFS(ТСО_1!X:X,ТСО_1!$A:$A,$C74,ТСО_1!$C:$C,$A$71)/V$68 -> 0 | W74: =SUMIFS(ТСО_1!Y:Y,ТСО_1!$A:$A,$C74,ТСО_1!$C:$C,$A$71)/W$68 -> 0 | X74: =SUMIFS(ТСО_1!Z:Z,ТСО_1!$A:$A,$C74,ТСО_1!$C:$C,$A$71)/X$68 -> 0 | Y74: =SUM(E74:X74) -> 6879.3691 | Z74: =Y74/K8 -> 859.92114 | AA74: =IF(Y74=0,"-",Y74/Y92-1) -> 0
B75: =B9 -> 1 | C75: =C9 -> БелАЗ 7531 (ГПФК) | D75: =D74 -> тыс. долл. | E75: =SUMIFS(ТСО_1!G:G,ТСО_1!$A:$A,$C75,ТСО_1!$C:$C,$A$71)/E$68 -> 148.04729 | F75: =SUMIFS(ТСО_1!H:H,ТСО_1!$A:$A,$C75,ТСО_1!$C:$C,$A$71)/F$68 -> 317.60136 | G75: =SUMIFS(ТСО_1!I:I,ТСО_1!$A:$A,$C75,ТСО_1!$C:$C,$A$71)/G$68 -> 572.06806 | H75: =SUMIFS(ТСО_1!J:J,ТСО_1!$A:$A,$C75,ТСО_1!$C:$C,$A$71)/H$68 -> 727.00656 | I75: =SUMIFS(ТСО_1!K:K,ТСО_1!$A:$A,$C75,ТСО_1!$C:$C,$A$71)/I$68 -> 631.62288 | J75: =SUMIFS(ТСО_1!L:L,ТСО_1!$A:$A,$C75,ТСО_1!$C:$C,$A$71)/J$68 -> 688.61907 | K75: =SUMIFS(ТСО_1!M:M,ТСО_1!$A:$A,$C75,ТСО_1!$C:$C,$A$71)/K$68 -> 180.49511 | L75: =SUMIFS(ТСО_1!N:N,ТСО_1!$A:$A,$C75,ТСО_1!$C:$C,$A$71)/L$68 -> 847.19412 | M75: =SUMIFS(ТСО_1!O:O,ТСО_1!$A:$A,$C75,ТСО_1!$C:$C,$A$71)/M$68 -> 961.75027 | N75: =SUMIFS(ТСО_1!P:P,ТСО_1!$A:$A,$C75,ТСО_1!$C:$C,$A$71)/N$68 -> 231.50896 | O75: =SUMIFS(ТСО_1!Q:Q,ТСО_1!$A:$A,$C75,ТСО_1!$C:$C,$A$71)/O$68 -> 0 | P75: =SUMIFS(ТСО_1!R:R,ТСО_1!$A:$A,$C75,ТСО_1!$C:$C,$A$71)/P$68 -> 0 | Q75: =SUMIFS(ТСО_1!S:S,ТСО_1!$A:$A,$C75,ТСО_1!$C:$C,$A$71)/Q$68 -> 0 | R75: =SUMIFS(ТСО_1!T:T,ТСО_1!$A:$A,$C75,ТСО_1!$C:$C,$A$71)/R$68 -> 0 | S75: =SUMIFS(ТСО_1!U:U,ТСО_1!$A:$A,$C75,ТСО_1!$C:$C,$A$71)/S$68 -> 0 | T75: =SUMIFS(ТСО_1!V:V,ТСО_1!$A:$A,$C75,ТСО_1!$C:$C,$A$71)/T$68 -> 0 | U75: =SUMIFS(ТСО_1!W:W,ТСО_1!$A:$A,$C75,ТСО_1!$C:$C,$A$71)/U$68 -> 0 | V75: =SUMIFS(ТСО_1!X:X,ТСО_1!$A:$A,$C75,ТСО_1!$C:$C,$A$71)/V$68 -> 0 | W75: =SUMIFS(ТСО_1!Y:Y,ТСО_1!$A:$A,$C75,ТСО_1!$C:$C,$A$71)/W$68 -> 0 | X75: =SUMIFS(ТСО_1!Z:Z,ТСО_1!$A:$A,$C75,ТСО_1!$C:$C,$A$71)/X$68 -> 0 | Y75: =SUM(E75:X75) -> 5305.9137 | Z75: =Y75/K9 -> 530.59137 | AA75: =IF(Y75=0,"-",Y75/Y93-1) -> 0
B76: =B10 -> 1 | C76: =C10 -> XCMG 240 | D76: =D75 -> тыс. долл. | E76: =SUMIFS(ТСО_1!G:G,ТСО_1!$A:$A,$C76,ТСО_1!$C:$C,$A$71)/E$68 -> 0 | F76: =SUMIFS(ТСО_1!H:H,ТСО_1!$A:$A,$C76,ТСО_1!$C:$C,$A$71)/F$68 -> 0 | G76: =SUMIFS(ТСО_1!I:I,ТСО_1!$A:$A,$C76,ТСО_1!$C:$C,$A$71)/G$68 -> 0 | H76: =SUMIFS(ТСО_1!J:J,ТСО_1!$A:$A,$C76,ТСО_1!$C:$C,$A$71)/H$68 -> 0 | I76: =SUMIFS(ТСО_1!K:K,ТСО_1!$A:$A,$C76,ТСО_1!$C:$C,$A$71)/I$68 -> 0 | J76: =SUMIFS(ТСО_1!L:L,ТСО_1!$A:$A,$C76,ТСО_1!$C:$C,$A$71)/J$68 -> 0 | K76: =SUMIFS(ТСО_1!M:M,ТСО_1!$A:$A,$C76,ТСО_1!$C:$C,$A$71)/K$68 -> 0 | L76: =SUMIFS(ТСО_1!N:N,ТСО_1!$A:$A,$C76,ТСО_1!$C:$C,$A$71)/L$68 -> 0 | M76: =SUMIFS(ТСО_1!O:O,ТСО_1!$A:$A,$C76,ТСО_1!$C:$C,$A$71)/M$68 -> 0 | N76: =SUMIFS(ТСО_1!P:P,ТСО_1!$A:$A,$C76,ТСО_1!$C:$C,$A$71)/N$68 -> 0 | O76: =SUMIFS(ТСО_1!Q:Q,ТСО_1!$A:$A,$C76,ТСО_1!$C:$C,$A$71)/O$68 -> 0 | P76: =SUMIFS(ТСО_1!R:R,ТСО_1!$A:$A,$C76,ТСО_1!$C:$C,$A$71)/P$68 -> 0 | Q76: =SUMIFS(ТСО_1!S:S,ТСО_1!$A:$A,$C76,ТСО_1!$C:$C,$A$71)/Q$68 -> 0 | R76: =SUMIFS(ТСО_1!T:T,ТСО_1!$A:$A,$C76,ТСО_1!$C:$C,$A$71)/R$68 -> 0 | S76: =SUMIFS(ТСО_1!U:U,ТСО_1!$A:$A,$C76,ТСО_1!$C:$C,$A$71)/S$68 -> 0 | T76: =SUMIFS(ТСО_1!V:V,ТСО_1!$A:$A,$C76,ТСО_1!$C:$C,$A$71)/T$68 -> 0 | U76: =SUMIFS(ТСО_1!W:W,ТСО_1!$A:$A,$C76,ТСО_1!$C:$C,$A$71)/U$68 -> 0 | V76: =SUMIFS(ТСО_1!X:X,ТСО_1!$A:$A,$C76,ТСО_1!$C:$C,$A$71)/V$68 -> 0 | W76: =SUMIFS(ТСО_1!Y:Y,ТСО_1!$A:$A,$C76,ТСО_1!$C:$C,$A$71)/W$68 -> 0 | X76: =SUMIFS(ТСО_1!Z:Z,ТСО_1!$A:$A,$C76,ТСО_1!$C:$C,$A$71)/X$68 -> 0 | Y76: =SUM(E76:X76) -> 0 | Z76: =Y76/K10 -> #DIV/0! | AA76: =IF(Y76=0,"-",Y76/Y94-1) -> -
B77: =B11 -> 1 | C77: =C11 -> БелАЗ 7531 (БТЛ) | D77: =D76 -> тыс. долл. | E77: =SUMIFS(ТСО_1!G:G,ТСО_1!$A:$A,$C77,ТСО_1!$C:$C,$A$71)/E$68 -> 130.7933 | F77: =SUMIFS(ТСО_1!H:H,ТСО_1!$A:$A,$C77,ТСО_1!$C:$C,$A$71)/F$68 -> 209.01238 | G77: =SUMIFS(ТСО_1!I:I,ТСО_1!$A:$A,$C77,ТСО_1!$C:$C,$A$71)/G$68 -> 615.43665 | H77: =SUMIFS(ТСО_1!J:J,ТСО_1!$A:$A,$C77,ТСО_1!$C:$C,$A$71)/H$68 -> 911.52059 | I77: =SUMIFS(ТСО_1!K:K,ТСО_1!$A:$A,$C77,ТСО_1!$C:$C,$A$71)/I$68 -> 364.66374 | J77: =SUMIFS(ТСО_1!L:L,ТСО_1!$A:$A,$C77,ТСО_1!$C:$C,$A$71)/J$68 -> 636.96468 | K77: =SUMIFS(ТСО_1!M:M,ТСО_1!$A:$A,$C77,ТСО_1!$C:$C,$A$71)/K$68 -> 323.46018 | L77: =SUMIFS(ТСО_1!N:N,ТСО_1!$A:$A,$C77,ТСО_1!$C:$C,$A$71)/L$68 -> 971.72701 | M77: =SUMIFS(ТСО_1!O:O,ТСО_1!$A:$A,$C77,ТСО_1!$C:$C,$A$71)/M$68 -> 805.29884 | N77: =SUMIFS(ТСО_1!P:P,ТСО_1!$A:$A,$C77,ТСО_1!$C:$C,$A$71)/N$68 -> 335.15355 | O77: =SUMIFS(ТСО_1!Q:Q,ТСО_1!$A:$A,$C77,ТСО_1!$C:$C,$A$71)/O$68 -> 0 | P77: =SUMIFS(ТСО_1!R:R,ТСО_1!$A:$A,$C77,ТСО_1!$C:$C,$A$71)/P$68 -> 0 | Q77: =SUMIFS(ТСО_1!S:S,ТСО_1!$A:$A,$C77,ТСО_1!$C:$C,$A$71)/Q$68 -> 0 | R77: =SUMIFS(ТСО_1!T:T,ТСО_1!$A:$A,$C77,ТСО_1!$C:$C,$A$71)/R$68 -> 0 | S77: =SUMIFS(ТСО_1!U:U,ТСО_1!$A:$A,$C77,ТСО_1!$C:$C,$A$71)/S$68 -> 0 | T77: =SUMIFS(ТСО_1!V:V,ТСО_1!$A:$A,$C77,ТСО_1!$C:$C,$A$71)/T$68 -> 0 | U77: =SUMIFS(ТСО_1!W:W,ТСО_1!$A:$A,$C77,ТСО_1!$C:$C,$A$71)/U$68 -> 0 | V77: =SUMIFS(ТСО_1!X:X,ТСО_1!$A:$A,$C77,ТСО_1!$C:$C,$A$71)/V$68 -> 0 | W77: =SUMIFS(ТСО_1!Y:Y,ТСО_1!$A:$A,$C77,ТСО_1!$C:$C,$A$71)/W$68 -> 0 | X77: =SUMIFS(ТСО_1!Z:Z,ТСО_1!$A:$A,$C77,ТСО_1!$C:$C,$A$71)/X$68 -> 0 | Y77: =SUM(E77:X77) -> 5304.0309 | Z77: =Y77/K11 -> 530.40309 | AA77: =IF(Y77=0,"-",Y77/Y95-1) -> 0
B78: =B12 -> 0 | C78: =C12 -> 0 | D78: =D77 -> тыс. долл. | E78: =SUMIFS(ТСО_1!G:G,ТСО_1!$A:$A,$C78,ТСО_1!$C:$C,$A$71)/E$68 -> 0 | F78: =SUMIFS(ТСО_1!H:H,ТСО_1!$A:$A,$C78,ТСО_1!$C:$C,$A$71)/F$68 -> 0 | G78: =SUMIFS(ТСО_1!I:I,ТСО_1!$A:$A,$C78,ТСО_1!$C:$C,$A$71)/G$68 -> 0 | H78: =SUMIFS(ТСО_1!J:J,ТСО_1!$A:$A,$C78,ТСО_1!$C:$C,$A$71)/H$68 -> 0 | I78: =SUMIFS(ТСО_1!K:K,ТСО_1!$A:$A,$C78,ТСО_1!$C:$C,$A$71)/I$68 -> 0 | J78: =SUMIFS(ТСО_1!L:L,ТСО_1!$A:$A,$C78,ТСО_1!$C:$C,$A$71)/J$68 -> 0 | K78: =SUMIFS(ТСО_1!M:M,ТСО_1!$A:$A,$C78,ТСО_1!$C:$C,$A$71)/K$68 -> 0 | L78: =SUMIFS(ТСО_1!N:N,ТСО_1!$A:$A,$C78,ТСО_1!$C:$C,$A$71)/L$68 -> 0 | M78: =SUMIFS(ТСО_1!O:O,ТСО_1!$A:$A,$C78,ТСО_1!$C:$C,$A$71)/M$68 -> 0 | N78: =SUMIFS(ТСО_1!P:P,ТСО_1!$A:$A,$C78,ТСО_1!$C:$C,$A$71)/N$68 -> 0 | O78: =SUMIFS(ТСО_1!Q:Q,ТСО_1!$A:$A,$C78,ТСО_1!$C:$C,$A$71)/O$68 -> 0 | P78: =SUMIFS(ТСО_1!R:R,ТСО_1!$A:$A,$C78,ТСО_1!$C:$C,$A$71)/P$68 -> 0 | Q78: =SUMIFS(ТСО_1!S:S,ТСО_1!$A:$A,$C78,ТСО_1!$C:$C,$A$71)/Q$68 -> 0 | R78: =SUMIFS(ТСО_1!T:T,ТСО_1!$A:$A,$C78,ТСО_1!$C:$C,$A$71)/R$68 -> 0 | S78: =SUMIFS(ТСО_1!U:U,ТСО_1!$A:$A,$C78,ТСО_1!$C:$C,$A$71)/S$68 -> 0 | T78: =SUMIFS(ТСО_1!V:V,ТСО_1!$A:$A,$C78,ТСО_1!$C:$C,$A$71)/T$68 -> 0 | U78: =SUMIFS(ТСО_1!W:W,ТСО_1!$A:$A,$C78,ТСО_1!$C:$C,$A$71)/U$68 -> 0 | V78: =SUMIFS(ТСО_1!X:X,ТСО_1!$A:$A,$C78,ТСО_1!$C:$C,$A$71)/V$68 -> 0 | W78: =SUMIFS(ТСО_1!Y:Y,ТСО_1!$A:$A,$C78,ТСО_1!$C:$C,$A$71)/W$68 -> 0 | X78: =SUMIFS(ТСО_1!Z:Z,ТСО_1!$A:$A,$C78,ТСО_1!$C:$C,$A$71)/X$68 -> 0 | Y78: =SUM(E78:X78) -> 0 | Z78: =Y78/K12 -> #DIV/0! | AA78: =IF(Y78=0,"-",Y78/Y96-1) -> -
B79: =B13 -> 0 | C79: =C13 -> 0 | D79: =D78 -> тыс. долл. | E79: =SUMIFS(ТСО_1!G:G,ТСО_1!$A:$A,$C79,ТСО_1!$C:$C,$A$71)/E$68 -> 0 | F79: =SUMIFS(ТСО_1!H:H,ТСО_1!$A:$A,$C79,ТСО_1!$C:$C,$A$71)/F$68 -> 0 | G79: =SUMIFS(ТСО_1!I:I,ТСО_1!$A:$A,$C79,ТСО_1!$C:$C,$A$71)/G$68 -> 0 | H79: =SUMIFS(ТСО_1!J:J,ТСО_1!$A:$A,$C79,ТСО_1!$C:$C,$A$71)/H$68 -> 0 | I79: =SUMIFS(ТСО_1!K:K,ТСО_1!$A:$A,$C79,ТСО_1!$C:$C,$A$71)/I$68 -> 0 | J79: =SUMIFS(ТСО_1!L:L,ТСО_1!$A:$A,$C79,ТСО_1!$C:$C,$A$71)/J$68 -> 0 | K79: =SUMIFS(ТСО_1!M:M,ТСО_1!$A:$A,$C79,ТСО_1!$C:$C,$A$71)/K$68 -> 0 | L79: =SUMIFS(ТСО_1!N:N,ТСО_1!$A:$A,$C79,ТСО_1!$C:$C,$A$71)/L$68 -> 0 | M79: =SUMIFS(ТСО_1!O:O,ТСО_1!$A:$A,$C79,ТСО_1!$C:$C,$A$71)/M$68 -> 0 | N79: =SUMIFS(ТСО_1!P:P,ТСО_1!$A:$A,$C79,ТСО_1!$C:$C,$A$71)/N$68 -> 0 | O79: =SUMIFS(ТСО_1!Q:Q,ТСО_1!$A:$A,$C79,ТСО_1!$C:$C,$A$71)/O$68 -> 0 | P79: =SUMIFS(ТСО_1!R:R,ТСО_1!$A:$A,$C79,ТСО_1!$C:$C,$A$71)/P$68 -> 0 | Q79: =SUMIFS(ТСО_1!S:S,ТСО_1!$A:$A,$C79,ТСО_1!$C:$C,$A$71)/Q$68 -> 0 | R79: =SUMIFS(ТСО_1!T:T,ТСО_1!$A:$A,$C79,ТСО_1!$C:$C,$A$71)/R$68 -> 0 | S79: =SUMIFS(ТСО_1!U:U,ТСО_1!$A:$A,$C79,ТСО_1!$C:$C,$A$71)/S$68 -> 0 | T79: =SUMIFS(ТСО_1!V:V,ТСО_1!$A:$A,$C79,ТСО_1!$C:$C,$A$71)/T$68 -> 0 | U79: =SUMIFS(ТСО_1!W:W,ТСО_1!$A:$A,$C79,ТСО_1!$C:$C,$A$71)/U$68 -> 0 | V79: =SUMIFS(ТСО_1!X:X,ТСО_1!$A:$A,$C79,ТСО_1!$C:$C,$A$71)/V$68 -> 0 | W79: =SUMIFS(ТСО_1!Y:Y,ТСО_1!$A:$A,$C79,ТСО_1!$C:$C,$A$71)/W$68 -> 0 | X79: =SUMIFS(ТСО_1!Z:Z,ТСО_1!$A:$A,$C79,ТСО_1!$C:$C,$A$71)/X$68 -> 0 | Y79: =SUM(E79:X79) -> 0 | Z79: =Y79/K13 -> #DIV/0! | AA79: =IF(Y79=0,"-",Y79/Y97-1) -> -
B80: =B14 -> 0 | C80: =C14 -> 0 | D80: =D79 -> тыс. долл. | E80: =SUMIFS(ТСО_1!G:G,ТСО_1!$A:$A,$C80,ТСО_1!$C:$C,$A$71)/E$68 -> 0 | F80: =SUMIFS(ТСО_1!H:H,ТСО_1!$A:$A,$C80,ТСО_1!$C:$C,$A$71)/F$68 -> 0 | G80: =SUMIFS(ТСО_1!I:I,ТСО_1!$A:$A,$C80,ТСО_1!$C:$C,$A$71)/G$68 -> 0 | H80: =SUMIFS(ТСО_1!J:J,ТСО_1!$A:$A,$C80,ТСО_1!$C:$C,$A$71)/H$68 -> 0 | I80: =SUMIFS(ТСО_1!K:K,ТСО_1!$A:$A,$C80,ТСО_1!$C:$C,$A$71)/I$68 -> 0 | J80: =SUMIFS(ТСО_1!L:L,ТСО_1!$A:$A,$C80,ТСО_1!$C:$C,$A$71)/J$68 -> 0 | K80: =SUMIFS(ТСО_1!M:M,ТСО_1!$A:$A,$C80,ТСО_1!$C:$C,$A$71)/K$68 -> 0 | L80: =SUMIFS(ТСО_1!N:N,ТСО_1!$A:$A,$C80,ТСО_1!$C:$C,$A$71)/L$68 -> 0 | M80: =SUMIFS(ТСО_1!O:O,ТСО_1!$A:$A,$C80,ТСО_1!$C:$C,$A$71)/M$68 -> 0 | N80: =SUMIFS(ТСО_1!P:P,ТСО_1!$A:$A,$C80,ТСО_1!$C:$C,$A$71)/N$68 -> 0 | O80: =SUMIFS(ТСО_1!Q:Q,ТСО_1!$A:$A,$C80,ТСО_1!$C:$C,$A$71)/O$68 -> 0 | P80: =SUMIFS(ТСО_1!R:R,ТСО_1!$A:$A,$C80,ТСО_1!$C:$C,$A$71)/P$68 -> 0 | Q80: =SUMIFS(ТСО_1!S:S,ТСО_1!$A:$A,$C80,ТСО_1!$C:$C,$A$71)/Q$68 -> 0 | R80: =SUMIFS(ТСО_1!T:T,ТСО_1!$A:$A,$C80,ТСО_1!$C:$C,$A$71)/R$68 -> 0 | S80: =SUMIFS(ТСО_1!U:U,ТСО_1!$A:$A,$C80,ТСО_1!$C:$C,$A$71)/S$68 -> 0 | T80: =SUMIFS(ТСО_1!V:V,ТСО_1!$A:$A,$C80,ТСО_1!$C:$C,$A$71)/T$68 -> 0 | U80: =SUMIFS(ТСО_1!W:W,ТСО_1!$A:$A,$C80,ТСО_1!$C:$C,$A$71)/U$68 -> 0 | V80: =SUMIFS(ТСО_1!X:X,ТСО_1!$A:$A,$C80,ТСО_1!$C:$C,$A$71)/V$68 -> 0 | W80: =SUMIFS(ТСО_1!Y:Y,ТСО_1!$A:$A,$C80,ТСО_1!$C:$C,$A$71)/W$68 -> 0 | X80: =SUMIFS(ТСО_1!Z:Z,ТСО_1!$A:$A,$C80,ТСО_1!$C:$C,$A$71)/X$68 -> 0 | Y80: =SUM(E80:X80) -> 0 | Z80: =Y80/K14 -> #DIV/0! | AA80: =IF(Y80=0,"-",Y80/Y98-1) -> -
B81: =B15 -> 0 | C81: =C15 -> 0 | D81: =D80 -> тыс. долл. | E81: =SUMIFS(ТСО_1!G:G,ТСО_1!$A:$A,$C81,ТСО_1!$C:$C,$A$71)/E$68 -> 0 | F81: =SUMIFS(ТСО_1!H:H,ТСО_1!$A:$A,$C81,ТСО_1!$C:$C,$A$71)/F$68 -> 0 | G81: =SUMIFS(ТСО_1!I:I,ТСО_1!$A:$A,$C81,ТСО_1!$C:$C,$A$71)/G$68 -> 0 | H81: =SUMIFS(ТСО_1!J:J,ТСО_1!$A:$A,$C81,ТСО_1!$C:$C,$A$71)/H$68 -> 0 | I81: =SUMIFS(ТСО_1!K:K,ТСО_1!$A:$A,$C81,ТСО_1!$C:$C,$A$71)/I$68 -> 0 | J81: =SUMIFS(ТСО_1!L:L,ТСО_1!$A:$A,$C81,ТСО_1!$C:$C,$A$71)/J$68 -> 0 | K81: =SUMIFS(ТСО_1!M:M,ТСО_1!$A:$A,$C81,ТСО_1!$C:$C,$A$71)/K$68 -> 0 | L81: =SUMIFS(ТСО_1!N:N,ТСО_1!$A:$A,$C81,ТСО_1!$C:$C,$A$71)/L$68 -> 0 | M81: =SUMIFS(ТСО_1!O:O,ТСО_1!$A:$A,$C81,ТСО_1!$C:$C,$A$71)/M$68 -> 0 | N81: =SUMIFS(ТСО_1!P:P,ТСО_1!$A:$A,$C81,ТСО_1!$C:$C,$A$71)/N$68 -> 0 | O81: =SUMIFS(ТСО_1!Q:Q,ТСО_1!$A:$A,$C81,ТСО_1!$C:$C,$A$71)/O$68 -> 0 | P81: =SUMIFS(ТСО_1!R:R,ТСО_1!$A:$A,$C81,ТСО_1!$C:$C,$A$71)/P$68 -> 0 | Q81: =SUMIFS(ТСО_1!S:S,ТСО_1!$A:$A,$C81,ТСО_1!$C:$C,$A$71)/Q$68 -> 0 | R81: =SUMIFS(ТСО_1!T:T,ТСО_1!$A:$A,$C81,ТСО_1!$C:$C,$A$71)/R$68 -> 0 | S81: =SUMIFS(ТСО_1!U:U,ТСО_1!$A:$A,$C81,ТСО_1!$C:$C,$A$71)/S$68 -> 0 | T81: =SUMIFS(ТСО_1!V:V,ТСО_1!$A:$A,$C81,ТСО_1!$C:$C,$A$71)/T$68 -> 0 | U81: =SUMIFS(ТСО_1!W:W,ТСО_1!$A:$A,$C81,ТСО_1!$C:$C,$A$71)/U$68 -> 0 | V81: =SUMIFS(ТСО_1!X:X,ТСО_1!$A:$A,$C81,ТСО_1!$C:$C,$A$71)/V$68 -> 0 | W81: =SUMIFS(ТСО_1!Y:Y,ТСО_1!$A:$A,$C81,ТСО_1!$C:$C,$A$71)/W$68 -> 0 | X81: =SUMIFS(ТСО_1!Z:Z,ТСО_1!$A:$A,$C81,ТСО_1!$C:$C,$A$71)/X$68 -> 0 | Y81: =SUM(E81:X81) -> 0 | Z81: =Y81/K15 -> #DIV/0! | AA81: =IF(Y81=0,"-",Y81/Y99-1) -> -
B82: =B16 -> 0 | C82: =C16 -> 0 | D82: =D81 -> тыс. долл. | E82: =SUMIFS(ТСО_1!G:G,ТСО_1!$A:$A,$C82,ТСО_1!$C:$C,$A$71)/E$68 -> 0 | F82: =SUMIFS(ТСО_1!H:H,ТСО_1!$A:$A,$C82,ТСО_1!$C:$C,$A$71)/F$68 -> 0 | G82: =SUMIFS(ТСО_1!I:I,ТСО_1!$A:$A,$C82,ТСО_1!$C:$C,$A$71)/G$68 -> 0 | H82: =SUMIFS(ТСО_1!J:J,ТСО_1!$A:$A,$C82,ТСО_1!$C:$C,$A$71)/H$68 -> 0 | I82: =SUMIFS(ТСО_1!K:K,ТСО_1!$A:$A,$C82,ТСО_1!$C:$C,$A$71)/I$68 -> 0 | J82: =SUMIFS(ТСО_1!L:L,ТСО_1!$A:$A,$C82,ТСО_1!$C:$C,$A$71)/J$68 -> 0 | K82: =SUMIFS(ТСО_1!M:M,ТСО_1!$A:$A,$C82,ТСО_1!$C:$C,$A$71)/K$68 -> 0 | L82: =SUMIFS(ТСО_1!N:N,ТСО_1!$A:$A,$C82,ТСО_1!$C:$C,$A$71)/L$68 -> 0 | M82: =SUMIFS(ТСО_1!O:O,ТСО_1!$A:$A,$C82,ТСО_1!$C:$C,$A$71)/M$68 -> 0 | N82: =SUMIFS(ТСО_1!P:P,ТСО_1!$A:$A,$C82,ТСО_1!$C:$C,$A$71)/N$68 -> 0 | O82: =SUMIFS(ТСО_1!Q:Q,ТСО_1!$A:$A,$C82,ТСО_1!$C:$C,$A$71)/O$68 -> 0 | P82: =SUMIFS(ТСО_1!R:R,ТСО_1!$A:$A,$C82,ТСО_1!$C:$C,$A$71)/P$68 -> 0 | Q82: =SUMIFS(ТСО_1!S:S,ТСО_1!$A:$A,$C82,ТСО_1!$C:$C,$A$71)/Q$68 -> 0 | R82: =SUMIFS(ТСО_1!T:T,ТСО_1!$A:$A,$C82,ТСО_1!$C:$C,$A$71)/R$68 -> 0 | S82: =SUMIFS(ТСО_1!U:U,ТСО_1!$A:$A,$C82,ТСО_1!$C:$C,$A$71)/S$68 -> 0 | T82: =SUMIFS(ТСО_1!V:V,ТСО_1!$A:$A,$C82,ТСО_1!$C:$C,$A$71)/T$68 -> 0 | U82: =SUMIFS(ТСО_1!W:W,ТСО_1!$A:$A,$C82,ТСО_1!$C:$C,$A$71)/U$68 -> 0 | V82: =SUMIFS(ТСО_1!X:X,ТСО_1!$A:$A,$C82,ТСО_1!$C:$C,$A$71)/V$68 -> 0 | W82: =SUMIFS(ТСО_1!Y:Y,ТСО_1!$A:$A,$C82,ТСО_1!$C:$C,$A$71)/W$68 -> 0 | X82: =SUMIFS(ТСО_1!Z:Z,ТСО_1!$A:$A,$C82,ТСО_1!$C:$C,$A$71)/X$68 -> 0 | Y82: =SUM(E82:X82) -> 0 | Z82: =Y82/K16 -> #DIV/0! | AA82: =IF(Y82=0,"-",Y82/Y100-1) -> -
B83: =B17 -> 0 | C83: =C17 -> 0 | D83: =D82 -> тыс. долл. | E83: =SUMIFS(ТСО_1!G:G,ТСО_1!$A:$A,$C83,ТСО_1!$C:$C,$A$71)/E$68 -> 0 | F83: =SUMIFS(ТСО_1!H:H,ТСО_1!$A:$A,$C83,ТСО_1!$C:$C,$A$71)/F$68 -> 0 | G83: =SUMIFS(ТСО_1!I:I,ТСО_1!$A:$A,$C83,ТСО_1!$C:$C,$A$71)/G$68 -> 0 | H83: =SUMIFS(ТСО_1!J:J,ТСО_1!$A:$A,$C83,ТСО_1!$C:$C,$A$71)/H$68 -> 0 | I83: =SUMIFS(ТСО_1!K:K,ТСО_1!$A:$A,$C83,ТСО_1!$C:$C,$A$71)/I$68 -> 0 | J83: =SUMIFS(ТСО_1!L:L,ТСО_1!$A:$A,$C83,ТСО_1!$C:$C,$A$71)/J$68 -> 0 | K83: =SUMIFS(ТСО_1!M:M,ТСО_1!$A:$A,$C83,ТСО_1!$C:$C,$A$71)/K$68 -> 0 | L83: =SUMIFS(ТСО_1!N:N,ТСО_1!$A:$A,$C83,ТСО_1!$C:$C,$A$71)/L$68 -> 0 | M83: =SUMIFS(ТСО_1!O:O,ТСО_1!$A:$A,$C83,ТСО_1!$C:$C,$A$71)/M$68 -> 0 | N83: =SUMIFS(ТСО_1!P:P,ТСО_1!$A:$A,$C83,ТСО_1!$C:$C,$A$71)/N$68 -> 0 | O83: =SUMIFS(ТСО_1!Q:Q,ТСО_1!$A:$A,$C83,ТСО_1!$C:$C,$A$71)/O$68 -> 0 | P83: =SUMIFS(ТСО_1!R:R,ТСО_1!$A:$A,$C83,ТСО_1!$C:$C,$A$71)/P$68 -> 0 | Q83: =SUMIFS(ТСО_1!S:S,ТСО_1!$A:$A,$C83,ТСО_1!$C:$C,$A$71)/Q$68 -> 0 | R83: =SUMIFS(ТСО_1!T:T,ТСО_1!$A:$A,$C83,ТСО_1!$C:$C,$A$71)/R$68 -> 0 | S83: =SUMIFS(ТСО_1!U:U,ТСО_1!$A:$A,$C83,ТСО_1!$C:$C,$A$71)/S$68 -> 0 | T83: =SUMIFS(ТСО_1!V:V,ТСО_1!$A:$A,$C83,ТСО_1!$C:$C,$A$71)/T$68 -> 0 | U83: =SUMIFS(ТСО_1!W:W,ТСО_1!$A:$A,$C83,ТСО_1!$C:$C,$A$71)/U$68 -> 0 | V83: =SUMIFS(ТСО_1!X:X,ТСО_1!$A:$A,$C83,ТСО_1!$C:$C,$A$71)/V$68 -> 0 | W83: =SUMIFS(ТСО_1!Y:Y,ТСО_1!$A:$A,$C83,ТСО_1!$C:$C,$A$71)/W$68 -> 0 | X83: =SUMIFS(ТСО_1!Z:Z,ТСО_1!$A:$A,$C83,ТСО_1!$C:$C,$A$71)/X$68 -> 0 | Y83: =SUM(E83:X83) -> 0 | Z83: =Y83/K17 -> #DIV/0! | AA83: =IF(Y83=0,"-",Y83/Y101-1) -> -
... B85: =B19 -> 0 | C85: =C19 -> 0 | D85: =D84 -> тыс. долл. | E85: =SUMIFS(ТСО_1!G:G,ТСО_1!$A:$A,$C85,ТСО_1!$C:$C,$A$71)/E$68 -> 0 | F85: =SUMIFS(ТСО_1!H:H,ТСО_1!$A:$A,$C85,ТСО_1!$C:$C,$A$71)/F$68 -> 0 | G85: =SUMIFS(ТСО_1!I:I,ТСО_1!$A:$A,$C85,ТСО_1!$C:$C,$A$71)/G$68 -> 0 | H85: =SUMIFS(ТСО_1!J:J,ТСО_1!$A:$A,$C85,ТСО_1!$C:$C,$A$71)/H$68 -> 0 | I85: =SUMIFS(ТСО_1!K:K,ТСО_1!$A:$A,$C85,ТСО_1!$C:$C,$A$71)/I$68 -> 0 | J85: =SUMIFS(ТСО_1!L:L,ТСО_1!$A:$A,$C85,ТСО_1!$C:$C,$A$71)/J$68 -> 0 | K85: =SUMIFS(ТСО_1!M:M,ТСО_1!$A:$A,$C85,ТСО_1!$C:$C,$A$71)/K$68 -> 0 | L85: =SUMIFS(ТСО_1!N:N,ТСО_1!$A:$A,$C85,ТСО_1!$C:$C,$A$71)/L$68 -> 0 | M85: =SUMIFS(ТСО_1!O:O,ТСО_1!$A:$A,$C85,ТСО_1!$C:$C,$A$71)/M$68 -> 0 | N85: =SUMIFS(ТСО_1!P:P,ТСО_1!$A:$A,$C85,ТСО_1!$C:$C,$A$71)/N$68 -> 0 | O85: =SUMIFS(ТСО_1!Q:Q,ТСО_1!$A:$A,$C85,ТСО_1!$C:$C,$A$71)/O$68 -> 0 | P85: =SUMIFS(ТСО_1!R:R,ТСО_1!$A:$A,$C85,ТСО_1!$C:$C,$A$71)/P$68 -> 0 | Q85: =SUMIFS(ТСО_1!S:S,ТСО_1!$A:$A,$C85,ТСО_1!$C:$C,$A$71)/Q$68 -> 0 | R85: =SUMIFS(ТСО_1!T:T,ТСО_1!$A:$A,$C85,ТСО_1!$C:$C,$A$71)/R$68 -> 0 | S85: =SUMIFS(ТСО_1!U:U,ТСО_1!$A:$A,$C85,ТСО_1!$C:$C,$A$71)/S$68 -> 0 | T85: =SUMIFS(ТСО_1!V:V,ТСО_1!$A:$A,$C85,ТСО_1!$C:$C,$A$71)/T$68 -> 0 | U85: =SUMIFS(ТСО_1!W:W,ТСО_1!$A:$A,$C85,ТСО_1!$C:$C,$A$71)/U$68 -> 0 | V85: =SUMIFS(ТСО_1!X:X,ТСО_1!$A:$A,$C85,ТСО_1!$C:$C,$A$71)/V$68 -> 0 | W85: =SUMIFS(ТСО_1!Y:Y,ТСО_1!$A:$A,$C85,ТСО_1!$C:$C,$A$71)/W$68 -> 0 | X85: =SUMIFS(ТСО_1!Z:Z,ТСО_1!$A:$A,$C85,ТСО_1!$C:$C,$A$71)/X$68 -> 0 | Y85: =SUM(E85:X85) -> 0 | Z85: =Y85/K19 -> #DIV/0! | AA85: =IF(Y85=0,"-",Y85/Y103-1) -> -
B86: =B20 -> 1
B87: 1
B88: 1 | C88: Затраты от поставщиков (текущий тендер) | D88: =D70 -> Ед. изм. | E88: =E70 -> 1 | F88: =F70 -> 2 | G88: =G70 -> 3 | H88: =H70 -> 4 | I88: =I70 -> 5 | J88: =J70 -> 6 | K88: =K70 -> 7 | ... Z88: =Z70 -> Среднее
B89: =B71 -> 1 | C89: =C71 -> NHL NTE 240 | D89: =D71 -> тыс. долл. | E89: =SUMIFS(ТСО!G:G,ТСО!$A:$A,$C89,ТСО!$C:$C,$A$71)/E$68 -> 63.91384 | F89: =SUMIFS(ТСО!H:H,ТСО!$A:$A,$C89,ТСО!$C:$C,$A$71)/F$68 -> 88.815489 | G89: =SUMIFS(ТСО!I:I,ТСО!$A:$A,$C89,ТСО!$C:$C,$A$71)/G$68 -> 526.21505 | H89: =SUMIFS(ТСО!J:J,ТСО!$A:$A,$C89,ТСО!$C:$C,$A$71)/H$68 -> 279.8431 | I89: =SUMIFS(ТСО!K:K,ТСО!$A:$A,$C89,ТСО!$C:$C,$A$71)/I$68 -> 93.326115 | J89: =SUMIFS(ТСО!L:L,ТСО!$A:$A,$C89,ТСО!$C:$C,$A$71)/J$68 -> 513.88141 | K89: =SUMIFS(ТСО!M:M,ТСО!$A:$A,$C89,ТСО!$C:$C,$A$71)/K$68 -> 86.516048 | L89: =SUMIFS(ТСО!N:N,ТСО!$A:$A,$C89,ТСО!$C:$C,$A$71)/L$68 -> 296.58055 | M89: =SUMIFS(ТСО!O:O,ТСО!$A:$A,$C89,ТСО!$C:$C,$A$71)/M$68 -> 958.65982 | N89: =SUMIFS(ТСО!P:P,ТСО!$A:$A,$C89,ТСО!$C:$C,$A$71)/N$68 -> 73.522262 | O89: =SUMIFS(ТСО!Q:Q,ТСО!$A:$A,$C89,ТСО!$C:$C,$A$71)/O$68 -> 2113.8489 | P89: =SUMIFS(ТСО!R:R,ТСО!$A:$A,$C89,ТСО!$C:$C,$A$71)/P$68 -> 515.23001 | Q89: =SUMIFS(ТСО!S:S,ТСО!$A:$A,$C89,ТСО!$C:$C,$A$71)/Q$68 -> 80.169897 | R89: =SUMIFS(ТСО!T:T,ТСО!$A:$A,$C89,ТСО!$C:$C,$A$71)/R$68 -> 81.530805 | S89: =SUMIFS(ТСО!U:U,ТСО!$A:$A,$C89,ТСО!$C:$C,$A$71)/S$68 -> 733.18369 | T89: =SUMIFS(ТСО!V:V,ТСО!$A:$A,$C89,ТСО!$C:$C,$A$71)/T$68 -> 81.693954 | U89: =SUMIFS(ТСО!W:W,ТСО!$A:$A,$C89,ТСО!$C:$C,$A$71)/U$68 -> 80.59716 | V89: =SUMIFS(ТСО!X:X,ТСО!$A:$A,$C89,ТСО!$C:$C,$A$71)/V$68 -> 1170.2928 | W89: =SUMIFS(ТСО!Y:Y,ТСО!$A:$A,$C89,ТСО!$C:$C,$A$71)/W$68 -> 83.014317 | X89: =SUMIFS(ТСО!Z:Z,ТСО!$A:$A,$C89,ТСО!$C:$C,$A$71)/X$68 -> 101.43293 | Y89: =SUM(E89:X89) -> 8022.2681 | Z89: =Y89/K5 -> 401.11341
B90: =B72 -> 1 | C90: =C72 -> Estar ESDE240 (ГПБ К) | D90: =D72 -> тыс. долл. | E90: =SUMIFS(ТСО!G:G,ТСО!$A:$A,$C90,ТСО!$C:$C,$A$71)/E$68 -> 180.53003 | F90: =SUMIFS(ТСО!H:H,ТСО!$A:$A,$C90,ТСО!$C:$C,$A$71)/F$68 -> 276.72926 | G90: =SUMIFS(ТСО!I:I,ТСО!$A:$A,$C90,ТСО!$C:$C,$A$71)/G$68 -> 928.14011 | H90: =SUMIFS(ТСО!J:J,ТСО!$A:$A,$C90,ТСО!$C:$C,$A$71)/H$68 -> 2751.3389 | I90: =SUMIFS(ТСО!K:K,ТСО!$A:$A,$C90,ТСО!$C:$C,$A$71)/I$68 -> 184.23303 | J90: =SUMIFS(ТСО!L:L,ТСО!$A:$A,$C90,ТСО!$C:$C,$A$71)/J$68 -> 1024.3393 | K90: =SUMIFS(ТСО!M:M,ТСО!$A:$A,$C90,ТСО!$C:$C,$A$71)/K$68 -> 180.53003 | L90: =SUMIFS(ТСО!N:N,ТСО!$A:$A,$C90,ТСО!$C:$C,$A$71)/L$68 -> 2751.3389 | M90: =SUMIFS(ТСО!O:O,ТСО!$A:$A,$C90,ТСО!$C:$C,$A$71)/M$68 -> 180.53003 | N90: =SUMIFS(ТСО!P:P,ТСО!$A:$A,$C90,ТСО!$C:$C,$A$71)/N$68 -> 180.53003 | O90: =SUMIFS(ТСО!Q:Q,ТСО!$A:$A,$C90,ТСО!$C:$C,$A$71)/O$68 -> 0 | P90: =SUMIFS(ТСО!R:R,ТСО!$A:$A,$C90,ТСО!$C:$C,$A$71)/P$68 -> 0 | Q90: =SUMIFS(ТСО!S:S,ТСО!$A:$A,$C90,ТСО!$C:$C,$A$71)/Q$68 -> 0 | R90: =SUMIFS(ТСО!T:T,ТСО!$A:$A,$C90,ТСО!$C:$C,$A$71)/R$68 -> 0 | S90: =SUMIFS(ТСО!U:U,ТСО!$A:$A,$C90,ТСО!$C:$C,$A$71)/S$68 -> 0 | T90: =SUMIFS(ТСО!V:V,ТСО!$A:$A,$C90,ТСО!$C:$C,$A$71)/T$68 -> 0 | U90: =SUMIFS(ТСО!W:W,ТСО!$A:$A,$C90,ТСО!$C:$C,$A$71)/U$68 -> 0 | V90: =SUMIFS(ТСО!X:X,ТСО!$A:$A,$C90,ТСО!$C:$C,$A$71)/V$68 -> 0 | W90: =SUMIFS(ТСО!Y:Y,ТСО!$A:$A,$C90,ТСО!$C:$C,$A$71)/W$68 -> 0 | X90: =SUMIFS(ТСО!Z:Z,ТСО!$A:$A,$C90,ТСО!$C:$C,$A$71)/X$68 -> 0 | Y90: =SUM(E90:X90) -> 8638.2397 | Z90: =Y90/K6 -> 863.82397
B91: =B73 -> 1 | C91: =C73 -> SANY SET240S | D91: =D73 -> тыс. долл. | E91: =SUMIFS(ТСО!G:G,ТСО!$A:$A,$C91,ТСО!$C:$C,$A$71)/E$68 -> 135.34771 | F91: =SUMIFS(ТСО!H:H,ТСО!$A:$A,$C91,ТСО!$C:$C,$A$71)/F$68 -> 211.26698 | G91: =SUMIFS(ТСО!I:I,ТСО!$A:$A,$C91,ТСО!$C:$C,$A$71)/G$68 -> 597.96064 | H91: =SUMIFS(ТСО!J:J,ТСО!$A:$A,$C91,ТСО!$C:$C,$A$71)/H$68 -> 305.14198 | I91: =SUMIFS(ТСО!K:K,ТСО!$A:$A,$C91,ТСО!$C:$C,$A$71)/I$68 -> 973.93701 | J91: =SUMIFS(ТСО!L:L,ТСО!$A:$A,$C91,ТСО!$C:$C,$A$71)/J$68 -> 741.2592 | K91: =SUMIFS(ТСО!M:M,ТСО!$A:$A,$C91,ТСО!$C:$C,$A$71)/K$68 -> 267.37571 | L91: =SUMIFS(ТСО!N:N,ТСО!$A:$A,$C91,ТСО!$C:$C,$A$71)/L$68 -> 268.93298 | M91: =SUMIFS(ТСО!O:O,ТСО!$A:$A,$C91,ТСО!$C:$C,$A$71)/M$68 -> 1349.3409 | N91: =SUMIFS(ТСО!P:P,ТСО!$A:$A,$C91,ТСО!$C:$C,$A$71)/N$68 -> 196.00098 | O91: =SUMIFS(ТСО!Q:Q,ТСО!$A:$A,$C91,ТСО!$C:$C,$A$71)/O$68 -> 258.79771 | P91: =SUMIFS(ТСО!R:R,ТСО!$A:$A,$C91,ТСО!$C:$C,$A$71)/P$68 -> 282.98871 | Q91: =SUMIFS(ТСО!S:S,ТСО!$A:$A,$C91,ТСО!$C:$C,$A$71)/Q$68 -> 0 | R91: =SUMIFS(ТСО!T:T,ТСО!$A:$A,$C91,ТСО!$C:$C,$A$71)/R$68 -> 0 | S91: =SUMIFS(ТСО!U:U,ТСО!$A:$A,$C91,ТСО!$C:$C,$A$71)/S$68 -> 0 | T91: =SUMIFS(ТСО!V:V,ТСО!$A:$A,$C91,ТСО!$C:$C,$A$71)/T$68 -> 0 | U91: =SUMIFS(ТСО!W:W,ТСО!$A:$A,$C91,ТСО!$C:$C,$A$71)/U$68 -> 0 | V91: =SUMIFS(ТСО!X:X,ТСО!$A:$A,$C91,ТСО!$C:$C,$A$71)/V$68 -> 0 | W91: =SUMIFS(ТСО!Y:Y,ТСО!$A:$A,$C91,ТСО!$C:$C,$A$71)/W$68 -> 0 | X91: =SUMIFS(ТСО!Z:Z,ТСО!$A:$A,$C91,ТСО!$C:$C,$A$71)/X$68 -> 0 | Y91: =SUM(E91:X91) -> 5588.3505 | Z91: =Y91/K7 -> 465.69588
B92: =B74 -> 1 | C92: =C74 -> TZCO TZE240 | D92: =D74 -> тыс. долл. | E92: =SUMIFS(ТСО!G:G,ТСО!$A:$A,$C92,ТСО!$C:$C,$A$71)/E$68 -> 299.33592 | F92: =SUMIFS(ТСО!H:H,ТСО!$A:$A,$C92,ТСО!$C:$C,$A$71)/F$68 -> 629.57257 | G92: =SUMIFS(ТСО!I:I,ТСО!$A:$A,$C92,ТСО!$C:$C,$A$71)/G$68 -> 1881.2035 | H92: =SUMIFS(ТСО!J:J,ТСО!$A:$A,$C92,ТСО!$C:$C,$A$71)/H$68 -> 629.57257 | I92: =SUMIFS(ТСО!K:K,ТСО!$A:$A,$C92,ТСО!$C:$C,$A$71)/I$68 -> 299.33592 | J92: =SUMIFS(ТСО!L:L,ТСО!$A:$A,$C92,ТСО!$C:$C,$A$71)/J$68 -> 2211.4401 | K92: =SUMIFS(ТСО!M:M,ТСО!$A:$A,$C92,ТСО!$C:$C,$A$71)/K$68 -> 299.33592 | L92: =SUMIFS(ТСО!N:N,ТСО!$A:$A,$C92,ТСО!$C:$C,$A$71)/L$68 -> 629.57257 | M92: =SUMIFS(ТСО!O:O,ТСО!$A:$A,$C92,ТСО!$C:$C,$A$71)/M$68 -> 0 | N92: =SUMIFS(ТСО!P:P,ТСО!$A:$A,$C92,ТСО!$C:$C,$A$71)/N$68 -> 0 | O92: =SUMIFS(ТСО!Q:Q,ТСО!$A:$A,$C92,ТСО!$C:$C,$A$71)/O$68 -> 0 | P92: =SUMIFS(ТСО!R:R,ТСО!$A:$A,$C92,ТСО!$C:$C,$A$71)/P$68 -> 0 | Q92: =SUMIFS(ТСО!S:S,ТСО!$A:$A,$C92,ТСО!$C:$C,$A$71)/Q$68 -> 0 | R92: =SUMIFS(ТСО!T:T,ТСО!$A:$A,$C92,ТСО!$C:$C,$A$71)/R$68 -> 0 | S92: =SUMIFS(ТСО!U:U,ТСО!$A:$A,$C92,ТСО!$C:$C,$A$71)/S$68 -> 0 | T92: =SUMIFS(ТСО!V:V,ТСО!$A:$A,$C92,ТСО!$C:$C,$A$71)/T$68 -> 0 | U92: =SUMIFS(ТСО!W:W,ТСО!$A:$A,$C92,ТСО!$C:$C,$A$71)/U$68 -> 0 | V92: =SUMIFS(ТСО!X:X,ТСО!$A:$A,$C92,ТСО!$C:$C,$A$71)/V$68 -> 0 | W92: =SUMIFS(ТСО!Y:Y,ТСО!$A:$A,$C92,ТСО!$C:$C,$A$71)/W$68 -> 0 | X92: =SUMIFS(ТСО!Z:Z,ТСО!$A:$A,$C92,ТСО!$C:$C,$A$71)/X$68 -> 0 | Y92: =SUM(E92:X92) -> 6879.3691 | Z92: =Y92/K8 -> 859.92114
B93: =B75 -> 1 | C93: =C75 -> БелАЗ 7531 (ГПФК) | D93: =D75 -> тыс. долл. | E93: =SUMIFS(ТСО!G:G,ТСО!$A:$A,$C93,ТСО!$C:$C,$A$71)/E$68 -> 148.04729 | F93: =SUMIFS(ТСО!H:H,ТСО!$A:$A,$C93,ТСО!$C:$C,$A$71)/F$68 -> 317.60136 | G93: =SUMIFS(ТСО!I:I,ТСО!$A:$A,$C93,ТСО!$C:$C,$A$71)/G$68 -> 572.06806 | H93: =SUMIFS(ТСО!J:J,ТСО!$A:$A,$C93,ТСО!$C:$C,$A$71)/H$68 -> 727.00656 | I93: =SUMIFS(ТСО!K:K,ТСО!$A:$A,$C93,ТСО!$C:$C,$A$71)/I$68 -> 631.62288 | J93: =SUMIFS(ТСО!L:L,ТСО!$A:$A,$C93,ТСО!$C:$C,$A$71)/J$68 -> 688.61907 | K93: =SUMIFS(ТСО!M:M,ТСО!$A:$A,$C93,ТСО!$C:$C,$A$71)/K$68 -> 180.49511 | L93: =SUMIFS(ТСО!N:N,ТСО!$A:$A,$C93,ТСО!$C:$C,$A$71)/L$68 -> 847.19412 | M93: =SUMIFS(ТСО!O:O,ТСО!$A:$A,$C93,ТСО!$C:$C,$A$71)/M$68 -> 961.75027 | N93: =SUMIFS(ТСО!P:P,ТСО!$A:$A,$C93,ТСО!$C:$C,$A$71)/N$68 -> 231.50896 | O93: =SUMIFS(ТСО!Q:Q,ТСО!$A:$A,$C93,ТСО!$C:$C,$A$71)/O$68 -> 0 | P93: =SUMIFS(ТСО!R:R,ТСО!$A:$A,$C93,ТСО!$C:$C,$A$71)/P$68 -> 0 | Q93: =SUMIFS(ТСО!S:S,ТСО!$A:$A,$C93,ТСО!$C:$C,$A$71)/Q$68 -> 0 | R93: =SUMIFS(ТСО!T:T,ТСО!$A:$A,$C93,ТСО!$C:$C,$A$71)/R$68 -> 0 | S93: =SUMIFS(ТСО!U:U,ТСО!$A:$A,$C93,ТСО!$C:$C,$A$71)/S$68 -> 0 | T93: =SUMIFS(ТСО!V:V,ТСО!$A:$A,$C93,ТСО!$C:$C,$A$71)/T$68 -> 0 | U93: =SUMIFS(ТСО!W:W,ТСО!$A:$A,$C93,ТСО!$C:$C,$A$71)/U$68 -> 0 | V93: =SUMIFS(ТСО!X:X,ТСО!$A:$A,$C93,ТСО!$C:$C,$A$71)/V$68 -> 0 | W93: =SUMIFS(ТСО!Y:Y,ТСО!$A:$A,$C93,ТСО!$C:$C,$A$71)/W$68 -> 0 | X93: =SUMIFS(ТСО!Z:Z,ТСО!$A:$A,$C93,ТСО!$C:$C,$A$71)/X$68 -> 0 | Y93: =SUM(E93:X93) -> 5305.9137 | Z93: =Y93/K9 -> 530.59137
B94: =B76 -> 1 | C94: =C76 -> XCMG 240 | D94: =D76 -> тыс. долл. | E94: =SUMIFS(ТСО!G:G,ТСО!$A:$A,$C94,ТСО!$C:$C,$A$71)/E$68 -> 0 | F94: =SUMIFS(ТСО!H:H,ТСО!$A:$A,$C94,ТСО!$C:$C,$A$71)/F$68 -> 0 | G94: =SUMIFS(ТСО!I:I,ТСО!$A:$A,$C94,ТСО!$C:$C,$A$71)/G$68 -> 0 | H94: =SUMIFS(ТСО!J:J,ТСО!$A:$A,$C94,ТСО!$C:$C,$A$71)/H$68 -> 0 | I94: =SUMIFS(ТСО!K:K,ТСО!$A:$A,$C94,ТСО!$C:$C,$A$71)/I$68 -> 0 | J94: =SUMIFS(ТСО!L:L,ТСО!$A:$A,$C94,ТСО!$C:$C,$A$71)/J$68 -> 0 | K94: =SUMIFS(ТСО!M:M,ТСО!$A:$A,$C94,ТСО!$C:$C,$A$71)/K$68 -> 0 | L94: =SUMIFS(ТСО!N:N,ТСО!$A:$A,$C94,ТСО!$C:$C,$A$71)/L$68 -> 0 | M94: =SUMIFS(ТСО!O:O,ТСО!$A:$A,$C94,ТСО!$C:$C,$A$71)/M$68 -> 0 | N94: =SUMIFS(ТСО!P:P,ТСО!$A:$A,$C94,ТСО!$C:$C,$A$71)/N$68 -> 0 | O94: =SUMIFS(ТСО!Q:Q,ТСО!$A:$A,$C94,ТСО!$C:$C,$A$71)/O$68 -> 0 | P94: =SUMIFS(ТСО!R:R,ТСО!$A:$A,$C94,ТСО!$C:$C,$A$71)/P$68 -> 0 | Q94: =SUMIFS(ТСО!S:S,ТСО!$A:$A,$C94,ТСО!$C:$C,$A$71)/Q$68 -> 0 | R94: =SUMIFS(ТСО!T:T,ТСО!$A:$A,$C94,ТСО!$C:$C,$A$71)/R$68 -> 0 | S94: =SUMIFS(ТСО!U:U,ТСО!$A:$A,$C94,ТСО!$C:$C,$A$71)/S$68 -> 0 | T94: =SUMIFS(ТСО!V:V,ТСО!$A:$A,$C94,ТСО!$C:$C,$A$71)/T$68 -> 0 | U94: =SUMIFS(ТСО!W:W,ТСО!$A:$A,$C94,ТСО!$C:$C,$A$71)/U$68 -> 0 | V94: =SUMIFS(ТСО!X:X,ТСО!$A:$A,$C94,ТСО!$C:$C,$A$71)/V$68 -> 0 | W94: =SUMIFS(ТСО!Y:Y,ТСО!$A:$A,$C94,ТСО!$C:$C,$A$71)/W$68 -> 0 | X94: =SUMIFS(ТСО!Z:Z,ТСО!$A:$A,$C94,ТСО!$C:$C,$A$71)/X$68 -> 0 | Y94: =SUM(E94:X94) -> 0 | Z94: =Y94/K10 -> #DIV/0!
B95: =B77 -> 1 | C95: =C77 -> БелАЗ 7531 (БТЛ) | D95: =D77 -> тыс. долл. | E95: =SUMIFS(ТСО!G:G,ТСО!$A:$A,$C95,ТСО!$C:$C,$A$71)/E$68 -> 130.7933 | F95: =SUMIFS(ТСО!H:H,ТСО!$A:$A,$C95,ТСО!$C:$C,$A$71)/F$68 -> 209.01238 | G95: =SUMIFS(ТСО!I:I,ТСО!$A:$A,$C95,ТСО!$C:$C,$A$71)/G$68 -> 615.43665 | H95: =SUMIFS(ТСО!J:J,ТСО!$A:$A,$C95,ТСО!$C:$C,$A$71)/H$68 -> 911.52059 | I95: =SUMIFS(ТСО!K:K,ТСО!$A:$A,$C95,ТСО!$C:$C,$A$71)/I$68 -> 364.66374 | J95: =SUMIFS(ТСО!L:L,ТСО!$A:$A,$C95,ТСО!$C:$C,$A$71)/J$68 -> 636.96468 | K95: =SUMIFS(ТСО!M:M,ТСО!$A:$A,$C95,ТСО!$C:$C,$A$71)/K$68 -> 323.46018 | L95: =SUMIFS(ТСО!N:N,ТСО!$A:$A,$C95,ТСО!$C:$C,$A$71)/L$68 -> 971.72701 | M95: =SUMIFS(ТСО!O:O,ТСО!$A:$A,$C95,ТСО!$C:$C,$A$71)/M$68 -> 805.29884 | N95: =SUMIFS(ТСО!P:P,ТСО!$A:$A,$C95,ТСО!$C:$C,$A$71)/N$68 -> 335.15355 | O95: =SUMIFS(ТСО!Q:Q,ТСО!$A:$A,$C95,ТСО!$C:$C,$A$71)/O$68 -> 0 | P95: =SUMIFS(ТСО!R:R,ТСО!$A:$A,$C95,ТСО!$C:$C,$A$71)/P$68 -> 0 | Q95: =SUMIFS(ТСО!S:S,ТСО!$A:$A,$C95,ТСО!$C:$C,$A$71)/Q$68 -> 0 | R95: =SUMIFS(ТСО!T:T,ТСО!$A:$A,$C95,ТСО!$C:$C,$A$71)/R$68 -> 0 | S95: =SUMIFS(ТСО!U:U,ТСО!$A:$A,$C95,ТСО!$C:$C,$A$71)/S$68 -> 0 | T95: =SUMIFS(ТСО!V:V,ТСО!$A:$A,$C95,ТСО!$C:$C,$A$71)/T$68 -> 0 | U95: =SUMIFS(ТСО!W:W,ТСО!$A:$A,$C95,ТСО!$C:$C,$A$71)/U$68 -> 0 | V95: =SUMIFS(ТСО!X:X,ТСО!$A:$A,$C95,ТСО!$C:$C,$A$71)/V$68 -> 0 | W95: =SUMIFS(ТСО!Y:Y,ТСО!$A:$A,$C95,ТСО!$C:$C,$A$71)/W$68 -> 0 | X95: =SUMIFS(ТСО!Z:Z,ТСО!$A:$A,$C95,ТСО!$C:$C,$A$71)/X$68 -> 0 | Y95: =SUM(E95:X95) -> 5304.0309 | Z95: =Y95/K11 -> 530.40309
B96: =B78 -> 0 | C96: =C78 -> 0 | D96: =D78 -> тыс. долл. | E96: =SUMIFS(ТСО!G:G,ТСО!$A:$A,$C96,ТСО!$C:$C,$A$71)/E$68 -> 0 | F96: =SUMIFS(ТСО!H:H,ТСО!$A:$A,$C96,ТСО!$C:$C,$A$71)/F$68 -> 0 | G96: =SUMIFS(ТСО!I:I,ТСО!$A:$A,$C96,ТСО!$C:$C,$A$71)/G$68 -> 0 | H96: =SUMIFS(ТСО!J:J,ТСО!$A:$A,$C96,ТСО!$C:$C,$A$71)/H$68 -> 0 | I96: =SUMIFS(ТСО!K:K,ТСО!$A:$A,$C96,ТСО!$C:$C,$A$71)/I$68 -> 0 | J96: =SUMIFS(ТСО!L:L,ТСО!$A:$A,$C96,ТСО!$C:$C,$A$71)/J$68 -> 0 | K96: =SUMIFS(ТСО!M:M,ТСО!$A:$A,$C96,ТСО!$C:$C,$A$71)/K$68 -> 0 | L96: =SUMIFS(ТСО!N:N,ТСО!$A:$A,$C96,ТСО!$C:$C,$A$71)/L$68 -> 0 | M96: =SUMIFS(ТСО!O:O,ТСО!$A:$A,$C96,ТСО!$C:$C,$A$71)/M$68 -> 0 | N96: =SUMIFS(ТСО!P:P,ТСО!$A:$A,$C96,ТСО!$C:$C,$A$71)/N$68 -> 0 | O96: =SUMIFS(ТСО!Q:Q,ТСО!$A:$A,$C96,ТСО!$C:$C,$A$71)/O$68 -> 0 | P96: =SUMIFS(ТСО!R:R,ТСО!$A:$A,$C96,ТСО!$C:$C,$A$71)/P$68 -> 0 | Q96: =SUMIFS(ТСО!S:S,ТСО!$A:$A,$C96,ТСО!$C:$C,$A$71)/Q$68 -> 0 | R96: =SUMIFS(ТСО!T:T,ТСО!$A:$A,$C96,ТСО!$C:$C,$A$71)/R$68 -> 0 | S96: =SUMIFS(ТСО!U:U,ТСО!$A:$A,$C96,ТСО!$C:$C,$A$71)/S$68 -> 0 | T96: =SUMIFS(ТСО!V:V,ТСО!$A:$A,$C96,ТСО!$C:$C,$A$71)/T$68 -> 0 | U96: =SUMIFS(ТСО!W:W,ТСО!$A:$A,$C96,ТСО!$C:$C,$A$71)/U$68 -> 0 | V96: =SUMIFS(ТСО!X:X,ТСО!$A:$A,$C96,ТСО!$C:$C,$A$71)/V$68 -> 0 | W96: =SUMIFS(ТСО!Y:Y,ТСО!$A:$A,$C96,ТСО!$C:$C,$A$71)/W$68 -> 0 | X96: =SUMIFS(ТСО!Z:Z,ТСО!$A:$A,$C96,ТСО!$C:$C,$A$71)/X$68 -> 0 | Y96: =SUM(E96:X96) -> 0 | Z96: =Y96/K12 -> #DIV/0!
B97: =B79 -> 0 | C97: =C79 -> 0 | D97: =D79 -> тыс. долл. | E97: =SUMIFS(ТСО!G:G,ТСО!$A:$A,$C97,ТСО!$C:$C,$A$71)/E$68 -> 0 | F97: =SUMIFS(ТСО!H:H,ТСО!$A:$A,$C97,ТСО!$C:$C,$A$71)/F$68 -> 0 | G97: =SUMIFS(ТСО!I:I,ТСО!$A:$A,$C97,ТСО!$C:$C,$A$71)/G$68 -> 0 | H97: =SUMIFS(ТСО!J:J,ТСО!$A:$A,$C97,ТСО!$C:$C,$A$71)/H$68 -> 0 | I97: =SUMIFS(ТСО!K:K,ТСО!$A:$A,$C97,ТСО!$C:$C,$A$71)/I$68 -> 0 | J97: =SUMIFS(ТСО!L:L,ТСО!$A:$A,$C97,ТСО!$C:$C,$A$71)/J$68 -> 0 | K97: =SUMIFS(ТСО!M:M,ТСО!$A:$A,$C97,ТСО!$C:$C,$A$71)/K$68 -> 0 | L97: =SUMIFS(ТСО!N:N,ТСО!$A:$A,$C97,ТСО!$C:$C,$A$71)/L$68 -> 0 | M97: =SUMIFS(ТСО!O:O,ТСО!$A:$A,$C97,ТСО!$C:$C,$A$71)/M$68 -> 0 | N97: =SUMIFS(ТСО!P:P,ТСО!$A:$A,$C97,ТСО!$C:$C,$A$71)/N$68 -> 0 | O97: =SUMIFS(ТСО!Q:Q,ТСО!$A:$A,$C97,ТСО!$C:$C,$A$71)/O$68 -> 0 | P97: =SUMIFS(ТСО!R:R,ТСО!$A:$A,$C97,ТСО!$C:$C,$A$71)/P$68 -> 0 | Q97: =SUMIFS(ТСО!S:S,ТСО!$A:$A,$C97,ТСО!$C:$C,$A$71)/Q$68 -> 0 | R97: =SUMIFS(ТСО!T:T,ТСО!$A:$A,$C97,ТСО!$C:$C,$A$71)/R$68 -> 0 | S97: =SUMIFS(ТСО!U:U,ТСО!$A:$A,$C97,ТСО!$C:$C,$A$71)/S$68 -> 0 | T97: =SUMIFS(ТСО!V:V,ТСО!$A:$A,$C97,ТСО!$C:$C,$A$71)/T$68 -> 0 | U97: =SUMIFS(ТСО!W:W,ТСО!$A:$A,$C97,ТСО!$C:$C,$A$71)/U$68 -> 0 | V97: =SUMIFS(ТСО!X:X,ТСО!$A:$A,$C97,ТСО!$C:$C,$A$71)/V$68 -> 0 | W97: =SUMIFS(ТСО!Y:Y,ТСО!$A:$A,$C97,ТСО!$C:$C,$A$71)/W$68 -> 0 | X97: =SUMIFS(ТСО!Z:Z,ТСО!$A:$A,$C97,ТСО!$C:$C,$A$71)/X$68 -> 0 | Y97: =SUM(E97:X97) -> 0 | Z97: =Y97/K13 -> #DIV/0!
B98: =B80 -> 0 | C98: =C80 -> 0 | D98: =D80 -> тыс. долл. | E98: =SUMIFS(ТСО!G:G,ТСО!$A:$A,$C98,ТСО!$C:$C,$A$71)/E$68 -> 0 | F98: =SUMIFS(ТСО!H:H,ТСО!$A:$A,$C98,ТСО!$C:$C,$A$71)/F$68 -> 0 | G98: =SUMIFS(ТСО!I:I,ТСО!$A:$A,$C98,ТСО!$C:$C,$A$71)/G$68 -> 0 | H98: =SUMIFS(ТСО!J:J,ТСО!$A:$A,$C98,ТСО!$C:$C,$A$71)/H$68 -> 0 | I98: =SUMIFS(ТСО!K:K,ТСО!$A:$A,$C98,ТСО!$C:$C,$A$71)/I$68 -> 0 | J98: =SUMIFS(ТСО!L:L,ТСО!$A:$A,$C98,ТСО!$C:$C,$A$71)/J$68 -> 0 | K98: =SUMIFS(ТСО!M:M,ТСО!$A:$A,$C98,ТСО!$C:$C,$A$71)/K$68 -> 0 | L98: =SUMIFS(ТСО!N:N,ТСО!$A:$A,$C98,ТСО!$C:$C,$A$71)/L$68 -> 0 | M98: =SUMIFS(ТСО!O:O,ТСО!$A:$A,$C98,ТСО!$C:$C,$A$71)/M$68 -> 0 | N98: =SUMIFS(ТСО!P:P,ТСО!$A:$A,$C98,ТСО!$C:$C,$A$71)/N$68 -> 0 | O98: =SUMIFS(ТСО!Q:Q,ТСО!$A:$A,$C98,ТСО!$C:$C,$A$71)/O$68 -> 0 | P98: =SUMIFS(ТСО!R:R,ТСО!$A:$A,$C98,ТСО!$C:$C,$A$71)/P$68 -> 0 | Q98: =SUMIFS(ТСО!S:S,ТСО!$A:$A,$C98,ТСО!$C:$C,$A$71)/Q$68 -> 0 | R98: =SUMIFS(ТСО!T:T,ТСО!$A:$A,$C98,ТСО!$C:$C,$A$71)/R$68 -> 0 | S98: =SUMIFS(ТСО!U:U,ТСО!$A:$A,$C98,ТСО!$C:$C,$A$71)/S$68 -> 0 | T98: =SUMIFS(ТСО!V:V,ТСО!$A:$A,$C98,ТСО!$C:$C,$A$71)/T$68 -> 0 | U98: =SUMIFS(ТСО!W:W,ТСО!$A:$A,$C98,ТСО!$C:$C,$A$71)/U$68 -> 0 | V98: =SUMIFS(ТСО!X:X,ТСО!$A:$A,$C98,ТСО!$C:$C,$A$71)/V$68 -> 0 | W98: =SUMIFS(ТСО!Y:Y,ТСО!$A:$A,$C98,ТСО!$C:$C,$A$71)/W$68 -> 0 | X98: =SUMIFS(ТСО!Z:Z,ТСО!$A:$A,$C98,ТСО!$C:$C,$A$71)/X$68 -> 0 | Y98: =SUM(E98:X98) -> 0 | Z98: =Y98/K14 -> #DIV/0!
B99: =B81 -> 0 | C99: =C81 -> 0 | D99: =D81 -> тыс. долл. | E99: =SUMIFS(ТСО!G:G,ТСО!$A:$A,$C99,ТСО!$C:$C,$A$71)/E$68 -> 0 | F99: =SUMIFS(ТСО!H:H,ТСО!$A:$A,$C99,ТСО!$C:$C,$A$71)/F$68 -> 0 | G99: =SUMIFS(ТСО!I:I,ТСО!$A:$A,$C99,ТСО!$C:$C,$A$71)/G$68 -> 0 | H99: =SUMIFS(ТСО!J:J,ТСО!$A:$A,$C99,ТСО!$C:$C,$A$71)/H$68 -> 0 | I99: =SUMIFS(ТСО!K:K,ТСО!$A:$A,$C99,ТСО!$C:$C,$A$71)/I$68 -> 0 | J99: =SUMIFS(ТСО!L:L,ТСО!$A:$A,$C99,ТСО!$C:$C,$A$71)/J$68 -> 0 | K99: =SUMIFS(ТСО!M:M,ТСО!$A:$A,$C99,ТСО!$C:$C,$A$71)/K$68 -> 0 | L99: =SUMIFS(ТСО!N:N,ТСО!$A:$A,$C99,ТСО!$C:$C,$A$71)/L$68 -> 0 | M99: =SUMIFS(ТСО!O:O,ТСО!$A:$A,$C99,ТСО!$C:$C,$A$71)/M$68 -> 0 | N99: =SUMIFS(ТСО!P:P,ТСО!$A:$A,$C99,ТСО!$C:$C,$A$71)/N$68 -> 0 | O99: =SUMIFS(ТСО!Q:Q,ТСО!$A:$A,$C99,ТСО!$C:$C,$A$71)/O$68 -> 0 | P99: =SUMIFS(ТСО!R:R,ТСО!$A:$A,$C99,ТСО!$C:$C,$A$71)/P$68 -> 0 | Q99: =SUMIFS(ТСО!S:S,ТСО!$A:$A,$C99,ТСО!$C:$C,$A$71)/Q$68 -> 0 | R99: =SUMIFS(ТСО!T:T,ТСО!$A:$A,$C99,ТСО!$C:$C,$A$71)/R$68 -> 0 | S99: =SUMIFS(ТСО!U:U,ТСО!$A:$A,$C99,ТСО!$C:$C,$A$71)/S$68 -> 0 | T99: =SUMIFS(ТСО!V:V,ТСО!$A:$A,$C99,ТСО!$C:$C,$A$71)/T$68 -> 0 | U99: =SUMIFS(ТСО!W:W,ТСО!$A:$A,$C99,ТСО!$C:$C,$A$71)/U$68 -> 0 | V99: =SUMIFS(ТСО!X:X,ТСО!$A:$A,$C99,ТСО!$C:$C,$A$71)/V$68 -> 0 | W99: =SUMIFS(ТСО!Y:Y,ТСО!$A:$A,$C99,ТСО!$C:$C,$A$71)/W$68 -> 0 | X99: =SUMIFS(ТСО!Z:Z,ТСО!$A:$A,$C99,ТСО!$C:$C,$A$71)/X$68 -> 0 | Y99: =SUM(E99:X99) -> 0 | Z99: =Y99/K15 -> #DIV/0!
B100: =B82 -> 0 | C100: =C82 -> 0 | D100: =D82 -> тыс. долл. | E100: =SUMIFS(ТСО!G:G,ТСО!$A:$A,$C100,ТСО!$C:$C,$A$71)/E$68 -> 0 | F100: =SUMIFS(ТСО!H:H,ТСО!$A:$A,$C100,ТСО!$C:$C,$A$71)/F$68 -> 0 | G100: =SUMIFS(ТСО!I:I,ТСО!$A:$A,$C100,ТСО!$C:$C,$A$71)/G$68 -> 0 | H100: =SUMIFS(ТСО!J:J,ТСО!$A:$A,$C100,ТСО!$C:$C,$A$71)/H$68 -> 0 | I100: =SUMIFS(ТСО!K:K,ТСО!$A:$A,$C100,ТСО!$C:$C,$A$71)/I$68 -> 0 | J100: =SUMIFS(ТСО!L:L,ТСО!$A:$A,$C100,ТСО!$C:$C,$A$71)/J$68 -> 0 | K100: =SUMIFS(ТСО!M:M,ТСО!$A:$A,$C100,ТСО!$C:$C,$A$71)/K$68 -> 0 | L100: =SUMIFS(ТСО!N:N,ТСО!$A:$A,$C100,ТСО!$C:$C,$A$71)/L$68 -> 0 | M100: =SUMIFS(ТСО!O:O,ТСО!$A:$A,$C100,ТСО!$C:$C,$A$71)/M$68 -> 0 | N100: =SUMIFS(ТСО!P:P,ТСО!$A:$A,$C100,ТСО!$C:$C,$A$71)/N$68 -> 0 | O100: =SUMIFS(ТСО!Q:Q,ТСО!$A:$A,$C100,ТСО!$C:$C,$A$71)/O$68 -> 0 | P100: =SUMIFS(ТСО!R:R,ТСО!$A:$A,$C100,ТСО!$C:$C,$A$71)/P$68 -> 0 | Q100: =SUMIFS(ТСО!S:S,ТСО!$A:$A,$C100,ТСО!$C:$C,$A$71)/Q$68 -> 0 | R100: =SUMIFS(ТСО!T:T,ТСО!$A:$A,$C100,ТСО!$C:$C,$A$71)/R$68 -> 0 | S100: =SUMIFS(ТСО!U:U,ТСО!$A:$A,$C100,ТСО!$C:$C,$A$71)/S$68 -> 0 | T100: =SUMIFS(ТСО!V:V,ТСО!$A:$A,$C100,ТСО!$C:$C,$A$71)/T$68 -> 0 | U100: =SUMIFS(ТСО!W:W,ТСО!$A:$A,$C100,ТСО!$C:$C,$A$71)/U$68 -> 0 | V100: =SUMIFS(ТСО!X:X,ТСО!$A:$A,$C100,ТСО!$C:$C,$A$71)/V$68 -> 0 | W100: =SUMIFS(ТСО!Y:Y,ТСО!$A:$A,$C100,ТСО!$C:$C,$A$71)/W$68 -> 0 | X100: =SUMIFS(ТСО!Z:Z,ТСО!$A:$A,$C100,ТСО!$C:$C,$A$71)/X$68 -> 0 | Y100: =SUM(E100:X100) -> 0 | Z100: =Y100/K16 -> #DIV/0!
... B103: =B85 -> 0 | C103: =C85 -> 0 | D103: =D85 -> тыс. долл. | E103: =SUMIFS(ТСО!G:G,ТСО!$A:$A,$C103,ТСО!$C:$C,$A$71)/E$68 -> 0 | F103: =SUMIFS(ТСО!H:H,ТСО!$A:$A,$C103,ТСО!$C:$C,$A$71)/F$68 -> 0 | G103: =SUMIFS(ТСО!I:I,ТСО!$A:$A,$C103,ТСО!$C:$C,$A$71)/G$68 -> 0 | H103: =SUMIFS(ТСО!J:J,ТСО!$A:$A,$C103,ТСО!$C:$C,$A$71)/H$68 -> 0 | I103: =SUMIFS(ТСО!K:K,ТСО!$A:$A,$C103,ТСО!$C:$C,$A$71)/I$68 -> 0 | J103: =SUMIFS(ТСО!L:L,ТСО!$A:$A,$C103,ТСО!$C:$C,$A$71)/J$68 -> 0 | K103: =SUMIFS(ТСО!M:M,ТСО!$A:$A,$C103,ТСО!$C:$C,$A$71)/K$68 -> 0 | L103: =SUMIFS(ТСО!N:N,ТСО!$A:$A,$C103,ТСО!$C:$C,$A$71)/L$68 -> 0 | M103: =SUMIFS(ТСО!O:O,ТСО!$A:$A,$C103,ТСО!$C:$C,$A$71)/M$68 -> 0 | N103: =SUMIFS(ТСО!P:P,ТСО!$A:$A,$C103,ТСО!$C:$C,$A$71)/N$68 -> 0 | O103: =SUMIFS(ТСО!Q:Q,ТСО!$A:$A,$C103,ТСО!$C:$C,$A$71)/O$68 -> 0 | P103: =SUMIFS(ТСО!R:R,ТСО!$A:$A,$C103,ТСО!$C:$C,$A$71)/P$68 -> 0 | Q103: =SUMIFS(ТСО!S:S,ТСО!$A:$A,$C103,ТСО!$C:$C,$A$71)/Q$68 -> 0 | R103: =SUMIFS(ТСО!T:T,ТСО!$A:$A,$C103,ТСО!$C:$C,$A$71)/R$68 -> 0 | S103: =SUMIFS(ТСО!U:U,ТСО!$A:$A,$C103,ТСО!$C:$C,$A$71)/S$68 -> 0 | T103: =SUMIFS(ТСО!V:V,ТСО!$A:$A,$C103,ТСО!$C:$C,$A$71)/T$68 -> 0 | U103: =SUMIFS(ТСО!W:W,ТСО!$A:$A,$C103,ТСО!$C:$C,$A$71)/U$68 -> 0 | V103: =SUMIFS(ТСО!X:X,ТСО!$A:$A,$C103,ТСО!$C:$C,$A$71)/V$68 -> 0 | W103: =SUMIFS(ТСО!Y:Y,ТСО!$A:$A,$C103,ТСО!$C:$C,$A$71)/W$68 -> 0 | X103: =SUMIFS(ТСО!Z:Z,ТСО!$A:$A,$C103,ТСО!$C:$C,$A$71)/X$68 -> 0 | Y103: =SUM(E103:X103) -> 0 | Z103: =Y103/K19 -> #DIV/0!
B104: =B86 -> 1
B105: 1
B106: 1 | C106: Затраты тендер дек. 2024 | D106: =D88 -> Ед. изм. | E106: =E88 -> 1 | F106: =F88 -> 2 | G106: =G88 -> 3 | H106: =H88 -> 4 | I106: =I88 -> 5 | J106: =J88 -> 6 | K106: =K88 -> 7 | ... Z106: =Z88 -> Среднее
B107: 1 | C107: =C62 -> NHL NTE 240 | D107: =D89 -> тыс. долл. | E107: 115.46064 | F107: 130.86592 | G107: 144.64789 | H107: 1832.2455 | I107: 260.77846 | J107: 156.03578 | K107: 1837.2103 | L107: 344.07359 | M107: 198.55635 | N107: 276.01151 | Y107: =SUM(E107:X107) -> 5295.8859 | Z107: =AVERAGE(E107:X107) -> 529.58859
B108: 1 | C108: =C63 -> ESTAR ESDE240 | D108: =D107 -> тыс. долл. | E108: 447.75407 | F108: 463.8443 | G108: 3542.9367 | H108: 468.20517 | I108: 1773.365 | J108: 3546.3709 | K108: 449.58761 | L108: 498.04017 | M108: 4857.7251 | N108: 424.38068 | Y108: =SUM(E108:X108) -> 16472.21 | Z108: =AVERAGE(E108:X108) -> 1647.221
B109: 1 | C109: =C64 -> БелАЗ-7531H привод Силовые Маш | D109: =D108 -> тыс. долл. | E109: 174.50985 | F109: 340.7414 | G109: 1174.6585 | H109: 266.85108 | I109: 523.77496 | J109: 1296.0426 | K109: 198.80204 | L109: 387.03863 | M109: 1438.1858 | N109: 254.649 | Y109: =SUM(E109:X109) -> 6055.2539 | Z109: =AVERAGE(E109:X109) -> 605.52539
...

Sheet Статус
C2: Все | D2: =Свод!F23 -> NHL NTE 240 | E2: =Свод!G23 -> Estar ESDE240 (ГПБ К) | F2: =Свод!H23 -> SANY SET240S | G2: =Свод!I23 -> TZCO TZE240 | H2: =Свод!J23 -> БелАЗ 7531 (ГПФК) | I2: =Свод!K23 -> XCMG 240 | J2: =Свод!L23 -> БелАЗ 7531 (БТЛ)
B3: Загрузка | C3: 07.07 - запросили политику загрузки с расчетом номинальной грузоподъемности, вес футеровки | D3: 09.07 - прислали политику; заданы вопросы (путаница в цифрах 220/240, 228/334) 10.07 - беру в расчет 227,8 (236 - 8,2 футеровка) пока нет иных данных | E3: 20.07 - прислали политику и схему футеровки | F3: 07.07 - прислали политику и вес стандартной футеровки 07.07 - запросили вес кузова с футеровкой под скальную спецификацию (с раскладкой листов в кузове, толщиной, весом и т.д.), отправили ТЗ на самосвал (по запросу) | G3: 15.07 - прислали политику, не прислали расчет номинальной; повторно запрошен | H3: 10.07 - ждут ответ от завода | J3: 22.07 - запросили расчет, политику
F4: 21.07 - прислали вес скального кузова; замечание Кузнецова В.Е. | G4: 16.07 - прислали расчет полезной нагрузки с учетом футеровки
F5: 22.07 - получен ответ
C6: долги | D6: Кузнецов В.Е., Михайлов А.С. - уточняют с поставщиком/заводом | H6: нет ответа от завода | J6: нет ответа
B7: Срок эксплуатации | C7: 07.07 - запрос (с ТСО) указать срок службы, установленный заводом-изготовителем (подтвердить документом) | D7: 29.07 - прислали письмо от завода (15-20 лет) | F7: 13.07 - прислали письмо о сроке службы (12 лет) | G7: 13.07 - по тексту письма: 8 лет | H7: 08.07 - прислали руководство; на встрече договорились, что запросят у завода 10.07 - ждут ответ от завода | J7: 22.07 - запросили
F8: 29.07 - еще раз прислали письмо, по запросу | G8: 29.07 - прислали письмо, 8 лет
C9: долги | E9: нет ответа, ТСО на 10 лет | H9: нет ответа от завода, ТСО на 10 лет | J9: нет ответа
B10: ТСО | C10: 25-26.06 - отправка шаблона для заполнения поставщикам | J10: 22.07 - прислали ТСО
C11: 03.07 - получены заполненные файлы от Михайлова А.С. (21:02) 06.07 - направлены в Развитие для оценки, Лысенко Д.В, Кузнецов В.Е. (09:11) | J11: 23.07 - принято (Кузнецов В.Е.)
C12: 07.07 - получены замечания от Развития, направлены поставщикам | D12: 1. КТГ завышен 2. Указать срок службы, установленный заводом-изготовителем (подтвердить документом) 3. Некорректная цикличность ТО – проверить и исправить 4. Текущие ремонты не заполнены 5. Реальные трудозатраты и текущие ремонты не оценены 6. Капитальные ремонты не досчитаны и не заполнены полностью 7. Стоимостные расчеты занижены | E12: 1. Текущие ремонты отсутствуют 2. Указать срок службы, установленный заводом-изготовителем (подтвердить документом) | F12: 1. Шины включены – исключить (указать стоимость дополнительно отдельно) 2. Неполное предоставление данных по затратам на КР | G12: 1. Цикличность – ок 2. Занижена станка н-часа 3. 5000H PERIODIC SERVICE(PM LABOR) - затраты в ТО не представлены 4. Автошины убрать (выделить стоимость) 5. Указать срок службы, установленный заводом-изготовителем (подтвердить документом) | H12: 1. Некорректная цикличность ТО (ТО-2 и ТО-3) – проверить и исправить 2. Исходя из цикличности проверить правильность расходников в ТО 3. Перепроверить периодичность КР узлов 4. Указать срок службы, установленный заводом-изготовителем (подтвердить документом) 5. КТГ завышен
D13: 08.07 - встреча с поставщиком (наши вопросы, как заполнять шаблон) | E13: 24.07 - прислали ТСО, берем в работу (Кузнецов В.Е.) | F13: 13.07 - прислали обновленный файл для обсуждения (встреча 13.07); на встрече обсудили вопросы, ждем данные для расчета с учетом замечаний (наработка узлов, завышен КТГ, не заполнены полностью часы простоя и трудоемкость) | G13: 13.07 - прислали ТСО; запрос: скорректировать на срок службы (8 лет)+замечания (трудозатраты и простои на КР, динамика КТГ с учетом КР) | H13: 08.07 - прислали руководство по эксплуатации БЕЛАЗ-7531; "Руководство во вложении, вы можете все перепроверить" 08.07 - встреча с поставщиком (наши вопросы, как заполнять шаблон)
D14: 14.07 - прислали ТСО с затратами на 35% меньше первой версии; замечания не исправлены, КТГ 0,94 на 20 лет; назначена встреча, еще раз обсудили замечания | F14: 16.07 - прислали ТСО, берем в работу (Кузнецов В.Е.) | G14: 15.07 - прислали ТСО, берем в работу (Кузнецов В.Е.) | H14: 09.07 - прислали данные, направлены вопросы (занижение ремонтов 7-й год (как результат, высокий КТГ), ремонты – не скорректирован ресурс до замены (обсуждали на встрече))
D15: 27.07 - прислали ТСО | H15: 10.07 - ответ, что данные корректны; берем в работу (Кузнецов В.Е.)
D16: 28.07 - отправили замечания, не правят; берем в работу что есть
C17: долги

Sheet Свод
C2: Технико-экономическая оценка стоимости владения
C4: Ранжирование общих аннуитетов - по возрастанию | G4: Ранжирование по стоимости самосвала - по возрастанию
C5: № | D5: Марка автосамосвала | E5: Аннуитет, руб/ткм | G5: =C5 -> № | H5: =D5 -> Марка автосамосвала | K5: Цена за ед., тыс. руб.
C6: 1 | D6: =IFERROR(HLOOKUP(E6,$F$64:$T$66,3,FALSE),"-") -> - | E6: =IFERROR(SMALL($F$64:$T$64,C6),"-") -> - | G6: =C6 -> 1 | H6: =IFERROR(HLOOKUP(K6,$F$65:$T$66,2,FALSE),"-") -> - | K6: =IFERROR(SMALL($F$65:$T$65,C6),"-") -> -
C7: =C6+1 -> 2 | D7: =IFERROR(HLOOKUP(E7,$F$64:$T$66,3,FALSE),"-") -> - | E7: =IFERROR(SMALL($F$64:$T$64,C7),"-") -> - | G7: =C7 -> 2 | H7: =IFERROR(HLOOKUP(K7,$F$65:$T$66,2,FALSE),"-") -> - | K7: =IFERROR(SMALL($F$65:$T$65,C7),"-") -> -
C8: =C7+1 -> 3 | D8: =IFERROR(HLOOKUP(E8,$F$64:$T$66,3,FALSE),"-") -> - | E8: =IFERROR(SMALL($F$64:$T$64,C8),"-") -> - | G8: =C8 -> 3 | H8: =IFERROR(HLOOKUP(K8,$F$65:$T$66,2,FALSE),"-") -> - | K8: =IFERROR(SMALL($F$65:$T$65,C8),"-") -> -
C9: =C8+1 -> 4 | D9: =IFERROR(HLOOKUP(E9,$F$64:$T$66,3,FALSE),"-") -> - | E9: =IFERROR(SMALL($F$64:$T$64,C9),"-") -> - | G9: =C9 -> 4 | H9: =IFERROR(HLOOKUP(K9,$F$65:$T$66,2,FALSE),"-") -> - | K9: =IFERROR(SMALL($F$65:$T$65,C9),"-") -> -
C10: =C9+1 -> 5 | D10: =IFERROR(HLOOKUP(E10,$F$64:$T$66,3,FALSE),"-") -> - | E10: =IFERROR(SMALL($F$64:$T$64,C10),"-") -> - | G10: =C10 -> 5 | H10: =IFERROR(HLOOKUP(K10,$F$65:$T$66,2,FALSE),"-") -> - | K10: =IFERROR(SMALL($F$65:$T$65,C10),"-") -> -
C11: =C10+1 -> 6 | D11: =IFERROR(HLOOKUP(E11,$F$64:$T$66,3,FALSE),"-") -> - | E11: =IFERROR(SMALL($F$64:$T$64,C11),"-") -> - | G11: =C11 -> 6 | H11: =IFERROR(HLOOKUP(K11,$F$65:$T$66,2,FALSE),"-") -> - | K11: =IFERROR(SMALL($F$65:$T$65,C11),"-") -> -
C12: =C11+1 -> 7 | D12: =IFERROR(HLOOKUP(E12,$F$64:$T$66,3,FALSE),"-") -> - | E12: =IFERROR(SMALL($F$64:$T$64,C12),"-") -> - | G12: =C12 -> 7 | H12: =IFERROR(HLOOKUP(K12,$F$65:$T$66,2,FALSE),"-") -> - | K12: =IFERROR(SMALL($F$65:$T$65,C12),"-") -> -
C13: =C12+1 -> 8 | D13: =IFERROR(HLOOKUP(E13,$F$64:$T$66,3,FALSE),"-") -> - | E13: =IFERROR(SMALL($F$64:$T$64,C13),"-") -> - | G13: =C13 -> 8 | H13: =IFERROR(HLOOKUP(K13,$F$65:$T$66,2,FALSE),"-") -> - | K13: =IFERROR(SMALL($F$65:$T$65,C13),"-") -> -
C14: =C13+1 -> 9 | D14: =IFERROR(HLOOKUP(E14,$F$64:$T$66,3,FALSE),"-") -> - | E14: =IFERROR(SMALL($F$64:$T$64,C14),"-") -> - | G14: =C14 -> 9 | H14: =IFERROR(HLOOKUP(K14,$F$65:$T$66,2,FALSE),"-") -> - | K14: =IFERROR(SMALL($F$65:$T$65,C14),"-") -> -
C15: =C14+1 -> 10 | D15: =IFERROR(HLOOKUP(E15,$F$64:$T$66,3,FALSE),"-") -> - | E15: =IFERROR(SMALL($F$64:$T$64,C15),"-") -> - | G15: =C15 -> 10 | H15: =IFERROR(HLOOKUP(K15,$F$65:$T$66,2,FALSE),"-") -> - | K15: =IFERROR(SMALL($F$65:$T$65,C15),"-") -> -
C16: =C15+1 -> 11 | D16: =IFERROR(HLOOKUP(E16,$F$64:$T$66,3,FALSE),"-") -> - | E16: =IFERROR(SMALL($F$64:$T$64,C16),"-") -> - | G16: =C16 -> 11 | H16: =IFERROR(HLOOKUP(K16,$F$65:$T$66,2,FALSE),"-") -> - | K16: =IFERROR(SMALL($F$65:$T$65,C16),"-") -> -
C17: =C16+1 -> 12 | D17: =IFERROR(HLOOKUP(E17,$F$64:$T$66,3,FALSE),"-") -> - | E17: =IFERROR(SMALL($F$64:$T$64,C17),"-") -> - | G17: =C17 -> 12 | H17: =IFERROR(HLOOKUP(K17,$F$65:$T$66,2,FALSE),"-") -> - | K17: =IFERROR(SMALL($F$65:$T$65,C17),"-") -> -
C18: =C17+1 -> 13 | D18: =IFERROR(HLOOKUP(E18,$F$64:$T$66,3,FALSE),"-") -> - | E18: =IFERROR(SMALL($F$64:$T$64,C18),"-") -> - | G18: =C18 -> 13 | H18: =IFERROR(HLOOKUP(K18,$F$65:$T$66,2,FALSE),"-") -> - | K18: =IFERROR(SMALL($F$65:$T$65,C18),"-") -> -
... C20: =C19+1 -> 15 | D20: =IFERROR(HLOOKUP(E20,$F$64:$T$66,3,FALSE),"-") -> - | E20: =IFERROR(SMALL($F$64:$T$64,C20),"-") -> - | G20: =C20 -> 15 | H20: =IFERROR(HLOOKUP(K20,$F$65:$T$66,2,FALSE),"-") -> - | K20: =IFERROR(SMALL($F$65:$T$65,C20),"-") -> -
C23: № | D23: Показатель | E23: Ед. изм. | F23: NHL NTE 240 | G23: Estar ESDE240 (ГПБ К) | H23: SANY SET240S | I23: TZCO TZE240 | J23: БелАЗ 7531 (ГПФК) | K23: XCMG 240 | L23: БелАЗ 7531 (БТЛ) | U23: Комментарий
C24: 1 | D24: Грузоподъемность | E24: т | F24: =SUMIFS(Производительность!$E$23:$E$39,Производительность!$C$23:$C$39,F$23) -> 227.8 | G24: =SUMIFS(Производительность!$E$23:$E$39,Производительность!$C$23:$C$39,G$23) -> 211.392 | H24: =SUMIFS(Производительность!$E$23:$E$39,Производительность!$C$23:$C$39,H$23) -> 216.362 | I24: =SUMIFS(Производительность!$E$23:$E$39,Производительность!$C$23:$C$39,I$23) -> 222 | J24: =SUMIFS(Производительность!$E$23:$E$39,Производительность!$C$23:$C$39,J$23) -> 231 | K24: =SUMIFS(Производительность!$E$23:$E$39,Производительность!$C$23:$C$39,K$23) -> 211.392 | L24: =SUMIFS(Производительность!$E$23:$E$39,Производительность!$C$23:$C$39,L$23) -> 231 | M24: =SUMIFS(Производительность!$E$23:$E$39,Производительность!$C$23:$C$39,M$23) -> 0 | ... T24: =SUMIFS(Производительность!$E$23:$E$39,Производительность!$C$23:$C$39,T$23) -> 0
C25: =MAX(C$24:C24)+1 -> 2 | D25: Мощность двигателя | E25: л.с. | F25: =SUMIFS('ФОТ, МТР, макро'!$AC$4:$AC$20,'ФОТ, МТР, макро'!$W$4:$W$20,F$23) -> 2500 | G25: =SUMIFS('ФОТ, МТР, макро'!$AC$4:$AC$20,'ФОТ, МТР, макро'!$W$4:$W$20,G$23) -> 1864 | H25: =SUMIFS('ФОТ, МТР, макро'!$AC$4:$AC$20,'ФОТ, МТР, макро'!$W$4:$W$20,H$23) -> 2843 | I25: =SUMIFS('ФОТ, МТР, макро'!$AC$4:$AC$20,'ФОТ, МТР, макро'!$W$4:$W$20,I$23) -> 2500 | J25: =SUMIFS('ФОТ, МТР, макро'!$AC$4:$AC$20,'ФОТ, МТР, макро'!$W$4:$W$20,J$23) -> 2535 | K25: =SUMIFS('ФОТ, МТР, макро'!$AC$4:$AC$20,'ФОТ, МТР, макро'!$W$4:$W$20,K$23) -> 0 | L25: =SUMIFS('ФОТ, МТР, макро'!$AC$4:$AC$20,'ФОТ, МТР, макро'!$W$4:$W$20,L$23) -> 2535 | M25: =SUMIFS('ФОТ, МТР, макро'!$AC$4:$AC$20,'ФОТ, МТР, макро'!$W$4:$W$20,M$23) -> 0 | ... T25: =SUMIFS('ФОТ, МТР, макро'!$AC$4:$AC$20,'ФОТ, МТР, макро'!$W$4:$W$20,T$23) -> 0
C26: =MAX(C$24:C25)+1 -> 3 | D26: Срок эксплуатации | E26: лет | F26: =SUMIFS(Производительность!$Y$55:$Y$71,Производительность!$C$55:$C$71,F$23) -> 20 | G26: =SUMIFS(Производительность!$Y$55:$Y$71,Производительность!$C$55:$C$71,G$23) -> 10 | H26: =SUMIFS(Производительность!$Y$55:$Y$71,Производительность!$C$55:$C$71,H$23) -> 12 | I26: =SUMIFS(Производительность!$Y$55:$Y$71,Производительность!$C$55:$C$71,I$23) -> 8 | J26: =SUMIFS(Производительность!$Y$55:$Y$71,Производительность!$C$55:$C$71,J$23) -> 10 | K26: =SUMIFS(Производительность!$Y$55:$Y$71,Производительность!$C$55:$C$71,K$23) -> 0 | L26: =SUMIFS(Производительность!$Y$55:$Y$71,Производительность!$C$55:$C$71,L$23) -> 10 | M26: =SUMIFS(Производительность!$Y$55:$Y$71,Производительность!$C$55:$C$71,M$23) -> 0 | ... T26: =SUMIFS(Производительность!$Y$55:$Y$71,Производительность!$C$55:$C$71,T$23) -> 0
C27: =MAX(C$24:C26)+1 -> 4 | D27: КТГ (средний за эксплуатацию) | E27: коэфф. | F27: =SUMIFS(Производительность!$Z$55:$Z$71,Производительность!$C$55:$C$71,F$23) -> 0.92288816 | G27: =SUMIFS(Производительность!$Z$55:$Z$71,Производительность!$C$55:$C$71,G$23) -> 0.8573313 | H27: =SUMIFS(Производительность!$Z$55:$Z$71,Производительность!$C$55:$C$71,H$23) -> 0.88337931 | I27: =SUMIFS(Производительность!$Z$55:$Z$71,Производительность!$C$55:$C$71,I$23) -> 0.86279173 | J27: =SUMIFS(Производительность!$Z$55:$Z$71,Производительность!$C$55:$C$71,J$23) -> 0.87156467 | K27: =SUMIFS(Производительность!$Z$55:$Z$71,Производительность!$C$55:$C$71,K$23) -> #DIV/0! | L27: =SUMIFS(Производительность!$Z$55:$Z$71,Производительность!$C$55:$C$71,L$23) -> 0.88411536 | M27: =SUMIFS(Производительность!$Z$55:$Z$71,Производительность!$C$55:$C$71,M$23) -> #DIV/0! | ... T27: =SUMIFS(Производительность!$Z$55:$Z$71,Производительность!$C$55:$C$71,T$23) -> #DIV/0!
C28: =MAX(C$24:C27)+1 -> 5 | D28: КТГ (1-й год) | E28: =E27 -> коэфф. | F28: =SUMIFS(Производительность!$E$55:$E$71,Производительность!$C$55:$C$71,F$23) -> 0.93755029 | G28: =SUMIFS(Производительность!$E$55:$E$71,Производительность!$C$55:$C$71,G$23) -> 0.91162481 | H28: =SUMIFS(Производительность!$E$55:$E$71,Производительность!$C$55:$C$71,H$23) -> 0.9357084 | I28: =SUMIFS(Производительность!$E$55:$E$71,Производительность!$C$55:$C$71,I$23) -> 0.90962709 | J28: =SUMIFS(Производительность!$E$55:$E$71,Производительность!$C$55:$C$71,J$23) -> 0.90830416 | K28: =SUMIFS(Производительность!$E$55:$E$71,Производительность!$C$55:$C$71,K$23) -> 0 | L28: =SUMIFS(Производительность!$E$55:$E$71,Производительность!$C$55:$C$71,L$23) -> 0.92956037 | M28: =SUMIFS(Производительность!$E$55:$E$71,Производительность!$C$55:$C$71,M$23) -> 0 | ... T28: =SUMIFS(Производительность!$E$55:$E$71,Производительность!$C$55:$C$71,T$23) -> 0
C29: =MAX(C$24:C28)+1 -> 6 | D29: КИО (средний за эксплуатацию) | E29: =E27 -> коэфф. | F29: =SUMIFS(Производительность!$Z$119:$Z$135,Производительность!$C$119:$C$135,F$23) -> 0.79732431 | G29: =SUMIFS(Производительность!$Z$119:$Z$135,Производительность!$C$119:$C$135,G$23) -> 0.74004467 | H29: =SUMIFS(Производительность!$Z$119:$Z$135,Производительность!$C$119:$C$135,H$23) -> 0.76275508 | I29: =SUMIFS(Производительность!$Z$119:$Z$135,Производительность!$C$119:$C$135,I$23) -> 0.74446948 | J29: =SUMIFS(Производительность!$Z$119:$Z$135,Производительность!$C$119:$C$135,J$23) -> 0.75236066 | K29: =SUMIFS(Производительность!$Z$119:$Z$135,Производительность!$C$119:$C$135,K$23) -> #DIV/0! | L29: =SUMIFS(Производительность!$Z$119:$Z$135,Производительность!$C$119:$C$135,L$23) -> 0.7631828 | M29: =SUMIFS(Производительность!$Z$119:$Z$135,Производительность!$C$119:$C$135,M$23) -> #DIV/0! | ... T29: =SUMIFS(Производительность!$Z$119:$Z$135,Производительность!$C$119:$C$135,T$23) -> #DIV/0!
C30: =MAX(C$24:C29)+1 -> 7 | D30: Среднетехническая скорость (1-й год) | E30: км/час | F30: =SUMIFS(Производительность!$E$151:$E$167,Производительность!$C$151:$C$167,F$23) -> 22.46 | G30: =SUMIFS(Производительность!$E$151:$E$167,Производительность!$C$151:$C$167,G$23) -> 22.46 | H30: =SUMIFS(Производительность!$E$151:$E$167,Производительность!$C$151:$C$167,H$23) -> 22.46 | I30: =SUMIFS(Производительность!$E$151:$E$167,Производительность!$C$151:$C$167,I$23) -> 22.46 | J30: =SUMIFS(Производительность!$E$151:$E$167,Производительность!$C$151:$C$167,J$23) -> 22.46 | K30: =SUMIFS(Производительность!$E$151:$E$167,Производительность!$C$151:$C$167,K$23) -> 22.46 | L30: =SUMIFS(Производительность!$E$151:$E$167,Производительность!$C$151:$C$167,L$23) -> 22.46 | M30: =SUMIFS(Производительность!$E$151:$E$167,Производительность!$C$151:$C$167,M$23) -> 0 | ... T30: =SUMIFS(Производительность!$E$151:$E$167,Производительность!$C$151:$C$167,T$23) -> 0
C31: =MAX(C$24:C30)+1 -> 8 | D31: Производительность (средняя за эксплуатацию) | E31: тыс. т | F31: =SUMIFS(Производительность!$Z$247:$Z$263,Производительность!$C$247:$C$263,F$23) -> 2756.3657 | G31: =SUMIFS(Производительность!$Z$247:$Z$263,Производительность!$C$247:$C$263,G$23) -> 2598.1276 | H31: =SUMIFS(Производительность!$Z$247:$Z$263,Производительность!$C$247:$C$263,H$23) -> 2677.4963 | I31: =SUMIFS(Производительность!$Z$247:$Z$263,Производительность!$C$247:$C$263,I$23) -> 2832.1807 | J31: =SUMIFS(Производительность!$Z$247:$Z$263,Производительность!$C$247:$C$263,J$23) -> 2885.6027 | K31: =SUMIFS(Производительность!$Z$247:$Z$263,Производительность!$C$247:$C$263,K$23) -> #DIV/0! | L31: =SUMIFS(Производительность!$Z$247:$Z$263,Производительность!$C$247:$C$263,L$23) -> 2928.2687 | M31: =SUMIFS(Производительность!$Z$247:$Z$263,Производительность!$C$247:$C$263,M$23) -> #DIV/0! | ... T31: =SUMIFS(Производительность!$Z$247:$Z$263,Производительность!$C$247:$C$263,T$23) -> #DIV/0!
C32: =MAX(C$24:C31)+1 -> 9 | E32: тыс. ткм | F32: =SUMIFS(Производительность!$Z$263:$Z$279,Производительность!$C$263:$C$279,F$23) -> 13243.304 | G32: =SUMIFS(Производительность!$Z$263:$Z$279,Производительность!$C$263:$C$279,G$23) -> 11054.29 | H32: =SUMIFS(Производительность!$Z$263:$Z$279,Производительность!$C$263:$C$279,H$23) -> 11760.948 | I32: =SUMIFS(Производительность!$Z$263:$Z$279,Производительность!$C$263:$C$279,I$23) -> 11541.076 | J32: =SUMIFS(Производительность!$Z$263:$Z$279,Производительность!$C$263:$C$279,J$23) -> 12281.888 | K32: =SUMIFS(Производительность!$Z$263:$Z$279,Производительность!$C$263:$C$279,K$23) -> #DIV/0! | L32: =SUMIFS(Производительность!$Z$263:$Z$279,Производительность!$C$263:$C$279,L$23) -> 12456.732 | M32: =SUMIFS(Производительность!$Z$263:$Z$279,Производительность!$C$263:$C$279,M$23) -> #DIV/0! | ... T32: =SUMIFS(Производительность!$Z$263:$Z$279,Производительность!$C$263:$C$279,T$23) -> #DIV/0!
C33: =MAX(C$24:C32)+1 -> 10 | D33: Производительность (1-й год) | E33: =E31 -> тыс. т | F33: =SUMIFS(Производительность!$E$247:$E$263,Производительность!$C$247:$C$263,F$23) -> 3844.3302 | G33: =SUMIFS(Производительность!$E$247:$E$263,Производительность!$C$247:$C$263,G$23) -> 3468.7825 | H33: =SUMIFS(Производительность!$E$247:$E$263,Производительность!$C$247:$C$263,H$23) -> 3644.1304 | I33: =SUMIFS(Производительность!$E$247:$E$263,Производительность!$C$247:$C$263,I$23) -> 3634.8689 | J33: =SUMIFS(Производительность!$E$247:$E$263,Производительность!$C$247:$C$263,J$23) -> 3776.7277 | K33: =SUMIFS(Производительность!$E$247:$E$263,Производительность!$C$247:$C$263,K$23) -> 0 | L33: =SUMIFS(Производительность!$E$247:$E$263,Производительность!$C$247:$C$263,L$23) -> 3865.111 | M33: =SUMIFS(Производительность!$E$247:$E$263,Производительность!$C$247:$C$263,M$23) -> 0 | ... T33: =SUMIFS(Производительность!$E$247:$E$263,Производительность!$C$247:$C$263,T$23) -> 0
C34: =MAX(C$24:C33)+1 -> 11 | E34: =E32 -> тыс. ткм | F34: =SUMIFS(Производительность!$E$263:$E$279,Производительность!$C$263:$C$279,F$23) -> 11685.165 | G34: =SUMIFS(Производительность!$E$263:$E$279,Производительность!$C$263:$C$279,G$23) -> 10543.656 | H34: =SUMIFS(Производительность!$E$263:$E$279,Производительность!$C$263:$C$279,H$23) -> 11076.641 | I34: =SUMIFS(Производительность!$E$263:$E$279,Производительность!$C$263:$C$279,I$23) -> 11048.49 | J34: =SUMIFS(Производительность!$E$263:$E$279,Производительность!$C$263:$C$279,J$23) -> 11479.681 | K34: =SUMIFS(Производительность!$E$263:$E$279,Производительность!$C$263:$C$279,K$23) -> 0 | L34: =SUMIFS(Производительность!$E$263:$E$279,Производительность!$C$263:$C$279,L$23) -> 11748.33 | M34: =SUMIFS(Производительность!$E$263:$E$279,Производительность!$C$263:$C$279,M$23) -> 0 | ... T34: =SUMIFS(Производительность!$E$263:$E$279,Производительность!$C$263:$C$279,T$23) -> 0
C36: =MAX(C$24:C35)+1 -> 12 | D36: Габариты:
A37: заполнить | C37: =MAX(C$24:C36)+1 -> 13 | D37: эксплуатационная ширина | E37: мм | F37: ='NHL NTE240'!D6 -> 8500 | G37: =ESDE240!D6 -> 9104 | H37: =SANY!D6 -> 8970 | I37: =TZCO!D6 -> 7822 | J37: =БелАЗ!E6 -> 8800 | L37: =БелАЗ_Б!E6 -> 8400
A38: заполнить | C38: =MAX(C$24:C37)+1 -> 14 | D38: высота по переднему козырьку | E38: =E37 -> мм | F38: ='NHL NTE240'!D7 -> 7300 | G38: =ESDE240!D7 -> 7205 | H38: =SANY!D7 -> 7050 | I38: =TZCO!D7 -> 7427 | J38: =БелАЗ!E7 -> 6720 | L38: =БелАЗ_Б!E7 -> 6720
A39: заполнить | C39: =MAX(C$24:C38)+1 -> 15 | D39: габаритная длина | E39: =E38 -> мм | F39: ='NHL NTE240'!D8 -> 15600 | G39: =ESDE240!D8 -> 14595 | H39: =SANY!D8 -> 14900 | I39: =TZCO!D8 -> 14380 | J39: =БелАЗ!E8 -> 13390 | L39: =БелАЗ_Б!E8 -> 13390
C41: =MAX(C$24:C40)+1 -> 16 | D41: Стоимость самосвала | E41: тыс. руб. | F41: =F44+F45+F46 -> 0 | G41: =G44+G45+G46 -> 0 | H41: =H44+H45+H46 -> 0 | I41: =I44+I45+I46 -> 0 | J41: =J44+J45+J46 -> 0 | K41: =K44+K45+K46 -> 0 | L41: =L44+L45+L46 -> 0 | M41: =M44+M45+M46 -> 0 | ... T41: =T44+T45+T46 -> 0 | W41: курс ЦБ на хх.07.2026
A42: заполнить | C42: =MAX(C$24:C41)+1 -> 17 | D42: Цена в долларах | E42: тыс. долл. | W42: 94.0485
A43: заполнить | C43: =MAX(C$24:C42)+1 -> 18 | D43: Цена в юанях | E43: тыс. юаней | W43: 12.7702
A44: заполнить | C44: =MAX(C$24:C43)+1 -> 19 | D44: Цена в рублях | E44: =E41 -> тыс. руб.
A45: заполнить | C45: =MAX(C$24:C44)+1 -> 20 | D45: Шины | E45: =E41 -> тыс. руб.
A46: заполнить | C46: =MAX(C$24:C45)+1 -> 21 | D46: Сборка | E46: =E41 -> тыс. руб.
A48: заполнить | C48: =MAX(C$24:C47)+1 -> 22 | D48: Потребность | E48: ед.
C49: =MAX(C$24:C48)+1 -> 23 | D49: CAPEX на потребность | E49: =E41 -> тыс. руб. | F49: =F48*F41 -> 0 | G49: =G48*G41 -> 0 | H49: =H48*H41 -> 0 | I49: =I48*I41 -> 0 | J49: =J48*J41 -> 0 | K49: =K48*K41 -> 0 | L49: =L48*L41 -> 0 | M49: =M48*M41 -> 0 | ... T49: =T48*T41 -> 0
C51: =MAX(C$24:C50)+1 -> 24 | D51: Среднегодовые затраты на ТО (включая смазочные) и ремонты | E51: тыс. руб. | F51: =SUMIFS(ТСО!$AB:$AB,ТСО!$A:$A,F$23) -> 37724.114 | G51: =SUMIFS(ТСО!$AB:$AB,ТСО!$A:$A,G$23) -> 81241.348 | H51: =SUMIFS(ТСО!$AB:$AB,ТСО!$A:$A,H$23) -> 43797.999 | I51: =SUMIFS(ТСО!$AB:$AB,ТСО!$A:$A,I$23) -> 80874.293 | J51: =SUMIFS(ТСО!$AB:$AB,ТСО!$A:$A,J$23) -> 49901.322 | K51: =SUMIFS(ТСО!$AB:$AB,ТСО!$A:$A,K$23) -> #DIV/0! | L51: =SUMIFS(ТСО!$AB:$AB,ТСО!$A:$A,L$23) -> 49883.615 | M51: =SUMIFS(ТСО!$AB:$AB,ТСО!$A:$A,M$23) -> 0 | ... T51: =SUMIFS(ТСО!$AB:$AB,ТСО!$A:$A,T$23) -> 0
A53: =ТСО!D74 -> Аннуитет операционный | C53: =MAX(C$24:C52)+1 -> 25 | D53: =ТСО!D74 -> Аннуитет операционный | E53: =ТСО!E74 -> руб/ткм | F53: =SUMIFS(ТСО!$AC:$AC,ТСО!$A:$A,F$23,ТСО!$B:$B,$A53) -> 8.7358346 | G53: =SUMIFS(ТСО!$AC:$AC,ТСО!$A:$A,G$23,ТСО!$B:$B,$A53) -> 12.629211 | H53: =SUMIFS(ТСО!$AC:$AC,ТСО!$A:$A,H$23,ТСО!$B:$B,$A53) -> 9.8330454 | I53: =SUMIFS(ТСО!$AC:$AC,ТСО!$A:$A,I$23,ТСО!$B:$B,$A53) -> 12.058796 | J53: =SUMIFS(ТСО!$AC:$AC,ТСО!$A:$A,J$23,ТСО!$B:$B,$A53) -> 9.6354781 | K53: =SUMIFS(ТСО!$AC:$AC,ТСО!$A:$A,K$23,ТСО!$B:$B,$A53) -> #DIV/0! | L53: =SUMIFS(ТСО!$AC:$AC,ТСО!$A:$A,L$23,ТСО!$B:$B,$A53) -> 9.5582597 | M53: =SUMIFS(ТСО!$AC:$AC,ТСО!$A:$A,M$23,ТСО!$B:$B,$A53) -> 0 | ... T53: =SUMIFS(ТСО!$AC:$AC,ТСО!$A:$A,T$23,ТСО!$B:$B,$A53) -> 0
A54: =ТСО!D75 -> ТО, ТР, ППР | C54: =MAX(C$24:C53)+1 -> 26 | D54: =ТСО!D75 -> ТО, ТР, ППР | E54: =ТСО!E75 -> руб/ткм | F54: =SUMIFS(ТСО!$AC:$AC,ТСО!$A:$A,F$23,ТСО!$B:$B,$A54) -> 2.4987646 | G54: =SUMIFS(ТСО!$AC:$AC,ТСО!$A:$A,G$23,ТСО!$B:$B,$A54) -> 7.1230851 | H54: =SUMIFS(ТСО!$AC:$AC,ТСО!$A:$A,H$23,ТСО!$B:$B,$A54) -> 3.5672806 | I54: =SUMIFS(ТСО!$AC:$AC,ТСО!$A:$A,I$23,ТСО!$B:$B,$A54) -> 6.8703769 | J54: =SUMIFS(ТСО!$AC:$AC,ТСО!$A:$A,J$23,ТСО!$B:$B,$A54) -> 3.8042479 | K54: =SUMIFS(ТСО!$AC:$AC,ТСО!$A:$A,K$23,ТСО!$B:$B,$A54) -> #DIV/0! | L54: =SUMIFS(ТСО!$AC:$AC,ТСО!$A:$A,L$23,ТСО!$B:$B,$A54) -> 3.6979755 | M54: =SUMIFS(ТСО!$AC:$AC,ТСО!$A:$A,M$23,ТСО!$B:$B,$A54) -> 0 | ... T54: =SUMIFS(ТСО!$AC:$AC,ТСО!$A:$A,T$23,ТСО!$B:$B,$A54) -> 0
A55: =ТСО!D76 -> Шины | C55: =MAX(C$24:C54)+1 -> 27 | D55: =ТСО!D76 -> Шины | E55: =ТСО!E76 -> руб/ткм | F55: =SUMIFS(ТСО!$AC:$AC,ТСО!$A:$A,F$23,ТСО!$B:$B,$A55) -> 1.9474572 | G55: =SUMIFS(ТСО!$AC:$AC,ТСО!$A:$A,G$23,ТСО!$B:$B,$A55) -> 2.1361623 | H55: =SUMIFS(ТСО!$AC:$AC,ТСО!$A:$A,H$23,ТСО!$B:$B,$A55) -> 2.0794733 | I55: =SUMIFS(ТСО!$AC:$AC,ТСО!$A:$A,I$23,ТСО!$B:$B,$A55) -> 1.7074967 | J55: =SUMIFS(ТСО!$AC:$AC,ТСО!$A:$A,J$23,ТСО!$B:$B,$A55) -> 1.6378791 | K55: =SUMIFS(ТСО!$AC:$AC,ТСО!$A:$A,K$23,ТСО!$B:$B,$A55) -> #DIV/0! | L55: =SUMIFS(ТСО!$AC:$AC,ТСО!$A:$A,L$23,ТСО!$B:$B,$A55) -> 1.6461339 | M55: =SUMIFS(ТСО!$AC:$AC,ТСО!$A:$A,M$23,ТСО!$B:$B,$A55) -> 0 | ... T55: =SUMIFS(ТСО!$AC:$AC,ТСО!$A:$A,T$23,ТСО!$B:$B,$A55) -> 0
A56: =ТСО!D77 -> Топливо | C56: =MAX(C$24:C55)+1 -> 28 | D56: =ТСО!D77 -> Топливо | E56: =ТСО!E77 -> руб/ткм | F56: =SUMIFS(ТСО!$AC:$AC,ТСО!$A:$A,F$23,ТСО!$B:$B,$A56) -> 5.7904221 | G56: =SUMIFS(ТСО!$AC:$AC,ТСО!$A:$A,G$23,ТСО!$B:$B,$A56) -> 5.8940167 | H56: =SUMIFS(ТСО!$AC:$AC,ТСО!$A:$A,H$23,ТСО!$B:$B,$A56) -> 5.8724985 | I56: =SUMIFS(ТСО!$AC:$AC,ТСО!$A:$A,I$23,ТСО!$B:$B,$A56) -> 5.8812531 | J56: =SUMIFS(ТСО!$AC:$AC,ТСО!$A:$A,J$23,ТСО!$B:$B,$A56) -> 5.8833368 | K56: =SUMIFS(ТСО!$AC:$AC,ТСО!$A:$A,K$23,ТСО!$B:$B,$A56) -> #DIV/0! | L56: =SUMIFS(ТСО!$AC:$AC,ТСО!$A:$A,L$23,ТСО!$B:$B,$A56) -> 5.8997573 | M56: =SUMIFS(ТСО!$AC:$AC,ТСО!$A:$A,M$23,ТСО!$B:$B,$A56) -> 0 | ... T56: =SUMIFS(ТСО!$AC:$AC,ТСО!$A:$A,T$23,ТСО!$B:$B,$A56) -> 0
A57: =ТСО!D78 -> Смазочные | C57: =MAX(C$24:C56)+1 -> 29 | D57: =ТСО!D78 -> Смазочные | E57: =ТСО!E78 -> руб/ткм | F57: =SUMIFS(ТСО!$AC:$AC,ТСО!$A:$A,F$23,ТСО!$B:$B,$A57) -> 0 | G57: =SUMIFS(ТСО!$AC:$AC,ТСО!$A:$A,G$23,ТСО!$B:$B,$A57) -> 0 | H57: =SUMIFS(ТСО!$AC:$AC,ТСО!$A:$A,H$23,ТСО!$B:$B,$A57) -> 0 | I57: =SUMIFS(ТСО!$AC:$AC,ТСО!$A:$A,I$23,ТСО!$B:$B,$A57) -> 0 | J57: =SUMIFS(ТСО!$AC:$AC,ТСО!$A:$A,J$23,ТСО!$B:$B,$A57) -> 0 | K57: =SUMIFS(ТСО!$AC:$AC,ТСО!$A:$A,K$23,ТСО!$B:$B,$A57) -> #DIV/0! | L57: =SUMIFS(ТСО!$AC:$AC,ТСО!$A:$A,L$23,ТСО!$B:$B,$A57) -> 0 | M57: =SUMIFS(ТСО!$AC:$AC,ТСО!$A:$A,M$23,ТСО!$B:$B,$A57) -> 0 | ... T57: =SUMIFS(ТСО!$AC:$AC,ТСО!$A:$A,T$23,ТСО!$B:$B,$A57) -> 0
A58: =ТСО!D79 -> Затраты на персонал | C58: =MAX(C$24:C57)+1 -> 30 | D58: =ТСО!D79 -> Затраты на персонал | E58: =ТСО!E79 -> руб/ткм | F58: =SUMIFS(ТСО!$AC:$AC,ТСО!$A:$A,F$23,ТСО!$B:$B,$A58) -> 1.3950897 | G58: =SUMIFS(ТСО!$AC:$AC,ТСО!$A:$A,G$23,ТСО!$B:$B,$A58) -> 1.6713507 | H58: =SUMIFS(ТСО!$AC:$AC,ТСО!$A:$A,H$23,ТСО!$B:$B,$A58) -> 1.5709275 | I58: =SUMIFS(ТСО!$AC:$AC,ТСО!$A:$A,I$23,ТСО!$B:$B,$A58) -> 1.6008556 | J58: =SUMIFS(ТСО!$AC:$AC,ТСО!$A:$A,J$23,ТСО!$B:$B,$A58) -> 1.5042961 | K58: =SUMIFS(ТСО!$AC:$AC,ТСО!$A:$A,K$23,ТСО!$B:$B,$A58) -> #DIV/0! | L58: =SUMIFS(ТСО!$AC:$AC,ТСО!$A:$A,L$23,ТСО!$B:$B,$A58) -> 1.4831817 | M58: =SUMIFS(ТСО!$AC:$AC,ТСО!$A:$A,M$23,ТСО!$B:$B,$A58) -> 0 | ... T58: =SUMIFS(ТСО!$AC:$AC,ТСО!$A:$A,T$23,ТСО!$B:$B,$A58) -> 0
A59: =ТСО!D80 -> Транспортный налог | C59: =MAX(C$24:C58)+1 -> 31 | D59: =ТСО!D80 -> Транспортный налог | E59: =ТСО!E80 -> руб/ткм | F59: =SUMIFS(ТСО!$AC:$AC,ТСО!$A:$A,F$23,ТСО!$B:$B,$A59) -> 0.016045845 | G59: =SUMIFS(ТСО!$AC:$AC,ТСО!$A:$A,G$23,ТСО!$B:$B,$A59) -> 0.014332896 | H59: =SUMIFS(ТСО!$AC:$AC,ТСО!$A:$A,H$23,ТСО!$B:$B,$A59) -> 0.020547239 | I59: =SUMIFS(ТСО!$AC:$AC,ТСО!$A:$A,I$23,ТСО!$B:$B,$A59) -> 0.018412494 | J59: =SUMIFS(ТСО!$AC:$AC,ТСО!$A:$A,J$23,ТСО!$B:$B,$A59) -> 0.017544127 | K59: =SUMIFS(ТСО!$AC:$AC,ТСО!$A:$A,K$23,ТСО!$B:$B,$A59) -> #DIV/0! | L59: =SUMIFS(ТСО!$AC:$AC,ТСО!$A:$A,L$23,ТСО!$B:$B,$A59) -> 0.017297876 | M59: =SUMIFS(ТСО!$AC:$AC,ТСО!$A:$A,M$23,ТСО!$B:$B,$A59) -> 0 | ... T59: =SUMIFS(ТСО!$AC:$AC,ТСО!$A:$A,T$23,ТСО!$B:$B,$A59) -> 0
A60: =ТСО!D81 -> Налог на прибыль | C60: =MAX(C$24:C59)+1 -> 32 | D60: =ТСО!D81 -> Налог на прибыль | E60: =ТСО!E81 -> руб/ткм | F60: =SUMIFS(ТСО!$AC:$AC,ТСО!$A:$A,F$23,ТСО!$B:$B,$A60) -> -2.9119449 | G60: =SUMIFS(ТСО!$AC:$AC,ТСО!$A:$A,G$23,ТСО!$B:$B,$A60) -> -4.2097369 | H60: =SUMIFS(ТСО!$AC:$AC,ТСО!$A:$A,H$23,ТСО!$B:$B,$A60) -> -3.2776818 | I60: =SUMIFS(ТСО!$AC:$AC,ТСО!$A:$A,I$23,ТСО!$B:$B,$A60) -> -4.0195987 | J60: =SUMIFS(ТСО!$AC:$AC,ТСО!$A:$A,J$23,ТСО!$B:$B,$A60) -> -3.211826 | K60: =SUMIFS(ТСО!$AC:$AC,ТСО!$A:$A,K$23,ТСО!$B:$B,$A60) -> #DIV/0! | L60: =SUMIFS(ТСО!$AC:$AC,ТСО!$A:$A,L$23,ТСО!$B:$B,$A60) -> -3.1860866 | M60: =SUMIFS(ТСО!$AC:$AC,ТСО!$A:$A,M$23,ТСО!$B:$B,$A60) -> 0 | ... T60: =SUMIFS(ТСО!$AC:$AC,ТСО!$A:$A,T$23,ТСО!$B:$B,$A60) -> 0
A61: =ТСО!D82 -> Аннуитет инвестиционный | C61: =MAX(C$24:C60)+1 -> 33 | D61: =ТСО!D82 -> Аннуитет инвестиционный | E61: =ТСО!E82 -> руб/ткм | F61: =SUMIFS(ТСО!$AC:$AC,ТСО!$A:$A,F$23,ТСО!$B:$B,$A61) -> 0 | G61: =SUMIFS(ТСО!$AC:$AC,ТСО!$A:$A,G$23,ТСО!$B:$B,$A61) -> 0 | H61: =SUMIFS(ТСО!$AC:$AC,ТСО!$A:$A,H$23,ТСО!$B:$B,$A61) -> 0 | I61: =SUMIFS(ТСО!$AC:$AC,ТСО!$A:$A,I$23,ТСО!$B:$B,$A61) -> 0 | J61: =SUMIFS(ТСО!$AC:$AC,ТСО!$A:$A,J$23,ТСО!$B:$B,$A61) -> 0 | K61: =SUMIFS(ТСО!$AC:$AC,ТСО!$A:$A,K$23,ТСО!$B:$B,$A61) -> #DIV/0! | L61: =SUMIFS(ТСО!$AC:$AC,ТСО!$A:$A,L$23,ТСО!$B:$B,$A61) -> 0 | M61: =SUMIFS(ТСО!$AC:$AC,ТСО!$A:$A,M$23,ТСО!$B:$B,$A61) -> 0 | ... T61: =SUMIFS(ТСО!$AC:$AC,ТСО!$A:$A,T$23,ТСО!$B:$B,$A61) -> 0
A62: =ТСО!D84 -> Аннуитет общий | C62: =MAX(C$24:C61)+1 -> 34 | D62: =ТСО!D84 -> Аннуитет общий | E62: =ТСО!E84 -> руб/ткм | F62: =SUMIFS(ТСО!$AC:$AC,ТСО!$A:$A,F$23,ТСО!$B:$B,$A62) -> 8.7358346 | G62: =SUMIFS(ТСО!$AC:$AC,ТСО!$A:$A,G$23,ТСО!$B:$B,$A62) -> 12.629211 | H62: =SUMIFS(ТСО!$AC:$AC,ТСО!$A:$A,H$23,ТСО!$B:$B,$A62) -> 9.8330454 | I62: =SUMIFS(ТСО!$AC:$AC,ТСО!$A:$A,I$23,ТСО!$B:$B,$A62) -> 12.058796 | J62: =SUMIFS(ТСО!$AC:$AC,ТСО!$A:$A,J$23,ТСО!$B:$B,$A62) -> 9.6354781 | K62: =SUMIFS(ТСО!$AC:$AC,ТСО!$A:$A,K$23,ТСО!$B:$B,$A62) -> #DIV/0! | L62: =SUMIFS(ТСО!$AC:$AC,ТСО!$A:$A,L$23,ТСО!$B:$B,$A62) -> 9.5582597 | M62: =SUMIFS(ТСО!$AC:$AC,ТСО!$A:$A,M$23,ТСО!$B:$B,$A62) -> 0 | ... T62: =SUMIFS(ТСО!$AC:$AC,ТСО!$A:$A,T$23,ТСО!$B:$B,$A62) -> 0
F63: =F53-SUM(F54:F60)+F62-F53-F61 -> 0 | G63: =G53-SUM(G54:G60)+G62-G53-G61 -> -1.7763568e-15 | H63: =H53-SUM(H54:H60)+H62-H53-H61 -> 0 | I63: =I53-SUM(I54:I60)+I62-I53-I61 -> 0 | J63: =J53-SUM(J54:J60)+J62-J53-J61 -> 3.5527137e-15 | K63: =K53-SUM(K54:K60)+K62-K53-K61 -> #DIV/0! | L63: =L53-SUM(L54:L60)+L62-L53-L61 -> 0 | M63: =M53-SUM(M54:M60)+M62-M53-M61 -> 0 | ... T63: =T53-SUM(T54:T60)+T62-T53-T61 -> 0
A64: для ранжирования | D64: =D62 -> Аннуитет общий | F64: =IF(F62>0,F62,"нет") -> 8.7358346 | G64: =IF(G62>0,G62,"нет") -> 12.629211 | H64: =IF(H62>0,H62,"нет") -> 9.8330454 | I64: =IF(I62>0,I62,"нет") -> 12.058796 | J64: =IF(J62>0,J62,"нет") -> 9.6354781 | K64: =IF(K62>0,K62,"нет") -> #DIV/0! | L64: =IF(L62>0,L62,"нет") -> 9.5582597 | M64: =IF(M62>0,M62,"нет") -> нет | ... T64: =IF(T62>0,T62,"нет") -> нет
A65: =A64 -> для ранжирования | D65: =D41 -> Стоимость самосвала | F65: =IF(F41>0,F41,"нет") -> нет | G65: =IF(G41>0,G41,"нет") -> нет | H65: =IF(H41>0,H41,"нет") -> нет | I65: =IF(I41>0,I41,"нет") -> нет | J65: =IF(J41>0,J41,"нет") -> нет | K65: =IF(K41>0,K41,"нет") -> нет | L65: =IF(L41>0,L41,"нет") -> нет | M65: =IF(M41>0,M41,"нет") -> нет | ... T65: =IF(T41>0,T41,"нет") -> нет
A66: =A64 -> для ранжирования | F66: =F23 -> NHL NTE 240 | G66: =G23 -> Estar ESDE240 (ГПБ К) | H66: =H23 -> SANY SET240S | I66: =I23 -> TZCO TZE240 | J66: =J23 -> БелАЗ 7531 (ГПФК) | K66: =K23 -> XCMG 240 | L66: =L23 -> БелАЗ 7531 (БТЛ) | M66: =M23 -> 0 | ... T66: =T23 -> 0
C69: Предыдущий тендер
D70: Аннуитет операционный | F70: 7.4355452 | G70: 14.061966 | J70: 7.6836603
D71: ТО, ремонты | F71: 3.1288699 | G71: 10.34358 | J71: 3.1206405
D72: сервис | F72: 0.090441354 | G72: 1.6932672 | J72: 0.35974292
D73: Шины | F73: 2.0014636 | G73: 2.0614105 | J73: 1.8237817
D74: Топливо | F74: 4.0757207 | G74: 3.5702157 | J74: 4.2845525
D75: Смазочные | F75: 0 | G75: 0 | J75: 0
D76: Расходы на персонал | F76: 0.76534042 | G76: 0.80074501 | J76: 0.75405566
D77: Транспортный налог | F77: 0.0028867681 | G77: 0.0030203097 | J77: 0.0028840222
D78: Налог на прибыль | F78: -2.6291776 | G78: -4.4102727 | J78: -2.6619969
D79: Аннуитет инвестиционный | F79: 4.7472171 | G79: 5.5144335 | J79: 4.5672028
D80: Аннуитет общий | F80: 12.182762 | G80: 19.5764 | J80: 12.250863
D83: =D53 -> Аннуитет операционный | F83: =F53-F70 -> 1.3002894 | G83: =G53-G70 -> -1.4327556 | J83: =J53-J70 -> 1.9518178 | K83: =K53-K70 -> #DIV/0! | L83: =L53-L70 -> 9.5582597
D84: =D54 -> ТО, ТР, ППР | F84: =F54-F71-F72 -> -0.72054664 | G84: =G54-G71-G72 -> -4.9137624 | J84: =J54-J71-J72 -> 0.32386457 | K84: =K54-K71-K72 -> #DIV/0! | L84: =L54-L71-L72 -> 3.6979755
D85: =D55 -> Шины | F85: =F55-F73 -> -0.054006406 | G85: =G55-G73 -> 0.074751784 | J85: =J55-J73 -> -0.18590258 | K85: =K55-K73 -> #DIV/0! | L85: =L55-L73 -> 1.6461339
D86: =D56 -> Топливо | F86: =F56-F74 -> 1.7147014 | G86: =G56-G74 -> 2.323801 | J86: =J56-J74 -> 1.5987843 | K86: =K56-K74 -> #DIV/0! | L86: =L56-L74 -> 5.8997573
D87: =D57 -> Смазочные | F87: =F57-F75 -> 0 | G87: =G57-G75 -> 0 | J87: =J57-J75 -> 0 | K87: =K57-K75 -> #DIV/0! | L87: =L57-L75 -> 0
D88: =D58 -> Затраты на персонал | F88: =F58-F76 -> 0.62974924 | G88: =G58-G76 -> 0.8706057 | J88: =J58-J76 -> 0.75024045 | K88: =K58-K76 -> #DIV/0! | L88: =L58-L76 -> 1.4831817
D89: =D59 -> Транспортный налог | F89: =F59-F77 -> 0.013159077 | G89: =G59-G77 -> 0.011312587 | J89: =J59-J77 -> 0.014660105 | K89: =K59-K77 -> #DIV/0! | L89: =L59-L77 -> 0.017297876
D90: =D60 -> Налог на прибыль | F90: =F60-F78 -> -0.28276729 | G90: =G60-G78 -> 0.20053575 | J90: =J60-J78 -> -0.54982907 | K90: =K60-K78 -> #DIV/0! | L90: =L60-L78 -> -3.1860866
D91: =D61 -> Аннуитет инвестиционный | F91: =F61-F79 -> -4.7472171 | G91: =G61-G79 -> -5.5144335 | J91: =J61-J79 -> -4.5672028 | K91: =K61-K79 -> #DIV/0! | L91: =L61-L79 -> 0
D92: =D62 -> Аннуитет общий | F92: =F62-F80 -> -3.4469277 | G92: =G62-G80 -> -6.947189 | J92: =J62-J80 -> -2.6153851 | K92: =K62-K80 -> #DIV/0! | L92: =L62-L80 -> 9.5582597

Sheet ТСО
A1: не удалять | B1: не удалять | C1: не удалять | D1: Показатель | E1: Ед. изм. | F1: =G1-1 -> 0 | G1: 1 | H1: =G1+1 -> 2 | I1: =H1+1 -> 3 | J1: =I1+1 -> 4 | K1: =J1+1 -> 5 | L1: =K1+1 -> 6 | M1: =L1+1 -> 7 | N1: =M1+1 -> 8 | O1: =N1+1 -> 9 | ... Z1: =Y1+1 -> 20 | AA1: не удалять | AB1: не удалять | AC1: не удалять
A2: * | F2: лет | G2: 2027 | H2: =G2+1 -> 2028 | I2: =H2+1 -> 2029 | J2: =I2+1 -> 2030 | K2: =J2+1 -> 2031 | L2: =K2+1 -> 2032 | M2: =L2+1 -> 2033 | N2: =M2+1 -> 2034 | O2: =N2+1 -> 2035 | ... Z2: =Y2+1 -> 2046 | AA2: проверки | AB2: средние на ТО, ТР, ППР | AC2: аннуитет
A3: * | D3: Расчет аннуитета
A4: *
A5: * | C5: =SUM(F55:Z55,F67:Z67,F86:Z86,AA39) -> -8.8817842e-16 | D5: =Свод!F23 -> NHL NTE 240 | E5: =SUMIFS(Производительность!$Y$55:$Y$71,Производительность!$C$55:$C$71,$D5) -> 20 | F5: =$F$2 -> лет
A6: *
A7: =D5 -> NHL NTE 240 | D7: =D$1 -> Показатель | E7: =E$1 -> Ед. изм. | F7: =F$1 -> 0 | G7: =G$1 -> 1 | H7: =H$1 -> 2 | I7: =I$1 -> 3 | J7: =J$1 -> 4 | K7: =K$1 -> 5 | ... Z7: =Z$1 -> 20
A8: =A7 -> NHL NTE 240 | D8: КТГ | E8: % | G8: =SUMIFS(Производительность!E$55:E$71,Производительность!$C$55:$C$71,$A8) -> 0.93755029 | H8: =SUMIFS(Производительность!F$55:F$71,Производительность!$C$55:$C$71,$A8) -> 0.93038071 | I8: =SUMIFS(Производительность!G$55:G$71,Производительность!$C$55:$C$71,$A8) -> 0.92090265 | J8: =SUMIFS(Производительность!H$55:H$71,Производительность!$C$55:$C$71,$A8) -> 0.90840582 | K8: =SUMIFS(Производительность!I$55:I$71,Производительность!$C$55:$C$71,$A8) -> 0.93333289 | L8: =SUMIFS(Производительность!J$55:J$71,Производительность!$C$55:$C$71,$A8) -> 0.92172393 | M8: =SUMIFS(Производительность!K$55:K$71,Производительность!$C$55:$C$71,$A8) -> 0.93126858 | N8: =SUMIFS(Производительность!L$55:L$71,Производительность!$C$55:$C$71,$A8) -> 0.91113604 | ... Z8: =SUMIFS(Производительность!X$55:X$71,Производительность!$C$55:$C$71,$A8) -> 0.92201249
A9: =A8 -> NHL NTE 240 | D9: КИО | E9: =E8 -> % | G9: =SUMIFS(Производительность!E$119:E$135,Производительность!$C$119:$C$135,$A9) -> 0.80423564 | H9: =SUMIFS(Производительность!F$119:F$135,Производительность!$C$119:$C$135,$A9) -> 0.79808553 | I9: =SUMIFS(Производительность!G$119:G$135,Производительность!$C$119:$C$135,$A9) -> 0.79624552 | J9: =SUMIFS(Производительность!H$119:H$135,Производительность!$C$119:$C$135,$A9) -> 0.78544031 | K9: =SUMIFS(Производительность!I$119:I$135,Производительность!$C$119:$C$135,$A9) -> 0.80699315 | L9: =SUMIFS(Производительность!J$119:J$135,Производительность!$C$119:$C$135,$A9) -> 0.79695563 | M9: =SUMIFS(Производительность!K$119:K$135,Производительность!$C$119:$C$135,$A9) -> 0.80520828 | N9: =SUMIFS(Производительность!L$119:L$135,Производительность!$C$119:$C$135,$A9) -> 0.78780095 | ... Z9: =SUMIFS(Производительность!X$119:X$135,Производительность!$C$119:$C$135,$A9) -> 0.79720513
A10: =A9 -> NHL NTE 240 | D10: Производительность: масса | E10: тыс. т | G10: =SUMIFS(Производительность!E$247:E$263,Производительность!$C$247:$C$263,$A10) -> 3844.3302 | H10: =SUMIFS(Производительность!F$247:F$263,Производительность!$C$247:$C$263,$A10) -> 3560.0083 | I10: =SUMIFS(Производительность!G$247:G$263,Производительность!$C$247:$C$263,$A10) -> 3123.9324 | J10: =SUMIFS(Производительность!H$247:H$263,Производительность!$C$247:$C$263,$A10) -> 3160.7422 | K10: =SUMIFS(Производительность!I$247:I$263,Производительность!$C$247:$C$263,$A10) -> 2793.918 | L10: =SUMIFS(Производительность!J$247:J$263,Производительность!$C$247:$C$263,$A10) -> 2535.7903 | M10: =SUMIFS(Производительность!K$247:K$263,Производительность!$C$247:$C$263,$A10) -> 2962.7003 | N10: =SUMIFS(Производительность!L$247:L$263,Производительность!$C$247:$C$263,$A10) -> 2847.7655 | ... Z10: =SUMIFS(Производительность!X$247:X$263,Производительность!$C$247:$C$263,$A10) -> 2103.0359
A11: =A10 -> NHL NTE 240 | D11: Производительность: грузооборот | E11: тыс. ткм | G11: =SUMIFS(Производительность!E$263:E$279,Производительность!$C$263:$C$279,$A11) -> 11685.165 | H11: =SUMIFS(Производительность!F$263:F$279,Производительность!$C$263:$C$279,$A11) -> 11996.598 | I11: =SUMIFS(Производительность!G$263:G$279,Производительность!$C$263:$C$279,$A11) -> 12641.634 | J11: =SUMIFS(Производительность!H$263:H$279,Производительность!$C$263:$C$279,$A11) -> 12345.563 | K11: =SUMIFS(Производительность!I$263:I$279,Производительность!$C$263:$C$279,$A11) -> 13397.412 | L11: =SUMIFS(Производительность!J$263:J$279,Производительность!$C$263:$C$279,$A11) -> 13581.965 | M11: =SUMIFS(Производительность!K$263:K$279,Производительность!$C$263:$C$279,$A11) -> 13092.705 | N11: =SUMIFS(Производительность!L$263:L$279,Производительность!$C$263:$C$279,$A11) -> 12889.665 | ... Z11: =SUMIFS(Производительность!X$263:X$279,Производительность!$C$263:$C$279,$A11) -> 14267.842
A12: =A11 -> NHL NTE 240 | D12: Грузооборот кумулятивный | E12: =E11 -> тыс. ткм | G12: =G11 -> 11685.165 | H12: =IF(H7>$E5,0,G12+H11) -> 23681.763 | I12: =IF(I7>$E5,0,H12+I11) -> 36323.397 | J12: =IF(J7>$E5,0,I12+J11) -> 48668.96 | K12: =IF(K7>$E5,0,J12+K11) -> 62066.371 | L12: =IF(L7>$E5,0,K12+L11) -> 75648.337 | M12: =IF(M7>$E5,0,L12+M11) -> 88741.042 | N12: =IF(N7>$E5,0,M12+N11) -> 101630.71 | O12: =IF(O7>$E5,0,N12+O11) -> 115159.92 | ... Z12: =IF(Z7>$E5,0,Y12+Z11) -> 264866.08
A13: =A12 -> NHL NTE 240 | D13: Пробег | E13: тыс. км | G13: =SUMIFS(Производительность!E$279:E$295,Производительность!$C$279:$C$295,$A13)/1000 -> 104.28993 | H13: =SUMIFS(Производительность!F$279:F$295,Производительность!$C$279:$C$295,$A13)/1000 -> 107.06946 | I13: =SUMIFS(Производительность!G$279:G$295,Производительность!$C$279:$C$295,$A13)/1000 -> 112.8264 | J13: =SUMIFS(Производительность!H$279:H$295,Производительность!$C$279:$C$295,$A13)/1000 -> 110.18397 | K13: =SUMIFS(Производительность!I$279:I$295,Производительность!$C$279:$C$295,$A13)/1000 -> 119.57171 | L13: =SUMIFS(Производительность!J$279:J$295,Производительность!$C$279:$C$295,$A13)/1000 -> 121.21884 | M13: =SUMIFS(Производительность!K$279:K$295,Производительность!$C$279:$C$295,$A13)/1000 -> 116.8522 | N13: =SUMIFS(Производительность!L$279:L$295,Производительность!$C$279:$C$295,$A13)/1000 -> 115.04007 | ... Z13: =SUMIFS(Производительность!X$279:X$295,Производительность!$C$279:$C$295,$A13)/1000 -> 127.34028
A14: =A13 -> NHL NTE 240
A15: =A14 -> NHL NTE 240 | D15: Операционный денежный поток | E15: тыс. руб. | F15: =F40+F41-F39 -> 0 | G15: =G40+G41-G39 -> 88109.824 | H15: =H40+H41-H39 -> 91720.889 | I15: =I40+I41-I39 -> 126414.68 | J15: =J40+J41-J39 -> 107273.38 | K15: =K40+K41-K39 -> 100380.94 | L15: =L40+L41-L39 -> 131144.41 | M15: =M40+M41-M39 -> 98086.046 | ... Z15: =Z40+Z41-Z39 -> 106136.2
A16: =A15 -> NHL NTE 240 | C16: =D16 -> ТО, ТР, ППР | D16: ТО, ТР, ППР | E16: =E15 -> тыс. руб. | G16: =(G17+G18+G19)*'ФОТ, МТР, макро'!AK$8 -> 6011.0008 | H16: =(H17+H18+H19)*'ФОТ, МТР, макро'!AL$8 -> 8352.9635 | I16: =(I17+I18+I19)*'ФОТ, МТР, макро'!AM$8 -> 49489.736 | J16: =(J17+J18+J19)*'ФОТ, МТР, макро'!AN$8 -> 26318.824 | K16: =(K17+K18+K19)*'ФОТ, МТР, макро'!AO$8 -> 8777.1811 | L16: =(L17+L18+L19)*'ФОТ, МТР, макро'!AP$8 -> 48329.776 | M16: =(M17+M18+M19)*'ФОТ, МТР, макро'!AQ$8 -> 8136.7045 | N16: =(N17+N18+N19)*'ФОТ, МТР, макро'!AR$8 -> 27892.956 | ... Z16: =(Z17+Z18+Z19)*'ФОТ, МТР, макро'!BD$8 -> 9539.6148 | AB16: =SUM(F16:Z16,F30:Z30)/E5 -> 37724.114
A17: =A16 -> NHL NTE 240 | D17: ТО (включая смазочные) | E17: тыс. юаней | G17: ='NHL NTE240'!E19 -> 297.27424 | H17: ='NHL NTE240'!F19 -> 297.27424 | I17: ='NHL NTE240'!G19 -> 297.27424 | J17: ='NHL NTE240'!H19 -> 297.27424 | K17: ='NHL NTE240'!I19 -> 297.27424 | L17: ='NHL NTE240'!J19 -> 297.27424 | M17: ='NHL NTE240'!K19 -> 297.27424 | N17: ='NHL NTE240'!L19 -> 297.27424 | ... Z17: ='NHL NTE240'!X19 -> 297.27424
A18: =A17 -> NHL NTE 240 | D18: ТР, ППР | E18: тыс. юаней | G18: ='NHL NTE240'!E20 -> 0 | H18: ='NHL NTE240'!F20 -> 151.6104 | I18: ='NHL NTE240'!G20 -> 3293.5408 | J18: ='NHL NTE240'!H20 -> 1329.6506 | K18: ='NHL NTE240'!I20 -> 207.44414 | L18: ='NHL NTE240'!J20 -> 3259.167 | M18: ='NHL NTE240'!K20 -> 47.96174 | N18: ='NHL NTE240'!L20 -> 1481.261 | ... Z18: ='NHL NTE240'!X20 -> 237.35227
A19: =A18 -> NHL NTE 240 | D19: трудозатраты | E19: тыс. юаней | G19: ='NHL NTE240'!E21+'NHL NTE240'!E22 -> 173.43106 | H19: ='NHL NTE240'!F21+'NHL NTE240'!F22 -> 205.21346 | I19: ='NHL NTE240'!G21+'NHL NTE240'!G22 -> 284.59306 | J19: ='NHL NTE240'!H21+'NHL NTE240'!H22 -> 434.03146 | K19: ='NHL NTE240'!I21+'NHL NTE240'!I22 -> 182.59906 | L19: ='NHL NTE240'!J21+'NHL NTE240'!J22 -> 228.13346 | M19: ='NHL NTE240'!K21+'NHL NTE240'!K22 -> 291.92746 | N19: ='NHL NTE240'!L21+'NHL NTE240'!L22 -> 405.68706 | ... Z19: ='NHL NTE240'!X21+'NHL NTE240'!X22 -> 212.39506
A20: =A19 -> NHL NTE 240 | D20: % стоимости справочно | G20: =G16/$F44 -> #DIV/0! | H20: =H16/$F44 -> #DIV/0! | I20: =I16/$F44 -> #DIV/0! | J20: =J16/$F44 -> #DIV/0! | K20: =K16/$F44 -> #DIV/0! | L20: =L16/$F44 -> #DIV/0! | M20: =M16/$F44 -> #DIV/0! | N20: =N16/$F44 -> #DIV/0! | ... Z20: =Z16/$F44 -> #DIV/0! | AA20: =SUM(F16:Z16)/$F44 -> #DIV/0!
A21: =A20 -> NHL NTE 240 | D21: Шины | E21: =E15 -> тыс. руб. | G21: =G23*G24 -> 23350.892 | H21: =H23*H24 -> 23973.24 | I21: =I23*I24 -> 25262.239 | J21: =J23*J24 -> 24670.589 | K21: =K23*K24 -> 26772.537 | L21: =L23*L24 -> 27141.337 | M21: =M23*M24 -> 26163.631 | N21: =N23*N24 -> 25757.887 | ... Z21: =Z23*Z24 -> 28511.949
A22: =A21 -> NHL NTE 240 | D22: удельный расход | E22: шт./тыс. км | F22: =SUMIFS('ФОТ, МТР, макро'!$Z$4:$Z$20,'ФОТ, МТР, макро'!$W$4:$W$20,$A22) -> 0.075 | G22: =F22 -> 0.075 | H22: =G22 -> 0.075 | I22: =H22 -> 0.075 | J22: =I22 -> 0.075 | K22: =J22 -> 0.075 | L22: =K22 -> 0.075 | M22: =L22 -> 0.075 | N22: =M22 -> 0.075 | ... Z22: =Y22 -> 0.075
A23: =A22 -> NHL NTE 240 | D23: расход за период | E23: шт. | G23: =G13*G22 -> 7.8217446 | H23: =H13*H22 -> 8.0302097 | I23: =I13*I22 -> 8.4619799 | J23: =J13*J22 -> 8.2637977 | K23: =K13*K22 -> 8.967878 | L23: =L13*L22 -> 9.0914131 | M23: =M13*M22 -> 8.7639153 | N23: =N13*N22 -> 8.6280052 | ... Z23: =Z13*Z22 -> 9.550521 | AA23: =SUM(F13:Z13)*F22-SUM(F23:Z23) -> 0
A24: =A23 -> NHL NTE 240 | D24: цена | E24: тыс. руб./шт. | F24: =SUMIFS('ФОТ, МТР, макро'!$AA$4:$AA$20,'ФОТ, МТР, макро'!$W$4:$W$20,$A24) -> 2985.3815 | G24: =F24 -> 2985.3815 | H24: =G24 -> 2985.3815 | I24: =H24 -> 2985.3815 | J24: =I24 -> 2985.3815 | K24: =J24 -> 2985.3815 | L24: =K24 -> 2985.3815 | M24: =L24 -> 2985.3815 | N24: =M24 -> 2985.3815 | ... Z24: =Y24 -> 2985.3815
A25: =A24 -> NHL NTE 240 | D25: Топливо | E25: =E15 -> тыс. руб. | G25: =G28*G29 -> 69429.777 | H25: =H28*H29 -> 71280.219 | I25: =I28*I29 -> 75112.831 | J25: =J28*J29 -> 73353.664 | K25: =K28*K29 -> 79603.439 | L25: =L28*L29 -> 80699.999 | M25: =M28*M29 -> 77792.962 | N25: =N28*N29 -> 76586.555 | ... Z25: =Z28*Z29 -> 84775.274
A26: =A25 -> NHL NTE 240 | D26: удельный расход | E26: =VLOOKUP($A26,'ФОТ, МТР, макро'!$N$4:$Q$20,4,FALSE) -> г/ткм | F26: =IF($E26="г/ткм",SUMIFS('ФОТ, МТР, макро'!$O$4:$O$20,'ФОТ, МТР, макро'!$N$4:$N$20,$A26),SUMIFS('ФОТ, МТР, макро'!$P$4:$P$20,'ФОТ, МТР, макро'!$N$4:$N$20,$A26)) -> 90 | G26: =F26 -> 90 | H26: =G26 -> 90 | I26: =H26 -> 90 | J26: =I26 -> 90 | K26: =J26 -> 90 | L26: =K26 -> 90 | M26: =L26 -> 90 | N26: =M26 -> 90 | ... Z26: =Y26 -> 90
A27: =A26 -> NHL NTE 240 | D27: справочно | E27: =IF(E26='ФОТ, МТР, макро'!$O$4,'ФОТ, МТР, макро'!$P$4,'ФОТ, МТР, макро'!$O$4) -> л/час | G27: =IF($E26="г/ткм",G28*1000/(365*24*G9),G28/G11*1000) -> 149.27598 | H27: =IF($E26="г/ткм",H28*1000/(365*24*H9),H28/H11*1000) -> 154.43548 | I27: =IF($E26="г/ткм",I28*1000/(365*24*I9),I28/I11*1000) -> 163.11527 | J27: =IF($E26="г/ткм",J28*1000/(365*24*J9),J28/J11*1000) -> 161.48646 | K27: =IF($E26="г/ткм",K28*1000/(365*24*K9),K28/K11*1000) -> 170.56482 | L27: =IF($E26="г/ткм",L28*1000/(365*24*L9),L28/L11*1000) -> 175.09223 | M27: =IF($E26="г/ткм",M28*1000/(365*24*M9),M28/M11*1000) -> 167.05503 | N27: =IF($E26="г/ткм",N28*1000/(365*24*N9),N28/N11*1000) -> 168.09838 | ... Z27: =IF($E26="г/ткм",Z28*1000/(365*24*Z9),Z28/Z11*1000) -> 183.87666
A28: =A27 -> NHL NTE 240 | D28: расход за период | E28: т | G28: =IF($E26="г/ткм",G11*G26/1000,365*24*G9*G26*0.85/1000) -> 1051.6648 | H28: =IF($E26="г/ткм",H11*H26/1000,365*24*H9*H26*0.85/1000) -> 1079.6938 | I28: =IF($E26="г/ткм",I11*I26/1000,365*24*I9*I26*0.85/1000) -> 1137.747 | J28: =IF($E26="г/ткм",J11*J26/1000,365*24*J9*J26*0.85/1000) -> 1111.1007 | K28: =IF($E26="г/ткм",K11*K26/1000,365*24*K9*K26*0.85/1000) -> 1205.7671 | L28: =IF($E26="г/ткм",L11*L26/1000,365*24*L9*L26*0.85/1000) -> 1222.3769 | M28: =IF($E26="г/ткм",M11*M26/1000,365*24*M9*M26*0.85/1000) -> 1178.3435 | N28: =IF($E26="г/ткм",N11*N26/1000,365*24*N9*N26*0.85/1000) -> 1160.0698 | ... Z28: =IF($E26="г/ткм",Z11*Z26/1000,365*24*Z9*Z26*0.85/1000) -> 1284.1058
A29: =A28 -> NHL NTE 240 | D29: цена | E29: тыс. руб./т | F29: ='ФОТ, МТР, макро'!$G$2 -> 66.018919 | G29: =F29 -> 66.018919 | H29: =G29 -> 66.018919 | I29: =H29 -> 66.018919 | J29: =I29 -> 66.018919 | K29: =J29 -> 66.018919 | L29: =K29 -> 66.018919 | M29: =L29 -> 66.018919 | N29: =M29 -> 66.018919 | ... Z29: =Y29 -> 66.018919
A30: =A29 -> NHL NTE 240 | C30: =C16 -> ТО, ТР, ППР | D30: Смазочные | E30: =E15 -> тыс. руб.
A31: =A30 -> NHL NTE 240
A32: =A31 -> NHL NTE 240 | D32: Затраты на персонал | E32: =E15 -> тыс. руб. | G32: =G33+G34+G35 -> 18475.596 | H32: =H33+H34+H35 -> 18475.596 | I32: =I33+I34+I35 -> 18475.596 | J32: =J33+J34+J35 -> 18475.596 | K32: =K33+K34+K35 -> 18475.596 | L32: =L33+L34+L35 -> 18475.596 | M32: =M33+M34+M35 -> 18475.596 | N32: =N33+N34+N35 -> 18475.596 | ... Z32: =Z33+Z34+Z35 -> 18475.596
A33: =A32 -> NHL NTE 240 | D33: ФОТ | E33: =E32 -> тыс. руб. | F33: ='ФОТ, МТР, макро'!$B$4*'ФОТ, МТР, макро'!$B$7 -> 11107.5 | G33: =IF(G10=0,0,$F33) -> 11107.5 | H33: =IF(H10=0,0,$F33) -> 11107.5 | I33: =IF(I10=0,0,$F33) -> 11107.5 | J33: =IF(J10=0,0,$F33) -> 11107.5 | K33: =IF(K10=0,0,$F33) -> 11107.5 | L33: =IF(L10=0,0,$F33) -> 11107.5 | M33: =IF(M10=0,0,$F33) -> 11107.5 | N33: =IF(N10=0,0,$F33) -> 11107.5 | ... Z33: =IF(Z10=0,0,$F33) -> 11107.5
A34: =A33 -> NHL NTE 240 | D34: отчисления | E34: =E32 -> тыс. руб. | F34: ='ФОТ, МТР, макро'!$B$5 -> 0.377 | G34: =G33*$F34 -> 4187.5275 | H34: =H33*$F34 -> 4187.5275 | I34: =I33*$F34 -> 4187.5275 | J34: =J33*$F34 -> 4187.5275 | K34: =K33*$F34 -> 4187.5275 | L34: =L33*$F34 -> 4187.5275 | M34: =M33*$F34 -> 4187.5275 | N34: =N33*$F34 -> 4187.5275 | ... Z34: =Z33*$F34 -> 4187.5275
A35: =A34 -> NHL NTE 240 | D35: прочее | F35: ='ФОТ, МТР, макро'!$C$13*'ФОТ, МТР, макро'!$B$7 -> 3180.5687 | G35: =IF(G10=0,0,$F35) -> 3180.5687 | H35: =IF(H10=0,0,$F35) -> 3180.5687 | I35: =IF(I10=0,0,$F35) -> 3180.5687 | J35: =IF(J10=0,0,$F35) -> 3180.5687 | K35: =IF(K10=0,0,$F35) -> 3180.5687 | L35: =IF(L10=0,0,$F35) -> 3180.5687 | M35: =IF(M10=0,0,$F35) -> 3180.5687 | N35: =IF(N10=0,0,$F35) -> 3180.5687 | ... Z35: =IF(Z10=0,0,$F35) -> 3180.5687
A36: =A35 -> NHL NTE 240 | D36: Транспортный налог | E36: =E15 -> тыс. руб. | G36: =IF(G10=0,0,G37*G38/1000) -> 212.5 | H36: =IF(H10=0,0,H37*H38/1000) -> 212.5 | I36: =IF(I10=0,0,I37*I38/1000) -> 212.5 | J36: =IF(J10=0,0,J37*J38/1000) -> 212.5 | K36: =IF(K10=0,0,K37*K38/1000) -> 212.5 | L36: =IF(L10=0,0,L37*L38/1000) -> 212.5 | M36: =IF(M10=0,0,M37*M38/1000) -> 212.5 | N36: =IF(N10=0,0,N37*N38/1000) -> 212.5 | ... Z36: =IF(Z10=0,0,Z37*Z38/1000) -> 212.5
A37: =A36 -> NHL NTE 240 | D37: мощность двигателя | E37: л.с. | F37: =SUMIFS('ФОТ, МТР, макро'!$AC$4:$AC$20,'ФОТ, МТР, макро'!$W$4:$W$20,$A37) -> 2500 | G37: =F37 -> 2500 | H37: =G37 -> 2500 | I37: =H37 -> 2500 | J37: =I37 -> 2500 | K37: =J37 -> 2500 | L37: =K37 -> 2500 | M37: =L37 -> 2500 | N37: =M37 -> 2500 | ... Z37: =Y37 -> 2500
A38: =A37 -> NHL NTE 240 | D38: налоговая ставка | E38: руб./л.с. | F38: =SUMIFS('ФОТ, МТР, макро'!$AD$4:$AD$20,'ФОТ, МТР, макро'!$W$4:$W$20,$A38) -> 85 | G38: =F38 -> 85 | H38: =G38 -> 85 | I38: =H38 -> 85 | J38: =I38 -> 85 | K38: =J38 -> 85 | L38: =K38 -> 85 | M38: =L38 -> 85 | N38: =M38 -> 85 | ... Z38: =Y38 -> 85
A39: =A38 -> NHL NTE 240 | C39: =SUMIFS('ФОТ, МТР, макро'!$AG$4:$AG$20,'ФОТ, МТР, макро'!$W$4:$W$20,$A39) -> 14.117647 | D39: Амортизация НУ | E39: =E15 -> тыс. руб. | G39: =IF(G7<=$C40,$F44*$C39%,"ОШИБКА") -> 0 | H39: =IF(H7<=$C40,$F44*$C39%,$F44-SUM($G39:G39)) -> 0 | I39: =IF(I7<=$C40,$F44*$C39%,$F44-SUM($G39:H39)) -> 0 | J39: =IF(J7<=$C40,$F44*$C39%,$F44-SUM($G39:I39)) -> 0 | K39: =IF(K7<=$C40,$F44*$C39%,$F44-SUM($G39:J39)) -> 0 | L39: =IF(L7<=$C40,$F44*$C39%,$F44-SUM($G39:K39)) -> 0 | M39: =IF(M7<=$C40,$F44*$C39%,$F44-SUM($G39:L39)) -> 0 | N39: =IF(N7<=$C40,$F44*$C39%,$F44-SUM($G39:M39)) -> 0 | O39: =IF(O7<=$C40,$F44*$C39%,$F44-SUM($G39:N39)) -> 0 | ... Z39: =IF(Z7<=$C40,$F44*$C39%,$F44-SUM($G39:Y39)) -> 0 | AA39: =F44-SUM(G39:Z39) -> 0
A40: =A39 -> NHL NTE 240 | C40: =SUMIFS('ФОТ, МТР, макро'!$AF$4:$AF$20,'ФОТ, МТР, макро'!$W$4:$W$20,$A40)/12 -> 7.0833333 | D40: Налогооблагаемая база (по налогу на прибыль) | E40: =E15 -> тыс. руб. | G40: =SUM(G16,G21,G25,G30,G32,G36,G39) -> 117479.77 | H40: =SUM(H16,H21,H25,H30,H32,H36,H39) -> 122294.52 | I40: =SUM(I16,I21,I25,I30,I32,I36,I39) -> 168552.9 | J40: =SUM(J16,J21,J25,J30,J32,J36,J39) -> 143031.17 | K40: =SUM(K16,K21,K25,K30,K32,K36,K39) -> 133841.25 | L40: =SUM(L16,L21,L25,L30,L32,L36,L39) -> 174859.21 | M40: =SUM(M16,M21,M25,M30,M32,M36,M39) -> 130781.39 | N40: =SUM(N16,N21,N25,N30,N32,N36,N39) -> 148925.49 | ... Z40: =SUM(Z16,Z21,Z25,Z30,Z32,Z36,Z39) -> 141514.93
A41: =A40 -> NHL NTE 240 | D41: Налог на прибыль | E41: =E15 -> тыс. руб. | G41: =-G40*'ФОТ, МТР, макро'!AK$11 -> -29369.941 | H41: =-H40*'ФОТ, МТР, макро'!AL$11 -> -30573.63 | I41: =-I40*'ФОТ, МТР, макро'!AM$11 -> -42138.225 | J41: =-J40*'ФОТ, МТР, макро'!AN$11 -> -35757.793 | K41: =-K40*'ФОТ, МТР, макро'!AO$11 -> -33460.313 | L41: =-L40*'ФОТ, МТР, макро'!AP$11 -> -43714.802 | M41: =-M40*'ФОТ, МТР, макро'!AQ$11 -> -32695.349 | N41: =-N40*'ФОТ, МТР, макро'!AR$11 -> -37231.374 | ... Z41: =-Z40*'ФОТ, МТР, макро'!BD$11 -> -35378.734
A42: =A41 -> NHL NTE 240
A43: =A42 -> NHL NTE 240 | D43: Инвестиционный денежный поток | E43: =E15 -> тыс. руб. | F43: =F44 -> 0 | G43: =G44 -> 0 | H43: =H44 -> 0 | I43: =I44 -> 0 | J43: =J44 -> 0 | K43: =K44 -> 0 | L43: =L44 -> 0 | M43: =M44 -> 0 | ... Z43: =Z44 -> 0
A44: =A43 -> NHL NTE 240 | D44: Самосвал | E44: =E43 -> тыс. руб. | F44: =SUMIFS(Свод!$D$41:$U$41,Свод!$D$23:$U$23,$A44) -> 0
A45: =A44 -> NHL NTE 240
A46: =A45 -> NHL NTE 240 | D46: Денежный поток | E46: =E15 -> тыс. руб. | F46: =F15+F43 -> 0 | G46: =G15+G43 -> 88109.824 | H46: =H15+H43 -> 91720.889 | I46: =I15+I43 -> 126414.68 | J46: =J15+J43 -> 107273.38 | K46: =K15+K43 -> 100380.94 | L46: =L15+L43 -> 131144.41 | M46: =M15+M43 -> 98086.046 | ... Z46: =Z15+Z43 -> 106136.2
A47: =A46 -> NHL NTE 240 | D47: Дисконтированный операционный денежный поток | E47: =E46 -> тыс. руб. | G47: =G15*'ФОТ, МТР, макро'!AK$13 -> 78669.486 | H47: =H15*'ФОТ, МТР, макро'!AL$13 -> 73119.331 | I47: =I15*'ФОТ, МТР, макро'!AM$13 -> 89979.47 | J47: =J15*'ФОТ, МТР, макро'!AN$13 -> 68174.172 | K47: =K15*'ФОТ, МТР, макро'!AO$13 -> 56958.841 | L47: =L15*'ФОТ, МТР, макро'!AP$13 -> 66441.837 | M47: =M15*'ФОТ, МТР, макро'!AQ$13 -> 44369.146 | N47: =N15*'ФОТ, МТР, макро'!AR$13 -> 45111.382 | ... Z47: =Z15*'ФОТ, МТР, макро'!BD$13 -> 11002.797
A48: =A47 -> NHL NTE 240 | D48: =D16 -> ТО, ТР, ППР | E48: =E47 -> тыс. руб. | G48: =G16*'ФОТ, МТР, макро'!AK$13 -> 5366.965 | H48: =H16*'ФОТ, МТР, макро'!AL$13 -> 6658.9314 | I48: =I16*'ФОТ, МТР, макро'!AM$13 -> 35225.817 | J48: =J16*'ФОТ, МТР, макро'!AN$13 -> 16726.089 | K48: =K16*'ФОТ, МТР, макро'!AO$13 -> 4980.4083 | L48: =L16*'ФОТ, МТР, макро'!AP$13 -> 24485.368 | M48: =M16*'ФОТ, МТР, макро'!AQ$13 -> 3680.6319 | N48: =N16*'ФОТ, МТР, макро'!AR$13 -> 11265.497 | ... Z48: =Z16*'ФОТ, МТР, макро'!BD$13 -> 988.94101
A49: =A48 -> NHL NTE 240 | D49: =D21 -> Шины | E49: =E48 -> тыс. руб. | G49: =G21*'ФОТ, МТР, макро'!AK$13 -> 20849.011 | H49: =H21*'ФОТ, МТР, макро'!AL$13 -> 19111.32 | I49: =I21*'ФОТ, МТР, макро'!AM$13 -> 17981.162 | J49: =J21*'ФОТ, МТР, макро'!AN$13 -> 15678.605 | K49: =K21*'ФОТ, МТР, макро'!AO$13 -> 15191.457 | L49: =L21*'ФОТ, МТР, макро'!AP$13 -> 13750.646 | M49: =M21*'ФОТ, МТР, макро'!AQ$13 -> 11835.098 | N49: =N21*'ФОТ, МТР, макро'!AR$13 -> 10403.179 | ... Z49: =Z21*'ФОТ, МТР, макро'!BD$13 -> 2955.7415
A50: =A49 -> NHL NTE 240 | D50: =D25 -> Топливо | E50: =E49 -> тыс. руб. | G50: =G25*'ФОТ, МТР, макро'!AK$13 -> 61990.872 | H50: =H25*'ФОТ, МТР, макро'!AL$13 -> 56824.154 | I50: =I25*'ФОТ, МТР, макро'!AM$13 -> 53463.829 | J50: =J25*'ФОТ, МТР, макро'!AN$13 -> 46617.58 | K50: =K25*'ФОТ, МТР, макро'!AO$13 -> 45169.129 | L50: =L25*'ФОТ, МТР, макро'!AP$13 -> 40885.131 | M50: =M25*'ФОТ, МТР, макро'!AQ$13 -> 35189.586 | N50: =N25*'ФОТ, МТР, макро'!AR$13 -> 30932.025 | ... Z50: =Z25*'ФОТ, МТР, макро'!BD$13 -> 8788.3784
A51: =A50 -> NHL NTE 240 | D51: =D30 -> Смазочные | E51: =E50 -> тыс. руб. | G51: =G30*'ФОТ, МТР, макро'!AK$13 -> 0 | H51: =H30*'ФОТ, МТР, макро'!AL$13 -> 0 | I51: =I30*'ФОТ, МТР, макро'!AM$13 -> 0 | J51: =J30*'ФОТ, МТР, макро'!AN$13 -> 0 | K51: =K30*'ФОТ, МТР, макро'!AO$13 -> 0 | L51: =L30*'ФОТ, МТР, макро'!AP$13 -> 0 | M51: =M30*'ФОТ, МТР, макро'!AQ$13 -> 0 | N51: =N30*'ФОТ, МТР, макро'!AR$13 -> 0 | ... Z51: =Z30*'ФОТ, МТР, макро'!BD$13 -> 0
A52: =A51 -> NHL NTE 240 | D52: =D32 -> Затраты на персонал | E52: =E51 -> тыс. руб. | G52: =G32*'ФОТ, МТР, макро'!AK$13 -> 16496.068 | H52: =H32*'ФОТ, МТР, макро'!AL$13 -> 14728.632 | I52: =I32*'ФОТ, МТР, макро'!AM$13 -> 13150.564 | J52: =J32*'ФОТ, МТР, макро'!AN$13 -> 11741.575 | K52: =K32*'ФОТ, МТР, макро'!AO$13 -> 10483.549 | L52: =L32*'ФОТ, МТР, макро'!AP$13 -> 9360.312 | M52: =M32*'ФОТ, МТР, макро'!AQ$13 -> 8357.4215 | N52: =N32*'ФОТ, МТР, макро'!AR$13 -> 7461.9834 | ... Z52: =Z32*'ФОТ, МТР, макро'!BD$13 -> 1915.3053
A53: =A52 -> NHL NTE 240 | D53: =D36 -> Транспортный налог | E53: =E52 -> тыс. руб. | G53: =G36*'ФОТ, МТР, макро'!AK$13 -> 189.73214 | H53: =H36*'ФОТ, МТР, макро'!AL$13 -> 169.4037 | I53: =I36*'ФОТ, МТР, макро'!AM$13 -> 151.2533 | J53: =J36*'ФОТ, МТР, макро'!AN$13 -> 135.04759 | K53: =K36*'ФОТ, МТР, макро'!AO$13 -> 120.57821 | L53: =L36*'ФОТ, МТР, макро'!AP$13 -> 107.65911 | M53: =M36*'ФОТ, МТР, макро'!AQ$13 -> 96.124208 | N53: =N36*'ФОТ, МТР, макро'!AR$13 -> 85.825186 | ... Z53: =Z36*'ФОТ, МТР, макро'!BD$13 -> 22.029188
A54: =A53 -> NHL NTE 240 | D54: =D41 -> Налог на прибыль | E54: =E53 -> тыс. руб. | G54: =G41*'ФОТ, МТР, макро'!AK$13 -> -26223.162 | H54: =H41*'ФОТ, МТР, макро'!AL$13 -> -24373.11 | I54: =I41*'ФОТ, МТР, макро'!AM$13 -> -29993.157 | J54: =J41*'ФОТ, МТР, макро'!AN$13 -> -22724.724 | K54: =K41*'ФОТ, МТР, макро'!AO$13 -> -18986.28 | L54: =L41*'ФОТ, МТР, макро'!AP$13 -> -22147.279 | M54: =M41*'ФОТ, МТР, макро'!AQ$13 -> -14789.715 | N54: =N41*'ФОТ, МТР, макро'!AR$13 -> -15037.127 | ... Z54: =Z41*'ФОТ, МТР, макро'!BD$13 -> -3667.5989
A55: =A54 -> NHL NTE 240 | D55: проверка полноты | G55: =G47-SUM(G48:G54) -> 0 | H55: =H47-SUM(H48:H54) -> 0 | I55: =I47-SUM(I48:I54) -> 0 | J55: =J47-SUM(J48:J54) -> 0 | K55: =K47-SUM(K48:K54) -> 0 | L55: =L47-SUM(L48:L54) -> 0 | M55: =M47-SUM(M48:M54) -> 0 | N55: =N47-SUM(N48:N54) -> 0 | ... Z55: =Z47-SUM(Z48:Z54) -> 0
A56: =A55 -> NHL NTE 240 | D56: Кумулятивный дисконтированный операционный денежный поток | E56: =E47 -> тыс. руб. | F56: =F47 -> 0 | G56: =F56+G47 -> 78669.486 | H56: =G56+H47 -> 151788.82 | I56: =H56+I47 -> 241768.29 | J56: =I56+J47 -> 309942.46 | K56: =J56+K47 -> 366901.3 | L56: =K56+L47 -> 433343.14 | M56: =L56+M47 -> 477712.28 | N56: =M56+N47 -> 522823.67 | ... Z56: =Y56+Z47 -> 864149.73
A57: =A56 -> NHL NTE 240 | D57: =D48 -> ТО, ТР, ППР | E57: =E48 -> тыс. руб. | F57: =F48 -> 0 | G57: =F57+G48 -> 5366.965 | H57: =G57+H48 -> 12025.896 | I57: =H57+I48 -> 47251.713 | J57: =I57+J48 -> 63977.801 | K57: =J57+K48 -> 68958.21 | L57: =K57+L48 -> 93443.578 | M57: =L57+M48 -> 97124.21 | N57: =M57+N48 -> 108389.71 | ... Z57: =Y57+Z48 -> 247178.08
A58: =A57 -> NHL NTE 240 | D58: =D49 -> Шины | E58: =E49 -> тыс. руб. | F58: =F49 -> 0 | G58: =F58+G49 -> 20849.011 | H58: =G58+H49 -> 39960.331 | I58: =H58+I49 -> 57941.493 | J58: =I58+J49 -> 73620.098 | K58: =J58+K49 -> 88811.555 | L58: =K58+L49 -> 102562.2 | M58: =L58+M49 -> 114397.3 | N58: =M58+N49 -> 124800.48 | ... Z58: =Y58+Z49 -> 192642.69
A59: =A58 -> NHL NTE 240 | D59: =D50 -> Топливо | E59: =E50 -> тыс. руб. | F59: =F50 -> 0 | G59: =F59+G50 -> 61990.872 | H59: =G59+H50 -> 118815.03 | I59: =H59+I50 -> 172278.86 | J59: =I59+J50 -> 218896.44 | K59: =J59+K50 -> 264065.56 | L59: =K59+L50 -> 304950.7 | M59: =L59+M50 -> 340140.28 | N59: =M59+N50 -> 371072.31 | ... Z59: =Y59+Z50 -> 572789.2
A60: =A59 -> NHL NTE 240 | D60: =D51 -> Смазочные | E60: =E51 -> тыс. руб. | F60: =F51 -> 0 | G60: =F60+G51 -> 0 | H60: =G60+H51 -> 0 | I60: =H60+I51 -> 0 | J60: =I60+J51 -> 0 | K60: =J60+K51 -> 0 | L60: =K60+L51 -> 0 | M60: =L60+M51 -> 0 | N60: =M60+N51 -> 0 | ... Z60: =Y60+Z51 -> 0
A61: =A60 -> NHL NTE 240 | D61: =D52 -> Затраты на персонал | E61: =E52 -> тыс. руб. | F61: =F52 -> 0 | G61: =F61+G52 -> 16496.068 | H61: =G61+H52 -> 31224.7 | I61: =H61+I52 -> 44375.265 | J61: =I61+J52 -> 56116.84 | K61: =J61+K52 -> 66600.39 | L61: =K61+L52 -> 75960.702 | M61: =L61+M52 -> 84318.123 | N61: =M61+N52 -> 91780.107 | ... Z61: =Y61+Z52 -> 138002.42
A62: =A61 -> NHL NTE 240 | D62: =D53 -> Транспортный налог | E62: =E53 -> тыс. руб. | F62: =F53 -> 0 | G62: =F62+G53 -> 189.73214 | H62: =G62+H53 -> 359.13584 | I62: =H62+I53 -> 510.38914 | J62: =I62+J53 -> 645.43674 | K62: =J62+K53 -> 766.01494 | L62: =K62+L53 -> 873.67406 | M62: =L62+M53 -> 969.79826 | N62: =M62+N53 -> 1055.6235 | ... Z62: =Y62+Z53 -> 1587.2568
A63: =A62 -> NHL NTE 240 | D63: =D54 -> Налог на прибыль | E63: =E54 -> тыс. руб. | F63: =F54 -> 0 | G63: =F63+G54 -> -26223.162 | H63: =G63+H54 -> -50596.272 | I63: =H63+I54 -> -80589.429 | J63: =I63+J54 -> -103314.15 | K63: =J63+K54 -> -122300.43 | L63: =K63+L54 -> -144447.71 | M63: =L63+M54 -> -159237.43 | N63: =M63+N54 -> -174274.56 | ... Z63: =Y63+Z54 -> -288049.91
A64: =A63 -> NHL NTE 240
A65: =A64 -> NHL NTE 240 | D65: Дисконтированный инвестиционный поток | E65: =E46 -> тыс. руб. | F65: =F43*'ФОТ, МТР, макро'!AJ$13 -> 0 | G65: =G43*'ФОТ, МТР, макро'!AK$13 -> 0 | H65: =H43*'ФОТ, МТР, макро'!AL$13 -> 0 | I65: =I43*'ФОТ, МТР, макро'!AM$13 -> 0 | J65: =J43*'ФОТ, МТР, макро'!AN$13 -> 0 | K65: =K43*'ФОТ, МТР, макро'!AO$13 -> 0 | L65: =L43*'ФОТ, МТР, макро'!AP$13 -> 0 | M65: =M43*'ФОТ, МТР, макро'!AQ$13 -> 0 | ... Z65: =Z43*'ФОТ, МТР, макро'!BD$13 -> 0
A66: =A65 -> NHL NTE 240 | D66: =D44 -> Самосвал | E66: =E65 -> тыс. руб. | F66: =F44*'ФОТ, МТР, макро'!AJ$13 -> 0 | G66: =G44*'ФОТ, МТР, макро'!AK$13 -> 0 | H66: =H44*'ФОТ, МТР, макро'!AL$13 -> 0 | I66: =I44*'ФОТ, МТР, макро'!AM$13 -> 0 | J66: =J44*'ФОТ, МТР, макро'!AN$13 -> 0 | K66: =K44*'ФОТ, МТР, макро'!AO$13 -> 0 | L66: =L44*'ФОТ, МТР, макро'!AP$13 -> 0 | M66: =M44*'ФОТ, МТР, макро'!AQ$13 -> 0 | ... Z66: =Z44*'ФОТ, МТР, макро'!BD$13 -> 0
A67: =A66 -> NHL NTE 240 | D67: проверка полноты | F67: =F65-F66 -> 0 | G67: =G65-G66 -> 0 | H67: =H65-H66 -> 0 | I67: =I65-I66 -> 0 | J67: =J65-J66 -> 0 | K67: =K65-K66 -> 0 | L67: =L65-L66 -> 0 | M67: =M65-M66 -> 0 | ... Z67: =Z65-Z66 -> 0
A68: =A67 -> NHL NTE 240 | D68: Кумулятивный инвестиционный поток | E68: =E65 -> тыс. руб. | F68: =F65 -> 0 | G68: =F68+G65 -> 0 | H68: =G68+H65 -> 0 | I68: =H68+I65 -> 0 | J68: =I68+J65 -> 0 | K68: =J68+K65 -> 0 | L68: =K68+L65 -> 0 | M68: =L68+M65 -> 0 | N68: =M68+N65 -> 0 | ... Z68: =Y68+Z65 -> 0
A69: =A68 -> NHL NTE 240 | D69: =D66 -> Самосвал | E69: =E66 -> тыс. руб. | F69: =F66 -> 0 | G69: =F69+G66 -> 0 | H69: =G69+H66 -> 0 | I69: =H69+I66 -> 0 | J69: =I69+J66 -> 0 | K69: =J69+K66 -> 0 | L69: =K69+L66 -> 0 | M69: =L69+M66 -> 0 | N69: =M69+N66 -> 0 | ... Z69: =Y69+Z66 -> 0
A70: =A69 -> NHL NTE 240
A71: =A70 -> NHL NTE 240 | D71: Дисконтированный денежный поток | E71: =E46 -> тыс. руб. | F71: =F46*'ФОТ, МТР, макро'!AJ$13 -> 0 | G71: =G46*'ФОТ, МТР, макро'!AK$13 -> 78669.486 | H71: =H46*'ФОТ, МТР, макро'!AL$13 -> 73119.331 | I71: =I46*'ФОТ, МТР, макро'!AM$13 -> 89979.47 | J71: =J46*'ФОТ, МТР, макро'!AN$13 -> 68174.172 | K71: =K46*'ФОТ, МТР, макро'!AO$13 -> 56958.841 | L71: =L46*'ФОТ, МТР, макро'!AP$13 -> 66441.837 | M71: =M46*'ФОТ, МТР, макро'!AQ$13 -> 44369.146 | ... Z71: =Z46*'ФОТ, МТР, макро'!BD$13 -> 11002.797
A72: =A71 -> NHL NTE 240 | D72: Кумулятивный дисконтированный денежный поток | E72: =E71 -> тыс. руб. | F72: =F71 -> 0 | G72: =F72+G71 -> 78669.486 | H72: =G72+H71 -> 151788.82 | I72: =H72+I71 -> 241768.29 | J72: =I72+J71 -> 309942.46 | K72: =J72+K71 -> 366901.3 | L72: =K72+L71 -> 433343.14 | M72: =L72+M71 -> 477712.28 | N72: =M72+N71 -> 522823.67 | ... Z72: =Y72+Z71 -> 864149.73
A73: =A72 -> NHL NTE 240
A74: =A73 -> NHL NTE 240 | B74: =D74 -> Аннуитет операционный | C74: =E5 -> 20 | D74: Аннуитет операционный | E74: руб/ткм | G74: =G56/'ФОТ, МТР, макро'!AK$14/(G12/G7) -> 7.540315 | H74: =H56/'ФОТ, МТР, макро'!AL$14/(H12/H7) -> 7.585006 | I74: =I56/'ФОТ, МТР, макро'!AM$14/(I12/I7) -> 8.3136481 | J74: =J56/'ФОТ, МТР, макро'!AN$14/(J12/J7) -> 8.3867608 | K74: =K56/'ФОТ, МТР, макро'!AO$14/(K12/K7) -> 8.1994475 | L74: =L56/'ФОТ, МТР, макро'!AP$14/(L12/L7) -> 8.3597499 | M74: =M56/'ФОТ, МТР, макро'!AQ$14/(M12/M7) -> 8.2569082 | N74: =N56/'ФОТ, МТР, макро'!AR$14/(N12/N7) -> 8.2845741 | ... Z74: =Z56/'ФОТ, МТР, макро'!BD$14/(Z12/Z7) -> 8.7358346 | AC74: {=INDEX(G74:Z74,1,$C74)} -> 8.7358346
A75: =A74 -> NHL NTE 240 | B75: =D75 -> ТО, ТР, ППР | C75: =C74 -> 20 | D75: =D57 -> ТО, ТР, ППР | E75: =E74 -> руб/ткм | G75: =G57/'ФОТ, МТР, макро'!AK$14/(G12/G7) -> 0.514413 | H75: =H57/'ФОТ, МТР, макро'!AL$14/(H12/H7) -> 0.60094345 | I75: =I57/'ФОТ, МТР, макро'!AM$14/(I12/I7) -> 1.6248372 | J75: =J57/'ФОТ, МТР, макро'!AN$14/(J12/J7) -> 1.7311811 | K75: =K57/'ФОТ, МТР, макро'!AO$14/(K12/K7) -> 1.5410663 | L75: =L57/'ФОТ, МТР, макро'!AP$14/(L12/L7) -> 1.8026476 | M75: =M57/'ФОТ, МТР, макро'!AQ$14/(M12/M7) -> 1.6787211 | N75: =N57/'ФОТ, МТР, макро'!AR$14/(N12/N7) -> 1.7175247 | ... Z75: =Z57/'ФОТ, МТР, макро'!BD$14/(Z12/Z7) -> 2.4987646 | AC75: {=INDEX(G75:Z75,1,$C75)} -> 2.4987646
A76: =A75 -> NHL NTE 240 | B76: =D76 -> Шины | C76: =C75 -> 20 | D76: =D58 -> Шины | E76: =E75 -> руб/ткм | G76: =G58/'ФОТ, МТР, макро'!AK$14/(G12/G7) -> 1.9983365 | H76: =H58/'ФОТ, МТР, макро'!AL$14/(H12/H7) -> 1.996849 | I76: =I58/'ФОТ, МТР, макро'!AM$14/(I12/I7) -> 1.992425 | J76: =J58/'ФОТ, МТР, макро'!AN$14/(J12/J7) -> 1.9920928 | K76: =K58/'ФОТ, МТР, макро'!AO$14/(K12/K7) -> 1.9847455 | L76: =L58/'ФОТ, МТР, макро'!AP$14/(L12/L7) -> 1.9785576 | M76: =M58/'ФОТ, МТР, макро'!AQ$14/(M12/M7) -> 1.9772738 | N76: =N58/'ФОТ, МТР, макро'!AR$14/(N12/N7) -> 1.977567 | ... Z76: =Z58/'ФОТ, МТР, макро'!BD$14/(Z12/Z7) -> 1.9474572 | AC76: {=INDEX(G76:Z76,1,$C76)} -> 1.9474572
A77: =A76 -> NHL NTE 240 | B77: =D77 -> Топливо | C77: =C76 -> 20 | D77: =D59 -> Топливо | E77: =E76 -> руб/ткм | G77: =G59/'ФОТ, МТР, макро'!AK$14/(G12/G7) -> 5.9417028 | H77: =H59/'ФОТ, МТР, макро'!AL$14/(H12/H7) -> 5.9372799 | I77: =I59/'ФОТ, МТР, макро'!AM$14/(I12/I7) -> 5.924126 | J77: =J59/'ФОТ, МТР, макро'!AN$14/(J12/J7) -> 5.9231383 | K77: =K59/'ФОТ, МТР, макро'!AO$14/(K12/K7) -> 5.9012921 | L77: =L59/'ФОТ, МТР, макро'!AP$14/(L12/L7) -> 5.8828936 | M77: =M59/'ФОТ, МТР, макро'!AQ$14/(M12/M7) -> 5.8790766 | N77: =N59/'ФОТ, МТР, макро'!AR$14/(N12/N7) -> 5.8799481 | ... Z77: =Z59/'ФОТ, МТР, макро'!BD$14/(Z12/Z7) -> 5.7904221 | AC77: {=INDEX(G77:Z77,1,$C77)} -> 5.7904221
A78: =A77 -> NHL NTE 240 | B78: =D78 -> Смазочные | C78: =C77 -> 20 | D78: =D60 -> Смазочные | E78: =E77 -> руб/ткм | G78: =G60/'ФОТ, МТР, макро'!AK$14/(G12/G7) -> 0 | H78: =H60/'ФОТ, МТР, макро'!AL$14/(H12/H7) -> 0 | I78: =I60/'ФОТ, МТР, макро'!AM$14/(I12/I7) -> 0 | J78: =J60/'ФОТ, МТР, макро'!AN$14/(J12/J7) -> 0 | K78: =K60/'ФОТ, МТР, макро'!AO$14/(K12/K7) -> 0 | L78: =L60/'ФОТ, МТР, макро'!AP$14/(L12/L7) -> 0 | M78: =M60/'ФОТ, МТР, макро'!AQ$14/(M12/M7) -> 0 | N78: =N60/'ФОТ, МТР, макро'!AR$14/(N12/N7) -> 0 | ... Z78: =Z60/'ФОТ, МТР, макро'!BD$14/(Z12/Z7) -> 0 | AC78: {=INDEX(G78:Z78,1,$C78)} -> 0
A79: =A78 -> NHL NTE 240 | B79: =D79 -> Затраты на персонал | C79: =C78 -> 20 | D79: =D61 -> Затраты на персонал | E79: =E78 -> руб/ткм | G79: =G61/'ФОТ, МТР, макро'!AK$14/(G12/G7) -> 1.5811156 | H79: =H61/'ФОТ, МТР, макро'!AL$14/(H12/H7) -> 1.5603227 | I79: =I61/'ФОТ, МТР, макро'!AM$14/(I12/I7) -> 1.5259253 | J79: =J61/'ФОТ, МТР, макро'!AN$14/(J12/J7) -> 1.5184706 | K79: =K61/'ФОТ, МТР, макро'!AO$14/(K12/K7) -> 1.4883741 | L79: =L61/'ФОТ, МТР, макро'!AP$14/(L12/L7) -> 1.4653802 | M79: =M61/'ФОТ, МТР, макро'!AQ$14/(M12/M7) -> 1.4573772 | N79: =N61/'ФОТ, МТР, макро'!AR$14/(N12/N7) -> 1.4543318 | ... Z79: =Z61/'ФОТ, МТР, макро'!BD$14/(Z12/Z7) -> 1.3950897 | AC79: {=INDEX(G79:Z79,1,$C79)} -> 1.3950897
A80: =A79 -> NHL NTE 240 | B80: =D80 -> Транспортный налог | C80: =C79 -> 20 | D80: =D62 -> Транспортный налог | E80: =E79 -> руб/ткм | G80: =G62/'ФОТ, МТР, макро'!AK$14/(G12/G7) -> 0.018185451 | H80: =H62/'ФОТ, МТР, макро'!AL$14/(H12/H7) -> 0.017946299 | I80: =I62/'ФОТ, МТР, макро'!AM$14/(I12/I7) -> 0.017550671 | J80: =J62/'ФОТ, МТР, макро'!AN$14/(J12/J7) -> 0.017464931 | K80: =K62/'ФОТ, МТР, макро'!AO$14/(K12/K7) -> 0.017118771 | L80: =L62/'ФОТ, МТР, макро'!AP$14/(L12/L7) -> 0.016854303 | M80: =M62/'ФОТ, МТР, макро'!AQ$14/(M12/M7) -> 0.016762255 | N80: =N62/'ФОТ, МТР, макро'!AR$14/(N12/N7) -> 0.016727228 | ... Z80: =Z62/'ФОТ, МТР, макро'!BD$14/(Z12/Z7) -> 0.016045845 | AC80: {=INDEX(G80:Z80,1,$C80)} -> 0.016045845
A81: =A80 -> NHL NTE 240 | B81: =D81 -> Налог на прибыль | C81: =C80 -> 20 | D81: =D63 -> Налог на прибыль | E81: =E80 -> руб/ткм | G81: =G63/'ФОТ, МТР, макро'!AK$14/(G12/G7) -> -2.5134383 | H81: =H63/'ФОТ, МТР, макро'!AL$14/(H12/H7) -> -2.5283353 | I81: =I63/'ФОТ, МТР, макро'!AM$14/(I12/I7) -> -2.771216 | J81: =J63/'ФОТ, МТР, макро'!AN$14/(J12/J7) -> -2.7955869 | K81: =K63/'ФОТ, МТР, макро'!AO$14/(K12/K7) -> -2.7331492 | L81: =L63/'ФОТ, МТР, макро'!AP$14/(L12/L7) -> -2.7865833 | M81: =M63/'ФОТ, МТР, макро'!AQ$14/(M12/M7) -> -2.7523027 | N81: =N63/'ФОТ, МТР, макро'!AR$14/(N12/N7) -> -2.7615247 | ... Z81: =Z63/'ФОТ, МТР, макро'!BD$14/(Z12/Z7) -> -2.9119449 | AC81: {=INDEX(G81:Z81,1,$C81)} -> -2.9119449
A82: =A81 -> NHL NTE 240 | B82: =D82 -> Аннуитет инвестиционный | C82: =C81 -> 20 | D82: Аннуитет инвестиционный | E82: =E74 -> руб/ткм | G82: =G68/'ФОТ, МТР, макро'!AK$14/(G12/G7) -> 0 | H82: =H68/'ФОТ, МТР, макро'!AL$14/(H12/H7) -> 0 | I82: =I68/'ФОТ, МТР, макро'!AM$14/(I12/I7) -> 0 | J82: =J68/'ФОТ, МТР, макро'!AN$14/(J12/J7) -> 0 | K82: =K68/'ФОТ, МТР, макро'!AO$14/(K12/K7) -> 0 | L82: =L68/'ФОТ, МТР, макро'!AP$14/(L12/L7) -> 0 | M82: =M68/'ФОТ, МТР, макро'!AQ$14/(M12/M7) -> 0 | N82: =N68/'ФОТ, МТР, макро'!AR$14/(N12/N7) -> 0 | ... Z82: =Z68/'ФОТ, МТР, макро'!BD$14/(Z12/Z7) -> 0 | AC82: {=INDEX(G82:Z82,1,$C82)} -> 0
A83: =A82 -> NHL NTE 240 | B83: =D83 -> Самосвал | C83: =C82 -> 20 | D83: =D69 -> Самосвал | E83: =E82 -> руб/ткм | G83: =G69/'ФОТ, МТР, макро'!AK$14/(G12/G7) -> 0 | H83: =H69/'ФОТ, МТР, макро'!AL$14/(H12/H7) -> 0 | I83: =I69/'ФОТ, МТР, макро'!AM$14/(I12/I7) -> 0 | J83: =J69/'ФОТ, МТР, макро'!AN$14/(J12/J7) -> 0 | K83: =K69/'ФОТ, МТР, макро'!AO$14/(K12/K7) -> 0 | L83: =L69/'ФОТ, МТР, макро'!AP$14/(L12/L7) -> 0 | M83: =M69/'ФОТ, МТР, макро'!AQ$14/(M12/M7) -> 0 | N83: =N69/'ФОТ, МТР, макро'!AR$14/(N12/N7) -> 0 | ... Z83: =Z69/'ФОТ, МТР, макро'!BD$14/(Z12/Z7) -> 0 | AC83: {=INDEX(G83:Z83,1,$C83)} -> 0
A84: =A83 -> NHL NTE 240 | B84: =D84 -> Аннуитет общий | C84: =C83 -> 20 | D84: Аннуитет общий | E84: =E74 -> руб/ткм | G84: =G72/'ФОТ, МТР, макро'!AK$14/(G12/G7) -> 7.540315 | H84: =H72/'ФОТ, МТР, макро'!AL$14/(H12/H7) -> 7.585006 | I84: =I72/'ФОТ, МТР, макро'!AM$14/(I12/I7) -> 8.3136481 | J84: =J72/'ФОТ, МТР, макро'!AN$14/(J12/J7) -> 8.3867608 | K84: =K72/'ФОТ, МТР, макро'!AO$14/(K12/K7) -> 8.1994475 | L84: =L72/'ФОТ, МТР, макро'!AP$14/(L12/L7) -> 8.3597499 | M84: =M72/'ФОТ, МТР, макро'!AQ$14/(M12/M7) -> 8.2569082 | N84: =N72/'ФОТ, МТР, макро'!AR$14/(N12/N7) -> 8.2845741 | ... Z84: =Z72/'ФОТ, МТР, макро'!BD$14/(Z12/Z7) -> 8.7358346 | AC84: {=INDEX(G84:Z84,1,$C84)} -> 8.7358346
A85: =A84 -> NHL NTE 240
A86: =A85 -> NHL NTE 240 | D86: проверка полноты | G86: =G84-G74-G82+G74-SUM(G75:G81)+G82-G83 -> 1.7763568e-15 | H86: =H84-H74-H82+H74-SUM(H75:H81)+H82-H83 -> 8.8817842e-16 | I86: =I84-I74-I82+I74-SUM(I75:I81)+I82-I83 -> -1.7763568e-15 | J86: =J84-J74-J82+J74-SUM(J75:J81)+J82-J83 -> 1.7763568e-15 | K86: =K84-K74-K82+K74-SUM(K75:K81)+K82-K83 -> 0 | L86: =L84-L74-L82+L74-SUM(L75:L81)+L82-L83 -> 0 | M86: =M84-M74-M82+M74-SUM(M75:M81)+M82-M83 -> -1.7763568e-15 | N86: =N84-N74-N82+N74-SUM(N75:N81)+N82-N83 -> 0 | ... Z86: =Z84-Z74-Z82+Z74-SUM(Z75:Z81)+Z82-Z83 -> 0
A87: =A86 -> NHL NTE 240
A88: =A87 -> NHL NTE 240 | D88: Себестоимость (справочно) | E88: =E84 -> руб/ткм | G88: =SUM(G89:G94) -> 10.053753 | H88: =SUM(H89:H94) -> 10.1941 | I88: =SUM(I89:I94) -> 13.333158 | J88: =SUM(J89:J94) -> 11.585634 | K88: =SUM(K89:K94) -> 9.9900828 | L88: =SUM(L89:L94) -> 12.874367 | M88: =SUM(M89:M94) -> 9.9888749 | N88: =SUM(N89:N94) -> 11.553869 | ... Z88: =SUM(Z89:Z94) -> 9.9184542
A89: =A88 -> NHL NTE 240 | D89: =D75 -> ТО, ТР, ППР | E89: =E88 -> руб/ткм | G89: =G16/G11 -> 0.514413 | H89: =H16/H11 -> 0.69627769 | I89: =I16/I11 -> 3.9148212 | J89: =J16/J11 -> 2.1318448 | K89: =K16/K11 -> 0.65514005 | L89: =L16/L11 -> 3.5583787 | M89: =M16/M11 -> 0.62146855 | N89: =N16/N11 -> 2.1639784 | ... Z89: =Z16/Z11 -> 0.66860952
A90: =A89 -> NHL NTE 240 | D90: =D76 -> Шины | E90: =E89 -> руб/ткм | G90: =G21/G11 -> 1.9983365 | H90: =H21/H11 -> 1.9983365 | I90: =I21/I11 -> 1.9983365 | J90: =J21/J11 -> 1.9983365 | K90: =K21/K11 -> 1.9983365 | L90: =L21/L11 -> 1.9983365 | M90: =M21/M11 -> 1.9983365 | N90: =N21/N11 -> 1.9983365 | ... Z90: =Z21/Z11 -> 1.9983365
A91: =A90 -> NHL NTE 240 | D91: =D77 -> Топливо | E91: =E90 -> руб/ткм | G91: =G25/G11 -> 5.9417028 | H91: =H25/H11 -> 5.9417028 | I91: =I25/I11 -> 5.9417028 | J91: =J25/J11 -> 5.9417028 | K91: =K25/K11 -> 5.9417028 | L91: =L25/L11 -> 5.9417028 | M91: =M25/M11 -> 5.9417028 | N91: =N25/N11 -> 5.9417028 | ... Z91: =Z25/Z11 -> 5.9417028
A92: =A91 -> NHL NTE 240 | D92: =D78 -> Смазочные | E92: =E91 -> руб/ткм | G92: =G30/G11 -> 0 | H92: =H30/H11 -> 0 | I92: =I30/I11 -> 0 | J92: =J30/J11 -> 0 | K92: =K30/K11 -> 0 | L92: =L30/L11 -> 0 | M92: =M30/M11 -> 0 | N92: =N30/N11 -> 0 | ... Z92: =Z30/Z11 -> 0
A93: =A92 -> NHL NTE 240 | D93: =D79 -> Затраты на персонал | E93: =E92 -> руб/ткм | G93: =G32/G11 -> 1.5811156 | H93: =H32/H11 -> 1.5400696 | I93: =I32/I11 -> 1.461488 | J93: =J32/J11 -> 1.4965374 | K93: =K32/K11 -> 1.3790422 | L93: =L32/L11 -> 1.3603036 | M93: =M32/M11 -> 1.4111367 | N93: =N32/N11 -> 1.4333652 | ... Z93: =Z32/Z11 -> 1.2949118
A94: =A93 -> NHL NTE 240 | D94: =D80 -> Транспортный налог | E94: =E93 -> руб/ткм | G94: =G36/G11 -> 0.018185451 | H94: =H36/H11 -> 0.017713355 | I94: =I36/I11 -> 0.016809536 | J94: =J36/J11 -> 0.017212662 | K94: =K36/K11 -> 0.015861272 | L94: =L36/L11 -> 0.015645748 | M94: =M36/M11 -> 0.016230412 | N94: =N36/N11 -> 0.016486077 | ... Z94: =Z36/Z11 -> 0.014893633
A95: =A94 -> NHL NTE 240 | G95: =G88-(G15-G41)/G11 -> 0 | H95: =H88-(H15-H41)/H11 -> 0 | I95: =I88-(I15-I41)/I11 -> 0 | J95: =J88-(J15-J41)/J11 -> 0 | K95: =K88-(K15-K41)/K11 -> 0 | L95: =L88-(L15-L41)/L11 -> 0 | M95: =M88-(M15-M41)/M11 -> 0 | N95: =N88-(N15-N41)/N11 -> 0 | ... Z95: =Z88-(Z15-Z41)/Z11 -> 0
A96: *
A97: *
A98: * | C98: =SUM(F148:Z148,F160:Z160,F179:Z179,AA132) -> #DIV/0! | D98: =Свод!G23 -> Estar ESDE240 (ГПБ К) | E98: =SUMIFS(Производительность!$Y$55:$Y$71,Производительность!$C$55:$C$71,$D98) -> 10 | F98: =$F$2 -> лет
A99: *
A100: =D98 -> Estar ESDE240 (ГПБ К) | D100: =D$1 -> Показатель | E100: =E$1 -> Ед. изм. | F100: =F$1 -> 0 | G100: =G$1 -> 1 | H100: =H$1 -> 2 | I100: =I$1 -> 3 | J100: =J$1 -> 4 | K100: =K$1 -> 5 | ... Z100: =Z$1 -> 20
...

Sheet Производительность
E1: =ТСО!G2 -> 2027 | F1: =ТСО!H2 -> 2028 | G1: =ТСО!I2 -> 2029 | H1: =ТСО!J2 -> 2030 | I1: =ТСО!K2 -> 2031 | J1: =ТСО!L2 -> 2032 | K1: =ТСО!M2 -> 2033 | L1: =ТСО!N2 -> 2034 | ... X1: =ТСО!Z2 -> 2046
B2: Производительность по годам эксплуатации
Y3: не удалять | Z3: не удалять | AA3: не удалять | AB3: не удалять | AC3: не удалять
A4: 1 | B4: № | C4: Наименование показателя | D4: Ед. изм. | E4: =ТСО!G1 -> 1 | F4: =ТСО!H1 -> 2 | G4: =ТСО!I1 -> 3 | H4: =ТСО!J1 -> 4 | I4: =ТСО!K1 -> 5 | J4: =ТСО!L1 -> 6 | K4: =ТСО!M1 -> 7 | L4: =ТСО!N1 -> 8 | ... X4: =ТСО!Z1 -> 20 | Z4: средняя
A5: 0 | B5: * | C5: Количество дней в периоде | D5: дней | E5: 365 | F5: =E5 -> 365 | G5: =F5 -> 365 | H5: =G5 -> 365 | I5: =H5 -> 365 | J5: =I5 -> 365 | K5: =J5 -> 365 | L5: =K5 -> 365 | M5: =L5 -> 365 | ... X5: =W5 -> 365
A6: 0 | B6: * | C6: Календарный фонд времени | D6: час. | E6: =E5*24 -> 8760 | F6: =F5*24 -> 8760 | G6: =G5*24 -> 8760 | H6: =H5*24 -> 8760 | I6: =I5*24 -> 8760 | J6: =J5*24 -> 8760 | K6: =K5*24 -> 8760 | L6: =L5*24 -> 8760 | ... X6: =X5*24 -> 8760
A7: =A23 -> 1 | B7: 1 | C7: Расстояние транспортировки | D7: км | E7: 3.0395841 | F7: 3.369823 | G7: 4.0467054 | H7: 3.9059063 | I7: 4.7952058 | J7: 5.3561073 | K7: 4.4191798 | L7: 4.526238 | M7: 5.3840572 | N7: 4.8197555 | O7: 4.7397683 | P7: 5.7368198 | Q7: 5.8316077 | R7: 6.0469833 | S7: 5.9999465 | T7: 5.6103506 | U7: 4.0567755 | V7: 4.6317429 | W7: 5.9728866 | X7: 6.7844023 | Y7: карьер, КП 1.0.1
A8: =A24 -> 1 | C8: =Свод!F23 -> NHL NTE 240 | D8: =D7 -> км | E8: =IF($A8=1,E$7,0) -> 3.0395841 | F8: =IF($A8=1,F$7,0) -> 3.369823 | G8: =IF($A8=1,G$7,0) -> 4.0467054 | H8: =IF($A8=1,H$7,0) -> 3.9059063 | I8: =IF($A8=1,I$7,0) -> 4.7952058 | J8: =IF($A8=1,J$7,0) -> 5.3561073 | K8: =IF($A8=1,K$7,0) -> 4.4191798 | L8: =IF($A8=1,L$7,0) -> 4.526238 | ... X8: =IF($A8=1,X$7,0) -> 6.7844023
A9: =A25 -> 1 | C9: =Свод!G23 -> Estar ESDE240 (ГПБ К) | D9: =D8 -> км | E9: =IF($A9=1,E$7,0) -> 3.0395841 | F9: =IF($A9=1,F$7,0) -> 3.369823 | G9: =IF($A9=1,G$7,0) -> 4.0467054 | H9: =IF($A9=1,H$7,0) -> 3.9059063 | I9: =IF($A9=1,I$7,0) -> 4.7952058 | J9: =IF($A9=1,J$7,0) -> 5.3561073 | K9: =IF($A9=1,K$7,0) -> 4.4191798 | L9: =IF($A9=1,L$7,0) -> 4.526238 | ... X9: =IF($A9=1,X$7,0) -> 6.7844023
A10: =A26 -> 1 | C10: =Свод!H23 -> SANY SET240S | D10: =D9 -> км | E10: =IF($A10=1,E$7,0) -> 3.0395841 | F10: =IF($A10=1,F$7,0) -> 3.369823 | G10: =IF($A10=1,G$7,0) -> 4.0467054 | H10: =IF($A10=1,H$7,0) -> 3.9059063 | I10: =IF($A10=1,I$7,0) -> 4.7952058 | J10: =IF($A10=1,J$7,0) -> 5.3561073 | K10: =IF($A10=1,K$7,0) -> 4.4191798 | L10: =IF($A10=1,L$7,0) -> 4.526238 | ... X10: =IF($A10=1,X$7,0) -> 6.7844023
A11: =A27 -> 1 | C11: =Свод!I23 -> TZCO TZE240 | D11: =D10 -> км | E11: =IF($A11=1,E$7,0) -> 3.0395841 | F11: =IF($A11=1,F$7,0) -> 3.369823 | G11: =IF($A11=1,G$7,0) -> 4.0467054 | H11: =IF($A11=1,H$7,0) -> 3.9059063 | I11: =IF($A11=1,I$7,0) -> 4.7952058 | J11: =IF($A11=1,J$7,0) -> 5.3561073 | K11: =IF($A11=1,K$7,0) -> 4.4191798 | L11: =IF($A11=1,L$7,0) -> 4.526238 | ... X11: =IF($A11=1,X$7,0) -> 6.7844023
A12: =A28 -> 1 | C12: =Свод!J23 -> БелАЗ 7531 (ГПФК) | D12: =D11 -> км | E12: =IF($A12=1,E$7,0) -> 3.0395841 | F12: =IF($A12=1,F$7,0) -> 3.369823 | G12: =IF($A12=1,G$7,0) -> 4.0467054 | H12: =IF($A12=1,H$7,0) -> 3.9059063 | I12: =IF($A12=1,I$7,0) -> 4.7952058 | J12: =IF($A12=1,J$7,0) -> 5.3561073 | K12: =IF($A12=1,K$7,0) -> 4.4191798 | L12: =IF($A12=1,L$7,0) -> 4.526238 | ... X12: =IF($A12=1,X$7,0) -> 6.7844023
A13: =A29 -> 1 | C13: =Свод!K23 -> XCMG 240 | D13: =D12 -> км | E13: =IF($A13=1,E$7,0) -> 3.0395841 | F13: =IF($A13=1,F$7,0) -> 3.369823 | G13: =IF($A13=1,G$7,0) -> 4.0467054 | H13: =IF($A13=1,H$7,0) -> 3.9059063 | I13: =IF($A13=1,I$7,0) -> 4.7952058 | J13: =IF($A13=1,J$7,0) -> 5.3561073 | K13: =IF($A13=1,K$7,0) -> 4.4191798 | L13: =IF($A13=1,L$7,0) -> 4.526238 | ... X13: =IF($A13=1,X$7,0) -> 6.7844023
A14: =A30 -> 1 | C14: =Свод!L23 -> БелАЗ 7531 (БТЛ) | D14: =D13 -> км | E14: =IF($A14=1,E$7,0) -> 3.0395841 | F14: =IF($A14=1,F$7,0) -> 3.369823 | G14: =IF($A14=1,G$7,0) -> 4.0467054 | H14: =IF($A14=1,H$7,0) -> 3.9059063 | I14: =IF($A14=1,I$7,0) -> 4.7952058 | J14: =IF($A14=1,J$7,0) -> 5.3561073 | K14: =IF($A14=1,K$7,0) -> 4.4191798 | L14: =IF($A14=1,L$7,0) -> 4.526238 | ... X14: =IF($A14=1,X$7,0) -> 6.7844023
A15: =A31 -> 0 | C15: =Свод!M23 -> 0 | D15: =D14 -> км | E15: =IF($A15=1,E$7,0) -> 0 | F15: =IF($A15=1,F$7,0) -> 0 | G15: =IF($A15=1,G$7,0) -> 0 | H15: =IF($A15=1,H$7,0) -> 0 | I15: =IF($A15=1,I$7,0) -> 0 | J15: =IF($A15=1,J$7,0) -> 0 | K15: =IF($A15=1,K$7,0) -> 0 | L15: =IF($A15=1,L$7,0) -> 0 | ... X15: =IF($A15=1,X$7,0) -> 0
A16: =A32 -> 0 | C16: =Свод!N23 -> 0 | D16: =D15 -> км | E16: =IF($A16=1,E$7,0) -> 0 | F16: =IF($A16=1,F$7,0) -> 0 | G16: =IF($A16=1,G$7,0) -> 0 | H16: =IF($A16=1,H$7,0) -> 0 | I16: =IF($A16=1,I$7,0) -> 0 | J16: =IF($A16=1,J$7,0) -> 0 | K16: =IF($A16=1,K$7,0) -> 0 | L16: =IF($A16=1,L$7,0) -> 0 | ... X16: =IF($A16=1,X$7,0) -> 0
A17: =A33 -> 0 | C17: =Свод!O23 -> 0 | D17: =D16 -> км | E17: =IF($A17=1,E$7,0) -> 0 | F17: =IF($A17=1,F$7,0) -> 0 | G17: =IF($A17=1,G$7,0) -> 0 | H17: =IF($A17=1,H$7,0) -> 0 | I17: =IF($A17=1,I$7,0) -> 0 | J17: =IF($A17=1,J$7,0) -> 0 | K17: =IF($A17=1,K$7,0) -> 0 | L17: =IF($A17=1,L$7,0) -> 0 | ... X17: =IF($A17=1,X$7,0) -> 0
A18: =A34 -> 0 | C18: =Свод!P23 -> 0 | D18: =D17 -> км | E18: =IF($A18=1,E$7,0) -> 0 | F18: =IF($A18=1,F$7,0) -> 0 | G18: =IF($A18=1,G$7,0) -> 0 | H18: =IF($A18=1,H$7,0) -> 0 | I18: =IF($A18=1,I$7,0) -> 0 | J18: =IF($A18=1,J$7,0) -> 0 | K18: =IF($A18=1,K$7,0) -> 0 | L18: =IF($A18=1,L$7,0) -> 0 | ... X18: =IF($A18=1,X$7,0) -> 0
A19: =A35 -> 0 | C19: =Свод!Q23 -> 0 | D19: =D18 -> км | E19: =IF($A19=1,E$7,0) -> 0 | F19: =IF($A19=1,F$7,0) -> 0 | G19: =IF($A19=1,G$7,0) -> 0 | H19: =IF($A19=1,H$7,0) -> 0 | I19: =IF($A19=1,I$7,0) -> 0 | J19: =IF($A19=1,J$7,0) -> 0 | K19: =IF($A19=1,K$7,0) -> 0 | L19: =IF($A19=1,L$7,0) -> 0 | ... X19: =IF($A19=1,X$7,0) -> 0
A20: =A36 -> 0 | C20: =Свод!R23 -> 0 | D20: =D19 -> км | E20: =IF($A20=1,E$7,0) -> 0 | F20: =IF($A20=1,F$7,0) -> 0 | G20: =IF($A20=1,G$7,0) -> 0 | H20: =IF($A20=1,H$7,0) -> 0 | I20: =IF($A20=1,I$7,0) -> 0 | J20: =IF($A20=1,J$7,0) -> 0 | K20: =IF($A20=1,K$7,0) -> 0 | L20: =IF($A20=1,L$7,0) -> 0 | ... X20: =IF($A20=1,X$7,0) -> 0
A21: =A37 -> 0 | C21: =Свод!S23 -> 0 | D21: =D20 -> км | E21: =IF($A21=1,E$7,0) -> 0 | F21: =IF($A21=1,F$7,0) -> 0 | G21: =IF($A21=1,G$7,0) -> 0 | H21: =IF($A21=1,H$7,0) -> 0 | I21: =IF($A21=1,I$7,0) -> 0 | J21: =IF($A21=1,J$7,0) -> 0 | K21: =IF($A21=1,K$7,0) -> 0 | L21: =IF($A21=1,L$7,0) -> 0 | ... X21: =IF($A21=1,X$7,0) -> 0
A22: =A38 -> 0 | C22: =Свод!T23 -> 0 | D22: =D21 -> км | E22: =IF($A22=1,E$7,0) -> 0 | F22: =IF($A22=1,F$7,0) -> 0 | G22: =IF($A22=1,G$7,0) -> 0 | H22: =IF($A22=1,H$7,0) -> 0 | I22: =IF($A22=1,I$7,0) -> 0 | J22: =IF($A22=1,J$7,0) -> 0 | K22: =IF($A22=1,K$7,0) -> 0 | L22: =IF($A22=1,L$7,0) -> 0 | ... X22: =IF($A22=1,X$7,0) -> 0
A23: 1 | B23: =B7+1 -> 2 | C23: Грузоподъемность | Z23: груженый | AA23: порожний | AB23: футеровка | AC23: номинал
A24: =IF(MAX(E24:P24)=0,0,1) -> 1 | C24: =C8 -> NHL NTE 240 | D24: т | E24: =AC24 -> 227.8 | F24: =E24 -> 227.8 | G24: =F24 -> 227.8 | H24: =G24 -> 227.8 | I24: =H24 -> 227.8 | J24: =I24 -> 227.8 | K24: =J24 -> 227.8 | L24: =K24 -> 227.8 | M24: =L24 -> 227.8 | ... X24: =W24 -> 227.8 | Y24: см. Загрузка | Z24: 236 | AB24: 8.2 | AC24: =Z24-AA24-AB24 -> 227.8
A25: =IF(MAX(E25:P25)=0,0,1) -> 1 | C25: =C9 -> Estar ESDE240 (ГПБ К) | D25: =D24 -> т | E25: =AC25 -> 211.392 | F25: =E25 -> 211.392 | G25: =F25 -> 211.392 | H25: =G25 -> 211.392 | I25: =H25 -> 211.392 | J25: =I25 -> 211.392 | K25: =J25 -> 211.392 | L25: =K25 -> 211.392 | M25: =L25 -> 211.392 | ... X25: =W25 -> 211.392 | Y25: см. Загрузка | Z25: =ESDE240!D9 -> 220 | AB25: 8.608 | AC25: =Z25-AA25-AB25 -> 211.392
A26: =IF(MAX(E26:P26)=0,0,1) -> 1 | C26: =C10 -> SANY SET240S | D26: =D25 -> т | E26: =AC26 -> 216.362 | F26: =E26 -> 216.362 | G26: =F26 -> 216.362 | H26: =G26 -> 216.362 | I26: =H26 -> 216.362 | J26: =I26 -> 216.362 | K26: =J26 -> 216.362 | L26: =K26 -> 216.362 | M26: =L26 -> 216.362 | ... X26: =W26 -> 216.362 | Y26: см. Загрузка | Z26: 390 | AA26: =170-4.8 -> 165.2 | AB26: =Загрузка!Y68/1000 -> 8.438 | AC26: =Z26-AA26-AB26 -> 216.362
A27: =IF(MAX(E27:P27)=0,0,1) -> 1 | C27: =C11 -> TZCO TZE240 | D27: =D26 -> т | E27: =AC27 -> 222 | F27: =E27 -> 222 | G27: =F27 -> 222 | H27: =G27 -> 222 | I27: =H27 -> 222 | J27: =I27 -> 222 | K27: =J27 -> 222 | L27: =K27 -> 222 | M27: =L27 -> 222 | ... X27: =W27 -> 222 | Y27: см. Загрузка | Z27: =Загрузка!E104/1000 -> 395 | AA27: =Загрузка!E103/1000 -> 165 | AB27: =Загрузка!E106/1000 -> 8 | AC27: =Z27-AA27-AB27 -> 222
A28: =IF(MAX(E28:P28)=0,0,1) -> 1 | C28: =C12 -> БелАЗ 7531 (ГПФК) | D28: =D27 -> т | E28: =AC28 -> 231 | F28: =E28 -> 231 | G28: =F28 -> 231 | H28: =G28 -> 231 | I28: =H28 -> 231 | J28: =I28 -> 231 | K28: =J28 -> 231 | L28: =K28 -> 231 | M28: =L28 -> 231 | ... X28: =W28 -> 231 | Z28: =БелАЗ!E9 -> 240 | AB28: 9 | AC28: =Z28-AA28-AB28 -> 231
A29: =IF(MAX(E29:P29)=0,0,1) -> 1 | C29: =C13 -> XCMG 240 | D29: =D28 -> т | E29: =AC29 -> 211.392 | F29: =E29 -> 211.392 | G29: =F29 -> 211.392 | H29: =G29 -> 211.392 | I29: =H29 -> 211.392 | J29: =I29 -> 211.392 | K29: =J29 -> 211.392 | L29: =K29 -> 211.392 | M29: =L29 -> 211.392 | ... X29: =W29 -> 211.392 | Z29: =Z25 -> 220 | AB29: =AB25 -> 8.608 | AC29: =Z29-AA29-AB29 -> 211.392
A30: =IF(MAX(E30:P30)=0,0,1) -> 1 | C30: =C14 -> БелАЗ 7531 (БТЛ) | D30: =D29 -> т | E30: =AC30 -> 231 | F30: =E30 -> 231 | G30: =F30 -> 231 | H30: =G30 -> 231 | I30: =H30 -> 231 | J30: =I30 -> 231 | K30: =J30 -> 231 | L30: =K30 -> 231 | M30: =L30 -> 231 | ... X30: =W30 -> 231 | Z30: =Z28 -> 240 | AB30: =AB28 -> 9 | AC30: =Z30-AA30-AB30 -> 231
A31: =IF(MAX(E31:P31)=0,0,1) -> 0 | C31: =C15 -> 0 | D31: =D30 -> т | F31: =E31 -> 0 | G31: =F31 -> 0 | H31: =G31 -> 0 | I31: =H31 -> 0 | J31: =I31 -> 0 | K31: =J31 -> 0 | L31: =K31 -> 0 | M31: =L31 -> 0 | ... X31: =W31 -> 0 | AC31: =Z31-AA31-AB31 -> 0
A32: =IF(MAX(E32:P32)=0,0,1) -> 0 | C32: =C16 -> 0 | D32: =D31 -> т | F32: =E32 -> 0 | G32: =F32 -> 0 | H32: =G32 -> 0 | I32: =H32 -> 0 | J32: =I32 -> 0 | K32: =J32 -> 0 | L32: =K32 -> 0 | M32: =L32 -> 0 | ... X32: =W32 -> 0 | AC32: =Z32-AA32-AB32 -> 0
A33: =IF(MAX(E33:P33)=0,0,1) -> 0 | C33: =C17 -> 0 | D33: =D32 -> т | F33: =E33 -> 0 | G33: =F33 -> 0 | H33: =G33 -> 0 | I33: =H33 -> 0 | J33: =I33 -> 0 | K33: =J33 -> 0 | L33: =K33 -> 0 | M33: =L33 -> 0 | ... X33: =W33 -> 0 | AC33: =Z33-AA33-AB33 -> 0
A34: =IF(MAX(E34:P34)=0,0,1) -> 0 | C34: =C18 -> 0 | D34: =D33 -> т | F34: =E34 -> 0 | G34: =F34 -> 0 | H34: =G34 -> 0 | I34: =H34 -> 0 | J34: =I34 -> 0 | K34: =J34 -> 0 | L34: =K34 -> 0 | M34: =L34 -> 0 | ... X34: =W34 -> 0 | AC34: =Z34-AA34-AB34 -> 0
A35: =IF(MAX(E35:P35)=0,0,1) -> 0 | C35: =C19 -> 0 | D35: =D34 -> т | F35: =E35 -> 0 | G35: =F35 -> 0 | H35: =G35 -> 0 | I35: =H35 -> 0 | J35: =I35 -> 0 | K35: =J35 -> 0 | L35: =K35 -> 0 | M35: =L35 -> 0 | ... X35: =W35 -> 0 | AC35: =Z35-AA35-AB35 -> 0
A36: =IF(MAX(E36:P36)=0,0,1) -> 0 | C36: =C20 -> 0 | D36: =D35 -> т | F36: =E36 -> 0 | G36: =F36 -> 0 | H36: =G36 -> 0 | I36: =H36 -> 0 | J36: =I36 -> 0 | K36: =J36 -> 0 | L36: =K36 -> 0 | M36: =L36 -> 0 | ... X36: =W36 -> 0 | AC36: =Z36-AA36-AB36 -> 0
A37: =IF(MAX(E37:P37)=0,0,1) -> 0 | C37: =C21 -> 0 | D37: =D36 -> т | F37: =E37 -> 0 | G37: =F37 -> 0 | H37: =G37 -> 0 | I37: =H37 -> 0 | J37: =I37 -> 0 | K37: =J37 -> 0 | L37: =K37 -> 0 | M37: =L37 -> 0 | ... X37: =W37 -> 0 | AC37: =Z37-AA37-AB37 -> 0
A38: =IF(MAX(E38:P38)=0,0,1) -> 0 | C38: =C22 -> 0 | D38: =D37 -> т | F38: =E38 -> 0 | G38: =F38 -> 0 | H38: =G38 -> 0 | I38: =H38 -> 0 | J38: =I38 -> 0 | K38: =J38 -> 0 | L38: =K38 -> 0 | M38: =L38 -> 0 | ... X38: =W38 -> 0 | AC38: =Z38-AA38-AB38 -> 0
A39: =A23 -> 1 | B39: =B23+1 -> 3 | C39: КИГ
A40: =A24 -> 1 | C40: =C24 -> NHL NTE 240 | D40: коэфф. | E40: ='Факт NTE'!D7 -> 0.98371378 | F40: =E40 -> 0.98371378 | G40: =F40 -> 0.98371378 | H40: =G40 -> 0.98371378 | I40: =H40 -> 0.98371378 | J40: =I40 -> 0.98371378 | K40: =J40 -> 0.98371378 | L40: =K40 -> 0.98371378 | M40: =L40 -> 0.98371378 | ... X40: =W40 -> 0.98371378 | Y40: факт NTE c WK-35 (ПК 2025)
A41: =A25 -> 1 | C41: =C25 -> Estar ESDE240 (ГПБ К) | D41: =D40 -> коэфф. | E41: =E40 -> 0.98371378 | F41: =E41 -> 0.98371378 | G41: =F41 -> 0.98371378 | H41: =G41 -> 0.98371378 | I41: =H41 -> 0.98371378 | J41: =I41 -> 0.98371378 | K41: =J41 -> 0.98371378 | L41: =K41 -> 0.98371378 | M41: =L41 -> 0.98371378 | ... X41: =W41 -> 0.98371378 | Y41: = NTE
A42: =A26 -> 1 | C42: =C26 -> SANY SET240S | D42: =D41 -> коэфф. | E42: =E41 -> 0.98371378 | F42: =E42 -> 0.98371378 | G42: =F42 -> 0.98371378 | H42: =G42 -> 0.98371378 | I42: =H42 -> 0.98371378 | J42: =I42 -> 0.98371378 | K42: =J42 -> 0.98371378 | L42: =K42 -> 0.98371378 | M42: =L42 -> 0.98371378 | ... X42: =W42 -> 0.98371378 | Y42: = NTE
A43: =A27 -> 1 | C43: =C27 -> TZCO TZE240 | D43: =D42 -> коэфф. | E43: =E42 -> 0.98371378 | F43: =E43 -> 0.98371378 | G43: =F43 -> 0.98371378 | H43: =G43 -> 0.98371378 | I43: =H43 -> 0.98371378 | J43: =I43 -> 0.98371378 | K43: =J43 -> 0.98371378 | L43: =K43 -> 0.98371378 | M43: =L43 -> 0.98371378 | ... X43: =W43 -> 0.98371378 | Y43: = NTE
A44: =A28 -> 1 | C44: =C28 -> БелАЗ 7531 (ГПФК) | D44: =D43 -> коэфф. | E44: =E43 -> 0.98371378 | F44: =E44 -> 0.98371378 | G44: =F44 -> 0.98371378 | H44: =G44 -> 0.98371378 | I44: =H44 -> 0.98371378 | J44: =I44 -> 0.98371378 | K44: =J44 -> 0.98371378 | L44: =K44 -> 0.98371378 | M44: =L44 -> 0.98371378 | ... X44: =W44 -> 0.98371378 | Y44: = NTE
A45: =A29 -> 1 | C45: =C29 -> XCMG 240 | D45: =D44 -> коэфф. | E45: =E44 -> 0.98371378 | F45: =E45 -> 0.98371378 | G45: =F45 -> 0.98371378 | H45: =G45 -> 0.98371378 | I45: =H45 -> 0.98371378 | J45: =I45 -> 0.98371378 | K45: =J45 -> 0.98371378 | L45: =K45 -> 0.98371378 | M45: =L45 -> 0.98371378 | ... X45: =W45 -> 0.98371378 | Y45: = NTE
A46: =A30 -> 1 | C46: =C30 -> БелАЗ 7531 (БТЛ) | D46: =D45 -> коэфф. | E46: =E45 -> 0.98371378 | F46: =E46 -> 0.98371378 | G46: =F46 -> 0.98371378 | H46: =G46 -> 0.98371378 | I46: =H46 -> 0.98371378 | J46: =I46 -> 0.98371378 | K46: =J46 -> 0.98371378 | L46: =K46 -> 0.98371378 | M46: =L46 -> 0.98371378 | ... X46: =W46 -> 0.98371378 | Y46: = NTE
A47: =A31 -> 0 | C47: =C31 -> 0 | D47: =D46 -> коэфф. | F47: =E47 -> 0 | G47: =F47 -> 0 | H47: =G47 -> 0 | I47: =H47 -> 0 | J47: =I47 -> 0 | K47: =J47 -> 0 | L47: =K47 -> 0 | M47: =L47 -> 0 | ... X47: =W47 -> 0
A48: =A32 -> 0 | C48: =C32 -> 0 | D48: =D47 -> коэфф. | F48: =E48 -> 0 | G48: =F48 -> 0 | H48: =G48 -> 0 | I48: =H48 -> 0 | J48: =I48 -> 0 | K48: =J48 -> 0 | L48: =K48 -> 0 | M48: =L48 -> 0 | ... X48: =W48 -> 0
A49: =A33 -> 0 | C49: =C33 -> 0 | D49: =D48 -> коэфф. | F49: =E49 -> 0 | G49: =F49 -> 0 | H49: =G49 -> 0 | I49: =H49 -> 0 | J49: =I49 -> 0 | K49: =J49 -> 0 | L49: =K49 -> 0 | M49: =L49 -> 0 | ... X49: =W49 -> 0
A50: =A34 -> 0 | C50: =C34 -> 0 | D50: =D49 -> коэфф. | F50: =E50 -> 0 | G50: =F50 -> 0 | H50: =G50 -> 0 | I50: =H50 -> 0 | J50: =I50 -> 0 | K50: =J50 -> 0 | L50: =K50 -> 0 | M50: =L50 -> 0 | ... X50: =W50 -> 0
A51: =A35 -> 0 | C51: =C35 -> 0 | D51: =D50 -> коэфф. | F51: =E51 -> 0 | G51: =F51 -> 0 | H51: =G51 -> 0 | I51: =H51 -> 0 | J51: =I51 -> 0 | K51: =J51 -> 0 | L51: =K51 -> 0 | M51: =L51 -> 0 | ... X51: =W51 -> 0
A52: =A36 -> 0 | C52: =C36 -> 0 | D52: =D51 -> коэфф. | F52: =E52 -> 0 | G52: =F52 -> 0 | H52: =G52 -> 0 | I52: =H52 -> 0 | J52: =I52 -> 0 | K52: =J52 -> 0 | L52: =K52 -> 0 | M52: =L52 -> 0 | ... X52: =W52 -> 0
A53: =A37 -> 0 | C53: =C37 -> 0 | D53: =D52 -> коэфф. | F53: =E53 -> 0 | G53: =F53 -> 0 | H53: =G53 -> 0 | I53: =H53 -> 0 | J53: =I53 -> 0 | K53: =J53 -> 0 | L53: =K53 -> 0 | M53: =L53 -> 0 | ... X53: =W53 -> 0
A54: =A38 -> 0 | C54: =C38 -> 0 | D54: =D53 -> коэфф. | F54: =E54 -> 0 | G54: =F54 -> 0 | H54: =G54 -> 0 | I54: =H54 -> 0 | J54: =I54 -> 0 | K54: =J54 -> 0 | L54: =K54 -> 0 | M54: =L54 -> 0 | ... X54: =W54 -> 0
A55: =A39 -> 1 | B55: =B39+1 -> 4 | C55: КТГ | Y55: лет
A56: =A40 -> 1 | C56: =C40 -> NHL NTE 240 | D56: коэфф. | E56: ='NHL NTE240'!E12 -> 0.93755029 | F56: ='NHL NTE240'!F12 -> 0.93038071 | G56: ='NHL NTE240'!G12 -> 0.92090265 | H56: ='NHL NTE240'!H12 -> 0.90840582 | I56: ='NHL NTE240'!I12 -> 0.93333289 | J56: ='NHL NTE240'!J12 -> 0.92172393 | K56: ='NHL NTE240'!K12 -> 0.93126858 | L56: ='NHL NTE240'!L12 -> 0.91113604 | ... X56: ='NHL NTE240'!X12 -> 0.92201249 | Y56: =COUNT(E56:X56) -> 20 | Z56: =SUM(E56:X56)/Y56 -> 0.92288816 | AA56: данные поставщика от 27.07.2026
A57: =A41 -> 1 | C57: =C41 -> Estar ESDE240 (ГПБ К) | D57: =D56 -> коэфф. | E57: =ESDE240!E12 -> 0.91162481 | F57: =ESDE240!F12 -> 0.89608701 | G57: =ESDE240!G12 -> 0.84869673 | H57: =ESDE240!H12 -> 0.80563483 | I57: =ESDE240!I12 -> 0.89852867 | J57: =ESDE240!J12 -> 0.8220605 | K57: =ESDE240!K12 -> 0.88942796 | L57: =ESDE240!L12 -> 0.81118404 | ... N57: =ESDE240!N12 -> 0.83393582 | Y57: =COUNT(E57:X57) -> 10 | Z57: =SUM(E57:X57)/Y57 -> 0.8573313 | AA57: данные поставщика от 24.07.2026
A58: =A42 -> 1 | C58: =C42 -> SANY SET240S | D58: =D57 -> коэфф. | E58: =SANY!E12 -> 0.9357084 | F58: =SANY!F12 -> 0.90263508 | G58: =SANY!G12 -> 0.86578831 | H58: =SANY!H12 -> 0.90352296 | I58: =SANY!I12 -> 0.85025051 | J58: =SANY!J12 -> 0.90352296 | K58: =SANY!K12 -> 0.86578831 | L58: =SANY!L12 -> 0.90352296 | ... P58: =SANY!P12 -> 0.87133752 | Y58: =COUNT(E58:X58) -> 12 | Z58: =SUM(E58:X58)/Y58 -> 0.88337931 | AA58: данные поставщика от 16.07.2026
A59: =A43 -> 1 | C59: =C43 -> TZCO TZE240 | D59: =D58 -> коэфф. | E59: =TZCO!E12 -> 0.90962709 | F59: =TZCO!F12 -> 0.88376776 | G59: =TZCO!G12 -> 0.77400431 | H59: =TZCO!H12 -> 0.88376776 | I59: =TZCO!I12 -> 0.90962709 | J59: =TZCO!J12 -> 0.74814498 | K59: =TZCO!K12 -> 0.90962709 | L59: =TZCO!L12 -> 0.88376776 | Y59: =COUNT(E59:X59) -> 8 | Z59: =SUM(E59:X59)/Y59 -> 0.86279173 | AA59: данные поставщика от 15.07.2026
A60: =A44 -> 1 | C60: =C44 -> БелАЗ 7531 (ГПФК) | D60: =D59 -> коэфф. | E60: =БелАЗ!E12 -> 0.90830416 | F60: =БелАЗ!F12 -> 0.88577435 | G60: =БелАЗ!G12 -> 0.86468734 | H60: =БелАЗ!H12 -> 0.87460194 | I60: =БелАЗ!I12 -> 0.88129799 | J60: =БелАЗ!J12 -> 0.84567204 | K60: =БелАЗ!K12 -> 0.89713174 | L60: =БелАЗ!L12 -> 0.85462477 | ... N60: =БелАЗ!N12 -> 0.86135781 | Y60: =COUNT(E60:X60) -> 10 | Z60: =SUM(E60:X60)/Y60 -> 0.87156467 | AA60: данные поставщика от 09.07.2026
A61: =A45 -> 1 | C61: =C45 -> XCMG 240 | D61: =D60 -> коэфф. | Y61: =COUNT(E61:X61) -> 0 | Z61: =SUM(E61:X61)/Y61 -> #DIV/0! | AA61: нет данных
A62: =A46 -> 1 | C62: =C46 -> БелАЗ 7531 (БТЛ) | D62: =D61 -> коэфф. | E62: =БелАЗ_Б!E12 -> 0.92956037 | F62: =БелАЗ_Б!F12 -> 0.90792065 | G62: =БелАЗ_Б!G12 -> 0.89941186 | H62: =БелАЗ_Б!H12 -> 0.88050754 | I62: =БелАЗ_Б!I12 -> 0.90115061 | J62: =БелАЗ_Б!J12 -> 0.87025999 | K62: =БелАЗ_Б!K12 -> 0.85058935 | L62: =БелАЗ_Б!L12 -> 0.89171695 | ... N62: =БелАЗ_Б!N12 -> 0.85228054 | Y62: =COUNT(E62:X62) -> 10 | Z62: =SUM(E62:X62)/Y62 -> 0.88411536 | AA62: данные поставщика от 22.07.2026
A63: =A47 -> 0 | C63: =C47 -> 0 | D63: =D62 -> коэфф. | Y63: =COUNT(E63:X63) -> 0 | Z63: =SUM(E63:X63)/Y63 -> #DIV/0!
A64: =A48 -> 0 | C64: =C48 -> 0 | D64: =D63 -> коэфф. | Y64: =COUNT(E64:X64) -> 0 | Z64: =SUM(E64:X64)/Y64 -> #DIV/0!
A65: =A49 -> 0 | C65: =C49 -> 0 | D65: =D64 -> коэфф. | Y65: =COUNT(E65:X65) -> 0 | Z65: =SUM(E65:X65)/Y65 -> #DIV/0!
A66: =A50 -> 0 | C66: =C50 -> 0 | D66: =D65 -> коэфф. | Y66: =COUNT(E66:X66) -> 0 | Z66: =SUM(E66:X66)/Y66 -> #DIV/0!
A67: =A51 -> 0 | C67: =C51 -> 0 | D67: =D66 -> коэфф. | Y67: =COUNT(E67:X67) -> 0 | Z67: =SUM(E67:X67)/Y67 -> #DIV/0!
A68: =A52 -> 0 | C68: =C52 -> 0 | D68: =D67 -> коэфф. | Y68: =COUNT(E68:X68) -> 0 | Z68: =SUM(E68:X68)/Y68 -> #DIV/0!
A69: =A53 -> 0 | C69: =C53 -> 0 | D69: =D68 -> коэфф. | Y69: =COUNT(E69:X69) -> 0 | Z69: =SUM(E69:X69)/Y69 -> #DIV/0!
A70: =A54 -> 0 | C70: =C54 -> 0 | D70: =D69 -> коэфф. | Y70: =COUNT(E70:X70) -> 0 | Z70: =SUM(E70:X70)/Y70 -> #DIV/0!
A71: =A55 -> 1 | B71: * | C71: Время технической готовности
A72: =A56 -> 1 | C72: =C56 -> NHL NTE 240 | D72: час. | E72: =E$6*E56 -> 8212.9406 | F72: =F$6*F56 -> 8150.135 | G72: =G$6*G56 -> 8067.1072 | H72: =H$6*H56 -> 7957.635 | I72: =I$6*I56 -> 8175.9961 | J72: =J$6*J56 -> 8074.3017 | K72: =K$6*K56 -> 8157.9128 | L72: =L$6*L56 -> 7981.5517 | ... X72: =X$6*X56 -> 8076.8294
A73: =A57 -> 1 | C73: =C57 -> Estar ESDE240 (ГПБ К) | D73: =D72 -> час. | E73: =E$6*E57 -> 7985.8333 | F73: =F$6*F57 -> 7849.7222 | G73: =G$6*G57 -> 7434.5833 | H73: =H$6*H57 -> 7057.3611 | I73: =I$6*I57 -> 7871.1111 | J73: =J$6*J57 -> 7201.25 | K73: =K$6*K57 -> 7791.3889 | L73: =L$6*L57 -> 7105.9722 | ... X73: =X$6*X57 -> 0
A74: =A58 -> 1 | C74: =C58 -> SANY SET240S | D74: =D73 -> час. | E74: =E$6*E58 -> 8196.8056 | F74: =F$6*F58 -> 7907.0833 | G74: =G$6*G58 -> 7584.3056 | H74: =H$6*H58 -> 7914.8611 | I74: =I$6*I58 -> 7448.1944 | J74: =J$6*J58 -> 7914.8611 | K74: =K$6*K58 -> 7584.3056 | L74: =L$6*L58 -> 7914.8611 | ... X74: =X$6*X58 -> 0
A75: =A59 -> 1 | C75: =C59 -> TZCO TZE240 | D75: =D74 -> час. | E75: =E$6*E59 -> 7968.3333 | F75: =F$6*F59 -> 7741.8056 | G75: =G$6*G59 -> 6780.2778 | H75: =H$6*H59 -> 7741.8056 | I75: =I$6*I59 -> 7968.3333 | J75: =J$6*J59 -> 6553.75 | K75: =K$6*K59 -> 7968.3333 | L75: =L$6*L59 -> 7741.8056 | ... X75: =X$6*X59 -> 0
A76: =A60 -> 1 | C76: =C60 -> БелАЗ 7531 (ГПФК) | D76: =D75 -> час. | E76: =E$6*E60 -> 7956.7444 | F76: =F$6*F60 -> 7759.3833 | G76: =G$6*G60 -> 7574.6611 | H76: =H$6*H60 -> 7661.513 | I76: =I$6*I60 -> 7720.1704 | J76: =J$6*J60 -> 7408.087 | K76: =K$6*K60 -> 7858.8741 | L76: =L$6*L60 -> 7486.513 | ... X76: =X$6*X60 -> 0
A77: =A61 -> 1 | C77: =C61 -> XCMG 240 | D77: =D76 -> час. | E77: =E$6*E61 -> 0 | F77: =F$6*F61 -> 0 | G77: =G$6*G61 -> 0 | H77: =H$6*H61 -> 0 | I77: =I$6*I61 -> 0 | J77: =J$6*J61 -> 0 | K77: =K$6*K61 -> 0 | L77: =L$6*L61 -> 0 | ... X77: =X$6*X61 -> 0
A78: =A62 -> 1 | C78: =C62 -> БелАЗ 7531 (БТЛ) | D78: =D77 -> час. | E78: =E$6*E62 -> 8142.9488 | F78: =F$6*F62 -> 7953.3849 | G78: =G$6*G62 -> 7878.8479 | H78: =H$6*H62 -> 7713.246 | I78: =I$6*I62 -> 7894.0794 | J78: =J$6*J62 -> 7623.4775 | K78: =K$6*K62 -> 7451.1627 | L78: =L$6*L62 -> 7811.4405 | ... X78: =X$6*X62 -> 0
A79: =A63 -> 0 | C79: =C63 -> 0 | D79: =D78 -> час. | E79: =E$6*E63 -> 0 | F79: =F$6*F63 -> 0 | G79: =G$6*G63 -> 0 | H79: =H$6*H63 -> 0 | I79: =I$6*I63 -> 0 | J79: =J$6*J63 -> 0 | K79: =K$6*K63 -> 0 | L79: =L$6*L63 -> 0 | ... X79: =X$6*X63 -> 0
A80: =A64 -> 0 | C80: =C64 -> 0 | D80: =D79 -> час. | E80: =E$6*E64 -> 0 | F80: =F$6*F64 -> 0 | G80: =G$6*G64 -> 0 | H80: =H$6*H64 -> 0 | I80: =I$6*I64 -> 0 | J80: =J$6*J64 -> 0 | K80: =K$6*K64 -> 0 | L80: =L$6*L64 -> 0 | ... X80: =X$6*X64 -> 0
A81: =A65 -> 0 | C81: =C65 -> 0 | D81: =D80 -> час. | E81: =E$6*E65 -> 0 | F81: =F$6*F65 -> 0 | G81: =G$6*G65 -> 0 | H81: =H$6*H65 -> 0 | I81: =I$6*I65 -> 0 | J81: =J$6*J65 -> 0 | K81: =K$6*K65 -> 0 | L81: =L$6*L65 -> 0 | ... X81: =X$6*X65 -> 0
A82: =A66 -> 0 | C82: =C66 -> 0 | D82: =D81 -> час. | E82: =E$6*E66 -> 0 | F82: =F$6*F66 -> 0 | G82: =G$6*G66 -> 0 | H82: =H$6*H66 -> 0 | I82: =I$6*I66 -> 0 | J82: =J$6*J66 -> 0 | K82: =K$6*K66 -> 0 | L82: =L$6*L66 -> 0 | ... X82: =X$6*X66 -> 0
A83: =A67 -> 0 | C83: =C67 -> 0 | D83: =D82 -> час. | E83: =E$6*E67 -> 0 | F83: =F$6*F67 -> 0 | G83: =G$6*G67 -> 0 | H83: =H$6*H67 -> 0 | I83: =I$6*I67 -> 0 | J83: =J$6*J67 -> 0 | K83: =K$6*K67 -> 0 | L83: =L$6*L67 -> 0 | ... X83: =X$6*X67 -> 0
A84: =A68 -> 0 | C84: =C68 -> 0 | D84: =D83 -> час. | E84: =E$6*E68 -> 0 | F84: =F$6*F68 -> 0 | G84: =G$6*G68 -> 0 | H84: =H$6*H68 -> 0 | I84: =I$6*I68 -> 0 | J84: =J$6*J68 -> 0 | K84: =K$6*K68 -> 0 | L84: =L$6*L68 -> 0 | ... X84: =X$6*X68 -> 0
... A86: =A70 -> 0 | C86: =C70 -> 0 | D86: =D85 -> час. | E86: =E$6*E70 -> 0 | F86: =F$6*F70 -> 0 | G86: =G$6*G70 -> 0 | H86: =H$6*H70 -> 0 | I86: =I$6*I70 -> 0 | J86: =J$6*J70 -> 0 | K86: =K$6*K70 -> 0 | L86: =L$6*L70 -> 0 | ... X86: =X$6*X70 -> 0
A87: =A71 -> 1 | B87: =B55+1 -> 5 | C87: Ежесменные регламентные простои (пересменка, обед, личные надобности)
A88: =A72 -> 1 | C88: =C72 -> NHL NTE 240 | D88: мин/см | E88: =SUM(Простои!M9:O9) -> 50 | F88: =E88 -> 50 | G88: =F88 -> 50 | H88: =G88 -> 50 | I88: =H88 -> 50 | J88: =I88 -> 50 | K88: =J88 -> 50 | L88: =K88 -> 50 | M88: =L88 -> 50 | ... X88: =W88 -> 50
A89: =A73 -> 1 | C89: =C73 -> Estar ESDE240 (ГПБ К) | D89: =D88 -> мин/см | E89: =SUM(Простои!M10:O10) -> 50 | F89: =E89 -> 50 | G89: =F89 -> 50 | H89: =G89 -> 50 | I89: =H89 -> 50 | J89: =I89 -> 50 | K89: =J89 -> 50 | L89: =K89 -> 50 | M89: =L89 -> 50 | ... X89: =W89 -> 50
A90: =A74 -> 1 | C90: =C74 -> SANY SET240S | D90: =D89 -> мин/см | E90: =SUM(Простои!M11:O11) -> 50 | F90: =E90 -> 50 | G90: =F90 -> 50 | H90: =G90 -> 50 | I90: =H90 -> 50 | J90: =I90 -> 50 | K90: =J90 -> 50 | L90: =K90 -> 50 | M90: =L90 -> 50 | ... X90: =W90 -> 50
A91: =A75 -> 1 | C91: =C75 -> TZCO TZE240 | D91: =D90 -> мин/см | E91: =SUM(Простои!M12:O12) -> 50 | F91: =E91 -> 50 | G91: =F91 -> 50 | H91: =G91 -> 50 | I91: =H91 -> 50 | J91: =I91 -> 50 | K91: =J91 -> 50 | L91: =K91 -> 50 | M91: =L91 -> 50 | ... X91: =W91 -> 50
A92: =A76 -> 1 | C92: =C76 -> БелАЗ 7531 (ГПФК) | D92: =D91 -> мин/см | E92: =SUM(Простои!M13:O13) -> 50 | F92: =E92 -> 50 | G92: =F92 -> 50 | H92: =G92 -> 50 | I92: =H92 -> 50 | J92: =I92 -> 50 | K92: =J92 -> 50 | L92: =K92 -> 50 | M92: =L92 -> 50 | ... X92: =W92 -> 50
A93: =A77 -> 1 | C93: =C77 -> XCMG 240 | D93: =D92 -> мин/см | E93: =SUM(Простои!M14:O14) -> 50 | F93: =E93 -> 50 | G93: =F93 -> 50 | H93: =G93 -> 50 | I93: =H93 -> 50 | J93: =I93 -> 50 | K93: =J93 -> 50 | L93: =K93 -> 50 | M93: =L93 -> 50 | ... X93: =W93 -> 50
A94: =A78 -> 1 | C94: =C78 -> БелАЗ 7531 (БТЛ) | D94: =D93 -> мин/см | E94: =SUM(Простои!M15:O15) -> 50 | F94: =E94 -> 50 | G94: =F94 -> 50 | H94: =G94 -> 50 | I94: =H94 -> 50 | J94: =I94 -> 50 | K94: =J94 -> 50 | L94: =K94 -> 50 | M94: =L94 -> 50 | ... X94: =W94 -> 50
A95: =A79 -> 0 | C95: =C79 -> 0 | D95: =D94 -> мин/см | E95: =SUM(Простои!M16:O16) -> 0 | F95: =E95 -> 0 | G95: =F95 -> 0 | H95: =G95 -> 0 | I95: =H95 -> 0 | J95: =I95 -> 0 | K95: =J95 -> 0 | L95: =K95 -> 0 | M95: =L95 -> 0 | ... X95: =W95 -> 0
A96: =A80 -> 0 | C96: =C80 -> 0 | D96: =D95 -> мин/см | E96: =SUM(Простои!M17:O17) -> 0 | F96: =E96 -> 0 | G96: =F96 -> 0 | H96: =G96 -> 0 | I96: =H96 -> 0 | J96: =I96 -> 0 | K96: =J96 -> 0 | L96: =K96 -> 0 | M96: =L96 -> 0 | ... X96: =W96 -> 0
A97: =A81 -> 0 | C97: =C81 -> 0 | D97: =D96 -> мин/см | E97: =SUM(Простои!M18:O18) -> 0 | F97: =E97 -> 0 | G97: =F97 -> 0 | H97: =G97 -> 0 | I97: =H97 -> 0 | J97: =I97 -> 0 | K97: =J97 -> 0 | L97: =K97 -> 0 | M97: =L97 -> 0 | ... X97: =W97 -> 0
A98: =A82 -> 0 | C98: =C82 -> 0 | D98: =D97 -> мин/см | E98: =SUM(Простои!M19:O19) -> 0 | F98: =E98 -> 0 | G98: =F98 -> 0 | H98: =G98 -> 0 | I98: =H98 -> 0 | J98: =I98 -> 0 | K98: =J98 -> 0 | L98: =K98 -> 0 | M98: =L98 -> 0 | ... X98: =W98 -> 0
A99: =A83 -> 0 | C99: =C83 -> 0 | D99: =D98 -> мин/см | E99: =SUM(Простои!M20:O20) -> 0 | F99: =E99 -> 0 | G99: =F99 -> 0 | H99: =G99 -> 0 | I99: =H99 -> 0 | J99: =I99 -> 0 | K99: =J99 -> 0 | L99: =K99 -> 0 | M99: =L99 -> 0 | ... X99: =W99 -> 0
A100: =A84 -> 0 | C100: =C84 -> 0 | D100: =D99 -> мин/см | E100: =SUM(Простои!M21:O21) -> 0 | F100: =E100 -> 0 | G100: =F100 -> 0 | H100: =G100 -> 0 | I100: =H100 -> 0 | J100: =I100 -> 0 | K100: =J100 -> 0 | L100: =K100 -> 0 | M100: =L100 -> 0 | ... X100: =W100 -> 0
... A102: =A86 -> 0 | C102: =C86 -> 0 | D102: =D101 -> мин/см | E102: =SUM(Простои!M23:O23) -> 0 | F102: =E102 -> 0 | G102: =F102 -> 0 | H102: =G102 -> 0 | I102: =H102 -> 0 | J102: =I102 -> 0 | K102: =J102 -> 0 | L102: =K102 -> 0 | M102: =L102 -> 0 | ... X102: =W102 -> 0
...

Sheet Загрузка
B2: =Свод!F23 -> NHL NTE 240 | E2: 227.8
B31: =Свод!G23 -> Estar ESDE240 (ГПБ К) | E31: =220-8.608 -> 211.392
B67: =Свод!H23 -> SANY SET240S | E67: =(390-138.2-31.8)-(Y68-L68)/1000 -> 216.362
H68: футеровка стандартный кузов | L68: 4800 | M68: кг | U68: футеровка скальный кузов | Y68: 8438 | Z68: кг
B99: =Свод!I23 -> TZCO TZE240 | E99: =E111/1000 -> 222
C101: п/п | D101: Модель | E101: TZE240
C102: 1 | D102: Ед. измерения | E102: кг
C103: 2 | D103: Масса порожнего самосвала | E103: 165000
C104: 3 | D104: Полная масса самосвала | E104: 395000
C105: 4 | D105: Масса стандартного кузова | E105: 27000
C106: 5 | D106: Масса футеровки кузова, дополнительно | E106: 8000
C107: 6 | D107: Размер шин | E107: 46/90R57
C108: 7 | D108: Масса шин (х6) | E108: 22800
C109: 8 | D109: Масса ободьев колес (x6) | E109: 7800
C110: 9 | D110: Топливный бак 100% | E110: 3740
C111: 10 | D111: Номинальная грузоподъемность (минус футеровка кузова) | E111: =(E104-E103)-E106 -> 222000
C112: 11 | D112: Загрузка 110% от номинальной грузоподъемности (с учетом футеровки кузова) | E112: 244200
C113: 12 | D113: Загрузка 120% от номинальной грузоподъемности. Никогда не превышать полезную нагрузку, свыше (с учетом футеровки кузова) | E113: 266400

Sheet Ресурс
B2: =Свод!H23 -> SANY SET240S | D2: 12 лет
B34: =Свод!I23 -> TZCO TZE240 | D34: 8 лет
B80: =Свод!J23 -> БелАЗ 7531 (ГПФК) | D80: 7 лет
Q81: 900000 | R81: км
Q82: 0.83 | R82: коэффициент
Q84: =Q81*Q82 -> 747000 | R84: км с коэффициентом
S86: =Производительность!E4 -> 1 | T86: =Производительность!F4 -> 2 | U86: =Производительность!G4 -> 3 | V86: =Производительность!H4 -> 4 | W86: =Производительность!I4 -> 5 | X86: =Производительность!J4 -> 6 | Y86: =Производительность!K4 -> 7 | Z86: =Производительность!L4 -> 8 | ... AB86: =Производительность!N4 -> 10
Q87: Пробег НИ | R87: тыс. км | S87: =Производительность!E284 -> 101036.69 | T87: =Производительность!F284+S87 -> 202972.79 | U87: =Производительность!G284+T87 -> 308911.85 | V87: =Производительность!H284+U87 -> 414995.62 | W87: =Производительность!I284+V87 -> 527901 | X87: =Производительность!J284+W87 -> 639118.01 | Y87: =Производительность!K284+X87 -> 751686.85 | Z87: =Производительность!L284+Y87 -> 859591.8 | AA87: =Производительность!M284+Z87 -> 970482.11 | AB87: =Производительность!N284+AA87 -> 1080971.9
Q88: Пробег НИ_1 | R88: =R87 -> тыс. км | S88: =Производительность_1!E284 -> 101036.69 | T88: =Производительность_1!F284+S88 -> 202972.79 | U88: =Производительность_1!G284+T88 -> 308911.85 | V88: =Производительность_1!H284+U88 -> 414995.62 | W88: =Производительность_1!I284+V88 -> 527901 | X88: =Производительность_1!J284+W88 -> 639118.01 | Y88: =Производительность_1!K284+X88 -> 751686.85 | Z88: =Производительность_1!L284+Y88 -> 859591.8 | AA88: =Производительность_1!M284+Z88 -> 970482.11 | AB88: =Производительность_1!N284+AA88 -> 1080971.9

Sheet Факт NTE
A2: Загрузка, 2025
B4: Грузоподъемность | C4: =Производительность!E24 -> 227.8
B5: Загрузка | D5: 224.09 | E5: 225.09
B7: КИГ | D7: =D5/$C$4 -> 0.98371378 | E7: =E5/$C$4 -> 0.9881036

Sheet Простои
A2: План БСЛ на 2027 (NTE 240)
B3: количество взрывов | C3: 5 | R3: =C3 -> 5 | V3: =R3 -> 5
B5: Простои в смену | Y5: Простои за рейс
Q6: второй год | U6: третий год
B7: взрыв | E7: планируемые (взрыв отдельно) | M7: регламент | Q7: =B7 -> взрыв | U7: =Q7 -> взрыв | Y7: погрузка | AB7: разгрузка | AD7: прочее | AF7: =35*2.8*1.027/1.5*0.9*0.85 -> 51.32946 | AG7: 45
B8: минут | C8: минут/смена | E8: Ожидание зачистки забоя/блока | F8: Перегон | G8: Подкачка шин | H8: Чистка кузова | I8: Протяжка колесных гаек | J8: Заправка | K8: Прочие | M8: обед | N8: пересменка | O8: личные | Q8: =B8 -> минут | R8: =C8 -> минут/смена | S8: +/- 2/1 | U8: =Q8 -> минут | V8: =R8 -> минут/смена | W8: +/- 3/2 | Y8: очередь на погрузку | Z8: установка на погрузку | AA8: загрузка | AB8: ожидание на разгрузке | AC8: разгрузка | AD8: прочее | AE8: тонн в кузове | AF8: кол-во циклов | AG8: погрузка, минут | AM8: подъем | AN8: опускание
A9: =Производительность!C8 -> NHL NTE 240 | B9: 300 | C9: =C$3*B9/(30.5*2) -> 24.590164 | E9: 7 | F9: 1 | G9: 0.8 | H9: 0.5 | I9: 0.49 | J9: 18 | M9: 30 | N9: 10 | O9: 10 | Q9: =B9 -> 300 | R9: =R$3*Q9/(30.5*2) -> 24.590164 | S9: =R9-C9 -> 0 | U9: =Q9-60 -> 240 | V9: =V$3*U9/(30.5*2) -> 19.672131 | W9: =V9-R9 -> -4.9180328 | Y9: 2.5 | Z9: 0.8 | AA9: 3.5 | AB9: 0.3 | AC9: 0.8 | AD9: 0.5 | AE9: =Производительность!E24*Производительность!E40 -> 224.09 | AF9: =AE9/$AF$7 -> 4.365719 | AG9: =ROUNDUP(AF9,0)*$AG$7/60 -> 3.75 | AI9: =SUM(C9,E9:K9,M9:O9) -> 102.38016 | AJ9: =AI9-C9 -> 77.79 | AK9: =AJ9-M9-N9-O9 -> 27.79 | AM9: ='NHL NTE240'!D16 -> 22 | AN9: ='NHL NTE240'!D17 -> 15 | AO9: =(AM9+AN9)/60 -> 0.61666667
A10: =Производительность!C9 -> Estar ESDE240 (ГПБ К) | B10: =B9 -> 300 | C10: =C$3*B10/(30.5*2) -> 24.590164 | E10: =E9 -> 7 | F10: =F9 -> 1 | G10: =G9 -> 0.8 | H10: =H9 -> 0.5 | I10: =I9 -> 0.49 | J10: =J9 -> 18 | M10: =M9 -> 30 | N10: =N9 -> 10 | O10: =O9 -> 10 | Q10: =Q9 -> 300 | R10: =R$3*Q10/(30.5*2) -> 24.590164 | S10: =R10-C10 -> 0 | U10: =U9 -> 240 | V10: =V$3*U10/(30.5*2) -> 19.672131 | W10: =V10-R10 -> -4.9180328 | Y10: =Y9 -> 2.5 | Z10: =Z9 -> 0.8 | AA10: =AA9 -> 3.5 | AB10: =AB9 -> 0.3 | AC10: =AC9 -> 0.8 | AD10: =AD9 -> 0.5 | AE10: =Производительность!E25*Производительность!E41 -> 207.94922 | AF10: =AE10/$AF$7 -> 4.0512646 | AG10: =ROUNDUP(AF10,0)*$AG$7/60 -> 3.75 | AI10: =SUM(C10,E10:K10,M10:O10) -> 102.38016 | AJ10: =AI10-C10 -> 77.79 | AK10: =AJ10-M10-N10-O10 -> 27.79 | AM10: =ESDE240!D16 -> 25 | AN10: =ESDE240!D17 -> 28 | AO10: =(AM10+AN10)/60 -> 0.88333333
A11: =Производительность!C10 -> SANY SET240S | B11: =B10 -> 300 | C11: =C$3*B11/(30.5*2) -> 24.590164 | E11: =E10 -> 7 | F11: =F10 -> 1 | G11: =G10 -> 0.8 | H11: =H10 -> 0.5 | I11: =I10 -> 0.49 | J11: =J10 -> 18 | M11: =M10 -> 30 | N11: =N10 -> 10 | O11: =O10 -> 10 | Q11: =Q10 -> 300 | R11: =R$3*Q11/(30.5*2) -> 24.590164 | S11: =R11-C11 -> 0 | U11: =U10 -> 240 | V11: =V$3*U11/(30.5*2) -> 19.672131 | W11: =V11-R11 -> -4.9180328 | Y11: =Y10 -> 2.5 | Z11: =Z10 -> 0.8 | AA11: =AA10 -> 3.5 | AB11: =AB10 -> 0.3 | AC11: =AC10 -> 0.8 | AD11: =AD10 -> 0.5 | AE11: =Производительность!E26*Производительность!E42 -> 212.83828 | AF11: =AE11/$AF$7 -> 4.1465132 | AG11: =ROUNDUP(AF11,0)*$AG$7/60 -> 3.75 | AI11: =SUM(C11,E11:K11,M11:O11) -> 102.38016 | AJ11: =AI11-C11 -> 77.79 | AK11: =AJ11-M11-N11-O11 -> 27.79 | AM11: =SANY!D16 -> 23 | AN11: =SANY!D17 -> 22 | AO11: =(AM11+AN11)/60 -> 0.75
A12: =Производительность!C11 -> TZCO TZE240 | B12: =B11 -> 300 | C12: =C$3*B12/(30.5*2) -> 24.590164 | E12: =E11 -> 7 | F12: =F11 -> 1 | G12: =G11 -> 0.8 | H12: =H11 -> 0.5 | I12: =I11 -> 0.49 | J12: =J11 -> 18 | M12: =M11 -> 30 | N12: =N11 -> 10 | O12: =O11 -> 10 | Q12: =Q11 -> 300 | R12: =R$3*Q12/(30.5*2) -> 24.590164 | S12: =R12-C12 -> 0 | U12: =U11 -> 240 | V12: =V$3*U12/(30.5*2) -> 19.672131 | W12: =V12-R12 -> -4.9180328 | Y12: =Y11 -> 2.5 | Z12: =Z11 -> 0.8 | AA12: =AA11 -> 3.5 | AB12: =AB11 -> 0.3 | AC12: =AC11 -> 0.8 | AD12: =AD11 -> 0.5 | AE12: =Производительность!E27*Производительность!E43 -> 218.38446 | AF12: =AE12/$AF$7 -> 4.2545638 | AG12: =ROUNDUP(AF12,0)*$AG$7/60 -> 3.75 | AI12: =SUM(C12,E12:K12,M12:O12) -> 102.38016 | AJ12: =AI12-C12 -> 77.79 | AK12: =AJ12-M12-N12-O12 -> 27.79 | AM12: =TZCO!D16 -> 23 | AN12: =TZCO!D17 -> 17 | AO12: =(AM12+AN12)/60 -> 0.66666667
A13: =Производительность!C12 -> БелАЗ 7531 (ГПФК) | B13: =B12 -> 300 | C13: =C$3*B13/(30.5*2) -> 24.590164 | E13: =E12 -> 7 | F13: =F12 -> 1 | G13: =G12 -> 0.8 | H13: =H12 -> 0.5 | I13: =I12 -> 0.49 | J13: =J12 -> 18 | M13: =M12 -> 30 | N13: =N12 -> 10 | O13: =O12 -> 10 | Q13: =Q12 -> 300 | R13: =R$3*Q13/(30.5*2) -> 24.590164 | S13: =R13-C13 -> 0 | U13: =U12 -> 240 | V13: =V$3*U13/(30.5*2) -> 19.672131 | W13: =V13-R13 -> -4.9180328 | Y13: =Y12 -> 2.5 | Z13: =Z12 -> 0.8 | AA13: =AA12 -> 3.5 | AB13: =AB12 -> 0.3 | AC13: =AC12 -> 0.8 | AD13: =AD12 -> 0.5 | AE13: =Производительность!E28*Производительность!E44 -> 227.23788 | AF13: =AE13/$AF$7 -> 4.4270461 | AG13: =ROUNDUP(AF13,0)*$AG$7/60 -> 3.75 | AI13: =SUM(C13,E13:K13,M13:O13) -> 102.38016 | AJ13: =AI13-C13 -> 77.79 | AK13: =AJ13-M13-N13-O13 -> 27.79 | AM13: =БелАЗ!E16 -> 22 | AN13: =БелАЗ!E17 -> 17 | AO13: =(AM13+AN13)/60 -> 0.65
A14: =Производительность!C13 -> XCMG 240 | B14: =B13 -> 300 | C14: =C$3*B14/(30.5*2) -> 24.590164 | E14: =E13 -> 7 | F14: =F13 -> 1 | G14: =G13 -> 0.8 | H14: =H13 -> 0.5 | I14: =I13 -> 0.49 | J14: =J13 -> 18 | M14: =M13 -> 30 | N14: =N13 -> 10 | O14: =O13 -> 10 | Q14: =Q13 -> 300 | R14: =R$3*Q14/(30.5*2) -> 24.590164 | S14: =R14-C14 -> 0 | U14: =U13 -> 240 | V14: =V$3*U14/(30.5*2) -> 19.672131 | W14: =V14-R14 -> -4.9180328 | Y14: =Y13 -> 2.5 | Z14: =Z13 -> 0.8 | AA14: =AA13 -> 3.5 | AB14: =AB13 -> 0.3 | AC14: =AC13 -> 0.8 | AD14: =AD13 -> 0.5 | AE14: =Производительность!E29*Производительность!E45 -> 207.94922 | AF14: =AE14/$AF$7 -> 4.0512646 | AG14: =ROUNDUP(AF14,0)*$AG$7/60 -> 3.75 | AI14: =SUM(C14,E14:K14,M14:O14) -> 102.38016 | AJ14: =AI14-C14 -> 77.79 | AK14: =AJ14-M14-N14-O14 -> 27.79 | AO14: =(AM14+AN14)/60 -> 0
A15: =Производительность!C14 -> БелАЗ 7531 (БТЛ) | B15: =B14 -> 300 | C15: =C$3*B15/(30.5*2) -> 24.590164 | E15: =E14 -> 7 | F15: =F14 -> 1 | G15: =G14 -> 0.8 | H15: =H14 -> 0.5 | I15: =I14 -> 0.49 | J15: =J14 -> 18 | M15: =M14 -> 30 | N15: =N14 -> 10 | O15: =O14 -> 10 | Q15: =Q14 -> 300 | R15: =R$3*Q15/(30.5*2) -> 24.590164 | S15: =R15-C15 -> 0 | U15: =U14 -> 240 | V15: =V$3*U15/(30.5*2) -> 19.672131 | W15: =V15-R15 -> -4.9180328 | Y15: =Y14 -> 2.5 | Z15: =Z14 -> 0.8 | AA15: =AA14 -> 3.5 | AB15: =AB14 -> 0.3 | AC15: =AC14 -> 0.8 | AD15: =AD14 -> 0.5 | AE15: =Производительность!E30*Производительность!E46 -> 227.23788 | AF15: =AE15/$AF$7 -> 4.4270461 | AG15: =ROUNDUP(AF15,0)*$AG$7/60 -> 3.75 | AI15: =SUM(C15,E15:K15,M15:O15) -> 102.38016 | AJ15: =AI15-C15 -> 77.79 | AK15: =AJ15-M15-N15-O15 -> 27.79 | AM15: =БелАЗ_Б!E16 -> 22 | AN15: =БелАЗ_Б!E17 -> 33 | AO15: =(AM15+AN15)/60 -> 0.91666667
A16: =Производительность!C15 -> 0 | C16: =C$3*B16/(30.5*2) -> 0 | R16: =R$3*Q16/(30.5*2) -> 0 | S16: =R16-C16 -> 0 | V16: =V$3*U16/(30.5*2) -> 0 | W16: =V16-R16 -> 0 | AE16: =Производительность!E31*Производительность!E47 -> 0 | AF16: =AE16/$AF$7 -> 0 | AG16: =ROUNDUP(AF16,0)*$AG$7/60 -> 0 | AI16: =SUM(C16,E16:K16,M16:O16) -> 0 | AJ16: =AI16-C16 -> 0 | AK16: =AJ16-M16-N16-O16 -> 0 | AO16: =(AM16+AN16)/60 -> 0
A17: =Производительность!C16 -> 0 | C17: =C$3*B17/(30.5*2) -> 0 | R17: =R$3*Q17/(30.5*2) -> 0 | S17: =R17-C17 -> 0 | V17: =V$3*U17/(30.5*2) -> 0 | W17: =V17-R17 -> 0 | AE17: =Производительность!E32*Производительность!E48 -> 0 | AF17: =AE17/$AF$7 -> 0 | AG17: =ROUNDUP(AF17,0)*$AG$7/60 -> 0 | AI17: =SUM(C17,E17:K17,M17:O17) -> 0 | AJ17: =AI17-C17 -> 0 | AK17: =AJ17-M17-N17-O17 -> 0 | AO17: =(AM17+AN17)/60 -> 0
A18: =Производительность!C17 -> 0 | C18: =C$3*B18/(30.5*2) -> 0 | R18: =R$3*Q18/(30.5*2) -> 0 | S18: =R18-C18 -> 0 | V18: =V$3*U18/(30.5*2) -> 0 | W18: =V18-R18 -> 0 | AE18: =Производительность!E33*Производительность!E49 -> 0 | AF18: =AE18/$AF$7 -> 0 | AG18: =ROUNDUP(AF18,0)*$AG$7/60 -> 0 | AI18: =SUM(C18,E18:K18,M18:O18) -> 0 | AJ18: =AI18-C18 -> 0 | AK18: =AJ18-M18-N18-O18 -> 0 | AO18: =(AM18+AN18)/60 -> 0
A19: =Производительность!C18 -> 0 | C19: =C$3*B19/(30.5*2) -> 0 | R19: =R$3*Q19/(30.5*2) -> 0 | S19: =R19-C19 -> 0 | V19: =V$3*U19/(30.5*2) -> 0 | W19: =V19-R19 -> 0 | AE19: =Производительность!E34*Производительность!E50 -> 0 | AF19: =AE19/$AF$7 -> 0 | AG19: =ROUNDUP(AF19,0)*$AG$7/60 -> 0 | AI19: =SUM(C19,E19:K19,M19:O19) -> 0 | AJ19: =AI19-C19 -> 0 | AK19: =AJ19-M19-N19-O19 -> 0 | AO19: =(AM19+AN19)/60 -> 0
A20: =Производительность!C19 -> 0 | C20: =C$3*B20/(30.5*2) -> 0 | R20: =R$3*Q20/(30.5*2) -> 0 | S20: =R20-C20 -> 0 | V20: =V$3*U20/(30.5*2) -> 0 | W20: =V20-R20 -> 0 | AE20: =Производительность!E35*Производительность!E51 -> 0 | AF20: =AE20/$AF$7 -> 0 | AG20: =ROUNDUP(AF20,0)*$AG$7/60 -> 0 | AI20: =SUM(C20,E20:K20,M20:O20) -> 0 | AJ20: =AI20-C20 -> 0 | AK20: =AJ20-M20-N20-O20 -> 0 | AO20: =(AM20+AN20)/60 -> 0
A21: =Производительность!C20 -> 0 | C21: =C$3*B21/(30.5*2) -> 0 | R21: =R$3*Q21/(30.5*2) -> 0 | S21: =R21-C21 -> 0 | V21: =V$3*U21/(30.5*2) -> 0 | W21: =V21-R21 -> 0 | AE21: =Производительность!E36*Производительность!E52 -> 0 | AF21: =AE21/$AF$7 -> 0 | AG21: =ROUNDUP(AF21,0)*$AG$7/60 -> 0 | AI21: =SUM(C21,E21:K21,M21:O21) -> 0 | AJ21: =AI21-C21 -> 0 | AK21: =AJ21-M21-N21-O21 -> 0 | AO21: =(AM21+AN21)/60 -> 0
A22: =Производительность!C21 -> 0 | C22: =C$3*B22/(30.5*2) -> 0 | R22: =R$3*Q22/(30.5*2) -> 0 | S22: =R22-C22 -> 0 | V22: =V$3*U22/(30.5*2) -> 0 | W22: =V22-R22 -> 0 | AE22: =Производительность!E37*Производительность!E53 -> 0 | AF22: =AE22/$AF$7 -> 0 | AG22: =ROUNDUP(AF22,0)*$AG$7/60 -> 0 | AI22: =SUM(C22,E22:K22,M22:O22) -> 0 | AJ22: =AI22-C22 -> 0 | AK22: =AJ22-M22-N22-O22 -> 0 | AO22: =(AM22+AN22)/60 -> 0
A23: =Производительность!C22 -> 0 | C23: =C$3*B23/(30.5*2) -> 0 | R23: =R$3*Q23/(30.5*2) -> 0 | S23: =R23-C23 -> 0 | V23: =V$3*U23/(30.5*2) -> 0 | W23: =V23-R23 -> 0 | AE23: =Производительность!E38*Производительность!E54 -> 0 | AF23: =AE23/$AF$7 -> 0 | AG23: =ROUNDUP(AF23,0)*$AG$7/60 -> 0 | AI23: =SUM(C23,E23:K23,M23:O23) -> 0 | AJ23: =AI23-C23 -> 0 | AK23: =AJ23-M23-N23-O23 -> 0 | AO23: =(AM23+AN23)/60 -> 0
Y25: NTE-240, ПК 2025

Sheet ФОТ, МТР, макро
A2: Персонал_ФОТ | F2: Топливо - цена | G2: =G4/I4 -> 66.018919 | H2: тыс. руб./т | N2: Топливо - расход | W2: Шины | AC2: Транспортный налог | AF2: Амортизация | AI2: Макро
A4: ФОТ+резервы (без взносов) | B4: 3702.5 | C4: тыс. руб. в год/чел. | F4: СЛ 2025 | G4: 1274749.9 | H4: тыс. руб. | I4: 19308.857 | J4: т | O4: г/ткм | P4: л/час | Q4: норма в расчет - заполнить | Y4: Пробег, тыс. км | Z4: норма, шт./тыс. км | AA4: цена, тыс. руб./шт. | AC4: мощность, л.с. | AD4: ставка, руб./л.с. | AF4: СПИ, мес. | AG4: %, год
A5: отчисления | B5: =(30+3.7+4)/100 -> 0.377 | N5: =Производительность!C8 -> NHL NTE 240 | O5: 90 | P5: 180 | Q5: =O4 -> г/ткм | W5: =Производительность!C8 -> NHL NTE 240 | X5: 50/80R57 | Y5: 80 | Z5: =6/Y5 -> 0.075 | AA5: =SUMIFS($AA$24:$AA$28,$W$24:$W$28,X5) -> 2985.3815 | AC5: ='NHL NTE240'!D11 -> 2500 | AD5: 85 | AF5: =7*12+1 -> 85 | AG5: =100/(AF5/12) -> 14.117647 | AJ5: 2026 | AK5: =ТСО!G2 -> 2027 | AL5: =ТСО!H2 -> 2028 | AM5: =ТСО!I2 -> 2029 | AN5: =ТСО!J2 -> 2030 | AO5: =ТСО!K2 -> 2031 | AP5: =ТСО!L2 -> 2032 | AQ5: =ТСО!M2 -> 2033 | AR5: =ТСО!N2 -> 2034 | ... BD5: =ТСО!Z2 -> 2046
N6: =Производительность!C9 -> Estar ESDE240 (ГПБ К) | O6: 90 | P6: 180 | Q6: =O4 -> г/ткм | W6: =Производительность!C9 -> Estar ESDE240 (ГПБ К) | X6: 50/80R57 | Y6: 80 | Z6: =6/Y6 -> 0.075 | AA6: =SUMIFS($AA$24:$AA$28,$W$24:$W$28,X6) -> 2985.3815 | AC6: =ESDE240!D11 -> 1864 | AD6: 85 | AF6: =7*12+1 -> 85 | AG6: =100/(AF6/12) -> 14.117647 | AI6: Курс валют
A7: Экипаж | B7: 3 | C7: человек | N7: =Производительность!C10 -> SANY SET240S | O7: 90 | P7: 180 | Q7: =O4 -> г/ткм | W7: =Производительность!C10 -> SANY SET240S | X7: 50/80R57 | Y7: 80 | Z7: =6/Y7 -> 0.075 | AA7: =SUMIFS($AA$24:$AA$28,$W$24:$W$28,X7) -> 2985.3815 | AC7: =SANY!S11 -> 2843 | AD7: 85 | AF7: =7*12+1 -> 85 | AG7: =100/(AF7/12) -> 14.117647 | AI7: доллар | AJ7: =Свод!W42 -> 94.0485 | AK7: =AJ7 -> 94.0485 | AL7: =AK7 -> 94.0485 | AM7: =AL7 -> 94.0485 | AN7: =AM7 -> 94.0485 | AO7: =AN7 -> 94.0485 | AP7: =AO7 -> 94.0485 | AQ7: =AP7 -> 94.0485 | AR7: =AQ7 -> 94.0485 | ... BD7: =BC7 -> 94.0485
N8: =Производительность!C11 -> TZCO TZE240 | O8: 90 | P8: 180 | Q8: =O4 -> г/ткм | W8: =Производительность!C11 -> TZCO TZE240 | X8: 46/90R57 | Y8: 80 | Z8: =6/Y8 -> 0.075 | AA8: =SUMIFS($AA$24:$AA$28,$W$24:$W$28,X8) -> 2511.4897 | AC8: =TZCO!D11 -> 2500 | AD8: 85 | AF8: =7*12+1 -> 85 | AG8: =100/(AF8/12) -> 14.117647 | AI8: юань | AJ8: =Свод!W43 -> 12.7702 | AK8: =AJ8 -> 12.7702 | AL8: =AK8 -> 12.7702 | AM8: =AL8 -> 12.7702 | AN8: =AM8 -> 12.7702 | AO8: =AN8 -> 12.7702 | AP8: =AO8 -> 12.7702 | AQ8: =AP8 -> 12.7702 | AR8: =AQ8 -> 12.7702 | ... BD8: =BC8 -> 12.7702
N9: =Производительность!C12 -> БелАЗ 7531 (ГПФК) | O9: 90 | P9: 180 | Q9: =O4 -> г/ткм | W9: =Производительность!C12 -> БелАЗ 7531 (ГПФК) | X9: 40.00R57 | Y9: 90 | Z9: =6/Y9 -> 0.066666667 | AA9: =SUMIFS($AA$24:$AA$28,$W$24:$W$28,X9) -> 2819.1038 | AC9: =БелАЗ!E11 -> 2535 | AD9: 85 | AF9: =7*12+1 -> 85 | AG9: =100/(AF9/12) -> 14.117647
N10: =Производительность!C13 -> XCMG 240 | O10: 90 | P10: 180 | Q10: =O4 -> г/ткм | W10: =Производительность!C13 -> XCMG 240 | X10: =X6 -> 50/80R57 | Y10: 80 | Z10: =6/Y10 -> 0.075 | AA10: =SUMIFS($AA$24:$AA$28,$W$24:$W$28,X10) -> 2985.3815 | AD10: 85 | AF10: =7*12+1 -> 85 | AG10: =100/(AF10/12) -> 14.117647
A11: Персонал_Прочее | N11: =Производительность!C14 -> БелАЗ 7531 (БТЛ) | O11: 90 | P11: 180 | Q11: =O4 -> г/ткм | W11: =Производительность!C14 -> БелАЗ 7531 (БТЛ) | X11: 46/90R57 | Y11: 80 | Z11: =6/Y11 -> 0.075 | AA11: =SUMIFS($AA$24:$AA$28,$W$24:$W$28,X11) -> 2511.4897 | AC11: =БелАЗ_Б!E11 -> 2535 | AD11: 85 | AF11: =7*12+1 -> 85 | AG11: =100/(AF11/12) -> 14.117647 | AI11: Налог на прибыль | AJ11: 0.25 | AK11: =AJ11 -> 0.25 | AL11: =AK11 -> 0.25 | AM11: =AL11 -> 0.25 | AN11: =AM11 -> 0.25 | AO11: =AN11 -> 0.25 | AP11: =AO11 -> 0.25 | AQ11: =AP11 -> 0.25 | AR11: =AQ11 -> 0.25 | ... BD11: =BC11 -> 0.25
N12: =Производительность!C15 -> 0 | W12: =Производительность!C15 -> 0 | Z12: =6/Y12 -> #DIV/0! | AG12: =100/(AF12/12) -> #DIV/0!
B13: Прочие затраты | C13: =SUM(C14:C20) -> 1060.1896 | D13: тыс. руб. в год/1 человек | N13: =Производительность!C16 -> 0 | W13: =Производительность!C16 -> 0 | Z13: =6/Y13 -> #DIV/0! | AG13: =100/(AF13/12) -> #DIV/0! | AI13: Дисконтирующий фактор | AJ13: 1 | AK13: =AJ13/(1+$AI$14) -> 0.89285714 | AL13: =AK13/(1+$AI$14) -> 0.79719388 | AM13: =AL13/(1+$AI$14) -> 0.71178025 | AN13: =AM13/(1+$AI$14) -> 0.63551808 | AO13: =AN13/(1+$AI$14) -> 0.56742686 | AP13: =AO13/(1+$AI$14) -> 0.50663112 | AQ13: =AP13/(1+$AI$14) -> 0.45234922 | AR13: =AQ13/(1+$AI$14) -> 0.40388323 | ... BD13: =BC13/(1+$AI$14) -> 0.10366677
B14: Питание | C14: 252.23989 | N14: =Производительность!C17 -> 0 | W14: =Производительность!C17 -> 0 | Z14: =6/Y14 -> #DIV/0! | AG14: =100/(AF14/12) -> #DIV/0! | AI14: 0.12 | AJ14: НИ | AK14: =AK13 -> 0.89285714 | AL14: =AK14+AL13 -> 1.690051 | AM14: =AL14+AM13 -> 2.4018313 | AN14: =AM14+AN13 -> 3.0373493 | AO14: =AN14+AO13 -> 3.6047762 | AP14: =AO14+AP13 -> 4.1114073 | AQ14: =AP14+AQ13 -> 4.5637565 | AR14: =AQ14+AR13 -> 4.9676398 | AS14: =AR14+AS13 -> 5.3282498 | ... BD14: =BC14+BD13 -> 7.4694436
B15: ДМС | C15: 10.343119 | N15: =Производительность!C18 -> 0 | W15: =Производительность!C18 -> 0 | Z15: =6/Y15 -> #DIV/0! | AG15: =100/(AF15/12) -> #DIV/0!
B16: СИЗы и АутсорсСпецодСпецОбувИдрСИЗ (УСО ПЛ) | C16: 66.086456 | N16: =Производительность!C19 -> 0 | W16: =Производительность!C19 -> 0 | Z16: =6/Y16 -> #DIV/0! | AG16: =100/(AF16/12) -> #DIV/0!
B17: Медосмотры | C17: 97.196423 | N17: =Производительность!C20 -> 0 | W17: =Производительность!C20 -> 0 | Z17: =6/Y17 -> #DIV/0! | AG17: =100/(AF17/12) -> #DIV/0!
B18: Проезд внутри ГОК | C18: 39.911169 | N18: =Производительность!C21 -> 0 | W18: =Производительность!C21 -> 0 | Z18: =6/Y18 -> #DIV/0! | AG18: =100/(AF18/12) -> #DIV/0!
B19: Проезд к месту работы и обратно | C19: 340.81253 | N19: =Производительность!C22 -> 0 | W19: =Производительность!C22 -> 0 | Z19: =6/Y19 -> #DIV/0! | AG19: =100/(AF19/12) -> #DIV/0!
B20: ВСХ с учетом проезда от места проживания до места работы | C20: 253.6
AC22: https://its.1c.ru/db/taxtrans#content:210:hdoc
AC23: Закон Иркутской области от 04.07.2007 № 53-оз (ред. от 09.06.2025)
X24: цена DDP Лесосибирск, без НДС: | AA24: тыс. руб./шт.
N25: ПК, 2025 | W25: 50/80R57 | X25: 50/80R57 MS453/403 S2 257/B TL Maxam | Y25: 31743 | Z25: долл/шт. | AA25: =Y25*AJ7/1000 -> 2985.3815
Q26: кг | R26: кг/ткм | S26: ткм | T26: рабочее время, час | W26: 40.00R57 | X26: 40.00R57 MS453/403 PRO E4 Maxam | Y26: 29975 | Z26: долл/шт. | AA26: =Y26*AJ7/1000 -> 2819.1038
N27: СЭБТ - NTE - 240 тн | O27: 1014842 | P27: Дизтопливо зимнее, кг | Q27: 34586669 | R27: 0.054017583 | W27: 46/90R57 | X27: 46/90R57 AG01 E4 TL Aeolus | Y27: 196668 | Z27: юаней/шт. | AA27: =Y27*AJ8/1000 -> 2511.4897
N28: СЭБТ - NTE - 240 тн | O28: 1014843 | P28: Дизтопливо летнее, кг | Q28: 25682645 | R28: 0.040111247
N29: СЭБТ - NTE - 240 тн | O29: 1014872 | P29: Дизтопливо летнее, кг | Q29: 2912182.3 | R29: 0.0045482567
N30: СЭБТ - NTE - 240 тн | O30: 1014858 | P30: Дизтопливо арктическое, кг | Q30: 27205.228 | R30: 4.2489223e-05
Q31: =SUM(Q27:Q30) -> 63208701 | R31: =SUM(R27:R30) -> 0.098719576 | S31: 6.4028538e+08 | T31: 409931.88
R32: =Q31/S31-R31 -> -3.8545236e-11
P33: г/ткм | Q33: =Q31*1000/S31 -> 98.719576
P34: кг/час | Q34: =Q31/T31 -> 154.19318
P35: л/час | Q35: =Q34/0.85 -> 181.40374
N37: ПК, 2026_6
Q38: кг | R38: кг/ткм | S38: ткм | T38: рабочее время, час
N39: Парк самосвалов NHL NTE240 | O39: 1014858 | P39: топливо дизельное арктическое (кг) | Q39: 1037503.6 | R39: 0.0022709648
N40: Парк самосвалов NHL NTE240 | O40: 1014842 | P40: топливо дизельное зимнее (кг) | Q40: 34855447 | R40: 0.076294191
N41: Парк самосвалов NHL NTE240 | O41: 1014843 | P41: топливо дизельное летнее (кг) | Q41: 11230418 | R41: 0.024581973
N42: Парк самосвалов NHL NTE240 | O42: 1014872 | P42: топливо дизельное межсезонное (кг) | Q42: 27988.647 | R42: 6.1263629e-05
Q43: =SUM(Q39:Q42) -> 47151358 | R43: =SUM(R39:R42) -> 0.10320839 | S43: 4.5700585e+08 | T43: 279377
R44: =Q43/S43-R43 -> -3.387649e-05
P45: г/ткм | Q45: =Q43*1000/S43 -> 103.17452
P46: кг/час | Q46: =Q43/T43 -> 168.77323
P47: л/час | Q47: =Q46/0.85 -> 198.55674

Sheet БелАЗ
B2: ячейки к заполнению поставщиком | M2: в действующих ценах на момент заполнения
B3: Карьерный автосамосвал | C3: Б-7531(G,H,N) | O3: Примечания
A4: 1 | B4: Период | C4: Ед. изм. | D4: 0 | E4: =D4+1 -> 1 | F4: =E4+1 -> 2 | G4: =F4+1 -> 3 | H4: =G4+1 -> 4 | I4: =H4+1 -> 5 | J4: =I4+1 -> 6 | K4: =J4+1 -> 7 | L4: =K4+1 -> 8 | ... N4: =M4+1 -> 10
A5: =A4+1 -> 2 | B5: Габариты машины
A6: =A5+1 -> 3 | B6: Эксплуатационная ширина (по зеркалам) | C6: мм | E6: 8800 | F6: 8800 | G6: 8800 | H6: 8800 | I6: 8800 | J6: 8800 | K6: 8800 | L6: 8800 | M6: 8800 | N6: 8800
A7: =A6+1 -> 4 | B7: Высота по переднему козырьку | C7: мм | E7: 6720 | F7: 6720 | G7: 6720 | H7: 6720 | I7: 6720 | J7: 6720 | K7: 6720 | L7: 6720 | M7: 6720 | N7: 6720
A8: =A7+1 -> 5 | B8: Габаритная длина | C8: мм | E8: 13390 | F8: 13390 | G8: 13390 | H8: 13390 | I8: 13390 | J8: 13390 | K8: 13390 | L8: 13390 | M8: 13390 | N8: 13390
A9: =A8+1 -> 6 | B9: Грузоподъемность | C9: тн | E9: 240 | F9: 240 | G9: 240 | H9: 240 | I9: 240 | J9: 240 | K9: 240 | L9: 240 | M9: 240 | N9: 240
A10: =A9+1 -> 7 | B10: Геометрические параметры кузова (конфигурация, размеры) | C10: м³ | E10: 130 | F10: 130 | G10: 130 | H10: 130 | I10: 130 | J10: 130 | K10: 130 | L10: 130 | M10: 130 | N10: 130
A11: =A10+1 -> 8 | B11: Мощность двигателя | C11: л.с. | E11: 2535 | F11: 2535 | G11: 2535 | H11: 2535 | I11: 2535 | J11: 2535 | K11: 2535 | L11: 2535 | M11: 2535 | N11: 2535
A12: =A11+1 -> 9 | B12: КТГ | E12: =(8760-E13-E14-E15)/8760 -> 0.90830416 | F12: =(8760-F13-F14-F15)/8760 -> 0.88577435 | G12: =(8760-G13-G14-G15)/8760 -> 0.86468734 | H12: =(8760-H13-H14-H15)/8760 -> 0.87460194 | I12: =(8760-I13-I14-I15)/8760 -> 0.88129799 | J12: =(8760-J13-J14-J15)/8760 -> 0.84567204 | K12: =(8760-K13-K14-K15)/8760 -> 0.89713174 | L12: =(8760-L13-L14-L15)/8760 -> 0.85462477 | ... N12: =(8760-N13-N14-N15)/8760 -> 0.86135781
A13: =A12+1 -> 10 | B13: простои на ТО | C13: час | E13: ='БелАЗ ТО'!F7 -> 455.92 | F13: ='БелАЗ ТО'!G7 -> 448.92 | G13: ='БелАЗ ТО'!H7 -> 448.92 | H13: ='БелАЗ ТО'!I7 -> 448.92 | I13: ='БелАЗ ТО'!J7 -> 448.92 | J13: ='БелАЗ ТО'!K7 -> 448.92 | K13: ='БелАЗ ТО'!L7 -> 448.92 | L13: ='БелАЗ ТО'!M7 -> 448.92 | ... N13: ='БелАЗ ТО'!O7 -> 448.92
A14: =A13+1 -> 11 | B14: простои в ремонтах | C14: час | E14: ='БелАЗ Рем'!F8 -> 120 | F14: ='БелАЗ Рем'!G8 -> 330 | G14: ='БелАЗ Рем'!H8 -> 520 | H14: ='БелАЗ Рем'!I8 -> 430.66667 | I14: ='БелАЗ Рем'!J8 -> 370.33333 | J14: ='БелАЗ Рем'!K8 -> 691.33333 | K14: ='БелАЗ Рем'!L8 -> 227.66667 | L14: ='БелАЗ Рем'!M8 -> 610.66667 | ... N14: ='БелАЗ Рем'!O8 -> 550
A15: =A14+1 -> 12 | B15: ежесменный осмотр (20 минут в смену) | C15: час | E15: =(8760-E13-E14)/12*20/60 -> 227.33556 | F15: =(8760-F13-F14)/12*20/60 -> 221.69667 | G15: =(8760-G13-G14)/12*20/60 -> 216.41889 | H15: =(8760-H13-H14)/12*20/60 -> 218.90037 | I15: =(8760-I13-I14)/12*20/60 -> 220.5763 | J15: =(8760-J13-J14)/12*20/60 -> 211.65963 | K15: =(8760-K13-K14)/12*20/60 -> 224.53926 | L15: =(8760-L13-L14)/12*20/60 -> 213.90037 | ... N15: =(8760-N13-N14)/12*20/60 -> 215.58556
A16: =A15+1 -> 13 | B16: Время подъема кузова с грузом | C16: сек | E16: 22 | F16: 22 | G16: 22 | H16: 22 | I16: 22 | J16: 22 | K16: 22 | L16: 22 | M16: 22 | N16: 22
A17: =A16+1 -> 14 | B17: Время опускания кузова | C17: сек | E17: 17 | F17: 17 | G17: 17 | H17: 17 | I17: 17 | J17: 17 | K17: 17 | L17: 17 | M17: 17 | N17: 17 | Q17: всего | R17: год
A18: =A17+1 -> 15 | B18: ТО, ТР, ПР, сервис (включая смазочные) | C18: тыс.долл/год | E18: =SUM(E19:E23) -> 148.04729 | F18: =SUM(F19:F23) -> 317.60136 | G18: =SUM(G19:G23) -> 572.06806 | H18: =SUM(H19:H23) -> 727.00655 | I18: =SUM(I19:I23) -> 631.62288 | J18: =SUM(J19:J23) -> 688.61907 | K18: =SUM(K19:K23) -> 180.49512 | L18: =SUM(L19:L23) -> 847.19411 | ... N18: =SUM(N19:N23) -> 231.50896 | Q18: =SUM(E18:N18) -> 5305.9137 | R18: =Q18/$N$4 -> 530.59137 | S18: =R18*'ФОТ, МТР, макро'!$AJ$7 -> 49901.322
A19: =A18+1 -> 16 | B19: ТО, включая смазочные | C19: тыс.дол./год | E19: ='БелАЗ ТО'!F9/1000 -> 62.26475 | F19: ='БелАЗ ТО'!G9/1000 -> 51.09977 | G19: ='БелАЗ ТО'!H9/1000 -> 51.09977 | H19: ='БелАЗ ТО'!I9/1000 -> 51.09977 | I19: ='БелАЗ ТО'!J9/1000 -> 51.09977 | J19: ='БелАЗ ТО'!K9/1000 -> 51.09977 | K19: ='БелАЗ ТО'!L9/1000 -> 51.09977 | L19: ='БелАЗ ТО'!M9/1000 -> 51.09977 | ... N19: ='БелАЗ ТО'!O9/1000 -> 51.09977 | Q19: =SUM(E19:N19) -> 522.16268 | R19: =Q19/$N$4 -> 52.216268
A20: =A19+1 -> 17 | B20: текущие ремонты | C20: тыс.дол./год | E20: ='БелАЗ Рем'!F10/1000 -> 16.5 | F20: ='БелАЗ Рем'!G10/1000 -> 183.7 | G20: ='БелАЗ Рем'!H10/1000 -> 158.5 | H20: ='БелАЗ Рем'!I10/1000 -> 50.7 | I20: ='БелАЗ Рем'!J10/1000 -> 163.5 | J20: ='БелАЗ Рем'!K10/1000 -> 188.7 | K20: ='БелАЗ Рем'!L10/1000 -> 35.5 | L20: ='БелАЗ Рем'!M10/1000 -> 198.7 | ... N20: ='БелАЗ Рем'!O10/1000 -> 70.7 | Q20: =SUM(E20:N20) -> 1240 | R20: =Q20/$N$4 -> 124
A21: =A20+1 -> 18 | B21: планово-предупредительные (капитальные) ремонты | C21: тыс.дол./год | E21: ='БелАЗ Рем'!F11/1000 -> 0 | F21: ='БелАЗ Рем'!G11/1000 -> 0 | G21: ='БелАЗ Рем'!H11/1000 -> 267.4 | H21: ='БелАЗ Рем'!I11/1000 -> 530 | I21: ='БелАЗ Рем'!J11/1000 -> 327 | J21: ='БелАЗ Рем'!K11/1000 -> 338.2 | K21: ='БелАЗ Рем'!L11/1000 -> 14.2 | L21: ='БелАЗ Рем'!M11/1000 -> 490 | ... N21: ='БелАЗ Рем'!O11/1000 -> 0 | Q21: =SUM(E21:N21) -> 2587 | R21: =Q21/$N$4 -> 258.7
A22: =A21+1 -> 19 | B22: сервис (трудозатраты) - ТО | C22: тыс.дол./год | E22: ='БелАЗ ТО'!F10/1000 -> 60.18144 | F22: ='БелАЗ ТО'!G10/1000 -> 59.25744 | G22: ='БелАЗ ТО'!H10/1000 -> 59.25744 | H22: ='БелАЗ ТО'!I10/1000 -> 59.25744 | I22: ='БелАЗ ТО'!J10/1000 -> 59.25744 | J22: ='БелАЗ ТО'!K10/1000 -> 59.25744 | K22: ='БелАЗ ТО'!L10/1000 -> 59.25744 | L22: ='БелАЗ ТО'!M10/1000 -> 59.25744 | ... N22: ='БелАЗ ТО'!O10/1000 -> 59.25744 | Q22: =SUM(E22:N22) -> 593.4984 | R22: =Q22/$N$4 -> 59.34984
A23: =A22+1 -> 20 | B23: сервис (трудозатраты) - ремонты | C23: тыс.дол./год | E23: ='БелАЗ Рем'!F12/1000 -> 9.1011 | F23: ='БелАЗ Рем'!G12/1000 -> 23.54415 | G23: ='БелАЗ Рем'!H12/1000 -> 35.81085 | H23: ='БелАЗ Рем'!I12/1000 -> 35.949345 | I23: ='БелАЗ Рем'!J12/1000 -> 30.765675 | J23: ='БелАЗ Рем'!K12/1000 -> 51.36186 | K23: ='БелАЗ Рем'!L12/1000 -> 20.437905 | L23: ='БелАЗ Рем'!M12/1000 -> 48.136905 | ... N23: ='БелАЗ Рем'!O12/1000 -> 50.45175 | Q23: =SUM(E23:N23) -> 363.2526 | R23: =Q23/$N$4 -> 36.32526
A24: =A23+1 -> 21 | B24: Шины
A25: =A24+1 -> 22 | B25: типоразмер | C25: 40.00 57 | D25: 40.00R57 Michelin
A26: =A25+1 -> 23 | B26: Цена за единицу | C26: Белшина | D26: $ | E26: 27000 | F26: 27000 | G26: 27000 | H26: 27000 | I26: 27000 | J26: 27000 | K26: 27000 | L26: 27000 | M26: 27000 | N26: 27000
A27: =A26+1 -> 24 | B27: Топливо
A28: =A27+1 -> 25 | B28: Расход - легкие условия | C28: л/час | E28: 110 | F28: 110 | G28: 110 | H28: 110 | I28: 110 | J28: 110 | K28: 110 | L28: 110 | M28: 110 | N28: 110
A29: =A28+1 -> 26 | B29: Расход - средние условия | C29: л/час | E29: 140 | F29: 140 | G29: 140 | H29: 140 | I29: 140 | J29: 140 | K29: 140 | L29: 140 | M29: 140 | N29: 140
A30: =A29+1 -> 27 | B30: Расход - тяжелые условия | C30: л/час | E30: 180 | F30: 180 | G30: 180 | H30: 180 | I30: 180 | J30: 180 | K30: 180 | L30: 180 | M30: 180 | N30: 180
A31: =A30+1 -> 28 | B31: Сроки поставки | C31: мес | E31: 6
E34: =E18/(365*24*E12)*1000 -> 18.606516 | F34: =F18/(365*24*F12)*1000 -> 40.931263 | G34: =G18/(365*24*G12)*1000 -> 75.523915 | H34: =H18/(365*24*H12)*1000 -> 94.89073 | I34: =I18/(365*24*I12)*1000 -> 81.81463 | J34: =J18/(365*24*J12)*1000 -> 92.955046 | K34: =K18/(365*24*K12)*1000 -> 22.967045 | L34: =L18/(365*24*L12)*1000 -> 113.16271 | ... N34: =N18/(365*24*N12)*1000 -> 30.681748 | O34: =SUMPRODUCT(E34:N34,E12:N12)/SUM(E12:N12) -> 69.495464

Sheet БелАЗ ТО
A2: ячейки к заполнению поставщиком
A3: Расчетный КТГ | F3: =БелАЗ!E12 -> 0.90830416 | G3: =БелАЗ!F12 -> 0.88577435 | H3: =БелАЗ!G12 -> 0.86468734 | I3: =БелАЗ!H12 -> 0.87460194 | J3: =БелАЗ!I12 -> 0.88129799 | K3: =БелАЗ!J12 -> 0.84567204 | L3: =БелАЗ!K12 -> 0.89713174 | M3: =БелАЗ!L12 -> 0.85462477 | ... O3: =БелАЗ!N12 -> 0.86135781
A4: Год службы (год) | B4: Ед. изм. | F4: =D4+1 -> 1 | G4: =F4+1 -> 2 | H4: =G4+1 -> 3 | I4: =H4+1 -> 4 | J4: =I4+1 -> 5 | K4: =J4+1 -> 6 | L4: =K4+1 -> 7 | M4: =L4+1 -> 8 | N4: =M4+1 -> 9 | O4: =N4+1 -> 10
A5: Наработка на начало года | B5: м/час | F5: 0 | G5: =F6+1 -> 7001 | H5: =G6+1 -> 14001 | I5: =H6+1 -> 21001 | J5: =I6+1 -> 28001 | K5: =J6+1 -> 35001 | L5: =K6+1 -> 42001 | M5: =L6+1 -> 49001 | N5: =M6+1 -> 56001 | O5: =N6+1 -> 63001
A6: Наработка на конец года | B6: м/час | E6: 7000 | F6: =E6 -> 7000 | G6: =F6+$E6 -> 14000 | H6: =G6+$E6 -> 21000 | I6: =H6+$E6 -> 28000 | J6: =I6+$E6 -> 35000 | K6: =J6+$E6 -> 42000 | L6: =K6+$E6 -> 49000 | M6: =L6+$E6 -> 56000 | N6: =M6+$E6 -> 63000 | O6: =N6+$E6 -> 70000
A7: длительность простоев на ТО | B7: часов | F7: =F13 -> 455.92 | G7: =G13 -> 448.92 | H7: =H13 -> 448.92 | I7: =I13 -> 448.92 | J7: =J13 -> 448.92 | K7: =K13 -> 448.92 | L7: =L13 -> 448.92 | M7: =M13 -> 448.92 | ... O7: =O13 -> 448.92
A8: Затраты на ТО | B8: долларов/год | F8: =SUM(F9:F10) -> 122446.19 | G8: =SUM(G9:G10) -> 110357.21 | H8: =SUM(H9:H10) -> 110357.21 | I8: =SUM(I9:I10) -> 110357.21 | J8: =SUM(J9:J10) -> 110357.21 | K8: =SUM(K9:K10) -> 110357.21 | L8: =SUM(L9:L10) -> 110357.21 | M8: =SUM(M9:M10) -> 110357.21 | ... O8: =SUM(O9:O10) -> 110357.21
A9: ТО, включая масла и смазки | B9: долларов/год | F9: =F23 -> 62264.75 | G9: =G23 -> 51099.77 | H9: =H23 -> 51099.77 | I9: =I23 -> 51099.77 | J9: =J23 -> 51099.77 | K9: =K23 -> 51099.77 | L9: =L23 -> 51099.77 | M9: =M23 -> 51099.77 | ... O9: =O23 -> 51099.77
A10: сервис (трудозатраты) на ТО | B10: долларов/год | E10: 44 | F10: =SUMPRODUCT(F14:F20,$E$14:$E$20)*$E10 -> 60181.44 | G10: =SUMPRODUCT(G14:G20,$E$14:$E$20)*$E10 -> 59257.44 | H10: =SUMPRODUCT(H14:H20,$E$14:$E$20)*$E10 -> 59257.44 | I10: =SUMPRODUCT(I14:I20,$E$14:$E$20)*$E10 -> 59257.44 | J10: =SUMPRODUCT(J14:J20,$E$14:$E$20)*$E10 -> 59257.44 | K10: =SUMPRODUCT(K14:K20,$E$14:$E$20)*$E10 -> 59257.44 | L10: =SUMPRODUCT(L14:L20,$E$14:$E$20)*$E10 -> 59257.44 | M10: =SUMPRODUCT(M14:M20,$E$14:$E$20)*$E10 -> 59257.44 | ... O10: =SUMPRODUCT(O14:O20,$E$14:$E$20)*$E10 -> 59257.44
A12: Простои оборудования на ТО | B12: Интервал ТО | C12: Длительность простоя на одном ТО, час | D12: Кол-во ТО в год | E12: Занято человек | F12: Простоев в год, час | G12: Простоев в год, час | H12: Простоев в год, час | I12: Простоев в год, час | J12: Простоев в год, час | K12: Простоев в год, час | L12: Простоев в год, час | M12: Простоев в год, час | N12: Простоев в год, час | O12: Простоев в год, час
A13: всего простоев на ТО, часов | F13: =SUM(F14:F20) -> 455.92 | G13: =SUM(G14:G20) -> 448.92 | H13: =SUM(H14:H20) -> 448.92 | I13: =SUM(I14:I20) -> 448.92 | J13: =SUM(J14:J20) -> 448.92 | K13: =SUM(K14:K20) -> 448.92 | L13: =SUM(L14:L20) -> 448.92 | M13: =SUM(M14:M20) -> 448.92 | ... O13: =SUM(O14:O20) -> 448.92
A14: ТО-100 (разовое) | B14: 100 | C14: 7 | D14: 1 | E14: 3 | F14: =$D14*$C14 -> 7
A15: ТО-1 | B15: 250 | C15: 7 | D15: 14 | E15: 3 | F15: =$D15*$C15 -> 98 | G15: =$D15*$C15 -> 98 | H15: =$D15*$C15 -> 98 | I15: =$D15*$C15 -> 98 | J15: =$D15*$C15 -> 98 | K15: =$D15*$C15 -> 98 | L15: =$D15*$C15 -> 98 | M15: =$D15*$C15 -> 98 | ... O15: =$D15*$C15 -> 98
A16: ТО-2 | B16: 500 | C16: 20.3 | D16: 3 | E16: 3 | F16: =$D16*$C16 -> 60.9 | G16: =$D16*$C16 -> 60.9 | H16: =$D16*$C16 -> 60.9 | I16: =$D16*$C16 -> 60.9 | J16: =$D16*$C16 -> 60.9 | K16: =$D16*$C16 -> 60.9 | L16: =$D16*$C16 -> 60.9 | M16: =$D16*$C16 -> 60.9 | ... O16: =$D16*$C16 -> 60.9
A17: ТО-3 | B17: 1000 | C17: 28.3 | D17: 6 | E17: 3 | F17: =$D17*$C17 -> 169.8 | G17: =$D17*$C17 -> 169.8 | H17: =$D17*$C17 -> 169.8 | I17: =$D17*$C17 -> 169.8 | J17: =$D17*$C17 -> 169.8 | K17: =$D17*$C17 -> 169.8 | L17: =$D17*$C17 -> 169.8 | M17: =$D17*$C17 -> 169.8 | ... O17: =$D17*$C17 -> 169.8
A18: СО | B18: 3500 | C18: 25.66 | D18: 2 | E18: 3 | F18: =$D18*$C18 -> 51.32 | G18: =$D18*$C18 -> 51.32 | H18: =$D18*$C18 -> 51.32 | I18: =$D18*$C18 -> 51.32 | J18: =$D18*$C18 -> 51.32 | K18: =$D18*$C18 -> 51.32 | L18: =$D18*$C18 -> 51.32 | M18: =$D18*$C18 -> 51.32 | ... O18: =$D18*$C18 -> 51.32
A19: ТО-2500 | B19: 2500 | C19: 20.3 | D19: 2 | E19: 3 | F19: =$D19*$C19 -> 40.6 | G19: =$D19*$C19 -> 40.6 | H19: =$D19*$C19 -> 40.6 | I19: =$D19*$C19 -> 40.6 | J19: =$D19*$C19 -> 40.6 | K19: =$D19*$C19 -> 40.6 | L19: =$D19*$C19 -> 40.6 | M19: =$D19*$C19 -> 40.6 | ... O19: =$D19*$C19 -> 40.6
A20: ТО-4000 | B20: 4000 | C20: 28.3 | D20: 1 | E20: 3 | F20: =$D20*$C20 -> 28.3 | G20: =$C20 -> 28.3 | H20: =$D20*$C20 -> 28.3 | I20: =$C20 -> 28.3 | J20: =$D20*$C20 -> 28.3 | K20: =$C20 -> 28.3 | L20: =$C20 -> 28.3 | M20: =$D20*$C20 -> 28.3 | N20: =$C20 -> 28.3 | O20: =$D20*$C20 -> 28.3
