Workbook

Sheet Свод_250-270_диз
C2: Технико-экономическая оценка стоимости владения
C4: Ранжирование общих аннуитетов - по возрастанию | G4: Ранжирование по стоимости самосвала - по возрастанию
C5: № | D5: Марка станка | E5: Аннуитет, руб/ткм | G5: =C5 -> № | H5: =D5 -> Марка станка | K5: Цена за ед., тыс. руб.
C6: 1 | D6: =IFERROR(HLOOKUP(E6,$F$58:$O$60,3,FALSE),"-") -> YANGZI DR75 | E6: =IFERROR(SMALL($F$58:$O$58,C6),"-") -> 11.045801 | G6: =C6 -> 1 | H6: =IFERROR(HLOOKUP(K6,$F$59:$O$60,2,FALSE),"-") -> - | K6: =IFERROR(SMALL($F$59:$O$59,C6),"-") -> -
C7: =C6+1 -> 2 | D7: =IFERROR(HLOOKUP(E7,$F$58:$O$60,3,FALSE),"-") -> Sunward SWDRT270SM | E7: =IFERROR(SMALL($F$58:$O$58,C7),"-") -> 12.086588 | G7: =C7 -> 2 | H7: =IFERROR(HLOOKUP(K7,$F$59:$O$60,2,FALSE),"-") -> - | K7: =IFERROR(SMALL($F$59:$O$59,C7),"-") -> -
C8: =C7+1 -> 3 | D8: =IFERROR(HLOOKUP(E8,$F$58:$O$60,3,FALSE),"-") -> Sunward SWDRT270B | E8: =IFERROR(SMALL($F$58:$O$58,C8),"-") -> 13.62781 | G8: =C8 -> 3 | H8: =IFERROR(HLOOKUP(K8,$F$59:$O$60,2,FALSE),"-") -> - | K8: =IFERROR(SMALL($F$59:$O$59,C8),"-") -> -
C9: =C8+1 -> 4 | D9: =IFERROR(HLOOKUP(E9,$F$58:$O$60,3,FALSE),"-") -> Sunward SWDRT250SM | E9: =IFERROR(SMALL($F$58:$O$58,C9),"-") -> 13.768153 | G9: =C9 -> 4 | H9: =IFERROR(HLOOKUP(K9,$F$59:$O$60,2,FALSE),"-") -> - | K9: =IFERROR(SMALL($F$59:$O$59,C9),"-") -> -
C10: =C9+1 -> 5 | D10: =IFERROR(HLOOKUP(E10,$F$58:$O$60,3,FALSE),"-") -> HIFO 75D | E10: =IFERROR(SMALL($F$58:$O$58,C10),"-") -> 14.68475 | G10: =C10 -> 5 | H10: =IFERROR(HLOOKUP(K10,$F$59:$O$60,2,FALSE),"-") -> - | K10: =IFERROR(SMALL($F$59:$O$59,C10),"-") -> -
C11: =C10+1 -> 6 | D11: =IFERROR(HLOOKUP(E11,$F$58:$O$60,3,FALSE),"-") -> - | E11: =IFERROR(SMALL($F$58:$O$58,C11),"-") -> - | G11: =C11 -> 6 | H11: =IFERROR(HLOOKUP(K11,$F$59:$O$60,2,FALSE),"-") -> - | K11: =IFERROR(SMALL($F$59:$O$59,C11),"-") -> -
C12: =C11+1 -> 7 | D12: =IFERROR(HLOOKUP(E12,$F$58:$O$60,3,FALSE),"-") -> - | E12: =IFERROR(SMALL($F$58:$O$58,C12),"-") -> - | G12: =C12 -> 7 | H12: =IFERROR(HLOOKUP(K12,$F$59:$O$60,2,FALSE),"-") -> - | K12: =IFERROR(SMALL($F$59:$O$59,C12),"-") -> -
C13: =C12+1 -> 8 | D13: =IFERROR(HLOOKUP(E13,$F$58:$O$60,3,FALSE),"-") -> - | E13: =IFERROR(SMALL($F$58:$O$58,C13),"-") -> - | G13: =C13 -> 8 | H13: =IFERROR(HLOOKUP(K13,$F$59:$O$60,2,FALSE),"-") -> - | K13: =IFERROR(SMALL($F$59:$O$59,C13),"-") -> -
C14: =C13+1 -> 9 | D14: =IFERROR(HLOOKUP(E14,$F$58:$O$60,3,FALSE),"-") -> - | E14: =IFERROR(SMALL($F$58:$O$58,C14),"-") -> - | G14: =C14 -> 9 | H14: =IFERROR(HLOOKUP(K14,$F$59:$O$60,2,FALSE),"-") -> - | K14: =IFERROR(SMALL($F$59:$O$59,C14),"-") -> -
C15: =C14+1 -> 10 | D15: =IFERROR(HLOOKUP(E15,$F$58:$O$60,3,FALSE),"-") -> - | E15: =IFERROR(SMALL($F$58:$O$58,C15),"-") -> - | G15: =C15 -> 10 | H15: =IFERROR(HLOOKUP(K15,$F$59:$O$60,2,FALSE),"-") -> - | K15: =IFERROR(SMALL($F$59:$O$59,C15),"-") -> -
F18: =VLOOKUP(F19,Производительность!$C$7:$AB$33,26,FALSE) -> Майнинг Солюшнс | G18: =VLOOKUP(G19,Производительность!$C$7:$AB$33,26,FALSE) -> Стройкомпозит-Н | H18: =VLOOKUP(H19,Производительность!$C$7:$AB$33,26,FALSE) -> Стройкомпозит-Н | I18: =VLOOKUP(I19,Производительность!$C$7:$AB$33,26,FALSE) -> Огунвей | J18: =VLOOKUP(J19,Производительность!$C$7:$AB$33,26,FALSE) -> Огунвей | K18: =VLOOKUP(K19,Производительность!$C$7:$AB$33,26,FALSE) -> #N/A | L18: =VLOOKUP(L19,Производительность!$C$7:$AB$33,26,FALSE) -> #N/A | M18: =VLOOKUP(M19,Производительность!$C$7:$AB$33,26,FALSE) -> #N/A | ... O18: =VLOOKUP(O19,Производительность!$C$7:$AB$33,26,FALSE) -> #N/A
C19: № | D19: Показатель | E19: Ед. изм. | F19: =Производительность!C12 -> HIFO 75D | G19: =Производительность!C10 -> Sunward SWDRT270SM | H19: =Производительность!C9 -> Sunward SWDRT250SM | I19: =Производительность!C8 -> YANGZI DR75 | J19: =Производительность!C11 -> Sunward SWDRT270B | P19: Комментарий
C20: 1 | D20: Диаметр бурения (в расчете) | E20: мм | F20: =SUMIFS('W час'!$E$19:$AF$19,'W час'!$E$4:$AF$4,F$19)*1000 -> 266.96421 | G20: =SUMIFS('W час'!$E$19:$AF$19,'W час'!$E$4:$AF$4,G$19)*1000 -> 266.96421 | H20: =SUMIFS('W час'!$E$19:$AF$19,'W час'!$E$4:$AF$4,H$19)*1000 -> 266.96421 | I20: =SUMIFS('W час'!$E$19:$AF$19,'W час'!$E$4:$AF$4,I$19)*1000 -> 266.96421 | J20: =SUMIFS('W час'!$E$19:$AF$19,'W час'!$E$4:$AF$4,J$19)*1000 -> 266.96421 | K20: =SUMIFS('W час'!$E$19:$AF$19,'W час'!$E$4:$AF$4,K$19)*1000 -> 0 | L20: =SUMIFS('W час'!$E$19:$AF$19,'W час'!$E$4:$AF$4,L$19)*1000 -> 0 | M20: =SUMIFS('W час'!$E$19:$AF$19,'W час'!$E$4:$AF$4,M$19)*1000 -> 0 | ... O20: =SUMIFS('W час'!$E$19:$AF$19,'W час'!$E$4:$AF$4,O$19)*1000 -> 0
C21: =MAX(C$20:C20)+1 -> 2 | D21: Вес станка | E21: т | F21: =HLOOKUP(F$19,'W час'!$E$4:$AF$5,2,FALSE) -> 68-85 | G21: =HLOOKUP(G$19,'W час'!$E$4:$AF$5,2,FALSE) -> 65-70 | H21: =HLOOKUP(H$19,'W час'!$E$4:$AF$5,2,FALSE) -> 65-70 | I21: =HLOOKUP(I$19,'W час'!$E$4:$AF$5,2,FALSE) -> не более 85 | J21: =HLOOKUP(J$19,'W час'!$E$4:$AF$5,2,FALSE) -> 65-70 | K21: =HLOOKUP(K$19,'W час'!$E$4:$AF$5,2,FALSE) -> #N/A | L21: =HLOOKUP(L$19,'W час'!$E$4:$AF$5,2,FALSE) -> #N/A | M21: =HLOOKUP(M$19,'W час'!$E$4:$AF$5,2,FALSE) -> #N/A | ... O21: =HLOOKUP(O$19,'W час'!$E$4:$AF$5,2,FALSE) -> #N/A
C22: =MAX(C$20:C21)+1 -> 3 | D22: Мощность привода вращателя (в расчете) | E22: кВт | F22: =SUMIFS('W час'!$E$22:$AF$22,'W час'!$E$4:$AF$4,F$19) -> 136 | G22: =SUMIFS('W час'!$E$22:$AF$22,'W час'!$E$4:$AF$4,G$19) -> 173.4 | H22: =SUMIFS('W час'!$E$22:$AF$22,'W час'!$E$4:$AF$4,H$19) -> 148.3 | I22: =SUMIFS('W час'!$E$22:$AF$22,'W час'!$E$4:$AF$4,I$19) -> 136 | J22: =SUMIFS('W час'!$E$22:$AF$22,'W час'!$E$4:$AF$4,J$19) -> 173.4 | K22: =SUMIFS('W час'!$E$22:$AF$22,'W час'!$E$4:$AF$4,K$19) -> 0 | L22: =SUMIFS('W час'!$E$22:$AF$22,'W час'!$E$4:$AF$4,L$19) -> 0 | M22: =SUMIFS('W час'!$E$22:$AF$22,'W час'!$E$4:$AF$4,M$19) -> 0 | ... O22: =SUMIFS('W час'!$E$22:$AF$22,'W час'!$E$4:$AF$4,O$19) -> 0
C23: =MAX(C$20:C22)+1 -> 4 | D23: Срок эксплуатации | E23: лет | F23: =SUMIFS(Производительность!$Y$7:$Y$34,Производительность!$C$7:$C$34,F$19) -> 10 | G23: =SUMIFS(Производительность!$Y$7:$Y$34,Производительность!$C$7:$C$34,G$19) -> 12 | H23: =SUMIFS(Производительность!$Y$7:$Y$34,Производительность!$C$7:$C$34,H$19) -> 12 | I23: =SUMIFS(Производительность!$Y$7:$Y$34,Производительность!$C$7:$C$34,I$19) -> 12 | J23: =SUMIFS(Производительность!$Y$7:$Y$34,Производительность!$C$7:$C$34,J$19) -> 12 | K23: =SUMIFS(Производительность!$Y$7:$Y$34,Производительность!$C$7:$C$34,K$19) -> 0 | L23: =SUMIFS(Производительность!$Y$7:$Y$34,Производительность!$C$7:$C$34,L$19) -> 0 | M23: =SUMIFS(Производительность!$Y$7:$Y$34,Производительность!$C$7:$C$34,M$19) -> 0 | ... O23: =SUMIFS(Производительность!$Y$7:$Y$34,Производительность!$C$7:$C$34,O$19) -> 0
C24: =MAX(C$20:C23)+1 -> 5 | D24: КТГ (средний за эксплуатацию) | E24: коэфф. | F24: =SUMIFS(Производительность!$Z$7:$Z$34,Производительность!$C$7:$C$34,F$19) -> 0.86279872 | G24: =SUMIFS(Производительность!$Z$7:$Z$34,Производительность!$C$7:$C$34,G$19) -> 0.86075942 | H24: =SUMIFS(Производительность!$Z$7:$Z$34,Производительность!$C$7:$C$34,H$19) -> 0.86075942 | I24: =SUMIFS(Производительность!$Z$7:$Z$34,Производительность!$C$7:$C$34,I$19) -> 0.90811031 | J24: =SUMIFS(Производительность!$Z$7:$Z$34,Производительность!$C$7:$C$34,J$19) -> 0.89583333 | K24: =SUMIFS(Производительность!$Z$7:$Z$34,Производительность!$C$7:$C$34,K$19) -> 0 | L24: =SUMIFS(Производительность!$Z$7:$Z$34,Производительность!$C$7:$C$34,L$19) -> 0 | M24: =SUMIFS(Производительность!$Z$7:$Z$34,Производительность!$C$7:$C$34,M$19) -> 0 | ... O24: =SUMIFS(Производительность!$Z$7:$Z$34,Производительность!$C$7:$C$34,O$19) -> 0
C25: =MAX(C$20:C24)+1 -> 6 | D25: КТГ (1-й год) | E25: =E24 -> коэфф. | F25: =SUMIFS(Производительность!$E$7:$E$34,Производительность!$C$7:$C$34,F$19) -> 0.89322362 | G25: =SUMIFS(Производительность!$E$7:$E$34,Производительность!$C$7:$C$34,G$19) -> 0.8947946 | H25: =SUMIFS(Производительность!$E$7:$E$34,Производительность!$C$7:$C$34,H$19) -> 0.8947946 | I25: =SUMIFS(Производительность!$E$7:$E$34,Производительность!$C$7:$C$34,I$19) -> 0.93093607 | J25: =SUMIFS(Производительность!$E$7:$E$34,Производительность!$C$7:$C$34,J$19) -> 0.93 | K25: =SUMIFS(Производительность!$E$7:$E$34,Производительность!$C$7:$C$34,K$19) -> 0 | L25: =SUMIFS(Производительность!$E$7:$E$34,Производительность!$C$7:$C$34,L$19) -> 0 | M25: =SUMIFS(Производительность!$E$7:$E$34,Производительность!$C$7:$C$34,M$19) -> 0 | ... O25: =SUMIFS(Производительность!$E$7:$E$34,Производительность!$C$7:$C$34,O$19) -> 0
C26: =MAX(C$20:C25)+1 -> 7 | D26: КИО (средний за эксплуатацию) | E26: =E24 -> коэфф. | F26: =SUMIFS(Производительность!$Z$115:$Z$142,Производительность!$C$115:$C$142,F$19) -> 0.69752392 | G26: =SUMIFS(Производительность!$Z$115:$Z$142,Производительность!$C$115:$C$142,G$19) -> 0.69587526 | H26: =SUMIFS(Производительность!$Z$115:$Z$142,Производительность!$C$115:$C$142,H$19) -> 0.69587526 | I26: =SUMIFS(Производительность!$Z$115:$Z$142,Производительность!$C$115:$C$142,I$19) -> 0.73415577 | J26: =SUMIFS(Производительность!$Z$115:$Z$142,Производительность!$C$115:$C$142,J$19) -> 0.72423053 | K26: =SUMIFS(Производительность!$Z$115:$Z$142,Производительность!$C$115:$C$142,K$19) -> 0 | L26: =SUMIFS(Производительность!$Z$115:$Z$142,Производительность!$C$115:$C$142,L$19) -> 0 | M26: =SUMIFS(Производительность!$Z$115:$Z$142,Производительность!$C$115:$C$142,M$19) -> 0 | ... O26: =SUMIFS(Производительность!$Z$115:$Z$142,Производительность!$C$115:$C$142,O$19) -> 0
C27: =MAX(C$20:C26)+1 -> 8 | D27: Часовая производительность | E27: п. м/час | F27: =SUMIFS(Производительность!$E$169:$E$196,Производительность!$C$169:$C$196,F$19) -> 16.310776 | G27: =SUMIFS(Производительность!$E$169:$E$196,Производительность!$C$169:$C$196,G$19) -> 20.040244 | H27: =SUMIFS(Производительность!$E$169:$E$196,Производительность!$C$169:$C$196,H$19) -> 17.592641 | I27: =SUMIFS(Производительность!$E$169:$E$196,Производительность!$C$169:$C$196,I$19) -> 16.310776 | J27: =SUMIFS(Производительность!$E$169:$E$196,Производительность!$C$169:$C$196,J$19) -> 20.040244 | K27: =SUMIFS(Производительность!$E$169:$E$196,Производительность!$C$169:$C$196,K$19) -> 0 | L27: =SUMIFS(Производительность!$E$169:$E$196,Производительность!$C$169:$C$196,L$19) -> 0 | M27: =SUMIFS(Производительность!$E$169:$E$196,Производительность!$C$169:$C$196,M$19) -> 0 | ... O27: =SUMIFS(Производительность!$E$169:$E$196,Производительность!$C$169:$C$196,O$19) -> 0
C28: =MAX(C$20:C27)+1 -> 9 | D28: Производительность (средняя за эксплуатацию) | E28: тыс. п. м | F28: =SUMIFS(Производительность!$Z$196:$Z$223,Производительность!$C$196:$C$223,F$19) -> 99.663889 | G28: =SUMIFS(Производительность!$Z$196:$Z$223,Производительность!$C$196:$C$223,G$19) -> 122.16267 | H28: =SUMIFS(Производительность!$Z$196:$Z$223,Производительность!$C$196:$C$223,H$19) -> 107.2424 | I28: =SUMIFS(Производительность!$Z$196:$Z$223,Производительность!$C$196:$C$223,I$19) -> 104.89794 | J28: =SUMIFS(Производительность!$Z$196:$Z$223,Производительность!$C$196:$C$223,J$19) -> 127.14051 | K28: =SUMIFS(Производительность!$Z$196:$Z$223,Производительность!$C$196:$C$223,K$19) -> 0 | L28: =SUMIFS(Производительность!$Z$196:$Z$223,Производительность!$C$196:$C$223,L$19) -> 0 | M28: =SUMIFS(Производительность!$Z$196:$Z$223,Производительность!$C$196:$C$223,M$19) -> 0 | ... O28: =SUMIFS(Производительность!$Z$196:$Z$223,Производительность!$C$196:$C$223,O$19) -> 0
C29: =MAX(C$20:C28)+1 -> 10 | E29: тыс. м3 | F29: =SUMIFS(Производительность!$Z$250:$Z$277,Производительность!$C$250:$C$277,F$19) -> 4724.592 | G29: =SUMIFS(Производительность!$Z$250:$Z$277,Производительность!$C$250:$C$277,G$19) -> 5871.7519 | H29: =SUMIFS(Производительность!$Z$250:$Z$277,Производительность!$C$250:$C$277,H$19) -> 5154.6091 | I29: =SUMIFS(Производительность!$Z$250:$Z$277,Производительность!$C$250:$C$277,I$19) -> 5043.4471 | J29: =SUMIFS(Производительность!$Z$250:$Z$277,Производительность!$C$250:$C$277,J$19) -> 6111.3813 | K29: =SUMIFS(Производительность!$Z$250:$Z$277,Производительность!$C$250:$C$277,K$19) -> 0 | L29: =SUMIFS(Производительность!$Z$250:$Z$277,Производительность!$C$250:$C$277,L$19) -> 0 | M29: =SUMIFS(Производительность!$Z$250:$Z$277,Производительность!$C$250:$C$277,M$19) -> 0 | ... O29: =SUMIFS(Производительность!$Z$250:$Z$277,Производительность!$C$250:$C$277,O$19) -> 0
C30: =MAX(C$20:C29)+1 -> 11 | D30: Производительность (1-й год) | E30: =E28 -> тыс. п. м | F30: =SUMIFS(Производительность!$E$196:$E$223,Производительность!$C$196:$C$223,F$19) -> 103.17834 | G30: =SUMIFS(Производительность!$E$196:$E$223,Производительность!$C$196:$C$223,G$19) -> 126.99308 | H30: =SUMIFS(Производительность!$E$196:$E$223,Производительность!$C$196:$C$223,H$19) -> 111.48286 | I30: =SUMIFS(Производительность!$E$196:$E$223,Производительность!$C$196:$C$223,I$19) -> 107.53459 | J30: =SUMIFS(Производительность!$E$196:$E$223,Производительность!$C$196:$C$223,J$19) -> 131.98959 | K30: =SUMIFS(Производительность!$E$196:$E$223,Производительность!$C$196:$C$223,K$19) -> 0 | L30: =SUMIFS(Производительность!$E$196:$E$223,Производительность!$C$196:$C$223,L$19) -> 0 | M30: =SUMIFS(Производительность!$E$196:$E$223,Производительность!$C$196:$C$223,M$19) -> 0 | ... O30: =SUMIFS(Производительность!$E$196:$E$223,Производительность!$C$196:$C$223,O$19) -> 0
C31: =MAX(C$20:C30)+1 -> 12 | E31: =E29 -> тыс. м3 | F31: =SUMIFS(Производительность!$E$250:$E$277,Производительность!$C$250:$C$277,F$19) -> 5103.7424 | G31: =SUMIFS(Производительность!$E$250:$E$277,Производительность!$C$250:$C$277,G$19) -> 6281.7447 | H31: =SUMIFS(Производительность!$E$250:$E$277,Производительность!$C$250:$C$277,H$19) -> 5514.5277 | I31: =SUMIFS(Производительность!$E$250:$E$277,Производительность!$C$250:$C$277,I$19) -> 5319.2255 | J31: =SUMIFS(Производительность!$E$250:$E$277,Производительность!$C$250:$C$277,J$19) -> 6528.8979 | K31: =SUMIFS(Производительность!$E$250:$E$277,Производительность!$C$250:$C$277,K$19) -> 0 | L31: =SUMIFS(Производительность!$E$250:$E$277,Производительность!$C$250:$C$277,L$19) -> 0 | M31: =SUMIFS(Производительность!$E$250:$E$277,Производительность!$C$250:$C$277,M$19) -> 0 | ... O31: =SUMIFS(Производительность!$E$250:$E$277,Производительность!$C$250:$C$277,O$19) -> 0
C33: =MAX(C$20:C32)+1 -> 13 | D33: Стоимость станка | E33: тыс. руб. | F33: =F37+F38 -> 0 | G33: =G37+G38 -> 0 | H33: =H37+H38 -> 0 | I33: =I37+I38 -> 0 | J33: =J37+J38 -> 0 | K33: =K37+K38 -> 0 | L33: =L37+L38 -> 0 | M33: =M37+M38 -> 0 | ... O33: =O37+O38 -> 0 | R33: курс ЦБ на хх.07.2026
A34: заполнить | C34: =MAX(C$20:C33)+1 -> 14 | D34: Цена в долларах | E34: тыс. долл. | R34: 80
A35: заполнить | C35: =MAX(C$20:C34)+1 -> 15 | D35: Цена в евро | E35: тыс. евро | R35: 90
A36: заполнить | C36: =MAX(C$20:C35)+1 -> 16 | D36: Цена в юанях | E36: тыс. юаней | R36: 11
A37: заполнить | C37: =MAX(C$20:C36)+1 -> 17 | D37: Цена в рублях | E37: =E33 -> тыс. руб.
A38: заполнить | C38: =MAX(C$20:C37)+1 -> 18 | D38: Сборка | E38: =E33 -> тыс. руб.
A40: заполнить | C40: =MAX(C$20:C39)+1 -> 19 | D40: Потребность | E40: ед.
C41: =MAX(C$20:C40)+1 -> 20 | D41: CAPEX на потребность | E41: =E33 -> тыс. руб. | F41: =F40*F33 -> 0 | G41: =G40*G33 -> 0 | H41: =H40*H33 -> 0 | I41: =I40*I33 -> 0 | J41: =J40*J33 -> 0 | K41: =K40*K33 -> 0 | L41: =L40*L33 -> 0 | M41: =M40*M33 -> 0 | ... O41: =O40*O33 -> 0
C43: =MAX(C$20:C42)+1 -> 21 | D43: Среднегодовые затраты на ТО (включая смазочные) и ремонты | E43: тыс. руб. | F43: =SUMIFS('ТСО_250-270_диз'!$AB:$AB,'ТСО_250-270_диз'!$A:$A,F$19) -> 50139.665 | G43: =SUMIFS('ТСО_250-270_диз'!$AB:$AB,'ТСО_250-270_диз'!$A:$A,G$19) -> 49385.811 | H43: =SUMIFS('ТСО_250-270_диз'!$AB:$AB,'ТСО_250-270_диз'!$A:$A,H$19) -> 49385.811 | I43: =SUMIFS('ТСО_250-270_диз'!$AB:$AB,'ТСО_250-270_диз'!$A:$A,I$19) -> 28597.333 | J43: =SUMIFS('ТСО_250-270_диз'!$AB:$AB,'ТСО_250-270_диз'!$A:$A,J$19) -> 66898.704 | K43: =SUMIFS('ТСО_250-270_диз'!$AB:$AB,'ТСО_250-270_диз'!$A:$A,K$19) -> 0 | L43: =SUMIFS('ТСО_250-270_диз'!$AB:$AB,'ТСО_250-270_диз'!$A:$A,L$19) -> 0 | M43: =SUMIFS('ТСО_250-270_диз'!$AB:$AB,'ТСО_250-270_диз'!$A:$A,M$19) -> 0 | ... O43: =SUMIFS('ТСО_250-270_диз'!$AB:$AB,'ТСО_250-270_диз'!$A:$A,O$19) -> 0
A45: ='ТСО_250-270_диз'!B87 -> Аннуитет операционный | C45: =MAX(C$20:C44)+1 -> 22 | D45: ='ТСО_250-270_диз'!D87 -> Аннуитет операционный | E45: ='ТСО_250-270_диз'!E87 -> руб/м3 | F45: =SUMIFS('ТСО_250-270_диз'!$AC:$AC,'ТСО_250-270_диз'!$A:$A,F$19,'ТСО_250-270_диз'!$B:$B,$A45) -> 14.68475 | G45: =SUMIFS('ТСО_250-270_диз'!$AC:$AC,'ТСО_250-270_диз'!$A:$A,G$19,'ТСО_250-270_диз'!$B:$B,$A45) -> 12.086588 | H45: =SUMIFS('ТСО_250-270_диз'!$AC:$AC,'ТСО_250-270_диз'!$A:$A,H$19,'ТСО_250-270_диз'!$B:$B,$A45) -> 13.768153 | I45: =SUMIFS('ТСО_250-270_диз'!$AC:$AC,'ТСО_250-270_диз'!$A:$A,I$19,'ТСО_250-270_диз'!$B:$B,$A45) -> 11.045801 | J45: =SUMIFS('ТСО_250-270_диз'!$AC:$AC,'ТСО_250-270_диз'!$A:$A,J$19,'ТСО_250-270_диз'!$B:$B,$A45) -> 13.62781 | K45: =SUMIFS('ТСО_250-270_диз'!$AC:$AC,'ТСО_250-270_диз'!$A:$A,K$19,'ТСО_250-270_диз'!$B:$B,$A45) -> 0 | L45: =SUMIFS('ТСО_250-270_диз'!$AC:$AC,'ТСО_250-270_диз'!$A:$A,L$19,'ТСО_250-270_диз'!$B:$B,$A45) -> 0 | M45: =SUMIFS('ТСО_250-270_диз'!$AC:$AC,'ТСО_250-270_диз'!$A:$A,M$19,'ТСО_250-270_диз'!$B:$B,$A45) -> 0 | ... O45: =SUMIFS('ТСО_250-270_диз'!$AC:$AC,'ТСО_250-270_диз'!$A:$A,O$19,'ТСО_250-270_диз'!$B:$B,$A45) -> 0
A46: ='ТСО_250-270_диз'!B88 -> ТО, ТР, ППР | C46: =MAX(C$20:C45)+1 -> 23 | D46: ='ТСО_250-270_диз'!D88 -> ТО, ТР, ППР | E46: ='ТСО_250-270_диз'!E88 -> руб/м3 | F46: =SUMIFS('ТСО_250-270_диз'!$AC:$AC,'ТСО_250-270_диз'!$A:$A,F$19,'ТСО_250-270_диз'!$B:$B,$A46) -> 10.019176 | G46: =SUMIFS('ТСО_250-270_диз'!$AC:$AC,'ТСО_250-270_диз'!$A:$A,G$19,'ТСО_250-270_диз'!$B:$B,$A46) -> 8.432075 | H46: =SUMIFS('ТСО_250-270_диз'!$AC:$AC,'ТСО_250-270_диз'!$A:$A,H$19,'ТСО_250-270_диз'!$B:$B,$A46) -> 9.6052002 | I46: =SUMIFS('ТСО_250-270_диз'!$AC:$AC,'ТСО_250-270_диз'!$A:$A,I$19,'ТСО_250-270_диз'!$B:$B,$A46) -> 5.4633445 | J46: =SUMIFS('ТСО_250-270_диз'!$AC:$AC,'ТСО_250-270_диз'!$A:$A,J$19,'ТСО_250-270_диз'!$B:$B,$A46) -> 10.571834 | K46: =SUMIFS('ТСО_250-270_диз'!$AC:$AC,'ТСО_250-270_диз'!$A:$A,K$19,'ТСО_250-270_диз'!$B:$B,$A46) -> 0 | L46: =SUMIFS('ТСО_250-270_диз'!$AC:$AC,'ТСО_250-270_диз'!$A:$A,L$19,'ТСО_250-270_диз'!$B:$B,$A46) -> 0 | M46: =SUMIFS('ТСО_250-270_диз'!$AC:$AC,'ТСО_250-270_диз'!$A:$A,M$19,'ТСО_250-270_диз'!$B:$B,$A46) -> 0 | ... O46: =SUMIFS('ТСО_250-270_диз'!$AC:$AC,'ТСО_250-270_диз'!$A:$A,O$19,'ТСО_250-270_диз'!$B:$B,$A46) -> 0
A47: ='ТСО_250-270_диз'!B89 -> Смазочные | C47: =MAX(C$20:C46)+1 -> 24 | D47: ='ТСО_250-270_диз'!D89 -> Смазочные | E47: ='ТСО_250-270_диз'!E89 -> руб/м3 | F47: =SUMIFS('ТСО_250-270_диз'!$AC:$AC,'ТСО_250-270_диз'!$A:$A,F$19,'ТСО_250-270_диз'!$B:$B,$A47) -> 0 | G47: =SUMIFS('ТСО_250-270_диз'!$AC:$AC,'ТСО_250-270_диз'!$A:$A,G$19,'ТСО_250-270_диз'!$B:$B,$A47) -> 0 | H47: =SUMIFS('ТСО_250-270_диз'!$AC:$AC,'ТСО_250-270_диз'!$A:$A,H$19,'ТСО_250-270_диз'!$B:$B,$A47) -> 0 | I47: =SUMIFS('ТСО_250-270_диз'!$AC:$AC,'ТСО_250-270_диз'!$A:$A,I$19,'ТСО_250-270_диз'!$B:$B,$A47) -> 0 | J47: =SUMIFS('ТСО_250-270_диз'!$AC:$AC,'ТСО_250-270_диз'!$A:$A,J$19,'ТСО_250-270_диз'!$B:$B,$A47) -> 0 | K47: =SUMIFS('ТСО_250-270_диз'!$AC:$AC,'ТСО_250-270_диз'!$A:$A,K$19,'ТСО_250-270_диз'!$B:$B,$A47) -> 0 | L47: =SUMIFS('ТСО_250-270_диз'!$AC:$AC,'ТСО_250-270_диз'!$A:$A,L$19,'ТСО_250-270_диз'!$B:$B,$A47) -> 0 | M47: =SUMIFS('ТСО_250-270_диз'!$AC:$AC,'ТСО_250-270_диз'!$A:$A,M$19,'ТСО_250-270_диз'!$B:$B,$A47) -> 0 | ... O47: =SUMIFS('ТСО_250-270_диз'!$AC:$AC,'ТСО_250-270_диз'!$A:$A,O$19,'ТСО_250-270_диз'!$B:$B,$A47) -> 0
A48: ='ТСО_250-270_диз'!B90 -> Долота | C48: =MAX(C$20:C47)+1 -> 25 | D48: ='ТСО_250-270_диз'!D90 -> Долота | E48: ='ТСО_250-270_диз'!E90 -> руб/м3 | F48: =SUMIFS('ТСО_250-270_диз'!$AC:$AC,'ТСО_250-270_диз'!$A:$A,F$19,'ТСО_250-270_диз'!$B:$B,$A48) -> 0 | G48: =SUMIFS('ТСО_250-270_диз'!$AC:$AC,'ТСО_250-270_диз'!$A:$A,G$19,'ТСО_250-270_диз'!$B:$B,$A48) -> 0 | H48: =SUMIFS('ТСО_250-270_диз'!$AC:$AC,'ТСО_250-270_диз'!$A:$A,H$19,'ТСО_250-270_диз'!$B:$B,$A48) -> 0 | I48: =SUMIFS('ТСО_250-270_диз'!$AC:$AC,'ТСО_250-270_диз'!$A:$A,I$19,'ТСО_250-270_диз'!$B:$B,$A48) -> 0 | J48: =SUMIFS('ТСО_250-270_диз'!$AC:$AC,'ТСО_250-270_диз'!$A:$A,J$19,'ТСО_250-270_диз'!$B:$B,$A48) -> 0 | K48: =SUMIFS('ТСО_250-270_диз'!$AC:$AC,'ТСО_250-270_диз'!$A:$A,K$19,'ТСО_250-270_диз'!$B:$B,$A48) -> 0 | L48: =SUMIFS('ТСО_250-270_диз'!$AC:$AC,'ТСО_250-270_диз'!$A:$A,L$19,'ТСО_250-270_диз'!$B:$B,$A48) -> 0 | M48: =SUMIFS('ТСО_250-270_диз'!$AC:$AC,'ТСО_250-270_диз'!$A:$A,M$19,'ТСО_250-270_диз'!$B:$B,$A48) -> 0 | ... O48: =SUMIFS('ТСО_250-270_диз'!$AC:$AC,'ТСО_250-270_диз'!$A:$A,O$19,'ТСО_250-270_диз'!$B:$B,$A48) -> 0
A49: ='ТСО_250-270_диз'!B91 -> Штанги буровые | C49: =MAX(C$20:C48)+1 -> 26 | D49: ='ТСО_250-270_диз'!D91 -> Штанги буровые | E49: ='ТСО_250-270_диз'!E91 -> руб/м3 | F49: =SUMIFS('ТСО_250-270_диз'!$AC:$AC,'ТСО_250-270_диз'!$A:$A,F$19,'ТСО_250-270_диз'!$B:$B,$A49) -> 0 | G49: =SUMIFS('ТСО_250-270_диз'!$AC:$AC,'ТСО_250-270_диз'!$A:$A,G$19,'ТСО_250-270_диз'!$B:$B,$A49) -> 0 | H49: =SUMIFS('ТСО_250-270_диз'!$AC:$AC,'ТСО_250-270_диз'!$A:$A,H$19,'ТСО_250-270_диз'!$B:$B,$A49) -> 0 | I49: =SUMIFS('ТСО_250-270_диз'!$AC:$AC,'ТСО_250-270_диз'!$A:$A,I$19,'ТСО_250-270_диз'!$B:$B,$A49) -> 0 | J49: =SUMIFS('ТСО_250-270_диз'!$AC:$AC,'ТСО_250-270_диз'!$A:$A,J$19,'ТСО_250-270_диз'!$B:$B,$A49) -> 0 | K49: =SUMIFS('ТСО_250-270_диз'!$AC:$AC,'ТСО_250-270_диз'!$A:$A,K$19,'ТСО_250-270_диз'!$B:$B,$A49) -> 0 | L49: =SUMIFS('ТСО_250-270_диз'!$AC:$AC,'ТСО_250-270_диз'!$A:$A,L$19,'ТСО_250-270_диз'!$B:$B,$A49) -> 0 | M49: =SUMIFS('ТСО_250-270_диз'!$AC:$AC,'ТСО_250-270_диз'!$A:$A,M$19,'ТСО_250-270_диз'!$B:$B,$A49) -> 0 | ... O49: =SUMIFS('ТСО_250-270_диз'!$AC:$AC,'ТСО_250-270_диз'!$A:$A,O$19,'ТСО_250-270_диз'!$B:$B,$A49) -> 0
A50: ='ТСО_250-270_диз'!B92 -> Расходники | C50: =MAX(C$20:C49)+1 -> 27 | D50: ='ТСО_250-270_диз'!D92 -> Расходники | E50: ='ТСО_250-270_диз'!E92 -> руб/м3 | F50: =SUMIFS('ТСО_250-270_диз'!$AC:$AC,'ТСО_250-270_диз'!$A:$A,F$19,'ТСО_250-270_диз'!$B:$B,$A50) -> 0 | G50: =SUMIFS('ТСО_250-270_диз'!$AC:$AC,'ТСО_250-270_диз'!$A:$A,G$19,'ТСО_250-270_диз'!$B:$B,$A50) -> 0 | H50: =SUMIFS('ТСО_250-270_диз'!$AC:$AC,'ТСО_250-270_диз'!$A:$A,H$19,'ТСО_250-270_диз'!$B:$B,$A50) -> 0 | I50: =SUMIFS('ТСО_250-270_диз'!$AC:$AC,'ТСО_250-270_диз'!$A:$A,I$19,'ТСО_250-270_диз'!$B:$B,$A50) -> 0 | J50: =SUMIFS('ТСО_250-270_диз'!$AC:$AC,'ТСО_250-270_диз'!$A:$A,J$19,'ТСО_250-270_диз'!$B:$B,$A50) -> 0 | K50: =SUMIFS('ТСО_250-270_диз'!$AC:$AC,'ТСО_250-270_диз'!$A:$A,K$19,'ТСО_250-270_диз'!$B:$B,$A50) -> 0 | L50: =SUMIFS('ТСО_250-270_диз'!$AC:$AC,'ТСО_250-270_диз'!$A:$A,L$19,'ТСО_250-270_диз'!$B:$B,$A50) -> 0 | M50: =SUMIFS('ТСО_250-270_диз'!$AC:$AC,'ТСО_250-270_диз'!$A:$A,M$19,'ТСО_250-270_диз'!$B:$B,$A50) -> 0 | ... O50: =SUMIFS('ТСО_250-270_диз'!$AC:$AC,'ТСО_250-270_диз'!$A:$A,O$19,'ТСО_250-270_диз'!$B:$B,$A50) -> 0
A51: ='ТСО_250-270_диз'!B93 -> Топливо/Электроэнергия | C51: =MAX(C$20:C50)+1 -> 28 | D51: ='ТСО_250-270_диз'!D93 -> Топливо/Электроэнергия | E51: ='ТСО_250-270_диз'!E93 -> руб/м3 | F51: =SUMIFS('ТСО_250-270_диз'!$AC:$AC,'ТСО_250-270_диз'!$A:$A,F$19,'ТСО_250-270_диз'!$B:$B,$A51) -> 6.2327336 | G51: =SUMIFS('ТСО_250-270_диз'!$AC:$AC,'ТСО_250-270_диз'!$A:$A,G$19,'ТСО_250-270_диз'!$B:$B,$A51) -> 5.0057891 | H51: =SUMIFS('ТСО_250-270_диз'!$AC:$AC,'ТСО_250-270_диз'!$A:$A,H$19,'ТСО_250-270_диз'!$B:$B,$A51) -> 5.702227 | I51: =SUMIFS('ТСО_250-270_диз'!$AC:$AC,'ТСО_250-270_диз'!$A:$A,I$19,'ТСО_250-270_диз'!$B:$B,$A51) -> 6.1470539 | J51: =SUMIFS('ТСО_250-270_диз'!$AC:$AC,'ТСО_250-270_диз'!$A:$A,J$19,'ТСО_250-270_диз'!$B:$B,$A51) -> 5.0259821 | K51: =SUMIFS('ТСО_250-270_диз'!$AC:$AC,'ТСО_250-270_диз'!$A:$A,K$19,'ТСО_250-270_диз'!$B:$B,$A51) -> 0 | L51: =SUMIFS('ТСО_250-270_диз'!$AC:$AC,'ТСО_250-270_диз'!$A:$A,L$19,'ТСО_250-270_диз'!$B:$B,$A51) -> 0 | M51: =SUMIFS('ТСО_250-270_диз'!$AC:$AC,'ТСО_250-270_диз'!$A:$A,M$19,'ТСО_250-270_диз'!$B:$B,$A51) -> 0 | ... O51: =SUMIFS('ТСО_250-270_диз'!$AC:$AC,'ТСО_250-270_диз'!$A:$A,O$19,'ТСО_250-270_диз'!$B:$B,$A51) -> 0
A52: ='ТСО_250-270_диз'!B94 -> Затраты на персонал | C52: =MAX(C$20:C51)+1 -> 29 | D52: ='ТСО_250-270_диз'!D94 -> Затраты на персонал | E52: ='ТСО_250-270_диз'!E94 -> руб/м3 | F52: =SUMIFS('ТСО_250-270_диз'!$AC:$AC,'ТСО_250-270_диз'!$A:$A,F$19,'ТСО_250-270_диз'!$B:$B,$A52) -> 3.3251807 | G52: =SUMIFS('ТСО_250-270_диз'!$AC:$AC,'ТСО_250-270_диз'!$A:$A,G$19,'ТСО_250-270_диз'!$B:$B,$A52) -> 2.6755426 | H52: =SUMIFS('ТСО_250-270_диз'!$AC:$AC,'ТСО_250-270_диз'!$A:$A,H$19,'ТСО_250-270_диз'!$B:$B,$A52) -> 3.0477815 | I52: =SUMIFS('ТСО_250-270_диз'!$AC:$AC,'ТСО_250-270_диз'!$A:$A,I$19,'ТСО_250-270_диз'!$B:$B,$A52) -> 3.1149572 | J52: =SUMIFS('ТСО_250-270_диз'!$AC:$AC,'ТСО_250-270_диз'!$A:$A,J$19,'ТСО_250-270_диз'!$B:$B,$A52) -> 2.5706336 | K52: =SUMIFS('ТСО_250-270_диз'!$AC:$AC,'ТСО_250-270_диз'!$A:$A,K$19,'ТСО_250-270_диз'!$B:$B,$A52) -> 0 | L52: =SUMIFS('ТСО_250-270_диз'!$AC:$AC,'ТСО_250-270_диз'!$A:$A,L$19,'ТСО_250-270_диз'!$B:$B,$A52) -> 0 | M52: =SUMIFS('ТСО_250-270_диз'!$AC:$AC,'ТСО_250-270_диз'!$A:$A,M$19,'ТСО_250-270_диз'!$B:$B,$A52) -> 0 | ... O52: =SUMIFS('ТСО_250-270_диз'!$AC:$AC,'ТСО_250-270_диз'!$A:$A,O$19,'ТСО_250-270_диз'!$B:$B,$A52) -> 0
A53: ='ТСО_250-270_диз'!B95 -> Транспортный налог | C53: =MAX(C$20:C52)+1 -> 30 | D53: ='ТСО_250-270_диз'!D95 -> Транспортный налог | E53: ='ТСО_250-270_диз'!E95 -> руб/м3 | F53: =SUMIFS('ТСО_250-270_диз'!$AC:$AC,'ТСО_250-270_диз'!$A:$A,F$19,'ТСО_250-270_диз'!$B:$B,$A53) -> 0.0025770261 | G53: =SUMIFS('ТСО_250-270_диз'!$AC:$AC,'ТСО_250-270_диз'!$A:$A,G$19,'ТСО_250-270_диз'!$B:$B,$A53) -> 0.0020436831 | H53: =SUMIFS('ТСО_250-270_диз'!$AC:$AC,'ТСО_250-270_диз'!$A:$A,H$19,'ТСО_250-270_диз'!$B:$B,$A53) -> 0.0023280136 | I53: =SUMIFS('ТСО_250-270_диз'!$AC:$AC,'ТСО_250-270_диз'!$A:$A,I$19,'ТСО_250-270_диз'!$B:$B,$A53) -> 0.002379325 | J53: =SUMIFS('ТСО_250-270_диз'!$AC:$AC,'ТСО_250-270_диз'!$A:$A,J$19,'ТСО_250-270_диз'!$B:$B,$A53) -> 0.0019635495 | K53: =SUMIFS('ТСО_250-270_диз'!$AC:$AC,'ТСО_250-270_диз'!$A:$A,K$19,'ТСО_250-270_диз'!$B:$B,$A53) -> 0 | L53: =SUMIFS('ТСО_250-270_диз'!$AC:$AC,'ТСО_250-270_диз'!$A:$A,L$19,'ТСО_250-270_диз'!$B:$B,$A53) -> 0 | M53: =SUMIFS('ТСО_250-270_диз'!$AC:$AC,'ТСО_250-270_диз'!$A:$A,M$19,'ТСО_250-270_диз'!$B:$B,$A53) -> 0 | ... O53: =SUMIFS('ТСО_250-270_диз'!$AC:$AC,'ТСО_250-270_диз'!$A:$A,O$19,'ТСО_250-270_диз'!$B:$B,$A53) -> 0
A54: ='ТСО_250-270_диз'!B96 -> Налог на прибыль | C54: =MAX(C$20:C53)+1 -> 31 | D54: ='ТСО_250-270_диз'!D96 -> Налог на прибыль | E54: ='ТСО_250-270_диз'!E96 -> руб/м3 | F54: =SUMIFS('ТСО_250-270_диз'!$AC:$AC,'ТСО_250-270_диз'!$A:$A,F$19,'ТСО_250-270_диз'!$B:$B,$A54) -> -4.8949168 | G54: =SUMIFS('ТСО_250-270_диз'!$AC:$AC,'ТСО_250-270_диз'!$A:$A,G$19,'ТСО_250-270_диз'!$B:$B,$A54) -> -4.0288626 | H54: =SUMIFS('ТСО_250-270_диз'!$AC:$AC,'ТСО_250-270_диз'!$A:$A,H$19,'ТСО_250-270_диз'!$B:$B,$A54) -> -4.5893842 | I54: =SUMIFS('ТСО_250-270_диз'!$AC:$AC,'ТСО_250-270_диз'!$A:$A,I$19,'ТСО_250-270_диз'!$B:$B,$A54) -> -3.6819338 | J54: =SUMIFS('ТСО_250-270_диз'!$AC:$AC,'ТСО_250-270_диз'!$A:$A,J$19,'ТСО_250-270_диз'!$B:$B,$A54) -> -4.5426033 | K54: =SUMIFS('ТСО_250-270_диз'!$AC:$AC,'ТСО_250-270_диз'!$A:$A,K$19,'ТСО_250-270_диз'!$B:$B,$A54) -> 0 | L54: =SUMIFS('ТСО_250-270_диз'!$AC:$AC,'ТСО_250-270_диз'!$A:$A,L$19,'ТСО_250-270_диз'!$B:$B,$A54) -> 0 | M54: =SUMIFS('ТСО_250-270_диз'!$AC:$AC,'ТСО_250-270_диз'!$A:$A,M$19,'ТСО_250-270_диз'!$B:$B,$A54) -> 0 | ... O54: =SUMIFS('ТСО_250-270_диз'!$AC:$AC,'ТСО_250-270_диз'!$A:$A,O$19,'ТСО_250-270_диз'!$B:$B,$A54) -> 0
A55: ='ТСО_250-270_диз'!B97 -> Аннуитет инвестиционный | C55: =MAX(C$20:C54)+1 -> 32 | D55: ='ТСО_250-270_диз'!D97 -> Аннуитет инвестиционный | E55: ='ТСО_250-270_диз'!E97 -> руб/м3 | F55: =SUMIFS('ТСО_250-270_диз'!$AC:$AC,'ТСО_250-270_диз'!$A:$A,F$19,'ТСО_250-270_диз'!$B:$B,$A55) -> 0 | G55: =SUMIFS('ТСО_250-270_диз'!$AC:$AC,'ТСО_250-270_диз'!$A:$A,G$19,'ТСО_250-270_диз'!$B:$B,$A55) -> 0 | H55: =SUMIFS('ТСО_250-270_диз'!$AC:$AC,'ТСО_250-270_диз'!$A:$A,H$19,'ТСО_250-270_диз'!$B:$B,$A55) -> 0 | I55: =SUMIFS('ТСО_250-270_диз'!$AC:$AC,'ТСО_250-270_диз'!$A:$A,I$19,'ТСО_250-270_диз'!$B:$B,$A55) -> 0 | J55: =SUMIFS('ТСО_250-270_диз'!$AC:$AC,'ТСО_250-270_диз'!$A:$A,J$19,'ТСО_250-270_диз'!$B:$B,$A55) -> 0 | K55: =SUMIFS('ТСО_250-270_диз'!$AC:$AC,'ТСО_250-270_диз'!$A:$A,K$19,'ТСО_250-270_диз'!$B:$B,$A55) -> 0 | L55: =SUMIFS('ТСО_250-270_диз'!$AC:$AC,'ТСО_250-270_диз'!$A:$A,L$19,'ТСО_250-270_диз'!$B:$B,$A55) -> 0 | M55: =SUMIFS('ТСО_250-270_диз'!$AC:$AC,'ТСО_250-270_диз'!$A:$A,M$19,'ТСО_250-270_диз'!$B:$B,$A55) -> 0 | ... O55: =SUMIFS('ТСО_250-270_диз'!$AC:$AC,'ТСО_250-270_диз'!$A:$A,O$19,'ТСО_250-270_диз'!$B:$B,$A55) -> 0
A56: ='ТСО_250-270_диз'!B99 -> Аннуитет общий | C56: =MAX(C$20:C55)+1 -> 33 | D56: ='ТСО_250-270_диз'!D99 -> Аннуитет общий | E56: ='ТСО_250-270_диз'!E99 -> руб/м3 | F56: =SUMIFS('ТСО_250-270_диз'!$AC:$AC,'ТСО_250-270_диз'!$A:$A,F$19,'ТСО_250-270_диз'!$B:$B,$A56) -> 14.68475 | G56: =SUMIFS('ТСО_250-270_диз'!$AC:$AC,'ТСО_250-270_диз'!$A:$A,G$19,'ТСО_250-270_диз'!$B:$B,$A56) -> 12.086588 | H56: =SUMIFS('ТСО_250-270_диз'!$AC:$AC,'ТСО_250-270_диз'!$A:$A,H$19,'ТСО_250-270_диз'!$B:$B,$A56) -> 13.768153 | I56: =SUMIFS('ТСО_250-270_диз'!$AC:$AC,'ТСО_250-270_диз'!$A:$A,I$19,'ТСО_250-270_диз'!$B:$B,$A56) -> 11.045801 | J56: =SUMIFS('ТСО_250-270_диз'!$AC:$AC,'ТСО_250-270_диз'!$A:$A,J$19,'ТСО_250-270_диз'!$B:$B,$A56) -> 13.62781 | K56: =SUMIFS('ТСО_250-270_диз'!$AC:$AC,'ТСО_250-270_диз'!$A:$A,K$19,'ТСО_250-270_диз'!$B:$B,$A56) -> 0 | L56: =SUMIFS('ТСО_250-270_диз'!$AC:$AC,'ТСО_250-270_диз'!$A:$A,L$19,'ТСО_250-270_диз'!$B:$B,$A56) -> 0 | M56: =SUMIFS('ТСО_250-270_диз'!$AC:$AC,'ТСО_250-270_диз'!$A:$A,M$19,'ТСО_250-270_диз'!$B:$B,$A56) -> 0 | ... O56: =SUMIFS('ТСО_250-270_диз'!$AC:$AC,'ТСО_250-270_диз'!$A:$A,O$19,'ТСО_250-270_диз'!$B:$B,$A56) -> 0
F57: =F45-SUM(F46:F54)+F56-F45-F55 -> -1.7763568e-15 | G57: =G45-SUM(G46:G54)+G56-G45-G55 -> 0 | H57: =H45-SUM(H46:H54)+H56-H45-H55 -> 0 | I57: =I45-SUM(I46:I54)+I56-I45-I55 -> -5.3290705e-15 | J57: =J45-SUM(J46:J54)+J56-J45-J55 -> -1.7763568e-15 | K57: =K45-SUM(K46:K54)+K56-K45-K55 -> 0 | L57: =L45-SUM(L46:L54)+L56-L45-L55 -> 0 | M57: =M45-SUM(M46:M54)+M56-M45-M55 -> 0 | ... O57: =O45-SUM(O46:O54)+O56-O45-O55 -> 0
A58: для ранжирования | D58: =D56 -> Аннуитет общий | F58: =IF(F56>0,F56,"нет") -> 14.68475 | G58: =IF(G56>0,G56,"нет") -> 12.086588 | H58: =IF(H56>0,H56,"нет") -> 13.768153 | I58: =IF(I56>0,I56,"нет") -> 11.045801 | J58: =IF(J56>0,J56,"нет") -> 13.62781 | K58: =IF(K56>0,K56,"нет") -> нет | L58: =IF(L56>0,L56,"нет") -> нет | M58: =IF(M56>0,M56,"нет") -> нет | ... O58: =IF(O56>0,O56,"нет") -> нет
A59: =A58 -> для ранжирования | D59: =D33 -> Стоимость станка | F59: =IF(F33>0,F33,"нет") -> нет | G59: =IF(G33>0,G33,"нет") -> нет | H59: =IF(H33>0,H33,"нет") -> нет | I59: =IF(I33>0,I33,"нет") -> нет | J59: =IF(J33>0,J33,"нет") -> нет | K59: =IF(K33>0,K33,"нет") -> нет | L59: =IF(L33>0,L33,"нет") -> нет | M59: =IF(M33>0,M33,"нет") -> нет | ... O59: =IF(O33>0,O33,"нет") -> нет
A60: =A58 -> для ранжирования | F60: =F19 -> HIFO 75D | G60: =G19 -> Sunward SWDRT270SM | H60: =H19 -> Sunward SWDRT250SM | I60: =I19 -> YANGZI DR75 | J60: =J19 -> Sunward SWDRT270B | K60: =K19 -> 0 | L60: =L19 -> 0 | M60: =M19 -> 0 | ... O60: =O19 -> 0

Sheet ТСО_250-270_диз
A1: не удалять | B1: не удалять | C1: не удалять | D1: Показатель | E1: Ед. изм. | F1: =G1-1 -> 0 | G1: 1 | H1: =G1+1 -> 2 | I1: =H1+1 -> 3 | J1: =I1+1 -> 4 | K1: =J1+1 -> 5 | L1: =K1+1 -> 6 | M1: =L1+1 -> 7 | N1: =M1+1 -> 8 | O1: =N1+1 -> 9 | ... Z1: =Y1+1 -> 20 | AA1: не удалять | AB1: не удалять | AC1: не удалять
A2: * | F2: лет | G2: 2027 | H2: =G2+1 -> 2028 | I2: =H2+1 -> 2029 | J2: =I2+1 -> 2030 | K2: =J2+1 -> 2031 | L2: =K2+1 -> 2032 | M2: =L2+1 -> 2033 | N2: =M2+1 -> 2034 | O2: =N2+1 -> 2035 | ... Z2: =Y2+1 -> 2046 | AA2: проверки | AB2: средние на ТО, ТР, ППР | AC2: аннуитет
A3: * | G3: =Производительность!E6 -> 8760 | H3: =Производительность!F6 -> 8760 | I3: =Производительность!G6 -> 8760 | J3: =Производительность!H6 -> 8760 | K3: =Производительность!I6 -> 8760 | L3: =Производительность!J6 -> 8760 | M3: =Производительность!K6 -> 8760 | N3: =Производительность!L6 -> 8760 | ... Z3: =Производительность!X6 -> 8760
A4: * | D4: Расчет аннуитета
A5: *
A6: * | C6: =SUM(F66:Z66,F80:Z80,F101:Z101,AA48) -> #DIV/0! | D6: ='Свод_250-270_диз'!F19 -> HIFO 75D | E6: =SUMIFS(Производительность!$Y$7:$Y$34,Производительность!$C$7:$C$34,$D6) -> 10 | F6: =$F$2 -> лет
A7: *
A8: =D6 -> HIFO 75D | D8: =D$1 -> Показатель | E8: =E$1 -> Ед. изм. | F8: =F$1 -> 0 | G8: =G$1 -> 1 | H8: =H$1 -> 2 | I8: =I$1 -> 3 | J8: =J$1 -> 4 | K8: =K$1 -> 5 | ... Z8: =Z$1 -> 20
A9: =A8 -> HIFO 75D | D9: КТГ | E9: % | G9: =SUMIFS(Производительность!E$7:E$34,Производительность!$C$7:$C$34,$A9) -> 0.89322362 | H9: =SUMIFS(Производительность!F$7:F$34,Производительность!$C$7:$C$34,$A9) -> 0.8669947 | I9: =SUMIFS(Производительность!G$7:G$34,Производительность!$C$7:$C$34,$A9) -> 0.85358337 | J9: =SUMIFS(Производительность!H$7:H$34,Производительность!$C$7:$C$34,$A9) -> 0.86506358 | K9: =SUMIFS(Производительность!I$7:I$34,Производительность!$C$7:$C$34,$A9) -> 0.87024876 | L9: =SUMIFS(Производительность!J$7:J$34,Производительность!$C$7:$C$34,$A9) -> 0.84426956 | M9: =SUMIFS(Производительность!K$7:K$34,Производительность!$C$7:$C$34,$A9) -> 0.85844004 | N9: =SUMIFS(Производительность!L$7:L$34,Производительность!$C$7:$C$34,$A9) -> 0.8705795 | ... Z9: =SUMIFS(Производительность!X$7:X$34,Производительность!$C$7:$C$34,$A9) -> 0
A10: =A9 -> HIFO 75D | D10: КИО | E10: =E9 -> % | G10: =SUMIFS(Производительность!E$115:E$142,Производительность!$C$115:$C$142,$A10) -> 0.72212072 | H10: =SUMIFS(Производительность!F$115:F$142,Производительность!$C$115:$C$142,$A10) -> 0.70091613 | I10: =SUMIFS(Производительность!G$115:G$142,Производительность!$C$115:$C$142,$A10) -> 0.69007382 | J10: =SUMIFS(Производительность!H$115:H$142,Производительность!$C$115:$C$142,$A10) -> 0.69935492 | K10: =SUMIFS(Производительность!I$115:I$142,Производительность!$C$115:$C$142,$A10) -> 0.70354685 | L10: =SUMIFS(Производительность!J$115:J$142,Производительность!$C$115:$C$142,$A10) -> 0.68254414 | M10: =SUMIFS(Производительность!K$115:K$142,Производительность!$C$115:$C$142,$A10) -> 0.69400017 | N10: =SUMIFS(Производительность!L$115:L$142,Производительность!$C$115:$C$142,$A10) -> 0.70381423 | ... Z10: =SUMIFS(Производительность!X$115:X$142,Производительность!$C$115:$C$142,$A10) -> 0
A11: =A10 -> HIFO 75D | D11: Производительность_бурение | E11: тыс. п. м | G11: =SUMIFS(Производительность!E$196:E$223,Производительность!$C$196:$C$223,$A11) -> 103.17834 | H11: =SUMIFS(Производительность!F$196:F$223,Производительность!$C$196:$C$223,$A11) -> 100.14858 | I11: =SUMIFS(Производительность!G$196:G$223,Производительность!$C$196:$C$223,$A11) -> 98.599402 | J11: =SUMIFS(Производительность!H$196:H$223,Производительность!$C$196:$C$223,$A11) -> 99.925508 | K11: =SUMIFS(Производительность!I$196:I$223,Производительность!$C$196:$C$223,$A11) -> 100.52446 | L11: =SUMIFS(Производительность!J$196:J$223,Производительность!$C$196:$C$223,$A11) -> 97.523543 | M11: =SUMIFS(Производительность!K$196:K$223,Производительность!$C$196:$C$223,$A11) -> 99.160407 | N11: =SUMIFS(Производительность!L$196:L$223,Производительность!$C$196:$C$223,$A11) -> 100.56266 | ... Z11: =SUMIFS(Производительность!X$196:X$223,Производительность!$C$196:$C$223,$A11) -> 0
A12: =A11 -> HIFO 75D | D12: Производительность_взрывание | E12: тыс. м3 | G12: =SUMIFS(Производительность!E$250:E$277,Производительность!$C$250:$C$277,$A12) -> 5103.7424 | H12: =SUMIFS(Производительность!F$250:F$277,Производительность!$C$250:$C$277,$A12) -> 4863.4854 | I12: =SUMIFS(Производительность!G$250:G$277,Производительность!$C$250:$C$277,$A12) -> 4506.8915 | J12: =SUMIFS(Производительность!H$250:H$277,Производительность!$C$250:$C$277,$A12) -> 4873.1427 | K12: =SUMIFS(Производительность!I$250:I$277,Производительность!$C$250:$C$277,$A12) -> 4960.8765 | L12: =SUMIFS(Производительность!J$250:J$277,Производительность!$C$250:$C$277,$A12) -> 4351.3171 | M12: =SUMIFS(Производительность!K$250:K$277,Производительность!$C$250:$C$277,$A12) -> 4474.4237 | N12: =SUMIFS(Производительность!L$250:L$277,Производительность!$C$250:$C$277,$A12) -> 5046.2503 | ... Z12: =SUMIFS(Производительность!X$250:X$277,Производительность!$C$250:$C$277,$A12) -> 0
A13: =A12 -> HIFO 75D | D13: Производительность кумулятивная | E13: =E12 -> тыс. м3 | G13: =G12 -> 5103.7424 | H13: =IF(H12=0,0,G13+H12) -> 9967.2278 | I13: =IF(I12=0,0,H13+I12) -> 14474.119 | J13: =IF(J12=0,0,I13+J12) -> 19347.262 | K13: =IF(K12=0,0,J13+K12) -> 24308.138 | L13: =IF(L12=0,0,K13+L12) -> 28659.456 | M13: =IF(M12=0,0,L13+M12) -> 33133.879 | N13: =IF(N12=0,0,M13+N12) -> 38180.13 | O13: =IF(O12=0,0,N13+O12) -> 42770.024 | ... Z13: =IF(Z12=0,0,Y13+Z12) -> 0
A14: =A13 -> HIFO 75D
A15: =A14 -> HIFO 75D | D15: Операционный денежный поток | E15: тыс. руб. | F15: =F49+F50-F48 -> 0 | G15: =G49+G50-G48 -> 43231.297 | H15: =H49+H50-H48 -> 60466.293 | I15: =I49+I50-I48 -> 81883.568 | J15: =J49+J50-J48 -> 73213.857 | K15: =K49+K50-K48 -> 85328.553 | L15: =L49+L50-L48 -> 70939.222 | M15: =M49+M50-M48 -> 75775.388 | ... Z15: =Z49+Z50-Z48 -> 0
A16: =A15 -> HIFO 75D | D16: ТО, ТР, ППР | E16: =E15 -> тыс. руб. | G16: =(G17+G18+G19)*'ФОТ, МТР, макро'!AJ$8 -> 11524.785 | H16: =(H17+H18+H19)*'ФОТ, МТР, макро'!AK$8 -> 35397.298 | I16: =(I17+I18+I19)*'ФОТ, МТР, макро'!AL$8 -> 64410.026 | J16: =(J17+J18+J19)*'ФОТ, МТР, макро'!AM$8 -> 52459.763 | K16: =(K17+K18+K19)*'ФОТ, МТР, макро'!AN$8 -> 68436.249 | L16: =(L17+L18+L19)*'ФОТ, МТР, макро'!AO$8 -> 50134.496 | M16: =(M17+M18+M19)*'ФОТ, МТР, макро'!AP$8 -> 56100.524 | N16: =(N17+N18+N19)*'ФОТ, МТР, макро'!AQ$8 -> 55898.672 | ... P16: =(P17+P18+P19)*'ФОТ, МТР, макро'!AS$8 -> 26275.082 | AB16: =SUM(F16:Z16,F21:Z21)/E6 -> 50139.665
A17: =A16 -> HIFO 75D | D17: ТО (включая смазочные) | E17: тыс. евро | G17: ='HIFO 75D'!E22 -> 74.95522 | H17: ='HIFO 75D'!F22 -> 78.685549 | I17: ='HIFO 75D'!G22 -> 101.7663 | J17: ='HIFO 75D'!H22 -> 78.685549 | K17: ='HIFO 75D'!I22 -> 100.97287 | L17: ='HIFO 75D'!J22 -> 79.478976 | M17: ='HIFO 75D'!K22 -> 74.95522 | N17: ='HIFO 75D'!L22 -> 104.7032 | ... P17: ='HIFO 75D'!N22 -> 104.7032
A18: =A17 -> HIFO 75D | D18: ТР, ППР | E18: тыс. евро | G18: ='HIFO 75D'!E23+'HIFO 75D'!E24 -> 11.889202 | H18: ='HIFO 75D'!F23+'HIFO 75D'!F24 -> 259.727 | I18: ='HIFO 75D'!G23+'HIFO 75D'!G24 -> 552.01401 | J18: ='HIFO 75D'!H23+'HIFO 75D'!H24 -> 448.30258 | K18: ='HIFO 75D'!I23+'HIFO 75D'!I24 -> 606.23657 | L18: ='HIFO 75D'!J23+'HIFO 75D'!J24 -> 410.82589 | M18: ='HIFO 75D'!K23+'HIFO 75D'!K24 -> 489.03072 | N18: ='HIFO 75D'!L23+'HIFO 75D'!L24 -> 463.37235 | ... P18: ='HIFO 75D'!N23+'HIFO 75D'!N24 -> 124.8831
A19: =A18 -> HIFO 75D | D19: трудозатраты | E19: тыс. евро | G19: ='HIFO 75D'!E25+'HIFO 75D'!E26 -> 41.208749 | H19: ='HIFO 75D'!F25+'HIFO 75D'!F26 -> 54.890771 | I19: ='HIFO 75D'!G25+'HIFO 75D'!G26 -> 61.886648 | J19: ='HIFO 75D'!H25+'HIFO 75D'!H26 -> 55.898122 | K19: ='HIFO 75D'!I25+'HIFO 75D'!I26 -> 53.193327 | L19: ='HIFO 75D'!J25+'HIFO 75D'!J26 -> 66.745089 | M19: ='HIFO 75D'!K25+'HIFO 75D'!K26 -> 59.353219 | N19: ='HIFO 75D'!L25+'HIFO 75D'!L26 -> 53.020804 | ... P19: ='HIFO 75D'!N25+'HIFO 75D'!N26 -> 62.359061
A20: =A19 -> HIFO 75D | D20: % стоимости справочно | G20: =G16/$F53 -> #DIV/0! | H20: =H16/$F53 -> #DIV/0! | I20: =I16/$F53 -> #DIV/0! | J20: =J16/$F53 -> #DIV/0! | K20: =K16/$F53 -> #DIV/0! | L20: =L16/$F53 -> #DIV/0! | M20: =M16/$F53 -> #DIV/0! | N20: =N16/$F53 -> #DIV/0! | ... Z20: =Z16/$F53 -> #DIV/0! | AA20: =SUM(F16:Z16)/$F53 -> #DIV/0!
A21: =A20 -> HIFO 75D | D21: Смазочные | E21: =E15 -> тыс. руб.
A22: =A21 -> HIFO 75D
A23: =A22 -> HIFO 75D | D23: Долота | E23: =E15 -> тыс. руб. | G23: =G25*G26 -> 0 | H23: =H25*H26 -> 0 | I23: =I25*I26 -> 0 | J23: =J25*J26 -> 0 | K23: =K25*K26 -> 0 | L23: =L25*L26 -> 0 | M23: =M25*M26 -> 0 | N23: =N25*N26 -> 0 | ... Z23: =Z25*Z26 -> 0
A24: =A23 -> HIFO 75D | D24: удельный расход | E24: шт./тыс. п. м | F24: =SUMIFS('ФОТ, МТР, макро'!$B$4:$B$31,'ФОТ, МТР, макро'!$A$4:$A$31,$A24) -> 0 | G24: =F24 -> 0 | H24: =G24 -> 0 | I24: =H24 -> 0 | J24: =I24 -> 0 | K24: =J24 -> 0 | L24: =K24 -> 0 | M24: =L24 -> 0 | N24: =M24 -> 0 | ... Z24: =Y24 -> 0
A25: =A24 -> HIFO 75D | D25: расход за период | E25: шт. | G25: =G11*G24 -> 0 | H25: =H11*H24 -> 0 | I25: =I11*I24 -> 0 | J25: =J11*J24 -> 0 | K25: =K11*K24 -> 0 | L25: =L11*L24 -> 0 | M25: =M11*M24 -> 0 | N25: =N11*N24 -> 0 | ... Z25: =Z11*Z24 -> 0
A26: =A25 -> HIFO 75D | D26: цена | E26: тыс. руб./шт. | F26: =SUMIFS('ФОТ, МТР, макро'!$C$4:$C$31,'ФОТ, МТР, макро'!$A$4:$A$31,$A26) -> 0 | G26: =F26 -> 0 | H26: =G26 -> 0 | I26: =H26 -> 0 | J26: =I26 -> 0 | K26: =J26 -> 0 | L26: =K26 -> 0 | M26: =L26 -> 0 | N26: =M26 -> 0 | ... Z26: =Y26 -> 0
A27: =A26 -> HIFO 75D | D27: Штанги буровые | E27: =E15 -> тыс. руб. | G27: =G29*G30 -> 0 | H27: =H29*H30 -> 0 | I27: =I29*I30 -> 0 | J27: =J29*J30 -> 0 | K27: =K29*K30 -> 0 | L27: =L29*L30 -> 0 | M27: =M29*M30 -> 0 | N27: =N29*N30 -> 0 | ... Z27: =Z29*Z30 -> 0
A28: =A27 -> HIFO 75D | D28: удельный расход | E28: шт./тыс. п. м | F28: =SUMIFS('ФОТ, МТР, макро'!$E$4:$E$31,'ФОТ, МТР, макро'!$A$4:$A$31,$A28) -> 0 | G28: =F28 -> 0 | H28: =G28 -> 0 | I28: =H28 -> 0 | J28: =I28 -> 0 | K28: =J28 -> 0 | L28: =K28 -> 0 | M28: =L28 -> 0 | N28: =M28 -> 0 | ... Z28: =Y28 -> 0
A29: =A28 -> HIFO 75D | D29: расход за период | E29: шт. | G29: =G11*G28 -> 0 | H29: =H11*H28 -> 0 | I29: =I11*I28 -> 0 | J29: =J11*J28 -> 0 | K29: =K11*K28 -> 0 | L29: =L11*L28 -> 0 | M29: =M11*M28 -> 0 | N29: =N11*N28 -> 0 | ... Z29: =Z11*Z28 -> 0
A30: =A29 -> HIFO 75D | D30: цена | E30: тыс. руб./шт. | F30: =SUMIFS('ФОТ, МТР, макро'!$F$4:$F$31,'ФОТ, МТР, макро'!$A$4:$A$31,$A30) -> 0 | G30: =F30 -> 0 | H30: =G30 -> 0 | I30: =H30 -> 0 | J30: =I30 -> 0 | K30: =J30 -> 0 | L30: =K30 -> 0 | M30: =L30 -> 0 | N30: =M30 -> 0 | ... Z30: =Y30 -> 0
A31: =A30 -> HIFO 75D | D31: Расходники | E31: =E15 -> тыс. руб. | G31: =G11*G32 -> 0 | H31: =H11*H32 -> 0 | I31: =I11*I32 -> 0 | J31: =J11*J32 -> 0 | K31: =K11*K32 -> 0 | L31: =L11*L32 -> 0 | M31: =M11*M32 -> 0 | N31: =N11*N32 -> 0 | ... Z31: =Z11*Z32 -> 0
A32: =A31 -> HIFO 75D | D32: удельный расход | E32: руб./п. м | F32: =SUMIFS('ФОТ, МТР, макро'!$H$4:$H$31,'ФОТ, МТР, макро'!$A$4:$A$31,$A32) -> 0 | G32: =F32 -> 0 | H32: =G32 -> 0 | I32: =H32 -> 0 | J32: =I32 -> 0 | K32: =J32 -> 0 | L32: =K32 -> 0 | M32: =L32 -> 0 | N32: =M32 -> 0 | ... Z32: =Y32 -> 0
A33: =A32 -> HIFO 75D | C33: =SUMIFS('ФОТ, МТР, макро'!$N$4:$N$31,'ФОТ, МТР, макро'!$J$4:$J$31,$A33) -> 1 | D33: Топливо/Электроэнергия | E33: =E15 -> тыс. руб. | G33: =IF($C33=1,G34,G38) -> 30394.646 | H33: =IF($C33=1,H34,H38) -> 29502.128 | I33: =IF($C33=1,I34,I38) -> 29045.766 | J33: =IF($C33=1,J34,J38) -> 29436.416 | K33: =IF($C33=1,K34,K38) -> 29612.857 | L33: =IF($C33=1,L34,L38) -> 28728.836 | M33: =IF($C33=1,M34,M38) -> 29211.029 | N33: =IF($C33=1,N34,N38) -> 29624.111 | ... Z33: =IF($C33=1,Z34,Z38) -> 0
A34: =A33 -> HIFO 75D | D34: - расчет (1) | E34: =E33 -> тыс. руб. | G34: =G36*G37 -> 30394.646 | H34: =H36*H37 -> 29502.128 | I34: =I36*I37 -> 29045.766 | J34: =J36*J37 -> 29436.416 | K34: =K36*K37 -> 29612.857 | L34: =L36*L37 -> 28728.836 | M34: =M36*M37 -> 29211.029 | N34: =N36*N37 -> 29624.111 | ... Z34: =Z36*Z37 -> 0
A35: =A34 -> HIFO 75D | D35: удельный расход | E35: =VLOOKUP($A35,'ФОТ, МТР, макро'!$J$4:$N$31,2,FALSE) -> кг/час | F35: =SUMIFS('ФОТ, МТР, макро'!$L$4:$L$31,'ФОТ, МТР, макро'!$J$4:$J$31,$A35) -> 72.780455 | G35: =F35 -> 72.780455 | H35: =G35 -> 72.780455 | I35: =H35 -> 72.780455 | J35: =I35 -> 72.780455 | K35: =J35 -> 72.780455 | L35: =K35 -> 72.780455 | M35: =L35 -> 72.780455 | N35: =M35 -> 72.780455 | ... Z35: =Y35 -> 72.780455
A36: =A35 -> HIFO 75D | D36: расход за период | E36: =IF(E35="кг/час","т","тыс. кВт*ч") -> т | G36: =G$3*G10*G35/1000 -> 460.39297 | H36: =H$3*H10*H35/1000 -> 446.87384 | I36: =I$3*I10*I35/1000 -> 439.96125 | J36: =J$3*J10*J35/1000 -> 445.87848 | K36: =K$3*K10*K35/1000 -> 448.55107 | L36: =L$3*L10*L35/1000 -> 435.16065 | M36: =M$3*M10*M35/1000 -> 442.46452 | N36: =N$3*N10*N35/1000 -> 448.72154 | ... Z36: =Z$3*Z10*Z35/1000 -> 0
A37: =A36 -> HIFO 75D | D37: цена | E37: =IF(E36="т","тыс. руб./т","руб./кВт*ч") -> тыс. руб./т | F37: =IF(E36="т",'ФОТ, МТР, макро'!$Q$2,'ФОТ, МТР, макро'!$Q$15) -> 66.018919 | G37: =F37 -> 66.018919 | H37: =G37 -> 66.018919 | I37: =H37 -> 66.018919 | J37: =I37 -> 66.018919 | K37: =J37 -> 66.018919 | L37: =K37 -> 66.018919 | M37: =L37 -> 66.018919 | N37: =M37 -> 66.018919 | ... Z37: =Y37 -> 66.018919
A38: =A37 -> HIFO 75D | D38: - поставщик (2) | E38: =E34 -> тыс. руб. | G38: =G40*G41 -> 39047.563 | H38: =H40*H41 -> 37900.958 | I38: =I40*I41 -> 37314.677 | J38: =J40*J41 -> 37816.538 | K38: =K40*K41 -> 38043.21 | L38: =L40*L41 -> 36907.521 | M38: =M40*M41 -> 37526.988 | N38: =N40*N41 -> 38057.668 | ... Z38: =Z40*Z41 -> 0
A39: =A38 -> HIFO 75D | D39: удельный расход | E39: =E35 -> кг/час | F39: =SUMIFS('ФОТ, МТР, макро'!$M$4:$M$31,'ФОТ, МТР, макро'!$J$4:$J$31,$A39) -> 93.5 | G39: =F39 -> 93.5 | H39: =G39 -> 93.5 | I39: =H39 -> 93.5 | J39: =I39 -> 93.5 | K39: =J39 -> 93.5 | L39: =K39 -> 93.5 | M39: =L39 -> 93.5 | N39: =M39 -> 93.5 | ... Z39: =Y39 -> 93.5
A40: =A39 -> HIFO 75D | D40: расход за период | E40: =E36 -> т | G40: =G$3*G10*G39/1000 -> 591.4602 | H40: =H$3*H10*H39/1000 -> 574.09237 | I40: =I$3*I10*I39/1000 -> 565.21186 | J40: =J$3*J10*J39/1000 -> 572.81364 | K40: =K$3*K10*K39/1000 -> 576.24709 | L40: =L$3*L10*L39/1000 -> 559.04461 | M40: =M$3*M10*M39/1000 -> 568.42778 | N40: =N$3*N10*N39/1000 -> 576.46609 | ... Z40: =Z$3*Z10*Z39/1000 -> 0
A41: =A40 -> HIFO 75D | D41: цена | E41: =E37 -> тыс. руб./т | G41: =G37 -> 66.018919 | H41: =H37 -> 66.018919 | I41: =I37 -> 66.018919 | J41: =J37 -> 66.018919 | K41: =K37 -> 66.018919 | L41: =L37 -> 66.018919 | M41: =M37 -> 66.018919 | N41: =N37 -> 66.018919 | ... Z41: =Z37 -> 66.018919
A42: =A41 -> HIFO 75D | D42: Затраты на персонал | E42: =E15 -> тыс. руб. | G42: =G43+G44 -> 15710.122 | H42: =H43+H44 -> 15710.122 | I42: =I43+I44 -> 15710.122 | J42: =J43+J44 -> 15710.122 | K42: =K43+K44 -> 15710.122 | L42: =L43+L44 -> 15710.122 | M42: =M43+M44 -> 15710.122 | N42: =N43+N44 -> 15710.122 | ... Z42: =Z43+Z44 -> 0
A43: =A42 -> HIFO 75D | D43: ФОТ с отчислениями | E43: =E42 -> тыс. руб. | F43: =SUMIFS('ФОТ, МТР, макро'!$X$4:$X$31,'ФОТ, МТР, макро'!$W$4:$W$31,$A43) -> 12529.553 | G43: =IF(G11=0,0,$F43) -> 12529.553 | H43: =IF(H11=0,0,$F43) -> 12529.553 | I43: =IF(I11=0,0,$F43) -> 12529.553 | J43: =IF(J11=0,0,$F43) -> 12529.553 | K43: =IF(K11=0,0,$F43) -> 12529.553 | L43: =IF(L11=0,0,$F43) -> 12529.553 | M43: =IF(M11=0,0,$F43) -> 12529.553 | N43: =IF(N11=0,0,$F43) -> 12529.553 | ... Z43: =IF(Z11=0,0,$F43) -> 0
A44: =A43 -> HIFO 75D | D44: прочее | F44: =SUMIFS('ФОТ, МТР, макро'!$Y$4:$Y$31,'ФОТ, МТР, макро'!$W$4:$W$31,$A44) -> 3180.5687 | G44: =IF(G11=0,0,$F44) -> 3180.5687 | H44: =IF(H11=0,0,$F44) -> 3180.5687 | I44: =IF(I11=0,0,$F44) -> 3180.5687 | J44: =IF(J11=0,0,$F44) -> 3180.5687 | K44: =IF(K11=0,0,$F44) -> 3180.5687 | L44: =IF(L11=0,0,$F44) -> 3180.5687 | M44: =IF(M11=0,0,$F44) -> 3180.5687 | N44: =IF(N11=0,0,$F44) -> 3180.5687 | ... Z44: =IF(Z11=0,0,$F44) -> 0
A45: =A44 -> HIFO 75D | D45: Транспортный налог | E45: =E15 -> тыс. руб. | G45: =IF(G11=0,0,G46*G47/1000) -> 12.175397 | H45: =IF(H11=0,0,H46*H47/1000) -> 12.175397 | I45: =IF(I11=0,0,I46*I47/1000) -> 12.175397 | J45: =IF(J11=0,0,J46*J47/1000) -> 12.175397 | K45: =IF(K11=0,0,K46*K47/1000) -> 12.175397 | L45: =IF(L11=0,0,L46*L47/1000) -> 12.175397 | M45: =IF(M11=0,0,M46*M47/1000) -> 12.175397 | N45: =IF(N11=0,0,N46*N47/1000) -> 12.175397 | ... Z45: =IF(Z11=0,0,Z46*Z47/1000) -> 0
A46: =A45 -> HIFO 75D | D46: мощность двигателя | E46: л.с. | F46: =SUMIFS('ФОТ, МТР, макро'!$AB$4:$AB$31,'ФОТ, МТР, макро'!$W$4:$W$31,$A46) -> 811.69314 | G46: =F46 -> 811.69314 | H46: =G46 -> 811.69314 | I46: =H46 -> 811.69314 | J46: =I46 -> 811.69314 | K46: =J46 -> 811.69314 | L46: =K46 -> 811.69314 | M46: =L46 -> 811.69314 | N46: =M46 -> 811.69314 | ... Z46: =Y46 -> 811.69314
A47: =A46 -> HIFO 75D | D47: налоговая ставка | E47: руб./л.с. | F47: =SUMIFS('ФОТ, МТР, макро'!$AC$4:$AC$31,'ФОТ, МТР, макро'!$W$4:$W$31,$A47) -> 15 | G47: =F47 -> 15 | H47: =G47 -> 15 | I47: =H47 -> 15 | J47: =I47 -> 15 | K47: =J47 -> 15 | L47: =K47 -> 15 | M47: =L47 -> 15 | N47: =M47 -> 15 | ... Z47: =Y47 -> 15
A48: =A47 -> HIFO 75D | C48: =SUMIFS('ФОТ, МТР, макро'!$AF$4:$AF$31,'ФОТ, МТР, макро'!$W$4:$W$31,$A48) -> 19.672131 | D48: Амортизация НУ | E48: =E15 -> тыс. руб. | G48: =IF(G8<=$C49,$F53*$C48%,"ОШИБКА") -> 0 | H48: =IF(H8<=$C49,$F53*$C48%,$F53-SUM($G48:G48)) -> 0 | I48: =IF(I8<=$C49,$F53*$C48%,$F53-SUM($G48:H48)) -> 0 | J48: =IF(J8<=$C49,$F53*$C48%,$F53-SUM($G48:I48)) -> 0 | K48: =IF(K8<=$C49,$F53*$C48%,$F53-SUM($G48:J48)) -> 0 | L48: =IF(L8<=$C49,$F53*$C48%,$F53-SUM($G48:K48)) -> 0 | M48: =IF(M8<=$C49,$F53*$C48%,$F53-SUM($G48:L48)) -> 0 | N48: =IF(N8<=$C49,$F53*$C48%,$F53-SUM($G48:M48)) -> 0 | O48: =IF(O8<=$C49,$F53*$C48%,$F53-SUM($G48:N48)) -> 0 | ... Z48: =IF(Z8<=$C49,$F53*$C48%,$F53-SUM($G48:Y48)) -> 0
A49: =A48 -> HIFO 75D | C49: =SUMIFS('ФОТ, МТР, макро'!$AE$4:$AE$31,'ФОТ, МТР, макро'!$W$4:$W$31,$A49)/12 -> 5.0833333 | D49: Налогооблагаемая база (по налогу на прибыль) | E49: =E15 -> тыс. руб. | G49: =SUM(G16,G21,G23,G27,G31,G33,G42,G45,G48) -> 57641.729 | H49: =SUM(H16,H21,H23,H27,H31,H33,H42,H45,H48) -> 80621.724 | I49: =SUM(I16,I21,I23,I27,I31,I33,I42,I45,I48) -> 109178.09 | J49: =SUM(J16,J21,J23,J27,J31,J33,J42,J45,J48) -> 97618.476 | K49: =SUM(K16,K21,K23,K27,K31,K33,K42,K45,K48) -> 113771.4 | L49: =SUM(L16,L21,L23,L27,L31,L33,L42,L45,L48) -> 94585.63 | M49: =SUM(M16,M21,M23,M27,M31,M33,M42,M45,M48) -> 101033.85 | N49: =SUM(N16,N21,N23,N27,N31,N33,N42,N45,N48) -> 101245.08 | ... Z49: =SUM(Z16,Z21,Z23,Z27,Z31,Z33,Z42,Z45,Z48) -> 0
A50: =A49 -> HIFO 75D | D50: Налог на прибыль | E50: =E15 -> тыс. руб. | G50: =-G49*'ФОТ, МТР, макро'!AJ$12 -> -14410.432 | H50: =-H49*'ФОТ, МТР, макро'!AK$12 -> -20155.431 | I50: =-I49*'ФОТ, МТР, макро'!AL$12 -> -27294.523 | J50: =-J49*'ФОТ, МТР, макро'!AM$12 -> -24404.619 | K50: =-K49*'ФОТ, МТР, макро'!AN$12 -> -28442.851 | L50: =-L49*'ФОТ, МТР, макро'!AO$12 -> -23646.407 | M50: =-M49*'ФОТ, МТР, макро'!AP$12 -> -25258.463 | N50: =-N49*'ФОТ, МТР, макро'!AQ$12 -> -25311.27 | ... Z50: =-Z49*'ФОТ, МТР, макро'!BC$12 -> 0
A51: =A50 -> HIFO 75D
A52: =A51 -> HIFO 75D | D52: Инвестиционный денежный поток | E52: =E15 -> тыс. руб. | F52: =F53 -> 0 | G52: =G53 -> 0 | H52: =H53 -> 0 | I52: =I53 -> 0 | J52: =J53 -> 0 | K52: =K53 -> 0 | L52: =L53 -> 0 | M52: =M53 -> 0 | ... Z52: =Z53 -> 0
A53: =A52 -> HIFO 75D | D53: Буровой станок | E53: =E52 -> тыс. руб. | F53: =SUMIFS('Свод_250-270_диз'!$D$33:$P$33,'Свод_250-270_диз'!$D$19:$P$19,$A53) -> 0
A54: =A53 -> HIFO 75D
A55: =A54 -> HIFO 75D | D55: Денежный поток | E55: =E15 -> тыс. руб. | F55: =F15+F52 -> 0 | G55: =G15+G52 -> 43231.297 | H55: =H15+H52 -> 60466.293 | I55: =I15+I52 -> 81883.568 | J55: =J15+J52 -> 73213.857 | K55: =K15+K52 -> 85328.553 | L55: =L15+L52 -> 70939.222 | M55: =M15+M52 -> 75775.388 | ... Z55: =Z15+Z52 -> 0
A56: =A55 -> HIFO 75D | D56: Дисконтированный операционный денежный поток | E56: =E55 -> тыс. руб. | G56: =G15*'ФОТ, МТР, макро'!AJ$14 -> 38599.372 | H56: =H15*'ФОТ, МТР, макро'!AK$14 -> 48203.359 | I56: =I15*'ФОТ, МТР, макро'!AL$14 -> 58283.106 | J56: =J15*'ФОТ, МТР, макро'!AM$14 -> 46528.73 | K56: =K15*'ФОТ, МТР, макро'!AN$14 -> 48417.712 | L56: =L15*'ФОТ, МТР, макро'!AO$14 -> 35940.018 | M56: =M15*'ФОТ, МТР, макро'!AP$14 -> 34276.937 | N56: =N15*'ФОТ, МТР, макро'!AQ$14 -> 30668.392 | ... Z56: =Z15*'ФОТ, МТР, макро'!BC$14 -> 0
A57: =A56 -> HIFO 75D | D57: =D16 -> ТО, ТР, ППР | E57: =E56 -> тыс. руб. | G57: =G16*'ФОТ, МТР, макро'!AJ$14 -> 10289.987 | H57: =H16*'ФОТ, МТР, макро'!AK$14 -> 28218.51 | I57: =I16*'ФОТ, МТР, макро'!AL$14 -> 45845.784 | J57: =J16*'ФОТ, МТР, макро'!AM$14 -> 33339.128 | K57: =K16*'ФОТ, МТР, макро'!AN$14 -> 38832.566 | L57: =L16*'ФОТ, МТР, макро'!AO$14 -> 25399.696 | M57: =M16*'ФОТ, МТР, макро'!AP$14 -> 25377.028 | N57: =N16*'ФОТ, МТР, макро'!AQ$14 -> 22576.536 | ... Z57: =Z16*'ФОТ, МТР, макро'!BC$14 -> 0
A58: =A57 -> HIFO 75D | D58: =D21 -> Смазочные | E58: =E57 -> тыс. руб. | G58: =G21*'ФОТ, МТР, макро'!AJ$14 -> 0 | H58: =H21*'ФОТ, МТР, макро'!AK$14 -> 0 | I58: =I21*'ФОТ, МТР, макро'!AL$14 -> 0 | J58: =J21*'ФОТ, МТР, макро'!AM$14 -> 0 | K58: =K21*'ФОТ, МТР, макро'!AN$14 -> 0 | L58: =L21*'ФОТ, МТР, макро'!AO$14 -> 0 | M58: =M21*'ФОТ, МТР, макро'!AP$14 -> 0 | N58: =N21*'ФОТ, МТР, макро'!AQ$14 -> 0 | ... Z58: =Z21*'ФОТ, МТР, макро'!BC$14 -> 0
A59: =A58 -> HIFO 75D | D59: =D23 -> Долота | E59: =E58 -> тыс. руб. | G59: =G23*'ФОТ, МТР, макро'!AJ$14 -> 0 | H59: =H23*'ФОТ, МТР, макро'!AK$14 -> 0 | I59: =I23*'ФОТ, МТР, макро'!AL$14 -> 0 | J59: =J23*'ФОТ, МТР, макро'!AM$14 -> 0 | K59: =K23*'ФОТ, МТР, макро'!AN$14 -> 0 | L59: =L23*'ФОТ, МТР, макро'!AO$14 -> 0 | M59: =M23*'ФОТ, МТР, макро'!AP$14 -> 0 | N59: =N23*'ФОТ, МТР, макро'!AQ$14 -> 0 | ... Z59: =Z23*'ФОТ, МТР, макро'!BC$14 -> 0
A60: =A59 -> HIFO 75D | D60: =D27 -> Штанги буровые | E60: =E59 -> тыс. руб. | G60: =G27*'ФОТ, МТР, макро'!AJ$14 -> 0 | H60: =H27*'ФОТ, МТР, макро'!AK$14 -> 0 | I60: =I27*'ФОТ, МТР, макро'!AL$14 -> 0 | J60: =J27*'ФОТ, МТР, макро'!AM$14 -> 0 | K60: =K27*'ФОТ, МТР, макро'!AN$14 -> 0 | L60: =L27*'ФОТ, МТР, макро'!AO$14 -> 0 | M60: =M27*'ФОТ, МТР, макро'!AP$14 -> 0 | N60: =N27*'ФОТ, МТР, макро'!AQ$14 -> 0 | ... Z60: =Z27*'ФОТ, МТР, макро'!BC$14 -> 0
A61: =A60 -> HIFO 75D | D61: =D31 -> Расходники | E61: =E60 -> тыс. руб. | G61: =G31*'ФОТ, МТР, макро'!AJ$14 -> 0 | H61: =H31*'ФОТ, МТР, макро'!AK$14 -> 0 | I61: =I31*'ФОТ, МТР, макро'!AL$14 -> 0 | J61: =J31*'ФОТ, МТР, макро'!AM$14 -> 0 | K61: =K31*'ФОТ, МТР, макро'!AN$14 -> 0 | L61: =L31*'ФОТ, МТР, макро'!AO$14 -> 0 | M61: =M31*'ФОТ, МТР, макро'!AP$14 -> 0 | N61: =N31*'ФОТ, МТР, макро'!AQ$14 -> 0 | ... Z61: =Z31*'ФОТ, МТР, макро'!BC$14 -> 0
A62: =A61 -> HIFO 75D | D62: =D33 -> Топливо/Электроэнергия | E62: =E61 -> тыс. руб. | G62: =G33*'ФОТ, МТР, макро'!AJ$14 -> 27138.077 | H62: =H33*'ФОТ, МТР, макро'!AK$14 -> 23518.916 | I62: =I33*'ФОТ, МТР, макро'!AL$14 -> 20674.203 | J62: =J33*'ФОТ, МТР, макро'!AM$14 -> 18707.374 | K62: =K33*'ФОТ, МТР, макро'!AN$14 -> 16803.13 | L62: =L33*'ФОТ, МТР, макро'!AO$14 -> 14554.922 | M62: =M33*'ФОТ, МТР, макро'!AP$14 -> 13213.586 | N62: =N33*'ФОТ, МТР, макро'!AQ$14 -> 11964.682 | ... Z62: =Z33*'ФОТ, МТР, макро'!BC$14 -> 0
A63: =A62 -> HIFO 75D | D63: =D42 -> Затраты на персонал | E63: =E62 -> тыс. руб. | G63: =G42*'ФОТ, МТР, макро'!AJ$14 -> 14026.895 | H63: =H42*'ФОТ, МТР, макро'!AK$14 -> 12524.013 | I63: =I42*'ФОТ, МТР, макро'!AL$14 -> 11182.155 | J63: =J42*'ФОТ, МТР, макро'!AM$14 -> 9984.0666 | K63: =K42*'ФОТ, МТР, макро'!AN$14 -> 8914.3452 | L63: =L42*'ФОТ, МТР, макро'!AO$14 -> 7959.2368 | M63: =M42*'ФОТ, МТР, макро'!AP$14 -> 7106.4614 | N63: =N42*'ФОТ, МТР, макро'!AQ$14 -> 6345.0548 | ... Z63: =Z42*'ФОТ, МТР, макро'!BC$14 -> 0
A64: =A63 -> HIFO 75D | D64: =D45 -> Транспортный налог | E64: =E63 -> тыс. руб. | G64: =G45*'ФОТ, МТР, макро'!AJ$14 -> 10.87089 | H64: =H45*'ФОТ, МТР, макро'!AK$14 -> 9.706152 | I64: =I45*'ФОТ, МТР, макро'!AL$14 -> 8.6662072 | J64: =J45*'ФОТ, МТР, макро'!AM$14 -> 7.737685 | K64: =K45*'ФОТ, МТР, макро'!AN$14 -> 6.9086473 | L64: =L45*'ФОТ, МТР, макро'!AO$14 -> 6.1684351 | M64: =M45*'ФОТ, МТР, макро'!AP$14 -> 5.5075313 | N64: =N45*'ФОТ, МТР, макро'!AQ$14 -> 4.9174387 | ... Z64: =Z45*'ФОТ, МТР, макро'!BC$14 -> 0
A65: =A64 -> HIFO 75D | D65: =D50 -> Налог на прибыль | E65: =E64 -> тыс. руб. | G65: =G50*'ФОТ, МТР, макро'!AJ$14 -> -12866.457 | H65: =H50*'ФОТ, МТР, макро'!AK$14 -> -16067.786 | I65: =I50*'ФОТ, МТР, макро'!AL$14 -> -19427.702 | J65: =J50*'ФОТ, МТР, макро'!AM$14 -> -15509.577 | K65: =K50*'ФОТ, МТР, макро'!AN$14 -> -16139.237 | L65: =L50*'ФОТ, МТР, макро'!AO$14 -> -11980.006 | M65: =M50*'ФОТ, МТР, макро'!AP$14 -> -11425.646 | N65: =N50*'ФОТ, МТР, макро'!AQ$14 -> -10222.797 | ... Z65: =Z50*'ФОТ, МТР, макро'!BC$14 -> 0
A66: =A65 -> HIFO 75D | D66: проверка полноты | G66: =G56-SUM(G57:G65) -> 0 | H66: =H56-SUM(H57:H65) -> 0 | I66: =I56-SUM(I57:I65) -> 0 | J66: =J56-SUM(J57:J65) -> 0 | K66: =K56-SUM(K57:K65) -> 0 | L66: =L56-SUM(L57:L65) -> 0 | M66: =M56-SUM(M57:M65) -> 0 | N66: =N56-SUM(N57:N65) -> 0 | ... Z66: =Z56-SUM(Z57:Z65) -> 0
A67: =A66 -> HIFO 75D | D67: Кумулятивный дисконтированный операционный денежный поток | E67: =E56 -> тыс. руб. | F67: =F56 -> 0 | G67: =F67+G56 -> 38599.372 | H67: =G67+H56 -> 86802.731 | I67: =H67+I56 -> 145085.84 | J67: =I67+J56 -> 191614.57 | K67: =J67+K56 -> 240032.28 | L67: =K67+L56 -> 275972.3 | M67: =L67+M56 -> 310249.23 | N67: =M67+N56 -> 340917.63 | ... Z67: =Y67+Z56 -> 392009.39
A68: =A67 -> HIFO 75D | D68: =D57 -> ТО, ТР, ППР | E68: =E57 -> тыс. руб. | F68: =F57 -> 0 | G68: =F68+G57 -> 10289.987 | H68: =G68+H57 -> 38508.496 | I68: =H68+I57 -> 84354.281 | J68: =I68+J57 -> 117693.41 | K68: =J68+K57 -> 156525.97 | L68: =K68+L57 -> 181925.67 | M68: =L68+M57 -> 207302.7 | N68: =M68+N57 -> 229879.23 | ... Z68: =Y68+Z57 -> 267461.89
A69: =A68 -> HIFO 75D | D69: =D58 -> Смазочные | E69: =E58 -> тыс. руб. | F69: =F58 -> 0 | G69: =F69+G58 -> 0 | H69: =G69+H58 -> 0 | I69: =H69+I58 -> 0 | J69: =I69+J58 -> 0 | K69: =J69+K58 -> 0 | L69: =K69+L58 -> 0 | M69: =L69+M58 -> 0 | N69: =M69+N58 -> 0 | ... Z69: =Y69+Z58 -> 0
A70: =A69 -> HIFO 75D | D70: =D59 -> Долота | E70: =E59 -> тыс. руб. | F70: =F59 -> 0 | G70: =F70+G59 -> 0 | H70: =G70+H59 -> 0 | I70: =H70+I59 -> 0 | J70: =I70+J59 -> 0 | K70: =J70+K59 -> 0 | L70: =K70+L59 -> 0 | M70: =L70+M59 -> 0 | N70: =M70+N59 -> 0 | ... Z70: =Y70+Z59 -> 0
A71: =A70 -> HIFO 75D | D71: =D60 -> Штанги буровые | E71: =E60 -> тыс. руб. | F71: =F60 -> 0 | G71: =F71+G60 -> 0 | H71: =G71+H60 -> 0 | I71: =H71+I60 -> 0 | J71: =I71+J60 -> 0 | K71: =J71+K60 -> 0 | L71: =K71+L60 -> 0 | M71: =L71+M60 -> 0 | N71: =M71+N60 -> 0 | ... Z71: =Y71+Z60 -> 0
A72: =A71 -> HIFO 75D | D72: =D61 -> Расходники | E72: =E61 -> тыс. руб. | F72: =F61 -> 0 | G72: =F72+G61 -> 0 | H72: =G72+H61 -> 0 | I72: =H72+I61 -> 0 | J72: =I72+J61 -> 0 | K72: =J72+K61 -> 0 | L72: =K72+L61 -> 0 | M72: =L72+M61 -> 0 | N72: =M72+N61 -> 0 | ... Z72: =Y72+Z61 -> 0
A73: =A72 -> HIFO 75D | D73: =D62 -> Топливо/Электроэнергия | E73: =E62 -> тыс. руб. | F73: =F62 -> 0 | G73: =F73+G62 -> 27138.077 | H73: =G73+H62 -> 50656.993 | I73: =H73+I62 -> 71331.196 | J73: =I73+J62 -> 90038.57 | K73: =J73+K62 -> 106841.7 | L73: =K73+L62 -> 121396.62 | M73: =L73+M62 -> 134610.21 | N73: =M73+N62 -> 146574.89 | ... Z73: =Y73+Z62 -> 166382.82
A74: =A73 -> HIFO 75D | D74: =D63 -> Затраты на персонал | E74: =E63 -> тыс. руб. | F74: =F63 -> 0 | G74: =F74+G63 -> 14026.895 | H74: =G74+H63 -> 26550.908 | I74: =H74+I63 -> 37733.063 | J74: =I74+J63 -> 47717.129 | K74: =J74+K63 -> 56631.474 | L74: =K74+L63 -> 64590.711 | M74: =L74+M63 -> 71697.173 | N74: =M74+N63 -> 78042.227 | ... Z74: =Y74+Z63 -> 88765.694
A75: =A74 -> HIFO 75D | D75: =D64 -> Транспортный налог | E75: =E64 -> тыс. руб. | F75: =F64 -> 0 | G75: =F75+G64 -> 10.87089 | H75: =G75+H64 -> 20.577042 | I75: =H75+I64 -> 29.243249 | J75: =I75+J64 -> 36.980934 | K75: =J75+K64 -> 43.889582 | L75: =K75+L64 -> 50.058017 | M75: =L75+M64 -> 55.565548 | N75: =M75+N64 -> 60.482987 | ... Z75: =Y75+Z64 -> 68.793709
A76: =A75 -> HIFO 75D | D76: =D65 -> Налог на прибыль | E76: =E65 -> тыс. руб. | F76: =F65 -> 0 | G76: =F76+G65 -> -12866.457 | H76: =G76+H65 -> -28934.244 | I76: =H76+I65 -> -48361.946 | J76: =I76+J65 -> -63871.522 | K76: =J76+K65 -> -80010.76 | L76: =K76+L65 -> -91990.766 | M76: =L76+M65 -> -103416.41 | N76: =M76+N65 -> -113639.21 | ... Z76: =Y76+Z65 -> -130669.8
A77: =A76 -> HIFO 75D
A78: =A77 -> HIFO 75D | D78: Дисконтированный инвестиционный поток | E78: =E55 -> тыс. руб. | F78: =F52*'ФОТ, МТР, макро'!AI$14 -> 0 | G78: =G52*'ФОТ, МТР, макро'!AJ$14 -> 0 | H78: =H52*'ФОТ, МТР, макро'!AK$14 -> 0 | I78: =I52*'ФОТ, МТР, макро'!AL$14 -> 0 | J78: =J52*'ФОТ, МТР, макро'!AM$14 -> 0 | K78: =K52*'ФОТ, МТР, макро'!AN$14 -> 0 | L78: =L52*'ФОТ, МТР, макро'!AO$14 -> 0 | M78: =M52*'ФОТ, МТР, макро'!AP$14 -> 0 | ... Z78: =Z52*'ФОТ, МТР, макро'!BC$14 -> 0
A79: =A78 -> HIFO 75D | D79: =D53 -> Буровой станок | E79: =E78 -> тыс. руб. | F79: =F53*'ФОТ, МТР, макро'!AI$14 -> 0 | G79: =G53*'ФОТ, МТР, макро'!AJ$14 -> 0 | H79: =H53*'ФОТ, МТР, макро'!AK$14 -> 0 | I79: =I53*'ФОТ, МТР, макро'!AL$14 -> 0 | J79: =J53*'ФОТ, МТР, макро'!AM$14 -> 0 | K79: =K53*'ФОТ, МТР, макро'!AN$14 -> 0 | L79: =L53*'ФОТ, МТР, макро'!AO$14 -> 0 | M79: =M53*'ФОТ, МТР, макро'!AP$14 -> 0 | ... Z79: =Z53*'ФОТ, МТР, макро'!BC$14 -> 0
A80: =A79 -> HIFO 75D | D80: проверка полноты | F80: =F78-F79 -> 0 | G80: =G78-G79 -> 0 | H80: =H78-H79 -> 0 | I80: =I78-I79 -> 0 | J80: =J78-J79 -> 0 | K80: =K78-K79 -> 0 | L80: =L78-L79 -> 0 | M80: =M78-M79 -> 0 | ... Z80: =Z78-Z79 -> 0
A81: =A80 -> HIFO 75D | D81: Кумулятивный инвестиционный поток | E81: =E78 -> тыс. руб. | F81: =F78 -> 0 | G81: =F81+G78 -> 0 | H81: =G81+H78 -> 0 | I81: =H81+I78 -> 0 | J81: =I81+J78 -> 0 | K81: =J81+K78 -> 0 | L81: =K81+L78 -> 0 | M81: =L81+M78 -> 0 | N81: =M81+N78 -> 0 | ... Z81: =Y81+Z78 -> 0
A82: =A81 -> HIFO 75D | D82: =D79 -> Буровой станок | E82: =E79 -> тыс. руб. | F82: =F79 -> 0 | G82: =F82+G79 -> 0 | H82: =G82+H79 -> 0 | I82: =H82+I79 -> 0 | J82: =I82+J79 -> 0 | K82: =J82+K79 -> 0 | L82: =K82+L79 -> 0 | M82: =L82+M79 -> 0 | N82: =M82+N79 -> 0 | ... Z82: =Y82+Z79 -> 0
A83: =A82 -> HIFO 75D
A84: =A83 -> HIFO 75D | D84: Дисконтированный денежный поток | E84: =E55 -> тыс. руб. | F84: =F55*'ФОТ, МТР, макро'!AI$14 -> 0 | G84: =G55*'ФОТ, МТР, макро'!AJ$14 -> 38599.372 | H84: =H55*'ФОТ, МТР, макро'!AK$14 -> 48203.359 | I84: =I55*'ФОТ, МТР, макро'!AL$14 -> 58283.106 | J84: =J55*'ФОТ, МТР, макро'!AM$14 -> 46528.73 | K84: =K55*'ФОТ, МТР, макро'!AN$14 -> 48417.712 | L84: =L55*'ФОТ, МТР, макро'!AO$14 -> 35940.018 | M84: =M55*'ФОТ, МТР, макро'!AP$14 -> 34276.937 | ... Z84: =Z55*'ФОТ, МТР, макро'!BC$14 -> 0
A85: =A84 -> HIFO 75D | D85: Кумулятивный дисконтированный денежный поток | E85: =E84 -> тыс. руб. | F85: =F84 -> 0 | G85: =F85+G84 -> 38599.372 | H85: =G85+H84 -> 86802.731 | I85: =H85+I84 -> 145085.84 | J85: =I85+J84 -> 191614.57 | K85: =J85+K84 -> 240032.28 | L85: =K85+L84 -> 275972.3 | M85: =L85+M84 -> 310249.23 | N85: =M85+N84 -> 340917.63 | ... Z85: =Y85+Z84 -> 392009.39
A86: =A85 -> HIFO 75D
A87: =A86 -> HIFO 75D | B87: =D87 -> Аннуитет операционный | C87: =E6 -> 10 | D87: Аннуитет операционный | E87: руб/м3 | G87: =G67/'ФОТ, МТР, макро'!AJ$15/(G13/G8) -> 8.4705092 | H87: =H67/'ФОТ, МТР, макро'!AK$15/(H13/H8) -> 10.305977 | I87: =I67/'ФОТ, МТР, макро'!AL$15/(I13/I8) -> 12.520211 | J87: =J67/'ФОТ, МТР, макро'!AM$15/(J13/J8) -> 13.042903 | K87: =K67/'ФОТ, МТР, макро'!AN$15/(K13/K8) -> 13.696501 | L87: =L67/'ФОТ, МТР, макро'!AO$15/(L13/L8) -> 14.052652 | M87: =M67/'ФОТ, МТР, макро'!AP$15/(M13/M8) -> 14.36197 | N87: =N67/'ФОТ, МТР, макро'!AQ$15/(N13/N8) -> 14.37977 | ... Z87: =Z67/'ФОТ, МТР, макро'!BC$15/(Z13/Z8) -> #DIV/0! | AC87: {=INDEX(G87:Z87,1,$C87)} -> 14.68475
A88: =A87 -> HIFO 75D | B88: =D88 -> ТО, ТР, ППР | C88: =C87 -> 10 | D88: =D68 -> ТО, ТР, ППР | E88: =E87 -> руб/м3 | G88: =G68/'ФОТ, МТР, макро'!AJ$15/(G13/G8) -> 2.2581048 | H88: =H68/'ФОТ, МТР, макро'!AK$15/(H13/H8) -> 4.5720646 | I88: =I68/'ФОТ, МТР, макро'!AL$15/(I13/I8) -> 7.2793691 | J88: =J68/'ФОТ, МТР, макро'!AM$15/(J13/J8) -> 8.0112055 | K88: =K68/'ФОТ, МТР, макро'!AN$15/(K13/K8) -> 8.9315413 | L88: =L68/'ФОТ, МТР, макро'!AO$15/(L13/L8) -> 9.2637493 | M88: =M68/'ФОТ, МТР, макро'!AP$15/(M13/M8) -> 9.5963978 | N88: =N68/'ФОТ, МТР, макро'!AQ$15/(N13/N8) -> 9.696215 | ... Z88: =Z68/'ФОТ, МТР, макро'!BC$15/(Z13/Z8) -> #DIV/0! | AC88: {=INDEX(G88:Z88,1,$C88)} -> 10.019176
A89: =A88 -> HIFO 75D | B89: =D89 -> Смазочные | C89: =C88 -> 10 | D89: =D69 -> Смазочные | E89: =E88 -> руб/м3 | G89: =G69/'ФОТ, МТР, макро'!AJ$15/(G13/G8) -> 0 | H89: =H69/'ФОТ, МТР, макро'!AK$15/(H13/H8) -> 0 | I89: =I69/'ФОТ, МТР, макро'!AL$15/(I13/I8) -> 0 | J89: =J69/'ФОТ, МТР, макро'!AM$15/(J13/J8) -> 0 | K89: =K69/'ФОТ, МТР, макро'!AN$15/(K13/K8) -> 0 | L89: =L69/'ФОТ, МТР, макро'!AO$15/(L13/L8) -> 0 | M89: =M69/'ФОТ, МТР, макро'!AP$15/(M13/M8) -> 0 | N89: =N69/'ФОТ, МТР, макро'!AQ$15/(N13/N8) -> 0 | ... Z89: =Z69/'ФОТ, МТР, макро'!BC$15/(Z13/Z8) -> #DIV/0! | AC89: {=INDEX(G89:Z89,1,$C89)} -> 0
A90: =A89 -> HIFO 75D | B90: =D90 -> Долота | C90: =C89 -> 10 | D90: =D70 -> Долота | E90: =E89 -> руб/м3 | G90: =G70/'ФОТ, МТР, макро'!AJ$15/(G13/G8) -> 0 | H90: =H70/'ФОТ, МТР, макро'!AK$15/(H13/H8) -> 0 | I90: =I70/'ФОТ, МТР, макро'!AL$15/(I13/I8) -> 0 | J90: =J70/'ФОТ, МТР, макро'!AM$15/(J13/J8) -> 0 | K90: =K70/'ФОТ, МТР, макро'!AN$15/(K13/K8) -> 0 | L90: =L70/'ФОТ, МТР, макро'!AO$15/(L13/L8) -> 0 | M90: =M70/'ФОТ, МТР, макро'!AP$15/(M13/M8) -> 0 | N90: =N70/'ФОТ, МТР, макро'!AQ$15/(N13/N8) -> 0 | ... Z90: =Z70/'ФОТ, МТР, макро'!BC$15/(Z13/Z8) -> #DIV/0! | AC90: {=INDEX(G90:Z90,1,$C90)} -> 0
A91: =A90 -> HIFO 75D | B91: =D91 -> Штанги буровые | C91: =C90 -> 10 | D91: =D71 -> Штанги буровые | E91: =E90 -> руб/м3 | G91: =G71/'ФОТ, МТР, макро'!AJ$15/(G13/G8) -> 0 | H91: =H71/'ФОТ, МТР, макро'!AK$15/(H13/H8) -> 0 | I91: =I71/'ФОТ, МТР, макро'!AL$15/(I13/I8) -> 0 | J91: =J71/'ФОТ, МТР, макро'!AM$15/(J13/J8) -> 0 | K91: =K71/'ФОТ, МТР, макро'!AN$15/(K13/K8) -> 0 | L91: =L71/'ФОТ, МТР, макро'!AO$15/(L13/L8) -> 0 | M91: =M71/'ФОТ, МТР, макро'!AP$15/(M13/M8) -> 0 | N91: =N71/'ФОТ, МТР, макро'!AQ$15/(N13/N8) -> 0 | ... Z91: =Z71/'ФОТ, МТР, макро'!BC$15/(Z13/Z8) -> #DIV/0! | AC91: {=INDEX(G91:Z91,1,$C91)} -> 0
A92: =A91 -> HIFO 75D | B92: =D92 -> Расходники | C92: =C91 -> 10 | D92: =D72 -> Расходники | E92: =E91 -> руб/м3 | G92: =G72/'ФОТ, МТР, макро'!AJ$15/(G13/G8) -> 0 | H92: =H72/'ФОТ, МТР, макро'!AK$15/(H13/H8) -> 0 | I92: =I72/'ФОТ, МТР, макро'!AL$15/(I13/I8) -> 0 | J92: =J72/'ФОТ, МТР, макро'!AM$15/(J13/J8) -> 0 | K92: =K72/'ФОТ, МТР, макро'!AN$15/(K13/K8) -> 0 | L92: =L72/'ФОТ, МТР, макро'!AO$15/(L13/L8) -> 0 | M92: =M72/'ФОТ, МТР, макро'!AP$15/(M13/M8) -> 0 | N92: =N72/'ФОТ, МТР, макро'!AQ$15/(N13/N8) -> 0 | ... Z92: =Z72/'ФОТ, МТР, макро'!BC$15/(Z13/Z8) -> #DIV/0! | AC92: {=INDEX(G92:Z92,1,$C92)} -> 0
A93: =A92 -> HIFO 75D | B93: =D93 -> Топливо/Электроэнергия | C93: =C92 -> 10 | D93: =D73 -> Топливо/Электроэнергия | E93: =E92 -> руб/м3 | G93: =G73/'ФОТ, МТР, макро'!AJ$15/(G13/G8) -> 5.9553645 | H93: =H73/'ФОТ, МТР, макро'!AK$15/(H13/H8) -> 6.0144401 | I93: =I73/'ФОТ, МТР, макро'!AL$15/(I13/I8) -> 6.1555394 | J93: =J73/'ФОТ, МТР, макро'!AM$15/(J13/J8) -> 6.1287841 | K93: =K73/'ФОТ, МТР, макро'!AN$15/(K13/K8) -> 6.0965029 | L93: =L73/'ФОТ, МТР, макро'!AO$15/(L13/L8) -> 6.1815789 | M93: =M73/'ФОТ, МТР, макро'!AP$15/(M13/M8) -> 6.2313377 | N93: =N73/'ФОТ, МТР, макро'!AQ$15/(N13/N8) -> 6.1824708 | ... Z93: =Z73/'ФОТ, МТР, макро'!BC$15/(Z13/Z8) -> #DIV/0! | AC93: {=INDEX(G93:Z93,1,$C93)} -> 6.2327336
A94: =A93 -> HIFO 75D | B94: =D94 -> Затраты на персонал | C94: =C93 -> 10 | D94: =D74 -> Затраты на персонал | E94: =E93 -> руб/м3 | G94: =G74/'ФОТ, МТР, макро'!AJ$15/(G13/G8) -> 3.0781574 | H94: =H74/'ФОТ, МТР, макро'!AK$15/(H13/H8) -> 3.1523554 | I94: =I74/'ФОТ, МТР, макро'!AL$15/(I13/I8) -> 3.256182 | J94: =J74/'ФОТ, МТР, макро'!AM$15/(J13/J8) -> 3.2480301 | K94: =K74/'ФОТ, МТР, макро'!AN$15/(K13/K8) -> 3.2314532 | L94: =L74/'ФОТ, МТР, макро'!AO$15/(L13/L8) -> 3.2889924 | M94: =M74/'ФОТ, МТР, макро'!AP$15/(M13/M8) -> 3.3189852 | N94: =N74/'ФОТ, МТР, макро'!AQ$15/(N13/N8) -> 3.2917902 | ... Z94: =Z74/'ФОТ, МТР, макро'!BC$15/(Z13/Z8) -> #DIV/0! | AC94: {=INDEX(G94:Z94,1,$C94)} -> 3.3251807
A95: =A94 -> HIFO 75D | B95: =D95 -> Транспортный налог | C95: =C94 -> 10 | D95: =D75 -> Транспортный налог | E95: =E94 -> руб/м3 | G95: =G75/'ФОТ, МТР, макро'!AJ$15/(G13/G8) -> 0.0023855822 | H95: =H75/'ФОТ, МТР, макро'!AK$15/(H13/H8) -> 0.002443086 | I95: =I75/'ФОТ, МТР, макро'!AL$15/(I13/I8) -> 0.0025235519 | J95: =J75/'ФОТ, МТР, макро'!AM$15/(J13/J8) -> 0.0025172341 | K95: =K75/'ФОТ, МТР, макро'!AN$15/(K13/K8) -> 0.002504387 | L95: =L75/'ФОТ, МТР, макро'!AO$15/(L13/L8) -> 0.0025489801 | M95: =M75/'ФОТ, МТР, макро'!AP$15/(M13/M8) -> 0.0025722246 | N95: =N75/'ФОТ, МТР, макро'!AQ$15/(N13/N8) -> 0.0025511484 | ... Z95: =Z75/'ФОТ, МТР, макро'!BC$15/(Z13/Z8) -> #DIV/0! | AC95: {=INDEX(G95:Z95,1,$C95)} -> 0.0025770261
A96: =A95 -> HIFO 75D | B96: =D96 -> Налог на прибыль | C96: =C95 -> 10 | D96: =D76 -> Налог на прибыль | E96: =E95 -> руб/м3 | G96: =G76/'ФОТ, МТР, макро'!AJ$15/(G13/G8) -> -2.8235031 | H96: =H76/'ФОТ, МТР, макро'!AK$15/(H13/H8) -> -3.4353258 | I96: =I76/'ФОТ, МТР, макро'!AL$15/(I13/I8) -> -4.1734035 | J96: =J76/'ФОТ, МТР, макро'!AM$15/(J13/J8) -> -4.3476342 | K96: =K76/'ФОТ, МТР, макро'!AN$15/(K13/K8) -> -4.5655005 | L96: =L76/'ФОТ, МТР, макро'!AO$15/(L13/L8) -> -4.6842174 | M96: =M76/'ФОТ, МТР, макро'!AP$15/(M13/M8) -> -4.7873232 | N96: =N76/'ФОТ, МТР, макро'!AQ$15/(N13/N8) -> -4.7932568 | ... Z96: =Z76/'ФОТ, МТР, макро'!BC$15/(Z13/Z8) -> #DIV/0! | AC96: {=INDEX(G96:Z96,1,$C96)} -> -4.8949168
A97: =A96 -> HIFO 75D | B97: =D97 -> Аннуитет инвестиционный | C97: =C96 -> 10 | D97: Аннуитет инвестиционный | E97: =E87 -> руб/м3 | G97: =G81/'ФОТ, МТР, макро'!AJ$15/(G13/G8) -> 0 | H97: =H81/'ФОТ, МТР, макро'!AK$15/(H13/H8) -> 0 | I97: =I81/'ФОТ, МТР, макро'!AL$15/(I13/I8) -> 0 | J97: =J81/'ФОТ, МТР, макро'!AM$15/(J13/J8) -> 0 | K97: =K81/'ФОТ, МТР, макро'!AN$15/(K13/K8) -> 0 | L97: =L81/'ФОТ, МТР, макро'!AO$15/(L13/L8) -> 0 | M97: =M81/'ФОТ, МТР, макро'!AP$15/(M13/M8) -> 0 | N97: =N81/'ФОТ, МТР, макро'!AQ$15/(N13/N8) -> 0 | ... Z97: =Z81/'ФОТ, МТР, макро'!BC$15/(Z13/Z8) -> #DIV/0! | AC97: {=INDEX(G97:Z97,1,$C97)} -> 0
A98: =A97 -> HIFO 75D | B98: =D98 -> Буровой станок | C98: =C97 -> 10 | D98: =D82 -> Буровой станок | E98: =E97 -> руб/м3 | G98: =G82/'ФОТ, МТР, макро'!AJ$15/(G13/G8) -> 0 | H98: =H82/'ФОТ, МТР, макро'!AK$15/(H13/H8) -> 0 | I98: =I82/'ФОТ, МТР, макро'!AL$15/(I13/I8) -> 0 | J98: =J82/'ФОТ, МТР, макро'!AM$15/(J13/J8) -> 0 | K98: =K82/'ФОТ, МТР, макро'!AN$15/(K13/K8) -> 0 | L98: =L82/'ФОТ, МТР, макро'!AO$15/(L13/L8) -> 0 | M98: =M82/'ФОТ, МТР, макро'!AP$15/(M13/M8) -> 0 | N98: =N82/'ФОТ, МТР, макро'!AQ$15/(N13/N8) -> 0 | ... Z98: =Z82/'ФОТ, МТР, макро'!BC$15/(Z13/Z8) -> #DIV/0! | AC98: {=INDEX(G98:Z98,1,$C98)} -> 0
A99: =A98 -> HIFO 75D | B99: =D99 -> Аннуитет общий | C99: =C98 -> 10 | D99: Аннуитет общий | E99: =E87 -> руб/м3 | G99: =G85/'ФОТ, МТР, макро'!AJ$15/(G13/G8) -> 8.4705092 | H99: =H85/'ФОТ, МТР, макро'!AK$15/(H13/H8) -> 10.305977 | I99: =I85/'ФОТ, МТР, макро'!AL$15/(I13/I8) -> 12.520211 | J99: =J85/'ФОТ, МТР, макро'!AM$15/(J13/J8) -> 13.042903 | K99: =K85/'ФОТ, МТР, макро'!AN$15/(K13/K8) -> 13.696501 | L99: =L85/'ФОТ, МТР, макро'!AO$15/(L13/L8) -> 14.052652 | M99: =M85/'ФОТ, МТР, макро'!AP$15/(M13/M8) -> 14.36197 | N99: =N85/'ФОТ, МТР, макро'!AQ$15/(N13/N8) -> 14.37977 | ... Z99: =Z85/'ФОТ, МТР, макро'!BC$15/(Z13/Z8) -> #DIV/0! | AC99: {=INDEX(G99:Z99,1,$C99)} -> 14.68475
A100: =A99 -> HIFO 75D
...

Sheet Свод_250-270_эл
C2: Технико-экономическая оценка стоимости владения
C4: Ранжирование общих аннуитетов - по возрастанию | G4: Ранжирование по стоимости самосвала - по возрастанию
C5: № | D5: Марка станка | E5: Аннуитет, руб/ткм | G5: =C5 -> № | H5: =D5 -> Марка станка | K5: Цена за ед., тыс. руб.
C6: 1 | D6: =IFERROR(HLOOKUP(E6,$F$58:$O$60,3,FALSE),"-") -> - | E6: =IFERROR(SMALL($F$58:$O$58,C6),"-") -> - | G6: =C6 -> 1 | H6: =IFERROR(HLOOKUP(K6,$F$59:$O$60,2,FALSE),"-") -> - | K6: =IFERROR(SMALL($F$59:$O$59,C6),"-") -> -
C7: =C6+1 -> 2 | D7: =IFERROR(HLOOKUP(E7,$F$58:$O$60,3,FALSE),"-") -> - | E7: =IFERROR(SMALL($F$58:$O$58,C7),"-") -> - | G7: =C7 -> 2 | H7: =IFERROR(HLOOKUP(K7,$F$59:$O$60,2,FALSE),"-") -> - | K7: =IFERROR(SMALL($F$59:$O$59,C7),"-") -> -
C8: =C7+1 -> 3 | D8: =IFERROR(HLOOKUP(E8,$F$58:$O$60,3,FALSE),"-") -> - | E8: =IFERROR(SMALL($F$58:$O$58,C8),"-") -> - | G8: =C8 -> 3 | H8: =IFERROR(HLOOKUP(K8,$F$59:$O$60,2,FALSE),"-") -> - | K8: =IFERROR(SMALL($F$59:$O$59,C8),"-") -> -
C9: =C8+1 -> 4 | D9: =IFERROR(HLOOKUP(E9,$F$58:$O$60,3,FALSE),"-") -> - | E9: =IFERROR(SMALL($F$58:$O$58,C9),"-") -> - | G9: =C9 -> 4 | H9: =IFERROR(HLOOKUP(K9,$F$59:$O$60,2,FALSE),"-") -> - | K9: =IFERROR(SMALL($F$59:$O$59,C9),"-") -> -
C10: =C9+1 -> 5 | D10: =IFERROR(HLOOKUP(E10,$F$58:$O$60,3,FALSE),"-") -> - | E10: =IFERROR(SMALL($F$58:$O$58,C10),"-") -> - | G10: =C10 -> 5 | H10: =IFERROR(HLOOKUP(K10,$F$59:$O$60,2,FALSE),"-") -> - | K10: =IFERROR(SMALL($F$59:$O$59,C10),"-") -> -
C11: =C10+1 -> 6 | D11: =IFERROR(HLOOKUP(E11,$F$58:$O$60,3,FALSE),"-") -> - | E11: =IFERROR(SMALL($F$58:$O$58,C11),"-") -> - | G11: =C11 -> 6 | H11: =IFERROR(HLOOKUP(K11,$F$59:$O$60,2,FALSE),"-") -> - | K11: =IFERROR(SMALL($F$59:$O$59,C11),"-") -> -
C12: =C11+1 -> 7 | D12: =IFERROR(HLOOKUP(E12,$F$58:$O$60,3,FALSE),"-") -> - | E12: =IFERROR(SMALL($F$58:$O$58,C12),"-") -> - | G12: =C12 -> 7 | H12: =IFERROR(HLOOKUP(K12,$F$59:$O$60,2,FALSE),"-") -> - | K12: =IFERROR(SMALL($F$59:$O$59,C12),"-") -> -
C13: =C12+1 -> 8 | D13: =IFERROR(HLOOKUP(E13,$F$58:$O$60,3,FALSE),"-") -> - | E13: =IFERROR(SMALL($F$58:$O$58,C13),"-") -> - | G13: =C13 -> 8 | H13: =IFERROR(HLOOKUP(K13,$F$59:$O$60,2,FALSE),"-") -> - | K13: =IFERROR(SMALL($F$59:$O$59,C13),"-") -> -
C14: =C13+1 -> 9 | D14: =IFERROR(HLOOKUP(E14,$F$58:$O$60,3,FALSE),"-") -> - | E14: =IFERROR(SMALL($F$58:$O$58,C14),"-") -> - | G14: =C14 -> 9 | H14: =IFERROR(HLOOKUP(K14,$F$59:$O$60,2,FALSE),"-") -> - | K14: =IFERROR(SMALL($F$59:$O$59,C14),"-") -> -
C15: =C14+1 -> 10 | D15: =IFERROR(HLOOKUP(E15,$F$58:$O$60,3,FALSE),"-") -> - | E15: =IFERROR(SMALL($F$58:$O$58,C15),"-") -> - | G15: =C15 -> 10 | H15: =IFERROR(HLOOKUP(K15,$F$59:$O$60,2,FALSE),"-") -> - | K15: =IFERROR(SMALL($F$59:$O$59,C15),"-") -> -
F18: =VLOOKUP(F19,Производительность!$C$7:$AB$33,26,FALSE) -> рудгормаш | G18: =VLOOKUP(G19,Производительность!$C$7:$AB$33,26,FALSE) -> #N/A | H18: =VLOOKUP(H19,Производительность!$C$7:$AB$33,26,FALSE) -> #N/A | I18: =VLOOKUP(I19,Производительность!$C$7:$AB$33,26,FALSE) -> #N/A | J18: =VLOOKUP(J19,Производительность!$C$7:$AB$33,26,FALSE) -> #N/A | K18: =VLOOKUP(K19,Производительность!$C$7:$AB$33,26,FALSE) -> #N/A | L18: =VLOOKUP(L19,Производительность!$C$7:$AB$33,26,FALSE) -> #N/A | M18: =VLOOKUP(M19,Производительность!$C$7:$AB$33,26,FALSE) -> #N/A | ... O18: =VLOOKUP(O19,Производительность!$C$7:$AB$33,26,FALSE) -> #N/A
C19: № | D19: Показатель | E19: Ед. изм. | F19: =Производительность!C16 -> СБШ-250/270КП | P19: Комментарий
C20: 1 | D20: Диаметр бурения (в расчете) | E20: мм | F20: =SUMIFS('W час'!$E$19:$AF$19,'W час'!$E$4:$AF$4,F$19)*1000 -> 266.96421 | G20: =SUMIFS('W час'!$E$19:$AF$19,'W час'!$E$4:$AF$4,G$19)*1000 -> 0 | H20: =SUMIFS('W час'!$E$19:$AF$19,'W час'!$E$4:$AF$4,H$19)*1000 -> 0 | I20: =SUMIFS('W час'!$E$19:$AF$19,'W час'!$E$4:$AF$4,I$19)*1000 -> 0 | J20: =SUMIFS('W час'!$E$19:$AF$19,'W час'!$E$4:$AF$4,J$19)*1000 -> 0 | K20: =SUMIFS('W час'!$E$19:$AF$19,'W час'!$E$4:$AF$4,K$19)*1000 -> 0 | L20: =SUMIFS('W час'!$E$19:$AF$19,'W час'!$E$4:$AF$4,L$19)*1000 -> 0 | M20: =SUMIFS('W час'!$E$19:$AF$19,'W час'!$E$4:$AF$4,M$19)*1000 -> 0 | ... O20: =SUMIFS('W час'!$E$19:$AF$19,'W час'!$E$4:$AF$4,O$19)*1000 -> 0
C21: =MAX(C$20:C20)+1 -> 2 | D21: Вес станка | E21: т | F21: =HLOOKUP(F$19,'W час'!$E$4:$AF$5,2,FALSE) -> 130 | G21: =HLOOKUP(G$19,'W час'!$E$4:$AF$5,2,FALSE) -> #N/A | H21: =HLOOKUP(H$19,'W час'!$E$4:$AF$5,2,FALSE) -> #N/A | I21: =HLOOKUP(I$19,'W час'!$E$4:$AF$5,2,FALSE) -> #N/A | J21: =HLOOKUP(J$19,'W час'!$E$4:$AF$5,2,FALSE) -> #N/A | K21: =HLOOKUP(K$19,'W час'!$E$4:$AF$5,2,FALSE) -> #N/A | L21: =HLOOKUP(L$19,'W час'!$E$4:$AF$5,2,FALSE) -> #N/A | M21: =HLOOKUP(M$19,'W час'!$E$4:$AF$5,2,FALSE) -> #N/A | ... O21: =HLOOKUP(O$19,'W час'!$E$4:$AF$5,2,FALSE) -> #N/A
C22: =MAX(C$20:C21)+1 -> 3 | D22: Мощность привода вращателя (в расчете) | E22: кВт | F22: =SUMIFS('W час'!$E$22:$AF$22,'W час'!$E$4:$AF$4,F$19) -> 120 | G22: =SUMIFS('W час'!$E$22:$AF$22,'W час'!$E$4:$AF$4,G$19) -> 0 | H22: =SUMIFS('W час'!$E$22:$AF$22,'W час'!$E$4:$AF$4,H$19) -> 0 | I22: =SUMIFS('W час'!$E$22:$AF$22,'W час'!$E$4:$AF$4,I$19) -> 0 | J22: =SUMIFS('W час'!$E$22:$AF$22,'W час'!$E$4:$AF$4,J$19) -> 0 | K22: =SUMIFS('W час'!$E$22:$AF$22,'W час'!$E$4:$AF$4,K$19) -> 0 | L22: =SUMIFS('W час'!$E$22:$AF$22,'W час'!$E$4:$AF$4,L$19) -> 0 | M22: =SUMIFS('W час'!$E$22:$AF$22,'W час'!$E$4:$AF$4,M$19) -> 0 | ... O22: =SUMIFS('W час'!$E$22:$AF$22,'W час'!$E$4:$AF$4,O$19) -> 0
C23: =MAX(C$20:C22)+1 -> 4 | D23: Срок эксплуатации | E23: лет | F23: =SUMIFS(Производительность!$Y$7:$Y$34,Производительность!$C$7:$C$34,F$19) -> 0 | G23: =SUMIFS(Производительность!$Y$7:$Y$34,Производительность!$C$7:$C$34,G$19) -> 0 | H23: =SUMIFS(Производительность!$Y$7:$Y$34,Производительность!$C$7:$C$34,H$19) -> 0 | I23: =SUMIFS(Производительность!$Y$7:$Y$34,Производительность!$C$7:$C$34,I$19) -> 0 | J23: =SUMIFS(Производительность!$Y$7:$Y$34,Производительность!$C$7:$C$34,J$19) -> 0 | K23: =SUMIFS(Производительность!$Y$7:$Y$34,Производительность!$C$7:$C$34,K$19) -> 0 | L23: =SUMIFS(Производительность!$Y$7:$Y$34,Производительность!$C$7:$C$34,L$19) -> 0 | M23: =SUMIFS(Производительность!$Y$7:$Y$34,Производительность!$C$7:$C$34,M$19) -> 0 | ... O23: =SUMIFS(Производительность!$Y$7:$Y$34,Производительность!$C$7:$C$34,O$19) -> 0
C24: =MAX(C$20:C23)+1 -> 5 | D24: КТГ (средний за эксплуатацию) | E24: коэфф. | F24: =SUMIFS(Производительность!$Z$7:$Z$34,Производительность!$C$7:$C$34,F$19) -> #DIV/0! | G24: =SUMIFS(Производительность!$Z$7:$Z$34,Производительность!$C$7:$C$34,G$19) -> 0 | H24: =SUMIFS(Производительность!$Z$7:$Z$34,Производительность!$C$7:$C$34,H$19) -> 0 | I24: =SUMIFS(Производительность!$Z$7:$Z$34,Производительность!$C$7:$C$34,I$19) -> 0 | J24: =SUMIFS(Производительность!$Z$7:$Z$34,Производительность!$C$7:$C$34,J$19) -> 0 | K24: =SUMIFS(Производительность!$Z$7:$Z$34,Производительность!$C$7:$C$34,K$19) -> 0 | L24: =SUMIFS(Производительность!$Z$7:$Z$34,Производительность!$C$7:$C$34,L$19) -> 0 | M24: =SUMIFS(Производительность!$Z$7:$Z$34,Производительность!$C$7:$C$34,M$19) -> 0 | ... O24: =SUMIFS(Производительность!$Z$7:$Z$34,Производительность!$C$7:$C$34,O$19) -> 0
C25: =MAX(C$20:C24)+1 -> 6 | D25: КТГ (1-й год) | E25: =E24 -> коэфф. | F25: =SUMIFS(Производительность!$E$7:$E$34,Производительность!$C$7:$C$34,F$19) -> 0 | G25: =SUMIFS(Производительность!$E$7:$E$34,Производительность!$C$7:$C$34,G$19) -> 0 | H25: =SUMIFS(Производительность!$E$7:$E$34,Производительность!$C$7:$C$34,H$19) -> 0 | I25: =SUMIFS(Производительность!$E$7:$E$34,Производительность!$C$7:$C$34,I$19) -> 0 | J25: =SUMIFS(Производительность!$E$7:$E$34,Производительность!$C$7:$C$34,J$19) -> 0 | K25: =SUMIFS(Производительность!$E$7:$E$34,Производительность!$C$7:$C$34,K$19) -> 0 | L25: =SUMIFS(Производительность!$E$7:$E$34,Производительность!$C$7:$C$34,L$19) -> 0 | M25: =SUMIFS(Производительность!$E$7:$E$34,Производительность!$C$7:$C$34,M$19) -> 0 | ... O25: =SUMIFS(Производительность!$E$7:$E$34,Производительность!$C$7:$C$34,O$19) -> 0
C26: =MAX(C$20:C25)+1 -> 7 | D26: КИО (средний за эксплуатацию) | E26: =E24 -> коэфф. | F26: =SUMIFS(Производительность!$Z$115:$Z$142,Производительность!$C$115:$C$142,F$19) -> #DIV/0! | G26: =SUMIFS(Производительность!$Z$115:$Z$142,Производительность!$C$115:$C$142,G$19) -> 0 | H26: =SUMIFS(Производительность!$Z$115:$Z$142,Производительность!$C$115:$C$142,H$19) -> 0 | I26: =SUMIFS(Производительность!$Z$115:$Z$142,Производительность!$C$115:$C$142,I$19) -> 0 | J26: =SUMIFS(Производительность!$Z$115:$Z$142,Производительность!$C$115:$C$142,J$19) -> 0 | K26: =SUMIFS(Производительность!$Z$115:$Z$142,Производительность!$C$115:$C$142,K$19) -> 0 | L26: =SUMIFS(Производительность!$Z$115:$Z$142,Производительность!$C$115:$C$142,L$19) -> 0 | M26: =SUMIFS(Производительность!$Z$115:$Z$142,Производительность!$C$115:$C$142,M$19) -> 0 | ... O26: =SUMIFS(Производительность!$Z$115:$Z$142,Производительность!$C$115:$C$142,O$19) -> 0
C27: =MAX(C$20:C26)+1 -> 8 | D27: Часовая производительность | E27: п. м/час | F27: =SUMIFS(Производительность!$E$169:$E$196,Производительность!$C$169:$C$196,F$19) -> 14.098448 | G27: =SUMIFS(Производительность!$E$169:$E$196,Производительность!$C$169:$C$196,G$19) -> 0 | H27: =SUMIFS(Производительность!$E$169:$E$196,Производительность!$C$169:$C$196,H$19) -> 0 | I27: =SUMIFS(Производительность!$E$169:$E$196,Производительность!$C$169:$C$196,I$19) -> 0 | J27: =SUMIFS(Производительность!$E$169:$E$196,Производительность!$C$169:$C$196,J$19) -> 0 | K27: =SUMIFS(Производительность!$E$169:$E$196,Производительность!$C$169:$C$196,K$19) -> 0 | L27: =SUMIFS(Производительность!$E$169:$E$196,Производительность!$C$169:$C$196,L$19) -> 0 | M27: =SUMIFS(Производительность!$E$169:$E$196,Производительность!$C$169:$C$196,M$19) -> 0 | ... O27: =SUMIFS(Производительность!$E$169:$E$196,Производительность!$C$169:$C$196,O$19) -> 0
C28: =MAX(C$20:C27)+1 -> 9 | D28: Производительность (средняя за эксплуатацию) | E28: тыс. п. м | F28: =SUMIFS(Производительность!$Z$196:$Z$223,Производительность!$C$196:$C$223,F$19) -> #DIV/0! | G28: =SUMIFS(Производительность!$Z$196:$Z$223,Производительность!$C$196:$C$223,G$19) -> 0 | H28: =SUMIFS(Производительность!$Z$196:$Z$223,Производительность!$C$196:$C$223,H$19) -> 0 | I28: =SUMIFS(Производительность!$Z$196:$Z$223,Производительность!$C$196:$C$223,I$19) -> 0 | J28: =SUMIFS(Производительность!$Z$196:$Z$223,Производительность!$C$196:$C$223,J$19) -> 0 | K28: =SUMIFS(Производительность!$Z$196:$Z$223,Производительность!$C$196:$C$223,K$19) -> 0 | L28: =SUMIFS(Производительность!$Z$196:$Z$223,Производительность!$C$196:$C$223,L$19) -> 0 | M28: =SUMIFS(Производительность!$Z$196:$Z$223,Производительность!$C$196:$C$223,M$19) -> 0 | ... O28: =SUMIFS(Производительность!$Z$196:$Z$223,Производительность!$C$196:$C$223,O$19) -> 0
C29: =MAX(C$20:C28)+1 -> 10 | E29: тыс. м3 | F29: =SUMIFS(Производительность!$Z$250:$Z$277,Производительность!$C$250:$C$277,F$19) -> #DIV/0! | G29: =SUMIFS(Производительность!$Z$250:$Z$277,Производительность!$C$250:$C$277,G$19) -> 0 | H29: =SUMIFS(Производительность!$Z$250:$Z$277,Производительность!$C$250:$C$277,H$19) -> 0 | I29: =SUMIFS(Производительность!$Z$250:$Z$277,Производительность!$C$250:$C$277,I$19) -> 0 | J29: =SUMIFS(Производительность!$Z$250:$Z$277,Производительность!$C$250:$C$277,J$19) -> 0 | K29: =SUMIFS(Производительность!$Z$250:$Z$277,Производительность!$C$250:$C$277,K$19) -> 0 | L29: =SUMIFS(Производительность!$Z$250:$Z$277,Производительность!$C$250:$C$277,L$19) -> 0 | M29: =SUMIFS(Производительность!$Z$250:$Z$277,Производительность!$C$250:$C$277,M$19) -> 0 | ... O29: =SUMIFS(Производительность!$Z$250:$Z$277,Производительность!$C$250:$C$277,O$19) -> 0
C30: =MAX(C$20:C29)+1 -> 11 | D30: Производительность (1-й год) | E30: =E28 -> тыс. п. м | F30: =SUMIFS(Производительность!$E$196:$E$223,Производительность!$C$196:$C$223,F$19) -> 0 | G30: =SUMIFS(Производительность!$E$196:$E$223,Производительность!$C$196:$C$223,G$19) -> 0 | H30: =SUMIFS(Производительность!$E$196:$E$223,Производительность!$C$196:$C$223,H$19) -> 0 | I30: =SUMIFS(Производительность!$E$196:$E$223,Производительность!$C$196:$C$223,I$19) -> 0 | J30: =SUMIFS(Производительность!$E$196:$E$223,Производительность!$C$196:$C$223,J$19) -> 0 | K30: =SUMIFS(Производительность!$E$196:$E$223,Производительность!$C$196:$C$223,K$19) -> 0 | L30: =SUMIFS(Производительность!$E$196:$E$223,Производительность!$C$196:$C$223,L$19) -> 0 | M30: =SUMIFS(Производительность!$E$196:$E$223,Производительность!$C$196:$C$223,M$19) -> 0 | ... O30: =SUMIFS(Производительность!$E$196:$E$223,Производительность!$C$196:$C$223,O$19) -> 0
C31: =MAX(C$20:C30)+1 -> 12 | E31: =E29 -> тыс. м3 | F31: =SUMIFS(Производительность!$E$250:$E$277,Производительность!$C$250:$C$277,F$19) -> 0 | G31: =SUMIFS(Производительность!$E$250:$E$277,Производительность!$C$250:$C$277,G$19) -> 0 | H31: =SUMIFS(Производительность!$E$250:$E$277,Производительность!$C$250:$C$277,H$19) -> 0 | I31: =SUMIFS(Производительность!$E$250:$E$277,Производительность!$C$250:$C$277,I$19) -> 0 | J31: =SUMIFS(Производительность!$E$250:$E$277,Производительность!$C$250:$C$277,J$19) -> 0 | K31: =SUMIFS(Производительность!$E$250:$E$277,Производительность!$C$250:$C$277,K$19) -> 0 | L31: =SUMIFS(Производительность!$E$250:$E$277,Производительность!$C$250:$C$277,L$19) -> 0 | M31: =SUMIFS(Производительность!$E$250:$E$277,Производительность!$C$250:$C$277,M$19) -> 0 | ... O31: =SUMIFS(Производительность!$E$250:$E$277,Производительность!$C$250:$C$277,O$19) -> 0
C33: =MAX(C$20:C32)+1 -> 13 | D33: Стоимость станка | E33: тыс. руб. | F33: =F37+F38 -> 0 | G33: =G37+G38 -> 0 | H33: =H37+H38 -> 0 | I33: =I37+I38 -> 0 | J33: =J37+J38 -> 0 | K33: =K37+K38 -> 0 | L33: =L37+L38 -> 0 | M33: =M37+M38 -> 0 | ... O33: =O37+O38 -> 0 | R33: ='Свод_250-270_диз'!R33 -> курс ЦБ на хх.07.2026
A34: заполнить | C34: =MAX(C$20:C33)+1 -> 14 | D34: Цена в долларах | E34: тыс. долл. | R34: ='Свод_250-270_диз'!R34 -> 80
A35: заполнить | C35: =MAX(C$20:C34)+1 -> 15 | D35: Цена в евро | E35: тыс. евро | R35: ='Свод_250-270_диз'!R35 -> 90
A36: заполнить | C36: =MAX(C$20:C35)+1 -> 16 | D36: Цена в юанях | E36: тыс. юаней | R36: ='Свод_250-270_диз'!R36 -> 11
A37: заполнить | C37: =MAX(C$20:C36)+1 -> 17 | D37: Цена в рублях | E37: =E33 -> тыс. руб.
A38: заполнить | C38: =MAX(C$20:C37)+1 -> 18 | D38: Сборка | E38: =E33 -> тыс. руб.
A40: заполнить | C40: =MAX(C$20:C39)+1 -> 19 | D40: Потребность | E40: ед.
C41: =MAX(C$20:C40)+1 -> 20 | D41: CAPEX на потребность | E41: =E33 -> тыс. руб. | F41: =F40*F33 -> 0 | G41: =G40*G33 -> 0 | H41: =H40*H33 -> 0 | I41: =I40*I33 -> 0 | J41: =J40*J33 -> 0 | K41: =K40*K33 -> 0 | L41: =L40*L33 -> 0 | M41: =M40*M33 -> 0 | ... O41: =O40*O33 -> 0
C43: =MAX(C$20:C42)+1 -> 21 | D43: Среднегодовые затраты на ТО (включая смазочные) и ремонты | E43: тыс. руб. | F43: =SUMIFS('ТСО_250-270_эл'!$AB:$AB,'ТСО_250-270_эл'!$A:$A,F$19) -> #DIV/0! | G43: =SUMIFS('ТСО_250-270_эл'!$AB:$AB,'ТСО_250-270_эл'!$A:$A,G$19) -> 0 | H43: =SUMIFS('ТСО_250-270_эл'!$AB:$AB,'ТСО_250-270_эл'!$A:$A,H$19) -> 0 | I43: =SUMIFS('ТСО_250-270_эл'!$AB:$AB,'ТСО_250-270_эл'!$A:$A,I$19) -> 0 | J43: =SUMIFS('ТСО_250-270_эл'!$AB:$AB,'ТСО_250-270_эл'!$A:$A,J$19) -> 0 | K43: =SUMIFS('ТСО_250-270_эл'!$AB:$AB,'ТСО_250-270_эл'!$A:$A,K$19) -> 0 | L43: =SUMIFS('ТСО_250-270_эл'!$AB:$AB,'ТСО_250-270_эл'!$A:$A,L$19) -> 0 | M43: =SUMIFS('ТСО_250-270_эл'!$AB:$AB,'ТСО_250-270_эл'!$A:$A,M$19) -> 0 | ... O43: =SUMIFS('ТСО_250-270_эл'!$AB:$AB,'ТСО_250-270_эл'!$A:$A,O$19) -> 0
A45: ='ТСО_250-270_эл'!B87 -> Аннуитет операционный | C45: =MAX(C$20:C44)+1 -> 22 | D45: ='ТСО_250-270_эл'!D87 -> Аннуитет операционный | E45: ='ТСО_250-270_эл'!E87 -> руб/м3 | F45: =SUMIFS('ТСО_250-270_эл'!$AC:$AC,'ТСО_250-270_эл'!$A:$A,F$19,'ТСО_250-270_эл'!$B:$B,$A45) -> #DIV/0! | G45: =SUMIFS('ТСО_250-270_эл'!$AC:$AC,'ТСО_250-270_эл'!$A:$A,G$19,'ТСО_250-270_эл'!$B:$B,$A45) -> 0 | H45: =SUMIFS('ТСО_250-270_эл'!$AC:$AC,'ТСО_250-270_эл'!$A:$A,H$19,'ТСО_250-270_эл'!$B:$B,$A45) -> 0 | I45: =SUMIFS('ТСО_250-270_эл'!$AC:$AC,'ТСО_250-270_эл'!$A:$A,I$19,'ТСО_250-270_эл'!$B:$B,$A45) -> 0 | J45: =SUMIFS('ТСО_250-270_эл'!$AC:$AC,'ТСО_250-270_эл'!$A:$A,J$19,'ТСО_250-270_эл'!$B:$B,$A45) -> 0 | K45: =SUMIFS('ТСО_250-270_эл'!$AC:$AC,'ТСО_250-270_эл'!$A:$A,K$19,'ТСО_250-270_эл'!$B:$B,$A45) -> 0 | L45: =SUMIFS('ТСО_250-270_эл'!$AC:$AC,'ТСО_250-270_эл'!$A:$A,L$19,'ТСО_250-270_эл'!$B:$B,$A45) -> 0 | M45: =SUMIFS('ТСО_250-270_эл'!$AC:$AC,'ТСО_250-270_эл'!$A:$A,M$19,'ТСО_250-270_эл'!$B:$B,$A45) -> 0 | ... O45: =SUMIFS('ТСО_250-270_эл'!$AC:$AC,'ТСО_250-270_эл'!$A:$A,O$19,'ТСО_250-270_эл'!$B:$B,$A45) -> 0
A46: ='ТСО_250-270_эл'!B88 -> ТО, ТР, ППР | C46: =MAX(C$20:C45)+1 -> 23 | D46: ='ТСО_250-270_эл'!D88 -> ТО, ТР, ППР | E46: ='ТСО_250-270_эл'!E88 -> руб/м3 | F46: =SUMIFS('ТСО_250-270_эл'!$AC:$AC,'ТСО_250-270_эл'!$A:$A,F$19,'ТСО_250-270_эл'!$B:$B,$A46) -> #DIV/0! | G46: =SUMIFS('ТСО_250-270_эл'!$AC:$AC,'ТСО_250-270_эл'!$A:$A,G$19,'ТСО_250-270_эл'!$B:$B,$A46) -> 0 | H46: =SUMIFS('ТСО_250-270_эл'!$AC:$AC,'ТСО_250-270_эл'!$A:$A,H$19,'ТСО_250-270_эл'!$B:$B,$A46) -> 0 | I46: =SUMIFS('ТСО_250-270_эл'!$AC:$AC,'ТСО_250-270_эл'!$A:$A,I$19,'ТСО_250-270_эл'!$B:$B,$A46) -> 0 | J46: =SUMIFS('ТСО_250-270_эл'!$AC:$AC,'ТСО_250-270_эл'!$A:$A,J$19,'ТСО_250-270_эл'!$B:$B,$A46) -> 0 | K46: =SUMIFS('ТСО_250-270_эл'!$AC:$AC,'ТСО_250-270_эл'!$A:$A,K$19,'ТСО_250-270_эл'!$B:$B,$A46) -> 0 | L46: =SUMIFS('ТСО_250-270_эл'!$AC:$AC,'ТСО_250-270_эл'!$A:$A,L$19,'ТСО_250-270_эл'!$B:$B,$A46) -> 0 | M46: =SUMIFS('ТСО_250-270_эл'!$AC:$AC,'ТСО_250-270_эл'!$A:$A,M$19,'ТСО_250-270_эл'!$B:$B,$A46) -> 0 | ... O46: =SUMIFS('ТСО_250-270_эл'!$AC:$AC,'ТСО_250-270_эл'!$A:$A,O$19,'ТСО_250-270_эл'!$B:$B,$A46) -> 0
A47: ='ТСО_250-270_эл'!B89 -> Смазочные | C47: =MAX(C$20:C46)+1 -> 24 | D47: ='ТСО_250-270_эл'!D89 -> Смазочные | E47: ='ТСО_250-270_эл'!E89 -> руб/м3 | F47: =SUMIFS('ТСО_250-270_эл'!$AC:$AC,'ТСО_250-270_эл'!$A:$A,F$19,'ТСО_250-270_эл'!$B:$B,$A47) -> #DIV/0! | G47: =SUMIFS('ТСО_250-270_эл'!$AC:$AC,'ТСО_250-270_эл'!$A:$A,G$19,'ТСО_250-270_эл'!$B:$B,$A47) -> 0 | H47: =SUMIFS('ТСО_250-270_эл'!$AC:$AC,'ТСО_250-270_эл'!$A:$A,H$19,'ТСО_250-270_эл'!$B:$B,$A47) -> 0 | I47: =SUMIFS('ТСО_250-270_эл'!$AC:$AC,'ТСО_250-270_эл'!$A:$A,I$19,'ТСО_250-270_эл'!$B:$B,$A47) -> 0 | J47: =SUMIFS('ТСО_250-270_эл'!$AC:$AC,'ТСО_250-270_эл'!$A:$A,J$19,'ТСО_250-270_эл'!$B:$B,$A47) -> 0 | K47: =SUMIFS('ТСО_250-270_эл'!$AC:$AC,'ТСО_250-270_эл'!$A:$A,K$19,'ТСО_250-270_эл'!$B:$B,$A47) -> 0 | L47: =SUMIFS('ТСО_250-270_эл'!$AC:$AC,'ТСО_250-270_эл'!$A:$A,L$19,'ТСО_250-270_эл'!$B:$B,$A47) -> 0 | M47: =SUMIFS('ТСО_250-270_эл'!$AC:$AC,'ТСО_250-270_эл'!$A:$A,M$19,'ТСО_250-270_эл'!$B:$B,$A47) -> 0 | ... O47: =SUMIFS('ТСО_250-270_эл'!$AC:$AC,'ТСО_250-270_эл'!$A:$A,O$19,'ТСО_250-270_эл'!$B:$B,$A47) -> 0
A48: ='ТСО_250-270_эл'!B90 -> Долота | C48: =MAX(C$20:C47)+1 -> 25 | D48: ='ТСО_250-270_эл'!D90 -> Долота | E48: ='ТСО_250-270_эл'!E90 -> руб/м3 | F48: =SUMIFS('ТСО_250-270_эл'!$AC:$AC,'ТСО_250-270_эл'!$A:$A,F$19,'ТСО_250-270_эл'!$B:$B,$A48) -> #DIV/0! | G48: =SUMIFS('ТСО_250-270_эл'!$AC:$AC,'ТСО_250-270_эл'!$A:$A,G$19,'ТСО_250-270_эл'!$B:$B,$A48) -> 0 | H48: =SUMIFS('ТСО_250-270_эл'!$AC:$AC,'ТСО_250-270_эл'!$A:$A,H$19,'ТСО_250-270_эл'!$B:$B,$A48) -> 0 | I48: =SUMIFS('ТСО_250-270_эл'!$AC:$AC,'ТСО_250-270_эл'!$A:$A,I$19,'ТСО_250-270_эл'!$B:$B,$A48) -> 0 | J48: =SUMIFS('ТСО_250-270_эл'!$AC:$AC,'ТСО_250-270_эл'!$A:$A,J$19,'ТСО_250-270_эл'!$B:$B,$A48) -> 0 | K48: =SUMIFS('ТСО_250-270_эл'!$AC:$AC,'ТСО_250-270_эл'!$A:$A,K$19,'ТСО_250-270_эл'!$B:$B,$A48) -> 0 | L48: =SUMIFS('ТСО_250-270_эл'!$AC:$AC,'ТСО_250-270_эл'!$A:$A,L$19,'ТСО_250-270_эл'!$B:$B,$A48) -> 0 | M48: =SUMIFS('ТСО_250-270_эл'!$AC:$AC,'ТСО_250-270_эл'!$A:$A,M$19,'ТСО_250-270_эл'!$B:$B,$A48) -> 0 | ... O48: =SUMIFS('ТСО_250-270_эл'!$AC:$AC,'ТСО_250-270_эл'!$A:$A,O$19,'ТСО_250-270_эл'!$B:$B,$A48) -> 0
A49: ='ТСО_250-270_эл'!B91 -> Штанги буровые | C49: =MAX(C$20:C48)+1 -> 26 | D49: ='ТСО_250-270_эл'!D91 -> Штанги буровые | E49: ='ТСО_250-270_эл'!E91 -> руб/м3 | F49: =SUMIFS('ТСО_250-270_эл'!$AC:$AC,'ТСО_250-270_эл'!$A:$A,F$19,'ТСО_250-270_эл'!$B:$B,$A49) -> #DIV/0! | G49: =SUMIFS('ТСО_250-270_эл'!$AC:$AC,'ТСО_250-270_эл'!$A:$A,G$19,'ТСО_250-270_эл'!$B:$B,$A49) -> 0 | H49: =SUMIFS('ТСО_250-270_эл'!$AC:$AC,'ТСО_250-270_эл'!$A:$A,H$19,'ТСО_250-270_эл'!$B:$B,$A49) -> 0 | I49: =SUMIFS('ТСО_250-270_эл'!$AC:$AC,'ТСО_250-270_эл'!$A:$A,I$19,'ТСО_250-270_эл'!$B:$B,$A49) -> 0 | J49: =SUMIFS('ТСО_250-270_эл'!$AC:$AC,'ТСО_250-270_эл'!$A:$A,J$19,'ТСО_250-270_эл'!$B:$B,$A49) -> 0 | K49: =SUMIFS('ТСО_250-270_эл'!$AC:$AC,'ТСО_250-270_эл'!$A:$A,K$19,'ТСО_250-270_эл'!$B:$B,$A49) -> 0 | L49: =SUMIFS('ТСО_250-270_эл'!$AC:$AC,'ТСО_250-270_эл'!$A:$A,L$19,'ТСО_250-270_эл'!$B:$B,$A49) -> 0 | M49: =SUMIFS('ТСО_250-270_эл'!$AC:$AC,'ТСО_250-270_эл'!$A:$A,M$19,'ТСО_250-270_эл'!$B:$B,$A49) -> 0 | ... O49: =SUMIFS('ТСО_250-270_эл'!$AC:$AC,'ТСО_250-270_эл'!$A:$A,O$19,'ТСО_250-270_эл'!$B:$B,$A49) -> 0
A50: ='ТСО_250-270_эл'!B92 -> Расходники | C50: =MAX(C$20:C49)+1 -> 27 | D50: ='ТСО_250-270_эл'!D92 -> Расходники | E50: ='ТСО_250-270_эл'!E92 -> руб/м3 | F50: =SUMIFS('ТСО_250-270_эл'!$AC:$AC,'ТСО_250-270_эл'!$A:$A,F$19,'ТСО_250-270_эл'!$B:$B,$A50) -> #DIV/0! | G50: =SUMIFS('ТСО_250-270_эл'!$AC:$AC,'ТСО_250-270_эл'!$A:$A,G$19,'ТСО_250-270_эл'!$B:$B,$A50) -> 0 | H50: =SUMIFS('ТСО_250-270_эл'!$AC:$AC,'ТСО_250-270_эл'!$A:$A,H$19,'ТСО_250-270_эл'!$B:$B,$A50) -> 0 | I50: =SUMIFS('ТСО_250-270_эл'!$AC:$AC,'ТСО_250-270_эл'!$A:$A,I$19,'ТСО_250-270_эл'!$B:$B,$A50) -> 0 | J50: =SUMIFS('ТСО_250-270_эл'!$AC:$AC,'ТСО_250-270_эл'!$A:$A,J$19,'ТСО_250-270_эл'!$B:$B,$A50) -> 0 | K50: =SUMIFS('ТСО_250-270_эл'!$AC:$AC,'ТСО_250-270_эл'!$A:$A,K$19,'ТСО_250-270_эл'!$B:$B,$A50) -> 0 | L50: =SUMIFS('ТСО_250-270_эл'!$AC:$AC,'ТСО_250-270_эл'!$A:$A,L$19,'ТСО_250-270_эл'!$B:$B,$A50) -> 0 | M50: =SUMIFS('ТСО_250-270_эл'!$AC:$AC,'ТСО_250-270_эл'!$A:$A,M$19,'ТСО_250-270_эл'!$B:$B,$A50) -> 0 | ... O50: =SUMIFS('ТСО_250-270_эл'!$AC:$AC,'ТСО_250-270_эл'!$A:$A,O$19,'ТСО_250-270_эл'!$B:$B,$A50) -> 0
A51: ='ТСО_250-270_эл'!B93 -> Топливо/Электроэнергия | C51: =MAX(C$20:C50)+1 -> 28 | D51: ='ТСО_250-270_эл'!D93 -> Топливо/Электроэнергия | E51: ='ТСО_250-270_эл'!E93 -> руб/м3 | F51: =SUMIFS('ТСО_250-270_эл'!$AC:$AC,'ТСО_250-270_эл'!$A:$A,F$19,'ТСО_250-270_эл'!$B:$B,$A51) -> #DIV/0! | G51: =SUMIFS('ТСО_250-270_эл'!$AC:$AC,'ТСО_250-270_эл'!$A:$A,G$19,'ТСО_250-270_эл'!$B:$B,$A51) -> 0 | H51: =SUMIFS('ТСО_250-270_эл'!$AC:$AC,'ТСО_250-270_эл'!$A:$A,H$19,'ТСО_250-270_эл'!$B:$B,$A51) -> 0 | I51: =SUMIFS('ТСО_250-270_эл'!$AC:$AC,'ТСО_250-270_эл'!$A:$A,I$19,'ТСО_250-270_эл'!$B:$B,$A51) -> 0 | J51: =SUMIFS('ТСО_250-270_эл'!$AC:$AC,'ТСО_250-270_эл'!$A:$A,J$19,'ТСО_250-270_эл'!$B:$B,$A51) -> 0 | K51: =SUMIFS('ТСО_250-270_эл'!$AC:$AC,'ТСО_250-270_эл'!$A:$A,K$19,'ТСО_250-270_эл'!$B:$B,$A51) -> 0 | L51: =SUMIFS('ТСО_250-270_эл'!$AC:$AC,'ТСО_250-270_эл'!$A:$A,L$19,'ТСО_250-270_эл'!$B:$B,$A51) -> 0 | M51: =SUMIFS('ТСО_250-270_эл'!$AC:$AC,'ТСО_250-270_эл'!$A:$A,M$19,'ТСО_250-270_эл'!$B:$B,$A51) -> 0 | ... O51: =SUMIFS('ТСО_250-270_эл'!$AC:$AC,'ТСО_250-270_эл'!$A:$A,O$19,'ТСО_250-270_эл'!$B:$B,$A51) -> 0
A52: ='ТСО_250-270_эл'!B94 -> Затраты на персонал | C52: =MAX(C$20:C51)+1 -> 29 | D52: ='ТСО_250-270_эл'!D94 -> Затраты на персонал | E52: ='ТСО_250-270_эл'!E94 -> руб/м3 | F52: =SUMIFS('ТСО_250-270_эл'!$AC:$AC,'ТСО_250-270_эл'!$A:$A,F$19,'ТСО_250-270_эл'!$B:$B,$A52) -> #DIV/0! | G52: =SUMIFS('ТСО_250-270_эл'!$AC:$AC,'ТСО_250-270_эл'!$A:$A,G$19,'ТСО_250-270_эл'!$B:$B,$A52) -> 0 | H52: =SUMIFS('ТСО_250-270_эл'!$AC:$AC,'ТСО_250-270_эл'!$A:$A,H$19,'ТСО_250-270_эл'!$B:$B,$A52) -> 0 | I52: =SUMIFS('ТСО_250-270_эл'!$AC:$AC,'ТСО_250-270_эл'!$A:$A,I$19,'ТСО_250-270_эл'!$B:$B,$A52) -> 0 | J52: =SUMIFS('ТСО_250-270_эл'!$AC:$AC,'ТСО_250-270_эл'!$A:$A,J$19,'ТСО_250-270_эл'!$B:$B,$A52) -> 0 | K52: =SUMIFS('ТСО_250-270_эл'!$AC:$AC,'ТСО_250-270_эл'!$A:$A,K$19,'ТСО_250-270_эл'!$B:$B,$A52) -> 0 | L52: =SUMIFS('ТСО_250-270_эл'!$AC:$AC,'ТСО_250-270_эл'!$A:$A,L$19,'ТСО_250-270_эл'!$B:$B,$A52) -> 0 | M52: =SUMIFS('ТСО_250-270_эл'!$AC:$AC,'ТСО_250-270_эл'!$A:$A,M$19,'ТСО_250-270_эл'!$B:$B,$A52) -> 0 | ... O52: =SUMIFS('ТСО_250-270_эл'!$AC:$AC,'ТСО_250-270_эл'!$A:$A,O$19,'ТСО_250-270_эл'!$B:$B,$A52) -> 0
A53: ='ТСО_250-270_эл'!B95 -> Транспортный налог | C53: =MAX(C$20:C52)+1 -> 30 | D53: ='ТСО_250-270_эл'!D95 -> Транспортный налог | E53: ='ТСО_250-270_эл'!E95 -> руб/м3 | F53: =SUMIFS('ТСО_250-270_эл'!$AC:$AC,'ТСО_250-270_эл'!$A:$A,F$19,'ТСО_250-270_эл'!$B:$B,$A53) -> #DIV/0! | G53: =SUMIFS('ТСО_250-270_эл'!$AC:$AC,'ТСО_250-270_эл'!$A:$A,G$19,'ТСО_250-270_эл'!$B:$B,$A53) -> 0 | H53: =SUMIFS('ТСО_250-270_эл'!$AC:$AC,'ТСО_250-270_эл'!$A:$A,H$19,'ТСО_250-270_эл'!$B:$B,$A53) -> 0 | I53: =SUMIFS('ТСО_250-270_эл'!$AC:$AC,'ТСО_250-270_эл'!$A:$A,I$19,'ТСО_250-270_эл'!$B:$B,$A53) -> 0 | J53: =SUMIFS('ТСО_250-270_эл'!$AC:$AC,'ТСО_250-270_эл'!$A:$A,J$19,'ТСО_250-270_эл'!$B:$B,$A53) -> 0 | K53: =SUMIFS('ТСО_250-270_эл'!$AC:$AC,'ТСО_250-270_эл'!$A:$A,K$19,'ТСО_250-270_эл'!$B:$B,$A53) -> 0 | L53: =SUMIFS('ТСО_250-270_эл'!$AC:$AC,'ТСО_250-270_эл'!$A:$A,L$19,'ТСО_250-270_эл'!$B:$B,$A53) -> 0 | M53: =SUMIFS('ТСО_250-270_эл'!$AC:$AC,'ТСО_250-270_эл'!$A:$A,M$19,'ТСО_250-270_эл'!$B:$B,$A53) -> 0 | ... O53: =SUMIFS('ТСО_250-270_эл'!$AC:$AC,'ТСО_250-270_эл'!$A:$A,O$19,'ТСО_250-270_эл'!$B:$B,$A53) -> 0
A54: ='ТСО_250-270_эл'!B96 -> Налог на прибыль | C54: =MAX(C$20:C53)+1 -> 31 | D54: ='ТСО_250-270_эл'!D96 -> Налог на прибыль | E54: ='ТСО_250-270_эл'!E96 -> руб/м3 | F54: =SUMIFS('ТСО_250-270_эл'!$AC:$AC,'ТСО_250-270_эл'!$A:$A,F$19,'ТСО_250-270_эл'!$B:$B,$A54) -> #DIV/0! | G54: =SUMIFS('ТСО_250-270_эл'!$AC:$AC,'ТСО_250-270_эл'!$A:$A,G$19,'ТСО_250-270_эл'!$B:$B,$A54) -> 0 | H54: =SUMIFS('ТСО_250-270_эл'!$AC:$AC,'ТСО_250-270_эл'!$A:$A,H$19,'ТСО_250-270_эл'!$B:$B,$A54) -> 0 | I54: =SUMIFS('ТСО_250-270_эл'!$AC:$AC,'ТСО_250-270_эл'!$A:$A,I$19,'ТСО_250-270_эл'!$B:$B,$A54) -> 0 | J54: =SUMIFS('ТСО_250-270_эл'!$AC:$AC,'ТСО_250-270_эл'!$A:$A,J$19,'ТСО_250-270_эл'!$B:$B,$A54) -> 0 | K54: =SUMIFS('ТСО_250-270_эл'!$AC:$AC,'ТСО_250-270_эл'!$A:$A,K$19,'ТСО_250-270_эл'!$B:$B,$A54) -> 0 | L54: =SUMIFS('ТСО_250-270_эл'!$AC:$AC,'ТСО_250-270_эл'!$A:$A,L$19,'ТСО_250-270_эл'!$B:$B,$A54) -> 0 | M54: =SUMIFS('ТСО_250-270_эл'!$AC:$AC,'ТСО_250-270_эл'!$A:$A,M$19,'ТСО_250-270_эл'!$B:$B,$A54) -> 0 | ... O54: =SUMIFS('ТСО_250-270_эл'!$AC:$AC,'ТСО_250-270_эл'!$A:$A,O$19,'ТСО_250-270_эл'!$B:$B,$A54) -> 0
A55: ='ТСО_250-270_эл'!B97 -> Аннуитет инвестиционный | C55: =MAX(C$20:C54)+1 -> 32 | D55: ='ТСО_250-270_эл'!D97 -> Аннуитет инвестиционный | E55: ='ТСО_250-270_эл'!E97 -> руб/м3 | F55: =SUMIFS('ТСО_250-270_эл'!$AC:$AC,'ТСО_250-270_эл'!$A:$A,F$19,'ТСО_250-270_эл'!$B:$B,$A55) -> #DIV/0! | G55: =SUMIFS('ТСО_250-270_эл'!$AC:$AC,'ТСО_250-270_эл'!$A:$A,G$19,'ТСО_250-270_эл'!$B:$B,$A55) -> 0 | H55: =SUMIFS('ТСО_250-270_эл'!$AC:$AC,'ТСО_250-270_эл'!$A:$A,H$19,'ТСО_250-270_эл'!$B:$B,$A55) -> 0 | I55: =SUMIFS('ТСО_250-270_эл'!$AC:$AC,'ТСО_250-270_эл'!$A:$A,I$19,'ТСО_250-270_эл'!$B:$B,$A55) -> 0 | J55: =SUMIFS('ТСО_250-270_эл'!$AC:$AC,'ТСО_250-270_эл'!$A:$A,J$19,'ТСО_250-270_эл'!$B:$B,$A55) -> 0 | K55: =SUMIFS('ТСО_250-270_эл'!$AC:$AC,'ТСО_250-270_эл'!$A:$A,K$19,'ТСО_250-270_эл'!$B:$B,$A55) -> 0 | L55: =SUMIFS('ТСО_250-270_эл'!$AC:$AC,'ТСО_250-270_эл'!$A:$A,L$19,'ТСО_250-270_эл'!$B:$B,$A55) -> 0 | M55: =SUMIFS('ТСО_250-270_эл'!$AC:$AC,'ТСО_250-270_эл'!$A:$A,M$19,'ТСО_250-270_эл'!$B:$B,$A55) -> 0 | ... O55: =SUMIFS('ТСО_250-270_эл'!$AC:$AC,'ТСО_250-270_эл'!$A:$A,O$19,'ТСО_250-270_эл'!$B:$B,$A55) -> 0
A56: ='ТСО_250-270_эл'!B99 -> Аннуитет общий | C56: =MAX(C$20:C55)+1 -> 33 | D56: ='ТСО_250-270_эл'!D99 -> Аннуитет общий | E56: ='ТСО_250-270_эл'!E99 -> руб/м3 | F56: =SUMIFS('ТСО_250-270_эл'!$AC:$AC,'ТСО_250-270_эл'!$A:$A,F$19,'ТСО_250-270_эл'!$B:$B,$A56) -> #DIV/0! | G56: =SUMIFS('ТСО_250-270_эл'!$AC:$AC,'ТСО_250-270_эл'!$A:$A,G$19,'ТСО_250-270_эл'!$B:$B,$A56) -> 0 | H56: =SUMIFS('ТСО_250-270_эл'!$AC:$AC,'ТСО_250-270_эл'!$A:$A,H$19,'ТСО_250-270_эл'!$B:$B,$A56) -> 0 | I56: =SUMIFS('ТСО_250-270_эл'!$AC:$AC,'ТСО_250-270_эл'!$A:$A,I$19,'ТСО_250-270_эл'!$B:$B,$A56) -> 0 | J56: =SUMIFS('ТСО_250-270_эл'!$AC:$AC,'ТСО_250-270_эл'!$A:$A,J$19,'ТСО_250-270_эл'!$B:$B,$A56) -> 0 | K56: =SUMIFS('ТСО_250-270_эл'!$AC:$AC,'ТСО_250-270_эл'!$A:$A,K$19,'ТСО_250-270_эл'!$B:$B,$A56) -> 0 | L56: =SUMIFS('ТСО_250-270_эл'!$AC:$AC,'ТСО_250-270_эл'!$A:$A,L$19,'ТСО_250-270_эл'!$B:$B,$A56) -> 0 | M56: =SUMIFS('ТСО_250-270_эл'!$AC:$AC,'ТСО_250-270_эл'!$A:$A,M$19,'ТСО_250-270_эл'!$B:$B,$A56) -> 0 | ... O56: =SUMIFS('ТСО_250-270_эл'!$AC:$AC,'ТСО_250-270_эл'!$A:$A,O$19,'ТСО_250-270_эл'!$B:$B,$A56) -> 0
F57: =F45-SUM(F46:F54)+F56-F45-F55 -> #DIV/0! | G57: =G45-SUM(G46:G54)+G56-G45-G55 -> 0 | H57: =H45-SUM(H46:H54)+H56-H45-H55 -> 0 | I57: =I45-SUM(I46:I54)+I56-I45-I55 -> 0 | J57: =J45-SUM(J46:J54)+J56-J45-J55 -> 0 | K57: =K45-SUM(K46:K54)+K56-K45-K55 -> 0 | L57: =L45-SUM(L46:L54)+L56-L45-L55 -> 0 | M57: =M45-SUM(M46:M54)+M56-M45-M55 -> 0 | ... O57: =O45-SUM(O46:O54)+O56-O45-O55 -> 0
A58: для ранжирования | D58: =D56 -> Аннуитет общий | F58: =IF(F56>0,F56,"нет") -> #DIV/0! | G58: =IF(G56>0,G56,"нет") -> нет | H58: =IF(H56>0,H56,"нет") -> нет | I58: =IF(I56>0,I56,"нет") -> нет | J58: =IF(J56>0,J56,"нет") -> нет | K58: =IF(K56>0,K56,"нет") -> нет | L58: =IF(L56>0,L56,"нет") -> нет | M58: =IF(M56>0,M56,"нет") -> нет | ... O58: =IF(O56>0,O56,"нет") -> нет
A59: =A58 -> для ранжирования | D59: =D33 -> Стоимость станка | F59: =IF(F33>0,F33,"нет") -> нет | G59: =IF(G33>0,G33,"нет") -> нет | H59: =IF(H33>0,H33,"нет") -> нет | I59: =IF(I33>0,I33,"нет") -> нет | J59: =IF(J33>0,J33,"нет") -> нет | K59: =IF(K33>0,K33,"нет") -> нет | L59: =IF(L33>0,L33,"нет") -> нет | M59: =IF(M33>0,M33,"нет") -> нет | ... O59: =IF(O33>0,O33,"нет") -> нет
A60: =A58 -> для ранжирования | F60: =F19 -> СБШ-250/270КП | G60: =G19 -> 0 | H60: =H19 -> 0 | I60: =I19 -> 0 | J60: =J19 -> 0 | K60: =K19 -> 0 | L60: =L19 -> 0 | M60: =M19 -> 0 | ... O60: =O19 -> 0

Sheet ТСО_250-270_эл
A1: не удалять | B1: не удалять | C1: не удалять | D1: Показатель | E1: Ед. изм. | F1: =G1-1 -> 0 | G1: 1 | H1: =G1+1 -> 2 | I1: =H1+1 -> 3 | J1: =I1+1 -> 4 | K1: =J1+1 -> 5 | L1: =K1+1 -> 6 | M1: =L1+1 -> 7 | N1: =M1+1 -> 8 | O1: =N1+1 -> 9 | ... Z1: =Y1+1 -> 20 | AA1: не удалять | AB1: не удалять | AC1: не удалять
A2: * | F2: лет | G2: 2027 | H2: =G2+1 -> 2028 | I2: =H2+1 -> 2029 | J2: =I2+1 -> 2030 | K2: =J2+1 -> 2031 | L2: =K2+1 -> 2032 | M2: =L2+1 -> 2033 | N2: =M2+1 -> 2034 | O2: =N2+1 -> 2035 | ... Z2: =Y2+1 -> 2046 | AA2: проверки | AB2: средние на ТО, ТР, ППР | AC2: аннуитет
A3: * | G3: =Производительность!E6 -> 8760 | H3: =Производительность!F6 -> 8760 | I3: =Производительность!G6 -> 8760 | J3: =Производительность!H6 -> 8760 | K3: =Производительность!I6 -> 8760 | L3: =Производительность!J6 -> 8760 | M3: =Производительность!K6 -> 8760 | N3: =Производительность!L6 -> 8760 | ... Z3: =Производительность!X6 -> 8760
A4: * | D4: Расчет аннуитета
A5: *
A6: * | C6: =SUM(F66:Z66,F80:Z80,F101:Z101,AA48) -> #DIV/0! | D6: ='Свод_250-270_эл'!F19 -> СБШ-250/270КП | E6: =SUMIFS(Производительность!$Y$7:$Y$34,Производительность!$C$7:$C$34,$D6) -> 0 | F6: =$F$2 -> лет
A7: *
A8: =D6 -> СБШ-250/270КП | D8: =D$1 -> Показатель | E8: =E$1 -> Ед. изм. | F8: =F$1 -> 0 | G8: =G$1 -> 1 | H8: =H$1 -> 2 | I8: =I$1 -> 3 | J8: =J$1 -> 4 | K8: =K$1 -> 5 | ... Z8: =Z$1 -> 20
A9: =A8 -> СБШ-250/270КП | D9: КТГ | E9: % | G9: =SUMIFS(Производительность!E$7:E$34,Производительность!$C$7:$C$34,$A9) -> 0 | H9: =SUMIFS(Производительность!F$7:F$34,Производительность!$C$7:$C$34,$A9) -> 0 | I9: =SUMIFS(Производительность!G$7:G$34,Производительность!$C$7:$C$34,$A9) -> 0 | J9: =SUMIFS(Производительность!H$7:H$34,Производительность!$C$7:$C$34,$A9) -> 0 | K9: =SUMIFS(Производительность!I$7:I$34,Производительность!$C$7:$C$34,$A9) -> 0 | L9: =SUMIFS(Производительность!J$7:J$34,Производительность!$C$7:$C$34,$A9) -> 0 | M9: =SUMIFS(Производительность!K$7:K$34,Производительность!$C$7:$C$34,$A9) -> 0 | N9: =SUMIFS(Производительность!L$7:L$34,Производительность!$C$7:$C$34,$A9) -> 0 | ... Z9: =SUMIFS(Производительность!X$7:X$34,Производительность!$C$7:$C$34,$A9) -> 0
A10: =A9 -> СБШ-250/270КП | D10: КИО | E10: =E9 -> % | G10: =SUMIFS(Производительность!E$115:E$142,Производительность!$C$115:$C$142,$A10) -> 0 | H10: =SUMIFS(Производительность!F$115:F$142,Производительность!$C$115:$C$142,$A10) -> 0 | I10: =SUMIFS(Производительность!G$115:G$142,Производительность!$C$115:$C$142,$A10) -> 0 | J10: =SUMIFS(Производительность!H$115:H$142,Производительность!$C$115:$C$142,$A10) -> 0 | K10: =SUMIFS(Производительность!I$115:I$142,Производительность!$C$115:$C$142,$A10) -> 0 | L10: =SUMIFS(Производительность!J$115:J$142,Производительность!$C$115:$C$142,$A10) -> 0 | M10: =SUMIFS(Производительность!K$115:K$142,Производительность!$C$115:$C$142,$A10) -> 0 | N10: =SUMIFS(Производительность!L$115:L$142,Производительность!$C$115:$C$142,$A10) -> 0 | ... Z10: =SUMIFS(Производительность!X$115:X$142,Производительность!$C$115:$C$142,$A10) -> 0
A11: =A10 -> СБШ-250/270КП | D11: Производительность_бурение | E11: тыс. п. м | G11: =SUMIFS(Производительность!E$196:E$223,Производительность!$C$196:$C$223,$A11) -> 0 | H11: =SUMIFS(Производительность!F$196:F$223,Производительность!$C$196:$C$223,$A11) -> 0 | I11: =SUMIFS(Производительность!G$196:G$223,Производительность!$C$196:$C$223,$A11) -> 0 | J11: =SUMIFS(Производительность!H$196:H$223,Производительность!$C$196:$C$223,$A11) -> 0 | K11: =SUMIFS(Производительность!I$196:I$223,Производительность!$C$196:$C$223,$A11) -> 0 | L11: =SUMIFS(Производительность!J$196:J$223,Производительность!$C$196:$C$223,$A11) -> 0 | M11: =SUMIFS(Производительность!K$196:K$223,Производительность!$C$196:$C$223,$A11) -> 0 | N11: =SUMIFS(Производительность!L$196:L$223,Производительность!$C$196:$C$223,$A11) -> 0 | ... Z11: =SUMIFS(Производительность!X$196:X$223,Производительность!$C$196:$C$223,$A11) -> 0
A12: =A11 -> СБШ-250/270КП | D12: Производительность_взрывание | E12: тыс. м3 | G12: =SUMIFS(Производительность!E$250:E$277,Производительность!$C$250:$C$277,$A12) -> 0 | H12: =SUMIFS(Производительность!F$250:F$277,Производительность!$C$250:$C$277,$A12) -> 0 | I12: =SUMIFS(Производительность!G$250:G$277,Производительность!$C$250:$C$277,$A12) -> 0 | J12: =SUMIFS(Производительность!H$250:H$277,Производительность!$C$250:$C$277,$A12) -> 0 | K12: =SUMIFS(Производительность!I$250:I$277,Производительность!$C$250:$C$277,$A12) -> 0 | L12: =SUMIFS(Производительность!J$250:J$277,Производительность!$C$250:$C$277,$A12) -> 0 | M12: =SUMIFS(Производительность!K$250:K$277,Производительность!$C$250:$C$277,$A12) -> 0 | N12: =SUMIFS(Производительность!L$250:L$277,Производительность!$C$250:$C$277,$A12) -> 0 | ... Z12: =SUMIFS(Производительность!X$250:X$277,Производительность!$C$250:$C$277,$A12) -> 0
A13: =A12 -> СБШ-250/270КП | D13: Производительность кумулятивная | E13: =E12 -> тыс. м3 | G13: =G12 -> 0 | H13: =IF(H12=0,0,G13+H12) -> 0 | I13: =IF(I12=0,0,H13+I12) -> 0 | J13: =IF(J12=0,0,I13+J12) -> 0 | K13: =IF(K12=0,0,J13+K12) -> 0 | L13: =IF(L12=0,0,K13+L12) -> 0 | M13: =IF(M12=0,0,L13+M12) -> 0 | N13: =IF(N12=0,0,M13+N12) -> 0 | O13: =IF(O12=0,0,N13+O12) -> 0 | ... Z13: =IF(Z12=0,0,Y13+Z12) -> 0
A14: =A13 -> СБШ-250/270КП
A15: =A14 -> СБШ-250/270КП | D15: Операционный денежный поток | E15: тыс. руб. | F15: =F49+F50-F48 -> 0 | G15: =G49+G50-G48 -> 0 | H15: =H49+H50-H48 -> 0 | I15: =I49+I50-I48 -> 0 | J15: =J49+J50-J48 -> 0 | K15: =K49+K50-K48 -> 0 | L15: =L49+L50-L48 -> 0 | M15: =M49+M50-M48 -> 0 | ... Z15: =Z49+Z50-Z48 -> 0
A16: =A15 -> СБШ-250/270КП | D16: ТО, ТР, ППР | E16: =E15 -> тыс. руб. | AB16: =SUM(F16:Z16,F21:Z21)/E6 -> #DIV/0!
A17: =A16 -> СБШ-250/270КП | D17: ТО (включая смазочные) | E17: тыс. долл
A18: =A17 -> СБШ-250/270КП | D18: ТР, ППР | E18: тыс. долл
A19: =A18 -> СБШ-250/270КП | D19: трудозатраты | E19: тыс. долл
A20: =A19 -> СБШ-250/270КП | D20: % стоимости справочно | G20: =G16/$F53 -> #DIV/0! | H20: =H16/$F53 -> #DIV/0! | I20: =I16/$F53 -> #DIV/0! | J20: =J16/$F53 -> #DIV/0! | K20: =K16/$F53 -> #DIV/0! | L20: =L16/$F53 -> #DIV/0! | M20: =M16/$F53 -> #DIV/0! | N20: =N16/$F53 -> #DIV/0! | ... Z20: =Z16/$F53 -> #DIV/0! | AA20: =SUM(F16:Z16)/$F53 -> #DIV/0!
A21: =A20 -> СБШ-250/270КП | D21: Смазочные | E21: =E15 -> тыс. руб.
A22: =A21 -> СБШ-250/270КП
A23: =A22 -> СБШ-250/270КП | D23: Долота | E23: =E15 -> тыс. руб. | G23: =G25*G26 -> 0 | H23: =H25*H26 -> 0 | I23: =I25*I26 -> 0 | J23: =J25*J26 -> 0 | K23: =K25*K26 -> 0 | L23: =L25*L26 -> 0 | M23: =M25*M26 -> 0 | N23: =N25*N26 -> 0 | ... Z23: =Z25*Z26 -> 0
A24: =A23 -> СБШ-250/270КП | D24: удельный расход | E24: шт./тыс. п. м | F24: =SUMIFS('ФОТ, МТР, макро'!$B$4:$B$31,'ФОТ, МТР, макро'!$A$4:$A$31,$A24) -> 0 | G24: =F24 -> 0 | H24: =G24 -> 0 | I24: =H24 -> 0 | J24: =I24 -> 0 | K24: =J24 -> 0 | L24: =K24 -> 0 | M24: =L24 -> 0 | N24: =M24 -> 0 | ... Z24: =Y24 -> 0
A25: =A24 -> СБШ-250/270КП | D25: расход за период | E25: шт. | G25: =G11*G24 -> 0 | H25: =H11*H24 -> 0 | I25: =I11*I24 -> 0 | J25: =J11*J24 -> 0 | K25: =K11*K24 -> 0 | L25: =L11*L24 -> 0 | M25: =M11*M24 -> 0 | N25: =N11*N24 -> 0 | ... Z25: =Z11*Z24 -> 0
A26: =A25 -> СБШ-250/270КП | D26: цена | E26: тыс. руб./шт. | F26: =SUMIFS('ФОТ, МТР, макро'!$C$4:$C$31,'ФОТ, МТР, макро'!$A$4:$A$31,$A26) -> 0 | G26: =F26 -> 0 | H26: =G26 -> 0 | I26: =H26 -> 0 | J26: =I26 -> 0 | K26: =J26 -> 0 | L26: =K26 -> 0 | M26: =L26 -> 0 | N26: =M26 -> 0 | ... Z26: =Y26 -> 0
A27: =A26 -> СБШ-250/270КП | D27: Штанги буровые | E27: =E15 -> тыс. руб. | G27: =G29*G30 -> 0 | H27: =H29*H30 -> 0 | I27: =I29*I30 -> 0 | J27: =J29*J30 -> 0 | K27: =K29*K30 -> 0 | L27: =L29*L30 -> 0 | M27: =M29*M30 -> 0 | N27: =N29*N30 -> 0 | ... Z27: =Z29*Z30 -> 0
A28: =A27 -> СБШ-250/270КП | D28: удельный расход | E28: шт./тыс. п. м | F28: =SUMIFS('ФОТ, МТР, макро'!$E$4:$E$31,'ФОТ, МТР, макро'!$A$4:$A$31,$A28) -> 0 | G28: =F28 -> 0 | H28: =G28 -> 0 | I28: =H28 -> 0 | J28: =I28 -> 0 | K28: =J28 -> 0 | L28: =K28 -> 0 | M28: =L28 -> 0 | N28: =M28 -> 0 | ... Z28: =Y28 -> 0
A29: =A28 -> СБШ-250/270КП | D29: расход за период | E29: шт. | G29: =G11*G28 -> 0 | H29: =H11*H28 -> 0 | I29: =I11*I28 -> 0 | J29: =J11*J28 -> 0 | K29: =K11*K28 -> 0 | L29: =L11*L28 -> 0 | M29: =M11*M28 -> 0 | N29: =N11*N28 -> 0 | ... Z29: =Z11*Z28 -> 0
A30: =A29 -> СБШ-250/270КП | D30: цена | E30: тыс. руб./шт. | F30: =SUMIFS('ФОТ, МТР, макро'!$F$4:$F$31,'ФОТ, МТР, макро'!$A$4:$A$31,$A30) -> 0 | G30: =F30 -> 0 | H30: =G30 -> 0 | I30: =H30 -> 0 | J30: =I30 -> 0 | K30: =J30 -> 0 | L30: =K30 -> 0 | M30: =L30 -> 0 | N30: =M30 -> 0 | ... Z30: =Y30 -> 0
A31: =A30 -> СБШ-250/270КП | D31: Расходники | E31: =E15 -> тыс. руб. | G31: =G11*G32 -> 0 | H31: =H11*H32 -> 0 | I31: =I11*I32 -> 0 | J31: =J11*J32 -> 0 | K31: =K11*K32 -> 0 | L31: =L11*L32 -> 0 | M31: =M11*M32 -> 0 | N31: =N11*N32 -> 0 | ... Z31: =Z11*Z32 -> 0
A32: =A31 -> СБШ-250/270КП | D32: удельный расход | E32: руб./п. м | F32: =SUMIFS('ФОТ, МТР, макро'!$H$4:$H$31,'ФОТ, МТР, макро'!$A$4:$A$31,$A32) -> 0 | G32: =F32 -> 0 | H32: =G32 -> 0 | I32: =H32 -> 0 | J32: =I32 -> 0 | K32: =J32 -> 0 | L32: =K32 -> 0 | M32: =L32 -> 0 | N32: =M32 -> 0 | ... Z32: =Y32 -> 0
A33: =A32 -> СБШ-250/270КП | C33: =SUMIFS('ФОТ, МТР, макро'!$N$4:$N$31,'ФОТ, МТР, макро'!$J$4:$J$31,$A33) -> 0 | D33: Топливо/Электроэнергия | E33: =E15 -> тыс. руб. | G33: =IF($C33=1,G34,G38) -> 0 | H33: =IF($C33=1,H34,H38) -> 0 | I33: =IF($C33=1,I34,I38) -> 0 | J33: =IF($C33=1,J34,J38) -> 0 | K33: =IF($C33=1,K34,K38) -> 0 | L33: =IF($C33=1,L34,L38) -> 0 | M33: =IF($C33=1,M34,M38) -> 0 | N33: =IF($C33=1,N34,N38) -> 0 | ... Z33: =IF($C33=1,Z34,Z38) -> 0
A34: =A33 -> СБШ-250/270КП | D34: - расчет (1) | E34: =E33 -> тыс. руб. | G34: =G36*G37 -> 0 | H34: =H36*H37 -> 0 | I34: =I36*I37 -> 0 | J34: =J36*J37 -> 0 | K34: =K36*K37 -> 0 | L34: =L36*L37 -> 0 | M34: =M36*M37 -> 0 | N34: =N36*N37 -> 0 | ... Z34: =Z36*Z37 -> 0
A35: =A34 -> СБШ-250/270КП | D35: удельный расход | E35: =VLOOKUP($A35,'ФОТ, МТР, макро'!$J$4:$N$31,2,FALSE) -> кВт/час | F35: =SUMIFS('ФОТ, МТР, макро'!$L$4:$L$31,'ФОТ, МТР, макро'!$J$4:$J$31,$A35) -> 0 | G35: =F35 -> 0 | H35: =G35 -> 0 | I35: =H35 -> 0 | J35: =I35 -> 0 | K35: =J35 -> 0 | L35: =K35 -> 0 | M35: =L35 -> 0 | N35: =M35 -> 0 | ... Z35: =Y35 -> 0
A36: =A35 -> СБШ-250/270КП | D36: расход за период | E36: =IF(E35="кг/час","т","тыс. кВт*ч") -> тыс. кВт*ч | G36: =G$3*G10*G35/1000 -> 0 | H36: =H$3*H10*H35/1000 -> 0 | I36: =I$3*I10*I35/1000 -> 0 | J36: =J$3*J10*J35/1000 -> 0 | K36: =K$3*K10*K35/1000 -> 0 | L36: =L$3*L10*L35/1000 -> 0 | M36: =M$3*M10*M35/1000 -> 0 | N36: =N$3*N10*N35/1000 -> 0 | ... Z36: =Z$3*Z10*Z35/1000 -> 0
A37: =A36 -> СБШ-250/270КП | D37: цена | E37: =IF(E36="т","тыс. руб./т","руб./кВт*ч") -> руб./кВт*ч | F37: =IF(E36="т",'ФОТ, МТР, макро'!$Q$2,'ФОТ, МТР, макро'!$Q$15) -> 5.1334545 | G37: =F37 -> 5.1334545 | H37: =G37 -> 5.1334545 | I37: =H37 -> 5.1334545 | J37: =I37 -> 5.1334545 | K37: =J37 -> 5.1334545 | L37: =K37 -> 5.1334545 | M37: =L37 -> 5.1334545 | N37: =M37 -> 5.1334545 | ... Z37: =Y37 -> 5.1334545
A38: =A37 -> СБШ-250/270КП | D38: - поставщик (2) | E38: =E34 -> тыс. руб. | G38: =G40*G41 -> 0 | H38: =H40*H41 -> 0 | I38: =I40*I41 -> 0 | J38: =J40*J41 -> 0 | K38: =K40*K41 -> 0 | L38: =L40*L41 -> 0 | M38: =M40*M41 -> 0 | N38: =N40*N41 -> 0 | ... Z38: =Z40*Z41 -> 0
A39: =A38 -> СБШ-250/270КП | D39: удельный расход | E39: =E35 -> кВт/час | F39: =SUMIFS('ФОТ, МТР, макро'!$M$4:$M$31,'ФОТ, МТР, макро'!$J$4:$J$31,$A39) -> 0 | G39: =F39 -> 0 | H39: =G39 -> 0 | I39: =H39 -> 0 | J39: =I39 -> 0 | K39: =J39 -> 0 | L39: =K39 -> 0 | M39: =L39 -> 0 | N39: =M39 -> 0 | ... Z39: =Y39 -> 0
A40: =A39 -> СБШ-250/270КП | D40: расход за период | E40: =E36 -> тыс. кВт*ч | G40: =G$3*G10*G39/1000 -> 0 | H40: =H$3*H10*H39/1000 -> 0 | I40: =I$3*I10*I39/1000 -> 0 | J40: =J$3*J10*J39/1000 -> 0 | K40: =K$3*K10*K39/1000 -> 0 | L40: =L$3*L10*L39/1000 -> 0 | M40: =M$3*M10*M39/1000 -> 0 | N40: =N$3*N10*N39/1000 -> 0 | ... Z40: =Z$3*Z10*Z39/1000 -> 0
A41: =A40 -> СБШ-250/270КП | D41: цена | E41: =E37 -> руб./кВт*ч | G41: =G37 -> 5.1334545 | H41: =H37 -> 5.1334545 | I41: =I37 -> 5.1334545 | J41: =J37 -> 5.1334545 | K41: =K37 -> 5.1334545 | L41: =L37 -> 5.1334545 | M41: =M37 -> 5.1334545 | N41: =N37 -> 5.1334545 | ... Z41: =Z37 -> 5.1334545
A42: =A41 -> СБШ-250/270КП | D42: Затраты на персонал | E42: =E15 -> тыс. руб. | G42: =G43+G44 -> 0 | H42: =H43+H44 -> 0 | I42: =I43+I44 -> 0 | J42: =J43+J44 -> 0 | K42: =K43+K44 -> 0 | L42: =L43+L44 -> 0 | M42: =M43+M44 -> 0 | N42: =N43+N44 -> 0 | ... Z42: =Z43+Z44 -> 0
A43: =A42 -> СБШ-250/270КП | D43: ФОТ с отчислениями | E43: =E42 -> тыс. руб. | F43: =SUMIFS('ФОТ, МТР, макро'!$X$4:$X$31,'ФОТ, МТР, макро'!$W$4:$W$31,$A43) -> 22904.17 | G43: =IF(G11=0,0,$F43) -> 0 | H43: =IF(H11=0,0,$F43) -> 0 | I43: =IF(I11=0,0,$F43) -> 0 | J43: =IF(J11=0,0,$F43) -> 0 | K43: =IF(K11=0,0,$F43) -> 0 | L43: =IF(L11=0,0,$F43) -> 0 | M43: =IF(M11=0,0,$F43) -> 0 | N43: =IF(N11=0,0,$F43) -> 0 | ... Z43: =IF(Z11=0,0,$F43) -> 0
A44: =A43 -> СБШ-250/270КП | D44: прочее | F44: =SUMIFS('ФОТ, МТР, макро'!$Y$4:$Y$31,'ФОТ, МТР, макро'!$W$4:$W$31,$A44) -> 6361.1375 | G44: =IF(G11=0,0,$F44) -> 0 | H44: =IF(H11=0,0,$F44) -> 0 | I44: =IF(I11=0,0,$F44) -> 0 | J44: =IF(J11=0,0,$F44) -> 0 | K44: =IF(K11=0,0,$F44) -> 0 | L44: =IF(L11=0,0,$F44) -> 0 | M44: =IF(M11=0,0,$F44) -> 0 | N44: =IF(N11=0,0,$F44) -> 0 | ... Z44: =IF(Z11=0,0,$F44) -> 0
A45: =A44 -> СБШ-250/270КП | D45: Транспортный налог | E45: =E15 -> тыс. руб. | G45: =IF(G11=0,0,G46*G47/1000) -> 0 | H45: =IF(H11=0,0,H46*H47/1000) -> 0 | I45: =IF(I11=0,0,I46*I47/1000) -> 0 | J45: =IF(J11=0,0,J46*J47/1000) -> 0 | K45: =IF(K11=0,0,K46*K47/1000) -> 0 | L45: =IF(L11=0,0,L46*L47/1000) -> 0 | M45: =IF(M11=0,0,M46*M47/1000) -> 0 | N45: =IF(N11=0,0,N46*N47/1000) -> 0 | ... Z45: =IF(Z11=0,0,Z46*Z47/1000) -> 0
A46: =A45 -> СБШ-250/270КП | D46: мощность двигателя | E46: л.с. | F46: =SUMIFS('ФОТ, МТР, макро'!$AB$4:$AB$31,'ФОТ, МТР, макро'!$W$4:$W$31,$A46) -> 0 | G46: =F46 -> 0 | H46: =G46 -> 0 | I46: =H46 -> 0 | J46: =I46 -> 0 | K46: =J46 -> 0 | L46: =K46 -> 0 | M46: =L46 -> 0 | N46: =M46 -> 0 | ... Z46: =Y46 -> 0
A47: =A46 -> СБШ-250/270КП | D47: налоговая ставка | E47: руб./л.с. | F47: =SUMIFS('ФОТ, МТР, макро'!$AC$4:$AC$31,'ФОТ, МТР, макро'!$W$4:$W$31,$A47) -> 15 | G47: =F47 -> 15 | H47: =G47 -> 15 | I47: =H47 -> 15 | J47: =I47 -> 15 | K47: =J47 -> 15 | L47: =K47 -> 15 | M47: =L47 -> 15 | N47: =M47 -> 15 | ... Z47: =Y47 -> 15
A48: =A47 -> СБШ-250/270КП | C48: =SUMIFS('ФОТ, МТР, макро'!$AF$4:$AF$31,'ФОТ, МТР, макро'!$W$4:$W$31,$A48) -> 19.672131 | D48: Амортизация НУ | E48: =E15 -> тыс. руб. | G48: =IF(G8<=$C49,$F53*$C48%,"ОШИБКА") -> 0 | H48: =IF(H8<=$C49,$F53*$C48%,$F53-SUM($G48:G48)) -> 0 | I48: =IF(I8<=$C49,$F53*$C48%,$F53-SUM($G48:H48)) -> 0 | J48: =IF(J8<=$C49,$F53*$C48%,$F53-SUM($G48:I48)) -> 0 | K48: =IF(K8<=$C49,$F53*$C48%,$F53-SUM($G48:J48)) -> 0 | L48: =IF(L8<=$C49,$F53*$C48%,$F53-SUM($G48:K48)) -> 0 | M48: =IF(M8<=$C49,$F53*$C48%,$F53-SUM($G48:L48)) -> 0 | N48: =IF(N8<=$C49,$F53*$C48%,$F53-SUM($G48:M48)) -> 0 | O48: =IF(O8<=$C49,$F53*$C48%,$F53-SUM($G48:N48)) -> 0 | ... Z48: =IF(Z8<=$C49,$F53*$C48%,$F53-SUM($G48:Y48)) -> 0
A49: =A48 -> СБШ-250/270КП | C49: =SUMIFS('ФОТ, МТР, макро'!$AE$4:$AE$31,'ФОТ, МТР, макро'!$W$4:$W$31,$A49)/12 -> 5.0833333 | D49: Налогооблагаемая база (по налогу на прибыль) | E49: =E15 -> тыс. руб. | G49: =SUM(G16,G21,G23,G27,G31,G33,G42,G45,G48) -> 0 | H49: =SUM(H16,H21,H23,H27,H31,H33,H42,H45,H48) -> 0 | I49: =SUM(I16,I21,I23,I27,I31,I33,I42,I45,I48) -> 0 | J49: =SUM(J16,J21,J23,J27,J31,J33,J42,J45,J48) -> 0 | K49: =SUM(K16,K21,K23,K27,K31,K33,K42,K45,K48) -> 0 | L49: =SUM(L16,L21,L23,L27,L31,L33,L42,L45,L48) -> 0 | M49: =SUM(M16,M21,M23,M27,M31,M33,M42,M45,M48) -> 0 | N49: =SUM(N16,N21,N23,N27,N31,N33,N42,N45,N48) -> 0 | ... Z49: =SUM(Z16,Z21,Z23,Z27,Z31,Z33,Z42,Z45,Z48) -> 0
A50: =A49 -> СБШ-250/270КП | D50: Налог на прибыль | E50: =E15 -> тыс. руб. | G50: =-G49*'ФОТ, МТР, макро'!AJ$12 -> 0 | H50: =-H49*'ФОТ, МТР, макро'!AK$12 -> 0 | I50: =-I49*'ФОТ, МТР, макро'!AL$12 -> 0 | J50: =-J49*'ФОТ, МТР, макро'!AM$12 -> 0 | K50: =-K49*'ФОТ, МТР, макро'!AN$12 -> 0 | L50: =-L49*'ФОТ, МТР, макро'!AO$12 -> 0 | M50: =-M49*'ФОТ, МТР, макро'!AP$12 -> 0 | N50: =-N49*'ФОТ, МТР, макро'!AQ$12 -> 0 | ... Z50: =-Z49*'ФОТ, МТР, макро'!BC$12 -> 0
A51: =A50 -> СБШ-250/270КП
A52: =A51 -> СБШ-250/270КП | D52: Инвестиционный денежный поток | E52: =E15 -> тыс. руб. | F52: =F53 -> 0 | G52: =G53 -> 0 | H52: =H53 -> 0 | I52: =I53 -> 0 | J52: =J53 -> 0 | K52: =K53 -> 0 | L52: =L53 -> 0 | M52: =M53 -> 0 | ... Z52: =Z53 -> 0
A53: =A52 -> СБШ-250/270КП | D53: Буровой станок | E53: =E52 -> тыс. руб. | F53: =SUMIFS('Свод_250-270_эл'!$D$33:$P$33,'Свод_250-270_эл'!$D$19:$P$19,$A53) -> 0
A54: =A53 -> СБШ-250/270КП
A55: =A54 -> СБШ-250/270КП | D55: Денежный поток | E55: =E15 -> тыс. руб. | F55: =F15+F52 -> 0 | G55: =G15+G52 -> 0 | H55: =H15+H52 -> 0 | I55: =I15+I52 -> 0 | J55: =J15+J52 -> 0 | K55: =K15+K52 -> 0 | L55: =L15+L52 -> 0 | M55: =M15+M52 -> 0 | ... Z55: =Z15+Z52 -> 0
A56: =A55 -> СБШ-250/270КП | D56: Дисконтированный операционный денежный поток | E56: =E55 -> тыс. руб. | G56: =G15*'ФОТ, МТР, макро'!AJ$14 -> 0 | H56: =H15*'ФОТ, МТР, макро'!AK$14 -> 0 | I56: =I15*'ФОТ, МТР, макро'!AL$14 -> 0 | J56: =J15*'ФОТ, МТР, макро'!AM$14 -> 0 | K56: =K15*'ФОТ, МТР, макро'!AN$14 -> 0 | L56: =L15*'ФОТ, МТР, макро'!AO$14 -> 0 | M56: =M15*'ФОТ, МТР, макро'!AP$14 -> 0 | N56: =N15*'ФОТ, МТР, макро'!AQ$14 -> 0 | ... Z56: =Z15*'ФОТ, МТР, макро'!BC$14 -> 0
A57: =A56 -> СБШ-250/270КП | D57: =D16 -> ТО, ТР, ППР | E57: =E56 -> тыс. руб. | G57: =G16*'ФОТ, МТР, макро'!AJ$14 -> 0 | H57: =H16*'ФОТ, МТР, макро'!AK$14 -> 0 | I57: =I16*'ФОТ, МТР, макро'!AL$14 -> 0 | J57: =J16*'ФОТ, МТР, макро'!AM$14 -> 0 | K57: =K16*'ФОТ, МТР, макро'!AN$14 -> 0 | L57: =L16*'ФОТ, МТР, макро'!AO$14 -> 0 | M57: =M16*'ФОТ, МТР, макро'!AP$14 -> 0 | N57: =N16*'ФОТ, МТР, макро'!AQ$14 -> 0 | ... Z57: =Z16*'ФОТ, МТР, макро'!BC$14 -> 0
A58: =A57 -> СБШ-250/270КП | D58: =D21 -> Смазочные | E58: =E57 -> тыс. руб. | G58: =G21*'ФОТ, МТР, макро'!AJ$14 -> 0 | H58: =H21*'ФОТ, МТР, макро'!AK$14 -> 0 | I58: =I21*'ФОТ, МТР, макро'!AL$14 -> 0 | J58: =J21*'ФОТ, МТР, макро'!AM$14 -> 0 | K58: =K21*'ФОТ, МТР, макро'!AN$14 -> 0 | L58: =L21*'ФОТ, МТР, макро'!AO$14 -> 0 | M58: =M21*'ФОТ, МТР, макро'!AP$14 -> 0 | N58: =N21*'ФОТ, МТР, макро'!AQ$14 -> 0 | ... Z58: =Z21*'ФОТ, МТР, макро'!BC$14 -> 0
A59: =A58 -> СБШ-250/270КП | D59: =D23 -> Долота | E59: =E58 -> тыс. руб. | G59: =G23*'ФОТ, МТР, макро'!AJ$14 -> 0 | H59: =H23*'ФОТ, МТР, макро'!AK$14 -> 0 | I59: =I23*'ФОТ, МТР, макро'!AL$14 -> 0 | J59: =J23*'ФОТ, МТР, макро'!AM$14 -> 0 | K59: =K23*'ФОТ, МТР, макро'!AN$14 -> 0 | L59: =L23*'ФОТ, МТР, макро'!AO$14 -> 0 | M59: =M23*'ФОТ, МТР, макро'!AP$14 -> 0 | N59: =N23*'ФОТ, МТР, макро'!AQ$14 -> 0 | ... Z59: =Z23*'ФОТ, МТР, макро'!BC$14 -> 0
A60: =A59 -> СБШ-250/270КП | D60: =D27 -> Штанги буровые | E60: =E59 -> тыс. руб. | G60: =G27*'ФОТ, МТР, макро'!AJ$14 -> 0 | H60: =H27*'ФОТ, МТР, макро'!AK$14 -> 0 | I60: =I27*'ФОТ, МТР, макро'!AL$14 -> 0 | J60: =J27*'ФОТ, МТР, макро'!AM$14 -> 0 | K60: =K27*'ФОТ, МТР, макро'!AN$14 -> 0 | L60: =L27*'ФОТ, МТР, макро'!AO$14 -> 0 | M60: =M27*'ФОТ, МТР, макро'!AP$14 -> 0 | N60: =N27*'ФОТ, МТР, макро'!AQ$14 -> 0 | ... Z60: =Z27*'ФОТ, МТР, макро'!BC$14 -> 0
A61: =A60 -> СБШ-250/270КП | D61: =D31 -> Расходники | E61: =E60 -> тыс. руб. | G61: =G31*'ФОТ, МТР, макро'!AJ$14 -> 0 | H61: =H31*'ФОТ, МТР, макро'!AK$14 -> 0 | I61: =I31*'ФОТ, МТР, макро'!AL$14 -> 0 | J61: =J31*'ФОТ, МТР, макро'!AM$14 -> 0 | K61: =K31*'ФОТ, МТР, макро'!AN$14 -> 0 | L61: =L31*'ФОТ, МТР, макро'!AO$14 -> 0 | M61: =M31*'ФОТ, МТР, макро'!AP$14 -> 0 | N61: =N31*'ФОТ, МТР, макро'!AQ$14 -> 0 | ... Z61: =Z31*'ФОТ, МТР, макро'!BC$14 -> 0
A62: =A61 -> СБШ-250/270КП | D62: =D33 -> Топливо/Электроэнергия | E62: =E61 -> тыс. руб. | G62: =G33*'ФОТ, МТР, макро'!AJ$14 -> 0 | H62: =H33*'ФОТ, МТР, макро'!AK$14 -> 0 | I62: =I33*'ФОТ, МТР, макро'!AL$14 -> 0 | J62: =J33*'ФОТ, МТР, макро'!AM$14 -> 0 | K62: =K33*'ФОТ, МТР, макро'!AN$14 -> 0 | L62: =L33*'ФОТ, МТР, макро'!AO$14 -> 0 | M62: =M33*'ФОТ, МТР, макро'!AP$14 -> 0 | N62: =N33*'ФОТ, МТР, макро'!AQ$14 -> 0 | ... Z62: =Z33*'ФОТ, МТР, макро'!BC$14 -> 0
A63: =A62 -> СБШ-250/270КП | D63: =D42 -> Затраты на персонал | E63: =E62 -> тыс. руб. | G63: =G42*'ФОТ, МТР, макро'!AJ$14 -> 0 | H63: =H42*'ФОТ, МТР, макро'!AK$14 -> 0 | I63: =I42*'ФОТ, МТР, макро'!AL$14 -> 0 | J63: =J42*'ФОТ, МТР, макро'!AM$14 -> 0 | K63: =K42*'ФОТ, МТР, макро'!AN$14 -> 0 | L63: =L42*'ФОТ, МТР, макро'!AO$14 -> 0 | M63: =M42*'ФОТ, МТР, макро'!AP$14 -> 0 | N63: =N42*'ФОТ, МТР, макро'!AQ$14 -> 0 | ... Z63: =Z42*'ФОТ, МТР, макро'!BC$14 -> 0
A64: =A63 -> СБШ-250/270КП | D64: =D45 -> Транспортный налог | E64: =E63 -> тыс. руб. | G64: =G45*'ФОТ, МТР, макро'!AJ$14 -> 0 | H64: =H45*'ФОТ, МТР, макро'!AK$14 -> 0 | I64: =I45*'ФОТ, МТР, макро'!AL$14 -> 0 | J64: =J45*'ФОТ, МТР, макро'!AM$14 -> 0 | K64: =K45*'ФОТ, МТР, макро'!AN$14 -> 0 | L64: =L45*'ФОТ, МТР, макро'!AO$14 -> 0 | M64: =M45*'ФОТ, МТР, макро'!AP$14 -> 0 | N64: =N45*'ФОТ, МТР, макро'!AQ$14 -> 0 | ... Z64: =Z45*'ФОТ, МТР, макро'!BC$14 -> 0
A65: =A64 -> СБШ-250/270КП | D65: =D50 -> Налог на прибыль | E65: =E64 -> тыс. руб. | G65: =G50*'ФОТ, МТР, макро'!AJ$14 -> 0 | H65: =H50*'ФОТ, МТР, макро'!AK$14 -> 0 | I65: =I50*'ФОТ, МТР, макро'!AL$14 -> 0 | J65: =J50*'ФОТ, МТР, макро'!AM$14 -> 0 | K65: =K50*'ФОТ, МТР, макро'!AN$14 -> 0 | L65: =L50*'ФОТ, МТР, макро'!AO$14 -> 0 | M65: =M50*'ФОТ, МТР, макро'!AP$14 -> 0 | N65: =N50*'ФОТ, МТР, макро'!AQ$14 -> 0 | ... Z65: =Z50*'ФОТ, МТР, макро'!BC$14 -> 0
A66: =A65 -> СБШ-250/270КП | D66: проверка полноты | G66: =G56-SUM(G57:G65) -> 0 | H66: =H56-SUM(H57:H65) -> 0 | I66: =I56-SUM(I57:I65) -> 0 | J66: =J56-SUM(J57:J65) -> 0 | K66: =K56-SUM(K57:K65) -> 0 | L66: =L56-SUM(L57:L65) -> 0 | M66: =M56-SUM(M57:M65) -> 0 | N66: =N56-SUM(N57:N65) -> 0 | ... Z66: =Z56-SUM(Z57:Z65) -> 0
A67: =A66 -> СБШ-250/270КП | D67: Кумулятивный дисконтированный операционный денежный поток | E67: =E56 -> тыс. руб. | F67: =F56 -> 0 | G67: =F67+G56 -> 0 | H67: =G67+H56 -> 0 | I67: =H67+I56 -> 0 | J67: =I67+J56 -> 0 | K67: =J67+K56 -> 0 | L67: =K67+L56 -> 0 | M67: =L67+M56 -> 0 | N67: =M67+N56 -> 0 | ... Z67: =Y67+Z56 -> 0
A68: =A67 -> СБШ-250/270КП | D68: =D57 -> ТО, ТР, ППР | E68: =E57 -> тыс. руб. | F68: =F57 -> 0 | G68: =F68+G57 -> 0 | H68: =G68+H57 -> 0 | I68: =H68+I57 -> 0 | J68: =I68+J57 -> 0 | K68: =J68+K57 -> 0 | L68: =K68+L57 -> 0 | M68: =L68+M57 -> 0 | N68: =M68+N57 -> 0 | ... Z68: =Y68+Z57 -> 0
A69: =A68 -> СБШ-250/270КП | D69: =D58 -> Смазочные | E69: =E58 -> тыс. руб. | F69: =F58 -> 0 | G69: =F69+G58 -> 0 | H69: =G69+H58 -> 0 | I69: =H69+I58 -> 0 | J69: =I69+J58 -> 0 | K69: =J69+K58 -> 0 | L69: =K69+L58 -> 0 | M69: =L69+M58 -> 0 | N69: =M69+N58 -> 0 | ... Z69: =Y69+Z58 -> 0
A70: =A69 -> СБШ-250/270КП | D70: =D59 -> Долота | E70: =E59 -> тыс. руб. | F70: =F59 -> 0 | G70: =F70+G59 -> 0 | H70: =G70+H59 -> 0 | I70: =H70+I59 -> 0 | J70: =I70+J59 -> 0 | K70: =J70+K59 -> 0 | L70: =K70+L59 -> 0 | M70: =L70+M59 -> 0 | N70: =M70+N59 -> 0 | ... Z70: =Y70+Z59 -> 0
A71: =A70 -> СБШ-250/270КП | D71: =D60 -> Штанги буровые | E71: =E60 -> тыс. руб. | F71: =F60 -> 0 | G71: =F71+G60 -> 0 | H71: =G71+H60 -> 0 | I71: =H71+I60 -> 0 | J71: =I71+J60 -> 0 | K71: =J71+K60 -> 0 | L71: =K71+L60 -> 0 | M71: =L71+M60 -> 0 | N71: =M71+N60 -> 0 | ... Z71: =Y71+Z60 -> 0
A72: =A71 -> СБШ-250/270КП | D72: =D61 -> Расходники | E72: =E61 -> тыс. руб. | F72: =F61 -> 0 | G72: =F72+G61 -> 0 | H72: =G72+H61 -> 0 | I72: =H72+I61 -> 0 | J72: =I72+J61 -> 0 | K72: =J72+K61 -> 0 | L72: =K72+L61 -> 0 | M72: =L72+M61 -> 0 | N72: =M72+N61 -> 0 | ... Z72: =Y72+Z61 -> 0
A73: =A72 -> СБШ-250/270КП | D73: =D62 -> Топливо/Электроэнергия | E73: =E62 -> тыс. руб. | F73: =F62 -> 0 | G73: =F73+G62 -> 0 | H73: =G73+H62 -> 0 | I73: =H73+I62 -> 0 | J73: =I73+J62 -> 0 | K73: =J73+K62 -> 0 | L73: =K73+L62 -> 0 | M73: =L73+M62 -> 0 | N73: =M73+N62 -> 0 | ... Z73: =Y73+Z62 -> 0
A74: =A73 -> СБШ-250/270КП | D74: =D63 -> Затраты на персонал | E74: =E63 -> тыс. руб. | F74: =F63 -> 0 | G74: =F74+G63 -> 0 | H74: =G74+H63 -> 0 | I74: =H74+I63 -> 0 | J74: =I74+J63 -> 0 | K74: =J74+K63 -> 0 | L74: =K74+L63 -> 0 | M74: =L74+M63 -> 0 | N74: =M74+N63 -> 0 | ... Z74: =Y74+Z63 -> 0
A75: =A74 -> СБШ-250/270КП | D75: =D64 -> Транспортный налог | E75: =E64 -> тыс. руб. | F75: =F64 -> 0 | G75: =F75+G64 -> 0 | H75: =G75+H64 -> 0 | I75: =H75+I64 -> 0 | J75: =I75+J64 -> 0 | K75: =J75+K64 -> 0 | L75: =K75+L64 -> 0 | M75: =L75+M64 -> 0 | N75: =M75+N64 -> 0 | ... Z75: =Y75+Z64 -> 0
A76: =A75 -> СБШ-250/270КП | D76: =D65 -> Налог на прибыль | E76: =E65 -> тыс. руб. | F76: =F65 -> 0 | G76: =F76+G65 -> 0 | H76: =G76+H65 -> 0 | I76: =H76+I65 -> 0 | J76: =I76+J65 -> 0 | K76: =J76+K65 -> 0 | L76: =K76+L65 -> 0 | M76: =L76+M65 -> 0 | N76: =M76+N65 -> 0 | ... Z76: =Y76+Z65 -> 0
A77: =A76 -> СБШ-250/270КП
A78: =A77 -> СБШ-250/270КП | D78: Дисконтированный инвестиционный поток | E78: =E55 -> тыс. руб. | F78: =F52*'ФОТ, МТР, макро'!AI$14 -> 0 | G78: =G52*'ФОТ, МТР, макро'!AJ$14 -> 0 | H78: =H52*'ФОТ, МТР, макро'!AK$14 -> 0 | I78: =I52*'ФОТ, МТР, макро'!AL$14 -> 0 | J78: =J52*'ФОТ, МТР, макро'!AM$14 -> 0 | K78: =K52*'ФОТ, МТР, макро'!AN$14 -> 0 | L78: =L52*'ФОТ, МТР, макро'!AO$14 -> 0 | M78: =M52*'ФОТ, МТР, макро'!AP$14 -> 0 | ... Z78: =Z52*'ФОТ, МТР, макро'!BC$14 -> 0
A79: =A78 -> СБШ-250/270КП | D79: =D53 -> Буровой станок | E79: =E78 -> тыс. руб. | F79: =F53*'ФОТ, МТР, макро'!AI$14 -> 0 | G79: =G53*'ФОТ, МТР, макро'!AJ$14 -> 0 | H79: =H53*'ФОТ, МТР, макро'!AK$14 -> 0 | I79: =I53*'ФОТ, МТР, макро'!AL$14 -> 0 | J79: =J53*'ФОТ, МТР, макро'!AM$14 -> 0 | K79: =K53*'ФОТ, МТР, макро'!AN$14 -> 0 | L79: =L53*'ФОТ, МТР, макро'!AO$14 -> 0 | M79: =M53*'ФОТ, МТР, макро'!AP$14 -> 0 | ... Z79: =Z53*'ФОТ, МТР, макро'!BC$14 -> 0
A80: =A79 -> СБШ-250/270КП | D80: проверка полноты | F80: =F78-F79 -> 0 | G80: =G78-G79 -> 0 | H80: =H78-H79 -> 0 | I80: =I78-I79 -> 0 | J80: =J78-J79 -> 0 | K80: =K78-K79 -> 0 | L80: =L78-L79 -> 0 | M80: =M78-M79 -> 0 | ... Z80: =Z78-Z79 -> 0
A81: =A80 -> СБШ-250/270КП | D81: Кумулятивный инвестиционный поток | E81: =E78 -> тыс. руб. | F81: =F78 -> 0 | G81: =F81+G78 -> 0 | H81: =G81+H78 -> 0 | I81: =H81+I78 -> 0 | J81: =I81+J78 -> 0 | K81: =J81+K78 -> 0 | L81: =K81+L78 -> 0 | M81: =L81+M78 -> 0 | N81: =M81+N78 -> 0 | ... Z81: =Y81+Z78 -> 0
A82: =A81 -> СБШ-250/270КП | D82: =D79 -> Буровой станок | E82: =E79 -> тыс. руб. | F82: =F79 -> 0 | G82: =F82+G79 -> 0 | H82: =G82+H79 -> 0 | I82: =H82+I79 -> 0 | J82: =I82+J79 -> 0 | K82: =J82+K79 -> 0 | L82: =K82+L79 -> 0 | M82: =L82+M79 -> 0 | N82: =M82+N79 -> 0 | ... Z82: =Y82+Z79 -> 0
A83: =A82 -> СБШ-250/270КП
A84: =A83 -> СБШ-250/270КП | D84: Дисконтированный денежный поток | E84: =E55 -> тыс. руб. | F84: =F55*'ФОТ, МТР, макро'!AI$14 -> 0 | G84: =G55*'ФОТ, МТР, макро'!AJ$14 -> 0 | H84: =H55*'ФОТ, МТР, макро'!AK$14 -> 0 | I84: =I55*'ФОТ, МТР, макро'!AL$14 -> 0 | J84: =J55*'ФОТ, МТР, макро'!AM$14 -> 0 | K84: =K55*'ФОТ, МТР, макро'!AN$14 -> 0 | L84: =L55*'ФОТ, МТР, макро'!AO$14 -> 0 | M84: =M55*'ФОТ, МТР, макро'!AP$14 -> 0 | ... Z84: =Z55*'ФОТ, МТР, макро'!BC$14 -> 0
A85: =A84 -> СБШ-250/270КП | D85: Кумулятивный дисконтированный денежный поток | E85: =E84 -> тыс. руб. | F85: =F84 -> 0 | G85: =F85+G84 -> 0 | H85: =G85+H84 -> 0 | I85: =H85+I84 -> 0 | J85: =I85+J84 -> 0 | K85: =J85+K84 -> 0 | L85: =K85+L84 -> 0 | M85: =L85+M84 -> 0 | N85: =M85+N84 -> 0 | ... Z85: =Y85+Z84 -> 0
A86: =A85 -> СБШ-250/270КП
A87: =A86 -> СБШ-250/270КП | B87: =D87 -> Аннуитет операционный | C87: =E6 -> 0 | D87: Аннуитет операционный | E87: руб/м3 | G87: =G67/'ФОТ, МТР, макро'!AJ$15/(G13/G8) -> #DIV/0! | H87: =H67/'ФОТ, МТР, макро'!AK$15/(H13/H8) -> #DIV/0! | I87: =I67/'ФОТ, МТР, макро'!AL$15/(I13/I8) -> #DIV/0! | J87: =J67/'ФОТ, МТР, макро'!AM$15/(J13/J8) -> #DIV/0! | K87: =K67/'ФОТ, МТР, макро'!AN$15/(K13/K8) -> #DIV/0! | L87: =L67/'ФОТ, МТР, макро'!AO$15/(L13/L8) -> #DIV/0! | M87: =M67/'ФОТ, МТР, макро'!AP$15/(M13/M8) -> #DIV/0! | N87: =N67/'ФОТ, МТР, макро'!AQ$15/(N13/N8) -> #DIV/0! | ... Z87: =Z67/'ФОТ, МТР, макро'!BC$15/(Z13/Z8) -> #DIV/0! | AC87: {=INDEX(G87:Z87,1,$C87)} -> #DIV/0! | AD87: #DIV/0! | AE87: #DIV/0! | AF87: #DIV/0! | AG87: #DIV/0! | AH87: #DIV/0! | AI87: #DIV/0! | AJ87: #DIV/0! | AK87: #DIV/0! | AL87: #DIV/0! | AM87: #DIV/0! | AN87: #DIV/0! | AO87: #DIV/0! | AP87: #DIV/0! | AQ87: #DIV/0! | AR87: #DIV/0! | AS87: #DIV/0! | AT87: #DIV/0! | AU87: #DIV/0! | AV87: #DIV/0!
A88: =A87 -> СБШ-250/270КП | B88: =D88 -> ТО, ТР, ППР | C88: =C87 -> 0 | D88: =D68 -> ТО, ТР, ППР | E88: =E87 -> руб/м3 | G88: =G68/'ФОТ, МТР, макро'!AJ$15/(G13/G8) -> #DIV/0! | H88: =H68/'ФОТ, МТР, макро'!AK$15/(H13/H8) -> #DIV/0! | I88: =I68/'ФОТ, МТР, макро'!AL$15/(I13/I8) -> #DIV/0! | J88: =J68/'ФОТ, МТР, макро'!AM$15/(J13/J8) -> #DIV/0! | K88: =K68/'ФОТ, МТР, макро'!AN$15/(K13/K8) -> #DIV/0! | L88: =L68/'ФОТ, МТР, макро'!AO$15/(L13/L8) -> #DIV/0! | M88: =M68/'ФОТ, МТР, макро'!AP$15/(M13/M8) -> #DIV/0! | N88: =N68/'ФОТ, МТР, макро'!AQ$15/(N13/N8) -> #DIV/0! | ... Z88: =Z68/'ФОТ, МТР, макро'!BC$15/(Z13/Z8) -> #DIV/0! | AC88: {=INDEX(G88:Z88,1,$C88)} -> #DIV/0! | AD88: #DIV/0! | AE88: #DIV/0! | AF88: #DIV/0! | AG88: #DIV/0! | AH88: #DIV/0! | AI88: #DIV/0! | AJ88: #DIV/0! | AK88: #DIV/0! | AL88: #DIV/0! | AM88: #DIV/0! | AN88: #DIV/0! | AO88: #DIV/0! | AP88: #DIV/0! | AQ88: #DIV/0! | AR88: #DIV/0! | AS88: #DIV/0! | AT88: #DIV/0! | AU88: #DIV/0! | AV88: #DIV/0!
A89: =A88 -> СБШ-250/270КП | B89: =D89 -> Смазочные | C89: =C88 -> 0 | D89: =D69 -> Смазочные | E89: =E88 -> руб/м3 | G89: =G69/'ФОТ, МТР, макро'!AJ$15/(G13/G8) -> #DIV/0! | H89: =H69/'ФОТ, МТР, макро'!AK$15/(H13/H8) -> #DIV/0! | I89: =I69/'ФОТ, МТР, макро'!AL$15/(I13/I8) -> #DIV/0! | J89: =J69/'ФОТ, МТР, макро'!AM$15/(J13/J8) -> #DIV/0! | K89: =K69/'ФОТ, МТР, макро'!AN$15/(K13/K8) -> #DIV/0! | L89: =L69/'ФОТ, МТР, макро'!AO$15/(L13/L8) -> #DIV/0! | M89: =M69/'ФОТ, МТР, макро'!AP$15/(M13/M8) -> #DIV/0! | N89: =N69/'ФОТ, МТР, макро'!AQ$15/(N13/N8) -> #DIV/0! | ... Z89: =Z69/'ФОТ, МТР, макро'!BC$15/(Z13/Z8) -> #DIV/0! | AC89: {=INDEX(G89:Z89,1,$C89)} -> #DIV/0! | AD89: #DIV/0! | AE89: #DIV/0! | AF89: #DIV/0! | AG89: #DIV/0! | AH89: #DIV/0! | AI89: #DIV/0! | AJ89: #DIV/0! | AK89: #DIV/0! | AL89: #DIV/0! | AM89: #DIV/0! | AN89: #DIV/0! | AO89: #DIV/0! | AP89: #DIV/0! | AQ89: #DIV/0! | AR89: #DIV/0! | AS89: #DIV/0! | AT89: #DIV/0! | AU89: #DIV/0! | AV89: #DIV/0!
A90: =A89 -> СБШ-250/270КП | B90: =D90 -> Долота | C90: =C89 -> 0 | D90: =D70 -> Долота | E90: =E89 -> руб/м3 | G90: =G70/'ФОТ, МТР, макро'!AJ$15/(G13/G8) -> #DIV/0! | H90: =H70/'ФОТ, МТР, макро'!AK$15/(H13/H8) -> #DIV/0! | I90: =I70/'ФОТ, МТР, макро'!AL$15/(I13/I8) -> #DIV/0! | J90: =J70/'ФОТ, МТР, макро'!AM$15/(J13/J8) -> #DIV/0! | K90: =K70/'ФОТ, МТР, макро'!AN$15/(K13/K8) -> #DIV/0! | L90: =L70/'ФОТ, МТР, макро'!AO$15/(L13/L8) -> #DIV/0! | M90: =M70/'ФОТ, МТР, макро'!AP$15/(M13/M8) -> #DIV/0! | N90: =N70/'ФОТ, МТР, макро'!AQ$15/(N13/N8) -> #DIV/0! | ... Z90: =Z70/'ФОТ, МТР, макро'!BC$15/(Z13/Z8) -> #DIV/0! | AC90: {=INDEX(G90:Z90,1,$C90)} -> #DIV/0! | AD90: #DIV/0! | AE90: #DIV/0! | AF90: #DIV/0! | AG90: #DIV/0! | AH90: #DIV/0! | AI90: #DIV/0! | AJ90: #DIV/0! | AK90: #DIV/0! | AL90: #DIV/0! | AM90: #DIV/0! | AN90: #DIV/0! | AO90: #DIV/0! | AP90: #DIV/0! | AQ90: #DIV/0! | AR90: #DIV/0! | AS90: #DIV/0! | AT90: #DIV/0! | AU90: #DIV/0! | AV90: #DIV/0!
A91: =A90 -> СБШ-250/270КП | B91: =D91 -> Штанги буровые | C91: =C90 -> 0 | D91: =D71 -> Штанги буровые | E91: =E90 -> руб/м3 | G91: =G71/'ФОТ, МТР, макро'!AJ$15/(G13/G8) -> #DIV/0! | H91: =H71/'ФОТ, МТР, макро'!AK$15/(H13/H8) -> #DIV/0! | I91: =I71/'ФОТ, МТР, макро'!AL$15/(I13/I8) -> #DIV/0! | J91: =J71/'ФОТ, МТР, макро'!AM$15/(J13/J8) -> #DIV/0! | K91: =K71/'ФОТ, МТР, макро'!AN$15/(K13/K8) -> #DIV/0! | L91: =L71/'ФОТ, МТР, макро'!AO$15/(L13/L8) -> #DIV/0! | M91: =M71/'ФОТ, МТР, макро'!AP$15/(M13/M8) -> #DIV/0! | N91: =N71/'ФОТ, МТР, макро'!AQ$15/(N13/N8) -> #DIV/0! | ... Z91: =Z71/'ФОТ, МТР, макро'!BC$15/(Z13/Z8) -> #DIV/0! | AC91: {=INDEX(G91:Z91,1,$C91)} -> #DIV/0! | AD91: #DIV/0! | AE91: #DIV/0! | AF91: #DIV/0! | AG91: #DIV/0! | AH91: #DIV/0! | AI91: #DIV/0! | AJ91: #DIV/0! | AK91: #DIV/0! | AL91: #DIV/0! | AM91: #DIV/0! | AN91: #DIV/0! | AO91: #DIV/0! | AP91: #DIV/0! | AQ91: #DIV/0! | AR91: #DIV/0! | AS91: #DIV/0! | AT91: #DIV/0! | AU91: #DIV/0! | AV91: #DIV/0!
A92: =A91 -> СБШ-250/270КП | B92: =D92 -> Расходники | C92: =C91 -> 0 | D92: =D72 -> Расходники | E92: =E91 -> руб/м3 | G92: =G72/'ФОТ, МТР, макро'!AJ$15/(G13/G8) -> #DIV/0! | H92: =H72/'ФОТ, МТР, макро'!AK$15/(H13/H8) -> #DIV/0! | I92: =I72/'ФОТ, МТР, макро'!AL$15/(I13/I8) -> #DIV/0! | J92: =J72/'ФОТ, МТР, макро'!AM$15/(J13/J8) -> #DIV/0! | K92: =K72/'ФОТ, МТР, макро'!AN$15/(K13/K8) -> #DIV/0! | L92: =L72/'ФОТ, МТР, макро'!AO$15/(L13/L8) -> #DIV/0! | M92: =M72/'ФОТ, МТР, макро'!AP$15/(M13/M8) -> #DIV/0! | N92: =N72/'ФОТ, МТР, макро'!AQ$15/(N13/N8) -> #DIV/0! | ... Z92: =Z72/'ФОТ, МТР, макро'!BC$15/(Z13/Z8) -> #DIV/0! | AC92: {=INDEX(G92:Z92,1,$C92)} -> #DIV/0! | AD92: #DIV/0! | AE92: #DIV/0! | AF92: #DIV/0! | AG92: #DIV/0! | AH92: #DIV/0! | AI92: #DIV/0! | AJ92: #DIV/0! | AK92: #DIV/0! | AL92: #DIV/0! | AM92: #DIV/0! | AN92: #DIV/0! | AO92: #DIV/0! | AP92: #DIV/0! | AQ92: #DIV/0! | AR92: #DIV/0! | AS92: #DIV/0! | AT92: #DIV/0! | AU92: #DIV/0! | AV92: #DIV/0!
A93: =A92 -> СБШ-250/270КП | B93: =D93 -> Топливо/Электроэнергия | C93: =C92 -> 0 | D93: =D73 -> Топливо/Электроэнергия | E93: =E92 -> руб/м3 | G93: =G73/'ФОТ, МТР, макро'!AJ$15/(G13/G8) -> #DIV/0! | H93: =H73/'ФОТ, МТР, макро'!AK$15/(H13/H8) -> #DIV/0! | I93: =I73/'ФОТ, МТР, макро'!AL$15/(I13/I8) -> #DIV/0! | J93: =J73/'ФОТ, МТР, макро'!AM$15/(J13/J8) -> #DIV/0! | K93: =K73/'ФОТ, МТР, макро'!AN$15/(K13/K8) -> #DIV/0! | L93: =L73/'ФОТ, МТР, макро'!AO$15/(L13/L8) -> #DIV/0! | M93: =M73/'ФОТ, МТР, макро'!AP$15/(M13/M8) -> #DIV/0! | N93: =N73/'ФОТ, МТР, макро'!AQ$15/(N13/N8) -> #DIV/0! | ... Z93: =Z73/'ФОТ, МТР, макро'!BC$15/(Z13/Z8) -> #DIV/0! | AC93: {=INDEX(G93:Z93,1,$C93)} -> #DIV/0! | AD93: #DIV/0! | AE93: #DIV/0! | AF93: #DIV/0! | AG93: #DIV/0! | AH93: #DIV/0! | AI93: #DIV/0! | AJ93: #DIV/0! | AK93: #DIV/0! | AL93: #DIV/0! | AM93: #DIV/0! | AN93: #DIV/0! | AO93: #DIV/0! | AP93: #DIV/0! | AQ93: #DIV/0! | AR93: #DIV/0! | AS93: #DIV/0! | AT93: #DIV/0! | AU93: #DIV/0! | AV93: #DIV/0!
A94: =A93 -> СБШ-250/270КП | B94: =D94 -> Затраты на персонал | C94: =C93 -> 0 | D94: =D74 -> Затраты на персонал | E94: =E93 -> руб/м3 | G94: =G74/'ФОТ, МТР, макро'!AJ$15/(G13/G8) -> #DIV/0! | H94: =H74/'ФОТ, МТР, макро'!AK$15/(H13/H8) -> #DIV/0! | I94: =I74/'ФОТ, МТР, макро'!AL$15/(I13/I8) -> #DIV/0! | J94: =J74/'ФОТ, МТР, макро'!AM$15/(J13/J8) -> #DIV/0! | K94: =K74/'ФОТ, МТР, макро'!AN$15/(K13/K8) -> #DIV/0! | L94: =L74/'ФОТ, МТР, макро'!AO$15/(L13/L8) -> #DIV/0! | M94: =M74/'ФОТ, МТР, макро'!AP$15/(M13/M8) -> #DIV/0! | N94: =N74/'ФОТ, МТР, макро'!AQ$15/(N13/N8) -> #DIV/0! | ... Z94: =Z74/'ФОТ, МТР, макро'!BC$15/(Z13/Z8) -> #DIV/0! | AC94: {=INDEX(G94:Z94,1,$C94)} -> #DIV/0! | AD94: #DIV/0! | AE94: #DIV/0! | AF94: #DIV/0! | AG94: #DIV/0! | AH94: #DIV/0! | AI94: #DIV/0! | AJ94: #DIV/0! | AK94: #DIV/0! | AL94: #DIV/0! | AM94: #DIV/0! | AN94: #DIV/0! | AO94: #DIV/0! | AP94: #DIV/0! | AQ94: #DIV/0! | AR94: #DIV/0! | AS94: #DIV/0! | AT94: #DIV/0! | AU94: #DIV/0! | AV94: #DIV/0!
A95: =A94 -> СБШ-250/270КП | B95: =D95 -> Транспортный налог | C95: =C94 -> 0 | D95: =D75 -> Транспортный налог | E95: =E94 -> руб/м3 | G95: =G75/'ФОТ, МТР, макро'!AJ$15/(G13/G8) -> #DIV/0! | H95: =H75/'ФОТ, МТР, макро'!AK$15/(H13/H8) -> #DIV/0! | I95: =I75/'ФОТ, МТР, макро'!AL$15/(I13/I8) -> #DIV/0! | J95: =J75/'ФОТ, МТР, макро'!AM$15/(J13/J8) -> #DIV/0! | K95: =K75/'ФОТ, МТР, макро'!AN$15/(K13/K8) -> #DIV/0! | L95: =L75/'ФОТ, МТР, макро'!AO$15/(L13/L8) -> #DIV/0! | M95: =M75/'ФОТ, МТР, макро'!AP$15/(M13/M8) -> #DIV/0! | N95: =N75/'ФОТ, МТР, макро'!AQ$15/(N13/N8) -> #DIV/0! | ... Z95: =Z75/'ФОТ, МТР, макро'!BC$15/(Z13/Z8) -> #DIV/0! | AC95: {=INDEX(G95:Z95,1,$C95)} -> #DIV/0! | AD95: #DIV/0! | AE95: #DIV/0! | AF95: #DIV/0! | AG95: #DIV/0! | AH95: #DIV/0! | AI95: #DIV/0! | AJ95: #DIV/0! | AK95: #DIV/0! | AL95: #DIV/0! | AM95: #DIV/0! | AN95: #DIV/0! | AO95: #DIV/0! | AP95: #DIV/0! | AQ95: #DIV/0! | AR95: #DIV/0! | AS95: #DIV/0! | AT95: #DIV/0! | AU95: #DIV/0! | AV95: #DIV/0!
A96: =A95 -> СБШ-250/270КП | B96: =D96 -> Налог на прибыль | C96: =C95 -> 0 | D96: =D76 -> Налог на прибыль | E96: =E95 -> руб/м3 | G96: =G76/'ФОТ, МТР, макро'!AJ$15/(G13/G8) -> #DIV/0! | H96: =H76/'ФОТ, МТР, макро'!AK$15/(H13/H8) -> #DIV/0! | I96: =I76/'ФОТ, МТР, макро'!AL$15/(I13/I8) -> #DIV/0! | J96: =J76/'ФОТ, МТР, макро'!AM$15/(J13/J8) -> #DIV/0! | K96: =K76/'ФОТ, МТР, макро'!AN$15/(K13/K8) -> #DIV/0! | L96: =L76/'ФОТ, МТР, макро'!AO$15/(L13/L8) -> #DIV/0! | M96: =M76/'ФОТ, МТР, макро'!AP$15/(M13/M8) -> #DIV/0! | N96: =N76/'ФОТ, МТР, макро'!AQ$15/(N13/N8) -> #DIV/0! | ... Z96: =Z76/'ФОТ, МТР, макро'!BC$15/(Z13/Z8) -> #DIV/0! | AC96: {=INDEX(G96:Z96,1,$C96)} -> #DIV/0! | AD96: #DIV/0! | AE96: #DIV/0! | AF96: #DIV/0! | AG96: #DIV/0! | AH96: #DIV/0! | AI96: #DIV/0! | AJ96: #DIV/0! | AK96: #DIV/0! | AL96: #DIV/0! | AM96: #DIV/0! | AN96: #DIV/0! | AO96: #DIV/0! | AP96: #DIV/0! | AQ96: #DIV/0! | AR96: #DIV/0! | AS96: #DIV/0! | AT96: #DIV/0! | AU96: #DIV/0! | AV96: #DIV/0!
A97: =A96 -> СБШ-250/270КП | B97: =D97 -> Аннуитет инвестиционный | C97: =C96 -> 0 | D97: Аннуитет инвестиционный | E97: =E87 -> руб/м3 | G97: =G81/'ФОТ, МТР, макро'!AJ$15/(G13/G8) -> #DIV/0! | H97: =H81/'ФОТ, МТР, макро'!AK$15/(H13/H8) -> #DIV/0! | I97: =I81/'ФОТ, МТР, макро'!AL$15/(I13/I8) -> #DIV/0! | J97: =J81/'ФОТ, МТР, макро'!AM$15/(J13/J8) -> #DIV/0! | K97: =K81/'ФОТ, МТР, макро'!AN$15/(K13/K8) -> #DIV/0! | L97: =L81/'ФОТ, МТР, макро'!AO$15/(L13/L8) -> #DIV/0! | M97: =M81/'ФОТ, МТР, макро'!AP$15/(M13/M8) -> #DIV/0! | N97: =N81/'ФОТ, МТР, макро'!AQ$15/(N13/N8) -> #DIV/0! | ... Z97: =Z81/'ФОТ, МТР, макро'!BC$15/(Z13/Z8) -> #DIV/0! | AC97: {=INDEX(G97:Z97,1,$C97)} -> #DIV/0! | AD97: #DIV/0! | AE97: #DIV/0! | AF97: #DIV/0! | AG97: #DIV/0! | AH97: #DIV/0! | AI97: #DIV/0! | AJ97: #DIV/0! | AK97: #DIV/0! | AL97: #DIV/0! | AM97: #DIV/0! | AN97: #DIV/0! | AO97: #DIV/0! | AP97: #DIV/0! | AQ97: #DIV/0! | AR97: #DIV/0! | AS97: #DIV/0! | AT97: #DIV/0! | AU97: #DIV/0! | AV97: #DIV/0!
A98: =A97 -> СБШ-250/270КП | B98: =D98 -> Буровой станок | C98: =C97 -> 0 | D98: =D82 -> Буровой станок | E98: =E97 -> руб/м3 | G98: =G82/'ФОТ, МТР, макро'!AJ$15/(G13/G8) -> #DIV/0! | H98: =H82/'ФОТ, МТР, макро'!AK$15/(H13/H8) -> #DIV/0! | I98: =I82/'ФОТ, МТР, макро'!AL$15/(I13/I8) -> #DIV/0! | J98: =J82/'ФОТ, МТР, макро'!AM$15/(J13/J8) -> #DIV/0! | K98: =K82/'ФОТ, МТР, макро'!AN$15/(K13/K8) -> #DIV/0! | L98: =L82/'ФОТ, МТР, макро'!AO$15/(L13/L8) -> #DIV/0! | M98: =M82/'ФОТ, МТР, макро'!AP$15/(M13/M8) -> #DIV/0! | N98: =N82/'ФОТ, МТР, макро'!AQ$15/(N13/N8) -> #DIV/0! | ... Z98: =Z82/'ФОТ, МТР, макро'!BC$15/(Z13/Z8) -> #DIV/0! | AC98: {=INDEX(G98:Z98,1,$C98)} -> #DIV/0! | AD98: #DIV/0! | AE98: #DIV/0! | AF98: #DIV/0! | AG98: #DIV/0! | AH98: #DIV/0! | AI98: #DIV/0! | AJ98: #DIV/0! | AK98: #DIV/0! | AL98: #DIV/0! | AM98: #DIV/0! | AN98: #DIV/0! | AO98: #DIV/0! | AP98: #DIV/0! | AQ98: #DIV/0! | AR98: #DIV/0! | AS98: #DIV/0! | AT98: #DIV/0! | AU98: #DIV/0! | AV98: #DIV/0!
A99: =A98 -> СБШ-250/270КП | B99: =D99 -> Аннуитет общий | C99: =C98 -> 0 | D99: Аннуитет общий | E99: =E87 -> руб/м3 | G99: =G85/'ФОТ, МТР, макро'!AJ$15/(G13/G8) -> #DIV/0! | H99: =H85/'ФОТ, МТР, макро'!AK$15/(H13/H8) -> #DIV/0! | I99: =I85/'ФОТ, МТР, макро'!AL$15/(I13/I8) -> #DIV/0! | J99: =J85/'ФОТ, МТР, макро'!AM$15/(J13/J8) -> #DIV/0! | K99: =K85/'ФОТ, МТР, макро'!AN$15/(K13/K8) -> #DIV/0! | L99: =L85/'ФОТ, МТР, макро'!AO$15/(L13/L8) -> #DIV/0! | M99: =M85/'ФОТ, МТР, макро'!AP$15/(M13/M8) -> #DIV/0! | N99: =N85/'ФОТ, МТР, макро'!AQ$15/(N13/N8) -> #DIV/0! | ... Z99: =Z85/'ФОТ, МТР, макро'!BC$15/(Z13/Z8) -> #DIV/0! | AC99: {=INDEX(G99:Z99,1,$C99)} -> #DIV/0! | AD99: #DIV/0! | AE99: #DIV/0! | AF99: #DIV/0! | AG99: #DIV/0! | AH99: #DIV/0! | AI99: #DIV/0! | AJ99: #DIV/0! | AK99: #DIV/0! | AL99: #DIV/0! | AM99: #DIV/0! | AN99: #DIV/0! | AO99: #DIV/0! | AP99: #DIV/0! | AQ99: #DIV/0! | AR99: #DIV/0! | AS99: #DIV/0! | AT99: #DIV/0! | AU99: #DIV/0! | AV99: #DIV/0!
A100: =A99 -> СБШ-250/270КП
...

Sheet Свод_215_диз
C2: Технико-экономическая оценка стоимости владения
C4: Ранжирование общих аннуитетов - по возрастанию | G4: Ранжирование по стоимости самосвала - по возрастанию
C5: № | D5: Марка станка | E5: Аннуитет, руб/ткм | G5: =C5 -> № | H5: =D5 -> Марка станка | K5: Цена за ед., тыс. руб.
C6: 1 | D6: =IFERROR(HLOOKUP(E6,$F$58:$O$60,3,FALSE),"-") -> - | E6: =IFERROR(SMALL($F$58:$O$58,C6),"-") -> - | G6: =C6 -> 1 | H6: =IFERROR(HLOOKUP(K6,$F$59:$O$60,2,FALSE),"-") -> - | K6: =IFERROR(SMALL($F$59:$O$59,C6),"-") -> -
C7: =C6+1 -> 2 | D7: =IFERROR(HLOOKUP(E7,$F$58:$O$60,3,FALSE),"-") -> - | E7: =IFERROR(SMALL($F$58:$O$58,C7),"-") -> - | G7: =C7 -> 2 | H7: =IFERROR(HLOOKUP(K7,$F$59:$O$60,2,FALSE),"-") -> - | K7: =IFERROR(SMALL($F$59:$O$59,C7),"-") -> -
C8: =C7+1 -> 3 | D8: =IFERROR(HLOOKUP(E8,$F$58:$O$60,3,FALSE),"-") -> - | E8: =IFERROR(SMALL($F$58:$O$58,C8),"-") -> - | G8: =C8 -> 3 | H8: =IFERROR(HLOOKUP(K8,$F$59:$O$60,2,FALSE),"-") -> - | K8: =IFERROR(SMALL($F$59:$O$59,C8),"-") -> -
C9: =C8+1 -> 4 | D9: =IFERROR(HLOOKUP(E9,$F$58:$O$60,3,FALSE),"-") -> - | E9: =IFERROR(SMALL($F$58:$O$58,C9),"-") -> - | G9: =C9 -> 4 | H9: =IFERROR(HLOOKUP(K9,$F$59:$O$60,2,FALSE),"-") -> - | K9: =IFERROR(SMALL($F$59:$O$59,C9),"-") -> -
C10: =C9+1 -> 5 | D10: =IFERROR(HLOOKUP(E10,$F$58:$O$60,3,FALSE),"-") -> - | E10: =IFERROR(SMALL($F$58:$O$58,C10),"-") -> - | G10: =C10 -> 5 | H10: =IFERROR(HLOOKUP(K10,$F$59:$O$60,2,FALSE),"-") -> - | K10: =IFERROR(SMALL($F$59:$O$59,C10),"-") -> -
C11: =C10+1 -> 6 | D11: =IFERROR(HLOOKUP(E11,$F$58:$O$60,3,FALSE),"-") -> - | E11: =IFERROR(SMALL($F$58:$O$58,C11),"-") -> - | G11: =C11 -> 6 | H11: =IFERROR(HLOOKUP(K11,$F$59:$O$60,2,FALSE),"-") -> - | K11: =IFERROR(SMALL($F$59:$O$59,C11),"-") -> -
C12: =C11+1 -> 7 | D12: =IFERROR(HLOOKUP(E12,$F$58:$O$60,3,FALSE),"-") -> - | E12: =IFERROR(SMALL($F$58:$O$58,C12),"-") -> - | G12: =C12 -> 7 | H12: =IFERROR(HLOOKUP(K12,$F$59:$O$60,2,FALSE),"-") -> - | K12: =IFERROR(SMALL($F$59:$O$59,C12),"-") -> -
C13: =C12+1 -> 8 | D13: =IFERROR(HLOOKUP(E13,$F$58:$O$60,3,FALSE),"-") -> - | E13: =IFERROR(SMALL($F$58:$O$58,C13),"-") -> - | G13: =C13 -> 8 | H13: =IFERROR(HLOOKUP(K13,$F$59:$O$60,2,FALSE),"-") -> - | K13: =IFERROR(SMALL($F$59:$O$59,C13),"-") -> -
C14: =C13+1 -> 9 | D14: =IFERROR(HLOOKUP(E14,$F$58:$O$60,3,FALSE),"-") -> - | E14: =IFERROR(SMALL($F$58:$O$58,C14),"-") -> - | G14: =C14 -> 9 | H14: =IFERROR(HLOOKUP(K14,$F$59:$O$60,2,FALSE),"-") -> - | K14: =IFERROR(SMALL($F$59:$O$59,C14),"-") -> -
C15: =C14+1 -> 10 | D15: =IFERROR(HLOOKUP(E15,$F$58:$O$60,3,FALSE),"-") -> - | E15: =IFERROR(SMALL($F$58:$O$58,C15),"-") -> - | G15: =C15 -> 10 | H15: =IFERROR(HLOOKUP(K15,$F$59:$O$60,2,FALSE),"-") -> - | K15: =IFERROR(SMALL($F$59:$O$59,C15),"-") -> -
F18: =VLOOKUP(F19,Производительность!$C$7:$AB$33,26,FALSE) -> Копейский машзавод | G18: =VLOOKUP(G19,Производительность!$C$7:$AB$33,26,FALSE) -> нипигормаш | H18: =VLOOKUP(H19,Производительность!$C$7:$AB$33,26,FALSE) -> #N/A | I18: =VLOOKUP(I19,Производительность!$C$7:$AB$33,26,FALSE) -> #N/A | J18: =VLOOKUP(J19,Производительность!$C$7:$AB$33,26,FALSE) -> #N/A | K18: =VLOOKUP(K19,Производительность!$C$7:$AB$33,26,FALSE) -> #N/A | L18: =VLOOKUP(L19,Производительность!$C$7:$AB$33,26,FALSE) -> #N/A | M18: =VLOOKUP(M19,Производительность!$C$7:$AB$33,26,FALSE) -> #N/A | ... O18: =VLOOKUP(O19,Производительность!$C$7:$AB$33,26,FALSE) -> #N/A
C19: № | D19: Показатель | E19: Ед. изм. | F19: =Производительность!C23 -> БС-215 | G19: =Производительность!C29 -> СБ-55Д-01 | P19: Комментарий
C20: 1 | D20: Диаметр бурения (в расчете) | E20: мм | F20: =SUMIFS('W час'!$E$19:$AF$19,'W час'!$E$4:$AF$4,F$19)*1000 -> 215 | G20: =SUMIFS('W час'!$E$19:$AF$19,'W час'!$E$4:$AF$4,G$19)*1000 -> 215 | H20: =SUMIFS('W час'!$E$19:$AF$19,'W час'!$E$4:$AF$4,H$19)*1000 -> 0 | I20: =SUMIFS('W час'!$E$19:$AF$19,'W час'!$E$4:$AF$4,I$19)*1000 -> 0 | J20: =SUMIFS('W час'!$E$19:$AF$19,'W час'!$E$4:$AF$4,J$19)*1000 -> 0 | K20: =SUMIFS('W час'!$E$19:$AF$19,'W час'!$E$4:$AF$4,K$19)*1000 -> 0 | L20: =SUMIFS('W час'!$E$19:$AF$19,'W час'!$E$4:$AF$4,L$19)*1000 -> 0 | M20: =SUMIFS('W час'!$E$19:$AF$19,'W час'!$E$4:$AF$4,M$19)*1000 -> 0 | ... O20: =SUMIFS('W час'!$E$19:$AF$19,'W час'!$E$4:$AF$4,O$19)*1000 -> 0
C21: =MAX(C$20:C20)+1 -> 2 | D21: Вес станка | E21: т | F21: =HLOOKUP(F$19,'W час'!$E$4:$AF$5,2,FALSE) -> 50 | G21: =HLOOKUP(G$19,'W час'!$E$4:$AF$5,2,FALSE) -> 57.3 | H21: =HLOOKUP(H$19,'W час'!$E$4:$AF$5,2,FALSE) -> #N/A | I21: =HLOOKUP(I$19,'W час'!$E$4:$AF$5,2,FALSE) -> #N/A | J21: =HLOOKUP(J$19,'W час'!$E$4:$AF$5,2,FALSE) -> #N/A | K21: =HLOOKUP(K$19,'W час'!$E$4:$AF$5,2,FALSE) -> #N/A | L21: =HLOOKUP(L$19,'W час'!$E$4:$AF$5,2,FALSE) -> #N/A | M21: =HLOOKUP(M$19,'W час'!$E$4:$AF$5,2,FALSE) -> #N/A | ... O21: =HLOOKUP(O$19,'W час'!$E$4:$AF$5,2,FALSE) -> #N/A
C22: =MAX(C$20:C21)+1 -> 3 | D22: Мощность привода вращателя (в расчете) | E22: кВт | F22: =SUMIFS('W час'!$E$22:$AF$22,'W час'!$E$4:$AF$4,F$19) -> 134 | G22: =SUMIFS('W час'!$E$22:$AF$22,'W час'!$E$4:$AF$4,G$19) -> 167 | H22: =SUMIFS('W час'!$E$22:$AF$22,'W час'!$E$4:$AF$4,H$19) -> 0 | I22: =SUMIFS('W час'!$E$22:$AF$22,'W час'!$E$4:$AF$4,I$19) -> 0 | J22: =SUMIFS('W час'!$E$22:$AF$22,'W час'!$E$4:$AF$4,J$19) -> 0 | K22: =SUMIFS('W час'!$E$22:$AF$22,'W час'!$E$4:$AF$4,K$19) -> 0 | L22: =SUMIFS('W час'!$E$22:$AF$22,'W час'!$E$4:$AF$4,L$19) -> 0 | M22: =SUMIFS('W час'!$E$22:$AF$22,'W час'!$E$4:$AF$4,M$19) -> 0 | ... O22: =SUMIFS('W час'!$E$22:$AF$22,'W час'!$E$4:$AF$4,O$19) -> 0
C23: =MAX(C$20:C22)+1 -> 4 | D23: Срок эксплуатации | E23: лет | F23: =SUMIFS(Производительность!$Y$7:$Y$34,Производительность!$C$7:$C$34,F$19) -> 12 | G23: =SUMIFS(Производительность!$Y$7:$Y$34,Производительность!$C$7:$C$34,G$19) -> 0 | H23: =SUMIFS(Производительность!$Y$7:$Y$34,Производительность!$C$7:$C$34,H$19) -> 0 | I23: =SUMIFS(Производительность!$Y$7:$Y$34,Производительность!$C$7:$C$34,I$19) -> 0 | J23: =SUMIFS(Производительность!$Y$7:$Y$34,Производительность!$C$7:$C$34,J$19) -> 0 | K23: =SUMIFS(Производительность!$Y$7:$Y$34,Производительность!$C$7:$C$34,K$19) -> 0 | L23: =SUMIFS(Производительность!$Y$7:$Y$34,Производительность!$C$7:$C$34,L$19) -> 0 | M23: =SUMIFS(Производительность!$Y$7:$Y$34,Производительность!$C$7:$C$34,M$19) -> 0 | ... O23: =SUMIFS(Производительность!$Y$7:$Y$34,Производительность!$C$7:$C$34,O$19) -> 0
C24: =MAX(C$20:C23)+1 -> 5 | D24: КТГ (средний за эксплуатацию) | E24: коэфф. | F24: =SUMIFS(Производительность!$Z$7:$Z$34,Производительность!$C$7:$C$34,F$19) -> 0.91206875 | G24: =SUMIFS(Производительность!$Z$7:$Z$34,Производительность!$C$7:$C$34,G$19) -> #DIV/0! | H24: =SUMIFS(Производительность!$Z$7:$Z$34,Производительность!$C$7:$C$34,H$19) -> 0 | I24: =SUMIFS(Производительность!$Z$7:$Z$34,Производительность!$C$7:$C$34,I$19) -> 0 | J24: =SUMIFS(Производительность!$Z$7:$Z$34,Производительность!$C$7:$C$34,J$19) -> 0 | K24: =SUMIFS(Производительность!$Z$7:$Z$34,Производительность!$C$7:$C$34,K$19) -> 0 | L24: =SUMIFS(Производительность!$Z$7:$Z$34,Производительность!$C$7:$C$34,L$19) -> 0 | M24: =SUMIFS(Производительность!$Z$7:$Z$34,Производительность!$C$7:$C$34,M$19) -> 0 | ... O24: =SUMIFS(Производительность!$Z$7:$Z$34,Производительность!$C$7:$C$34,O$19) -> 0
C25: =MAX(C$20:C24)+1 -> 6 | D25: КТГ (1-й год) | E25: =E24 -> коэфф. | F25: =SUMIFS(Производительность!$E$7:$E$34,Производительность!$C$7:$C$34,F$19) -> 0.92538686 | G25: =SUMIFS(Производительность!$E$7:$E$34,Производительность!$C$7:$C$34,G$19) -> 0 | H25: =SUMIFS(Производительность!$E$7:$E$34,Производительность!$C$7:$C$34,H$19) -> 0 | I25: =SUMIFS(Производительность!$E$7:$E$34,Производительность!$C$7:$C$34,I$19) -> 0 | J25: =SUMIFS(Производительность!$E$7:$E$34,Производительность!$C$7:$C$34,J$19) -> 0 | K25: =SUMIFS(Производительность!$E$7:$E$34,Производительность!$C$7:$C$34,K$19) -> 0 | L25: =SUMIFS(Производительность!$E$7:$E$34,Производительность!$C$7:$C$34,L$19) -> 0 | M25: =SUMIFS(Производительность!$E$7:$E$34,Производительность!$C$7:$C$34,M$19) -> 0 | ... O25: =SUMIFS(Производительность!$E$7:$E$34,Производительность!$C$7:$C$34,O$19) -> 0
C26: =MAX(C$20:C25)+1 -> 7 | D26: КИО (средний за эксплуатацию) | E26: =E24 -> коэфф. | F26: =SUMIFS(Производительность!$Z$115:$Z$142,Производительность!$C$115:$C$142,F$19) -> 0.74115623 | G26: =SUMIFS(Производительность!$Z$115:$Z$142,Производительность!$C$115:$C$142,G$19) -> #DIV/0! | H26: =SUMIFS(Производительность!$Z$115:$Z$142,Производительность!$C$115:$C$142,H$19) -> 0 | I26: =SUMIFS(Производительность!$Z$115:$Z$142,Производительность!$C$115:$C$142,I$19) -> 0 | J26: =SUMIFS(Производительность!$Z$115:$Z$142,Производительность!$C$115:$C$142,J$19) -> 0 | K26: =SUMIFS(Производительность!$Z$115:$Z$142,Производительность!$C$115:$C$142,K$19) -> 0 | L26: =SUMIFS(Производительность!$Z$115:$Z$142,Производительность!$C$115:$C$142,L$19) -> 0 | M26: =SUMIFS(Производительность!$Z$115:$Z$142,Производительность!$C$115:$C$142,M$19) -> 0 | ... O26: =SUMIFS(Производительность!$Z$115:$Z$142,Производительность!$C$115:$C$142,O$19) -> 0
C27: =MAX(C$20:C26)+1 -> 8 | D27: Часовая производительность | E27: п. м/час | F27: =SUMIFS(Производительность!$E$169:$E$196,Производительность!$C$169:$C$196,F$19) -> 20.204182 | G27: =SUMIFS(Производительность!$E$169:$E$196,Производительность!$C$169:$C$196,G$19) -> 22.953285 | H27: =SUMIFS(Производительность!$E$169:$E$196,Производительность!$C$169:$C$196,H$19) -> 0 | I27: =SUMIFS(Производительность!$E$169:$E$196,Производительность!$C$169:$C$196,I$19) -> 0 | J27: =SUMIFS(Производительность!$E$169:$E$196,Производительность!$C$169:$C$196,J$19) -> 0 | K27: =SUMIFS(Производительность!$E$169:$E$196,Производительность!$C$169:$C$196,K$19) -> 0 | L27: =SUMIFS(Производительность!$E$169:$E$196,Производительность!$C$169:$C$196,L$19) -> 0 | M27: =SUMIFS(Производительность!$E$169:$E$196,Производительность!$C$169:$C$196,M$19) -> 0 | ... O27: =SUMIFS(Производительность!$E$169:$E$196,Производительность!$C$169:$C$196,O$19) -> 0
C28: =MAX(C$20:C27)+1 -> 9 | D28: Производительность (средняя за эксплуатацию) | E28: тыс. п. м | F28: =SUMIFS(Производительность!$Z$196:$Z$223,Производительность!$C$196:$C$223,F$19) -> 131.17623 | G28: =SUMIFS(Производительность!$Z$196:$Z$223,Производительность!$C$196:$C$223,G$19) -> #DIV/0! | H28: =SUMIFS(Производительность!$Z$196:$Z$223,Производительность!$C$196:$C$223,H$19) -> 0 | I28: =SUMIFS(Производительность!$Z$196:$Z$223,Производительность!$C$196:$C$223,I$19) -> 0 | J28: =SUMIFS(Производительность!$Z$196:$Z$223,Производительность!$C$196:$C$223,J$19) -> 0 | K28: =SUMIFS(Производительность!$Z$196:$Z$223,Производительность!$C$196:$C$223,K$19) -> 0 | L28: =SUMIFS(Производительность!$Z$196:$Z$223,Производительность!$C$196:$C$223,L$19) -> 0 | M28: =SUMIFS(Производительность!$Z$196:$Z$223,Производительность!$C$196:$C$223,M$19) -> 0 | ... O28: =SUMIFS(Производительность!$Z$196:$Z$223,Производительность!$C$196:$C$223,O$19) -> 0
C29: =MAX(C$20:C28)+1 -> 10 | E29: тыс. м3 | F29: =SUMIFS(Производительность!$Z$250:$Z$277,Производительность!$C$250:$C$277,F$19) -> 2766.0545 | G29: =SUMIFS(Производительность!$Z$250:$Z$277,Производительность!$C$250:$C$277,G$19) -> #DIV/0! | H29: =SUMIFS(Производительность!$Z$250:$Z$277,Производительность!$C$250:$C$277,H$19) -> 0 | I29: =SUMIFS(Производительность!$Z$250:$Z$277,Производительность!$C$250:$C$277,I$19) -> 0 | J29: =SUMIFS(Производительность!$Z$250:$Z$277,Производительность!$C$250:$C$277,J$19) -> 0 | K29: =SUMIFS(Производительность!$Z$250:$Z$277,Производительность!$C$250:$C$277,K$19) -> 0 | L29: =SUMIFS(Производительность!$Z$250:$Z$277,Производительность!$C$250:$C$277,L$19) -> 0 | M29: =SUMIFS(Производительность!$Z$250:$Z$277,Производительность!$C$250:$C$277,M$19) -> 0 | ... O29: =SUMIFS(Производительность!$Z$250:$Z$277,Производительность!$C$250:$C$277,O$19) -> 0
C30: =MAX(C$20:C29)+1 -> 11 | D30: Производительность (1-й год) | E30: =E28 -> тыс. п. м | F30: =SUMIFS(Производительность!$E$196:$E$223,Производительность!$C$196:$C$223,F$19) -> 133.09168 | G30: =SUMIFS(Производительность!$E$196:$E$223,Производительность!$C$196:$C$223,G$19) -> 0 | H30: =SUMIFS(Производительность!$E$196:$E$223,Производительность!$C$196:$C$223,H$19) -> 0 | I30: =SUMIFS(Производительность!$E$196:$E$223,Производительность!$C$196:$C$223,I$19) -> 0 | J30: =SUMIFS(Производительность!$E$196:$E$223,Производительность!$C$196:$C$223,J$19) -> 0 | K30: =SUMIFS(Производительность!$E$196:$E$223,Производительность!$C$196:$C$223,K$19) -> 0 | L30: =SUMIFS(Производительность!$E$196:$E$223,Производительность!$C$196:$C$223,L$19) -> 0 | M30: =SUMIFS(Производительность!$E$196:$E$223,Производительность!$C$196:$C$223,M$19) -> 0 | ... O30: =SUMIFS(Производительность!$E$196:$E$223,Производительность!$C$196:$C$223,O$19) -> 0
C31: =MAX(C$20:C30)+1 -> 12 | E31: =E29 -> тыс. м3 | F31: =SUMIFS(Производительность!$E$250:$E$277,Производительность!$C$250:$C$277,F$19) -> 2540.6227 | G31: =SUMIFS(Производительность!$E$250:$E$277,Производительность!$C$250:$C$277,G$19) -> 0 | H31: =SUMIFS(Производительность!$E$250:$E$277,Производительность!$C$250:$C$277,H$19) -> 0 | I31: =SUMIFS(Производительность!$E$250:$E$277,Производительность!$C$250:$C$277,I$19) -> 0 | J31: =SUMIFS(Производительность!$E$250:$E$277,Производительность!$C$250:$C$277,J$19) -> 0 | K31: =SUMIFS(Производительность!$E$250:$E$277,Производительность!$C$250:$C$277,K$19) -> 0 | L31: =SUMIFS(Производительность!$E$250:$E$277,Производительность!$C$250:$C$277,L$19) -> 0 | M31: =SUMIFS(Производительность!$E$250:$E$277,Производительность!$C$250:$C$277,M$19) -> 0 | ... O31: =SUMIFS(Производительность!$E$250:$E$277,Производительность!$C$250:$C$277,O$19) -> 0
C33: =MAX(C$20:C32)+1 -> 13 | D33: Стоимость станка | E33: тыс. руб. | F33: =F37+F38 -> 0 | G33: =G37+G38 -> 0 | H33: =H37+H38 -> 0 | I33: =I37+I38 -> 0 | J33: =J37+J38 -> 0 | K33: =K37+K38 -> 0 | L33: =L37+L38 -> 0 | M33: =M37+M38 -> 0 | ... O33: =O37+O38 -> 0 | R33: ='Свод_250-270_диз'!R33 -> курс ЦБ на хх.07.2026
A34: заполнить | C34: =MAX(C$20:C33)+1 -> 14 | D34: Цена в долларах | E34: тыс. долл. | R34: ='Свод_250-270_диз'!R34 -> 80
A35: заполнить | C35: =MAX(C$20:C34)+1 -> 15 | D35: Цена в евро | E35: тыс. евро | R35: ='Свод_250-270_диз'!R35 -> 90
A36: заполнить | C36: =MAX(C$20:C35)+1 -> 16 | D36: Цена в юанях | E36: тыс. юаней | R36: ='Свод_250-270_диз'!R36 -> 11
A37: заполнить | C37: =MAX(C$20:C36)+1 -> 17 | D37: Цена в рублях | E37: =E33 -> тыс. руб.
A38: заполнить | C38: =MAX(C$20:C37)+1 -> 18 | D38: Сборка | E38: =E33 -> тыс. руб.
A40: заполнить | C40: =MAX(C$20:C39)+1 -> 19 | D40: Потребность | E40: ед.
C41: =MAX(C$20:C40)+1 -> 20 | D41: CAPEX на потребность | E41: =E33 -> тыс. руб. | F41: =F40*F33 -> 0 | G41: =G40*G33 -> 0 | H41: =H40*H33 -> 0 | I41: =I40*I33 -> 0 | J41: =J40*J33 -> 0 | K41: =K40*K33 -> 0 | L41: =L40*L33 -> 0 | M41: =M40*M33 -> 0 | ... O41: =O40*O33 -> 0
C43: =MAX(C$20:C42)+1 -> 21 | D43: Среднегодовые затраты на ТО (включая смазочные) и ремонты | E43: тыс. руб. | F43: =SUMIFS(ТСО_215_диз!$AB:$AB,ТСО_215_диз!$A:$A,F$19) -> 17547.479 | G43: =SUMIFS(ТСО_215_диз!$AB:$AB,ТСО_215_диз!$A:$A,G$19) -> #DIV/0! | H43: =SUMIFS(ТСО_215_диз!$AB:$AB,ТСО_215_диз!$A:$A,H$19) -> 0 | I43: =SUMIFS(ТСО_215_диз!$AB:$AB,ТСО_215_диз!$A:$A,I$19) -> 0 | J43: =SUMIFS(ТСО_215_диз!$AB:$AB,ТСО_215_диз!$A:$A,J$19) -> 0 | K43: =SUMIFS(ТСО_215_диз!$AB:$AB,ТСО_215_диз!$A:$A,K$19) -> 0 | L43: =SUMIFS(ТСО_215_диз!$AB:$AB,ТСО_215_диз!$A:$A,L$19) -> 0 | M43: =SUMIFS(ТСО_215_диз!$AB:$AB,ТСО_215_диз!$A:$A,M$19) -> 0 | ... O43: =SUMIFS(ТСО_215_диз!$AB:$AB,ТСО_215_диз!$A:$A,O$19) -> 0
A45: =ТСО_215_диз!B87 -> Аннуитет операционный | C45: =MAX(C$20:C44)+1 -> 22 | D45: =ТСО_215_диз!D87 -> Аннуитет операционный | E45: =ТСО_215_диз!E87 -> руб/м3 | F45: =SUMIFS(ТСО_215_диз!$AC:$AC,ТСО_215_диз!$A:$A,F$19,ТСО_215_диз!$B:$B,$A45) -> 13.256545 | G45: =SUMIFS(ТСО_215_диз!$AC:$AC,ТСО_215_диз!$A:$A,G$19,ТСО_215_диз!$B:$B,$A45) -> #DIV/0! | H45: =SUMIFS(ТСО_215_диз!$AC:$AC,ТСО_215_диз!$A:$A,H$19,ТСО_215_диз!$B:$B,$A45) -> 0 | I45: =SUMIFS(ТСО_215_диз!$AC:$AC,ТСО_215_диз!$A:$A,I$19,ТСО_215_диз!$B:$B,$A45) -> 0 | J45: =SUMIFS(ТСО_215_диз!$AC:$AC,ТСО_215_диз!$A:$A,J$19,ТСО_215_диз!$B:$B,$A45) -> 0 | K45: =SUMIFS(ТСО_215_диз!$AC:$AC,ТСО_215_диз!$A:$A,K$19,ТСО_215_диз!$B:$B,$A45) -> 0 | L45: =SUMIFS(ТСО_215_диз!$AC:$AC,ТСО_215_диз!$A:$A,L$19,ТСО_215_диз!$B:$B,$A45) -> 0 | M45: =SUMIFS(ТСО_215_диз!$AC:$AC,ТСО_215_диз!$A:$A,M$19,ТСО_215_диз!$B:$B,$A45) -> 0 | ... O45: =SUMIFS(ТСО_215_диз!$AC:$AC,ТСО_215_диз!$A:$A,O$19,ТСО_215_диз!$B:$B,$A45) -> 0
A46: =ТСО_215_диз!B88 -> ТО, ТР, ППР | C46: =MAX(C$20:C45)+1 -> 23 | D46: =ТСО_215_диз!D88 -> ТО, ТР, ППР | E46: =ТСО_215_диз!E88 -> руб/м3 | F46: =SUMIFS(ТСО_215_диз!$AC:$AC,ТСО_215_диз!$A:$A,F$19,ТСО_215_диз!$B:$B,$A46) -> 6.0955477 | G46: =SUMIFS(ТСО_215_диз!$AC:$AC,ТСО_215_диз!$A:$A,G$19,ТСО_215_диз!$B:$B,$A46) -> #DIV/0! | H46: =SUMIFS(ТСО_215_диз!$AC:$AC,ТСО_215_диз!$A:$A,H$19,ТСО_215_диз!$B:$B,$A46) -> 0 | I46: =SUMIFS(ТСО_215_диз!$AC:$AC,ТСО_215_диз!$A:$A,I$19,ТСО_215_диз!$B:$B,$A46) -> 0 | J46: =SUMIFS(ТСО_215_диз!$AC:$AC,ТСО_215_диз!$A:$A,J$19,ТСО_215_диз!$B:$B,$A46) -> 0 | K46: =SUMIFS(ТСО_215_диз!$AC:$AC,ТСО_215_диз!$A:$A,K$19,ТСО_215_диз!$B:$B,$A46) -> 0 | L46: =SUMIFS(ТСО_215_диз!$AC:$AC,ТСО_215_диз!$A:$A,L$19,ТСО_215_диз!$B:$B,$A46) -> 0 | M46: =SUMIFS(ТСО_215_диз!$AC:$AC,ТСО_215_диз!$A:$A,M$19,ТСО_215_диз!$B:$B,$A46) -> 0 | ... O46: =SUMIFS(ТСО_215_диз!$AC:$AC,ТСО_215_диз!$A:$A,O$19,ТСО_215_диз!$B:$B,$A46) -> 0
A47: =ТСО_215_диз!B89 -> Смазочные | C47: =MAX(C$20:C46)+1 -> 24 | D47: =ТСО_215_диз!D89 -> Смазочные | E47: =ТСО_215_диз!E89 -> руб/м3 | F47: =SUMIFS(ТСО_215_диз!$AC:$AC,ТСО_215_диз!$A:$A,F$19,ТСО_215_диз!$B:$B,$A47) -> 0 | G47: =SUMIFS(ТСО_215_диз!$AC:$AC,ТСО_215_диз!$A:$A,G$19,ТСО_215_диз!$B:$B,$A47) -> #DIV/0! | H47: =SUMIFS(ТСО_215_диз!$AC:$AC,ТСО_215_диз!$A:$A,H$19,ТСО_215_диз!$B:$B,$A47) -> 0 | I47: =SUMIFS(ТСО_215_диз!$AC:$AC,ТСО_215_диз!$A:$A,I$19,ТСО_215_диз!$B:$B,$A47) -> 0 | J47: =SUMIFS(ТСО_215_диз!$AC:$AC,ТСО_215_диз!$A:$A,J$19,ТСО_215_диз!$B:$B,$A47) -> 0 | K47: =SUMIFS(ТСО_215_диз!$AC:$AC,ТСО_215_диз!$A:$A,K$19,ТСО_215_диз!$B:$B,$A47) -> 0 | L47: =SUMIFS(ТСО_215_диз!$AC:$AC,ТСО_215_диз!$A:$A,L$19,ТСО_215_диз!$B:$B,$A47) -> 0 | M47: =SUMIFS(ТСО_215_диз!$AC:$AC,ТСО_215_диз!$A:$A,M$19,ТСО_215_диз!$B:$B,$A47) -> 0 | ... O47: =SUMIFS(ТСО_215_диз!$AC:$AC,ТСО_215_диз!$A:$A,O$19,ТСО_215_диз!$B:$B,$A47) -> 0
A48: =ТСО_215_диз!B90 -> Долота | C48: =MAX(C$20:C47)+1 -> 25 | D48: =ТСО_215_диз!D90 -> Долота | E48: =ТСО_215_диз!E90 -> руб/м3 | F48: =SUMIFS(ТСО_215_диз!$AC:$AC,ТСО_215_диз!$A:$A,F$19,ТСО_215_диз!$B:$B,$A48) -> 0 | G48: =SUMIFS(ТСО_215_диз!$AC:$AC,ТСО_215_диз!$A:$A,G$19,ТСО_215_диз!$B:$B,$A48) -> #DIV/0! | H48: =SUMIFS(ТСО_215_диз!$AC:$AC,ТСО_215_диз!$A:$A,H$19,ТСО_215_диз!$B:$B,$A48) -> 0 | I48: =SUMIFS(ТСО_215_диз!$AC:$AC,ТСО_215_диз!$A:$A,I$19,ТСО_215_диз!$B:$B,$A48) -> 0 | J48: =SUMIFS(ТСО_215_диз!$AC:$AC,ТСО_215_диз!$A:$A,J$19,ТСО_215_диз!$B:$B,$A48) -> 0 | K48: =SUMIFS(ТСО_215_диз!$AC:$AC,ТСО_215_диз!$A:$A,K$19,ТСО_215_диз!$B:$B,$A48) -> 0 | L48: =SUMIFS(ТСО_215_диз!$AC:$AC,ТСО_215_диз!$A:$A,L$19,ТСО_215_диз!$B:$B,$A48) -> 0 | M48: =SUMIFS(ТСО_215_диз!$AC:$AC,ТСО_215_диз!$A:$A,M$19,ТСО_215_диз!$B:$B,$A48) -> 0 | ... O48: =SUMIFS(ТСО_215_диз!$AC:$AC,ТСО_215_диз!$A:$A,O$19,ТСО_215_диз!$B:$B,$A48) -> 0
A49: =ТСО_215_диз!B91 -> Штанги буровые | C49: =MAX(C$20:C48)+1 -> 26 | D49: =ТСО_215_диз!D91 -> Штанги буровые | E49: =ТСО_215_диз!E91 -> руб/м3 | F49: =SUMIFS(ТСО_215_диз!$AC:$AC,ТСО_215_диз!$A:$A,F$19,ТСО_215_диз!$B:$B,$A49) -> 0 | G49: =SUMIFS(ТСО_215_диз!$AC:$AC,ТСО_215_диз!$A:$A,G$19,ТСО_215_диз!$B:$B,$A49) -> #DIV/0! | H49: =SUMIFS(ТСО_215_диз!$AC:$AC,ТСО_215_диз!$A:$A,H$19,ТСО_215_диз!$B:$B,$A49) -> 0 | I49: =SUMIFS(ТСО_215_диз!$AC:$AC,ТСО_215_диз!$A:$A,I$19,ТСО_215_диз!$B:$B,$A49) -> 0 | J49: =SUMIFS(ТСО_215_диз!$AC:$AC,ТСО_215_диз!$A:$A,J$19,ТСО_215_диз!$B:$B,$A49) -> 0 | K49: =SUMIFS(ТСО_215_диз!$AC:$AC,ТСО_215_диз!$A:$A,K$19,ТСО_215_диз!$B:$B,$A49) -> 0 | L49: =SUMIFS(ТСО_215_диз!$AC:$AC,ТСО_215_диз!$A:$A,L$19,ТСО_215_диз!$B:$B,$A49) -> 0 | M49: =SUMIFS(ТСО_215_диз!$AC:$AC,ТСО_215_диз!$A:$A,M$19,ТСО_215_диз!$B:$B,$A49) -> 0 | ... O49: =SUMIFS(ТСО_215_диз!$AC:$AC,ТСО_215_диз!$A:$A,O$19,ТСО_215_диз!$B:$B,$A49) -> 0
A50: =ТСО_215_диз!B92 -> Расходники | C50: =MAX(C$20:C49)+1 -> 27 | D50: =ТСО_215_диз!D92 -> Расходники | E50: =ТСО_215_диз!E92 -> руб/м3 | F50: =SUMIFS(ТСО_215_диз!$AC:$AC,ТСО_215_диз!$A:$A,F$19,ТСО_215_диз!$B:$B,$A50) -> 0 | G50: =SUMIFS(ТСО_215_диз!$AC:$AC,ТСО_215_диз!$A:$A,G$19,ТСО_215_диз!$B:$B,$A50) -> #DIV/0! | H50: =SUMIFS(ТСО_215_диз!$AC:$AC,ТСО_215_диз!$A:$A,H$19,ТСО_215_диз!$B:$B,$A50) -> 0 | I50: =SUMIFS(ТСО_215_диз!$AC:$AC,ТСО_215_диз!$A:$A,I$19,ТСО_215_диз!$B:$B,$A50) -> 0 | J50: =SUMIFS(ТСО_215_диз!$AC:$AC,ТСО_215_диз!$A:$A,J$19,ТСО_215_диз!$B:$B,$A50) -> 0 | K50: =SUMIFS(ТСО_215_диз!$AC:$AC,ТСО_215_диз!$A:$A,K$19,ТСО_215_диз!$B:$B,$A50) -> 0 | L50: =SUMIFS(ТСО_215_диз!$AC:$AC,ТСО_215_диз!$A:$A,L$19,ТСО_215_диз!$B:$B,$A50) -> 0 | M50: =SUMIFS(ТСО_215_диз!$AC:$AC,ТСО_215_диз!$A:$A,M$19,ТСО_215_диз!$B:$B,$A50) -> 0 | ... O50: =SUMIFS(ТСО_215_диз!$AC:$AC,ТСО_215_диз!$A:$A,O$19,ТСО_215_диз!$B:$B,$A50) -> 0
A51: =ТСО_215_диз!B93 -> Топливо/Электроэнергия | C51: =MAX(C$20:C50)+1 -> 28 | D51: =ТСО_215_диз!D93 -> Топливо/Электроэнергия | E51: =ТСО_215_диз!E93 -> руб/м3 | F51: =SUMIFS(ТСО_215_диз!$AC:$AC,ТСО_215_диз!$A:$A,F$19,ТСО_215_диз!$B:$B,$A51) -> 5.9002316 | G51: =SUMIFS(ТСО_215_диз!$AC:$AC,ТСО_215_диз!$A:$A,G$19,ТСО_215_диз!$B:$B,$A51) -> #DIV/0! | H51: =SUMIFS(ТСО_215_диз!$AC:$AC,ТСО_215_диз!$A:$A,H$19,ТСО_215_диз!$B:$B,$A51) -> 0 | I51: =SUMIFS(ТСО_215_диз!$AC:$AC,ТСО_215_диз!$A:$A,I$19,ТСО_215_диз!$B:$B,$A51) -> 0 | J51: =SUMIFS(ТСО_215_диз!$AC:$AC,ТСО_215_диз!$A:$A,J$19,ТСО_215_диз!$B:$B,$A51) -> 0 | K51: =SUMIFS(ТСО_215_диз!$AC:$AC,ТСО_215_диз!$A:$A,K$19,ТСО_215_диз!$B:$B,$A51) -> 0 | L51: =SUMIFS(ТСО_215_диз!$AC:$AC,ТСО_215_диз!$A:$A,L$19,ТСО_215_диз!$B:$B,$A51) -> 0 | M51: =SUMIFS(ТСО_215_диз!$AC:$AC,ТСО_215_диз!$A:$A,M$19,ТСО_215_диз!$B:$B,$A51) -> 0 | ... O51: =SUMIFS(ТСО_215_диз!$AC:$AC,ТСО_215_диз!$A:$A,O$19,ТСО_215_диз!$B:$B,$A51) -> 0
A52: =ТСО_215_диз!B94 -> Затраты на персонал | C52: =MAX(C$20:C51)+1 -> 29 | D52: =ТСО_215_диз!D94 -> Затраты на персонал | E52: =ТСО_215_диз!E94 -> руб/м3 | F52: =SUMIFS(ТСО_215_диз!$AC:$AC,ТСО_215_диз!$A:$A,F$19,ТСО_215_диз!$B:$B,$A52) -> 5.679614 | G52: =SUMIFS(ТСО_215_диз!$AC:$AC,ТСО_215_диз!$A:$A,G$19,ТСО_215_диз!$B:$B,$A52) -> #DIV/0! | H52: =SUMIFS(ТСО_215_диз!$AC:$AC,ТСО_215_диз!$A:$A,H$19,ТСО_215_диз!$B:$B,$A52) -> 0 | I52: =SUMIFS(ТСО_215_диз!$AC:$AC,ТСО_215_диз!$A:$A,I$19,ТСО_215_диз!$B:$B,$A52) -> 0 | J52: =SUMIFS(ТСО_215_диз!$AC:$AC,ТСО_215_диз!$A:$A,J$19,ТСО_215_диз!$B:$B,$A52) -> 0 | K52: =SUMIFS(ТСО_215_диз!$AC:$AC,ТСО_215_диз!$A:$A,K$19,ТСО_215_диз!$B:$B,$A52) -> 0 | L52: =SUMIFS(ТСО_215_диз!$AC:$AC,ТСО_215_диз!$A:$A,L$19,ТСО_215_диз!$B:$B,$A52) -> 0 | M52: =SUMIFS(ТСО_215_диз!$AC:$AC,ТСО_215_диз!$A:$A,M$19,ТСО_215_диз!$B:$B,$A52) -> 0 | ... O52: =SUMIFS(ТСО_215_диз!$AC:$AC,ТСО_215_диз!$A:$A,O$19,ТСО_215_диз!$B:$B,$A52) -> 0
A53: =ТСО_215_диз!B95 -> Транспортный налог | C53: =MAX(C$20:C52)+1 -> 30 | D53: =ТСО_215_диз!D95 -> Транспортный налог | E53: =ТСО_215_диз!E95 -> руб/м3 | F53: =SUMIFS(ТСО_215_диз!$AC:$AC,ТСО_215_диз!$A:$A,F$19,ТСО_215_диз!$B:$B,$A53) -> 0 | G53: =SUMIFS(ТСО_215_диз!$AC:$AC,ТСО_215_диз!$A:$A,G$19,ТСО_215_диз!$B:$B,$A53) -> #DIV/0! | H53: =SUMIFS(ТСО_215_диз!$AC:$AC,ТСО_215_диз!$A:$A,H$19,ТСО_215_диз!$B:$B,$A53) -> 0 | I53: =SUMIFS(ТСО_215_диз!$AC:$AC,ТСО_215_диз!$A:$A,I$19,ТСО_215_диз!$B:$B,$A53) -> 0 | J53: =SUMIFS(ТСО_215_диз!$AC:$AC,ТСО_215_диз!$A:$A,J$19,ТСО_215_диз!$B:$B,$A53) -> 0 | K53: =SUMIFS(ТСО_215_диз!$AC:$AC,ТСО_215_диз!$A:$A,K$19,ТСО_215_диз!$B:$B,$A53) -> 0 | L53: =SUMIFS(ТСО_215_диз!$AC:$AC,ТСО_215_диз!$A:$A,L$19,ТСО_215_диз!$B:$B,$A53) -> 0 | M53: =SUMIFS(ТСО_215_диз!$AC:$AC,ТСО_215_диз!$A:$A,M$19,ТСО_215_диз!$B:$B,$A53) -> 0 | ... O53: =SUMIFS(ТСО_215_диз!$AC:$AC,ТСО_215_диз!$A:$A,O$19,ТСО_215_диз!$B:$B,$A53) -> 0
A54: =ТСО_215_диз!B96 -> Налог на прибыль | C54: =MAX(C$20:C53)+1 -> 31 | D54: =ТСО_215_диз!D96 -> Налог на прибыль | E54: =ТСО_215_диз!E96 -> руб/м3 | F54: =SUMIFS(ТСО_215_диз!$AC:$AC,ТСО_215_диз!$A:$A,F$19,ТСО_215_диз!$B:$B,$A54) -> -4.4188483 | G54: =SUMIFS(ТСО_215_диз!$AC:$AC,ТСО_215_диз!$A:$A,G$19,ТСО_215_диз!$B:$B,$A54) -> #DIV/0! | H54: =SUMIFS(ТСО_215_диз!$AC:$AC,ТСО_215_диз!$A:$A,H$19,ТСО_215_диз!$B:$B,$A54) -> 0 | I54: =SUMIFS(ТСО_215_диз!$AC:$AC,ТСО_215_диз!$A:$A,I$19,ТСО_215_диз!$B:$B,$A54) -> 0 | J54: =SUMIFS(ТСО_215_диз!$AC:$AC,ТСО_215_диз!$A:$A,J$19,ТСО_215_диз!$B:$B,$A54) -> 0 | K54: =SUMIFS(ТСО_215_диз!$AC:$AC,ТСО_215_диз!$A:$A,K$19,ТСО_215_диз!$B:$B,$A54) -> 0 | L54: =SUMIFS(ТСО_215_диз!$AC:$AC,ТСО_215_диз!$A:$A,L$19,ТСО_215_диз!$B:$B,$A54) -> 0 | M54: =SUMIFS(ТСО_215_диз!$AC:$AC,ТСО_215_диз!$A:$A,M$19,ТСО_215_диз!$B:$B,$A54) -> 0 | ... O54: =SUMIFS(ТСО_215_диз!$AC:$AC,ТСО_215_диз!$A:$A,O$19,ТСО_215_диз!$B:$B,$A54) -> 0
A55: =ТСО_215_диз!B97 -> Аннуитет инвестиционный | C55: =MAX(C$20:C54)+1 -> 32 | D55: =ТСО_215_диз!D97 -> Аннуитет инвестиционный | E55: =ТСО_215_диз!E97 -> руб/м3 | F55: =SUMIFS(ТСО_215_диз!$AC:$AC,ТСО_215_диз!$A:$A,F$19,ТСО_215_диз!$B:$B,$A55) -> 0 | G55: =SUMIFS(ТСО_215_диз!$AC:$AC,ТСО_215_диз!$A:$A,G$19,ТСО_215_диз!$B:$B,$A55) -> #DIV/0! | H55: =SUMIFS(ТСО_215_диз!$AC:$AC,ТСО_215_диз!$A:$A,H$19,ТСО_215_диз!$B:$B,$A55) -> 0 | I55: =SUMIFS(ТСО_215_диз!$AC:$AC,ТСО_215_диз!$A:$A,I$19,ТСО_215_диз!$B:$B,$A55) -> 0 | J55: =SUMIFS(ТСО_215_диз!$AC:$AC,ТСО_215_диз!$A:$A,J$19,ТСО_215_диз!$B:$B,$A55) -> 0 | K55: =SUMIFS(ТСО_215_диз!$AC:$AC,ТСО_215_диз!$A:$A,K$19,ТСО_215_диз!$B:$B,$A55) -> 0 | L55: =SUMIFS(ТСО_215_диз!$AC:$AC,ТСО_215_диз!$A:$A,L$19,ТСО_215_диз!$B:$B,$A55) -> 0 | M55: =SUMIFS(ТСО_215_диз!$AC:$AC,ТСО_215_диз!$A:$A,M$19,ТСО_215_диз!$B:$B,$A55) -> 0 | ... O55: =SUMIFS(ТСО_215_диз!$AC:$AC,ТСО_215_диз!$A:$A,O$19,ТСО_215_диз!$B:$B,$A55) -> 0
A56: =ТСО_215_диз!B99 -> Аннуитет общий | C56: =MAX(C$20:C55)+1 -> 33 | D56: =ТСО_215_диз!D99 -> Аннуитет общий | E56: =ТСО_215_диз!E99 -> руб/м3 | F56: =SUMIFS(ТСО_215_диз!$AC:$AC,ТСО_215_диз!$A:$A,F$19,ТСО_215_диз!$B:$B,$A56) -> 13.256545 | G56: =SUMIFS(ТСО_215_диз!$AC:$AC,ТСО_215_диз!$A:$A,G$19,ТСО_215_диз!$B:$B,$A56) -> #DIV/0! | H56: =SUMIFS(ТСО_215_диз!$AC:$AC,ТСО_215_диз!$A:$A,H$19,ТСО_215_диз!$B:$B,$A56) -> 0 | I56: =SUMIFS(ТСО_215_диз!$AC:$AC,ТСО_215_диз!$A:$A,I$19,ТСО_215_диз!$B:$B,$A56) -> 0 | J56: =SUMIFS(ТСО_215_диз!$AC:$AC,ТСО_215_диз!$A:$A,J$19,ТСО_215_диз!$B:$B,$A56) -> 0 | K56: =SUMIFS(ТСО_215_диз!$AC:$AC,ТСО_215_диз!$A:$A,K$19,ТСО_215_диз!$B:$B,$A56) -> 0 | L56: =SUMIFS(ТСО_215_диз!$AC:$AC,ТСО_215_диз!$A:$A,L$19,ТСО_215_диз!$B:$B,$A56) -> 0 | M56: =SUMIFS(ТСО_215_диз!$AC:$AC,ТСО_215_диз!$A:$A,M$19,ТСО_215_диз!$B:$B,$A56) -> 0 | ... O56: =SUMIFS(ТСО_215_диз!$AC:$AC,ТСО_215_диз!$A:$A,O$19,ТСО_215_диз!$B:$B,$A56) -> 0
F57: =F45-SUM(F46:F54)+F56-F45-F55 -> -1.7763568e-15 | G57: =G45-SUM(G46:G54)+G56-G45-G55 -> #DIV/0! | H57: =H45-SUM(H46:H54)+H56-H45-H55 -> 0 | I57: =I45-SUM(I46:I54)+I56-I45-I55 -> 0 | J57: =J45-SUM(J46:J54)+J56-J45-J55 -> 0 | K57: =K45-SUM(K46:K54)+K56-K45-K55 -> 0 | L57: =L45-SUM(L46:L54)+L56-L45-L55 -> 0 | M57: =M45-SUM(M46:M54)+M56-M45-M55 -> 0 | ... O57: =O45-SUM(O46:O54)+O56-O45-O55 -> 0
A58: для ранжирования | D58: =D56 -> Аннуитет общий | F58: =IF(F56>0,F56,"нет") -> 13.256545 | G58: =IF(G56>0,G56,"нет") -> #DIV/0! | H58: =IF(H56>0,H56,"нет") -> нет | I58: =IF(I56>0,I56,"нет") -> нет | J58: =IF(J56>0,J56,"нет") -> нет | K58: =IF(K56>0,K56,"нет") -> нет | L58: =IF(L56>0,L56,"нет") -> нет | M58: =IF(M56>0,M56,"нет") -> нет | ... O58: =IF(O56>0,O56,"нет") -> нет
A59: =A58 -> для ранжирования | D59: =D33 -> Стоимость станка | F59: =IF(F33>0,F33,"нет") -> нет | G59: =IF(G33>0,G33,"нет") -> нет | H59: =IF(H33>0,H33,"нет") -> нет | I59: =IF(I33>0,I33,"нет") -> нет | J59: =IF(J33>0,J33,"нет") -> нет | K59: =IF(K33>0,K33,"нет") -> нет | L59: =IF(L33>0,L33,"нет") -> нет | M59: =IF(M33>0,M33,"нет") -> нет | ... O59: =IF(O33>0,O33,"нет") -> нет
A60: =A58 -> для ранжирования | F60: =F19 -> БС-215 | G60: =G19 -> СБ-55Д-01 | H60: =H19 -> 0 | I60: =I19 -> 0 | J60: =J19 -> 0 | K60: =K19 -> 0 | L60: =L19 -> 0 | M60: =M19 -> 0 | ... O60: =O19 -> 0

Sheet ТСО_215_диз
A1: не удалять | B1: не удалять | C1: не удалять | D1: Показатель | E1: Ед. изм. | F1: =G1-1 -> 0 | G1: 1 | H1: =G1+1 -> 2 | I1: =H1+1 -> 3 | J1: =I1+1 -> 4 | K1: =J1+1 -> 5 | L1: =K1+1 -> 6 | M1: =L1+1 -> 7 | N1: =M1+1 -> 8 | O1: =N1+1 -> 9 | ... Z1: =Y1+1 -> 20 | AA1: не удалять | AB1: не удалять | AC1: не удалять
A2: * | F2: лет | G2: 2027 | H2: =G2+1 -> 2028 | I2: =H2+1 -> 2029 | J2: =I2+1 -> 2030 | K2: =J2+1 -> 2031 | L2: =K2+1 -> 2032 | M2: =L2+1 -> 2033 | N2: =M2+1 -> 2034 | O2: =N2+1 -> 2035 | ... Z2: =Y2+1 -> 2046 | AA2: проверки | AB2: средние на ТО, ТР, ППР | AC2: аннуитет
A3: * | G3: =Производительность!E6 -> 8760 | H3: =Производительность!F6 -> 8760 | I3: =Производительность!G6 -> 8760 | J3: =Производительность!H6 -> 8760 | K3: =Производительность!I6 -> 8760 | L3: =Производительность!J6 -> 8760 | M3: =Производительность!K6 -> 8760 | N3: =Производительность!L6 -> 8760 | ... Z3: =Производительность!X6 -> 8760
A4: * | D4: Расчет аннуитета
A5: *
A6: * | C6: =SUM(F66:Z66,F80:Z80,F101:Z101,AA48) -> #DIV/0! | D6: =Свод_215_диз!F19 -> БС-215 | E6: =SUMIFS(Производительность!$Y$7:$Y$34,Производительность!$C$7:$C$34,$D6) -> 12 | F6: =$F$2 -> лет
A7: *
A8: =D6 -> БС-215 | D8: =D$1 -> Показатель | E8: =E$1 -> Ед. изм. | F8: =F$1 -> 0 | G8: =G$1 -> 1 | H8: =H$1 -> 2 | I8: =I$1 -> 3 | J8: =J$1 -> 4 | K8: =K$1 -> 5 | ... Z8: =Z$1 -> 20
A9: =A8 -> БС-215 | D9: КТГ | E9: % | G9: =SUMIFS(Производительность!E$7:E$34,Производительность!$C$7:$C$34,$A9) -> 0.92538686 | H9: =SUMIFS(Производительность!F$7:F$34,Производительность!$C$7:$C$34,$A9) -> 0.92272324 | I9: =SUMIFS(Производительность!G$7:G$34,Производительность!$C$7:$C$34,$A9) -> 0.92139143 | J9: =SUMIFS(Производительность!H$7:H$34,Производительность!$C$7:$C$34,$A9) -> 0.89075977 | K9: =SUMIFS(Производительность!I$7:I$34,Производительность!$C$7:$C$34,$A9) -> 0.92005961 | L9: =SUMIFS(Производительность!J$7:J$34,Производительность!$C$7:$C$34,$A9) -> 0.91340056 | M9: =SUMIFS(Производительность!K$7:K$34,Производительность!$C$7:$C$34,$A9) -> 0.89075977 | N9: =SUMIFS(Производительность!L$7:L$34,Производительность!$C$7:$C$34,$A9) -> 0.91739599 | ... Z9: =SUMIFS(Производительность!X$7:X$34,Производительность!$C$7:$C$34,$A9) -> 0
A10: =A9 -> БС-215 | D10: КИО | E10: =E9 -> % | G10: =SUMIFS(Производительность!E$115:E$142,Производительность!$C$115:$C$142,$A10) -> 0.75197866 | H10: =SUMIFS(Производительность!F$115:F$142,Производительность!$C$115:$C$142,$A10) -> 0.74981417 | I10: =SUMIFS(Производительность!G$115:G$142,Производительность!$C$115:$C$142,$A10) -> 0.74873193 | J10: =SUMIFS(Производительность!H$115:H$142,Производительность!$C$115:$C$142,$A10) -> 0.72384034 | K10: =SUMIFS(Производительность!I$115:I$142,Производительность!$C$115:$C$142,$A10) -> 0.74764969 | L10: =SUMIFS(Производительность!J$115:J$142,Производительность!$C$115:$C$142,$A10) -> 0.74223847 | M10: =SUMIFS(Производительность!K$115:K$142,Производительность!$C$115:$C$142,$A10) -> 0.72384034 | N10: =SUMIFS(Производительность!L$115:L$142,Производительность!$C$115:$C$142,$A10) -> 0.7454852 | ... Z10: =SUMIFS(Производительность!X$115:X$142,Производительность!$C$115:$C$142,$A10) -> 0
A11: =A10 -> БС-215 | D11: Производительность_бурение | E11: тыс. п. м | G11: =SUMIFS(Производительность!E$196:E$223,Производительность!$C$196:$C$223,$A11) -> 133.09168 | H11: =SUMIFS(Производительность!F$196:F$223,Производительность!$C$196:$C$223,$A11) -> 132.70859 | I11: =SUMIFS(Производительность!G$196:G$223,Производительность!$C$196:$C$223,$A11) -> 132.51704 | J11: =SUMIFS(Производительность!H$196:H$223,Производительность!$C$196:$C$223,$A11) -> 128.11151 | K11: =SUMIFS(Производительность!I$196:I$223,Производительность!$C$196:$C$223,$A11) -> 132.3255 | L11: =SUMIFS(Производительность!J$196:J$223,Производительность!$C$196:$C$223,$A11) -> 131.36777 | M11: =SUMIFS(Производительность!K$196:K$223,Производительность!$C$196:$C$223,$A11) -> 128.11151 | N11: =SUMIFS(Производительность!L$196:L$223,Производительность!$C$196:$C$223,$A11) -> 131.94241 | ... Z11: =SUMIFS(Производительность!X$196:X$223,Производительность!$C$196:$C$223,$A11) -> 0
A12: =A11 -> БС-215 | D12: Производительность_взрывание | E12: тыс. м3 | G12: =SUMIFS(Производительность!E$250:E$277,Производительность!$C$250:$C$277,$A12) -> 2540.6227 | H12: =SUMIFS(Производительность!F$250:F$277,Производительность!$C$250:$C$277,$A12) -> 2701.8296 | I12: =SUMIFS(Производительность!G$250:G$277,Производительность!$C$250:$C$277,$A12) -> 2739.3009 | J12: =SUMIFS(Производительность!H$250:H$277,Производительность!$C$250:$C$277,$A12) -> 2700.9288 | K12: =SUMIFS(Производительность!I$250:I$277,Производительность!$C$250:$C$277,$A12) -> 2945.1177 | L12: =SUMIFS(Производительность!J$250:J$277,Производительность!$C$250:$C$277,$A12) -> 2904.1695 | M12: =SUMIFS(Производительность!K$250:K$277,Производительность!$C$250:$C$277,$A12) -> 2707.4979 | N12: =SUMIFS(Производительность!L$250:L$277,Производительность!$C$250:$C$277,$A12) -> 3041.4284 | ... Z12: =SUMIFS(Производительность!X$250:X$277,Производительность!$C$250:$C$277,$A12) -> 0
A13: =A12 -> БС-215 | D13: Производительность кумулятивная | E13: =E12 -> тыс. м3 | G13: =G12 -> 2540.6227 | H13: =IF(H12=0,0,G13+H12) -> 5242.4523 | I13: =IF(I12=0,0,H13+I12) -> 7981.7531 | J13: =IF(J12=0,0,I13+J12) -> 10682.682 | K13: =IF(K12=0,0,J13+K12) -> 13627.8 | L13: =IF(L12=0,0,K13+L12) -> 16531.969 | M13: =IF(M12=0,0,L13+M12) -> 19239.467 | N13: =IF(N12=0,0,M13+N12) -> 22280.895 | O13: =IF(O12=0,0,N13+O12) -> 25182.253 | ... Z13: =IF(Z12=0,0,Y13+Z12) -> 0
A14: =A13 -> БС-215
A15: =A14 -> БС-215 | D15: Операционный денежный поток | E15: тыс. руб. | F15: =F49+F50-F48 -> 0 | G15: =G49+G50-G48 -> 32891.745 | H15: =H49+H50-H48 -> 33138.535 | I15: =I49+I50-I48 -> 37300.736 | J15: =J49+J50-J48 -> 41581.731 | K15: =K49+K50-K48 -> 34401.57 | L15: =L49+L50-L48 -> 38174.703 | M15: =M49+M50-M48 -> 38509.401 | ... Z15: =Z49+Z50-Z48 -> 0
A16: =A15 -> БС-215 | D16: ТО, ТР, ППР | E16: =E15 -> тыс. руб. | G16: =(G17+G18+G19) -> 11613.321 | H16: =(H17+H18+H19) -> 11989.961 | I16: =(I17+I18+I19) -> 17563.355 | J16: =(J17+J18+J19) -> 23818.589 | K16: =(K17+K18+K19) -> 13721.592 | L16: =(L17+L18+L19) -> 18871.402 | M16: =(M17+M18+M19) -> 19722.149 | N16: =(N17+N18+N19) -> 18917.808 | ... R16: =(R17+R18+R19) -> 12803.979 | AB16: =SUM(F16:Z16,F21:Z21)/E6 -> 17547.479
A17: =A16 -> БС-215 | D17: ТО (включая смазочные) | E17: тыс. руб. | G17: ='БС-215'!E29 -> 7677.652 | H17: ='БС-215'!F29 -> 7677.652 | I17: ='БС-215'!G29 -> 7677.652 | J17: ='БС-215'!H29 -> 7677.652 | K17: ='БС-215'!I29 -> 7677.652 | L17: ='БС-215'!J29 -> 7677.652 | M17: ='БС-215'!K29 -> 7677.652 | N17: ='БС-215'!L29 -> 7677.652 | ... R17: ='БС-215'!P29 -> 7677.652
A18: =A17 -> БС-215 | D18: ТР, ППР | E18: тыс. руб. | G18: ='БС-215'!E30+'БС-215'!E31 -> 1544.06 | H18: ='БС-215'!F30+'БС-215'!F31 -> 1784.684 | I18: ='БС-215'!G30+'БС-215'!G31 -> 7290.07 | J18: ='БС-215'!H30+'БС-215'!H31 -> 11981.124 | K18: ='БС-215'!I30+'БС-215'!I31 -> 3380.3 | L18: ='БС-215'!J30+'БС-215'!J31 -> 8190.07 | M18: ='БС-215'!K30+'БС-215'!K31 -> 7884.684 | N18: ='БС-215'!L30+'БС-215'!L31 -> 8440.5 | ... R18: ='БС-215'!P30+'БС-215'!P31 -> 2530.694
A19: =A18 -> БС-215 | D19: трудозатраты | E19: тыс. руб. | G19: ='БС-215'!E32+'БС-215'!E33 -> 2391.609 | H19: ='БС-215'!F32+'БС-215'!F33 -> 2527.6247 | I19: ='БС-215'!G32+'БС-215'!G33 -> 2595.6326 | J19: ='БС-215'!H32+'БС-215'!H33 -> 4159.8129 | K19: ='БС-215'!I32+'БС-215'!I33 -> 2663.6404 | L19: ='БС-215'!J32+'БС-215'!J33 -> 3003.6796 | M19: ='БС-215'!K32+'БС-215'!K33 -> 4159.8129 | N19: ='БС-215'!L32+'БС-215'!L33 -> 2799.6561 | ... R19: ='БС-215'!P32+'БС-215'!P33 -> 2595.6326
A20: =A19 -> БС-215 | D20: % стоимости справочно | G20: =G16/$F53 -> #DIV/0! | H20: =H16/$F53 -> #DIV/0! | I20: =I16/$F53 -> #DIV/0! | J20: =J16/$F53 -> #DIV/0! | K20: =K16/$F53 -> #DIV/0! | L20: =L16/$F53 -> #DIV/0! | M20: =M16/$F53 -> #DIV/0! | N20: =N16/$F53 -> #DIV/0! | ... Z20: =Z16/$F53 -> #DIV/0! | AA20: =SUM(F16:Z16)/$F53 -> #DIV/0!
A21: =A20 -> БС-215 | D21: Смазочные | E21: =E15 -> тыс. руб.
A22: =A21 -> БС-215
A23: =A22 -> БС-215 | D23: Долота | E23: =E15 -> тыс. руб. | G23: =G25*G26 -> 0 | H23: =H25*H26 -> 0 | I23: =I25*I26 -> 0 | J23: =J25*J26 -> 0 | K23: =K25*K26 -> 0 | L23: =L25*L26 -> 0 | M23: =M25*M26 -> 0 | N23: =N25*N26 -> 0 | ... Z23: =Z25*Z26 -> 0
A24: =A23 -> БС-215 | D24: удельный расход | E24: шт./тыс. п. м | F24: =SUMIFS('ФОТ, МТР, макро'!$B$4:$B$31,'ФОТ, МТР, макро'!$A$4:$A$31,$A24) -> 0 | G24: =F24 -> 0 | H24: =G24 -> 0 | I24: =H24 -> 0 | J24: =I24 -> 0 | K24: =J24 -> 0 | L24: =K24 -> 0 | M24: =L24 -> 0 | N24: =M24 -> 0 | ... Z24: =Y24 -> 0
A25: =A24 -> БС-215 | D25: расход за период | E25: шт. | G25: =G11*G24 -> 0 | H25: =H11*H24 -> 0 | I25: =I11*I24 -> 0 | J25: =J11*J24 -> 0 | K25: =K11*K24 -> 0 | L25: =L11*L24 -> 0 | M25: =M11*M24 -> 0 | N25: =N11*N24 -> 0 | ... Z25: =Z11*Z24 -> 0
A26: =A25 -> БС-215 | D26: цена | E26: тыс. руб./шт. | F26: =SUMIFS('ФОТ, МТР, макро'!$C$4:$C$31,'ФОТ, МТР, макро'!$A$4:$A$31,$A26) -> 0 | G26: =F26 -> 0 | H26: =G26 -> 0 | I26: =H26 -> 0 | J26: =I26 -> 0 | K26: =J26 -> 0 | L26: =K26 -> 0 | M26: =L26 -> 0 | N26: =M26 -> 0 | ... Z26: =Y26 -> 0
A27: =A26 -> БС-215 | D27: Штанги буровые | E27: =E15 -> тыс. руб. | G27: =G29*G30 -> 0 | H27: =H29*H30 -> 0 | I27: =I29*I30 -> 0 | J27: =J29*J30 -> 0 | K27: =K29*K30 -> 0 | L27: =L29*L30 -> 0 | M27: =M29*M30 -> 0 | N27: =N29*N30 -> 0 | ... Z27: =Z29*Z30 -> 0
A28: =A27 -> БС-215 | D28: удельный расход | E28: шт./тыс. п. м | F28: =SUMIFS('ФОТ, МТР, макро'!$E$4:$E$31,'ФОТ, МТР, макро'!$A$4:$A$31,$A28) -> 0 | G28: =F28 -> 0 | H28: =G28 -> 0 | I28: =H28 -> 0 | J28: =I28 -> 0 | K28: =J28 -> 0 | L28: =K28 -> 0 | M28: =L28 -> 0 | N28: =M28 -> 0 | ... Z28: =Y28 -> 0
A29: =A28 -> БС-215 | D29: расход за период | E29: шт. | G29: =G11*G28 -> 0 | H29: =H11*H28 -> 0 | I29: =I11*I28 -> 0 | J29: =J11*J28 -> 0 | K29: =K11*K28 -> 0 | L29: =L11*L28 -> 0 | M29: =M11*M28 -> 0 | N29: =N11*N28 -> 0 | ... Z29: =Z11*Z28 -> 0
A30: =A29 -> БС-215 | D30: цена | E30: тыс. руб./шт. | F30: =SUMIFS('ФОТ, МТР, макро'!$F$4:$F$31,'ФОТ, МТР, макро'!$A$4:$A$31,$A30) -> 0 | G30: =F30 -> 0 | H30: =G30 -> 0 | I30: =H30 -> 0 | J30: =I30 -> 0 | K30: =J30 -> 0 | L30: =K30 -> 0 | M30: =L30 -> 0 | N30: =M30 -> 0 | ... Z30: =Y30 -> 0
A31: =A30 -> БС-215 | D31: Расходники | E31: =E15 -> тыс. руб. | G31: =G11*G32 -> 0 | H31: =H11*H32 -> 0 | I31: =I11*I32 -> 0 | J31: =J11*J32 -> 0 | K31: =K11*K32 -> 0 | L31: =L11*L32 -> 0 | M31: =M11*M32 -> 0 | N31: =N11*N32 -> 0 | ... Z31: =Z11*Z32 -> 0
A32: =A31 -> БС-215 | D32: удельный расход | E32: руб./п. м | F32: =SUMIFS('ФОТ, МТР, макро'!$H$4:$H$31,'ФОТ, МТР, макро'!$A$4:$A$31,$A32) -> 0 | G32: =F32 -> 0 | H32: =G32 -> 0 | I32: =H32 -> 0 | J32: =I32 -> 0 | K32: =J32 -> 0 | L32: =K32 -> 0 | M32: =L32 -> 0 | N32: =M32 -> 0 | ... Z32: =Y32 -> 0
A33: =A32 -> БС-215 | C33: =SUMIFS('ФОТ, МТР, макро'!$N$4:$N$31,'ФОТ, МТР, макро'!$J$4:$J$31,$A33) -> 1 | D33: Топливо/Электроэнергия | E33: =E15 -> тыс. руб. | G33: =IF($C33=1,G34,G38) -> 16532.217 | H33: =IF($C33=1,H34,H38) -> 16484.631 | I33: =IF($C33=1,I34,I38) -> 16460.838 | J33: =IF($C33=1,J34,J38) -> 15913.597 | K33: =IF($C33=1,K34,K38) -> 16437.045 | L33: =IF($C33=1,L34,L38) -> 16318.08 | M33: =IF($C33=1,M34,M38) -> 15913.597 | N33: =IF($C33=1,N34,N38) -> 16389.459 | ... Z33: =IF($C33=1,Z34,Z38) -> 0
A34: =A33 -> БС-215 | D34: - расчет (1) | E34: =E33 -> тыс. руб. | G34: =G36*G37 -> 16532.217 | H34: =H36*H37 -> 16484.631 | I34: =I36*I37 -> 16460.838 | J34: =J36*J37 -> 15913.597 | K34: =K36*K37 -> 16437.045 | L34: =L36*L37 -> 16318.08 | M34: =M36*M37 -> 15913.597 | N34: =N36*N37 -> 16389.459 | ... Z34: =Z36*Z37 -> 0
A35: =A34 -> БС-215 | D35: удельный расход | E35: =VLOOKUP($A35,'ФОТ, МТР, макро'!$J$4:$N$31,2,FALSE) -> кг/час | F35: =SUMIFS('ФОТ, МТР, макро'!$L$4:$L$31,'ФОТ, МТР, макро'!$J$4:$J$31,$A35) -> 38.014831 | G35: =F35 -> 38.014831 | H35: =G35 -> 38.014831 | I35: =H35 -> 38.014831 | J35: =I35 -> 38.014831 | K35: =J35 -> 38.014831 | L35: =K35 -> 38.014831 | M35: =L35 -> 38.014831 | N35: =M35 -> 38.014831 | ... Z35: =Y35 -> 38.014831
A36: =A35 -> БС-215 | D36: расход за период | E36: =IF(E35="кг/час","т","тыс. кВт*ч") -> т | G36: =G$3*G10*G35/1000 -> 250.41636 | H36: =H$3*H10*H35/1000 -> 249.69556 | I36: =I$3*I10*I35/1000 -> 249.33516 | J36: =J$3*J10*J35/1000 -> 241.04602 | K36: =K$3*K10*K35/1000 -> 248.97477 | L36: =L$3*L10*L35/1000 -> 247.17278 | M36: =M$3*M10*M35/1000 -> 241.04602 | N36: =N$3*N10*N35/1000 -> 248.25397 | ... Z36: =Z$3*Z10*Z35/1000 -> 0
A37: =A36 -> БС-215 | D37: цена | E37: =IF(E36="т","тыс. руб./т","руб./кВт*ч") -> тыс. руб./т | F37: =IF(E36="т",'ФОТ, МТР, макро'!$Q$2,'ФОТ, МТР, макро'!$Q$15) -> 66.018919 | G37: =F37 -> 66.018919 | H37: =G37 -> 66.018919 | I37: =H37 -> 66.018919 | J37: =I37 -> 66.018919 | K37: =J37 -> 66.018919 | L37: =K37 -> 66.018919 | M37: =L37 -> 66.018919 | N37: =M37 -> 66.018919 | ... Z37: =Y37 -> 66.018919
A38: =A37 -> БС-215 | D38: - поставщик (2) | E38: =E34 -> тыс. руб. | G38: =G40*G41 -> 16634.489 | H38: =H40*H41 -> 16586.609 | I38: =I40*I41 -> 16562.669 | J38: =J40*J41 -> 16012.043 | K38: =K40*K41 -> 16538.728 | L38: =L40*L41 -> 16419.027 | M38: =M40*M41 -> 16012.043 | N38: =N40*N41 -> 16490.848 | ... Z38: =Z40*Z41 -> 0
A39: =A38 -> БС-215 | D39: удельный расход | E39: =E35 -> кг/час | F39: =SUMIFS('ФОТ, МТР, макро'!$M$4:$M$31,'ФОТ, МТР, макро'!$J$4:$J$31,$A39) -> 38.25 | G39: =F39 -> 38.25 | H39: =G39 -> 38.25 | I39: =H39 -> 38.25 | J39: =I39 -> 38.25 | K39: =J39 -> 38.25 | L39: =K39 -> 38.25 | M39: =L39 -> 38.25 | N39: =M39 -> 38.25 | ... Z39: =Y39 -> 38.25
A40: =A39 -> БС-215 | D40: расход за период | E40: =E36 -> т | G40: =G$3*G10*G39/1000 -> 251.96549 | H40: =H$3*H10*H39/1000 -> 251.24024 | I40: =I$3*I10*I39/1000 -> 250.87761 | J40: =J$3*J10*J39/1000 -> 242.53718 | K40: =K$3*K10*K39/1000 -> 250.51498 | L40: =L$3*L10*L39/1000 -> 248.70184 | M40: =M$3*M10*M39/1000 -> 242.53718 | N40: =N$3*N10*N39/1000 -> 249.78973 | ... Z40: =Z$3*Z10*Z39/1000 -> 0
A41: =A40 -> БС-215 | D41: цена | E41: =E37 -> тыс. руб./т | G41: =G37 -> 66.018919 | H41: =H37 -> 66.018919 | I41: =I37 -> 66.018919 | J41: =J37 -> 66.018919 | K41: =K37 -> 66.018919 | L41: =L37 -> 66.018919 | M41: =M37 -> 66.018919 | N41: =N37 -> 66.018919 | ... Z41: =Z37 -> 66.018919
A42: =A41 -> БС-215 | D42: Затраты на персонал | E42: =E15 -> тыс. руб. | G42: =G43+G44 -> 15710.122 | H42: =H43+H44 -> 15710.122 | I42: =I43+I44 -> 15710.122 | J42: =J43+J44 -> 15710.122 | K42: =K43+K44 -> 15710.122 | L42: =L43+L44 -> 15710.122 | M42: =M43+M44 -> 15710.122 | N42: =N43+N44 -> 15710.122 | ... Z42: =Z43+Z44 -> 0
A43: =A42 -> БС-215 | D43: ФОТ с отчислениями | E43: =E42 -> тыс. руб. | F43: =SUMIFS('ФОТ, МТР, макро'!$X$4:$X$31,'ФОТ, МТР, макро'!$W$4:$W$31,$A43) -> 12529.553 | G43: =IF(G11=0,0,$F43) -> 12529.553 | H43: =IF(H11=0,0,$F43) -> 12529.553 | I43: =IF(I11=0,0,$F43) -> 12529.553 | J43: =IF(J11=0,0,$F43) -> 12529.553 | K43: =IF(K11=0,0,$F43) -> 12529.553 | L43: =IF(L11=0,0,$F43) -> 12529.553 | M43: =IF(M11=0,0,$F43) -> 12529.553 | N43: =IF(N11=0,0,$F43) -> 12529.553 | ... Z43: =IF(Z11=0,0,$F43) -> 0
A44: =A43 -> БС-215 | D44: прочее | F44: =SUMIFS('ФОТ, МТР, макро'!$Y$4:$Y$31,'ФОТ, МТР, макро'!$W$4:$W$31,$A44) -> 3180.5687 | G44: =IF(G11=0,0,$F44) -> 3180.5687 | H44: =IF(H11=0,0,$F44) -> 3180.5687 | I44: =IF(I11=0,0,$F44) -> 3180.5687 | J44: =IF(J11=0,0,$F44) -> 3180.5687 | K44: =IF(K11=0,0,$F44) -> 3180.5687 | L44: =IF(L11=0,0,$F44) -> 3180.5687 | M44: =IF(M11=0,0,$F44) -> 3180.5687 | N44: =IF(N11=0,0,$F44) -> 3180.5687 | ... Z44: =IF(Z11=0,0,$F44) -> 0
A45: =A44 -> БС-215 | D45: Транспортный налог | E45: =E15 -> тыс. руб. | G45: =IF(G11=0,0,G46*G47/1000) -> 0 | H45: =IF(H11=0,0,H46*H47/1000) -> 0 | I45: =IF(I11=0,0,I46*I47/1000) -> 0 | J45: =IF(J11=0,0,J46*J47/1000) -> 0 | K45: =IF(K11=0,0,K46*K47/1000) -> 0 | L45: =IF(L11=0,0,L46*L47/1000) -> 0 | M45: =IF(M11=0,0,M46*M47/1000) -> 0 | N45: =IF(N11=0,0,N46*N47/1000) -> 0 | ... Z45: =IF(Z11=0,0,Z46*Z47/1000) -> 0
A46: =A45 -> БС-215 | D46: мощность двигателя | E46: л.с. | F46: =SUMIFS('ФОТ, МТР, макро'!$AB$4:$AB$31,'ФОТ, МТР, макро'!$W$4:$W$31,$A46) -> 0 | G46: =F46 -> 0 | H46: =G46 -> 0 | I46: =H46 -> 0 | J46: =I46 -> 0 | K46: =J46 -> 0 | L46: =K46 -> 0 | M46: =L46 -> 0 | N46: =M46 -> 0 | ... Z46: =Y46 -> 0
A47: =A46 -> БС-215 | D47: налоговая ставка | E47: руб./л.с. | F47: =SUMIFS('ФОТ, МТР, макро'!$AC$4:$AC$31,'ФОТ, МТР, макро'!$W$4:$W$31,$A47) -> 15 | G47: =F47 -> 15 | H47: =G47 -> 15 | I47: =H47 -> 15 | J47: =I47 -> 15 | K47: =J47 -> 15 | L47: =K47 -> 15 | M47: =L47 -> 15 | N47: =M47 -> 15 | ... Z47: =Y47 -> 15
A48: =A47 -> БС-215 | C48: =SUMIFS('ФОТ, МТР, макро'!$AF$4:$AF$31,'ФОТ, МТР, макро'!$W$4:$W$31,$A48) -> 19.672131 | D48: Амортизация НУ | E48: =E15 -> тыс. руб. | G48: =IF(G8<=$C49,$F53*$C48%,"ОШИБКА") -> 0 | H48: =IF(H8<=$C49,$F53*$C48%,$F53-SUM($G48:G48)) -> 0 | I48: =IF(I8<=$C49,$F53*$C48%,$F53-SUM($G48:H48)) -> 0 | J48: =IF(J8<=$C49,$F53*$C48%,$F53-SUM($G48:I48)) -> 0 | K48: =IF(K8<=$C49,$F53*$C48%,$F53-SUM($G48:J48)) -> 0 | L48: =IF(L8<=$C49,$F53*$C48%,$F53-SUM($G48:K48)) -> 0 | M48: =IF(M8<=$C49,$F53*$C48%,$F53-SUM($G48:L48)) -> 0 | N48: =IF(N8<=$C49,$F53*$C48%,$F53-SUM($G48:M48)) -> 0 | O48: =IF(O8<=$C49,$F53*$C48%,$F53-SUM($G48:N48)) -> 0 | ... Z48: =IF(Z8<=$C49,$F53*$C48%,$F53-SUM($G48:Y48)) -> 0
A49: =A48 -> БС-215 | C49: =SUMIFS('ФОТ, МТР, макро'!$AE$4:$AE$31,'ФОТ, МТР, макро'!$W$4:$W$31,$A49)/12 -> 5.0833333 | D49: Налогооблагаемая база (по налогу на прибыль) | E49: =E15 -> тыс. руб. | G49: =SUM(G16,G21,G23,G27,G31,G33,G42,G45,G48) -> 43855.66 | H49: =SUM(H16,H21,H23,H27,H31,H33,H42,H45,H48) -> 44184.714 | I49: =SUM(I16,I21,I23,I27,I31,I33,I42,I45,I48) -> 49734.315 | J49: =SUM(J16,J21,J23,J27,J31,J33,J42,J45,J48) -> 55442.308 | K49: =SUM(K16,K21,K23,K27,K31,K33,K42,K45,K48) -> 45868.76 | L49: =SUM(L16,L21,L23,L27,L31,L33,L42,L45,L48) -> 50899.603 | M49: =SUM(M16,M21,M23,M27,M31,M33,M42,M45,M48) -> 51345.868 | N49: =SUM(N16,N21,N23,N27,N31,N33,N42,N45,N48) -> 51017.389 | ... Z49: =SUM(Z16,Z21,Z23,Z27,Z31,Z33,Z42,Z45,Z48) -> 0
A50: =A49 -> БС-215 | D50: Налог на прибыль | E50: =E15 -> тыс. руб. | G50: =-G49*'ФОТ, МТР, макро'!AJ$12 -> -10963.915 | H50: =-H49*'ФОТ, МТР, макро'!AK$12 -> -11046.178 | I50: =-I49*'ФОТ, МТР, макро'!AL$12 -> -12433.579 | J50: =-J49*'ФОТ, МТР, макро'!AM$12 -> -13860.577 | K50: =-K49*'ФОТ, МТР, макро'!AN$12 -> -11467.19 | L50: =-L49*'ФОТ, МТР, макро'!AO$12 -> -12724.901 | M50: =-M49*'ФОТ, МТР, макро'!AP$12 -> -12836.467 | N50: =-N49*'ФОТ, МТР, макро'!AQ$12 -> -12754.347 | ... Z50: =-Z49*'ФОТ, МТР, макро'!BC$12 -> 0
A51: =A50 -> БС-215
A52: =A51 -> БС-215 | D52: Инвестиционный денежный поток | E52: =E15 -> тыс. руб. | F52: =F53 -> 0 | G52: =G53 -> 0 | H52: =H53 -> 0 | I52: =I53 -> 0 | J52: =J53 -> 0 | K52: =K53 -> 0 | L52: =L53 -> 0 | M52: =M53 -> 0 | ... Z52: =Z53 -> 0
A53: =A52 -> БС-215 | D53: Буровой станок | E53: =E52 -> тыс. руб. | F53: =SUMIFS(Свод_215_диз!$D$33:$P$33,Свод_215_диз!$D$19:$P$19,$A53) -> 0
A54: =A53 -> БС-215
A55: =A54 -> БС-215 | D55: Денежный поток | E55: =E15 -> тыс. руб. | F55: =F15+F52 -> 0 | G55: =G15+G52 -> 32891.745 | H55: =H15+H52 -> 33138.535 | I55: =I15+I52 -> 37300.736 | J55: =J15+J52 -> 41581.731 | K55: =K15+K52 -> 34401.57 | L55: =L15+L52 -> 38174.703 | M55: =M15+M52 -> 38509.401 | ... Z55: =Z15+Z52 -> 0
A56: =A55 -> БС-215 | D56: Дисконтированный операционный денежный поток | E56: =E55 -> тыс. руб. | G56: =G15*'ФОТ, МТР, макро'!AJ$14 -> 29367.63 | H56: =H15*'ФОТ, МТР, макро'!AK$14 -> 26417.838 | I56: =I15*'ФОТ, МТР, макро'!AL$14 -> 26549.927 | J56: =J15*'ФОТ, МТР, макро'!AM$14 -> 26425.942 | K56: =K15*'ФОТ, МТР, макро'!AN$14 -> 19520.374 | L56: =L15*'ФОТ, МТР, макро'!AO$14 -> 19340.492 | M56: =M15*'ФОТ, МТР, макро'!AP$14 -> 17419.697 | N56: =N15*'ФОТ, МТР, макро'!AQ$14 -> 15453.801 | ... Z56: =Z15*'ФОТ, МТР, макро'!BC$14 -> 0
A57: =A56 -> БС-215 | D57: =D16 -> ТО, ТР, ППР | E57: =E56 -> тыс. руб. | G57: =G16*'ФОТ, МТР, макро'!AJ$14 -> 10369.037 | H57: =H16*'ФОТ, МТР, макро'!AK$14 -> 9558.3233 | I57: =I16*'ФОТ, МТР, макро'!AL$14 -> 12501.249 | J57: =J16*'ФОТ, МТР, макро'!AM$14 -> 15137.144 | K57: =K16*'ФОТ, МТР, макро'!AN$14 -> 7786 | L57: =L16*'ФОТ, МТР, макро'!AO$14 -> 9560.8394 | M57: =M16*'ФОТ, МТР, макро'!AP$14 -> 8921.2986 | N57: =N16*'ФОТ, МТР, макро'!AQ$14 -> 7640.5854 | ... Z57: =Z16*'ФОТ, МТР, макро'!BC$14 -> 0
A58: =A57 -> БС-215 | D58: =D21 -> Смазочные | E58: =E57 -> тыс. руб. | G58: =G21*'ФОТ, МТР, макро'!AJ$14 -> 0 | H58: =H21*'ФОТ, МТР, макро'!AK$14 -> 0 | I58: =I21*'ФОТ, МТР, макро'!AL$14 -> 0 | J58: =J21*'ФОТ, МТР, макро'!AM$14 -> 0 | K58: =K21*'ФОТ, МТР, макро'!AN$14 -> 0 | L58: =L21*'ФОТ, МТР, макро'!AO$14 -> 0 | M58: =M21*'ФОТ, МТР, макро'!AP$14 -> 0 | N58: =N21*'ФОТ, МТР, макро'!AQ$14 -> 0 | ... Z58: =Z21*'ФОТ, МТР, макро'!BC$14 -> 0
A59: =A58 -> БС-215 | D59: =D23 -> Долота | E59: =E58 -> тыс. руб. | G59: =G23*'ФОТ, МТР, макро'!AJ$14 -> 0 | H59: =H23*'ФОТ, МТР, макро'!AK$14 -> 0 | I59: =I23*'ФОТ, МТР, макро'!AL$14 -> 0 | J59: =J23*'ФОТ, МТР, макро'!AM$14 -> 0 | K59: =K23*'ФОТ, МТР, макро'!AN$14 -> 0 | L59: =L23*'ФОТ, МТР, макро'!AO$14 -> 0 | M59: =M23*'ФОТ, МТР, макро'!AP$14 -> 0 | N59: =N23*'ФОТ, МТР, макро'!AQ$14 -> 0 | ... Z59: =Z23*'ФОТ, МТР, макро'!BC$14 -> 0
A60: =A59 -> БС-215 | D60: =D27 -> Штанги буровые | E60: =E59 -> тыс. руб. | G60: =G27*'ФОТ, МТР, макро'!AJ$14 -> 0 | H60: =H27*'ФОТ, МТР, макро'!AK$14 -> 0 | I60: =I27*'ФОТ, МТР, макро'!AL$14 -> 0 | J60: =J27*'ФОТ, МТР, макро'!AM$14 -> 0 | K60: =K27*'ФОТ, МТР, макро'!AN$14 -> 0 | L60: =L27*'ФОТ, МТР, макро'!AO$14 -> 0 | M60: =M27*'ФОТ, МТР, макро'!AP$14 -> 0 | N60: =N27*'ФОТ, МТР, макро'!AQ$14 -> 0 | ... Z60: =Z27*'ФОТ, МТР, макро'!BC$14 -> 0
A61: =A60 -> БС-215 | D61: =D31 -> Расходники | E61: =E60 -> тыс. руб. | G61: =G31*'ФОТ, МТР, макро'!AJ$14 -> 0 | H61: =H31*'ФОТ, МТР, макро'!AK$14 -> 0 | I61: =I31*'ФОТ, МТР, макро'!AL$14 -> 0 | J61: =J31*'ФОТ, МТР, макро'!AM$14 -> 0 | K61: =K31*'ФОТ, МТР, макро'!AN$14 -> 0 | L61: =L31*'ФОТ, МТР, макро'!AO$14 -> 0 | M61: =M31*'ФОТ, МТР, макро'!AP$14 -> 0 | N61: =N31*'ФОТ, МТР, макро'!AQ$14 -> 0 | ... Z61: =Z31*'ФОТ, МТР, макро'!BC$14 -> 0
A62: =A61 -> БС-215 | D62: =D33 -> Топливо/Электроэнергия | E62: =E61 -> тыс. руб. | G62: =G33*'ФОТ, МТР, макро'!AJ$14 -> 14760.908 | H62: =H33*'ФОТ, МТР, макро'!AK$14 -> 13141.447 | I62: =I33*'ФОТ, МТР, макро'!AL$14 -> 11716.499 | J62: =J33*'ФОТ, МТР, макро'!AM$14 -> 10113.379 | K62: =K33*'ФОТ, МТР, макро'!AN$14 -> 9326.8208 | L62: =L33*'ФОТ, МТР, макро'!AO$14 -> 8267.247 | M62: =M33*'ФОТ, МТР, макро'!AP$14 -> 7198.5033 | N62: =N33*'ФОТ, МТР, макро'!AQ$14 -> 6619.4275 | ... Z62: =Z33*'ФОТ, МТР, макро'!BC$14 -> 0
A63: =A62 -> БС-215 | D63: =D42 -> Затраты на персонал | E63: =E62 -> тыс. руб. | G63: =G42*'ФОТ, МТР, макро'!AJ$14 -> 14026.895 | H63: =H42*'ФОТ, МТР, макро'!AK$14 -> 12524.013 | I63: =I42*'ФОТ, МТР, макро'!AL$14 -> 11182.155 | J63: =J42*'ФОТ, МТР, макро'!AM$14 -> 9984.0666 | K63: =K42*'ФОТ, МТР, макро'!AN$14 -> 8914.3452 | L63: =L42*'ФОТ, МТР, макро'!AO$14 -> 7959.2368 | M63: =M42*'ФОТ, МТР, макро'!AP$14 -> 7106.4614 | N63: =N42*'ФОТ, МТР, макро'!AQ$14 -> 6345.0548 | ... Z63: =Z42*'ФОТ, МТР, макро'!BC$14 -> 0
A64: =A63 -> БС-215 | D64: =D45 -> Транспортный налог | E64: =E63 -> тыс. руб. | G64: =G45*'ФОТ, МТР, макро'!AJ$14 -> 0 | H64: =H45*'ФОТ, МТР, макро'!AK$14 -> 0 | I64: =I45*'ФОТ, МТР, макро'!AL$14 -> 0 | J64: =J45*'ФОТ, МТР, макро'!AM$14 -> 0 | K64: =K45*'ФОТ, МТР, макро'!AN$14 -> 0 | L64: =L45*'ФОТ, МТР, макро'!AO$14 -> 0 | M64: =M45*'ФОТ, МТР, макро'!AP$14 -> 0 | N64: =N45*'ФОТ, МТР, макро'!AQ$14 -> 0 | ... Z64: =Z45*'ФОТ, МТР, макро'!BC$14 -> 0
A65: =A64 -> БС-215 | D65: =D50 -> Налог на прибыль | E65: =E64 -> тыс. руб. | G65: =G50*'ФОТ, МТР, макро'!AJ$14 -> -9789.2099 | H65: =H50*'ФОТ, МТР, макро'!AK$14 -> -8805.9459 | I65: =I50*'ФОТ, МТР, макро'!AL$14 -> -8849.9757 | J65: =J50*'ФОТ, МТР, макро'!AM$14 -> -8808.6473 | K65: =K50*'ФОТ, МТР, макро'!AN$14 -> -6506.7915 | L65: =L50*'ФОТ, МТР, макро'!AO$14 -> -6446.8308 | M65: =M50*'ФОТ, МТР, макро'!AP$14 -> -5806.5658 | N65: =N50*'ФОТ, МТР, макро'!AQ$14 -> -5151.2669 | ... Z65: =Z50*'ФОТ, МТР, макро'!BC$14 -> 0
A66: =A65 -> БС-215 | D66: проверка полноты | G66: =G56-SUM(G57:G65) -> 0 | H66: =H56-SUM(H57:H65) -> 0 | I66: =I56-SUM(I57:I65) -> 0 | J66: =J56-SUM(J57:J65) -> 0 | K66: =K56-SUM(K57:K65) -> 0 | L66: =L56-SUM(L57:L65) -> 0 | M66: =M56-SUM(M57:M65) -> 0 | N66: =N56-SUM(N57:N65) -> 0 | ... Z66: =Z56-SUM(Z57:Z65) -> 0
A67: =A66 -> БС-215 | D67: Кумулятивный дисконтированный операционный денежный поток | E67: =E56 -> тыс. руб. | F67: =F56 -> 0 | G67: =F67+G56 -> 29367.63 | H67: =G67+H56 -> 55785.467 | I67: =H67+I56 -> 82335.394 | J67: =I67+J56 -> 108761.34 | K67: =J67+K56 -> 128281.71 | L67: =K67+L56 -> 147622.2 | M67: =L67+M56 -> 165041.9 | N67: =M67+N56 -> 180495.7 | ... Z67: =Y67+Z56 -> 227137.34
A68: =A67 -> БС-215 | D68: =D57 -> ТО, ТР, ППР | E68: =E57 -> тыс. руб. | F68: =F57 -> 0 | G68: =F68+G57 -> 10369.037 | H68: =G68+H57 -> 19927.36 | I68: =H68+I57 -> 32428.609 | J68: =I68+J57 -> 47565.753 | K68: =J68+K57 -> 55351.753 | L68: =K68+L57 -> 64912.592 | M68: =L68+M57 -> 73833.891 | N68: =M68+N57 -> 81474.476 | ... Z68: =Y68+Z57 -> 104440.97
A69: =A68 -> БС-215 | D69: =D58 -> Смазочные | E69: =E58 -> тыс. руб. | F69: =F58 -> 0 | G69: =F69+G58 -> 0 | H69: =G69+H58 -> 0 | I69: =H69+I58 -> 0 | J69: =I69+J58 -> 0 | K69: =J69+K58 -> 0 | L69: =K69+L58 -> 0 | M69: =L69+M58 -> 0 | N69: =M69+N58 -> 0 | ... Z69: =Y69+Z58 -> 0
A70: =A69 -> БС-215 | D70: =D59 -> Долота | E70: =E59 -> тыс. руб. | F70: =F59 -> 0 | G70: =F70+G59 -> 0 | H70: =G70+H59 -> 0 | I70: =H70+I59 -> 0 | J70: =I70+J59 -> 0 | K70: =J70+K59 -> 0 | L70: =K70+L59 -> 0 | M70: =L70+M59 -> 0 | N70: =M70+N59 -> 0 | ... Z70: =Y70+Z59 -> 0
A71: =A70 -> БС-215 | D71: =D60 -> Штанги буровые | E71: =E60 -> тыс. руб. | F71: =F60 -> 0 | G71: =F71+G60 -> 0 | H71: =G71+H60 -> 0 | I71: =H71+I60 -> 0 | J71: =I71+J60 -> 0 | K71: =J71+K60 -> 0 | L71: =K71+L60 -> 0 | M71: =L71+M60 -> 0 | N71: =M71+N60 -> 0 | ... Z71: =Y71+Z60 -> 0
A72: =A71 -> БС-215 | D72: =D61 -> Расходники | E72: =E61 -> тыс. руб. | F72: =F61 -> 0 | G72: =F72+G61 -> 0 | H72: =G72+H61 -> 0 | I72: =H72+I61 -> 0 | J72: =I72+J61 -> 0 | K72: =J72+K61 -> 0 | L72: =K72+L61 -> 0 | M72: =L72+M61 -> 0 | N72: =M72+N61 -> 0 | ... Z72: =Y72+Z61 -> 0
A73: =A72 -> БС-215 | D73: =D62 -> Топливо/Электроэнергия | E73: =E62 -> тыс. руб. | F73: =F62 -> 0 | G73: =F73+G62 -> 14760.908 | H73: =G73+H62 -> 27902.355 | I73: =H73+I62 -> 39618.855 | J73: =I73+J62 -> 49732.234 | K73: =J73+K62 -> 59059.054 | L73: =K73+L62 -> 67326.301 | M73: =L73+M62 -> 74524.805 | N73: =M73+N62 -> 81144.232 | ... Z73: =Y73+Z62 -> 101094.43
A74: =A73 -> БС-215 | D74: =D63 -> Затраты на персонал | E74: =E63 -> тыс. руб. | F74: =F63 -> 0 | G74: =F74+G63 -> 14026.895 | H74: =G74+H63 -> 26550.908 | I74: =H74+I63 -> 37733.063 | J74: =I74+J63 -> 47717.129 | K74: =J74+K63 -> 56631.474 | L74: =K74+L63 -> 64590.711 | M74: =L74+M63 -> 71697.173 | N74: =M74+N63 -> 78042.227 | ... Z74: =Y74+Z63 -> 97314.375
A75: =A74 -> БС-215 | D75: =D64 -> Транспортный налог | E75: =E64 -> тыс. руб. | F75: =F64 -> 0 | G75: =F75+G64 -> 0 | H75: =G75+H64 -> 0 | I75: =H75+I64 -> 0 | J75: =I75+J64 -> 0 | K75: =J75+K64 -> 0 | L75: =K75+L64 -> 0 | M75: =L75+M64 -> 0 | N75: =M75+N64 -> 0 | ... Z75: =Y75+Z64 -> 0
A76: =A75 -> БС-215 | D76: =D65 -> Налог на прибыль | E76: =E65 -> тыс. руб. | F76: =F65 -> 0 | G76: =F76+G65 -> -9789.2099 | H76: =G76+H65 -> -18595.156 | I76: =H76+I65 -> -27445.131 | J76: =I76+J65 -> -36253.779 | K76: =J76+K65 -> -42760.57 | L76: =K76+L65 -> -49207.401 | M76: =L76+M65 -> -55013.967 | N76: =M76+N65 -> -60165.234 | ... Z76: =Y76+Z65 -> -75712.445
A77: =A76 -> БС-215
A78: =A77 -> БС-215 | D78: Дисконтированный инвестиционный поток | E78: =E55 -> тыс. руб. | F78: =F52*'ФОТ, МТР, макро'!AI$14 -> 0 | G78: =G52*'ФОТ, МТР, макро'!AJ$14 -> 0 | H78: =H52*'ФОТ, МТР, макро'!AK$14 -> 0 | I78: =I52*'ФОТ, МТР, макро'!AL$14 -> 0 | J78: =J52*'ФОТ, МТР, макро'!AM$14 -> 0 | K78: =K52*'ФОТ, МТР, макро'!AN$14 -> 0 | L78: =L52*'ФОТ, МТР, макро'!AO$14 -> 0 | M78: =M52*'ФОТ, МТР, макро'!AP$14 -> 0 | ... Z78: =Z52*'ФОТ, МТР, макро'!BC$14 -> 0
A79: =A78 -> БС-215 | D79: =D53 -> Буровой станок | E79: =E78 -> тыс. руб. | F79: =F53*'ФОТ, МТР, макро'!AI$14 -> 0 | G79: =G53*'ФОТ, МТР, макро'!AJ$14 -> 0 | H79: =H53*'ФОТ, МТР, макро'!AK$14 -> 0 | I79: =I53*'ФОТ, МТР, макро'!AL$14 -> 0 | J79: =J53*'ФОТ, МТР, макро'!AM$14 -> 0 | K79: =K53*'ФОТ, МТР, макро'!AN$14 -> 0 | L79: =L53*'ФОТ, МТР, макро'!AO$14 -> 0 | M79: =M53*'ФОТ, МТР, макро'!AP$14 -> 0 | ... Z79: =Z53*'ФОТ, МТР, макро'!BC$14 -> 0
A80: =A79 -> БС-215 | D80: проверка полноты | F80: =F78-F79 -> 0 | G80: =G78-G79 -> 0 | H80: =H78-H79 -> 0 | I80: =I78-I79 -> 0 | J80: =J78-J79 -> 0 | K80: =K78-K79 -> 0 | L80: =L78-L79 -> 0 | M80: =M78-M79 -> 0 | ... Z80: =Z78-Z79 -> 0
A81: =A80 -> БС-215 | D81: Кумулятивный инвестиционный поток | E81: =E78 -> тыс. руб. | F81: =F78 -> 0 | G81: =F81+G78 -> 0 | H81: =G81+H78 -> 0 | I81: =H81+I78 -> 0 | J81: =I81+J78 -> 0 | K81: =J81+K78 -> 0 | L81: =K81+L78 -> 0 | M81: =L81+M78 -> 0 | N81: =M81+N78 -> 0 | ... Z81: =Y81+Z78 -> 0
A82: =A81 -> БС-215 | D82: =D79 -> Буровой станок | E82: =E79 -> тыс. руб. | F82: =F79 -> 0 | G82: =F82+G79 -> 0 | H82: =G82+H79 -> 0 | I82: =H82+I79 -> 0 | J82: =I82+J79 -> 0 | K82: =J82+K79 -> 0 | L82: =K82+L79 -> 0 | M82: =L82+M79 -> 0 | N82: =M82+N79 -> 0 | ... Z82: =Y82+Z79 -> 0
A83: =A82 -> БС-215
A84: =A83 -> БС-215 | D84: Дисконтированный денежный поток | E84: =E55 -> тыс. руб. | F84: =F55*'ФОТ, МТР, макро'!AI$14 -> 0 | G84: =G55*'ФОТ, МТР, макро'!AJ$14 -> 29367.63 | H84: =H55*'ФОТ, МТР, макро'!AK$14 -> 26417.838 | I84: =I55*'ФОТ, МТР, макро'!AL$14 -> 26549.927 | J84: =J55*'ФОТ, МТР, макро'!AM$14 -> 26425.942 | K84: =K55*'ФОТ, МТР, макро'!AN$14 -> 19520.374 | L84: =L55*'ФОТ, МТР, макро'!AO$14 -> 19340.492 | M84: =M55*'ФОТ, МТР, макро'!AP$14 -> 17419.697 | ... Z84: =Z55*'ФОТ, МТР, макро'!BC$14 -> 0
A85: =A84 -> БС-215 | D85: Кумулятивный дисконтированный денежный поток | E85: =E84 -> тыс. руб. | F85: =F84 -> 0 | G85: =F85+G84 -> 29367.63 | H85: =G85+H84 -> 55785.467 | I85: =H85+I84 -> 82335.394 | J85: =I85+J84 -> 108761.34 | K85: =J85+K84 -> 128281.71 | L85: =K85+L84 -> 147622.2 | M85: =L85+M84 -> 165041.9 | N85: =M85+N84 -> 180495.7 | ... Z85: =Y85+Z84 -> 227137.34
A86: =A85 -> БС-215
