Workbook
Name _____NAY14: #REF!
Name _____PDR11: #REF!
Name _____PDR13: '[1]#ССЫЛКА'!$I$5
Name _____PDR14: #REF!
Name _____PDR20: #REF!
Name _____PDR9: #REF!
Name ____NAU11: #REF!
Name ____NAU13: #REF!
Name ____NAU14: #REF!
Name ____NAU20: #REF!
Name ____NAY14: #REF!
Name ____PDR11: #REF!
Name ____PDR13: '[2]#ССЫЛКА'!$I$5
Name ____PDR14: #REF!
Name ____PDR20: #REF!
Name ____PDR9: #REF!
Name ___NAU11: #REF!
Name ___NAU13: #REF!
Name ___NAU14: #REF!
Name ___NAU20: #REF!
Name ___NAY14: #REF!
Name ___PDR11: #REF!
Name ___PDR13: '[1]#ССЫЛКА'!$I$5
Name ___PDR14: #REF!
Name ___PDR20: #REF!
Name ___PDR9: #REF!
Name __bas186: [6]Stocks!#REF!
Name __bas187: [6]Stocks!#REF!
Name __bas188: [6]Stocks!#REF!
Name __bas189: [6]Stocks!#REF!
Name __bas190: [6]Stocks!#REF!
Name __bas286: [6]Stocks!#REF!
Name __bas287: [6]Stocks!#REF!
Name __bas288: [6]Stocks!#REF!
Name __bas289: [6]Stocks!#REF!
Name __bas290: [6]Stocks!#REF!
Name __bas386: [6]Stocks!#REF!
Name __bas387: [6]Stocks!#REF!
Name __bas388: [6]Stocks!#REF!
Name __bas389: [6]Stocks!#REF!
Name __bas486: [6]Stocks!#REF!
Name __bas487: [6]Stocks!#REF!
Name __bas488: [6]Stocks!#REF!
Name __bas489: [6]Stocks!#REF!
Name __cap01: '[6]Mine Capacity'!#REF!
Name __cap02: '[6]Mine Capacity'!#REF!
Name __cap03: '[6]Mine Capacity'!#REF!
Name __cap04: '[6]Mine Capacity'!#REF!
Name __cap05: '[6]Mine Capacity'!#REF!
Name __cap06: '[6]Mine Capacity'!#REF!
Name __cap07: '[6]Mine Capacity'!#REF!
Name __cap20: '[6]Mine Capacity'!#REF!
Name __cap90: '[6]Mine Capacity'!#REF!
Name __cap91: '[6]Mine Capacity'!#REF!
Name __cap92: '[6]Mine Capacity'!#REF!
Name __cap93: '[6]Mine Capacity'!#REF!
Name __cap94: '[6]Mine Capacity'!#REF!
Name __cap95: '[6]Mine Capacity'!#REF!
Name __cap96: '[6]Mine Capacity'!#REF!
Name __cap97: '[6]Mine Capacity'!#REF!

Sheet 1. Сводная_аннуитеты
B2: версия "производство"
A4: Ранжирование общих аннуитетов экскаваторов | E4: Ранжирование по стоимости оборудования
A5: № | B5: Экскаватор | C5: Аннуитет, руб/м3 | E5: № | F5: Экскаватор | H5: Цена за ед., тыс.руб.
A6: 1 | B6: =VLOOKUP(C6,$B$54:$D$63,3,FALSE) -> Komatsu PC2000-11R Огунвэй | C6: =SMALL($D$49:$M$49,A6) -> 46.005042 | E6: 1 | F6: =VLOOKUP(H6,$C$54:$D$63,2,FALSE) -> TZCO TZ2000 Дзикай | H6: =SMALL($D$31:$M$31,E6) -> 172584.72
A7: =A6+1 -> 2 | B7: =VLOOKUP(C7,$B$54:$D$63,3,FALSE) -> Komatsu PC2000-11R ИСТК | C7: =SMALL($D$49:$M$49,A7) -> 48.838068 | E7: =E6+1 -> 2 | F7: =VLOOKUP(H7,$C$54:$D$63,2,FALSE) -> Shantui SE2000LCW Строймпорттехника | H7: =SMALL($D$31:$M$31,E7) -> 187624.79
A8: =A7+1 -> 3 | B8: =VLOOKUP(C8,$B$54:$D$63,3,FALSE) -> Zoomlion ZE2000G ОРИКС | C8: =SMALL($D$49:$M$49,A8) -> 49.38578 | E8: =E7+1 -> 3 | F8: =VLOOKUP(H8,$C$54:$D$63,2,FALSE) -> Estar ESE2000 ГПБ Комплект | H8: =SMALL($D$31:$M$31,E8) -> 193158.57
A9: =A8+1 -> 4 | B9: =VLOOKUP(C9,$B$54:$D$63,3,FALSE) -> Komatsu PC2000-11R Mining Solutions | C9: =SMALL($D$49:$M$49,A9) -> 51.164872 | E9: =E8+1 -> 4 | F9: =VLOOKUP(H9,$C$54:$D$63,2,FALSE) -> Sany SY2000 АСТ | H9: =SMALL($D$31:$M$31,E9) -> 219895.6
A10: =A9+1 -> 5 | B10: =VLOOKUP(C10,$B$54:$D$63,3,FALSE) -> Shantui SE2000LCW Строймпорттехника | C10: =SMALL($D$49:$M$49,A10) -> 52.357275 | E10: =E9+1 -> 5 | F10: =VLOOKUP(H10,$C$54:$D$63,2,FALSE) -> Komatsu PC2000-11R Огунвэй | H10: =SMALL($D$31:$M$31,E10) -> 222029.35
A11: =A10+1 -> 6 | B11: =VLOOKUP(C11,$B$54:$D$63,3,FALSE) -> Hitachi EX2000 Майнтек | C11: =SMALL($D$49:$M$49,A11) -> 53.489754 | E11: =E10+1 -> 6 | F11: =VLOOKUP(H11,$C$54:$D$63,2,FALSE) -> Zoomlion ZE2000G ОРИКС | H11: =SMALL($D$31:$M$31,E11) -> 225581.68
A12: =A11+1 -> 7 | B12: =VLOOKUP(C12,$B$54:$D$63,3,FALSE) -> Estar ESE2000 ГПБ Комплект | C12: =SMALL($D$49:$M$49,A12) -> 55.110917 | E12: =E11+1 -> 7 | F12: =VLOOKUP(H12,$C$54:$D$63,2,FALSE) -> XCMG LYR 2000 Огунвэй | H12: =SMALL($D$31:$M$31,E12) -> 231366.47
A13: =A12+1 -> 8 | B13: =VLOOKUP(C13,$B$54:$D$63,3,FALSE) -> Sany SY2000 АСТ | C13: =SMALL($D$49:$M$49,A13) -> 58.703686 | E13: =E12+1 -> 8 | F13: =VLOOKUP(H13,$C$54:$D$63,2,FALSE) -> Hitachi EX2000 Майнтек | H13: =SMALL($D$31:$M$31,E13) -> 243602.56
A14: =A13+1 -> 9 | B14: =VLOOKUP(C14,$B$54:$D$63,3,FALSE) -> #NUM! | C14: =SMALL($D$49:$M$49,A14) -> #NUM! | E14: =E13+1 -> 9 | F14: =VLOOKUP(H14,$C$54:$D$63,2,FALSE) -> Komatsu PC2000-11R ИСТК | H14: =SMALL($D$31:$M$31,E14) -> 258952.52
A15: =A14+1 -> 10 | B15: =VLOOKUP(C15,$B$54:$D$63,3,FALSE) -> #NUM! | C15: =SMALL($D$49:$M$49,A15) -> #NUM! | E15: =E14+1 -> 10 | F15: =VLOOKUP(H15,$C$54:$D$63,2,FALSE) -> Komatsu PC2000-11R Mining Solutions | H15: =SMALL($D$31:$M$31,E15) -> 289278.04
F17: в верхней части только из-за ковша | I17: не дали данные по ремонтам, только ТО. В мире - 3 ед., 2 - из них на ОПИ | J17: не предоставили данные для расчета, приравнены к PC2000 ИСТК. Поставка из Китая - 15 мес!!! | K17: не предоставили данные для расчета
A18: № п/п | B18: Параметры | C18: Ед.изм. | D18: Komatsu PC2000-11R Mining Solutions | E18: Komatsu PC2000-11R ИСТК | F18: Zoomlion ZE2000G ОРИКС | G18: Sany SY2000 АСТ | H18: Shantui SE2000LCW Строймпорттехника | I18: TZCO TZ2000 Дзикай | J18: Komatsu PC2000-11R Огунвэй | K18: XCMG LYR 2000 Огунвэй | L18: Hitachi EX2000 Майнтек | M18: Estar ESE2000 ГПБ Комплект | N18: Примечания
A19: 1 | B19: Производственные показатели
A20: =A19+1 -> 2 | B20: Геометрическая емкость ковша | C20: м3 | D20: ='3. Час.произв.'!D6 -> 10 | E20: ='3. Час.произв.'!E6 -> 10 | F20: ='3. Час.произв.'!F6 -> 12 | G20: ='3. Час.произв.'!G6 -> 10 | H20: ='3. Час.произв.'!H6 -> 9.6 | I20: ='3. Час.произв.'!I6 -> 12 | J20: ='3. Час.произв.'!J6 -> 10 | L20: ='3. Час.произв.'!L6 -> 9.5 | M20: ='3. Час.произв.'!M6 -> 10
A21: =A20+1 -> 3 | B21: Емкость ковша с шапкой | C21: м3 | D21: ='3. Час.произв.'!D7 -> 12 | E21: ='3. Час.произв.'!E7 -> 12 | F21: ='3. Час.произв.'!F7 -> 13 | G21: ='3. Час.произв.'!G7 -> 12 | H21: ='3. Час.произв.'!H7 -> 12 | I21: ='3. Час.произв.'!I7 -> 13.5 | J21: ='3. Час.произв.'!J7 -> 12 | L21: ='3. Час.произв.'!L7 -> 12 | M21: ='3. Час.произв.'!M7 -> 12
A22: =A21+1 -> 4 | B22: Время цикла | C22: сек | D22: ='3. Час.произв.'!D19 -> 37.3 | E22: ='3. Час.произв.'!E19 -> 37.3 | F22: ='3. Час.произв.'!F19 -> 37.3 | G22: ='3. Час.произв.'!G19 -> 37.3 | H22: ='3. Час.произв.'!H19 -> 37.3 | I22: ='3. Час.произв.'!I19 -> 37.3 | J22: ='3. Час.произв.'!J19 -> 37.3 | L22: ='3. Час.произв.'!L19 -> 37.3 | M22: ='3. Час.произв.'!M19 -> 37.3
A23: =A22+1 -> 5 | B23: КТГ экскаватора (средний за период эксплуатации) | C23: коэфф. | D23: ='2. Произв-сть экскаваторов'!N18 -> 0.79038201 | E23: ='2. Произв-сть экскаваторов'!N19 -> 0.79038201 | F23: ='2. Произв-сть экскаваторов'!N20 -> 0.72097116 | G23: ='2. Произв-сть экскаваторов'!N21 -> 0.72097116 | H23: ='2. Произв-сть экскаваторов'!N22 -> 0.72097116 | I23: ='2. Произв-сть экскаваторов'!N23 -> 0.72097116 | J23: ='2. Произв-сть экскаваторов'!N24 -> 0.79038201 | L23: ='2. Произв-сть экскаваторов'!N26 -> 0.72245288 | M23: ='2. Произв-сть экскаваторов'!N27 -> 0.72097116
A24: =A23+1 -> 6 | B24: Производительность нового экск. (средняя за период экспл.) | C24: тыс.м3 | D24: ='2. Произв-сть экскаваторов'!N83 -> 1894.8939 | E24: ='2. Произв-сть экскаваторов'!N84 -> 1894.8939 | F24: ='2. Произв-сть экскаваторов'!N85 -> 2118.7596 | G24: ='2. Произв-сть экскаваторов'!N86 -> 1728.4893 | H24: ='2. Произв-сть экскаваторов'!N87 -> 1728.4893 | I24: ='2. Произв-сть экскаваторов'!N88 -> 2118.7596 | J24: ='2. Произв-сть экскаваторов'!N89 -> 1894.8939 | L24: ='2. Произв-сть экскаваторов'!N91 -> 1732.114 | M24: ='2. Произв-сть экскаваторов'!N92 -> 1728.4893
A25: =A24+1 -> 7 | B25: Двигатель | C25: марка | D25: Кomatsu SAA12V140E[1]3 12 - 140 x 165 30.48 | E25: Komatsu SAA12V140E-7 12 - 140 x 165 30.48 | F25: Cummins QST30 | G25: Cummins QSK38 | H25: Weichai 12M33 | I25: Weichai 12M33 | L25: Cummins QST30-C | M25: Cummins QSK38
A26: =A25+1 -> 8 | B26: Расход ДТ - от поставщика | D26: ='PC2000-8 MS'!D50 -> 80 литров в час | E26: 105 литров в час | F26: 0,286 кг/м3 | G26: ='Sany АСТ'!$D$38 -> 0,19 гр/м3 | H26: 120 л/час = 102 кг/час | I26: 60 кг/час | L26: 129 кг/ч | M26: 110-140 л/час. Среднее - 125 л/час = 106 кг/час
A27: =A26+1 -> 9 | B27: Расход ДТ - в расчете | C27: значение | D27: ='4. Аннуитеты'!D42 -> 88.464215 | E27: ='4. Аннуитеты'!D183 -> 88.464215 | F27: ='4. Аннуитеты'!D330 -> 0.286 | G27: ='4. Аннуитеты'!D471 -> 0.19 | H27: ='4. Аннуитеты'!D606 -> 102 | J27: ='4. Аннуитеты'!$D$888 -> 88.464215 | L27: ='4. Аннуитеты'!D1170 -> 129.2425 | M27: ='4. Аннуитеты'!D1311 -> 106.25
A28: =A27+1 -> 10 | C28: ед.изм. | D28: ='4. Аннуитеты'!C42 -> кг/час | E28: ='4. Аннуитеты'!C183 -> кг/час | F28: ='4. Аннуитеты'!C330 -> кг/м3 | G28: ='4. Аннуитеты'!C471 -> кг/м3 | H28: ='4. Аннуитеты'!C606 -> кг/час | J28: ='4. Аннуитеты'!C888 -> кг/час | L28: ='4. Аннуитеты'!C1170 -> кг/час | M28: ='4. Аннуитеты'!C1311 -> кг/час
A29: =A28+1 -> 11 | C29: комментарий | D29: факт КБЕ по PC2000 | E29: факт КБЕ по PC2000 | F29: от поставщика | G29: от поставщика | H29: от поставщика | J29: факт КБЕ по PC2000 | L29: от поставщика | M29: поставщик
A30: =A29+1 -> 12 | B30: Срок эксплуатации | C30: лет | D30: 10 | E30: 10 | F30: 10 | G30: 10 | H30: 10 | I30: 10 | J30: 10 | L30: 10 | M30: 10
A31: =A30+1 -> 13 | B31: Стоимость экскаватора | C31: тыс.руб | D31: =SUM(D34:D35) -> 289278.04 | E31: =SUM(E34:E35) -> 258952.52 | F31: =SUM(F34:F35) -> 225581.68 | G31: =SUM(G34:G35) -> 219895.6 | H31: =SUM(H34:H35) -> 187624.79 | I31: =SUM(I34:I35) -> 172584.72 | J31: =SUM(J34:J35) -> 222029.35 | K31: =SUM(K34:K35) -> 231366.47 | ... M31: =SUM(M34:M35) -> 193158.57 | Q31: Курс ЦБ с 08.07.2026
A32: =A31+1 -> 14 | B32: Цена за 1 ед., тыс.юаней | C32: 0 | F32: =20129 -> 20129 | G32: =19621.62259 -> 19621.623 | H32: =16742.0489 -> 16742.049 | I32: 15400 | J32: =19812.02 -> 19812.02 | K32: =20645.186 -> 20645.186 | M32: =17235.836 -> 17235.836 | Q32: 11.2068 | R32: юань
A33: =A32+1 -> 15 | B33: Цена за 1 ед., тыс.долларов | C33: 0 | D33: =3800 -> 3800 | E33: 3401.6393 | L33: 3200 | Q33: 76.1258 | R33: доллар
A34: =A33+1 -> 16 | B34: Цена за 1 ед., тыс.руб | C34: тыс.руб | D34: =D33*$Q$33 -> 289278.04 | E34: =E33*$Q$33 -> 258952.52 | F34: =F32*$Q32 -> 225581.68 | G34: =G32*$Q32 -> 219895.6 | H34: =H32*$Q32 -> 187624.79 | I34: =I32*$Q32 -> 172584.72 | J34: =J32*$Q32 -> 222029.35 | K34: =K32*$Q32 -> 231366.47 | L34: =L33*$Q$33 -> 243602.56 | M34: =M32*$Q32 -> 193158.57 | Q34: 86.8976 | R34: евро
A35: =A34+1 -> 17 | B35: Стоимость монтажных работ | C35: тыс.руб
A36: =A35+1 -> 18 | B36: Срок поставки | C36: мес. | D36: =120/30 -> 4 | E36: =310/30 -> 10.333333 | F36: =30/30 -> 1 | G36: =90/30 -> 3 | H36: =70/30 -> 2.3333333 | I36: =210/30 -> 7 | J36: =450/30 -> 15 | K36: =100/30 -> 3.3333333 | L36: 4 мес - но уточни у Леши Михайлова | N36: Потребность - апр.2027 | Q36: =(U36-S36)/30 -> 8.1333333 | R36: месяцев до ввода с | S36: 46234 | U36: 46478
A37: =A36+1 -> 19 | B37: Референс | F37: 3 ед. - в РФ | G37: 5 ед. в РФ 2025-2025 гг | H37: 1 ед. - в Китае, на угле; 5 ед. Shantui1500 (3 - Красноярский кр., по 1 - Индонезия и Китай) | I37: 3 ед. (в т.ч. 1 - электр.), введены в 2026 году. Из 3 ед. - 2 ед.на ОПИ в Китае | L37: 50 ед в РФ, всего произведено 113 ед с 2019 года | M37: 7 ед. - введены в РФ в 2024-2025 гг
A39: =A37+1 -> 20 | B39: Аннуитеты
A40: =A39+1 -> 21 | B40: операционный аннуитет | C40: руб./м3 | D40: ='4. Аннуитеты'!N116 -> 24.14614 | E40: ='4. Аннуитеты'!N257 -> 24.651757 | F40: ='4. Аннуитеты'!N398 -> 30.542498 | G40: ='4. Аннуитеты'!N539 -> 36.188048 | H40: ='4. Аннуитеты'!N680 -> 33.145923 | J40: ='4. Аннуитеты'!N962 -> 25.267376 | L40: ='4. Аннуитеты'!N1244 -> 28.598901 | M40: ='4. Аннуитеты'!N1385 -> 35.332948
A41: =A40+1 -> 22 | B41: ='4. Аннуитеты'!B117 -> ТО, ТР, ППР, вкл смазочные | C41: руб./м3 | D41: ='4. Аннуитеты'!N117 -> 19.817928 | E41: ='4. Аннуитеты'!N258 -> 19.817928 | F41: ='4. Аннуитеты'!N399 -> 22.24111 | G41: ='4. Аннуитеты'!N540 -> 32.88677 | H41: ='4. Аннуитеты'!N681 -> 27.262861 | J41: ='4. Аннуитеты'!N963 -> 19.817928 | L41: ='4. Аннуитеты'!N1245 -> 19.528463 | M41: ='4. Аннуитеты'!N1386 -> 28.045203
A42: =A41+1 -> 23 | B42: ='4. Аннуитеты'!B118 -> затраты на сервис: ремонты и ТО | C42: руб./м3 | D42: ='4. Аннуитеты'!N118 -> 1.2600942 | E42: ='4. Аннуитеты'!N259 -> 1.2600942 | F42: ='4. Аннуитеты'!N400 -> 1.3742268 | G42: ='4. Аннуитеты'!N541 -> 3.4256417 | H42: ='4. Аннуитеты'!N682 -> 1.6845093 | J42: ='4. Аннуитеты'!N964 -> 1.2600942 | L42: ='4. Аннуитеты'!N1246 -> 1.5291124 | M42: ='4. Аннуитеты'!N1387 -> 3.4057112
A43: =A42+1 -> 24 | B43: ='4. Аннуитеты'!B119 -> расходники на ковш | C43: руб./м3 | D43: ='4. Аннуитеты'!N119 -> 0.88762507 | E43: ='4. Аннуитеты'!N260 -> 0.88762507 | F43: ='4. Аннуитеты'!N401 -> 0.88907324 | G43: ='4. Аннуитеты'!N542 -> 0.88907324 | H43: ='4. Аннуитеты'!N683 -> 0.88907324 | J43: ='4. Аннуитеты'!N965 -> 0.88762507 | L43: ='4. Аннуитеты'!N1247 -> 0.87297406 | M43: ='4. Аннуитеты'!N1388 -> 0.88907324
A44: =A43+1 -> 25 | B44: ='4. Аннуитеты'!B120 -> Дизтопливо | C44: руб./м3 | D44: ='4. Аннуитеты'!N120 -> 11.374639 | E44: ='4. Аннуитеты'!N261 -> 11.374639 | F44: ='4. Аннуитеты'!N402 -> 15.976934 | G44: ='4. Аннуитеты'!N543 -> 10.614047 | H44: ='4. Аннуитеты'!N684 -> 13.136454 | J44: ='4. Аннуитеты'!N966 -> 11.374639 | L44: ='4. Аннуитеты'!N1248 -> 16.343578 | M44: ='4. Аннуитеты'!N1389 -> 13.683806
A45: =A44+1 -> 26 | B45: ='4. Аннуитеты'!B121 -> Смазочные | C45: руб./м3 | D45: ='4. Аннуитеты'!N121 -> 0 | E45: ='4. Аннуитеты'!N262 -> 0 | F45: ='4. Аннуитеты'!N403 -> 0 | G45: ='4. Аннуитеты'!N544 -> 0 | H45: ='4. Аннуитеты'!N685 -> 0 | J45: ='4. Аннуитеты'!N967 -> 0 | L45: ='4. Аннуитеты'!N1249 -> 0 | M45: ='4. Аннуитеты'!N1390 -> 0
A46: =A45+1 -> 27 | B46: ='4. Аннуитеты'!B122 -> Расходы на персонал | C46: руб./м3 | D46: ='4. Аннуитеты'!N122 -> 5.2853991 | E46: ='4. Аннуитеты'!N263 -> 5.2853991 | F46: ='4. Аннуитеты'!N404 -> 4.72695 | G46: ='4. Аннуитеты'!N545 -> 5.7942335 | H46: ='4. Аннуитеты'!N686 -> 5.7942335 | J46: ='4. Аннуитеты'!N968 -> 5.2853991 | L46: ='4. Аннуитеты'!N1250 -> 5.7821084 | M46: ='4. Аннуитеты'!N1391 -> 5.7942335
A47: =A46+1 -> 28 | B47: ='4. Аннуитеты'!B123 -> Налог на прибыль | C47: руб./м3 | D47: ='4. Аннуитеты'!N123 -> -14.479546 | E47: ='4. Аннуитеты'!N264 -> -13.973929 | F47: ='4. Аннуитеты'!N405 -> -14.665795 | G47: ='4. Аннуитеты'!N546 -> -17.421716 | H47: ='4. Аннуитеты'!N687 -> -15.621209 | J47: ='4. Аннуитеты'!N969 -> -13.35831 | L47: ='4. Аннуитеты'!N1251 -> -15.457335 | M47: ='4. Аннуитеты'!N1392 -> -16.48508
A48: =A47+1 -> 29 | B48: инвестиционный аннуитет | C48: руб./м3 | D48: ='4. Аннуитеты'!N124 -> 27.018732 | E48: ='4. Аннуитеты'!N265 -> 24.186311 | F48: ='4. Аннуитеты'!N406 -> 18.843282 | G48: ='4. Аннуитеты'!N547 -> 22.515637 | H48: ='4. Аннуитеты'!N688 -> 19.211352 | J48: ='4. Аннуитеты'!N970 -> 20.737666 | L48: ='4. Аннуитеты'!N1252 -> 24.890853 | M48: ='4. Аннуитеты'!N1393 -> 19.777969
A49: =A48+1 -> 30 | B49: общий аннуитет экскаватора | C49: руб./м3 | D49: ='4. Аннуитеты'!N125 -> 51.164872 | E49: ='4. Аннуитеты'!N266 -> 48.838068 | F49: ='4. Аннуитеты'!N407 -> 49.38578 | G49: ='4. Аннуитеты'!N548 -> 58.703686 | H49: ='4. Аннуитеты'!N689 -> 52.357275 | J49: ='4. Аннуитеты'!N971 -> 46.005042 | L49: ='4. Аннуитеты'!N1253 -> 53.489754 | M49: ='4. Аннуитеты'!N1394 -> 55.110917 | Q49: на 10 лет
B52: Для ранжирования
B53: общий аннуитет | C53: цена за ед. | D53: экскаватор
B54: =D49 -> 51.164872 | C54: =D31 -> 289278.04 | D54: =D18 -> Komatsu PC2000-11R Mining Solutions
B55: =E49 -> 48.838068 | C55: =E31 -> 258952.52 | D55: =E18 -> Komatsu PC2000-11R ИСТК
B56: =F49 -> 49.38578 | C56: =F31 -> 225581.68 | D56: =F18 -> Zoomlion ZE2000G ОРИКС
B57: =G49 -> 58.703686 | C57: =G31 -> 219895.6 | D57: =G18 -> Sany SY2000 АСТ
B58: =H49 -> 52.357275 | C58: =H31 -> 187624.79 | D58: =H18 -> Shantui SE2000LCW Строймпорттехника
B59: =I49 -> 0 | C59: =I31 -> 172584.72 | D59: =I18 -> TZCO TZ2000 Дзикай
B60: =J49 -> 46.005042 | C60: =J31 -> 222029.35 | D60: =J18 -> Komatsu PC2000-11R Огунвэй
B61: =K49 -> 0 | C61: =K31 -> 231366.47 | D61: =K18 -> XCMG LYR 2000 Огунвэй
B62: =L49 -> 53.489754 | C62: =L31 -> 243602.56 | D62: =L18 -> Hitachi EX2000 Майнтек
B63: =M49 -> 55.110917 | C63: =M31 -> 193158.57 | D63: =M18 -> Estar ESE2000 ГПБ Комплект
B67: Общий аннуитет | D67: 1 | E67: =D67+1 -> 2 | F67: =E67+1 -> 3 | G67: =F67+1 -> 4 | H67: =G67+1 -> 5 | I67: =H67+1 -> 6 | J67: =I67+1 -> 7 | K67: =J67+1 -> 8 | L67: =K67+1 -> 9 | M67: =L67+1 -> 10
B68: Komatsu PC2000-8 Mining Solutions | C68: руб./м3 | D68: ='4. Аннуитеты'!E125 -> 155.07714 | E68: ='4. Аннуитеты'!F125 -> 92.143221 | F68: ='4. Аннуитеты'!G125 -> 72.711564 | G68: ='4. Аннуитеты'!H125 -> 68.659442 | H68: ='4. Аннуитеты'!I125 -> 60.562141 | I68: ='4. Аннуитеты'!J125 -> 56.975168 | J68: ='4. Аннуитеты'!K125 -> 53.248172 | K68: ='4. Аннуитеты'!L125 -> 53.059725 | ... M68: ='4. Аннуитеты'!N125 -> 51.164872
B69: Komatsu PC2000-11R ИСТК | C69: руб./м3 | D69: ='4. Аннуитеты'!E266 -> 140.39587 | E69: ='4. Аннуитеты'!F266 -> 84.16379 | F69: ='4. Аннуитеты'!G266 -> 67.227996 | G69: ='4. Аннуитеты'!H266 -> 64.365994 | H69: ='4. Аннуитеты'!I266 -> 57.00486 | I69: ='4. Аннуитеты'!J266 -> 53.871238 | J69: ='4. Аннуитеты'!K266 -> 50.437916 | K69: ='4. Аннуитеты'!L266 -> 50.490526 | ... M69: ='4. Аннуитеты'!N266 -> 48.838068
B70: Zoomlion ZE2000G ОРИКС | C70: руб./м3 | D70: ='4. Аннуитеты'!E407 -> 115.54046 | E70: ='4. Аннуитеты'!F407 -> 74.262259 | F70: ='4. Аннуитеты'!G407 -> 65.578884 | G70: ='4. Аннуитеты'!H407 -> 58.710797 | H70: ='4. Аннуитеты'!I407 -> 54.008695 | I70: ='4. Аннуитеты'!J407 -> 53.785082 | J70: ='4. Аннуитеты'!K407 -> 50.685188 | K70: ='4. Аннуитеты'!L407 -> 48.960556 | ... M70: ='4. Аннуитеты'!N407 -> 49.38578
B71: Sany SY2000 АСТ | C71: руб./м3 | D71: ='4. Аннуитеты'!E548 -> 136.65933 | E71: ='4. Аннуитеты'!F548 -> 88.292913 | F71: ='4. Аннуитеты'!G548 -> 79.036604 | G71: ='4. Аннуитеты'!H548 -> 69.018314 | H71: ='4. Аннуитеты'!I548 -> 63.44998 | I71: ='4. Аннуитеты'!J548 -> 63.940837 | J71: ='4. Аннуитеты'!K548 -> 60.558865 | K71: ='4. Аннуитеты'!L548 -> 58.440561 | ... M71: ='4. Аннуитеты'!N548 -> 58.703686
B72: Shantui SE2000LCW Строймпорттехника | C72: руб./м3 | D72: ='4. Аннуитеты'!E689 -> 116.86568 | E72: ='4. Аннуитеты'!F689 -> 75.250449 | F72: ='4. Аннуитеты'!G689 -> 67.992606 | G72: ='4. Аннуитеты'!H689 -> 61.164746 | H72: ='4. Аннуитеты'!I689 -> 56.387449 | I72: ='4. Аннуитеты'!J689 -> 56.739892 | J72: ='4. Аннуитеты'!K689 -> 53.336511 | K72: ='4. Аннуитеты'!L689 -> 51.567675 | ... M72: ='4. Аннуитеты'!N689 -> 52.357275
B73: TZCO TZ2000 Дзикай | C73: руб./м3 | D73: ='4. Аннуитеты'!E830 -> 85.712979 | E73: ='4. Аннуитеты'!F830 -> 54.742673 | F73: ='4. Аннуитеты'!G830 -> 50.290668 | G73: ='4. Аннуитеты'!H830 -> 45.26019 | H73: ='4. Аннуитеты'!I830 -> 41.675146 | I73: ='4. Аннуитеты'!J830 -> 42.305403 | J73: ='4. Аннуитеты'!K830 -> 39.595577 | K73: ='4. Аннуитеты'!L830 -> 38.266893 | ... M73: ='4. Аннуитеты'!N830 -> 39.056532
B74: Komatsu PC2000-11R Огунвэй | C74: руб./м3 | D74: ='4. Аннуитеты'!E971 -> 122.52053 | E74: ='4. Аннуитеты'!F971 -> 74.448347 | F74: ='4. Аннуитеты'!G971 -> 60.551419 | G74: ='4. Аннуитеты'!H971 -> 59.138459 | H74: ='4. Аннуитеты'!I971 -> 52.673654 | I74: ='4. Аннуитеты'!J971 -> 50.092014 | J74: ='4. Аннуитеты'!K971 -> 47.016259 | K74: ='4. Аннуитеты'!L971 -> 47.362369 | ... M74: ='4. Аннуитеты'!N971 -> 46.005042
B75: XCMG LYR 2000 Огунвэй | C75: руб./м3 | D75: ='4. Аннуитеты'!E1112 -> 136.80652 | E75: ='4. Аннуитеты'!F1112 -> 82.259045 | F75: ='4. Аннуитеты'!G1112 -> 61.673079 | G75: ='4. Аннуитеты'!H1112 -> 52.023357 | H75: ='4. Аннуитеты'!I1112 -> 46.038151 | I75: ='4. Аннуитеты'!J1112 -> 42.243309 | J75: ='4. Аннуитеты'!K1112 -> 39.836516 | K75: ='4. Аннуитеты'!L1112 -> 37.759183 | ... M75: ='4. Аннуитеты'!N1112 -> 36.064695
B76: =L18 -> Hitachi EX2000 Майнтек | C76: руб./м3 | D76: ='4. Аннуитеты'!E1253 -> 168.15469 | E76: ='4. Аннуитеты'!F1253 -> 97.483357 | F76: ='4. Аннуитеты'!G1253 -> 74.289922 | G76: ='4. Аннуитеты'!H1253 -> 68.433989 | H76: ='4. Аннуитеты'!I1253 -> 60.379496 | I76: ='4. Аннуитеты'!J1253 -> 61.178235 | J76: ='4. Аннуитеты'!K1253 -> 60.88706 | K76: ='4. Аннуитеты'!L1253 -> 58.531854 | ... M76: ='4. Аннуитеты'!N1253 -> 53.489754
B77: Estar ESE2000 ГПБ Комплект | C77: руб./м3 | D77: ='4. Аннуитеты'!E1394 -> 120.09451 | E77: ='4. Аннуитеты'!F1394 -> 80.494572 | F77: ='4. Аннуитеты'!G1394 -> 73.553232 | G77: ='4. Аннуитеты'!H1394 -> 65.313716 | H77: ='4. Аннуитеты'!I1394 -> 58.11516 | I77: ='4. Аннуитеты'!J1394 -> 60.146419 | J77: ='4. Аннуитеты'!K1394 -> 56.406758 | K77: ='4. Аннуитеты'!L1394 -> 55.619678 | ... M77: ='4. Аннуитеты'!N1394 -> 55.110917

Sheet 2. Произв-сть экскаваторов
B2: Производительность новых экскаваторов | D2: 1 | E2: =D2+1 -> 2 | F2: =E2+1 -> 3 | G2: =F2+1 -> 4 | H2: =G2+1 -> 5 | I2: =H2+1 -> 6 | J2: =I2+1 -> 7 | K2: =J2+1 -> 8 | L2: =K2+1 -> 9 | M2: =L2+1 -> 10
B3: Наименование показателя | C3: Ед. изм. | D3: 2027 | E3: =D3+1 -> 2028 | F3: =E3+1 -> 2029 | G3: =F3+1 -> 2030 | H3: =G3+1 -> 2031 | I3: =H3+1 -> 2032 | J3: =I3+1 -> 2033 | K3: =J3+1 -> 2034 | L3: =K3+1 -> 2035 | M3: =L3+1 -> 2036 | N3: среднее
B4: Дней | C4: дн | D4: 365 | E4: 366 | F4: 365 | G4: 365 | H4: 365 | I4: 366 | J4: 365 | K4: 365 | L4: 365 | M4: 366
B5: КФВ | C5: час | D5: =D4*24 -> 8760 | E5: =E4*24 -> 8784 | F5: =F4*24 -> 8760 | G5: =G4*24 -> 8760 | H5: =H4*24 -> 8760 | I5: =I4*24 -> 8784 | J5: =J4*24 -> 8760 | K5: =K4*24 -> 8760 | ... M5: =M4*24 -> 8784
B6: Объем ковша с шапкой
B7: ='1. Сводная_аннуитеты'!D18 -> Komatsu PC2000-11R Mining Solutions | C7: м3 | D7: ='PC2000-8 MS'!$D$6 -> 12 | E7: =D7 -> 12 | F7: =E7 -> 12 | G7: =F7 -> 12 | H7: =G7 -> 12 | I7: =H7 -> 12 | J7: =I7 -> 12 | K7: =J7 -> 12 | L7: =K7 -> 12 | M7: =L7 -> 12
B8: ='1. Сводная_аннуитеты'!E18 -> Komatsu PC2000-11R ИСТК | C8: м3 | D8: ='PC2000-11R ИСТК'!D6 -> 12 | E8: =D8 -> 12 | F8: =E8 -> 12 | G8: =F8 -> 12 | H8: =G8 -> 12 | I8: =H8 -> 12 | J8: =I8 -> 12 | K8: =J8 -> 12 | L8: =K8 -> 12 | M8: =L8 -> 12
B9: ='1. Сводная_аннуитеты'!F18 -> Zoomlion ZE2000G ОРИКС | C9: м3 | D9: =Zooml_Орикс!D6 -> 13 | E9: =D9 -> 13 | F9: =E9 -> 13 | G9: =F9 -> 13 | H9: =G9 -> 13 | I9: =H9 -> 13 | J9: =I9 -> 13 | K9: =J9 -> 13 | L9: =K9 -> 13 | M9: =L9 -> 13
B10: ='1. Сводная_аннуитеты'!G18 -> Sany SY2000 АСТ | C10: м3 | D10: ='Sany АСТ'!D6 -> 12 | E10: =D10 -> 12 | F10: =E10 -> 12 | G10: =F10 -> 12 | H10: =G10 -> 12 | I10: =H10 -> 12 | J10: =I10 -> 12 | K10: =J10 -> 12 | L10: =K10 -> 12 | M10: =L10 -> 12
B11: ='1. Сводная_аннуитеты'!H18 -> Shantui SE2000LCW Строймпорттехника | C11: м3 | D11: ='Shantui Стройимп'!D6 -> 12 | E11: =D11 -> 12 | F11: =E11 -> 12 | G11: =F11 -> 12 | H11: =G11 -> 12 | I11: =H11 -> 12 | J11: =I11 -> 12 | K11: =J11 -> 12 | L11: =K11 -> 12 | M11: =L11 -> 12
B12: ='1. Сводная_аннуитеты'!I18 -> TZCO TZ2000 Дзикай | C12: м3 | D12: ='TZCO Дзикай'!D6 -> 13.5 | E12: =D12 -> 13.5 | F12: =E12 -> 13.5 | G12: =F12 -> 13.5 | H12: =G12 -> 13.5 | I12: =H12 -> 13.5 | J12: =I12 -> 13.5 | K12: =J12 -> 13.5 | L12: =K12 -> 13.5 | M12: =L12 -> 13.5
B13: ='1. Сводная_аннуитеты'!J18 -> Komatsu PC2000-11R Огунвэй | C13: м3 | D13: 12 | E13: =D13 -> 12 | F13: =E13 -> 12 | G13: =F13 -> 12 | H13: =G13 -> 12 | I13: =H13 -> 12 | J13: =I13 -> 12 | K13: =J13 -> 12 | L13: =K13 -> 12 | M13: =L13 -> 12
B14: ='1. Сводная_аннуитеты'!K18 -> XCMG LYR 2000 Огунвэй | C14: м3 | D14: 12 | E14: =D14 -> 12 | F14: =E14 -> 12 | G14: =F14 -> 12 | H14: =G14 -> 12 | I14: =H14 -> 12 | J14: =I14 -> 12 | K14: =J14 -> 12 | L14: =K14 -> 12 | M14: =L14 -> 12
B15: ='1. Сводная_аннуитеты'!L18 -> Hitachi EX2000 Майнтек | C15: м3 | D15: 12 | E15: =D15 -> 12 | F15: =E15 -> 12 | G15: =F15 -> 12 | H15: =G15 -> 12 | I15: =H15 -> 12 | J15: =I15 -> 12 | K15: =J15 -> 12 | L15: =K15 -> 12 | M15: =L15 -> 12
B16: ='1. Сводная_аннуитеты'!M18 -> Estar ESE2000 ГПБ Комплект | C16: м3 | D16: 12 | E16: =D16 -> 12 | F16: =E16 -> 12 | G16: =F16 -> 12 | H16: =G16 -> 12 | I16: =H16 -> 12 | J16: =I16 -> 12 | K16: =J16 -> 12 | L16: =K16 -> 12 | M16: =L16 -> 12
B17: КТГ
B18: =B7 -> Komatsu PC2000-11R Mining Solutions | C18: коэф. | D18: ='PC2000-8 MS'!E7 -> 0.92406268 | E18: ='PC2000-8 MS'!F7 -> 0.79773755 | F18: ='PC2000-8 MS'!G7 -> 0.82453381 | G18: ='PC2000-8 MS'!H7 -> 0.76394441 | H18: ='PC2000-8 MS'!I7 -> 0.76281505 | I18: ='PC2000-8 MS'!J7 -> 0.81214813 | J18: ='PC2000-8 MS'!K7 -> 0.78656324 | K18: ='PC2000-8 MS'!L7 -> 0.84263903 | ... M18: ='PC2000-8 MS'!N7 -> 0.82670539 | N18: =AVERAGE(D18:M18) -> 0.79038201 | O18: ='PC2000-8 MS'!O7 -> факт по Группе
B19: =B8 -> Komatsu PC2000-11R ИСТК | C19: коэф. | D19: ='PC2000-11R ИСТК'!E7 -> 0.92406268 | E19: ='PC2000-11R ИСТК'!F7 -> 0.79773755 | F19: ='PC2000-11R ИСТК'!G7 -> 0.82453381 | G19: ='PC2000-11R ИСТК'!H7 -> 0.76394441 | H19: ='PC2000-11R ИСТК'!I7 -> 0.76281505 | I19: ='PC2000-11R ИСТК'!J7 -> 0.81214813 | J19: ='PC2000-11R ИСТК'!K7 -> 0.78656324 | K19: ='PC2000-11R ИСТК'!L7 -> 0.84263903 | ... M19: ='PC2000-11R ИСТК'!N7 -> 0.82670539 | N19: =AVERAGE(D19:M19) -> 0.79038201 | O19: ='PC2000-11R ИСТК'!Y7 -> равно PC2000 - факт по Группе
B20: =B9 -> Zoomlion ZE2000G ОРИКС | C20: коэф. | D20: =Zooml_Орикс!E7 -> 0.85465183 | E20: =Zooml_Орикс!F7 -> 0.7283267 | F20: =Zooml_Орикс!G7 -> 0.75512296 | G20: =Zooml_Орикс!H7 -> 0.69453356 | H20: =Zooml_Орикс!I7 -> 0.6934042 | I20: =Zooml_Орикс!J7 -> 0.74273728 | J20: =Zooml_Орикс!K7 -> 0.71715238 | K20: =Zooml_Орикс!L7 -> 0.77322818 | ... M20: =Zooml_Орикс!N7 -> 0.75729454 | N20: =AVERAGE(D20:M20) -> 0.72097116 | O20: =Zooml_Орикс!Y7 -> первый год - факт Люгонга по Группе, далее динамика от факта PC2000
B21: =B10 -> Sany SY2000 АСТ | C21: коэф. | D21: ='Sany АСТ'!E7 -> 0.85465183 | E21: ='Sany АСТ'!F7 -> 0.7283267 | F21: ='Sany АСТ'!G7 -> 0.75512296 | G21: ='Sany АСТ'!H7 -> 0.69453356 | H21: ='Sany АСТ'!I7 -> 0.6934042 | I21: ='Sany АСТ'!J7 -> 0.74273728 | J21: ='Sany АСТ'!K7 -> 0.71715238 | K21: ='Sany АСТ'!L7 -> 0.77322818 | ... M21: ='Sany АСТ'!N7 -> 0.75729454 | N21: =AVERAGE(D21:M21) -> 0.72097116 | O21: ='Sany АСТ'!O7 -> первый год - факт Люгонга по Группе, далее динамика от факта PC2000
B22: =B11 -> Shantui SE2000LCW Строймпорттехника | C22: коэф. | D22: ='Shantui Стройимп'!E7 -> 0.85465183 | E22: ='Shantui Стройимп'!F7 -> 0.7283267 | F22: ='Shantui Стройимп'!G7 -> 0.75512296 | G22: ='Shantui Стройимп'!H7 -> 0.69453356 | H22: ='Shantui Стройимп'!I7 -> 0.6934042 | I22: ='Shantui Стройимп'!J7 -> 0.74273728 | J22: ='Shantui Стройимп'!K7 -> 0.71715238 | K22: ='Shantui Стройимп'!L7 -> 0.77322818 | ... M22: ='Shantui Стройимп'!N7 -> 0.75729454 | N22: =AVERAGE(D22:M22) -> 0.72097116 | O22: ='Shantui Стройимп'!Y7 -> первый год - факт Люгонга по Группе, далее динамика от факта PC2000
B23: =B12 -> TZCO TZ2000 Дзикай | C23: коэф. | D23: ='TZCO Дзикай'!E7 -> 0.85465183 | E23: ='TZCO Дзикай'!F7 -> 0.7283267 | F23: ='TZCO Дзикай'!G7 -> 0.75512296 | G23: ='TZCO Дзикай'!H7 -> 0.69453356 | H23: ='TZCO Дзикай'!I7 -> 0.6934042 | I23: ='TZCO Дзикай'!J7 -> 0.74273728 | J23: ='TZCO Дзикай'!K7 -> 0.71715238 | K23: ='TZCO Дзикай'!L7 -> 0.77322818 | ... M23: ='TZCO Дзикай'!N7 -> 0.75729454 | N23: =AVERAGE(D23:M23) -> 0.72097116 | O23: ='TZCO Дзикай'!Y7 -> первый год - факт Люгонга по Группе, далее динамика от факта PC2000
B24: =B13 -> Komatsu PC2000-11R Огунвэй | C24: коэф. | D24: =D19 -> 0.92406268 | E24: =E19 -> 0.79773755 | F24: =F19 -> 0.82453381 | G24: =G19 -> 0.76394441 | H24: =H19 -> 0.76281505 | I24: =I19 -> 0.81214813 | J24: =J19 -> 0.78656324 | K24: =K19 -> 0.84263903 | ... M24: =M19 -> 0.82670539 | N24: =AVERAGE(D24:M24) -> 0.79038201 | O24: =O19 -> равно PC2000 - факт по Группе
B25: =B14 -> XCMG LYR 2000 Огунвэй | C25: коэф. | D25: =Факт.КТГ!D23 -> 0.85465183 | E25: =Факт.КТГ!E23 -> 0.7283267 | F25: =Факт.КТГ!F23 -> 0.75512296 | G25: =Факт.КТГ!G23 -> 0.69453356 | H25: =Факт.КТГ!H23 -> 0.6934042 | I25: =Факт.КТГ!I23 -> 0.74273728 | J25: =Факт.КТГ!J23 -> 0.71715238 | K25: =Факт.КТГ!K23 -> 0.77322818 | ... M25: =Факт.КТГ!M23 -> 0.75729454 | N25: =AVERAGE(D25:M25) -> 0.72097116 | O25: =O20 -> первый год - факт Люгонга по Группе, далее динамика от факта PC2000
B26: =B15 -> Hitachi EX2000 Майнтек | C26: коэф. | D26: ='Факт.КТГ Алдан Hitachi'!I33 -> 0.74 | E26: ='Факт.КТГ Алдан Hitachi'!J33 -> 0.73 | F26: ='Факт.КТГ Алдан Hitachi'!K33 -> 0.79 | G26: ='Факт.КТГ Алдан Hitachi'!L33 -> 0.63 | H26: ='Факт.КТГ Алдан Hitachi'!M33 -> 0.68812671 | I26: ='Факт.КТГ Алдан Hitachi'!N33 -> 0.82178051 | J26: ='Факт.КТГ Алдан Hitachi'!O33 -> 0.57808219 | K26: ='Факт.КТГ Алдан Hitachi'!P33 -> 0.70980826 | ... M26: ='Факт.КТГ Алдан Hitachi'!R33 -> 0.79134985 | N26: =AVERAGE(D26:M26) -> 0.72245288 | O26: факт Алдана по Hitachi EX1200 (обратная лопата)
B27: =B16 -> Estar ESE2000 ГПБ Комплект | C27: коэф. | D27: =D25 -> 0.85465183 | E27: =E25 -> 0.7283267 | F27: =F25 -> 0.75512296 | G27: =G25 -> 0.69453356 | H27: =H25 -> 0.6934042 | I27: =I25 -> 0.74273728 | J27: =J25 -> 0.71715238 | K27: =K25 -> 0.77322818 | ... M27: =M25 -> 0.75729454 | N27: =AVERAGE(D27:M27) -> 0.72097116 | O27: =O25 -> первый год - факт Люгонга по Группе, далее динамика от факта PC2000
B28: Техническая готовность
B29: =B7 -> Komatsu PC2000-11R Mining Solutions | C29: час. | D29: =D$5*D18 -> 8094.7891 | E29: =E$5*E18 -> 7007.3267 | F29: =F$5*F18 -> 7222.9162 | G29: =G$5*G18 -> 6692.1531 | H29: =H$5*H18 -> 6682.2598 | I29: =I$5*I18 -> 7133.9091 | J29: =J$5*J18 -> 6890.2939 | K29: =K$5*K18 -> 7381.5179 | ... M29: =M$5*M18 -> 7261.7802
B30: =B8 -> Komatsu PC2000-11R ИСТК | C30: час. | D30: =D$5*D19 -> 8094.7891 | E30: =E$5*E19 -> 7007.3267 | F30: =F$5*F19 -> 7222.9162 | G30: =G$5*G19 -> 6692.1531 | H30: =H$5*H19 -> 6682.2598 | I30: =I$5*I19 -> 7133.9091 | J30: =J$5*J19 -> 6890.2939 | K30: =K$5*K19 -> 7381.5179 | ... M30: =M$5*M19 -> 7261.7802
B31: =B9 -> Zoomlion ZE2000G ОРИКС | C31: час. | D31: =D$5*D20 -> 7486.75 | E31: =E$5*E20 -> 6397.6217 | F31: =F$5*F20 -> 6614.8771 | G31: =G$5*G20 -> 6084.114 | H31: =H$5*H20 -> 6074.2208 | I31: =I$5*I20 -> 6524.2042 | J31: =J$5*J20 -> 6282.2549 | K31: =K$5*K20 -> 6773.4789 | ... M31: =M$5*M20 -> 6652.0753
B32: =B10 -> Sany SY2000 АСТ | C32: час. | D32: =D$5*D21 -> 7486.75 | E32: =E$5*E21 -> 6397.6217 | F32: =F$5*F21 -> 6614.8771 | G32: =G$5*G21 -> 6084.114 | H32: =H$5*H21 -> 6074.2208 | I32: =I$5*I21 -> 6524.2042 | J32: =J$5*J21 -> 6282.2549 | K32: =K$5*K21 -> 6773.4789 | ... M32: =M$5*M21 -> 6652.0753
B33: =B11 -> Shantui SE2000LCW Строймпорттехника | C33: час. | D33: =D$5*D22 -> 7486.75 | E33: =E$5*E22 -> 6397.6217 | F33: =F$5*F22 -> 6614.8771 | G33: =G$5*G22 -> 6084.114 | H33: =H$5*H22 -> 6074.2208 | I33: =I$5*I22 -> 6524.2042 | J33: =J$5*J22 -> 6282.2549 | K33: =K$5*K22 -> 6773.4789 | ... M33: =M$5*M22 -> 6652.0753
B34: =B12 -> TZCO TZ2000 Дзикай | C34: час. | D34: =D$5*D23 -> 7486.75 | E34: =E$5*E23 -> 6397.6217 | F34: =F$5*F23 -> 6614.8771 | G34: =G$5*G23 -> 6084.114 | H34: =H$5*H23 -> 6074.2208 | I34: =I$5*I23 -> 6524.2042 | J34: =J$5*J23 -> 6282.2549 | K34: =K$5*K23 -> 6773.4789 | ... M34: =M$5*M23 -> 6652.0753
B35: =B13 -> Komatsu PC2000-11R Огунвэй | C35: час. | D35: =D$5*D24 -> 8094.7891 | E35: =E$5*E24 -> 7007.3267 | F35: =F$5*F24 -> 7222.9162 | G35: =G$5*G24 -> 6692.1531 | H35: =H$5*H24 -> 6682.2598 | I35: =I$5*I24 -> 7133.9091 | J35: =J$5*J24 -> 6890.2939 | K35: =K$5*K24 -> 7381.5179 | ... M35: =M$5*M24 -> 7261.7802
B36: =B14 -> XCMG LYR 2000 Огунвэй | C36: час. | D36: =D$5*D25 -> 7486.75 | E36: =E$5*E25 -> 6397.6217 | F36: =F$5*F25 -> 6614.8771 | G36: =G$5*G25 -> 6084.114 | H36: =H$5*H25 -> 6074.2208 | I36: =I$5*I25 -> 6524.2042 | J36: =J$5*J25 -> 6282.2549 | K36: =K$5*K25 -> 6773.4789 | ... M36: =M$5*M25 -> 6652.0753
B37: =B15 -> Hitachi EX2000 Майнтек | C37: час. | D37: =D$5*D26 -> 6482.4 | E37: =E$5*E26 -> 6412.32 | F37: =F$5*F26 -> 6920.4 | G37: =G$5*G26 -> 5518.8 | H37: =H$5*H26 -> 6027.99 | I37: =I$5*I26 -> 7218.52 | J37: =J$5*J26 -> 5064 | K37: =K$5*K26 -> 6217.9204 | ... M37: =M$5*M26 -> 6951.2171
B38: =B16 -> Estar ESE2000 ГПБ Комплект | C38: час. | D38: =D$5*D27 -> 7486.75 | E38: =E$5*E27 -> 6397.6217 | F38: =F$5*F27 -> 6614.8771 | G38: =G$5*G27 -> 6084.114 | H38: =H$5*H27 -> 6074.2208 | I38: =I$5*I27 -> 6524.2042 | J38: =J$5*J27 -> 6282.2549 | K38: =K$5*K27 -> 6773.4789 | ... M38: =M$5*M27 -> 6652.0753
B39: Ежесменные регламентные простои | C39: мин/см | D39: =SUM(D40:D42) -> 0 | E39: =SUM(E40:E42) -> 0 | F39: =SUM(F40:F42) -> 0 | G39: =SUM(G40:G42) -> 0 | H39: =SUM(H40:H42) -> 0 | I39: =SUM(I40:I42) -> 0 | J39: =SUM(J40:J42) -> 0 | K39: =SUM(K40:K42) -> 0 | ... M39: =SUM(M40:M42) -> 0
C40: мин/см | E40: =D40 -> 0 | F40: =E40 -> 0 | G40: =F40 -> 0 | H40: =G40 -> 0 | I40: =H40 -> 0 | J40: =I40 -> 0 | K40: =J40 -> 0 | L40: =K40 -> 0 | M40: =L40 -> 0 | N40: Балансировка КБЕ - новый PC2000
B41: все регламентные | C41: мин/см | E41: =D41 -> 0 | F41: =E41 -> 0 | G41: =F41 -> 0 | H41: =G41 -> 0 | I41: =H41 -> 0 | J41: =I41 -> 0 | K41: =J41 -> 0 | L41: =K41 -> 0 | M41: =L41 -> 0 | N41: Балансировка КБЕ - новый PC2000
C42: мин/см | E42: =D42 -> 0 | F42: =E42 -> 0 | G42: =F42 -> 0 | H42: =G42 -> 0 | I42: =H42 -> 0 | J42: =I42 -> 0 | K42: =J42 -> 0 | L42: =K42 -> 0 | M42: =L42 -> 0 | N42: Балансировка КБЕ - новый PC2000
B43: Ежесменные простои | C43: мин/см | D43: =SUM(D44:D48) -> 266.1 | E43: =SUM(E44:E48) -> 266.1 | F43: =SUM(F44:F48) -> 266.1 | G43: =SUM(G44:G48) -> 266.1 | H43: =SUM(H44:H48) -> 266.1 | I43: =SUM(I44:I48) -> 266.1 | J43: =SUM(J44:J48) -> 266.1 | K43: =SUM(K44:K48) -> 266.1 | ... M43: =SUM(M44:M48) -> 266.1
B44: ОТМ (взрывы, перегоны, подготовка забоя, подчистка забоя, постановка экск.в забой, заправка) | C44: мин/см | D44: 77 | E44: =D44 -> 77 | F44: =E44 -> 77 | G44: =F44 -> 77 | H44: =G44 -> 77 | I44: =H44 -> 77 | J44: =I44 -> 77 | K44: =J44 -> 77 | L44: =K44 -> 77 | M44: =L44 -> 77 | N44: Балансировка КБЕ - новый PC2000
B45: Энергетические (переключения, захлест проводов, разрыв) | C45: мин/см | E45: =D45 -> 0 | F45: =E45 -> 0 | G45: =F45 -> 0 | H45: =G45 -> 0 | I45: =H45 -> 0 | J45: =I45 -> 0 | K45: =J45 -> 0 | L45: =K45 -> 0 | M45: =L45 -> 0 | N45: Балансировка КБЕ - новый PC2000
B46: Отсутствие экипажа | C46: мин/см | E46: =D46 -> 0 | F46: =E46 -> 0 | G46: =F46 -> 0 | H46: =G46 -> 0 | I46: =H46 -> 0 | J46: =I46 -> 0 | K46: =J46 -> 0 | L46: =K46 -> 0 | M46: =L46 -> 0 | N46: Балансировка КБЕ - новый PC2000
B47: Ожидание самосвала (для дизельных - ожидание с включенным двигателем) | C47: мин/см | D47: 174 | E47: =D47 -> 174 | F47: =E47 -> 174 | G47: =F47 -> 174 | H47: =G47 -> 174 | I47: =H47 -> 174 | J47: =I47 -> 174 | K47: =J47 -> 174 | L47: =K47 -> 174 | M47: =L47 -> 174 | N47: Балансировка КБЕ - новый PC2000
B48: прочие (переэкскавация, хоз.работы и т.п.) | C48: мин/см | D48: 15.1 | E48: =D48 -> 15.1 | F48: =E48 -> 15.1 | G48: =F48 -> 15.1 | H48: =G48 -> 15.1 | I48: =H48 -> 15.1 | J48: =I48 -> 15.1 | K48: =J48 -> 15.1 | L48: =K48 -> 15.1 | M48: =L48 -> 15.1 | N48: Балансировка КБЕ - новый PC2000
B49: Эффективное время
B50: =B29 -> Komatsu PC2000-11R Mining Solutions | C50: час. | D50: =D29-((D$39+D$43)/60*(D29/12)) -> 5103.09 | E50: =E29-((E$39+E$43)/60*(E29/12)) -> 4417.5355 | F50: =F29-((F$39+F$43)/60*(F29/12)) -> 4553.4467 | G50: =G29-((G$39+G$43)/60*(G29/12)) -> 4218.8448 | H50: =H29-((H$39+H$43)/60*(H29/12)) -> 4212.608 | I50: =I29-((I$39+I$43)/60*(I29/12)) -> 4497.3352 | J50: =J29-((J$39+J$43)/60*(J29/12)) -> 4343.7561 | K50: =K29-((K$39+K$43)/60*(K29/12)) -> 4653.4319 | ... M50: =M29-((M$39+M$43)/60*(M29/12)) -> 4577.9473
B51: =B30 -> Komatsu PC2000-11R ИСТК | C51: час. | D51: =D30-((D$39+D$43)/60*(D30/12)) -> 5103.09 | E51: =E30-((E$39+E$43)/60*(E30/12)) -> 4417.5355 | F51: =F30-((F$39+F$43)/60*(F30/12)) -> 4553.4467 | G51: =G30-((G$39+G$43)/60*(G30/12)) -> 4218.8448 | H51: =H30-((H$39+H$43)/60*(H30/12)) -> 4212.608 | I51: =I30-((I$39+I$43)/60*(I30/12)) -> 4497.3352 | J51: =J30-((J$39+J$43)/60*(J30/12)) -> 4343.7561 | K51: =K30-((K$39+K$43)/60*(K30/12)) -> 4653.4319 | ... M51: =M30-((M$39+M$43)/60*(M30/12)) -> 4577.9473
B52: =B31 -> Zoomlion ZE2000G ОРИКС | C52: час. | D52: =D31-((D$39+D$43)/60*(D31/12)) -> 4719.772 | E52: =E31-((E$39+E$43)/60*(E31/12)) -> 4033.1674 | F52: =F31-((F$39+F$43)/60*(F31/12)) -> 4170.1288 | G52: =G31-((G$39+G$43)/60*(G31/12)) -> 3835.5269 | H52: =H31-((H$39+H$43)/60*(H31/12)) -> 3829.29 | I52: =I31-((I$39+I$43)/60*(I31/12)) -> 4112.9671 | J52: =J31-((J$39+J$43)/60*(J31/12)) -> 3960.4382 | K52: =K31-((K$39+K$43)/60*(K31/12)) -> 4270.114 | ... M52: =M31-((M$39+M$43)/60*(M31/12)) -> 4193.5791
B53: =B32 -> Sany SY2000 АСТ | C53: час. | D53: =D32-((D$39+D$43)/60*(D32/12)) -> 4719.772 | E53: =E32-((E$39+E$43)/60*(E32/12)) -> 4033.1674 | F53: =F32-((F$39+F$43)/60*(F32/12)) -> 4170.1288 | G53: =G32-((G$39+G$43)/60*(G32/12)) -> 3835.5269 | H53: =H32-((H$39+H$43)/60*(H32/12)) -> 3829.29 | I53: =I32-((I$39+I$43)/60*(I32/12)) -> 4112.9671 | J53: =J32-((J$39+J$43)/60*(J32/12)) -> 3960.4382 | K53: =K32-((K$39+K$43)/60*(K32/12)) -> 4270.114 | ... M53: =M32-((M$39+M$43)/60*(M32/12)) -> 4193.5791
B54: =B33 -> Shantui SE2000LCW Строймпорттехника | C54: час. | D54: =D33-((D$39+D$43)/60*(D33/12)) -> 4719.772 | E54: =E33-((E$39+E$43)/60*(E33/12)) -> 4033.1674 | F54: =F33-((F$39+F$43)/60*(F33/12)) -> 4170.1288 | G54: =G33-((G$39+G$43)/60*(G33/12)) -> 3835.5269 | H54: =H33-((H$39+H$43)/60*(H33/12)) -> 3829.29 | I54: =I33-((I$39+I$43)/60*(I33/12)) -> 4112.9671 | J54: =J33-((J$39+J$43)/60*(J33/12)) -> 3960.4382 | K54: =K33-((K$39+K$43)/60*(K33/12)) -> 4270.114 | ... M54: =M33-((M$39+M$43)/60*(M33/12)) -> 4193.5791
B55: =B34 -> TZCO TZ2000 Дзикай | C55: час. | D55: =D34-((D$39+D$43)/60*(D34/12)) -> 4719.772 | E55: =E34-((E$39+E$43)/60*(E34/12)) -> 4033.1674 | F55: =F34-((F$39+F$43)/60*(F34/12)) -> 4170.1288 | G55: =G34-((G$39+G$43)/60*(G34/12)) -> 3835.5269 | H55: =H34-((H$39+H$43)/60*(H34/12)) -> 3829.29 | I55: =I34-((I$39+I$43)/60*(I34/12)) -> 4112.9671 | J55: =J34-((J$39+J$43)/60*(J34/12)) -> 3960.4382 | K55: =K34-((K$39+K$43)/60*(K34/12)) -> 4270.114 | ... M55: =M34-((M$39+M$43)/60*(M34/12)) -> 4193.5791
B56: =B35 -> Komatsu PC2000-11R Огунвэй | C56: час. | D56: =D35-((D$39+D$43)/60*(D35/12)) -> 5103.09 | E56: =E35-((E$39+E$43)/60*(E35/12)) -> 4417.5355 | F56: =F35-((F$39+F$43)/60*(F35/12)) -> 4553.4467 | G56: =G35-((G$39+G$43)/60*(G35/12)) -> 4218.8448 | H56: =H35-((H$39+H$43)/60*(H35/12)) -> 4212.608 | I56: =I35-((I$39+I$43)/60*(I35/12)) -> 4497.3352 | J56: =J35-((J$39+J$43)/60*(J35/12)) -> 4343.7561 | K56: =K35-((K$39+K$43)/60*(K35/12)) -> 4653.4319 | ... M56: =M35-((M$39+M$43)/60*(M35/12)) -> 4577.9473
B57: =B36 -> XCMG LYR 2000 Огунвэй | C57: час. | D57: =D36-((D$39+D$43)/60*(D36/12)) -> 4719.772 | E57: =E36-((E$39+E$43)/60*(E36/12)) -> 4033.1674 | F57: =F36-((F$39+F$43)/60*(F36/12)) -> 4170.1288 | G57: =G36-((G$39+G$43)/60*(G36/12)) -> 3835.5269 | H57: =H36-((H$39+H$43)/60*(H36/12)) -> 3829.29 | I57: =I36-((I$39+I$43)/60*(I36/12)) -> 4112.9671 | J57: =J36-((J$39+J$43)/60*(J36/12)) -> 3960.4382 | K57: =K36-((K$39+K$43)/60*(K36/12)) -> 4270.114 | ... M57: =M36-((M$39+M$43)/60*(M36/12)) -> 4193.5791
B58: =B37 -> Hitachi EX2000 Майнтек | C58: час. | D58: =D37-((D$39+D$43)/60*(D37/12)) -> 4086.613 | E58: =E37-((E$39+E$43)/60*(E37/12)) -> 4042.4334 | F58: =F37-((F$39+F$43)/60*(F37/12)) -> 4362.7355 | G58: =G37-((G$39+G$43)/60*(G37/12)) -> 3479.1435 | H58: =H37-((H$39+H$43)/60*(H37/12)) -> 3800.1454 | I58: =I37-((I$39+I$43)/60*(I37/12)) -> 4550.6753 | J58: =J37-((J$39+J$43)/60*(J37/12)) -> 3192.43 | K58: =K37-((K$39+K$43)/60*(K37/12)) -> 3919.8806 | ... M58: =M37-((M$39+M$43)/60*(M37/12)) -> 4382.1631
B59: =B38 -> Estar ESE2000 ГПБ Комплект | C59: час. | D59: =D38-((D$39+D$43)/60*(D38/12)) -> 4719.772 | E59: =E38-((E$39+E$43)/60*(E38/12)) -> 4033.1674 | F59: =F38-((F$39+F$43)/60*(F38/12)) -> 4170.1288 | G59: =G38-((G$39+G$43)/60*(G38/12)) -> 3835.5269 | H59: =H38-((H$39+H$43)/60*(H38/12)) -> 3829.29 | I59: =I38-((I$39+I$43)/60*(I38/12)) -> 4112.9671 | J59: =J38-((J$39+J$43)/60*(J38/12)) -> 3960.4382 | K59: =K38-((K$39+K$43)/60*(K38/12)) -> 4270.114 | ... M59: =M38-((M$39+M$43)/60*(M38/12)) -> 4193.5791
B60: КИО на погрузке г.м.
B61: =B50 -> Komatsu PC2000-11R Mining Solutions | C61: коэф. | D61: =D50/D$5 -> 0.58254452 | E61: =E50/E$5 -> 0.50290705 | F61: =F50/F$5 -> 0.51979986 | G61: =G50/G$5 -> 0.48160329 | H61: =H50/H$5 -> 0.48089132 | I61: =I50/I$5 -> 0.51199171 | J61: =J50/J$5 -> 0.49586257 | K61: =K50/K$5 -> 0.53121369 | ... M61: =M50/M$5 -> 0.52116886 | N61: =AVERAGE(D61:M61) -> 0.49826999 | O61: среднее
B62: =B51 -> Komatsu PC2000-11R ИСТК | C62: коэф. | D62: =D51/D$5 -> 0.58254452 | E62: =E51/E$5 -> 0.50290705 | F62: =F51/F$5 -> 0.51979986 | G62: =G51/G$5 -> 0.48160329 | H62: =H51/H$5 -> 0.48089132 | I62: =I51/I$5 -> 0.51199171 | J62: =J51/J$5 -> 0.49586257 | K62: =K51/K$5 -> 0.53121369 | ... M62: =M51/M$5 -> 0.52116886 | N62: =AVERAGE(D62:M62) -> 0.49826999 | O62: среднее
B63: =B52 -> Zoomlion ZE2000G ОРИКС | C63: коэф. | D63: =D52/D$5 -> 0.53878676 | E63: =E52/E$5 -> 0.45914929 | F63: =F52/F$5 -> 0.4760421 | G63: =G52/G$5 -> 0.43784553 | H63: =H52/H$5 -> 0.43713356 | I63: =I52/I$5 -> 0.46823396 | J63: =J52/J$5 -> 0.45210482 | K63: =K52/K$5 -> 0.48745593 | ... M63: =M52/M$5 -> 0.4774111 | N63: =AVERAGE(D63:M63) -> 0.45451223 | O63: среднее
B64: =B53 -> Sany SY2000 АСТ | C64: коэф. | D64: =D53/D$5 -> 0.53878676 | E64: =E53/E$5 -> 0.45914929 | F64: =F53/F$5 -> 0.4760421 | G64: =G53/G$5 -> 0.43784553 | H64: =H53/H$5 -> 0.43713356 | I64: =I53/I$5 -> 0.46823396 | J64: =J53/J$5 -> 0.45210482 | K64: =K53/K$5 -> 0.48745593 | ... M64: =M53/M$5 -> 0.4774111 | N64: =AVERAGE(D64:M64) -> 0.45451223
B65: =B54 -> Shantui SE2000LCW Строймпорттехника | C65: коэф. | D65: =D54/D$5 -> 0.53878676 | E65: =E54/E$5 -> 0.45914929 | F65: =F54/F$5 -> 0.4760421 | G65: =G54/G$5 -> 0.43784553 | H65: =H54/H$5 -> 0.43713356 | I65: =I54/I$5 -> 0.46823396 | J65: =J54/J$5 -> 0.45210482 | K65: =K54/K$5 -> 0.48745593 | ... M65: =M54/M$5 -> 0.4774111 | N65: =AVERAGE(D65:M65) -> 0.45451223
B66: =B55 -> TZCO TZ2000 Дзикай | C66: коэф. | D66: =D55/D$5 -> 0.53878676 | E66: =E55/E$5 -> 0.45914929 | F66: =F55/F$5 -> 0.4760421 | G66: =G55/G$5 -> 0.43784553 | H66: =H55/H$5 -> 0.43713356 | I66: =I55/I$5 -> 0.46823396 | J66: =J55/J$5 -> 0.45210482 | K66: =K55/K$5 -> 0.48745593 | ... M66: =M55/M$5 -> 0.4774111 | N66: =AVERAGE(D66:M66) -> 0.45451223
B67: =B56 -> Komatsu PC2000-11R Огунвэй | C67: коэф. | D67: =D56/D$5 -> 0.58254452 | E67: =E56/E$5 -> 0.50290705 | F67: =F56/F$5 -> 0.51979986 | G67: =G56/G$5 -> 0.48160329 | H67: =H56/H$5 -> 0.48089132 | I67: =I56/I$5 -> 0.51199171 | J67: =J56/J$5 -> 0.49586257 | K67: =K56/K$5 -> 0.53121369 | ... M67: =M56/M$5 -> 0.52116886 | N67: =AVERAGE(D67:M67) -> 0.49826999
B68: =B57 -> XCMG LYR 2000 Огунвэй | C68: коэф. | D68: =D57/D$5 -> 0.53878676 | E68: =E57/E$5 -> 0.45914929 | F68: =F57/F$5 -> 0.4760421 | G68: =G57/G$5 -> 0.43784553 | H68: =H57/H$5 -> 0.43713356 | I68: =I57/I$5 -> 0.46823396 | J68: =J57/J$5 -> 0.45210482 | K68: =K57/K$5 -> 0.48745593 | ... M68: =M57/M$5 -> 0.4774111 | N68: =AVERAGE(D68:M68) -> 0.45451223
B69: =B58 -> Hitachi EX2000 Майнтек | C69: коэф. | D69: =D58/D$5 -> 0.46650833 | E69: =E58/E$5 -> 0.46020417 | F69: =F58/F$5 -> 0.49802917 | G69: =G58/G$5 -> 0.3971625 | H69: =H58/H$5 -> 0.43380655 | I69: =I58/I$5 -> 0.51806413 | J69: =J58/J$5 -> 0.36443265 | K69: =K58/K$5 -> 0.44747496 | ... M69: =M58/M$5 -> 0.49888014 | N69: =AVERAGE(D69:M69) -> 0.45544634
B70: =B59 -> Estar ESE2000 ГПБ Комплект | C70: коэф. | D70: =D59/D$5 -> 0.53878676 | E70: =E59/E$5 -> 0.45914929 | F70: =F59/F$5 -> 0.4760421 | G70: =G59/G$5 -> 0.43784553 | H70: =H59/H$5 -> 0.43713356 | I70: =I59/I$5 -> 0.46823396 | J70: =J59/J$5 -> 0.45210482 | K70: =K59/K$5 -> 0.48745593 | ... M70: =M59/M$5 -> 0.4774111 | N70: =AVERAGE(D70:M70) -> 0.45451223
B71: Часовая производительность на 1 ед. - чистая
B72: =B61 -> Komatsu PC2000-11R Mining Solutions | C72: м3/час | D72: ='3. Час.произв.'!D26 -> 433.75992 | E72: =D72 -> 433.75992 | F72: =E72 -> 433.75992 | G72: =F72 -> 433.75992 | H72: =G72 -> 433.75992 | I72: =H72 -> 433.75992 | J72: =I72 -> 433.75992 | K72: =J72 -> 433.75992 | L72: =K72 -> 433.75992 | M72: =L72 -> 433.75992
B73: =B62 -> Komatsu PC2000-11R ИСТК | C73: м3/час | D73: ='3. Час.произв.'!E26 -> 433.75992 | E73: =D73 -> 433.75992 | F73: =E73 -> 433.75992 | G73: =F73 -> 433.75992 | H73: =G73 -> 433.75992 | I73: =H73 -> 433.75992 | J73: =I73 -> 433.75992 | K73: =J73 -> 433.75992 | L73: =K73 -> 433.75992 | M73: =L73 -> 433.75992
B74: =B63 -> Zoomlion ZE2000G ОРИКС | C74: м3/час | D74: ='3. Час.произв.'!F26 -> 531.69723 | E74: =D74 -> 531.69723 | F74: =E74 -> 531.69723 | G74: =F74 -> 531.69723 | H74: =G74 -> 531.69723 | I74: =H74 -> 531.69723 | J74: =I74 -> 531.69723 | K74: =J74 -> 531.69723 | L74: =K74 -> 531.69723 | M74: =L74 -> 531.69723
B75: =B64 -> Sany SY2000 АСТ | C75: м3/час | D75: ='3. Час.произв.'!G26 -> 433.75992 | E75: =D75 -> 433.75992 | F75: =E75 -> 433.75992 | G75: =F75 -> 433.75992 | H75: =G75 -> 433.75992 | I75: =H75 -> 433.75992 | J75: =I75 -> 433.75992 | K75: =J75 -> 433.75992 | L75: =K75 -> 433.75992 | M75: =L75 -> 433.75992
B76: =B65 -> Shantui SE2000LCW Строймпорттехника | C76: м3/час | D76: ='3. Час.произв.'!H26 -> 433.75992 | E76: =D76 -> 433.75992 | F76: =E76 -> 433.75992 | G76: =F76 -> 433.75992 | H76: =G76 -> 433.75992 | I76: =H76 -> 433.75992 | J76: =I76 -> 433.75992 | K76: =J76 -> 433.75992 | L76: =K76 -> 433.75992 | M76: =L76 -> 433.75992
B77: =B66 -> TZCO TZ2000 Дзикай | C77: м3/час | D77: ='3. Час.произв.'!I26 -> 531.69723 | E77: =D77 -> 531.69723 | F77: =E77 -> 531.69723 | G77: =F77 -> 531.69723 | H77: =G77 -> 531.69723 | I77: =H77 -> 531.69723 | J77: =I77 -> 531.69723 | K77: =J77 -> 531.69723 | L77: =K77 -> 531.69723 | M77: =L77 -> 531.69723
B78: =B67 -> Komatsu PC2000-11R Огунвэй | C78: м3/час | D78: ='3. Час.произв.'!J26 -> 433.75992 | E78: =D78 -> 433.75992 | F78: =E78 -> 433.75992 | G78: =F78 -> 433.75992 | H78: =G78 -> 433.75992 | I78: =H78 -> 433.75992 | J78: =I78 -> 433.75992 | K78: =J78 -> 433.75992 | L78: =K78 -> 433.75992 | M78: =L78 -> 433.75992
B79: =B68 -> XCMG LYR 2000 Огунвэй | C79: м3/час | D79: ='3. Час.произв.'!K26 -> 433.75992 | E79: =D79 -> 433.75992 | F79: =E79 -> 433.75992 | G79: =F79 -> 433.75992 | H79: =G79 -> 433.75992 | I79: =H79 -> 433.75992 | J79: =I79 -> 433.75992 | K79: =J79 -> 433.75992 | L79: =K79 -> 433.75992 | M79: =L79 -> 433.75992
B80: =B69 -> Hitachi EX2000 Майнтек | C80: м3/час | D80: ='3. Час.произв.'!L26 -> 433.75992 | E80: =D80 -> 433.75992 | F80: =E80 -> 433.75992 | G80: =F80 -> 433.75992 | H80: =G80 -> 433.75992 | I80: =H80 -> 433.75992 | J80: =I80 -> 433.75992 | K80: =J80 -> 433.75992 | L80: =K80 -> 433.75992 | M80: =L80 -> 433.75992
B81: =B70 -> Estar ESE2000 ГПБ Комплект | C81: м3/час | D81: ='3. Час.произв.'!M26 -> 433.75992 | E81: =D81 -> 433.75992 | F81: =E81 -> 433.75992 | G81: =F81 -> 433.75992 | H81: =G81 -> 433.75992 | I81: =H81 -> 433.75992 | J81: =I81 -> 433.75992 | K81: =J81 -> 433.75992 | L81: =K81 -> 433.75992 | M81: =L81 -> 433.75992
B82: Годовая производительность на 1 ед.
B83: =B72 -> Komatsu PC2000-11R Mining Solutions | C83: тыс. м3 | D83: =D72*D50/1000 -> 2213.5159 | E83: =E72*E50/1000 -> 1916.1498 | F83: =F72*F50/1000 -> 1975.1027 | G83: =G72*G50/1000 -> 1829.9658 | H83: =H72*H50/1000 -> 1827.2605 | I83: =I72*I50/1000 -> 1950.7638 | J83: =J72*J50/1000 -> 1884.1473 | K83: =K72*K50/1000 -> 2018.4722 | ... M83: =M72*M50/1000 -> 1985.73 | N83: =AVERAGE(D83:M83) -> 1894.8939 | O83: среднее
B84: =B73 -> Komatsu PC2000-11R ИСТК | C84: тыс. м3 | D84: =D73*D51/1000 -> 2213.5159 | E84: =E73*E51/1000 -> 1916.1498 | F84: =F73*F51/1000 -> 1975.1027 | G84: =G73*G51/1000 -> 1829.9658 | H84: =H73*H51/1000 -> 1827.2605 | I84: =I73*I51/1000 -> 1950.7638 | J84: =J73*J51/1000 -> 1884.1473 | K84: =K73*K51/1000 -> 2018.4722 | ... M84: =M73*M51/1000 -> 1985.73 | N84: =AVERAGE(D84:M84) -> 1894.8939 | O84: среднее
B85: =B74 -> Zoomlion ZE2000G ОРИКС | C85: тыс. м3 | D85: =D74*D52/1000 -> 2509.4897 | E85: =E74*E52/1000 -> 2144.4239 | F85: =F74*F52/1000 -> 2217.2459 | G85: =G74*G52/1000 -> 2039.339 | H85: =H74*H52/1000 -> 2036.0229 | I85: =I74*I52/1000 -> 2186.8532 | J85: =J74*J52/1000 -> 2105.754 | K85: =K74*K52/1000 -> 2270.4078 | ... M85: =M74*M52/1000 -> 2229.7144 | N85: =AVERAGE(D85:M85) -> 2118.7596 | O85: среднее
B86: =B75 -> Sany SY2000 АСТ | C86: тыс. м3 | D86: =D75*D53/1000 -> 2047.2479 | E86: =E75*E53/1000 -> 1749.4263 | F86: =F75*F53/1000 -> 1808.8347 | G86: =G75*G53/1000 -> 1663.6978 | H86: =H75*H53/1000 -> 1660.9925 | I86: =I75*I53/1000 -> 1784.0403 | J86: =J75*J53/1000 -> 1717.8793 | K86: =K75*K53/1000 -> 1852.2043 | ... M86: =M75*M53/1000 -> 1819.0065 | N86: =AVERAGE(D86:M86) -> 1728.4893
B87: =B76 -> Shantui SE2000LCW Строймпорттехника | C87: тыс. м3 | D87: =D76*D54/1000 -> 2047.2479 | E87: =E76*E54/1000 -> 1749.4263 | F87: =F76*F54/1000 -> 1808.8347 | G87: =G76*G54/1000 -> 1663.6978 | H87: =H76*H54/1000 -> 1660.9925 | I87: =I76*I54/1000 -> 1784.0403 | J87: =J76*J54/1000 -> 1717.8793 | K87: =K76*K54/1000 -> 1852.2043 | ... M87: =M76*M54/1000 -> 1819.0065 | N87: =AVERAGE(D87:M87) -> 1728.4893
B88: =B77 -> TZCO TZ2000 Дзикай | C88: тыс. м3 | D88: =D77*D55/1000 -> 2509.4897 | E88: =E77*E55/1000 -> 2144.4239 | F88: =F77*F55/1000 -> 2217.2459 | G88: =G77*G55/1000 -> 2039.339 | H88: =H77*H55/1000 -> 2036.0229 | I88: =I77*I55/1000 -> 2186.8532 | J88: =J77*J55/1000 -> 2105.754 | K88: =K77*K55/1000 -> 2270.4078 | ... M88: =M77*M55/1000 -> 2229.7144 | N88: =AVERAGE(D88:M88) -> 2118.7596
B89: =B78 -> Komatsu PC2000-11R Огунвэй | C89: тыс. м3 | D89: =D78*D56/1000 -> 2213.5159 | E89: =E78*E56/1000 -> 1916.1498 | F89: =F78*F56/1000 -> 1975.1027 | G89: =G78*G56/1000 -> 1829.9658 | H89: =H78*H56/1000 -> 1827.2605 | I89: =I78*I56/1000 -> 1950.7638 | J89: =J78*J56/1000 -> 1884.1473 | K89: =K78*K56/1000 -> 2018.4722 | ... M89: =M78*M56/1000 -> 1985.73 | N89: =AVERAGE(D89:M89) -> 1894.8939
B90: =B79 -> XCMG LYR 2000 Огунвэй | C90: тыс. м3 | D90: =D79*D57/1000 -> 2047.2479 | E90: =E79*E57/1000 -> 1749.4263 | F90: =F79*F57/1000 -> 1808.8347 | G90: =G79*G57/1000 -> 1663.6978 | H90: =H79*H57/1000 -> 1660.9925 | I90: =I79*I57/1000 -> 1784.0403 | J90: =J79*J57/1000 -> 1717.8793 | K90: =K79*K57/1000 -> 1852.2043 | ... M90: =M79*M57/1000 -> 1819.0065 | N90: =AVERAGE(D90:M90) -> 1728.4893
B91: =B80 -> Hitachi EX2000 Майнтек | C91: тыс. м3 | D91: =D80*D58/1000 -> 1772.6089 | E91: =E80*E58/1000 -> 1753.4456 | F91: =F80*F58/1000 -> 1892.3798 | G91: =G80*G58/1000 -> 1509.113 | H91: =H80*H58/1000 -> 1648.3507 | I91: =I80*I58/1000 -> 1973.9005 | J91: =J80*J58/1000 -> 1384.7482 | K91: =K80*K58/1000 -> 1700.2871 | ... M91: =M80*M58/1000 -> 1900.8067 | N91: =AVERAGE(D91:M91) -> 1732.114
B92: =B81 -> Estar ESE2000 ГПБ Комплект | C92: тыс. м3 | D92: =D81*D59/1000 -> 2047.2479 | E92: =E81*E59/1000 -> 1749.4263 | F92: =F81*F59/1000 -> 1808.8347 | G92: =G81*G59/1000 -> 1663.6978 | H92: =H81*H59/1000 -> 1660.9925 | I92: =I81*I59/1000 -> 1784.0403 | J92: =J81*J59/1000 -> 1717.8793 | K92: =K81*K59/1000 -> 1852.2043 | ... M92: =M81*M59/1000 -> 1819.0065 | N92: =AVERAGE(D92:M92) -> 1728.4893

Sheet 3. Час.произв.
B1: Часовая производительность погрузочной техники
B4: Модель экскаватора | C4: Ед.изм. | D4: ='1. Сводная_аннуитеты'!D18 -> Komatsu PC2000-11R Mining Solutions | E4: ='1. Сводная_аннуитеты'!E18 -> Komatsu PC2000-11R ИСТК | F4: ='1. Сводная_аннуитеты'!F18 -> Zoomlion ZE2000G ОРИКС | G4: ='1. Сводная_аннуитеты'!G18 -> Sany SY2000 АСТ | H4: ='1. Сводная_аннуитеты'!H18 -> Shantui SE2000LCW Строймпорттехника | I4: ='1. Сводная_аннуитеты'!I18 -> TZCO TZ2000 Дзикай | J4: ='1. Сводная_аннуитеты'!J18 -> Komatsu PC2000-11R Огунвэй | K4: ='1. Сводная_аннуитеты'!K18 -> XCMG LYR 2000 Огунвэй | ... M4: ='1. Сводная_аннуитеты'!M18 -> Estar ESE2000 ГПБ Комплект
B5: Объём ковша - в расчете | C5: м3 | D5: =D6 -> 10 | E5: =E6 -> 10 | F5: =F6 -> 12 | G5: =G6 -> 10 | H5: =H6 -> 9.6 | I5: =I6 -> 12 | J5: =J6 -> 10 | K5: =K6 -> 10 | ... M5: =M6 -> 10
B6: Объём ковша - геометрический | C6: м3 | D6: =E6 -> 10 | E6: ='PC2000-11R ИСТК'!D5 -> 10 | F6: =Zooml_Орикс!D5 -> 12 | G6: ='Sany АСТ'!D5 -> 10 | H6: ='Shantui Стройимп'!D5 -> 9.6 | I6: ='TZCO Дзикай'!D5 -> 12 | J6: =E6 -> 10 | K6: =J6 -> 10 | L6: 9.5 | M6: =K6 -> 10
B7: Объём ковша - с шапкой | C7: м3 | D7: ='PC2000-8 MS'!D6 -> 12 | E7: ='PC2000-11R ИСТК'!D6 -> 12 | F7: =Zooml_Орикс!D6 -> 13 | G7: ='Sany АСТ'!D6 -> 12 | H7: ='Shantui Стройимп'!D6 -> 12 | I7: ='TZCO Дзикай'!D6 -> 13.5 | J7: =E7 -> 12 | K7: =J7 -> 12 | L7: 12 | M7: ='Estar ГПБ'!D6 -> 12
B8: Грузоподъёмность самосвала | C8: тн | D8: 136 | E8: =D8 -> 136 | F8: =E8 -> 136 | G8: =F8 -> 136 | H8: =G8 -> 136 | I8: =H8 -> 136 | J8: =I8 -> 136 | K8: =J8 -> 136 | L8: =K8 -> 136 | M8: =K8 -> 136
B9: Плотность породы | C9: кг/м3 | D9: 2.787 | E9: =D9 -> 2.787 | F9: =E9 -> 2.787 | G9: =F9 -> 2.787 | H9: =G9 -> 2.787 | I9: =H9 -> 2.787 | J9: =I9 -> 2.787 | K9: =J9 -> 2.787 | L9: =K9 -> 2.787 | M9: =K9 -> 2.787 | N9: балансировка КБЕ
B10: Коэффициент разрыхления | C10: коэф. | D10: 1.5 | E10: =D10 -> 1.5 | F10: =E10 -> 1.5 | G10: =F10 -> 1.5 | H10: =G10 -> 1.5 | I10: =H10 -> 1.5 | J10: =I10 -> 1.5 | K10: =J10 -> 1.5 | L10: =K10 -> 1.5 | M10: =K10 -> 1.5 | N10: балансировка КБЕ
B11: Коэффициент наполнения ковша | C11: % | D11: 0.9 | E11: =D11 -> 0.9 | F11: =E11 -> 0.9 | G11: =F11 -> 0.9 | H11: =G11 -> 0.9 | I11: =H11 -> 0.9 | J11: =I11 -> 0.9 | K11: =J11 -> 0.9 | L11: =K11 -> 0.9 | M11: =K11 -> 0.9 | N11: балансировка КБЕ
B12: Коэффициент экскавации | C12: % | D12: =D11/D10 -> 0.6 | E12: =E11/E10 -> 0.6 | F12: =F11/F10 -> 0.6 | G12: =G11/G10 -> 0.6 | H12: =H11/H10 -> 0.6 | I12: =I11/I10 -> 0.6 | J12: =J11/J10 -> 0.6 | K12: =K11/K10 -> 0.6 | ... M12: =M11/M10 -> 0.6
B13: Коэффициент потерь горной массы при экскавации | C13: % | D13: 0.9 | E13: =D13 -> 0.9 | F13: =E13 -> 0.9 | G13: =F13 -> 0.9 | H13: =G13 -> 0.9 | I13: =H13 -> 0.9 | J13: =I13 -> 0.9 | K13: =J13 -> 0.9 | L13: =K13 -> 0.9 | M13: =K13 -> 0.9 | N13: балансировка КБЕ
B14: Порода в ковше | C14: тн | D14: =D5*D9*D12*D13 -> 15.0498 | E14: =E5*E9*E12*E13 -> 15.0498 | F14: =F5*F9*F12*F13 -> 18.05976 | G14: =G5*G9*G12*G13 -> 15.0498 | H14: =H5*H9*H12*H13 -> 14.447808 | I14: =I5*I9*I12*I13 -> 18.05976 | J14: =J5*J9*J12*J13 -> 15.0498 | K14: =K5*K9*K12*K13 -> 15.0498 | ... M14: =M5*M9*M12*M13 -> 15.0498
B15: Коэффициент использования грузоподъемности АС | C15: коэф. | D15: 1 | E15: =D15 -> 1 | F15: =E15 -> 1 | G15: =F15 -> 1 | H15: =G15 -> 1 | I15: =H15 -> 1 | J15: =I15 -> 1 | K15: =J15 -> 1 | L15: =K15 -> 1 | M15: =K15 -> 1 | N15: балансировка КБЕ
B16: Масса породы в самосвале | C16: тн | D16: =D8*D15 -> 136 | E16: =E8*E15 -> 136 | F16: =F8*F15 -> 136 | G16: =G8*G15 -> 136 | H16: =H8*H15 -> 136 | I16: =I8*I15 -> 136 | J16: =J8*J15 -> 136 | K16: =K8*K15 -> 136 | ... M16: =M8*M15 -> 136
B17: Кол-во ковшей, дробное | C17: шт. | D17: =D16/D14 -> 9.0366649 | E17: =E16/E14 -> 9.0366649 | F17: =F16/F14 -> 7.5305541 | G17: =G16/G14 -> 9.0366649 | H17: =H16/H14 -> 9.4131926 | I17: =I16/I14 -> 7.5305541 | J17: =J16/J14 -> 9.0366649 | K17: =K16/K14 -> 9.0366649 | ... M17: =M16/M14 -> 9.0366649
B18: Кол-во ковшей (циклов погрузки), практически | C18: шт. | D18: =ROUNDUP(D17,0) -> 10 | E18: =ROUNDUP(E17,0) -> 10 | F18: =ROUNDUP(F17,0) -> 8 | G18: =ROUNDUP(G17,0) -> 10 | H18: =ROUNDUP(H17,0) -> 10 | I18: =ROUNDUP(I17,0) -> 8 | J18: =ROUNDUP(J17,0) -> 10 | K18: =ROUNDUP(K17,0) -> 10 | ... M18: =ROUNDUP(M17,0) -> 10
B19: Время цикла | C19: сек | D19: 37.3 | E19: =D19 -> 37.3 | F19: =E19 -> 37.3 | G19: =F19 -> 37.3 | H19: =G19 -> 37.3 | I19: =H19 -> 37.3 | J19: =I19 -> 37.3 | K19: =J19 -> 37.3 | L19: =K19 -> 37.3 | M19: =K19 -> 37.3
B20: Время постановки самосвала под загрузку (время оборота а/с) | C20: сек | D20: 32 | E20: =D20 -> 32 | F20: =D20 -> 32 | G20: =E20 -> 32 | H20: =F20 -> 32 | I20: =G20 -> 32 | J20: =H20 -> 32 | K20: =I20 -> 32 | L20: =J20 -> 32 | M20: =J20 -> 32 | N20: балансировка КБЕ
B21: Максимальная теоретическая производительность | C21: а/с за час работы | D21: =3600/(D18*D19+D20) -> 8.8888889 | E21: =3600/(E18*E19+E20) -> 8.8888889 | F21: =3600/(F18*F19+F20) -> 10.895884 | G21: =3600/(G18*G19+G20) -> 8.8888889 | H21: =3600/(H18*H19+H20) -> 8.8888889 | I21: =3600/(I18*I19+I20) -> 10.895884 | J21: =3600/(J18*J19+J20) -> 8.8888889 | K21: =3600/(K18*K19+K20) -> 8.8888889 | ... M21: =3600/(M18*M19+M20) -> 8.8888889
C22: тн/час | D22: =D14*D17*D21 -> 1208.8889 | E22: =E14*E17*E21 -> 1208.8889 | F22: =F14*F17*F21 -> 1481.8402 | G22: =G14*G17*G21 -> 1208.8889 | H22: =H14*H17*H21 -> 1208.8889 | I22: =I14*I17*I21 -> 1481.8402 | J22: =J14*J17*J21 -> 1208.8889 | K22: =K14*K17*K21 -> 1208.8889 | ... M22: =M14*M17*M21 -> 1208.8889
C23: м3/час | D23: =D22/D9 -> 433.75992 | E23: =E22/E9 -> 433.75992 | F23: =F22/F9 -> 531.69723 | G23: =G22/G9 -> 433.75992 | H23: =H22/H9 -> 433.75992 | I23: =I22/I9 -> 531.69723 | J23: =J22/J9 -> 433.75992 | K23: =K22/K9 -> 433.75992 | ... M23: =M22/M9 -> 433.75992
B24: Теоретическая производительность | C24: а/с за час работы | D24: =3600/(D18*D19+D20) -> 8.8888889 | E24: =3600/(E18*E19+E20) -> 8.8888889 | F24: =3600/(F18*F19+F20) -> 10.895884 | G24: =3600/(G18*G19+G20) -> 8.8888889 | H24: =3600/(H18*H19+H20) -> 8.8888889 | I24: =3600/(I18*I19+I20) -> 10.895884 | J24: =3600/(J18*J19+J20) -> 8.8888889 | K24: =3600/(K18*K19+K20) -> 8.8888889 | ... M24: =3600/(M18*M19+M20) -> 8.8888889
C25: тн/час | D25: =D14*D17*D24 -> 1208.8889 | E25: =E14*E17*E24 -> 1208.8889 | F25: =F14*F17*F24 -> 1481.8402 | G25: =G14*G17*G24 -> 1208.8889 | H25: =H14*H17*H24 -> 1208.8889 | I25: =I14*I17*I24 -> 1481.8402 | J25: =J14*J17*J24 -> 1208.8889 | K25: =K14*K17*K24 -> 1208.8889 | ... M25: =M14*M17*M24 -> 1208.8889
C26: м3/час | D26: =D25/D9 -> 433.75992 | E26: =E25/E9 -> 433.75992 | F26: =F25/F9 -> 531.69723 | G26: =G25/G9 -> 433.75992 | H26: =H25/H9 -> 433.75992 | I26: =I25/I9 -> 531.69723 | J26: =J25/J9 -> 433.75992 | K26: =K25/K9 -> 433.75992 | ... M26: =M25/M9 -> 433.75992
B27: Время погрузки самосвала | C27: мин | D27: =D18*D19/60 -> 6.2166667 | E27: =E18*E19/60 -> 6.2166667 | F27: =F18*F19/60 -> 4.9733333 | G27: =G18*G19/60 -> 6.2166667 | H27: =H18*H19/60 -> 6.2166667 | I27: =I18*I19/60 -> 4.9733333 | J27: =J18*J19/60 -> 6.2166667 | K27: =K18*K19/60 -> 6.2166667 | ... M27: =M18*M19/60 -> 6.2166667
B29: Годовая (1-ый год) | C29: тыс.м3 | D29: =VLOOKUP(D$4,'2. Произв-сть экскаваторов'!$B$83:$D$92,3,FALSE) -> 2213.5159 | E29: =VLOOKUP(E$4,'2. Произв-сть экскаваторов'!$B$83:$D$92,3,FALSE) -> 2213.5159 | F29: =VLOOKUP(F$4,'2. Произв-сть экскаваторов'!$B$83:$D$92,3,FALSE) -> 2509.4897 | G29: =VLOOKUP(G$4,'2. Произв-сть экскаваторов'!$B$83:$D$92,3,FALSE) -> 2047.2479 | H29: =VLOOKUP(H$4,'2. Произв-сть экскаваторов'!$B$83:$D$92,3,FALSE) -> 2047.2479 | I29: =VLOOKUP(I$4,'2. Произв-сть экскаваторов'!$B$83:$D$92,3,FALSE) -> 2509.4897 | J29: =VLOOKUP(J$4,'2. Произв-сть экскаваторов'!$B$83:$D$92,3,FALSE) -> 2213.5159 | K29: =VLOOKUP(K$4,'2. Произв-сть экскаваторов'!$B$83:$D$92,3,FALSE) -> 2047.2479 | L29: ='2. Произв-сть экскаваторов'!D91 -> 1772.6089 | M29: =VLOOKUP(M$4,'2. Произв-сть экскаваторов'!$B$83:$D$92,3,FALSE) -> 2047.2479
D32: =D4 -> Komatsu PC2000-11R Mining Solutions | E32: =E4 -> Komatsu PC2000-11R ИСТК | F32: =F4 -> Zoomlion ZE2000G ОРИКС | G32: =G4 -> Sany SY2000 АСТ | H32: =H4 -> Shantui SE2000LCW Строймпорттехника | I32: =I4 -> TZCO TZ2000 Дзикай | J32: =J4 -> Komatsu PC2000-11R Огунвэй | K32: =K4 -> XCMG LYR 2000 Огунвэй | M32: =M4 -> Estar ESE2000 ГПБ Комплект
B33: Время цикла от постащиков | C33: сек | D33: ='PC2000-8 MS'!E13 -> 27 | E33: ='PC2000-11R ИСТК'!D13 -> 29 | F33: =Zooml_Орикс!D13 -> 30 | G33: ='Sany АСТ'!E13 -> 29.25 | H33: ='Shantui Стройимп'!D13 -> 25 | I33: ='TZCO Дзикай'!D13 -> 0 | M33: ='Estar ГПБ'!D11 -> 26
B39: Сухой Лог ОПР, прямая лопата. 2025
D67: =D69*1.5 -> 39.39
D68: 6.5
B69: PC-1250: Красноярск и Верни/СЛ ОПР - обратная лопата. 2025 | D69: 26.26
B121: Часовая PC-2000, факт-2025

Sheet 4. Аннуитеты
D1: 2026 | E1: =D1+1 -> 2027 | F1: =E1+1 -> 2028 | G1: =F1+1 -> 2029 | H1: =G1+1 -> 2030 | I1: =H1+1 -> 2031 | J1: =I1+1 -> 2032 | K1: =J1+1 -> 2033 | L1: =K1+1 -> 2034 | ... N1: =M1+1 -> 2036 | O1: 1.35962
E2: 1 | F2: =E2+1 -> 2 | G2: =F2+1 -> 3 | H2: =G2+1 -> 4 | I2: =H2+1 -> 5 | J2: =I2+1 -> 6 | K2: =J2+1 -> 7 | L2: =K2+1 -> 8 | M2: =L2+1 -> 9 | N2: =M2+1 -> 10
B3: Аннуитет затрат экскаватора
B5: ='1. Сводная_аннуитеты'!D18 -> Komatsu PC2000-11R Mining Solutions
B6: Показатель | C6: Ед. изм. | D6: Период | P6: =B5 -> Komatsu PC2000-11R Mining Solutions
D7: 0 | E7: =D7+1 -> 1 | F7: =E7+1 -> 2 | G7: =F7+1 -> 3 | H7: =G7+1 -> 4 | I7: =H7+1 -> 5 | J7: =I7+1 -> 6 | K7: =J7+1 -> 7 | L7: =K7+1 -> 8 | ... N7: =M7+1 -> 10 | P7: =P6 -> Komatsu PC2000-11R Mining Solutions
B8: Календарный фонд времени | E8: ='2. Произв-сть экскаваторов'!D$5 -> 8760 | F8: ='2. Произв-сть экскаваторов'!E$5 -> 8784 | G8: ='2. Произв-сть экскаваторов'!F$5 -> 8760 | H8: ='2. Произв-сть экскаваторов'!G$5 -> 8760 | I8: ='2. Произв-сть экскаваторов'!H$5 -> 8760 | J8: ='2. Произв-сть экскаваторов'!I$5 -> 8784 | K8: ='2. Произв-сть экскаваторов'!J$5 -> 8760 | L8: ='2. Произв-сть экскаваторов'!K$5 -> 8760 | ... N8: ='2. Произв-сть экскаваторов'!M$5 -> 8784 | P8: =P7 -> Komatsu PC2000-11R Mining Solutions
B9: КТГ | C9: % | E9: ='2. Произв-сть экскаваторов'!D18 -> 0.92406268 | F9: ='2. Произв-сть экскаваторов'!E18 -> 0.79773755 | G9: ='2. Произв-сть экскаваторов'!F18 -> 0.82453381 | H9: ='2. Произв-сть экскаваторов'!G18 -> 0.76394441 | I9: ='2. Произв-сть экскаваторов'!H18 -> 0.76281505 | J9: ='2. Произв-сть экскаваторов'!I18 -> 0.81214813 | K9: ='2. Произв-сть экскаваторов'!J18 -> 0.78656324 | L9: ='2. Произв-сть экскаваторов'!K18 -> 0.84263903 | ... N9: ='2. Произв-сть экскаваторов'!M18 -> 0.82670539 | P9: =P8 -> Komatsu PC2000-11R Mining Solutions
B10: КИО | C10: % | E10: ='2. Произв-сть экскаваторов'!D61 -> 0.58254452 | F10: ='2. Произв-сть экскаваторов'!E61 -> 0.50290705 | G10: ='2. Произв-сть экскаваторов'!F61 -> 0.51979986 | H10: ='2. Произв-сть экскаваторов'!G61 -> 0.48160329 | I10: ='2. Произв-сть экскаваторов'!H61 -> 0.48089132 | J10: ='2. Произв-сть экскаваторов'!I61 -> 0.51199171 | K10: ='2. Произв-сть экскаваторов'!J61 -> 0.49586257 | L10: ='2. Произв-сть экскаваторов'!K61 -> 0.53121369 | ... N10: ='2. Произв-сть экскаваторов'!M61 -> 0.52116886 | P10: =P9 -> Komatsu PC2000-11R Mining Solutions
B11: Производительность | C11: тыс.м3 | E11: ='2. Произв-сть экскаваторов'!D83 -> 2213.5159 | F11: ='2. Произв-сть экскаваторов'!E83 -> 1916.1498 | G11: ='2. Произв-сть экскаваторов'!F83 -> 1975.1027 | H11: ='2. Произв-сть экскаваторов'!G83 -> 1829.9658 | I11: ='2. Произв-сть экскаваторов'!H83 -> 1827.2605 | J11: ='2. Произв-сть экскаваторов'!I83 -> 1950.7638 | K11: ='2. Произв-сть экскаваторов'!J83 -> 1884.1473 | L11: ='2. Произв-сть экскаваторов'!K83 -> 2018.4722 | ... N11: ='2. Произв-сть экскаваторов'!M83 -> 1985.73 | P11: =P10 -> Komatsu PC2000-11R Mining Solutions
B12: Операционный денежный поток | C12: тыс. руб. | E12: =E88+E89-E84 -> 19274.311 | F12: =F88+F89-F84 -> 18894.341 | G12: =G88+G89-G84 -> 47530.209 | H12: =H88+H89-H84 -> 91739.297 | I12: =I88+I89-I84 -> 22119.593 | J12: =J88+J89-J84 -> 61283.154 | K12: =K88+K89-K84 -> 32602.326 | L12: =L88+L89-L84 -> 105132.38 | ... N12: =N88+N89-N84 -> 31212.191 | P12: =P11 -> Komatsu PC2000-11R Mining Solutions
B13: ТО, ТР, ППР, вкл смазочные | C13: тыс. руб. | E13: =E15 -> 5653.5622 | F13: =F15 -> 8598.4209 | G13: =G15 -> 45686.378 | H13: =H15 -> 105913.26 | I13: =I15 -> 14027.4 | J13: =J15 -> 48631.237 | K13: =K15 -> 8598.4209 | L13: =L15 -> 102968.4 | ... N13: =N15 -> 5653.5622 | P13: =P12 -> Komatsu PC2000-11R Mining Solutions
B14: ремонты и ТО | C14: тыс.долл./год | E14: =E155 -> 74.266046 | F14: =F155 -> 112.95016 | G14: =G155 -> 600.14316 | H14: =H155 -> 1391.2926 | I14: =I155 -> 184.26605 | J14: =J155 -> 638.82727 | K14: =K155 -> 112.95016 | L14: =L155 -> 1352.6085 | ... N14: =N155 -> 74.266046 | P14: =P13 -> Komatsu PC2000-11R Mining Solutions
C15: тыс.руб./год | E15: =E14*Макро!D$4 -> 5653.5622 | F15: =F14*Макро!E$4 -> 8598.4209 | G15: =G14*Макро!F$4 -> 45686.378 | H15: =H14*Макро!G$4 -> 105913.26 | I15: =I14*Макро!H$4 -> 14027.4 | J15: =J14*Макро!I$4 -> 48631.237 | K15: =K14*Макро!J$4 -> 8598.4209 | L15: =L14*Макро!K$4 -> 102968.4 | ... N15: =N14*Макро!M$4 -> 5653.5622 | P15: =P14 -> Komatsu PC2000-11R Mining Solutions
B16: затраты на сервис: ремонты и ТО | C16: тыс.руб. | E16: =E18 -> 2009.7211 | F16: =F18 -> 2142.9413 | G16: =G18 -> 2525.4734 | H16: =H18 -> 2993.6471 | I16: =I18 -> 2085.8469 | J16: =J18 -> 2658.6936 | K16: =K18 -> 2142.9413 | L16: =L18 -> 2860.4269 | ... N16: =N18 -> 2009.7211 | P16: =P15 -> Komatsu PC2000-11R Mining Solutions
B17: трудозатраты | C17: тыс.долл./год | E17: =E158 -> 26.4 | F17: =F158 -> 28.15 | G17: =G158 -> 33.175 | H17: =H158 -> 39.325 | I17: =I158 -> 27.4 | J17: =J158 -> 34.925 | K17: =K158 -> 28.15 | L17: =L158 -> 37.575 | ... N17: =N158 -> 26.4 | P17: =P16 -> Komatsu PC2000-11R Mining Solutions
C18: тыс.руб./год | E18: =E17*Макро!D$4 -> 2009.7211 | F18: =F17*Макро!E$4 -> 2142.9413 | G18: =G17*Макро!F$4 -> 2525.4734 | H18: =H17*Макро!G$4 -> 2993.6471 | I18: =I17*Макро!H$4 -> 2085.8469 | J18: =J17*Макро!I$4 -> 2658.6936 | K18: =K17*Макро!J$4 -> 2142.9413 | L18: =L17*Макро!K$4 -> 2860.4269 | ... N18: =N17*Макро!M$4 -> 2009.7211 | P18: =P17 -> Komatsu PC2000-11R Mining Solutions
B19: расходники на ковш | C19: тыс.руб. | E19: =E21+E25 -> 1931.5402 | F19: =F21+F25 -> 1672.0551 | G19: =G21+G25 -> 1723.498 | H19: =H21+H25 -> 1596.8498 | I19: =I21+I25 -> 1594.4892 | J19: =J21+J25 -> 1702.2596 | K19: =K21+K25 -> 1644.1293 | L19: =L21+L25 -> 1761.3428 | ... N19: =N21+N25 -> 1732.7715 | P19: =P18 -> Komatsu PC2000-11R Mining Solutions
P20: =P19 -> Komatsu PC2000-11R Mining Solutions
B21: расходники на ковш (зубья, коронки, фиксаторы…) | C21: тыс.руб. | E21: =E24*E11 -> 1931.5402 | F21: =F24*F11 -> 1672.0551 | G21: =G24*G11 -> 1723.498 | H21: =H24*H11 -> 1596.8498 | I21: =I24*I11 -> 1594.4892 | J21: =J24*J11 -> 1702.2596 | K21: =K24*K11 -> 1644.1293 | L21: =L24*L11 -> 1761.3428 | ... N21: =N24*N11 -> 1732.7715 | P21: =P20 -> Komatsu PC2000-11R Mining Solutions
B22: удельный расход | C22: шт/тыс.м3 | P22: =P21 -> Komatsu PC2000-11R Mining Solutions
B23: расход | C23: шт/год | P23: =P22 -> Komatsu PC2000-11R Mining Solutions
B24: цена за шт. | C24: руб./м3 | D24: ='Зубья ковша, коронки'!$P$57 -> 0.011462761 | E24: =$D24*Макро!D$4 -> 0.87261185 | F24: =$D24*Макро!E$4 -> 0.87261185 | G24: =$D24*Макро!F$4 -> 0.87261185 | H24: =$D24*Макро!G$4 -> 0.87261185 | I24: =$D24*Макро!H$4 -> 0.87261185 | J24: =$D24*Макро!I$4 -> 0.87261185 | K24: =$D24*Макро!J$4 -> 0.87261185 | L24: =$D24*Макро!K$4 -> 0.87261185 | ... N24: =$D24*Макро!M$4 -> 0.87261185 | P24: =P23 -> Komatsu PC2000-11R Mining Solutions
B25: другое | C25: тыс.руб. | E25: =E26*E27/1000 -> 0 | F25: =F26*F27/1000 -> 0 | G25: =G26*G27/1000 -> 0 | H25: =H26*H27/1000 -> 0 | I25: =I26*I27/1000 -> 0 | J25: =J26*J27/1000 -> 0 | K25: =K26*K27/1000 -> 0 | L25: =L26*L27/1000 -> 0 | ... N25: =N26*N27/1000 -> 0 | P25: =P24 -> Komatsu PC2000-11R Mining Solutions
B26: удельный расход | C26: комплект | P26: =P25 -> Komatsu PC2000-11R Mining Solutions
B27: цена за компл. | C27: руб.компл. | P27: =P26 -> Komatsu PC2000-11R Mining Solutions
C28: тыс.руб. | P28: =P27 -> Komatsu PC2000-11R Mining Solutions
B29: удельный расход | C29: мчас/комплект | P29: =P28 -> Komatsu PC2000-11R Mining Solutions
B30: расход | C30: компл./год | P30: =P29 -> Komatsu PC2000-11R Mining Solutions
B31: цена за компл. | C31: руб.компл. | P31: =P30 -> Komatsu PC2000-11R Mining Solutions
C32: тыс.руб. | P32: =P31 -> Komatsu PC2000-11R Mining Solutions
P33: =P32 -> Komatsu PC2000-11R Mining Solutions
B34: расход | C34: компл./год | P34: =P33 -> Komatsu PC2000-11R Mining Solutions
B35: цена за компл. | C35: руб.компл. | P35: =P34 -> Komatsu PC2000-11R Mining Solutions
P36: =P35 -> Komatsu PC2000-11R Mining Solutions
P37: =P36 -> Komatsu PC2000-11R Mining Solutions
P38: =P37 -> Komatsu PC2000-11R Mining Solutions
B39: Дизтопливо | C39: тыс.руб. | E39: =E41 -> 24752.087 | F39: =F41 -> 21426.866 | G39: =G41 -> 22086.091 | H39: =H41 -> 20463.134 | I39: =I41 -> 20432.883 | J39: =J41 -> 21813.927 | K39: =K41 -> 21069.005 | L39: =L41 -> 22571.06 | ... N39: =N41 -> 22204.929 | P39: =P38 -> Komatsu PC2000-11R Mining Solutions
P40: =P39 -> Komatsu PC2000-11R Mining Solutions
B41: расход (факт кг/час) | C41: тыс.руб. | E41: =E43*E44 -> 24752.087 | F41: =F43*F44 -> 21426.866 | G41: =G43*G44 -> 22086.091 | H41: =H43*H44 -> 20463.134 | I41: =I43*I44 -> 20432.883 | J41: =J43*J44 -> 21813.927 | K41: =K43*K44 -> 21069.005 | L41: =L43*L44 -> 22571.06 | ... N41: =N43*N44 -> 22204.929 | P41: =P40 -> Komatsu PC2000-11R Mining Solutions
B42: удельный расход | C42: кг/час | D42: ='МТР, ФЗП'!$E$6 -> 88.464215 | E42: =D42 -> 88.464215 | F42: =E42 -> 88.464215 | G42: =F42 -> 88.464215 | H42: =G42 -> 88.464215 | I42: =H42 -> 88.464215 | J42: =I42 -> 88.464215 | K42: =J42 -> 88.464215 | L42: =K42 -> 88.464215 | ... N42: =M42 -> 88.464215 | P42: =P41 -> Komatsu PC2000-11R Mining Solutions | S42: факт-2019 Красноярск (похож на удельный в час Алдана-2025)
B43: Расход | C43: тн | E43: =E8*E10*E42/1000 -> 451.44085 | F43: =F8*F10*F42/1000 -> 390.79381 | G43: =G8*G10*G42/1000 -> 402.81709 | H43: =H8*H10*H42/1000 -> 373.2168 | I43: =I8*I10*I42/1000 -> 372.66506 | J43: =J8*J10*J42/1000 -> 397.85323 | K43: =K8*K10*K42/1000 -> 384.26698 | L43: =L8*L10*L42/1000 -> 411.6622 | ... N43: =N8*N10*N42/1000 -> 404.98451 | P43: =P42 -> Komatsu PC2000-11R Mining Solutions
B44: Цена | C44: руб./кг | D44: ='МТР, ФЗП'!$E$17 -> 54.829081 | E44: =$D44 -> 54.829081 | F44: =$D44 -> 54.829081 | G44: =$D44 -> 54.829081 | H44: =$D44 -> 54.829081 | I44: =$D44 -> 54.829081 | J44: =$D44 -> 54.829081 | K44: =$D44 -> 54.829081 | L44: =$D44 -> 54.829081 | ... N44: =$D44 -> 54.829081 | P44: =P43 -> Komatsu PC2000-11R Mining Solutions | S44: факт-2025 КБЕ
P45: =P44 -> Komatsu PC2000-11R Mining Solutions
P46: =P45 -> Komatsu PC2000-11R Mining Solutions
P47: =P46 -> Komatsu PC2000-11R Mining Solutions
P48: =P47 -> Komatsu PC2000-11R Mining Solutions
P49: =P48 -> Komatsu PC2000-11R Mining Solutions
P50: =P49 -> Komatsu PC2000-11R Mining Solutions
P51: =P50 -> Komatsu PC2000-11R Mining Solutions
P52: =P51 -> Komatsu PC2000-11R Mining Solutions
P53: =P52 -> Komatsu PC2000-11R Mining Solutions
P54: =P53 -> Komatsu PC2000-11R Mining Solutions
B55: Смазочные | C55: тыс.руб. | E55: =SUMPRODUCT(E64:E69,E71:E76)/1000 -> 0 | F55: =SUMPRODUCT(F64:F69,F71:F76)/1000 -> 0 | G55: =SUMPRODUCT(G64:G69,G71:G76)/1000 -> 0 | H55: =SUMPRODUCT(H64:H69,H71:H76)/1000 -> 0 | I55: =SUMPRODUCT(I64:I69,I71:I76)/1000 -> 0 | J55: =SUMPRODUCT(J64:J69,J71:J76)/1000 -> 0 | K55: =SUMPRODUCT(K64:K69,K71:K76)/1000 -> 0 | L55: =SUMPRODUCT(L64:L69,L71:L76)/1000 -> 0 | ... N55: =SUMPRODUCT(N64:N69,N71:N76)/1000 -> 0 | P55: =P54 -> Komatsu PC2000-11R Mining Solutions | S55: в ремонтах | W55: =E55-V55 -> 0
B56: удельный расход | P56: =P55 -> Komatsu PC2000-11R Mining Solutions
C57: л/час | P57: =P56 -> Komatsu PC2000-11R Mining Solutions
C58: л/час | P58: =P57 -> Komatsu PC2000-11R Mining Solutions
C59: л/час | P59: =P58 -> Komatsu PC2000-11R Mining Solutions
C60: кг/час | P60: =P59 -> Komatsu PC2000-11R Mining Solutions
C61: л/час | P61: =P60 -> Komatsu PC2000-11R Mining Solutions
P62: =P61 -> Komatsu PC2000-11R Mining Solutions
B63: абсолютный расход | P63: =P62 -> Komatsu PC2000-11R Mining Solutions
B64: =B57 -> 0 | C64: л | E64: =E8*E10*E57 -> 0 | F64: =F8*F10*F57 -> 0 | G64: =G8*G10*G57 -> 0 | H64: =H8*H10*H57 -> 0 | I64: =I8*I10*I57 -> 0 | J64: =J8*J10*J57 -> 0 | K64: =K8*K10*K57 -> 0 | L64: =L8*L10*L57 -> 0 | ... N64: =N8*N10*N57 -> 0 | P64: =P63 -> Komatsu PC2000-11R Mining Solutions
B65: =B58 -> 0 | C65: л | E65: =E8*E10*E58 -> 0 | F65: =F8*F10*F58 -> 0 | G65: =G8*G10*G58 -> 0 | H65: =H8*H10*H58 -> 0 | I65: =I8*I10*I58 -> 0 | J65: =J8*J10*J58 -> 0 | K65: =K8*K10*K58 -> 0 | L65: =L8*L10*L58 -> 0 | ... N65: =N8*N10*N58 -> 0 | P65: =P64 -> Komatsu PC2000-11R Mining Solutions
B66: =B59 -> 0 | C66: л | E66: =E8*E10*E59 -> 0 | F66: =F8*F10*F59 -> 0 | G66: =G8*G10*G59 -> 0 | H66: =H8*H10*H59 -> 0 | I66: =I8*I10*I59 -> 0 | J66: =J8*J10*J59 -> 0 | K66: =K8*K10*K59 -> 0 | L66: =L8*L10*L59 -> 0 | ... N66: =N8*N10*N59 -> 0 | P66: =P65 -> Komatsu PC2000-11R Mining Solutions
B67: =B60 -> 0 | C67: кг | E67: =E8*E10*E60 -> 0 | F67: =F8*F10*F60 -> 0 | G67: =G8*G10*G60 -> 0 | H67: =H8*H10*H60 -> 0 | I67: =I8*I10*I60 -> 0 | J67: =J8*J10*J60 -> 0 | K67: =K8*K10*K60 -> 0 | L67: =L8*L10*L60 -> 0 | ... N67: =N8*N10*N60 -> 0 | P67: =P66 -> Komatsu PC2000-11R Mining Solutions
B68: =B61 -> 0 | C68: л | E68: =E8*E10*E61 -> 0 | F68: =F8*F10*F61 -> 0 | G68: =G8*G10*G61 -> 0 | H68: =H8*H10*H61 -> 0 | I68: =I8*I10*I61 -> 0 | J68: =J8*J10*J61 -> 0 | K68: =K8*K10*K61 -> 0 | L68: =L8*L10*L61 -> 0 | ... N68: =N8*N10*N61 -> 0 | P68: =P67 -> Komatsu PC2000-11R Mining Solutions
B69: =B62 -> 0 | E69: =E8*E10*E62 -> 0 | F69: =F8*F10*F62 -> 0 | G69: =G8*G10*G62 -> 0 | H69: =H8*H10*H62 -> 0 | I69: =I8*I10*I62 -> 0 | J69: =J8*J10*J62 -> 0 | K69: =K8*K10*K62 -> 0 | L69: =L8*L10*L62 -> 0 | ... N69: =N8*N10*N62 -> 0 | P69: =P68 -> Komatsu PC2000-11R Mining Solutions
B70: цена за ед. | P70: =P69 -> Komatsu PC2000-11R Mining Solutions
B71: =B64 -> 0 | C71: руб./л | P71: =P70 -> Komatsu PC2000-11R Mining Solutions
B72: =B65 -> 0 | C72: руб./л | P72: =P71 -> Komatsu PC2000-11R Mining Solutions
B73: =B66 -> 0 | C73: руб./л | P73: =P72 -> Komatsu PC2000-11R Mining Solutions
B74: =B67 -> 0 | C74: руб./кг | P74: =P73 -> Komatsu PC2000-11R Mining Solutions
B75: =B68 -> 0 | C75: руб./л | P75: =P74 -> Komatsu PC2000-11R Mining Solutions
B76: =B69 -> 0 | P76: =P75 -> Komatsu PC2000-11R Mining Solutions
P77: =P76 -> Komatsu PC2000-11R Mining Solutions
P78: =P77 -> Komatsu PC2000-11R Mining Solutions
P79: =P78 -> Komatsu PC2000-11R Mining Solutions
B80: Расходы на персонал | C80: тыс. руб. | E80: =E81*12 -> 10015.271 | F80: =F81*12 -> 10015.271 | G80: =G81*12 -> 10015.271 | H80: =H81*12 -> 10015.271 | I80: =I81*12 -> 10015.271 | J80: =J81*12 -> 10015.271 | K80: =K81*12 -> 10015.271 | L80: =L81*12 -> 10015.271 | ... N80: =N81*12 -> 10015.271 | P80: =P79 -> Komatsu PC2000-11R Mining Solutions
B81: Средняя зар.плата на экипаж, с отчислениями | C81: тыс.руб./мес | D81: ='МТР, ФЗП'!$E$23/12 -> 834.6059 | E81: =D81 -> 834.6059 | F81: =E81 -> 834.6059 | G81: =F81 -> 834.6059 | H81: =G81 -> 834.6059 | I81: =H81 -> 834.6059 | J81: =I81 -> 834.6059 | K81: =J81 -> 834.6059 | L81: =K81 -> 834.6059 | ... N81: =M81 -> 834.6059 | P81: =P80 -> Komatsu PC2000-11R Mining Solutions | S81: факт-2025 КБЕ, PC-1250
P82: =P81 -> Komatsu PC2000-11R Mining Solutions
P83: =P82 -> Komatsu PC2000-11R Mining Solutions
B84: Амортизация НУ | C84: тыс. руб. | E84: =$D90*$D85% -> 55989.298 | F84: =$D90*$D85% -> 55989.298 | G84: =$D90*$D85% -> 55989.298 | H84: =$D90*$D85% -> 55989.298 | I84: =$D90*$D85% -> 55989.298 | J84: =D91-SUM(E84:I84) -> 9331.5497 | O84: =SUM(E84:N84)-D91 -> 0 | P84: =P83 -> Komatsu PC2000-11R Mining Solutions
B85: процент амортизации | C85: % | D85: =100/(62/12) -> 19.354839 | P85: =P84 -> Komatsu PC2000-11R Mining Solutions | S85: факт КБЕ на последний 1250
B86: стоимость на начало года | C86: тыс. руб. | D86: =D91 -> 289278.04 | E86: =D87 -> 289278.04 | F86: =E87 -> 233288.74 | G86: =F87 -> 177299.44 | H86: =G87 -> 121310.15 | I86: =H87 -> 65320.848 | J86: =I87 -> 9331.5497 | K86: =J87 -> -1.4551915e-11 | L86: =K87 -> -1.4551915e-11 | ... N86: =M87 -> -1.4551915e-11 | P86: =P85 -> Komatsu PC2000-11R Mining Solutions
B87: стоимость на конец года | C87: тыс. руб. | D87: =D86-D84 -> 289278.04 | E87: =E86-E84 -> 233288.74 | F87: =F86-F84 -> 177299.44 | G87: =G86-G84 -> 121310.15 | H87: =H86-H84 -> 65320.848 | I87: =I86-I84 -> 9331.5497 | J87: =J86-J84 -> -1.4551915e-11 | K87: =K86-K84 -> -1.4551915e-11 | ... N87: =N86-N84 -> -1.4551915e-11 | P87: =P86 -> Komatsu PC2000-11R Mining Solutions
B88: Затраты (налогооблагаемая база) | C88: тыс. руб. | E88: =E13+E19+E39+E55+E80+E84+E16 -> 100351.48 | F88: =F13+F19+F39+F55+F80+F84+F16 -> 99844.852 | G88: =G13+G19+G39+G55+G80+G84+G16 -> 138026.01 | H88: =H13+H19+H39+H55+H80+H84+H16 -> 196971.46 | I88: =I13+I19+I39+I55+I80+I84+I16 -> 104145.19 | J88: =J13+J19+J39+J55+J80+J84+J16 -> 94152.938 | K88: =K13+K19+K39+K55+K80+K84+K16 -> 43469.768 | L88: =L13+L19+L39+L55+L80+L84+L16 -> 140176.5 | ... N88: =N13+N19+N39+N55+N80+N84+N16 -> 41616.254 | P88: =P87 -> Komatsu PC2000-11R Mining Solutions
B89: Налог на прибыль | C89: тыс. руб. | E89: =-E88*Макро!D$12 -> -25087.87 | F89: =-F88*Макро!E$12 -> -24961.213 | G89: =-G88*Макро!F$12 -> -34506.502 | H89: =-H88*Макро!G$12 -> -49242.865 | I89: =-I88*Макро!H$12 -> -26036.297 | J89: =-J88*Макро!I$12 -> -23538.234 | K89: =-K88*Макро!J$12 -> -10867.442 | L89: =-L88*Макро!K$12 -> -35044.126 | ... N89: =-N88*Макро!M$12 -> -10404.064 | P89: =P88 -> Komatsu PC2000-11R Mining Solutions
B90: Инвестиционная деятельность | C90: тыс.руб. | D90: =D91 -> 289278.04 | E90: =E91 -> 0 | F90: =F91 -> 0 | G90: =G91 -> 0 | H90: =H91 -> 0 | I90: =I91 -> 0 | J90: =J91 -> 0 | K90: =K91 -> 0 | ... N90: =N91 -> 0 | P90: =P89 -> Komatsu PC2000-11R Mining Solutions
B91: Инвестиции | C91: тыс.руб. | D91: ='1. Сводная_аннуитеты'!D31 -> 289278.04 | P91: =P90 -> Komatsu PC2000-11R Mining Solutions
B92: Производительность кумулятивная | C92: тыс. м3 | E92: =E11 -> 2213.5159 | F92: =E92+F11 -> 4129.6657 | G92: =F92+G11 -> 6104.7684 | H92: =G92+H11 -> 7934.7342 | I92: =H92+I11 -> 9761.9947 | J92: =I92+J11 -> 11712.758 | K92: =J92+K11 -> 13596.906 | L92: =K92+L11 -> 15615.378 | M92: =L92+M11 -> 16963.209 | N92: =M92+N11 -> 18948.939 | P92: =P91 -> Komatsu PC2000-11R Mining Solutions
B93: CF - Денежный поток | C93: тыс. руб. | D93: =D91+D12 -> 289278.04 | E93: =E91+E12 -> 19274.311 | F93: =F91+F12 -> 18894.341 | G93: =G91+G12 -> 47530.209 | H93: =H91+H12 -> 91739.297 | I93: =I91+I12 -> 22119.593 | J93: =J91+J12 -> 61283.154 | K93: =K91+K12 -> 32602.326 | ... N93: =N91+N12 -> 31212.191 | P93: =P92 -> Komatsu PC2000-11R Mining Solutions
B94: DOCF - Дисконтированный операционный поток | C94: тыс. руб. | D94: =D12*Макро!C$10 -> 0 | E94: =E12*Макро!D$10 -> 17209.206 | F94: =F12*Макро!E$10 -> 15062.453 | G94: =G12*Макро!F$10 -> 33831.064 | H94: =H12*Макро!G$10 -> 58301.982 | I94: =I12*Макро!H$10 -> 12551.251 | J94: =J12*Макро!I$10 -> 31047.953 | K94: =K12*Макро!J$10 -> 14747.636 | ... N94: =N12*Макро!M$10 -> 10049.49 | P94: =P93 -> Komatsu PC2000-11R Mining Solutions
B95: =B13 -> ТО, ТР, ППР, вкл смазочные | C95: тыс. руб. | D95: =D13*Макро!C$10 -> 0 | E95: =E13*Макро!D$10 -> 5047.8234 | F95: =F13*Макро!E$10 -> 6854.6085 | G95: =G13*Макро!F$10 -> 32518.662 | H95: =H13*Макро!G$10 -> 67309.792 | I95: =I13*Макро!H$10 -> 7959.5236 | J95: =J13*Макро!I$10 -> 24638.098 | K95: =K13*Макро!J$10 -> 3889.489 | ... N95: =N13*Макро!M$10 -> 1820.2957 | P95: =P94 -> Komatsu PC2000-11R Mining Solutions
B96: =B16 -> затраты на сервис: ремонты и ТО | C96: тыс. руб. | D96: =D16*Макро!C$10 -> 0 | E96: =E16*Макро!D$10 -> 1794.3939 | F96: =F16*Макро!E$10 -> 1708.3397 | G96: =G16*Макро!F$10 -> 1797.5821 | H96: =H16*Макро!G$10 -> 1902.5168 | I96: =I16*Макро!H$10 -> 1183.5656 | J96: =J16*Макро!I$10 -> 1346.9769 | K96: =K16*Макро!J$10 -> 969.3578 | ... N96: =N16*Макро!M$10 -> 647.07641 | P96: =P95 -> Komatsu PC2000-11R Mining Solutions
B97: =B19 -> расходники на ковш | C97: тыс. руб. | D97: =D19*Макро!C$10 -> 0 | E97: =E19*Макро!D$10 -> 1724.5894 | F97: =F19*Макро!E$10 -> 1332.9521 | G97: =G19*Макро!F$10 -> 1226.7518 | H97: =H19*Макро!G$10 -> 1014.8269 | I97: =I19*Макро!H$10 -> 904.75597 | J97: =J19*Макро!I$10 -> 862.41767 | K97: =K19*Макро!J$10 -> 743.72058 | ... N97: =N19*Макро!M$10 -> 557.90606 | P97: =P96 -> Komatsu PC2000-11R Mining Solutions
B98: Дизтопливо | C98: тыс. руб. | D98: =D39*Макро!C$10 -> 0 | E98: =E39*Макро!D$10 -> 22100.078 | F98: =F39*Макро!E$10 -> 17081.366 | G98: =G39*Макро!F$10 -> 15720.443 | H98: =H39*Макро!G$10 -> 13004.692 | I98: =I39*Макро!H$10 -> 11594.166 | J98: =J39*Макро!I$10 -> 11051.614 | K98: =K39*Макро!J$10 -> 9530.548 | ... N98: =N39*Макро!M$10 -> 7149.3927 | P98: =P97 -> Komatsu PC2000-11R Mining Solutions
B99: Смазочные | C99: тыс. руб. | D99: =D55*Макро!C$10 -> 0 | E99: =E55*Макро!D$10 -> 0 | F99: =F55*Макро!E$10 -> 0 | G99: =G55*Макро!F$10 -> 0 | H99: =H55*Макро!G$10 -> 0 | I99: =I55*Макро!H$10 -> 0 | J99: =J55*Макро!I$10 -> 0 | K99: =K55*Макро!J$10 -> 0 | ... N99: =N55*Макро!M$10 -> 0 | P99: =P98 -> Komatsu PC2000-11R Mining Solutions
B100: Расходы на персонал | C100: тыс. руб. | D100: =D80*Макро!C$10 -> 0 | E100: =E80*Макро!D$10 -> 8942.206 | F100: =F80*Макро!E$10 -> 7984.1125 | G100: =G80*Макро!F$10 -> 7128.6719 | H100: =H80*Макро!G$10 -> 6364.8856 | I100: =I80*Макро!H$10 -> 5682.9336 | J100: =J80*Макро!I$10 -> 5074.0479 | K100: =K80*Макро!J$10 -> 4530.3999 | ... N100: =N80*Макро!M$10 -> 3224.6491 | P100: =P99 -> Komatsu PC2000-11R Mining Solutions
B101: Налог на прибыль | C101: тыс. руб. | D101: =D89*Макро!C$10 -> 0 | E101: =E89*Макро!D$10 -> -22399.884 | F101: =F89*Макро!E$10 -> -19898.926 | G101: =G89*Макро!F$10 -> -24561.047 | H101: =H89*Макро!G$10 -> -31294.731 | I101: =I89*Макро!H$10 -> -14773.694 | J101: =J89*Макро!I$10 -> -11925.202 | K101: =K89*Макро!J$10 -> -4915.8788 | ... N101: =N89*Макро!M$10 -> -3349.83 | P101: =P100 -> Komatsu PC2000-11R Mining Solutions
...

Sheet PC2000-8 MS
B2: ячейки к заполнению поставщиком
B3: Экскаватор | C3: Komatsu PC2000-8 | D3: 16.07.2026: Доронин Ю.: PC2000-11 будет к поставке, не PC2000-8 | O3: Примечания
A4: 1 | B4: Период (год) | C4: Ед. изм. | D4: 0 | E4: =D4+1 -> 1 | F4: =E4+1 -> 2 | G4: =F4+1 -> 3 | H4: =G4+1 -> 4 | I4: =H4+1 -> 5 | J4: =I4+1 -> 6 | K4: =J4+1 -> 7 | L4: =K4+1 -> 8 | ... N4: =M4+1 -> 10
A5: =A4+1 -> 2 | B5: Геометрическая емкость ковша экскаватора | C5: м3 | D5: 8.5
A6: =A5+1 -> 3 | B6: Емкость ковша с шапкой | C6: м3 | D6: 12
B7: КТГ - в расчет | C7: коэф. | E7: =Факт.КТГ!D10 -> 0.92406268 | F7: =Факт.КТГ!E10 -> 0.79773755 | G7: =Факт.КТГ!F10 -> 0.82453381 | H7: =Факт.КТГ!G10 -> 0.76394441 | I7: =Факт.КТГ!H10 -> 0.76281505 | J7: =Факт.КТГ!I10 -> 0.81214813 | K7: =Факт.КТГ!J10 -> 0.78656324 | L7: =Факт.КТГ!K10 -> 0.84263903 | ... N7: =Факт.КТГ!M10 -> 0.82670539 | O7: факт по Группе
A9: =A6+1 -> 4 | B9: КТГ при нормативной эксплуатации | E9: =(8760-E10-E11-E12)/8760 -> 0.94081367 | F9: =(8760-F10-F11-F12)/8760 -> 0.90174721 | G9: =(8760-G10-G11-G12)/8760 -> 0.87999429 | H9: =(8760-H10-H11-H12)/8760 -> 0.90441083 | I9: =(8760-I10-I11-I12)/8760 -> 0.93726218 | J9: =(8760-J10-J11-J12)/8760 -> 0.85513382 | K9: =(8760-K10-K11-K12)/8760 -> 0.9279395 | L9: =(8760-L10-L11-L12)/8760 -> 0.853802 | ... N9: =(8760-N10-N11-N12)/8760 -> 0.91106989 | O9: Расчетный - от поставщика
A10: =A9+1 -> 5 | B10: простои на ТО | C10: час | E10: ='PC2000-8 MS_ТО'!G7 -> 259 | F10: ='PC2000-8 MS_ТО'!H7 -> 259 | G10: ='PC2000-8 MS_ТО'!I7 -> 259 | H10: ='PC2000-8 MS_ТО'!J7 -> 259 | I10: ='PC2000-8 MS_ТО'!K7 -> 259 | J10: ='PC2000-8 MS_ТО'!L7 -> 259 | K10: ='PC2000-8 MS_ТО'!M7 -> 259 | L10: ='PC2000-8 MS_ТО'!N7 -> 259 | ... N10: ='PC2000-8 MS_ТО'!P7 -> 259
A11: =A10+1 -> 6 | B11: простои в ремонтах | C11: час | E11: ='PC2000-8 MS_Ремонты'!F8 -> 24 | F11: ='PC2000-8 MS_Ремонты'!G8 -> 376 | G11: ='PC2000-8 MS_Ремонты'!H8 -> 572 | H11: ='PC2000-8 MS_Ремонты'!I8 -> 352 | I11: ='PC2000-8 MS_Ремонты'!J8 -> 56 | J11: ='PC2000-8 MS_Ремонты'!K8 -> 796 | K11: ='PC2000-8 MS_Ремонты'!L8 -> 140 | L11: ='PC2000-8 MS_Ремонты'!M8 -> 808 | ... N11: ='PC2000-8 MS_Ремонты'!O8 -> 292
A12: =A11+1 -> 7 | B12: ежесменный осмотр (20 минут в смену) | C12: час | E12: =(8760-E10-E11)/12*20/60 -> 235.47222 | F12: =(8760-F10-F11)/12*20/60 -> 225.69444 | G12: =(8760-G10-G11)/12*20/60 -> 220.25 | H12: =(8760-H10-H11)/12*20/60 -> 226.36111 | I12: =(8760-I10-I11)/12*20/60 -> 234.58333 | J12: =(8760-J10-J11)/12*20/60 -> 214.02778 | K12: =(8760-K10-K11)/12*20/60 -> 232.25 | L12: =(8760-L10-L11)/12*20/60 -> 213.69444 | ... N12: =(8760-N10-N11)/12*20/60 -> 228.02778
A13: =A12+1 -> 8 | B13: Время цикла | C13: сек | D13: 26-28 секунд | E13: =AVERAGE(26,28) -> 27
A14: =A13+1 -> 9 | B14: Мощность двигателя | C14: л.с. | D14: 1050
A15: =A14+1 -> 10 | B15: Затраты на ТО и ремонты | C15: тыс.дол./год | E15: =SUM(E16:E20) -> 142.08144 | F15: =SUM(F16:F20) -> 1515.237 | G15: =SUM(G16:G20) -> 1617.9303 | H15: =SUM(H16:H20) -> 1513.4951 | I15: =SUM(I16:I20) -> 150.17068 | J15: =SUM(J16:J20) -> 2932.4804 | K15: =SUM(K16:K20) -> 199.81592 | L15: =SUM(L16:L20) -> 2933.3514 | ... N15: =SUM(N16:N20) -> 1465.5918
A16: =A15+1 -> 11 | B16: ТО, включая смазочные | C16: тыс.дол./год | E16: ='PC2000-8 MS_ТО'!G9/1000 -> 102.74293 | F16: ='PC2000-8 MS_ТО'!H9/1000 -> 102.74293 | G16: ='PC2000-8 MS_ТО'!I9/1000 -> 102.74293 | H16: ='PC2000-8 MS_ТО'!J9/1000 -> 102.74293 | I16: ='PC2000-8 MS_ТО'!K9/1000 -> 102.74293 | J16: ='PC2000-8 MS_ТО'!L9/1000 -> 102.74293 | K16: ='PC2000-8 MS_ТО'!M9/1000 -> 102.74293 | L16: ='PC2000-8 MS_ТО'!N9/1000 -> 102.74293 | ... N16: ='PC2000-8 MS_ТО'!P9/1000 -> 102.74293
A17: =A16+1 -> 12 | B17: текущие ремонты | C17: тыс.дол./год | E17: ='PC2000-8 MS_Ремонты'!F10/1000 -> 1.7419268 | F17: ='PC2000-8 MS_Ремонты'!G10/1000 -> 4.3548171 | G17: ='PC2000-8 MS_Ремонты'!H10/1000 -> 3.4838537 | H17: ='PC2000-8 MS_Ремонты'!I10/1000 -> 2.6128903 | I17: ='PC2000-8 MS_Ремонты'!J10/1000 -> 3.4838537 | J17: ='PC2000-8 MS_Ремонты'!K10/1000 -> 2.6128903 | K17: ='PC2000-8 MS_Ремонты'!L10/1000 -> 4.3548171 | L17: ='PC2000-8 MS_Ремонты'!M10/1000 -> 3.4838537 | ... N17: ='PC2000-8 MS_Ремонты'!O10/1000 -> 3.4838537
A18: =A17+1 -> 13 | B18: планово-предупредительные (капитальные) ремонты | C18: тыс.дол./год | E18: ='PC2000-8 MS_Ремонты'!F11/1000 -> 0 | F18: ='PC2000-8 MS_Ремонты'!G11/1000 -> 1347.6073 | G18: ='PC2000-8 MS_Ремонты'!H11/1000 -> 1436.0748 | H18: ='PC2000-8 MS_Ремонты'!I11/1000 -> 1347.6073 | I18: ='PC2000-8 MS_Ремонты'!J11/1000 -> 5.7666667 | J18: ='PC2000-8 MS_Ремонты'!K11/1000 -> 2734.367 | K18: ='PC2000-8 MS_Ремонты'!L11/1000 -> 49.315167 | L18: ='PC2000-8 MS_Ремонты'!M11/1000 -> 2734.367 | ... N18: ='PC2000-8 MS_Ремонты'!O11/1000 -> 1304.0588
A19: =A18+1 -> 14 | B19: сервис (трудозатраты) - ТО | C19: тыс.дол./год | E19: ='PC2000-8 MS_ТО'!G10/1000 -> 37.596588 | F19: ='PC2000-8 MS_ТО'!H10/1000 -> 37.596588 | G19: ='PC2000-8 MS_ТО'!I10/1000 -> 37.596588 | H19: ='PC2000-8 MS_ТО'!J10/1000 -> 37.596588 | I19: ='PC2000-8 MS_ТО'!K10/1000 -> 37.596588 | J19: ='PC2000-8 MS_ТО'!L10/1000 -> 37.596588 | K19: ='PC2000-8 MS_ТО'!M10/1000 -> 37.596588 | L19: ='PC2000-8 MS_ТО'!N10/1000 -> 37.596588 | ... N19: ='PC2000-8 MS_ТО'!P10/1000 -> 37.596588
A20: =A19+1 -> 15 | B20: сервис (трудозатраты) - ремонты | C20: тыс.дол./год | E20: ='PC2000-8 MS_Ремонты'!F12/1000 -> 0 | F20: ='PC2000-8 MS_Ремонты'!G12/1000 -> 22.93537 | G20: ='PC2000-8 MS_Ремонты'!H12/1000 -> 38.032069 | H20: ='PC2000-8 MS_Ремонты'!I12/1000 -> 22.93537 | I20: ='PC2000-8 MS_Ремонты'!J12/1000 -> 0.58064228 | J20: ='PC2000-8 MS_Ремонты'!K12/1000 -> 55.161017 | K20: ='PC2000-8 MS_Ремонты'!L12/1000 -> 5.8064228 | L20: ='PC2000-8 MS_Ремонты'!M12/1000 -> 55.161017 | ... N20: ='PC2000-8 MS_Ремонты'!O12/1000 -> 17.70959
A21: =A20+1 -> 16 | B21: Расходные материалы:
A22: =A21+1 -> 17 | B22: зубья ковша | C22: 5 шт. | O22: кол-во штук на ковше
A23: =A22+1 -> 18 | B23: удельный расход на 7000 м.ч | C23: 110 | E23: 110 | F23: 110 | G23: 110 | H23: 110 | I23: 110 | J23: 110 | K23: 110 | L23: 110 | M23: 110 | N23: 110
A24: =A23+1 -> 19 | B24: цена за ед. | C24: 444 | E24: =E23*C24 -> 48840 | F24: =F23*C24 -> 48840 | G24: =G23*C24 -> 48840 | H24: =H23*C24 -> 48840 | I24: =I23*C24 -> 48840 | J24: =J23*C24 -> 48840 | K24: =K23*C24 -> 48840 | L24: =L23*C24 -> 48840 | M24: =M23*C24 -> 48840 | N24: =N23*C24 -> 48840
A25: =A24+1 -> 20 | B25: Палец коронки | C25: 5 шт. | O25: кол-во штук на ковше
A26: =A25+1 -> 21 | B26: удельный расход на 7000 м.ч | C26: 110 | E26: 110 | F26: 110 | G26: 110 | H26: 110 | I26: 110 | J26: 110 | K26: 110 | L26: 110 | M26: 110 | N26: 110
A27: =A26+1 -> 22 | B27: цена за ед. | C27: 48 | E27: =E26*C27 -> 5280 | F27: =F26*C27 -> 5280 | G27: =G26*C27 -> 5280 | H27: =H26*C27 -> 5280 | I27: =I26*C27 -> 5280 | J27: =J26*C27 -> 5280 | K27: =K26*C27 -> 5280 | L27: =L26*C27 -> 5280 | M27: =M26*C27 -> 5280 | N27: =N26*C27 -> 5280
A28: =A27+1 -> 23 | B28: Крышка износа центральная | C28: 3 шт. | O28: кол-во штук на ковше
A29: =A28+1 -> 24 | B29: удельный расход на 7000 м.ч | C29: 21 | E29: 21 | F29: 21 | G29: 21 | H29: 21 | I29: 21 | J29: 21 | K29: 21 | L29: 21 | M29: 21 | N29: 21
A30: =A29+1 -> 25 | B30: цена за ед. | C30: 224 | E30: =E29*C30 -> 4704 | F30: =F29*C30 -> 4704 | G30: =G29*C30 -> 4704 | H30: =H29*C30 -> 4704 | I30: =I29*C30 -> 4704 | J30: =J29*C30 -> 4704 | K30: =K29*C30 -> 4704 | L30: =L29*C30 -> 4704 | M30: =M29*C30 -> 4704 | N30: =N29*C30 -> 4704
A31: =A30+1 -> 26 | B31: Крышка износа угловая | C31: 2 шт. | O31: кол-во штук на ковше
A32: =A31+1 -> 27 | B32: удельный расход на 7000 м.ч | C32: 14 | E32: 14 | F32: 14 | G32: 14 | H32: 14 | I32: 14 | J32: 14 | K32: 14 | L32: 14 | M32: 14 | N32: 14
A33: =A32+1 -> 28 | B33: цена за ед. | C33: 560 | E33: =E32*C33 -> 7840 | F33: =F32*C33 -> 7840 | G33: =G32*C33 -> 7840 | H33: =H32*C33 -> 7840 | I33: =I32*C33 -> 7840 | J33: =J32*C33 -> 7840 | K33: =K32*C33 -> 7840 | L33: =L32*C33 -> 7840 | M33: =M32*C33 -> 7840 | N33: =N32*C33 -> 7840
A34: =A33+1 -> 29 | B34: Мезубка. | C34: 4 шт. | O34: кол-во штук на ковше
A35: =A34+1 -> 30 | B35: удельный расход на 7000 м.ч | C35: 28 | E35: 28 | F35: 28 | G35: 28 | H35: 28 | I35: 28 | J35: 28 | K35: 28 | L35: 28 | M35: 28 | N35: 28
A36: =A35+1 -> 31 | B36: цена за ед. | C36: 1634 | E36: =E35*C36 -> 45752 | F36: =F35*C36 -> 45752 | G36: =G35*C36 -> 45752 | H36: =H35*C36 -> 45752 | I36: =I35*C36 -> 45752 | J36: =J35*C36 -> 45752 | K36: =K35*C36 -> 45752 | L36: =L35*C36 -> 45752 | M36: =M35*C36 -> 45752 | N36: =N35*C36 -> 45752
A37: =A36+1 -> 32 | B37: J болт | C37: 4 шт. | O37: кол-во штук на ковше
A38: =A37+1 -> 33 | B38: удельный расход на 7000 м.ч | C38: 28 | E38: 28 | F38: 28 | G38: 28 | H38: 28 | I38: 28 | J38: 28 | K38: 28 | L38: 28 | M38: 28 | N38: 28
A39: =A38+1 -> 34 | B39: цена за ед. | C39: 326 | E39: =E38*C39 -> 9128 | F39: =F38*C39 -> 9128 | G39: =G38*C39 -> 9128 | H39: =H38*C39 -> 9128 | I39: =I38*C39 -> 9128 | J39: =J38*C39 -> 9128 | K39: =K38*C39 -> 9128 | L39: =L38*C39 -> 9128 | M39: =M38*C39 -> 9128 | N39: =N38*C39 -> 9128
A40: =A39+1 -> 35 | B40: угловая защита | C40: 12 шт. | O40: кол-во штук на ковше
A41: =A40+1 -> 36 | B41: удельный расход на 7000 м.ч | C41: 48 | E41: 48 | F41: 48 | G41: 48 | H41: 48 | I41: 48 | J41: 48 | K41: 48 | L41: 48 | M41: 48 | N41: 48
A42: =A41+1 -> 37 | B42: цена за ед. | C42: 294 | E42: =E41*C42 -> 14112 | F42: =F41*C42 -> 14112 | G42: =G41*C42 -> 14112 | H42: =H41*C42 -> 14112 | I42: =I41*C42 -> 14112 | J42: =J41*C42 -> 14112 | K42: =K41*C42 -> 14112 | L42: =L41*C42 -> 14112 | M42: =M41*C42 -> 14112 | N42: =N41*C42 -> 14112
A43: =A42+1 -> 38 | B43: Бокорезы | C43: 2 шт. | O43: кол-во штук на ковше
A44: =A43+1 -> 39 | B44: удельный расход на 7000 м.ч | C44: 12 | E44: 12 | F44: 12 | G44: 12 | H44: 12 | I44: 12 | J44: 12 | K44: 12 | L44: 12 | M44: 12 | N44: 12
A45: =A44+1 -> 40 | B45: цена за ед. | C45: 464 | E45: =E44*C45 -> 5568 | F45: =F44*C45 -> 5568 | G45: =G44*C45 -> 5568 | H45: =H44*C45 -> 5568 | I45: =I44*C45 -> 5568 | J45: =J44*C45 -> 5568 | K45: =K44*C45 -> 5568 | L45: =L44*C45 -> 5568 | M45: =M44*C45 -> 5568 | N45: =N44*C45 -> 5568
A46: =A45+1 -> 41 | B46: Пальцы бокореза | C46: 4 шт. | O46: кол-во штук на ковше
A47: =A46+1 -> 42 | B47: удельный расход на 7000 м.ч | C47: 24 | E47: 24 | F47: 24 | G47: 24 | H47: 24 | I47: 24 | J47: 24 | K47: 24 | L47: 24 | M47: 24 | N47: 24
A48: =A47+1 -> 43 | B48: цена за ед. | C48: 6.08 | E48: =E47*C48 -> 145.92 | F48: =F47*C48 -> 145.92 | G48: =G47*C48 -> 145.92 | H48: =H47*C48 -> 145.92 | I48: =I47*C48 -> 145.92 | J48: =J47*C48 -> 145.92 | K48: =K47*C48 -> 145.92 | L48: =L47*C48 -> 145.92 | M48: =M47*C48 -> 145.92 | N48: =N47*C48 -> 145.92
A49: =A48+1 -> 44 | B49: Дизтопливо
A50: =A49+1 -> 45 | B50: удельный расход | C50: сред расх литры.в ч. | D50: 80 литров в час | O50: Указать удельный расход и единицы измерения
A51: =A50+1 -> 46 | B51: Сроки поставки | C51: дней | D51: 30-45 дней

Sheet PC2000-8 MS_ТО
B2: ячейки к заполнению поставщиком
B3: Расчетный КТГ | G3: ='PC2000-8 MS'!E9 -> 0.94081367 | H3: ='PC2000-8 MS'!F9 -> 0.90174721 | I3: ='PC2000-8 MS'!G9 -> 0.87999429 | J3: ='PC2000-8 MS'!H9 -> 0.90441083 | K3: ='PC2000-8 MS'!I9 -> 0.93726218 | L3: ='PC2000-8 MS'!J9 -> 0.85513382 | M3: ='PC2000-8 MS'!K9 -> 0.9279395 | N3: ='PC2000-8 MS'!L9 -> 0.853802 | ... P3: ='PC2000-8 MS'!N9 -> 0.91106989
B4: Год службы (год) | C4: Ед. изм. | G4: =E4+1 -> 1 | H4: =G4+1 -> 2 | I4: =H4+1 -> 3 | J4: =I4+1 -> 4 | K4: =J4+1 -> 5 | L4: =K4+1 -> 6 | M4: =L4+1 -> 7 | N4: =M4+1 -> 8 | O4: =N4+1 -> 9 | P4: =O4+1 -> 10
B5: Наработка на начало года | C5: м/час | G5: 0 | H5: =G6+1 -> 7001 | I5: =H6+1 -> 14001 | J5: =I6+1 -> 21001 | K5: =J6+1 -> 28001 | L5: =K6+1 -> 35001 | M5: =L6+1 -> 42001 | N5: =M6+1 -> 49001 | O5: =N6+1 -> 56001 | P5: =O6+1 -> 63001
B6: Наработка на конец года | C6: м/час | F6: 7000 | G6: =F6 -> 7000 | H6: =G6+$F6 -> 14000 | I6: =H6+$F6 -> 21000 | J6: =I6+$F6 -> 28000 | K6: =J6+$F6 -> 35000 | L6: =K6+$F6 -> 42000 | M6: =L6+$F6 -> 49000 | N6: =M6+$F6 -> 56000 | O6: =N6+$F6 -> 63000 | P6: =O6+$F6 -> 70000
B7: длительность простоев на ТО | C7: часов | G7: =G13 -> 259 | H7: =H13 -> 259 | I7: =I13 -> 259 | J7: =J13 -> 259 | K7: =K13 -> 259 | L7: =L13 -> 259 | M7: =M13 -> 259 | N7: =N13 -> 259 | ... P7: =P13 -> 259
B8: Затраты на ТО | C8: долларов/год | G8: =SUM(G9:G10) -> 140339.51 | H8: =SUM(H9:H10) -> 140339.51 | I8: =SUM(I9:I10) -> 140339.51 | J8: =SUM(J9:J10) -> 140339.51 | K8: =SUM(K9:K10) -> 140339.51 | L8: =SUM(L9:L10) -> 140339.51 | M8: =SUM(M9:M10) -> 140339.51 | N8: =SUM(N9:N10) -> 140339.51 | ... P8: =SUM(P9:P10) -> 140339.51
B9: ТО, включая масла и смазки | C9: долларов/год | G9: =G21 -> 102742.93 | H9: =H21 -> 102742.93 | I9: =I21 -> 102742.93 | J9: =J21 -> 102742.93 | K9: =K21 -> 102742.93 | L9: =L21 -> 102742.93 | M9: =M21 -> 102742.93 | N9: =N21 -> 102742.93 | ... P9: =P21 -> 102742.93
B10: сервис (трудозатраты) на ТО | C10: долларов/год | F10: 72.580285 | G10: =SUMPRODUCT(G14:G18,$F$14:$F$18)*$F10 -> 37596.588 | H10: =SUMPRODUCT(H14:H18,$F$14:$F$18)*$F10 -> 37596.588 | I10: =SUMPRODUCT(I14:I18,$F$14:$F$18)*$F10 -> 37596.588 | J10: =SUMPRODUCT(J14:J18,$F$14:$F$18)*$F10 -> 37596.588 | K10: =SUMPRODUCT(K14:K18,$F$14:$F$18)*$F10 -> 37596.588 | L10: =SUMPRODUCT(L14:L18,$F$14:$F$18)*$F10 -> 37596.588 | M10: =SUMPRODUCT(M14:M18,$F$14:$F$18)*$F10 -> 37596.588 | N10: =SUMPRODUCT(N14:N18,$F$14:$F$18)*$F10 -> 37596.588 | ... P10: =SUMPRODUCT(P14:P18,$F$14:$F$18)*$F10 -> 37596.588
B12: Простои оборудования на ТО | C12: Интервал ТО | D12: Длительность простоя на одном ТО, час | E12: Кол-во ТО в год | F12: Занято человек | G12: Простоев в год, час | H12: Простоев в год, час | I12: Простоев в год, час | J12: Простоев в год, час | K12: Простоев в год, час | L12: Простоев в год, час | M12: Простоев в год, час | N12: Простоев в год, час | O12: Простоев в год, час | P12: Простоев в год, час | R12: цена руб без ндс месяц за 1 человека | T12: часов в смене | U12: колличество дней | V12: цена за 1 час руб. без ндс | W12: курс USD | X12: 74.63
B13: всего простоев на ТО, часов | G13: =SUM(G14:G18) -> 259 | H13: =SUM(H14:H18) -> 259 | I13: =SUM(I14:I18) -> 259 | J13: =SUM(J14:J18) -> 259 | K13: =SUM(K14:K18) -> 259 | L13: =SUM(L14:L18) -> 259 | M13: =SUM(M14:M18) -> 259 | N13: =SUM(N14:N18) -> 259 | ... P13: =SUM(P14:P18) -> 259 | R13: 1300000 | T13: 8 | U13: 30 | V13: =R13/(T13*U13) -> 5416.6667 | X13: =V13/X12 -> 72.580285
B14: ТО-1 | C14: 500 | D14: 10.2 | E14: =$F$6/C14 -> 14 | F14: 2 | G14: =$E14*$D14 -> 142.8 | H14: =$E14*$D14 -> 142.8 | I14: =$E14*$D14 -> 142.8 | J14: =$E14*$D14 -> 142.8 | K14: =$E14*$D14 -> 142.8 | L14: =$E14*$D14 -> 142.8 | M14: =$E14*$D14 -> 142.8 | N14: =$E14*$D14 -> 142.8 | ... P14: =$E14*$D14 -> 142.8
B15: ТО-2 | C15: 1000 | D15: 9.4 | E15: =$F$6/C15 -> 7 | F15: 2 | G15: =$E15*$D15 -> 65.8 | H15: =$E15*$D15 -> 65.8 | I15: =$E15*$D15 -> 65.8 | J15: =$E15*$D15 -> 65.8 | K15: =$E15*$D15 -> 65.8 | L15: =$E15*$D15 -> 65.8 | M15: =$E15*$D15 -> 65.8 | N15: =$E15*$D15 -> 65.8 | ... P15: =$E15*$D15 -> 65.8
B16: ТО-3 | C16: 2000 | D16: 12.4 | E16: 3 | F16: 2 | G16: =$E16*$D16 -> 37.2 | H16: =$E16*$D16 -> 37.2 | I16: =$E16*$D16 -> 37.2 | J16: =$E16*$D16 -> 37.2 | K16: =$E16*$D16 -> 37.2 | L16: =$E16*$D16 -> 37.2 | M16: =$E16*$D16 -> 37.2 | N16: =$E16*$D16 -> 37.2 | ... P16: =$E16*$D16 -> 37.2
B17: ТО-4 | C17: 4000 | D17: 7.8 | E17: 1 | F17: 2 | G17: =$E17*$D17 -> 7.8 | H17: =$E17*$D17 -> 7.8 | I17: =$E17*$D17 -> 7.8 | J17: =$E17*$D17 -> 7.8 | K17: =$E17*$D17 -> 7.8 | L17: =$E17*$D17 -> 7.8 | M17: =$E17*$D17 -> 7.8 | N17: =$E17*$D17 -> 7.8 | ... P17: =$E17*$D17 -> 7.8
B18: ТО-5 | C18: 5000 | D18: 5.4 | E18: 1 | F18: 2 | G18: =$E18*$D18 -> 5.4 | H18: =$E18*$D18 -> 5.4 | I18: =$E18*$D18 -> 5.4 | J18: =$E18*$D18 -> 5.4 | K18: =$E18*$D18 -> 5.4 | L18: =$E18*$D18 -> 5.4 | M18: =$E18*$D18 -> 5.4 | N18: =$E18*$D18 -> 5.4 | ... P18: =$E18*$D18 -> 5.4
B20: Затраты на ТО | C20: Каталожный номер | D20: стоимость за ед., $ | E20: Кол-во | F20: Кол-во ТО в год | G20: $ | H20: $ | I20: $ | J20: $ | K20: $ | L20: $ | M20: $ | N20: $ | O20: $ | P20: $
B21: ТО | G21: =SUM(G22:G53) -> 102742.93 | H21: =SUM(H22:H53) -> 102742.93 | I21: =SUM(I22:I53) -> 102742.93 | J21: =SUM(J22:J53) -> 102742.93 | K21: =SUM(K22:K53) -> 102742.93 | L21: =SUM(L22:L53) -> 102742.93 | M21: =SUM(M22:M53) -> 102742.93 | N21: =SUM(N22:N53) -> 102742.93 | ... P21: =SUM(P22:P53) -> 102742.93
B22: ТО-1 | E22: =VLOOKUP($B22,$B$14:$C$18,2,FALSE) -> 500 | F22: =VLOOKUP($B22,$B$14:$E$18,4,FALSE) -> 14
B23: Маслянный фильтр | C23: 600-211-1341 | D23: 114.83333 | E23: 4 | G23: =IF(G$14=0,0,G$14/$D$14*$E23*$D23) -> 6430.6667 | H23: =IF(H$14=0,0,H$14/$D$14*$E23*$D23) -> 6430.6667 | I23: =IF(I$14=0,0,I$14/$D$14*$E23*$D23) -> 6430.6667 | J23: =IF(J$14=0,0,J$14/$D$14*$E23*$D23) -> 6430.6667 | K23: =IF(K$14=0,0,K$14/$D$14*$E23*$D23) -> 6430.6667 | L23: =IF(L$14=0,0,L$14/$D$14*$E23*$D23) -> 6430.6667 | M23: =IF(M$14=0,0,M$14/$D$14*$E23*$D23) -> 6430.6667 | N23: =IF(N$14=0,0,N$14/$D$14*$E23*$D23) -> 6430.6667 | ... P23: =IF(P$14=0,0,P$14/$D$14*$E23*$D23) -> 6430.6667
B24: Топливный фильтр | C24: 600-319-4540 | D24: 141.33333 | E24: 2 | G24: =IF(G$14=0,0,G$14/$D$14*$E24*$D24) -> 3957.3333 | H24: =IF(H$14=0,0,H$14/$D$14*$E24*$D24) -> 3957.3333 | I24: =IF(I$14=0,0,I$14/$D$14*$E24*$D24) -> 3957.3333 | J24: =IF(J$14=0,0,J$14/$D$14*$E24*$D24) -> 3957.3333 | K24: =IF(K$14=0,0,K$14/$D$14*$E24*$D24) -> 3957.3333 | L24: =IF(L$14=0,0,L$14/$D$14*$E24*$D24) -> 3957.3333 | M24: =IF(M$14=0,0,M$14/$D$14*$E24*$D24) -> 3957.3333 | N24: =IF(N$14=0,0,N$14/$D$14*$E24*$D24) -> 3957.3333 | ... P24: =IF(P$14=0,0,P$14/$D$14*$E24*$D24) -> 3957.3333
B25: Масло ДВС | C25: ROCKET ENGIEN SUPER 15W40 | D25: 6.8716216 | E25: 130 | G25: =IF(G$14=0,0,G$14/$D$14*$E25*$D25) -> 12506.351 | H25: =IF(H$14=0,0,H$14/$D$14*$E25*$D25) -> 12506.351 | I25: =IF(I$14=0,0,I$14/$D$14*$E25*$D25) -> 12506.351 | J25: =IF(J$14=0,0,J$14/$D$14*$E25*$D25) -> 12506.351 | K25: =IF(K$14=0,0,K$14/$D$14*$E25*$D25) -> 12506.351 | L25: =IF(L$14=0,0,L$14/$D$14*$E25*$D25) -> 12506.351 | M25: =IF(M$14=0,0,M$14/$D$14*$E25*$D25) -> 12506.351 | N25: =IF(N$14=0,0,N$14/$D$14*$E25*$D25) -> 12506.351 | ... P25: =IF(P$14=0,0,P$14/$D$14*$E25*$D25) -> 12506.351
B26: Фильтр управляющего контура | C26: 21Т-60-31410 | D26: 126 | E26: 1 | G26: =IF(G$14=0,0,G$14/$D$14*$E26*$D26) -> 1764 | H26: =IF(H$14=0,0,H$14/$D$14*$E26*$D26) -> 1764 | I26: =IF(I$14=0,0,I$14/$D$14*$E26*$D26) -> 1764 | J26: =IF(J$14=0,0,J$14/$D$14*$E26*$D26) -> 1764 | K26: =IF(K$14=0,0,K$14/$D$14*$E26*$D26) -> 1764 | L26: =IF(L$14=0,0,L$14/$D$14*$E26*$D26) -> 1764 | M26: =IF(M$14=0,0,M$14/$D$14*$E26*$D26) -> 1764 | N26: =IF(N$14=0,0,N$14/$D$14*$E26*$D26) -> 1764 | ... P26: =IF(P$14=0,0,P$14/$D$14*$E26*$D26) -> 1764
B27: Сливной фильтр | C27: 113-60-23160 | D27: 30.666667 | E27: 2 | G27: =IF(G$14=0,0,G$14/$D$14*$E27*$D27) -> 858.66667 | H27: =IF(H$14=0,0,H$14/$D$14*$E27*$D27) -> 858.66667 | I27: =IF(I$14=0,0,I$14/$D$14*$E27*$D27) -> 858.66667 | J27: =IF(J$14=0,0,J$14/$D$14*$E27*$D27) -> 858.66667 | K27: =IF(K$14=0,0,K$14/$D$14*$E27*$D27) -> 858.66667 | L27: =IF(L$14=0,0,L$14/$D$14*$E27*$D27) -> 858.66667 | M27: =IF(M$14=0,0,M$14/$D$14*$E27*$D27) -> 858.66667 | N27: =IF(N$14=0,0,N$14/$D$14*$E27*$D27) -> 858.66667 | ... P27: =IF(P$14=0,0,P$14/$D$14*$E27*$D27) -> 858.66667
B28: Сливной фильтр насоса | C28: 21Т-60-31450 | D28: 201 | E28: 3 | G28: =IF(G$14=0,0,G$14/$D$14*$E28*$D28) -> 8442 | H28: =IF(H$14=0,0,H$14/$D$14*$E28*$D28) -> 8442 | I28: =IF(I$14=0,0,I$14/$D$14*$E28*$D28) -> 8442 | J28: =IF(J$14=0,0,J$14/$D$14*$E28*$D28) -> 8442 | K28: =IF(K$14=0,0,K$14/$D$14*$E28*$D28) -> 8442 | L28: =IF(L$14=0,0,L$14/$D$14*$E28*$D28) -> 8442 | M28: =IF(M$14=0,0,M$14/$D$14*$E28*$D28) -> 8442 | N28: =IF(N$14=0,0,N$14/$D$14*$E28*$D28) -> 8442 | ... P28: =IF(P$14=0,0,P$14/$D$14*$E28*$D28) -> 8442
B29: Смазка | C29: ROCKET GREASE EP 2 | D29: 12.243243 | E29: 200 | G29: =IF(G$14=0,0,G$14/$D$14*$E29*$D29) -> 34281.081 | H29: =IF(H$14=0,0,H$14/$D$14*$E29*$D29) -> 34281.081 | I29: =IF(I$14=0,0,I$14/$D$14*$E29*$D29) -> 34281.081 | J29: =IF(J$14=0,0,J$14/$D$14*$E29*$D29) -> 34281.081 | K29: =IF(K$14=0,0,K$14/$D$14*$E29*$D29) -> 34281.081 | L29: =IF(L$14=0,0,L$14/$D$14*$E29*$D29) -> 34281.081 | M29: =IF(M$14=0,0,M$14/$D$14*$E29*$D29) -> 34281.081 | N29: =IF(N$14=0,0,N$14/$D$14*$E29*$D29) -> 34281.081 | ... P29: =IF(P$14=0,0,P$14/$D$14*$E29*$D29) -> 34281.081
B30: ТО-2 | E30: =VLOOKUP($B30,$B$14:$C$18,2,FALSE) -> 1000 | F30: =VLOOKUP($B30,$B$14:$E$18,4,FALSE) -> 7
B31: Топливный фильтр | C31: 600-319-3550 | D31: 80.166667 | E31: 2 | G31: =IF(G$15=0,0,G$15/$D$15*$E31*$D31) -> 1122.3333 | H31: =IF(H$15=0,0,H$15/$D$15*$E31*$D31) -> 1122.3333 | I31: =IF(I$15=0,0,I$15/$D$15*$E31*$D31) -> 1122.3333 | J31: =IF(J$15=0,0,J$15/$D$15*$E31*$D31) -> 1122.3333 | K31: =IF(K$15=0,0,K$15/$D$15*$E31*$D31) -> 1122.3333 | L31: =IF(L$15=0,0,L$15/$D$15*$E31*$D31) -> 1122.3333 | M31: =IF(M$15=0,0,M$15/$D$15*$E31*$D31) -> 1122.3333 | N31: =IF(N$15=0,0,N$15/$D$15*$E31*$D31) -> 1122.3333 | ... P31: =IF(P$15=0,0,P$15/$D$15*$E31*$D31) -> 1122.3333
B32: Фильтр сапуна топливного бака | C32: 421-60-35170 | D32: 19.166667 | E32: 1 | G32: =IF(G$15=0,0,G$15/$D$15*$E32*$D32) -> 134.16667 | H32: =IF(H$15=0,0,H$15/$D$15*$E32*$D32) -> 134.16667 | I32: =IF(I$15=0,0,I$15/$D$15*$E32*$D32) -> 134.16667 | J32: =IF(J$15=0,0,J$15/$D$15*$E32*$D32) -> 134.16667 | K32: =IF(K$15=0,0,K$15/$D$15*$E32*$D32) -> 134.16667 | L32: =IF(L$15=0,0,L$15/$D$15*$E32*$D32) -> 134.16667 | M32: =IF(M$15=0,0,M$15/$D$15*$E32*$D32) -> 134.16667 | N32: =IF(N$15=0,0,N$15/$D$15*$E32*$D32) -> 134.16667 | ... P32: =IF(P$15=0,0,P$15/$D$15*$E32*$D32) -> 134.16667
B33: Фильтр сапуна гидробака | C33: 421-60-35170 | D33: 19.166667 | E33: 2 | G33: =IF(G$15=0,0,G$15/$D$15*$E33*$D33) -> 268.33333 | H33: =IF(H$15=0,0,H$15/$D$15*$E33*$D33) -> 268.33333 | I33: =IF(I$15=0,0,I$15/$D$15*$E33*$D33) -> 268.33333 | J33: =IF(J$15=0,0,J$15/$D$15*$E33*$D33) -> 268.33333 | K33: =IF(K$15=0,0,K$15/$D$15*$E33*$D33) -> 268.33333 | L33: =IF(L$15=0,0,L$15/$D$15*$E33*$D33) -> 268.33333 | M33: =IF(M$15=0,0,M$15/$D$15*$E33*$D33) -> 268.33333 | N33: =IF(N$15=0,0,N$15/$D$15*$E33*$D33) -> 268.33333 | ... P33: =IF(P$15=0,0,P$15/$D$15*$E33*$D33) -> 268.33333
B34: Гидравлический фильтр | C34: 209-60-77532 | D34: 344.33333 | E34: 3 | G34: =IF(G$15=0,0,G$15/$D$15*$E34*$D34) -> 7231 | H34: =IF(H$15=0,0,H$15/$D$15*$E34*$D34) -> 7231 | I34: =IF(I$15=0,0,I$15/$D$15*$E34*$D34) -> 7231 | J34: =IF(J$15=0,0,J$15/$D$15*$E34*$D34) -> 7231 | K34: =IF(K$15=0,0,K$15/$D$15*$E34*$D34) -> 7231 | L34: =IF(L$15=0,0,L$15/$D$15*$E34*$D34) -> 7231 | M34: =IF(M$15=0,0,M$15/$D$15*$E34*$D34) -> 7231 | N34: =IF(N$15=0,0,N$15/$D$15*$E34*$D34) -> 7231 | ... P34: =IF(P$15=0,0,P$15/$D$15*$E34*$D34) -> 7231
B35: О-кольцо | C35: 07000-B5180 | D35: 24.5 | E35: 3 | G35: =IF(G$15=0,0,G$15/$D$15*$E35*$D35) -> 514.5 | H35: =IF(H$15=0,0,H$15/$D$15*$E35*$D35) -> 514.5 | I35: =IF(I$15=0,0,I$15/$D$15*$E35*$D35) -> 514.5 | J35: =IF(J$15=0,0,J$15/$D$15*$E35*$D35) -> 514.5 | K35: =IF(K$15=0,0,K$15/$D$15*$E35*$D35) -> 514.5 | L35: =IF(L$15=0,0,L$15/$D$15*$E35*$D35) -> 514.5 | M35: =IF(M$15=0,0,M$15/$D$15*$E35*$D35) -> 514.5 | N35: =IF(N$15=0,0,N$15/$D$15*$E35*$D35) -> 514.5 | ... P35: =IF(P$15=0,0,P$15/$D$15*$E35*$D35) -> 514.5
B36: Воздушный фильтр | C36: 600-185-6100 | D36: 401.33333 | E36: 2 | G36: =IF(G$15=0,0,G$15/$D$15*$E36*$D36) -> 5618.6667 | H36: =IF(H$15=0,0,H$15/$D$15*$E36*$D36) -> 5618.6667 | I36: =IF(I$15=0,0,I$15/$D$15*$E36*$D36) -> 5618.6667 | J36: =IF(J$15=0,0,J$15/$D$15*$E36*$D36) -> 5618.6667 | K36: =IF(K$15=0,0,K$15/$D$15*$E36*$D36) -> 5618.6667 | L36: =IF(L$15=0,0,L$15/$D$15*$E36*$D36) -> 5618.6667 | M36: =IF(M$15=0,0,M$15/$D$15*$E36*$D36) -> 5618.6667 | N36: =IF(N$15=0,0,N$15/$D$15*$E36*$D36) -> 5618.6667 | ... P36: =IF(P$15=0,0,P$15/$D$15*$E36*$D36) -> 5618.6667
B37: О-кольцо | C37: 706-76-71390 | D37: 9.8333333 | E37: 2 | G37: =IF(G$15=0,0,G$15/$D$15*$E37*$D37) -> 137.66667 | H37: =IF(H$15=0,0,H$15/$D$15*$E37*$D37) -> 137.66667 | I37: =IF(I$15=0,0,I$15/$D$15*$E37*$D37) -> 137.66667 | J37: =IF(J$15=0,0,J$15/$D$15*$E37*$D37) -> 137.66667 | K37: =IF(K$15=0,0,K$15/$D$15*$E37*$D37) -> 137.66667 | L37: =IF(L$15=0,0,L$15/$D$15*$E37*$D37) -> 137.66667 | M37: =IF(M$15=0,0,M$15/$D$15*$E37*$D37) -> 137.66667 | N37: =IF(N$15=0,0,N$15/$D$15*$E37*$D37) -> 137.66667 | ... P37: =IF(P$15=0,0,P$15/$D$15*$E37*$D37) -> 137.66667
B38: Масло редуктора поворота | C38: ROCKET FLUID 30 | D38: 6.8918919 | E38: 60 | G38: =IF(G$15=0,0,G$15/$D$15*$E38*$D38) -> 2894.5946 | H38: =IF(H$15=0,0,H$15/$D$15*$E38*$D38) -> 2894.5946 | I38: =IF(I$15=0,0,I$15/$D$15*$E38*$D38) -> 2894.5946 | J38: =IF(J$15=0,0,J$15/$D$15*$E38*$D38) -> 2894.5946 | K38: =IF(K$15=0,0,K$15/$D$15*$E38*$D38) -> 2894.5946 | L38: =IF(L$15=0,0,L$15/$D$15*$E38*$D38) -> 2894.5946 | M38: =IF(M$15=0,0,M$15/$D$15*$E38*$D38) -> 2894.5946 | N38: =IF(N$15=0,0,N$15/$D$15*$E38*$D38) -> 2894.5946 | ... P38: =IF(P$15=0,0,P$15/$D$15*$E38*$D38) -> 2894.5946
B39: Масло механизма отбора мощн. | C39: ROCKET FLUID 30 | D39: 6.8918919 | E39: 36 | G39: =IF(G$15=0,0,G$15/$D$15*$E39*$D39) -> 1736.7568 | H39: =IF(H$15=0,0,H$15/$D$15*$E39*$D39) -> 1736.7568 | I39: =IF(I$15=0,0,I$15/$D$15*$E39*$D39) -> 1736.7568 | J39: =IF(J$15=0,0,J$15/$D$15*$E39*$D39) -> 1736.7568 | K39: =IF(K$15=0,0,K$15/$D$15*$E39*$D39) -> 1736.7568 | L39: =IF(L$15=0,0,L$15/$D$15*$E39*$D39) -> 1736.7568 | M39: =IF(M$15=0,0,M$15/$D$15*$E39*$D39) -> 1736.7568 | N39: =IF(N$15=0,0,N$15/$D$15*$E39*$D39) -> 1736.7568 | ... P39: =IF(P$15=0,0,P$15/$D$15*$E39*$D39) -> 1736.7568
B40: Фильтр гидромотора поворота | C40: 20Y-62-51691 | D40: 102 | E40: 2 | G40: =IF(G$15=0,0,G$15/$D$15*$E40*$D40) -> 1428 | H40: =IF(H$15=0,0,H$15/$D$15*$E40*$D40) -> 1428 | I40: =IF(I$15=0,0,I$15/$D$15*$E40*$D40) -> 1428 | J40: =IF(J$15=0,0,J$15/$D$15*$E40*$D40) -> 1428 | K40: =IF(K$15=0,0,K$15/$D$15*$E40*$D40) -> 1428 | L40: =IF(L$15=0,0,L$15/$D$15*$E40*$D40) -> 1428 | M40: =IF(M$15=0,0,M$15/$D$15*$E40*$D40) -> 1428 | N40: =IF(N$15=0,0,N$15/$D$15*$E40*$D40) -> 1428 | ... P40: =IF(P$15=0,0,P$15/$D$15*$E40*$D40) -> 1428
B41: ТО-3 | E41: =VLOOKUP($B41,$B$14:$C$18,2,FALSE) -> 2000 | F41: =VLOOKUP($B41,$B$14:$E$18,4,FALSE) -> 3
B42: Прокладка клапанной крышки | C42: 6218-11-8830 | D42: 4.1666667 | E42: 12 | G42: =IF(G$16=0,0,G$16/$D$16*$E42*$D42) -> 150 | H42: =IF(H$16=0,0,H$16/$D$16*$E42*$D42) -> 150 | I42: =IF(I$16=0,0,I$16/$D$16*$E42*$D42) -> 150 | J42: =IF(J$16=0,0,J$16/$D$16*$E42*$D42) -> 150 | K42: =IF(K$16=0,0,K$16/$D$16*$E42*$D42) -> 150 | L42: =IF(L$16=0,0,L$16/$D$16*$E42*$D42) -> 150 | M42: =IF(M$16=0,0,M$16/$D$16*$E42*$D42) -> 150 | N42: =IF(N$16=0,0,N$16/$D$16*$E42*$D42) -> 150 | ... P42: =IF(P$16=0,0,P$16/$D$16*$E42*$D42) -> 150
B43: Фильтр салонный кондиционера | C43: 208-979-7620 | D43: 10.833333 | E43: 2 | G43: =IF(G$16=0,0,G$16/$D$16*$E43*$D43) -> 65 | H43: =IF(H$16=0,0,H$16/$D$16*$E43*$D43) -> 65 | I43: =IF(I$16=0,0,I$16/$D$16*$E43*$D43) -> 65 | J43: =IF(J$16=0,0,J$16/$D$16*$E43*$D43) -> 65 | K43: =IF(K$16=0,0,K$16/$D$16*$E43*$D43) -> 65 | L43: =IF(L$16=0,0,L$16/$D$16*$E43*$D43) -> 65 | M43: =IF(M$16=0,0,M$16/$D$16*$E43*$D43) -> 65 | N43: =IF(N$16=0,0,N$16/$D$16*$E43*$D43) -> 65 | ... P43: =IF(P$16=0,0,P$16/$D$16*$E43*$D43) -> 65
B44: Фильтр наружний кондиционера | C44: 17M-911-3530 | D44: 51.333333 | E44: 2 | G44: =IF(G$16=0,0,G$16/$D$16*$E44*$D44) -> 308 | H44: =IF(H$16=0,0,H$16/$D$16*$E44*$D44) -> 308 | I44: =IF(I$16=0,0,I$16/$D$16*$E44*$D44) -> 308 | J44: =IF(J$16=0,0,J$16/$D$16*$E44*$D44) -> 308 | K44: =IF(K$16=0,0,K$16/$D$16*$E44*$D44) -> 308 | L44: =IF(L$16=0,0,L$16/$D$16*$E44*$D44) -> 308 | M44: =IF(M$16=0,0,M$16/$D$16*$E44*$D44) -> 308 | N44: =IF(N$16=0,0,N$16/$D$16*$E44*$D44) -> 308 | ... P44: =IF(P$16=0,0,P$16/$D$16*$E44*$D44) -> 308
B45: Масло конечной передачи | C45: ROCKET FLUID 30 | D45: 6.8918919 | E45: 170 | G45: =IF(G$16=0,0,G$16/$D$16*$E45*$D45) -> 3514.8649 | H45: =IF(H$16=0,0,H$16/$D$16*$E45*$D45) -> 3514.8649 | I45: =IF(I$16=0,0,I$16/$D$16*$E45*$D45) -> 3514.8649 | J45: =IF(J$16=0,0,J$16/$D$16*$E45*$D45) -> 3514.8649 | K45: =IF(K$16=0,0,K$16/$D$16*$E45*$D45) -> 3514.8649 | L45: =IF(L$16=0,0,L$16/$D$16*$E45*$D45) -> 3514.8649 | M45: =IF(M$16=0,0,M$16/$D$16*$E45*$D45) -> 3514.8649 | N45: =IF(N$16=0,0,N$16/$D$16*$E45*$D45) -> 3514.8649 | ... P45: =IF(P$16=0,0,P$16/$D$16*$E45*$D45) -> 3514.8649
B46: ТО-4 | E46: =VLOOKUP($B46,$B$14:$C$18,2,FALSE) -> 4000 | F46: =VLOOKUP($B46,$B$14:$E$18,4,FALSE) -> 1
B47: фильтр охлаждающей жидкости | C47: 600-411-5110 | D47: 134.83333 | E47: 2 | G47: =IF(G$17=0,0,G$17/$D$17*$E47*$D47) -> 269.66667 | H47: =IF(H$17=0,0,H$17/$D$17*$E47*$D47) -> 269.66667 | I47: =IF(I$17=0,0,I$17/$D$17*$E47*$D47) -> 269.66667 | J47: =IF(J$17=0,0,J$17/$D$17*$E47*$D47) -> 269.66667 | K47: =IF(K$17=0,0,K$17/$D$17*$E47*$D47) -> 269.66667 | L47: =IF(L$17=0,0,L$17/$D$17*$E47*$D47) -> 269.66667 | M47: =IF(M$17=0,0,M$17/$D$17*$E47*$D47) -> 269.66667 | N47: =IF(N$17=0,0,N$17/$D$17*$E47*$D47) -> 269.66667 | ... P47: =IF(P$17=0,0,P$17/$D$17*$E47*$D47) -> 269.66667
B48: Ремень генератора | C48: 6266-81-6760 | D48: 28 | E48: 1 | G48: =IF(G$17=0,0,G$17/$D$17*$E48*$D48) -> 28 | H48: =IF(H$17=0,0,H$17/$D$17*$E48*$D48) -> 28 | I48: =IF(I$17=0,0,I$17/$D$17*$E48*$D48) -> 28 | J48: =IF(J$17=0,0,J$17/$D$17*$E48*$D48) -> 28 | K48: =IF(K$17=0,0,K$17/$D$17*$E48*$D48) -> 28 | L48: =IF(L$17=0,0,L$17/$D$17*$E48*$D48) -> 28 | M48: =IF(M$17=0,0,M$17/$D$17*$E48*$D48) -> 28 | N48: =IF(N$17=0,0,N$17/$D$17*$E48*$D48) -> 28 | ... P48: =IF(P$17=0,0,P$17/$D$17*$E48*$D48) -> 28
B49: Ремень генератора | C49: 6266-81-6750 | D49: 157.5 | E49: 1 | G49: =IF(G$17=0,0,G$17/$D$17*$E49*$D49) -> 157.5 | H49: =IF(H$17=0,0,H$17/$D$17*$E49*$D49) -> 157.5 | I49: =IF(I$17=0,0,I$17/$D$17*$E49*$D49) -> 157.5 | J49: =IF(J$17=0,0,J$17/$D$17*$E49*$D49) -> 157.5 | K49: =IF(K$17=0,0,K$17/$D$17*$E49*$D49) -> 157.5 | L49: =IF(L$17=0,0,L$17/$D$17*$E49*$D49) -> 157.5 | M49: =IF(M$17=0,0,M$17/$D$17*$E49*$D49) -> 157.5 | N49: =IF(N$17=0,0,N$17/$D$17*$E49*$D49) -> 157.5 | ... P49: =IF(P$17=0,0,P$17/$D$17*$E49*$D49) -> 157.5
B50: Ремень кондиционера | C50: 04120-21757 | D50: 61 | E50: 2 | G50: =IF(G$17=0,0,G$17/$D$17*$E50*$D50) -> 122 | H50: =IF(H$17=0,0,H$17/$D$17*$E50*$D50) -> 122 | I50: =IF(I$17=0,0,I$17/$D$17*$E50*$D50) -> 122 | J50: =IF(J$17=0,0,J$17/$D$17*$E50*$D50) -> 122 | K50: =IF(K$17=0,0,K$17/$D$17*$E50*$D50) -> 122 | L50: =IF(L$17=0,0,L$17/$D$17*$E50*$D50) -> 122 | M50: =IF(M$17=0,0,M$17/$D$17*$E50*$D50) -> 122 | N50: =IF(N$17=0,0,N$17/$D$17*$E50*$D50) -> 122 | ... P50: =IF(P$17=0,0,P$17/$D$17*$E50*$D50) -> 122
B51: Охлаждающая жидкость | C51: Антифриз Газпромнефть Антифриз | D51: 2.36 | E51: 190 | G51: =IF(G$17=0,0,G$17/$D$17*$E51*$D51) -> 448.4 | H51: =IF(H$17=0,0,H$17/$D$17*$E51*$D51) -> 448.4 | I51: =IF(I$17=0,0,I$17/$D$17*$E51*$D51) -> 448.4 | J51: =IF(J$17=0,0,J$17/$D$17*$E51*$D51) -> 448.4 | K51: =IF(K$17=0,0,K$17/$D$17*$E51*$D51) -> 448.4 | L51: =IF(L$17=0,0,L$17/$D$17*$E51*$D51) -> 448.4 | M51: =IF(M$17=0,0,M$17/$D$17*$E51*$D51) -> 448.4 | N51: =IF(N$17=0,0,N$17/$D$17*$E51*$D51) -> 448.4 | ... P51: =IF(P$17=0,0,P$17/$D$17*$E51*$D51) -> 448.4
B52: ТО-5 | E52: 5000 | F52: =VLOOKUP($B52,$B$14:$E$18,4,FALSE) -> 1
B53: Гидравлическое масло | C53: ROCKET FLUID 10W | D53: 6.4256757 | E53: 1300 | G53: =IF(G$18=0,0,G$18/$D$18*$E53*$D53) -> 8353.3784 | H53: =IF(H$18=0,0,H$18/$D$18*$E53*$D53) -> 8353.3784 | I53: =IF(I$18=0,0,I$18/$D$18*$E53*$D53) -> 8353.3784 | J53: =IF(J$18=0,0,J$18/$D$18*$E53*$D53) -> 8353.3784 | K53: =IF(K$18=0,0,K$18/$D$18*$E53*$D53) -> 8353.3784 | L53: =IF(L$18=0,0,L$18/$D$18*$E53*$D53) -> 8353.3784 | M53: =IF(M$18=0,0,M$18/$D$18*$E53*$D53) -> 8353.3784 | N53: =IF(N$18=0,0,N$18/$D$18*$E53*$D53) -> 8353.3784 | ... P53: =IF(P$18=0,0,P$18/$D$18*$E53*$D53) -> 8353.3784

Sheet PC2000-8 MS_Ремонты
B2: ячейки к заполнению поставщиком
B3: Расчетный КТГ | F3: ='PC2000-8 MS'!E9 -> 0.94081367 | G3: ='PC2000-8 MS'!F9 -> 0.90174721 | H3: ='PC2000-8 MS'!G9 -> 0.87999429 | I3: ='PC2000-8 MS'!H9 -> 0.90441083 | J3: ='PC2000-8 MS'!I9 -> 0.93726218 | K3: ='PC2000-8 MS'!J9 -> 0.85513382 | L3: ='PC2000-8 MS'!K9 -> 0.9279395 | M3: ='PC2000-8 MS'!L9 -> 0.853802 | ... O3: ='PC2000-8 MS'!N9 -> 0.91106989
B4: Год службы (год) | C4: Ед.изм. | F4: 1 | G4: =F4+1 -> 2 | H4: =G4+1 -> 3 | I4: =H4+1 -> 4 | J4: =I4+1 -> 5 | K4: =J4+1 -> 6 | L4: =K4+1 -> 7 | M4: =L4+1 -> 8 | N4: =M4+1 -> 9 | O4: =N4+1 -> 10
B5: Наработка на начало года | C5: м/час | F5: 0 | G5: =F6+1 -> 7001 | H5: =G6+1 -> 14001 | I5: =H6+1 -> 21001 | J5: =I6+1 -> 28001 | K5: =J6+1 -> 35001 | L5: =K6+1 -> 42001 | M5: =L6+1 -> 49001 | N5: =M6+1 -> 56001 | O5: =N6+1 -> 63001
B6: Наработка на конец года | C6: м/час | E6: ='PC2000-8 MS_ТО'!F6 -> 7000 | F6: =E6 -> 7000 | G6: =F6+$E6 -> 14000 | H6: =G6+$E6 -> 21000 | I6: =H6+$E6 -> 28000 | J6: =I6+$E6 -> 35000 | K6: =J6+$E6 -> 42000 | L6: =K6+$E6 -> 49000 | M6: =L6+$E6 -> 56000 | N6: =M6+$E6 -> 63000 | O6: =N6+$E6 -> 70000
B8: Простои в ремонтах | C8: часов | F8: =F16 -> 24 | G8: =G16 -> 376 | H8: =H16 -> 572 | I8: =I16 -> 352 | J8: =J16 -> 56 | K8: =K16 -> 796 | L8: =L16 -> 140 | M8: =M16 -> 808 | ... O8: =O16 -> 292
B9: Затраты на ТО и ремонты | C9: $/год | F9: =SUM(F10:F12) -> 1741.9268 | G9: =SUM(G10:G12) -> 1374897.5 | H9: =SUM(H10:H12) -> 1477590.8 | I9: =SUM(I10:I12) -> 1373155.6 | J9: =SUM(J10:J12) -> 9831.1626 | K9: =SUM(K10:K12) -> 2792140.9 | L9: =SUM(L10:L12) -> 59476.407 | M9: =SUM(M10:M12) -> 2793011.9 | ... O9: =SUM(O10:O12) -> 1325252.3
B10: текущие ремонты | C10: $/год | F10: =F94 -> 1741.9268 | G10: =G94 -> 4354.8171 | H10: =H94 -> 3483.8537 | I10: =I94 -> 2612.8903 | J10: =J94 -> 3483.8537 | K10: =K94 -> 2612.8903 | L10: =L94 -> 4354.8171 | M10: =M94 -> 3483.8537 | ... O10: =O94 -> 3483.8537
B11: планово-предупредительные (капитальные) ремонты | C11: $/год | F11: =F99 -> 0 | G11: =G99 -> 1347607.3 | H11: =H99 -> 1436074.8 | I11: =I99 -> 1347607.3 | J11: =J99 -> 5766.6667 | K11: =K99 -> 2734367 | L11: =L99 -> 49315.167 | M11: =M99 -> 2734367 | ... O11: =O99 -> 1304058.8
B12: сервис (трудозатраты) | C12: $/год | F12: =F57 -> 0 | G12: =G57 -> 22935.37 | H12: =H57 -> 38032.069 | I12: =I57 -> 22935.37 | J12: =J57 -> 580.64228 | K12: =K57 -> 55161.017 | L12: =L57 -> 5806.4228 | M12: =M57 -> 55161.017 | ... O12: =O57 -> 17709.59
B14: Простои в ремонте (час)
B15: Вид ремонта | C15: Ед.изм. | F15: =F4 -> 1 | G15: =G4 -> 2 | H15: =H4 -> 3 | I15: =I4 -> 4 | J15: =J4 -> 5 | K15: =K4 -> 6 | L15: =L4 -> 7 | M15: =M4 -> 8 | ... O15: =O4 -> 10
B16: Всего простоев | F16: =SUM(F17:F53) -> 24 | G16: =SUM(G17:G53) -> 376 | H16: =SUM(H17:H53) -> 572 | I16: =SUM(I17:I53) -> 352 | J16: =SUM(J17:J53) -> 56 | K16: =SUM(K17:K53) -> 796 | L16: =SUM(L17:L53) -> 140 | M16: =SUM(M17:M53) -> 808 | ... O16: =SUM(O17:O53) -> 292
B17: Ходовая часть | C17: часов
B18: Звёздочка | C18: часов | D18: 24 | H18: 24 | K18: 24 | M18: 24
B19: Редуктор хода | C19: часов | D19: 24 | H19: 24 | K19: 24 | M19: 24
B20: Натяжное колесо | C20: часов | D20: 24 | H20: 24 | K20: 24 | M20: 24
B21: Гусеничная лента | C21: часов | D21: 36 | H21: 36 | K21: 36 | M21: 36
B22: Г. мотор хода | C22: часов | D22: 12 | G22: 12 | I22: 12 | K22: 12 | M22: 12 | O22: 12
B23: Поддерживающий каток | C23: часов | D23: 12 | H23: 12 | K23: 12 | M23: 12
B24: Опорный каток | C24: часов | D24: 36 | H24: 36 | K24: 36 | M24: 36
B25: Рабочее оборудование | C25: часов
B26: Г. цилиндр стрелы | C26: часов | D26: 12 | G26: 12 | I26: 12 | K26: 12 | M26: 12 | O26: 12
B27: Г. цилиндр стрелы | C27: часов | D27: 12 | G27: 12 | I27: 12 | K27: 12 | M27: 12 | O27: 12
B28: Г. цилиндр рукояти | C28: часов | D28: 8 | G28: 8 | I28: 8 | K28: 8 | M28: 8 | O28: 8
B29: Г. цилиндр ковша | C29: часов | D29: 12 | G29: 12 | I29: 12 | K29: 12 | M29: 12 | O29: 12
B30: Гидравлическая система | C30: часов
B31: Г. распределитель | C31: часов | D31: 36 | G31: 36 | I31: 36 | K31: 36 | M31: 36 | O31: 36
B32: Г. распределитель | C32: часов | D32: 36 | G32: 36 | I32: 36 | K32: 36 | M32: 36 | O32: 36
B33: Г.насос управления | C33: часов | D33: 24 | G33: 24 | I33: 24 | K33: 24 | M33: 24 | O33: 24
B34: Г.насос | C34: часов | D34: 36 | G34: 36 | I34: 36 | K34: 36 | M34: 36 | O34: 36
B35: Г.мотор вентелятора | C35: часов | D35: 8 | G35: 8 | I35: 8 | K35: 8 | M35: 8 | O35: 8
B36: Система поворота | C36: часов
B37: Г. мотор поворота | C37: часов | D37: 24 | G37: 24 | I37: 24 | K37: 24 | M37: 24 | O37: 24
B38: Поворотный круг | C38: часов | D38: 144 | H38: 144 | K38: 144 | M38: 144
B39: Редуктор поворота 21T-26-00300 | C39: часов | D39: 24 | G39: 24 | I39: 24 | K39: 24 | M39: 24 | O39: 24
B40: ДВС | C40: часов
B41: ДВС | C41: часов | D41: 72 | H41: 72 | K41: 72 | M41: 72
B42: МЕХАНИЗМ ОТБОРА МОЩНОСТИ | C42: часов | D42: 48 | H42: 48 | K42: 48 | M42: 48
B43: Турбокомпрессор | C43: часов | D43: 8 | G43: 8 | H43: 8 | I43: 8 | K43: 8 | L43: 8 | M43: 8 | N43: 8
B44: Турбокомпрессор | C44: часов | D44: 8 | G44: 8 | H44: 8 | I44: 8 | K44: 8 | L44: 8 | M44: 8 | N44: 8
B45: Топл. Насос | C45: часов | D45: 24 | H45: 24 | K45: 24 | M45: 24
B46: Топл. Форсунка | C46: часов | D46: 24 | G46: 24 | H46: 24 | I46: 24 | K46: 24 | L46: 24 | M46: 24 | N46: 24
B47: Водиной насос | C47: часов | D47: 24 | G47: 24 | H47: 24 | I47: 24 | K47: 24 | L47: 24 | M47: 24 | N47: 24
B48: Генератор | C48: часов | D48: 8 | H48: 8 | J48: 8 | L48: 8 | N48: 8
B49: Стартер | C49: часов | D49: 8 | G49: 8 | H49: 8 | I49: 8 | K49: 8 | L49: 8 | M49: 8 | N49: 8
B50: ремонты
B51: Ремонт системы смазки | C51: часов | D51: 24 | G51: =D51 -> 24 | H51: =D51 -> 24 | J51: =D51 -> 24 | L51: =D51 -> 24 | M51: =D51 -> 24 | O51: =D51 -> 24
B52: Ремонт системы кондиционировани | C52: часов | D52: 12 | G52: =D52 -> 12 | I52: =D52 -> 12 | K52: =D52 -> 12 | L52: =D52 -> 12 | N52: =D52 -> 12
B53: Чистка радиаторов | C53: часов | D53: 24 | F53: =D53 -> 24 | G53: =D53 -> 24 | H53: =D53 -> 24 | I53: =D53 -> 24 | J53: =D53 -> 24 | K53: =D53 -> 24 | L53: =D53 -> 24 | M53: =D53 -> 24 | N53: =D53 -> 24 | O53: =D53 -> 24
B55: Трудозатраты на ремонты (ч/час) | D55: ='PC2000-8 MS_ТО'!F10 -> 72.580285
B56: Вид ремонта | C56: Ед.изм. | D56: Стоимость ч/часа | F56: =F15 -> 1 | G56: =G15 -> 2 | H56: =H15 -> 3 | I56: =I15 -> 4 | J56: =J15 -> 5 | K56: =K15 -> 6 | L56: =L15 -> 7 | M56: =M15 -> 8 | ... O56: =O15 -> 10
B57: Всего ч/часов | C57: ч/часов | F57: =SUM(F58:F90) -> 0 | G57: =SUM(G58:G90) -> 22935.37 | H57: =SUM(H58:H90) -> 38032.069 | I57: =SUM(I58:I90) -> 22935.37 | J57: =SUM(J58:J90) -> 580.64228 | K57: =SUM(K58:K90) -> 55161.017 | L57: =SUM(L58:L90) -> 5806.4228 | M57: =SUM(M58:M90) -> 55161.017 | ... O57: =SUM(O58:O90) -> 17709.59
B58: Ходовая часть
B59: Звёздочка | C59: ч/часов | D59: =$D$55 -> 72.580285 | E59: 24 | H59: =E59*D59 -> 1741.9268 | K59: =E59*D59 -> 1741.9268 | M59: =E59*D59 -> 1741.9268
B60: Редуктор хода | C60: ч/часов | D60: =$D$55 -> 72.580285 | E60: 24 | H60: =E60*D60 -> 1741.9268 | K60: =E60*D60 -> 1741.9268 | M60: =E60*D60 -> 1741.9268
B61: Натяжное колесо | C61: ч/часов | D61: =$D$55 -> 72.580285 | E61: 24 | H61: =E61*D61 -> 1741.9268 | K61: =E61*D61 -> 1741.9268 | M61: =E61*D61 -> 1741.9268
B62: Гусеничная лента | C62: ч/часов | D62: =$D$55 -> 72.580285 | E62: 36 | H62: =E62*D62 -> 2612.8903 | K62: =E62*D62 -> 2612.8903 | M62: =E62*D62 -> 2612.8903
B63: Г. мотор хода | C63: ч/часов | D63: =$D$55 -> 72.580285 | E63: 12 | G63: =E63*D63 -> 870.96342 | I63: =E63*D63 -> 870.96342 | K63: =E63*D63 -> 870.96342 | M63: =E63*D63 -> 870.96342 | O63: =E63*D63 -> 870.96342
B64: Поддерживающий каток | C64: ч/часов | D64: =$D$55 -> 72.580285 | E64: 12 | H64: =E64*D64 -> 870.96342 | K64: =E64*D64 -> 870.96342 | M64: =E64*D64 -> 870.96342
B65: Опорный каток | C65: ч/часов | D65: =$D$55 -> 72.580285 | E65: 36 | H65: =E65*D65 -> 2612.8903 | K65: =E65*D65 -> 2612.8903 | M65: =E65*D65 -> 2612.8903
B66: Рабочее оборудование | K66: =E66*D66 -> 0
B67: Г. цилиндр стрелы | C67: ч/часов | D67: =$D$55 -> 72.580285 | E67: 12 | G67: =E67*D67 -> 870.96342 | I67: =E67*D67 -> 870.96342 | K67: =E67*D67 -> 870.96342 | M67: =E67*D67 -> 870.96342 | O67: =E67*D67 -> 870.96342
B68: Г. цилиндр стрелы | C68: ч/часов | D68: =$D$55 -> 72.580285 | E68: 12 | G68: =E68*D68 -> 870.96342 | I68: =E68*D68 -> 870.96342 | K68: =E68*D68 -> 870.96342 | M68: =E68*D68 -> 870.96342 | O68: =E68*D68 -> 870.96342
B69: Г. цилиндр рукояти | C69: ч/часов | D69: =$D$55 -> 72.580285 | E69: 8 | G69: =E69*D69 -> 580.64228 | I69: =E69*D69 -> 580.64228 | K69: =E69*D69 -> 580.64228 | M69: =E69*D69 -> 580.64228 | O69: =E69*D69 -> 580.64228
B70: Г. цилиндр ковша | C70: ч/часов | D70: =$D$55 -> 72.580285 | E70: 12 | G70: =E70*D70 -> 870.96342 | I70: =E70*D70 -> 870.96342 | K70: =E70*D70 -> 870.96342 | M70: =E70*D70 -> 870.96342 | O70: =E70*D70 -> 870.96342
B71: Гидравлическая система
B72: Г. распределитель | C72: ч/часов | D72: =$D$55 -> 72.580285 | E72: 36 | G72: =E72*D72 -> 2612.8903 | I72: =E72*D72 -> 2612.8903 | K72: =E72*D72 -> 2612.8903 | M72: =E72*D72 -> 2612.8903 | O72: =E72*D72 -> 2612.8903
B73: Г. распределитель | C73: ч/часов | D73: =$D$55 -> 72.580285 | E73: 36 | G73: =E73*D73 -> 2612.8903 | I73: =E73*D73 -> 2612.8903 | K73: =E73*D73 -> 2612.8903 | M73: =E73*D73 -> 2612.8903 | O73: =E73*D73 -> 2612.8903
B74: Г.насос управления | C74: ч/часов | D74: =$D$55 -> 72.580285 | E74: 24 | G74: =E74*D74 -> 1741.9268 | I74: =E74*D74 -> 1741.9268 | K74: =E74*D74 -> 1741.9268 | M74: =E74*D74 -> 1741.9268 | O74: =E74*D74 -> 1741.9268
B75: Г.насос | C75: ч/часов | D75: =$D$55 -> 72.580285 | E75: 36 | G75: =E75*D75 -> 2612.8903 | I75: =E75*D75 -> 2612.8903 | K75: =E75*D75 -> 2612.8903 | M75: =E75*D75 -> 2612.8903 | O75: =E75*D75 -> 2612.8903
B76: Г.мотор вентелятора | C76: ч/часов | D76: =$D$55 -> 72.580285 | E76: 8 | G76: =E76*D76 -> 580.64228 | I76: =E76*D76 -> 580.64228 | K76: =E76*D76 -> 580.64228 | M76: =E76*D76 -> 580.64228 | O76: =E76*D76 -> 580.64228
B77: Система поворота
B78: Г. мотор поворота | C78: ч/часов | D78: =$D$55 -> 72.580285 | E78: 24 | G78: =E78*D78 -> 1741.9268 | I78: =E78*D78 -> 1741.9268 | K78: =E78*D78 -> 1741.9268 | M78: =E78*D78 -> 1741.9268 | O78: =E78*D78 -> 1741.9268
B79: Поворотный круг | C79: ч/часов | D79: =$D$55 -> 72.580285 | E79: 144 | H79: =E79*D79 -> 10451.561 | K79: =E79*D79 -> 10451.561 | M79: =E79*D79 -> 10451.561
B80: РЕДУКТОР ПОВОРОТА | C80: ч/часов | D80: =$D$55 -> 72.580285 | E80: 24 | G80: =E80*D80 -> 1741.9268 | I80: =E80*D80 -> 1741.9268 | K80: =E80*D80 -> 1741.9268 | M80: =E80*D80 -> 1741.9268 | O80: =E80*D80 -> 1741.9268
B81: ДВС
B82: ДВС | C82: ч/часов | D82: =$D$55 -> 72.580285 | E82: 72 | H82: =E82*D82 -> 5225.7805 | K82: =E82*D82 -> 5225.7805 | M82: =E82*D82 -> 5225.7805
B83: МЕХАНИЗМ ОТБОРА МОЩНОСТИ | C83: ч/часов | D83: =$D$55 -> 72.580285 | E83: 48 | H83: =E83*D83 -> 3483.8537 | K83: =E83*D83 -> 3483.8537 | M83: =E83*D83 -> 3483.8537
B84: Турбокомпрессор | C84: ч/часов | D84: =$D$55 -> 72.580285 | E84: 8 | G84: =E84*D84 -> 580.64228 | H84: =E84*D84 -> 580.64228 | I84: =E84*D84 -> 580.64228 | K84: =E84*D84 -> 580.64228 | L84: =E84*D84 -> 580.64228 | M84: =E84*D84 -> 580.64228 | N84: =E84*D84 -> 580.64228
B85: Турбокомпрессор | C85: ч/часов | D85: =$D$55 -> 72.580285 | E85: 8 | G85: =E85*D85 -> 580.64228 | H85: =E85*D85 -> 580.64228 | I85: =E85*D85 -> 580.64228 | K85: =E85*D85 -> 580.64228 | L85: =E85*D85 -> 580.64228 | M85: =E85*D85 -> 580.64228 | N85: =E85*D85 -> 580.64228
B86: Топл. Насос | C86: ч/часов | D86: =$D$55 -> 72.580285 | E86: 24 | H86: =E86*D86 -> 1741.9268 | K86: =E86*D86 -> 1741.9268 | M86: =E86*D86 -> 1741.9268
B87: Топл. Форсунка | C87: ч/часов | D87: =$D$55 -> 72.580285 | E87: 24 | G87: =E87*D87 -> 1741.9268 | H87: =E87*D87 -> 1741.9268 | I87: =E87*D87 -> 1741.9268 | K87: =E87*D87 -> 1741.9268 | L87: =E87*D87 -> 1741.9268 | M87: =E87*D87 -> 1741.9268 | N87: =E87*D87 -> 1741.9268
B88: Водиной насос | C88: ч/часов | D88: =$D$55 -> 72.580285 | E88: 24 | G88: =E88*D88 -> 1741.9268 | H88: =E88*D88 -> 1741.9268 | I88: =E88*D88 -> 1741.9268 | K88: =E88*D88 -> 1741.9268 | L88: =E88*D88 -> 1741.9268 | M88: =E88*D88 -> 1741.9268 | N88: =E88*D88 -> 1741.9268
B89: Генератор | C89: ч/часов | D89: =$D$55 -> 72.580285 | E89: 8 | H89: =E89*D89 -> 580.64228 | J89: =E89*D89 -> 580.64228 | L89: =E89*D89 -> 580.64228 | N89: =E89*D89 -> 580.64228
B90: Стартер | C90: ч/часов | D90: =$D$55 -> 72.580285 | E90: 8 | G90: =E90*D90 -> 580.64228 | H90: =E90*D90 -> 580.64228 | I90: =E90*D90 -> 580.64228 | K90: =E90*D90 -> 580.64228 | L90: =E90*D90 -> 580.64228 | M90: =E90*D90 -> 580.64228 | N90: =E90*D90 -> 580.64228
B92: Затраты на ремонты ($)
B93: Детализация затрат | C93: Стоимость за ед., $ | D93: Ресурс до замены / ремонта, м/ч | E93: Кол-во МТР | F93: $ | G93: $ | H93: $ | I93: $ | J93: $ | K93: $ | L93: $ | M93: $ | N93: $ | O93: $
B94: Текущие ремонты (если планируются) | F94: =SUM(F95:F97) -> 1741.9268 | G94: =SUM(G95:G97) -> 4354.8171 | H94: =SUM(H95:H97) -> 3483.8537 | I94: =SUM(I95:I97) -> 2612.8903 | J94: =SUM(J95:J97) -> 3483.8537 | K94: =SUM(K95:K97) -> 2612.8903 | L94: =SUM(L95:L97) -> 4354.8171 | M94: =SUM(M95:M97) -> 3483.8537 | ... O94: =SUM(O95:O97) -> 3483.8537
B95: Ремонт системы смазки | C95: 1741.9268 | D95: 10 000 | E95: 1 | G95: =C95 -> 1741.9268 | H95: =C95 -> 1741.9268 | J95: =C95 -> 1741.9268 | L95: =C95 -> 1741.9268 | M95: =C95 -> 1741.9268 | O95: =C95 -> 1741.9268
B96: Ремонт системы кондиционировани | C96: 870.96342 | D96: 12 000 | E96: 1 | G96: =C96 -> 870.96342 | I96: =C96 -> 870.96342 | K96: =C96 -> 870.96342 | L96: =C96 -> 870.96342 | N96: =C96 -> 870.96342
B97: Чистка радиаторов | C97: 1741.9268 | D97: 7 000 | E97: 1 | F97: =C97 -> 1741.9268 | G97: =C97 -> 1741.9268 | H97: =C97 -> 1741.9268 | I97: =C97 -> 1741.9268 | J97: =C97 -> 1741.9268 | K97: =C97 -> 1741.9268 | L97: =C97 -> 1741.9268 | M97: =C97 -> 1741.9268 | N97: =C97 -> 1741.9268 | O97: =C97 -> 1741.9268
B99: планово-предупредительные (капитальные) ремонты | F99: =SUM(F100:F132) -> 0 | G99: =SUM(G100:G132) -> 1347607.3 | H99: =SUM(H100:H132) -> 1436074.8 | I99: =SUM(I100:I132) -> 1347607.3 | J99: =SUM(J100:J132) -> 5766.6667 | K99: =SUM(K100:K132) -> 2734367 | L99: =SUM(L100:L132) -> 49315.167 | M99: =SUM(M100:M132) -> 2734367 | ... O99: =SUM(O100:O132) -> 1304058.8 | Q99: 1 | R99: 2 | S99: 3 | T99: 4 | U99: 5 | V99: 6
B100: Ходовая часть
B101: Звёздочка | C101: 7884 | D101: 17600 | E101: 2 | H101: =E101*C101 -> 15768 | K101: =E101*C101 -> 15768 | M101: =E101*C101 -> 15768 | Q101: =$D101*Q$99 -> 17600 | R101: =$D101*R$99 -> 35200 | S101: =$D101*S$99 -> 52800 | T101: =$D101*T$99 -> 70400 | U101: =$D101*U$99 -> 88000 | V101: =$D101*V$99 -> 105600
B102: Редуктор хода | C102: 235650.33 | D102: 17600 | E102: 2 | H102: =E102*C102 -> 471300.67 | K102: =E102*C102 -> 471300.67 | M102: =E102*C102 -> 471300.67 | Q102: =$D102*Q$99 -> 17600 | R102: =$D102*R$99 -> 35200 | S102: =$D102*S$99 -> 52800 | T102: =$D102*T$99 -> 70400 | U102: =$D102*U$99 -> 88000 | V102: =$D102*V$99 -> 105600
B103: Натяжное колесо | C103: 18572.667 | D103: 17600 | E103: 2 | H103: =E103*C103 -> 37145.333 | K103: =E103*C103 -> 37145.333 | M103: =E103*C103 -> 37145.333 | Q103: =$D103*Q$99 -> 17600 | R103: =$D103*R$99 -> 35200 | S103: =$D103*S$99 -> 52800 | T103: =$D103*T$99 -> 70400 | U103: =$D103*U$99 -> 88000 | V103: =$D103*V$99 -> 105600
B104: Гусеничная лента | C104: 21.333333 | D104: 17600 | E104: 1 | H104: =E104*C104 -> 21.333333 | K104: =E104*C104 -> 21.333333 | M104: =E104*C104 -> 21.333333 | Q104: =$D104*Q$99 -> 17600 | R104: =$D104*R$99 -> 35200 | S104: =$D104*S$99 -> 52800 | T104: =$D104*T$99 -> 70400 | U104: =$D104*U$99 -> 88000 | V104: =$D104*V$99 -> 105600
B105: Г. мотор хода | C105: 38619.667 | D105: 13200 | E105: 2 | G105: =E105*C105 -> 77239.333 | I105: =E105*C105 -> 77239.333 | K105: =E105*C105 -> 77239.333 | M105: =E105*C105 -> 77239.333 | O105: =E105*C105 -> 77239.333 | Q105: =$D105*Q$99 -> 13200 | R105: =$D105*R$99 -> 26400 | S105: =$D105*S$99 -> 39600 | T105: =$D105*T$99 -> 52800 | U105: =$D105*U$99 -> 66000 | V105: =$D105*V$99 -> 79200
B106: Поддерживающий каток | C106: 2500.6667 | D106: 17600 | E106: 6 | H106: =E106*C106 -> 15004 | K106: =E106*C106 -> 15004 | M106: =E106*C106 -> 15004 | Q106: =$D106*Q$99 -> 17600 | R106: =$D106*R$99 -> 35200 | S106: =$D106*S$99 -> 52800 | T106: =$D106*T$99 -> 70400 | U106: =$D106*U$99 -> 88000 | V106: =$D106*V$99 -> 105600
...

Sheet PC2000-11R ИСТК
B2: ячейки к заполнению поставщиком
B3: Экскаватор | C3: PC2000-11R | D3: расход ДТ - чуть меньше, чем у 2000-8 | Y3: Примечания
A4: 1 | B4: Период (год) | C4: Ед. изм. | D4: 0 | E4: =D4+1 -> 1 | F4: =E4+1 -> 2 | G4: =F4+1 -> 3 | H4: =G4+1 -> 4 | I4: =H4+1 -> 5 | J4: =I4+1 -> 6 | K4: =J4+1 -> 7 | L4: =K4+1 -> 8 | ... X4: =W4+1 -> 20 | Y4: Учесть срок эксплуатации (в данном примере это 20 лет)
A5: =A4+1 -> 2 | B5: Геометрическая емкость ковша экскаватора | C5: м3 | D5: 10
A6: =A5+1 -> 3 | B6: Емкость ковша с шапкой | C6: м3 | D6: 12
B7: КТГ в расчет | C7: коэф. | E7: ='PC2000-8 MS'!E7 -> 0.92406268 | F7: ='PC2000-8 MS'!F7 -> 0.79773755 | G7: ='PC2000-8 MS'!G7 -> 0.82453381 | H7: ='PC2000-8 MS'!H7 -> 0.76394441 | I7: ='PC2000-8 MS'!I7 -> 0.76281505 | J7: ='PC2000-8 MS'!J7 -> 0.81214813 | K7: ='PC2000-8 MS'!K7 -> 0.78656324 | L7: ='PC2000-8 MS'!L7 -> 0.84263903 | ... N7: ='PC2000-8 MS'!N7 -> 0.82670539 | Y7: равно PC2000 - факт по Группе
A9: =A6+1 -> 4 | B9: КТГ при нормативной эксплуатации | E9: =(8760-E10-E11-E12)/8760 -> 0.94292237 | F9: =(8760-F10-F11-F12)/8760 -> 0.93515348 | G9: =(8760-G10-G11-G12)/8760 -> 0.91284564 | H9: =(8760-H10-H11-H12)/8760 -> 0.88554351 | I9: =(8760-I10-I11-I12)/8760 -> 0.938483 | J9: =(8760-J10-J11-J12)/8760 -> 0.90507674 | K9: =(8760-K10-K11-K12)/8760 -> 0.93515348 | L9: =(8760-L10-L11-L12)/8760 -> 0.8933124 | ... X9: =(8760-X10-X11-X12)/8760 -> 0.91684107 | Y9: Расчетный
A10: =A9+1 -> 5 | B10: простои на ТО | C10: час | E10: ='PC2000-11R ИСТК_ТО'!G7 -> 264 | F10: ='PC2000-11R ИСТК_ТО'!H7 -> 264 | G10: ='PC2000-11R ИСТК_ТО'!I7 -> 264 | H10: ='PC2000-11R ИСТК_ТО'!J7 -> 264 | I10: ='PC2000-11R ИСТК_ТО'!K7 -> 264 | J10: ='PC2000-11R ИСТК_ТО'!L7 -> 264 | K10: ='PC2000-11R ИСТК_ТО'!M7 -> 264 | L10: ='PC2000-11R ИСТК_ТО'!N7 -> 264 | ... X10: ='PC2000-11R ИСТК_ТО'!Z7 -> 264
A11: =A10+1 -> 6 | B11: простои в ремонтах | C11: час | E11: ='PC2000-11R ИСТК_Ремонты'!F8 -> 0 | F11: ='PC2000-11R ИСТК_Ремонты'!G8 -> 70 | G11: ='PC2000-11R ИСТК_Ремонты'!H8 -> 271 | H11: ='PC2000-11R ИСТК_Ремонты'!I8 -> 517 | I11: ='PC2000-11R ИСТК_Ремонты'!J8 -> 40 | J11: ='PC2000-11R ИСТК_Ремонты'!K8 -> 341 | K11: ='PC2000-11R ИСТК_Ремонты'!L8 -> 70 | L11: ='PC2000-11R ИСТК_Ремонты'!M8 -> 447 | ... X11: ='PC2000-11R ИСТК_Ремонты'!Y8 -> 235
A12: =A11+1 -> 7 | B12: ежесменный осмотр (20 минут в смену) | C12: час | E12: =(8760-E10-E11)/12*20/60 -> 236 | F12: =(8760-F10-F11)/12*20/60 -> 234.05556 | G12: =(8760-G10-G11)/12*20/60 -> 228.47222 | H12: =(8760-H10-H11)/12*20/60 -> 221.63889 | I12: =(8760-I10-I11)/12*20/60 -> 234.88889 | J12: =(8760-J10-J11)/12*20/60 -> 226.52778 | K12: =(8760-K10-K11)/12*20/60 -> 234.05556 | L12: =(8760-L10-L11)/12*20/60 -> 223.58333 | ... X12: =(8760-X10-X11)/12*20/60 -> 229.47222
A13: =A12+1 -> 8 | B13: Время цикла | C13: сек | D13: 29
A14: =A13+1 -> 9 | B14: Мощность двигателя | C14: л.с. | D14: 990
A15: =A14+1 -> 10 | B15: Затраты на ТО и ремонты | C15: тыс.дол./год | E15: =SUM(E16:E20) -> 100.66605 | F15: =SUM(F16:F20) -> 141.10016 | G15: =SUM(G16:G20) -> 633.31816 | H15: =SUM(H16:H20) -> 1430.6176 | I15: =SUM(I16:I20) -> 211.66605 | J15: =SUM(J16:J20) -> 673.75227 | K15: =SUM(K16:K20) -> 141.10016 | L15: =SUM(L16:L20) -> 1390.1835 | ... X15: =SUM(X16:X20) -> 448.41816
A16: =A15+1 -> 11 | B16: ТО, включая смазочные | C16: тыс.дол./год | E16: ='PC2000-11R ИСТК_ТО'!G9/1000 -> 74.266046 | F16: ='PC2000-11R ИСТК_ТО'!H9/1000 -> 74.266046 | G16: ='PC2000-11R ИСТК_ТО'!I9/1000 -> 74.266046 | H16: ='PC2000-11R ИСТК_ТО'!J9/1000 -> 74.266046 | I16: ='PC2000-11R ИСТК_ТО'!K9/1000 -> 74.266046 | J16: ='PC2000-11R ИСТК_ТО'!L9/1000 -> 74.266046 | K16: ='PC2000-11R ИСТК_ТО'!M9/1000 -> 74.266046 | L16: ='PC2000-11R ИСТК_ТО'!N9/1000 -> 74.266046 | ... X16: ='PC2000-11R ИСТК_ТО'!Z9/1000 -> 74.266046
A17: =A16+1 -> 12 | B17: текущие ремонты | C17: тыс.дол./год | E17: ='PC2000-11R ИСТК_Ремонты'!F10/1000 -> 0 | F17: ='PC2000-11R ИСТК_Ремонты'!G10/1000 -> 0 | G17: ='PC2000-11R ИСТК_Ремонты'!H10/1000 -> 0 | H17: ='PC2000-11R ИСТК_Ремонты'!I10/1000 -> 0 | I17: ='PC2000-11R ИСТК_Ремонты'!J10/1000 -> 0 | J17: ='PC2000-11R ИСТК_Ремонты'!K10/1000 -> 0 | K17: ='PC2000-11R ИСТК_Ремонты'!L10/1000 -> 0 | L17: ='PC2000-11R ИСТК_Ремонты'!M10/1000 -> 0 | ... X17: ='PC2000-11R ИСТК_Ремонты'!Y10/1000 -> 0
A18: =A17+1 -> 13 | B18: планово-предупредительные (капитальные) ремонты | C18: тыс.дол./год | E18: ='PC2000-11R ИСТК_Ремонты'!F11/1000 -> 0 | F18: ='PC2000-11R ИСТК_Ремонты'!G11/1000 -> 38.68411 | G18: ='PC2000-11R ИСТК_Ремонты'!H11/1000 -> 525.87712 | H18: ='PC2000-11R ИСТК_Ремонты'!I11/1000 -> 1317.0265 | I18: ='PC2000-11R ИСТК_Ремонты'!J11/1000 -> 110 | J18: ='PC2000-11R ИСТК_Ремонты'!K11/1000 -> 564.56123 | K18: ='PC2000-11R ИСТК_Ремонты'!L11/1000 -> 38.68411 | L18: ='PC2000-11R ИСТК_Ремонты'!M11/1000 -> 1278.3424 | ... X18: ='PC2000-11R ИСТК_Ремонты'!Y11/1000 -> 341.87712
A19: =A18+1 -> 14 | B19: сервис (трудозатраты) - ТО | C19: тыс.дол./год | E19: ='PC2000-11R ИСТК_ТО'!G10/1000 -> 26.4 | F19: ='PC2000-11R ИСТК_ТО'!H10/1000 -> 26.4 | G19: ='PC2000-11R ИСТК_ТО'!I10/1000 -> 26.4 | H19: ='PC2000-11R ИСТК_ТО'!J10/1000 -> 26.4 | I19: ='PC2000-11R ИСТК_ТО'!K10/1000 -> 26.4 | J19: ='PC2000-11R ИСТК_ТО'!L10/1000 -> 26.4 | K19: ='PC2000-11R ИСТК_ТО'!M10/1000 -> 26.4 | L19: ='PC2000-11R ИСТК_ТО'!N10/1000 -> 26.4 | ... X19: ='PC2000-11R ИСТК_ТО'!Z10/1000 -> 26.4
A20: =A19+1 -> 15 | B20: сервис (трудозатраты) - ремонты | C20: тыс.дол./год | E20: ='PC2000-11R ИСТК_Ремонты'!F12/1000 -> 0 | F20: ='PC2000-11R ИСТК_Ремонты'!G12/1000 -> 1.75 | G20: ='PC2000-11R ИСТК_Ремонты'!H12/1000 -> 6.775 | H20: ='PC2000-11R ИСТК_Ремонты'!I12/1000 -> 12.925 | I20: ='PC2000-11R ИСТК_Ремонты'!J12/1000 -> 1 | J20: ='PC2000-11R ИСТК_Ремонты'!K12/1000 -> 8.525 | K20: ='PC2000-11R ИСТК_Ремонты'!L12/1000 -> 1.75 | L20: ='PC2000-11R ИСТК_Ремонты'!M12/1000 -> 11.175 | ... X20: ='PC2000-11R ИСТК_Ремонты'!Y12/1000 -> 5.875
A21: =A20+1 -> 16 | B21: Расходные материалы: | Y21: Здесь перечень приведен в качестве примера
A22: =A21+1 -> 17 | B22: канаты | Y22: Указать нужные данные (здесь приведены - в качестве примера)
A23: =A22+1 -> 18 | B23: удельный расход | Y23: Указать нужные данные (здесь приведены - в качестве примера)
A24: =A23+1 -> 19 | B24: цена за ед. | Y24: Указать нужные данные (здесь приведены - в качестве примера)
A25: =A24+1 -> 20 | B25: кабели | Y25: Указать нужные данные (здесь приведены - в качестве примера)
A26: =A25+1 -> 21 | B26: удельный расход | Y26: Указать нужные данные (здесь приведены - в качестве примера)
A27: =A26+1 -> 22 | B27: цена за ед. | Y27: Указать нужные данные (здесь приведены - в качестве примера)
A28: =A27+1 -> 23 | B28: зубья ковша | Y28: Указать нужные данные (здесь приведены - в качестве примера)
A29: =A28+1 -> 24 | B29: удельный расход | C29: шт. в год | E29: 30 | Y29: Указать нужные данные (здесь приведены - в качестве примера)
A30: =A29+1 -> 25 | B30: цена за ед. | C30: за 1 шт. | E30: 350 | Y30: Указать нужные данные (здесь приведены - в качестве примера)
A31: =A30+1 -> 26 | B31: режущие кромки | Y31: Указать нужные данные (здесь приведены - в качестве примера)
A32: =A31+1 -> 27 | B32: удельный расход | Y32: Указать нужные данные (здесь приведены - в качестве примера)
A33: =A32+1 -> 28 | B33: цена за ед. | Y33: Указать нужные данные (здесь приведены - в качестве примера)
A34: =A33+1 -> 29 | B34: защита ковша и т.д. | Y34: Указать нужные данные (здесь приведены - в качестве примера)
A35: =A34+1 -> 30 | B35: удельный расход | Y35: Указать нужные данные (здесь приведены - в качестве примера)
A36: =A35+1 -> 31 | B36: цена за ед. | Y36: Указать нужные данные (здесь приведены - в качестве примера)
A37: =A36+1 -> 32 | B37: Электроэнергия / дизтопливо
A38: =A37+1 -> 33 | B38: удельный расход | C38: л/ч | D38: 105 | Y38: Указать удельный расход и единицы измерения
A39: =A38+1 -> 34 | B39: Сроки поставки | C39: мес | D39: 10

Sheet PC2000-11R ИСТК_ТО
B2: ячейки к заполнению поставщиком
B3: Расчетный КТГ | G3: ='PC2000-11R ИСТК'!E9 -> 0.94292237 | H3: ='PC2000-11R ИСТК'!F9 -> 0.93515348 | I3: ='PC2000-11R ИСТК'!G9 -> 0.91284564 | J3: ='PC2000-11R ИСТК'!H9 -> 0.88554351 | K3: ='PC2000-11R ИСТК'!I9 -> 0.938483 | L3: ='PC2000-11R ИСТК'!J9 -> 0.90507674 | M3: ='PC2000-11R ИСТК'!K9 -> 0.93515348 | N3: ='PC2000-11R ИСТК'!L9 -> 0.8933124 | ... Z3: ='PC2000-11R ИСТК'!X9 -> 0.91684107
B4: Год службы (год) | C4: Ед. изм. | G4: =E4+1 -> 1 | H4: =G4+1 -> 2 | I4: =H4+1 -> 3 | J4: =I4+1 -> 4 | K4: =J4+1 -> 5 | L4: =K4+1 -> 6 | M4: =L4+1 -> 7 | N4: =M4+1 -> 8 | O4: =N4+1 -> 9 | ... Z4: =Y4+1 -> 20
B5: Наработка на начало года | C5: м/час | G5: 0 | H5: =G6+1 -> 7001 | I5: =H6+1 -> 14001 | J5: =I6+1 -> 21001 | K5: =J6+1 -> 28001 | L5: =K6+1 -> 35001 | M5: =L6+1 -> 42001 | N5: =M6+1 -> 49001 | O5: =N6+1 -> 56001 | ... Z5: =Y6+1 -> 133001
B6: Наработка на конец года | C6: м/час | F6: 7000 | G6: =F6 -> 7000 | H6: =G6+$F6 -> 14000 | I6: =H6+$F6 -> 21000 | J6: =I6+$F6 -> 28000 | K6: =J6+$F6 -> 35000 | L6: =K6+$F6 -> 42000 | M6: =L6+$F6 -> 49000 | N6: =M6+$F6 -> 56000 | O6: =N6+$F6 -> 63000 | ... Z6: =Y6+$F6 -> 140000
B7: длительность простоев на ТО | C7: часов | G7: =G13 -> 264 | H7: =H13 -> 264 | I7: =I13 -> 264 | J7: =J13 -> 264 | K7: =K13 -> 264 | L7: =L13 -> 264 | M7: =M13 -> 264 | N7: =N13 -> 264 | ... Z7: =Z13 -> 264
B8: Затраты на ТО | C8: долларов/год | G8: =SUM(G9:G10) -> 100666.05 | H8: =SUM(H9:H10) -> 100666.05 | I8: =SUM(I9:I10) -> 100666.05 | J8: =SUM(J9:J10) -> 100666.05 | K8: =SUM(K9:K10) -> 100666.05 | L8: =SUM(L9:L10) -> 100666.05 | M8: =SUM(M9:M10) -> 100666.05 | N8: =SUM(N9:N10) -> 100666.05 | ... Z8: =SUM(Z9:Z10) -> 100666.05
B9: ТО, включая масла и смазки | C9: долларов/год | G9: =G22 -> 74266.046 | H9: =H22 -> 74266.046 | I9: =I22 -> 74266.046 | J9: =J22 -> 74266.046 | K9: =K22 -> 74266.046 | L9: =L22 -> 74266.046 | M9: =M22 -> 74266.046 | N9: =N22 -> 74266.046 | ... Z9: =Z22 -> 74266.046
B10: сервис (трудозатраты) на ТО | C10: долларов/год | F10: 50 | G10: =SUMPRODUCT(G14:G19,$F$14:$F$19)*$F10 -> 26400 | H10: =SUMPRODUCT(H14:H19,$F$14:$F$19)*$F10 -> 26400 | I10: =SUMPRODUCT(I14:I19,$F$14:$F$19)*$F10 -> 26400 | J10: =SUMPRODUCT(J14:J19,$F$14:$F$19)*$F10 -> 26400 | K10: =SUMPRODUCT(K14:K19,$F$14:$F$19)*$F10 -> 26400 | L10: =SUMPRODUCT(L14:L19,$F$14:$F$19)*$F10 -> 26400 | M10: =SUMPRODUCT(M14:M19,$F$14:$F$19)*$F10 -> 26400 | N10: =SUMPRODUCT(N14:N19,$F$14:$F$19)*$F10 -> 26400 | ... Z10: =SUMPRODUCT(Z14:Z19,$F$14:$F$19)*$F10 -> 26400
B12: Простои оборудования на ТО | C12: Интервал ТО - от МС берем | D12: Длительность простоя на одном ТО, час | E12: Кол-во ТО в год | F12: Занято человек | G12: Простоев в год, час | H12: Простоев в год, час | I12: Простоев в год, час | J12: Простоев в год, час | K12: Простоев в год, час | L12: Простоев в год, час | M12: Простоев в год, час | N12: Простоев в год, час | O12: Простоев в год, час | P12: Простоев в год, час | Q12: Простоев в год, час | R12: Простоев в год, час | S12: Простоев в год, час | T12: Простоев в год, час | U12: Простоев в год, час | V12: Простоев в год, час | W12: Простоев в год, час | X12: Простоев в год, час | Y12: Простоев в год, час | Z12: Простоев в год, час
B13: всего простоев на ТО, часов | G13: =SUM(G14:G19) -> 264 | H13: =SUM(H14:H19) -> 264 | I13: =SUM(I14:I19) -> 264 | J13: =SUM(J14:J19) -> 264 | K13: =SUM(K14:K19) -> 264 | L13: =SUM(L14:L19) -> 264 | M13: =SUM(M14:M19) -> 264 | N13: =SUM(N14:N19) -> 264 | ... Z13: =SUM(Z14:Z19) -> 264
B14: ТО-1 | C14: 500 | D14: 11 | E14: 8 | F14: 2 | G14: =$E14*$D14 -> 88 | H14: =$E14*$D14 -> 88 | I14: =$E14*$D14 -> 88 | J14: =$E14*$D14 -> 88 | K14: =$E14*$D14 -> 88 | L14: =$E14*$D14 -> 88 | M14: =$E14*$D14 -> 88 | N14: =$E14*$D14 -> 88 | ... Z14: =$E14*$D14 -> 88 | AB14: формулы для примера, можно менять под необходимые параметры
B15: ТО-2 | C15: 1000 | D15: 23 | E15: 4 | F15: 2 | G15: =$E15*$D15 -> 92 | H15: =$E15*$D15 -> 92 | I15: =$E15*$D15 -> 92 | J15: =$E15*$D15 -> 92 | K15: =$E15*$D15 -> 92 | L15: =$E15*$D15 -> 92 | M15: =$E15*$D15 -> 92 | N15: =$E15*$D15 -> 92 | ... Z15: =$E15*$D15 -> 92 | AB15: формулы для примера, можно менять под необходимые параметры
B16: ТО-3 | C16: 2000 | D16: 27 | E16: 2 | F16: 2 | G16: =$E16*$D16 -> 54 | H16: =$E16*$D16 -> 54 | I16: =$E16*$D16 -> 54 | J16: =$E16*$D16 -> 54 | K16: =$E16*$D16 -> 54 | L16: =$E16*$D16 -> 54 | M16: =$E16*$D16 -> 54 | N16: =$E16*$D16 -> 54 | ... Z16: =$E16*$D16 -> 54 | AB16: формулы для примера, можно менять под необходимые параметры
B17: ТО-4 | C17: 4000 | D17: 30 | E17: 1 | F17: 2 | G17: =$E17*$D17 -> 30 | H17: =$E17*$D17 -> 30 | I17: =$E17*$D17 -> 30 | J17: =$E17*$D17 -> 30 | K17: =$E17*$D17 -> 30 | L17: =$E17*$D17 -> 30 | M17: =$E17*$D17 -> 30 | N17: =$E17*$D17 -> 30 | ... Z17: =$E17*$D17 -> 30 | AB17: формулы для примера, можно менять под необходимые параметры
B18: ТО-5 | G18: =$E18*$D18 -> 0 | H18: =$E18*$D18 -> 0 | I18: =$E18*$D18 -> 0 | J18: =$E18*$D18 -> 0 | K18: =$E18*$D18 -> 0 | L18: =$E18*$D18 -> 0 | M18: =$E18*$D18 -> 0 | N18: =$E18*$D18 -> 0 | ... Z18: =$E18*$D18 -> 0 | AB18: формулы для примера, можно менять под необходимые параметры
B19: ТО-6 | H19: =$D19 -> 0 | J19: =$D19 -> 0 | L19: =$D19 -> 0 | M19: =$D19 -> 0 | O19: =$D19 -> 0 | Q19: =$D19 -> 0 | R19: =$D19 -> 0 | T19: =$D19 -> 0 | V19: =$D19 -> 0 | X19: =$D19 -> 0 | Z19: =$D19 -> 0 | AB19: формулы для примера, можно менять под необходимые параметры
B21: Затраты на ТО | C21: Каталожный номер | D21: стоимость за ед., $ | E21: Кол-во | F21: Кол-во ТО в год | G21: $ | H21: $ | I21: $ | J21: $ | K21: $ | L21: $ | M21: $ | N21: $ | O21: $ | P21: $ | Q21: $ | R21: $ | S21: $ | T21: $ | U21: $ | V21: $ | W21: $ | X21: $ | Y21: $ | Z21: $
B22: ТО | G22: =SUM(G23:G101) -> 74266.046 | H22: =SUM(H23:H101) -> 74266.046 | I22: =SUM(I23:I101) -> 74266.046 | J22: =SUM(J23:J101) -> 74266.046 | K22: =SUM(K23:K101) -> 74266.046 | L22: =SUM(L23:L101) -> 74266.046 | M22: =SUM(M23:M101) -> 74266.046 | N22: =SUM(N23:N101) -> 74266.046 | ... Z22: =SUM(Z23:Z101) -> 74266.046
B23: ТО-1 | E23: =VLOOKUP($B23,$B$14:$C$19,2,FALSE) -> 500 | F23: =VLOOKUP($B23,$B$14:$E$19,4,FALSE) -> 8
B24: фильтр | C24: 600-211-1341 (MP) Фильтр масляный | D24: 35.942623 | E24: 4 | G24: =IF(G$14=0,0,G$14/$D$14*$E24*$D24) -> 1150.1639 | H24: =IF(H$14=0,0,H$14/$D$14*$E24*$D24) -> 1150.1639 | I24: =IF(I$14=0,0,I$14/$D$14*$E24*$D24) -> 1150.1639 | J24: =IF(J$14=0,0,J$14/$D$14*$E24*$D24) -> 1150.1639 | K24: =IF(K$14=0,0,K$14/$D$14*$E24*$D24) -> 1150.1639 | L24: =IF(L$14=0,0,L$14/$D$14*$E24*$D24) -> 1150.1639 | M24: =IF(M$14=0,0,M$14/$D$14*$E24*$D24) -> 1150.1639 | N24: =IF(N$14=0,0,N$14/$D$14*$E24*$D24) -> 1150.1639 | ... Z24: =IF(Z$14=0,0,Z$14/$D$14*$E24*$D24) -> 1150.1639
B25: фильтр | C25: 600-319-5410 (MP) Фильтр топливный | D25: 78.877049 | E25: 2 | G25: =IF(G$14=0,0,G$14/$D$14*$E25*$D25) -> 1262.0328 | H25: =IF(H$14=0,0,H$14/$D$14*$E25*$D25) -> 1262.0328 | I25: =IF(I$14=0,0,I$14/$D$14*$E25*$D25) -> 1262.0328 | J25: =IF(J$14=0,0,J$14/$D$14*$E25*$D25) -> 1262.0328 | K25: =IF(K$14=0,0,K$14/$D$14*$E25*$D25) -> 1262.0328 | L25: =IF(L$14=0,0,L$14/$D$14*$E25*$D25) -> 1262.0328 | M25: =IF(M$14=0,0,M$14/$D$14*$E25*$D25) -> 1262.0328 | N25: =IF(N$14=0,0,N$14/$D$14*$E25*$D25) -> 1262.0328 | ... Z25: =IF(Z$14=0,0,Z$14/$D$14*$E25*$D25) -> 1262.0328
B26: фильтр | C26: 21T-60-31410 (MP) Фильтр гидравлический | D26: 117.84426 | E26: 1 | G26: =IF(G$14=0,0,G$14/$D$14*$E26*$D26) -> 942.7541 | H26: =IF(H$14=0,0,H$14/$D$14*$E26*$D26) -> 942.7541 | I26: =IF(I$14=0,0,I$14/$D$14*$E26*$D26) -> 942.7541 | J26: =IF(J$14=0,0,J$14/$D$14*$E26*$D26) -> 942.7541 | K26: =IF(K$14=0,0,K$14/$D$14*$E26*$D26) -> 942.7541 | L26: =IF(L$14=0,0,L$14/$D$14*$E26*$D26) -> 942.7541 | M26: =IF(M$14=0,0,M$14/$D$14*$E26*$D26) -> 942.7541 | N26: =IF(N$14=0,0,N$14/$D$14*$E26*$D26) -> 942.7541 | ... Z26: =IF(Z$14=0,0,Z$14/$D$14*$E26*$D26) -> 942.7541
B27: фильтр | C27: 113-60-23160 (MP) Фильтр гидравлический | D27: 25.344262 | E27: 2 | G27: =IF(G$14=0,0,G$14/$D$14*$E27*$D27) -> 405.5082 | H27: =IF(H$14=0,0,H$14/$D$14*$E27*$D27) -> 405.5082 | I27: =IF(I$14=0,0,I$14/$D$14*$E27*$D27) -> 405.5082 | J27: =IF(J$14=0,0,J$14/$D$14*$E27*$D27) -> 405.5082 | K27: =IF(K$14=0,0,K$14/$D$14*$E27*$D27) -> 405.5082 | L27: =IF(L$14=0,0,L$14/$D$14*$E27*$D27) -> 405.5082 | M27: =IF(M$14=0,0,M$14/$D$14*$E27*$D27) -> 405.5082 | N27: =IF(N$14=0,0,N$14/$D$14*$E27*$D27) -> 405.5082 | ... Z27: =IF(Z$14=0,0,Z$14/$D$14*$E27*$D27) -> 405.5082
B28: фильтр | C28: 21T-60-31450 (MP) Фильтр гидравлический | D28: 69.040984 | E28: 3 | G28: =IF(G$14=0,0,G$14/$D$14*$E28*$D28) -> 1656.9836 | H28: =IF(H$14=0,0,H$14/$D$14*$E28*$D28) -> 1656.9836 | I28: =IF(I$14=0,0,I$14/$D$14*$E28*$D28) -> 1656.9836 | J28: =IF(J$14=0,0,J$14/$D$14*$E28*$D28) -> 1656.9836 | K28: =IF(K$14=0,0,K$14/$D$14*$E28*$D28) -> 1656.9836 | L28: =IF(L$14=0,0,L$14/$D$14*$E28*$D28) -> 1656.9836 | M28: =IF(M$14=0,0,M$14/$D$14*$E28*$D28) -> 1656.9836 | N28: =IF(N$14=0,0,N$14/$D$14*$E28*$D28) -> 1656.9836 | ... Z28: =IF(Z$14=0,0,Z$14/$D$14*$E28*$D28) -> 1656.9836
B29: масло | C29: Гейзер XLT 32 | D29: 7.3032787 | E29: 0 | G29: =IF(G$14=0,0,G$14/$D$14*$E29*$D29) -> 0 | H29: =IF(H$14=0,0,H$14/$D$14*$E29*$D29) -> 0 | I29: =IF(I$14=0,0,I$14/$D$14*$E29*$D29) -> 0 | J29: =IF(J$14=0,0,J$14/$D$14*$E29*$D29) -> 0 | K29: =IF(K$14=0,0,K$14/$D$14*$E29*$D29) -> 0 | L29: =IF(L$14=0,0,L$14/$D$14*$E29*$D29) -> 0 | M29: =IF(M$14=0,0,M$14/$D$14*$E29*$D29) -> 0 | N29: =IF(N$14=0,0,N$14/$D$14*$E29*$D29) -> 0 | ... Z29: =IF(Z$14=0,0,Z$14/$D$14*$E29*$D29) -> 0
B30: масло | C30: Гейзер ММ Synth 5W-30 | D30: 5.3606557 | E30: 0 | G30: =IF(G$14=0,0,G$14/$D$14*$E30*$D30) -> 0 | H30: =IF(H$14=0,0,H$14/$D$14*$E30*$D30) -> 0 | I30: =IF(I$14=0,0,I$14/$D$14*$E30*$D30) -> 0 | J30: =IF(J$14=0,0,J$14/$D$14*$E30*$D30) -> 0 | K30: =IF(K$14=0,0,K$14/$D$14*$E30*$D30) -> 0 | L30: =IF(L$14=0,0,L$14/$D$14*$E30*$D30) -> 0 | M30: =IF(M$14=0,0,M$14/$D$14*$E30*$D30) -> 0 | N30: =IF(N$14=0,0,N$14/$D$14*$E30*$D30) -> 0 | ... Z30: =IF(Z$14=0,0,Z$14/$D$14*$E30*$D30) -> 0
B31: смазка | C31: СИНТОФЛЕКС 2-100 (17кг) | D31: 29.795082 | E31: 80 | G31: =IF(G$14=0,0,G$14/$D$14*$E31*$D31) -> 19068.852 | H31: =IF(H$14=0,0,H$14/$D$14*$E31*$D31) -> 19068.852 | I31: =IF(I$14=0,0,I$14/$D$14*$E31*$D31) -> 19068.852 | J31: =IF(J$14=0,0,J$14/$D$14*$E31*$D31) -> 19068.852 | K31: =IF(K$14=0,0,K$14/$D$14*$E31*$D31) -> 19068.852 | L31: =IF(L$14=0,0,L$14/$D$14*$E31*$D31) -> 19068.852 | M31: =IF(M$14=0,0,M$14/$D$14*$E31*$D31) -> 19068.852 | N31: =IF(N$14=0,0,N$14/$D$14*$E31*$D31) -> 19068.852 | ... Z31: =IF(Z$14=0,0,Z$14/$D$14*$E31*$D31) -> 19068.852
B32: масло | C32: АВАНГАРД ПРОФЕССИОНАЛ М5 5W-30 (170кг/200л) | D32: 3.4262295 | E32: 130 | G32: =IF(G$14=0,0,G$14/$D$14*$E32*$D32) -> 3563.2787 | H32: =IF(H$14=0,0,H$14/$D$14*$E32*$D32) -> 3563.2787 | I32: =IF(I$14=0,0,I$14/$D$14*$E32*$D32) -> 3563.2787 | J32: =IF(J$14=0,0,J$14/$D$14*$E32*$D32) -> 3563.2787 | K32: =IF(K$14=0,0,K$14/$D$14*$E32*$D32) -> 3563.2787 | L32: =IF(L$14=0,0,L$14/$D$14*$E32*$D32) -> 3563.2787 | M32: =IF(M$14=0,0,M$14/$D$14*$E32*$D32) -> 3563.2787 | N32: =IF(N$14=0,0,N$14/$D$14*$E32*$D32) -> 3563.2787 | ... Z32: =IF(Z$14=0,0,Z$14/$D$14*$E32*$D32) -> 3563.2787
B33: масло | C33: COOL FLUID PREMIUM 60/40 (220 кг) | D33: 3.2 | E33: 0 | G33: =IF(G$14=0,0,G$14/$D$14*$E33*$D33) -> 0 | H33: =IF(H$14=0,0,H$14/$D$14*$E33*$D33) -> 0 | I33: =IF(I$14=0,0,I$14/$D$14*$E33*$D33) -> 0 | J33: =IF(J$14=0,0,J$14/$D$14*$E33*$D33) -> 0 | K33: =IF(K$14=0,0,K$14/$D$14*$E33*$D33) -> 0 | L33: =IF(L$14=0,0,L$14/$D$14*$E33*$D33) -> 0 | M33: =IF(M$14=0,0,M$14/$D$14*$E33*$D33) -> 0 | N33: =IF(N$14=0,0,N$14/$D$14*$E33*$D33) -> 0 | ... Z33: =IF(Z$14=0,0,Z$14/$D$14*$E33*$D33) -> 0
B34: ТО-2 | E34: =VLOOKUP($B34,$B$14:$C$19,2,FALSE) -> 1000 | F34: =VLOOKUP($B34,$B$14:$E$19,4,FALSE) -> 4
B35: фильтр | C35: 600-211-1341 (MP) Фильтр масляный | D35: 35.942623 | E35: 4 | G35: =IF(G$15=0,0,G$15/$D$15*$E35*$D35) -> 575.08197 | H35: =IF(H$15=0,0,H$15/$D$15*$E35*$D35) -> 575.08197 | I35: =IF(I$15=0,0,I$15/$D$15*$E35*$D35) -> 575.08197 | J35: =IF(J$15=0,0,J$15/$D$15*$E35*$D35) -> 575.08197 | K35: =IF(K$15=0,0,K$15/$D$15*$E35*$D35) -> 575.08197 | L35: =IF(L$15=0,0,L$15/$D$15*$E35*$D35) -> 575.08197 | M35: =IF(M$15=0,0,M$15/$D$15*$E35*$D35) -> 575.08197 | N35: =IF(N$15=0,0,N$15/$D$15*$E35*$D35) -> 575.08197 | ... Z35: =IF(Z$15=0,0,Z$15/$D$15*$E35*$D35) -> 575.08197
B36: фильтр | C36: 600-319-5410 (MP) Фильтр топливный | D36: 78.877049 | E36: 2 | G36: =IF(G$15=0,0,G$15/$D$15*$E36*$D36) -> 631.01639 | H36: =IF(H$15=0,0,H$15/$D$15*$E36*$D36) -> 631.01639 | I36: =IF(I$15=0,0,I$15/$D$15*$E36*$D36) -> 631.01639 | J36: =IF(J$15=0,0,J$15/$D$15*$E36*$D36) -> 631.01639 | K36: =IF(K$15=0,0,K$15/$D$15*$E36*$D36) -> 631.01639 | L36: =IF(L$15=0,0,L$15/$D$15*$E36*$D36) -> 631.01639 | M36: =IF(M$15=0,0,M$15/$D$15*$E36*$D36) -> 631.01639 | N36: =IF(N$15=0,0,N$15/$D$15*$E36*$D36) -> 631.01639 | ... Z36: =IF(Z$15=0,0,Z$15/$D$15*$E36*$D36) -> 631.01639
B37: фильтр | C37: 21T-60-31410 (MP) Фильтр гидравлический | D37: 117.84426 | E37: 1 | G37: =IF(G$15=0,0,G$15/$D$15*$E37*$D37) -> 471.37705 | H37: =IF(H$15=0,0,H$15/$D$15*$E37*$D37) -> 471.37705 | I37: =IF(I$15=0,0,I$15/$D$15*$E37*$D37) -> 471.37705 | J37: =IF(J$15=0,0,J$15/$D$15*$E37*$D37) -> 471.37705 | K37: =IF(K$15=0,0,K$15/$D$15*$E37*$D37) -> 471.37705 | L37: =IF(L$15=0,0,L$15/$D$15*$E37*$D37) -> 471.37705 | M37: =IF(M$15=0,0,M$15/$D$15*$E37*$D37) -> 471.37705 | N37: =IF(N$15=0,0,N$15/$D$15*$E37*$D37) -> 471.37705 | ... Z37: =IF(Z$15=0,0,Z$15/$D$15*$E37*$D37) -> 471.37705
B38: фильтр | C38: 113-60-23160 (MP) Фильтр гидравлический | D38: 25.344262 | E38: 2 | G38: =IF(G$15=0,0,G$15/$D$15*$E38*$D38) -> 202.7541 | H38: =IF(H$15=0,0,H$15/$D$15*$E38*$D38) -> 202.7541 | I38: =IF(I$15=0,0,I$15/$D$15*$E38*$D38) -> 202.7541 | J38: =IF(J$15=0,0,J$15/$D$15*$E38*$D38) -> 202.7541 | K38: =IF(K$15=0,0,K$15/$D$15*$E38*$D38) -> 202.7541 | L38: =IF(L$15=0,0,L$15/$D$15*$E38*$D38) -> 202.7541 | M38: =IF(M$15=0,0,M$15/$D$15*$E38*$D38) -> 202.7541 | N38: =IF(N$15=0,0,N$15/$D$15*$E38*$D38) -> 202.7541 | ... Z38: =IF(Z$15=0,0,Z$15/$D$15*$E38*$D38) -> 202.7541
B39: фильтр | C39: 21T-60-31450 (MP) Фильтр гидравлический | D39: 69.040984 | E39: 3 | G39: =IF(G$15=0,0,G$15/$D$15*$E39*$D39) -> 828.4918 | H39: =IF(H$15=0,0,H$15/$D$15*$E39*$D39) -> 828.4918 | I39: =IF(I$15=0,0,I$15/$D$15*$E39*$D39) -> 828.4918 | J39: =IF(J$15=0,0,J$15/$D$15*$E39*$D39) -> 828.4918 | K39: =IF(K$15=0,0,K$15/$D$15*$E39*$D39) -> 828.4918 | L39: =IF(L$15=0,0,L$15/$D$15*$E39*$D39) -> 828.4918 | M39: =IF(M$15=0,0,M$15/$D$15*$E39*$D39) -> 828.4918 | N39: =IF(N$15=0,0,N$15/$D$15*$E39*$D39) -> 828.4918 | ... Z39: =IF(Z$15=0,0,Z$15/$D$15*$E39*$D39) -> 828.4918
B40: фильтр | C40: 600-319-3841 (MP) Фильтр топливный | D40: 47.47541 | E40: 2 | G40: =IF(G$15=0,0,G$15/$D$15*$E40*$D40) -> 379.80328 | H40: =IF(H$15=0,0,H$15/$D$15*$E40*$D40) -> 379.80328 | I40: =IF(I$15=0,0,I$15/$D$15*$E40*$D40) -> 379.80328 | J40: =IF(J$15=0,0,J$15/$D$15*$E40*$D40) -> 379.80328 | K40: =IF(K$15=0,0,K$15/$D$15*$E40*$D40) -> 379.80328 | L40: =IF(L$15=0,0,L$15/$D$15*$E40*$D40) -> 379.80328 | M40: =IF(M$15=0,0,M$15/$D$15*$E40*$D40) -> 379.80328 | N40: =IF(N$15=0,0,N$15/$D$15*$E40*$D40) -> 379.80328 | ... Z40: =IF(Z$15=0,0,Z$15/$D$15*$E40*$D40) -> 379.80328
B41: фильтр | C41: 421-60-35170 (MP) Фильтр сапуна гидробака | D41: 10.778689 | E41: 3 | G41: =IF(G$15=0,0,G$15/$D$15*$E41*$D41) -> 129.34426 | H41: =IF(H$15=0,0,H$15/$D$15*$E41*$D41) -> 129.34426 | I41: =IF(I$15=0,0,I$15/$D$15*$E41*$D41) -> 129.34426 | J41: =IF(J$15=0,0,J$15/$D$15*$E41*$D41) -> 129.34426 | K41: =IF(K$15=0,0,K$15/$D$15*$E41*$D41) -> 129.34426 | L41: =IF(L$15=0,0,L$15/$D$15*$E41*$D41) -> 129.34426 | M41: =IF(M$15=0,0,M$15/$D$15*$E41*$D41) -> 129.34426 | N41: =IF(N$15=0,0,N$15/$D$15*$E41*$D41) -> 129.34426 | ... Z41: =IF(Z$15=0,0,Z$15/$D$15*$E41*$D41) -> 129.34426
B42: фильтр | C42: 21M-60-51250 (MP) Фильтр гидравлический | D42: 64.163934 | E42: 3 | G42: =IF(G$15=0,0,G$15/$D$15*$E42*$D42) -> 769.96721 | H42: =IF(H$15=0,0,H$15/$D$15*$E42*$D42) -> 769.96721 | I42: =IF(I$15=0,0,I$15/$D$15*$E42*$D42) -> 769.96721 | J42: =IF(J$15=0,0,J$15/$D$15*$E42*$D42) -> 769.96721 | K42: =IF(K$15=0,0,K$15/$D$15*$E42*$D42) -> 769.96721 | L42: =IF(L$15=0,0,L$15/$D$15*$E42*$D42) -> 769.96721 | M42: =IF(M$15=0,0,M$15/$D$15*$E42*$D42) -> 769.96721 | N42: =IF(N$15=0,0,N$15/$D$15*$E42*$D42) -> 769.96721 | ... Z42: =IF(Z$15=0,0,Z$15/$D$15*$E42*$D42) -> 769.96721
B43: фильтр | C43: 07000-B5180Z УПЛОТНИТЕЛЬНОЕ КОЛЬЦО | D43: 28.819672 | E43: 3 | G43: =IF(G$15=0,0,G$15/$D$15*$E43*$D43) -> 345.83607 | H43: =IF(H$15=0,0,H$15/$D$15*$E43*$D43) -> 345.83607 | I43: =IF(I$15=0,0,I$15/$D$15*$E43*$D43) -> 345.83607 | J43: =IF(J$15=0,0,J$15/$D$15*$E43*$D43) -> 345.83607 | K43: =IF(K$15=0,0,K$15/$D$15*$E43*$D43) -> 345.83607 | L43: =IF(L$15=0,0,L$15/$D$15*$E43*$D43) -> 345.83607 | M43: =IF(M$15=0,0,M$15/$D$15*$E43*$D43) -> 345.83607 | N43: =IF(N$15=0,0,N$15/$D$15*$E43*$D43) -> 345.83607 | ... Z43: =IF(Z$15=0,0,Z$15/$D$15*$E43*$D43) -> 345.83607
B44: фильтр | C44: 07030-00252 (MP) Фильтр сапун | D44: 21.081967 | E44: 2 | G44: =IF(G$15=0,0,G$15/$D$15*$E44*$D44) -> 168.65574 | H44: =IF(H$15=0,0,H$15/$D$15*$E44*$D44) -> 168.65574 | I44: =IF(I$15=0,0,I$15/$D$15*$E44*$D44) -> 168.65574 | J44: =IF(J$15=0,0,J$15/$D$15*$E44*$D44) -> 168.65574 | K44: =IF(K$15=0,0,K$15/$D$15*$E44*$D44) -> 168.65574 | L44: =IF(L$15=0,0,L$15/$D$15*$E44*$D44) -> 168.65574 | M44: =IF(M$15=0,0,M$15/$D$15*$E44*$D44) -> 168.65574 | N44: =IF(N$15=0,0,N$15/$D$15*$E44*$D44) -> 168.65574 | ... Z44: =IF(Z$15=0,0,Z$15/$D$15*$E44*$D44) -> 168.65574
B45: фильтр | C45: 21T-64-34590 (MP) Фильтр гидравлический | D45: 11.836066 | E45: 2 | G45: =IF(G$15=0,0,G$15/$D$15*$E45*$D45) -> 94.688525 | H45: =IF(H$15=0,0,H$15/$D$15*$E45*$D45) -> 94.688525 | I45: =IF(I$15=0,0,I$15/$D$15*$E45*$D45) -> 94.688525 | J45: =IF(J$15=0,0,J$15/$D$15*$E45*$D45) -> 94.688525 | K45: =IF(K$15=0,0,K$15/$D$15*$E45*$D45) -> 94.688525 | L45: =IF(L$15=0,0,L$15/$D$15*$E45*$D45) -> 94.688525 | M45: =IF(M$15=0,0,M$15/$D$15*$E45*$D45) -> 94.688525 | N45: =IF(N$15=0,0,N$15/$D$15*$E45*$D45) -> 94.688525 | ... Z45: =IF(Z$15=0,0,Z$15/$D$15*$E45*$D45) -> 94.688525
B46: фильтр | C46: 706-76-71390 (MP) Уплотнительное кольцо | D46: 1.8770492 | E46: 2 | G46: =IF(G$15=0,0,G$15/$D$15*$E46*$D46) -> 15.016393 | H46: =IF(H$15=0,0,H$15/$D$15*$E46*$D46) -> 15.016393 | I46: =IF(I$15=0,0,I$15/$D$15*$E46*$D46) -> 15.016393 | J46: =IF(J$15=0,0,J$15/$D$15*$E46*$D46) -> 15.016393 | K46: =IF(K$15=0,0,K$15/$D$15*$E46*$D46) -> 15.016393 | L46: =IF(L$15=0,0,L$15/$D$15*$E46*$D46) -> 15.016393 | M46: =IF(M$15=0,0,M$15/$D$15*$E46*$D46) -> 15.016393 | N46: =IF(N$15=0,0,N$15/$D$15*$E46*$D46) -> 15.016393 | ... Z46: =IF(Z$15=0,0,Z$15/$D$15*$E46*$D46) -> 15.016393
... B51: масло | C51: COOL FLUID PREMIUM 60/40 (220 кг) | D51: 3.2 | E51: 0 | G51: =IF(G$15=0,0,G$15/$D$15*$E51*$D51) -> 0 | H51: =IF(H$15=0,0,H$15/$D$15*$E51*$D51) -> 0 | I51: =IF(I$15=0,0,I$15/$D$15*$E51*$D51) -> 0 | J51: =IF(J$15=0,0,J$15/$D$15*$E51*$D51) -> 0 | K51: =IF(K$15=0,0,K$15/$D$15*$E51*$D51) -> 0 | L51: =IF(L$15=0,0,L$15/$D$15*$E51*$D51) -> 0 | M51: =IF(M$15=0,0,M$15/$D$15*$E51*$D51) -> 0 | N51: =IF(N$15=0,0,N$15/$D$15*$E51*$D51) -> 0 | ... Z51: =IF(Z$15=0,0,Z$15/$D$15*$E51*$D51) -> 0
B52: ТО-3 | E52: =VLOOKUP($B52,$B$14:$C$19,2,FALSE) -> 2000 | F52: =VLOOKUP($B52,$B$14:$E$19,4,FALSE) -> 2
B53: фильтр | C53: 600-211-1341 (MP) Фильтр масляный | D53: 35.942623 | E53: 4 | G53: =IF(G$16=0,0,G$16/$D$16*$E53*$D53) -> 287.54098 | H53: =IF(H$16=0,0,H$16/$D$16*$E53*$D53) -> 287.54098 | I53: =IF(I$16=0,0,I$16/$D$16*$E53*$D53) -> 287.54098 | J53: =IF(J$16=0,0,J$16/$D$16*$E53*$D53) -> 287.54098 | K53: =IF(K$16=0,0,K$16/$D$16*$E53*$D53) -> 287.54098 | L53: =IF(L$16=0,0,L$16/$D$16*$E53*$D53) -> 287.54098 | M53: =IF(M$16=0,0,M$16/$D$16*$E53*$D53) -> 287.54098 | N53: =IF(N$16=0,0,N$16/$D$16*$E53*$D53) -> 287.54098 | ... Z53: =IF(Z$16=0,0,Z$16/$D$16*$E53*$D53) -> 287.54098
B54: фильтр | C54: 600-319-5410 (MP) Фильтр топливный | D54: 78.877049 | E54: 2 | G54: =IF(G$16=0,0,G$16/$D$16*$E54*$D54) -> 315.5082 | H54: =IF(H$16=0,0,H$16/$D$16*$E54*$D54) -> 315.5082 | I54: =IF(I$16=0,0,I$16/$D$16*$E54*$D54) -> 315.5082 | J54: =IF(J$16=0,0,J$16/$D$16*$E54*$D54) -> 315.5082 | K54: =IF(K$16=0,0,K$16/$D$16*$E54*$D54) -> 315.5082 | L54: =IF(L$16=0,0,L$16/$D$16*$E54*$D54) -> 315.5082 | M54: =IF(M$16=0,0,M$16/$D$16*$E54*$D54) -> 315.5082 | N54: =IF(N$16=0,0,N$16/$D$16*$E54*$D54) -> 315.5082 | ... Z54: =IF(Z$16=0,0,Z$16/$D$16*$E54*$D54) -> 315.5082
B55: фильтр | C55: 21T-60-31410 (MP) Фильтр гидравлический | D55: 117.84426 | E55: 1 | G55: =IF(G$16=0,0,G$16/$D$16*$E55*$D55) -> 235.68852 | H55: =IF(H$16=0,0,H$16/$D$16*$E55*$D55) -> 235.68852 | I55: =IF(I$16=0,0,I$16/$D$16*$E55*$D55) -> 235.68852 | J55: =IF(J$16=0,0,J$16/$D$16*$E55*$D55) -> 235.68852 | K55: =IF(K$16=0,0,K$16/$D$16*$E55*$D55) -> 235.68852 | L55: =IF(L$16=0,0,L$16/$D$16*$E55*$D55) -> 235.68852 | M55: =IF(M$16=0,0,M$16/$D$16*$E55*$D55) -> 235.68852 | N55: =IF(N$16=0,0,N$16/$D$16*$E55*$D55) -> 235.68852 | ... Z55: =IF(Z$16=0,0,Z$16/$D$16*$E55*$D55) -> 235.68852
B56: фильтр | C56: 113-60-23160 (MP) Фильтр гидравлический | D56: 25.344262 | E56: 2 | G56: =IF(G$16=0,0,G$16/$D$16*$E56*$D56) -> 101.37705 | H56: =IF(H$16=0,0,H$16/$D$16*$E56*$D56) -> 101.37705 | I56: =IF(I$16=0,0,I$16/$D$16*$E56*$D56) -> 101.37705 | J56: =IF(J$16=0,0,J$16/$D$16*$E56*$D56) -> 101.37705 | K56: =IF(K$16=0,0,K$16/$D$16*$E56*$D56) -> 101.37705 | L56: =IF(L$16=0,0,L$16/$D$16*$E56*$D56) -> 101.37705 | M56: =IF(M$16=0,0,M$16/$D$16*$E56*$D56) -> 101.37705 | N56: =IF(N$16=0,0,N$16/$D$16*$E56*$D56) -> 101.37705 | ... Z56: =IF(Z$16=0,0,Z$16/$D$16*$E56*$D56) -> 101.37705
B57: фильтр | C57: 21T-60-31450 (MP) Фильтр гидравлический | D57: 69.040984 | E57: 3 | G57: =IF(G$16=0,0,G$16/$D$16*$E57*$D57) -> 414.2459 | H57: =IF(H$16=0,0,H$16/$D$16*$E57*$D57) -> 414.2459 | I57: =IF(I$16=0,0,I$16/$D$16*$E57*$D57) -> 414.2459 | J57: =IF(J$16=0,0,J$16/$D$16*$E57*$D57) -> 414.2459 | K57: =IF(K$16=0,0,K$16/$D$16*$E57*$D57) -> 414.2459 | L57: =IF(L$16=0,0,L$16/$D$16*$E57*$D57) -> 414.2459 | M57: =IF(M$16=0,0,M$16/$D$16*$E57*$D57) -> 414.2459 | N57: =IF(N$16=0,0,N$16/$D$16*$E57*$D57) -> 414.2459 | ... Z57: =IF(Z$16=0,0,Z$16/$D$16*$E57*$D57) -> 414.2459
B58: фильтр | C58: 600-319-3841 (MP) Фильтр топливный | D58: 47.47541 | E58: 2 | G58: =IF(G$16=0,0,G$16/$D$16*$E58*$D58) -> 189.90164 | H58: =IF(H$16=0,0,H$16/$D$16*$E58*$D58) -> 189.90164 | I58: =IF(I$16=0,0,I$16/$D$16*$E58*$D58) -> 189.90164 | J58: =IF(J$16=0,0,J$16/$D$16*$E58*$D58) -> 189.90164 | K58: =IF(K$16=0,0,K$16/$D$16*$E58*$D58) -> 189.90164 | L58: =IF(L$16=0,0,L$16/$D$16*$E58*$D58) -> 189.90164 | M58: =IF(M$16=0,0,M$16/$D$16*$E58*$D58) -> 189.90164 | N58: =IF(N$16=0,0,N$16/$D$16*$E58*$D58) -> 189.90164 | ... Z58: =IF(Z$16=0,0,Z$16/$D$16*$E58*$D58) -> 189.90164
B59: фильтр | C59: 421-60-35170 (MP) Фильтр сапуна гидробака | D59: 10.778689 | E59: 3 | G59: =IF(G$16=0,0,G$16/$D$16*$E59*$D59) -> 64.672131 | H59: =IF(H$16=0,0,H$16/$D$16*$E59*$D59) -> 64.672131 | I59: =IF(I$16=0,0,I$16/$D$16*$E59*$D59) -> 64.672131 | J59: =IF(J$16=0,0,J$16/$D$16*$E59*$D59) -> 64.672131 | K59: =IF(K$16=0,0,K$16/$D$16*$E59*$D59) -> 64.672131 | L59: =IF(L$16=0,0,L$16/$D$16*$E59*$D59) -> 64.672131 | M59: =IF(M$16=0,0,M$16/$D$16*$E59*$D59) -> 64.672131 | N59: =IF(N$16=0,0,N$16/$D$16*$E59*$D59) -> 64.672131 | ... Z59: =IF(Z$16=0,0,Z$16/$D$16*$E59*$D59) -> 64.672131
B60: фильтр | C60: 21M-60-51250 (MP) Фильтр гидравлический | D60: 64.163934 | E60: 3 | G60: =IF(G$16=0,0,G$16/$D$16*$E60*$D60) -> 384.98361 | H60: =IF(H$16=0,0,H$16/$D$16*$E60*$D60) -> 384.98361 | I60: =IF(I$16=0,0,I$16/$D$16*$E60*$D60) -> 384.98361 | J60: =IF(J$16=0,0,J$16/$D$16*$E60*$D60) -> 384.98361 | K60: =IF(K$16=0,0,K$16/$D$16*$E60*$D60) -> 384.98361 | L60: =IF(L$16=0,0,L$16/$D$16*$E60*$D60) -> 384.98361 | M60: =IF(M$16=0,0,M$16/$D$16*$E60*$D60) -> 384.98361 | N60: =IF(N$16=0,0,N$16/$D$16*$E60*$D60) -> 384.98361 | ... Z60: =IF(Z$16=0,0,Z$16/$D$16*$E60*$D60) -> 384.98361
B61: фильтр | C61: 07000-B5180Z УПЛОТНИТЕЛЬНОЕ КОЛЬЦО | D61: 28.819672 | E61: 3 | G61: =IF(G$16=0,0,G$16/$D$16*$E61*$D61) -> 172.91803 | H61: =IF(H$16=0,0,H$16/$D$16*$E61*$D61) -> 172.91803 | I61: =IF(I$16=0,0,I$16/$D$16*$E61*$D61) -> 172.91803 | J61: =IF(J$16=0,0,J$16/$D$16*$E61*$D61) -> 172.91803 | K61: =IF(K$16=0,0,K$16/$D$16*$E61*$D61) -> 172.91803 | L61: =IF(L$16=0,0,L$16/$D$16*$E61*$D61) -> 172.91803 | M61: =IF(M$16=0,0,M$16/$D$16*$E61*$D61) -> 172.91803 | N61: =IF(N$16=0,0,N$16/$D$16*$E61*$D61) -> 172.91803 | ... Z61: =IF(Z$16=0,0,Z$16/$D$16*$E61*$D61) -> 172.91803
B62: фильтр | C62: 07030-00252 (MP) Фильтр сапун | D62: 21.081967 | E62: 2 | G62: =IF(G$16=0,0,G$16/$D$16*$E62*$D62) -> 84.327869 | H62: =IF(H$16=0,0,H$16/$D$16*$E62*$D62) -> 84.327869 | I62: =IF(I$16=0,0,I$16/$D$16*$E62*$D62) -> 84.327869 | J62: =IF(J$16=0,0,J$16/$D$16*$E62*$D62) -> 84.327869 | K62: =IF(K$16=0,0,K$16/$D$16*$E62*$D62) -> 84.327869 | L62: =IF(L$16=0,0,L$16/$D$16*$E62*$D62) -> 84.327869 | M62: =IF(M$16=0,0,M$16/$D$16*$E62*$D62) -> 84.327869 | N62: =IF(N$16=0,0,N$16/$D$16*$E62*$D62) -> 84.327869 | ... Z62: =IF(Z$16=0,0,Z$16/$D$16*$E62*$D62) -> 84.327869
B63: фильтр | C63: 21T-64-34590 (MP) Фильтр гидравлический | D63: 11.836066 | E63: 2 | G63: =IF(G$16=0,0,G$16/$D$16*$E63*$D63) -> 47.344262 | H63: =IF(H$16=0,0,H$16/$D$16*$E63*$D63) -> 47.344262 | I63: =IF(I$16=0,0,I$16/$D$16*$E63*$D63) -> 47.344262 | J63: =IF(J$16=0,0,J$16/$D$16*$E63*$D63) -> 47.344262 | K63: =IF(K$16=0,0,K$16/$D$16*$E63*$D63) -> 47.344262 | L63: =IF(L$16=0,0,L$16/$D$16*$E63*$D63) -> 47.344262 | M63: =IF(M$16=0,0,M$16/$D$16*$E63*$D63) -> 47.344262 | N63: =IF(N$16=0,0,N$16/$D$16*$E63*$D63) -> 47.344262 | ... Z63: =IF(Z$16=0,0,Z$16/$D$16*$E63*$D63) -> 47.344262
B64: фильтр | C64: 706-76-71390 (MP) Уплотнительное кольцо | D64: 1.8770492 | E64: 2 | G64: =IF(G$16=0,0,G$16/$D$16*$E64*$D64) -> 7.5081967 | H64: =IF(H$16=0,0,H$16/$D$16*$E64*$D64) -> 7.5081967 | I64: =IF(I$16=0,0,I$16/$D$16*$E64*$D64) -> 7.5081967 | J64: =IF(J$16=0,0,J$16/$D$16*$E64*$D64) -> 7.5081967 | K64: =IF(K$16=0,0,K$16/$D$16*$E64*$D64) -> 7.5081967 | L64: =IF(L$16=0,0,L$16/$D$16*$E64*$D64) -> 7.5081967 | M64: =IF(M$16=0,0,M$16/$D$16*$E64*$D64) -> 7.5081967 | N64: =IF(N$16=0,0,N$16/$D$16*$E64*$D64) -> 7.5081967 | ... Z64: =IF(Z$16=0,0,Z$16/$D$16*$E64*$D64) -> 7.5081967
... B72: масло | C72: COOL FLUID PREMIUM 60/40 (220 кг) | D72: 3.2 | E72: 50 | G72: =IF(G$16=0,0,G$16/$D$16*$E72*$D72) -> 320 | H72: =IF(H$16=0,0,H$16/$D$16*$E72*$D72) -> 320 | I72: =IF(I$16=0,0,I$16/$D$16*$E72*$D72) -> 320 | J72: =IF(J$16=0,0,J$16/$D$16*$E72*$D72) -> 320 | K72: =IF(K$16=0,0,K$16/$D$16*$E72*$D72) -> 320 | L72: =IF(L$16=0,0,L$16/$D$16*$E72*$D72) -> 320 | M72: =IF(M$16=0,0,M$16/$D$16*$E72*$D72) -> 320 | N72: =IF(N$16=0,0,N$16/$D$16*$E72*$D72) -> 320 | ... Z72: =IF(Z$16=0,0,Z$16/$D$16*$E72*$D72) -> 320
B73: ТО-4 | E73: =VLOOKUP($B73,$B$14:$C$19,2,FALSE) -> 4000 | F73: =VLOOKUP($B73,$B$14:$E$19,4,FALSE) -> 1
B74: фильтр | C74: 600-211-1341 (MP) Фильтр масляный | D74: 35.942623 | E74: 4 | G74: =IF(G$17=0,0,G$17/$D$17*$E74*$D74) -> 143.77049 | H74: =IF(H$17=0,0,H$17/$D$17*$E74*$D74) -> 143.77049 | I74: =IF(I$17=0,0,I$17/$D$17*$E74*$D74) -> 143.77049 | J74: =IF(J$17=0,0,J$17/$D$17*$E74*$D74) -> 143.77049 | K74: =IF(K$17=0,0,K$17/$D$17*$E74*$D74) -> 143.77049 | L74: =IF(L$17=0,0,L$17/$D$17*$E74*$D74) -> 143.77049 | M74: =IF(M$17=0,0,M$17/$D$17*$E74*$D74) -> 143.77049 | N74: =IF(N$17=0,0,N$17/$D$17*$E74*$D74) -> 143.77049 | ... Z74: =IF(Z$17=0,0,Z$17/$D$17*$E74*$D74) -> 143.77049
B75: фильтр | C75: 600-319-5410 (MP) Фильтр топливный | D75: 78.877049 | E75: 2 | G75: =IF(G$17=0,0,G$17/$D$17*$E75*$D75) -> 157.7541 | H75: =IF(H$17=0,0,H$17/$D$17*$E75*$D75) -> 157.7541 | I75: =IF(I$17=0,0,I$17/$D$17*$E75*$D75) -> 157.7541 | J75: =IF(J$17=0,0,J$17/$D$17*$E75*$D75) -> 157.7541 | K75: =IF(K$17=0,0,K$17/$D$17*$E75*$D75) -> 157.7541 | L75: =IF(L$17=0,0,L$17/$D$17*$E75*$D75) -> 157.7541 | M75: =IF(M$17=0,0,M$17/$D$17*$E75*$D75) -> 157.7541 | N75: =IF(N$17=0,0,N$17/$D$17*$E75*$D75) -> 157.7541 | ... Z75: =IF(Z$17=0,0,Z$17/$D$17*$E75*$D75) -> 157.7541
B76: фильтр | C76: 21T-60-31410 (MP) Фильтр гидравлический | D76: 117.84426 | E76: 1 | G76: =IF(G$17=0,0,G$17/$D$17*$E76*$D76) -> 117.84426 | H76: =IF(H$17=0,0,H$17/$D$17*$E76*$D76) -> 117.84426 | I76: =IF(I$17=0,0,I$17/$D$17*$E76*$D76) -> 117.84426 | J76: =IF(J$17=0,0,J$17/$D$17*$E76*$D76) -> 117.84426 | K76: =IF(K$17=0,0,K$17/$D$17*$E76*$D76) -> 117.84426 | L76: =IF(L$17=0,0,L$17/$D$17*$E76*$D76) -> 117.84426 | M76: =IF(M$17=0,0,M$17/$D$17*$E76*$D76) -> 117.84426 | N76: =IF(N$17=0,0,N$17/$D$17*$E76*$D76) -> 117.84426 | ... Z76: =IF(Z$17=0,0,Z$17/$D$17*$E76*$D76) -> 117.84426
B77: фильтр | C77: 113-60-23160 (MP) Фильтр гидравлический | D77: 25.344262 | E77: 2 | G77: =IF(G$17=0,0,G$17/$D$17*$E77*$D77) -> 50.688525 | H77: =IF(H$17=0,0,H$17/$D$17*$E77*$D77) -> 50.688525 | I77: =IF(I$17=0,0,I$17/$D$17*$E77*$D77) -> 50.688525 | J77: =IF(J$17=0,0,J$17/$D$17*$E77*$D77) -> 50.688525 | K77: =IF(K$17=0,0,K$17/$D$17*$E77*$D77) -> 50.688525 | L77: =IF(L$17=0,0,L$17/$D$17*$E77*$D77) -> 50.688525 | M77: =IF(M$17=0,0,M$17/$D$17*$E77*$D77) -> 50.688525 | N77: =IF(N$17=0,0,N$17/$D$17*$E77*$D77) -> 50.688525 | ... Z77: =IF(Z$17=0,0,Z$17/$D$17*$E77*$D77) -> 50.688525
B78: фильтр | C78: 21T-60-31450 (MP) Фильтр гидравлический | D78: 69.040984 | E78: 3 | G78: =IF(G$17=0,0,G$17/$D$17*$E78*$D78) -> 207.12295 | H78: =IF(H$17=0,0,H$17/$D$17*$E78*$D78) -> 207.12295 | I78: =IF(I$17=0,0,I$17/$D$17*$E78*$D78) -> 207.12295 | J78: =IF(J$17=0,0,J$17/$D$17*$E78*$D78) -> 207.12295 | K78: =IF(K$17=0,0,K$17/$D$17*$E78*$D78) -> 207.12295 | L78: =IF(L$17=0,0,L$17/$D$17*$E78*$D78) -> 207.12295 | M78: =IF(M$17=0,0,M$17/$D$17*$E78*$D78) -> 207.12295 | N78: =IF(N$17=0,0,N$17/$D$17*$E78*$D78) -> 207.12295 | ... Z78: =IF(Z$17=0,0,Z$17/$D$17*$E78*$D78) -> 207.12295
B79: фильтр | C79: 600-319-3841 (MP) Фильтр топливный | D79: 47.47541 | E79: 2 | G79: =IF(G$17=0,0,G$17/$D$17*$E79*$D79) -> 94.95082 | H79: =IF(H$17=0,0,H$17/$D$17*$E79*$D79) -> 94.95082 | I79: =IF(I$17=0,0,I$17/$D$17*$E79*$D79) -> 94.95082 | J79: =IF(J$17=0,0,J$17/$D$17*$E79*$D79) -> 94.95082 | K79: =IF(K$17=0,0,K$17/$D$17*$E79*$D79) -> 94.95082 | L79: =IF(L$17=0,0,L$17/$D$17*$E79*$D79) -> 94.95082 | M79: =IF(M$17=0,0,M$17/$D$17*$E79*$D79) -> 94.95082 | N79: =IF(N$17=0,0,N$17/$D$17*$E79*$D79) -> 94.95082 | ... Z79: =IF(Z$17=0,0,Z$17/$D$17*$E79*$D79) -> 94.95082
B80: фильтр | C80: 421-60-35170 (MP) Фильтр сапуна гидробака | D80: 10.778689 | E80: 3 | G80: =IF(G$17=0,0,G$17/$D$17*$E80*$D80) -> 32.336066 | H80: =IF(H$17=0,0,H$17/$D$17*$E80*$D80) -> 32.336066 | I80: =IF(I$17=0,0,I$17/$D$17*$E80*$D80) -> 32.336066 | J80: =IF(J$17=0,0,J$17/$D$17*$E80*$D80) -> 32.336066 | K80: =IF(K$17=0,0,K$17/$D$17*$E80*$D80) -> 32.336066 | L80: =IF(L$17=0,0,L$17/$D$17*$E80*$D80) -> 32.336066 | M80: =IF(M$17=0,0,M$17/$D$17*$E80*$D80) -> 32.336066 | N80: =IF(N$17=0,0,N$17/$D$17*$E80*$D80) -> 32.336066 | ... Z80: =IF(Z$17=0,0,Z$17/$D$17*$E80*$D80) -> 32.336066
B81: фильтр | C81: 21M-60-51250 (MP) Фильтр гидравлический | D81: 64.163934 | E81: 3 | G81: =IF(G$17=0,0,G$17/$D$17*$E81*$D81) -> 192.4918 | H81: =IF(H$17=0,0,H$17/$D$17*$E81*$D81) -> 192.4918 | I81: =IF(I$17=0,0,I$17/$D$17*$E81*$D81) -> 192.4918 | J81: =IF(J$17=0,0,J$17/$D$17*$E81*$D81) -> 192.4918 | K81: =IF(K$17=0,0,K$17/$D$17*$E81*$D81) -> 192.4918 | L81: =IF(L$17=0,0,L$17/$D$17*$E81*$D81) -> 192.4918 | M81: =IF(M$17=0,0,M$17/$D$17*$E81*$D81) -> 192.4918 | N81: =IF(N$17=0,0,N$17/$D$17*$E81*$D81) -> 192.4918 | ... Z81: =IF(Z$17=0,0,Z$17/$D$17*$E81*$D81) -> 192.4918
B82: фильтр | C82: 07000-B5180Z УПЛОТНИТЕЛЬНОЕ КОЛЬЦО | D82: 28.819672 | E82: 3 | G82: =IF(G$17=0,0,G$17/$D$17*$E82*$D82) -> 86.459016 | H82: =IF(H$17=0,0,H$17/$D$17*$E82*$D82) -> 86.459016 | I82: =IF(I$17=0,0,I$17/$D$17*$E82*$D82) -> 86.459016 | J82: =IF(J$17=0,0,J$17/$D$17*$E82*$D82) -> 86.459016 | K82: =IF(K$17=0,0,K$17/$D$17*$E82*$D82) -> 86.459016 | L82: =IF(L$17=0,0,L$17/$D$17*$E82*$D82) -> 86.459016 | M82: =IF(M$17=0,0,M$17/$D$17*$E82*$D82) -> 86.459016 | N82: =IF(N$17=0,0,N$17/$D$17*$E82*$D82) -> 86.459016 | ... Z82: =IF(Z$17=0,0,Z$17/$D$17*$E82*$D82) -> 86.459016
B83: фильтр | C83: 07030-00252 (MP) Фильтр сапун | D83: 21.081967 | E83: 2 | G83: =IF(G$17=0,0,G$17/$D$17*$E83*$D83) -> 42.163934 | H83: =IF(H$17=0,0,H$17/$D$17*$E83*$D83) -> 42.163934 | I83: =IF(I$17=0,0,I$17/$D$17*$E83*$D83) -> 42.163934 | J83: =IF(J$17=0,0,J$17/$D$17*$E83*$D83) -> 42.163934 | K83: =IF(K$17=0,0,K$17/$D$17*$E83*$D83) -> 42.163934 | L83: =IF(L$17=0,0,L$17/$D$17*$E83*$D83) -> 42.163934 | M83: =IF(M$17=0,0,M$17/$D$17*$E83*$D83) -> 42.163934 | N83: =IF(N$17=0,0,N$17/$D$17*$E83*$D83) -> 42.163934 | ... Z83: =IF(Z$17=0,0,Z$17/$D$17*$E83*$D83) -> 42.163934
B84: фильтр | C84: 21T-64-34590 (MP) Фильтр гидравлический | D84: 11.836066 | E84: 2 | G84: =IF(G$17=0,0,G$17/$D$17*$E84*$D84) -> 23.672131 | H84: =IF(H$17=0,0,H$17/$D$17*$E84*$D84) -> 23.672131 | I84: =IF(I$17=0,0,I$17/$D$17*$E84*$D84) -> 23.672131 | J84: =IF(J$17=0,0,J$17/$D$17*$E84*$D84) -> 23.672131 | K84: =IF(K$17=0,0,K$17/$D$17*$E84*$D84) -> 23.672131 | L84: =IF(L$17=0,0,L$17/$D$17*$E84*$D84) -> 23.672131 | M84: =IF(M$17=0,0,M$17/$D$17*$E84*$D84) -> 23.672131 | N84: =IF(N$17=0,0,N$17/$D$17*$E84*$D84) -> 23.672131 | ... Z84: =IF(Z$17=0,0,Z$17/$D$17*$E84*$D84) -> 23.672131
B85: фильтр | C85: 706-76-71390 (MP) Уплотнительное кольцо | D85: 1.8770492 | E85: 2 | G85: =IF(G$17=0,0,G$17/$D$17*$E85*$D85) -> 3.7540984 | H85: =IF(H$17=0,0,H$17/$D$17*$E85*$D85) -> 3.7540984 | I85: =IF(I$17=0,0,I$17/$D$17*$E85*$D85) -> 3.7540984 | J85: =IF(J$17=0,0,J$17/$D$17*$E85*$D85) -> 3.7540984 | K85: =IF(K$17=0,0,K$17/$D$17*$E85*$D85) -> 3.7540984 | L85: =IF(L$17=0,0,L$17/$D$17*$E85*$D85) -> 3.7540984 | M85: =IF(M$17=0,0,M$17/$D$17*$E85*$D85) -> 3.7540984 | N85: =IF(N$17=0,0,N$17/$D$17*$E85*$D85) -> 3.7540984 | ... Z85: =IF(Z$17=0,0,Z$17/$D$17*$E85*$D85) -> 3.7540984
... B93: масло | C93: COOL FLUID PREMIUM 60/40 (220 кг) | D93: 3.2 | E93: 50 | G93: =IF(G$17=0,0,G$17/$D$17*$E93*$D93) -> 160 | H93: =IF(H$17=0,0,H$17/$D$17*$E93*$D93) -> 160 | I93: =IF(I$17=0,0,I$17/$D$17*$E93*$D93) -> 160 | J93: =IF(J$17=0,0,J$17/$D$17*$E93*$D93) -> 160 | K93: =IF(K$17=0,0,K$17/$D$17*$E93*$D93) -> 160 | L93: =IF(L$17=0,0,L$17/$D$17*$E93*$D93) -> 160 | M93: =IF(M$17=0,0,M$17/$D$17*$E93*$D93) -> 160 | N93: =IF(N$17=0,0,N$17/$D$17*$E93*$D93) -> 160 | ... Z93: =IF(Z$17=0,0,Z$17/$D$17*$E93*$D93) -> 160
B94: ТО-5 | E94: =VLOOKUP($B94,$B$14:$C$19,2,FALSE) -> 0 | F94: =VLOOKUP($B94,$B$14:$E$19,4,FALSE) -> 0
B95: фильтр | D95: 100 | E95: 2 | G95: =IF(G$18=0,0,G$18/$D$18*$E95*$D95) -> 0 | H95: =IF(H$18=0,0,H$18/$D$18*$E95*$D95) -> 0 | I95: =IF(I$18=0,0,I$18/$D$18*$E95*$D95) -> 0 | J95: =IF(J$18=0,0,J$18/$D$18*$E95*$D95) -> 0 | K95: =IF(K$18=0,0,K$18/$D$18*$E95*$D95) -> 0 | L95: =IF(L$18=0,0,L$18/$D$18*$E95*$D95) -> 0 | M95: =IF(M$18=0,0,M$18/$D$18*$E95*$D95) -> 0 | N95: =IF(N$18=0,0,N$18/$D$18*$E95*$D95) -> 0 | ... Z95: =IF(Z$18=0,0,Z$18/$D$18*$E95*$D95) -> 0
B96: фильтр | D96: 50 | E96: 2 | G96: =IF(G$18=0,0,G$18/$D$18*$E96*$D96) -> 0 | H96: =IF(H$18=0,0,H$18/$D$18*$E96*$D96) -> 0 | I96: =IF(I$18=0,0,I$18/$D$18*$E96*$D96) -> 0 | J96: =IF(J$18=0,0,J$18/$D$18*$E96*$D96) -> 0 | K96: =IF(K$18=0,0,K$18/$D$18*$E96*$D96) -> 0 | L96: =IF(L$18=0,0,L$18/$D$18*$E96*$D96) -> 0 | M96: =IF(M$18=0,0,M$18/$D$18*$E96*$D96) -> 0 | N96: =IF(N$18=0,0,N$18/$D$18*$E96*$D96) -> 0 | ... Z96: =IF(Z$18=0,0,Z$18/$D$18*$E96*$D96) -> 0
B97: масло | D97: 3 | E97: 100 | G97: =IF(G$18=0,0,G$18/$D$18*$E97*$D97) -> 0 | H97: =IF(H$18=0,0,H$18/$D$18*$E97*$D97) -> 0 | I97: =IF(I$18=0,0,I$18/$D$18*$E97*$D97) -> 0 | J97: =IF(J$18=0,0,J$18/$D$18*$E97*$D97) -> 0 | K97: =IF(K$18=0,0,K$18/$D$18*$E97*$D97) -> 0 | L97: =IF(L$18=0,0,L$18/$D$18*$E97*$D97) -> 0 | M97: =IF(M$18=0,0,M$18/$D$18*$E97*$D97) -> 0 | N97: =IF(N$18=0,0,N$18/$D$18*$E97*$D97) -> 0 | ... Z97: =IF(Z$18=0,0,Z$18/$D$18*$E97*$D97) -> 0
B98: масло | D98: 3 | E98: 100 | G98: =IF(G$18=0,0,G$18/$D$18*$E98*$D98) -> 0 | H98: =IF(H$18=0,0,H$18/$D$18*$E98*$D98) -> 0 | I98: =IF(I$18=0,0,I$18/$D$18*$E98*$D98) -> 0 | J98: =IF(J$18=0,0,J$18/$D$18*$E98*$D98) -> 0 | K98: =IF(K$18=0,0,K$18/$D$18*$E98*$D98) -> 0 | L98: =IF(L$18=0,0,L$18/$D$18*$E98*$D98) -> 0 | M98: =IF(M$18=0,0,M$18/$D$18*$E98*$D98) -> 0 | N98: =IF(N$18=0,0,N$18/$D$18*$E98*$D98) -> 0 | ... Z98: =IF(Z$18=0,0,Z$18/$D$18*$E98*$D98) -> 0
B99: смазка | D99: 5 | E99: 50 | G99: =IF(G$18=0,0,G$18/$D$18*$E99*$D99) -> 0 | H99: =IF(H$18=0,0,H$18/$D$18*$E99*$D99) -> 0 | I99: =IF(I$18=0,0,I$18/$D$18*$E99*$D99) -> 0 | J99: =IF(J$18=0,0,J$18/$D$18*$E99*$D99) -> 0 | K99: =IF(K$18=0,0,K$18/$D$18*$E99*$D99) -> 0 | L99: =IF(L$18=0,0,L$18/$D$18*$E99*$D99) -> 0 | M99: =IF(M$18=0,0,M$18/$D$18*$E99*$D99) -> 0 | N99: =IF(N$18=0,0,N$18/$D$18*$E99*$D99) -> 0 | ... Z99: =IF(Z$18=0,0,Z$18/$D$18*$E99*$D99) -> 0
B100: смазка | D100: 5 | E100: 50 | G100: =IF(G$18=0,0,G$18/$D$18*$E100*$D100) -> 0 | H100: =IF(H$18=0,0,H$18/$D$18*$E100*$D100) -> 0 | I100: =IF(I$18=0,0,I$18/$D$18*$E100*$D100) -> 0 | J100: =IF(J$18=0,0,J$18/$D$18*$E100*$D100) -> 0 | K100: =IF(K$18=0,0,K$18/$D$18*$E100*$D100) -> 0 | L100: =IF(L$18=0,0,L$18/$D$18*$E100*$D100) -> 0 | M100: =IF(M$18=0,0,M$18/$D$18*$E100*$D100) -> 0 | N100: =IF(N$18=0,0,N$18/$D$18*$E100*$D100) -> 0 | ... Z100: =IF(Z$18=0,0,Z$18/$D$18*$E100*$D100) -> 0
B101: ТО-6 | E101: =VLOOKUP($B101,$B$14:$C$19,2,FALSE) -> 0
B102: фильтр | D102: 100 | E102: 2 | G102: =IF(G$19=0,0,G$19/$D$19*$E102*$D102) -> 0 | H102: =IF(H$19=0,0,H$19/$D$19*$E102*$D102) -> 0 | I102: =IF(I$19=0,0,I$19/$D$19*$E102*$D102) -> 0 | J102: =IF(J$19=0,0,J$19/$D$19*$E102*$D102) -> 0 | K102: =IF(K$19=0,0,K$19/$D$19*$E102*$D102) -> 0 | L102: =IF(L$19=0,0,L$19/$D$19*$E102*$D102) -> 0 | M102: =IF(M$19=0,0,M$19/$D$19*$E102*$D102) -> 0 | N102: =IF(N$19=0,0,N$19/$D$19*$E102*$D102) -> 0 | ... Z102: =IF(Z$19=0,0,Z$19/$D$19*$E102*$D102) -> 0
B103: фильтр | D103: 50 | E103: 2 | G103: =IF(G$19=0,0,G$19/$D$19*$E103*$D103) -> 0 | H103: =IF(H$19=0,0,H$19/$D$19*$E103*$D103) -> 0 | I103: =IF(I$19=0,0,I$19/$D$19*$E103*$D103) -> 0 | J103: =IF(J$19=0,0,J$19/$D$19*$E103*$D103) -> 0 | K103: =IF(K$19=0,0,K$19/$D$19*$E103*$D103) -> 0 | L103: =IF(L$19=0,0,L$19/$D$19*$E103*$D103) -> 0 | M103: =IF(M$19=0,0,M$19/$D$19*$E103*$D103) -> 0 | N103: =IF(N$19=0,0,N$19/$D$19*$E103*$D103) -> 0 | ... Z103: =IF(Z$19=0,0,Z$19/$D$19*$E103*$D103) -> 0
B104: масло | D104: 3 | E104: 100 | G104: =IF(G$19=0,0,G$19/$D$19*$E104*$D104) -> 0 | H104: =IF(H$19=0,0,H$19/$D$19*$E104*$D104) -> 0 | I104: =IF(I$19=0,0,I$19/$D$19*$E104*$D104) -> 0 | J104: =IF(J$19=0,0,J$19/$D$19*$E104*$D104) -> 0 | K104: =IF(K$19=0,0,K$19/$D$19*$E104*$D104) -> 0 | L104: =IF(L$19=0,0,L$19/$D$19*$E104*$D104) -> 0 | M104: =IF(M$19=0,0,M$19/$D$19*$E104*$D104) -> 0 | N104: =IF(N$19=0,0,N$19/$D$19*$E104*$D104) -> 0 | ... Z104: =IF(Z$19=0,0,Z$19/$D$19*$E104*$D104) -> 0
B105: масло | D105: 3 | E105: 100 | G105: =IF(G$19=0,0,G$19/$D$19*$E105*$D105) -> 0 | H105: =IF(H$19=0,0,H$19/$D$19*$E105*$D105) -> 0 | I105: =IF(I$19=0,0,I$19/$D$19*$E105*$D105) -> 0 | J105: =IF(J$19=0,0,J$19/$D$19*$E105*$D105) -> 0 | K105: =IF(K$19=0,0,K$19/$D$19*$E105*$D105) -> 0 | L105: =IF(L$19=0,0,L$19/$D$19*$E105*$D105) -> 0 | M105: =IF(M$19=0,0,M$19/$D$19*$E105*$D105) -> 0 | N105: =IF(N$19=0,0,N$19/$D$19*$E105*$D105) -> 0 | ... Z105: =IF(Z$19=0,0,Z$19/$D$19*$E105*$D105) -> 0
B106: смазка | D106: 5 | E106: 50 | G106: =IF(G$19=0,0,G$19/$D$19*$E106*$D106) -> 0 | H106: =IF(H$19=0,0,H$19/$D$19*$E106*$D106) -> 0 | I106: =IF(I$19=0,0,I$19/$D$19*$E106*$D106) -> 0 | J106: =IF(J$19=0,0,J$19/$D$19*$E106*$D106) -> 0 | K106: =IF(K$19=0,0,K$19/$D$19*$E106*$D106) -> 0 | L106: =IF(L$19=0,0,L$19/$D$19*$E106*$D106) -> 0 | M106: =IF(M$19=0,0,M$19/$D$19*$E106*$D106) -> 0 | N106: =IF(N$19=0,0,N$19/$D$19*$E106*$D106) -> 0 | ... Z106: =IF(Z$19=0,0,Z$19/$D$19*$E106*$D106) -> 0
B107: смазка | D107: 5 | E107: 50 | G107: =IF(G$19=0,0,G$19/$D$19*$E107*$D107) -> 0 | H107: =IF(H$19=0,0,H$19/$D$19*$E107*$D107) -> 0 | I107: =IF(I$19=0,0,I$19/$D$19*$E107*$D107) -> 0 | J107: =IF(J$19=0,0,J$19/$D$19*$E107*$D107) -> 0 | K107: =IF(K$19=0,0,K$19/$D$19*$E107*$D107) -> 0 | L107: =IF(L$19=0,0,L$19/$D$19*$E107*$D107) -> 0 | M107: =IF(M$19=0,0,M$19/$D$19*$E107*$D107) -> 0 | N107: =IF(N$19=0,0,N$19/$D$19*$E107*$D107) -> 0 | ... Z107: =IF(Z$19=0,0,Z$19/$D$19*$E107*$D107) -> 0

Sheet PC2000-11R ИСТК_Ремонты
B2: ячейки к заполнению поставщиком
B3: Расчетный КТГ | F3: ='PC2000-11R ИСТК'!E9 -> 0.94292237 | G3: ='PC2000-11R ИСТК'!F9 -> 0.93515348 | H3: ='PC2000-11R ИСТК'!G9 -> 0.91284564 | I3: ='PC2000-11R ИСТК'!H9 -> 0.88554351 | J3: ='PC2000-11R ИСТК'!I9 -> 0.938483 | K3: ='PC2000-11R ИСТК'!J9 -> 0.90507674 | L3: ='PC2000-11R ИСТК'!K9 -> 0.93515348 | M3: ='PC2000-11R ИСТК'!L9 -> 0.8933124 | ... Y3: ='PC2000-11R ИСТК'!X9 -> 0.91684107
B4: Год службы (год) | C4: Ед.изм. | F4: 1 | G4: =F4+1 -> 2 | H4: =G4+1 -> 3 | I4: =H4+1 -> 4 | J4: =I4+1 -> 5 | K4: =J4+1 -> 6 | L4: =K4+1 -> 7 | M4: =L4+1 -> 8 | N4: =M4+1 -> 9 | ... Y4: =X4+1 -> 20
B5: Наработка на начало года | C5: м/час | F5: 0 | G5: =F6+1 -> 7001 | H5: =G6+1 -> 14001 | I5: =H6+1 -> 21001 | J5: =I6+1 -> 28001 | K5: =J6+1 -> 35001 | L5: =K6+1 -> 42001 | M5: =L6+1 -> 49001 | N5: =M6+1 -> 56001 | ... Y5: =X6+1 -> 133001
B6: Наработка на конец года | C6: м/час | E6: ='PC2000-11R ИСТК_ТО'!F6 -> 7000 | F6: =E6 -> 7000 | G6: =F6+$E6 -> 14000 | H6: =G6+$E6 -> 21000 | I6: =H6+$E6 -> 28000 | J6: =I6+$E6 -> 35000 | K6: =J6+$E6 -> 42000 | L6: =K6+$E6 -> 49000 | M6: =L6+$E6 -> 56000 | N6: =M6+$E6 -> 63000 | ... Y6: =X6+$E6 -> 140000
B8: Простои в ремонтах | C8: часов | F8: =F16 -> 0 | G8: =G16 -> 70 | H8: =H16 -> 271 | I8: =I16 -> 517 | J8: =J16 -> 40 | K8: =K16 -> 341 | L8: =L16 -> 70 | M8: =M16 -> 447 | ... Y8: =Y16 -> 235
B9: Затраты на ремонты | C9: $/год | F9: =SUM(F10:F12) -> 0 | G9: =SUM(G10:G12) -> 40434.11 | H9: =SUM(H10:H12) -> 532652.12 | I9: =SUM(I10:I12) -> 1329951.5 | J9: =SUM(J10:J12) -> 111000 | K9: =SUM(K10:K12) -> 573086.23 | L9: =SUM(L10:L12) -> 40434.11 | M9: =SUM(M10:M12) -> 1289517.4 | ... Y9: =SUM(Y10:Y12) -> 347752.12
B10: текущие ремонты | C10: $/год | F10: =F34 -> 0 | G10: =G34 -> 0 | H10: =H34 -> 0 | I10: =I34 -> 0 | J10: =J34 -> 0 | K10: =K34 -> 0 | L10: =L34 -> 0 | M10: =M34 -> 0 | ... Y10: =Y34 -> 0
B11: планово-предупредительные (капитальные) ремонты | C11: $/год | F11: =F40 -> 0 | G11: =G40 -> 38684.11 | H11: =H40 -> 525877.12 | I11: =I40 -> 1317026.5 | J11: =J40 -> 110000 | K11: =K40 -> 564561.23 | L11: =L40 -> 38684.11 | M11: =M40 -> 1278342.4 | ... Y11: =Y40 -> 341877.12
B12: сервис (трудозатраты) | C12: $/год | F12: =SUMPRODUCT($D26:$D30,F$26:F$30) -> 0 | G12: =SUMPRODUCT($D26:$D30,G$26:G$30) -> 1750 | H12: =SUMPRODUCT($D26:$D30,H$26:H$30) -> 6775 | I12: =SUMPRODUCT($D26:$D30,I$26:I$30) -> 12925 | J12: =SUMPRODUCT($D26:$D30,J$26:J$30) -> 1000 | K12: =SUMPRODUCT($D26:$D30,K$26:K$30) -> 8525 | L12: =SUMPRODUCT($D26:$D30,L$26:L$30) -> 1750 | M12: =SUMPRODUCT($D26:$D30,M$26:M$30) -> 11175 | ... Y12: =SUMPRODUCT($D26:$D30,Y$26:Y$30) -> 5875
B14: Простои в ремонте (час)
B15: Вид ремонта | C15: Ед.изм. | F15: =F4 -> 1 | G15: =G4 -> 2 | H15: =H4 -> 3 | I15: =I4 -> 4 | J15: =J4 -> 5 | K15: =K4 -> 6 | L15: =L4 -> 7 | M15: =M4 -> 8 | ... Y15: =Y4 -> 20
B16: Всего простоев | F16: =SUM(F17:F21) -> 0 | G16: =SUM(G17:G21) -> 70 | H16: =SUM(H17:H21) -> 271 | I16: =SUM(I17:I21) -> 517 | J16: =SUM(J17:J21) -> 40 | K16: =SUM(K17:K21) -> 341 | L16: =SUM(L17:L21) -> 70 | M16: =SUM(M17:M21) -> 447 | ... Y16: =SUM(Y17:Y21) -> 235
B17: ремонт-(ППР) | C17: часов | G17: 70 | H17: 271 | I17: 517 | J17: 40 | K17: 341 | L17: 70 | M17: 447 | N17: 381 | P17: 517 | Q17: 341 | R17: 40 | S17: 70 | T17: 718 | U17: 70 | W17: 828 | X17: 70 | Y17: 235
C18: часов
C19: часов
C20: часов
C21: часов
B23: Трудозатраты на ремонты (ч/час) | D23: ='PC2000-11R ИСТК_ТО'!F10 -> 50
B24: Вид ремонта | C24: Ед.изм. | D24: Стоимость ч/часа | F24: =F15 -> 1 | G24: =G15 -> 2 | H24: =H15 -> 3 | I24: =I15 -> 4 | J24: =J15 -> 5 | K24: =K15 -> 6 | L24: =L15 -> 7 | M24: =M15 -> 8 | ... Y24: =Y15 -> 20
B25: Всего ч/часов | C25: ч/часов | F25: =SUM(F26:F30) -> 0 | G25: =SUM(G26:G30) -> 35 | H25: =SUM(H26:H30) -> 135.5 | I25: =SUM(I26:I30) -> 258.5 | J25: =SUM(J26:J30) -> 20 | K25: =SUM(K26:K30) -> 170.5 | L25: =SUM(L26:L30) -> 35 | M25: =SUM(M26:M30) -> 223.5 | ... Y25: =SUM(Y26:Y30) -> 117.5
B26: =B17 -> ремонт-(ППР) | C26: ч/часов | D26: =$D$23 -> 50 | G26: =G17/2 -> 35 | H26: =H17/2 -> 135.5 | I26: =I17/2 -> 258.5 | J26: =J17/2 -> 20 | K26: =K17/2 -> 170.5 | L26: =L17/2 -> 35 | M26: =M17/2 -> 223.5 | N26: =N17/2 -> 190.5 | ... Y26: =Y17/2 -> 117.5
B27: =B18 -> 0 | C27: ч/часов | D27: =$D$23 -> 50
B28: =B19 -> 0 | C28: ч/часов | D28: =$D$23 -> 50
B29: =B20 -> 0 | C29: ч/часов | D29: =$D$23 -> 50
B30: =B21 -> 0 | C30: ч/часов | D30: =$D$23 -> 50
B32: Затраты на ремонты ($)
B33: Детализация затрат | C33: Стоимость за ед., $ | D33: Ресурс до замены / ремонта, м/ч | E33: Кол-во МТР | F33: $ | G33: $ | H33: $ | I33: $ | J33: $ | K33: $ | L33: $ | M33: $ | N33: $ | O33: $ | P33: $ | Q33: $ | R33: $ | S33: $ | T33: $ | U33: $ | V33: $ | W33: $ | X33: $ | Y33: $
B34: Текущие ремонты (если планируются) | F34: =SUM(F35:F39) -> 0 | G34: =SUM(G35:G39) -> 0 | H34: =SUM(H35:H39) -> 0 | I34: =SUM(I35:I39) -> 0 | J34: =SUM(J35:J39) -> 0 | K34: =SUM(K35:K39) -> 0 | L34: =SUM(L35:L39) -> 0 | M34: =SUM(M35:M39) -> 0 | ... Y34: =SUM(Y35:Y39) -> 0
B35: текущий ремонт (ходовая часть) | F35: =$E35*$C35 -> 0 | G35: =$E35*$C35 -> 0 | H35: =$E35*$C35 -> 0 | I35: =$E35*$C35 -> 0 | J35: =$E35*$C35 -> 0 | K35: =$E35*$C35 -> 0 | L35: =$E35*$C35 -> 0 | M35: =$E35*$C35 -> 0 | ... Y35: =$E35*$C35 -> 0
B36: текущий ремонт (рабочее оборудование) | F36: =$E36*$C36 -> 0 | G36: =$E36*$C36 -> 0 | H36: =$E36*$C36 -> 0 | I36: =$E36*$C36 -> 0 | J36: =$E36*$C36 -> 0 | K36: =$E36*$C36 -> 0 | L36: =$E36*$C36 -> 0 | M36: =$E36*$C36 -> 0 | ... Y36: =$E36*$C36 -> 0
B37: другое | F37: =$E37*$C37 -> 0 | G37: =$E37*$C37 -> 0 | H37: =$E37*$C37 -> 0 | I37: =$E37*$C37 -> 0 | J37: =$E37*$C37 -> 0 | K37: =$E37*$C37 -> 0 | L37: =$E37*$C37 -> 0 | M37: =$E37*$C37 -> 0 | ... Y37: =$E37*$C37 -> 0
B38: другое | F38: =$E38*$C38 -> 0 | G38: =$E38*$C38 -> 0 | H38: =$E38*$C38 -> 0 | I38: =$E38*$C38 -> 0 | J38: =$E38*$C38 -> 0 | K38: =$E38*$C38 -> 0 | L38: =$E38*$C38 -> 0 | M38: =$E38*$C38 -> 0 | ... Y38: =$E38*$C38 -> 0
B39: другое | F39: =$E39*$C39 -> 0 | G39: =$E39*$C39 -> 0 | H39: =$E39*$C39 -> 0 | I39: =$E39*$C39 -> 0 | J39: =$E39*$C39 -> 0 | K39: =$E39*$C39 -> 0 | L39: =$E39*$C39 -> 0 | M39: =$E39*$C39 -> 0 | ... Y39: =$E39*$C39 -> 0
B40: планово-предупредительные (капитальные) ремонты+работа | D40: приравнять к 2000 от МС. И ТР | F40: =SUM(F41:F61) -> 0 | G40: =SUM(G41:G61) -> 38684.11 | H40: =SUM(H41:H61) -> 525877.12 | I40: =SUM(I41:I61) -> 1317026.5 | J40: =SUM(J41:J61) -> 110000 | K40: =SUM(K41:K61) -> 564561.23 | L40: =SUM(L41:L61) -> 38684.11 | M40: =SUM(M41:M61) -> 1278342.4 | ... Y40: =SUM(Y41:Y61) -> 341877.12 | Z40: Часы
B41: Ходовая часть
B42: Ходовые моторы | C42: 44950 | D42: 25000 | E42: 2 | I42: =C42*E42 -> 89900 | M42: 89900 | P42: 89900 | T42: 89900 | W42: 89900 | Z42: 53
B43: Редуктор хода | C43: 166150 | D43: 25000 | E43: 2 | I43: =C43*E43 -> 332300 | M43: 332300 | P43: 332300 | T43: 332300 | W43: 332300 | Z43: 125
B44: Гусеничная лента | C44: 92000 | D44: 20000 | E44: 2 | H44: =E44*C44 -> 184000 | K44: 184000 | N44: 184000 | Q44: 184000 | T44: 184000 | W44: 184000 | Z44: 36
B45: Опорные ролики (комп) | C45: 119410.84 | D45: 20000 | E45: 1 | H45: =C45*E45 -> 119410.84 | K45: 119410.84 | N45: 119410.84 | Q45: 119410.84 | T45: 119410.84 | W45: 119410.84 | Y45: 119410.84 | Z45: 88
B46: Поддерживающие катки (комп) | C46: 31381.533 | D46: 20000 | E46: 1 | H46: =E46*C46 -> 31381.533 | K46: 31381.533 | N46: 31381.533 | Q46: 31381.533 | T46: 31381.533 | W46: 31381.533 | Y46: 31381.533 | Z46: 18
B47: Механизм натяжения гусениц | C47: 55000 | D47: 30000 | E47: 2 | J47: =C47*E47 -> 110000 | N47: 110000 | R47: 110000 | W47: 110000 | Z47: 40
B48: Натяжное колесо | C48: 40000 | D48: 20000 | E48: 2 | H48: =C48*E48 -> 80000 | K48: 80000 | N48: 80000 | Q48: 80000 | T48: 80000 | W48: 80000 | Y48: 80000 | Z48: 40
B49: Система поворота
B50: Гидромотор поворота платформы | C50: 56486.313 | D50: 25000 | E50: 1 | I50: =E50*C50 -> 56486.313 | M50: 56486.313 | P50: 56486.313 | T50: 56486.313 | W50: 56486.313 | Z50: 11
B51: Редуктор поворота платформы | C51: 84279.477 | D51: 20000 | E51: 1 | H51: =C51*E51 -> 84279.477 | K51: 84279.477 | N51: 84279.477 | Q51: 84279.477 | T51: 84279.477 | W51: 84279.477 | Y51: 84279.477 | Z51: 53
B52: Основные узлы | C52: =C53/'PC2000-8 MS_Ремонты'!C124 -> 0.79246334
B53: ДВС | C53: 320000 | D53: 25000 | E53: 1 | I53: =E53*C53 -> 320000 | M53: 320000 | P53: 320000 | T53: 320000 | W53: 320000 | Z53: 170
B54: Главные насосы, 2 шт. | C54: 317539.93 | D54: 25000 | E54: 1 | I54: =C54*E54 -> 317539.93 | M54: 317539.93 | P54: 317539.93 | T54: 317539.93 | W54: 317539.93 | Z54: 22
B55: Главный распределительный клапан | C55: 162116.17 | D55: 25000 | E55: 1 | I55: =C55*E55 -> 162116.17 | M55: 162116.17 | P55: 162116.17 | T55: 162116.17 | W55: 162116.17 | Z55: 66
B56: Рабочее оборудование
B57: Ремонт гидроцилиндров стрелы | C57: 18330.411 | D57: 12000 | E57: 1 | G57: =C57*E57 -> 18330.411 | I57: 18330.411 | K57: 18330.411 | L57: 18330.411 | N57: 18330.411 | P57: 18330.411 | Q57: 18330.411 | S57: 18330.411 | U57: 18330.411 | W57: 18330.411 | X57: 18330.411 | Z57: 26
B58: Ремонт гидроцилиндра рукояти | C58: 11198.082 | D58: 12000 | E58: 1 | G58: =C58*E58 -> 11198.082 | I58: 11198.082 | K58: 11198.082 | L58: 11198.082 | N58: 11198.082 | P58: 11198.082 | Q58: 11198.082 | S58: 11198.082 | U58: 11198.082 | W58: 11198.082 | X58: 11198.082 | Z58: 18
B59: Ремонт гидроцилиндра ковша | C59: 9155.6164 | D59: 12000 | E59: 1 | G59: =E59*C59 -> 9155.6164 | I59: 9155.6164 | K59: 9155.6164 | L59: 9155.6164 | N59: 9155.6164 | P59: 9155.6164 | Q59: 9155.6164 | S59: 9155.6164 | U59: 9155.6164 | W59: 9155.6164 | X59: 9155.6164 | Z59: 26
B60: РВД рабочего оборудования | C60: 26805.271 | D60: 20000 | E60: 1 | H60: =E60*C60 -> 26805.271 | K60: 26805.271 | N60: 26805.271 | Q60: 26805.271 | T60: 26805.271 | W60: 26805.271 | Y60: 26805.271 | Z60: 36

Sheet Zooml_Орикс
B2: ячейки к заполнению поставщиком
B3: Экскаватор | C3: Zoomlion ZE2000G | Y3: Примечания
A4: 1 | B4: Период (год) | C4: Ед. изм. | D4: 0 | E4: =D4+1 -> 1 | F4: =E4+1 -> 2 | G4: =F4+1 -> 3 | H4: =G4+1 -> 4 | I4: =H4+1 -> 5 | J4: =I4+1 -> 6 | K4: =J4+1 -> 7 | L4: =K4+1 -> 8 | ... X4: =W4+1 -> 20 | Y4: Учесть срок эксплуатации (в данном примере это 20 лет)
A5: =A4+1 -> 2 | B5: Геометрическая емкость ковша экскаватора | C5: м3 | D5: 12
A6: =A5+1 -> 3 | B6: Емкость ковша с шапкой | C6: м3 | D6: 13
B7: КТГ в расчет | E7: =Факт.КТГ!D23 -> 0.85465183 | F7: =Факт.КТГ!E23 -> 0.7283267 | G7: =Факт.КТГ!F23 -> 0.75512296 | H7: =Факт.КТГ!G23 -> 0.69453356 | I7: =Факт.КТГ!H23 -> 0.6934042 | J7: =Факт.КТГ!I23 -> 0.74273728 | K7: =Факт.КТГ!J23 -> 0.71715238 | L7: =Факт.КТГ!K23 -> 0.77322818 | ... N7: =Факт.КТГ!M23 -> 0.75729454 | Y7: первый год - факт Люгонга по Группе, далее динамика от факта PC2000
A9: =A6+1 -> 4 | B9: КТГ при нормативной эксплуатации | E9: =(8760-E10-E11-E12)/8760 -> 0.94392123 | F9: =(8760-F10-F11-F12)/8760 -> 0.93948186 | G9: =(8760-G10-G11-G12)/8760 -> 0.90618658 | H9: =(8760-H10-H11-H12)/8760 -> 0.93060312 | I9: =(8760-I10-I11-I12)/8760 -> 0.90618658 | J9: =(8760-J10-J11-J12)/8760 -> 0.93948186 | K9: =(8760-K10-K11-K12)/8760 -> 0.90618658 | L9: =(8760-L10-L11-L12)/8760 -> 0.93060312 | ... X9: =(8760-X10-X11-X12)/8760 -> 0.90618658 | Y9: Расчетный
A10: =A9+1 -> 5 | B10: простои на ТО | C10: час | E10: =Zooml_Орикс_ТО!G7 -> 175 | F10: =Zooml_Орикс_ТО!H7 -> 175 | G10: =Zooml_Орикс_ТО!I7 -> 175 | H10: =Zooml_Орикс_ТО!J7 -> 175 | I10: =Zooml_Орикс_ТО!K7 -> 175 | J10: =Zooml_Орикс_ТО!L7 -> 175 | K10: =Zooml_Орикс_ТО!M7 -> 175 | L10: =Zooml_Орикс_ТО!N7 -> 175 | ... X10: =Zooml_Орикс_ТО!Z7 -> 175
A11: =A10+1 -> 6 | B11: простои в ремонтах | C11: час | E11: =Zooml_Орикс_Ремонты!F8 -> 80 | F11: =Zooml_Орикс_Ремонты!G8 -> 120 | G11: =Zooml_Орикс_Ремонты!H8 -> 420 | H11: =Zooml_Орикс_Ремонты!I8 -> 200 | I11: =Zooml_Орикс_Ремонты!J8 -> 420 | J11: =Zooml_Орикс_Ремонты!K8 -> 120 | K11: =Zooml_Орикс_Ремонты!L8 -> 420 | L11: =Zooml_Орикс_Ремонты!M8 -> 200 | ... X11: =Zooml_Орикс_Ремонты!Y8 -> 420
A12: =A11+1 -> 7 | B12: ежесменный осмотр (20 минут в смену) | C12: час | E12: =(8760-E10-E11)/12*20/60 -> 236.25 | F12: =(8760-F10-F11)/12*20/60 -> 235.13889 | G12: =(8760-G10-G11)/12*20/60 -> 226.80556 | H12: =(8760-H10-H11)/12*20/60 -> 232.91667 | I12: =(8760-I10-I11)/12*20/60 -> 226.80556 | J12: =(8760-J10-J11)/12*20/60 -> 235.13889 | K12: =(8760-K10-K11)/12*20/60 -> 226.80556 | L12: =(8760-L10-L11)/12*20/60 -> 232.91667 | ... X12: =(8760-X10-X11)/12*20/60 -> 226.80556
A13: =A12+1 -> 8 | B13: Время цикла | C13: сек | D13: 30
A14: =A13+1 -> 9 | B14: Мощность двигателя | C14: л.с. | D14: 1065
A15: =A14+1 -> 10 | B15: Затраты на ТО и ремонты | C15: тыс.дол./год | E15: =SUM(E16:E20) -> 101.323 | F15: =SUM(F16:F20) -> 127.652 | G15: =SUM(G16:G20) -> 700.369 | H15: =SUM(H16:H20) -> 219.452 | I15: =SUM(I16:I20) -> 539.3174 | J15: =SUM(J16:J20) -> 129.348 | K15: =SUM(K16:K20) -> 539.3174 | L15: =SUM(L16:L20) -> 219.452 | ... X15: =SUM(X16:X20) -> 539.3174
A16: =A15+1 -> 11 | B16: ТО, включая смазочные | C16: тыс.дол./год | E16: =Zooml_Орикс_ТО!G9/1000 -> 84.411 | F16: =Zooml_Орикс_ТО!H9/1000 -> 84.411 | G16: =Zooml_Орикс_ТО!I9/1000 -> 84.411 | H16: =Zooml_Орикс_ТО!J9/1000 -> 84.411 | I16: =Zooml_Орикс_ТО!K9/1000 -> 84.411 | J16: =Zooml_Орикс_ТО!L9/1000 -> 84.411 | K16: =Zooml_Орикс_ТО!M9/1000 -> 84.411 | L16: =Zooml_Орикс_ТО!N9/1000 -> 84.411 | ... X16: =Zooml_Орикс_ТО!Z9/1000 -> 84.411
A17: =A16+1 -> 12 | B17: текущие ремонты | C17: тыс.дол./год | E17: =Zooml_Орикс_Ремонты!F10/1000 -> 1.862 | F17: =Zooml_Орикс_Ремонты!G10/1000 -> 1.862 | G17: =Zooml_Орикс_Ремонты!H10/1000 -> 5.119 | H17: =Zooml_Орикс_Ремонты!I10/1000 -> 1.862 | I17: =Zooml_Орикс_Ремонты!J10/1000 -> 3.423 | J17: =Zooml_Орикс_Ремонты!K10/1000 -> 3.558 | K17: =Zooml_Орикс_Ремонты!L10/1000 -> 3.423 | L17: =Zooml_Орикс_Ремонты!M10/1000 -> 1.862 | ... X17: =Zooml_Орикс_Ремонты!Y10/1000 -> 3.423
A18: =A17+1 -> 13 | B18: планово-предупредительные (капитальные) ремонты | C18: тыс.дол./год | E18: =Zooml_Орикс_Ремонты!F11/1000 -> 0 | F18: =Zooml_Орикс_Ремонты!G11/1000 -> 24.929 | G18: =Zooml_Орикс_Ремонты!H11/1000 -> 583.889 | H18: =Zooml_Орикс_Ремонты!I11/1000 -> 113.929 | I18: =Zooml_Орикс_Ремонты!J11/1000 -> 424.5334 | J18: =Zooml_Орикс_Ремонты!K11/1000 -> 24.929 | K18: =Zooml_Орикс_Ремонты!L11/1000 -> 424.5334 | L18: =Zooml_Орикс_Ремонты!M11/1000 -> 113.929 | ... X18: =Zooml_Орикс_Ремонты!Y11/1000 -> 424.5334
A19: =A18+1 -> 14 | B19: сервис (трудозатраты) - ТО | C19: тыс.дол./год | E19: =Zooml_Орикс_ТО!G10/1000 -> 12.25 | F19: =Zooml_Орикс_ТО!H10/1000 -> 12.25 | G19: =Zooml_Орикс_ТО!I10/1000 -> 12.25 | H19: =Zooml_Орикс_ТО!J10/1000 -> 12.25 | I19: =Zooml_Орикс_ТО!K10/1000 -> 12.25 | J19: =Zooml_Орикс_ТО!L10/1000 -> 12.25 | K19: =Zooml_Орикс_ТО!M10/1000 -> 12.25 | L19: =Zooml_Орикс_ТО!N10/1000 -> 12.25 | ... X19: =Zooml_Орикс_ТО!Z10/1000 -> 12.25
A20: =A19+1 -> 15 | B20: сервис (трудозатраты) - ремонты | C20: тыс.дол./год | E20: =Zooml_Орикс_Ремонты!F12/1000 -> 2.8 | F20: =Zooml_Орикс_Ремонты!G12/1000 -> 4.2 | G20: =Zooml_Орикс_Ремонты!H12/1000 -> 14.7 | H20: =Zooml_Орикс_Ремонты!I12/1000 -> 7 | I20: =Zooml_Орикс_Ремонты!J12/1000 -> 14.7 | J20: =Zooml_Орикс_Ремонты!K12/1000 -> 4.2 | K20: =Zooml_Орикс_Ремонты!L12/1000 -> 14.7 | L20: =Zooml_Орикс_Ремонты!M12/1000 -> 7 | ... X20: =Zooml_Орикс_Ремонты!Y12/1000 -> 14.7
A21: =A20+1 -> 16 | B21: Расходные материалы: | Y21: Здесь перечень приведен в качестве примера
A22: =A21+1 -> 17 | B22: канаты | Y22: Указать нужные данные (здесь приведены - в качестве примера)
A23: =A22+1 -> 18 | B23: удельный расход | Y23: Указать нужные данные (здесь приведены - в качестве примера)
A24: =A23+1 -> 19 | B24: цена за ед. | Y24: Указать нужные данные (здесь приведены - в качестве примера)
A25: =A24+1 -> 20 | B25: кабели | Y25: Указать нужные данные (здесь приведены - в качестве примера)
A26: =A25+1 -> 21 | B26: удельный расход | Y26: Указать нужные данные (здесь приведены - в качестве примера)
A27: =A26+1 -> 22 | B27: цена за ед. | Y27: Указать нужные данные (здесь приведены - в качестве примера)
A28: =A27+1 -> 23 | B28: зубья ковша | Y28: Указать нужные данные (здесь приведены - в качестве примера)
A29: =A28+1 -> 24 | B29: удельный расход | E29: 100 | F29: 100 | G29: 100 | H29: 100 | I29: 100 | J29: 100 | K29: 100 | L29: 100 | M29: 100 | N29: 100 | O29: 100 | P29: 100 | Q29: 100 | R29: 100 | S29: 100 | T29: 100 | U29: 100 | V29: 100 | W29: 100 | X29: 100 | Y29: Указать нужные данные (здесь приведены - в качестве примера)
A30: =A29+1 -> 25 | B30: цена за ед. | E30: 660 | F30: 660 | G30: 660 | H30: 660 | I30: 660 | J30: 660 | K30: 660 | L30: 660 | M30: 660 | N30: 660 | O30: 660 | P30: 660 | Q30: 660 | R30: 660 | S30: 660 | T30: 660 | U30: 660 | V30: 660 | W30: 660 | X30: 660 | Y30: Указать нужные данные (здесь приведены - в качестве примера)
A31: =A30+1 -> 26 | B31: режущие кромки | Y31: Указать нужные данные (здесь приведены - в качестве примера)
A32: =A31+1 -> 27 | B32: удельный расход | Y32: Указать нужные данные (здесь приведены - в качестве примера)
A33: =A32+1 -> 28 | B33: цена за ед. | Y33: Указать нужные данные (здесь приведены - в качестве примера)
A34: =A33+1 -> 29 | B34: защита ковша и т.д. | Y34: Указать нужные данные (здесь приведены - в качестве примера)
A35: =A34+1 -> 30 | B35: удельный расход | Y35: Указать нужные данные (здесь приведены - в качестве примера)
A36: =A35+1 -> 31 | B36: цена за ед. | Y36: Указать нужные данные (здесь приведены - в качестве примера)
A37: =A36+1 -> 32 | B37: Электроэнергия / дизтопливо
A38: =A37+1 -> 33 | B38: удельный расход дизтоплива | C38: кг/куб.м | D38: 0.286 | Y38: Указать удельный расход и единицы измерения
A39: =A38+1 -> 34 | B39: Сроки поставки | C39: мес

Sheet Zooml_Орикс_ТО
B2: ячейки к заполнению поставщиком
B3: Расчетный КТГ | G3: =Zooml_Орикс!E9 -> 0.94392123 | H3: =Zooml_Орикс!F9 -> 0.93948186 | I3: =Zooml_Орикс!G9 -> 0.90618658 | J3: =Zooml_Орикс!H9 -> 0.93060312 | K3: =Zooml_Орикс!I9 -> 0.90618658 | L3: =Zooml_Орикс!J9 -> 0.93948186 | M3: =Zooml_Орикс!K9 -> 0.90618658 | N3: =Zooml_Орикс!L9 -> 0.93060312 | ... Z3: =Zooml_Орикс!X9 -> 0.90618658
B4: Год службы (год) | C4: Ед. изм. | G4: =E4+1 -> 1 | H4: =G4+1 -> 2 | I4: =H4+1 -> 3 | J4: =I4+1 -> 4 | K4: =J4+1 -> 5 | L4: =K4+1 -> 6 | M4: =L4+1 -> 7 | N4: =M4+1 -> 8 | O4: =N4+1 -> 9 | ... Z4: =Y4+1 -> 20
B5: Наработка на начало года | C5: м/час | G5: 0 | H5: =G6+1 -> 7001 | I5: =H6+1 -> 14001 | J5: =I6+1 -> 21001 | K5: =J6+1 -> 28001 | L5: =K6+1 -> 35001 | M5: =L6+1 -> 42001 | N5: =M6+1 -> 49001 | O5: =N6+1 -> 56001 | ... Z5: =Y6+1 -> 133001
B6: Наработка на конец года | C6: м/час | F6: 7000 | G6: =F6 -> 7000 | H6: =G6+$F6 -> 14000 | I6: =H6+$F6 -> 21000 | J6: =I6+$F6 -> 28000 | K6: =J6+$F6 -> 35000 | L6: =K6+$F6 -> 42000 | M6: =L6+$F6 -> 49000 | N6: =M6+$F6 -> 56000 | O6: =N6+$F6 -> 63000 | ... Z6: =Y6+$F6 -> 140000
B7: длительность простоев на ТО | C7: часов | G7: =G13 -> 175 | H7: =H13 -> 175 | I7: =I13 -> 175 | J7: =J13 -> 175 | K7: =K13 -> 175 | L7: =L13 -> 175 | M7: =M13 -> 175 | N7: =N13 -> 175 | ... Z7: =Z13 -> 175
B8: Затраты на ТО | C8: долларов/год | G8: =SUM(G9:G10) -> 96661 | H8: =SUM(H9:H10) -> 96661 | I8: =SUM(I9:I10) -> 96661 | J8: =SUM(J9:J10) -> 96661 | K8: =SUM(K9:K10) -> 96661 | L8: =SUM(L9:L10) -> 96661 | M8: =SUM(M9:M10) -> 96661 | N8: =SUM(N9:N10) -> 96661 | ... Z8: =SUM(Z9:Z10) -> 96661
B9: ТО, включая масла и смазки | C9: долларов/год | G9: =G22 -> 84411 | H9: =H22 -> 84411 | I9: =I22 -> 84411 | J9: =J22 -> 84411 | K9: =K22 -> 84411 | L9: =L22 -> 84411 | M9: =M22 -> 84411 | N9: =N22 -> 84411 | ... Z9: =Z22 -> 84411
B10: сервис (трудозатраты) на ТО | C10: долларов/год | F10: 35 | G10: =SUMPRODUCT(G14:G19,$F$14:$F$19)*$F10 -> 12250 | H10: =SUMPRODUCT(H14:H19,$F$14:$F$19)*$F10 -> 12250 | I10: =SUMPRODUCT(I14:I19,$F$14:$F$19)*$F10 -> 12250 | J10: =SUMPRODUCT(J14:J19,$F$14:$F$19)*$F10 -> 12250 | K10: =SUMPRODUCT(K14:K19,$F$14:$F$19)*$F10 -> 12250 | L10: =SUMPRODUCT(L14:L19,$F$14:$F$19)*$F10 -> 12250 | M10: =SUMPRODUCT(M14:M19,$F$14:$F$19)*$F10 -> 12250 | N10: =SUMPRODUCT(N14:N19,$F$14:$F$19)*$F10 -> 12250 | ... Z10: =SUMPRODUCT(Z14:Z19,$F$14:$F$19)*$F10 -> 12250
B12: Простои оборудования на ТО | C12: Интервал ТО | D12: Длительность простоя на одном ТО, час | E12: Кол-во ТО в год | F12: Занято человек | G12: Простоев в год, час | H12: Простоев в год, час | I12: Простоев в год, час | J12: Простоев в год, час | K12: Простоев в год, час | L12: Простоев в год, час | M12: Простоев в год, час | N12: Простоев в год, час | O12: Простоев в год, час | P12: Простоев в год, час | Q12: Простоев в год, час | R12: Простоев в год, час | S12: Простоев в год, час | T12: Простоев в год, час | U12: Простоев в год, час | V12: Простоев в год, час | W12: Простоев в год, час | X12: Простоев в год, час | Y12: Простоев в год, час | Z12: Простоев в год, час
B13: всего простоев на ТО, часов | G13: =SUM(G14:G19) -> 175 | H13: =SUM(H14:H19) -> 175 | I13: =SUM(I14:I19) -> 175 | J13: =SUM(J14:J19) -> 175 | K13: =SUM(K14:K19) -> 175 | L13: =SUM(L14:L19) -> 175 | M13: =SUM(M14:M19) -> 175 | N13: =SUM(N14:N19) -> 175 | ... Z13: =SUM(Z14:Z19) -> 175
B14: ТО-1 | C14: 500 | D14: 4 | E14: =$F$6/C14 -> 14 | F14: 2 | G14: =$E14*$D14 -> 56 | H14: =$E14*$D14 -> 56 | I14: =$E14*$D14 -> 56 | J14: =$E14*$D14 -> 56 | K14: =$E14*$D14 -> 56 | L14: =$E14*$D14 -> 56 | M14: =$E14*$D14 -> 56 | N14: =$E14*$D14 -> 56 | ... Z14: =$E14*$D14 -> 56 | AB14: формулы для примера, можно менять под необходимые параметры
B15: ТО-2 | C15: 1000 | D15: 8 | E15: =$F$6/C15 -> 7 | F15: 2 | G15: =$E15*$D15 -> 56 | H15: =$E15*$D15 -> 56 | I15: =$E15*$D15 -> 56 | J15: =$E15*$D15 -> 56 | K15: =$E15*$D15 -> 56 | L15: =$E15*$D15 -> 56 | M15: =$E15*$D15 -> 56 | N15: =$E15*$D15 -> 56 | ... Z15: =$E15*$D15 -> 56 | AB15: формулы для примера, можно менять под необходимые параметры
