Workbook

Sheet Методика
B1: МЕТОДИКА: АННУИТЕТ ЗАТРАТ (РУБ/ТКМ) НА ВЛАДЕНИЕ АВТОСАМОСВАЛАМИ
B2: Пост-налоговый погодовой дисконтированный аннуитет жизненного цикла.
C4: 1. НАЗНАЧЕНИЕ
C5: Экономическое сравнение карьерных автосамосвалов одного класса по удельному аннуитету затрат (руб/ткм грузооборота, а также руб/т перевезённой массы) за полный срок эксплуатации. Метрика корректно сопоставляет самосвалы с разной ценой, грузоподъёмностью и производительностью. Лучший вариант — минимум руб/ткм.
C6: 2. ПРОИЗВОДИТЕЛЬНОСТЬ (транспортный цикл из файла «Производительность»)
C7: Время рейса = (подход + погрузка + разгрузка + прочее) + время движения; время движения = 2 × плечо / скорость × 60 (гружёный + порожний ход). Рейсов/час = 60 / время рейса. Часовая производительность (т/эфф.час) = рейсов/час × грузоподъёмность × КИГ. КИО = КТГ × (1 − простои_смены/(60 × смена)); эффективное время = КФВ × КИО. Годовой объём (тыс.т) = часовая × эффективное время; грузооборот (тыс.ткм) = объём × плечо; пробег = рейсы × 2 × плечо.
C8: 3. ПОГОДОВОЙ ДЕНЕЖНЫЙ ПОТОК (10 лет)
C9: Для каждого года считаются: топливо (грузооборот × г/ткм × цена), ТОиР и сервис (задаются ПО ГОДАМ на листах «Поставщик N» — ТО, текущие и капитальные ремонты; годы капремонтов дают всплеск затрат), шины (пробег × удельный расход × цена), персонал, транспортный налог. Добавляются амортизация (НУ) и налог на прибыль (щит). Операционный поток = база + налог − амортизация. Инвестиции — в год 0, остаточная стоимость — в конце срока.
C10: 4. АННУИТЕТ (ЯДРО)
C11: Потоки дисконтируются и преобразуются в эквивалентный годовой платёж: Аннуитет = NPV затрат / Σ(дисконт-факторов). Инвестиционный аннуитет = (Цена − дисконт. остаточная стоимость) / Σ(дисконт-факторов). Операционный аннуитет — приведённые эксплуатационные затраты после налога. Общий = инвестиционный + операционный. Удельный аннуитет (руб/ткм) = общий аннуитет / средний годовой грузооборот; руб/т = руб/ткм × плечо.
C12: 5. ПОРЯДОК РАБОТЫ
C13: «Параметры» → «Ввод данных» (цена, грузоподъёмность, мощность двигателя, персонал) → листы «Поставщик 1…6»: по каждой машине задаются КТГ, простои и затраты ТОиР по годам — КТГ и ИТОГО ТОиР считаются автоматически. Сводка «Данные по годам» тянет итоги сама → авторасчёт «Производительность», «Денежный поток», «Расчёт аннуитета» → «Дашборд», «Сравнение», «Аналитика», «Чувствительность». Правки — в листах «Поставщик N» и «Ввод данных».
C14: 6. ДОПУЩЕНИЯ
C15: • Самосвалы сравниваются в одном классе и одной задаче; разница в производительности учтена через руб/ткм и руб/т.
... C22: зелёные ячейки — итоговые показатели / лучший вариант

Sheet Дашборд
B1: ИТОГОВЫЙ ДАШБОРД — СРАВНЕНИЕ АВТОСАМОСВАЛОВ
B2: Ключевые показатели и графики. Данные обновляются автоматически.
B4: КЛЮЧЕВЫЕ ПОКАЗАТЕЛИ
B5: Лучший вариант | C5: Мин. аннуитет, руб/ткм | D5: Мин. NPV владения, тыс.руб | E5: Разброс аннуитета, руб/ткм
B6: =INDEX('Ввод данных'!D7:I7,MATCH(MIN('Расчёт аннуитета'!D26:I26),'Расчёт аннуитета'!D26:I26,0)) -> NHL NTE 240 | C6: =MIN('Расчёт аннуитета'!D26:I26) -> 12.046304 | D6: =MIN('Расчёт аннуитета'!D14:I14) -> 784177.62 | E6: =MAX('Расчёт аннуитета'!D26:I26)-MIN('Расчёт аннуитета'!D26:I26) -> 5.290397
B8: РЕЙТИНГ ПО УДЕЛЬНОМУ АННУИТЕТУ (руб/ткм)
B9: Место | C9: Автосамосвал | G9: руб/ткм | I9: руб/т
B10: 1 | C10: =INDEX('Ввод данных'!D7:I7,MATCH(SMALL('Расчёт аннуитета'!D26:I26,1),'Расчёт аннуитета'!D26:I26,0)) -> NHL NTE 240 | G10: =SMALL('Расчёт аннуитета'!D26:I26,1) -> 12.046304 | I10: =INDEX('Расчёт аннуитета'!$D$28:$I$28,MATCH(SMALL('Расчёт аннуитета'!D26:I26,1),'Расчёт аннуитета'!D26:I26,0)) -> 36.615947
B11: 2 | C11: =INDEX('Ввод данных'!D7:I7,MATCH(SMALL('Расчёт аннуитета'!D26:I26,2),'Расчёт аннуитета'!D26:I26,0)) -> SANY SET240S | G11: =SMALL('Расчёт аннуитета'!D26:I26,2) -> 14.02617 | I11: =INDEX('Расчёт аннуитета'!$D$28:$I$28,MATCH(SMALL('Расчёт аннуитета'!D26:I26,2),'Расчёт аннуитета'!D26:I26,0)) -> 42.633947
B12: 3 | C12: =INDEX('Ввод данных'!D7:I7,MATCH(SMALL('Расчёт аннуитета'!D26:I26,3),'Расчёт аннуитета'!D26:I26,0)) -> БелАЗ 7531 (БТЛ) | G12: =SMALL('Расчёт аннуитета'!D26:I26,3) -> 14.09582 | I12: =INDEX('Расчёт аннуитета'!$D$28:$I$28,MATCH(SMALL('Расчёт аннуитета'!D26:I26,3),'Расчёт аннуитета'!D26:I26,0)) -> 42.845655
B13: 4 | C13: =INDEX('Ввод данных'!D7:I7,MATCH(SMALL('Расчёт аннуитета'!D26:I26,4),'Расчёт аннуитета'!D26:I26,0)) -> БелАЗ 7531 (ГПФК) | G13: =SMALL('Расчёт аннуитета'!D26:I26,4) -> 14.372984 | I13: =INDEX('Расчёт аннуитета'!$D$28:$I$28,MATCH(SMALL('Расчёт аннуитета'!D26:I26,4),'Расчёт аннуитета'!D26:I26,0)) -> 43.688123
B14: 5 | C14: =INDEX('Ввод данных'!D7:I7,MATCH(SMALL('Расчёт аннуитета'!D26:I26,5),'Расчёт аннуитета'!D26:I26,0)) -> TZCO TZE240 | G14: =SMALL('Расчёт аннуитета'!D26:I26,5) -> 16.119303 | I14: =INDEX('Расчёт аннуитета'!$D$28:$I$28,MATCH(SMALL('Расчёт аннуитета'!D26:I26,5),'Расчёт аннуитета'!D26:I26,0)) -> 48.996232
B15: 6 | C15: =INDEX('Ввод данных'!D7:I7,MATCH(SMALL('Расчёт аннуитета'!D26:I26,6),'Расчёт аннуитета'!D26:I26,0)) -> Estar ESDE240 (ГПБ К) | G15: =SMALL('Расчёт аннуитета'!D26:I26,6) -> 17.336701 | I15: =INDEX('Расчёт аннуитета'!$D$28:$I$28,MATCH(SMALL('Расчёт аннуитета'!D26:I26,6),'Расчёт аннуитета'!D26:I26,0)) -> 52.696638

Sheet Параметры
B1: ГЛОБАЛЬНЫЕ ПАРАМЕТРЫ МОДЕЛИ
B2: Единые допущения для всех вариантов. Жёлтые ячейки — ввод.
B4: Финансовые допущения
B5: Параметр | C5: Значение | D5: Ед. | E5: Комментарий
B6: Ставка дисконтирования (WACC) | C6: 0.12 | D6: %/год | E6: Стоимость капитала для приведения к текущей стоимости
B7: Налог на прибыль | C7: 0.25 | D7: % | E7: Формирует налоговый щит на затраты и амортизацию
B8: Срок эксплуатации (горизонт) | C8: 10 | D8: лет | E8: Фиксирован = 10 лет в погодовом движке
B9: Срок амортизации (налоговый учёт) | C9: 5.083 | D9: лет | E9: Линейная; 61 мес ≈ 5,08 года
B10: Цена дизельного топлива | C10: 66.019 | D10: тыс.руб/т | E10: СЛ 2025: 1 274 749,9 тыс.руб / 19 308,86 т
B12: Эскалация цен (реальный/номинальный рост)
B13: Параметр | C13: Значение | D13: Ед. | E13: Комментарий
B14: Эскалация цены топлива | C14: 0 | D14: %/год | E14: 0 = данные уже с учётом инфляции
B15: Эскалация ЗЧ/шин/расходников | C15: 0 | D15: %/год | E15: ТОиР задаётся по годам напрямую
B16: Эскалация оплаты труда | C16: 0 | D16: %/год | E16: Рост ФОТ экипажей
B18: Курсы валют
B19: Параметр | C19: Значение | D19: Ед. | E19: Комментарий
B20: Курс юаня (CNY) | C20: 12.7702 | D20: руб | E20: Для оборудования из Китая
B21: Курс доллара (USD) | C21: 94.0485 | D21: руб
B22: Курс евро (EUR) | C22: 100 | D22: руб
B24: Параметры производительности (транспортный цикл)
B25: Параметр | C25: Значение | D25: Ед. | E25: Комментарий
B26: Календарный фонд времени | C26: 8760 | D26: час/год | E26: 24 ч × 365 дн
B27: Длительность смены | C27: 12 | D27: час | E27: Для пересчёта простоев
B28: Расстояние транспортировки (плечо) | C28: 3.0396 | D28: км | E28: Среднее плечо откатки (гружёный ход)
B29: Средняя техническая скорость | C29: 22.46 | D29: км/час | E29: С учётом профиля трассы
B30: КИГ (использование грузоподъёмности) | C30: 0.9837 | D30: коэф. | E30: Доля номинальной грузоподъёмности (факт NTE)
B31: Фикс. время рейса (подход+погр+разгр+прочее) | C31: 8.4 | D31: мин | E31: Подход/погрузка/разгрузка 7,9 + прочие 0,5
B32: Удельный расход топлива | C32: 90 | D32: г/ткм | E32: На тонно-километр грузооборота
B34: Шины
B35: Параметр | C35: Значение | D35: Ед. | E35: Комментарий
B36: Удельный расход шин | C36: 0.075 | D36: шт./тыс.км | E36: Комплект/износ на пробег
B37: Цена шины | C37: 2985.38 | D37: тыс.руб/шт | E37: DDP, без НДС (типоразмер 50/80R57 и аналоги)
B39: Транспортный налог и персонал
B40: Параметр | C40: Значение | D40: Ед. | E40: Комментарий
B41: Ставка транспортного налога | C41: 85 | D41: руб/л.с. | E41: Иркутская область
B43: Расчётные финансовые коэффициенты
B44: Параметр | C44: Значение | D44: Ед. | E44: Комментарий
B45: Коэф. аннуитета Σдиск.факторов (r, N) | C45: =IF('Параметры'!C6=0,'Параметры'!C8,(1-(1+'Параметры'!C6)^-'Параметры'!C8)/'Параметры'!C6) -> 5.650223 | D45: коэф. | E45: Сумма дисконт-факторов за срок службы
B46: Коэф. приведённой амортизации | C46: =(1/'Параметры'!C9)*((1-(1+'Параметры'!C6)^-INT('Параметры'!C9))/'Параметры'!C6+('Параметры'!C9-INT('Параметры'!C9))*(1+'Параметры'!C6)^-(INT('Параметры'!C9)+1)) -> 0.71745555 | D46: коэф. | E46: Приведённая амортизация на 1 руб. цены (налог. щит)
B48: Легенда: | D48: — ввод данных
D49: — расчётные показатели

Sheet Ввод данных
B1: ВВОД ИСХОДНЫХ ДАННЫХ ПО АВТОСАМОСВАЛАМ
B2: Сравнение до 6 машин одного класса. Пример: самосвалы класса 220–240 т, карьер «Сухой Лог».
B4: Показатель | C4: Ед. | D4: Самосвал 1 | E4: Самосвал 2 | F4: Самосвал 3 | G4: Самосвал 4 | H4: Самосвал 5 | I4: Самосвал 6 | K4: Пояснение
B6: A. ИДЕНТИФИКАЦИЯ
B7: Наименование / модель | C7: — | D7: NHL NTE 240 | E7: Estar ESDE240 (ГПБ К) | F7: SANY SET240S | G7: TZCO TZE240 | H7: БелАЗ 7531 (ГПФК) | I7: БелАЗ 7531 (БТЛ) | K7: Название варианта
B8: Поставщик | C8: — | D8: Горная Евразия | E8: ГПБ | F8: ИСТК | G8: ИСТК | H8: ГПФК | I8: БТЛ
B9: Двигатель / привод | C9: — | D9: электро (2500 л.с.) | E9: 1864 л.с. | F9: 2843 л.с. | G9: 2500 л.с. | H9: 2535 л.с. | I9: 2535 л.с.
B10: B. СТОИМОСТЬ И ОСТАТОЧНАЯ ЦЕНА
B11: Цена за единицу | C11: тыс.вал. | D11: 20000 | E11: 2800 | F11: 2700 | G11: 2700 | H11: 300000 | I11: 290000 | K11: ⚠ В файле поставщика цена не указана — ОЦЕНКА, уточнить
B12: Валюта цены | C12: — | D12: CNY | E12: USD | F12: USD | G12: USD | H12: RUB | I12: RUB | K12: CNY / USD / EUR / RUB
B13: Доставка, ПНР, шеф-монтаж | C13: тыс.руб | D13: 0 | E13: 0 | F13: 0 | G13: 0 | H13: 0 | I13: 0 | K13: Дополнительно к цене
B14: Остаточная стоимость | C14: % от цены | D14: 0 | E14: 0 | F14: 0 | G14: 0 | H14: 0 | I14: 0 | K14: Реализация в конце срока (0 = не учитывать)
B15: C. ПРОИЗВОДИТЕЛЬНОСТЬ
B16: Грузоподъёмность (в расчёте) | C16: т | D16: 227.8 | E16: 211.392 | F16: 216.362 | G16: 222 | H16: 231 | I16: 231 | K16: × КИГ (лист «Параметры») = фактическая загрузка
B17: D. ПРОЧИЕ ГОДОВЫЕ ЗАТРАТЫ И ПАРАМЕТРЫ
B18: Расходы на персонал (экипаж) | C18: тыс.руб/год | D18: 18475.6 | E18: 18475.6 | F18: 18475.6 | G18: 18475.6 | H18: 18475.6 | I18: 18475.6 | K18: ФОТ+отчисления+прочее на 1 машину
B19: Мощность двигателя (транспортный налог) | C19: л.с. | D19: 2500 | E19: 1864 | F19: 2843 | G19: 2500 | H19: 2535 | I19: 2535 | K19: × ставку налога (руб/л.с.)
B20: ℹ КТГ, простои и затраты на ТОиР (ТО/ТР/капремонты/сервис) задаются ПО ГОДАМ на листах «Поставщик 1…6». Расход топлива (г/ткм), шины и КИГ — общие на листе «Параметры». Сводка — на листе «Данные по годам».

Sheet Поставщик 1
B1: ДАННЫЕ ПОСТАВЩИКА — ВАРИАНТ 1 (ТО и Ремонты ПО ГОДАМ)
B2: Жёлтое — ввод (данные поставщика/расчёта). Зелёное — авто; сводка тянется в «Данные по годам».
B4: Автосамосвал: | E4: ='Ввод данных'!D7 -> NHL NTE 240
B5: Валюта затрат ТОиР: | D5: CNY
B6: Показатель | C6: Ед. | E6: год 1 | F6: год 2 | G6: год 3 | H6: год 4 | I6: год 5 | J6: год 6 | K6: год 7 | L6: год 8 | M6: год 9 | N6: год 10
B7: СВОДКА ПО ГОДАМ (зелёное — авто; тянется в расчёт)
B8: Простои на ТО | C8: ч/год | E8: =E19 -> 173.404 | F8: =F19 -> 202.004 | G8: =G19 -> 173.404 | H8: =H19 -> 202.004 | I8: =I19 -> 173.404 | J8: =J19 -> 202.004 | K8: =K19 -> 202.004 | L8: =L19 -> 173.404 | ... N8: =N19 -> 173.404
B9: Простои в ремонтах | C9: ч/год | E9: =E20 -> 139 | F9: =F20 -> 175 | G9: =G20 -> 289 | H9: =H20 -> 373 | I9: =I20 -> 177 | J9: =J20 -> 253 | K9: =K20 -> 167 | L9: =L20 -> 377 | ... N9: =N20 -> 187
B10: Ежесменный осмотр (20 мин/смену), справочно | C10: ч/год | E10: =('Параметры'!C26-E8-E9)/'Параметры'!C27*20/60 -> 234.65544 | F10: =('Параметры'!C26-F8-F9)/'Параметры'!C27*20/60 -> 232.861 | G10: =('Параметры'!C26-G8-G9)/'Параметры'!C27*20/60 -> 230.48878 | H10: =('Параметры'!C26-H8-H9)/'Параметры'!C27*20/60 -> 227.361 | I10: =('Параметры'!C26-I8-I9)/'Параметры'!C27*20/60 -> 233.59989 | J10: =('Параметры'!C26-J8-J9)/'Параметры'!C27*20/60 -> 230.69433 | K10: =('Параметры'!C26-K8-K9)/'Параметры'!C27*20/60 -> 233.08322 | L10: =('Параметры'!C26-L8-L9)/'Параметры'!C27*20/60 -> 228.04433 | M10: =('Параметры'!C26-M8-M9)/'Параметры'!C27*20/60 -> 229.52767 | N10: =('Параметры'!C26-N8-N9)/'Параметры'!C27*20/60 -> 233.32211
B11: КТГ (техготовность) → «Данные по годам» | C11: коэф. | E11: 0.9376 | F11: 0.9304 | G11: 0.9209 | H11: 0.9084 | I11: 0.9333 | J11: 0.9217 | K11: 0.9313 | L11: 0.9111 | M11: 0.9171 | N11: 0.9322
B12: Затраты на ТО (ЗЧ+смазочные) | C12: тыс.вал/г | E12: =E21 -> 297.274 | F12: =F21 -> 297.274 | G12: =G21 -> 297.274 | H12: =H21 -> 297.274 | I12: =I21 -> 297.274 | J12: =J21 -> 297.274 | K12: =K21 -> 297.274 | L12: =L21 -> 297.274 | ... N12: =N21 -> 297.274
B13: Затраты на текущие ремонты | C13: тыс.вал/г | E13: =E22 -> 0 | F13: =F22 -> 0 | G13: =G22 -> 0 | H13: =H22 -> 0 | I13: =I22 -> 0 | J13: =J22 -> 0 | K13: =K22 -> 0 | L13: =L22 -> 0 | ... N13: =N22 -> 0
B14: Затраты на капитальные/ППР ремонты | C14: тыс.вал/г | E14: =E23 -> 0 | F14: =F23 -> 151.61 | G14: =G23 -> 3293.541 | H14: =H23 -> 1329.651 | I14: =I23 -> 207.444 | J14: =J23 -> 3259.167 | K14: =K23 -> 47.962 | L14: =L23 -> 1481.261 | ... N14: =N23 -> 44.023
B15: Сервис (трудозатраты) — ТО | C15: тыс.вал/г | E15: =E24 -> 126.063 | F15: =F24 -> 147.913 | G15: =G24 -> 126.063 | H15: =H24 -> 147.913 | I15: =I24 -> 126.063 | J15: =J24 -> 147.913 | K15: =K24 -> 147.913 | L15: =L24 -> 126.063 | ... N15: =N24 -> 126.063
B16: Сервис (трудозатраты) — ремонты | C16: тыс.вал/г | E16: =E25 -> 47.368 | F16: =F25 -> 57.3 | G16: =G25 -> 158.53 | H16: =H25 -> 286.118 | I16: =I25 -> 56.536 | J16: =J25 -> 80.22 | K16: =K25 -> 144.014 | L16: =L25 -> 279.624 | ... N16: =N25 -> 74.108
B17: ИТОГО ТОиР → «Данные по годам» | C17: тыс.вал/г | E17: =E12+E13+E14+E15+E16 -> 470.705 | F17: =F12+F13+F14+F15+F16 -> 654.097 | G17: =G12+G13+G14+G15+G16 -> 3875.408 | H17: =H12+H13+H14+H15+H16 -> 2060.956 | I17: =I12+I13+I14+I15+I16 -> 687.317 | J17: =J12+J13+J14+J15+J16 -> 3784.574 | K17: =K12+K13+K14+K15+K16 -> 637.163 | L17: =L12+L13+L14+L15+L16 -> 2184.222 | ... N17: =N12+N13+N14+N15+N16 -> 541.468
B18: ВВОД ДАННЫХ ПОСТАВЩИКА ПО ГОДАМ (жёлтое)
B19: Простои на ТО | C19: ч/год | E19: 173.404 | F19: 202.004 | G19: 173.404 | H19: 202.004 | I19: 173.404 | J19: 202.004 | K19: 202.004 | L19: 173.404 | M19: 202.004 | N19: 173.404
B20: Простои в ремонтах | C20: ч/год | E20: 139 | F20: 175 | G20: 289 | H20: 373 | I20: 177 | J20: 253 | K20: 167 | L20: 377 | M20: 295 | N20: 187
B21: Затраты на ТО (ЗЧ+смазочные) | C21: тыс.вал/г | E21: 297.274 | F21: 297.274 | G21: 297.274 | H21: 297.274 | I21: 297.274 | J21: 297.274 | K21: 297.274 | L21: 297.274 | M21: 297.274 | N21: 297.274
B22: Затраты на текущие ремонты | C22: тыс.вал/г | E22: 0 | F22: 0 | G22: 0 | H22: 0 | I22: 0 | J22: 0 | K22: 0 | L22: 0 | M22: 0 | N22: 0
B23: Затраты на капитальные/ППР ремонты | C23: тыс.вал/г | E23: 0 | F23: 151.61 | G23: 3293.541 | H23: 1329.651 | I23: 207.444 | J23: 3259.167 | K23: 47.962 | L23: 1481.261 | M23: 6533.292 | N23: 44.023
B24: Сервис (трудозатраты) — ТО | C24: тыс.вал/г | E24: 126.063 | F24: 147.913 | G24: 126.063 | H24: 147.913 | I24: 126.063 | J24: 147.913 | K24: 147.913 | L24: 126.063 | M24: 147.913 | N24: 126.063
B25: Сервис (трудозатраты) — ремонты | C25: тыс.вал/г | E25: 47.368 | F25: 57.3 | G25: 158.53 | H25: 286.118 | I25: 56.536 | J25: 80.22 | K25: 144.014 | L25: 279.624 | M25: 81.748 | N25: 74.108
B27: Строки 18–24 — ввод (жёлтое): простои и затраты ТОиР по годам, в валюте (см. «Валюта затрат ТОиР»). Пересчёт в рубли — в «Денежном потоке» по курсу с листа «Параметры». Данные примера — «в расчёте» из 000_БСЛ-2027 (карьер «Сухой Лог»). «Рваный» график капремонтов по годам учитывается дисконтированием.

Sheet Поставщик 2
B1: ДАННЫЕ ПОСТАВЩИКА — ВАРИАНТ 2 (ТО и Ремонты ПО ГОДАМ)
B2: Жёлтое — ввод (данные поставщика/расчёта). Зелёное — авто; сводка тянется в «Данные по годам».
B4: Автосамосвал: | E4: ='Ввод данных'!E7 -> Estar ESDE240 (ГПБ К)
B5: Валюта затрат ТОиР: | D5: USD
B6: Показатель | C6: Ед. | E6: год 1 | F6: год 2 | G6: год 3 | H6: год 4 | I6: год 5 | J6: год 6 | K6: год 7 | L6: год 8 | M6: год 9 | N6: год 10
B7: СВОДКА ПО ГОДАМ (зелёное — авто; тянется в расчёт)
B8: Простои на ТО | C8: ч/год | E8: =E19 -> 153 | F8: =F19 -> 153 | G8: =G19 -> 153 | H8: =H19 -> 153 | I8: =I19 -> 153 | J8: =J19 -> 153 | K8: =K19 -> 153 | L8: =L19 -> 153 | ... N8: =N19 -> 153
B9: Простои в ремонтах | C9: ч/год | E9: =E20 -> 420 | F9: =F20 -> 505 | G9: =G20 -> 905 | H9: =H20 -> 1287 | I9: =I20 -> 455 | J9: =J20 -> 1132 | K9: =K20 -> 485 | L9: =L20 -> 1290 | ... N9: =N20 -> 1155
B10: Ежесменный осмотр (20 мин/смену), справочно | C10: ч/год | E10: =('Параметры'!C26-E8-E9)/'Параметры'!C27*20/60 -> 227.41667 | F10: =('Параметры'!C26-F8-F9)/'Параметры'!C27*20/60 -> 225.05556 | G10: =('Параметры'!C26-G8-G9)/'Параметры'!C27*20/60 -> 213.94444 | H10: =('Параметры'!C26-H8-H9)/'Параметры'!C27*20/60 -> 203.33333 | I10: =('Параметры'!C26-I8-I9)/'Параметры'!C27*20/60 -> 226.44444 | J10: =('Параметры'!C26-J8-J9)/'Параметры'!C27*20/60 -> 207.63889 | K10: =('Параметры'!C26-K8-K9)/'Параметры'!C27*20/60 -> 225.61111 | L10: =('Параметры'!C26-L8-L9)/'Параметры'!C27*20/60 -> 203.25 | M10: =('Параметры'!C26-M8-M9)/'Параметры'!C27*20/60 -> 217.36111 | N10: =('Параметры'!C26-N8-N9)/'Параметры'!C27*20/60 -> 207
B11: КТГ (техготовность) → «Данные по годам» | C11: коэф. | E11: 0.9116 | F11: 0.8956 | G11: 0.8493 | H11: 0.806 | I11: 0.899 | J11: 0.8221 | K11: 0.8886 | L11: 0.8107 | M11: 0.8562 | N11: 0.834
B12: Затраты на ТО (ЗЧ+смазочные) | C12: тыс.вал/г | E12: =E21 -> 154.719 | F12: =F21 -> 154.719 | G12: =G21 -> 154.719 | H12: =H21 -> 154.719 | I12: =I21 -> 154.719 | J12: =J21 -> 154.719 | K12: =K21 -> 154.719 | L12: =L21 -> 154.719 | ... N12: =N21 -> 154.719
B13: Затраты на текущие ремонты | C13: тыс.вал/г | E13: =E22 -> 0 | F13: =F22 -> 0 | G13: =G22 -> 0 | H13: =H22 -> 0 | I13: =I22 -> 0 | J13: =J22 -> 0 | K13: =K22 -> 0 | L13: =L22 -> 0 | ... N13: =N22 -> 0
B14: Затраты на капитальные/ППР ремонты | C14: тыс.вал/г | E14: =E23 -> 4.931 | F14: =F23 -> 88.53 | G14: =G23 -> 701.511 | H14: =H23 -> 2494.29 | I14: =I23 -> 7.014 | J14: =J23 -> 785.11 | K14: =K23 -> 4.931 | L14: =L23 -> 2494.29 | ... N14: =N23 -> 4.931
B15: Сервис (трудозатраты) — ТО | C15: тыс.вал/г | E15: =E24 -> 19.44 | F15: =F24 -> 19.44 | G15: =G24 -> 19.44 | H15: =H24 -> 19.44 | I15: =I24 -> 19.44 | J15: =J24 -> 19.44 | K15: =K24 -> 19.44 | L15: =L24 -> 19.44 | ... N15: =N24 -> 19.44
B16: Сервис (трудозатраты) — ремонты | C16: тыс.вал/г | E16: =E25 -> 1.44 | F16: =F25 -> 14.04 | G16: =G25 -> 52.47 | H16: =H25 -> 82.89 | I16: =I25 -> 3.06 | J16: =J25 -> 65.07 | K16: =K25 -> 1.44 | L16: =L25 -> 82.89 | ... N16: =N25 -> 1.44
B17: ИТОГО ТОиР → «Данные по годам» | C17: тыс.вал/г | E17: =E12+E13+E14+E15+E16 -> 180.53 | F17: =F12+F13+F14+F15+F16 -> 276.729 | G17: =G12+G13+G14+G15+G16 -> 928.14 | H17: =H12+H13+H14+H15+H16 -> 2751.339 | I17: =I12+I13+I14+I15+I16 -> 184.233 | J17: =J12+J13+J14+J15+J16 -> 1024.339 | K17: =K12+K13+K14+K15+K16 -> 180.53 | L17: =L12+L13+L14+L15+L16 -> 2751.339 | ... N17: =N12+N13+N14+N15+N16 -> 180.53
B18: ВВОД ДАННЫХ ПОСТАВЩИКА ПО ГОДАМ (жёлтое)
B19: Простои на ТО | C19: ч/год | E19: 153 | F19: 153 | G19: 153 | H19: 153 | I19: 153 | J19: 153 | K19: 153 | L19: 153 | M19: 153 | N19: 153
B20: Простои в ремонтах | C20: ч/год | E20: 420 | F20: 505 | G20: 905 | H20: 1287 | I20: 455 | J20: 1132 | K20: 485 | L20: 1290 | M20: 782 | N20: 1155
B21: Затраты на ТО (ЗЧ+смазочные) | C21: тыс.вал/г | E21: 154.719 | F21: 154.719 | G21: 154.719 | H21: 154.719 | I21: 154.719 | J21: 154.719 | K21: 154.719 | L21: 154.719 | M21: 154.719 | N21: 154.719
B22: Затраты на текущие ремонты | C22: тыс.вал/г | E22: 0 | F22: 0 | G22: 0 | H22: 0 | I22: 0 | J22: 0 | K22: 0 | L22: 0 | M22: 0 | N22: 0
B23: Затраты на капитальные/ППР ремонты | C23: тыс.вал/г | E23: 4.931 | F23: 88.53 | G23: 701.511 | H23: 2494.29 | I23: 7.014 | J23: 785.11 | K23: 4.931 | L23: 2494.29 | M23: 4.931 | N23: 4.931
B24: Сервис (трудозатраты) — ТО | C24: тыс.вал/г | E24: 19.44 | F24: 19.44 | G24: 19.44 | H24: 19.44 | I24: 19.44 | J24: 19.44 | K24: 19.44 | L24: 19.44 | M24: 19.44 | N24: 19.44
B25: Сервис (трудозатраты) — ремонты | C25: тыс.вал/г | E25: 1.44 | F25: 14.04 | G25: 52.47 | H25: 82.89 | I25: 3.06 | J25: 65.07 | K25: 1.44 | L25: 82.89 | M25: 1.44 | N25: 1.44
B27: Строки 18–24 — ввод (жёлтое): простои и затраты ТОиР по годам, в валюте (см. «Валюта затрат ТОиР»). Пересчёт в рубли — в «Денежном потоке» по курсу с листа «Параметры». Данные примера — «в расчёте» из 000_БСЛ-2027 (карьер «Сухой Лог»). «Рваный» график капремонтов по годам учитывается дисконтированием.

Sheet Поставщик 3
B1: ДАННЫЕ ПОСТАВЩИКА — ВАРИАНТ 3 (ТО и Ремонты ПО ГОДАМ)
B2: Жёлтое — ввод (данные поставщика/расчёта). Зелёное — авто; сводка тянется в «Данные по годам».
B4: Автосамосвал: | E4: ='Ввод данных'!F7 -> SANY SET240S
B5: Валюта затрат ТОиР: | D5: USD
B6: Показатель | C6: Ед. | E6: год 1 | F6: год 2 | G6: год 3 | H6: год 4 | I6: год 5 | J6: год 6 | K6: год 7 | L6: год 8 | M6: год 9 | N6: год 10
B7: СВОДКА ПО ГОДАМ (зелёное — авто; тянется в расчёт)
B8: Простои на ТО | C8: ч/год | E8: =E19 -> 186 | F8: =F19 -> 186 | G8: =G19 -> 186 | H8: =H19 -> 186 | I8: =I19 -> 186 | J8: =J19 -> 186 | K8: =K19 -> 186 | L8: =L19 -> 186 | ... N8: =N19 -> 186
B9: Простои в ремонтах | C9: ч/год | E9: =E20 -> 280 | F9: =F20 -> 570 | G9: =G20 -> 750 | H9: =H20 -> 505 | I9: =I20 -> 930 | J9: =J20 -> 505 | K9: =K20 -> 750 | L9: =L20 -> 505 | ... N9: =N20 -> 660
B10: Ежесменный осмотр (20 мин/смену), справочно | C10: ч/год | E10: =('Параметры'!C26-E8-E9)/'Параметры'!C27*20/60 -> 230.38889 | F10: =('Параметры'!C26-F8-F9)/'Параметры'!C27*20/60 -> 222.33333 | G10: =('Параметры'!C26-G8-G9)/'Параметры'!C27*20/60 -> 217.33333 | H10: =('Параметры'!C26-H8-H9)/'Параметры'!C27*20/60 -> 224.13889 | I10: =('Параметры'!C26-I8-I9)/'Параметры'!C27*20/60 -> 212.33333 | J10: =('Параметры'!C26-J8-J9)/'Параметры'!C27*20/60 -> 224.13889 | K10: =('Параметры'!C26-K8-K9)/'Параметры'!C27*20/60 -> 217.33333 | L10: =('Параметры'!C26-L8-L9)/'Параметры'!C27*20/60 -> 224.13889 | M10: =('Параметры'!C26-M8-M9)/'Параметры'!C27*20/60 -> 212.33333 | N10: =('Параметры'!C26-N8-N9)/'Параметры'!C27*20/60 -> 219.83333
B11: КТГ (техготовность) → «Данные по годам» | C11: коэф. | E11: 0.9357 | F11: 0.9026 | G11: 0.8659 | H11: 0.904 | I11: 0.85 | J11: 0.904 | K11: 0.8659 | L11: 0.904 | M11: 0.85 | N11: 0.885
B12: Затраты на ТО (ЗЧ+смазочные) | C12: тыс.вал/г | E12: =E21 -> 93.681 | F12: =F21 -> 93.681 | G12: =G21 -> 93.681 | H12: =H21 -> 93.681 | I12: =I21 -> 93.681 | J12: =J21 -> 93.681 | K12: =K21 -> 93.681 | L12: =L21 -> 93.681 | ... N12: =N21 -> 93.681
B13: Затраты на текущие ремонты | C13: тыс.вал/г | E13: =E22 -> 17.931 | F13: =F22 -> 17.931 | G13: =G22 -> 17.931 | H13: =H22 -> 17.931 | I13: =I22 -> 17.931 | J13: =J22 -> 17.931 | K13: =K22 -> 17.931 | L13: =L22 -> 17.931 | ... N13: =N22 -> 17.931
B14: Затраты на капитальные/ППР ремонты | C14: тыс.вал/г | E14: =E23 -> 0 | F14: =F23 -> 62.211 | G14: =G23 -> 433.633 | H14: =H23 -> 156.454 | I14: =I23 -> 803.169 | J14: =J23 -> 592.571 | K14: =K23 -> 103.048 | L14: =L23 -> 120.245 | ... N14: =N23 -> 39.493
B15: Сервис (трудозатраты) — ТО | C15: тыс.вал/г | E15: =E24 -> 17.204 | F15: =F24 -> 17.204 | G15: =G24 -> 17.204 | H15: =H24 -> 17.204 | I15: =I24 -> 17.204 | J15: =J24 -> 17.204 | K15: =K24 -> 17.204 | L15: =L24 -> 17.204 | ... N15: =N24 -> 17.204
B16: Сервис (трудозатраты) — ремонты | C16: тыс.вал/г | E16: =E25 -> 6.532 | F16: =F25 -> 20.24 | G16: =G25 -> 35.512 | H16: =H25 -> 19.872 | I16: =I25 -> 41.952 | J16: =J25 -> 19.872 | K16: =K25 -> 35.512 | L16: =L25 -> 19.872 | ... N16: =N25 -> 27.692
B17: ИТОГО ТОиР → «Данные по годам» | C17: тыс.вал/г | E17: =E12+E13+E14+E15+E16 -> 135.348 | F17: =F12+F13+F14+F15+F16 -> 211.267 | G17: =G12+G13+G14+G15+G16 -> 597.961 | H17: =H12+H13+H14+H15+H16 -> 305.142 | I17: =I12+I13+I14+I15+I16 -> 973.937 | J17: =J12+J13+J14+J15+J16 -> 741.259 | K17: =K12+K13+K14+K15+K16 -> 267.376 | L17: =L12+L13+L14+L15+L16 -> 268.933 | ... N17: =N12+N13+N14+N15+N16 -> 196.001
B18: ВВОД ДАННЫХ ПОСТАВЩИКА ПО ГОДАМ (жёлтое)
B19: Простои на ТО | C19: ч/год | E19: 186 | F19: 186 | G19: 186 | H19: 186 | I19: 186 | J19: 186 | K19: 186 | L19: 186 | M19: 186 | N19: 186
B20: Простои в ремонтах | C20: ч/год | E20: 280 | F20: 570 | G20: 750 | H20: 505 | I20: 930 | J20: 505 | K20: 750 | L20: 505 | M20: 930 | N20: 660
B21: Затраты на ТО (ЗЧ+смазочные) | C21: тыс.вал/г | E21: 93.681 | F21: 93.681 | G21: 93.681 | H21: 93.681 | I21: 93.681 | J21: 93.681 | K21: 93.681 | L21: 93.681 | M21: 93.681 | N21: 93.681
B22: Затраты на текущие ремонты | C22: тыс.вал/г | E22: 17.931 | F22: 17.931 | G22: 17.931 | H22: 17.931 | I22: 17.931 | J22: 17.931 | K22: 17.931 | L22: 17.931 | M22: 17.931 | N22: 17.931
B23: Затраты на капитальные/ППР ремонты | C23: тыс.вал/г | E23: 0 | F23: 62.211 | G23: 433.633 | H23: 156.454 | I23: 803.169 | J23: 592.571 | K23: 103.048 | L23: 120.245 | M23: 1178.573 | N23: 39.493
B24: Сервис (трудозатраты) — ТО | C24: тыс.вал/г | E24: 17.204 | F24: 17.204 | G24: 17.204 | H24: 17.204 | I24: 17.204 | J24: 17.204 | K24: 17.204 | L24: 17.204 | M24: 17.204 | N24: 17.204
B25: Сервис (трудозатраты) — ремонты | C25: тыс.вал/г | E25: 6.532 | F25: 20.24 | G25: 35.512 | H25: 19.872 | I25: 41.952 | J25: 19.872 | K25: 35.512 | L25: 19.872 | M25: 41.952 | N25: 27.692
B27: Строки 18–24 — ввод (жёлтое): простои и затраты ТОиР по годам, в валюте (см. «Валюта затрат ТОиР»). Пересчёт в рубли — в «Денежном потоке» по курсу с листа «Параметры». Данные примера — «в расчёте» из 000_БСЛ-2027 (карьер «Сухой Лог»). «Рваный» график капремонтов по годам учитывается дисконтированием.

Sheet Поставщик 4
B1: ДАННЫЕ ПОСТАВЩИКА — ВАРИАНТ 4 (ТО и Ремонты ПО ГОДАМ)
B2: Жёлтое — ввод (данные поставщика/расчёта). Зелёное — авто; сводка тянется в «Данные по годам».
B4: Автосамосвал: | E4: ='Ввод данных'!G7 -> TZCO TZE240
B5: Валюта затрат ТОиР: | D5: USD
B6: Показатель | C6: Ед. | E6: год 1 | F6: год 2 | G6: год 3 | H6: год 4 | I6: год 5 | J6: год 6 | K6: год 7 | L6: год 8 | M6: год 9 | N6: год 10
B7: СВОДКА ПО ГОДАМ (зелёное — авто; тянется в расчёт)
B8: Простои на ТО | C8: ч/год | E8: =E19 -> 196 | F8: =F19 -> 196 | G8: =G19 -> 196 | H8: =H19 -> 196 | I8: =I19 -> 196 | J8: =J19 -> 196 | K8: =K19 -> 196 | L8: =L19 -> 196 | ... N8: =N19 -> 196
B9: Простои в ремонтах | C9: ч/год | E9: =E20 -> 425 | F9: =F20 -> 690 | G9: =G20 -> 1600 | H9: =H20 -> 690 | I9: =I20 -> 425 | J9: =J20 -> 1800 | K9: =K20 -> 425 | L9: =L20 -> 690 | ... N9: =N20 -> 690
B10: Ежесменный осмотр (20 мин/смену), справочно | C10: ч/год | E10: =('Параметры'!C26-E8-E9)/'Параметры'!C27*20/60 -> 226.08333 | F10: =('Параметры'!C26-F8-F9)/'Параметры'!C27*20/60 -> 218.72222 | G10: =('Параметры'!C26-G8-G9)/'Параметры'!C27*20/60 -> 193.44444 | H10: =('Параметры'!C26-H8-H9)/'Параметры'!C27*20/60 -> 218.72222 | I10: =('Параметры'!C26-I8-I9)/'Параметры'!C27*20/60 -> 226.08333 | J10: =('Параметры'!C26-J8-J9)/'Параметры'!C27*20/60 -> 187.88889 | K10: =('Параметры'!C26-K8-K9)/'Параметры'!C27*20/60 -> 226.08333 | L10: =('Параметры'!C26-L8-L9)/'Параметры'!C27*20/60 -> 218.72222 | M10: =('Параметры'!C26-M8-M9)/'Параметры'!C27*20/60 -> 226.08333 | N10: =('Параметры'!C26-N8-N9)/'Параметры'!C27*20/60 -> 218.72222
B11: КТГ (техготовность) → «Данные по годам» | C11: коэф. | E11: 0.9096 | F11: 0.8842 | G11: 0.774 | H11: 0.8842 | I11: 0.9096 | J11: 0.748 | K11: 0.9096 | L11: 0.8842 | M11: 0.9096 | N11: 0.8842
B12: Затраты на ТО (ЗЧ+смазочные) | C12: тыс.вал/г | E12: =E21 -> 217.032 | F12: =F21 -> 217.032 | G12: =G21 -> 217.032 | H12: =H21 -> 217.032 | I12: =I21 -> 217.032 | J12: =J21 -> 217.032 | K12: =K21 -> 217.032 | L12: =L21 -> 217.032 | ... N12: =N21 -> 217.032
B13: Затраты на текущие ремонты | C13: тыс.вал/г | E13: =E22 -> 7.5 | F13: =F22 -> 7.5 | G13: =G22 -> 7.5 | H13: =H22 -> 7.5 | I13: =I22 -> 7.5 | J13: =J22 -> 7.5 | K13: =K22 -> 7.5 | L13: =L22 -> 7.5 | ... N13: =N22 -> 7.5
B14: Затраты на капитальные/ППР ремонты | C14: тыс.вал/г | E14: =E23 -> 22.18 | F14: =F23 -> 117.302 | G14: =G23 -> 1471.522 | H14: =H23 -> 117.302 | I14: =I23 -> 22.18 | J14: =J23 -> 1566.643 | K14: =K23 -> 22.18 | L14: =L23 -> 117.302 | ... N14: =N23 -> 117.302
B15: Сервис (трудозатраты) — ТО | C15: тыс.вал/г | E15: =E24 -> 50.416 | F15: =F24 -> 50.416 | G15: =G24 -> 50.416 | H15: =H24 -> 50.416 | I15: =I24 -> 50.416 | J15: =J24 -> 50.416 | K15: =K24 -> 50.416 | L15: =L24 -> 50.416 | ... N15: =N24 -> 50.416
B16: Сервис (трудозатраты) — ремонты | C16: тыс.вал/г | E16: =E25 -> 2.208 | F16: =F25 -> 237.323 | G16: =G25 -> 134.734 | H16: =H25 -> 237.323 | I16: =I25 -> 2.208 | J16: =J25 -> 369.849 | K16: =K25 -> 2.208 | L16: =L25 -> 237.323 | ... N16: =N25 -> 237.323
B17: ИТОГО ТОиР → «Данные по годам» | C17: тыс.вал/г | E17: =E12+E13+E14+E15+E16 -> 299.336 | F17: =F12+F13+F14+F15+F16 -> 629.573 | G17: =G12+G13+G14+G15+G16 -> 1881.204 | H17: =H12+H13+H14+H15+H16 -> 629.573 | I17: =I12+I13+I14+I15+I16 -> 299.336 | J17: =J12+J13+J14+J15+J16 -> 2211.44 | K17: =K12+K13+K14+K15+K16 -> 299.336 | L17: =L12+L13+L14+L15+L16 -> 629.573 | ... N17: =N12+N13+N14+N15+N16 -> 629.573
B18: ВВОД ДАННЫХ ПОСТАВЩИКА ПО ГОДАМ (жёлтое)
B19: Простои на ТО | C19: ч/год | E19: 196 | F19: 196 | G19: 196 | H19: 196 | I19: 196 | J19: 196 | K19: 196 | L19: 196 | M19: 196 | N19: 196
B20: Простои в ремонтах | C20: ч/год | E20: 425 | F20: 690 | G20: 1600 | H20: 690 | I20: 425 | J20: 1800 | K20: 425 | L20: 690 | M20: 425 | N20: 690
B21: Затраты на ТО (ЗЧ+смазочные) | C21: тыс.вал/г | E21: 217.032 | F21: 217.032 | G21: 217.032 | H21: 217.032 | I21: 217.032 | J21: 217.032 | K21: 217.032 | L21: 217.032 | M21: 217.032 | N21: 217.032
B22: Затраты на текущие ремонты | C22: тыс.вал/г | E22: 7.5 | F22: 7.5 | G22: 7.5 | H22: 7.5 | I22: 7.5 | J22: 7.5 | K22: 7.5 | L22: 7.5 | M22: 7.5 | N22: 7.5
B23: Затраты на капитальные/ППР ремонты | C23: тыс.вал/г | E23: 22.18 | F23: 117.302 | G23: 1471.522 | H23: 117.302 | I23: 22.18 | J23: 1566.643 | K23: 22.18 | L23: 117.302 | M23: 22.18 | N23: 117.302
B24: Сервис (трудозатраты) — ТО | C24: тыс.вал/г | E24: 50.416 | F24: 50.416 | G24: 50.416 | H24: 50.416 | I24: 50.416 | J24: 50.416 | K24: 50.416 | L24: 50.416 | M24: 50.416 | N24: 50.416
B25: Сервис (трудозатраты) — ремонты | C25: тыс.вал/г | E25: 2.208 | F25: 237.323 | G25: 134.734 | H25: 237.323 | I25: 2.208 | J25: 369.849 | K25: 2.208 | L25: 237.323 | M25: 2.208 | N25: 237.323
B27: Строки 18–24 — ввод (жёлтое): простои и затраты ТОиР по годам, в валюте (см. «Валюта затрат ТОиР»). Пересчёт в рубли — в «Денежном потоке» по курсу с листа «Параметры». Данные примера — «в расчёте» из 000_БСЛ-2027 (карьер «Сухой Лог»). «Рваный» график капремонтов по годам учитывается дисконтированием.

Sheet Поставщик 5
B1: ДАННЫЕ ПОСТАВЩИКА — ВАРИАНТ 5 (ТО и Ремонты ПО ГОДАМ)
B2: Жёлтое — ввод (данные поставщика/расчёта). Зелёное — авто; сводка тянется в «Данные по годам».
B4: Автосамосвал: | E4: ='Ввод данных'!H7 -> БелАЗ 7531 (ГПФК)
B5: Валюта затрат ТОиР: | D5: USD
B6: Показатель | C6: Ед. | E6: год 1 | F6: год 2 | G6: год 3 | H6: год 4 | I6: год 5 | J6: год 6 | K6: год 7 | L6: год 8 | M6: год 9 | N6: год 10
B7: СВОДКА ПО ГОДАМ (зелёное — авто; тянется в расчёт)
B8: Простои на ТО | C8: ч/год | E8: =E19 -> 249.395 | F8: =F19 -> 238.375 | G8: =G19 -> 238.375 | H8: =H19 -> 238.375 | I8: =I19 -> 238.375 | J8: =J19 -> 238.375 | K8: =K19 -> 238.375 | L8: =L19 -> 238.375 | ... N8: =N19 -> 238.375
B9: Простои в ремонтах | C9: ч/год | E9: =E20 -> 135 | F9: =F20 -> 341 | G9: =G20 -> 417.667 | H9: =H20 -> 588 | I9: =I20 -> 402 | J9: =J20 -> 680.333 | K9: =K20 -> 549 | L9: =L20 -> 487 | ... N9: =N20 -> 842.333
B10: Ежесменный осмотр (20 мин/смену), справочно | C10: ч/год | E10: =('Параметры'!C26-E8-E9)/'Параметры'!C27*20/60 -> 232.65569 | F10: =('Параметры'!C26-F8-F9)/'Параметры'!C27*20/60 -> 227.23958 | G10: =('Параметры'!C26-G8-G9)/'Параметры'!C27*20/60 -> 225.10994 | H10: =('Параметры'!C26-H8-H9)/'Параметры'!C27*20/60 -> 220.37847 | I10: =('Параметры'!C26-I8-I9)/'Параметры'!C27*20/60 -> 225.54514 | J10: =('Параметры'!C26-J8-J9)/'Параметры'!C27*20/60 -> 217.81367 | K10: =('Параметры'!C26-K8-K9)/'Параметры'!C27*20/60 -> 221.46181 | L10: =('Параметры'!C26-L8-L9)/'Параметры'!C27*20/60 -> 223.18403 | M10: =('Параметры'!C26-M8-M9)/'Параметры'!C27*20/60 -> 214.68403 | N10: =('Параметры'!C26-N8-N9)/'Параметры'!C27*20/60 -> 213.31367
B11: КТГ (техготовность) → «Данные по годам» | C11: коэф. | E11: 0.9083 | F11: 0.8858 | G11: 0.8646 | H11: 0.8748 | I11: 0.8813 | J11: 0.8464 | K11: 0.8971 | L11: 0.8546 | M11: 0.842 | N11: 0.8611
B12: Затраты на ТО (ЗЧ+смазочные) | C12: тыс.вал/г | E12: =E21 -> 62.265 | F12: =F21 -> 51.1 | G12: =G21 -> 51.1 | H12: =H21 -> 51.1 | I12: =I21 -> 51.1 | J12: =J21 -> 51.1 | K12: =K21 -> 51.1 | L12: =L21 -> 51.1 | ... N12: =N21 -> 51.1
B13: Затраты на текущие ремонты | C13: тыс.вал/г | E13: =E22 -> 16.5 | F13: =F22 -> 183.7 | G13: =G22 -> 158.5 | H13: =H22 -> 50.7 | I13: =I22 -> 163.5 | J13: =J22 -> 188.7 | K13: =K22 -> 35.5 | L13: =L22 -> 198.7 | ... N13: =N22 -> 70.7
B14: Затраты на капитальные/ППР ремонты | C14: тыс.вал/г | E14: =E23 -> 0 | F14: =F23 -> 0 | G14: =G23 -> 267.4 | H14: =H23 -> 530 | I14: =I23 -> 327 | J14: =J23 -> 338.2 | K14: =K23 -> 14.2 | L14: =L23 -> 490 | ... N14: =N23 -> 0
B15: Сервис (трудозатраты) — ТО | C15: тыс.вал/г | E15: =E24 -> 60.181 | F15: =F24 -> 59.257 | G15: =G24 -> 59.257 | H15: =H24 -> 59.257 | I15: =I24 -> 59.257 | J15: =J24 -> 59.257 | K15: =K24 -> 59.257 | L15: =L24 -> 59.257 | ... N15: =N24 -> 59.257
B16: Сервис (трудозатраты) — ремонты | C16: тыс.вал/г | E16: =E25 -> 9.101 | F16: =F25 -> 23.544 | G16: =G25 -> 35.811 | H16: =H25 -> 35.949 | I16: =I25 -> 30.766 | J16: =J25 -> 51.362 | K16: =K25 -> 20.438 | L16: =L25 -> 48.137 | ... N16: =N25 -> 50.452
B17: ИТОГО ТОиР → «Данные по годам» | C17: тыс.вал/г | E17: =E12+E13+E14+E15+E16 -> 148.047 | F17: =F12+F13+F14+F15+F16 -> 317.601 | G17: =G12+G13+G14+G15+G16 -> 572.068 | H17: =H12+H13+H14+H15+H16 -> 727.006 | I17: =I12+I13+I14+I15+I16 -> 631.623 | J17: =J12+J13+J14+J15+J16 -> 688.619 | K17: =K12+K13+K14+K15+K16 -> 180.495 | L17: =L12+L13+L14+L15+L16 -> 847.194 | ... N17: =N12+N13+N14+N15+N16 -> 231.509
B18: ВВОД ДАННЫХ ПОСТАВЩИКА ПО ГОДАМ (жёлтое)
B19: Простои на ТО | C19: ч/год | E19: 249.395 | F19: 238.375 | G19: 238.375 | H19: 238.375 | I19: 238.375 | J19: 238.375 | K19: 238.375 | L19: 238.375 | M19: 238.375 | N19: 238.375
B20: Простои в ремонтах | C20: ч/год | E20: 135 | F20: 341 | G20: 417.667 | H20: 588 | I20: 402 | J20: 680.333 | K20: 549 | L20: 487 | M20: 793 | N20: 842.333
B21: Затраты на ТО (ЗЧ+смазочные) | C21: тыс.вал/г | E21: 62.265 | F21: 51.1 | G21: 51.1 | H21: 51.1 | I21: 51.1 | J21: 51.1 | K21: 51.1 | L21: 51.1 | M21: 51.1 | N21: 51.1
B22: Затраты на текущие ремонты | C22: тыс.вал/г | E22: 16.5 | F22: 183.7 | G22: 158.5 | H22: 50.7 | I22: 163.5 | J22: 188.7 | K22: 35.5 | L22: 198.7 | M22: 173.5 | N22: 70.7
B23: Затраты на капитальные/ППР ремонты | C23: тыс.вал/г | E23: 0 | F23: 0 | G23: 267.4 | H23: 530 | I23: 327 | J23: 338.2 | K23: 14.2 | L23: 490 | M23: 620.2 | N23: 0
B24: Сервис (трудозатраты) — ТО | C24: тыс.вал/г | E24: 60.181 | F24: 59.257 | G24: 59.257 | H24: 59.257 | I24: 59.257 | J24: 59.257 | K24: 59.257 | L24: 59.257 | M24: 59.257 | N24: 59.257
B25: Сервис (трудозатраты) — ремонты | C25: тыс.вал/г | E25: 9.101 | F25: 23.544 | G25: 35.811 | H25: 35.949 | I25: 30.766 | J25: 51.362 | K25: 20.438 | L25: 48.137 | M25: 57.693 | N25: 50.452
B27: Строки 18–24 — ввод (жёлтое): простои и затраты ТОиР по годам, в валюте (см. «Валюта затрат ТОиР»). Пересчёт в рубли — в «Денежном потоке» по курсу с листа «Параметры». Данные примера — «в расчёте» из 000_БСЛ-2027 (карьер «Сухой Лог»). «Рваный» график капремонтов по годам учитывается дисконтированием.

Sheet Поставщик 6
B1: ДАННЫЕ ПОСТАВЩИКА — ВАРИАНТ 6 (ТО и Ремонты ПО ГОДАМ)
B2: Жёлтое — ввод (данные поставщика/расчёта). Зелёное — авто; сводка тянется в «Данные по годам».
B4: Автосамосвал: | E4: ='Ввод данных'!I7 -> БелАЗ 7531 (БТЛ)
B5: Валюта затрат ТОиР: | D5: USD
B6: Показатель | C6: Ед. | E6: год 1 | F6: год 2 | G6: год 3 | H6: год 4 | I6: год 5 | J6: год 6 | K6: год 7 | L6: год 8 | M6: год 9 | N6: год 10
B7: СВОДКА ПО ГОДАМ (зелёное — авто; тянется в расчёт)
B8: Простои на ТО | C8: ч/год | E8: =E19 -> 249.395 | F8: =F19 -> 238.375 | G8: =G19 -> 238.375 | H8: =H19 -> 238.375 | I8: =I19 -> 238.375 | J8: =J19 -> 238.375 | K8: =K19 -> 238.375 | L8: =L19 -> 238.375 | ... N8: =N19 -> 238.375
B9: Простои в ремонтах | C9: ч/год | E9: =E20 -> 135 | F9: =F20 -> 341 | G9: =G20 -> 417.667 | H9: =H20 -> 588 | I9: =I20 -> 402 | J9: =J20 -> 680.333 | K9: =K20 -> 549 | L9: =L20 -> 487 | ... N9: =N20 -> 842.333
B10: Ежесменный осмотр (20 мин/смену), справочно | C10: ч/год | E10: =('Параметры'!C26-E8-E9)/'Параметры'!C27*20/60 -> 232.65569 | F10: =('Параметры'!C26-F8-F9)/'Параметры'!C27*20/60 -> 227.23958 | G10: =('Параметры'!C26-G8-G9)/'Параметры'!C27*20/60 -> 225.10994 | H10: =('Параметры'!C26-H8-H9)/'Параметры'!C27*20/60 -> 220.37847 | I10: =('Параметры'!C26-I8-I9)/'Параметры'!C27*20/60 -> 225.54514 | J10: =('Параметры'!C26-J8-J9)/'Параметры'!C27*20/60 -> 217.81367 | K10: =('Параметры'!C26-K8-K9)/'Параметры'!C27*20/60 -> 221.46181 | L10: =('Параметры'!C26-L8-L9)/'Параметры'!C27*20/60 -> 223.18403 | M10: =('Параметры'!C26-M8-M9)/'Параметры'!C27*20/60 -> 214.68403 | N10: =('Параметры'!C26-N8-N9)/'Параметры'!C27*20/60 -> 213.31367
B11: КТГ (техготовность) → «Данные по годам» | C11: коэф. | E11: 0.93 | F11: 0.908 | G11: 0.899 | H11: 0.881 | I11: 0.901 | J11: 0.87 | K11: 0.851 | L11: 0.892 | M11: 0.858 | N11: 0.852
B12: Затраты на ТО (ЗЧ+смазочные) | C12: тыс.вал/г | E12: =E21 -> 49.6 | F12: =F21 -> 41.135 | G12: =G21 -> 41.135 | H12: =H21 -> 41.135 | I12: =I21 -> 41.135 | J12: =J21 -> 41.135 | K12: =K21 -> 41.135 | L12: =L21 -> 41.135 | ... N12: =N21 -> 41.135
B13: Затраты на текущие ремонты | C13: тыс.вал/г | E13: =E22 -> 15.011 | F13: =F22 -> 77.065 | G13: =G22 -> 50.721 | H13: =H22 -> 89.861 | I13: =I22 -> 60.141 | J13: =J22 -> 102.874 | K13: =K22 -> 80.547 | L13: =L22 -> 64.172 | ... N13: =N22 -> 90.366
B14: Затраты на капитальные/ППР ремонты | C14: тыс.вал/г | E14: =E23 -> 0 | F14: =F23 -> 0 | G14: =G23 -> 410.928 | H14: =H23 -> 652.532 | I14: =I23 -> 158.405 | J14: =J23 -> 339.483 | K14: =K23 -> 71.445 | L14: =L23 -> 721.657 | ... N14: =N23 -> 0
B15: Сервис (трудозатраты) — ТО | C15: тыс.вал/г | E15: =E24 -> 48.632 | F15: =F24 -> 46.483 | G15: =G24 -> 46.483 | H15: =H24 -> 46.483 | I15: =I24 -> 46.483 | J15: =J24 -> 46.483 | K15: =K24 -> 46.483 | L15: =L24 -> 46.483 | ... N15: =N24 -> 46.483
B16: Сервис (трудозатраты) — ремонты | C16: тыс.вал/г | E16: =E25 -> 17.55 | F16: =F25 -> 44.33 | G16: =G25 -> 66.17 | H16: =H25 -> 81.51 | I16: =I25 -> 58.5 | J16: =J25 -> 106.99 | K16: =K25 -> 83.85 | L16: =L25 -> 98.28 | ... N16: =N25 -> 157.17
B17: ИТОГО ТОиР → «Данные по годам» | C17: тыс.вал/г | E17: =E12+E13+E14+E15+E16 -> 130.793 | F17: =F12+F13+F14+F15+F16 -> 209.013 | G17: =G12+G13+G14+G15+G16 -> 615.437 | H17: =H12+H13+H14+H15+H16 -> 911.521 | I17: =I12+I13+I14+I15+I16 -> 364.664 | J17: =J12+J13+J14+J15+J16 -> 636.965 | K17: =K12+K13+K14+K15+K16 -> 323.46 | L17: =L12+L13+L14+L15+L16 -> 971.727 | ... N17: =N12+N13+N14+N15+N16 -> 335.154
B18: ВВОД ДАННЫХ ПОСТАВЩИКА ПО ГОДАМ (жёлтое)
B19: Простои на ТО | C19: ч/год | E19: 249.395 | F19: 238.375 | G19: 238.375 | H19: 238.375 | I19: 238.375 | J19: 238.375 | K19: 238.375 | L19: 238.375 | M19: 238.375 | N19: 238.375
B20: Простои в ремонтах | C20: ч/год | E20: 135 | F20: 341 | G20: 417.667 | H20: 588 | I20: 402 | J20: 680.333 | K20: 549 | L20: 487 | M20: 793 | N20: 842.333
B21: Затраты на ТО (ЗЧ+смазочные) | C21: тыс.вал/г | E21: 49.6 | F21: 41.135 | G21: 41.135 | H21: 41.135 | I21: 41.135 | J21: 41.135 | K21: 41.135 | L21: 41.135 | M21: 41.135 | N21: 41.135
B22: Затраты на текущие ремонты | C22: тыс.вал/г | E22: 15.011 | F22: 77.065 | G22: 50.721 | H22: 89.861 | I22: 60.141 | J22: 102.874 | K22: 80.547 | L22: 64.172 | M22: 74.323 | N22: 90.366
B23: Затраты на капитальные/ППР ремонты | C23: тыс.вал/г | E23: 0 | F23: 0 | G23: 410.928 | H23: 652.532 | I23: 158.405 | J23: 339.483 | K23: 71.445 | L23: 721.657 | M23: 497.888 | N23: 0
B24: Сервис (трудозатраты) — ТО | C24: тыс.вал/г | E24: 48.632 | F24: 46.483 | G24: 46.483 | H24: 46.483 | I24: 46.483 | J24: 46.483 | K24: 46.483 | L24: 46.483 | M24: 46.483 | N24: 46.483
B25: Сервис (трудозатраты) — ремонты | C25: тыс.вал/г | E25: 17.55 | F25: 44.33 | G25: 66.17 | H25: 81.51 | I25: 58.5 | J25: 106.99 | K25: 83.85 | L25: 98.28 | M25: 145.47 | N25: 157.17
B27: Строки 18–24 — ввод (жёлтое): простои и затраты ТОиР по годам, в валюте (см. «Валюта затрат ТОиР»). Пересчёт в рубли — в «Денежном потоке» по курсу с листа «Параметры». Данные примера — «в расчёте» из 000_БСЛ-2027 (карьер «Сухой Лог»). «Рваный» график капремонтов по годам учитывается дисконтированием.

Sheet Данные по годам
B1: ПОГОДОВЫЕ ДАННЫЕ ЭКСПЛУАТАЦИИ (СВОДКА)
B2: Автоматически из листов «Поставщик 1…6». Правьте данные там, здесь — только просмотр.
B4: Значения ТЯНУТСЯ из листов «Поставщик 1…6» (КТГ и ИТОГО ТОиР — авто). Чтобы изменить данные по машине — откройте её лист и правьте жёлтые ячейки; сводка и расчёт обновятся сами.
B5: Показатель | C5: Ед. | D5: Валюта | E5: год 1 | F5: год 2 | G5: год 3 | H5: год 4 | I5: год 5 | J5: год 6 | K5: год 7 | L5: год 8 | M5: год 9 | N5: год 10
B6: ="Вариант 1: "&'Ввод данных'!D7 -> Вариант 1: NHL NTE 240
B7: КТГ (техготовность) | C7: коэф. | E7: ='Поставщик 1'!E11 -> 0.9376 | F7: ='Поставщик 1'!F11 -> 0.9304 | G7: ='Поставщик 1'!G11 -> 0.9209 | H7: ='Поставщик 1'!H11 -> 0.9084 | I7: ='Поставщик 1'!I11 -> 0.9333 | J7: ='Поставщик 1'!J11 -> 0.9217 | K7: ='Поставщик 1'!K11 -> 0.9313 | L7: ='Поставщик 1'!L11 -> 0.9111 | ... N7: ='Поставщик 1'!N11 -> 0.9322
B8: Затраты на ТОиР и сервис | C8: тыс.вал/г | D8: ='Поставщик 1'!$D$5 -> CNY | E8: ='Поставщик 1'!E17 -> 470.705 | F8: ='Поставщик 1'!F17 -> 654.097 | G8: ='Поставщик 1'!G17 -> 3875.408 | H8: ='Поставщик 1'!H17 -> 2060.956 | I8: ='Поставщик 1'!I17 -> 687.317 | J8: ='Поставщик 1'!J17 -> 3784.574 | K8: ='Поставщик 1'!K17 -> 637.163 | L8: ='Поставщик 1'!L17 -> 2184.222 | ... N8: ='Поставщик 1'!N17 -> 541.468
B9: ="Вариант 2: "&'Ввод данных'!E7 -> Вариант 2: Estar ESDE240 (ГПБ К)
B10: КТГ (техготовность) | C10: коэф. | E10: ='Поставщик 2'!E11 -> 0.9116 | F10: ='Поставщик 2'!F11 -> 0.8956 | G10: ='Поставщик 2'!G11 -> 0.8493 | H10: ='Поставщик 2'!H11 -> 0.806 | I10: ='Поставщик 2'!I11 -> 0.899 | J10: ='Поставщик 2'!J11 -> 0.8221 | K10: ='Поставщик 2'!K11 -> 0.8886 | L10: ='Поставщик 2'!L11 -> 0.8107 | ... N10: ='Поставщик 2'!N11 -> 0.834
B11: Затраты на ТОиР и сервис | C11: тыс.вал/г | D11: ='Поставщик 2'!$D$5 -> USD | E11: ='Поставщик 2'!E17 -> 180.53 | F11: ='Поставщик 2'!F17 -> 276.729 | G11: ='Поставщик 2'!G17 -> 928.14 | H11: ='Поставщик 2'!H17 -> 2751.339 | I11: ='Поставщик 2'!I17 -> 184.233 | J11: ='Поставщик 2'!J17 -> 1024.339 | K11: ='Поставщик 2'!K17 -> 180.53 | L11: ='Поставщик 2'!L17 -> 2751.339 | ... N11: ='Поставщик 2'!N17 -> 180.53
B12: ="Вариант 3: "&'Ввод данных'!F7 -> Вариант 3: SANY SET240S
B13: КТГ (техготовность) | C13: коэф. | E13: ='Поставщик 3'!E11 -> 0.9357 | F13: ='Поставщик 3'!F11 -> 0.9026 | G13: ='Поставщик 3'!G11 -> 0.8659 | H13: ='Поставщик 3'!H11 -> 0.904 | I13: ='Поставщик 3'!I11 -> 0.85 | J13: ='Поставщик 3'!J11 -> 0.904 | K13: ='Поставщик 3'!K11 -> 0.8659 | L13: ='Поставщик 3'!L11 -> 0.904 | ... N13: ='Поставщик 3'!N11 -> 0.885
B14: Затраты на ТОиР и сервис | C14: тыс.вал/г | D14: ='Поставщик 3'!$D$5 -> USD | E14: ='Поставщик 3'!E17 -> 135.348 | F14: ='Поставщик 3'!F17 -> 211.267 | G14: ='Поставщик 3'!G17 -> 597.961 | H14: ='Поставщик 3'!H17 -> 305.142 | I14: ='Поставщик 3'!I17 -> 973.937 | J14: ='Поставщик 3'!J17 -> 741.259 | K14: ='Поставщик 3'!K17 -> 267.376 | L14: ='Поставщик 3'!L17 -> 268.933 | ... N14: ='Поставщик 3'!N17 -> 196.001
B15: ="Вариант 4: "&'Ввод данных'!G7 -> Вариант 4: TZCO TZE240
B16: КТГ (техготовность) | C16: коэф. | E16: ='Поставщик 4'!E11 -> 0.9096 | F16: ='Поставщик 4'!F11 -> 0.8842 | G16: ='Поставщик 4'!G11 -> 0.774 | H16: ='Поставщик 4'!H11 -> 0.8842 | I16: ='Поставщик 4'!I11 -> 0.9096 | J16: ='Поставщик 4'!J11 -> 0.748 | K16: ='Поставщик 4'!K11 -> 0.9096 | L16: ='Поставщик 4'!L11 -> 0.8842 | ... N16: ='Поставщик 4'!N11 -> 0.8842
B17: Затраты на ТОиР и сервис | C17: тыс.вал/г | D17: ='Поставщик 4'!$D$5 -> USD | E17: ='Поставщик 4'!E17 -> 299.336 | F17: ='Поставщик 4'!F17 -> 629.573 | G17: ='Поставщик 4'!G17 -> 1881.204 | H17: ='Поставщик 4'!H17 -> 629.573 | I17: ='Поставщик 4'!I17 -> 299.336 | J17: ='Поставщик 4'!J17 -> 2211.44 | K17: ='Поставщик 4'!K17 -> 299.336 | L17: ='Поставщик 4'!L17 -> 629.573 | ... N17: ='Поставщик 4'!N17 -> 629.573
B18: ="Вариант 5: "&'Ввод данных'!H7 -> Вариант 5: БелАЗ 7531 (ГПФК)
B19: КТГ (техготовность) | C19: коэф. | E19: ='Поставщик 5'!E11 -> 0.9083 | F19: ='Поставщик 5'!F11 -> 0.8858 | G19: ='Поставщик 5'!G11 -> 0.8646 | H19: ='Поставщик 5'!H11 -> 0.8748 | I19: ='Поставщик 5'!I11 -> 0.8813 | J19: ='Поставщик 5'!J11 -> 0.8464 | K19: ='Поставщик 5'!K11 -> 0.8971 | L19: ='Поставщик 5'!L11 -> 0.8546 | ... N19: ='Поставщик 5'!N11 -> 0.8611
B20: Затраты на ТОиР и сервис | C20: тыс.вал/г | D20: ='Поставщик 5'!$D$5 -> USD | E20: ='Поставщик 5'!E17 -> 148.047 | F20: ='Поставщик 5'!F17 -> 317.601 | G20: ='Поставщик 5'!G17 -> 572.068 | H20: ='Поставщик 5'!H17 -> 727.006 | I20: ='Поставщик 5'!I17 -> 631.623 | J20: ='Поставщик 5'!J17 -> 688.619 | K20: ='Поставщик 5'!K17 -> 180.495 | L20: ='Поставщик 5'!L17 -> 847.194 | ... N20: ='Поставщик 5'!N17 -> 231.509
B21: ="Вариант 6: "&'Ввод данных'!I7 -> Вариант 6: БелАЗ 7531 (БТЛ)
B22: КТГ (техготовность) | C22: коэф. | E22: ='Поставщик 6'!E11 -> 0.93 | F22: ='Поставщик 6'!F11 -> 0.908 | G22: ='Поставщик 6'!G11 -> 0.899 | H22: ='Поставщик 6'!H11 -> 0.881 | I22: ='Поставщик 6'!I11 -> 0.901 | J22: ='Поставщик 6'!J11 -> 0.87 | K22: ='Поставщик 6'!K11 -> 0.851 | L22: ='Поставщик 6'!L11 -> 0.892 | ... N22: ='Поставщик 6'!N11 -> 0.852
B23: Затраты на ТОиР и сервис | C23: тыс.вал/г | D23: ='Поставщик 6'!$D$5 -> USD | E23: ='Поставщик 6'!E17 -> 130.793 | F23: ='Поставщик 6'!F17 -> 209.013 | G23: ='Поставщик 6'!G17 -> 615.437 | H23: ='Поставщик 6'!H17 -> 911.521 | I23: ='Поставщик 6'!I17 -> 364.664 | J23: ='Поставщик 6'!J17 -> 636.965 | K23: ='Поставщик 6'!K17 -> 323.46 | L23: ='Поставщик 6'!L17 -> 971.727 | ... N23: ='Поставщик 6'!N17 -> 335.154

Sheet Производительность
B1: РАСЧЁТ ПРОИЗВОДИТЕЛЬНОСТИ (транспортный цикл)
B2: Часовая производительность (т/эфф.час) — по времени рейса; полная погодовая таблица — с КТГ по годам.
B4: Показатель | C4: Ед. | D4: ='Ввод данных'!D7 -> NHL NTE 240 | E4: ='Ввод данных'!E7 -> Estar ESDE240 (ГПБ К) | F4: ='Ввод данных'!F7 -> SANY SET240S | G4: ='Ввод данных'!G7 -> TZCO TZE240 | H4: ='Ввод данных'!H7 -> БелАЗ 7531 (ГПФК) | I4: ='Ввод данных'!I7 -> БелАЗ 7531 (БТЛ)
B5: Стоимость в рублях | C5: тыс.руб | D5: ='Ввод данных'!D11*IF('Ввод данных'!D12="CNY",'Параметры'!C20,IF('Ввод данных'!D12="USD",'Параметры'!C21,IF('Ввод данных'!D12="EUR",'Параметры'!C22,1)))+'Ввод данных'!D13 -> 255404 | E5: ='Ввод данных'!E11*IF('Ввод данных'!E12="CNY",'Параметры'!C20,IF('Ввод данных'!E12="USD",'Параметры'!C21,IF('Ввод данных'!E12="EUR",'Параметры'!C22,1)))+'Ввод данных'!E13 -> 263335.8 | F5: ='Ввод данных'!F11*IF('Ввод данных'!F12="CNY",'Параметры'!C20,IF('Ввод данных'!F12="USD",'Параметры'!C21,IF('Ввод данных'!F12="EUR",'Параметры'!C22,1)))+'Ввод данных'!F13 -> 253930.95 | G5: ='Ввод данных'!G11*IF('Ввод данных'!G12="CNY",'Параметры'!C20,IF('Ввод данных'!G12="USD",'Параметры'!C21,IF('Ввод данных'!G12="EUR",'Параметры'!C22,1)))+'Ввод данных'!G13 -> 253930.95 | H5: ='Ввод данных'!H11*IF('Ввод данных'!H12="CNY",'Параметры'!C20,IF('Ввод данных'!H12="USD",'Параметры'!C21,IF('Ввод данных'!H12="EUR",'Параметры'!C22,1)))+'Ввод данных'!H13 -> 300000 | I5: ='Ввод данных'!I11*IF('Ввод данных'!I12="CNY",'Параметры'!C20,IF('Ввод данных'!I12="USD",'Параметры'!C21,IF('Ввод данных'!I12="EUR",'Параметры'!C22,1)))+'Ввод данных'!I13 -> 290000
B6: Время движения (гружёный+порожний) | C6: мин | D6: =2*'Параметры'!C28/'Параметры'!C29*60 -> 16.240071 | E6: =2*'Параметры'!C28/'Параметры'!C29*60 -> 16.240071 | F6: =2*'Параметры'!C28/'Параметры'!C29*60 -> 16.240071 | G6: =2*'Параметры'!C28/'Параметры'!C29*60 -> 16.240071 | H6: =2*'Параметры'!C28/'Параметры'!C29*60 -> 16.240071 | I6: =2*'Параметры'!C28/'Параметры'!C29*60 -> 16.240071
B7: Время рейса | C7: мин | D7: ='Параметры'!C31+D6 -> 24.640071 | E7: ='Параметры'!C31+E6 -> 24.640071 | F7: ='Параметры'!C31+F6 -> 24.640071 | G7: ='Параметры'!C31+G6 -> 24.640071 | H7: ='Параметры'!C31+H6 -> 24.640071 | I7: ='Параметры'!C31+I6 -> 24.640071
B8: Рейсов в час | C8: рейс/час | D8: =60/D7 -> 2.4350579 | E8: =60/E7 -> 2.4350579 | F8: =60/F7 -> 2.4350579 | G8: =60/G7 -> 2.4350579 | H8: =60/H7 -> 2.4350579 | I8: =60/I7 -> 2.4350579
B9: Часовая производительность | C9: т/эфф.час | D9: =D8*'Ввод данных'!D16*'Параметры'!C30 -> 545.66448 | E9: =E8*'Ввод данных'!E16*'Параметры'!C30 -> 506.3613 | F9: =F8*'Ввод данных'!F16*'Параметры'!C30 -> 518.26628 | G9: =G8*'Ввод данных'!G16*'Параметры'!C30 -> 531.77135 | H9: =H8*'Ввод данных'!H16*'Параметры'!C30 -> 553.32965 | I9: =I8*'Ввод данных'!I16*'Параметры'!C30 -> 553.32965
B10: КИО (1-й год) | C10: коэф. | D10: ='Данные по годам'!E7*(1-102.38/(60*'Параметры'!C27)) -> 0.80427849 | E10: ='Данные по годам'!E10*(1-102.38/(60*'Параметры'!C27)) -> 0.78197554 | F10: ='Данные по годам'!E13*(1-102.38/(60*'Параметры'!C27)) -> 0.80264866 | G10: ='Данные по годам'!E16*(1-102.38/(60*'Параметры'!C27)) -> 0.78025993 | H10: ='Данные по годам'!E19*(1-102.38/(60*'Параметры'!C27)) -> 0.77914479 | I10: ='Данные по годам'!E22*(1-102.38/(60*'Параметры'!C27)) -> 0.79775917
B12: ПОГОДОВАЯ ПРОИЗВОДИТЕЛЬНОСТЬ (КТГ по годам из «Данные по годам»; часовая производительность — из цикла выше)
B13: Показатель | C13: Ед. | E13: год 1 | F13: год 2 | G13: год 3 | H13: год 4 | I13: год 5 | J13: год 6 | K13: год 7 | L13: год 8 | M13: год 9 | N13: год 10
B14: ="Вариант 1: "&'Ввод данных'!D7 -> Вариант 1: NHL NTE 240
B15: КТГ (по годам) | C15: коэф. | E15: ='Данные по годам'!E7 -> 0.9376 | F15: ='Данные по годам'!F7 -> 0.9304 | G15: ='Данные по годам'!G7 -> 0.9209 | H15: ='Данные по годам'!H7 -> 0.9084 | I15: ='Данные по годам'!I7 -> 0.9333 | J15: ='Данные по годам'!J7 -> 0.9217 | K15: ='Данные по годам'!K7 -> 0.9313 | L15: ='Данные по годам'!L7 -> 0.9111 | ... N15: ='Данные по годам'!N7 -> 0.9322
B16: КИО | C16: коэф. | E16: =E15*(1-102.38/(60*'Параметры'!C27)) -> 0.80427849 | F16: =F15*(1-102.38/(60*'Параметры'!C27)) -> 0.79810229 | G16: =G15*(1-102.38/(60*'Параметры'!C27)) -> 0.78995314 | H16: =H15*(1-102.38/(60*'Параметры'!C27)) -> 0.77923057 | I16: =I15*(1-102.38/(60*'Параметры'!C27)) -> 0.80058993 | J16: =J15*(1-102.38/(60*'Параметры'!C27)) -> 0.79063938 | K16: =K15*(1-102.38/(60*'Параметры'!C27)) -> 0.79887431 | L16: =L15*(1-102.38/(60*'Параметры'!C27)) -> 0.78154664 | M16: =M15*(1-102.38/(60*'Параметры'!C27)) -> 0.78669348 | N16: =N15*(1-102.38/(60*'Параметры'!C27)) -> 0.79964634
B17: Эффективное время | C17: час/год | E17: ='Параметры'!C26*E16 -> 7045.4796 | F17: ='Параметры'!C26*F16 -> 6991.3761 | G17: ='Параметры'!C26*G16 -> 6919.9895 | H17: ='Параметры'!C26*H16 -> 6826.0598 | I17: ='Параметры'!C26*I16 -> 7013.1677 | J17: ='Параметры'!C26*J16 -> 6926.001 | K17: ='Параметры'!C26*K16 -> 6998.139 | L17: ='Параметры'!C26*L16 -> 6846.3486 | M17: ='Параметры'!C26*M16 -> 6891.4348 | N17: ='Параметры'!C26*N16 -> 7004.9019
B18: Объём перевозки | C18: тыс.т | E18: ='Производительность'!D9*E17/1000 -> 3844.4679 | F18: ='Производительность'!D9*F17/1000 -> 3814.9456 | G18: ='Производительность'!D9*G17/1000 -> 3775.9924 | H18: ='Производительность'!D9*H17/1000 -> 3724.7383 | I18: ='Производительность'!D9*I17/1000 -> 3826.8365 | J18: ='Производительность'!D9*J17/1000 -> 3779.2727 | K18: ='Производительность'!D9*K17/1000 -> 3818.6359 | L18: ='Производительность'!D9*L17/1000 -> 3735.8092 | M18: ='Производительность'!D9*M17/1000 -> 3760.4112 | N18: ='Производительность'!D9*N17/1000 -> 3822.3262
B19: Грузооборот | C19: тыс.ткм | E19: =E18*'Параметры'!C28 -> 11685.645 | F19: =F18*'Параметры'!C28 -> 11595.909 | G19: =G18*'Параметры'!C28 -> 11477.507 | H19: =H18*'Параметры'!C28 -> 11321.715 | I19: =I18*'Параметры'!C28 -> 11632.052 | J19: =J18*'Параметры'!C28 -> 11487.477 | K19: =K18*'Параметры'!C28 -> 11607.126 | L19: =L18*'Параметры'!C28 -> 11355.366 | M19: =M18*'Параметры'!C28 -> 11430.146 | N19: =N18*'Параметры'!C28 -> 11618.343
B20: Пробег | C20: тыс.км | E20: ='Производительность'!D8*E17*2*'Параметры'!C28/1000 -> 104.29567 | F20: ='Производительность'!D8*F17*2*'Параметры'!C28/1000 -> 103.49477 | G20: ='Производительность'!D8*G17*2*'Параметры'!C28/1000 -> 102.43802 | H20: ='Производительность'!D8*H17*2*'Параметры'!C28/1000 -> 101.04755 | I20: ='Производительность'!D8*I17*2*'Параметры'!C28/1000 -> 103.81735 | J20: ='Производительность'!D8*J17*2*'Параметры'!C28/1000 -> 102.52701 | K20: ='Производительность'!D8*K17*2*'Параметры'!C28/1000 -> 103.59488 | L20: ='Производительность'!D8*L17*2*'Параметры'!C28/1000 -> 101.34789 | M20: ='Производительность'!D8*M17*2*'Параметры'!C28/1000 -> 102.01532 | N20: ='Производительность'!D8*N17*2*'Параметры'!C28/1000 -> 103.69499
B22: ="Вариант 2: "&'Ввод данных'!E7 -> Вариант 2: Estar ESDE240 (ГПБ К)
B23: КТГ (по годам) | C23: коэф. | E23: ='Данные по годам'!E10 -> 0.9116 | F23: ='Данные по годам'!F10 -> 0.8956 | G23: ='Данные по годам'!G10 -> 0.8493 | H23: ='Данные по годам'!H10 -> 0.806 | I23: ='Данные по годам'!I10 -> 0.899 | J23: ='Данные по годам'!J10 -> 0.8221 | K23: ='Данные по годам'!K10 -> 0.8886 | L23: ='Данные по годам'!L10 -> 0.8107 | ... N23: ='Данные по годам'!N10 -> 0.834
B24: КИО | C24: коэф. | E24: =E23*(1-102.38/(60*'Параметры'!C27)) -> 0.78197554 | F24: =F23*(1-102.38/(60*'Параметры'!C27)) -> 0.76825066 | G24: =G23*(1-102.38/(60*'Параметры'!C27)) -> 0.72853426 | H24: =H23*(1-102.38/(60*'Параметры'!C27)) -> 0.69139128 | I24: =I23*(1-102.38/(60*'Параметры'!C27)) -> 0.77116719 | J24: =J23*(1-102.38/(60*'Параметры'!C27)) -> 0.70520195 | K24: =K23*(1-102.38/(60*'Параметры'!C27)) -> 0.76224602 | L24: =L23*(1-102.38/(60*'Параметры'!C27)) -> 0.69542296 | M24: =M23*(1-102.38/(60*'Параметры'!C27)) -> 0.73445312 | N24: =N23*(1-102.38/(60*'Параметры'!C27)) -> 0.71540983
B25: Эффективное время | C25: час/год | E25: ='Параметры'!C26*E24 -> 6850.1058 | F25: ='Параметры'!C26*F24 -> 6729.8757 | G25: ='Параметры'!C26*G24 -> 6381.9601 | H25: ='Параметры'!C26*H24 -> 6056.5876 | I25: ='Параметры'!C26*I24 -> 6755.4246 | J25: ='Параметры'!C26*J24 -> 6177.5691 | K25: ='Параметры'!C26*K24 -> 6677.2751 | L25: ='Параметры'!C26*L24 -> 6091.9052 | M25: ='Параметры'!C26*M24 -> 6433.8093 | N25: ='Параметры'!C26*N24 -> 6266.9901
B26: Объём перевозки | C26: тыс.т | E26: ='Производительность'!E9*E25/1000 -> 3468.6285 | F26: ='Производительность'!E9*F25/1000 -> 3407.7487 | G26: ='Производительность'!E9*G25/1000 -> 3231.5776 | H26: ='Производительность'!E9*H25/1000 -> 3066.8216 | I26: ='Производительность'!E9*I25/1000 -> 3420.6856 | J26: ='Производительность'!E9*J25/1000 -> 3128.0819 | K26: ='Производительность'!E9*K25/1000 -> 3381.1137 | L26: ='Производительность'!E9*L25/1000 -> 3084.705 | M26: ='Производительность'!E9*M25/1000 -> 3257.8321 | N26: ='Производительность'!E9*N25/1000 -> 3173.3613
B27: Грузооборот | C27: тыс.ткм | E27: =E26*'Параметры'!C28 -> 10543.243 | F27: =F26*'Параметры'!C28 -> 10358.193 | G27: =G26*'Параметры'!C28 -> 9822.7034 | H27: =H26*'Параметры'!C28 -> 9321.9109 | I27: =I26*'Параметры'!C28 -> 10397.516 | J27: =J26*'Параметры'!C28 -> 9508.1178 | K27: =K26*'Параметры'!C28 -> 10277.233 | L27: =L26*'Параметры'!C28 -> 9376.2695 | M27: =M26*'Параметры'!C28 -> 9902.5064 | N27: =N26*'Параметры'!C28 -> 9645.749
B28: Пробег | C28: тыс.км | E28: ='Производительность'!E8*E25*2*'Параметры'!C28/1000 -> 101.40351 | F28: ='Производительность'!E8*F25*2*'Параметры'!C28/1000 -> 99.623723 | G28: ='Производительность'!E8*G25*2*'Параметры'!C28/1000 -> 94.473457 | H28: ='Производительность'!E8*H25*2*'Параметры'!C28/1000 -> 89.656901 | I28: ='Производительность'!E8*I25*2*'Параметры'!C28/1000 -> 100.00193 | J28: ='Производительность'!E8*J25*2*'Параметры'!C28/1000 -> 91.447815 | K28: ='Производительность'!E8*K25*2*'Параметры'!C28/1000 -> 98.845065 | L28: ='Производительность'!E8*L25*2*'Параметры'!C28/1000 -> 90.179715 | M28: ='Производительность'!E8*M25*2*'Параметры'!C28/1000 -> 95.240991 | N28: ='Производительность'!E8*N25*2*'Параметры'!C28/1000 -> 92.771533
B30: ="Вариант 3: "&'Ввод данных'!F7 -> Вариант 3: SANY SET240S
B31: КТГ (по годам) | C31: коэф. | E31: ='Данные по годам'!E13 -> 0.9357 | F31: ='Данные по годам'!F13 -> 0.9026 | G31: ='Данные по годам'!G13 -> 0.8659 | H31: ='Данные по годам'!H13 -> 0.904 | I31: ='Данные по годам'!I13 -> 0.85 | J31: ='Данные по годам'!J13 -> 0.904 | K31: ='Данные по годам'!K13 -> 0.8659 | L31: ='Данные по годам'!L13 -> 0.904 | ... N31: ='Данные по годам'!N13 -> 0.885
B32: КИО | C32: коэф. | E32: =E31*(1-102.38/(60*'Параметры'!C27)) -> 0.80264866 | F32: =F31*(1-102.38/(60*'Параметры'!C27)) -> 0.77425529 | G32: =G31*(1-102.38/(60*'Параметры'!C27)) -> 0.74277383 | H32: =H31*(1-102.38/(60*'Параметры'!C27)) -> 0.77545622 | I32: =I31*(1-102.38/(60*'Параметры'!C27)) -> 0.72913472 | J32: =J31*(1-102.38/(60*'Параметры'!C27)) -> 0.77545622 | K32: =K31*(1-102.38/(60*'Параметры'!C27)) -> 0.74277383 | L32: =L31*(1-102.38/(60*'Параметры'!C27)) -> 0.77545622 | M32: =M31*(1-102.38/(60*'Параметры'!C27)) -> 0.72913472 | N32: =N31*(1-102.38/(60*'Параметры'!C27)) -> 0.75915792
B33: Эффективное время | C33: час/год | E33: ='Параметры'!C26*E32 -> 7031.2022 | F33: ='Параметры'!C26*F32 -> 6782.4764 | G33: ='Параметры'!C26*G32 -> 6506.6988 | H33: ='Параметры'!C26*H32 -> 6792.9965 | I33: ='Параметры'!C26*I32 -> 6387.2202 | J33: ='Параметры'!C26*J32 -> 6792.9965 | K33: ='Параметры'!C26*K32 -> 6506.6988 | L33: ='Параметры'!C26*L32 -> 6792.9965 | M33: ='Параметры'!C26*M32 -> 6387.2202 | N33: ='Параметры'!C26*N32 -> 6650.2234
B34: Объём перевозки | C34: тыс.т | E34: ='Производительность'!F9*E33/1000 -> 3644.035 | F34: ='Производительность'!F9*F33/1000 -> 3515.1288 | G34: ='Производительность'!F9*G33/1000 -> 3372.2025 | H34: ='Производительность'!F9*H33/1000 -> 3520.581 | I34: ='Производительность'!F9*I33/1000 -> 3310.2808 | J34: ='Производительность'!F9*J33/1000 -> 3520.581 | K34: ='Производительность'!F9*K33/1000 -> 3372.2025 | L34: ='Производительность'!F9*L33/1000 -> 3520.581 | M34: ='Производительность'!F9*M33/1000 -> 3310.2808 | N34: ='Производительность'!F9*N33/1000 -> 3446.5865
B35: Грузооборот | C35: тыс.ткм | E35: =E34*'Параметры'!C28 -> 11076.409 | F35: =F34*'Параметры'!C28 -> 10684.585 | G35: =G34*'Параметры'!C28 -> 10250.147 | H35: =H34*'Параметры'!C28 -> 10701.158 | I35: =I34*'Параметры'!C28 -> 10061.93 | J35: =J34*'Параметры'!C28 -> 10701.158 | K35: =K34*'Параметры'!C28 -> 10250.147 | L35: =L34*'Параметры'!C28 -> 10701.158 | M35: =M34*'Параметры'!C28 -> 10061.93 | N35: =N34*'Параметры'!C28 -> 10476.244
B36: Пробег | C36: тыс.км | E36: ='Производительность'!F8*E33*2*'Параметры'!C28/1000 -> 104.08432 | F36: ='Производительность'!F8*F33*2*'Параметры'!C28/1000 -> 100.40238 | G36: ='Производительность'!F8*G33*2*'Параметры'!C28/1000 -> 96.319989 | H36: ='Производительность'!F8*H33*2*'Параметры'!C28/1000 -> 100.55811 | I36: ='Производительность'!F8*I33*2*'Параметры'!C28/1000 -> 94.551323 | J36: ='Производительность'!F8*J33*2*'Параметры'!C28/1000 -> 100.55811 | K36: ='Производительность'!F8*K33*2*'Параметры'!C28/1000 -> 96.319989 | L36: ='Производительность'!F8*L33*2*'Параметры'!C28/1000 -> 100.55811 | M36: ='Производительность'!F8*M33*2*'Параметры'!C28/1000 -> 94.551323 | N36: ='Производительность'!F8*N33*2*'Параметры'!C28/1000 -> 98.444613
B38: ="Вариант 4: "&'Ввод данных'!G7 -> Вариант 4: TZCO TZE240
B39: КТГ (по годам) | C39: коэф. | E39: ='Данные по годам'!E16 -> 0.9096 | F39: ='Данные по годам'!F16 -> 0.8842 | G39: ='Данные по годам'!G16 -> 0.774 | H39: ='Данные по годам'!H16 -> 0.8842 | I39: ='Данные по годам'!I16 -> 0.9096 | J39: ='Данные по годам'!J16 -> 0.748 | K39: ='Данные по годам'!K16 -> 0.9096 | L39: ='Данные по годам'!L16 -> 0.8842 | ... N39: ='Данные по годам'!N16 -> 0.8842
B40: КИО | C40: коэф. | E40: =E39*(1-102.38/(60*'Параметры'!C27)) -> 0.78025993 | F40: =F39*(1-102.38/(60*'Параметры'!C27)) -> 0.75847167 | G40: =G39*(1-102.38/(60*'Параметры'!C27)) -> 0.6639415 | H40: =H39*(1-102.38/(60*'Параметры'!C27)) -> 0.75847167 | I40: =I39*(1-102.38/(60*'Параметры'!C27)) -> 0.78025993 | J40: =J39*(1-102.38/(60*'Параметры'!C27)) -> 0.64163856 | K40: =K39*(1-102.38/(60*'Параметры'!C27)) -> 0.78025993 | L40: =L39*(1-102.38/(60*'Параметры'!C27)) -> 0.75847167 | M40: =M39*(1-102.38/(60*'Параметры'!C27)) -> 0.78025993 | N40: =N39*(1-102.38/(60*'Параметры'!C27)) -> 0.75847167
B41: Эффективное время | C41: час/год | E41: ='Параметры'!C26*E40 -> 6835.077 | F41: ='Параметры'!C26*F40 -> 6644.2118 | G41: ='Параметры'!C26*G40 -> 5816.1275 | H41: ='Параметры'!C26*H40 -> 6644.2118 | I41: ='Параметры'!C26*I40 -> 6835.077 | J41: ='Параметры'!C26*J40 -> 5620.7537 | K41: ='Параметры'!C26*K40 -> 6835.077 | L41: ='Параметры'!C26*L40 -> 6644.2118 | M41: ='Параметры'!C26*M40 -> 6835.077 | N41: ='Параметры'!C26*N40 -> 6644.2118
B42: Объём перевозки | C42: тыс.т | E42: ='Производительность'!G9*E41/1000 -> 3634.6981 | F42: ='Производительность'!G9*F41/1000 -> 3533.2015 | G42: ='Производительность'!G9*G41/1000 -> 3092.85 | H42: ='Производительность'!G9*H41/1000 -> 3533.2015 | I42: ='Производительность'!G9*I41/1000 -> 3634.6981 | J42: ='Производительность'!G9*J41/1000 -> 2988.9558 | K42: ='Производительность'!G9*K41/1000 -> 3634.6981 | L42: ='Производительность'!G9*L41/1000 -> 3533.2015 | M42: ='Производительность'!G9*M41/1000 -> 3634.6981 | N42: ='Производительность'!G9*N41/1000 -> 3533.2015
B43: Грузооборот | C43: тыс.ткм | E43: =E42*'Параметры'!C28 -> 11048.028 | F43: =F42*'Параметры'!C28 -> 10739.519 | G43: =G42*'Параметры'!C28 -> 9401.0269 | H43: =H42*'Параметры'!C28 -> 10739.519 | I43: =I42*'Параметры'!C28 -> 11048.028 | J43: =J42*'Параметры'!C28 -> 9085.2301 | K43: =K42*'Параметры'!C28 -> 11048.028 | L43: =L42*'Параметры'!C28 -> 10739.519 | M43: =M42*'Параметры'!C28 -> 11048.028 | N43: =N42*'Параметры'!C28 -> 10739.519
B44: Пробег | C44: тыс.км | E44: ='Производительность'!G8*E41*2*'Параметры'!C28/1000 -> 101.18104 | F44: ='Производительность'!G8*F41*2*'Параметры'!C28/1000 -> 98.355623 | G44: ='Производительность'!G8*G41*2*'Параметры'!C28/1000 -> 86.097322 | H44: ='Производительность'!G8*H41*2*'Параметры'!C28/1000 -> 98.355623 | I44: ='Производительность'!G8*I41*2*'Параметры'!C28/1000 -> 101.18104 | J44: ='Производительность'!G8*J41*2*'Параметры'!C28/1000 -> 83.205164 | K44: ='Производительность'!G8*K41*2*'Параметры'!C28/1000 -> 101.18104 | L44: ='Производительность'!G8*L41*2*'Параметры'!C28/1000 -> 98.355623 | M44: ='Производительность'!G8*M41*2*'Параметры'!C28/1000 -> 101.18104 | N44: ='Производительность'!G8*N41*2*'Параметры'!C28/1000 -> 98.355623
B46: ="Вариант 5: "&'Ввод данных'!H7 -> Вариант 5: БелАЗ 7531 (ГПФК)
B47: КТГ (по годам) | C47: коэф. | E47: ='Данные по годам'!E19 -> 0.9083 | F47: ='Данные по годам'!F19 -> 0.8858 | G47: ='Данные по годам'!G19 -> 0.8646 | H47: ='Данные по годам'!H19 -> 0.8748 | I47: ='Данные по годам'!I19 -> 0.8813 | J47: ='Данные по годам'!J19 -> 0.8464 | K47: ='Данные по годам'!K19 -> 0.8971 | L47: ='Данные по годам'!L19 -> 0.8546 | ... N47: ='Данные по годам'!N19 -> 0.8611
B48: КИО | C48: коэф. | E48: =E47*(1-102.38/(60*'Параметры'!C27)) -> 0.77914479 | F48: =F47*(1-102.38/(60*'Параметры'!C27)) -> 0.75984416 | G48: =G47*(1-102.38/(60*'Параметры'!C27)) -> 0.74165868 | H48: =H47*(1-102.38/(60*'Параметры'!C27)) -> 0.7504083 | I48: =I47*(1-102.38/(60*'Параметры'!C27)) -> 0.75598404 | J48: =J47*(1-102.38/(60*'Параметры'!C27)) -> 0.72604662 | K48: =K47*(1-102.38/(60*'Параметры'!C27)) -> 0.76953736 | L48: =L47*(1-102.38/(60*'Параметры'!C27)) -> 0.73308063 | M48: =M47*(1-102.38/(60*'Параметры'!C27)) -> 0.72227228 | N48: =N47*(1-102.38/(60*'Параметры'!C27)) -> 0.73865636
B49: Эффективное время | C49: час/год | E49: ='Параметры'!C26*E48 -> 6825.3083 | F49: ='Параметры'!C26*F48 -> 6656.2349 | G49: ='Параметры'!C26*G48 -> 6496.9301 | H49: ='Параметры'!C26*H48 -> 6573.5767 | I49: ='Параметры'!C26*I48 -> 6622.4202 | J49: ='Параметры'!C26*J48 -> 6360.1684 | K49: ='Параметры'!C26*K48 -> 6741.1473 | L49: ='Параметры'!C26*L48 -> 6421.7863 | M49: ='Параметры'!C26*M48 -> 6327.1052 | N49: ='Параметры'!C26*N48 -> 6470.6297
B50: Объём перевозки | C50: тыс.т | E50: ='Производительность'!H9*E49/1000 -> 3776.6455 | F50: ='Производительность'!H9*F49/1000 -> 3683.0921 | G50: ='Производительность'!H9*G49/1000 -> 3594.944 | H50: ='Производительность'!H9*H49/1000 -> 3637.3549 | I50: ='Производительность'!H9*I49/1000 -> 3664.3814 | J50: ='Производительность'!H9*J49/1000 -> 3519.2698 | K50: ='Производительность'!H9*K49/1000 -> 3730.0767 | L50: ='Производительность'!H9*L49/1000 -> 3553.3648 | M50: ='Производительность'!H9*M49/1000 -> 3500.9749 | N50: ='Производительность'!H9*N49/1000 -> 3580.3913
B51: Грузооборот | C51: тыс.ткм | E51: =E50*'Параметры'!C28 -> 11479.492 | F51: =F50*'Параметры'!C28 -> 11195.127 | G51: =G50*'Параметры'!C28 -> 10927.192 | H51: =H50*'Параметры'!C28 -> 11056.104 | I51: =I50*'Параметры'!C28 -> 11138.254 | J51: =J50*'Параметры'!C28 -> 10697.172 | K51: =K50*'Параметры'!C28 -> 11337.941 | L51: =L50*'Параметры'!C28 -> 10800.808 | M51: =M50*'Параметры'!C28 -> 10641.563 | N51: =N50*'Параметры'!C28 -> 10882.957
B52: Пробег | C52: тыс.км | E52: ='Производительность'!H8*E49*2*'Параметры'!C28/1000 -> 101.03643 | F52: ='Производительность'!H8*F49*2*'Параметры'!C28/1000 -> 98.533602 | G52: ='Производительность'!H8*G49*2*'Параметры'!C28/1000 -> 96.175381 | H52: ='Производительность'!H8*H49*2*'Параметры'!C28/1000 -> 97.309997 | I52: ='Производительность'!H8*I49*2*'Параметры'!C28/1000 -> 98.033036 | J52: ='Производительность'!H8*J49*2*'Параметры'!C28/1000 -> 94.15087 | K52: ='Производительность'!H8*K49*2*'Параметры'!C28/1000 -> 99.790578 | L52: ='Производительность'!H8*L49*2*'Параметры'!C28/1000 -> 95.063012 | M52: ='Производительность'!H8*M49*2*'Параметры'!C28/1000 -> 93.661428 | N52: ='Производительность'!H8*N49*2*'Параметры'!C28/1000 -> 95.786052
B54: ="Вариант 6: "&'Ввод данных'!I7 -> Вариант 6: БелАЗ 7531 (БТЛ)
B55: КТГ (по годам) | C55: коэф. | E55: ='Данные по годам'!E22 -> 0.93 | F55: ='Данные по годам'!F22 -> 0.908 | G55: ='Данные по годам'!G22 -> 0.899 | H55: ='Данные по годам'!H22 -> 0.881 | I55: ='Данные по годам'!I22 -> 0.901 | J55: ='Данные по годам'!J22 -> 0.87 | K55: ='Данные по годам'!K22 -> 0.851 | L55: ='Данные по годам'!L22 -> 0.892 | ... N55: ='Данные по годам'!N22 -> 0.852
B56: КИО | C56: коэф. | E56: =E55*(1-102.38/(60*'Параметры'!C27)) -> 0.79775917 | F56: =F55*(1-102.38/(60*'Параметры'!C27)) -> 0.77888744 | G56: =G55*(1-102.38/(60*'Параметры'!C27)) -> 0.77116719 | H56: =H55*(1-102.38/(60*'Параметры'!C27)) -> 0.75572669 | I56: =I55*(1-102.38/(60*'Параметры'!C27)) -> 0.77288281 | J56: =J55*(1-102.38/(60*'Параметры'!C27)) -> 0.74629083 | K56: =K55*(1-102.38/(60*'Параметры'!C27)) -> 0.72999253 | L56: =L55*(1-102.38/(60*'Параметры'!C27)) -> 0.76516256 | M56: =M55*(1-102.38/(60*'Параметры'!C27)) -> 0.73599717 | N56: =N55*(1-102.38/(60*'Параметры'!C27)) -> 0.73085033
B57: Эффективное время | C57: час/год | E57: ='Параметры'!C26*E56 -> 6988.3703 | F57: ='Параметры'!C26*F56 -> 6823.054 | G57: ='Параметры'!C26*G56 -> 6755.4246 | H57: ='Параметры'!C26*H56 -> 6620.1658 | I57: ='Параметры'!C26*I56 -> 6770.4534 | J57: ='Параметры'!C26*J56 -> 6537.5077 | K57: ='Параметры'!C26*K56 -> 6394.7345 | L57: ='Параметры'!C26*L56 -> 6702.824 | M57: ='Параметры'!C26*M56 -> 6447.3352 | N57: ='Параметры'!C26*N56 -> 6402.2489
B58: Объём перевозки | C58: тыс.т | E58: ='Производительность'!I9*E57/1000 -> 3866.8725 | F58: ='Производительность'!I9*F57/1000 -> 3775.3981 | G58: ='Производительность'!I9*G57/1000 -> 3737.9767 | H58: ='Производительность'!I9*H57/1000 -> 3663.1341 | I58: ='Производительность'!I9*I57/1000 -> 3746.2926 | J58: ='Производительность'!I9*J57/1000 -> 3617.3968 | K58: ='Производительность'!I9*K57/1000 -> 3538.3962 | L58: ='Производительность'!I9*L57/1000 -> 3708.8713 | M58: ='Производительность'!I9*M57/1000 -> 3567.5017 | N58: ='Производительность'!I9*N57/1000 -> 3542.5542
B59: Грузооборот | C59: тыс.ткм | E59: =E58*'Параметры'!C28 -> 11753.746 | F59: =F58*'Параметры'!C28 -> 11475.7 | G59: =G58*'Параметры'!C28 -> 11361.954 | H59: =H58*'Параметры'!C28 -> 11134.462 | I59: =I58*'Параметры'!C28 -> 11387.231 | J59: =J58*'Параметры'!C28 -> 10995.439 | K59: =K58*'Параметры'!C28 -> 10755.309 | L59: =L58*'Параметры'!C28 -> 11273.485 | M59: =M58*'Параметры'!C28 -> 10843.778 | N59: =N58*'Параметры'!C28 -> 10767.948
B60: Пробег | C60: тыс.км | E60: ='Производительность'!I8*E57*2*'Параметры'!C28/1000 -> 103.45027 | F60: ='Производительность'!I8*F57*2*'Параметры'!C28/1000 -> 101.00306 | G60: ='Производительность'!I8*G57*2*'Параметры'!C28/1000 -> 100.00193 | H60: ='Производительность'!I8*H57*2*'Параметры'!C28/1000 -> 97.999665 | I60: ='Производительность'!I8*I57*2*'Параметры'!C28/1000 -> 100.2244 | J60: ='Производительность'!I8*J57*2*'Параметры'!C28/1000 -> 96.77606 | K60: ='Производительность'!I8*K57*2*'Параметры'!C28/1000 -> 94.66256 | L60: ='Производительность'!I8*L57*2*'Параметры'!C28/1000 -> 99.223271 | M60: ='Производительность'!I8*M57*2*'Параметры'!C28/1000 -> 95.441218 | N60: ='Производительность'!I8*N57*2*'Параметры'!C28/1000 -> 94.773797

Sheet Денежный поток
B1: ПОГОДОВОЙ ДЕНЕЖНЫЙ ПОТОК И АННУИТЕТ
B2: Пост-налоговый жизненный цикл по годам: период 0 — инвестиции, 1–10 — эксплуатация.
B4: Период | D4: 0 | E4: 1 | F4: 2 | G4: 3 | H4: 4 | I4: 5 | J4: 6 | K4: 7 | L4: 8 | M4: 9 | N4: 10
B5: Календарный год | D5: 2027 | E5: 2028 | F5: 2029 | G5: 2030 | H5: 2031 | I5: 2032 | J5: 2033 | K5: 2034 | L5: 2035 | M5: 2036 | N5: 2037
B6: Дисконт-фактор | D6: =1/(1+'Параметры'!C6)^D$4 -> 1 | E6: =1/(1+'Параметры'!C6)^E$4 -> 0.89285714 | F6: =1/(1+'Параметры'!C6)^F$4 -> 0.79719388 | G6: =1/(1+'Параметры'!C6)^G$4 -> 0.71178025 | H6: =1/(1+'Параметры'!C6)^H$4 -> 0.63551808 | I6: =1/(1+'Параметры'!C6)^I$4 -> 0.56742686 | J6: =1/(1+'Параметры'!C6)^J$4 -> 0.50663112 | K6: =1/(1+'Параметры'!C6)^K$4 -> 0.45234922 | L6: =1/(1+'Параметры'!C6)^L$4 -> 0.40388323 | M6: =1/(1+'Параметры'!C6)^M$4 -> 0.36061002 | N6: =1/(1+'Параметры'!C6)^N$4 -> 0.32197324
B8: ="Вариант 1: "&'Ввод данных'!D7 -> Вариант 1: NHL NTE 240
B9: КТГ | C9: коэф. | E9: ='Данные по годам'!E7 -> 0.9376 | F9: ='Данные по годам'!F7 -> 0.9304 | G9: ='Данные по годам'!G7 -> 0.9209 | H9: ='Данные по годам'!H7 -> 0.9084 | I9: ='Данные по годам'!I7 -> 0.9333 | J9: ='Данные по годам'!J7 -> 0.9217 | K9: ='Данные по годам'!K7 -> 0.9313 | L9: ='Данные по годам'!L7 -> 0.9111 | ... N9: ='Данные по годам'!N7 -> 0.9322
B10: Эффективное время | C10: час/год | E10: ='Параметры'!C26*E9*(1-102.38/(60*'Параметры'!C27)) -> 7045.4796 | F10: ='Параметры'!C26*F9*(1-102.38/(60*'Параметры'!C27)) -> 6991.3761 | G10: ='Параметры'!C26*G9*(1-102.38/(60*'Параметры'!C27)) -> 6919.9895 | H10: ='Параметры'!C26*H9*(1-102.38/(60*'Параметры'!C27)) -> 6826.0598 | I10: ='Параметры'!C26*I9*(1-102.38/(60*'Параметры'!C27)) -> 7013.1677 | J10: ='Параметры'!C26*J9*(1-102.38/(60*'Параметры'!C27)) -> 6926.001 | K10: ='Параметры'!C26*K9*(1-102.38/(60*'Параметры'!C27)) -> 6998.139 | L10: ='Параметры'!C26*L9*(1-102.38/(60*'Параметры'!C27)) -> 6846.3486 | M10: ='Параметры'!C26*M9*(1-102.38/(60*'Параметры'!C27)) -> 6891.4348 | N10: ='Параметры'!C26*N9*(1-102.38/(60*'Параметры'!C27)) -> 7004.9019
B11: Объём перевозки | C11: тыс.т | E11: ='Производительность'!D9*E10/1000 -> 3844.4679 | F11: ='Производительность'!D9*F10/1000 -> 3814.9456 | G11: ='Производительность'!D9*G10/1000 -> 3775.9924 | H11: ='Производительность'!D9*H10/1000 -> 3724.7383 | I11: ='Производительность'!D9*I10/1000 -> 3826.8365 | J11: ='Производительность'!D9*J10/1000 -> 3779.2727 | K11: ='Производительность'!D9*K10/1000 -> 3818.6359 | L11: ='Производительность'!D9*L10/1000 -> 3735.8092 | M11: ='Производительность'!D9*M10/1000 -> 3760.4112 | N11: ='Производительность'!D9*N10/1000 -> 3822.3262
B12: Грузооборот | C12: тыс.ткм | E12: =E11*'Параметры'!C28 -> 11685.645 | F12: =F11*'Параметры'!C28 -> 11595.909 | G12: =G11*'Параметры'!C28 -> 11477.507 | H12: =H11*'Параметры'!C28 -> 11321.715 | I12: =I11*'Параметры'!C28 -> 11632.052 | J12: =J11*'Параметры'!C28 -> 11487.477 | K12: =K11*'Параметры'!C28 -> 11607.126 | L12: =L11*'Параметры'!C28 -> 11355.366 | M12: =M11*'Параметры'!C28 -> 11430.146 | N12: =N11*'Параметры'!C28 -> 11618.343
B13: Пробег | C13: тыс.км | E13: ='Производительность'!D8*E10*2*'Параметры'!C28/1000 -> 104.29567 | F13: ='Производительность'!D8*F10*2*'Параметры'!C28/1000 -> 103.49477 | G13: ='Производительность'!D8*G10*2*'Параметры'!C28/1000 -> 102.43802 | H13: ='Производительность'!D8*H10*2*'Параметры'!C28/1000 -> 101.04755 | I13: ='Производительность'!D8*I10*2*'Параметры'!C28/1000 -> 103.81735 | J13: ='Производительность'!D8*J10*2*'Параметры'!C28/1000 -> 102.52701 | K13: ='Производительность'!D8*K10*2*'Параметры'!C28/1000 -> 103.59488 | L13: ='Производительность'!D8*L10*2*'Параметры'!C28/1000 -> 101.34789 | M13: ='Производительность'!D8*M10*2*'Параметры'!C28/1000 -> 102.01532 | N13: ='Производительность'!D8*N10*2*'Параметры'!C28/1000 -> 103.69499
B14: Топливо | C14: тыс.руб | E14: =E12*'Параметры'!C32/1000*'Параметры'!C10*(1+'Параметры'!C14)^(E$4-1) -> 69432.712 | F14: =F12*'Параметры'!C32/1000*'Параметры'!C10*(1+'Параметры'!C14)^(F$4-1) -> 68899.526 | G14: =G12*'Параметры'!C32/1000*'Параметры'!C10*(1+'Параметры'!C14)^(G$4-1) -> 68196.016 | H14: =H12*'Параметры'!C32/1000*'Параметры'!C10*(1+'Параметры'!C14)^(H$4-1) -> 67270.345 | I14: =I12*'Параметры'!C32/1000*'Параметры'!C10*(1+'Параметры'!C14)^(I$4-1) -> 69114.281 | J14: =J12*'Параметры'!C32/1000*'Параметры'!C10*(1+'Параметры'!C14)^(J$4-1) -> 68255.259 | K14: =K12*'Параметры'!C32/1000*'Параметры'!C10*(1+'Параметры'!C14)^(K$4-1) -> 68966.174 | L14: =L12*'Параметры'!C32/1000*'Параметры'!C10*(1+'Параметры'!C14)^(L$4-1) -> 67470.29 | M14: =M12*'Параметры'!C32/1000*'Параметры'!C10*(1+'Параметры'!C14)^(M$4-1) -> 67914.612 | N14: =N12*'Параметры'!C32/1000*'Параметры'!C10*(1+'Параметры'!C14)^(N$4-1) -> 69032.822
B15: ТОиР и сервис (по годам) | C15: тыс.руб | E15: ='Данные по годам'!E8*IF('Данные по годам'!$D$8="CNY",'Параметры'!C20,IF('Данные по годам'!$D$8="USD",'Параметры'!C21,IF('Данные по годам'!$D$8="EUR",'Параметры'!C22,1))) -> 6010.997 | F15: ='Данные по годам'!F8*IF('Данные по годам'!$D$8="CNY",'Параметры'!C20,IF('Данные по годам'!$D$8="USD",'Параметры'!C21,IF('Данные по годам'!$D$8="EUR",'Параметры'!C22,1))) -> 8352.9495 | G15: ='Данные по годам'!G8*IF('Данные по годам'!$D$8="CNY",'Параметры'!C20,IF('Данные по годам'!$D$8="USD",'Параметры'!C21,IF('Данные по годам'!$D$8="EUR",'Параметры'!C22,1))) -> 49489.735 | H15: ='Данные по годам'!H8*IF('Данные по годам'!$D$8="CNY",'Параметры'!C20,IF('Данные по годам'!$D$8="USD",'Параметры'!C21,IF('Данные по годам'!$D$8="EUR",'Параметры'!C22,1))) -> 26318.82 | I15: ='Данные по годам'!I8*IF('Данные по годам'!$D$8="CNY",'Параметры'!C20,IF('Данные по годам'!$D$8="USD",'Параметры'!C21,IF('Данные по годам'!$D$8="EUR",'Параметры'!C22,1))) -> 8777.1756 | J15: ='Данные по годам'!J8*IF('Данные по годам'!$D$8="CNY",'Параметры'!C20,IF('Данные по годам'!$D$8="USD",'Параметры'!C21,IF('Данные по годам'!$D$8="EUR",'Параметры'!C22,1))) -> 48329.767 | K15: ='Данные по годам'!K8*IF('Данные по годам'!$D$8="CNY",'Параметры'!C20,IF('Данные по годам'!$D$8="USD",'Параметры'!C21,IF('Данные по годам'!$D$8="EUR",'Параметры'!C22,1))) -> 8136.6989 | L15: ='Данные по годам'!L8*IF('Данные по годам'!$D$8="CNY",'Параметры'!C20,IF('Данные по годам'!$D$8="USD",'Параметры'!C21,IF('Данные по годам'!$D$8="EUR",'Параметры'!C22,1))) -> 27892.952 | M15: ='Данные по годам'!M8*IF('Данные по годам'!$D$8="CNY",'Параметры'!C20,IF('Данные по годам'!$D$8="USD",'Параметры'!C21,IF('Данные по годам'!$D$8="EUR",'Параметры'!C22,1))) -> 90160.511 | N15: ='Данные по годам'!N8*IF('Данные по годам'!$D$8="CNY",'Параметры'!C20,IF('Данные по годам'!$D$8="USD",'Параметры'!C21,IF('Данные по годам'!$D$8="EUR",'Параметры'!C22,1))) -> 6914.6547
B16: Шины | C16: тыс.руб | E16: =E13*'Параметры'!C36*'Параметры'!C37*(1+'Параметры'!C15)^(E$4-1) -> 23352.166 | F16: =F13*'Параметры'!C36*'Параметры'!C37*(1+'Параметры'!C15)^(F$4-1) -> 23172.84 | G16: =G13*'Параметры'!C36*'Параметры'!C37*(1+'Параметры'!C15)^(G$4-1) -> 22936.23 | H16: =H13*'Параметры'!C36*'Параметры'!C37*(1+'Параметры'!C15)^(H$4-1) -> 22624.901 | I16: =I13*'Параметры'!C36*'Параметры'!C37*(1+'Параметры'!C15)^(I$4-1) -> 23245.069 | J16: =J13*'Параметры'!C36*'Параметры'!C37*(1+'Параметры'!C15)^(J$4-1) -> 22956.155 | K16: =K13*'Параметры'!C36*'Параметры'!C37*(1+'Параметры'!C15)^(K$4-1) -> 23195.256 | L16: =L13*'Параметры'!C36*'Параметры'!C37*(1+'Параметры'!C15)^(L$4-1) -> 22692.148 | M16: =M13*'Параметры'!C36*'Параметры'!C37*(1+'Параметры'!C15)^(M$4-1) -> 22841.586 | N16: =N13*'Параметры'!C36*'Параметры'!C37*(1+'Параметры'!C15)^(N$4-1) -> 23217.672
B17: Персонал | C17: тыс.руб | E17: ='Ввод данных'!D18*(1+'Параметры'!C16)^(E$4-1) -> 18475.6 | F17: ='Ввод данных'!D18*(1+'Параметры'!C16)^(F$4-1) -> 18475.6 | G17: ='Ввод данных'!D18*(1+'Параметры'!C16)^(G$4-1) -> 18475.6 | H17: ='Ввод данных'!D18*(1+'Параметры'!C16)^(H$4-1) -> 18475.6 | I17: ='Ввод данных'!D18*(1+'Параметры'!C16)^(I$4-1) -> 18475.6 | J17: ='Ввод данных'!D18*(1+'Параметры'!C16)^(J$4-1) -> 18475.6 | K17: ='Ввод данных'!D18*(1+'Параметры'!C16)^(K$4-1) -> 18475.6 | L17: ='Ввод данных'!D18*(1+'Параметры'!C16)^(L$4-1) -> 18475.6 | M17: ='Ввод данных'!D18*(1+'Параметры'!C16)^(M$4-1) -> 18475.6 | N17: ='Ввод данных'!D18*(1+'Параметры'!C16)^(N$4-1) -> 18475.6
B18: Транспортный налог | C18: тыс.руб | E18: ='Ввод данных'!D19*'Параметры'!C41/1000 -> 212.5 | F18: ='Ввод данных'!D19*'Параметры'!C41/1000 -> 212.5 | G18: ='Ввод данных'!D19*'Параметры'!C41/1000 -> 212.5 | H18: ='Ввод данных'!D19*'Параметры'!C41/1000 -> 212.5 | I18: ='Ввод данных'!D19*'Параметры'!C41/1000 -> 212.5 | J18: ='Ввод данных'!D19*'Параметры'!C41/1000 -> 212.5 | K18: ='Ввод данных'!D19*'Параметры'!C41/1000 -> 212.5 | L18: ='Ввод данных'!D19*'Параметры'!C41/1000 -> 212.5 | M18: ='Ввод данных'!D19*'Параметры'!C41/1000 -> 212.5 | N18: ='Ввод данных'!D19*'Параметры'!C41/1000 -> 212.5
B19: Итого денежные затраты | C19: тыс.руб | E19: =E14+E15+E16+E17+E18 -> 117483.97 | F19: =F14+F15+F16+F17+F18 -> 119113.42 | G19: =G14+G15+G16+G17+G18 -> 159310.08 | H19: =H14+H15+H16+H17+H18 -> 134902.17 | I19: =I14+I15+I16+I17+I18 -> 119824.63 | J19: =J14+J15+J16+J17+J18 -> 158229.28 | K19: =K14+K15+K16+K17+K18 -> 118986.23 | L19: =L14+L15+L16+L17+L18 -> 136743.49 | ... N19: =N14+N15+N16+N17+N18 -> 117853.25
B20: Амортизация (НУ) | C20: тыс.руб | E20: =IF(E$4<=INT('Параметры'!C9),'Производительность'!D5/'Параметры'!C9,IF(E$4=INT('Параметры'!C9)+1,'Производительность'!D5*('Параметры'!C9-INT('Параметры'!C9))/'Параметры'!C9,0)) -> 50246.705 | F20: =IF(F$4<=INT('Параметры'!C9),'Производительность'!D5/'Параметры'!C9,IF(F$4=INT('Параметры'!C9)+1,'Производительность'!D5*('Параметры'!C9-INT('Параметры'!C9))/'Параметры'!C9,0)) -> 50246.705 | G20: =IF(G$4<=INT('Параметры'!C9),'Производительность'!D5/'Параметры'!C9,IF(G$4=INT('Параметры'!C9)+1,'Производительность'!D5*('Параметры'!C9-INT('Параметры'!C9))/'Параметры'!C9,0)) -> 50246.705 | H20: =IF(H$4<=INT('Параметры'!C9),'Производительность'!D5/'Параметры'!C9,IF(H$4=INT('Параметры'!C9)+1,'Производительность'!D5*('Параметры'!C9-INT('Параметры'!C9))/'Параметры'!C9,0)) -> 50246.705 | I20: =IF(I$4<=INT('Параметры'!C9),'Производительность'!D5/'Параметры'!C9,IF(I$4=INT('Параметры'!C9)+1,'Производительность'!D5*('Параметры'!C9-INT('Параметры'!C9))/'Параметры'!C9,0)) -> 50246.705 | J20: =IF(J$4<=INT('Параметры'!C9),'Производительность'!D5/'Параметры'!C9,IF(J$4=INT('Параметры'!C9)+1,'Производительность'!D5*('Параметры'!C9-INT('Параметры'!C9))/'Параметры'!C9,0)) -> 4170.4765 | K20: =IF(K$4<=INT('Параметры'!C9),'Производительность'!D5/'Параметры'!C9,IF(K$4=INT('Параметры'!C9)+1,'Производительность'!D5*('Параметры'!C9-INT('Параметры'!C9))/'Параметры'!C9,0)) -> 0 | L20: =IF(L$4<=INT('Параметры'!C9),'Производительность'!D5/'Параметры'!C9,IF(L$4=INT('Параметры'!C9)+1,'Производительность'!D5*('Параметры'!C9-INT('Параметры'!C9))/'Параметры'!C9,0)) -> 0 | M20: =IF(M$4<=INT('Параметры'!C9),'Производительность'!D5/'Параметры'!C9,IF(M$4=INT('Параметры'!C9)+1,'Производительность'!D5*('Параметры'!C9-INT('Параметры'!C9))/'Параметры'!C9,0)) -> 0 | N20: =IF(N$4<=INT('Параметры'!C9),'Производительность'!D5/'Параметры'!C9,IF(N$4=INT('Параметры'!C9)+1,'Производительность'!D5*('Параметры'!C9-INT('Параметры'!C9))/'Параметры'!C9,0)) -> 0
B21: Налогооблагаемая база | C21: тыс.руб | E21: =E19+E20 -> 167730.68 | F21: =F19+F20 -> 169360.12 | G21: =G19+G20 -> 209556.79 | H21: =H19+H20 -> 185148.87 | I21: =I19+I20 -> 170071.33 | J21: =J19+J20 -> 162399.76 | K21: =K19+K20 -> 118986.23 | L21: =L19+L20 -> 136743.49 | ... N21: =N19+N20 -> 117853.25
B22: Налог на прибыль (щит) | C22: тыс.руб | E22: =-E21*'Параметры'!C7 -> -41932.67 | F22: =-F21*'Параметры'!C7 -> -42340.03 | G22: =-G21*'Параметры'!C7 -> -52389.197 | H22: =-H21*'Параметры'!C7 -> -46287.218 | I22: =-I21*'Параметры'!C7 -> -42517.833 | J22: =-J21*'Параметры'!C7 -> -40599.939 | K22: =-K21*'Параметры'!C7 -> -29746.557 | L22: =-L21*'Параметры'!C7 -> -34185.873 | M22: =-M21*'Параметры'!C7 -> -49901.202 | N22: =-N21*'Параметры'!C7 -> -29463.312
B23: Операц. денежный поток | C23: тыс.руб | E23: =E21+E22-E20 -> 75551.305 | F23: =F21+F22-F20 -> 76773.385 | G23: =G21+G22-G20 -> 106920.88 | H23: =H21+H22-H20 -> 88614.949 | I23: =I21+I22-I20 -> 77306.793 | J23: =J21+J22-J20 -> 117629.34 | K23: =K21+K22-K20 -> 89239.672 | L23: =L21+L22-L20 -> 102557.62 | ... N23: =N21+N22-N20 -> 88389.936
B24: Инвестиции / остаточная ст-ть | C24: тыс.руб | D24: =IF(D$4=0,'Производительность'!D5,IF(D$4='Параметры'!C8,-'Ввод данных'!D14*'Производительность'!D5,0)) -> 255404 | E24: =IF(E$4=0,'Производительность'!D5,IF(E$4='Параметры'!C8,-'Ввод данных'!D14*'Производительность'!D5,0)) -> 0 | F24: =IF(F$4=0,'Производительность'!D5,IF(F$4='Параметры'!C8,-'Ввод данных'!D14*'Производительность'!D5,0)) -> 0 | G24: =IF(G$4=0,'Производительность'!D5,IF(G$4='Параметры'!C8,-'Ввод данных'!D14*'Производительность'!D5,0)) -> 0 | H24: =IF(H$4=0,'Производительность'!D5,IF(H$4='Параметры'!C8,-'Ввод данных'!D14*'Производительность'!D5,0)) -> 0 | I24: =IF(I$4=0,'Производительность'!D5,IF(I$4='Параметры'!C8,-'Ввод данных'!D14*'Производительность'!D5,0)) -> 0 | J24: =IF(J$4=0,'Производительность'!D5,IF(J$4='Параметры'!C8,-'Ввод данных'!D14*'Производительность'!D5,0)) -> 0 | K24: =IF(K$4=0,'Производительность'!D5,IF(K$4='Параметры'!C8,-'Ввод данных'!D14*'Производительность'!D5,0)) -> 0 | L24: =IF(L$4=0,'Производительность'!D5,IF(L$4='Параметры'!C8,-'Ввод данных'!D14*'Производительность'!D5,0)) -> 0 | M24: =IF(M$4=0,'Производительность'!D5,IF(M$4='Параметры'!C8,-'Ввод данных'!D14*'Производительность'!D5,0)) -> 0 | N24: =IF(N$4=0,'Производительность'!D5,IF(N$4='Параметры'!C8,-'Ввод данных'!D14*'Производительность'!D5,0)) -> 0
B25: Чистый денежный поток | C25: тыс.руб | D25: =0+D24 -> 255404 | E25: =E23+E24 -> 75551.305 | F25: =F23+F24 -> 76773.385 | G25: =G23+G24 -> 106920.88 | H25: =H23+H24 -> 88614.949 | I25: =I23+I24 -> 77306.793 | J25: =J23+J24 -> 117629.34 | K25: =K23+K24 -> 89239.672 | L25: =L23+L24 -> 102557.62 | ... N25: =N23+N24 -> 88389.936
B26: Дисконтированный поток | C26: тыс.руб | D26: =D25*D$6 -> 255404 | E26: =E25*E$6 -> 67456.522 | F26: =F25*F$6 -> 61203.273 | G26: =G25*G$6 -> 76104.174 | H26: =H25*H$6 -> 56316.402 | I26: =I25*I$6 -> 43865.95 | J26: =J25*J$6 -> 59594.685 | K26: =K25*K$6 -> 40367.495 | ... N26: =N25*N$6 -> 28459.194
B27: Кумул. дисконт. поток | C27: тыс.руб | D27: =SUM($D26:D26) -> 255404 | E27: =SUM($D26:E26) -> 322860.52 | F27: =SUM($D26:F26) -> 384063.79 | G27: =SUM($D26:G26) -> 460167.97 | H27: =SUM($D26:H26) -> 516484.37 | I27: =SUM($D26:I26) -> 560350.32 | J27: =SUM($D26:J26) -> 619945.01 | K27: =SUM($D26:K26) -> 660312.5 | ... N27: =SUM($D26:N26) -> 784177.62
B28: Аннуитет по году | C28: руб/ткм | E28: =SUM($D26:E26)/SUM($E$6:E$6)/(SUM($E12:E12)/E$4) -> 30.944273 | F28: =SUM($D26:F26)/SUM($E$6:F$6)/(SUM($E12:F12)/F$4) -> 19.521878 | G28: =SUM($D26:G26)/SUM($E$6:G$6)/(SUM($E12:G12)/G$4) -> 16.535873 | H28: =SUM($D26:H26)/SUM($E$6:H$6)/(SUM($E12:H12)/H$4) -> 14.760554 | I28: =SUM($D26:I26)/SUM($E$6:I$6)/(SUM($E12:I12)/I$4) -> 13.467252 | J28: =SUM($D26:J26)/SUM($E$6:J$6)/(SUM($E12:J12)/J$4) -> 13.073923 | K28: =SUM($D26:K26)/SUM($E$6:K$6)/(SUM($E12:K12)/K$4) -> 12.533541 | L28: =SUM($D26:L26)/SUM($E$6:L$6)/(SUM($E12:L12)/L$4) -> 12.261868 | ... N28: =SUM($D26:N26)/SUM($E$6:N$6)/(SUM($E12:N12)/N$4) -> 12.046304
B30: ="Вариант 2: "&'Ввод данных'!E7 -> Вариант 2: Estar ESDE240 (ГПБ К)
B31: КТГ | C31: коэф. | E31: ='Данные по годам'!E10 -> 0.9116 | F31: ='Данные по годам'!F10 -> 0.8956 | G31: ='Данные по годам'!G10 -> 0.8493 | H31: ='Данные по годам'!H10 -> 0.806 | I31: ='Данные по годам'!I10 -> 0.899 | J31: ='Данные по годам'!J10 -> 0.8221 | K31: ='Данные по годам'!K10 -> 0.8886 | L31: ='Данные по годам'!L10 -> 0.8107 | ... N31: ='Данные по годам'!N10 -> 0.834
B32: Эффективное время | C32: час/год | E32: ='Параметры'!C26*E31*(1-102.38/(60*'Параметры'!C27)) -> 6850.1058 | F32: ='Параметры'!C26*F31*(1-102.38/(60*'Параметры'!C27)) -> 6729.8757 | G32: ='Параметры'!C26*G31*(1-102.38/(60*'Параметры'!C27)) -> 6381.9601 | H32: ='Параметры'!C26*H31*(1-102.38/(60*'Параметры'!C27)) -> 6056.5876 | I32: ='Параметры'!C26*I31*(1-102.38/(60*'Параметры'!C27)) -> 6755.4246 | J32: ='Параметры'!C26*J31*(1-102.38/(60*'Параметры'!C27)) -> 6177.5691 | K32: ='Параметры'!C26*K31*(1-102.38/(60*'Параметры'!C27)) -> 6677.2751 | L32: ='Параметры'!C26*L31*(1-102.38/(60*'Параметры'!C27)) -> 6091.9052 | M32: ='Параметры'!C26*M31*(1-102.38/(60*'Параметры'!C27)) -> 6433.8093 | N32: ='Параметры'!C26*N31*(1-102.38/(60*'Параметры'!C27)) -> 6266.9901
B33: Объём перевозки | C33: тыс.т | E33: ='Производительность'!E9*E32/1000 -> 3468.6285 | F33: ='Производительность'!E9*F32/1000 -> 3407.7487 | G33: ='Производительность'!E9*G32/1000 -> 3231.5776 | H33: ='Производительность'!E9*H32/1000 -> 3066.8216 | I33: ='Производительность'!E9*I32/1000 -> 3420.6856 | J33: ='Производительность'!E9*J32/1000 -> 3128.0819 | K33: ='Производительность'!E9*K32/1000 -> 3381.1137 | L33: ='Производительность'!E9*L32/1000 -> 3084.705 | M33: ='Производительность'!E9*M32/1000 -> 3257.8321 | N33: ='Производительность'!E9*N32/1000 -> 3173.3613
B34: Грузооборот | C34: тыс.ткм | E34: =E33*'Параметры'!C28 -> 10543.243 | F34: =F33*'Параметры'!C28 -> 10358.193 | G34: =G33*'Параметры'!C28 -> 9822.7034 | H34: =H33*'Параметры'!C28 -> 9321.9109 | I34: =I33*'Параметры'!C28 -> 10397.516 | J34: =J33*'Параметры'!C28 -> 9508.1178 | K34: =K33*'Параметры'!C28 -> 10277.233 | L34: =L33*'Параметры'!C28 -> 9376.2695 | M34: =M33*'Параметры'!C28 -> 9902.5064 | N34: =N33*'Параметры'!C28 -> 9645.749
B35: Пробег | C35: тыс.км | E35: ='Производительность'!E8*E32*2*'Параметры'!C28/1000 -> 101.40351 | F35: ='Производительность'!E8*F32*2*'Параметры'!C28/1000 -> 99.623723 | G35: ='Производительность'!E8*G32*2*'Параметры'!C28/1000 -> 94.473457 | H35: ='Производительность'!E8*H32*2*'Параметры'!C28/1000 -> 89.656901 | I35: ='Производительность'!E8*I32*2*'Параметры'!C28/1000 -> 100.00193 | J35: ='Производительность'!E8*J32*2*'Параметры'!C28/1000 -> 91.447815 | K35: ='Производительность'!E8*K32*2*'Параметры'!C28/1000 -> 98.845065 | L35: ='Производительность'!E8*L32*2*'Параметры'!C28/1000 -> 90.179715 | M35: ='Производительность'!E8*M32*2*'Параметры'!C28/1000 -> 95.240991 | N35: ='Производительность'!E8*N32*2*'Параметры'!C28/1000 -> 92.771533
B36: Топливо | C36: тыс.руб | E36: =E34*'Параметры'!C32/1000*'Параметры'!C10*(1+'Параметры'!C14)^(E$4-1) -> 62644.893 | F36: =F34*'Параметры'!C32/1000*'Параметры'!C10*(1+'Параметры'!C14)^(F$4-1) -> 61545.378 | G36: =G34*'Параметры'!C32/1000*'Параметры'!C10*(1+'Параметры'!C14)^(G$4-1) -> 58363.655 | H36: =H34*'Параметры'!C32/1000*'Параметры'!C10*(1+'Параметры'!C14)^(H$4-1) -> 55388.091 | I36: =I34*'Параметры'!C32/1000*'Параметры'!C10*(1+'Параметры'!C14)^(I$4-1) -> 61779.025 | J36: =J34*'Параметры'!C32/1000*'Параметры'!C10*(1+'Параметры'!C14)^(J$4-1) -> 56494.479 | K36: =K34*'Параметры'!C32/1000*'Параметры'!C10*(1+'Параметры'!C14)^(K$4-1) -> 61064.34 | L36: =L34*'Параметры'!C32/1000*'Параметры'!C10*(1+'Параметры'!C14)^(L$4-1) -> 55711.074 | M36: =M34*'Параметры'!C32/1000*'Параметры'!C10*(1+'Параметры'!C14)^(M$4-1) -> 58837.821 | N36: =N34*'Параметры'!C32/1000*'Параметры'!C10*(1+'Параметры'!C14)^(N$4-1) -> 57312.243
B37: ТОиР и сервис (по годам) | C37: тыс.руб | E37: ='Данные по годам'!E11*IF('Данные по годам'!$D$11="CNY",'Параметры'!C20,IF('Данные по годам'!$D$11="USD",'Параметры'!C21,IF('Данные по годам'!$D$11="EUR",'Параметры'!C22,1))) -> 16978.576 | F37: ='Данные по годам'!F11*IF('Данные по годам'!$D$11="CNY",'Параметры'!C20,IF('Данные по годам'!$D$11="USD",'Параметры'!C21,IF('Данные по годам'!$D$11="EUR",'Параметры'!C22,1))) -> 26025.947 | G37: ='Данные по годам'!G11*IF('Данные по годам'!$D$11="CNY",'Параметры'!C20,IF('Данные по годам'!$D$11="USD",'Параметры'!C21,IF('Данные по годам'!$D$11="EUR",'Параметры'!C22,1))) -> 87290.175 | H37: ='Данные по годам'!H11*IF('Данные по годам'!$D$11="CNY",'Параметры'!C20,IF('Данные по годам'!$D$11="USD",'Параметры'!C21,IF('Данные по годам'!$D$11="EUR",'Параметры'!C22,1))) -> 258759.31 | I37: ='Данные по годам'!I11*IF('Данные по годам'!$D$11="CNY",'Параметры'!C20,IF('Данные по годам'!$D$11="USD",'Параметры'!C21,IF('Данные по годам'!$D$11="EUR",'Параметры'!C22,1))) -> 17326.837 | J37: ='Данные по годам'!J11*IF('Данные по годам'!$D$11="CNY",'Параметры'!C20,IF('Данные по годам'!$D$11="USD",'Параметры'!C21,IF('Данные по годам'!$D$11="EUR",'Параметры'!C22,1))) -> 96337.546 | K37: ='Данные по годам'!K11*IF('Данные по годам'!$D$11="CNY",'Параметры'!C20,IF('Данные по годам'!$D$11="USD",'Параметры'!C21,IF('Данные по годам'!$D$11="EUR",'Параметры'!C22,1))) -> 16978.576 | L37: ='Данные по годам'!L11*IF('Данные по годам'!$D$11="CNY",'Параметры'!C20,IF('Данные по годам'!$D$11="USD",'Параметры'!C21,IF('Данные по годам'!$D$11="EUR",'Параметры'!C22,1))) -> 258759.31 | M37: ='Данные по годам'!M11*IF('Данные по годам'!$D$11="CNY",'Параметры'!C20,IF('Данные по годам'!$D$11="USD",'Параметры'!C21,IF('Данные по годам'!$D$11="EUR",'Параметры'!C22,1))) -> 16978.576 | N37: ='Данные по годам'!N11*IF('Данные по годам'!$D$11="CNY",'Параметры'!C20,IF('Данные по годам'!$D$11="USD",'Параметры'!C21,IF('Данные по годам'!$D$11="EUR",'Параметры'!C22,1))) -> 16978.576
B38: Шины | C38: тыс.руб | E38: =E35*'Параметры'!C36*'Параметры'!C37*(1+'Параметры'!C15)^(E$4-1) -> 22704.601 | F38: =F35*'Параметры'!C36*'Параметры'!C37*(1+'Параметры'!C15)^(F$4-1) -> 22306.1 | G38: =G35*'Параметры'!C36*'Параметры'!C37*(1+'Параметры'!C15)^(G$4-1) -> 21152.938 | H38: =H35*'Параметры'!C36*'Параметры'!C37*(1+'Параметры'!C15)^(H$4-1) -> 20074.494 | I38: =I35*'Параметры'!C36*'Параметры'!C37*(1+'Параметры'!C15)^(I$4-1) -> 22390.782 | J38: =J35*'Параметры'!C36*'Параметры'!C37*(1+'Параметры'!C15)^(J$4-1) -> 20475.486 | K38: =K35*'Параметры'!C36*'Параметры'!C37*(1+'Параметры'!C15)^(K$4-1) -> 22131.756 | L38: =L35*'Параметры'!C36*'Параметры'!C37*(1+'Параметры'!C15)^(L$4-1) -> 20191.554 | M38: =M35*'Параметры'!C36*'Параметры'!C37*(1+'Параметры'!C15)^(M$4-1) -> 21324.791 | N38: =N35*'Параметры'!C36*'Параметры'!C37*(1+'Параметры'!C15)^(N$4-1) -> 20771.871
B39: Персонал | C39: тыс.руб | E39: ='Ввод данных'!E18*(1+'Параметры'!C16)^(E$4-1) -> 18475.6 | F39: ='Ввод данных'!E18*(1+'Параметры'!C16)^(F$4-1) -> 18475.6 | G39: ='Ввод данных'!E18*(1+'Параметры'!C16)^(G$4-1) -> 18475.6 | H39: ='Ввод данных'!E18*(1+'Параметры'!C16)^(H$4-1) -> 18475.6 | I39: ='Ввод данных'!E18*(1+'Параметры'!C16)^(I$4-1) -> 18475.6 | J39: ='Ввод данных'!E18*(1+'Параметры'!C16)^(J$4-1) -> 18475.6 | K39: ='Ввод данных'!E18*(1+'Параметры'!C16)^(K$4-1) -> 18475.6 | L39: ='Ввод данных'!E18*(1+'Параметры'!C16)^(L$4-1) -> 18475.6 | M39: ='Ввод данных'!E18*(1+'Параметры'!C16)^(M$4-1) -> 18475.6 | N39: ='Ввод данных'!E18*(1+'Параметры'!C16)^(N$4-1) -> 18475.6
B40: Транспортный налог | C40: тыс.руб | E40: ='Ввод данных'!E19*'Параметры'!C41/1000 -> 158.44 | F40: ='Ввод данных'!E19*'Параметры'!C41/1000 -> 158.44 | G40: ='Ввод данных'!E19*'Параметры'!C41/1000 -> 158.44 | H40: ='Ввод данных'!E19*'Параметры'!C41/1000 -> 158.44 | I40: ='Ввод данных'!E19*'Параметры'!C41/1000 -> 158.44 | J40: ='Ввод данных'!E19*'Параметры'!C41/1000 -> 158.44 | K40: ='Ввод данных'!E19*'Параметры'!C41/1000 -> 158.44 | L40: ='Ввод данных'!E19*'Параметры'!C41/1000 -> 158.44 | M40: ='Ввод данных'!E19*'Параметры'!C41/1000 -> 158.44 | N40: ='Ввод данных'!E19*'Параметры'!C41/1000 -> 158.44
B41: Итого денежные затраты | C41: тыс.руб | E41: =E36+E37+E38+E39+E40 -> 120962.11 | F41: =F36+F37+F38+F39+F40 -> 128511.47 | G41: =G36+G37+G38+G39+G40 -> 185440.81 | H41: =H36+H37+H38+H39+H40 -> 352855.93 | I41: =I36+I37+I38+I39+I40 -> 120130.68 | J41: =J36+J37+J38+J39+J40 -> 191941.55 | K41: =K36+K37+K38+K39+K40 -> 118808.71 | L41: =L36+L37+L38+L39+L40 -> 353295.97 | ... N41: =N36+N37+N38+N39+N40 -> 113696.73
B42: Амортизация (НУ) | C42: тыс.руб | E42: =IF(E$4<=INT('Параметры'!C9),'Производительность'!E5/'Параметры'!C9,IF(E$4=INT('Параметры'!C9)+1,'Производительность'!E5*('Параметры'!C9-INT('Параметры'!C9))/'Параметры'!C9,0)) -> 51807.161 | F42: =IF(F$4<=INT('Параметры'!C9),'Производительность'!E5/'Параметры'!C9,IF(F$4=INT('Параметры'!C9)+1,'Производительность'!E5*('Параметры'!C9-INT('Параметры'!C9))/'Параметры'!C9,0)) -> 51807.161 | G42: =IF(G$4<=INT('Параметры'!C9),'Производительность'!E5/'Параметры'!C9,IF(G$4=INT('Параметры'!C9)+1,'Производительность'!E5*('Параметры'!C9-INT('Параметры'!C9))/'Параметры'!C9,0)) -> 51807.161 | H42: =IF(H$4<=INT('Параметры'!C9),'Производительность'!E5/'Параметры'!C9,IF(H$4=INT('Параметры'!C9)+1,'Производительность'!E5*('Параметры'!C9-INT('Параметры'!C9))/'Параметры'!C9,0)) -> 51807.161 | I42: =IF(I$4<=INT('Параметры'!C9),'Производительность'!E5/'Параметры'!C9,IF(I$4=INT('Параметры'!C9)+1,'Производительность'!E5*('Параметры'!C9-INT('Параметры'!C9))/'Параметры'!C9,0)) -> 51807.161 | J42: =IF(J$4<=INT('Параметры'!C9),'Производительность'!E5/'Параметры'!C9,IF(J$4=INT('Параметры'!C9)+1,'Производительность'!E5*('Параметры'!C9-INT('Параметры'!C9))/'Параметры'!C9,0)) -> 4299.9944 | K42: =IF(K$4<=INT('Параметры'!C9),'Производительность'!E5/'Параметры'!C9,IF(K$4=INT('Параметры'!C9)+1,'Производительность'!E5*('Параметры'!C9-INT('Параметры'!C9))/'Параметры'!C9,0)) -> 0 | L42: =IF(L$4<=INT('Параметры'!C9),'Производительность'!E5/'Параметры'!C9,IF(L$4=INT('Параметры'!C9)+1,'Производительность'!E5*('Параметры'!C9-INT('Параметры'!C9))/'Параметры'!C9,0)) -> 0 | M42: =IF(M$4<=INT('Параметры'!C9),'Производительность'!E5/'Параметры'!C9,IF(M$4=INT('Параметры'!C9)+1,'Производительность'!E5*('Параметры'!C9-INT('Параметры'!C9))/'Параметры'!C9,0)) -> 0 | N42: =IF(N$4<=INT('Параметры'!C9),'Производительность'!E5/'Параметры'!C9,IF(N$4=INT('Параметры'!C9)+1,'Производительность'!E5*('Параметры'!C9-INT('Параметры'!C9))/'Параметры'!C9,0)) -> 0
B43: Налогооблагаемая база | C43: тыс.руб | E43: =E41+E42 -> 172769.27 | F43: =F41+F42 -> 180318.63 | G43: =G41+G42 -> 237247.97 | H43: =H41+H42 -> 404663.09 | I43: =I41+I42 -> 171937.85 | J43: =J41+J42 -> 196241.55 | K43: =K41+K42 -> 118808.71 | L43: =L41+L42 -> 353295.97 | ... N43: =N41+N42 -> 113696.73
B44: Налог на прибыль (щит) | C44: тыс.руб | E44: =-E43*'Параметры'!C7 -> -43192.318 | F44: =-F43*'Параметры'!C7 -> -45079.657 | G44: =-G43*'Параметры'!C7 -> -59311.992 | H44: =-H43*'Параметры'!C7 -> -101165.77 | I44: =-I43*'Параметры'!C7 -> -42984.461 | J44: =-J43*'Параметры'!C7 -> -49060.386 | K44: =-K43*'Параметры'!C7 -> -29702.178 | L44: =-L43*'Параметры'!C7 -> -88323.993 | M44: =-M43*'Параметры'!C7 -> -28943.807 | N44: =-N43*'Параметры'!C7 -> -28424.183
B45: Операц. денежный поток | C45: тыс.руб | E45: =E43+E44-E42 -> 77769.793 | F45: =F43+F44-F42 -> 83431.809 | G45: =G43+G44-G42 -> 126128.82 | H45: =H43+H44-H42 -> 251690.16 | I45: =I43+I44-I42 -> 77146.223 | J45: =J43+J44-J42 -> 142881.16 | K45: =K43+K44-K42 -> 89106.534 | L45: =L43+L44-L42 -> 264971.98 | ... N45: =N43+N44-N42 -> 85272.548
B46: Инвестиции / остаточная ст-ть | C46: тыс.руб | D46: =IF(D$4=0,'Производительность'!E5,IF(D$4='Параметры'!C8,-'Ввод данных'!E14*'Производительность'!E5,0)) -> 263335.8 | E46: =IF(E$4=0,'Производительность'!E5,IF(E$4='Параметры'!C8,-'Ввод данных'!E14*'Производительность'!E5,0)) -> 0 | F46: =IF(F$4=0,'Производительность'!E5,IF(F$4='Параметры'!C8,-'Ввод данных'!E14*'Производительность'!E5,0)) -> 0 | G46: =IF(G$4=0,'Производительность'!E5,IF(G$4='Параметры'!C8,-'Ввод данных'!E14*'Производительность'!E5,0)) -> 0 | H46: =IF(H$4=0,'Производительность'!E5,IF(H$4='Параметры'!C8,-'Ввод данных'!E14*'Производительность'!E5,0)) -> 0 | I46: =IF(I$4=0,'Производительность'!E5,IF(I$4='Параметры'!C8,-'Ввод данных'!E14*'Производительность'!E5,0)) -> 0 | J46: =IF(J$4=0,'Производительность'!E5,IF(J$4='Параметры'!C8,-'Ввод данных'!E14*'Производительность'!E5,0)) -> 0 | K46: =IF(K$4=0,'Производительность'!E5,IF(K$4='Параметры'!C8,-'Ввод данных'!E14*'Производительность'!E5,0)) -> 0 | L46: =IF(L$4=0,'Производительность'!E5,IF(L$4='Параметры'!C8,-'Ввод данных'!E14*'Производительность'!E5,0)) -> 0 | M46: =IF(M$4=0,'Производительность'!E5,IF(M$4='Параметры'!C8,-'Ввод данных'!E14*'Производительность'!E5,0)) -> 0 | N46: =IF(N$4=0,'Производительность'!E5,IF(N$4='Параметры'!C8,-'Ввод данных'!E14*'Производительность'!E5,0)) -> 0
B47: Чистый денежный поток | C47: тыс.руб | D47: =0+D46 -> 263335.8 | E47: =E45+E46 -> 77769.793 | F47: =F45+F46 -> 83431.809 | G47: =G45+G46 -> 126128.82 | H47: =H45+H46 -> 251690.16 | I47: =I45+I46 -> 77146.223 | J47: =J45+J46 -> 142881.16 | K47: =K45+K46 -> 89106.534 | L47: =L45+L46 -> 264971.98 | ... N47: =N45+N46 -> 85272.548
B48: Дисконтированный поток | C48: тыс.руб | D48: =D47*D$6 -> 263335.8 | E48: =E47*E$6 -> 69437.315 | F48: =F47*F$6 -> 66511.327 | G48: =G47*G$6 -> 89775.999 | H48: =H47*H$6 -> 159953.65 | I48: =I47*I$6 -> 43774.839 | J48: =J47*J$6 -> 72388.045 | K48: =K47*K$6 -> 40307.271 | ... N48: =N47*N$6 -> 27455.478
B49: Кумул. дисконт. поток | C49: тыс.руб | D49: =SUM($D48:D48) -> 263335.8 | E49: =SUM($D48:E48) -> 332773.11 | F49: =SUM($D48:F48) -> 399284.44 | G49: =SUM($D48:G48) -> 489060.44 | H49: =SUM($D48:H48) -> 649014.09 | I49: =SUM($D48:I48) -> 692788.93 | J49: =SUM($D48:J48) -> 765176.97 | K49: =SUM($D48:K48) -> 805484.24 | ... N49: =SUM($D48:N48) -> 971269.74
B50: Аннуитет по году | C50: руб/ткм | E50: =SUM($D48:E48)/SUM($E$6:E$6)/(SUM($E34:E34)/E$4) -> 35.350213 | F50: =SUM($D48:F48)/SUM($E$6:F$6)/(SUM($E34:F34)/F$4) -> 22.606662 | G50: =SUM($D48:G48)/SUM($E$6:G$6)/(SUM($E34:G34)/G$4) -> 19.882069 | H50: =SUM($D48:H48)/SUM($E$6:H$6)/(SUM($E34:H34)/H$4) -> 21.343207 | I50: =SUM($D48:I48)/SUM($E$6:I$6)/(SUM($E34:I34)/I$4) -> 19.049643 | J50: =SUM($D48:J48)/SUM($E$6:J$6)/(SUM($E34:J34)/J$4) -> 18.626071 | K50: =SUM($D48:K48)/SUM($E$6:K$6)/(SUM($E34:K34)/K$4) -> 17.592058 | L50: =SUM($D48:L48)/SUM($E$6:L$6)/(SUM($E34:L34)/L$4) -> 18.460027 | ... N50: =SUM($D48:N48)/SUM($E$6:N$6)/(SUM($E34:N34)/N$4) -> 17.336701
B52: ="Вариант 3: "&'Ввод данных'!F7 -> Вариант 3: SANY SET240S
B53: КТГ | C53: коэф. | E53: ='Данные по годам'!E13 -> 0.9357 | F53: ='Данные по годам'!F13 -> 0.9026 | G53: ='Данные по годам'!G13 -> 0.8659 | H53: ='Данные по годам'!H13 -> 0.904 | I53: ='Данные по годам'!I13 -> 0.85 | J53: ='Данные по годам'!J13 -> 0.904 | K53: ='Данные по годам'!K13 -> 0.8659 | L53: ='Данные по годам'!L13 -> 0.904 | ... N53: ='Данные по годам'!N13 -> 0.885
B54: Эффективное время | C54: час/год | E54: ='Параметры'!C26*E53*(1-102.38/(60*'Параметры'!C27)) -> 7031.2022 | F54: ='Параметры'!C26*F53*(1-102.38/(60*'Параметры'!C27)) -> 6782.4764 | G54: ='Параметры'!C26*G53*(1-102.38/(60*'Параметры'!C27)) -> 6506.6988 | H54: ='Параметры'!C26*H53*(1-102.38/(60*'Параметры'!C27)) -> 6792.9965 | I54: ='Параметры'!C26*I53*(1-102.38/(60*'Параметры'!C27)) -> 6387.2202 | J54: ='Параметры'!C26*J53*(1-102.38/(60*'Параметры'!C27)) -> 6792.9965 | K54: ='Параметры'!C26*K53*(1-102.38/(60*'Параметры'!C27)) -> 6506.6988 | L54: ='Параметры'!C26*L53*(1-102.38/(60*'Параметры'!C27)) -> 6792.9965 | M54: ='Параметры'!C26*M53*(1-102.38/(60*'Параметры'!C27)) -> 6387.2202 | N54: ='Параметры'!C26*N53*(1-102.38/(60*'Параметры'!C27)) -> 6650.2234
B55: Объём перевозки | C55: тыс.т | E55: ='Производительность'!F9*E54/1000 -> 3644.035 | F55: ='Производительность'!F9*F54/1000 -> 3515.1288 | G55: ='Производительность'!F9*G54/1000 -> 3372.2025 | H55: ='Производительность'!F9*H54/1000 -> 3520.581 | I55: ='Производительность'!F9*I54/1000 -> 3310.2808 | J55: ='Производительность'!F9*J54/1000 -> 3520.581 | K55: ='Производительность'!F9*K54/1000 -> 3372.2025 | L55: ='Производительность'!F9*L54/1000 -> 3520.581 | M55: ='Производительность'!F9*M54/1000 -> 3310.2808 | N55: ='Производительность'!F9*N54/1000 -> 3446.5865
B56: Грузооборот | C56: тыс.ткм | E56: =E55*'Параметры'!C28 -> 11076.409 | F56: =F55*'Параметры'!C28 -> 10684.585 | G56: =G55*'Параметры'!C28 -> 10250.147 | H56: =H55*'Параметры'!C28 -> 10701.158 | I56: =I55*'Параметры'!C28 -> 10061.93 | J56: =J55*'Параметры'!C28 -> 10701.158 | K56: =K55*'Параметры'!C28 -> 10250.147 | L56: =L55*'Параметры'!C28 -> 10701.158 | M56: =M55*'Параметры'!C28 -> 10061.93 | N56: =N55*'Параметры'!C28 -> 10476.244
B57: Пробег | C57: тыс.км | E57: ='Производительность'!F8*E54*2*'Параметры'!C28/1000 -> 104.08432 | F57: ='Производительность'!F8*F54*2*'Параметры'!C28/1000 -> 100.40238 | G57: ='Производительность'!F8*G54*2*'Параметры'!C28/1000 -> 96.319989 | H57: ='Производительность'!F8*H54*2*'Параметры'!C28/1000 -> 100.55811 | I57: ='Производительность'!F8*I54*2*'Параметры'!C28/1000 -> 94.551323 | J57: ='Производительность'!F8*J54*2*'Параметры'!C28/1000 -> 100.55811 | K57: ='Производительность'!F8*K54*2*'Параметры'!C28/1000 -> 96.319989 | L57: ='Производительность'!F8*L54*2*'Параметры'!C28/1000 -> 100.55811 | M57: ='Производительность'!F8*M54*2*'Параметры'!C28/1000 -> 94.551323 | N57: ='Производительность'!F8*N54*2*'Параметры'!C28/1000 -> 98.444613
B58: Топливо | C58: тыс.руб | E58: =E56*'Параметры'!C32/1000*'Параметры'!C10*(1+'Параметры'!C14)^(E$4-1) -> 65812.809 | F58: =F56*'Параметры'!C32/1000*'Параметры'!C10*(1+'Параметры'!C14)^(F$4-1) -> 63484.708 | G58: =G56*'Параметры'!C32/1000*'Параметры'!C10*(1+'Параметры'!C14)^(G$4-1) -> 60903.4 | H58: =H56*'Параметры'!C32/1000*'Параметры'!C10*(1+'Параметры'!C14)^(H$4-1) -> 63583.178 | I58: =I56*'Параметры'!C32/1000*'Параметры'!C10*(1+'Параметры'!C14)^(I$4-1) -> 59785.067 | J58: =J56*'Параметры'!C32/1000*'Параметры'!C10*(1+'Параметры'!C14)^(J$4-1) -> 63583.178 | K58: =K56*'Параметры'!C32/1000*'Параметры'!C10*(1+'Параметры'!C14)^(K$4-1) -> 60903.4 | L58: =L56*'Параметры'!C32/1000*'Параметры'!C10*(1+'Параметры'!C14)^(L$4-1) -> 63583.178 | M58: =M56*'Параметры'!C32/1000*'Параметры'!C10*(1+'Параметры'!C14)^(M$4-1) -> 59785.067 | N58: =N56*'Параметры'!C32/1000*'Параметры'!C10*(1+'Параметры'!C14)^(N$4-1) -> 62246.806
B59: ТОиР и сервис (по годам) | C59: тыс.руб | E59: ='Данные по годам'!E14*IF('Данные по годам'!$D$14="CNY",'Параметры'!C20,IF('Данные по годам'!$D$14="USD",'Параметры'!C21,IF('Данные по годам'!$D$14="EUR",'Параметры'!C22,1))) -> 12729.276 | F59: ='Данные по годам'!F14*IF('Данные по годам'!$D$14="CNY",'Параметры'!C20,IF('Данные по годам'!$D$14="USD",'Параметры'!C21,IF('Данные по годам'!$D$14="EUR",'Параметры'!C22,1))) -> 19869.344 | G59: ='Данные по годам'!G14*IF('Данные по годам'!$D$14="CNY",'Параметры'!C20,IF('Данные по годам'!$D$14="USD",'Параметры'!C21,IF('Данные по годам'!$D$14="EUR",'Параметры'!C22,1))) -> 56237.335 | H59: ='Данные по годам'!H14*IF('Данные по годам'!$D$14="CNY",'Параметры'!C20,IF('Данные по годам'!$D$14="USD",'Параметры'!C21,IF('Данные по годам'!$D$14="EUR",'Параметры'!C22,1))) -> 28698.147 | I59: ='Данные по годам'!I14*IF('Данные по годам'!$D$14="CNY",'Параметры'!C20,IF('Данные по годам'!$D$14="USD",'Параметры'!C21,IF('Данные по годам'!$D$14="EUR",'Параметры'!C22,1))) -> 91597.314 | J59: ='Данные по годам'!J14*IF('Данные по годам'!$D$14="CNY",'Параметры'!C20,IF('Данные по годам'!$D$14="USD",'Параметры'!C21,IF('Данные по годам'!$D$14="EUR",'Параметры'!C22,1))) -> 69714.297 | K59: ='Данные по годам'!K14*IF('Данные по годам'!$D$14="CNY",'Параметры'!C20,IF('Данные по годам'!$D$14="USD",'Параметры'!C21,IF('Данные по годам'!$D$14="EUR",'Параметры'!C22,1))) -> 25146.312 | L59: ='Данные по годам'!L14*IF('Данные по годам'!$D$14="CNY",'Параметры'!C20,IF('Данные по годам'!$D$14="USD",'Параметры'!C21,IF('Данные по годам'!$D$14="EUR",'Параметры'!C22,1))) -> 25292.745 | M59: ='Данные по годам'!M14*IF('Данные по годам'!$D$14="CNY",'Параметры'!C20,IF('Данные по годам'!$D$14="USD",'Параметры'!C21,IF('Данные по годам'!$D$14="EUR",'Параметры'!C22,1))) -> 126903.5 | N59: ='Данные по годам'!N14*IF('Данные по годам'!$D$14="CNY",'Параметры'!C20,IF('Данные по годам'!$D$14="USD",'Параметры'!C21,IF('Данные по годам'!$D$14="EUR",'Параметры'!C22,1))) -> 18433.6
B60: Шины | C60: тыс.руб | E60: =E57*'Параметры'!C36*'Параметры'!C37*(1+'Параметры'!C15)^(E$4-1) -> 23304.844 | F60: =F57*'Параметры'!C36*'Параметры'!C37*(1+'Параметры'!C15)^(F$4-1) -> 22480.445 | G60: =G57*'Параметры'!C36*'Параметры'!C37*(1+'Параметры'!C15)^(G$4-1) -> 21566.383 | H60: =H57*'Параметры'!C36*'Параметры'!C37*(1+'Параметры'!C15)^(H$4-1) -> 22515.313 | I60: =I57*'Параметры'!C36*'Параметры'!C37*(1+'Параметры'!C15)^(I$4-1) -> 21170.372 | J60: =J57*'Параметры'!C36*'Параметры'!C37*(1+'Параметры'!C15)^(J$4-1) -> 22515.313 | K60: =K57*'Параметры'!C36*'Параметры'!C37*(1+'Параметры'!C15)^(K$4-1) -> 21566.383 | L60: =L57*'Параметры'!C36*'Параметры'!C37*(1+'Параметры'!C15)^(L$4-1) -> 22515.313 | M60: =M57*'Параметры'!C36*'Параметры'!C37*(1+'Параметры'!C15)^(M$4-1) -> 21170.372 | N60: =N57*'Параметры'!C36*'Параметры'!C37*(1+'Параметры'!C15)^(N$4-1) -> 22042.093
B61: Персонал | C61: тыс.руб | E61: ='Ввод данных'!F18*(1+'Параметры'!C16)^(E$4-1) -> 18475.6 | F61: ='Ввод данных'!F18*(1+'Параметры'!C16)^(F$4-1) -> 18475.6 | G61: ='Ввод данных'!F18*(1+'Параметры'!C16)^(G$4-1) -> 18475.6 | H61: ='Ввод данных'!F18*(1+'Параметры'!C16)^(H$4-1) -> 18475.6 | I61: ='Ввод данных'!F18*(1+'Параметры'!C16)^(I$4-1) -> 18475.6 | J61: ='Ввод данных'!F18*(1+'Параметры'!C16)^(J$4-1) -> 18475.6 | K61: ='Ввод данных'!F18*(1+'Параметры'!C16)^(K$4-1) -> 18475.6 | L61: ='Ввод данных'!F18*(1+'Параметры'!C16)^(L$4-1) -> 18475.6 | M61: ='Ввод данных'!F18*(1+'Параметры'!C16)^(M$4-1) -> 18475.6 | N61: ='Ввод данных'!F18*(1+'Параметры'!C16)^(N$4-1) -> 18475.6
B62: Транспортный налог | C62: тыс.руб | E62: ='Ввод данных'!F19*'Параметры'!C41/1000 -> 241.655 | F62: ='Ввод данных'!F19*'Параметры'!C41/1000 -> 241.655 | G62: ='Ввод данных'!F19*'Параметры'!C41/1000 -> 241.655 | H62: ='Ввод данных'!F19*'Параметры'!C41/1000 -> 241.655 | I62: ='Ввод данных'!F19*'Параметры'!C41/1000 -> 241.655 | J62: ='Ввод данных'!F19*'Параметры'!C41/1000 -> 241.655 | K62: ='Ввод данных'!F19*'Параметры'!C41/1000 -> 241.655 | L62: ='Ввод данных'!F19*'Параметры'!C41/1000 -> 241.655 | M62: ='Ввод данных'!F19*'Параметры'!C41/1000 -> 241.655 | N62: ='Ввод данных'!F19*'Параметры'!C41/1000 -> 241.655
B63: Итого денежные затраты | C63: тыс.руб | E63: =E58+E59+E60+E61+E62 -> 120564.18 | F63: =F58+F59+F60+F61+F62 -> 124551.75 | G63: =G58+G59+G60+G61+G62 -> 157424.37 | H63: =H58+H59+H60+H61+H62 -> 133513.89 | I63: =I58+I59+I60+I61+I62 -> 191270.01 | J63: =J58+J59+J60+J61+J62 -> 174530.04 | K63: =K58+K59+K60+K61+K62 -> 126333.35 | L63: =L58+L59+L60+L61+L62 -> 130108.49 | ... N63: =N58+N59+N60+N61+N62 -> 121439.75
B64: Амортизация (НУ) | C64: тыс.руб | E64: =IF(E$4<=INT('Параметры'!C9),'Производительность'!F5/'Параметры'!C9,IF(E$4=INT('Параметры'!C9)+1,'Производительность'!F5*('Параметры'!C9-INT('Параметры'!C9))/'Параметры'!C9,0)) -> 49956.905 | F64: =IF(F$4<=INT('Параметры'!C9),'Производительность'!F5/'Параметры'!C9,IF(F$4=INT('Параметры'!C9)+1,'Производительность'!F5*('Параметры'!C9-INT('Параметры'!C9))/'Параметры'!C9,0)) -> 49956.905 | G64: =IF(G$4<=INT('Параметры'!C9),'Производительность'!F5/'Параметры'!C9,IF(G$4=INT('Параметры'!C9)+1,'Производительность'!F5*('Параметры'!C9-INT('Параметры'!C9))/'Параметры'!C9,0)) -> 49956.905 | H64: =IF(H$4<=INT('Параметры'!C9),'Производительность'!F5/'Параметры'!C9,IF(H$4=INT('Параметры'!C9)+1,'Производительность'!F5*('Параметры'!C9-INT('Параметры'!C9))/'Параметры'!C9,0)) -> 49956.905 | I64: =IF(I$4<=INT('Параметры'!C9),'Производительность'!F5/'Параметры'!C9,IF(I$4=INT('Параметры'!C9)+1,'Производительность'!F5*('Параметры'!C9-INT('Параметры'!C9))/'Параметры'!C9,0)) -> 49956.905 | J64: =IF(J$4<=INT('Параметры'!C9),'Производительность'!F5/'Параметры'!C9,IF(J$4=INT('Параметры'!C9)+1,'Производительность'!F5*('Параметры'!C9-INT('Параметры'!C9))/'Параметры'!C9,0)) -> 4146.4231 | K64: =IF(K$4<=INT('Параметры'!C9),'Производительность'!F5/'Параметры'!C9,IF(K$4=INT('Параметры'!C9)+1,'Производительность'!F5*('Параметры'!C9-INT('Параметры'!C9))/'Параметры'!C9,0)) -> 0 | L64: =IF(L$4<=INT('Параметры'!C9),'Производительность'!F5/'Параметры'!C9,IF(L$4=INT('Параметры'!C9)+1,'Производительность'!F5*('Параметры'!C9-INT('Параметры'!C9))/'Параметры'!C9,0)) -> 0 | M64: =IF(M$4<=INT('Параметры'!C9),'Производительность'!F5/'Параметры'!C9,IF(M$4=INT('Параметры'!C9)+1,'Производительность'!F5*('Параметры'!C9-INT('Параметры'!C9))/'Параметры'!C9,0)) -> 0 | N64: =IF(N$4<=INT('Параметры'!C9),'Производительность'!F5/'Параметры'!C9,IF(N$4=INT('Параметры'!C9)+1,'Производительность'!F5*('Параметры'!C9-INT('Параметры'!C9))/'Параметры'!C9,0)) -> 0
B65: Налогооблагаемая база | C65: тыс.руб | E65: =E63+E64 -> 170521.09 | F65: =F63+F64 -> 174508.66 | G65: =G63+G64 -> 207381.28 | H65: =H63+H64 -> 183470.8 | I65: =I63+I64 -> 241226.91 | J65: =J63+J64 -> 178676.47 | K65: =K63+K64 -> 126333.35 | L65: =L63+L64 -> 130108.49 | ... N65: =N63+N64 -> 121439.75
B66: Налог на прибыль (щит) | C66: тыс.руб | E66: =-E65*'Параметры'!C7 -> -42630.272 | F66: =-F65*'Параметры'!C7 -> -43627.164 | G66: =-G65*'Параметры'!C7 -> -51845.319 | H66: =-H65*'Параметры'!C7 -> -45867.7 | I66: =-I65*'Параметры'!C7 -> -60306.728 | J66: =-J65*'Параметры'!C7 -> -44669.117 | K66: =-K65*'Параметры'!C7 -> -31583.337 | L66: =-L65*'Параметры'!C7 -> -32527.123 | M66: =-M65*'Параметры'!C7 -> -56644.048 | N66: =-N65*'Параметры'!C7 -> -30359.938
B67: Операц. денежный поток | C67: тыс.руб | E67: =E65+E66-E64 -> 77933.912 | F67: =F65+F66-F64 -> 80924.588 | G67: =G65+G66-G64 -> 105579.05 | H67: =H65+H66-H64 -> 87646.194 | I67: =I65+I66-I64 -> 130963.28 | J67: =J65+J66-J64 -> 129860.93 | K67: =K65+K66-K64 -> 94750.012 | L67: =L65+L66-L64 -> 97581.368 | ... N67: =N65+N66-N64 -> 91079.815
B68: Инвестиции / остаточная ст-ть | C68: тыс.руб | D68: =IF(D$4=0,'Производительность'!F5,IF(D$4='Параметры'!C8,-'Ввод данных'!F14*'Производительность'!F5,0)) -> 253930.95 | E68: =IF(E$4=0,'Производительность'!F5,IF(E$4='Параметры'!C8,-'Ввод данных'!F14*'Производительность'!F5,0)) -> 0 | F68: =IF(F$4=0,'Производительность'!F5,IF(F$4='Параметры'!C8,-'Ввод данных'!F14*'Производительность'!F5,0)) -> 0 | G68: =IF(G$4=0,'Производительность'!F5,IF(G$4='Параметры'!C8,-'Ввод данных'!F14*'Производительность'!F5,0)) -> 0 | H68: =IF(H$4=0,'Производительность'!F5,IF(H$4='Параметры'!C8,-'Ввод данных'!F14*'Производительность'!F5,0)) -> 0 | I68: =IF(I$4=0,'Производительность'!F5,IF(I$4='Параметры'!C8,-'Ввод данных'!F14*'Производительность'!F5,0)) -> 0 | J68: =IF(J$4=0,'Производительность'!F5,IF(J$4='Параметры'!C8,-'Ввод данных'!F14*'Производительность'!F5,0)) -> 0 | K68: =IF(K$4=0,'Производительность'!F5,IF(K$4='Параметры'!C8,-'Ввод данных'!F14*'Производительность'!F5,0)) -> 0 | L68: =IF(L$4=0,'Производительность'!F5,IF(L$4='Параметры'!C8,-'Ввод данных'!F14*'Производительность'!F5,0)) -> 0 | M68: =IF(M$4=0,'Производительность'!F5,IF(M$4='Параметры'!C8,-'Ввод данных'!F14*'Производительность'!F5,0)) -> 0 | N68: =IF(N$4=0,'Производительность'!F5,IF(N$4='Параметры'!C8,-'Ввод данных'!F14*'Производительность'!F5,0)) -> 0
B69: Чистый денежный поток | C69: тыс.руб | D69: =0+D68 -> 253930.95 | E69: =E67+E68 -> 77933.912 | F69: =F67+F68 -> 80924.588 | G69: =G67+G68 -> 105579.05 | H69: =H67+H68 -> 87646.194 | I69: =I67+I68 -> 130963.28 | J69: =J67+J68 -> 129860.93 | K69: =K67+K68 -> 94750.012 | L69: =L67+L68 -> 97581.368 | ... N69: =N67+N68 -> 91079.815
B70: Дисконтированный поток | C70: тыс.руб | D70: =D69*D$6 -> 253930.95 | E70: =E69*E$6 -> 69583.85 | F70: =F69*F$6 -> 64512.586 | G70: =G69*G$6 -> 75149.085 | H70: =H69*H$6 -> 55700.741 | I70: =I69*I$6 -> 74312.082 | J70: =J69*J$6 -> 65791.587 | K70: =K69*K$6 -> 42860.094 | ... N70: =N69*N$6 -> 29325.263
B71: Кумул. дисконт. поток | C71: тыс.руб | D71: =SUM($D70:D70) -> 253930.95 | E71: =SUM($D70:E70) -> 323514.8 | F71: =SUM($D70:F70) -> 388027.39 | G71: =SUM($D70:G70) -> 463176.47 | H71: =SUM($D70:H70) -> 518877.21 | I71: =SUM($D70:I70) -> 593189.29 | J71: =SUM($D70:J70) -> 658980.88 | K71: =SUM($D70:K70) -> 701840.97 | ... N71: =SUM($D70:N70) -> 831856.95
B72: Аннуитет по году | C72: руб/ткм | E72: =SUM($D70:E70)/SUM($E$6:E$6)/(SUM($E56:E56)/E$4) -> 32.71246 | F72: =SUM($D70:F70)/SUM($E$6:F$6)/(SUM($E56:F56)/F$4) -> 21.101524 | G72: =SUM($D70:G70)/SUM($E$6:G$6)/(SUM($E56:G56)/G$4) -> 18.072744 | H72: =SUM($D70:H70)/SUM($E$6:H$6)/(SUM($E56:H56)/H$4) -> 15.998413 | I72: =SUM($D70:I70)/SUM($E$6:I$6)/(SUM($E56:I56)/I$4) -> 15.59061 | J72: =SUM($D70:J70)/SUM($E$6:J$6)/(SUM($E56:J56)/J$4) -> 15.150543 | K72: =SUM($D70:K70)/SUM($E$6:K$6)/(SUM($E56:K56)/K$4) -> 14.601463 | L72: =SUM($D70:L70)/SUM($E$6:L$6)/(SUM($E56:L56)/L$4) -> 14.139246 | ... N72: =SUM($D70:N70)/SUM($E$6:N$6)/(SUM($E56:N56)/N$4) -> 14.02617
B74: ="Вариант 4: "&'Ввод данных'!G7 -> Вариант 4: TZCO TZE240
B75: КТГ | C75: коэф. | E75: ='Данные по годам'!E16 -> 0.9096 | F75: ='Данные по годам'!F16 -> 0.8842 | G75: ='Данные по годам'!G16 -> 0.774 | H75: ='Данные по годам'!H16 -> 0.8842 | I75: ='Данные по годам'!I16 -> 0.9096 | J75: ='Данные по годам'!J16 -> 0.748 | K75: ='Данные по годам'!K16 -> 0.9096 | L75: ='Данные по годам'!L16 -> 0.8842 | ... N75: ='Данные по годам'!N16 -> 0.8842
B76: Эффективное время | C76: час/год | E76: ='Параметры'!C26*E75*(1-102.38/(60*'Параметры'!C27)) -> 6835.077 | F76: ='Параметры'!C26*F75*(1-102.38/(60*'Параметры'!C27)) -> 6644.2118 | G76: ='Параметры'!C26*G75*(1-102.38/(60*'Параметры'!C27)) -> 5816.1275 | H76: ='Параметры'!C26*H75*(1-102.38/(60*'Параметры'!C27)) -> 6644.2118 | I76: ='Параметры'!C26*I75*(1-102.38/(60*'Параметры'!C27)) -> 6835.077 | J76: ='Параметры'!C26*J75*(1-102.38/(60*'Параметры'!C27)) -> 5620.7537 | K76: ='Параметры'!C26*K75*(1-102.38/(60*'Параметры'!C27)) -> 6835.077 | L76: ='Параметры'!C26*L75*(1-102.38/(60*'Параметры'!C27)) -> 6644.2118 | M76: ='Параметры'!C26*M75*(1-102.38/(60*'Параметры'!C27)) -> 6835.077 | N76: ='Параметры'!C26*N75*(1-102.38/(60*'Параметры'!C27)) -> 6644.2118
B77: Объём перевозки | C77: тыс.т | E77: ='Производительность'!G9*E76/1000 -> 3634.6981 | F77: ='Производительность'!G9*F76/1000 -> 3533.2015 | G77: ='Производительность'!G9*G76/1000 -> 3092.85 | H77: ='Производительность'!G9*H76/1000 -> 3533.2015 | I77: ='Производительность'!G9*I76/1000 -> 3634.6981 | J77: ='Производительность'!G9*J76/1000 -> 2988.9558 | K77: ='Производительность'!G9*K76/1000 -> 3634.6981 | L77: ='Производительность'!G9*L76/1000 -> 3533.2015 | M77: ='Производительность'!G9*M76/1000 -> 3634.6981 | N77: ='Производительность'!G9*N76/1000 -> 3533.2015
B78: Грузооборот | C78: тыс.ткм | E78: =E77*'Параметры'!C28 -> 11048.028 | F78: =F77*'Параметры'!C28 -> 10739.519 | G78: =G77*'Параметры'!C28 -> 9401.0269 | H78: =H77*'Параметры'!C28 -> 10739.519 | I78: =I77*'Параметры'!C28 -> 11048.028 | J78: =J77*'Параметры'!C28 -> 9085.2301 | K78: =K77*'Параметры'!C28 -> 11048.028 | L78: =L77*'Параметры'!C28 -> 10739.519 | M78: =M77*'Параметры'!C28 -> 11048.028 | N78: =N77*'Параметры'!C28 -> 10739.519
B79: Пробег | C79: тыс.км | E79: ='Производительность'!G8*E76*2*'Параметры'!C28/1000 -> 101.18104 | F79: ='Производительность'!G8*F76*2*'Параметры'!C28/1000 -> 98.355623 | G79: ='Производительность'!G8*G76*2*'Параметры'!C28/1000 -> 86.097322 | H79: ='Производительность'!G8*H76*2*'Параметры'!C28/1000 -> 98.355623 | I79: ='Производительность'!G8*I76*2*'Параметры'!C28/1000 -> 101.18104 | J79: ='Производительность'!G8*J76*2*'Параметры'!C28/1000 -> 83.205164 | K79: ='Производительность'!G8*K76*2*'Параметры'!C28/1000 -> 101.18104 | L79: ='Производительность'!G8*L76*2*'Параметры'!C28/1000 -> 98.355623 | M79: ='Производительность'!G8*M76*2*'Параметры'!C28/1000 -> 101.18104 | N79: ='Производительность'!G8*N76*2*'Параметры'!C28/1000 -> 98.355623
B80: Топливо | C80: тыс.руб | E80: =E78*'Параметры'!C32/1000*'Параметры'!C10*(1+'Параметры'!C14)^(E$4-1) -> 65644.181 | F80: =F78*'Параметры'!C32/1000*'Параметры'!C10*(1+'Параметры'!C14)^(F$4-1) -> 63811.109 | G80: =G78*'Параметры'!C32/1000*'Параметры'!C10*(1+'Параметры'!C14)^(G$4-1) -> 55858.175 | H80: =H78*'Параметры'!C32/1000*'Параметры'!C10*(1+'Параметры'!C14)^(H$4-1) -> 63811.109 | I80: =I78*'Параметры'!C32/1000*'Параметры'!C10*(1+'Параметры'!C14)^(I$4-1) -> 65644.181 | J80: =J78*'Параметры'!C32/1000*'Параметры'!C10*(1+'Параметры'!C14)^(J$4-1) -> 53981.803 | K80: =K78*'Параметры'!C32/1000*'Параметры'!C10*(1+'Параметры'!C14)^(K$4-1) -> 65644.181 | L80: =L78*'Параметры'!C32/1000*'Параметры'!C10*(1+'Параметры'!C14)^(L$4-1) -> 63811.109 | M80: =M78*'Параметры'!C32/1000*'Параметры'!C10*(1+'Параметры'!C14)^(M$4-1) -> 65644.181 | N80: =N78*'Параметры'!C32/1000*'Параметры'!C10*(1+'Параметры'!C14)^(N$4-1) -> 63811.109
B81: ТОиР и сервис (по годам) | C81: тыс.руб | E81: ='Данные по годам'!E17*IF('Данные по годам'!$D$17="CNY",'Параметры'!C20,IF('Данные по годам'!$D$17="USD",'Параметры'!C21,IF('Данные по годам'!$D$17="EUR",'Параметры'!C22,1))) -> 28152.102 | F81: ='Данные по годам'!F17*IF('Данные по годам'!$D$17="CNY",'Параметры'!C20,IF('Данные по годам'!$D$17="USD",'Параметры'!C21,IF('Данные по годам'!$D$17="EUR",'Параметры'!C22,1))) -> 59210.396 | G81: ='Данные по годам'!G17*IF('Данные по годам'!$D$17="CNY",'Параметры'!C20,IF('Данные по годам'!$D$17="USD",'Параметры'!C21,IF('Данные по годам'!$D$17="EUR",'Параметры'!C22,1))) -> 176924.41 | H81: ='Данные по годам'!H17*IF('Данные по годам'!$D$17="CNY",'Параметры'!C20,IF('Данные по годам'!$D$17="USD",'Параметры'!C21,IF('Данные по годам'!$D$17="EUR",'Параметры'!C22,1))) -> 59210.396 | I81: ='Данные по годам'!I17*IF('Данные по годам'!$D$17="CNY",'Параметры'!C20,IF('Данные по годам'!$D$17="USD",'Параметры'!C21,IF('Данные по годам'!$D$17="EUR",'Параметры'!C22,1))) -> 28152.102 | J81: ='Данные по годам'!J17*IF('Данные по годам'!$D$17="CNY",'Параметры'!C20,IF('Данные по годам'!$D$17="USD",'Параметры'!C21,IF('Данные по годам'!$D$17="EUR",'Параметры'!C22,1))) -> 207982.61 | K81: ='Данные по годам'!K17*IF('Данные по годам'!$D$17="CNY",'Параметры'!C20,IF('Данные по годам'!$D$17="USD",'Параметры'!C21,IF('Данные по годам'!$D$17="EUR",'Параметры'!C22,1))) -> 28152.102 | L81: ='Данные по годам'!L17*IF('Данные по годам'!$D$17="CNY",'Параметры'!C20,IF('Данные по годам'!$D$17="USD",'Параметры'!C21,IF('Данные по годам'!$D$17="EUR",'Параметры'!C22,1))) -> 59210.396 | M81: ='Данные по годам'!M17*IF('Данные по годам'!$D$17="CNY",'Параметры'!C20,IF('Данные по годам'!$D$17="USD",'Параметры'!C21,IF('Данные по годам'!$D$17="EUR",'Параметры'!C22,1))) -> 28152.102 | N81: ='Данные по годам'!N17*IF('Данные по годам'!$D$17="CNY",'Параметры'!C20,IF('Данные по годам'!$D$17="USD",'Параметры'!C21,IF('Данные по годам'!$D$17="EUR",'Параметры'!C22,1))) -> 59210.396
B82: Шины | C82: тыс.руб | E82: =E79*'Параметры'!C36*'Параметры'!C37*(1+'Параметры'!C15)^(E$4-1) -> 22654.789 | F82: =F79*'Параметры'!C36*'Параметры'!C37*(1+'Параметры'!C15)^(F$4-1) -> 22022.168 | G82: =G79*'Параметры'!C36*'Параметры'!C37*(1+'Параметры'!C15)^(G$4-1) -> 19277.492 | H82: =H79*'Параметры'!C36*'Параметры'!C37*(1+'Параметры'!C15)^(H$4-1) -> 22022.168 | I82: =I79*'Параметры'!C36*'Параметры'!C37*(1+'Параметры'!C15)^(I$4-1) -> 22654.789 | J82: =J79*'Параметры'!C36*'Параметры'!C37*(1+'Параметры'!C15)^(J$4-1) -> 18629.927 | K82: =K79*'Параметры'!C36*'Параметры'!C37*(1+'Параметры'!C15)^(K$4-1) -> 22654.789 | L82: =L79*'Параметры'!C36*'Параметры'!C37*(1+'Параметры'!C15)^(L$4-1) -> 22022.168 | M82: =M79*'Параметры'!C36*'Параметры'!C37*(1+'Параметры'!C15)^(M$4-1) -> 22654.789 | N82: =N79*'Параметры'!C36*'Параметры'!C37*(1+'Параметры'!C15)^(N$4-1) -> 22022.168
B83: Персонал | C83: тыс.руб | E83: ='Ввод данных'!G18*(1+'Параметры'!C16)^(E$4-1) -> 18475.6 | F83: ='Ввод данных'!G18*(1+'Параметры'!C16)^(F$4-1) -> 18475.6 | G83: ='Ввод данных'!G18*(1+'Параметры'!C16)^(G$4-1) -> 18475.6 | H83: ='Ввод данных'!G18*(1+'Параметры'!C16)^(H$4-1) -> 18475.6 | I83: ='Ввод данных'!G18*(1+'Параметры'!C16)^(I$4-1) -> 18475.6 | J83: ='Ввод данных'!G18*(1+'Параметры'!C16)^(J$4-1) -> 18475.6 | K83: ='Ввод данных'!G18*(1+'Параметры'!C16)^(K$4-1) -> 18475.6 | L83: ='Ввод данных'!G18*(1+'Параметры'!C16)^(L$4-1) -> 18475.6 | M83: ='Ввод данных'!G18*(1+'Параметры'!C16)^(M$4-1) -> 18475.6 | N83: ='Ввод данных'!G18*(1+'Параметры'!C16)^(N$4-1) -> 18475.6
B84: Транспортный налог | C84: тыс.руб | E84: ='Ввод данных'!G19*'Параметры'!C41/1000 -> 212.5 | F84: ='Ввод данных'!G19*'Параметры'!C41/1000 -> 212.5 | G84: ='Ввод данных'!G19*'Параметры'!C41/1000 -> 212.5 | H84: ='Ввод данных'!G19*'Параметры'!C41/1000 -> 212.5 | I84: ='Ввод данных'!G19*'Параметры'!C41/1000 -> 212.5 | J84: ='Ввод данных'!G19*'Параметры'!C41/1000 -> 212.5 | K84: ='Ввод данных'!G19*'Параметры'!C41/1000 -> 212.5 | L84: ='Ввод данных'!G19*'Параметры'!C41/1000 -> 212.5 | M84: ='Ввод данных'!G19*'Параметры'!C41/1000 -> 212.5 | N84: ='Ввод данных'!G19*'Параметры'!C41/1000 -> 212.5
B85: Итого денежные затраты | C85: тыс.руб | E85: =E80+E81+E82+E83+E84 -> 135139.17 | F85: =F80+F81+F82+F83+F84 -> 163731.77 | G85: =G80+G81+G82+G83+G84 -> 270748.18 | H85: =H80+H81+H82+H83+H84 -> 163731.77 | I85: =I80+I81+I82+I83+I84 -> 135139.17 | J85: =J80+J81+J82+J83+J84 -> 299282.44 | K85: =K80+K81+K82+K83+K84 -> 135139.17 | L85: =L80+L81+L82+L83+L84 -> 163731.77 | ... N85: =N80+N81+N82+N83+N84 -> 163731.77
B86: Амортизация (НУ) | C86: тыс.руб | E86: =IF(E$4<=INT('Параметры'!C9),'Производительность'!G5/'Параметры'!C9,IF(E$4=INT('Параметры'!C9)+1,'Производительность'!G5*('Параметры'!C9-INT('Параметры'!C9))/'Параметры'!C9,0)) -> 49956.905 | F86: =IF(F$4<=INT('Параметры'!C9),'Производительность'!G5/'Параметры'!C9,IF(F$4=INT('Параметры'!C9)+1,'Производительность'!G5*('Параметры'!C9-INT('Параметры'!C9))/'Параметры'!C9,0)) -> 49956.905 | G86: =IF(G$4<=INT('Параметры'!C9),'Производительность'!G5/'Параметры'!C9,IF(G$4=INT('Параметры'!C9)+1,'Производительность'!G5*('Параметры'!C9-INT('Параметры'!C9))/'Параметры'!C9,0)) -> 49956.905 | H86: =IF(H$4<=INT('Параметры'!C9),'Производительность'!G5/'Параметры'!C9,IF(H$4=INT('Параметры'!C9)+1,'Производительность'!G5*('Параметры'!C9-INT('Параметры'!C9))/'Параметры'!C9,0)) -> 49956.905 | I86: =IF(I$4<=INT('Параметры'!C9),'Производительность'!G5/'Параметры'!C9,IF(I$4=INT('Параметры'!C9)+1,'Производительность'!G5*('Параметры'!C9-INT('Параметры'!C9))/'Параметры'!C9,0)) -> 49956.905 | J86: =IF(J$4<=INT('Параметры'!C9),'Производительность'!G5/'Параметры'!C9,IF(J$4=INT('Параметры'!C9)+1,'Производительность'!G5*('Параметры'!C9-INT('Параметры'!C9))/'Параметры'!C9,0)) -> 4146.4231 | K86: =IF(K$4<=INT('Параметры'!C9),'Производительность'!G5/'Параметры'!C9,IF(K$4=INT('Параметры'!C9)+1,'Производительность'!G5*('Параметры'!C9-INT('Параметры'!C9))/'Параметры'!C9,0)) -> 0 | L86: =IF(L$4<=INT('Параметры'!C9),'Производительность'!G5/'Параметры'!C9,IF(L$4=INT('Параметры'!C9)+1,'Производительность'!G5*('Параметры'!C9-INT('Параметры'!C9))/'Параметры'!C9,0)) -> 0 | M86: =IF(M$4<=INT('Параметры'!C9),'Производительность'!G5/'Параметры'!C9,IF(M$4=INT('Параметры'!C9)+1,'Производительность'!G5*('Параметры'!C9-INT('Параметры'!C9))/'Параметры'!C9,0)) -> 0 | N86: =IF(N$4<=INT('Параметры'!C9),'Производительность'!G5/'Параметры'!C9,IF(N$4=INT('Параметры'!C9)+1,'Производительность'!G5*('Параметры'!C9-INT('Параметры'!C9))/'Параметры'!C9,0)) -> 0
B87: Налогооблагаемая база | C87: тыс.руб | E87: =E85+E86 -> 185096.08 | F87: =F85+F86 -> 213688.68 | G87: =G85+G86 -> 320705.09 | H87: =H85+H86 -> 213688.68 | I87: =I85+I86 -> 185096.08 | J87: =J85+J86 -> 303428.87 | K87: =K85+K86 -> 135139.17 | L87: =L85+L86 -> 163731.77 | ... N87: =N85+N86 -> 163731.77
B88: Налог на прибыль (щит) | C88: тыс.руб | E88: =-E87*'Параметры'!C7 -> -46274.019 | F88: =-F87*'Параметры'!C7 -> -53422.17 | G88: =-G87*'Параметры'!C7 -> -80176.272 | H88: =-H87*'Параметры'!C7 -> -53422.17 | I88: =-I87*'Параметры'!C7 -> -46274.019 | J88: =-J87*'Параметры'!C7 -> -75857.217 | K88: =-K87*'Параметры'!C7 -> -33784.793 | L88: =-L87*'Параметры'!C7 -> -40932.943 | M88: =-M87*'Параметры'!C7 -> -33784.793 | N88: =-N87*'Параметры'!C7 -> -40932.943
B89: Операц. денежный поток | C89: тыс.руб | E89: =E87+E88-E86 -> 88865.153 | F89: =F87+F88-F86 -> 110309.6 | G89: =G87+G88-G86 -> 190571.91 | H89: =H87+H88-H86 -> 110309.6 | I89: =I87+I88-I86 -> 88865.153 | J89: =J87+J88-J86 -> 223425.23 | K89: =K87+K88-K86 -> 101354.38 | L89: =L87+L88-L86 -> 122798.83 | ... N89: =N87+N88-N86 -> 122798.83
B90: Инвестиции / остаточная ст-ть | C90: тыс.руб | D90: =IF(D$4=0,'Производительность'!G5,IF(D$4='Параметры'!C8,-'Ввод данных'!G14*'Производительность'!G5,0)) -> 253930.95 | E90: =IF(E$4=0,'Производительность'!G5,IF(E$4='Параметры'!C8,-'Ввод данных'!G14*'Производительность'!G5,0)) -> 0 | F90: =IF(F$4=0,'Производительность'!G5,IF(F$4='Параметры'!C8,-'Ввод данных'!G14*'Производительность'!G5,0)) -> 0 | G90: =IF(G$4=0,'Производительность'!G5,IF(G$4='Параметры'!C8,-'Ввод данных'!G14*'Производительность'!G5,0)) -> 0 | H90: =IF(H$4=0,'Производительность'!G5,IF(H$4='Параметры'!C8,-'Ввод данных'!G14*'Производительность'!G5,0)) -> 0 | I90: =IF(I$4=0,'Производительность'!G5,IF(I$4='Параметры'!C8,-'Ввод данных'!G14*'Производительность'!G5,0)) -> 0 | J90: =IF(J$4=0,'Производительность'!G5,IF(J$4='Параметры'!C8,-'Ввод данных'!G14*'Производительность'!G5,0)) -> 0 | K90: =IF(K$4=0,'Производительность'!G5,IF(K$4='Параметры'!C8,-'Ввод данных'!G14*'Производительность'!G5,0)) -> 0 | L90: =IF(L$4=0,'Производительность'!G5,IF(L$4='Параметры'!C8,-'Ввод данных'!G14*'Производительность'!G5,0)) -> 0 | M90: =IF(M$4=0,'Производительность'!G5,IF(M$4='Параметры'!C8,-'Ввод данных'!G14*'Производительность'!G5,0)) -> 0 | N90: =IF(N$4=0,'Производительность'!G5,IF(N$4='Параметры'!C8,-'Ввод данных'!G14*'Производительность'!G5,0)) -> 0
B91: Чистый денежный поток | C91: тыс.руб | D91: =0+D90 -> 253930.95 | E91: =E89+E90 -> 88865.153 | F91: =F89+F90 -> 110309.6 | G91: =G89+G90 -> 190571.91 | H91: =H89+H90 -> 110309.6 | I91: =I89+I90 -> 88865.153 | J91: =J89+J90 -> 223425.23 | K91: =K89+K90 -> 101354.38 | L91: =L89+L90 -> 122798.83 | ... N91: =N89+N90 -> 122798.83
B92: Дисконтированный поток | C92: тыс.руб | D92: =D91*D$6 -> 253930.95 | E92: =E91*E$6 -> 79343.886 | F92: =F91*F$6 -> 87938.141 | G92: =G91*G$6 -> 135645.32 | H92: =H91*H$6 -> 70103.748 | I92: =I91*I$6 -> 50424.474 | J92: =J91*J$6 -> 113194.17 | K92: =K91*K$6 -> 45847.574 | ... N92: =N91*N$6 -> 39537.937
B93: Кумул. дисконт. поток | C93: тыс.руб | D93: =SUM($D92:D92) -> 253930.95 | E93: =SUM($D92:E92) -> 333274.84 | F93: =SUM($D92:F92) -> 421212.98 | G93: =SUM($D92:G92) -> 556858.3 | H93: =SUM($D92:H92) -> 626962.05 | I93: =SUM($D92:I92) -> 677386.52 | J93: =SUM($D92:J92) -> 790580.69 | K93: =SUM($D92:K92) -> 836428.27 | ... N93: =SUM($D92:N92) -> 962112
B94: Аннуитет по году | C94: руб/ткм | E94: =SUM($D92:E92)/SUM($E$6:E$6)/(SUM($E78:E78)/E$4) -> 33.785921 | F94: =SUM($D92:F92)/SUM($E$6:F$6)/(SUM($E78:F78)/F$4) -> 22.87829 | G94: =SUM($D92:G92)/SUM($E$6:G$6)/(SUM($E78:G78)/G$4) -> 22.301184 | H94: =SUM($D92:H92)/SUM($E$6:H$6)/(SUM($E78:H78)/H$4) -> 19.692524 | I94: =SUM($D92:I92)/SUM($E$6:I$6)/(SUM($E78:I78)/I$4) -> 17.73569 | J94: =SUM($D92:J92)/SUM($E$6:J$6)/(SUM($E78:J78)/J$4) -> 18.590271 | K94: =SUM($D92:K92)/SUM($E$6:K$6)/(SUM($E78:K78)/K$4) -> 17.548143 | L94: =SUM($D92:L92)/SUM($E$6:L$6)/(SUM($E78:L78)/L$4) -> 17.017209 | ... N94: =SUM($D92:N92)/SUM($E$6:N$6)/(SUM($E78:N78)/N$4) -> 16.119303
B96: ="Вариант 5: "&'Ввод данных'!H7 -> Вариант 5: БелАЗ 7531 (ГПФК)
B97: КТГ | C97: коэф. | E97: ='Данные по годам'!E19 -> 0.9083 | F97: ='Данные по годам'!F19 -> 0.8858 | G97: ='Данные по годам'!G19 -> 0.8646 | H97: ='Данные по годам'!H19 -> 0.8748 | I97: ='Данные по годам'!I19 -> 0.8813 | J97: ='Данные по годам'!J19 -> 0.8464 | K97: ='Данные по годам'!K19 -> 0.8971 | L97: ='Данные по годам'!L19 -> 0.8546 | ... N97: ='Данные по годам'!N19 -> 0.8611
B98: Эффективное время | C98: час/год | E98: ='Параметры'!C26*E97*(1-102.38/(60*'Параметры'!C27)) -> 6825.3083 | F98: ='Параметры'!C26*F97*(1-102.38/(60*'Параметры'!C27)) -> 6656.2349 | G98: ='Параметры'!C26*G97*(1-102.38/(60*'Параметры'!C27)) -> 6496.9301 | H98: ='Параметры'!C26*H97*(1-102.38/(60*'Параметры'!C27)) -> 6573.5767 | I98: ='Параметры'!C26*I97*(1-102.38/(60*'Параметры'!C27)) -> 6622.4202 | J98: ='Параметры'!C26*J97*(1-102.38/(60*'Параметры'!C27)) -> 6360.1684 | K98: ='Параметры'!C26*K97*(1-102.38/(60*'Параметры'!C27)) -> 6741.1473 | L98: ='Параметры'!C26*L97*(1-102.38/(60*'Параметры'!C27)) -> 6421.7863 | M98: ='Параметры'!C26*M97*(1-102.38/(60*'Параметры'!C27)) -> 6327.1052 | N98: ='Параметры'!C26*N97*(1-102.38/(60*'Параметры'!C27)) -> 6470.6297
B99: Объём перевозки | C99: тыс.т | E99: ='Производительность'!H9*E98/1000 -> 3776.6455 | F99: ='Производительность'!H9*F98/1000 -> 3683.0921 | G99: ='Производительность'!H9*G98/1000 -> 3594.944 | H99: ='Производительность'!H9*H98/1000 -> 3637.3549 | I99: ='Производительность'!H9*I98/1000 -> 3664.3814 | J99: ='Производительность'!H9*J98/1000 -> 3519.2698 | K99: ='Производительность'!H9*K98/1000 -> 3730.0767 | L99: ='Производительность'!H9*L98/1000 -> 3553.3648 | M99: ='Производительность'!H9*M98/1000 -> 3500.9749 | N99: ='Производительность'!H9*N98/1000 -> 3580.3913
B100: Грузооборот | C100: тыс.ткм | E100: =E99*'Параметры'!C28 -> 11479.492 | F100: =F99*'Параметры'!C28 -> 11195.127 | G100: =G99*'Параметры'!C28 -> 10927.192 | H100: =H99*'Параметры'!C28 -> 11056.104 | I100: =I99*'Параметры'!C28 -> 11138.254 | J100: =J99*'Параметры'!C28 -> 10697.172 | K100: =K99*'Параметры'!C28 -> 11337.941 | L100: =L99*'Параметры'!C28 -> 10800.808 | M100: =M99*'Параметры'!C28 -> 10641.563 | N100: =N99*'Параметры'!C28 -> 10882.957
B101: Пробег | C101: тыс.км | E101: ='Производительность'!H8*E98*2*'Параметры'!C28/1000 -> 101.03643 | F101: ='Производительность'!H8*F98*2*'Параметры'!C28/1000 -> 98.533602 | G101: ='Производительность'!H8*G98*2*'Параметры'!C28/1000 -> 96.175381 | H101: ='Производительность'!H8*H98*2*'Параметры'!C28/1000 -> 97.309997 | I101: ='Производительность'!H8*I98*2*'Параметры'!C28/1000 -> 98.033036 | J101: ='Производительность'!H8*J98*2*'Параметры'!C28/1000 -> 94.15087 | K101: ='Производительность'!H8*K98*2*'Параметры'!C28/1000 -> 99.790578 | L101: ='Производительность'!H8*L98*2*'Параметры'!C28/1000 -> 95.063012 | M101: ='Производительность'!H8*M98*2*'Параметры'!C28/1000 -> 93.661428 | N101: ='Производительность'!H8*N98*2*'Параметры'!C28/1000 -> 95.786052
B102: Топливо | C102: тыс.руб | E102: =E100*'Параметры'!C32/1000*'Параметры'!C10*(1+'Параметры'!C14)^(E$4-1) -> 68207.81 | F102: =F100*'Параметры'!C32/1000*'Параметры'!C10*(1+'Параметры'!C14)^(F$4-1) -> 66518.197 | G102: =G100*'Параметры'!C32/1000*'Параметры'!C10*(1+'Параметры'!C14)^(G$4-1) -> 64926.205 | H102: =H100*'Параметры'!C32/1000*'Параметры'!C10*(1+'Параметры'!C14)^(H$4-1) -> 65692.163 | I102: =I100*'Параметры'!C32/1000*'Параметры'!C10*(1+'Параметры'!C14)^(I$4-1) -> 66180.274 | J102: =J100*'Параметры'!C32/1000*'Параметры'!C10*(1+'Параметры'!C14)^(J$4-1) -> 63559.496 | K102: =K100*'Параметры'!C32/1000*'Параметры'!C10*(1+'Параметры'!C14)^(K$4-1) -> 67366.758 | L102: =L100*'Параметры'!C32/1000*'Параметры'!C10*(1+'Параметры'!C14)^(L$4-1) -> 64175.266 | M102: =M100*'Параметры'!C32/1000*'Параметры'!C10*(1+'Параметры'!C14)^(M$4-1) -> 63229.083 | N102: =N100*'Параметры'!C32/1000*'Параметры'!C10*(1+'Параметры'!C14)^(N$4-1) -> 64663.377
B103: ТОиР и сервис (по годам) | C103: тыс.руб | E103: ='Данные по годам'!E20*IF('Данные по годам'!$D$20="CNY",'Параметры'!C20,IF('Данные по годам'!$D$20="USD",'Параметры'!C21,IF('Данные по годам'!$D$20="EUR",'Параметры'!C22,1))) -> 13923.598 | F103: ='Данные по годам'!F20*IF('Данные по годам'!$D$20="CNY",'Параметры'!C20,IF('Данные по годам'!$D$20="USD",'Параметры'!C21,IF('Данные по годам'!$D$20="EUR",'Параметры'!C22,1))) -> 29869.898 | G103: ='Данные по годам'!G20*IF('Данные по годам'!$D$20="CNY",'Параметры'!C20,IF('Данные по годам'!$D$20="USD",'Параметры'!C21,IF('Данные по годам'!$D$20="EUR",'Параметры'!C22,1))) -> 53802.137 | H103: ='Данные по годам'!H20*IF('Данные по годам'!$D$20="CNY",'Параметры'!C20,IF('Данные по годам'!$D$20="USD",'Параметры'!C21,IF('Данные по годам'!$D$20="EUR",'Параметры'!C22,1))) -> 68373.824 | I103: ='Данные по годам'!I20*IF('Данные по годам'!$D$20="CNY",'Параметры'!C20,IF('Данные по годам'!$D$20="USD",'Параметры'!C21,IF('Данные по годам'!$D$20="EUR",'Параметры'!C22,1))) -> 59403.196 | J103: ='Данные по годам'!J20*IF('Данные по годам'!$D$20="CNY",'Параметры'!C20,IF('Данные по годам'!$D$20="USD",'Параметры'!C21,IF('Данные по годам'!$D$20="EUR",'Параметры'!C22,1))) -> 64763.584 | K103: ='Данные по годам'!K20*IF('Данные по годам'!$D$20="CNY",'Параметры'!C20,IF('Данные по годам'!$D$20="USD",'Параметры'!C21,IF('Данные по годам'!$D$20="EUR",'Параметры'!C22,1))) -> 16975.284 | L103: ='Данные по годам'!L20*IF('Данные по годам'!$D$20="CNY",'Параметры'!C20,IF('Данные по годам'!$D$20="USD",'Параметры'!C21,IF('Данные по годам'!$D$20="EUR",'Параметры'!C22,1))) -> 79677.325 | M103: ='Данные по годам'!M20*IF('Данные по годам'!$D$20="CNY",'Параметры'!C20,IF('Данные по годам'!$D$20="USD",'Параметры'!C21,IF('Данные по годам'!$D$20="EUR",'Параметры'!C22,1))) -> 90451.145 | N103: ='Данные по годам'!N20*IF('Данные по годам'!$D$20="CNY",'Параметры'!C20,IF('Данные по годам'!$D$20="USD",'Параметры'!C21,IF('Данные по годам'!$D$20="EUR",'Параметры'!C22,1))) -> 21773.074
B104: Шины | C104: тыс.руб | E104: =E101*'Параметры'!C36*'Параметры'!C37*(1+'Параметры'!C15)^(E$4-1) -> 22622.411 | F104: =F101*'Параметры'!C36*'Параметры'!C37*(1+'Параметры'!C15)^(F$4-1) -> 22062.018 | G104: =G101*'Параметры'!C36*'Параметры'!C37*(1+'Параметры'!C15)^(G$4-1) -> 21534.004 | H104: =H101*'Параметры'!C36*'Параметры'!C37*(1+'Параметры'!C15)^(H$4-1) -> 21788.049 | I104: =I101*'Параметры'!C36*'Параметры'!C37*(1+'Параметры'!C15)^(I$4-1) -> 21949.94 | J104: =J101*'Параметры'!C36*'Параметры'!C37*(1+'Параметры'!C15)^(J$4-1) -> 21080.709 | K104: =K101*'Параметры'!C36*'Параметры'!C37*(1+'Параметры'!C15)^(K$4-1) -> 22343.46 | L104: =L101*'Параметры'!C36*'Параметры'!C37*(1+'Параметры'!C15)^(L$4-1) -> 21284.941 | M104: =M101*'Параметры'!C36*'Параметры'!C37*(1+'Параметры'!C15)^(M$4-1) -> 20971.122 | N104: =N101*'Параметры'!C36*'Параметры'!C37*(1+'Параметры'!C15)^(N$4-1) -> 21446.832
B105: Персонал | C105: тыс.руб | E105: ='Ввод данных'!H18*(1+'Параметры'!C16)^(E$4-1) -> 18475.6 | F105: ='Ввод данных'!H18*(1+'Параметры'!C16)^(F$4-1) -> 18475.6 | G105: ='Ввод данных'!H18*(1+'Параметры'!C16)^(G$4-1) -> 18475.6 | H105: ='Ввод данных'!H18*(1+'Параметры'!C16)^(H$4-1) -> 18475.6 | I105: ='Ввод данных'!H18*(1+'Параметры'!C16)^(I$4-1) -> 18475.6 | J105: ='Ввод данных'!H18*(1+'Параметры'!C16)^(J$4-1) -> 18475.6 | K105: ='Ввод данных'!H18*(1+'Параметры'!C16)^(K$4-1) -> 18475.6 | L105: ='Ввод данных'!H18*(1+'Параметры'!C16)^(L$4-1) -> 18475.6 | M105: ='Ввод данных'!H18*(1+'Параметры'!C16)^(M$4-1) -> 18475.6 | N105: ='Ввод данных'!H18*(1+'Параметры'!C16)^(N$4-1) -> 18475.6
B106: Транспортный налог | C106: тыс.руб | E106: ='Ввод данных'!H19*'Параметры'!C41/1000 -> 215.475 | F106: ='Ввод данных'!H19*'Параметры'!C41/1000 -> 215.475 | G106: ='Ввод данных'!H19*'Параметры'!C41/1000 -> 215.475 | H106: ='Ввод данных'!H19*'Параметры'!C41/1000 -> 215.475 | I106: ='Ввод данных'!H19*'Параметры'!C41/1000 -> 215.475 | J106: ='Ввод данных'!H19*'Параметры'!C41/1000 -> 215.475 | K106: ='Ввод данных'!H19*'Параметры'!C41/1000 -> 215.475 | L106: ='Ввод данных'!H19*'Параметры'!C41/1000 -> 215.475 | M106: ='Ввод данных'!H19*'Параметры'!C41/1000 -> 215.475 | N106: ='Ввод данных'!H19*'Параметры'!C41/1000 -> 215.475
...

Sheet Расчёт аннуитета
B1: РАСЧЁТ АННУИТЕТА (СВОД)
B2: Приведённые NPV затрат из погодового движка → аннуитет руб/ткм и руб/т.
B4: Статья | C4: Ед. | D4: ='Ввод данных'!D7 -> NHL NTE 240 | E4: ='Ввод данных'!E7 -> Estar ESDE240 (ГПБ К) | F4: ='Ввод данных'!F7 -> SANY SET240S | G4: ='Ввод данных'!G7 -> TZCO TZE240 | H4: ='Ввод данных'!H7 -> БелАЗ 7531 (ГПФК) | I4: ='Ввод данных'!I7 -> БелАЗ 7531 (БТЛ)
B5: ПРИВЕДЁННЫЕ ЗАТРАТЫ ЗА ЖИЗНЕННЫЙ ЦИКЛ (NPV, тыс.руб)
B6: NPV топлива | C6: тыс.руб | D6: =SUMPRODUCT('Денежный поток'!E14:N14,'Денежный поток'!$E$6:$N$6) -> 387173.73 | E6: =SUMPRODUCT('Денежный поток'!E36:N36,'Денежный поток'!$E$6:$N$6) -> 335209.4 | F6: =SUMPRODUCT('Денежный поток'!E58:N58,'Денежный поток'!$E$6:$N$6) -> 354096.71 | G6: =SUMPRODUCT('Денежный поток'!E80:N80,'Денежный поток'!$E$6:$N$6) -> 354073.44 | H6: =SUMPRODUCT('Денежный поток'!E102:N102,'Денежный поток'!$E$6:$N$6) -> 371656.69 | I6: =SUMPRODUCT('Денежный поток'!E124:N124,'Денежный поток'!$E$6:$N$6) -> 378094.1
B7: NPV ТОиР (по годам, вкл. капремонты) | C7: тыс.руб | D7: =SUMPRODUCT('Денежный поток'!E15:N15,'Денежный поток'!$E$6:$N$6) -> 143128.8 | E7: =SUMPRODUCT('Денежный поток'!E37:N37,'Денежный поток'!$E$6:$N$6) -> 444902.2 | F7: =SUMPRODUCT('Денежный поток'!E59:N59,'Денежный поток'!$E$6:$N$6) -> 246054.2 | G7: =SUMPRODUCT('Денежный поток'!E81:N81,'Денежный поток'!$E$6:$N$6) -> 423108.04 | H7: =SUMPRODUCT('Денежный поток'!E103:N103,'Денежный поток'!$E$6:$N$6) -> 263997.23 | I7: =SUMPRODUCT('Денежный поток'!E125:N125,'Денежный поток'!$E$6:$N$6) -> 260275.87
B8: NPV шин | C8: тыс.руб | D8: =SUMPRODUCT('Денежный поток'!E16:N16,'Денежный поток'!$E$6:$N$6) -> 130217.37 | E8: =SUMPRODUCT('Денежный поток'!E38:N38,'Денежный поток'!$E$6:$N$6) -> 121491.08 | F8: =SUMPRODUCT('Денежный поток'!E60:N60,'Денежный поток'!$E$6:$N$6) -> 125388.49 | G8: =SUMPRODUCT('Денежный поток'!E82:N82,'Денежный поток'!$E$6:$N$6) -> 122196.04 | H8: =SUMPRODUCT('Денежный поток'!E104:N104,'Денежный поток'!$E$6:$N$6) -> 123266.97 | I8: =SUMPRODUCT('Денежный поток'!E126:N126,'Денежный поток'!$E$6:$N$6) -> 125402.06
B9: NPV персонала | C9: тыс.руб | D9: =SUMPRODUCT('Денежный поток'!E17:N17,'Денежный поток'!$E$6:$N$6) -> 104391.26 | E9: =SUMPRODUCT('Денежный поток'!E39:N39,'Денежный поток'!$E$6:$N$6) -> 104391.26 | F9: =SUMPRODUCT('Денежный поток'!E61:N61,'Денежный поток'!$E$6:$N$6) -> 104391.26 | G9: =SUMPRODUCT('Денежный поток'!E83:N83,'Денежный поток'!$E$6:$N$6) -> 104391.26 | H9: =SUMPRODUCT('Денежный поток'!E105:N105,'Денежный поток'!$E$6:$N$6) -> 104391.26 | I9: =SUMPRODUCT('Денежный поток'!E127:N127,'Денежный поток'!$E$6:$N$6) -> 104391.26
B10: NPV транспортного налога | C10: тыс.руб | D10: =SUMPRODUCT('Денежный поток'!E18:N18,'Денежный поток'!$E$6:$N$6) -> 1200.6724 | E10: =SUMPRODUCT('Денежный поток'!E40:N40,'Денежный поток'!$E$6:$N$6) -> 895.22134 | F10: =SUMPRODUCT('Денежный поток'!E62:N62,'Денежный поток'!$E$6:$N$6) -> 1365.4046 | G10: =SUMPRODUCT('Денежный поток'!E84:N84,'Денежный поток'!$E$6:$N$6) -> 1200.6724 | H10: =SUMPRODUCT('Денежный поток'!E106:N106,'Денежный поток'!$E$6:$N$6) -> 1217.4818 | I10: =SUMPRODUCT('Денежный поток'!E128:N128,'Денежный поток'!$E$6:$N$6) -> 1217.4818
B11: NPV налога (щит) | C11: тыс.руб | D11: =SUMPRODUCT('Денежный поток'!E22:N22,'Денежный поток'!$E$6:$N$6) -> -237338.21 | E11: =SUMPRODUCT('Денежный поток'!E44:N44,'Денежный поток'!$E$6:$N$6) -> -298955.22 | F11: =SUMPRODUCT('Денежный поток'!E66:N66,'Денежный поток'!$E$6:$N$6) -> -253370.06 | G11: =SUMPRODUCT('Денежный поток'!E88:N88,'Денежный поток'!$E$6:$N$6) -> -296788.41 | H11: =SUMPRODUCT('Денежный поток'!E110:N110,'Денежный поток'!$E$6:$N$6) -> -269941.58 | I11: =SUMPRODUCT('Денежный поток'!E132:N132,'Денежный поток'!$E$6:$N$6) -> -269360.72
B12: NPV инвестиций (за вычетом остат.) | C12: тыс.руб | D12: ='Производительность'!D5*(1-'Ввод данных'!D14*'Денежный поток'!$N$6) -> 255404 | E12: ='Производительность'!E5*(1-'Ввод данных'!E14*'Денежный поток'!$N$6) -> 263335.8 | F12: ='Производительность'!F5*(1-'Ввод данных'!F14*'Денежный поток'!$N$6) -> 253930.95 | G12: ='Производительность'!G5*(1-'Ввод данных'!G14*'Денежный поток'!$N$6) -> 253930.95 | H12: ='Производительность'!H5*(1-'Ввод данных'!H14*'Денежный поток'!$N$6) -> 300000 | I12: ='Производительность'!I5*(1-'Ввод данных'!I14*'Денежный поток'!$N$6) -> 290000
B13: NPV операционных затрат | C13: тыс.руб | D13: =D6+D7+D8+D9+D10+D11 -> 528773.62 | E13: =E6+E7+E8+E9+E10+E11 -> 707933.94 | F13: =F6+F7+F8+F9+F10+F11 -> 577926 | G13: =G6+G7+G8+G9+G10+G11 -> 708181.05 | H13: =H6+H7+H8+H9+H10+H11 -> 594588.06 | I13: =I6+I7+I8+I9+I10+I11 -> 600020.05
B14: NPV полной стоимости владения | C14: тыс.руб | D14: =D12+D13 -> 784177.62 | E14: =E12+E13 -> 971269.74 | F14: =F12+F13 -> 831856.95 | G14: =G12+G13 -> 962112 | H14: =H12+H13 -> 894588.06 | I14: =I12+I13 -> 890020.05
B15: Средний годовой грузооборот | C15: тыс.ткм/год | D15: =AVERAGE('Денежный поток'!E12:N12) -> 11521.128 | E15: =AVERAGE('Денежный поток'!E34:N34) -> 9915.3442 | F15: =AVERAGE('Денежный поток'!E56:N56) -> 10496.487 | G15: =AVERAGE('Денежный поток'!E78:N78) -> 10563.645 | H15: =AVERAGE('Денежный поток'!E100:N100) -> 11015.661 | I15: =AVERAGE('Денежный поток'!E122:N122) -> 11174.905
B16: Средний годовой объём перевозки | C16: тыс.т/год | D16: =AVERAGE('Денежный поток'!E11:N11) -> 3790.3436 | E16: =AVERAGE('Денежный поток'!E33:N33) -> 3262.0556 | F16: =AVERAGE('Денежный поток'!E55:N55) -> 3453.246 | G16: =AVERAGE('Денежный поток'!E77:N77) -> 3475.3404 | H16: =AVERAGE('Денежный поток'!E99:N99) -> 3624.0495 | I16: =AVERAGE('Денежный поток'!E121:N121) -> 3676.4394
B17: УДЕЛЬНЫЙ АННУИТЕТ (руб/ткм) — ГЛАВНЫЙ КРИТЕРИЙ
B18: Инвестиционный | C18: руб/ткм | D18: =D12/'Параметры'!C45/D15 -> 3.9234407 | E18: =E12/'Параметры'!C45/E15 -> 4.7004184 | F18: =F12/'Параметры'!C45/F15 -> 4.2816 | G18: =G12/'Параметры'!C45/G15 -> 4.2543798 | H18: =H12/'Параметры'!C45/H15 -> 4.8199785 | I18: =I12/'Параметры'!C45/I15 -> 4.5929166
B19: Топливо | C19: руб/ткм | D19: =D6/'Параметры'!C45/D15 -> 5.9476483 | E19: =E6/'Параметры'!C45/E15 -> 5.9833279 | F19: =F6/'Параметры'!C45/F15 -> 5.9705226 | G19: =G6/'Параметры'!C45/G15 -> 5.9321753 | H19: =H6/'Параметры'!C45/H15 -> 5.9712576 | I19: =I6/'Параметры'!C45/I15 -> 5.9881195
B20: ТОиР + капремонты | C20: руб/ткм | D20: =D7/'Параметры'!C45/D15 -> 2.1987022 | E20: =E7/'Параметры'!C45/E15 -> 7.941292 | F20: =F7/'Параметры'!C45/F15 -> 4.1487879 | G20: =G7/'Параметры'!C45/G15 -> 7.0887864 | H20: =H7/'Параметры'!C45/H15 -> 4.2415366 | I20: =I7/'Параметры'!C45/I15 -> 4.1221565
B21: Шины | C21: руб/ткм | D21: =D8/'Параметры'!C45/D15 -> 2.0003607 | E21: =E8/'Параметры'!C45/E15 -> 2.1685578 | F21: =F8/'Параметры'!C45/F15 -> 2.1142099 | G21: =G8/'Параметры'!C45/G15 -> 2.0472824 | H21: =H8/'Параметры'!C45/H15 -> 1.9804805 | I21: =I8/'Параметры'!C45/I15 -> 1.9860731
B22: Персонал | C22: руб/ткм | D22: =D9/'Параметры'!C45/D15 -> 1.6036276 | E22: =E9/'Параметры'!C45/E15 -> 1.8633342 | F22: =F9/'Параметры'!C45/F15 -> 1.7601699 | G22: =G9/'Параметры'!C45/G15 -> 1.7489797 | H22: =H9/'Параметры'!C45/H15 -> 1.6772121 | I22: =I9/'Параметры'!C45/I15 -> 1.6533116
B23: Транспортный налог | C23: руб/ткм | D23: =D10/'Параметры'!C45/D15 -> 0.018444374 | E23: =E10/'Параметры'!C45/E15 -> 0.015979274 | F23: =F10/'Параметры'!C45/F15 -> 0.023022466 | G23: =G10/'Параметры'!C45/G15 -> 0.020116163 | H23: =H10/'Параметры'!C45/H15 -> 0.019560787 | I23: =I10/'Параметры'!C45/I15 -> 0.019282043
B24: Налог на прибыль (щит) | C24: руб/ткм | D24: =D11/'Параметры'!C45/D15 -> -3.6459194 | E24: =E11/'Параметры'!C45/E15 -> -5.3362081 | F24: =F11/'Параметры'!C45/F15 -> -4.2721426 | G24: =G11/'Параметры'!C45/G15 -> -4.9724171 | H24: =H11/'Параметры'!C45/H15 -> -4.337042 | I24: =I11/'Параметры'!C45/I15 -> -4.266039
B25: Операционный аннуитет | C25: руб/ткм | D25: =D13/'Параметры'!C45/D15 -> 8.1228638 | E25: =E13/'Параметры'!C45/E15 -> 12.636283 | F25: =F13/'Параметры'!C45/F15 -> 9.7445702 | G25: =G13/'Параметры'!C45/G15 -> 11.864923 | H25: =H13/'Параметры'!C45/H15 -> 9.5530056 | I25: =I13/'Параметры'!C45/I15 -> 9.5029036
B26: ОБЩИЙ АННУИТЕТ | C26: руб/ткм | D26: =D14/'Параметры'!C45/D15 -> 12.046304 | E26: =E14/'Параметры'!C45/E15 -> 17.336701 | F26: =F14/'Параметры'!C45/F15 -> 14.02617 | G26: =G14/'Параметры'!C45/G15 -> 16.119303 | H26: =H14/'Параметры'!C45/H15 -> 14.372984 | I26: =I14/'Параметры'!C45/I15 -> 14.09582
B27: ДОПОЛНИТЕЛЬНЫЕ ПОКАЗАТЕЛИ
B28: Удельный аннуитет на тонну | C28: руб/т | D28: =D26*'Параметры'!C28 -> 36.615947 | E28: =E26*'Параметры'!C28 -> 52.696638 | F28: =F26*'Параметры'!C28 -> 42.633947 | G28: =G26*'Параметры'!C28 -> 48.996232 | H28: =H26*'Параметры'!C28 -> 43.688123 | I28: =I26*'Параметры'!C28 -> 42.845655
B29: Себестоимость (без дисконта) | C29: руб/ткм | D29: =AVERAGE('Денежный поток'!E19:N19)/D15 -> 11.995798 | E29: =AVERAGE('Денежный поток'!E41:N41)/E15 -> 18.167994 | F29: =AVERAGE('Денежный поток'!E63:N63)/F15 -> 14.350631 | G29: =AVERAGE('Денежный поток'!E85:N85)/G15 -> 16.713118 | H29: =AVERAGE('Денежный поток'!E107:N107)/H15 -> 14.139196 | I29: =AVERAGE('Денежный поток'!E129:N129)/I15 -> 14.048882
B30: Доля инвестиций в аннуитете | C30: % | D30: =D18/D26 -> 0.32569662 | E30: =E18/E26 -> 0.2711253 | F30: =F18/F26 -> 0.30525795 | G30: =G18/G26 -> 0.26393076 | H30: =H18/H26 -> 0.33534988 | I30: =I18/I26 -> 0.32583536

Sheet Сравнение
B1: СРАВНИТЕЛЬНЫЙ АНАЛИЗ АВТОСАМОСВАЛОВ
B2: Ранжирование по удельному аннуитету (руб/ткм). Зелёным — лучший вариант.
B4: Показатель | C4: Ед. | D4: ='Ввод данных'!D7 -> NHL NTE 240 | E4: ='Ввод данных'!E7 -> Estar ESDE240 (ГПБ К) | F4: ='Ввод данных'!F7 -> SANY SET240S | G4: ='Ввод данных'!G7 -> TZCO TZE240 | H4: ='Ввод данных'!H7 -> БелАЗ 7531 (ГПФК) | I4: ='Ввод данных'!I7 -> БелАЗ 7531 (БТЛ)
B5: Стоимость (в рублях) | C5: тыс.руб | D5: ='Производительность'!D5 -> 255404 | E5: ='Производительность'!E5 -> 263335.8 | F5: ='Производительность'!F5 -> 253930.95 | G5: ='Производительность'!G5 -> 253930.95 | H5: ='Производительность'!H5 -> 300000 | I5: ='Производительность'!I5 -> 290000
B6: Часовая производительность | C6: т/эфф.час | D6: ='Производительность'!D9 -> 545.66448 | E6: ='Производительность'!E9 -> 506.3613 | F6: ='Производительность'!F9 -> 518.26628 | G6: ='Производительность'!G9 -> 531.77135 | H6: ='Производительность'!H9 -> 553.32965 | I6: ='Производительность'!I9 -> 553.32965
B7: Средний годовой грузооборот | C7: тыс.ткм | D7: ='Расчёт аннуитета'!D15 -> 11521.128 | E7: ='Расчёт аннуитета'!E15 -> 9915.3442 | F7: ='Расчёт аннуитета'!F15 -> 10496.487 | G7: ='Расчёт аннуитета'!G15 -> 10563.645 | H7: ='Расчёт аннуитета'!H15 -> 11015.661 | I7: ='Расчёт аннуитета'!I15 -> 11174.905
B8: NPV стоимости владения | C8: тыс.руб | D8: ='Расчёт аннуитета'!D14 -> 784177.62 | E8: ='Расчёт аннуитета'!E14 -> 971269.74 | F8: ='Расчёт аннуитета'!F14 -> 831856.95 | G8: ='Расчёт аннуитета'!G14 -> 962112 | H8: ='Расчёт аннуитета'!H14 -> 894588.06 | I8: ='Расчёт аннуитета'!I14 -> 890020.05
B9: Себестоимость (без дисконта) | C9: руб/ткм | D9: ='Расчёт аннуитета'!D29 -> 11.995798 | E9: ='Расчёт аннуитета'!E29 -> 18.167994 | F9: ='Расчёт аннуитета'!F29 -> 14.350631 | G9: ='Расчёт аннуитета'!G29 -> 16.713118 | H9: ='Расчёт аннуитета'!H29 -> 14.139196 | I9: ='Расчёт аннуитета'!I29 -> 14.048882
B10: Инвестиционный аннуитет | C10: руб/ткм | D10: ='Расчёт аннуитета'!D18 -> 3.9234407 | E10: ='Расчёт аннуитета'!E18 -> 4.7004184 | F10: ='Расчёт аннуитета'!F18 -> 4.2816 | G10: ='Расчёт аннуитета'!G18 -> 4.2543798 | H10: ='Расчёт аннуитета'!H18 -> 4.8199785 | I10: ='Расчёт аннуитета'!I18 -> 4.5929166
B11: Операционный аннуитет | C11: руб/ткм | D11: ='Расчёт аннуитета'!D25 -> 8.1228638 | E11: ='Расчёт аннуитета'!E25 -> 12.636283 | F11: ='Расчёт аннуитета'!F25 -> 9.7445702 | G11: ='Расчёт аннуитета'!G25 -> 11.864923 | H11: ='Расчёт аннуитета'!H25 -> 9.5530056 | I11: ='Расчёт аннуитета'!I25 -> 9.5029036
B12: ОБЩИЙ АННУИТЕТ | C12: руб/ткм | D12: ='Расчёт аннуитета'!D26 -> 12.046304 | E12: ='Расчёт аннуитета'!E26 -> 17.336701 | F12: ='Расчёт аннуитета'!F26 -> 14.02617 | G12: ='Расчёт аннуитета'!G26 -> 16.119303 | H12: ='Расчёт аннуитета'!H26 -> 14.372984 | I12: ='Расчёт аннуитета'!I26 -> 14.09582
B13: Аннуитет на тонну | C13: руб/т | D13: ='Расчёт аннуитета'!D28 -> 36.615947 | E13: ='Расчёт аннуитета'!E28 -> 52.696638 | F13: ='Расчёт аннуитета'!F28 -> 42.633947 | G13: ='Расчёт аннуитета'!G28 -> 48.996232 | H13: ='Расчёт аннуитета'!H28 -> 43.688123 | I13: ='Расчёт аннуитета'!I28 -> 42.845655
B14: РАНЖИРОВАНИЕ (критерий: минимум аннуитета руб/ткм)
B15: Место в рейтинге | D15: =RANK(D12,D12:I12,1) -> 1 | E15: =RANK(E12,D12:I12,1) -> 6 | F15: =RANK(F12,D12:I12,1) -> 2 | G15: =RANK(G12,D12:I12,1) -> 5 | H15: =RANK(H12,D12:I12,1) -> 4 | I15: =RANK(I12,D12:I12,1) -> 3
B16: Отклонение от лучшего | D16: =D12/MIN(D12:I12)-1 -> 0 | E16: =E12/MIN(D12:I12)-1 -> 0.43917178 | F16: =F12/MIN(D12:I12)-1 -> 0.16435461 | G16: =G12/MIN(D12:I12)-1 -> 0.33811184 | H16: =H12/MIN(D12:I12)-1 -> 0.19314468 | I16: =I12/MIN(D12:I12)-1 -> 0.17013647
B18: РЕКОМЕНДУЕМЫЙ ВАРИАНТ: | C18: =INDEX(D4:I4,MATCH(MIN(D12:I12),D12:I12,0))&" ("&TEXT(MIN(D12:I12),"0.00")&" руб/ткм)" -> NHL NTE 240 (12.05 руб/ткм)
B20: СТРУКТУРА УДЕЛЬНОГО АННУИТЕТА (руб/ткм)
B21: Статья | D21: ='Ввод данных'!D7 -> NHL NTE 240 | E21: ='Ввод данных'!E7 -> Estar ESDE240 (ГПБ К) | F21: ='Ввод данных'!F7 -> SANY SET240S | G21: ='Ввод данных'!G7 -> TZCO TZE240 | H21: ='Ввод данных'!H7 -> БелАЗ 7531 (ГПФК) | I21: ='Ввод данных'!I7 -> БелАЗ 7531 (БТЛ)
B22: Инвестиционный | D22: ='Расчёт аннуитета'!D18 -> 3.9234407 | E22: ='Расчёт аннуитета'!E18 -> 4.7004184 | F22: ='Расчёт аннуитета'!F18 -> 4.2816 | G22: ='Расчёт аннуитета'!G18 -> 4.2543798 | H22: ='Расчёт аннуитета'!H18 -> 4.8199785 | I22: ='Расчёт аннуитета'!I18 -> 4.5929166
B23: Топливо | D23: ='Расчёт аннуитета'!D19 -> 5.9476483 | E23: ='Расчёт аннуитета'!E19 -> 5.9833279 | F23: ='Расчёт аннуитета'!F19 -> 5.9705226 | G23: ='Расчёт аннуитета'!G19 -> 5.9321753 | H23: ='Расчёт аннуитета'!H19 -> 5.9712576 | I23: ='Расчёт аннуитета'!I19 -> 5.9881195
B24: ТОиР + капремонты | D24: ='Расчёт аннуитета'!D20 -> 2.1987022 | E24: ='Расчёт аннуитета'!E20 -> 7.941292 | F24: ='Расчёт аннуитета'!F20 -> 4.1487879 | G24: ='Расчёт аннуитета'!G20 -> 7.0887864 | H24: ='Расчёт аннуитета'!H20 -> 4.2415366 | I24: ='Расчёт аннуитета'!I20 -> 4.1221565
B25: Шины | D25: ='Расчёт аннуитета'!D21 -> 2.0003607 | E25: ='Расчёт аннуитета'!E21 -> 2.1685578 | F25: ='Расчёт аннуитета'!F21 -> 2.1142099 | G25: ='Расчёт аннуитета'!G21 -> 2.0472824 | H25: ='Расчёт аннуитета'!H21 -> 1.9804805 | I25: ='Расчёт аннуитета'!I21 -> 1.9860731
B26: Персонал | D26: ='Расчёт аннуитета'!D22 -> 1.6036276 | E26: ='Расчёт аннуитета'!E22 -> 1.8633342 | F26: ='Расчёт аннуитета'!F22 -> 1.7601699 | G26: ='Расчёт аннуитета'!G22 -> 1.7489797 | H26: ='Расчёт аннуитета'!H22 -> 1.6772121 | I26: ='Расчёт аннуитета'!I22 -> 1.6533116
B27: Транспортный налог | D27: ='Расчёт аннуитета'!D23 -> 0.018444374 | E27: ='Расчёт аннуитета'!E23 -> 0.015979274 | F27: ='Расчёт аннуитета'!F23 -> 0.023022466 | G27: ='Расчёт аннуитета'!G23 -> 0.020116163 | H27: ='Расчёт аннуитета'!H23 -> 0.019560787 | I27: ='Расчёт аннуитета'!I23 -> 0.019282043
B28: Налог (щит) | D28: ='Расчёт аннуитета'!D24 -> -3.6459194 | E28: ='Расчёт аннуитета'!E24 -> -5.3362081 | F28: ='Расчёт аннуитета'!F24 -> -4.2721426 | G28: ='Расчёт аннуитета'!G24 -> -4.9724171 | H28: ='Расчёт аннуитета'!H24 -> -4.337042 | I28: ='Расчёт аннуитета'!I24 -> -4.266039

Sheet Аналитика
B1: РАСШИРЕННАЯ АНАЛИТИКА РЕЗУЛЬТАТОВ
B2: Многокритериальная оценка, разложение затрат, диапазон риска, эффективность.
B4: Показатель | C4: Ед. | D4: ='Ввод данных'!D7 -> NHL NTE 240 | E4: ='Ввод данных'!E7 -> Estar ESDE240 (ГПБ К) | F4: ='Ввод данных'!F7 -> SANY SET240S | G4: ='Ввод данных'!G7 -> TZCO TZE240 | H4: ='Ввод данных'!H7 -> БелАЗ 7531 (ГПФК) | I4: ='Ввод данных'!I7 -> БелАЗ 7531 (БТЛ)
B5: МНОГОКРИТЕРИАЛЬНАЯ ОЦЕНКА (levelized cost + драйверы)
B6: Цена (CAPEX) | C6: тыс.руб | D6: ='Производительность'!D5 -> 255404 | E6: ='Производительность'!E5 -> 263335.8 | F6: ='Производительность'!F5 -> 253930.95 | G6: ='Производительность'!G5 -> 253930.95 | H6: ='Производительность'!H5 -> 300000 | I6: ='Производительность'!I5 -> 290000
B7: Средний годовой грузооборот | C7: тыс.ткм | D7: ='Расчёт аннуитета'!D15 -> 11521.128 | E7: ='Расчёт аннуитета'!E15 -> 9915.3442 | F7: ='Расчёт аннуитета'!F15 -> 10496.487 | G7: ='Расчёт аннуитета'!G15 -> 10563.645 | H7: ='Расчёт аннуитета'!H15 -> 11015.661 | I7: ='Расчёт аннуитета'!I15 -> 11174.905
B8: КТГ средний | C8: коэф. | D8: =AVERAGE('Данные по годам'!E7:N7) -> 0.9244 | E8: =AVERAGE('Данные по годам'!E10:N10) -> 0.85731 | F8: =AVERAGE('Данные по годам'!E13:N13) -> 0.88671 | G8: =AVERAGE('Данные по годам'!E16:N16) -> 0.86972 | H8: =AVERAGE('Данные по годам'!E19:N19) -> 0.8716 | I8: =AVERAGE('Данные по годам'!E22:N22) -> 0.8842
B9: Аннуитет | C9: руб/ткм | D9: ='Расчёт аннуитета'!D26 -> 12.046304 | E9: ='Расчёт аннуитета'!E26 -> 17.336701 | F9: ='Расчёт аннуитета'!F26 -> 14.02617 | G9: ='Расчёт аннуитета'!G26 -> 16.119303 | H9: ='Расчёт аннуитета'!H26 -> 14.372984 | I9: ='Расчёт аннуитета'!I26 -> 14.09582
B10: Аннуитет | C10: руб/т | D10: ='Расчёт аннуитета'!D28 -> 36.615947 | E10: ='Расчёт аннуитета'!E28 -> 52.696638 | F10: ='Расчёт аннуитета'!F28 -> 42.633947 | G10: ='Расчёт аннуитета'!G28 -> 48.996232 | H10: ='Расчёт аннуитета'!H28 -> 43.688123 | I10: ='Расчёт аннуитета'!I28 -> 42.845655
B11: NPV стоимости владения | C11: тыс.руб | D11: ='Расчёт аннуитета'!D14 -> 784177.62 | E11: ='Расчёт аннуитета'!E14 -> 971269.74 | F11: ='Расчёт аннуитета'!F14 -> 831856.95 | G11: ='Расчёт аннуитета'!G14 -> 962112 | H11: ='Расчёт аннуитета'!H14 -> 894588.06 | I11: ='Расчёт аннуитета'!I14 -> 890020.05
B12: Доля CAPEX | C12: % | D12: ='Расчёт аннуитета'!D18/'Расчёт аннуитета'!D26 -> 0.32569662 | E12: ='Расчёт аннуитета'!E18/'Расчёт аннуитета'!E26 -> 0.2711253 | F12: ='Расчёт аннуитета'!F18/'Расчёт аннуитета'!F26 -> 0.30525795 | G12: ='Расчёт аннуитета'!G18/'Расчёт аннуитета'!G26 -> 0.26393076 | H12: ='Расчёт аннуитета'!H18/'Расчёт аннуитета'!H26 -> 0.33534988 | I12: ='Расчёт аннуитета'!I18/'Расчёт аннуитета'!I26 -> 0.32583536
B13: Доля топлива | C13: % | D13: ='Расчёт аннуитета'!D19/'Расчёт аннуитета'!D26 -> 0.49373219 | E13: ='Расчёт аннуитета'!E19/'Расчёт аннуитета'!E26 -> 0.34512493 | F13: ='Расчёт аннуитета'!F19/'Расчёт аннуитета'!F26 -> 0.42567019 | G13: ='Расчёт аннуитета'!G19/'Расчёт аннуитета'!G26 -> 0.36801687 | H13: ='Расчёт аннуитета'!H19/'Расчёт аннуитета'!H26 -> 0.41545009 | I13: ='Расчёт аннуитета'!I19/'Расчёт аннуитета'!I26 -> 0.42481526
B14: Доля ТОиР | C14: % | D14: ='Расчёт аннуитета'!D20/'Расчёт аннуитета'!D26 -> 0.18252089 | E14: ='Расчёт аннуитета'!E20/'Расчёт аннуитета'!E26 -> 0.45806245 | F14: ='Расчёт аннуитета'!F20/'Расчёт аннуитета'!F26 -> 0.29578908 | G14: ='Расчёт аннуитета'!G20/'Расчёт аннуитета'!G26 -> 0.43977004 | H14: ='Расчёт аннуитета'!H20/'Расчёт аннуитета'!H26 -> 0.2951048 | I14: ='Расчёт аннуитета'!I20/'Расчёт аннуитета'!I26 -> 0.29243821
B15: Место в рейтинге | D15: =RANK(D9,D9:I9,1) -> 1 | E15: =RANK(E9,D9:I9,1) -> 6 | F15: =RANK(F9,D9:I9,1) -> 2 | G15: =RANK(G9,D9:I9,1) -> 5 | H15: =RANK(H9,D9:I9,1) -> 4 | I15: =RANK(I9,D9:I9,1) -> 3
B16: РАЗЛОЖЕНИЕ ПРЕВЫШЕНИЯ АННУИТЕТА НАД ЛУЧШИМ (руб/ткм)
B17: Δ инвестиции | C17: руб/ткм | D17: ='Расчёт аннуитета'!D18-MIN(D18:I18) -> -0.18688532 | E17: ='Расчёт аннуитета'!E18-MIN(D18:I18) -> 0.59009242 | F17: ='Расчёт аннуитета'!F18-MIN(D18:I18) -> 0.17127405 | G17: ='Расчёт аннуитета'!G18-MIN(D18:I18) -> 0.14405381 | H17: ='Расчёт аннуитета'!H18-MIN(D18:I18) -> 0.70965255 | I17: ='Расчёт аннуитета'!I18-MIN(D18:I18) -> 0.48259061
B18: Δ топливо | C18: руб/ткм | D18: ='Расчёт аннуитета'!D19-MIN(D19:I19) -> 4.125799 | E18: ='Расчёт аннуитета'!E19-MIN(D19:I19) -> 4.1614786 | F18: ='Расчёт аннуитета'!F19-MIN(D19:I19) -> 4.1486733 | G18: ='Расчёт аннуитета'!G19-MIN(D19:I19) -> 4.110326 | H18: ='Расчёт аннуитета'!H19-MIN(D19:I19) -> 4.1494083 | I18: ='Расчёт аннуитета'!I19-MIN(D19:I19) -> 4.1662702
B19: Δ ТОиР | C19: руб/ткм | D19: ='Расчёт аннуитета'!D20-MIN(D20:I20) -> 1.8218493 | E19: ='Расчёт аннуитета'!E20-MIN(D20:I20) -> 7.5644391 | F19: ='Расчёт аннуитета'!F20-MIN(D20:I20) -> 3.771935 | G19: ='Расчёт аннуитета'!G20-MIN(D20:I20) -> 6.7119335 | H19: ='Расчёт аннуитета'!H20-MIN(D20:I20) -> 3.8646837 | I19: ='Расчёт аннуитета'!I20-MIN(D20:I20) -> 3.7453036
B20: Δ шины | C20: руб/ткм | D20: ='Расчёт аннуитета'!D21-MIN(D21:I21) -> 0.39673305 | E20: ='Расчёт аннуитета'!E21-MIN(D21:I21) -> 0.56493018 | F20: ='Расчёт аннуитета'!F21-MIN(D21:I21) -> 0.5105823 | G20: ='Расчёт аннуитета'!G21-MIN(D21:I21) -> 0.44365476 | H20: ='Расчёт аннуитета'!H21-MIN(D21:I21) -> 0.3768529 | I20: ='Расчёт аннуитета'!I21-MIN(D21:I21) -> 0.38244546
B21: Δ персонал | C21: руб/ткм | D21: ='Расчёт аннуитета'!D22-MIN(D22:I22) -> 1.6036276 | E21: ='Расчёт аннуитета'!E22-MIN(D22:I22) -> 1.8633342 | F21: ='Расчёт аннуитета'!F22-MIN(D22:I22) -> 1.7601699 | G21: ='Расчёт аннуитета'!G22-MIN(D22:I22) -> 1.7489797 | H21: ='Расчёт аннуитета'!H22-MIN(D22:I22) -> 1.6772121 | I21: ='Расчёт аннуитета'!I22-MIN(D22:I22) -> 1.6533116
B22: ИТОГО превышение над лучшим | C22: руб/ткм | D22: =D9-MIN(D9:I9) -> 0 | E22: =E9-MIN(D9:I9) -> 5.290397 | F22: =F9-MIN(D9:I9) -> 1.9798657 | G22: =G9-MIN(D9:I9) -> 4.0729981 | H22: =H9-MIN(D9:I9) -> 2.3266796 | I22: =I9-MIN(D9:I9) -> 2.0495157
B23: ДИАПАЗОН РИСКА АННУИТЕТА (руб/ткм)
B24: Оптимистичный (КТГ +10%, ДТ −20%) | C24: руб/ткм | D24: =('Расчёт аннуитета'!D18+'Расчёт аннуитета'!D20+'Расчёт аннуитета'!D22+'Расчёт аннуитета'!D23+'Расчёт аннуитета'!D24)/1.1+('Расчёт аннуитета'!D19+'Расчёт аннуитета'!D21)-0.2*'Расчёт аннуитета'!D19 -> 10.484203 | E24: =('Расчёт аннуитета'!E18+'Расчёт аннуитета'!E20+'Расчёт аннуитета'!E22+'Расчёт аннуитета'!E23+'Расчёт аннуитета'!E24)/1.1+('Расчёт аннуитета'!E19+'Расчёт аннуитета'!E21)-0.2*'Расчёт аннуитета'!E19 -> 15.305053 | F24: =('Расчёт аннуитета'!F18+'Расчёт аннуитета'!F20+'Расчёт аннуитета'!F22+'Расчёт аннуитета'!F23+'Расчёт аннуитета'!F24)/1.1+('Расчёт аннуитета'!F19+'Расчёт аннуитета'!F21)-0.2*'Расчёт аннуитета'!F19 -> 12.291935 | G24: =('Расчёт аннуитета'!G18+'Расчёт аннуитета'!G20+'Расчёт аннуитета'!G22+'Расчёт аннуитета'!G23+'Расчёт аннуитета'!G24)/1.1+('Расчёт аннуитета'!G19+'Расчёт аннуитета'!G21)-0.2*'Расчёт аннуитета'!G19 -> 14.192882 | H24: =('Расчёт аннуитета'!H18+'Расчёт аннуитета'!H20+'Расчёт аннуитета'!H22+'Расчёт аннуитета'!H23+'Расчёт аннуитета'!H24)/1.1+('Расчёт аннуитета'!H19+'Расчёт аннуитета'!H21)-0.2*'Расчёт аннуитета'!H19 -> 12.594983 | I24: =('Расчёт аннуитета'!I18+'Расчёт аннуитета'!I20+'Расчёт аннуитета'!I22+'Расчёт аннуитета'!I23+'Расчёт аннуитета'!I24)/1.1+('Расчёт аннуитета'!I19+'Расчёт аннуитета'!I21)-0.2*'Расчёт аннуитета'!I19 -> 12.341685
B25: Базовый | C25: руб/ткм | D25: ='Расчёт аннуитета'!D26 -> 12.046304 | E25: ='Расчёт аннуитета'!E26 -> 17.336701 | F25: ='Расчёт аннуитета'!F26 -> 14.02617 | G25: ='Расчёт аннуитета'!G26 -> 16.119303 | H25: ='Расчёт аннуитета'!H26 -> 14.372984 | I25: ='Расчёт аннуитета'!I26 -> 14.09582
B26: Пессимистичный (КТГ −10%, ДТ +20%) | C26: руб/ткм | D26: =('Расчёт аннуитета'!D18+'Расчёт аннуитета'!D20+'Расчёт аннуитета'!D22+'Расчёт аннуитета'!D23+'Расчёт аннуитета'!D24)/0.9+('Расчёт аннуитета'!D19+'Расчёт аннуитета'!D21)+0.2*'Расчёт аннуитета'!D19 -> 13.6912 | E26: =('Расчёт аннуитета'!E18+'Расчёт аннуитета'!E20+'Расчёт аннуитета'!E22+'Расчёт аннуитета'!E23+'Расчёт аннуитета'!E24)/0.9+('Расчёт аннуитета'!E19+'Расчёт аннуитета'!E21)+0.2*'Расчёт аннуитета'!E19 -> 19.553902 | F26: =('Расчёт аннуитета'!F18+'Расчёт аннуитета'!F20+'Расчёт аннуитета'!F22+'Расчёт аннуитета'!F23+'Расчёт аннуитета'!F24)/0.9+('Расчёт аннуитета'!F19+'Расчёт аннуитета'!F21)+0.2*'Расчёт аннуитета'!F19 -> 15.880434 | G26: =('Расчёт аннуитета'!G18+'Расчёт аннуитета'!G20+'Расчёт аннуитета'!G22+'Расчёт аннуитета'!G23+'Расчёт аннуитета'!G24)/0.9+('Расчёт аннуитета'!G19+'Расчёт аннуитета'!G21)+0.2*'Расчёт аннуитета'!G19 -> 18.210165 | H26: =('Расчёт аннуитета'!H18+'Расчёт аннуитета'!H20+'Расчёт аннуитета'!H22+'Расчёт аннуитета'!H23+'Расчёт аннуитета'!H24)/0.9+('Расчёт аннуитета'!H19+'Расчёт аннуитета'!H21)+0.2*'Расчёт аннуитета'!H19 -> 16.280707 | I26: =('Расчёт аннуитета'!I18+'Расчёт аннуитета'!I20+'Расчёт аннуитета'!I22+'Расчёт аннуитета'!I23+'Расчёт аннуитета'!I24)/0.9+('Расчёт аннуитета'!I19+'Расчёт аннуитета'!I21)+0.2*'Расчёт аннуитета'!I19 -> 15.973625
B27: Ширина диапазона (риск) | C27: руб/ткм | D27: =D26-D24 -> 3.2069978 | E27: =E26-E24 -> 4.2488495 | F27: =F26-F24 -> 3.5884995 | G27: =G26-G24 -> 4.0172832 | H27: =H26-H24 -> 3.6857244 | I27: =I26-I24 -> 3.6319402
B28: ЭФФЕКТИВНОСТЬ И ЦЕННОСТЬ ГОТОВНОСТИ
B29: Эффект +1 п.п. КТГ на аннуитет | C29: руб/ткм | D29: =-('Расчёт аннуитета'!D18+'Расчёт аннуитета'!D20+'Расчёт аннуитета'!D22+'Расчёт аннуитета'!D23+'Расчёт аннуитета'!D24)*0.01/AVERAGE('Данные по годам'!E7:N7) -> -0.044334655 | E29: =-('Расчёт аннуитета'!E18+'Расчёт аннуитета'!E20+'Расчёт аннуитета'!E22+'Расчёт аннуитета'!E23+'Расчёт аннуитета'!E24)*0.01/AVERAGE('Данные по годам'!E10:N10) -> -0.10713529 | F29: =-('Расчёт аннуитета'!F18+'Расчёт аннуитета'!F20+'Расчёт аннуитета'!F22+'Расчёт аннуитета'!F23+'Расчёт аннуитета'!F24)*0.01/AVERAGE('Данные по годам'!E13:N13) -> -0.067005421 | G29: =-('Расчёт аннуитета'!G18+'Расчёт аннуитета'!G20+'Расчёт аннуитета'!G22+'Расчёт аннуитета'!G23+'Расчёт аннуитета'!G24)*0.01/AVERAGE('Данные по годам'!E16:N16) -> -0.093591558 | H29: =-('Расчёт аннуитета'!H18+'Расчёт аннуитета'!H20+'Расчёт аннуитета'!H22+'Расчёт аннуитета'!H23+'Расчёт аннуитета'!H24)*0.01/AVERAGE('Данные по годам'!E19:N19) -> -0.073671937 | I29: =-('Расчёт аннуитета'!I18+'Расчёт аннуитета'!I20+'Расчёт аннуитета'!I22+'Расчёт аннуитета'!I23+'Расчёт аннуитета'!I24)*0.01/AVERAGE('Данные по годам'!E22:N22) -> -0.069233517
B31: ВЫВОД: | C31: ="Лучший по удельному TCO: "&INDEX(D4:I4,MATCH(MIN(D9:I9),D9:I9,0))&" ("&TEXT(MIN(D9:I9),"0.00")&" руб/ткм, "&TEXT(MIN(D10:I10),"0.00")&" руб/т). "&"Отрыв от худшего: "&TEXT(MAX(D9:I9)-MIN(D9:I9),"0.00")&" руб/ткм." -> Лучший по удельному TCO: NHL NTE 240 (12.05 руб/ткм, 36.62 руб/т). Отрыв от худшего: 5.29 руб/ткм.
B33: Метод (лучшие практики):
B34: • Levelized cost — приведённые затраты на единицу транспортной работы (руб/ткм, руб/т) уравнивают самосвалы с разной ценой, грузоподъёмностью и производительностью.
B35: • Многокритериальная оценка — не только цена, но и структура затрат, КТГ, доля топлива.
B36: • Разложение над лучшим — показывает, за счёт каких статей вариант дороже (управляемость).
B37: • Диапазон риска — устойчивость выбора к колебаниям КТГ и цены топлива.
B38: • Ценность готовности — сколько руб/ткм даёт рост КТГ на 1 п.п. (обоснование сервисного контракта).

Sheet Чувствительность
B1: АНАЛИЗ ЧУВСТВИТЕЛЬНОСТИ
B2: Торнадо драйверов, влияние КТГ и ставки дисконтирования на аннуитет.
B4: Анализируемый самосвал (1–6): | C4: 1 | D4: =INDEX('Ввод данных'!D7:I7,$C$4) -> NHL NTE 240
B6: БАЗОВЫЕ ВЕЛИЧИНЫ ВЫБРАННОГО ВАРИАНТА
B7: Общий аннуитет | C7: руб/ткм | D7: =INDEX('Расчёт аннуитета'!D26:I26,$C$4) -> 12.046304
B8: — инвестиционный | C8: руб/ткм | D8: =INDEX('Расчёт аннуитета'!D18:I18,$C$4) -> 3.9234407
B9: — топливо | C9: руб/ткм | D9: =INDEX('Расчёт аннуитета'!D19:I19,$C$4) -> 5.9476483
B10: — ТОиР + капремонты | C10: руб/ткм | D10: =INDEX('Расчёт аннуитета'!D20:I20,$C$4) -> 2.1987022
B11: — персонал | C11: руб/ткм | D11: =INDEX('Расчёт аннуитета'!D22:I22,$C$4) -> 1.6036276
B12: Средний годовой грузооборот | C12: тыс.ткм | D12: =INDEX('Расчёт аннуитета'!D15:I15,$C$4) -> 11521.128
B13: Стоимость (руб) | C13: тыс.руб | D13: =INDEX('Производительность'!D5:I5,$C$4) -> 255404
B14: Постоянные (инв+ТОиР+перс+налоги) | C14: руб/ткм | D14: =INDEX('Расчёт аннуитета'!D18:I18,$C$4)+INDEX('Расчёт аннуитета'!D20:I20,$C$4)+INDEX('Расчёт аннуитета'!D22:I22,$C$4)+INDEX('Расчёт аннуитета'!D23:I23,$C$4)+INDEX('Расчёт аннуитета'!D24:I24,$C$4) -> 4.0982955
B15: Переменные (топливо+шины) | C15: руб/ткм | D15: =INDEX('Расчёт аннуитета'!D19:I19,$C$4)+INDEX('Расчёт аннуитета'!D21:I21,$C$4) -> 7.948009
B17: ТОРНАДО: ВЛИЯНИЕ ДРАЙВЕРОВ НА ОБЩИЙ АННУИТЕТ (руб/ткм)
B18: Драйвер | C18: Диапазон | D18: При снижении | E18: При росте | F18: Размах | I18: низкое | J18: высокое
B19: Расход / цена ДТ | C19: ±20% | D19: =$D$7-0.2*($D$9*(1-'Параметры'!C7)) -> 11.154157 | E19: =$D$7+0.2*($D$9*(1-'Параметры'!C7)) -> 12.938452 | F19: =E19-D19 -> 1.7842945 | I19: =D19-$D$7 -> -0.89214724 | J19: =E19-$D$7 -> 0.89214724
B20: Затраты на ТОиР/ремонты | C20: ±25% | D20: =$D$7-0.25*($D$10*(1-'Параметры'!C7)) -> 11.634048 | E20: =$D$7+0.25*($D$10*(1-'Параметры'!C7)) -> 12.458561 | F20: =E20-D20 -> 0.82451332 | I20: =D20-$D$7 -> -0.41225666 | J20: =E20-$D$7 -> 0.41225666
B21: Цена приобретения | C21: ±15% | D21: =$D$7-0.15*($D$8*(1-'Параметры'!C7*'Параметры'!C46)) -> 11.563347 | E21: =$D$7+0.15*($D$8*(1-'Параметры'!C7*'Параметры'!C46)) -> 12.529262 | F21: =E21-D21 -> 0.96591512 | I21: =D21-$D$7 -> -0.48295756 | J21: =E21-$D$7 -> 0.48295756
B22: Расходы на персонал | C22: ±15% | D22: =$D$7-0.15*($D$11*(1-'Параметры'!C7)) -> 11.865896 | E22: =$D$7+0.15*($D$11*(1-'Параметры'!C7)) -> 12.226713 | F22: =E22-D22 -> 0.36081622 | I22: =D22-$D$7 -> -0.18040811 | J22: =E22-$D$7 -> 0.18040811
B25: ВЛИЯНИЕ ПРОИЗВОДИТЕЛЬНОСТИ (КТГ / УТИЛИЗАЦИИ)
B26: Изменение производительности | C26: -15% | D26: -10% | E26: 0% | F26: +10% | G26: +15%
B27: Общий аннуитет, руб/ткм | C27: =$D$14/(1+-0.15)+$D$15 -> 12.769533 | D27: =$D$14/(1+-0.1)+$D$15 -> 12.501671 | E27: =$D$14/(1+0.0)+$D$15 -> 12.046304 | F27: =$D$14/(1+0.1)+$D$15 -> 11.673732 | G27: =$D$14/(1+0.15)+$D$15 -> 11.511744
B29: ВЛИЯНИЕ СТАВКИ ДИСКОНТИРОВАНИЯ
B30: Ставка дисконтирования | C30: 0.08 | D30: 0.1 | E30: 0.12 | F30: 0.14 | G30: 0.16
B31: Общий аннуитет, руб/ткм (оценка) | C31: =$D$13*(1-INDEX('Ввод данных'!D14:I14,$C$4)/(1+C30)^'Параметры'!C8)/((1-(1+C30)^-'Параметры'!C8)/C30)/$D$12+$D$7-$D$8 -> 11.426596 | D31: =$D$13*(1-INDEX('Ввод данных'!D14:I14,$C$4)/(1+D30)^'Параметры'!C8)/((1-(1+D30)^-'Параметры'!C8)/D30)/$D$12+$D$7-$D$8 -> 11.730655 | E31: =$D$13*(1-INDEX('Ввод данных'!D14:I14,$C$4)/(1+E30)^'Параметры'!C8)/((1-(1+E30)^-'Параметры'!C8)/E30)/$D$12+$D$7-$D$8 -> 12.046304 | F31: =$D$13*(1-INDEX('Ввод данных'!D14:I14,$C$4)/(1+F30)^'Параметры'!C8)/((1-(1+F30)^-'Параметры'!C8)/F30)/$D$12+$D$7-$D$8 -> 12.37283 | G31: =$D$13*(1-INDEX('Ввод данных'!D14:I14,$C$4)/(1+G30)^'Параметры'!C8)/((1-(1+G30)^-'Параметры'!C8)/G30)/$D$12+$D$7-$D$8 -> 12.709512
B33: Оценка по ставке: инвестиционный аннуитет пересчитан точно, операционный принят постоянным (аннуитет равномерного потока ≈ инвариантен к ставке).

Sheet Справочник
B1: СПРАВОЧНИК ОРИЕНТИРОВОЧНЫХ ЗНАЧЕНИЙ
B2: Диапазоны для проверки исходных данных. Требуют уточнения по данным поставщика.
B4: Показатель | C4: Класс 220–240 т | D4: Диапазон | E4: Комментарий
B5: Ставка дисконтирования (WACC) | C5: 12% | D5: 8–16% | E5: Согласуется с эскалацией
B6: Налог на прибыль | C6: 25% | D6: 20–25% | E6: Действующая ставка РФ
B7: КТГ (техготовность) | C7: 0,85–0,94 | D7: 0,80–0,95 | E7: Зависит от бренда и сервиса
B8: КИО (использование) | C8: 0,78–0,80 | D8: 0,72–0,85 | E8: Доля рабочего времени в КФВ
B9: КИГ (использование г/п) | C9: 0,98 | D9: 0,90–1,00 | E9: Доля номинальной грузоподъёмности
B10: Грузоподъёмность | C10: 211–231 | D10: 200–240 т | E10: Класс 220–240 т
B11: Средняя тех. скорость | C11: 22,5 | D11: 18–28 км/ч | E11: Профиль трассы, плечо
B12: Расход топлива | C12: 90 | D12: 80–110 г/ткм | E12: Двигатель, плечо, уклоны
B13: Шины (удельный расход) | C13: 0,075 | D13: 0,05–0,10 шт/тыс.км | E13: Тип, трасса, давление
B14: Срок амортизации (НУ) | C14: 61 мес | D14: 5–7 лет | E14: Линейная амортизация
B15: Остаточная стоимость | C15: 0–10% | D15: 0–20% | E15: Реализация в конце срока
B17: Методические примечания:
B18: • Производительность считается по транспортному циклу (методика листа «Производительность» исходного файла): время рейса = фикс. операции + движение (2·плечо/скорость); объём = рейсы × грузоподъёмность × КИГ.
B19: • ТОиР задаётся по годам (ТО, текущие и капитальные ремонты, сервис) — «рваный» график капремонтов учитывается дисконтированием.
B20: • Цена самосвалов в исходном файле не заполнена — в модель подставлена ОЦЕНКА; замените жёлтые ячейки данными ТКП.
B21: • Значения таблицы — ориентир порядка величин, а не норматив.
