Workbook

Sheet Методика
B1: МЕТОДИКА: АННУИТЕТ ЗАТРАТ (РУБ/М³) НА ВЛАДЕНИЕ ЭКСКАВАТОРАМИ
B2: Пост-налоговый погодовой дисконтированный аннуитет жизненного цикла.
C4: 1. НАЗНАЧЕНИЕ
C5: Экономическое сравнение экскаваторов одного класса по удельному аннуитету затрат (руб/м³ вынутой горной массы) за полный срок эксплуатации. Метрика корректно сопоставляет машины с разной ценой, производительностью и структурой затрат. Лучший вариант — минимум руб/м³.
C6: 2. ПРОИЗВОДИТЕЛЬНОСТЬ
C7: Порода в ковше = ковш × плотность × (наполнение/разрыхление) × потери. Ковшей на самосвал = ОКРУГЛ.ВВЕРХ(грузоподъёмность / порода в ковше). Самосвалов/час = 3600/(ковшей × цикл + постановка а/с). т/ч = грузоподъёмность × самосвалов/час; м³/ч = т/ч / плотность. Годовой объём = м³/ч × эффективное время; эффективное время = КФВ × КТГ × (1 − простои/смена). КТГ снижается с возрастом машины.
C8: 3. ПОГОДОВОЙ ДЕНЕЖНЫЙ ПОТОК (10 лет)
C9: Для каждого года считаются: дизтопливо (эфф.время × кг/ч × цена), ТОиР и сервис (задаются ПО ГОДАМ на листе «Данные по годам» — включают плановое ТО, текущие и капитальные ремонты; годы капремонтов дают всплеск затрат), расходники на ковш, персонал. Добавляются амортизация (НУ) и налог на прибыль (щит). Операционный поток = база + налог − амортизация. Инвестиции — в год 0, остаточная стоимость — в конце срока. КТГ также задаётся по годам.
C10: 4. АННУИТЕТ (ЯДРО)
C11: Потоки дисконтируются и преобразуются в эквивалентный годовой платёж: Аннуитет = NPV затрат / Σ(дисконт-факторов). Инвестиционный аннуитет = (Цена − дисконт. остаточная стоимость) / Σ(дисконт-факторов). Операционный аннуитет — приведённые эксплуатационные затраты после налога. Общий = инвестиционный + операционный. Удельный аннуитет (руб/м³) = общий аннуитет / средний годовой объём; руб/т = руб/м³ / плотность.
C12: 5. ПОРЯДОК РАБОТЫ
C13: «Параметры» → «Ввод данных» (цена, ковш, персонал) → листы «Поставщик 1…6»: по каждой машине встроены модели ТО (интервалы обслуживания → простои, запчасти, сервис) и Ремонтов (простои, текущие и капитальные ремонты, сервис по годам) — КТГ и ИТОГО ТОиР считаются автоматически снизу вверх. Сводка «Данные по годам» тянет итоги сама → авторасчёт «Производительность», «Денежный поток», «Расчёт аннуитета» → «Дашборд», «Сравнение», «Аналитика» (многокритериальная оценка, разложение над лучшим, диапазон риска, ценность готовности), «Чувствительность». Правки — только в листах «Поставщик N».
C14: 6. ДОПУЩЕНИЯ
C15: • Машины сравниваются в одном классе и одной задаче; разница в производительности учтена через руб/м³.
... C22: зелёные ячейки — итоговые показатели / лучший вариант

Sheet Дашборд
B1: ИТОГОВЫЙ ДАШБОРД — СРАВНЕНИЕ ЭКСКАВАТОРОВ
B2: Ключевые показатели и графики. Данные обновляются автоматически.
B4: КЛЮЧЕВЫЕ ПОКАЗАТЕЛИ
B5: Лучший вариант | C5: Мин. аннуитет, руб/м³ | D5: Мин. NPV владения, тыс.руб | E5: Разброс аннуитета, руб/м³
B6: =INDEX('Ввод данных'!D7:J7,MATCH(MIN('Расчёт аннуитета'!D23:J23),'Расчёт аннуитета'!D23:J23,0)) -> XCMG ESTAR ESE2000 (поставщик не указан) | C6: =MIN('Расчёт аннуитета'!D23:J23) -> 31.40079 | D6: =MIN('Расчёт аннуитета'!D13:J13) -> 387032.41 | E6: =MAX('Расчёт аннуитета'!D23:J23)-MIN('Расчёт аннуитета'!D23:J23) -> 115.2246
B8: РЕЙТИНГ ПО УДЕЛЬНОМУ АННУИТЕТУ (руб/м³)
B9: Место | C9: Экскаватор | G9: Аннуитет, руб/м³ | I9: руб/т
B10: 1 | C10: =INDEX('Ввод данных'!D7:J7,MATCH(SMALL('Расчёт аннуитета'!D23:J23,1),'Расчёт аннуитета'!D23:J23,0)) -> XCMG ESTAR ESE2000 (поставщик не указан) | G10: =SMALL('Расчёт аннуитета'!D23:J23,1) -> 31.40079 | I10: =INDEX('Расчёт аннуитета'!$D$25:$J$25,MATCH(SMALL('Расчёт аннуитета'!D23:J23,1),'Расчёт аннуитета'!D23:J23,0)) -> 11.266878
B11: 2 | C11: =INDEX('Ввод данных'!D7:J7,MATCH(SMALL('Расчёт аннуитета'!D23:J23,2),'Расчёт аннуитета'!D23:J23,0)) -> TZCO TZ2000 Дзикай | G11: =SMALL('Расчёт аннуитета'!D23:J23,2) -> 31.591418 | I11: =INDEX('Расчёт аннуитета'!$D$25:$J$25,MATCH(SMALL('Расчёт аннуитета'!D23:J23,2),'Расчёт аннуитета'!D23:J23,0)) -> 11.335277
B12: 3 | C12: =INDEX('Ввод данных'!D7:J7,MATCH(SMALL('Расчёт аннуитета'!D23:J23,3),'Расчёт аннуитета'!D23:J23,0)) -> Sany SY2000 АСТ | G12: =SMALL('Расчёт аннуитета'!D23:J23,3) -> 45.546682 | I12: =INDEX('Расчёт аннуитета'!$D$25:$J$25,MATCH(SMALL('Расчёт аннуитета'!D23:J23,3),'Расчёт аннуитета'!D23:J23,0)) -> 16.342548
B13: 4 | C13: =INDEX('Ввод данных'!D7:J7,MATCH(SMALL('Расчёт аннуитета'!D23:J23,4),'Расчёт аннуитета'!D23:J23,0)) -> Zoomlion ZE2000G Орикс | G13: =SMALL('Расчёт аннуитета'!D23:J23,4) -> 45.840766 | I13: =INDEX('Расчёт аннуитета'!$D$25:$J$25,MATCH(SMALL('Расчёт аннуитета'!D23:J23,4),'Расчёт аннуитета'!D23:J23,0)) -> 16.448068
B14: 5 | C14: =INDEX('Ввод данных'!D7:J7,MATCH(SMALL('Расчёт аннуитета'!D23:J23,5),'Расчёт аннуитета'!D23:J23,0)) -> Komatsu PC2000-11R ИСТК | G14: =SMALL('Расчёт аннуитета'!D23:J23,5) -> 48.691794 | I14: =INDEX('Расчёт аннуитета'!$D$25:$J$25,MATCH(SMALL('Расчёт аннуитета'!D23:J23,5),'Расчёт аннуитета'!D23:J23,0)) -> 17.471042
B15: 6 | C15: =INDEX('Ввод данных'!D7:J7,MATCH(SMALL('Расчёт аннуитета'!D23:J23,6),'Расчёт аннуитета'!D23:J23,0)) -> Komatsu PC2000-8 Mining Solutions | G15: =SMALL('Расчёт аннуитета'!D23:J23,6) -> 67.82058 | I15: =INDEX('Расчёт аннуитета'!$D$25:$J$25,MATCH(SMALL('Расчёт аннуитета'!D23:J23,6),'Расчёт аннуитета'!D23:J23,0)) -> 24.334618
B16: 7 | C16: =INDEX('Ввод данных'!D7:J7,MATCH(SMALL('Расчёт аннуитета'!D23:J23,7),'Расчёт аннуитета'!D23:J23,0)) -> Shantui SE2000LCW | G16: =SMALL('Расчёт аннуитета'!D23:J23,7) -> 146.62539 | I16: =INDEX('Расчёт аннуитета'!$D$25:$J$25,MATCH(SMALL('Расчёт аннуитета'!D23:J23,7),'Расчёт аннуитета'!D23:J23,0)) -> 52.610475

Sheet Параметры
B1: ГЛОБАЛЬНЫЕ ПАРАМЕТРЫ МОДЕЛИ
B2: Единые допущения для всех вариантов. Жёлтые ячейки — ввод.
B4: Финансовые допущения
B5: Параметр | C5: Значение | D5: Ед. | E5: Комментарий
B6: Ставка дисконтирования (WACC) | C6: 0.12 | D6: %/год | E6: Стоимость капитала для приведения к текущей стоимости
B7: Налог на прибыль | C7: 0.25 | D7: % | E7: Формирует налоговый щит на затраты и амортизацию
B8: Срок эксплуатации (горизонт) | C8: 10 | D8: лет | E8: Фиксирован = 10 лет в погодовом движке
B9: Срок амортизации (налоговый учёт) | C9: 5.17 | D9: лет | E9: Линейная; 62 мес ≈ 5,17 года
B10: Цена дизельного топлива | C10: 54.83 | D10: руб/кг | E10: Средняя цена на площадке эксплуатации
B12: Эскалация цен (реальный/номинальный рост)
B13: Параметр | C13: Значение | D13: Ед. | E13: Комментарий
B14: Эскалация цены топлива | C14: 0 | D14: %/год | E14: Рост цены ДТ (0 = данные уже с учётом инфляции)
B15: Эскалация расходников и персонала | C15: 0 | D15: %/год | E15: ТОиР задаётся по годам напрямую (см. «Данные по годам»)
B16: Эскалация оплаты труда | C16: 0 | D16: %/год | E16: Рост ФОТ экипажей
B18: Курсы валют
B19: Параметр | C19: Значение | D19: Ед. | E19: Комментарий
B20: Курс юаня (CNY) | C20: 11.2068 | D20: руб | E20: Для оборудования из Китая
B21: Курс доллара (USD) | C21: 76.1258 | D21: руб
B22: Курс евро (EUR) | C22: 86.8976 | D22: руб
B24: Параметры производительности (карьер)
B25: Параметр | C25: Значение | D25: Ед. | E25: Комментарий
B26: Календарный фонд времени | C26: 8760 | D26: час/год | E26: 24 ч × 365 дн
B27: Плотность породы | C27: 2.787 | D27: т/м³ | E27: В целике; используется и для пересчёта руб/т
B28: Коэффициент разрыхления | C28: 1.5 | D28: коэф.
B29: Коэффициент наполнения ковша | C29: 0.9 | D29: коэф.
B30: Коэффициент потерь при экскавации | C30: 0.9 | D30: коэф.
B31: Грузоподъёмность самосвала | C31: 136 | D31: т | E31: Эталонный самосвал для расчёта
B32: Время постановки самосвала | C32: 32 | D32: сек | E32: Время оборота а/с под погрузку
B33: Длительность смены | C33: 12 | D33: час | E33: Для пересчёта простоев
B35: Расчётные финансовые коэффициенты
B36: Параметр | C36: Значение | D36: Ед. | E36: Комментарий
B37: Коэф. аннуитета Σдиск.факторов (r, N) | C37: =IF('Параметры'!C6=0,'Параметры'!C8,(1-(1+'Параметры'!C6)^-'Параметры'!C8)/'Параметры'!C6) -> 5.650223 | D37: коэф. | E37: Сумма дисконт-факторов за срок службы
B38: Коэф. приведённой амортизации | C38: =(1/'Параметры'!C9)*((1-(1+'Параметры'!C6)^-INT('Параметры'!C9))/'Параметры'!C6+('Параметры'!C9-INT('Параметры'!C9))*(1+'Параметры'!C6)^-(INT('Параметры'!C9)+1)) -> 0.71390783 | D38: коэф. | E38: Приведённая амортизация на 1 руб. цены (налог. щит)
B40: Легенда: | D40: — ввод данных
D41: — расчётные показатели

Sheet Ввод данных
B1: ВВОД ИСХОДНЫХ ДАННЫХ ПО ЭКСКАВАТОРАМ
B2: Сравнение до 6 машин одного класса. Пример: экскаваторы класса 2000 (~12 м³).
B4: Показатель | C4: Ед. | D4: Экскаватор 1 | E4: Экскаватор 2 | F4: Экскаватор 3 | G4: Экскаватор 4 | H4: Экскаватор 5 | I4: Экскаватор 6 | J4: Экскаватор 7 | K4: Пояснение
B6: A. ИДЕНТИФИКАЦИЯ
B7: Наименование / модель | C7: — | D7: Komatsu PC2000-8 Mining Solutions | E7: Komatsu PC2000-11R ИСТК | F7: Zoomlion ZE2000G Орикс | G7: Sany SY2000 АСТ | H7: Shantui SE2000LCW | I7: TZCO TZ2000 Дзикай | J7: XCMG ESTAR ESE2000 (поставщик не указан) | K7: Название варианта
B8: Поставщик | C8: — | D8: Mining Solutions | E8: ИСТК | F8: Орикс | G8: АСТ | H8: Строймпорттехника | I8: Дзикай | J8: —
B9: Двигатель | C9: — | D9: Komatsu SAA12V140E | E9: Komatsu SAA12V140E-7 | F9: Cummins QST30 | G9: Cummins QSK38 | H9: Weichai 12M33 | I9: Weichai 12M33 | J9: 1102 л.с.
B10: B. СТОИМОСТЬ И ОСТАТОЧНАЯ ЦЕНА
B11: Цена за единицу | C11: тыс.вал. | D11: 3800 | E11: 3401.64 | F11: 20129 | G11: 19621.62 | H11: 16742.05 | I11: 15400 | J11: 18000 | K11: В валюте контракта
B12: Валюта цены | C12: — | D12: USD | E12: USD | F12: CNY | G12: CNY | H12: CNY | I12: CNY | J12: CNY | K12: CNY / USD / EUR / RUB
B13: Монтаж, доставка, ПНР | C13: тыс.руб | D13: 0 | E13: 0 | F13: 0 | G13: 0 | H13: 0 | I13: 0 | J13: 0 | K13: Дополнительно к цене
B14: Остаточная стоимость | C14: % от цены | D14: 0 | E14: 0 | F14: 0 | G14: 0 | H14: 0 | I14: 0 | J14: 0 | K14: Стоимость реализации в конце срока (0 = не учитывать)
B15: C. ПРОИЗВОДИТЕЛЬНОСТЬ
B16: Геометрический объём ковша | C16: м³ | D16: 10 | E16: 10 | F16: 10 | G16: 10 | H16: 9.6 | I16: 12 | J16: 12 | K16: Участвует в расчёте производительности
B17: Время цикла экскавации | C17: сек | D17: 37.3 | E17: 37.3 | F17: 37.3 | G17: 37.3 | H17: 37.3 | I17: 37.3 | J17: 26 | K17: Черпание–поворот–разгрузка–поворот
B18: Ежесменные простои | C18: мин/см | D18: 266.1 | E18: 266.1 | F18: 266.1 | G18: 266.1 | H18: 266.1 | I18: 266.1 | J18: 266.1 | K18: ОТМ, ожидание а/с, прочие организационные
B19: D. ПРОЧИЕ ГОДОВЫЕ ЗАТРАТЫ
B20: Расходы на персонал (экипаж) | C20: тыс.руб/год | D20: 10015 | E20: 10015 | F20: 10015 | G20: 10015 | H20: 10015 | I20: 10015 | J20: 10015 | K20: ФОТ с отчислениями на 1 машину
B21: ℹ КТГ, расход ДТ, ТОиР и расходники на ковш задаются ПО ГОДАМ на листе «Данные по годам». Пустой бланк для сбора данных с поставщика — на листе «Шаблон поставщика».

Sheet Поставщик 1
B1: ШАБЛОН ДАННЫХ ПОСТАВЩИКА — ВАРИАНТ 1
B2: Полные модели ТО и Ремонтов ПО ГОДАМ (затраты и трудозатраты — раздельно для ТО / текущих / капитальных ремонтов). Зелёное — авто; сводка тянется в «Данные по годам».
B4: Экскаватор: | E4: ='Ввод данных'!D7 -> Komatsu PC2000-8 Mining Solutions
B5: Валюта затрат ТОиР: | D5: USD
B6: Показатель | C6: Ед. | E6: год 1 | F6: год 2 | G6: год 3 | H6: год 4 | I6: год 5 | J6: год 6 | K6: год 7 | L6: год 8 | M6: год 9 | N6: год 10
B7: СВОДКА ПО ГОДАМ (зелёное — авто из моделей ниже; тянется в расчёт)
B8: Простои на ТО | C8: ч/год | E8: =E37 -> 273.21 | F8: =F37 -> 273.21 | G8: =G37 -> 273.21 | H8: =H37 -> 273.21 | I8: =I37 -> 273.21 | J8: =J37 -> 273.21 | K8: =K37 -> 273.21 | L8: =L37 -> 273.21 | ... N8: =N37 -> 273.21
B9: Простои в текущих + капитальных ремонтах | C9: ч/год | E9: =E80 -> 160.72 | F9: =F80 -> 377.53 | G9: =G80 -> 737.94 | H9: =H80 -> 828.05 | I9: =I80 -> 737.94 | J9: =J80 -> 1169.1 | K9: =K80 -> 1399.63 | L9: =L80 -> 894.37 | ... N9: =N80 -> 1037.94
B10: Ежесменное ТО (20 мин/смену) | C10: ч/год | E10: =('Параметры'!C26-E8-E9)/'Параметры'!C33*20/60 -> 231.27972 | F10: =('Параметры'!C26-F8-F9)/'Параметры'!C33*20/60 -> 225.25722 | G10: =('Параметры'!C26-G8-G9)/'Параметры'!C33*20/60 -> 215.24583 | H10: =('Параметры'!C26-H8-H9)/'Параметры'!C33*20/60 -> 212.74278 | I10: =('Параметры'!C26-I8-I9)/'Параметры'!C33*20/60 -> 215.24583 | J10: =('Параметры'!C26-J8-J9)/'Параметры'!C33*20/60 -> 203.26917 | K10: =('Параметры'!C26-K8-K9)/'Параметры'!C33*20/60 -> 196.86556 | L10: =('Параметры'!C26-L8-L9)/'Параметры'!C33*20/60 -> 210.90056 | M10: =('Параметры'!C26-M8-M9)/'Параметры'!C33*20/60 -> 184.55583 | N10: =('Параметры'!C26-N8-N9)/'Параметры'!C33*20/60 -> 206.9125
B11: КТГ (авто) = (8760 − простои)/8760 | C11: коэф. | E11: =('Параметры'!C26-E8-E9-E10)/'Параметры'!C26 -> 0.92406282 | F11: =('Параметры'!C26-F8-F9-F10)/'Параметры'!C26 -> 0.90000032 | G11: =('Параметры'!C26-G8-G9-G10)/'Параметры'!C26 -> 0.86000048 | H11: =('Параметры'!C26-H8-H9-H10)/'Параметры'!C26 -> 0.84999968 | I11: =('Параметры'!C26-I8-I9-I10)/'Параметры'!C26 -> 0.86000048 | J11: =('Параметры'!C26-J8-J9-J10)/'Параметры'!C26 -> 0.8121485 | K11: =('Параметры'!C26-K8-K9-K10)/'Параметры'!C26 -> 0.78656329 | L11: =('Параметры'!C26-L8-L9-L10)/'Параметры'!C26 -> 0.84263921 | M11: =('Параметры'!C26-M8-M9-M10)/'Параметры'!C26 -> 0.73738061 | N11: =('Параметры'!C26-N8-N9-N10)/'Параметры'!C26 -> 0.82670519
B12: Затраты на ТО (ЗЧ, из каталога) | C12: тыс/год | E12: =E75 -> 107.51972 | F12: =F75 -> 107.51972 | G12: =G75 -> 107.51972 | H12: =H75 -> 107.51972 | I12: =I75 -> 107.51972 | J12: =J75 -> 107.51972 | K12: =K75 -> 107.51972 | L12: =L75 -> 107.51972 | ... N12: =N75 -> 107.51972
B13: Затраты на текущие ремонты (ЗЧ) | C13: тыс/год | E13: =E88*$E$81 -> 1.742 | F13: =F88*$E$81 -> 4.355 | G13: =G88*$E$81 -> 3.484 | H13: =H88*$E$81 -> 2.613 | I13: =I88*$E$81 -> 3.484 | J13: =J88*$E$81 -> 4.355 | K13: =K88*$E$81 -> 2.613 | L13: =L88*$E$81 -> 3.484 | ... N13: =N88*$E$81 -> 3.484
B14: Затраты на капитальные ремонты (ЗЧ, цех) | C14: тыс/год | E14: =E125*$E$81 -> 0 | F14: =F125*$E$81 -> 1347.6074 | G14: =G125*$E$81 -> 1436.0748 | H14: =H125*$E$81 -> 1347.6074 | I14: =I125*$E$81 -> 5.7667 | J14: =J125*$E$81 -> 2734.3671 | K14: =K125*$E$81 -> 49.3151 | L14: =L125*$E$81 -> 2734.3671 | ... N14: =N125*$E$81 -> 1304.059
B15: Трудозатраты на ТО | C15: ч-час/год | E15: =E43 -> 546.42 | F15: =F43 -> 546.42 | G15: =G43 -> 546.42 | H15: =H43 -> 546.42 | I15: =I43 -> 546.42 | J15: =J43 -> 546.42 | K15: =K43 -> 546.42 | L15: =L43 -> 546.42 | ... N15: =N43 -> 546.42
B16: Трудозатраты на текущие ремонты | C16: ч-час/год | E16: =E93*$E$81 -> 0 | F16: =F93*$E$81 -> 0 | G16: =G93*$E$81 -> 0 | H16: =H93*$E$81 -> 0 | I16: =I93*$E$81 -> 0 | J16: =J93*$E$81 -> 0 | K16: =K93*$E$81 -> 0 | L16: =L93*$E$81 -> 0 | ... N16: =N93*$E$81 -> 0
B17: Трудозатраты на капитальные ремонты (цех) | C17: чел-час/год | E17: =E157*$E$81 -> 0 | F17: =F157*$E$81 -> 316 | G17: =G157*$E$81 -> 524 | H17: =H157*$E$81 -> 316 | I17: =I157*$E$81 -> 8 | J17: =J157*$E$81 -> 760 | K17: =K157*$E$81 -> 80 | L17: =L157*$E$81 -> 760 | ... N17: =N157*$E$81 -> 244
B18: Сервис ТО (авто) = трудозатраты ТО × ставка | C18: тыс/год | E18: =E15*$E$77/1000 -> 27.321 | F18: =F15*$E$77/1000 -> 27.321 | G18: =G15*$E$77/1000 -> 27.321 | H18: =H15*$E$77/1000 -> 27.321 | I18: =I15*$E$77/1000 -> 27.321 | J18: =J15*$E$77/1000 -> 27.321 | K18: =K15*$E$77/1000 -> 27.321 | L18: =L15*$E$77/1000 -> 27.321 | ... N18: =N15*$E$77/1000 -> 27.321
B19: Сервис текущих ремонтов (авто) | C19: тыс/год | E19: =E16*$E$77/1000 -> 0 | F19: =F16*$E$77/1000 -> 0 | G19: =G16*$E$77/1000 -> 0 | H19: =H16*$E$77/1000 -> 0 | I19: =I16*$E$77/1000 -> 0 | J19: =J16*$E$77/1000 -> 0 | K19: =K16*$E$77/1000 -> 0 | L19: =L16*$E$77/1000 -> 0 | ... N19: =N16*$E$77/1000 -> 0
B20: Сервис капитальных ремонтов (цех, авто) | C20: тыс/год | E20: =E17*$E$77/1000 -> 0 | F20: =F17*$E$77/1000 -> 15.8 | G20: =G17*$E$77/1000 -> 26.2 | H20: =H17*$E$77/1000 -> 15.8 | I20: =I17*$E$77/1000 -> 0.4 | J20: =J17*$E$77/1000 -> 38 | K20: =K17*$E$77/1000 -> 4 | L20: =L17*$E$77/1000 -> 38 | ... N20: =N17*$E$77/1000 -> 12.2
B21: ИТОГО ТОиР (авто) → «Данные по годам» | C21: тыс/год | E21: =E12+E13+E14+E18+E19+E20 -> 136.58272 | F21: =F12+F13+F14+F18+F19+F20 -> 1502.6031 | G21: =G12+G13+G14+G18+G19+G20 -> 1600.5995 | H21: =H12+H13+H14+H18+H19+H20 -> 1500.8611 | I21: =I12+I13+I14+I18+I19+I20 -> 144.49142 | J21: =J12+J13+J14+J18+J19+J20 -> 2911.5628 | K21: =K12+K13+K14+K18+K19+K20 -> 190.76882 | L21: =L12+L13+L14+L18+L19+L20 -> 2910.6918 | ... N21: =N12+N13+N14+N18+N19+N20 -> 1454.5837
B22: Удельный расход ДТ | C22: кг/час | E22: 88.46 | F22: 88.46 | G22: 88.46 | H22: 88.46 | I22: 88.46 | J22: 88.46 | K22: 88.46 | L22: 88.46 | M22: 88.46 | N22: 88.46
B23: Расходники на ковш | C23: руб/м³ | E23: 0.87 | F23: 0.87 | G23: 0.87 | H23: 0.87 | I23: 0.87 | J23: 0.87 | K23: 0.87 | L23: 0.87 | M23: 0.87 | N23: 0.87
B24: РАСЧЁТ ТО (по интервалам обслуживания), ПО ГОДАМ
B25: Наработка по годам | C25: м/час | E25: 7000 | F25: 7000 | G25: 7000 | H25: 7000 | I25: 7000 | J25: 7000 | K25: 7000 | L25: 7000 | M25: 7000 | N25: 7000
B26: Вид ТО | C26: интервал | D26: длит.простоя | E26: персонал
B27: ТО-1 | C27: 500 | D27: 10.2 | E27: 2
B28: ТО-2 | C28: 1000 | D28: 9.4 | E28: 2
B29: ТО-3 | C29: 2000 | D29: 12.4 | E29: 2
B30: ТО-4 | C30: 4000 | D30: 7.8 | E30: 2
B31: ТО-5 | C31: 5000 | D31: 5.4 | E31: 2
B32: ТО-1: простои, ч/год | C32: #,##0 | E32: =(E$25/$C27)*$D27 -> 142.8 | F32: =(F$25/$C27)*$D27 -> 142.8 | G32: =(G$25/$C27)*$D27 -> 142.8 | H32: =(H$25/$C27)*$D27 -> 142.8 | I32: =(I$25/$C27)*$D27 -> 142.8 | J32: =(J$25/$C27)*$D27 -> 142.8 | K32: =(K$25/$C27)*$D27 -> 142.8 | L32: =(L$25/$C27)*$D27 -> 142.8 | ... N32: =(N$25/$C27)*$D27 -> 142.8
B33: ТО-2: простои, ч/год | C33: #,##0 | E33: =(E$25/$C28)*$D28 -> 65.8 | F33: =(F$25/$C28)*$D28 -> 65.8 | G33: =(G$25/$C28)*$D28 -> 65.8 | H33: =(H$25/$C28)*$D28 -> 65.8 | I33: =(I$25/$C28)*$D28 -> 65.8 | J33: =(J$25/$C28)*$D28 -> 65.8 | K33: =(K$25/$C28)*$D28 -> 65.8 | L33: =(L$25/$C28)*$D28 -> 65.8 | ... N33: =(N$25/$C28)*$D28 -> 65.8
B34: ТО-3: простои, ч/год | C34: #,##0 | E34: =(E$25/$C29)*$D29 -> 43.4 | F34: =(F$25/$C29)*$D29 -> 43.4 | G34: =(G$25/$C29)*$D29 -> 43.4 | H34: =(H$25/$C29)*$D29 -> 43.4 | I34: =(I$25/$C29)*$D29 -> 43.4 | J34: =(J$25/$C29)*$D29 -> 43.4 | K34: =(K$25/$C29)*$D29 -> 43.4 | L34: =(L$25/$C29)*$D29 -> 43.4 | ... N34: =(N$25/$C29)*$D29 -> 43.4
B35: ТО-4: простои, ч/год | C35: #,##0 | E35: =(E$25/$C30)*$D30 -> 13.65 | F35: =(F$25/$C30)*$D30 -> 13.65 | G35: =(G$25/$C30)*$D30 -> 13.65 | H35: =(H$25/$C30)*$D30 -> 13.65 | I35: =(I$25/$C30)*$D30 -> 13.65 | J35: =(J$25/$C30)*$D30 -> 13.65 | K35: =(K$25/$C30)*$D30 -> 13.65 | L35: =(L$25/$C30)*$D30 -> 13.65 | ... N35: =(N$25/$C30)*$D30 -> 13.65
B36: ТО-5: простои, ч/год | C36: #,##0 | E36: =(E$25/$C31)*$D31 -> 7.56 | F36: =(F$25/$C31)*$D31 -> 7.56 | G36: =(G$25/$C31)*$D31 -> 7.56 | H36: =(H$25/$C31)*$D31 -> 7.56 | I36: =(I$25/$C31)*$D31 -> 7.56 | J36: =(J$25/$C31)*$D31 -> 7.56 | K36: =(K$25/$C31)*$D31 -> 7.56 | L36: =(L$25/$C31)*$D31 -> 7.56 | ... N36: =(N$25/$C31)*$D31 -> 7.56
B37: Итого простои ТО, ч/год | C37: ч/год | E37: =SUM(E32:E36) -> 273.21 | F37: =SUM(F32:F36) -> 273.21 | G37: =SUM(G32:G36) -> 273.21 | H37: =SUM(H32:H36) -> 273.21 | I37: =SUM(I32:I36) -> 273.21 | J37: =SUM(J32:J36) -> 273.21 | K37: =SUM(K32:K36) -> 273.21 | L37: =SUM(L32:L36) -> 273.21 | ... N37: =SUM(N32:N36) -> 273.21
B38: ТО-1: ч·часы/год | C38: #,##0 | E38: =E32*$E27 -> 285.6 | F38: =F32*$E27 -> 285.6 | G38: =G32*$E27 -> 285.6 | H38: =H32*$E27 -> 285.6 | I38: =I32*$E27 -> 285.6 | J38: =J32*$E27 -> 285.6 | K38: =K32*$E27 -> 285.6 | L38: =L32*$E27 -> 285.6 | ... N38: =N32*$E27 -> 285.6
B39: ТО-2: ч·часы/год | C39: #,##0 | E39: =E33*$E28 -> 131.6 | F39: =F33*$E28 -> 131.6 | G39: =G33*$E28 -> 131.6 | H39: =H33*$E28 -> 131.6 | I39: =I33*$E28 -> 131.6 | J39: =J33*$E28 -> 131.6 | K39: =K33*$E28 -> 131.6 | L39: =L33*$E28 -> 131.6 | ... N39: =N33*$E28 -> 131.6
B40: ТО-3: ч·часы/год | C40: #,##0 | E40: =E34*$E29 -> 86.8 | F40: =F34*$E29 -> 86.8 | G40: =G34*$E29 -> 86.8 | H40: =H34*$E29 -> 86.8 | I40: =I34*$E29 -> 86.8 | J40: =J34*$E29 -> 86.8 | K40: =K34*$E29 -> 86.8 | L40: =L34*$E29 -> 86.8 | ... N40: =N34*$E29 -> 86.8
B41: ТО-4: ч·часы/год | C41: #,##0 | E41: =E35*$E30 -> 27.3 | F41: =F35*$E30 -> 27.3 | G41: =G35*$E30 -> 27.3 | H41: =H35*$E30 -> 27.3 | I41: =I35*$E30 -> 27.3 | J41: =J35*$E30 -> 27.3 | K41: =K35*$E30 -> 27.3 | L41: =L35*$E30 -> 27.3 | ... N41: =N35*$E30 -> 27.3
B42: ТО-5: ч·часы/год | C42: #,##0 | E42: =E36*$E31 -> 15.12 | F42: =F36*$E31 -> 15.12 | G42: =G36*$E31 -> 15.12 | H42: =H36*$E31 -> 15.12 | I42: =I36*$E31 -> 15.12 | J42: =J36*$E31 -> 15.12 | K42: =K36*$E31 -> 15.12 | L42: =L36*$E31 -> 15.12 | ... N42: =N36*$E31 -> 15.12
B43: Итого ч·часы ТО, ч-час/год | C43: ч-час | E43: =SUM(E38:E42) -> 546.42 | F43: =SUM(F38:F42) -> 546.42 | G43: =SUM(G38:G42) -> 546.42 | H43: =SUM(H38:H42) -> 546.42 | I43: =SUM(I38:I42) -> 546.42 | J43: =SUM(J38:J42) -> 546.42 | K43: =SUM(K38:K42) -> 546.42 | L43: =SUM(L38:L42) -> 546.42 | ... N43: =SUM(N38:N42) -> 546.42
B45: КАТАЛОГ ЗАПЧАСТЕЙ ТО (заполняет подрядчик), ПО ГОДАМ
B46: Наименование | C46: цена за ед | D46: кол-во/ТО | E46: год 1 | F46: год 2 | G46: год 3 | H46: год 4 | I46: год 5 | J46: год 6 | K46: год 7 | L46: год 8 | M46: год 9 | N46: год 10 | P46: № ТО
B47: Масляный фильтр | C47: 114.83 | D47: 4 | E47: =(E$25/INDEX($C$27:$C$31,$P47))*D47*C47/1000 -> 6.43048 | F47: =(F$25/INDEX($C$27:$C$31,$P47))*D47*C47/1000 -> 6.43048 | G47: =(G$25/INDEX($C$27:$C$31,$P47))*D47*C47/1000 -> 6.43048 | H47: =(H$25/INDEX($C$27:$C$31,$P47))*D47*C47/1000 -> 6.43048 | I47: =(I$25/INDEX($C$27:$C$31,$P47))*D47*C47/1000 -> 6.43048 | J47: =(J$25/INDEX($C$27:$C$31,$P47))*D47*C47/1000 -> 6.43048 | K47: =(K$25/INDEX($C$27:$C$31,$P47))*D47*C47/1000 -> 6.43048 | L47: =(L$25/INDEX($C$27:$C$31,$P47))*D47*C47/1000 -> 6.43048 | M47: =(M$25/INDEX($C$27:$C$31,$P47))*D47*C47/1000 -> 6.43048 | N47: =(N$25/INDEX($C$27:$C$31,$P47))*D47*C47/1000 -> 6.43048 | P47: 1
B48: Топливный фильтр | C48: 141.33 | D48: 2 | E48: =(E$25/INDEX($C$27:$C$31,$P48))*D48*C48/1000 -> 3.95724 | F48: =(F$25/INDEX($C$27:$C$31,$P48))*D48*C48/1000 -> 3.95724 | G48: =(G$25/INDEX($C$27:$C$31,$P48))*D48*C48/1000 -> 3.95724 | H48: =(H$25/INDEX($C$27:$C$31,$P48))*D48*C48/1000 -> 3.95724 | I48: =(I$25/INDEX($C$27:$C$31,$P48))*D48*C48/1000 -> 3.95724 | J48: =(J$25/INDEX($C$27:$C$31,$P48))*D48*C48/1000 -> 3.95724 | K48: =(K$25/INDEX($C$27:$C$31,$P48))*D48*C48/1000 -> 3.95724 | L48: =(L$25/INDEX($C$27:$C$31,$P48))*D48*C48/1000 -> 3.95724 | M48: =(M$25/INDEX($C$27:$C$31,$P48))*D48*C48/1000 -> 3.95724 | N48: =(N$25/INDEX($C$27:$C$31,$P48))*D48*C48/1000 -> 3.95724 | P48: 1
B49: Масло ДВС | C49: 6.87 | D49: 130 | E49: =(E$25/INDEX($C$27:$C$31,$P49))*D49*C49/1000 -> 12.5034 | F49: =(F$25/INDEX($C$27:$C$31,$P49))*D49*C49/1000 -> 12.5034 | G49: =(G$25/INDEX($C$27:$C$31,$P49))*D49*C49/1000 -> 12.5034 | H49: =(H$25/INDEX($C$27:$C$31,$P49))*D49*C49/1000 -> 12.5034 | I49: =(I$25/INDEX($C$27:$C$31,$P49))*D49*C49/1000 -> 12.5034 | J49: =(J$25/INDEX($C$27:$C$31,$P49))*D49*C49/1000 -> 12.5034 | K49: =(K$25/INDEX($C$27:$C$31,$P49))*D49*C49/1000 -> 12.5034 | L49: =(L$25/INDEX($C$27:$C$31,$P49))*D49*C49/1000 -> 12.5034 | M49: =(M$25/INDEX($C$27:$C$31,$P49))*D49*C49/1000 -> 12.5034 | N49: =(N$25/INDEX($C$27:$C$31,$P49))*D49*C49/1000 -> 12.5034 | P49: 1
B50: Фильтр управляющего контура | C50: 126 | D50: 1 | E50: =(E$25/INDEX($C$27:$C$31,$P50))*D50*C50/1000 -> 1.764 | F50: =(F$25/INDEX($C$27:$C$31,$P50))*D50*C50/1000 -> 1.764 | G50: =(G$25/INDEX($C$27:$C$31,$P50))*D50*C50/1000 -> 1.764 | H50: =(H$25/INDEX($C$27:$C$31,$P50))*D50*C50/1000 -> 1.764 | I50: =(I$25/INDEX($C$27:$C$31,$P50))*D50*C50/1000 -> 1.764 | J50: =(J$25/INDEX($C$27:$C$31,$P50))*D50*C50/1000 -> 1.764 | K50: =(K$25/INDEX($C$27:$C$31,$P50))*D50*C50/1000 -> 1.764 | L50: =(L$25/INDEX($C$27:$C$31,$P50))*D50*C50/1000 -> 1.764 | M50: =(M$25/INDEX($C$27:$C$31,$P50))*D50*C50/1000 -> 1.764 | N50: =(N$25/INDEX($C$27:$C$31,$P50))*D50*C50/1000 -> 1.764 | P50: 1
B51: Сливной фильтр | C51: 30.67 | D51: 2 | E51: =(E$25/INDEX($C$27:$C$31,$P51))*D51*C51/1000 -> 0.85876 | F51: =(F$25/INDEX($C$27:$C$31,$P51))*D51*C51/1000 -> 0.85876 | G51: =(G$25/INDEX($C$27:$C$31,$P51))*D51*C51/1000 -> 0.85876 | H51: =(H$25/INDEX($C$27:$C$31,$P51))*D51*C51/1000 -> 0.85876 | I51: =(I$25/INDEX($C$27:$C$31,$P51))*D51*C51/1000 -> 0.85876 | J51: =(J$25/INDEX($C$27:$C$31,$P51))*D51*C51/1000 -> 0.85876 | K51: =(K$25/INDEX($C$27:$C$31,$P51))*D51*C51/1000 -> 0.85876 | L51: =(L$25/INDEX($C$27:$C$31,$P51))*D51*C51/1000 -> 0.85876 | M51: =(M$25/INDEX($C$27:$C$31,$P51))*D51*C51/1000 -> 0.85876 | N51: =(N$25/INDEX($C$27:$C$31,$P51))*D51*C51/1000 -> 0.85876 | P51: 1
B52: Сливной фильтр насоса | C52: 201 | D52: 3 | E52: =(E$25/INDEX($C$27:$C$31,$P52))*D52*C52/1000 -> 8.442 | F52: =(F$25/INDEX($C$27:$C$31,$P52))*D52*C52/1000 -> 8.442 | G52: =(G$25/INDEX($C$27:$C$31,$P52))*D52*C52/1000 -> 8.442 | H52: =(H$25/INDEX($C$27:$C$31,$P52))*D52*C52/1000 -> 8.442 | I52: =(I$25/INDEX($C$27:$C$31,$P52))*D52*C52/1000 -> 8.442 | J52: =(J$25/INDEX($C$27:$C$31,$P52))*D52*C52/1000 -> 8.442 | K52: =(K$25/INDEX($C$27:$C$31,$P52))*D52*C52/1000 -> 8.442 | L52: =(L$25/INDEX($C$27:$C$31,$P52))*D52*C52/1000 -> 8.442 | M52: =(M$25/INDEX($C$27:$C$31,$P52))*D52*C52/1000 -> 8.442 | N52: =(N$25/INDEX($C$27:$C$31,$P52))*D52*C52/1000 -> 8.442 | P52: 1
B53: Смазка | C53: 12.24 | D53: 200 | E53: =(E$25/INDEX($C$27:$C$31,$P53))*D53*C53/1000 -> 34.272 | F53: =(F$25/INDEX($C$27:$C$31,$P53))*D53*C53/1000 -> 34.272 | G53: =(G$25/INDEX($C$27:$C$31,$P53))*D53*C53/1000 -> 34.272 | H53: =(H$25/INDEX($C$27:$C$31,$P53))*D53*C53/1000 -> 34.272 | I53: =(I$25/INDEX($C$27:$C$31,$P53))*D53*C53/1000 -> 34.272 | J53: =(J$25/INDEX($C$27:$C$31,$P53))*D53*C53/1000 -> 34.272 | K53: =(K$25/INDEX($C$27:$C$31,$P53))*D53*C53/1000 -> 34.272 | L53: =(L$25/INDEX($C$27:$C$31,$P53))*D53*C53/1000 -> 34.272 | M53: =(M$25/INDEX($C$27:$C$31,$P53))*D53*C53/1000 -> 34.272 | N53: =(N$25/INDEX($C$27:$C$31,$P53))*D53*C53/1000 -> 34.272 | P53: 1
B54: Топливный фильтр (ТО-2) | C54: 80.17 | D54: 2 | E54: =(E$25/INDEX($C$27:$C$31,$P54))*D54*C54/1000 -> 1.12238 | F54: =(F$25/INDEX($C$27:$C$31,$P54))*D54*C54/1000 -> 1.12238 | G54: =(G$25/INDEX($C$27:$C$31,$P54))*D54*C54/1000 -> 1.12238 | H54: =(H$25/INDEX($C$27:$C$31,$P54))*D54*C54/1000 -> 1.12238 | I54: =(I$25/INDEX($C$27:$C$31,$P54))*D54*C54/1000 -> 1.12238 | J54: =(J$25/INDEX($C$27:$C$31,$P54))*D54*C54/1000 -> 1.12238 | K54: =(K$25/INDEX($C$27:$C$31,$P54))*D54*C54/1000 -> 1.12238 | L54: =(L$25/INDEX($C$27:$C$31,$P54))*D54*C54/1000 -> 1.12238 | M54: =(M$25/INDEX($C$27:$C$31,$P54))*D54*C54/1000 -> 1.12238 | N54: =(N$25/INDEX($C$27:$C$31,$P54))*D54*C54/1000 -> 1.12238 | P54: 2
B55: Фильтр сапуна топл.бака | C55: 19.17 | D55: 1 | E55: =(E$25/INDEX($C$27:$C$31,$P55))*D55*C55/1000 -> 0.13419 | F55: =(F$25/INDEX($C$27:$C$31,$P55))*D55*C55/1000 -> 0.13419 | G55: =(G$25/INDEX($C$27:$C$31,$P55))*D55*C55/1000 -> 0.13419 | H55: =(H$25/INDEX($C$27:$C$31,$P55))*D55*C55/1000 -> 0.13419 | I55: =(I$25/INDEX($C$27:$C$31,$P55))*D55*C55/1000 -> 0.13419 | J55: =(J$25/INDEX($C$27:$C$31,$P55))*D55*C55/1000 -> 0.13419 | K55: =(K$25/INDEX($C$27:$C$31,$P55))*D55*C55/1000 -> 0.13419 | L55: =(L$25/INDEX($C$27:$C$31,$P55))*D55*C55/1000 -> 0.13419 | M55: =(M$25/INDEX($C$27:$C$31,$P55))*D55*C55/1000 -> 0.13419 | N55: =(N$25/INDEX($C$27:$C$31,$P55))*D55*C55/1000 -> 0.13419 | P55: 2
B56: Фильтр сапуна гидробака | C56: 19.17 | D56: 2 | E56: =(E$25/INDEX($C$27:$C$31,$P56))*D56*C56/1000 -> 0.26838 | F56: =(F$25/INDEX($C$27:$C$31,$P56))*D56*C56/1000 -> 0.26838 | G56: =(G$25/INDEX($C$27:$C$31,$P56))*D56*C56/1000 -> 0.26838 | H56: =(H$25/INDEX($C$27:$C$31,$P56))*D56*C56/1000 -> 0.26838 | I56: =(I$25/INDEX($C$27:$C$31,$P56))*D56*C56/1000 -> 0.26838 | J56: =(J$25/INDEX($C$27:$C$31,$P56))*D56*C56/1000 -> 0.26838 | K56: =(K$25/INDEX($C$27:$C$31,$P56))*D56*C56/1000 -> 0.26838 | L56: =(L$25/INDEX($C$27:$C$31,$P56))*D56*C56/1000 -> 0.26838 | M56: =(M$25/INDEX($C$27:$C$31,$P56))*D56*C56/1000 -> 0.26838 | N56: =(N$25/INDEX($C$27:$C$31,$P56))*D56*C56/1000 -> 0.26838 | P56: 2
B57: Гидравлический фильтр | C57: 344.33 | D57: 3 | E57: =(E$25/INDEX($C$27:$C$31,$P57))*D57*C57/1000 -> 7.23093 | F57: =(F$25/INDEX($C$27:$C$31,$P57))*D57*C57/1000 -> 7.23093 | G57: =(G$25/INDEX($C$27:$C$31,$P57))*D57*C57/1000 -> 7.23093 | H57: =(H$25/INDEX($C$27:$C$31,$P57))*D57*C57/1000 -> 7.23093 | I57: =(I$25/INDEX($C$27:$C$31,$P57))*D57*C57/1000 -> 7.23093 | J57: =(J$25/INDEX($C$27:$C$31,$P57))*D57*C57/1000 -> 7.23093 | K57: =(K$25/INDEX($C$27:$C$31,$P57))*D57*C57/1000 -> 7.23093 | L57: =(L$25/INDEX($C$27:$C$31,$P57))*D57*C57/1000 -> 7.23093 | M57: =(M$25/INDEX($C$27:$C$31,$P57))*D57*C57/1000 -> 7.23093 | N57: =(N$25/INDEX($C$27:$C$31,$P57))*D57*C57/1000 -> 7.23093 | P57: 2
B58: О-кольцо | C58: 24.5 | D58: 3 | E58: =(E$25/INDEX($C$27:$C$31,$P58))*D58*C58/1000 -> 0.5145 | F58: =(F$25/INDEX($C$27:$C$31,$P58))*D58*C58/1000 -> 0.5145 | G58: =(G$25/INDEX($C$27:$C$31,$P58))*D58*C58/1000 -> 0.5145 | H58: =(H$25/INDEX($C$27:$C$31,$P58))*D58*C58/1000 -> 0.5145 | I58: =(I$25/INDEX($C$27:$C$31,$P58))*D58*C58/1000 -> 0.5145 | J58: =(J$25/INDEX($C$27:$C$31,$P58))*D58*C58/1000 -> 0.5145 | K58: =(K$25/INDEX($C$27:$C$31,$P58))*D58*C58/1000 -> 0.5145 | L58: =(L$25/INDEX($C$27:$C$31,$P58))*D58*C58/1000 -> 0.5145 | M58: =(M$25/INDEX($C$27:$C$31,$P58))*D58*C58/1000 -> 0.5145 | N58: =(N$25/INDEX($C$27:$C$31,$P58))*D58*C58/1000 -> 0.5145 | P58: 2
... B73: Гидравлическое масло | C73: 6.43 | D73: 1300 | E73: =(E$25/INDEX($C$27:$C$31,$P73))*D73*C73/1000 -> 11.7026 | F73: =(F$25/INDEX($C$27:$C$31,$P73))*D73*C73/1000 -> 11.7026 | G73: =(G$25/INDEX($C$27:$C$31,$P73))*D73*C73/1000 -> 11.7026 | H73: =(H$25/INDEX($C$27:$C$31,$P73))*D73*C73/1000 -> 11.7026 | I73: =(I$25/INDEX($C$27:$C$31,$P73))*D73*C73/1000 -> 11.7026 | J73: =(J$25/INDEX($C$27:$C$31,$P73))*D73*C73/1000 -> 11.7026 | K73: =(K$25/INDEX($C$27:$C$31,$P73))*D73*C73/1000 -> 11.7026 | L73: =(L$25/INDEX($C$27:$C$31,$P73))*D73*C73/1000 -> 11.7026 | M73: =(M$25/INDEX($C$27:$C$31,$P73))*D73*C73/1000 -> 11.7026 | N73: =(N$25/INDEX($C$27:$C$31,$P73))*D73*C73/1000 -> 11.7026 | P73: 5
B74: Корректировка (поглощения/прочее) | E74: 0 | F74: 0 | G74: 0 | H74: 0 | I74: 0 | J74: 0 | K74: 0 | L74: 0 | M74: 0 | N74: 0
B75: ИТОГО затраты на запчасти ТО, тыс/год | E75: =SUM(E47:E74) -> 107.51972 | F75: =SUM(F47:F74) -> 107.51972 | G75: =SUM(G47:G74) -> 107.51972 | H75: =SUM(H47:H74) -> 107.51972 | I75: =SUM(I47:I74) -> 107.51972 | J75: =SUM(J47:J74) -> 107.51972 | K75: =SUM(K47:K74) -> 107.51972 | L75: =SUM(L47:L74) -> 107.51972 | ... N75: =SUM(N47:N74) -> 107.51972
B77: Ставка сервиса | C77: вал/ч·час | E77: 50
B79: РАСЧЁТ РЕМОНТОВ (из списков по периодичности замены узлов)
B80: Простои в текущих + капитальных ремонтах | C80: ч/год | E80: 160.72 | F80: 377.53 | G80: 737.94 | H80: 828.05 | I80: 737.94 | J80: 1169.1 | K80: 1399.63 | L80: 894.37 | M80: 1842.78 | N80: 1037.94
B81: Коэффициент поглощения (0–1; 1=как у поставщика) | C81: коэф. | E81: 1
B83: ТЕКУЩИЕ РЕМОНТЫ — ЗАТРАТЫ НА ЗЧ (по ресурсу замены)
B84: Наименование | C84: стоим.замены,тыс | D84: ресурс, м/ч | E84: год 1 | F84: год 2 | G84: год 3 | H84: год 4 | I84: год 5 | J84: год 6 | K84: год 7 | L84: год 8 | M84: год 9 | N84: год 10
B85: Ремонт системы смазки | C85: 1.742 | D85: 10000 | E85: =(INT($E$25*1/$D85)-INT($E$25*(1-1)/$D85))*$C85 -> 0 | F85: =(INT($E$25*2/$D85)-INT($E$25*(2-1)/$D85))*$C85 -> 1.742 | G85: =(INT($E$25*3/$D85)-INT($E$25*(3-1)/$D85))*$C85 -> 1.742 | H85: =(INT($E$25*4/$D85)-INT($E$25*(4-1)/$D85))*$C85 -> 0 | I85: =(INT($E$25*5/$D85)-INT($E$25*(5-1)/$D85))*$C85 -> 1.742 | J85: =(INT($E$25*6/$D85)-INT($E$25*(6-1)/$D85))*$C85 -> 1.742 | K85: =(INT($E$25*7/$D85)-INT($E$25*(7-1)/$D85))*$C85 -> 0 | L85: =(INT($E$25*8/$D85)-INT($E$25*(8-1)/$D85))*$C85 -> 1.742 | M85: =(INT($E$25*9/$D85)-INT($E$25*(9-1)/$D85))*$C85 -> 1.742 | N85: =(INT($E$25*10/$D85)-INT($E$25*(10-1)/$D85))*$C85 -> 1.742
B86: Ремонт системы кондиционирования | C86: 0.871 | D86: 12000 | E86: =(INT($E$25*1/$D86)-INT($E$25*(1-1)/$D86))*$C86 -> 0 | F86: =(INT($E$25*2/$D86)-INT($E$25*(2-1)/$D86))*$C86 -> 0.871 | G86: =(INT($E$25*3/$D86)-INT($E$25*(3-1)/$D86))*$C86 -> 0 | H86: =(INT($E$25*4/$D86)-INT($E$25*(4-1)/$D86))*$C86 -> 0.871 | I86: =(INT($E$25*5/$D86)-INT($E$25*(5-1)/$D86))*$C86 -> 0 | J86: =(INT($E$25*6/$D86)-INT($E$25*(6-1)/$D86))*$C86 -> 0.871 | K86: =(INT($E$25*7/$D86)-INT($E$25*(7-1)/$D86))*$C86 -> 0.871 | L86: =(INT($E$25*8/$D86)-INT($E$25*(8-1)/$D86))*$C86 -> 0 | M86: =(INT($E$25*9/$D86)-INT($E$25*(9-1)/$D86))*$C86 -> 0.871 | N86: =(INT($E$25*10/$D86)-INT($E$25*(10-1)/$D86))*$C86 -> 0
B87: Чистка радиаторов | C87: 1.742 | D87: 7000 | E87: =(INT($E$25*1/$D87)-INT($E$25*(1-1)/$D87))*$C87 -> 1.742 | F87: =(INT($E$25*2/$D87)-INT($E$25*(2-1)/$D87))*$C87 -> 1.742 | G87: =(INT($E$25*3/$D87)-INT($E$25*(3-1)/$D87))*$C87 -> 1.742 | H87: =(INT($E$25*4/$D87)-INT($E$25*(4-1)/$D87))*$C87 -> 1.742 | I87: =(INT($E$25*5/$D87)-INT($E$25*(5-1)/$D87))*$C87 -> 1.742 | J87: =(INT($E$25*6/$D87)-INT($E$25*(6-1)/$D87))*$C87 -> 1.742 | K87: =(INT($E$25*7/$D87)-INT($E$25*(7-1)/$D87))*$C87 -> 1.742 | L87: =(INT($E$25*8/$D87)-INT($E$25*(8-1)/$D87))*$C87 -> 1.742 | M87: =(INT($E$25*9/$D87)-INT($E$25*(9-1)/$D87))*$C87 -> 1.742 | N87: =(INT($E$25*10/$D87)-INT($E$25*(10-1)/$D87))*$C87 -> 1.742
B88: ИТОГО | E88: =SUM(E85:E87) -> 1.742 | F88: =SUM(F85:F87) -> 4.355 | G88: =SUM(G85:G87) -> 3.484 | H88: =SUM(H85:H87) -> 2.613 | I88: =SUM(I85:I87) -> 3.484 | J88: =SUM(J85:J87) -> 4.355 | K88: =SUM(K85:K87) -> 2.613 | L88: =SUM(L85:L87) -> 3.484 | ... N88: =SUM(N85:N87) -> 3.484
B90: ТЕКУЩИЕ РЕМОНТЫ — ТРУДОЗАТРАТЫ (по ресурсу замены)
B91: Наименование | C91: нормо-час/событие | D91: ресурс, м/ч | E91: год 1 | F91: год 2 | G91: год 3 | H91: год 4 | I91: год 5 | J91: год 6 | K91: год 7 | L91: год 8 | M91: год 9 | N91: год 10
B93: ИТОГО | E93: =SUM(E92:E92) -> 0 | F93: =SUM(F92:F92) -> 0 | G93: =SUM(G92:G92) -> 0 | H93: =SUM(H92:H92) -> 0 | I93: =SUM(I92:I92) -> 0 | J93: =SUM(J92:J92) -> 0 | K93: =SUM(K92:K92) -> 0 | L93: =SUM(L92:L92) -> 0 | ... N93: =SUM(N92:N92) -> 0
B95: КАПИТАЛЬНЫЕ РЕМОНТЫ (ЦЕХ) — ЗАТРАТЫ НА ЗЧ (по ресурсу до замены узла)
B96: Наименование | C96: стоим.замены,тыс | D96: ресурс, м/ч | E96: год 1 | F96: год 2 | G96: год 3 | H96: год 4 | I96: год 5 | J96: год 6 | K96: год 7 | L96: год 8 | M96: год 9 | N96: год 10
B97: Звёздочка | C97: 15.768 | D97: 17600 | E97: =(INT($E$25*1/$D97)-INT($E$25*(1-1)/$D97))*$C97 -> 0 | F97: =(INT($E$25*2/$D97)-INT($E$25*(2-1)/$D97))*$C97 -> 0 | G97: =(INT($E$25*3/$D97)-INT($E$25*(3-1)/$D97))*$C97 -> 15.768 | H97: =(INT($E$25*4/$D97)-INT($E$25*(4-1)/$D97))*$C97 -> 0 | I97: =(INT($E$25*5/$D97)-INT($E$25*(5-1)/$D97))*$C97 -> 0 | J97: =(INT($E$25*6/$D97)-INT($E$25*(6-1)/$D97))*$C97 -> 15.768 | K97: =(INT($E$25*7/$D97)-INT($E$25*(7-1)/$D97))*$C97 -> 0 | L97: =(INT($E$25*8/$D97)-INT($E$25*(8-1)/$D97))*$C97 -> 15.768 | M97: =(INT($E$25*9/$D97)-INT($E$25*(9-1)/$D97))*$C97 -> 0 | N97: =(INT($E$25*10/$D97)-INT($E$25*(10-1)/$D97))*$C97 -> 0
B98: Редуктор хода | C98: 471.3007 | D98: 17600 | E98: =(INT($E$25*1/$D98)-INT($E$25*(1-1)/$D98))*$C98 -> 0 | F98: =(INT($E$25*2/$D98)-INT($E$25*(2-1)/$D98))*$C98 -> 0 | G98: =(INT($E$25*3/$D98)-INT($E$25*(3-1)/$D98))*$C98 -> 471.3007 | H98: =(INT($E$25*4/$D98)-INT($E$25*(4-1)/$D98))*$C98 -> 0 | I98: =(INT($E$25*5/$D98)-INT($E$25*(5-1)/$D98))*$C98 -> 0 | J98: =(INT($E$25*6/$D98)-INT($E$25*(6-1)/$D98))*$C98 -> 471.3007 | K98: =(INT($E$25*7/$D98)-INT($E$25*(7-1)/$D98))*$C98 -> 0 | L98: =(INT($E$25*8/$D98)-INT($E$25*(8-1)/$D98))*$C98 -> 471.3007 | M98: =(INT($E$25*9/$D98)-INT($E$25*(9-1)/$D98))*$C98 -> 0 | N98: =(INT($E$25*10/$D98)-INT($E$25*(10-1)/$D98))*$C98 -> 0
B99: Натяжное колесо | C99: 37.1453 | D99: 17600 | E99: =(INT($E$25*1/$D99)-INT($E$25*(1-1)/$D99))*$C99 -> 0 | F99: =(INT($E$25*2/$D99)-INT($E$25*(2-1)/$D99))*$C99 -> 0 | G99: =(INT($E$25*3/$D99)-INT($E$25*(3-1)/$D99))*$C99 -> 37.1453 | H99: =(INT($E$25*4/$D99)-INT($E$25*(4-1)/$D99))*$C99 -> 0 | I99: =(INT($E$25*5/$D99)-INT($E$25*(5-1)/$D99))*$C99 -> 0 | J99: =(INT($E$25*6/$D99)-INT($E$25*(6-1)/$D99))*$C99 -> 37.1453 | K99: =(INT($E$25*7/$D99)-INT($E$25*(7-1)/$D99))*$C99 -> 0 | L99: =(INT($E$25*8/$D99)-INT($E$25*(8-1)/$D99))*$C99 -> 37.1453 | M99: =(INT($E$25*9/$D99)-INT($E$25*(9-1)/$D99))*$C99 -> 0 | N99: =(INT($E$25*10/$D99)-INT($E$25*(10-1)/$D99))*$C99 -> 0
B100: Гусеничная лента | C100: 0.0213 | D100: 17600 | E100: =(INT($E$25*1/$D100)-INT($E$25*(1-1)/$D100))*$C100 -> 0 | F100: =(INT($E$25*2/$D100)-INT($E$25*(2-1)/$D100))*$C100 -> 0 | G100: =(INT($E$25*3/$D100)-INT($E$25*(3-1)/$D100))*$C100 -> 0.0213 | H100: =(INT($E$25*4/$D100)-INT($E$25*(4-1)/$D100))*$C100 -> 0 | I100: =(INT($E$25*5/$D100)-INT($E$25*(5-1)/$D100))*$C100 -> 0 | J100: =(INT($E$25*6/$D100)-INT($E$25*(6-1)/$D100))*$C100 -> 0.0213 | K100: =(INT($E$25*7/$D100)-INT($E$25*(7-1)/$D100))*$C100 -> 0 | L100: =(INT($E$25*8/$D100)-INT($E$25*(8-1)/$D100))*$C100 -> 0.0213 | M100: =(INT($E$25*9/$D100)-INT($E$25*(9-1)/$D100))*$C100 -> 0 | N100: =(INT($E$25*10/$D100)-INT($E$25*(10-1)/$D100))*$C100 -> 0
B101: Г. мотор хода | C101: 77.2393 | D101: 13200 | E101: =(INT($E$25*1/$D101)-INT($E$25*(1-1)/$D101))*$C101 -> 0 | F101: =(INT($E$25*2/$D101)-INT($E$25*(2-1)/$D101))*$C101 -> 77.2393 | G101: =(INT($E$25*3/$D101)-INT($E$25*(3-1)/$D101))*$C101 -> 0 | H101: =(INT($E$25*4/$D101)-INT($E$25*(4-1)/$D101))*$C101 -> 77.2393 | I101: =(INT($E$25*5/$D101)-INT($E$25*(5-1)/$D101))*$C101 -> 0 | J101: =(INT($E$25*6/$D101)-INT($E$25*(6-1)/$D101))*$C101 -> 77.2393 | K101: =(INT($E$25*7/$D101)-INT($E$25*(7-1)/$D101))*$C101 -> 0 | L101: =(INT($E$25*8/$D101)-INT($E$25*(8-1)/$D101))*$C101 -> 77.2393 | M101: =(INT($E$25*9/$D101)-INT($E$25*(9-1)/$D101))*$C101 -> 0 | N101: =(INT($E$25*10/$D101)-INT($E$25*(10-1)/$D101))*$C101 -> 77.2393
B102: Поддерживающий каток | C102: 15.004 | D102: 17600 | E102: =(INT($E$25*1/$D102)-INT($E$25*(1-1)/$D102))*$C102 -> 0 | F102: =(INT($E$25*2/$D102)-INT($E$25*(2-1)/$D102))*$C102 -> 0 | G102: =(INT($E$25*3/$D102)-INT($E$25*(3-1)/$D102))*$C102 -> 15.004 | H102: =(INT($E$25*4/$D102)-INT($E$25*(4-1)/$D102))*$C102 -> 0 | I102: =(INT($E$25*5/$D102)-INT($E$25*(5-1)/$D102))*$C102 -> 0 | J102: =(INT($E$25*6/$D102)-INT($E$25*(6-1)/$D102))*$C102 -> 15.004 | K102: =(INT($E$25*7/$D102)-INT($E$25*(7-1)/$D102))*$C102 -> 0 | L102: =(INT($E$25*8/$D102)-INT($E$25*(8-1)/$D102))*$C102 -> 15.004 | M102: =(INT($E$25*9/$D102)-INT($E$25*(9-1)/$D102))*$C102 -> 0 | N102: =(INT($E$25*10/$D102)-INT($E$25*(10-1)/$D102))*$C102 -> 0
B103: Опорный каток | C103: 54.6107 | D103: 17600 | E103: =(INT($E$25*1/$D103)-INT($E$25*(1-1)/$D103))*$C103 -> 0 | F103: =(INT($E$25*2/$D103)-INT($E$25*(2-1)/$D103))*$C103 -> 0 | G103: =(INT($E$25*3/$D103)-INT($E$25*(3-1)/$D103))*$C103 -> 54.6107 | H103: =(INT($E$25*4/$D103)-INT($E$25*(4-1)/$D103))*$C103 -> 0 | I103: =(INT($E$25*5/$D103)-INT($E$25*(5-1)/$D103))*$C103 -> 0 | J103: =(INT($E$25*6/$D103)-INT($E$25*(6-1)/$D103))*$C103 -> 54.6107 | K103: =(INT($E$25*7/$D103)-INT($E$25*(7-1)/$D103))*$C103 -> 0 | L103: =(INT($E$25*8/$D103)-INT($E$25*(8-1)/$D103))*$C103 -> 54.6107 | M103: =(INT($E$25*9/$D103)-INT($E$25*(9-1)/$D103))*$C103 -> 0 | N103: =(INT($E$25*10/$D103)-INT($E$25*(10-1)/$D103))*$C103 -> 0
B104: Г. цилиндр стрелы | C104: 202.673 | D104: 13200 | E104: =(INT($E$25*1/$D104)-INT($E$25*(1-1)/$D104))*$C104 -> 0 | F104: =(INT($E$25*2/$D104)-INT($E$25*(2-1)/$D104))*$C104 -> 202.673 | G104: =(INT($E$25*3/$D104)-INT($E$25*(3-1)/$D104))*$C104 -> 0 | H104: =(INT($E$25*4/$D104)-INT($E$25*(4-1)/$D104))*$C104 -> 202.673 | I104: =(INT($E$25*5/$D104)-INT($E$25*(5-1)/$D104))*$C104 -> 0 | J104: =(INT($E$25*6/$D104)-INT($E$25*(6-1)/$D104))*$C104 -> 202.673 | K104: =(INT($E$25*7/$D104)-INT($E$25*(7-1)/$D104))*$C104 -> 0 | L104: =(INT($E$25*8/$D104)-INT($E$25*(8-1)/$D104))*$C104 -> 202.673 | M104: =(INT($E$25*9/$D104)-INT($E$25*(9-1)/$D104))*$C104 -> 0 | N104: =(INT($E$25*10/$D104)-INT($E$25*(10-1)/$D104))*$C104 -> 202.673
B105: Г. цилиндр стрелы (2) | C105: 172.3207 | D105: 13200 | E105: =(INT($E$25*1/$D105)-INT($E$25*(1-1)/$D105))*$C105 -> 0 | F105: =(INT($E$25*2/$D105)-INT($E$25*(2-1)/$D105))*$C105 -> 172.3207 | G105: =(INT($E$25*3/$D105)-INT($E$25*(3-1)/$D105))*$C105 -> 0 | H105: =(INT($E$25*4/$D105)-INT($E$25*(4-1)/$D105))*$C105 -> 172.3207 | I105: =(INT($E$25*5/$D105)-INT($E$25*(5-1)/$D105))*$C105 -> 0 | J105: =(INT($E$25*6/$D105)-INT($E$25*(6-1)/$D105))*$C105 -> 172.3207 | K105: =(INT($E$25*7/$D105)-INT($E$25*(7-1)/$D105))*$C105 -> 0 | L105: =(INT($E$25*8/$D105)-INT($E$25*(8-1)/$D105))*$C105 -> 172.3207 | M105: =(INT($E$25*9/$D105)-INT($E$25*(9-1)/$D105))*$C105 -> 0 | N105: =(INT($E$25*10/$D105)-INT($E$25*(10-1)/$D105))*$C105 -> 172.3207
B106: Г. цилиндр рукояти | C106: 63.3717 | D106: 13200 | E106: =(INT($E$25*1/$D106)-INT($E$25*(1-1)/$D106))*$C106 -> 0 | F106: =(INT($E$25*2/$D106)-INT($E$25*(2-1)/$D106))*$C106 -> 63.3717 | G106: =(INT($E$25*3/$D106)-INT($E$25*(3-1)/$D106))*$C106 -> 0 | H106: =(INT($E$25*4/$D106)-INT($E$25*(4-1)/$D106))*$C106 -> 63.3717 | I106: =(INT($E$25*5/$D106)-INT($E$25*(5-1)/$D106))*$C106 -> 0 | J106: =(INT($E$25*6/$D106)-INT($E$25*(6-1)/$D106))*$C106 -> 63.3717 | K106: =(INT($E$25*7/$D106)-INT($E$25*(7-1)/$D106))*$C106 -> 0 | L106: =(INT($E$25*8/$D106)-INT($E$25*(8-1)/$D106))*$C106 -> 63.3717 | M106: =(INT($E$25*9/$D106)-INT($E$25*(9-1)/$D106))*$C106 -> 0 | N106: =(INT($E$25*10/$D106)-INT($E$25*(10-1)/$D106))*$C106 -> 63.3717
B107: Г. цилиндр ковша | C107: 106.5927 | D107: 13200 | E107: =(INT($E$25*1/$D107)-INT($E$25*(1-1)/$D107))*$C107 -> 0 | F107: =(INT($E$25*2/$D107)-INT($E$25*(2-1)/$D107))*$C107 -> 106.5927 | G107: =(INT($E$25*3/$D107)-INT($E$25*(3-1)/$D107))*$C107 -> 0 | H107: =(INT($E$25*4/$D107)-INT($E$25*(4-1)/$D107))*$C107 -> 106.5927 | I107: =(INT($E$25*5/$D107)-INT($E$25*(5-1)/$D107))*$C107 -> 0 | J107: =(INT($E$25*6/$D107)-INT($E$25*(6-1)/$D107))*$C107 -> 106.5927 | K107: =(INT($E$25*7/$D107)-INT($E$25*(7-1)/$D107))*$C107 -> 0 | L107: =(INT($E$25*8/$D107)-INT($E$25*(8-1)/$D107))*$C107 -> 106.5927 | M107: =(INT($E$25*9/$D107)-INT($E$25*(9-1)/$D107))*$C107 -> 0 | N107: =(INT($E$25*10/$D107)-INT($E$25*(10-1)/$D107))*$C107 -> 106.5927
B108: Г. распределитель | C108: 130.6045 | D108: 13200 | E108: =(INT($E$25*1/$D108)-INT($E$25*(1-1)/$D108))*$C108 -> 0 | F108: =(INT($E$25*2/$D108)-INT($E$25*(2-1)/$D108))*$C108 -> 130.6045 | G108: =(INT($E$25*3/$D108)-INT($E$25*(3-1)/$D108))*$C108 -> 0 | H108: =(INT($E$25*4/$D108)-INT($E$25*(4-1)/$D108))*$C108 -> 130.6045 | I108: =(INT($E$25*5/$D108)-INT($E$25*(5-1)/$D108))*$C108 -> 0 | J108: =(INT($E$25*6/$D108)-INT($E$25*(6-1)/$D108))*$C108 -> 130.6045 | K108: =(INT($E$25*7/$D108)-INT($E$25*(7-1)/$D108))*$C108 -> 0 | L108: =(INT($E$25*8/$D108)-INT($E$25*(8-1)/$D108))*$C108 -> 130.6045 | M108: =(INT($E$25*9/$D108)-INT($E$25*(9-1)/$D108))*$C108 -> 0 | N108: =(INT($E$25*10/$D108)-INT($E$25*(10-1)/$D108))*$C108 -> 130.6045
... B124: Стартер | C124: 5.4263 | D124: 8800 | E124: =(INT($E$25*1/$D124)-INT($E$25*(1-1)/$D124))*$C124 -> 0 | F124: =(INT($E$25*2/$D124)-INT($E$25*(2-1)/$D124))*$C124 -> 5.4263 | G124: =(INT($E$25*3/$D124)-INT($E$25*(3-1)/$D124))*$C124 -> 5.4263 | H124: =(INT($E$25*4/$D124)-INT($E$25*(4-1)/$D124))*$C124 -> 5.4263 | I124: =(INT($E$25*5/$D124)-INT($E$25*(5-1)/$D124))*$C124 -> 0 | J124: =(INT($E$25*6/$D124)-INT($E$25*(6-1)/$D124))*$C124 -> 5.4263 | K124: =(INT($E$25*7/$D124)-INT($E$25*(7-1)/$D124))*$C124 -> 5.4263 | L124: =(INT($E$25*8/$D124)-INT($E$25*(8-1)/$D124))*$C124 -> 5.4263 | M124: =(INT($E$25*9/$D124)-INT($E$25*(9-1)/$D124))*$C124 -> 5.4263 | N124: =(INT($E$25*10/$D124)-INT($E$25*(10-1)/$D124))*$C124 -> 0
B125: ИТОГО | E125: =SUM(E97:E124) -> 0 | F125: =SUM(F97:F124) -> 1347.6074 | G125: =SUM(G97:G124) -> 1436.0748 | H125: =SUM(H97:H124) -> 1347.6074 | I125: =SUM(I97:I124) -> 5.7667 | J125: =SUM(J97:J124) -> 2734.3671 | K125: =SUM(K97:K124) -> 49.3151 | L125: =SUM(L97:L124) -> 2734.3671 | ... N125: =SUM(N97:N124) -> 1304.059
B127: КАПИТАЛЬНЫЕ РЕМОНТЫ (ЦЕХ) — ТРУДОЗАТРАТЫ (по ресурсу до замены узла)
B128: Наименование | C128: нормо-час/событие | D128: ресурс, м/ч | E128: год 1 | F128: год 2 | G128: год 3 | H128: год 4 | I128: год 5 | J128: год 6 | K128: год 7 | L128: год 8 | M128: год 9 | N128: год 10
B129: Звёздочка | C129: 24 | D129: 17600 | E129: =(INT($E$25*1/$D129)-INT($E$25*(1-1)/$D129))*$C129 -> 0 | F129: =(INT($E$25*2/$D129)-INT($E$25*(2-1)/$D129))*$C129 -> 0 | G129: =(INT($E$25*3/$D129)-INT($E$25*(3-1)/$D129))*$C129 -> 24 | H129: =(INT($E$25*4/$D129)-INT($E$25*(4-1)/$D129))*$C129 -> 0 | I129: =(INT($E$25*5/$D129)-INT($E$25*(5-1)/$D129))*$C129 -> 0 | J129: =(INT($E$25*6/$D129)-INT($E$25*(6-1)/$D129))*$C129 -> 24 | K129: =(INT($E$25*7/$D129)-INT($E$25*(7-1)/$D129))*$C129 -> 0 | L129: =(INT($E$25*8/$D129)-INT($E$25*(8-1)/$D129))*$C129 -> 24 | M129: =(INT($E$25*9/$D129)-INT($E$25*(9-1)/$D129))*$C129 -> 0 | N129: =(INT($E$25*10/$D129)-INT($E$25*(10-1)/$D129))*$C129 -> 0
B130: Редуктор хода | C130: 24 | D130: 17600 | E130: =(INT($E$25*1/$D130)-INT($E$25*(1-1)/$D130))*$C130 -> 0 | F130: =(INT($E$25*2/$D130)-INT($E$25*(2-1)/$D130))*$C130 -> 0 | G130: =(INT($E$25*3/$D130)-INT($E$25*(3-1)/$D130))*$C130 -> 24 | H130: =(INT($E$25*4/$D130)-INT($E$25*(4-1)/$D130))*$C130 -> 0 | I130: =(INT($E$25*5/$D130)-INT($E$25*(5-1)/$D130))*$C130 -> 0 | J130: =(INT($E$25*6/$D130)-INT($E$25*(6-1)/$D130))*$C130 -> 24 | K130: =(INT($E$25*7/$D130)-INT($E$25*(7-1)/$D130))*$C130 -> 0 | L130: =(INT($E$25*8/$D130)-INT($E$25*(8-1)/$D130))*$C130 -> 24 | M130: =(INT($E$25*9/$D130)-INT($E$25*(9-1)/$D130))*$C130 -> 0 | N130: =(INT($E$25*10/$D130)-INT($E$25*(10-1)/$D130))*$C130 -> 0
B131: Натяжное колесо | C131: 24 | D131: 17600 | E131: =(INT($E$25*1/$D131)-INT($E$25*(1-1)/$D131))*$C131 -> 0 | F131: =(INT($E$25*2/$D131)-INT($E$25*(2-1)/$D131))*$C131 -> 0 | G131: =(INT($E$25*3/$D131)-INT($E$25*(3-1)/$D131))*$C131 -> 24 | H131: =(INT($E$25*4/$D131)-INT($E$25*(4-1)/$D131))*$C131 -> 0 | I131: =(INT($E$25*5/$D131)-INT($E$25*(5-1)/$D131))*$C131 -> 0 | J131: =(INT($E$25*6/$D131)-INT($E$25*(6-1)/$D131))*$C131 -> 24 | K131: =(INT($E$25*7/$D131)-INT($E$25*(7-1)/$D131))*$C131 -> 0 | L131: =(INT($E$25*8/$D131)-INT($E$25*(8-1)/$D131))*$C131 -> 24 | M131: =(INT($E$25*9/$D131)-INT($E$25*(9-1)/$D131))*$C131 -> 0 | N131: =(INT($E$25*10/$D131)-INT($E$25*(10-1)/$D131))*$C131 -> 0
B132: Гусеничная лента | C132: 36 | D132: 17600 | E132: =(INT($E$25*1/$D132)-INT($E$25*(1-1)/$D132))*$C132 -> 0 | F132: =(INT($E$25*2/$D132)-INT($E$25*(2-1)/$D132))*$C132 -> 0 | G132: =(INT($E$25*3/$D132)-INT($E$25*(3-1)/$D132))*$C132 -> 36 | H132: =(INT($E$25*4/$D132)-INT($E$25*(4-1)/$D132))*$C132 -> 0 | I132: =(INT($E$25*5/$D132)-INT($E$25*(5-1)/$D132))*$C132 -> 0 | J132: =(INT($E$25*6/$D132)-INT($E$25*(6-1)/$D132))*$C132 -> 36 | K132: =(INT($E$25*7/$D132)-INT($E$25*(7-1)/$D132))*$C132 -> 0 | L132: =(INT($E$25*8/$D132)-INT($E$25*(8-1)/$D132))*$C132 -> 36 | M132: =(INT($E$25*9/$D132)-INT($E$25*(9-1)/$D132))*$C132 -> 0 | N132: =(INT($E$25*10/$D132)-INT($E$25*(10-1)/$D132))*$C132 -> 0
B133: Г. мотор хода | C133: 12 | D133: 13200 | E133: =(INT($E$25*1/$D133)-INT($E$25*(1-1)/$D133))*$C133 -> 0 | F133: =(INT($E$25*2/$D133)-INT($E$25*(2-1)/$D133))*$C133 -> 12 | G133: =(INT($E$25*3/$D133)-INT($E$25*(3-1)/$D133))*$C133 -> 0 | H133: =(INT($E$25*4/$D133)-INT($E$25*(4-1)/$D133))*$C133 -> 12 | I133: =(INT($E$25*5/$D133)-INT($E$25*(5-1)/$D133))*$C133 -> 0 | J133: =(INT($E$25*6/$D133)-INT($E$25*(6-1)/$D133))*$C133 -> 12 | K133: =(INT($E$25*7/$D133)-INT($E$25*(7-1)/$D133))*$C133 -> 0 | L133: =(INT($E$25*8/$D133)-INT($E$25*(8-1)/$D133))*$C133 -> 12 | M133: =(INT($E$25*9/$D133)-INT($E$25*(9-1)/$D133))*$C133 -> 0 | N133: =(INT($E$25*10/$D133)-INT($E$25*(10-1)/$D133))*$C133 -> 12
B134: Поддерживающий каток | C134: 12 | D134: 17600 | E134: =(INT($E$25*1/$D134)-INT($E$25*(1-1)/$D134))*$C134 -> 0 | F134: =(INT($E$25*2/$D134)-INT($E$25*(2-1)/$D134))*$C134 -> 0 | G134: =(INT($E$25*3/$D134)-INT($E$25*(3-1)/$D134))*$C134 -> 12 | H134: =(INT($E$25*4/$D134)-INT($E$25*(4-1)/$D134))*$C134 -> 0 | I134: =(INT($E$25*5/$D134)-INT($E$25*(5-1)/$D134))*$C134 -> 0 | J134: =(INT($E$25*6/$D134)-INT($E$25*(6-1)/$D134))*$C134 -> 12 | K134: =(INT($E$25*7/$D134)-INT($E$25*(7-1)/$D134))*$C134 -> 0 | L134: =(INT($E$25*8/$D134)-INT($E$25*(8-1)/$D134))*$C134 -> 12 | M134: =(INT($E$25*9/$D134)-INT($E$25*(9-1)/$D134))*$C134 -> 0 | N134: =(INT($E$25*10/$D134)-INT($E$25*(10-1)/$D134))*$C134 -> 0
B135: Опорный каток | C135: 36 | D135: 17600 | E135: =(INT($E$25*1/$D135)-INT($E$25*(1-1)/$D135))*$C135 -> 0 | F135: =(INT($E$25*2/$D135)-INT($E$25*(2-1)/$D135))*$C135 -> 0 | G135: =(INT($E$25*3/$D135)-INT($E$25*(3-1)/$D135))*$C135 -> 36 | H135: =(INT($E$25*4/$D135)-INT($E$25*(4-1)/$D135))*$C135 -> 0 | I135: =(INT($E$25*5/$D135)-INT($E$25*(5-1)/$D135))*$C135 -> 0 | J135: =(INT($E$25*6/$D135)-INT($E$25*(6-1)/$D135))*$C135 -> 36 | K135: =(INT($E$25*7/$D135)-INT($E$25*(7-1)/$D135))*$C135 -> 0 | L135: =(INT($E$25*8/$D135)-INT($E$25*(8-1)/$D135))*$C135 -> 36 | M135: =(INT($E$25*9/$D135)-INT($E$25*(9-1)/$D135))*$C135 -> 0 | N135: =(INT($E$25*10/$D135)-INT($E$25*(10-1)/$D135))*$C135 -> 0
B136: Г. цилиндр стрелы | C136: 12 | D136: 13200 | E136: =(INT($E$25*1/$D136)-INT($E$25*(1-1)/$D136))*$C136 -> 0 | F136: =(INT($E$25*2/$D136)-INT($E$25*(2-1)/$D136))*$C136 -> 12 | G136: =(INT($E$25*3/$D136)-INT($E$25*(3-1)/$D136))*$C136 -> 0 | H136: =(INT($E$25*4/$D136)-INT($E$25*(4-1)/$D136))*$C136 -> 12 | I136: =(INT($E$25*5/$D136)-INT($E$25*(5-1)/$D136))*$C136 -> 0 | J136: =(INT($E$25*6/$D136)-INT($E$25*(6-1)/$D136))*$C136 -> 12 | K136: =(INT($E$25*7/$D136)-INT($E$25*(7-1)/$D136))*$C136 -> 0 | L136: =(INT($E$25*8/$D136)-INT($E$25*(8-1)/$D136))*$C136 -> 12 | M136: =(INT($E$25*9/$D136)-INT($E$25*(9-1)/$D136))*$C136 -> 0 | N136: =(INT($E$25*10/$D136)-INT($E$25*(10-1)/$D136))*$C136 -> 12
B137: Г. цилиндр стрелы (2) | C137: 12 | D137: 13200 | E137: =(INT($E$25*1/$D137)-INT($E$25*(1-1)/$D137))*$C137 -> 0 | F137: =(INT($E$25*2/$D137)-INT($E$25*(2-1)/$D137))*$C137 -> 12 | G137: =(INT($E$25*3/$D137)-INT($E$25*(3-1)/$D137))*$C137 -> 0 | H137: =(INT($E$25*4/$D137)-INT($E$25*(4-1)/$D137))*$C137 -> 12 | I137: =(INT($E$25*5/$D137)-INT($E$25*(5-1)/$D137))*$C137 -> 0 | J137: =(INT($E$25*6/$D137)-INT($E$25*(6-1)/$D137))*$C137 -> 12 | K137: =(INT($E$25*7/$D137)-INT($E$25*(7-1)/$D137))*$C137 -> 0 | L137: =(INT($E$25*8/$D137)-INT($E$25*(8-1)/$D137))*$C137 -> 12 | M137: =(INT($E$25*9/$D137)-INT($E$25*(9-1)/$D137))*$C137 -> 0 | N137: =(INT($E$25*10/$D137)-INT($E$25*(10-1)/$D137))*$C137 -> 12
B138: Г. цилиндр рукояти | C138: 8 | D138: 13200 | E138: =(INT($E$25*1/$D138)-INT($E$25*(1-1)/$D138))*$C138 -> 0 | F138: =(INT($E$25*2/$D138)-INT($E$25*(2-1)/$D138))*$C138 -> 8 | G138: =(INT($E$25*3/$D138)-INT($E$25*(3-1)/$D138))*$C138 -> 0 | H138: =(INT($E$25*4/$D138)-INT($E$25*(4-1)/$D138))*$C138 -> 8 | I138: =(INT($E$25*5/$D138)-INT($E$25*(5-1)/$D138))*$C138 -> 0 | J138: =(INT($E$25*6/$D138)-INT($E$25*(6-1)/$D138))*$C138 -> 8 | K138: =(INT($E$25*7/$D138)-INT($E$25*(7-1)/$D138))*$C138 -> 0 | L138: =(INT($E$25*8/$D138)-INT($E$25*(8-1)/$D138))*$C138 -> 8 | M138: =(INT($E$25*9/$D138)-INT($E$25*(9-1)/$D138))*$C138 -> 0 | N138: =(INT($E$25*10/$D138)-INT($E$25*(10-1)/$D138))*$C138 -> 8
...

Sheet Поставщик 2
B1: ШАБЛОН ДАННЫХ ПОСТАВЩИКА — ВАРИАНТ 2
B2: Полные модели ТО и Ремонтов ПО ГОДАМ (затраты и трудозатраты — раздельно для ТО / текущих / капитальных ремонтов). Зелёное — авто; сводка тянется в «Данные по годам».
B4: Экскаватор: | E4: ='Ввод данных'!E7 -> Komatsu PC2000-11R ИСТК
B5: Валюта затрат ТОиР: | D5: USD
B6: Показатель | C6: Ед. | E6: год 1 | F6: год 2 | G6: год 3 | H6: год 4 | I6: год 5 | J6: год 6 | K6: год 7 | L6: год 8 | M6: год 9 | N6: год 10
B7: СВОДКА ПО ГОДАМ (зелёное — авто из моделей ниже; тянется в расчёт)
B8: Простои на ТО | C8: ч/год | E8: =E37 -> 273.21 | F8: =F37 -> 273.21 | G8: =G37 -> 273.21 | H8: =H37 -> 273.21 | I8: =I37 -> 273.21 | J8: =J37 -> 273.21 | K8: =K37 -> 273.21 | L8: =L37 -> 273.21 | ... N8: =N37 -> 273.21
B9: Простои в текущих + капитальных ремонтах | C9: ч/год | E9: =E80 -> 160.72 | F9: =F80 -> 1298.94 | G9: =G80 -> 1057.5 | H9: =H80 -> 1603.44 | I9: =I80 -> 1613.61 | J9: =J80 -> 1169.1 | K9: =K80 -> 1399.63 | L9: =L80 -> 894.37 | ... N9: =N80 -> 1037.94
B10: Ежесменное ТО (20 мин/смену) | C10: ч/год | E10: =('Параметры'!C26-E8-E9)/'Параметры'!C33*20/60 -> 231.27972 | F10: =('Параметры'!C26-F8-F9)/'Параметры'!C33*20/60 -> 199.6625 | G10: =('Параметры'!C26-G8-G9)/'Параметры'!C33*20/60 -> 206.36917 | H10: =('Параметры'!C26-H8-H9)/'Параметры'!C33*20/60 -> 191.20417 | I10: =('Параметры'!C26-I8-I9)/'Параметры'!C33*20/60 -> 190.92167 | J10: =('Параметры'!C26-J8-J9)/'Параметры'!C33*20/60 -> 203.26917 | K10: =('Параметры'!C26-K8-K9)/'Параметры'!C33*20/60 -> 196.86556 | L10: =('Параметры'!C26-L8-L9)/'Параметры'!C33*20/60 -> 210.90056 | M10: =('Параметры'!C26-M8-M9)/'Параметры'!C33*20/60 -> 184.55583 | N10: =('Параметры'!C26-N8-N9)/'Параметры'!C33*20/60 -> 206.9125
B11: КТГ (авто) = (8760 − простои)/8760 | C11: коэф. | E11: =('Параметры'!C26-E8-E9-E10)/'Параметры'!C26 -> 0.92406282 | F11: =('Параметры'!C26-F8-F9-F10)/'Параметры'!C26 -> 0.7977383 | G11: =('Параметры'!C26-G8-G9-G10)/'Параметры'!C26 -> 0.82453434 | H11: =('Параметры'!C26-H8-H9-H10)/'Параметры'!C26 -> 0.76394359 | I11: =('Параметры'!C26-I8-I9-I10)/'Параметры'!C26 -> 0.76281488 | J11: =('Параметры'!C26-J8-J9-J10)/'Параметры'!C26 -> 0.8121485 | K11: =('Параметры'!C26-K8-K9-K10)/'Параметры'!C26 -> 0.78656329 | L11: =('Параметры'!C26-L8-L9-L10)/'Параметры'!C26 -> 0.84263921 | M11: =('Параметры'!C26-M8-M9-M10)/'Параметры'!C26 -> 0.73738061 | N11: =('Параметры'!C26-N8-N9-N10)/'Параметры'!C26 -> 0.82670519
B12: Затраты на ТО (ЗЧ, из каталога) | C12: тыс/год | E12: =E75 -> 107.51972 | F12: =F75 -> 107.51972 | G12: =G75 -> 107.51972 | H12: =H75 -> 107.51972 | I12: =I75 -> 107.51972 | J12: =J75 -> 107.51972 | K12: =K75 -> 107.51972 | L12: =L75 -> 107.51972 | ... N12: =N75 -> 107.51972
B13: Затраты на текущие ремонты (ЗЧ) | C13: тыс/год | E13: =E86*$E$81 -> 0 | F13: =F86*$E$81 -> 0 | G13: =G86*$E$81 -> 0 | H13: =H86*$E$81 -> 0 | I13: =I86*$E$81 -> 0 | J13: =J86*$E$81 -> 0 | K13: =K86*$E$81 -> 0 | L13: =L86*$E$81 -> 0 | ... N13: =N86*$E$81 -> 0
B14: Затраты на капитальные ремонты (ЗЧ, цех) | C14: тыс/год | E14: =E111*$E$81 -> 0 | F14: =F111*$E$81 -> 38.6841 | G14: =G111*$E$81 -> 525.8771 | H14: =H111*$E$81 -> 1317.0265 | I14: =I111*$E$81 -> 110 | J14: =J111*$E$81 -> 564.5612 | K14: =K111*$E$81 -> 38.6841 | L14: =L111*$E$81 -> 1278.3424 | ... N14: =N111*$E$81 -> 0
B15: Трудозатраты на ТО | C15: ч-час/год | E15: =E43 -> 546.42 | F15: =F43 -> 546.42 | G15: =G43 -> 546.42 | H15: =H43 -> 546.42 | I15: =I43 -> 546.42 | J15: =J43 -> 546.42 | K15: =K43 -> 546.42 | L15: =L43 -> 546.42 | ... N15: =N43 -> 546.42
B16: Трудозатраты на текущие ремонты | C16: ч-час/год | E16: =E91*$E$81 -> 0 | F16: =F91*$E$81 -> 0 | G16: =G91*$E$81 -> 0 | H16: =H91*$E$81 -> 0 | I16: =I91*$E$81 -> 0 | J16: =J91*$E$81 -> 0 | K16: =K91*$E$81 -> 0 | L16: =L91*$E$81 -> 0 | ... N16: =N91*$E$81 -> 0
B17: Трудозатраты на капитальные ремонты (цех) | C17: чел-час/год | E17: =E131*$E$81 -> 0 | F17: =F131*$E$81 -> 32 | G17: =G131*$E$81 -> 148 | H17: =H131*$E$81 -> 236 | I17: =I131*$E$81 -> 24 | J17: =J131*$E$81 -> 180 | K17: =K131*$E$81 -> 32 | L17: =L131*$E$81 -> 204 | ... N17: =N131*$E$81 -> 0
B18: Сервис ТО (авто) = трудозатраты ТО × ставка | C18: тыс/год | E18: =E15*$E$77/1000 -> 27.321 | F18: =F15*$E$77/1000 -> 27.321 | G18: =G15*$E$77/1000 -> 27.321 | H18: =H15*$E$77/1000 -> 27.321 | I18: =I15*$E$77/1000 -> 27.321 | J18: =J15*$E$77/1000 -> 27.321 | K18: =K15*$E$77/1000 -> 27.321 | L18: =L15*$E$77/1000 -> 27.321 | ... N18: =N15*$E$77/1000 -> 27.321
B19: Сервис текущих ремонтов (авто) | C19: тыс/год | E19: =E16*$E$77/1000 -> 0 | F19: =F16*$E$77/1000 -> 0 | G19: =G16*$E$77/1000 -> 0 | H19: =H16*$E$77/1000 -> 0 | I19: =I16*$E$77/1000 -> 0 | J19: =J16*$E$77/1000 -> 0 | K19: =K16*$E$77/1000 -> 0 | L19: =L16*$E$77/1000 -> 0 | ... N19: =N16*$E$77/1000 -> 0
B20: Сервис капитальных ремонтов (цех, авто) | C20: тыс/год | E20: =E17*$E$77/1000 -> 0 | F20: =F17*$E$77/1000 -> 1.6 | G20: =G17*$E$77/1000 -> 7.4 | H20: =H17*$E$77/1000 -> 11.8 | I20: =I17*$E$77/1000 -> 1.2 | J20: =J17*$E$77/1000 -> 9 | K20: =K17*$E$77/1000 -> 1.6 | L20: =L17*$E$77/1000 -> 10.2 | ... N20: =N17*$E$77/1000 -> 0
B21: ИТОГО ТОиР (авто) → «Данные по годам» | C21: тыс/год | E21: =E12+E13+E14+E18+E19+E20 -> 134.84072 | F21: =F12+F13+F14+F18+F19+F20 -> 175.12482 | G21: =G12+G13+G14+G18+G19+G20 -> 668.11782 | H21: =H12+H13+H14+H18+H19+H20 -> 1463.6672 | I21: =I12+I13+I14+I18+I19+I20 -> 246.04072 | J21: =J12+J13+J14+J18+J19+J20 -> 708.40192 | K21: =K12+K13+K14+K18+K19+K20 -> 175.12482 | L21: =L12+L13+L14+L18+L19+L20 -> 1423.3831 | ... N21: =N12+N13+N14+N18+N19+N20 -> 134.84072
B22: Удельный расход ДТ | C22: кг/час | E22: 85.81 | F22: 85.81 | G22: 85.81 | H22: 85.81 | I22: 85.81 | J22: 85.81 | K22: 85.81 | L22: 85.81 | M22: 85.81 | N22: 85.81
B23: Расходники на ковш | C23: руб/м³ | E23: 0.87 | F23: 0.87 | G23: 0.87 | H23: 0.87 | I23: 0.87 | J23: 0.87 | K23: 0.87 | L23: 0.87 | M23: 0.87 | N23: 0.87
B24: РАСЧЁТ ТО (по интервалам обслуживания), ПО ГОДАМ
B25: Наработка по годам | C25: м/час | E25: 7000 | F25: 7000 | G25: 7000 | H25: 7000 | I25: 7000 | J25: 7000 | K25: 7000 | L25: 7000 | M25: 7000 | N25: 7000
B26: Вид ТО | C26: интервал | D26: длит.простоя | E26: персонал
B27: ТО-1 | C27: 500 | D27: 10.2 | E27: 2
B28: ТО-2 | C28: 1000 | D28: 9.4 | E28: 2
B29: ТО-3 | C29: 2000 | D29: 12.4 | E29: 2
B30: ТО-4 | C30: 4000 | D30: 7.8 | E30: 2
B31: ТО-5 | C31: 5000 | D31: 5.4 | E31: 2
B32: ТО-1: простои, ч/год | C32: #,##0 | E32: =(E$25/$C27)*$D27 -> 142.8 | F32: =(F$25/$C27)*$D27 -> 142.8 | G32: =(G$25/$C27)*$D27 -> 142.8 | H32: =(H$25/$C27)*$D27 -> 142.8 | I32: =(I$25/$C27)*$D27 -> 142.8 | J32: =(J$25/$C27)*$D27 -> 142.8 | K32: =(K$25/$C27)*$D27 -> 142.8 | L32: =(L$25/$C27)*$D27 -> 142.8 | ... N32: =(N$25/$C27)*$D27 -> 142.8
B33: ТО-2: простои, ч/год | C33: #,##0 | E33: =(E$25/$C28)*$D28 -> 65.8 | F33: =(F$25/$C28)*$D28 -> 65.8 | G33: =(G$25/$C28)*$D28 -> 65.8 | H33: =(H$25/$C28)*$D28 -> 65.8 | I33: =(I$25/$C28)*$D28 -> 65.8 | J33: =(J$25/$C28)*$D28 -> 65.8 | K33: =(K$25/$C28)*$D28 -> 65.8 | L33: =(L$25/$C28)*$D28 -> 65.8 | ... N33: =(N$25/$C28)*$D28 -> 65.8
B34: ТО-3: простои, ч/год | C34: #,##0 | E34: =(E$25/$C29)*$D29 -> 43.4 | F34: =(F$25/$C29)*$D29 -> 43.4 | G34: =(G$25/$C29)*$D29 -> 43.4 | H34: =(H$25/$C29)*$D29 -> 43.4 | I34: =(I$25/$C29)*$D29 -> 43.4 | J34: =(J$25/$C29)*$D29 -> 43.4 | K34: =(K$25/$C29)*$D29 -> 43.4 | L34: =(L$25/$C29)*$D29 -> 43.4 | ... N34: =(N$25/$C29)*$D29 -> 43.4
B35: ТО-4: простои, ч/год | C35: #,##0 | E35: =(E$25/$C30)*$D30 -> 13.65 | F35: =(F$25/$C30)*$D30 -> 13.65 | G35: =(G$25/$C30)*$D30 -> 13.65 | H35: =(H$25/$C30)*$D30 -> 13.65 | I35: =(I$25/$C30)*$D30 -> 13.65 | J35: =(J$25/$C30)*$D30 -> 13.65 | K35: =(K$25/$C30)*$D30 -> 13.65 | L35: =(L$25/$C30)*$D30 -> 13.65 | ... N35: =(N$25/$C30)*$D30 -> 13.65
B36: ТО-5: простои, ч/год | C36: #,##0 | E36: =(E$25/$C31)*$D31 -> 7.56 | F36: =(F$25/$C31)*$D31 -> 7.56 | G36: =(G$25/$C31)*$D31 -> 7.56 | H36: =(H$25/$C31)*$D31 -> 7.56 | I36: =(I$25/$C31)*$D31 -> 7.56 | J36: =(J$25/$C31)*$D31 -> 7.56 | K36: =(K$25/$C31)*$D31 -> 7.56 | L36: =(L$25/$C31)*$D31 -> 7.56 | ... N36: =(N$25/$C31)*$D31 -> 7.56
B37: Итого простои ТО, ч/год | C37: ч/год | E37: =SUM(E32:E36) -> 273.21 | F37: =SUM(F32:F36) -> 273.21 | G37: =SUM(G32:G36) -> 273.21 | H37: =SUM(H32:H36) -> 273.21 | I37: =SUM(I32:I36) -> 273.21 | J37: =SUM(J32:J36) -> 273.21 | K37: =SUM(K32:K36) -> 273.21 | L37: =SUM(L32:L36) -> 273.21 | ... N37: =SUM(N32:N36) -> 273.21
B38: ТО-1: ч·часы/год | C38: #,##0 | E38: =E32*$E27 -> 285.6 | F38: =F32*$E27 -> 285.6 | G38: =G32*$E27 -> 285.6 | H38: =H32*$E27 -> 285.6 | I38: =I32*$E27 -> 285.6 | J38: =J32*$E27 -> 285.6 | K38: =K32*$E27 -> 285.6 | L38: =L32*$E27 -> 285.6 | ... N38: =N32*$E27 -> 285.6
B39: ТО-2: ч·часы/год | C39: #,##0 | E39: =E33*$E28 -> 131.6 | F39: =F33*$E28 -> 131.6 | G39: =G33*$E28 -> 131.6 | H39: =H33*$E28 -> 131.6 | I39: =I33*$E28 -> 131.6 | J39: =J33*$E28 -> 131.6 | K39: =K33*$E28 -> 131.6 | L39: =L33*$E28 -> 131.6 | ... N39: =N33*$E28 -> 131.6
B40: ТО-3: ч·часы/год | C40: #,##0 | E40: =E34*$E29 -> 86.8 | F40: =F34*$E29 -> 86.8 | G40: =G34*$E29 -> 86.8 | H40: =H34*$E29 -> 86.8 | I40: =I34*$E29 -> 86.8 | J40: =J34*$E29 -> 86.8 | K40: =K34*$E29 -> 86.8 | L40: =L34*$E29 -> 86.8 | ... N40: =N34*$E29 -> 86.8
B41: ТО-4: ч·часы/год | C41: #,##0 | E41: =E35*$E30 -> 27.3 | F41: =F35*$E30 -> 27.3 | G41: =G35*$E30 -> 27.3 | H41: =H35*$E30 -> 27.3 | I41: =I35*$E30 -> 27.3 | J41: =J35*$E30 -> 27.3 | K41: =K35*$E30 -> 27.3 | L41: =L35*$E30 -> 27.3 | ... N41: =N35*$E30 -> 27.3
B42: ТО-5: ч·часы/год | C42: #,##0 | E42: =E36*$E31 -> 15.12 | F42: =F36*$E31 -> 15.12 | G42: =G36*$E31 -> 15.12 | H42: =H36*$E31 -> 15.12 | I42: =I36*$E31 -> 15.12 | J42: =J36*$E31 -> 15.12 | K42: =K36*$E31 -> 15.12 | L42: =L36*$E31 -> 15.12 | ... N42: =N36*$E31 -> 15.12
B43: Итого ч·часы ТО, ч-час/год | C43: ч-час | E43: =SUM(E38:E42) -> 546.42 | F43: =SUM(F38:F42) -> 546.42 | G43: =SUM(G38:G42) -> 546.42 | H43: =SUM(H38:H42) -> 546.42 | I43: =SUM(I38:I42) -> 546.42 | J43: =SUM(J38:J42) -> 546.42 | K43: =SUM(K38:K42) -> 546.42 | L43: =SUM(L38:L42) -> 546.42 | ... N43: =SUM(N38:N42) -> 546.42
B45: КАТАЛОГ ЗАПЧАСТЕЙ ТО (заполняет подрядчик), ПО ГОДАМ
B46: Наименование | C46: цена за ед | D46: кол-во/ТО | E46: год 1 | F46: год 2 | G46: год 3 | H46: год 4 | I46: год 5 | J46: год 6 | K46: год 7 | L46: год 8 | M46: год 9 | N46: год 10 | P46: № ТО
B47: Масляный фильтр | C47: 114.83 | D47: 4 | E47: =(E$25/INDEX($C$27:$C$31,$P47))*D47*C47/1000 -> 6.43048 | F47: =(F$25/INDEX($C$27:$C$31,$P47))*D47*C47/1000 -> 6.43048 | G47: =(G$25/INDEX($C$27:$C$31,$P47))*D47*C47/1000 -> 6.43048 | H47: =(H$25/INDEX($C$27:$C$31,$P47))*D47*C47/1000 -> 6.43048 | I47: =(I$25/INDEX($C$27:$C$31,$P47))*D47*C47/1000 -> 6.43048 | J47: =(J$25/INDEX($C$27:$C$31,$P47))*D47*C47/1000 -> 6.43048 | K47: =(K$25/INDEX($C$27:$C$31,$P47))*D47*C47/1000 -> 6.43048 | L47: =(L$25/INDEX($C$27:$C$31,$P47))*D47*C47/1000 -> 6.43048 | M47: =(M$25/INDEX($C$27:$C$31,$P47))*D47*C47/1000 -> 6.43048 | N47: =(N$25/INDEX($C$27:$C$31,$P47))*D47*C47/1000 -> 6.43048 | P47: 1
B48: Топливный фильтр | C48: 141.33 | D48: 2 | E48: =(E$25/INDEX($C$27:$C$31,$P48))*D48*C48/1000 -> 3.95724 | F48: =(F$25/INDEX($C$27:$C$31,$P48))*D48*C48/1000 -> 3.95724 | G48: =(G$25/INDEX($C$27:$C$31,$P48))*D48*C48/1000 -> 3.95724 | H48: =(H$25/INDEX($C$27:$C$31,$P48))*D48*C48/1000 -> 3.95724 | I48: =(I$25/INDEX($C$27:$C$31,$P48))*D48*C48/1000 -> 3.95724 | J48: =(J$25/INDEX($C$27:$C$31,$P48))*D48*C48/1000 -> 3.95724 | K48: =(K$25/INDEX($C$27:$C$31,$P48))*D48*C48/1000 -> 3.95724 | L48: =(L$25/INDEX($C$27:$C$31,$P48))*D48*C48/1000 -> 3.95724 | M48: =(M$25/INDEX($C$27:$C$31,$P48))*D48*C48/1000 -> 3.95724 | N48: =(N$25/INDEX($C$27:$C$31,$P48))*D48*C48/1000 -> 3.95724 | P48: 1
B49: Масло ДВС | C49: 6.87 | D49: 130 | E49: =(E$25/INDEX($C$27:$C$31,$P49))*D49*C49/1000 -> 12.5034 | F49: =(F$25/INDEX($C$27:$C$31,$P49))*D49*C49/1000 -> 12.5034 | G49: =(G$25/INDEX($C$27:$C$31,$P49))*D49*C49/1000 -> 12.5034 | H49: =(H$25/INDEX($C$27:$C$31,$P49))*D49*C49/1000 -> 12.5034 | I49: =(I$25/INDEX($C$27:$C$31,$P49))*D49*C49/1000 -> 12.5034 | J49: =(J$25/INDEX($C$27:$C$31,$P49))*D49*C49/1000 -> 12.5034 | K49: =(K$25/INDEX($C$27:$C$31,$P49))*D49*C49/1000 -> 12.5034 | L49: =(L$25/INDEX($C$27:$C$31,$P49))*D49*C49/1000 -> 12.5034 | M49: =(M$25/INDEX($C$27:$C$31,$P49))*D49*C49/1000 -> 12.5034 | N49: =(N$25/INDEX($C$27:$C$31,$P49))*D49*C49/1000 -> 12.5034 | P49: 1
B50: Фильтр управляющего контура | C50: 126 | D50: 1 | E50: =(E$25/INDEX($C$27:$C$31,$P50))*D50*C50/1000 -> 1.764 | F50: =(F$25/INDEX($C$27:$C$31,$P50))*D50*C50/1000 -> 1.764 | G50: =(G$25/INDEX($C$27:$C$31,$P50))*D50*C50/1000 -> 1.764 | H50: =(H$25/INDEX($C$27:$C$31,$P50))*D50*C50/1000 -> 1.764 | I50: =(I$25/INDEX($C$27:$C$31,$P50))*D50*C50/1000 -> 1.764 | J50: =(J$25/INDEX($C$27:$C$31,$P50))*D50*C50/1000 -> 1.764 | K50: =(K$25/INDEX($C$27:$C$31,$P50))*D50*C50/1000 -> 1.764 | L50: =(L$25/INDEX($C$27:$C$31,$P50))*D50*C50/1000 -> 1.764 | M50: =(M$25/INDEX($C$27:$C$31,$P50))*D50*C50/1000 -> 1.764 | N50: =(N$25/INDEX($C$27:$C$31,$P50))*D50*C50/1000 -> 1.764 | P50: 1
B51: Сливной фильтр | C51: 30.67 | D51: 2 | E51: =(E$25/INDEX($C$27:$C$31,$P51))*D51*C51/1000 -> 0.85876 | F51: =(F$25/INDEX($C$27:$C$31,$P51))*D51*C51/1000 -> 0.85876 | G51: =(G$25/INDEX($C$27:$C$31,$P51))*D51*C51/1000 -> 0.85876 | H51: =(H$25/INDEX($C$27:$C$31,$P51))*D51*C51/1000 -> 0.85876 | I51: =(I$25/INDEX($C$27:$C$31,$P51))*D51*C51/1000 -> 0.85876 | J51: =(J$25/INDEX($C$27:$C$31,$P51))*D51*C51/1000 -> 0.85876 | K51: =(K$25/INDEX($C$27:$C$31,$P51))*D51*C51/1000 -> 0.85876 | L51: =(L$25/INDEX($C$27:$C$31,$P51))*D51*C51/1000 -> 0.85876 | M51: =(M$25/INDEX($C$27:$C$31,$P51))*D51*C51/1000 -> 0.85876 | N51: =(N$25/INDEX($C$27:$C$31,$P51))*D51*C51/1000 -> 0.85876 | P51: 1
B52: Сливной фильтр насоса | C52: 201 | D52: 3 | E52: =(E$25/INDEX($C$27:$C$31,$P52))*D52*C52/1000 -> 8.442 | F52: =(F$25/INDEX($C$27:$C$31,$P52))*D52*C52/1000 -> 8.442 | G52: =(G$25/INDEX($C$27:$C$31,$P52))*D52*C52/1000 -> 8.442 | H52: =(H$25/INDEX($C$27:$C$31,$P52))*D52*C52/1000 -> 8.442 | I52: =(I$25/INDEX($C$27:$C$31,$P52))*D52*C52/1000 -> 8.442 | J52: =(J$25/INDEX($C$27:$C$31,$P52))*D52*C52/1000 -> 8.442 | K52: =(K$25/INDEX($C$27:$C$31,$P52))*D52*C52/1000 -> 8.442 | L52: =(L$25/INDEX($C$27:$C$31,$P52))*D52*C52/1000 -> 8.442 | M52: =(M$25/INDEX($C$27:$C$31,$P52))*D52*C52/1000 -> 8.442 | N52: =(N$25/INDEX($C$27:$C$31,$P52))*D52*C52/1000 -> 8.442 | P52: 1
B53: Смазка | C53: 12.24 | D53: 200 | E53: =(E$25/INDEX($C$27:$C$31,$P53))*D53*C53/1000 -> 34.272 | F53: =(F$25/INDEX($C$27:$C$31,$P53))*D53*C53/1000 -> 34.272 | G53: =(G$25/INDEX($C$27:$C$31,$P53))*D53*C53/1000 -> 34.272 | H53: =(H$25/INDEX($C$27:$C$31,$P53))*D53*C53/1000 -> 34.272 | I53: =(I$25/INDEX($C$27:$C$31,$P53))*D53*C53/1000 -> 34.272 | J53: =(J$25/INDEX($C$27:$C$31,$P53))*D53*C53/1000 -> 34.272 | K53: =(K$25/INDEX($C$27:$C$31,$P53))*D53*C53/1000 -> 34.272 | L53: =(L$25/INDEX($C$27:$C$31,$P53))*D53*C53/1000 -> 34.272 | M53: =(M$25/INDEX($C$27:$C$31,$P53))*D53*C53/1000 -> 34.272 | N53: =(N$25/INDEX($C$27:$C$31,$P53))*D53*C53/1000 -> 34.272 | P53: 1
B54: Топливный фильтр (ТО-2) | C54: 80.17 | D54: 2 | E54: =(E$25/INDEX($C$27:$C$31,$P54))*D54*C54/1000 -> 1.12238 | F54: =(F$25/INDEX($C$27:$C$31,$P54))*D54*C54/1000 -> 1.12238 | G54: =(G$25/INDEX($C$27:$C$31,$P54))*D54*C54/1000 -> 1.12238 | H54: =(H$25/INDEX($C$27:$C$31,$P54))*D54*C54/1000 -> 1.12238 | I54: =(I$25/INDEX($C$27:$C$31,$P54))*D54*C54/1000 -> 1.12238 | J54: =(J$25/INDEX($C$27:$C$31,$P54))*D54*C54/1000 -> 1.12238 | K54: =(K$25/INDEX($C$27:$C$31,$P54))*D54*C54/1000 -> 1.12238 | L54: =(L$25/INDEX($C$27:$C$31,$P54))*D54*C54/1000 -> 1.12238 | M54: =(M$25/INDEX($C$27:$C$31,$P54))*D54*C54/1000 -> 1.12238 | N54: =(N$25/INDEX($C$27:$C$31,$P54))*D54*C54/1000 -> 1.12238 | P54: 2
B55: Фильтр сапуна топл.бака | C55: 19.17 | D55: 1 | E55: =(E$25/INDEX($C$27:$C$31,$P55))*D55*C55/1000 -> 0.13419 | F55: =(F$25/INDEX($C$27:$C$31,$P55))*D55*C55/1000 -> 0.13419 | G55: =(G$25/INDEX($C$27:$C$31,$P55))*D55*C55/1000 -> 0.13419 | H55: =(H$25/INDEX($C$27:$C$31,$P55))*D55*C55/1000 -> 0.13419 | I55: =(I$25/INDEX($C$27:$C$31,$P55))*D55*C55/1000 -> 0.13419 | J55: =(J$25/INDEX($C$27:$C$31,$P55))*D55*C55/1000 -> 0.13419 | K55: =(K$25/INDEX($C$27:$C$31,$P55))*D55*C55/1000 -> 0.13419 | L55: =(L$25/INDEX($C$27:$C$31,$P55))*D55*C55/1000 -> 0.13419 | M55: =(M$25/INDEX($C$27:$C$31,$P55))*D55*C55/1000 -> 0.13419 | N55: =(N$25/INDEX($C$27:$C$31,$P55))*D55*C55/1000 -> 0.13419 | P55: 2
B56: Фильтр сапуна гидробака | C56: 19.17 | D56: 2 | E56: =(E$25/INDEX($C$27:$C$31,$P56))*D56*C56/1000 -> 0.26838 | F56: =(F$25/INDEX($C$27:$C$31,$P56))*D56*C56/1000 -> 0.26838 | G56: =(G$25/INDEX($C$27:$C$31,$P56))*D56*C56/1000 -> 0.26838 | H56: =(H$25/INDEX($C$27:$C$31,$P56))*D56*C56/1000 -> 0.26838 | I56: =(I$25/INDEX($C$27:$C$31,$P56))*D56*C56/1000 -> 0.26838 | J56: =(J$25/INDEX($C$27:$C$31,$P56))*D56*C56/1000 -> 0.26838 | K56: =(K$25/INDEX($C$27:$C$31,$P56))*D56*C56/1000 -> 0.26838 | L56: =(L$25/INDEX($C$27:$C$31,$P56))*D56*C56/1000 -> 0.26838 | M56: =(M$25/INDEX($C$27:$C$31,$P56))*D56*C56/1000 -> 0.26838 | N56: =(N$25/INDEX($C$27:$C$31,$P56))*D56*C56/1000 -> 0.26838 | P56: 2
B57: Гидравлический фильтр | C57: 344.33 | D57: 3 | E57: =(E$25/INDEX($C$27:$C$31,$P57))*D57*C57/1000 -> 7.23093 | F57: =(F$25/INDEX($C$27:$C$31,$P57))*D57*C57/1000 -> 7.23093 | G57: =(G$25/INDEX($C$27:$C$31,$P57))*D57*C57/1000 -> 7.23093 | H57: =(H$25/INDEX($C$27:$C$31,$P57))*D57*C57/1000 -> 7.23093 | I57: =(I$25/INDEX($C$27:$C$31,$P57))*D57*C57/1000 -> 7.23093 | J57: =(J$25/INDEX($C$27:$C$31,$P57))*D57*C57/1000 -> 7.23093 | K57: =(K$25/INDEX($C$27:$C$31,$P57))*D57*C57/1000 -> 7.23093 | L57: =(L$25/INDEX($C$27:$C$31,$P57))*D57*C57/1000 -> 7.23093 | M57: =(M$25/INDEX($C$27:$C$31,$P57))*D57*C57/1000 -> 7.23093 | N57: =(N$25/INDEX($C$27:$C$31,$P57))*D57*C57/1000 -> 7.23093 | P57: 2
B58: О-кольцо | C58: 24.5 | D58: 3 | E58: =(E$25/INDEX($C$27:$C$31,$P58))*D58*C58/1000 -> 0.5145 | F58: =(F$25/INDEX($C$27:$C$31,$P58))*D58*C58/1000 -> 0.5145 | G58: =(G$25/INDEX($C$27:$C$31,$P58))*D58*C58/1000 -> 0.5145 | H58: =(H$25/INDEX($C$27:$C$31,$P58))*D58*C58/1000 -> 0.5145 | I58: =(I$25/INDEX($C$27:$C$31,$P58))*D58*C58/1000 -> 0.5145 | J58: =(J$25/INDEX($C$27:$C$31,$P58))*D58*C58/1000 -> 0.5145 | K58: =(K$25/INDEX($C$27:$C$31,$P58))*D58*C58/1000 -> 0.5145 | L58: =(L$25/INDEX($C$27:$C$31,$P58))*D58*C58/1000 -> 0.5145 | M58: =(M$25/INDEX($C$27:$C$31,$P58))*D58*C58/1000 -> 0.5145 | N58: =(N$25/INDEX($C$27:$C$31,$P58))*D58*C58/1000 -> 0.5145 | P58: 2
... B73: Гидравлическое масло | C73: 6.43 | D73: 1300 | E73: =(E$25/INDEX($C$27:$C$31,$P73))*D73*C73/1000 -> 11.7026 | F73: =(F$25/INDEX($C$27:$C$31,$P73))*D73*C73/1000 -> 11.7026 | G73: =(G$25/INDEX($C$27:$C$31,$P73))*D73*C73/1000 -> 11.7026 | H73: =(H$25/INDEX($C$27:$C$31,$P73))*D73*C73/1000 -> 11.7026 | I73: =(I$25/INDEX($C$27:$C$31,$P73))*D73*C73/1000 -> 11.7026 | J73: =(J$25/INDEX($C$27:$C$31,$P73))*D73*C73/1000 -> 11.7026 | K73: =(K$25/INDEX($C$27:$C$31,$P73))*D73*C73/1000 -> 11.7026 | L73: =(L$25/INDEX($C$27:$C$31,$P73))*D73*C73/1000 -> 11.7026 | M73: =(M$25/INDEX($C$27:$C$31,$P73))*D73*C73/1000 -> 11.7026 | N73: =(N$25/INDEX($C$27:$C$31,$P73))*D73*C73/1000 -> 11.7026 | P73: 5
B74: Корректировка (поглощения/прочее) | E74: 0 | F74: 0 | G74: 0 | H74: 0 | I74: 0 | J74: 0 | K74: 0 | L74: 0 | M74: 0 | N74: 0
B75: ИТОГО затраты на запчасти ТО, тыс/год | E75: =SUM(E47:E74) -> 107.51972 | F75: =SUM(F47:F74) -> 107.51972 | G75: =SUM(G47:G74) -> 107.51972 | H75: =SUM(H47:H74) -> 107.51972 | I75: =SUM(I47:I74) -> 107.51972 | J75: =SUM(J47:J74) -> 107.51972 | K75: =SUM(K47:K74) -> 107.51972 | L75: =SUM(L47:L74) -> 107.51972 | ... N75: =SUM(N47:N74) -> 107.51972
B77: Ставка сервиса | C77: вал/ч·час | E77: 50
B79: РАСЧЁТ РЕМОНТОВ (из списков по периодичности замены узлов)
B80: Простои в текущих + капитальных ремонтах | C80: ч/год | E80: 160.72 | F80: 1298.94 | G80: 1057.5 | H80: 1603.44 | I80: 1613.61 | J80: 1169.1 | K80: 1399.63 | L80: 894.37 | M80: 1842.78 | N80: 1037.94
B81: Коэффициент поглощения (0–1; 1=как у поставщика) | C81: коэф. | E81: 1
B83: ТЕКУЩИЕ РЕМОНТЫ — ЗАТРАТЫ НА ЗЧ (по ресурсу замены)
B84: Наименование | C84: стоим.замены,тыс | D84: ресурс, м/ч | E84: год 1 | F84: год 2 | G84: год 3 | H84: год 4 | I84: год 5 | J84: год 6 | K84: год 7 | L84: год 8 | M84: год 9 | N84: год 10
B86: ИТОГО | E86: =SUM(E85:E85) -> 0 | F86: =SUM(F85:F85) -> 0 | G86: =SUM(G85:G85) -> 0 | H86: =SUM(H85:H85) -> 0 | I86: =SUM(I85:I85) -> 0 | J86: =SUM(J85:J85) -> 0 | K86: =SUM(K85:K85) -> 0 | L86: =SUM(L85:L85) -> 0 | ... N86: =SUM(N85:N85) -> 0
B88: ТЕКУЩИЕ РЕМОНТЫ — ТРУДОЗАТРАТЫ (по ресурсу замены)
B89: Наименование | C89: нормо-час/событие | D89: ресурс, м/ч | E89: год 1 | F89: год 2 | G89: год 3 | H89: год 4 | I89: год 5 | J89: год 6 | K89: год 7 | L89: год 8 | M89: год 9 | N89: год 10
B91: ИТОГО | E91: =SUM(E90:E90) -> 0 | F91: =SUM(F90:F90) -> 0 | G91: =SUM(G90:G90) -> 0 | H91: =SUM(H90:H90) -> 0 | I91: =SUM(I90:I90) -> 0 | J91: =SUM(J90:J90) -> 0 | K91: =SUM(K90:K90) -> 0 | L91: =SUM(L90:L90) -> 0 | ... N91: =SUM(N90:N90) -> 0
B93: КАПИТАЛЬНЫЕ РЕМОНТЫ (ЦЕХ) — ЗАТРАТЫ НА ЗЧ (по ресурсу до замены узла)
B94: Наименование | C94: стоим.замены,тыс | D94: ресурс, м/ч | E94: год 1 | F94: год 2 | G94: год 3 | H94: год 4 | I94: год 5 | J94: год 6 | K94: год 7 | L94: год 8 | M94: год 9 | N94: год 10
B95: Ходовые моторы | C95: 89.9 | D95: 25000 | E95: =(INT($E$25*1/$D95)-INT($E$25*(1-1)/$D95))*$C95 -> 0 | F95: =(INT($E$25*2/$D95)-INT($E$25*(2-1)/$D95))*$C95 -> 0 | G95: =(INT($E$25*3/$D95)-INT($E$25*(3-1)/$D95))*$C95 -> 0 | H95: =(INT($E$25*4/$D95)-INT($E$25*(4-1)/$D95))*$C95 -> 89.9 | I95: =(INT($E$25*5/$D95)-INT($E$25*(5-1)/$D95))*$C95 -> 0 | J95: =(INT($E$25*6/$D95)-INT($E$25*(6-1)/$D95))*$C95 -> 0 | K95: =(INT($E$25*7/$D95)-INT($E$25*(7-1)/$D95))*$C95 -> 0 | L95: =(INT($E$25*8/$D95)-INT($E$25*(8-1)/$D95))*$C95 -> 89.9 | M95: =(INT($E$25*9/$D95)-INT($E$25*(9-1)/$D95))*$C95 -> 0 | N95: =(INT($E$25*10/$D95)-INT($E$25*(10-1)/$D95))*$C95 -> 0
B96: Редуктор хода | C96: 332.3 | D96: 25000 | E96: =(INT($E$25*1/$D96)-INT($E$25*(1-1)/$D96))*$C96 -> 0 | F96: =(INT($E$25*2/$D96)-INT($E$25*(2-1)/$D96))*$C96 -> 0 | G96: =(INT($E$25*3/$D96)-INT($E$25*(3-1)/$D96))*$C96 -> 0 | H96: =(INT($E$25*4/$D96)-INT($E$25*(4-1)/$D96))*$C96 -> 332.3 | I96: =(INT($E$25*5/$D96)-INT($E$25*(5-1)/$D96))*$C96 -> 0 | J96: =(INT($E$25*6/$D96)-INT($E$25*(6-1)/$D96))*$C96 -> 0 | K96: =(INT($E$25*7/$D96)-INT($E$25*(7-1)/$D96))*$C96 -> 0 | L96: =(INT($E$25*8/$D96)-INT($E$25*(8-1)/$D96))*$C96 -> 332.3 | M96: =(INT($E$25*9/$D96)-INT($E$25*(9-1)/$D96))*$C96 -> 0 | N96: =(INT($E$25*10/$D96)-INT($E$25*(10-1)/$D96))*$C96 -> 0
B97: Гусеничная лента | C97: 184 | D97: 20000 | E97: =(INT($E$25*1/$D97)-INT($E$25*(1-1)/$D97))*$C97 -> 0 | F97: =(INT($E$25*2/$D97)-INT($E$25*(2-1)/$D97))*$C97 -> 0 | G97: =(INT($E$25*3/$D97)-INT($E$25*(3-1)/$D97))*$C97 -> 184 | H97: =(INT($E$25*4/$D97)-INT($E$25*(4-1)/$D97))*$C97 -> 0 | I97: =(INT($E$25*5/$D97)-INT($E$25*(5-1)/$D97))*$C97 -> 0 | J97: =(INT($E$25*6/$D97)-INT($E$25*(6-1)/$D97))*$C97 -> 184 | K97: =(INT($E$25*7/$D97)-INT($E$25*(7-1)/$D97))*$C97 -> 0 | L97: =(INT($E$25*8/$D97)-INT($E$25*(8-1)/$D97))*$C97 -> 0 | M97: =(INT($E$25*9/$D97)-INT($E$25*(9-1)/$D97))*$C97 -> 184 | N97: =(INT($E$25*10/$D97)-INT($E$25*(10-1)/$D97))*$C97 -> 0
B98: Опорные ролики (комп) | C98: 119.4108 | D98: 20000 | E98: =(INT($E$25*1/$D98)-INT($E$25*(1-1)/$D98))*$C98 -> 0 | F98: =(INT($E$25*2/$D98)-INT($E$25*(2-1)/$D98))*$C98 -> 0 | G98: =(INT($E$25*3/$D98)-INT($E$25*(3-1)/$D98))*$C98 -> 119.4108 | H98: =(INT($E$25*4/$D98)-INT($E$25*(4-1)/$D98))*$C98 -> 0 | I98: =(INT($E$25*5/$D98)-INT($E$25*(5-1)/$D98))*$C98 -> 0 | J98: =(INT($E$25*6/$D98)-INT($E$25*(6-1)/$D98))*$C98 -> 119.4108 | K98: =(INT($E$25*7/$D98)-INT($E$25*(7-1)/$D98))*$C98 -> 0 | L98: =(INT($E$25*8/$D98)-INT($E$25*(8-1)/$D98))*$C98 -> 0 | M98: =(INT($E$25*9/$D98)-INT($E$25*(9-1)/$D98))*$C98 -> 119.4108 | N98: =(INT($E$25*10/$D98)-INT($E$25*(10-1)/$D98))*$C98 -> 0
B99: Поддерживающие катки (комп) | C99: 31.3815 | D99: 20000 | E99: =(INT($E$25*1/$D99)-INT($E$25*(1-1)/$D99))*$C99 -> 0 | F99: =(INT($E$25*2/$D99)-INT($E$25*(2-1)/$D99))*$C99 -> 0 | G99: =(INT($E$25*3/$D99)-INT($E$25*(3-1)/$D99))*$C99 -> 31.3815 | H99: =(INT($E$25*4/$D99)-INT($E$25*(4-1)/$D99))*$C99 -> 0 | I99: =(INT($E$25*5/$D99)-INT($E$25*(5-1)/$D99))*$C99 -> 0 | J99: =(INT($E$25*6/$D99)-INT($E$25*(6-1)/$D99))*$C99 -> 31.3815 | K99: =(INT($E$25*7/$D99)-INT($E$25*(7-1)/$D99))*$C99 -> 0 | L99: =(INT($E$25*8/$D99)-INT($E$25*(8-1)/$D99))*$C99 -> 0 | M99: =(INT($E$25*9/$D99)-INT($E$25*(9-1)/$D99))*$C99 -> 31.3815 | N99: =(INT($E$25*10/$D99)-INT($E$25*(10-1)/$D99))*$C99 -> 0
B100: Механизм натяжения гусениц | C100: 110 | D100: 30000 | E100: =(INT($E$25*1/$D100)-INT($E$25*(1-1)/$D100))*$C100 -> 0 | F100: =(INT($E$25*2/$D100)-INT($E$25*(2-1)/$D100))*$C100 -> 0 | G100: =(INT($E$25*3/$D100)-INT($E$25*(3-1)/$D100))*$C100 -> 0 | H100: =(INT($E$25*4/$D100)-INT($E$25*(4-1)/$D100))*$C100 -> 0 | I100: =(INT($E$25*5/$D100)-INT($E$25*(5-1)/$D100))*$C100 -> 110 | J100: =(INT($E$25*6/$D100)-INT($E$25*(6-1)/$D100))*$C100 -> 0 | K100: =(INT($E$25*7/$D100)-INT($E$25*(7-1)/$D100))*$C100 -> 0 | L100: =(INT($E$25*8/$D100)-INT($E$25*(8-1)/$D100))*$C100 -> 0 | M100: =(INT($E$25*9/$D100)-INT($E$25*(9-1)/$D100))*$C100 -> 110 | N100: =(INT($E$25*10/$D100)-INT($E$25*(10-1)/$D100))*$C100 -> 0
B101: Натяжное колесо | C101: 80 | D101: 20000 | E101: =(INT($E$25*1/$D101)-INT($E$25*(1-1)/$D101))*$C101 -> 0 | F101: =(INT($E$25*2/$D101)-INT($E$25*(2-1)/$D101))*$C101 -> 0 | G101: =(INT($E$25*3/$D101)-INT($E$25*(3-1)/$D101))*$C101 -> 80 | H101: =(INT($E$25*4/$D101)-INT($E$25*(4-1)/$D101))*$C101 -> 0 | I101: =(INT($E$25*5/$D101)-INT($E$25*(5-1)/$D101))*$C101 -> 0 | J101: =(INT($E$25*6/$D101)-INT($E$25*(6-1)/$D101))*$C101 -> 80 | K101: =(INT($E$25*7/$D101)-INT($E$25*(7-1)/$D101))*$C101 -> 0 | L101: =(INT($E$25*8/$D101)-INT($E$25*(8-1)/$D101))*$C101 -> 0 | M101: =(INT($E$25*9/$D101)-INT($E$25*(9-1)/$D101))*$C101 -> 80 | N101: =(INT($E$25*10/$D101)-INT($E$25*(10-1)/$D101))*$C101 -> 0
B102: Гидромотор поворота платформы | C102: 56.4863 | D102: 25000 | E102: =(INT($E$25*1/$D102)-INT($E$25*(1-1)/$D102))*$C102 -> 0 | F102: =(INT($E$25*2/$D102)-INT($E$25*(2-1)/$D102))*$C102 -> 0 | G102: =(INT($E$25*3/$D102)-INT($E$25*(3-1)/$D102))*$C102 -> 0 | H102: =(INT($E$25*4/$D102)-INT($E$25*(4-1)/$D102))*$C102 -> 56.4863 | I102: =(INT($E$25*5/$D102)-INT($E$25*(5-1)/$D102))*$C102 -> 0 | J102: =(INT($E$25*6/$D102)-INT($E$25*(6-1)/$D102))*$C102 -> 0 | K102: =(INT($E$25*7/$D102)-INT($E$25*(7-1)/$D102))*$C102 -> 0 | L102: =(INT($E$25*8/$D102)-INT($E$25*(8-1)/$D102))*$C102 -> 56.4863 | M102: =(INT($E$25*9/$D102)-INT($E$25*(9-1)/$D102))*$C102 -> 0 | N102: =(INT($E$25*10/$D102)-INT($E$25*(10-1)/$D102))*$C102 -> 0
B103: Редуктор поворота платформы | C103: 84.2795 | D103: 20000 | E103: =(INT($E$25*1/$D103)-INT($E$25*(1-1)/$D103))*$C103 -> 0 | F103: =(INT($E$25*2/$D103)-INT($E$25*(2-1)/$D103))*$C103 -> 0 | G103: =(INT($E$25*3/$D103)-INT($E$25*(3-1)/$D103))*$C103 -> 84.2795 | H103: =(INT($E$25*4/$D103)-INT($E$25*(4-1)/$D103))*$C103 -> 0 | I103: =(INT($E$25*5/$D103)-INT($E$25*(5-1)/$D103))*$C103 -> 0 | J103: =(INT($E$25*6/$D103)-INT($E$25*(6-1)/$D103))*$C103 -> 84.2795 | K103: =(INT($E$25*7/$D103)-INT($E$25*(7-1)/$D103))*$C103 -> 0 | L103: =(INT($E$25*8/$D103)-INT($E$25*(8-1)/$D103))*$C103 -> 0 | M103: =(INT($E$25*9/$D103)-INT($E$25*(9-1)/$D103))*$C103 -> 84.2795 | N103: =(INT($E$25*10/$D103)-INT($E$25*(10-1)/$D103))*$C103 -> 0
B104: ДВС | C104: 320 | D104: 25000 | E104: =(INT($E$25*1/$D104)-INT($E$25*(1-1)/$D104))*$C104 -> 0 | F104: =(INT($E$25*2/$D104)-INT($E$25*(2-1)/$D104))*$C104 -> 0 | G104: =(INT($E$25*3/$D104)-INT($E$25*(3-1)/$D104))*$C104 -> 0 | H104: =(INT($E$25*4/$D104)-INT($E$25*(4-1)/$D104))*$C104 -> 320 | I104: =(INT($E$25*5/$D104)-INT($E$25*(5-1)/$D104))*$C104 -> 0 | J104: =(INT($E$25*6/$D104)-INT($E$25*(6-1)/$D104))*$C104 -> 0 | K104: =(INT($E$25*7/$D104)-INT($E$25*(7-1)/$D104))*$C104 -> 0 | L104: =(INT($E$25*8/$D104)-INT($E$25*(8-1)/$D104))*$C104 -> 320 | M104: =(INT($E$25*9/$D104)-INT($E$25*(9-1)/$D104))*$C104 -> 0 | N104: =(INT($E$25*10/$D104)-INT($E$25*(10-1)/$D104))*$C104 -> 0
B105: Главные насосы, 2 шт. | C105: 317.5399 | D105: 25000 | E105: =(INT($E$25*1/$D105)-INT($E$25*(1-1)/$D105))*$C105 -> 0 | F105: =(INT($E$25*2/$D105)-INT($E$25*(2-1)/$D105))*$C105 -> 0 | G105: =(INT($E$25*3/$D105)-INT($E$25*(3-1)/$D105))*$C105 -> 0 | H105: =(INT($E$25*4/$D105)-INT($E$25*(4-1)/$D105))*$C105 -> 317.5399 | I105: =(INT($E$25*5/$D105)-INT($E$25*(5-1)/$D105))*$C105 -> 0 | J105: =(INT($E$25*6/$D105)-INT($E$25*(6-1)/$D105))*$C105 -> 0 | K105: =(INT($E$25*7/$D105)-INT($E$25*(7-1)/$D105))*$C105 -> 0 | L105: =(INT($E$25*8/$D105)-INT($E$25*(8-1)/$D105))*$C105 -> 317.5399 | M105: =(INT($E$25*9/$D105)-INT($E$25*(9-1)/$D105))*$C105 -> 0 | N105: =(INT($E$25*10/$D105)-INT($E$25*(10-1)/$D105))*$C105 -> 0
B106: Главный распределительный клапан | C106: 162.1162 | D106: 25000 | E106: =(INT($E$25*1/$D106)-INT($E$25*(1-1)/$D106))*$C106 -> 0 | F106: =(INT($E$25*2/$D106)-INT($E$25*(2-1)/$D106))*$C106 -> 0 | G106: =(INT($E$25*3/$D106)-INT($E$25*(3-1)/$D106))*$C106 -> 0 | H106: =(INT($E$25*4/$D106)-INT($E$25*(4-1)/$D106))*$C106 -> 162.1162 | I106: =(INT($E$25*5/$D106)-INT($E$25*(5-1)/$D106))*$C106 -> 0 | J106: =(INT($E$25*6/$D106)-INT($E$25*(6-1)/$D106))*$C106 -> 0 | K106: =(INT($E$25*7/$D106)-INT($E$25*(7-1)/$D106))*$C106 -> 0 | L106: =(INT($E$25*8/$D106)-INT($E$25*(8-1)/$D106))*$C106 -> 162.1162 | M106: =(INT($E$25*9/$D106)-INT($E$25*(9-1)/$D106))*$C106 -> 0 | N106: =(INT($E$25*10/$D106)-INT($E$25*(10-1)/$D106))*$C106 -> 0
... B110: РВД рабочего оборудования | C110: 26.8053 | D110: 20000 | E110: =(INT($E$25*1/$D110)-INT($E$25*(1-1)/$D110))*$C110 -> 0 | F110: =(INT($E$25*2/$D110)-INT($E$25*(2-1)/$D110))*$C110 -> 0 | G110: =(INT($E$25*3/$D110)-INT($E$25*(3-1)/$D110))*$C110 -> 26.8053 | H110: =(INT($E$25*4/$D110)-INT($E$25*(4-1)/$D110))*$C110 -> 0 | I110: =(INT($E$25*5/$D110)-INT($E$25*(5-1)/$D110))*$C110 -> 0 | J110: =(INT($E$25*6/$D110)-INT($E$25*(6-1)/$D110))*$C110 -> 26.8053 | K110: =(INT($E$25*7/$D110)-INT($E$25*(7-1)/$D110))*$C110 -> 0 | L110: =(INT($E$25*8/$D110)-INT($E$25*(8-1)/$D110))*$C110 -> 0 | M110: =(INT($E$25*9/$D110)-INT($E$25*(9-1)/$D110))*$C110 -> 26.8053 | N110: =(INT($E$25*10/$D110)-INT($E$25*(10-1)/$D110))*$C110 -> 0
B111: ИТОГО | E111: =SUM(E95:E110) -> 0 | F111: =SUM(F95:F110) -> 38.6841 | G111: =SUM(G95:G110) -> 525.8771 | H111: =SUM(H95:H110) -> 1317.0265 | I111: =SUM(I95:I110) -> 110 | J111: =SUM(J95:J110) -> 564.5612 | K111: =SUM(K95:K110) -> 38.6841 | L111: =SUM(L95:L110) -> 1278.3424 | ... N111: =SUM(N95:N110) -> 0
B113: КАПИТАЛЬНЫЕ РЕМОНТЫ (ЦЕХ) — ТРУДОЗАТРАТЫ (по ресурсу до замены узла)
B114: Наименование | C114: нормо-час/событие | D114: ресурс, м/ч | E114: год 1 | F114: год 2 | G114: год 3 | H114: год 4 | I114: год 5 | J114: год 6 | K114: год 7 | L114: год 8 | M114: год 9 | N114: год 10
B115: Ходовые моторы | C115: 12 | D115: 25000 | E115: =(INT($E$25*1/$D115)-INT($E$25*(1-1)/$D115))*$C115 -> 0 | F115: =(INT($E$25*2/$D115)-INT($E$25*(2-1)/$D115))*$C115 -> 0 | G115: =(INT($E$25*3/$D115)-INT($E$25*(3-1)/$D115))*$C115 -> 0 | H115: =(INT($E$25*4/$D115)-INT($E$25*(4-1)/$D115))*$C115 -> 12 | I115: =(INT($E$25*5/$D115)-INT($E$25*(5-1)/$D115))*$C115 -> 0 | J115: =(INT($E$25*6/$D115)-INT($E$25*(6-1)/$D115))*$C115 -> 0 | K115: =(INT($E$25*7/$D115)-INT($E$25*(7-1)/$D115))*$C115 -> 0 | L115: =(INT($E$25*8/$D115)-INT($E$25*(8-1)/$D115))*$C115 -> 12 | M115: =(INT($E$25*9/$D115)-INT($E$25*(9-1)/$D115))*$C115 -> 0 | N115: =(INT($E$25*10/$D115)-INT($E$25*(10-1)/$D115))*$C115 -> 0
B116: Редуктор хода | C116: 24 | D116: 25000 | E116: =(INT($E$25*1/$D116)-INT($E$25*(1-1)/$D116))*$C116 -> 0 | F116: =(INT($E$25*2/$D116)-INT($E$25*(2-1)/$D116))*$C116 -> 0 | G116: =(INT($E$25*3/$D116)-INT($E$25*(3-1)/$D116))*$C116 -> 0 | H116: =(INT($E$25*4/$D116)-INT($E$25*(4-1)/$D116))*$C116 -> 24 | I116: =(INT($E$25*5/$D116)-INT($E$25*(5-1)/$D116))*$C116 -> 0 | J116: =(INT($E$25*6/$D116)-INT($E$25*(6-1)/$D116))*$C116 -> 0 | K116: =(INT($E$25*7/$D116)-INT($E$25*(7-1)/$D116))*$C116 -> 0 | L116: =(INT($E$25*8/$D116)-INT($E$25*(8-1)/$D116))*$C116 -> 24 | M116: =(INT($E$25*9/$D116)-INT($E$25*(9-1)/$D116))*$C116 -> 0 | N116: =(INT($E$25*10/$D116)-INT($E$25*(10-1)/$D116))*$C116 -> 0
B117: Гусеничная лента | C117: 36 | D117: 20000 | E117: =(INT($E$25*1/$D117)-INT($E$25*(1-1)/$D117))*$C117 -> 0 | F117: =(INT($E$25*2/$D117)-INT($E$25*(2-1)/$D117))*$C117 -> 0 | G117: =(INT($E$25*3/$D117)-INT($E$25*(3-1)/$D117))*$C117 -> 36 | H117: =(INT($E$25*4/$D117)-INT($E$25*(4-1)/$D117))*$C117 -> 0 | I117: =(INT($E$25*5/$D117)-INT($E$25*(5-1)/$D117))*$C117 -> 0 | J117: =(INT($E$25*6/$D117)-INT($E$25*(6-1)/$D117))*$C117 -> 36 | K117: =(INT($E$25*7/$D117)-INT($E$25*(7-1)/$D117))*$C117 -> 0 | L117: =(INT($E$25*8/$D117)-INT($E$25*(8-1)/$D117))*$C117 -> 0 | M117: =(INT($E$25*9/$D117)-INT($E$25*(9-1)/$D117))*$C117 -> 36 | N117: =(INT($E$25*10/$D117)-INT($E$25*(10-1)/$D117))*$C117 -> 0
B118: Опорные ролики (комп) | C118: 36 | D118: 20000 | E118: =(INT($E$25*1/$D118)-INT($E$25*(1-1)/$D118))*$C118 -> 0 | F118: =(INT($E$25*2/$D118)-INT($E$25*(2-1)/$D118))*$C118 -> 0 | G118: =(INT($E$25*3/$D118)-INT($E$25*(3-1)/$D118))*$C118 -> 36 | H118: =(INT($E$25*4/$D118)-INT($E$25*(4-1)/$D118))*$C118 -> 0 | I118: =(INT($E$25*5/$D118)-INT($E$25*(5-1)/$D118))*$C118 -> 0 | J118: =(INT($E$25*6/$D118)-INT($E$25*(6-1)/$D118))*$C118 -> 36 | K118: =(INT($E$25*7/$D118)-INT($E$25*(7-1)/$D118))*$C118 -> 0 | L118: =(INT($E$25*8/$D118)-INT($E$25*(8-1)/$D118))*$C118 -> 0 | M118: =(INT($E$25*9/$D118)-INT($E$25*(9-1)/$D118))*$C118 -> 36 | N118: =(INT($E$25*10/$D118)-INT($E$25*(10-1)/$D118))*$C118 -> 0
B119: Поддерживающие катки (комп) | C119: 12 | D119: 20000 | E119: =(INT($E$25*1/$D119)-INT($E$25*(1-1)/$D119))*$C119 -> 0 | F119: =(INT($E$25*2/$D119)-INT($E$25*(2-1)/$D119))*$C119 -> 0 | G119: =(INT($E$25*3/$D119)-INT($E$25*(3-1)/$D119))*$C119 -> 12 | H119: =(INT($E$25*4/$D119)-INT($E$25*(4-1)/$D119))*$C119 -> 0 | I119: =(INT($E$25*5/$D119)-INT($E$25*(5-1)/$D119))*$C119 -> 0 | J119: =(INT($E$25*6/$D119)-INT($E$25*(6-1)/$D119))*$C119 -> 12 | K119: =(INT($E$25*7/$D119)-INT($E$25*(7-1)/$D119))*$C119 -> 0 | L119: =(INT($E$25*8/$D119)-INT($E$25*(8-1)/$D119))*$C119 -> 0 | M119: =(INT($E$25*9/$D119)-INT($E$25*(9-1)/$D119))*$C119 -> 12 | N119: =(INT($E$25*10/$D119)-INT($E$25*(10-1)/$D119))*$C119 -> 0
B120: Механизм натяжения гусениц | C120: 24 | D120: 30000 | E120: =(INT($E$25*1/$D120)-INT($E$25*(1-1)/$D120))*$C120 -> 0 | F120: =(INT($E$25*2/$D120)-INT($E$25*(2-1)/$D120))*$C120 -> 0 | G120: =(INT($E$25*3/$D120)-INT($E$25*(3-1)/$D120))*$C120 -> 0 | H120: =(INT($E$25*4/$D120)-INT($E$25*(4-1)/$D120))*$C120 -> 0 | I120: =(INT($E$25*5/$D120)-INT($E$25*(5-1)/$D120))*$C120 -> 24 | J120: =(INT($E$25*6/$D120)-INT($E$25*(6-1)/$D120))*$C120 -> 0 | K120: =(INT($E$25*7/$D120)-INT($E$25*(7-1)/$D120))*$C120 -> 0 | L120: =(INT($E$25*8/$D120)-INT($E$25*(8-1)/$D120))*$C120 -> 0 | M120: =(INT($E$25*9/$D120)-INT($E$25*(9-1)/$D120))*$C120 -> 24 | N120: =(INT($E$25*10/$D120)-INT($E$25*(10-1)/$D120))*$C120 -> 0
B121: Натяжное колесо | C121: 24 | D121: 20000 | E121: =(INT($E$25*1/$D121)-INT($E$25*(1-1)/$D121))*$C121 -> 0 | F121: =(INT($E$25*2/$D121)-INT($E$25*(2-1)/$D121))*$C121 -> 0 | G121: =(INT($E$25*3/$D121)-INT($E$25*(3-1)/$D121))*$C121 -> 24 | H121: =(INT($E$25*4/$D121)-INT($E$25*(4-1)/$D121))*$C121 -> 0 | I121: =(INT($E$25*5/$D121)-INT($E$25*(5-1)/$D121))*$C121 -> 0 | J121: =(INT($E$25*6/$D121)-INT($E$25*(6-1)/$D121))*$C121 -> 24 | K121: =(INT($E$25*7/$D121)-INT($E$25*(7-1)/$D121))*$C121 -> 0 | L121: =(INT($E$25*8/$D121)-INT($E$25*(8-1)/$D121))*$C121 -> 0 | M121: =(INT($E$25*9/$D121)-INT($E$25*(9-1)/$D121))*$C121 -> 24 | N121: =(INT($E$25*10/$D121)-INT($E$25*(10-1)/$D121))*$C121 -> 0
B122: Гидромотор поворота платформы | C122: 24 | D122: 25000 | E122: =(INT($E$25*1/$D122)-INT($E$25*(1-1)/$D122))*$C122 -> 0 | F122: =(INT($E$25*2/$D122)-INT($E$25*(2-1)/$D122))*$C122 -> 0 | G122: =(INT($E$25*3/$D122)-INT($E$25*(3-1)/$D122))*$C122 -> 0 | H122: =(INT($E$25*4/$D122)-INT($E$25*(4-1)/$D122))*$C122 -> 24 | I122: =(INT($E$25*5/$D122)-INT($E$25*(5-1)/$D122))*$C122 -> 0 | J122: =(INT($E$25*6/$D122)-INT($E$25*(6-1)/$D122))*$C122 -> 0 | K122: =(INT($E$25*7/$D122)-INT($E$25*(7-1)/$D122))*$C122 -> 0 | L122: =(INT($E$25*8/$D122)-INT($E$25*(8-1)/$D122))*$C122 -> 24 | M122: =(INT($E$25*9/$D122)-INT($E$25*(9-1)/$D122))*$C122 -> 0 | N122: =(INT($E$25*10/$D122)-INT($E$25*(10-1)/$D122))*$C122 -> 0
B123: Редуктор поворота платформы | C123: 24 | D123: 20000 | E123: =(INT($E$25*1/$D123)-INT($E$25*(1-1)/$D123))*$C123 -> 0 | F123: =(INT($E$25*2/$D123)-INT($E$25*(2-1)/$D123))*$C123 -> 0 | G123: =(INT($E$25*3/$D123)-INT($E$25*(3-1)/$D123))*$C123 -> 24 | H123: =(INT($E$25*4/$D123)-INT($E$25*(4-1)/$D123))*$C123 -> 0 | I123: =(INT($E$25*5/$D123)-INT($E$25*(5-1)/$D123))*$C123 -> 0 | J123: =(INT($E$25*6/$D123)-INT($E$25*(6-1)/$D123))*$C123 -> 24 | K123: =(INT($E$25*7/$D123)-INT($E$25*(7-1)/$D123))*$C123 -> 0 | L123: =(INT($E$25*8/$D123)-INT($E$25*(8-1)/$D123))*$C123 -> 0 | M123: =(INT($E$25*9/$D123)-INT($E$25*(9-1)/$D123))*$C123 -> 24 | N123: =(INT($E$25*10/$D123)-INT($E$25*(10-1)/$D123))*$C123 -> 0
B124: ДВС | C124: 72 | D124: 25000 | E124: =(INT($E$25*1/$D124)-INT($E$25*(1-1)/$D124))*$C124 -> 0 | F124: =(INT($E$25*2/$D124)-INT($E$25*(2-1)/$D124))*$C124 -> 0 | G124: =(INT($E$25*3/$D124)-INT($E$25*(3-1)/$D124))*$C124 -> 0 | H124: =(INT($E$25*4/$D124)-INT($E$25*(4-1)/$D124))*$C124 -> 72 | I124: =(INT($E$25*5/$D124)-INT($E$25*(5-1)/$D124))*$C124 -> 0 | J124: =(INT($E$25*6/$D124)-INT($E$25*(6-1)/$D124))*$C124 -> 0 | K124: =(INT($E$25*7/$D124)-INT($E$25*(7-1)/$D124))*$C124 -> 0 | L124: =(INT($E$25*8/$D124)-INT($E$25*(8-1)/$D124))*$C124 -> 72 | M124: =(INT($E$25*9/$D124)-INT($E$25*(9-1)/$D124))*$C124 -> 0 | N124: =(INT($E$25*10/$D124)-INT($E$25*(10-1)/$D124))*$C124 -> 0
B125: Главные насосы, 2 шт. | C125: 36 | D125: 25000 | E125: =(INT($E$25*1/$D125)-INT($E$25*(1-1)/$D125))*$C125 -> 0 | F125: =(INT($E$25*2/$D125)-INT($E$25*(2-1)/$D125))*$C125 -> 0 | G125: =(INT($E$25*3/$D125)-INT($E$25*(3-1)/$D125))*$C125 -> 0 | H125: =(INT($E$25*4/$D125)-INT($E$25*(4-1)/$D125))*$C125 -> 36 | I125: =(INT($E$25*5/$D125)-INT($E$25*(5-1)/$D125))*$C125 -> 0 | J125: =(INT($E$25*6/$D125)-INT($E$25*(6-1)/$D125))*$C125 -> 0 | K125: =(INT($E$25*7/$D125)-INT($E$25*(7-1)/$D125))*$C125 -> 0 | L125: =(INT($E$25*8/$D125)-INT($E$25*(8-1)/$D125))*$C125 -> 36 | M125: =(INT($E$25*9/$D125)-INT($E$25*(9-1)/$D125))*$C125 -> 0 | N125: =(INT($E$25*10/$D125)-INT($E$25*(10-1)/$D125))*$C125 -> 0
B126: Главный распределительный клапан | C126: 36 | D126: 25000 | E126: =(INT($E$25*1/$D126)-INT($E$25*(1-1)/$D126))*$C126 -> 0 | F126: =(INT($E$25*2/$D126)-INT($E$25*(2-1)/$D126))*$C126 -> 0 | G126: =(INT($E$25*3/$D126)-INT($E$25*(3-1)/$D126))*$C126 -> 0 | H126: =(INT($E$25*4/$D126)-INT($E$25*(4-1)/$D126))*$C126 -> 36 | I126: =(INT($E$25*5/$D126)-INT($E$25*(5-1)/$D126))*$C126 -> 0 | J126: =(INT($E$25*6/$D126)-INT($E$25*(6-1)/$D126))*$C126 -> 0 | K126: =(INT($E$25*7/$D126)-INT($E$25*(7-1)/$D126))*$C126 -> 0 | L126: =(INT($E$25*8/$D126)-INT($E$25*(8-1)/$D126))*$C126 -> 36 | M126: =(INT($E$25*9/$D126)-INT($E$25*(9-1)/$D126))*$C126 -> 0 | N126: =(INT($E$25*10/$D126)-INT($E$25*(10-1)/$D126))*$C126 -> 0
... B130: РВД рабочего оборудования | C130: 16 | D130: 20000 | E130: =(INT($E$25*1/$D130)-INT($E$25*(1-1)/$D130))*$C130 -> 0 | F130: =(INT($E$25*2/$D130)-INT($E$25*(2-1)/$D130))*$C130 -> 0 | G130: =(INT($E$25*3/$D130)-INT($E$25*(3-1)/$D130))*$C130 -> 16 | H130: =(INT($E$25*4/$D130)-INT($E$25*(4-1)/$D130))*$C130 -> 0 | I130: =(INT($E$25*5/$D130)-INT($E$25*(5-1)/$D130))*$C130 -> 0 | J130: =(INT($E$25*6/$D130)-INT($E$25*(6-1)/$D130))*$C130 -> 16 | K130: =(INT($E$25*7/$D130)-INT($E$25*(7-1)/$D130))*$C130 -> 0 | L130: =(INT($E$25*8/$D130)-INT($E$25*(8-1)/$D130))*$C130 -> 0 | M130: =(INT($E$25*9/$D130)-INT($E$25*(9-1)/$D130))*$C130 -> 16 | N130: =(INT($E$25*10/$D130)-INT($E$25*(10-1)/$D130))*$C130 -> 0
...

Sheet Поставщик 3
B1: ШАБЛОН ДАННЫХ ПОСТАВЩИКА — ВАРИАНТ 3
B2: Полные модели ТО и Ремонтов ПО ГОДАМ (затраты и трудозатраты — раздельно для ТО / текущих / капитальных ремонтов). Зелёное — авто; сводка тянется в «Данные по годам».
B4: Экскаватор: | E4: ='Ввод данных'!F7 -> Zoomlion ZE2000G Орикс
B5: Валюта затрат ТОиР: | D5: USD
B6: Показатель | C6: Ед. | E6: год 1 | F6: год 2 | G6: год 3 | H6: год 4 | I6: год 5 | J6: год 6 | K6: год 7 | L6: год 8 | M6: год 9 | N6: год 10
B7: СВОДКА ПО ГОДАМ (зелёное — авто из моделей ниже; тянется в расчёт)
B8: Простои на ТО | C8: ч/год | E8: =E37 -> 273.21 | F8: =F37 -> 273.21 | G8: =G37 -> 273.21 | H8: =H37 -> 273.21 | I8: =I37 -> 273.21 | J8: =J37 -> 273.21 | K8: =K37 -> 273.21 | L8: =L37 -> 273.21 | ... N8: =N37 -> 273.21
B9: Простои в текущих + капитальных ремонтах | C9: ч/год | E9: =E80 -> 786.13 | F9: =F80 -> 1924.36 | G9: =G80 -> 1682.92 | H9: =H80 -> 2228.84 | I9: =I80 -> 2239.02 | J9: =J80 -> 1794.52 | K9: =K80 -> 2025.05 | L9: =L80 -> 1519.78 | ... N9: =N80 -> 1663.35
B10: Ежесменное ТО (20 мин/смену) | C10: ч/год | E10: =('Параметры'!C26-E8-E9)/'Параметры'!C33*20/60 -> 213.90722 | F10: =('Параметры'!C26-F8-F9)/'Параметры'!C33*20/60 -> 182.28972 | G10: =('Параметры'!C26-G8-G9)/'Параметры'!C33*20/60 -> 188.99639 | H10: =('Параметры'!C26-H8-H9)/'Параметры'!C33*20/60 -> 173.83194 | I10: =('Параметры'!C26-I8-I9)/'Параметры'!C33*20/60 -> 173.54917 | J10: =('Параметры'!C26-J8-J9)/'Параметры'!C33*20/60 -> 185.89639 | K10: =('Параметры'!C26-K8-K9)/'Параметры'!C33*20/60 -> 179.49278 | L10: =('Параметры'!C26-L8-L9)/'Параметры'!C33*20/60 -> 193.52806 | M10: =('Параметры'!C26-M8-M9)/'Параметры'!C33*20/60 -> 167.18333 | N10: =('Параметры'!C26-N8-N9)/'Параметры'!C33*20/60 -> 189.54
B11: КТГ (авто) = (8760 − простои)/8760 | C11: коэф. | E11: =('Параметры'!C26-E8-E9-E10)/'Параметры'!C26 -> 0.85465214 | F11: =('Параметры'!C26-F8-F9-F10)/'Параметры'!C26 -> 0.72832652 | G11: =('Параметры'!C26-G8-G9-G10)/'Параметры'!C26 -> 0.75512256 | H11: =('Параметры'!C26-H8-H9-H10)/'Параметры'!C26 -> 0.69453402 | I11: =('Параметры'!C26-I8-I9-I10)/'Параметры'!C26 -> 0.6934042 | J11: =('Параметры'!C26-J8-J9-J10)/'Параметры'!C26 -> 0.74273671 | K11: =('Параметры'!C26-K8-K9-K10)/'Параметры'!C26 -> 0.71715151 | L11: =('Параметры'!C26-L8-L9-L10)/'Параметры'!C26 -> 0.77322853 | M11: =('Параметры'!C26-M8-M9-M10)/'Параметры'!C26 -> 0.66796994 | N11: =('Параметры'!C26-N8-N9-N10)/'Параметры'!C26 -> 0.75729452
B12: Затраты на ТО (ЗЧ, из каталога) | C12: тыс/год | E12: =E75 -> 107.51972 | F12: =F75 -> 107.51972 | G12: =G75 -> 107.51972 | H12: =H75 -> 107.51972 | I12: =I75 -> 107.51972 | J12: =J75 -> 107.51972 | K12: =K75 -> 107.51972 | L12: =L75 -> 107.51972 | ... N12: =N75 -> 107.51972
B13: Затраты на текущие ремонты (ЗЧ) | C13: тыс/год | E13: =E90*$E$81 -> 29.143 | F13: =F90*$E$81 -> 29.143 | G13: =G90*$E$81 -> 32.4 | H13: =H90*$E$81 -> 29.143 | I13: =I90*$E$81 -> 30.704 | J13: =J90*$E$81 -> 30.839 | K13: =K90*$E$81 -> 30.704 | L13: =L90*$E$81 -> 29.143 | ... N13: =N90*$E$81 -> 29.143
B14: Затраты на капитальные ремонты (ЗЧ, цех) | C14: тыс/год | E14: =E112*$E$81 -> 0 | F14: =F112*$E$81 -> 24.929 | G14: =G112*$E$81 -> 608.818 | H14: =H112*$E$81 -> 89 | I14: =I112*$E$81 -> 608.818 | J14: =J112*$E$81 -> 24.929 | K14: =K112*$E$81 -> 583.889 | L14: =L112*$E$81 -> 113.929 | ... N14: =N112*$E$81 -> 24.929
B15: Трудозатраты на ТО | C15: ч-час/год | E15: =E43 -> 546.42 | F15: =F43 -> 546.42 | G15: =G43 -> 546.42 | H15: =H43 -> 546.42 | I15: =I43 -> 546.42 | J15: =J43 -> 546.42 | K15: =K43 -> 546.42 | L15: =L43 -> 546.42 | ... N15: =N43 -> 546.42
B16: Трудозатраты на текущие ремонты | C16: ч-час/год | E16: =E95*$E$81 -> 80 | F16: =F95*$E$81 -> 80 | G16: =G95*$E$81 -> 80 | H16: =H95*$E$81 -> 80 | I16: =I95*$E$81 -> 80 | J16: =J95*$E$81 -> 80 | K16: =K95*$E$81 -> 80 | L16: =L95*$E$81 -> 80 | ... N16: =N95*$E$81 -> 80
B17: Трудозатраты на капитальные ремонты (цех) | C17: чел-час/год | E17: =E121*$E$81 -> 0 | F17: =F121*$E$81 -> 40 | G17: =G121*$E$81 -> 380 | H17: =H121*$E$81 -> 80 | I17: =I121*$E$81 -> 380 | J17: =J121*$E$81 -> 40 | K17: =K121*$E$81 -> 340 | L17: =L121*$E$81 -> 120 | ... N17: =N121*$E$81 -> 40
B18: Сервис ТО (авто) = трудозатраты ТО × ставка | C18: тыс/год | E18: =E15*$E$77/1000 -> 27.321 | F18: =F15*$E$77/1000 -> 27.321 | G18: =G15*$E$77/1000 -> 27.321 | H18: =H15*$E$77/1000 -> 27.321 | I18: =I15*$E$77/1000 -> 27.321 | J18: =J15*$E$77/1000 -> 27.321 | K18: =K15*$E$77/1000 -> 27.321 | L18: =L15*$E$77/1000 -> 27.321 | ... N18: =N15*$E$77/1000 -> 27.321
B19: Сервис текущих ремонтов (авто) | C19: тыс/год | E19: =E16*$E$77/1000 -> 4 | F19: =F16*$E$77/1000 -> 4 | G19: =G16*$E$77/1000 -> 4 | H19: =H16*$E$77/1000 -> 4 | I19: =I16*$E$77/1000 -> 4 | J19: =J16*$E$77/1000 -> 4 | K19: =K16*$E$77/1000 -> 4 | L19: =L16*$E$77/1000 -> 4 | ... N19: =N16*$E$77/1000 -> 4
B20: Сервис капитальных ремонтов (цех, авто) | C20: тыс/год | E20: =E17*$E$77/1000 -> 0 | F20: =F17*$E$77/1000 -> 2 | G20: =G17*$E$77/1000 -> 19 | H20: =H17*$E$77/1000 -> 4 | I20: =I17*$E$77/1000 -> 19 | J20: =J17*$E$77/1000 -> 2 | K20: =K17*$E$77/1000 -> 17 | L20: =L17*$E$77/1000 -> 6 | ... N20: =N17*$E$77/1000 -> 2
B21: ИТОГО ТОиР (авто) → «Данные по годам» | C21: тыс/год | E21: =E12+E13+E14+E18+E19+E20 -> 167.98372 | F21: =F12+F13+F14+F18+F19+F20 -> 194.91272 | G21: =G12+G13+G14+G18+G19+G20 -> 799.05872 | H21: =H12+H13+H14+H18+H19+H20 -> 260.98372 | I21: =I12+I13+I14+I18+I19+I20 -> 797.36272 | J21: =J12+J13+J14+J18+J19+J20 -> 196.60872 | K21: =K12+K13+K14+K18+K19+K20 -> 770.43372 | L21: =L12+L13+L14+L18+L19+L20 -> 287.91272 | ... N21: =N12+N13+N14+N18+N19+N20 -> 194.91272
B22: Удельный расход ДТ | C22: кг/час | E22: 90.23 | F22: 90.23 | G22: 90.23 | H22: 90.23 | I22: 90.23 | J22: 90.23 | K22: 90.23 | L22: 90.23 | M22: 90.23 | N22: 90.23
B23: Расходники на ковш | C23: руб/м³ | E23: 0.87 | F23: 0.87 | G23: 0.87 | H23: 0.87 | I23: 0.87 | J23: 0.87 | K23: 0.87 | L23: 0.87 | M23: 0.87 | N23: 0.87
B24: РАСЧЁТ ТО (по интервалам обслуживания), ПО ГОДАМ
B25: Наработка по годам | C25: м/час | E25: 7000 | F25: 7000 | G25: 7000 | H25: 7000 | I25: 7000 | J25: 7000 | K25: 7000 | L25: 7000 | M25: 7000 | N25: 7000
B26: Вид ТО | C26: интервал | D26: длит.простоя | E26: персонал
B27: ТО-1 | C27: 500 | D27: 10.2 | E27: 2
B28: ТО-2 | C28: 1000 | D28: 9.4 | E28: 2
B29: ТО-3 | C29: 2000 | D29: 12.4 | E29: 2
B30: ТО-4 | C30: 4000 | D30: 7.8 | E30: 2
B31: ТО-5 | C31: 5000 | D31: 5.4 | E31: 2
B32: ТО-1: простои, ч/год | C32: #,##0 | E32: =(E$25/$C27)*$D27 -> 142.8 | F32: =(F$25/$C27)*$D27 -> 142.8 | G32: =(G$25/$C27)*$D27 -> 142.8 | H32: =(H$25/$C27)*$D27 -> 142.8 | I32: =(I$25/$C27)*$D27 -> 142.8 | J32: =(J$25/$C27)*$D27 -> 142.8 | K32: =(K$25/$C27)*$D27 -> 142.8 | L32: =(L$25/$C27)*$D27 -> 142.8 | ... N32: =(N$25/$C27)*$D27 -> 142.8
B33: ТО-2: простои, ч/год | C33: #,##0 | E33: =(E$25/$C28)*$D28 -> 65.8 | F33: =(F$25/$C28)*$D28 -> 65.8 | G33: =(G$25/$C28)*$D28 -> 65.8 | H33: =(H$25/$C28)*$D28 -> 65.8 | I33: =(I$25/$C28)*$D28 -> 65.8 | J33: =(J$25/$C28)*$D28 -> 65.8 | K33: =(K$25/$C28)*$D28 -> 65.8 | L33: =(L$25/$C28)*$D28 -> 65.8 | ... N33: =(N$25/$C28)*$D28 -> 65.8
B34: ТО-3: простои, ч/год | C34: #,##0 | E34: =(E$25/$C29)*$D29 -> 43.4 | F34: =(F$25/$C29)*$D29 -> 43.4 | G34: =(G$25/$C29)*$D29 -> 43.4 | H34: =(H$25/$C29)*$D29 -> 43.4 | I34: =(I$25/$C29)*$D29 -> 43.4 | J34: =(J$25/$C29)*$D29 -> 43.4 | K34: =(K$25/$C29)*$D29 -> 43.4 | L34: =(L$25/$C29)*$D29 -> 43.4 | ... N34: =(N$25/$C29)*$D29 -> 43.4
B35: ТО-4: простои, ч/год | C35: #,##0 | E35: =(E$25/$C30)*$D30 -> 13.65 | F35: =(F$25/$C30)*$D30 -> 13.65 | G35: =(G$25/$C30)*$D30 -> 13.65 | H35: =(H$25/$C30)*$D30 -> 13.65 | I35: =(I$25/$C30)*$D30 -> 13.65 | J35: =(J$25/$C30)*$D30 -> 13.65 | K35: =(K$25/$C30)*$D30 -> 13.65 | L35: =(L$25/$C30)*$D30 -> 13.65 | ... N35: =(N$25/$C30)*$D30 -> 13.65
B36: ТО-5: простои, ч/год | C36: #,##0 | E36: =(E$25/$C31)*$D31 -> 7.56 | F36: =(F$25/$C31)*$D31 -> 7.56 | G36: =(G$25/$C31)*$D31 -> 7.56 | H36: =(H$25/$C31)*$D31 -> 7.56 | I36: =(I$25/$C31)*$D31 -> 7.56 | J36: =(J$25/$C31)*$D31 -> 7.56 | K36: =(K$25/$C31)*$D31 -> 7.56 | L36: =(L$25/$C31)*$D31 -> 7.56 | ... N36: =(N$25/$C31)*$D31 -> 7.56
B37: Итого простои ТО, ч/год | C37: ч/год | E37: =SUM(E32:E36) -> 273.21 | F37: =SUM(F32:F36) -> 273.21 | G37: =SUM(G32:G36) -> 273.21 | H37: =SUM(H32:H36) -> 273.21 | I37: =SUM(I32:I36) -> 273.21 | J37: =SUM(J32:J36) -> 273.21 | K37: =SUM(K32:K36) -> 273.21 | L37: =SUM(L32:L36) -> 273.21 | ... N37: =SUM(N32:N36) -> 273.21
B38: ТО-1: ч·часы/год | C38: #,##0 | E38: =E32*$E27 -> 285.6 | F38: =F32*$E27 -> 285.6 | G38: =G32*$E27 -> 285.6 | H38: =H32*$E27 -> 285.6 | I38: =I32*$E27 -> 285.6 | J38: =J32*$E27 -> 285.6 | K38: =K32*$E27 -> 285.6 | L38: =L32*$E27 -> 285.6 | ... N38: =N32*$E27 -> 285.6
B39: ТО-2: ч·часы/год | C39: #,##0 | E39: =E33*$E28 -> 131.6 | F39: =F33*$E28 -> 131.6 | G39: =G33*$E28 -> 131.6 | H39: =H33*$E28 -> 131.6 | I39: =I33*$E28 -> 131.6 | J39: =J33*$E28 -> 131.6 | K39: =K33*$E28 -> 131.6 | L39: =L33*$E28 -> 131.6 | ... N39: =N33*$E28 -> 131.6
B40: ТО-3: ч·часы/год | C40: #,##0 | E40: =E34*$E29 -> 86.8 | F40: =F34*$E29 -> 86.8 | G40: =G34*$E29 -> 86.8 | H40: =H34*$E29 -> 86.8 | I40: =I34*$E29 -> 86.8 | J40: =J34*$E29 -> 86.8 | K40: =K34*$E29 -> 86.8 | L40: =L34*$E29 -> 86.8 | ... N40: =N34*$E29 -> 86.8
B41: ТО-4: ч·часы/год | C41: #,##0 | E41: =E35*$E30 -> 27.3 | F41: =F35*$E30 -> 27.3 | G41: =G35*$E30 -> 27.3 | H41: =H35*$E30 -> 27.3 | I41: =I35*$E30 -> 27.3 | J41: =J35*$E30 -> 27.3 | K41: =K35*$E30 -> 27.3 | L41: =L35*$E30 -> 27.3 | ... N41: =N35*$E30 -> 27.3
B42: ТО-5: ч·часы/год | C42: #,##0 | E42: =E36*$E31 -> 15.12 | F42: =F36*$E31 -> 15.12 | G42: =G36*$E31 -> 15.12 | H42: =H36*$E31 -> 15.12 | I42: =I36*$E31 -> 15.12 | J42: =J36*$E31 -> 15.12 | K42: =K36*$E31 -> 15.12 | L42: =L36*$E31 -> 15.12 | ... N42: =N36*$E31 -> 15.12
B43: Итого ч·часы ТО, ч-час/год | C43: ч-час | E43: =SUM(E38:E42) -> 546.42 | F43: =SUM(F38:F42) -> 546.42 | G43: =SUM(G38:G42) -> 546.42 | H43: =SUM(H38:H42) -> 546.42 | I43: =SUM(I38:I42) -> 546.42 | J43: =SUM(J38:J42) -> 546.42 | K43: =SUM(K38:K42) -> 546.42 | L43: =SUM(L38:L42) -> 546.42 | ... N43: =SUM(N38:N42) -> 546.42
B45: КАТАЛОГ ЗАПЧАСТЕЙ ТО (заполняет подрядчик), ПО ГОДАМ
B46: Наименование | C46: цена за ед | D46: кол-во/ТО | E46: год 1 | F46: год 2 | G46: год 3 | H46: год 4 | I46: год 5 | J46: год 6 | K46: год 7 | L46: год 8 | M46: год 9 | N46: год 10 | P46: № ТО
B47: Масляный фильтр | C47: 114.83 | D47: 4 | E47: =(E$25/INDEX($C$27:$C$31,$P47))*D47*C47/1000 -> 6.43048 | F47: =(F$25/INDEX($C$27:$C$31,$P47))*D47*C47/1000 -> 6.43048 | G47: =(G$25/INDEX($C$27:$C$31,$P47))*D47*C47/1000 -> 6.43048 | H47: =(H$25/INDEX($C$27:$C$31,$P47))*D47*C47/1000 -> 6.43048 | I47: =(I$25/INDEX($C$27:$C$31,$P47))*D47*C47/1000 -> 6.43048 | J47: =(J$25/INDEX($C$27:$C$31,$P47))*D47*C47/1000 -> 6.43048 | K47: =(K$25/INDEX($C$27:$C$31,$P47))*D47*C47/1000 -> 6.43048 | L47: =(L$25/INDEX($C$27:$C$31,$P47))*D47*C47/1000 -> 6.43048 | M47: =(M$25/INDEX($C$27:$C$31,$P47))*D47*C47/1000 -> 6.43048 | N47: =(N$25/INDEX($C$27:$C$31,$P47))*D47*C47/1000 -> 6.43048 | P47: 1
B48: Топливный фильтр | C48: 141.33 | D48: 2 | E48: =(E$25/INDEX($C$27:$C$31,$P48))*D48*C48/1000 -> 3.95724 | F48: =(F$25/INDEX($C$27:$C$31,$P48))*D48*C48/1000 -> 3.95724 | G48: =(G$25/INDEX($C$27:$C$31,$P48))*D48*C48/1000 -> 3.95724 | H48: =(H$25/INDEX($C$27:$C$31,$P48))*D48*C48/1000 -> 3.95724 | I48: =(I$25/INDEX($C$27:$C$31,$P48))*D48*C48/1000 -> 3.95724 | J48: =(J$25/INDEX($C$27:$C$31,$P48))*D48*C48/1000 -> 3.95724 | K48: =(K$25/INDEX($C$27:$C$31,$P48))*D48*C48/1000 -> 3.95724 | L48: =(L$25/INDEX($C$27:$C$31,$P48))*D48*C48/1000 -> 3.95724 | M48: =(M$25/INDEX($C$27:$C$31,$P48))*D48*C48/1000 -> 3.95724 | N48: =(N$25/INDEX($C$27:$C$31,$P48))*D48*C48/1000 -> 3.95724 | P48: 1
B49: Масло ДВС | C49: 6.87 | D49: 130 | E49: =(E$25/INDEX($C$27:$C$31,$P49))*D49*C49/1000 -> 12.5034 | F49: =(F$25/INDEX($C$27:$C$31,$P49))*D49*C49/1000 -> 12.5034 | G49: =(G$25/INDEX($C$27:$C$31,$P49))*D49*C49/1000 -> 12.5034 | H49: =(H$25/INDEX($C$27:$C$31,$P49))*D49*C49/1000 -> 12.5034 | I49: =(I$25/INDEX($C$27:$C$31,$P49))*D49*C49/1000 -> 12.5034 | J49: =(J$25/INDEX($C$27:$C$31,$P49))*D49*C49/1000 -> 12.5034 | K49: =(K$25/INDEX($C$27:$C$31,$P49))*D49*C49/1000 -> 12.5034 | L49: =(L$25/INDEX($C$27:$C$31,$P49))*D49*C49/1000 -> 12.5034 | M49: =(M$25/INDEX($C$27:$C$31,$P49))*D49*C49/1000 -> 12.5034 | N49: =(N$25/INDEX($C$27:$C$31,$P49))*D49*C49/1000 -> 12.5034 | P49: 1
B50: Фильтр управляющего контура | C50: 126 | D50: 1 | E50: =(E$25/INDEX($C$27:$C$31,$P50))*D50*C50/1000 -> 1.764 | F50: =(F$25/INDEX($C$27:$C$31,$P50))*D50*C50/1000 -> 1.764 | G50: =(G$25/INDEX($C$27:$C$31,$P50))*D50*C50/1000 -> 1.764 | H50: =(H$25/INDEX($C$27:$C$31,$P50))*D50*C50/1000 -> 1.764 | I50: =(I$25/INDEX($C$27:$C$31,$P50))*D50*C50/1000 -> 1.764 | J50: =(J$25/INDEX($C$27:$C$31,$P50))*D50*C50/1000 -> 1.764 | K50: =(K$25/INDEX($C$27:$C$31,$P50))*D50*C50/1000 -> 1.764 | L50: =(L$25/INDEX($C$27:$C$31,$P50))*D50*C50/1000 -> 1.764 | M50: =(M$25/INDEX($C$27:$C$31,$P50))*D50*C50/1000 -> 1.764 | N50: =(N$25/INDEX($C$27:$C$31,$P50))*D50*C50/1000 -> 1.764 | P50: 1
B51: Сливной фильтр | C51: 30.67 | D51: 2 | E51: =(E$25/INDEX($C$27:$C$31,$P51))*D51*C51/1000 -> 0.85876 | F51: =(F$25/INDEX($C$27:$C$31,$P51))*D51*C51/1000 -> 0.85876 | G51: =(G$25/INDEX($C$27:$C$31,$P51))*D51*C51/1000 -> 0.85876 | H51: =(H$25/INDEX($C$27:$C$31,$P51))*D51*C51/1000 -> 0.85876 | I51: =(I$25/INDEX($C$27:$C$31,$P51))*D51*C51/1000 -> 0.85876 | J51: =(J$25/INDEX($C$27:$C$31,$P51))*D51*C51/1000 -> 0.85876 | K51: =(K$25/INDEX($C$27:$C$31,$P51))*D51*C51/1000 -> 0.85876 | L51: =(L$25/INDEX($C$27:$C$31,$P51))*D51*C51/1000 -> 0.85876 | M51: =(M$25/INDEX($C$27:$C$31,$P51))*D51*C51/1000 -> 0.85876 | N51: =(N$25/INDEX($C$27:$C$31,$P51))*D51*C51/1000 -> 0.85876 | P51: 1
B52: Сливной фильтр насоса | C52: 201 | D52: 3 | E52: =(E$25/INDEX($C$27:$C$31,$P52))*D52*C52/1000 -> 8.442 | F52: =(F$25/INDEX($C$27:$C$31,$P52))*D52*C52/1000 -> 8.442 | G52: =(G$25/INDEX($C$27:$C$31,$P52))*D52*C52/1000 -> 8.442 | H52: =(H$25/INDEX($C$27:$C$31,$P52))*D52*C52/1000 -> 8.442 | I52: =(I$25/INDEX($C$27:$C$31,$P52))*D52*C52/1000 -> 8.442 | J52: =(J$25/INDEX($C$27:$C$31,$P52))*D52*C52/1000 -> 8.442 | K52: =(K$25/INDEX($C$27:$C$31,$P52))*D52*C52/1000 -> 8.442 | L52: =(L$25/INDEX($C$27:$C$31,$P52))*D52*C52/1000 -> 8.442 | M52: =(M$25/INDEX($C$27:$C$31,$P52))*D52*C52/1000 -> 8.442 | N52: =(N$25/INDEX($C$27:$C$31,$P52))*D52*C52/1000 -> 8.442 | P52: 1
B53: Смазка | C53: 12.24 | D53: 200 | E53: =(E$25/INDEX($C$27:$C$31,$P53))*D53*C53/1000 -> 34.272 | F53: =(F$25/INDEX($C$27:$C$31,$P53))*D53*C53/1000 -> 34.272 | G53: =(G$25/INDEX($C$27:$C$31,$P53))*D53*C53/1000 -> 34.272 | H53: =(H$25/INDEX($C$27:$C$31,$P53))*D53*C53/1000 -> 34.272 | I53: =(I$25/INDEX($C$27:$C$31,$P53))*D53*C53/1000 -> 34.272 | J53: =(J$25/INDEX($C$27:$C$31,$P53))*D53*C53/1000 -> 34.272 | K53: =(K$25/INDEX($C$27:$C$31,$P53))*D53*C53/1000 -> 34.272 | L53: =(L$25/INDEX($C$27:$C$31,$P53))*D53*C53/1000 -> 34.272 | M53: =(M$25/INDEX($C$27:$C$31,$P53))*D53*C53/1000 -> 34.272 | N53: =(N$25/INDEX($C$27:$C$31,$P53))*D53*C53/1000 -> 34.272 | P53: 1
B54: Топливный фильтр (ТО-2) | C54: 80.17 | D54: 2 | E54: =(E$25/INDEX($C$27:$C$31,$P54))*D54*C54/1000 -> 1.12238 | F54: =(F$25/INDEX($C$27:$C$31,$P54))*D54*C54/1000 -> 1.12238 | G54: =(G$25/INDEX($C$27:$C$31,$P54))*D54*C54/1000 -> 1.12238 | H54: =(H$25/INDEX($C$27:$C$31,$P54))*D54*C54/1000 -> 1.12238 | I54: =(I$25/INDEX($C$27:$C$31,$P54))*D54*C54/1000 -> 1.12238 | J54: =(J$25/INDEX($C$27:$C$31,$P54))*D54*C54/1000 -> 1.12238 | K54: =(K$25/INDEX($C$27:$C$31,$P54))*D54*C54/1000 -> 1.12238 | L54: =(L$25/INDEX($C$27:$C$31,$P54))*D54*C54/1000 -> 1.12238 | M54: =(M$25/INDEX($C$27:$C$31,$P54))*D54*C54/1000 -> 1.12238 | N54: =(N$25/INDEX($C$27:$C$31,$P54))*D54*C54/1000 -> 1.12238 | P54: 2
B55: Фильтр сапуна топл.бака | C55: 19.17 | D55: 1 | E55: =(E$25/INDEX($C$27:$C$31,$P55))*D55*C55/1000 -> 0.13419 | F55: =(F$25/INDEX($C$27:$C$31,$P55))*D55*C55/1000 -> 0.13419 | G55: =(G$25/INDEX($C$27:$C$31,$P55))*D55*C55/1000 -> 0.13419 | H55: =(H$25/INDEX($C$27:$C$31,$P55))*D55*C55/1000 -> 0.13419 | I55: =(I$25/INDEX($C$27:$C$31,$P55))*D55*C55/1000 -> 0.13419 | J55: =(J$25/INDEX($C$27:$C$31,$P55))*D55*C55/1000 -> 0.13419 | K55: =(K$25/INDEX($C$27:$C$31,$P55))*D55*C55/1000 -> 0.13419 | L55: =(L$25/INDEX($C$27:$C$31,$P55))*D55*C55/1000 -> 0.13419 | M55: =(M$25/INDEX($C$27:$C$31,$P55))*D55*C55/1000 -> 0.13419 | N55: =(N$25/INDEX($C$27:$C$31,$P55))*D55*C55/1000 -> 0.13419 | P55: 2
B56: Фильтр сапуна гидробака | C56: 19.17 | D56: 2 | E56: =(E$25/INDEX($C$27:$C$31,$P56))*D56*C56/1000 -> 0.26838 | F56: =(F$25/INDEX($C$27:$C$31,$P56))*D56*C56/1000 -> 0.26838 | G56: =(G$25/INDEX($C$27:$C$31,$P56))*D56*C56/1000 -> 0.26838 | H56: =(H$25/INDEX($C$27:$C$31,$P56))*D56*C56/1000 -> 0.26838 | I56: =(I$25/INDEX($C$27:$C$31,$P56))*D56*C56/1000 -> 0.26838 | J56: =(J$25/INDEX($C$27:$C$31,$P56))*D56*C56/1000 -> 0.26838 | K56: =(K$25/INDEX($C$27:$C$31,$P56))*D56*C56/1000 -> 0.26838 | L56: =(L$25/INDEX($C$27:$C$31,$P56))*D56*C56/1000 -> 0.26838 | M56: =(M$25/INDEX($C$27:$C$31,$P56))*D56*C56/1000 -> 0.26838 | N56: =(N$25/INDEX($C$27:$C$31,$P56))*D56*C56/1000 -> 0.26838 | P56: 2
B57: Гидравлический фильтр | C57: 344.33 | D57: 3 | E57: =(E$25/INDEX($C$27:$C$31,$P57))*D57*C57/1000 -> 7.23093 | F57: =(F$25/INDEX($C$27:$C$31,$P57))*D57*C57/1000 -> 7.23093 | G57: =(G$25/INDEX($C$27:$C$31,$P57))*D57*C57/1000 -> 7.23093 | H57: =(H$25/INDEX($C$27:$C$31,$P57))*D57*C57/1000 -> 7.23093 | I57: =(I$25/INDEX($C$27:$C$31,$P57))*D57*C57/1000 -> 7.23093 | J57: =(J$25/INDEX($C$27:$C$31,$P57))*D57*C57/1000 -> 7.23093 | K57: =(K$25/INDEX($C$27:$C$31,$P57))*D57*C57/1000 -> 7.23093 | L57: =(L$25/INDEX($C$27:$C$31,$P57))*D57*C57/1000 -> 7.23093 | M57: =(M$25/INDEX($C$27:$C$31,$P57))*D57*C57/1000 -> 7.23093 | N57: =(N$25/INDEX($C$27:$C$31,$P57))*D57*C57/1000 -> 7.23093 | P57: 2
B58: О-кольцо | C58: 24.5 | D58: 3 | E58: =(E$25/INDEX($C$27:$C$31,$P58))*D58*C58/1000 -> 0.5145 | F58: =(F$25/INDEX($C$27:$C$31,$P58))*D58*C58/1000 -> 0.5145 | G58: =(G$25/INDEX($C$27:$C$31,$P58))*D58*C58/1000 -> 0.5145 | H58: =(H$25/INDEX($C$27:$C$31,$P58))*D58*C58/1000 -> 0.5145 | I58: =(I$25/INDEX($C$27:$C$31,$P58))*D58*C58/1000 -> 0.5145 | J58: =(J$25/INDEX($C$27:$C$31,$P58))*D58*C58/1000 -> 0.5145 | K58: =(K$25/INDEX($C$27:$C$31,$P58))*D58*C58/1000 -> 0.5145 | L58: =(L$25/INDEX($C$27:$C$31,$P58))*D58*C58/1000 -> 0.5145 | M58: =(M$25/INDEX($C$27:$C$31,$P58))*D58*C58/1000 -> 0.5145 | N58: =(N$25/INDEX($C$27:$C$31,$P58))*D58*C58/1000 -> 0.5145 | P58: 2
... B73: Гидравлическое масло | C73: 6.43 | D73: 1300 | E73: =(E$25/INDEX($C$27:$C$31,$P73))*D73*C73/1000 -> 11.7026 | F73: =(F$25/INDEX($C$27:$C$31,$P73))*D73*C73/1000 -> 11.7026 | G73: =(G$25/INDEX($C$27:$C$31,$P73))*D73*C73/1000 -> 11.7026 | H73: =(H$25/INDEX($C$27:$C$31,$P73))*D73*C73/1000 -> 11.7026 | I73: =(I$25/INDEX($C$27:$C$31,$P73))*D73*C73/1000 -> 11.7026 | J73: =(J$25/INDEX($C$27:$C$31,$P73))*D73*C73/1000 -> 11.7026 | K73: =(K$25/INDEX($C$27:$C$31,$P73))*D73*C73/1000 -> 11.7026 | L73: =(L$25/INDEX($C$27:$C$31,$P73))*D73*C73/1000 -> 11.7026 | M73: =(M$25/INDEX($C$27:$C$31,$P73))*D73*C73/1000 -> 11.7026 | N73: =(N$25/INDEX($C$27:$C$31,$P73))*D73*C73/1000 -> 11.7026 | P73: 5
B74: Корректировка (поглощения/прочее) | E74: 0 | F74: 0 | G74: 0 | H74: 0 | I74: 0 | J74: 0 | K74: 0 | L74: 0 | M74: 0 | N74: 0
B75: ИТОГО затраты на запчасти ТО, тыс/год | E75: =SUM(E47:E74) -> 107.51972 | F75: =SUM(F47:F74) -> 107.51972 | G75: =SUM(G47:G74) -> 107.51972 | H75: =SUM(H47:H74) -> 107.51972 | I75: =SUM(I47:I74) -> 107.51972 | J75: =SUM(J47:J74) -> 107.51972 | K75: =SUM(K47:K74) -> 107.51972 | L75: =SUM(L47:L74) -> 107.51972 | ... N75: =SUM(N47:N74) -> 107.51972
B77: Ставка сервиса | C77: вал/ч·час | E77: 50
B79: РАСЧЁТ РЕМОНТОВ (из списков по периодичности замены узлов)
B80: Простои в текущих + капитальных ремонтах | C80: ч/год | E80: 786.13 | F80: 1924.36 | G80: 1682.92 | H80: 2228.84 | I80: 2239.02 | J80: 1794.52 | K80: 2025.05 | L80: 1519.78 | M80: 2468.19 | N80: 1663.35
B81: Коэффициент поглощения (0–1; 1=как у поставщика) | C81: коэф. | E81: 1
B83: ТЕКУЩИЕ РЕМОНТЫ — ЗАТРАТЫ НА ЗЧ (по ресурсу замены)
B84: Наименование | C84: стоим.замены,тыс | D84: ресурс, м/ч | E84: год 1 | F84: год 2 | G84: год 3 | H84: год 4 | I84: год 5 | J84: год 6 | K84: год 7 | L84: год 8 | M84: год 9 | N84: год 10
B85: Быстроизнашиваемые элементы (GET) ковша, флэт-годовой | C85: 27.281 | D85: 7000 | E85: =(INT($E$25*1/$D85)-INT($E$25*(1-1)/$D85))*$C85 -> 27.281 | F85: =(INT($E$25*2/$D85)-INT($E$25*(2-1)/$D85))*$C85 -> 27.281 | G85: =(INT($E$25*3/$D85)-INT($E$25*(3-1)/$D85))*$C85 -> 27.281 | H85: =(INT($E$25*4/$D85)-INT($E$25*(4-1)/$D85))*$C85 -> 27.281 | I85: =(INT($E$25*5/$D85)-INT($E$25*(5-1)/$D85))*$C85 -> 27.281 | J85: =(INT($E$25*6/$D85)-INT($E$25*(6-1)/$D85))*$C85 -> 27.281 | K85: =(INT($E$25*7/$D85)-INT($E$25*(7-1)/$D85))*$C85 -> 27.281 | L85: =(INT($E$25*8/$D85)-INT($E$25*(8-1)/$D85))*$C85 -> 27.281 | M85: =(INT($E$25*9/$D85)-INT($E$25*(9-1)/$D85))*$C85 -> 27.281 | N85: =(INT($E$25*10/$D85)-INT($E$25*(10-1)/$D85))*$C85 -> 27.281
B86: Быстроизнашиваемые детали (ремни), флэт-годовой | C86: 0.354 | D86: 7000 | E86: =(INT($E$25*1/$D86)-INT($E$25*(1-1)/$D86))*$C86 -> 0.354 | F86: =(INT($E$25*2/$D86)-INT($E$25*(2-1)/$D86))*$C86 -> 0.354 | G86: =(INT($E$25*3/$D86)-INT($E$25*(3-1)/$D86))*$C86 -> 0.354 | H86: =(INT($E$25*4/$D86)-INT($E$25*(4-1)/$D86))*$C86 -> 0.354 | I86: =(INT($E$25*5/$D86)-INT($E$25*(5-1)/$D86))*$C86 -> 0.354 | J86: =(INT($E$25*6/$D86)-INT($E$25*(6-1)/$D86))*$C86 -> 0.354 | K86: =(INT($E$25*7/$D86)-INT($E$25*(7-1)/$D86))*$C86 -> 0.354 | L86: =(INT($E$25*8/$D86)-INT($E$25*(8-1)/$D86))*$C86 -> 0.354 | M86: =(INT($E$25*9/$D86)-INT($E$25*(9-1)/$D86))*$C86 -> 0.354 | N86: =(INT($E$25*10/$D86)-INT($E$25*(10-1)/$D86))*$C86 -> 0.354
B87: Крыльчатка вентилятора | C87: 1.561 | D87: 15000 | E87: =(INT($E$25*1/$D87)-INT($E$25*(1-1)/$D87))*$C87 -> 0 | F87: =(INT($E$25*2/$D87)-INT($E$25*(2-1)/$D87))*$C87 -> 0 | G87: =(INT($E$25*3/$D87)-INT($E$25*(3-1)/$D87))*$C87 -> 1.561 | H87: =(INT($E$25*4/$D87)-INT($E$25*(4-1)/$D87))*$C87 -> 0 | I87: =(INT($E$25*5/$D87)-INT($E$25*(5-1)/$D87))*$C87 -> 1.561 | J87: =(INT($E$25*6/$D87)-INT($E$25*(6-1)/$D87))*$C87 -> 0 | K87: =(INT($E$25*7/$D87)-INT($E$25*(7-1)/$D87))*$C87 -> 1.561 | L87: =(INT($E$25*8/$D87)-INT($E$25*(8-1)/$D87))*$C87 -> 0 | M87: =(INT($E$25*9/$D87)-INT($E$25*(9-1)/$D87))*$C87 -> 1.561 | N87: =(INT($E$25*10/$D87)-INT($E$25*(10-1)/$D87))*$C87 -> 0
B88: Аккумуляторная батарея | C88: 1.696 | D88: 20000 | E88: =(INT($E$25*1/$D88)-INT($E$25*(1-1)/$D88))*$C88 -> 0 | F88: =(INT($E$25*2/$D88)-INT($E$25*(2-1)/$D88))*$C88 -> 0 | G88: =(INT($E$25*3/$D88)-INT($E$25*(3-1)/$D88))*$C88 -> 1.696 | H88: =(INT($E$25*4/$D88)-INT($E$25*(4-1)/$D88))*$C88 -> 0 | I88: =(INT($E$25*5/$D88)-INT($E$25*(5-1)/$D88))*$C88 -> 0 | J88: =(INT($E$25*6/$D88)-INT($E$25*(6-1)/$D88))*$C88 -> 1.696 | K88: =(INT($E$25*7/$D88)-INT($E$25*(7-1)/$D88))*$C88 -> 0 | L88: =(INT($E$25*8/$D88)-INT($E$25*(8-1)/$D88))*$C88 -> 0 | M88: =(INT($E$25*9/$D88)-INT($E$25*(9-1)/$D88))*$C88 -> 1.696 | N88: =(INT($E$25*10/$D88)-INT($E$25*(10-1)/$D88))*$C88 -> 0
B89: Смазка пластичная GRAND EP Lithium Complex №2, флэт-годовой | C89: 1.508 | D89: 7000 | E89: =(INT($E$25*1/$D89)-INT($E$25*(1-1)/$D89))*$C89 -> 1.508 | F89: =(INT($E$25*2/$D89)-INT($E$25*(2-1)/$D89))*$C89 -> 1.508 | G89: =(INT($E$25*3/$D89)-INT($E$25*(3-1)/$D89))*$C89 -> 1.508 | H89: =(INT($E$25*4/$D89)-INT($E$25*(4-1)/$D89))*$C89 -> 1.508 | I89: =(INT($E$25*5/$D89)-INT($E$25*(5-1)/$D89))*$C89 -> 1.508 | J89: =(INT($E$25*6/$D89)-INT($E$25*(6-1)/$D89))*$C89 -> 1.508 | K89: =(INT($E$25*7/$D89)-INT($E$25*(7-1)/$D89))*$C89 -> 1.508 | L89: =(INT($E$25*8/$D89)-INT($E$25*(8-1)/$D89))*$C89 -> 1.508 | M89: =(INT($E$25*9/$D89)-INT($E$25*(9-1)/$D89))*$C89 -> 1.508 | N89: =(INT($E$25*10/$D89)-INT($E$25*(10-1)/$D89))*$C89 -> 1.508
B90: ИТОГО | E90: =SUM(E85:E89) -> 29.143 | F90: =SUM(F85:F89) -> 29.143 | G90: =SUM(G85:G89) -> 32.4 | H90: =SUM(H85:H89) -> 29.143 | I90: =SUM(I85:I89) -> 30.704 | J90: =SUM(J85:J89) -> 30.839 | K90: =SUM(K85:K89) -> 30.704 | L90: =SUM(L85:L89) -> 29.143 | ... N90: =SUM(N85:N89) -> 29.143
B92: ТЕКУЩИЕ РЕМОНТЫ — ТРУДОЗАТРАТЫ (по ресурсу замены)
B93: Наименование | C93: нормо-час/событие | D93: ресурс, м/ч | E93: год 1 | F93: год 2 | G93: год 3 | H93: год 4 | I93: год 5 | J93: год 6 | K93: год 7 | L93: год 8 | M93: год 9 | N93: год 10
B94: Ремонт ковша (GET) | C94: 80 | D94: 7000 | E94: =(INT($E$25*1/$D94)-INT($E$25*(1-1)/$D94))*$C94 -> 80 | F94: =(INT($E$25*2/$D94)-INT($E$25*(2-1)/$D94))*$C94 -> 80 | G94: =(INT($E$25*3/$D94)-INT($E$25*(3-1)/$D94))*$C94 -> 80 | H94: =(INT($E$25*4/$D94)-INT($E$25*(4-1)/$D94))*$C94 -> 80 | I94: =(INT($E$25*5/$D94)-INT($E$25*(5-1)/$D94))*$C94 -> 80 | J94: =(INT($E$25*6/$D94)-INT($E$25*(6-1)/$D94))*$C94 -> 80 | K94: =(INT($E$25*7/$D94)-INT($E$25*(7-1)/$D94))*$C94 -> 80 | L94: =(INT($E$25*8/$D94)-INT($E$25*(8-1)/$D94))*$C94 -> 80 | M94: =(INT($E$25*9/$D94)-INT($E$25*(9-1)/$D94))*$C94 -> 80 | N94: =(INT($E$25*10/$D94)-INT($E$25*(10-1)/$D94))*$C94 -> 80
B95: ИТОГО | E95: =SUM(E94:E94) -> 80 | F95: =SUM(F94:F94) -> 80 | G95: =SUM(G94:G94) -> 80 | H95: =SUM(H94:H94) -> 80 | I95: =SUM(I94:I94) -> 80 | J95: =SUM(J94:J94) -> 80 | K95: =SUM(K94:K94) -> 80 | L95: =SUM(L94:L94) -> 80 | ... N95: =SUM(N94:N94) -> 80
B97: КАПИТАЛЬНЫЕ РЕМОНТЫ (ЦЕХ) — ЗАТРАТЫ НА ЗЧ (по ресурсу до замены узла)
B98: Наименование | C98: стоим.замены,тыс | D98: ресурс, м/ч | E98: год 1 | F98: год 2 | G98: год 3 | H98: год 4 | I98: год 5 | J98: год 6 | K98: год 7 | L98: год 8 | M98: год 9 | N98: год 10
B99: Капитальный ремонт двигателя | C99: 326.279 | D99: 15000 | E99: =(INT($E$25*1/$D99)-INT($E$25*(1-1)/$D99))*$C99 -> 0 | F99: =(INT($E$25*2/$D99)-INT($E$25*(2-1)/$D99))*$C99 -> 0 | G99: =(INT($E$25*3/$D99)-INT($E$25*(3-1)/$D99))*$C99 -> 326.279 | H99: =(INT($E$25*4/$D99)-INT($E$25*(4-1)/$D99))*$C99 -> 0 | I99: =(INT($E$25*5/$D99)-INT($E$25*(5-1)/$D99))*$C99 -> 326.279 | J99: =(INT($E$25*6/$D99)-INT($E$25*(6-1)/$D99))*$C99 -> 0 | K99: =(INT($E$25*7/$D99)-INT($E$25*(7-1)/$D99))*$C99 -> 326.279 | L99: =(INT($E$25*8/$D99)-INT($E$25*(8-1)/$D99))*$C99 -> 0 | M99: =(INT($E$25*9/$D99)-INT($E$25*(9-1)/$D99))*$C99 -> 326.279 | N99: =(INT($E$25*10/$D99)-INT($E$25*(10-1)/$D99))*$C99 -> 0
B100: Ходовой мотор-редуктор | C100: 22 | D100: 15000 | E100: =(INT($E$25*1/$D100)-INT($E$25*(1-1)/$D100))*$C100 -> 0 | F100: =(INT($E$25*2/$D100)-INT($E$25*(2-1)/$D100))*$C100 -> 0 | G100: =(INT($E$25*3/$D100)-INT($E$25*(3-1)/$D100))*$C100 -> 22 | H100: =(INT($E$25*4/$D100)-INT($E$25*(4-1)/$D100))*$C100 -> 0 | I100: =(INT($E$25*5/$D100)-INT($E$25*(5-1)/$D100))*$C100 -> 22 | J100: =(INT($E$25*6/$D100)-INT($E$25*(6-1)/$D100))*$C100 -> 0 | K100: =(INT($E$25*7/$D100)-INT($E$25*(7-1)/$D100))*$C100 -> 22 | L100: =(INT($E$25*8/$D100)-INT($E$25*(8-1)/$D100))*$C100 -> 0 | M100: =(INT($E$25*9/$D100)-INT($E$25*(9-1)/$D100))*$C100 -> 22 | N100: =(INT($E$25*10/$D100)-INT($E$25*(10-1)/$D100))*$C100 -> 0
B101: Редуктор хода | C101: 72.11 | D101: 15000 | E101: =(INT($E$25*1/$D101)-INT($E$25*(1-1)/$D101))*$C101 -> 0 | F101: =(INT($E$25*2/$D101)-INT($E$25*(2-1)/$D101))*$C101 -> 0 | G101: =(INT($E$25*3/$D101)-INT($E$25*(3-1)/$D101))*$C101 -> 72.11 | H101: =(INT($E$25*4/$D101)-INT($E$25*(4-1)/$D101))*$C101 -> 0 | I101: =(INT($E$25*5/$D101)-INT($E$25*(5-1)/$D101))*$C101 -> 72.11 | J101: =(INT($E$25*6/$D101)-INT($E$25*(6-1)/$D101))*$C101 -> 0 | K101: =(INT($E$25*7/$D101)-INT($E$25*(7-1)/$D101))*$C101 -> 72.11 | L101: =(INT($E$25*8/$D101)-INT($E$25*(8-1)/$D101))*$C101 -> 0 | M101: =(INT($E$25*9/$D101)-INT($E$25*(9-1)/$D101))*$C101 -> 72.11 | N101: =(INT($E$25*10/$D101)-INT($E$25*(10-1)/$D101))*$C101 -> 0
B102: Ремонт форсунок | C102: 15.514 | D102: 10000 | E102: =(INT($E$25*1/$D102)-INT($E$25*(1-1)/$D102))*$C102 -> 0 | F102: =(INT($E$25*2/$D102)-INT($E$25*(2-1)/$D102))*$C102 -> 15.514 | G102: =(INT($E$25*3/$D102)-INT($E$25*(3-1)/$D102))*$C102 -> 15.514 | H102: =(INT($E$25*4/$D102)-INT($E$25*(4-1)/$D102))*$C102 -> 0 | I102: =(INT($E$25*5/$D102)-INT($E$25*(5-1)/$D102))*$C102 -> 15.514 | J102: =(INT($E$25*6/$D102)-INT($E$25*(6-1)/$D102))*$C102 -> 15.514 | K102: =(INT($E$25*7/$D102)-INT($E$25*(7-1)/$D102))*$C102 -> 0 | L102: =(INT($E$25*8/$D102)-INT($E$25*(8-1)/$D102))*$C102 -> 15.514 | M102: =(INT($E$25*9/$D102)-INT($E$25*(9-1)/$D102))*$C102 -> 15.514 | N102: =(INT($E$25*10/$D102)-INT($E$25*(10-1)/$D102))*$C102 -> 15.514
B103: Стартер | C103: 9.415 | D103: 10000 | E103: =(INT($E$25*1/$D103)-INT($E$25*(1-1)/$D103))*$C103 -> 0 | F103: =(INT($E$25*2/$D103)-INT($E$25*(2-1)/$D103))*$C103 -> 9.415 | G103: =(INT($E$25*3/$D103)-INT($E$25*(3-1)/$D103))*$C103 -> 9.415 | H103: =(INT($E$25*4/$D103)-INT($E$25*(4-1)/$D103))*$C103 -> 0 | I103: =(INT($E$25*5/$D103)-INT($E$25*(5-1)/$D103))*$C103 -> 9.415 | J103: =(INT($E$25*6/$D103)-INT($E$25*(6-1)/$D103))*$C103 -> 9.415 | K103: =(INT($E$25*7/$D103)-INT($E$25*(7-1)/$D103))*$C103 -> 0 | L103: =(INT($E$25*8/$D103)-INT($E$25*(8-1)/$D103))*$C103 -> 9.415 | M103: =(INT($E$25*9/$D103)-INT($E$25*(9-1)/$D103))*$C103 -> 9.415 | N103: =(INT($E$25*10/$D103)-INT($E$25*(10-1)/$D103))*$C103 -> 9.415
B104: Цилиндр стрелы | C104: 28.5 | D104: 15000 | E104: =(INT($E$25*1/$D104)-INT($E$25*(1-1)/$D104))*$C104 -> 0 | F104: =(INT($E$25*2/$D104)-INT($E$25*(2-1)/$D104))*$C104 -> 0 | G104: =(INT($E$25*3/$D104)-INT($E$25*(3-1)/$D104))*$C104 -> 28.5 | H104: =(INT($E$25*4/$D104)-INT($E$25*(4-1)/$D104))*$C104 -> 0 | I104: =(INT($E$25*5/$D104)-INT($E$25*(5-1)/$D104))*$C104 -> 28.5 | J104: =(INT($E$25*6/$D104)-INT($E$25*(6-1)/$D104))*$C104 -> 0 | K104: =(INT($E$25*7/$D104)-INT($E$25*(7-1)/$D104))*$C104 -> 28.5 | L104: =(INT($E$25*8/$D104)-INT($E$25*(8-1)/$D104))*$C104 -> 0 | M104: =(INT($E$25*9/$D104)-INT($E$25*(9-1)/$D104))*$C104 -> 28.5 | N104: =(INT($E$25*10/$D104)-INT($E$25*(10-1)/$D104))*$C104 -> 0
B105: Цилиндр рукояти | C105: 18 | D105: 15000 | E105: =(INT($E$25*1/$D105)-INT($E$25*(1-1)/$D105))*$C105 -> 0 | F105: =(INT($E$25*2/$D105)-INT($E$25*(2-1)/$D105))*$C105 -> 0 | G105: =(INT($E$25*3/$D105)-INT($E$25*(3-1)/$D105))*$C105 -> 18 | H105: =(INT($E$25*4/$D105)-INT($E$25*(4-1)/$D105))*$C105 -> 0 | I105: =(INT($E$25*5/$D105)-INT($E$25*(5-1)/$D105))*$C105 -> 18 | J105: =(INT($E$25*6/$D105)-INT($E$25*(6-1)/$D105))*$C105 -> 0 | K105: =(INT($E$25*7/$D105)-INT($E$25*(7-1)/$D105))*$C105 -> 18 | L105: =(INT($E$25*8/$D105)-INT($E$25*(8-1)/$D105))*$C105 -> 0 | M105: =(INT($E$25*9/$D105)-INT($E$25*(9-1)/$D105))*$C105 -> 18 | N105: =(INT($E$25*10/$D105)-INT($E$25*(10-1)/$D105))*$C105 -> 0
B106: Цилиндр ковша (левый) | C106: 11.5 | D106: 15000 | E106: =(INT($E$25*1/$D106)-INT($E$25*(1-1)/$D106))*$C106 -> 0 | F106: =(INT($E$25*2/$D106)-INT($E$25*(2-1)/$D106))*$C106 -> 0 | G106: =(INT($E$25*3/$D106)-INT($E$25*(3-1)/$D106))*$C106 -> 11.5 | H106: =(INT($E$25*4/$D106)-INT($E$25*(4-1)/$D106))*$C106 -> 0 | I106: =(INT($E$25*5/$D106)-INT($E$25*(5-1)/$D106))*$C106 -> 11.5 | J106: =(INT($E$25*6/$D106)-INT($E$25*(6-1)/$D106))*$C106 -> 0 | K106: =(INT($E$25*7/$D106)-INT($E$25*(7-1)/$D106))*$C106 -> 11.5 | L106: =(INT($E$25*8/$D106)-INT($E$25*(8-1)/$D106))*$C106 -> 0 | M106: =(INT($E$25*9/$D106)-INT($E$25*(9-1)/$D106))*$C106 -> 11.5 | N106: =(INT($E$25*10/$D106)-INT($E$25*(10-1)/$D106))*$C106 -> 0
B107: Цилиндр ковша (правый) | C107: 11.5 | D107: 15000 | E107: =(INT($E$25*1/$D107)-INT($E$25*(1-1)/$D107))*$C107 -> 0 | F107: =(INT($E$25*2/$D107)-INT($E$25*(2-1)/$D107))*$C107 -> 0 | G107: =(INT($E$25*3/$D107)-INT($E$25*(3-1)/$D107))*$C107 -> 11.5 | H107: =(INT($E$25*4/$D107)-INT($E$25*(4-1)/$D107))*$C107 -> 0 | I107: =(INT($E$25*5/$D107)-INT($E$25*(5-1)/$D107))*$C107 -> 11.5 | J107: =(INT($E$25*6/$D107)-INT($E$25*(6-1)/$D107))*$C107 -> 0 | K107: =(INT($E$25*7/$D107)-INT($E$25*(7-1)/$D107))*$C107 -> 11.5 | L107: =(INT($E$25*8/$D107)-INT($E$25*(8-1)/$D107))*$C107 -> 0 | M107: =(INT($E$25*9/$D107)-INT($E$25*(9-1)/$D107))*$C107 -> 11.5 | N107: =(INT($E$25*10/$D107)-INT($E$25*(10-1)/$D107))*$C107 -> 0
B108: Двигатель поворота | C108: 38 | D108: 15000 | E108: =(INT($E$25*1/$D108)-INT($E$25*(1-1)/$D108))*$C108 -> 0 | F108: =(INT($E$25*2/$D108)-INT($E$25*(2-1)/$D108))*$C108 -> 0 | G108: =(INT($E$25*3/$D108)-INT($E$25*(3-1)/$D108))*$C108 -> 38 | H108: =(INT($E$25*4/$D108)-INT($E$25*(4-1)/$D108))*$C108 -> 0 | I108: =(INT($E$25*5/$D108)-INT($E$25*(5-1)/$D108))*$C108 -> 38 | J108: =(INT($E$25*6/$D108)-INT($E$25*(6-1)/$D108))*$C108 -> 0 | K108: =(INT($E$25*7/$D108)-INT($E$25*(7-1)/$D108))*$C108 -> 38 | L108: =(INT($E$25*8/$D108)-INT($E$25*(8-1)/$D108))*$C108 -> 0 | M108: =(INT($E$25*9/$D108)-INT($E$25*(9-1)/$D108))*$C108 -> 38 | N108: =(INT($E$25*10/$D108)-INT($E$25*(10-1)/$D108))*$C108 -> 0
B109: Поворотный редуктор | C109: 56 | D109: 15000 | E109: =(INT($E$25*1/$D109)-INT($E$25*(1-1)/$D109))*$C109 -> 0 | F109: =(INT($E$25*2/$D109)-INT($E$25*(2-1)/$D109))*$C109 -> 0 | G109: =(INT($E$25*3/$D109)-INT($E$25*(3-1)/$D109))*$C109 -> 56 | H109: =(INT($E$25*4/$D109)-INT($E$25*(4-1)/$D109))*$C109 -> 0 | I109: =(INT($E$25*5/$D109)-INT($E$25*(5-1)/$D109))*$C109 -> 56 | J109: =(INT($E$25*6/$D109)-INT($E$25*(6-1)/$D109))*$C109 -> 0 | K109: =(INT($E$25*7/$D109)-INT($E$25*(7-1)/$D109))*$C109 -> 56 | L109: =(INT($E$25*8/$D109)-INT($E$25*(8-1)/$D109))*$C109 -> 0 | M109: =(INT($E$25*9/$D109)-INT($E$25*(9-1)/$D109))*$C109 -> 56 | N109: =(INT($E$25*10/$D109)-INT($E$25*(10-1)/$D109))*$C109 -> 0
B110: Центральный поворотный узел | C110: 26.5 | D110: 25000 | E110: =(INT($E$25*1/$D110)-INT($E$25*(1-1)/$D110))*$C110 -> 0 | F110: =(INT($E$25*2/$D110)-INT($E$25*(2-1)/$D110))*$C110 -> 0 | G110: =(INT($E$25*3/$D110)-INT($E$25*(3-1)/$D110))*$C110 -> 0 | H110: =(INT($E$25*4/$D110)-INT($E$25*(4-1)/$D110))*$C110 -> 26.5 | I110: =(INT($E$25*5/$D110)-INT($E$25*(5-1)/$D110))*$C110 -> 0 | J110: =(INT($E$25*6/$D110)-INT($E$25*(6-1)/$D110))*$C110 -> 0 | K110: =(INT($E$25*7/$D110)-INT($E$25*(7-1)/$D110))*$C110 -> 0 | L110: =(INT($E$25*8/$D110)-INT($E$25*(8-1)/$D110))*$C110 -> 26.5 | M110: =(INT($E$25*9/$D110)-INT($E$25*(9-1)/$D110))*$C110 -> 0 | N110: =(INT($E$25*10/$D110)-INT($E$25*(10-1)/$D110))*$C110 -> 0
B111: Опора поворотного устройства | C111: 62.5 | D111: 25000 | E111: =(INT($E$25*1/$D111)-INT($E$25*(1-1)/$D111))*$C111 -> 0 | F111: =(INT($E$25*2/$D111)-INT($E$25*(2-1)/$D111))*$C111 -> 0 | G111: =(INT($E$25*3/$D111)-INT($E$25*(3-1)/$D111))*$C111 -> 0 | H111: =(INT($E$25*4/$D111)-INT($E$25*(4-1)/$D111))*$C111 -> 62.5 | I111: =(INT($E$25*5/$D111)-INT($E$25*(5-1)/$D111))*$C111 -> 0 | J111: =(INT($E$25*6/$D111)-INT($E$25*(6-1)/$D111))*$C111 -> 0 | K111: =(INT($E$25*7/$D111)-INT($E$25*(7-1)/$D111))*$C111 -> 0 | L111: =(INT($E$25*8/$D111)-INT($E$25*(8-1)/$D111))*$C111 -> 62.5 | M111: =(INT($E$25*9/$D111)-INT($E$25*(9-1)/$D111))*$C111 -> 0 | N111: =(INT($E$25*10/$D111)-INT($E$25*(10-1)/$D111))*$C111 -> 0
B112: ИТОГО | E112: =SUM(E99:E111) -> 0 | F112: =SUM(F99:F111) -> 24.929 | G112: =SUM(G99:G111) -> 608.818 | H112: =SUM(H99:H111) -> 89 | I112: =SUM(I99:I111) -> 608.818 | J112: =SUM(J99:J111) -> 24.929 | K112: =SUM(K99:K111) -> 583.889 | L112: =SUM(L99:L111) -> 113.929 | ... N112: =SUM(N99:N111) -> 24.929
B114: КАПИТАЛЬНЫЕ РЕМОНТЫ (ЦЕХ) — ТРУДОЗАТРАТЫ (по ресурсу до замены узла)
B115: Наименование | C115: нормо-час/событие | D115: ресурс, м/ч | E115: год 1 | F115: год 2 | G115: год 3 | H115: год 4 | I115: год 5 | J115: год 6 | K115: год 7 | L115: год 8 | M115: год 9 | N115: год 10
B116: Ремонт двигателя, ходовой части | C116: 200 | D116: 15000 | E116: =(INT($E$25*1/$D116)-INT($E$25*(1-1)/$D116))*$C116 -> 0 | F116: =(INT($E$25*2/$D116)-INT($E$25*(2-1)/$D116))*$C116 -> 0 | G116: =(INT($E$25*3/$D116)-INT($E$25*(3-1)/$D116))*$C116 -> 200 | H116: =(INT($E$25*4/$D116)-INT($E$25*(4-1)/$D116))*$C116 -> 0 | I116: =(INT($E$25*5/$D116)-INT($E$25*(5-1)/$D116))*$C116 -> 200 | J116: =(INT($E$25*6/$D116)-INT($E$25*(6-1)/$D116))*$C116 -> 0 | K116: =(INT($E$25*7/$D116)-INT($E$25*(7-1)/$D116))*$C116 -> 200 | L116: =(INT($E$25*8/$D116)-INT($E$25*(8-1)/$D116))*$C116 -> 0 | M116: =(INT($E$25*9/$D116)-INT($E$25*(9-1)/$D116))*$C116 -> 200 | N116: =(INT($E$25*10/$D116)-INT($E$25*(10-1)/$D116))*$C116 -> 0
B117: Ремонт форсунок, стартер | C117: 40 | D117: 10000 | E117: =(INT($E$25*1/$D117)-INT($E$25*(1-1)/$D117))*$C117 -> 0 | F117: =(INT($E$25*2/$D117)-INT($E$25*(2-1)/$D117))*$C117 -> 40 | G117: =(INT($E$25*3/$D117)-INT($E$25*(3-1)/$D117))*$C117 -> 40 | H117: =(INT($E$25*4/$D117)-INT($E$25*(4-1)/$D117))*$C117 -> 0 | I117: =(INT($E$25*5/$D117)-INT($E$25*(5-1)/$D117))*$C117 -> 40 | J117: =(INT($E$25*6/$D117)-INT($E$25*(6-1)/$D117))*$C117 -> 40 | K117: =(INT($E$25*7/$D117)-INT($E$25*(7-1)/$D117))*$C117 -> 0 | L117: =(INT($E$25*8/$D117)-INT($E$25*(8-1)/$D117))*$C117 -> 40 | M117: =(INT($E$25*9/$D117)-INT($E$25*(9-1)/$D117))*$C117 -> 40 | N117: =(INT($E$25*10/$D117)-INT($E$25*(10-1)/$D117))*$C117 -> 40
B118: Ремонт системы подъема (цилиндры) | C118: 80 | D118: 15000 | E118: =(INT($E$25*1/$D118)-INT($E$25*(1-1)/$D118))*$C118 -> 0 | F118: =(INT($E$25*2/$D118)-INT($E$25*(2-1)/$D118))*$C118 -> 0 | G118: =(INT($E$25*3/$D118)-INT($E$25*(3-1)/$D118))*$C118 -> 80 | H118: =(INT($E$25*4/$D118)-INT($E$25*(4-1)/$D118))*$C118 -> 0 | I118: =(INT($E$25*5/$D118)-INT($E$25*(5-1)/$D118))*$C118 -> 80 | J118: =(INT($E$25*6/$D118)-INT($E$25*(6-1)/$D118))*$C118 -> 0 | K118: =(INT($E$25*7/$D118)-INT($E$25*(7-1)/$D118))*$C118 -> 80 | L118: =(INT($E$25*8/$D118)-INT($E$25*(8-1)/$D118))*$C118 -> 0 | M118: =(INT($E$25*9/$D118)-INT($E$25*(9-1)/$D118))*$C118 -> 80 | N118: =(INT($E$25*10/$D118)-INT($E$25*(10-1)/$D118))*$C118 -> 0
B119: Ремонт системы поворота | C119: 60 | D119: 15000 | E119: =(INT($E$25*1/$D119)-INT($E$25*(1-1)/$D119))*$C119 -> 0 | F119: =(INT($E$25*2/$D119)-INT($E$25*(2-1)/$D119))*$C119 -> 0 | G119: =(INT($E$25*3/$D119)-INT($E$25*(3-1)/$D119))*$C119 -> 60 | H119: =(INT($E$25*4/$D119)-INT($E$25*(4-1)/$D119))*$C119 -> 0 | I119: =(INT($E$25*5/$D119)-INT($E$25*(5-1)/$D119))*$C119 -> 60 | J119: =(INT($E$25*6/$D119)-INT($E$25*(6-1)/$D119))*$C119 -> 0 | K119: =(INT($E$25*7/$D119)-INT($E$25*(7-1)/$D119))*$C119 -> 60 | L119: =(INT($E$25*8/$D119)-INT($E$25*(8-1)/$D119))*$C119 -> 0 | M119: =(INT($E$25*9/$D119)-INT($E$25*(9-1)/$D119))*$C119 -> 60 | N119: =(INT($E$25*10/$D119)-INT($E$25*(10-1)/$D119))*$C119 -> 0
B120: Ремонт центр. поворотного узла, ОПУ | C120: 80 | D120: 25000 | E120: =(INT($E$25*1/$D120)-INT($E$25*(1-1)/$D120))*$C120 -> 0 | F120: =(INT($E$25*2/$D120)-INT($E$25*(2-1)/$D120))*$C120 -> 0 | G120: =(INT($E$25*3/$D120)-INT($E$25*(3-1)/$D120))*$C120 -> 0 | H120: =(INT($E$25*4/$D120)-INT($E$25*(4-1)/$D120))*$C120 -> 80 | I120: =(INT($E$25*5/$D120)-INT($E$25*(5-1)/$D120))*$C120 -> 0 | J120: =(INT($E$25*6/$D120)-INT($E$25*(6-1)/$D120))*$C120 -> 0 | K120: =(INT($E$25*7/$D120)-INT($E$25*(7-1)/$D120))*$C120 -> 0 | L120: =(INT($E$25*8/$D120)-INT($E$25*(8-1)/$D120))*$C120 -> 80 | M120: =(INT($E$25*9/$D120)-INT($E$25*(9-1)/$D120))*$C120 -> 0 | N120: =(INT($E$25*10/$D120)-INT($E$25*(10-1)/$D120))*$C120 -> 0
B121: ИТОГО | E121: =SUM(E116:E120) -> 0 | F121: =SUM(F116:F120) -> 40 | G121: =SUM(G116:G120) -> 380 | H121: =SUM(H116:H120) -> 80 | I121: =SUM(I116:I120) -> 380 | J121: =SUM(J116:J120) -> 40 | K121: =SUM(K116:K120) -> 340 | L121: =SUM(L116:L120) -> 120 | ... N121: =SUM(N116:N120) -> 40
B123: Все таблицы — ПО ГОДАМ. Затраты и трудозатраты считаются РАЗДЕЛЬНО для ТО / текущих ремонтов / капитальных (цеховых) ремонтов, каждая — по полному списку узлов из файла поставщика (без группировки). Капремонты и текущие ремонты по узлам считаются ПО ПЕРИОДИЧНОСТИ: у каждого узла — стоимость/трудоёмкость замены и ресурс (м/ч); затрата возникает в те годы, когда наработка пересекает кратное ресурсу значение (число замен = ЦЕЛОЕ(наработка×год/ресурс) − ЦЕЛОЕ(наработка×(год−1)/ресурс)). «Коэффициент поглощения» < 1 учитывает восстановление/поглощение узлов (у поставщика = 1).

Sheet Поставщик 4
B1: ШАБЛОН ДАННЫХ ПОСТАВЩИКА — ВАРИАНТ 4
B2: Полные модели ТО и Ремонтов ПО ГОДАМ (затраты и трудозатраты — раздельно для ТО / текущих / капитальных ремонтов). Зелёное — авто; сводка тянется в «Данные по годам».
B4: Экскаватор: | E4: ='Ввод данных'!G7 -> Sany SY2000 АСТ
B5: Валюта затрат ТОиР: | D5: USD
B6: Показатель | C6: Ед. | E6: год 1 | F6: год 2 | G6: год 3 | H6: год 4 | I6: год 5 | J6: год 6 | K6: год 7 | L6: год 8 | M6: год 9 | N6: год 10
B7: СВОДКА ПО ГОДАМ (зелёное — авто из моделей ниже; тянется в расчёт)
B8: Простои на ТО | C8: ч/год | E8: =E37 -> 273.21 | F8: =F37 -> 273.21 | G8: =G37 -> 273.21 | H8: =H37 -> 273.21 | I8: =I37 -> 273.21 | J8: =J37 -> 273.21 | K8: =K37 -> 273.21 | L8: =L37 -> 273.21 | ... N8: =N37 -> 273.21
B9: Простои в текущих + капитальных ремонтах | C9: ч/год | E9: =E80 -> 786.13 | F9: =F80 -> 1924.36 | G9: =G80 -> 1682.92 | H9: =H80 -> 2228.84 | I9: =I80 -> 2239.02 | J9: =J80 -> 1794.52 | K9: =K80 -> 2025.05 | L9: =L80 -> 1519.78 | ... N9: =N80 -> 1663.35
B10: Ежесменное ТО (20 мин/смену) | C10: ч/год | E10: =('Параметры'!C26-E8-E9)/'Параметры'!C33*20/60 -> 213.90722 | F10: =('Параметры'!C26-F8-F9)/'Параметры'!C33*20/60 -> 182.28972 | G10: =('Параметры'!C26-G8-G9)/'Параметры'!C33*20/60 -> 188.99639 | H10: =('Параметры'!C26-H8-H9)/'Параметры'!C33*20/60 -> 173.83194 | I10: =('Параметры'!C26-I8-I9)/'Параметры'!C33*20/60 -> 173.54917 | J10: =('Параметры'!C26-J8-J9)/'Параметры'!C33*20/60 -> 185.89639 | K10: =('Параметры'!C26-K8-K9)/'Параметры'!C33*20/60 -> 179.49278 | L10: =('Параметры'!C26-L8-L9)/'Параметры'!C33*20/60 -> 193.52806 | M10: =('Параметры'!C26-M8-M9)/'Параметры'!C33*20/60 -> 167.18333 | N10: =('Параметры'!C26-N8-N9)/'Параметры'!C33*20/60 -> 189.54
B11: КТГ (авто) = (8760 − простои)/8760 | C11: коэф. | E11: =('Параметры'!C26-E8-E9-E10)/'Параметры'!C26 -> 0.85465214 | F11: =('Параметры'!C26-F8-F9-F10)/'Параметры'!C26 -> 0.72832652 | G11: =('Параметры'!C26-G8-G9-G10)/'Параметры'!C26 -> 0.75512256 | H11: =('Параметры'!C26-H8-H9-H10)/'Параметры'!C26 -> 0.69453402 | I11: =('Параметры'!C26-I8-I9-I10)/'Параметры'!C26 -> 0.6934042 | J11: =('Параметры'!C26-J8-J9-J10)/'Параметры'!C26 -> 0.74273671 | K11: =('Параметры'!C26-K8-K9-K10)/'Параметры'!C26 -> 0.71715151 | L11: =('Параметры'!C26-L8-L9-L10)/'Параметры'!C26 -> 0.77322853 | M11: =('Параметры'!C26-M8-M9-M10)/'Параметры'!C26 -> 0.66796994 | N11: =('Параметры'!C26-N8-N9-N10)/'Параметры'!C26 -> 0.75729452
B12: Затраты на ТО (ЗЧ, из каталога) | C12: тыс/год | E12: =E75 -> 107.51972 | F12: =F75 -> 107.51972 | G12: =G75 -> 107.51972 | H12: =H75 -> 107.51972 | I12: =I75 -> 107.51972 | J12: =J75 -> 107.51972 | K12: =K75 -> 107.51972 | L12: =L75 -> 107.51972 | ... N12: =N75 -> 107.51972
B13: Затраты на текущие ремонты (ЗЧ) | C13: тыс/год | E13: =E90*$E$81 -> 29.143 | F13: =F90*$E$81 -> 29.143 | G13: =G90*$E$81 -> 32.4 | H13: =H90*$E$81 -> 29.143 | I13: =I90*$E$81 -> 30.704 | J13: =J90*$E$81 -> 30.839 | K13: =K90*$E$81 -> 30.704 | L13: =L90*$E$81 -> 29.143 | ... N13: =N90*$E$81 -> 29.143
B14: Затраты на капитальные ремонты (ЗЧ, цех) | C14: тыс/год | E14: =E112*$E$81 -> 0 | F14: =F112*$E$81 -> 24.929 | G14: =G112*$E$81 -> 608.818 | H14: =H112*$E$81 -> 89 | I14: =I112*$E$81 -> 608.818 | J14: =J112*$E$81 -> 24.929 | K14: =K112*$E$81 -> 583.889 | L14: =L112*$E$81 -> 113.929 | ... N14: =N112*$E$81 -> 24.929
B15: Трудозатраты на ТО | C15: ч-час/год | E15: =E43 -> 546.42 | F15: =F43 -> 546.42 | G15: =G43 -> 546.42 | H15: =H43 -> 546.42 | I15: =I43 -> 546.42 | J15: =J43 -> 546.42 | K15: =K43 -> 546.42 | L15: =L43 -> 546.42 | ... N15: =N43 -> 546.42
B16: Трудозатраты на текущие ремонты | C16: ч-час/год | E16: =E95*$E$81 -> 80 | F16: =F95*$E$81 -> 80 | G16: =G95*$E$81 -> 80 | H16: =H95*$E$81 -> 80 | I16: =I95*$E$81 -> 80 | J16: =J95*$E$81 -> 80 | K16: =K95*$E$81 -> 80 | L16: =L95*$E$81 -> 80 | ... N16: =N95*$E$81 -> 80
B17: Трудозатраты на капитальные ремонты (цех) | C17: чел-час/год | E17: =E121*$E$81 -> 0 | F17: =F121*$E$81 -> 40 | G17: =G121*$E$81 -> 380 | H17: =H121*$E$81 -> 80 | I17: =I121*$E$81 -> 380 | J17: =J121*$E$81 -> 40 | K17: =K121*$E$81 -> 340 | L17: =L121*$E$81 -> 120 | ... N17: =N121*$E$81 -> 40
B18: Сервис ТО (авто) = трудозатраты ТО × ставка | C18: тыс/год | E18: =E15*$E$77/1000 -> 27.321 | F18: =F15*$E$77/1000 -> 27.321 | G18: =G15*$E$77/1000 -> 27.321 | H18: =H15*$E$77/1000 -> 27.321 | I18: =I15*$E$77/1000 -> 27.321 | J18: =J15*$E$77/1000 -> 27.321 | K18: =K15*$E$77/1000 -> 27.321 | L18: =L15*$E$77/1000 -> 27.321 | ... N18: =N15*$E$77/1000 -> 27.321
B19: Сервис текущих ремонтов (авто) | C19: тыс/год | E19: =E16*$E$77/1000 -> 4 | F19: =F16*$E$77/1000 -> 4 | G19: =G16*$E$77/1000 -> 4 | H19: =H16*$E$77/1000 -> 4 | I19: =I16*$E$77/1000 -> 4 | J19: =J16*$E$77/1000 -> 4 | K19: =K16*$E$77/1000 -> 4 | L19: =L16*$E$77/1000 -> 4 | ... N19: =N16*$E$77/1000 -> 4
B20: Сервис капитальных ремонтов (цех, авто) | C20: тыс/год | E20: =E17*$E$77/1000 -> 0 | F20: =F17*$E$77/1000 -> 2 | G20: =G17*$E$77/1000 -> 19 | H20: =H17*$E$77/1000 -> 4 | I20: =I17*$E$77/1000 -> 19 | J20: =J17*$E$77/1000 -> 2 | K20: =K17*$E$77/1000 -> 17 | L20: =L17*$E$77/1000 -> 6 | ... N20: =N17*$E$77/1000 -> 2
B21: ИТОГО ТОиР (авто) → «Данные по годам» | C21: тыс/год | E21: =E12+E13+E14+E18+E19+E20 -> 167.98372 | F21: =F12+F13+F14+F18+F19+F20 -> 194.91272 | G21: =G12+G13+G14+G18+G19+G20 -> 799.05872 | H21: =H12+H13+H14+H18+H19+H20 -> 260.98372 | I21: =I12+I13+I14+I18+I19+I20 -> 797.36272 | J21: =J12+J13+J14+J18+J19+J20 -> 196.60872 | K21: =K12+K13+K14+K18+K19+K20 -> 770.43372 | L21: =L12+L13+L14+L18+L19+L20 -> 287.91272 | ... N21: =N12+N13+N14+N18+N19+N20 -> 194.91272
B22: Удельный расход ДТ | C22: кг/час | E22: 92.04 | F22: 92.04 | G22: 92.04 | H22: 92.04 | I22: 92.04 | J22: 92.04 | K22: 92.04 | L22: 92.04 | M22: 92.04 | N22: 92.04
B23: Расходники на ковш | C23: руб/м³ | E23: 0.87 | F23: 0.87 | G23: 0.87 | H23: 0.87 | I23: 0.87 | J23: 0.87 | K23: 0.87 | L23: 0.87 | M23: 0.87 | N23: 0.87
B24: РАСЧЁТ ТО (по интервалам обслуживания), ПО ГОДАМ
B25: Наработка по годам | C25: м/час | E25: 7000 | F25: 7000 | G25: 7000 | H25: 7000 | I25: 7000 | J25: 7000 | K25: 7000 | L25: 7000 | M25: 7000 | N25: 7000
B26: Вид ТО | C26: интервал | D26: длит.простоя | E26: персонал
B27: ТО-1 | C27: 500 | D27: 10.2 | E27: 2
B28: ТО-2 | C28: 1000 | D28: 9.4 | E28: 2
B29: ТО-3 | C29: 2000 | D29: 12.4 | E29: 2
B30: ТО-4 | C30: 4000 | D30: 7.8 | E30: 2
B31: ТО-5 | C31: 5000 | D31: 5.4 | E31: 2
B32: ТО-1: простои, ч/год | C32: #,##0 | E32: =(E$25/$C27)*$D27 -> 142.8 | F32: =(F$25/$C27)*$D27 -> 142.8 | G32: =(G$25/$C27)*$D27 -> 142.8 | H32: =(H$25/$C27)*$D27 -> 142.8 | I32: =(I$25/$C27)*$D27 -> 142.8 | J32: =(J$25/$C27)*$D27 -> 142.8 | K32: =(K$25/$C27)*$D27 -> 142.8 | L32: =(L$25/$C27)*$D27 -> 142.8 | ... N32: =(N$25/$C27)*$D27 -> 142.8
B33: ТО-2: простои, ч/год | C33: #,##0 | E33: =(E$25/$C28)*$D28 -> 65.8 | F33: =(F$25/$C28)*$D28 -> 65.8 | G33: =(G$25/$C28)*$D28 -> 65.8 | H33: =(H$25/$C28)*$D28 -> 65.8 | I33: =(I$25/$C28)*$D28 -> 65.8 | J33: =(J$25/$C28)*$D28 -> 65.8 | K33: =(K$25/$C28)*$D28 -> 65.8 | L33: =(L$25/$C28)*$D28 -> 65.8 | ... N33: =(N$25/$C28)*$D28 -> 65.8
B34: ТО-3: простои, ч/год | C34: #,##0 | E34: =(E$25/$C29)*$D29 -> 43.4 | F34: =(F$25/$C29)*$D29 -> 43.4 | G34: =(G$25/$C29)*$D29 -> 43.4 | H34: =(H$25/$C29)*$D29 -> 43.4 | I34: =(I$25/$C29)*$D29 -> 43.4 | J34: =(J$25/$C29)*$D29 -> 43.4 | K34: =(K$25/$C29)*$D29 -> 43.4 | L34: =(L$25/$C29)*$D29 -> 43.4 | ... N34: =(N$25/$C29)*$D29 -> 43.4
B35: ТО-4: простои, ч/год | C35: #,##0 | E35: =(E$25/$C30)*$D30 -> 13.65 | F35: =(F$25/$C30)*$D30 -> 13.65 | G35: =(G$25/$C30)*$D30 -> 13.65 | H35: =(H$25/$C30)*$D30 -> 13.65 | I35: =(I$25/$C30)*$D30 -> 13.65 | J35: =(J$25/$C30)*$D30 -> 13.65 | K35: =(K$25/$C30)*$D30 -> 13.65 | L35: =(L$25/$C30)*$D30 -> 13.65 | ... N35: =(N$25/$C30)*$D30 -> 13.65
B36: ТО-5: простои, ч/год | C36: #,##0 | E36: =(E$25/$C31)*$D31 -> 7.56 | F36: =(F$25/$C31)*$D31 -> 7.56 | G36: =(G$25/$C31)*$D31 -> 7.56 | H36: =(H$25/$C31)*$D31 -> 7.56 | I36: =(I$25/$C31)*$D31 -> 7.56 | J36: =(J$25/$C31)*$D31 -> 7.56 | K36: =(K$25/$C31)*$D31 -> 7.56 | L36: =(L$25/$C31)*$D31 -> 7.56 | ... N36: =(N$25/$C31)*$D31 -> 7.56
B37: Итого простои ТО, ч/год | C37: ч/год | E37: =SUM(E32:E36) -> 273.21 | F37: =SUM(F32:F36) -> 273.21 | G37: =SUM(G32:G36) -> 273.21 | H37: =SUM(H32:H36) -> 273.21 | I37: =SUM(I32:I36) -> 273.21 | J37: =SUM(J32:J36) -> 273.21 | K37: =SUM(K32:K36) -> 273.21 | L37: =SUM(L32:L36) -> 273.21 | ... N37: =SUM(N32:N36) -> 273.21
B38: ТО-1: ч·часы/год | C38: #,##0 | E38: =E32*$E27 -> 285.6 | F38: =F32*$E27 -> 285.6 | G38: =G32*$E27 -> 285.6 | H38: =H32*$E27 -> 285.6 | I38: =I32*$E27 -> 285.6 | J38: =J32*$E27 -> 285.6 | K38: =K32*$E27 -> 285.6 | L38: =L32*$E27 -> 285.6 | ... N38: =N32*$E27 -> 285.6
B39: ТО-2: ч·часы/год | C39: #,##0 | E39: =E33*$E28 -> 131.6 | F39: =F33*$E28 -> 131.6 | G39: =G33*$E28 -> 131.6 | H39: =H33*$E28 -> 131.6 | I39: =I33*$E28 -> 131.6 | J39: =J33*$E28 -> 131.6 | K39: =K33*$E28 -> 131.6 | L39: =L33*$E28 -> 131.6 | ... N39: =N33*$E28 -> 131.6
B40: ТО-3: ч·часы/год | C40: #,##0 | E40: =E34*$E29 -> 86.8 | F40: =F34*$E29 -> 86.8 | G40: =G34*$E29 -> 86.8 | H40: =H34*$E29 -> 86.8 | I40: =I34*$E29 -> 86.8 | J40: =J34*$E29 -> 86.8 | K40: =K34*$E29 -> 86.8 | L40: =L34*$E29 -> 86.8 | ... N40: =N34*$E29 -> 86.8
B41: ТО-4: ч·часы/год | C41: #,##0 | E41: =E35*$E30 -> 27.3 | F41: =F35*$E30 -> 27.3 | G41: =G35*$E30 -> 27.3 | H41: =H35*$E30 -> 27.3 | I41: =I35*$E30 -> 27.3 | J41: =J35*$E30 -> 27.3 | K41: =K35*$E30 -> 27.3 | L41: =L35*$E30 -> 27.3 | ... N41: =N35*$E30 -> 27.3
B42: ТО-5: ч·часы/год | C42: #,##0 | E42: =E36*$E31 -> 15.12 | F42: =F36*$E31 -> 15.12 | G42: =G36*$E31 -> 15.12 | H42: =H36*$E31 -> 15.12 | I42: =I36*$E31 -> 15.12 | J42: =J36*$E31 -> 15.12 | K42: =K36*$E31 -> 15.12 | L42: =L36*$E31 -> 15.12 | ... N42: =N36*$E31 -> 15.12
B43: Итого ч·часы ТО, ч-час/год | C43: ч-час | E43: =SUM(E38:E42) -> 546.42 | F43: =SUM(F38:F42) -> 546.42 | G43: =SUM(G38:G42) -> 546.42 | H43: =SUM(H38:H42) -> 546.42 | I43: =SUM(I38:I42) -> 546.42 | J43: =SUM(J38:J42) -> 546.42 | K43: =SUM(K38:K42) -> 546.42 | L43: =SUM(L38:L42) -> 546.42 | ... N43: =SUM(N38:N42) -> 546.42
B45: КАТАЛОГ ЗАПЧАСТЕЙ ТО (заполняет подрядчик), ПО ГОДАМ
B46: Наименование | C46: цена за ед | D46: кол-во/ТО | E46: год 1 | F46: год 2 | G46: год 3 | H46: год 4 | I46: год 5 | J46: год 6 | K46: год 7 | L46: год 8 | M46: год 9 | N46: год 10 | P46: № ТО
B47: Масляный фильтр | C47: 114.83 | D47: 4 | E47: =(E$25/INDEX($C$27:$C$31,$P47))*D47*C47/1000 -> 6.43048 | F47: =(F$25/INDEX($C$27:$C$31,$P47))*D47*C47/1000 -> 6.43048 | G47: =(G$25/INDEX($C$27:$C$31,$P47))*D47*C47/1000 -> 6.43048 | H47: =(H$25/INDEX($C$27:$C$31,$P47))*D47*C47/1000 -> 6.43048 | I47: =(I$25/INDEX($C$27:$C$31,$P47))*D47*C47/1000 -> 6.43048 | J47: =(J$25/INDEX($C$27:$C$31,$P47))*D47*C47/1000 -> 6.43048 | K47: =(K$25/INDEX($C$27:$C$31,$P47))*D47*C47/1000 -> 6.43048 | L47: =(L$25/INDEX($C$27:$C$31,$P47))*D47*C47/1000 -> 6.43048 | M47: =(M$25/INDEX($C$27:$C$31,$P47))*D47*C47/1000 -> 6.43048 | N47: =(N$25/INDEX($C$27:$C$31,$P47))*D47*C47/1000 -> 6.43048 | P47: 1
B48: Топливный фильтр | C48: 141.33 | D48: 2 | E48: =(E$25/INDEX($C$27:$C$31,$P48))*D48*C48/1000 -> 3.95724 | F48: =(F$25/INDEX($C$27:$C$31,$P48))*D48*C48/1000 -> 3.95724 | G48: =(G$25/INDEX($C$27:$C$31,$P48))*D48*C48/1000 -> 3.95724 | H48: =(H$25/INDEX($C$27:$C$31,$P48))*D48*C48/1000 -> 3.95724 | I48: =(I$25/INDEX($C$27:$C$31,$P48))*D48*C48/1000 -> 3.95724 | J48: =(J$25/INDEX($C$27:$C$31,$P48))*D48*C48/1000 -> 3.95724 | K48: =(K$25/INDEX($C$27:$C$31,$P48))*D48*C48/1000 -> 3.95724 | L48: =(L$25/INDEX($C$27:$C$31,$P48))*D48*C48/1000 -> 3.95724 | M48: =(M$25/INDEX($C$27:$C$31,$P48))*D48*C48/1000 -> 3.95724 | N48: =(N$25/INDEX($C$27:$C$31,$P48))*D48*C48/1000 -> 3.95724 | P48: 1
B49: Масло ДВС | C49: 6.87 | D49: 130 | E49: =(E$25/INDEX($C$27:$C$31,$P49))*D49*C49/1000 -> 12.5034 | F49: =(F$25/INDEX($C$27:$C$31,$P49))*D49*C49/1000 -> 12.5034 | G49: =(G$25/INDEX($C$27:$C$31,$P49))*D49*C49/1000 -> 12.5034 | H49: =(H$25/INDEX($C$27:$C$31,$P49))*D49*C49/1000 -> 12.5034 | I49: =(I$25/INDEX($C$27:$C$31,$P49))*D49*C49/1000 -> 12.5034 | J49: =(J$25/INDEX($C$27:$C$31,$P49))*D49*C49/1000 -> 12.5034 | K49: =(K$25/INDEX($C$27:$C$31,$P49))*D49*C49/1000 -> 12.5034 | L49: =(L$25/INDEX($C$27:$C$31,$P49))*D49*C49/1000 -> 12.5034 | M49: =(M$25/INDEX($C$27:$C$31,$P49))*D49*C49/1000 -> 12.5034 | N49: =(N$25/INDEX($C$27:$C$31,$P49))*D49*C49/1000 -> 12.5034 | P49: 1
B50: Фильтр управляющего контура | C50: 126 | D50: 1 | E50: =(E$25/INDEX($C$27:$C$31,$P50))*D50*C50/1000 -> 1.764 | F50: =(F$25/INDEX($C$27:$C$31,$P50))*D50*C50/1000 -> 1.764 | G50: =(G$25/INDEX($C$27:$C$31,$P50))*D50*C50/1000 -> 1.764 | H50: =(H$25/INDEX($C$27:$C$31,$P50))*D50*C50/1000 -> 1.764 | I50: =(I$25/INDEX($C$27:$C$31,$P50))*D50*C50/1000 -> 1.764 | J50: =(J$25/INDEX($C$27:$C$31,$P50))*D50*C50/1000 -> 1.764 | K50: =(K$25/INDEX($C$27:$C$31,$P50))*D50*C50/1000 -> 1.764 | L50: =(L$25/INDEX($C$27:$C$31,$P50))*D50*C50/1000 -> 1.764 | M50: =(M$25/INDEX($C$27:$C$31,$P50))*D50*C50/1000 -> 1.764 | N50: =(N$25/INDEX($C$27:$C$31,$P50))*D50*C50/1000 -> 1.764 | P50: 1
B51: Сливной фильтр | C51: 30.67 | D51: 2 | E51: =(E$25/INDEX($C$27:$C$31,$P51))*D51*C51/1000 -> 0.85876 | F51: =(F$25/INDEX($C$27:$C$31,$P51))*D51*C51/1000 -> 0.85876 | G51: =(G$25/INDEX($C$27:$C$31,$P51))*D51*C51/1000 -> 0.85876 | H51: =(H$25/INDEX($C$27:$C$31,$P51))*D51*C51/1000 -> 0.85876 | I51: =(I$25/INDEX($C$27:$C$31,$P51))*D51*C51/1000 -> 0.85876 | J51: =(J$25/INDEX($C$27:$C$31,$P51))*D51*C51/1000 -> 0.85876 | K51: =(K$25/INDEX($C$27:$C$31,$P51))*D51*C51/1000 -> 0.85876 | L51: =(L$25/INDEX($C$27:$C$31,$P51))*D51*C51/1000 -> 0.85876 | M51: =(M$25/INDEX($C$27:$C$31,$P51))*D51*C51/1000 -> 0.85876 | N51: =(N$25/INDEX($C$27:$C$31,$P51))*D51*C51/1000 -> 0.85876 | P51: 1
B52: Сливной фильтр насоса | C52: 201 | D52: 3 | E52: =(E$25/INDEX($C$27:$C$31,$P52))*D52*C52/1000 -> 8.442 | F52: =(F$25/INDEX($C$27:$C$31,$P52))*D52*C52/1000 -> 8.442 | G52: =(G$25/INDEX($C$27:$C$31,$P52))*D52*C52/1000 -> 8.442 | H52: =(H$25/INDEX($C$27:$C$31,$P52))*D52*C52/1000 -> 8.442 | I52: =(I$25/INDEX($C$27:$C$31,$P52))*D52*C52/1000 -> 8.442 | J52: =(J$25/INDEX($C$27:$C$31,$P52))*D52*C52/1000 -> 8.442 | K52: =(K$25/INDEX($C$27:$C$31,$P52))*D52*C52/1000 -> 8.442 | L52: =(L$25/INDEX($C$27:$C$31,$P52))*D52*C52/1000 -> 8.442 | M52: =(M$25/INDEX($C$27:$C$31,$P52))*D52*C52/1000 -> 8.442 | N52: =(N$25/INDEX($C$27:$C$31,$P52))*D52*C52/1000 -> 8.442 | P52: 1
B53: Смазка | C53: 12.24 | D53: 200 | E53: =(E$25/INDEX($C$27:$C$31,$P53))*D53*C53/1000 -> 34.272 | F53: =(F$25/INDEX($C$27:$C$31,$P53))*D53*C53/1000 -> 34.272 | G53: =(G$25/INDEX($C$27:$C$31,$P53))*D53*C53/1000 -> 34.272 | H53: =(H$25/INDEX($C$27:$C$31,$P53))*D53*C53/1000 -> 34.272 | I53: =(I$25/INDEX($C$27:$C$31,$P53))*D53*C53/1000 -> 34.272 | J53: =(J$25/INDEX($C$27:$C$31,$P53))*D53*C53/1000 -> 34.272 | K53: =(K$25/INDEX($C$27:$C$31,$P53))*D53*C53/1000 -> 34.272 | L53: =(L$25/INDEX($C$27:$C$31,$P53))*D53*C53/1000 -> 34.272 | M53: =(M$25/INDEX($C$27:$C$31,$P53))*D53*C53/1000 -> 34.272 | N53: =(N$25/INDEX($C$27:$C$31,$P53))*D53*C53/1000 -> 34.272 | P53: 1
B54: Топливный фильтр (ТО-2) | C54: 80.17 | D54: 2 | E54: =(E$25/INDEX($C$27:$C$31,$P54))*D54*C54/1000 -> 1.12238 | F54: =(F$25/INDEX($C$27:$C$31,$P54))*D54*C54/1000 -> 1.12238 | G54: =(G$25/INDEX($C$27:$C$31,$P54))*D54*C54/1000 -> 1.12238 | H54: =(H$25/INDEX($C$27:$C$31,$P54))*D54*C54/1000 -> 1.12238 | I54: =(I$25/INDEX($C$27:$C$31,$P54))*D54*C54/1000 -> 1.12238 | J54: =(J$25/INDEX($C$27:$C$31,$P54))*D54*C54/1000 -> 1.12238 | K54: =(K$25/INDEX($C$27:$C$31,$P54))*D54*C54/1000 -> 1.12238 | L54: =(L$25/INDEX($C$27:$C$31,$P54))*D54*C54/1000 -> 1.12238 | M54: =(M$25/INDEX($C$27:$C$31,$P54))*D54*C54/1000 -> 1.12238 | N54: =(N$25/INDEX($C$27:$C$31,$P54))*D54*C54/1000 -> 1.12238 | P54: 2
B55: Фильтр сапуна топл.бака | C55: 19.17 | D55: 1 | E55: =(E$25/INDEX($C$27:$C$31,$P55))*D55*C55/1000 -> 0.13419 | F55: =(F$25/INDEX($C$27:$C$31,$P55))*D55*C55/1000 -> 0.13419 | G55: =(G$25/INDEX($C$27:$C$31,$P55))*D55*C55/1000 -> 0.13419 | H55: =(H$25/INDEX($C$27:$C$31,$P55))*D55*C55/1000 -> 0.13419 | I55: =(I$25/INDEX($C$27:$C$31,$P55))*D55*C55/1000 -> 0.13419 | J55: =(J$25/INDEX($C$27:$C$31,$P55))*D55*C55/1000 -> 0.13419 | K55: =(K$25/INDEX($C$27:$C$31,$P55))*D55*C55/1000 -> 0.13419 | L55: =(L$25/INDEX($C$27:$C$31,$P55))*D55*C55/1000 -> 0.13419 | M55: =(M$25/INDEX($C$27:$C$31,$P55))*D55*C55/1000 -> 0.13419 | N55: =(N$25/INDEX($C$27:$C$31,$P55))*D55*C55/1000 -> 0.13419 | P55: 2
B56: Фильтр сапуна гидробака | C56: 19.17 | D56: 2 | E56: =(E$25/INDEX($C$27:$C$31,$P56))*D56*C56/1000 -> 0.26838 | F56: =(F$25/INDEX($C$27:$C$31,$P56))*D56*C56/1000 -> 0.26838 | G56: =(G$25/INDEX($C$27:$C$31,$P56))*D56*C56/1000 -> 0.26838 | H56: =(H$25/INDEX($C$27:$C$31,$P56))*D56*C56/1000 -> 0.26838 | I56: =(I$25/INDEX($C$27:$C$31,$P56))*D56*C56/1000 -> 0.26838 | J56: =(J$25/INDEX($C$27:$C$31,$P56))*D56*C56/1000 -> 0.26838 | K56: =(K$25/INDEX($C$27:$C$31,$P56))*D56*C56/1000 -> 0.26838 | L56: =(L$25/INDEX($C$27:$C$31,$P56))*D56*C56/1000 -> 0.26838 | M56: =(M$25/INDEX($C$27:$C$31,$P56))*D56*C56/1000 -> 0.26838 | N56: =(N$25/INDEX($C$27:$C$31,$P56))*D56*C56/1000 -> 0.26838 | P56: 2
B57: Гидравлический фильтр | C57: 344.33 | D57: 3 | E57: =(E$25/INDEX($C$27:$C$31,$P57))*D57*C57/1000 -> 7.23093 | F57: =(F$25/INDEX($C$27:$C$31,$P57))*D57*C57/1000 -> 7.23093 | G57: =(G$25/INDEX($C$27:$C$31,$P57))*D57*C57/1000 -> 7.23093 | H57: =(H$25/INDEX($C$27:$C$31,$P57))*D57*C57/1000 -> 7.23093 | I57: =(I$25/INDEX($C$27:$C$31,$P57))*D57*C57/1000 -> 7.23093 | J57: =(J$25/INDEX($C$27:$C$31,$P57))*D57*C57/1000 -> 7.23093 | K57: =(K$25/INDEX($C$27:$C$31,$P57))*D57*C57/1000 -> 7.23093 | L57: =(L$25/INDEX($C$27:$C$31,$P57))*D57*C57/1000 -> 7.23093 | M57: =(M$25/INDEX($C$27:$C$31,$P57))*D57*C57/1000 -> 7.23093 | N57: =(N$25/INDEX($C$27:$C$31,$P57))*D57*C57/1000 -> 7.23093 | P57: 2
B58: О-кольцо | C58: 24.5 | D58: 3 | E58: =(E$25/INDEX($C$27:$C$31,$P58))*D58*C58/1000 -> 0.5145 | F58: =(F$25/INDEX($C$27:$C$31,$P58))*D58*C58/1000 -> 0.5145 | G58: =(G$25/INDEX($C$27:$C$31,$P58))*D58*C58/1000 -> 0.5145 | H58: =(H$25/INDEX($C$27:$C$31,$P58))*D58*C58/1000 -> 0.5145 | I58: =(I$25/INDEX($C$27:$C$31,$P58))*D58*C58/1000 -> 0.5145 | J58: =(J$25/INDEX($C$27:$C$31,$P58))*D58*C58/1000 -> 0.5145 | K58: =(K$25/INDEX($C$27:$C$31,$P58))*D58*C58/1000 -> 0.5145 | L58: =(L$25/INDEX($C$27:$C$31,$P58))*D58*C58/1000 -> 0.5145 | M58: =(M$25/INDEX($C$27:$C$31,$P58))*D58*C58/1000 -> 0.5145 | N58: =(N$25/INDEX($C$27:$C$31,$P58))*D58*C58/1000 -> 0.5145 | P58: 2
... B73: Гидравлическое масло | C73: 6.43 | D73: 1300 | E73: =(E$25/INDEX($C$27:$C$31,$P73))*D73*C73/1000 -> 11.7026 | F73: =(F$25/INDEX($C$27:$C$31,$P73))*D73*C73/1000 -> 11.7026 | G73: =(G$25/INDEX($C$27:$C$31,$P73))*D73*C73/1000 -> 11.7026 | H73: =(H$25/INDEX($C$27:$C$31,$P73))*D73*C73/1000 -> 11.7026 | I73: =(I$25/INDEX($C$27:$C$31,$P73))*D73*C73/1000 -> 11.7026 | J73: =(J$25/INDEX($C$27:$C$31,$P73))*D73*C73/1000 -> 11.7026 | K73: =(K$25/INDEX($C$27:$C$31,$P73))*D73*C73/1000 -> 11.7026 | L73: =(L$25/INDEX($C$27:$C$31,$P73))*D73*C73/1000 -> 11.7026 | M73: =(M$25/INDEX($C$27:$C$31,$P73))*D73*C73/1000 -> 11.7026 | N73: =(N$25/INDEX($C$27:$C$31,$P73))*D73*C73/1000 -> 11.7026 | P73: 5
B74: Корректировка (поглощения/прочее) | E74: 0 | F74: 0 | G74: 0 | H74: 0 | I74: 0 | J74: 0 | K74: 0 | L74: 0 | M74: 0 | N74: 0
B75: ИТОГО затраты на запчасти ТО, тыс/год | E75: =SUM(E47:E74) -> 107.51972 | F75: =SUM(F47:F74) -> 107.51972 | G75: =SUM(G47:G74) -> 107.51972 | H75: =SUM(H47:H74) -> 107.51972 | I75: =SUM(I47:I74) -> 107.51972 | J75: =SUM(J47:J74) -> 107.51972 | K75: =SUM(K47:K74) -> 107.51972 | L75: =SUM(L47:L74) -> 107.51972 | ... N75: =SUM(N47:N74) -> 107.51972
B77: Ставка сервиса | C77: вал/ч·час | E77: 50
B79: РАСЧЁТ РЕМОНТОВ (из списков по периодичности замены узлов)
B80: Простои в текущих + капитальных ремонтах | C80: ч/год | E80: 786.13 | F80: 1924.36 | G80: 1682.92 | H80: 2228.84 | I80: 2239.02 | J80: 1794.52 | K80: 2025.05 | L80: 1519.78 | M80: 2468.19 | N80: 1663.35
B81: Коэффициент поглощения (0–1; 1=как у поставщика) | C81: коэф. | E81: 1
B83: ТЕКУЩИЕ РЕМОНТЫ — ЗАТРАТЫ НА ЗЧ (по ресурсу замены)
B84: Наименование | C84: стоим.замены,тыс | D84: ресурс, м/ч | E84: год 1 | F84: год 2 | G84: год 3 | H84: год 4 | I84: год 5 | J84: год 6 | K84: год 7 | L84: год 8 | M84: год 9 | N84: год 10
B85: Быстроизнашиваемые элементы (GET) ковша, флэт-годовой | C85: 27.281 | D85: 7000 | E85: =(INT($E$25*1/$D85)-INT($E$25*(1-1)/$D85))*$C85 -> 27.281 | F85: =(INT($E$25*2/$D85)-INT($E$25*(2-1)/$D85))*$C85 -> 27.281 | G85: =(INT($E$25*3/$D85)-INT($E$25*(3-1)/$D85))*$C85 -> 27.281 | H85: =(INT($E$25*4/$D85)-INT($E$25*(4-1)/$D85))*$C85 -> 27.281 | I85: =(INT($E$25*5/$D85)-INT($E$25*(5-1)/$D85))*$C85 -> 27.281 | J85: =(INT($E$25*6/$D85)-INT($E$25*(6-1)/$D85))*$C85 -> 27.281 | K85: =(INT($E$25*7/$D85)-INT($E$25*(7-1)/$D85))*$C85 -> 27.281 | L85: =(INT($E$25*8/$D85)-INT($E$25*(8-1)/$D85))*$C85 -> 27.281 | M85: =(INT($E$25*9/$D85)-INT($E$25*(9-1)/$D85))*$C85 -> 27.281 | N85: =(INT($E$25*10/$D85)-INT($E$25*(10-1)/$D85))*$C85 -> 27.281
B86: Быстроизнашиваемые детали (ремни), флэт-годовой | C86: 0.354 | D86: 7000 | E86: =(INT($E$25*1/$D86)-INT($E$25*(1-1)/$D86))*$C86 -> 0.354 | F86: =(INT($E$25*2/$D86)-INT($E$25*(2-1)/$D86))*$C86 -> 0.354 | G86: =(INT($E$25*3/$D86)-INT($E$25*(3-1)/$D86))*$C86 -> 0.354 | H86: =(INT($E$25*4/$D86)-INT($E$25*(4-1)/$D86))*$C86 -> 0.354 | I86: =(INT($E$25*5/$D86)-INT($E$25*(5-1)/$D86))*$C86 -> 0.354 | J86: =(INT($E$25*6/$D86)-INT($E$25*(6-1)/$D86))*$C86 -> 0.354 | K86: =(INT($E$25*7/$D86)-INT($E$25*(7-1)/$D86))*$C86 -> 0.354 | L86: =(INT($E$25*8/$D86)-INT($E$25*(8-1)/$D86))*$C86 -> 0.354 | M86: =(INT($E$25*9/$D86)-INT($E$25*(9-1)/$D86))*$C86 -> 0.354 | N86: =(INT($E$25*10/$D86)-INT($E$25*(10-1)/$D86))*$C86 -> 0.354
B87: Крыльчатка вентилятора | C87: 1.561 | D87: 15000 | E87: =(INT($E$25*1/$D87)-INT($E$25*(1-1)/$D87))*$C87 -> 0 | F87: =(INT($E$25*2/$D87)-INT($E$25*(2-1)/$D87))*$C87 -> 0 | G87: =(INT($E$25*3/$D87)-INT($E$25*(3-1)/$D87))*$C87 -> 1.561 | H87: =(INT($E$25*4/$D87)-INT($E$25*(4-1)/$D87))*$C87 -> 0 | I87: =(INT($E$25*5/$D87)-INT($E$25*(5-1)/$D87))*$C87 -> 1.561 | J87: =(INT($E$25*6/$D87)-INT($E$25*(6-1)/$D87))*$C87 -> 0 | K87: =(INT($E$25*7/$D87)-INT($E$25*(7-1)/$D87))*$C87 -> 1.561 | L87: =(INT($E$25*8/$D87)-INT($E$25*(8-1)/$D87))*$C87 -> 0 | M87: =(INT($E$25*9/$D87)-INT($E$25*(9-1)/$D87))*$C87 -> 1.561 | N87: =(INT($E$25*10/$D87)-INT($E$25*(10-1)/$D87))*$C87 -> 0
B88: Аккумуляторная батарея | C88: 1.696 | D88: 20000 | E88: =(INT($E$25*1/$D88)-INT($E$25*(1-1)/$D88))*$C88 -> 0 | F88: =(INT($E$25*2/$D88)-INT($E$25*(2-1)/$D88))*$C88 -> 0 | G88: =(INT($E$25*3/$D88)-INT($E$25*(3-1)/$D88))*$C88 -> 1.696 | H88: =(INT($E$25*4/$D88)-INT($E$25*(4-1)/$D88))*$C88 -> 0 | I88: =(INT($E$25*5/$D88)-INT($E$25*(5-1)/$D88))*$C88 -> 0 | J88: =(INT($E$25*6/$D88)-INT($E$25*(6-1)/$D88))*$C88 -> 1.696 | K88: =(INT($E$25*7/$D88)-INT($E$25*(7-1)/$D88))*$C88 -> 0 | L88: =(INT($E$25*8/$D88)-INT($E$25*(8-1)/$D88))*$C88 -> 0 | M88: =(INT($E$25*9/$D88)-INT($E$25*(9-1)/$D88))*$C88 -> 1.696 | N88: =(INT($E$25*10/$D88)-INT($E$25*(10-1)/$D88))*$C88 -> 0
B89: Смазка пластичная GRAND EP Lithium Complex №2, флэт-годовой | C89: 1.508 | D89: 7000 | E89: =(INT($E$25*1/$D89)-INT($E$25*(1-1)/$D89))*$C89 -> 1.508 | F89: =(INT($E$25*2/$D89)-INT($E$25*(2-1)/$D89))*$C89 -> 1.508 | G89: =(INT($E$25*3/$D89)-INT($E$25*(3-1)/$D89))*$C89 -> 1.508 | H89: =(INT($E$25*4/$D89)-INT($E$25*(4-1)/$D89))*$C89 -> 1.508 | I89: =(INT($E$25*5/$D89)-INT($E$25*(5-1)/$D89))*$C89 -> 1.508 | J89: =(INT($E$25*6/$D89)-INT($E$25*(6-1)/$D89))*$C89 -> 1.508 | K89: =(INT($E$25*7/$D89)-INT($E$25*(7-1)/$D89))*$C89 -> 1.508 | L89: =(INT($E$25*8/$D89)-INT($E$25*(8-1)/$D89))*$C89 -> 1.508 | M89: =(INT($E$25*9/$D89)-INT($E$25*(9-1)/$D89))*$C89 -> 1.508 | N89: =(INT($E$25*10/$D89)-INT($E$25*(10-1)/$D89))*$C89 -> 1.508
B90: ИТОГО | E90: =SUM(E85:E89) -> 29.143 | F90: =SUM(F85:F89) -> 29.143 | G90: =SUM(G85:G89) -> 32.4 | H90: =SUM(H85:H89) -> 29.143 | I90: =SUM(I85:I89) -> 30.704 | J90: =SUM(J85:J89) -> 30.839 | K90: =SUM(K85:K89) -> 30.704 | L90: =SUM(L85:L89) -> 29.143 | ... N90: =SUM(N85:N89) -> 29.143
B92: ТЕКУЩИЕ РЕМОНТЫ — ТРУДОЗАТРАТЫ (по ресурсу замены)
B93: Наименование | C93: нормо-час/событие | D93: ресурс, м/ч | E93: год 1 | F93: год 2 | G93: год 3 | H93: год 4 | I93: год 5 | J93: год 6 | K93: год 7 | L93: год 8 | M93: год 9 | N93: год 10
B94: Ремонт ковша (GET) | C94: 80 | D94: 7000 | E94: =(INT($E$25*1/$D94)-INT($E$25*(1-1)/$D94))*$C94 -> 80 | F94: =(INT($E$25*2/$D94)-INT($E$25*(2-1)/$D94))*$C94 -> 80 | G94: =(INT($E$25*3/$D94)-INT($E$25*(3-1)/$D94))*$C94 -> 80 | H94: =(INT($E$25*4/$D94)-INT($E$25*(4-1)/$D94))*$C94 -> 80 | I94: =(INT($E$25*5/$D94)-INT($E$25*(5-1)/$D94))*$C94 -> 80 | J94: =(INT($E$25*6/$D94)-INT($E$25*(6-1)/$D94))*$C94 -> 80 | K94: =(INT($E$25*7/$D94)-INT($E$25*(7-1)/$D94))*$C94 -> 80 | L94: =(INT($E$25*8/$D94)-INT($E$25*(8-1)/$D94))*$C94 -> 80 | M94: =(INT($E$25*9/$D94)-INT($E$25*(9-1)/$D94))*$C94 -> 80 | N94: =(INT($E$25*10/$D94)-INT($E$25*(10-1)/$D94))*$C94 -> 80
B95: ИТОГО | E95: =SUM(E94:E94) -> 80 | F95: =SUM(F94:F94) -> 80 | G95: =SUM(G94:G94) -> 80 | H95: =SUM(H94:H94) -> 80 | I95: =SUM(I94:I94) -> 80 | J95: =SUM(J94:J94) -> 80 | K95: =SUM(K94:K94) -> 80 | L95: =SUM(L94:L94) -> 80 | ... N95: =SUM(N94:N94) -> 80
B97: КАПИТАЛЬНЫЕ РЕМОНТЫ (ЦЕХ) — ЗАТРАТЫ НА ЗЧ (по ресурсу до замены узла)
B98: Наименование | C98: стоим.замены,тыс | D98: ресурс, м/ч | E98: год 1 | F98: год 2 | G98: год 3 | H98: год 4 | I98: год 5 | J98: год 6 | K98: год 7 | L98: год 8 | M98: год 9 | N98: год 10
B99: Капитальный ремонт двигателя | C99: 326.279 | D99: 15000 | E99: =(INT($E$25*1/$D99)-INT($E$25*(1-1)/$D99))*$C99 -> 0 | F99: =(INT($E$25*2/$D99)-INT($E$25*(2-1)/$D99))*$C99 -> 0 | G99: =(INT($E$25*3/$D99)-INT($E$25*(3-1)/$D99))*$C99 -> 326.279 | H99: =(INT($E$25*4/$D99)-INT($E$25*(4-1)/$D99))*$C99 -> 0 | I99: =(INT($E$25*5/$D99)-INT($E$25*(5-1)/$D99))*$C99 -> 326.279 | J99: =(INT($E$25*6/$D99)-INT($E$25*(6-1)/$D99))*$C99 -> 0 | K99: =(INT($E$25*7/$D99)-INT($E$25*(7-1)/$D99))*$C99 -> 326.279 | L99: =(INT($E$25*8/$D99)-INT($E$25*(8-1)/$D99))*$C99 -> 0 | M99: =(INT($E$25*9/$D99)-INT($E$25*(9-1)/$D99))*$C99 -> 326.279 | N99: =(INT($E$25*10/$D99)-INT($E$25*(10-1)/$D99))*$C99 -> 0
B100: Ходовой мотор-редуктор | C100: 22 | D100: 15000 | E100: =(INT($E$25*1/$D100)-INT($E$25*(1-1)/$D100))*$C100 -> 0 | F100: =(INT($E$25*2/$D100)-INT($E$25*(2-1)/$D100))*$C100 -> 0 | G100: =(INT($E$25*3/$D100)-INT($E$25*(3-1)/$D100))*$C100 -> 22 | H100: =(INT($E$25*4/$D100)-INT($E$25*(4-1)/$D100))*$C100 -> 0 | I100: =(INT($E$25*5/$D100)-INT($E$25*(5-1)/$D100))*$C100 -> 22 | J100: =(INT($E$25*6/$D100)-INT($E$25*(6-1)/$D100))*$C100 -> 0 | K100: =(INT($E$25*7/$D100)-INT($E$25*(7-1)/$D100))*$C100 -> 22 | L100: =(INT($E$25*8/$D100)-INT($E$25*(8-1)/$D100))*$C100 -> 0 | M100: =(INT($E$25*9/$D100)-INT($E$25*(9-1)/$D100))*$C100 -> 22 | N100: =(INT($E$25*10/$D100)-INT($E$25*(10-1)/$D100))*$C100 -> 0
B101: Редуктор хода | C101: 72.11 | D101: 15000 | E101: =(INT($E$25*1/$D101)-INT($E$25*(1-1)/$D101))*$C101 -> 0 | F101: =(INT($E$25*2/$D101)-INT($E$25*(2-1)/$D101))*$C101 -> 0 | G101: =(INT($E$25*3/$D101)-INT($E$25*(3-1)/$D101))*$C101 -> 72.11 | H101: =(INT($E$25*4/$D101)-INT($E$25*(4-1)/$D101))*$C101 -> 0 | I101: =(INT($E$25*5/$D101)-INT($E$25*(5-1)/$D101))*$C101 -> 72.11 | J101: =(INT($E$25*6/$D101)-INT($E$25*(6-1)/$D101))*$C101 -> 0 | K101: =(INT($E$25*7/$D101)-INT($E$25*(7-1)/$D101))*$C101 -> 72.11 | L101: =(INT($E$25*8/$D101)-INT($E$25*(8-1)/$D101))*$C101 -> 0 | M101: =(INT($E$25*9/$D101)-INT($E$25*(9-1)/$D101))*$C101 -> 72.11 | N101: =(INT($E$25*10/$D101)-INT($E$25*(10-1)/$D101))*$C101 -> 0
B102: Ремонт форсунок | C102: 15.514 | D102: 10000 | E102: =(INT($E$25*1/$D102)-INT($E$25*(1-1)/$D102))*$C102 -> 0 | F102: =(INT($E$25*2/$D102)-INT($E$25*(2-1)/$D102))*$C102 -> 15.514 | G102: =(INT($E$25*3/$D102)-INT($E$25*(3-1)/$D102))*$C102 -> 15.514 | H102: =(INT($E$25*4/$D102)-INT($E$25*(4-1)/$D102))*$C102 -> 0 | I102: =(INT($E$25*5/$D102)-INT($E$25*(5-1)/$D102))*$C102 -> 15.514 | J102: =(INT($E$25*6/$D102)-INT($E$25*(6-1)/$D102))*$C102 -> 15.514 | K102: =(INT($E$25*7/$D102)-INT($E$25*(7-1)/$D102))*$C102 -> 0 | L102: =(INT($E$25*8/$D102)-INT($E$25*(8-1)/$D102))*$C102 -> 15.514 | M102: =(INT($E$25*9/$D102)-INT($E$25*(9-1)/$D102))*$C102 -> 15.514 | N102: =(INT($E$25*10/$D102)-INT($E$25*(10-1)/$D102))*$C102 -> 15.514
B103: Стартер | C103: 9.415 | D103: 10000 | E103: =(INT($E$25*1/$D103)-INT($E$25*(1-1)/$D103))*$C103 -> 0 | F103: =(INT($E$25*2/$D103)-INT($E$25*(2-1)/$D103))*$C103 -> 9.415 | G103: =(INT($E$25*3/$D103)-INT($E$25*(3-1)/$D103))*$C103 -> 9.415 | H103: =(INT($E$25*4/$D103)-INT($E$25*(4-1)/$D103))*$C103 -> 0 | I103: =(INT($E$25*5/$D103)-INT($E$25*(5-1)/$D103))*$C103 -> 9.415 | J103: =(INT($E$25*6/$D103)-INT($E$25*(6-1)/$D103))*$C103 -> 9.415 | K103: =(INT($E$25*7/$D103)-INT($E$25*(7-1)/$D103))*$C103 -> 0 | L103: =(INT($E$25*8/$D103)-INT($E$25*(8-1)/$D103))*$C103 -> 9.415 | M103: =(INT($E$25*9/$D103)-INT($E$25*(9-1)/$D103))*$C103 -> 9.415 | N103: =(INT($E$25*10/$D103)-INT($E$25*(10-1)/$D103))*$C103 -> 9.415
B104: Цилиндр стрелы | C104: 28.5 | D104: 15000 | E104: =(INT($E$25*1/$D104)-INT($E$25*(1-1)/$D104))*$C104 -> 0 | F104: =(INT($E$25*2/$D104)-INT($E$25*(2-1)/$D104))*$C104 -> 0 | G104: =(INT($E$25*3/$D104)-INT($E$25*(3-1)/$D104))*$C104 -> 28.5 | H104: =(INT($E$25*4/$D104)-INT($E$25*(4-1)/$D104))*$C104 -> 0 | I104: =(INT($E$25*5/$D104)-INT($E$25*(5-1)/$D104))*$C104 -> 28.5 | J104: =(INT($E$25*6/$D104)-INT($E$25*(6-1)/$D104))*$C104 -> 0 | K104: =(INT($E$25*7/$D104)-INT($E$25*(7-1)/$D104))*$C104 -> 28.5 | L104: =(INT($E$25*8/$D104)-INT($E$25*(8-1)/$D104))*$C104 -> 0 | M104: =(INT($E$25*9/$D104)-INT($E$25*(9-1)/$D104))*$C104 -> 28.5 | N104: =(INT($E$25*10/$D104)-INT($E$25*(10-1)/$D104))*$C104 -> 0
B105: Цилиндр рукояти | C105: 18 | D105: 15000 | E105: =(INT($E$25*1/$D105)-INT($E$25*(1-1)/$D105))*$C105 -> 0 | F105: =(INT($E$25*2/$D105)-INT($E$25*(2-1)/$D105))*$C105 -> 0 | G105: =(INT($E$25*3/$D105)-INT($E$25*(3-1)/$D105))*$C105 -> 18 | H105: =(INT($E$25*4/$D105)-INT($E$25*(4-1)/$D105))*$C105 -> 0 | I105: =(INT($E$25*5/$D105)-INT($E$25*(5-1)/$D105))*$C105 -> 18 | J105: =(INT($E$25*6/$D105)-INT($E$25*(6-1)/$D105))*$C105 -> 0 | K105: =(INT($E$25*7/$D105)-INT($E$25*(7-1)/$D105))*$C105 -> 18 | L105: =(INT($E$25*8/$D105)-INT($E$25*(8-1)/$D105))*$C105 -> 0 | M105: =(INT($E$25*9/$D105)-INT($E$25*(9-1)/$D105))*$C105 -> 18 | N105: =(INT($E$25*10/$D105)-INT($E$25*(10-1)/$D105))*$C105 -> 0
B106: Цилиндр ковша (левый) | C106: 11.5 | D106: 15000 | E106: =(INT($E$25*1/$D106)-INT($E$25*(1-1)/$D106))*$C106 -> 0 | F106: =(INT($E$25*2/$D106)-INT($E$25*(2-1)/$D106))*$C106 -> 0 | G106: =(INT($E$25*3/$D106)-INT($E$25*(3-1)/$D106))*$C106 -> 11.5 | H106: =(INT($E$25*4/$D106)-INT($E$25*(4-1)/$D106))*$C106 -> 0 | I106: =(INT($E$25*5/$D106)-INT($E$25*(5-1)/$D106))*$C106 -> 11.5 | J106: =(INT($E$25*6/$D106)-INT($E$25*(6-1)/$D106))*$C106 -> 0 | K106: =(INT($E$25*7/$D106)-INT($E$25*(7-1)/$D106))*$C106 -> 11.5 | L106: =(INT($E$25*8/$D106)-INT($E$25*(8-1)/$D106))*$C106 -> 0 | M106: =(INT($E$25*9/$D106)-INT($E$25*(9-1)/$D106))*$C106 -> 11.5 | N106: =(INT($E$25*10/$D106)-INT($E$25*(10-1)/$D106))*$C106 -> 0
B107: Цилиндр ковша (правый) | C107: 11.5 | D107: 15000 | E107: =(INT($E$25*1/$D107)-INT($E$25*(1-1)/$D107))*$C107 -> 0 | F107: =(INT($E$25*2/$D107)-INT($E$25*(2-1)/$D107))*$C107 -> 0 | G107: =(INT($E$25*3/$D107)-INT($E$25*(3-1)/$D107))*$C107 -> 11.5 | H107: =(INT($E$25*4/$D107)-INT($E$25*(4-1)/$D107))*$C107 -> 0 | I107: =(INT($E$25*5/$D107)-INT($E$25*(5-1)/$D107))*$C107 -> 11.5 | J107: =(INT($E$25*6/$D107)-INT($E$25*(6-1)/$D107))*$C107 -> 0 | K107: =(INT($E$25*7/$D107)-INT($E$25*(7-1)/$D107))*$C107 -> 11.5 | L107: =(INT($E$25*8/$D107)-INT($E$25*(8-1)/$D107))*$C107 -> 0 | M107: =(INT($E$25*9/$D107)-INT($E$25*(9-1)/$D107))*$C107 -> 11.5 | N107: =(INT($E$25*10/$D107)-INT($E$25*(10-1)/$D107))*$C107 -> 0
B108: Двигатель поворота | C108: 38 | D108: 15000 | E108: =(INT($E$25*1/$D108)-INT($E$25*(1-1)/$D108))*$C108 -> 0 | F108: =(INT($E$25*2/$D108)-INT($E$25*(2-1)/$D108))*$C108 -> 0 | G108: =(INT($E$25*3/$D108)-INT($E$25*(3-1)/$D108))*$C108 -> 38 | H108: =(INT($E$25*4/$D108)-INT($E$25*(4-1)/$D108))*$C108 -> 0 | I108: =(INT($E$25*5/$D108)-INT($E$25*(5-1)/$D108))*$C108 -> 38 | J108: =(INT($E$25*6/$D108)-INT($E$25*(6-1)/$D108))*$C108 -> 0 | K108: =(INT($E$25*7/$D108)-INT($E$25*(7-1)/$D108))*$C108 -> 38 | L108: =(INT($E$25*8/$D108)-INT($E$25*(8-1)/$D108))*$C108 -> 0 | M108: =(INT($E$25*9/$D108)-INT($E$25*(9-1)/$D108))*$C108 -> 38 | N108: =(INT($E$25*10/$D108)-INT($E$25*(10-1)/$D108))*$C108 -> 0
B109: Поворотный редуктор | C109: 56 | D109: 15000 | E109: =(INT($E$25*1/$D109)-INT($E$25*(1-1)/$D109))*$C109 -> 0 | F109: =(INT($E$25*2/$D109)-INT($E$25*(2-1)/$D109))*$C109 -> 0 | G109: =(INT($E$25*3/$D109)-INT($E$25*(3-1)/$D109))*$C109 -> 56 | H109: =(INT($E$25*4/$D109)-INT($E$25*(4-1)/$D109))*$C109 -> 0 | I109: =(INT($E$25*5/$D109)-INT($E$25*(5-1)/$D109))*$C109 -> 56 | J109: =(INT($E$25*6/$D109)-INT($E$25*(6-1)/$D109))*$C109 -> 0 | K109: =(INT($E$25*7/$D109)-INT($E$25*(7-1)/$D109))*$C109 -> 56 | L109: =(INT($E$25*8/$D109)-INT($E$25*(8-1)/$D109))*$C109 -> 0 | M109: =(INT($E$25*9/$D109)-INT($E$25*(9-1)/$D109))*$C109 -> 56 | N109: =(INT($E$25*10/$D109)-INT($E$25*(10-1)/$D109))*$C109 -> 0
B110: Центральный поворотный узел | C110: 26.5 | D110: 25000 | E110: =(INT($E$25*1/$D110)-INT($E$25*(1-1)/$D110))*$C110 -> 0 | F110: =(INT($E$25*2/$D110)-INT($E$25*(2-1)/$D110))*$C110 -> 0 | G110: =(INT($E$25*3/$D110)-INT($E$25*(3-1)/$D110))*$C110 -> 0 | H110: =(INT($E$25*4/$D110)-INT($E$25*(4-1)/$D110))*$C110 -> 26.5 | I110: =(INT($E$25*5/$D110)-INT($E$25*(5-1)/$D110))*$C110 -> 0 | J110: =(INT($E$25*6/$D110)-INT($E$25*(6-1)/$D110))*$C110 -> 0 | K110: =(INT($E$25*7/$D110)-INT($E$25*(7-1)/$D110))*$C110 -> 0 | L110: =(INT($E$25*8/$D110)-INT($E$25*(8-1)/$D110))*$C110 -> 26.5 | M110: =(INT($E$25*9/$D110)-INT($E$25*(9-1)/$D110))*$C110 -> 0 | N110: =(INT($E$25*10/$D110)-INT($E$25*(10-1)/$D110))*$C110 -> 0
B111: Опора поворотного устройства | C111: 62.5 | D111: 25000 | E111: =(INT($E$25*1/$D111)-INT($E$25*(1-1)/$D111))*$C111 -> 0 | F111: =(INT($E$25*2/$D111)-INT($E$25*(2-1)/$D111))*$C111 -> 0 | G111: =(INT($E$25*3/$D111)-INT($E$25*(3-1)/$D111))*$C111 -> 0 | H111: =(INT($E$25*4/$D111)-INT($E$25*(4-1)/$D111))*$C111 -> 62.5 | I111: =(INT($E$25*5/$D111)-INT($E$25*(5-1)/$D111))*$C111 -> 0 | J111: =(INT($E$25*6/$D111)-INT($E$25*(6-1)/$D111))*$C111 -> 0 | K111: =(INT($E$25*7/$D111)-INT($E$25*(7-1)/$D111))*$C111 -> 0 | L111: =(INT($E$25*8/$D111)-INT($E$25*(8-1)/$D111))*$C111 -> 62.5 | M111: =(INT($E$25*9/$D111)-INT($E$25*(9-1)/$D111))*$C111 -> 0 | N111: =(INT($E$25*10/$D111)-INT($E$25*(10-1)/$D111))*$C111 -> 0
B112: ИТОГО | E112: =SUM(E99:E111) -> 0 | F112: =SUM(F99:F111) -> 24.929 | G112: =SUM(G99:G111) -> 608.818 | H112: =SUM(H99:H111) -> 89 | I112: =SUM(I99:I111) -> 608.818 | J112: =SUM(J99:J111) -> 24.929 | K112: =SUM(K99:K111) -> 583.889 | L112: =SUM(L99:L111) -> 113.929 | ... N112: =SUM(N99:N111) -> 24.929
B114: КАПИТАЛЬНЫЕ РЕМОНТЫ (ЦЕХ) — ТРУДОЗАТРАТЫ (по ресурсу до замены узла)
B115: Наименование | C115: нормо-час/событие | D115: ресурс, м/ч | E115: год 1 | F115: год 2 | G115: год 3 | H115: год 4 | I115: год 5 | J115: год 6 | K115: год 7 | L115: год 8 | M115: год 9 | N115: год 10
B116: Ремонт двигателя, ходовой части | C116: 200 | D116: 15000 | E116: =(INT($E$25*1/$D116)-INT($E$25*(1-1)/$D116))*$C116 -> 0 | F116: =(INT($E$25*2/$D116)-INT($E$25*(2-1)/$D116))*$C116 -> 0 | G116: =(INT($E$25*3/$D116)-INT($E$25*(3-1)/$D116))*$C116 -> 200 | H116: =(INT($E$25*4/$D116)-INT($E$25*(4-1)/$D116))*$C116 -> 0 | I116: =(INT($E$25*5/$D116)-INT($E$25*(5-1)/$D116))*$C116 -> 200 | J116: =(INT($E$25*6/$D116)-INT($E$25*(6-1)/$D116))*$C116 -> 0 | K116: =(INT($E$25*7/$D116)-INT($E$25*(7-1)/$D116))*$C116 -> 200 | L116: =(INT($E$25*8/$D116)-INT($E$25*(8-1)/$D116))*$C116 -> 0 | M116: =(INT($E$25*9/$D116)-INT($E$25*(9-1)/$D116))*$C116 -> 200 | N116: =(INT($E$25*10/$D116)-INT($E$25*(10-1)/$D116))*$C116 -> 0
B117: Ремонт форсунок, стартер | C117: 40 | D117: 10000 | E117: =(INT($E$25*1/$D117)-INT($E$25*(1-1)/$D117))*$C117 -> 0 | F117: =(INT($E$25*2/$D117)-INT($E$25*(2-1)/$D117))*$C117 -> 40 | G117: =(INT($E$25*3/$D117)-INT($E$25*(3-1)/$D117))*$C117 -> 40 | H117: =(INT($E$25*4/$D117)-INT($E$25*(4-1)/$D117))*$C117 -> 0 | I117: =(INT($E$25*5/$D117)-INT($E$25*(5-1)/$D117))*$C117 -> 40 | J117: =(INT($E$25*6/$D117)-INT($E$25*(6-1)/$D117))*$C117 -> 40 | K117: =(INT($E$25*7/$D117)-INT($E$25*(7-1)/$D117))*$C117 -> 0 | L117: =(INT($E$25*8/$D117)-INT($E$25*(8-1)/$D117))*$C117 -> 40 | M117: =(INT($E$25*9/$D117)-INT($E$25*(9-1)/$D117))*$C117 -> 40 | N117: =(INT($E$25*10/$D117)-INT($E$25*(10-1)/$D117))*$C117 -> 40
B118: Ремонт системы подъема (цилиндры) | C118: 80 | D118: 15000 | E118: =(INT($E$25*1/$D118)-INT($E$25*(1-1)/$D118))*$C118 -> 0 | F118: =(INT($E$25*2/$D118)-INT($E$25*(2-1)/$D118))*$C118 -> 0 | G118: =(INT($E$25*3/$D118)-INT($E$25*(3-1)/$D118))*$C118 -> 80 | H118: =(INT($E$25*4/$D118)-INT($E$25*(4-1)/$D118))*$C118 -> 0 | I118: =(INT($E$25*5/$D118)-INT($E$25*(5-1)/$D118))*$C118 -> 80 | J118: =(INT($E$25*6/$D118)-INT($E$25*(6-1)/$D118))*$C118 -> 0 | K118: =(INT($E$25*7/$D118)-INT($E$25*(7-1)/$D118))*$C118 -> 80 | L118: =(INT($E$25*8/$D118)-INT($E$25*(8-1)/$D118))*$C118 -> 0 | M118: =(INT($E$25*9/$D118)-INT($E$25*(9-1)/$D118))*$C118 -> 80 | N118: =(INT($E$25*10/$D118)-INT($E$25*(10-1)/$D118))*$C118 -> 0
B119: Ремонт системы поворота | C119: 60 | D119: 15000 | E119: =(INT($E$25*1/$D119)-INT($E$25*(1-1)/$D119))*$C119 -> 0 | F119: =(INT($E$25*2/$D119)-INT($E$25*(2-1)/$D119))*$C119 -> 0 | G119: =(INT($E$25*3/$D119)-INT($E$25*(3-1)/$D119))*$C119 -> 60 | H119: =(INT($E$25*4/$D119)-INT($E$25*(4-1)/$D119))*$C119 -> 0 | I119: =(INT($E$25*5/$D119)-INT($E$25*(5-1)/$D119))*$C119 -> 60 | J119: =(INT($E$25*6/$D119)-INT($E$25*(6-1)/$D119))*$C119 -> 0 | K119: =(INT($E$25*7/$D119)-INT($E$25*(7-1)/$D119))*$C119 -> 60 | L119: =(INT($E$25*8/$D119)-INT($E$25*(8-1)/$D119))*$C119 -> 0 | M119: =(INT($E$25*9/$D119)-INT($E$25*(9-1)/$D119))*$C119 -> 60 | N119: =(INT($E$25*10/$D119)-INT($E$25*(10-1)/$D119))*$C119 -> 0
B120: Ремонт центр. поворотного узла, ОПУ | C120: 80 | D120: 25000 | E120: =(INT($E$25*1/$D120)-INT($E$25*(1-1)/$D120))*$C120 -> 0 | F120: =(INT($E$25*2/$D120)-INT($E$25*(2-1)/$D120))*$C120 -> 0 | G120: =(INT($E$25*3/$D120)-INT($E$25*(3-1)/$D120))*$C120 -> 0 | H120: =(INT($E$25*4/$D120)-INT($E$25*(4-1)/$D120))*$C120 -> 80 | I120: =(INT($E$25*5/$D120)-INT($E$25*(5-1)/$D120))*$C120 -> 0 | J120: =(INT($E$25*6/$D120)-INT($E$25*(6-1)/$D120))*$C120 -> 0 | K120: =(INT($E$25*7/$D120)-INT($E$25*(7-1)/$D120))*$C120 -> 0 | L120: =(INT($E$25*8/$D120)-INT($E$25*(8-1)/$D120))*$C120 -> 80 | M120: =(INT($E$25*9/$D120)-INT($E$25*(9-1)/$D120))*$C120 -> 0 | N120: =(INT($E$25*10/$D120)-INT($E$25*(10-1)/$D120))*$C120 -> 0
B121: ИТОГО | E121: =SUM(E116:E120) -> 0 | F121: =SUM(F116:F120) -> 40 | G121: =SUM(G116:G120) -> 380 | H121: =SUM(H116:H120) -> 80 | I121: =SUM(I116:I120) -> 380 | J121: =SUM(J116:J120) -> 40 | K121: =SUM(K116:K120) -> 340 | L121: =SUM(L116:L120) -> 120 | ... N121: =SUM(N116:N120) -> 40
B123: Все таблицы — ПО ГОДАМ. Затраты и трудозатраты считаются РАЗДЕЛЬНО для ТО / текущих ремонтов / капитальных (цеховых) ремонтов, каждая — по полному списку узлов из файла поставщика (без группировки). Капремонты и текущие ремонты по узлам считаются ПО ПЕРИОДИЧНОСТИ: у каждого узла — стоимость/трудоёмкость замены и ресурс (м/ч); затрата возникает в те годы, когда наработка пересекает кратное ресурсу значение (число замен = ЦЕЛОЕ(наработка×год/ресурс) − ЦЕЛОЕ(наработка×(год−1)/ресурс)). «Коэффициент поглощения» < 1 учитывает восстановление/поглощение узлов (у поставщика = 1).

Sheet Поставщик 5
B1: ШАБЛОН ДАННЫХ ПОСТАВЩИКА — ВАРИАНТ 5
B2: Полные модели ТО и Ремонтов ПО ГОДАМ (затраты и трудозатраты — раздельно для ТО / текущих / капитальных ремонтов). Зелёное — авто; сводка тянется в «Данные по годам».
B4: Экскаватор: | E4: ='Ввод данных'!H7 -> Shantui SE2000LCW
B5: Валюта затрат ТОиР: | D5: USD
B6: Показатель | C6: Ед. | E6: год 1 | F6: год 2 | G6: год 3 | H6: год 4 | I6: год 5 | J6: год 6 | K6: год 7 | L6: год 8 | M6: год 9 | N6: год 10
B7: СВОДКА ПО ГОДАМ (зелёное — авто из моделей ниже; тянется в расчёт)
B8: Простои на ТО | C8: ч/год | E8: =E37 -> 273.21 | F8: =F37 -> 273.21 | G8: =G37 -> 273.21 | H8: =H37 -> 273.21 | I8: =I37 -> 273.21 | J8: =J37 -> 273.21 | K8: =K37 -> 273.21 | L8: =L37 -> 273.21 | ... N8: =N37 -> 273.21
B9: Простои в текущих + капитальных ремонтах | C9: ч/год | E9: =E80 -> 786.13 | F9: =F80 -> 1924.36 | G9: =G80 -> 1682.92 | H9: =H80 -> 2228.84 | I9: =I80 -> 2239.02 | J9: =J80 -> 1794.52 | K9: =K80 -> 2025.05 | L9: =L80 -> 1519.78 | ... N9: =N80 -> 1663.35
B10: Ежесменное ТО (20 мин/смену) | C10: ч/год | E10: =('Параметры'!C26-E8-E9)/'Параметры'!C33*20/60 -> 213.90722 | F10: =('Параметры'!C26-F8-F9)/'Параметры'!C33*20/60 -> 182.28972 | G10: =('Параметры'!C26-G8-G9)/'Параметры'!C33*20/60 -> 188.99639 | H10: =('Параметры'!C26-H8-H9)/'Параметры'!C33*20/60 -> 173.83194 | I10: =('Параметры'!C26-I8-I9)/'Параметры'!C33*20/60 -> 173.54917 | J10: =('Параметры'!C26-J8-J9)/'Параметры'!C33*20/60 -> 185.89639 | K10: =('Параметры'!C26-K8-K9)/'Параметры'!C33*20/60 -> 179.49278 | L10: =('Параметры'!C26-L8-L9)/'Параметры'!C33*20/60 -> 193.52806 | M10: =('Параметры'!C26-M8-M9)/'Параметры'!C33*20/60 -> 167.18333 | N10: =('Параметры'!C26-N8-N9)/'Параметры'!C33*20/60 -> 189.54
B11: КТГ (авто) = (8760 − простои)/8760 | C11: коэф. | E11: =('Параметры'!C26-E8-E9-E10)/'Параметры'!C26 -> 0.85465214 | F11: =('Параметры'!C26-F8-F9-F10)/'Параметры'!C26 -> 0.72832652 | G11: =('Параметры'!C26-G8-G9-G10)/'Параметры'!C26 -> 0.75512256 | H11: =('Параметры'!C26-H8-H9-H10)/'Параметры'!C26 -> 0.69453402 | I11: =('Параметры'!C26-I8-I9-I10)/'Параметры'!C26 -> 0.6934042 | J11: =('Параметры'!C26-J8-J9-J10)/'Параметры'!C26 -> 0.74273671 | K11: =('Параметры'!C26-K8-K9-K10)/'Параметры'!C26 -> 0.71715151 | L11: =('Параметры'!C26-L8-L9-L10)/'Параметры'!C26 -> 0.77322853 | M11: =('Параметры'!C26-M8-M9-M10)/'Параметры'!C26 -> 0.66796994 | N11: =('Параметры'!C26-N8-N9-N10)/'Параметры'!C26 -> 0.75729452
B12: Затраты на ТО (ЗЧ, из каталога) | C12: тыс/год | E12: =E75 -> 107.51972 | F12: =F75 -> 107.51972 | G12: =G75 -> 107.51972 | H12: =H75 -> 107.51972 | I12: =I75 -> 107.51972 | J12: =J75 -> 107.51972 | K12: =K75 -> 107.51972 | L12: =L75 -> 107.51972 | ... N12: =N75 -> 107.51972
B13: Затраты на текущие ремонты (ЗЧ) | C13: тыс/год | E13: =E86*$E$81 -> 0 | F13: =F86*$E$81 -> 0 | G13: =G86*$E$81 -> 0 | H13: =H86*$E$81 -> 0 | I13: =I86*$E$81 -> 0 | J13: =J86*$E$81 -> 0 | K13: =K86*$E$81 -> 0 | L13: =L86*$E$81 -> 0 | ... N13: =N86*$E$81 -> 0
B14: Затраты на капитальные ремонты (ЗЧ, цех) | C14: тыс/год | E14: =E126*$E$81 -> 43.4832 | F14: =F126*$E$81 -> 1092.9194 | G14: =G126*$E$81 -> 7491.5263 | H14: =H126*$E$81 -> 3128.3212 | I14: =I126*$E$81 -> 2381.5915 | J14: =J126*$E$81 -> 8584.4457 | K14: =K126*$E$81 -> 3128.3212 | L14: =L126*$E$81 -> 7491.5263 | ... N14: =N126*$E$81 -> 43.4832
B15: Трудозатраты на ТО | C15: ч-час/год | E15: =E43 -> 546.42 | F15: =F43 -> 546.42 | G15: =G43 -> 546.42 | H15: =H43 -> 546.42 | I15: =I43 -> 546.42 | J15: =J43 -> 546.42 | K15: =K43 -> 546.42 | L15: =L43 -> 546.42 | ... N15: =N43 -> 546.42
B16: Трудозатраты на текущие ремонты | C16: ч-час/год | E16: =E91*$E$81 -> 0 | F16: =F91*$E$81 -> 0 | G16: =G91*$E$81 -> 0 | H16: =H91*$E$81 -> 0 | I16: =I91*$E$81 -> 0 | J16: =J91*$E$81 -> 0 | K16: =K91*$E$81 -> 0 | L16: =L91*$E$81 -> 0 | ... N16: =N91*$E$81 -> 0
B17: Трудозатраты на капитальные ремонты (цех) | C17: чел-час/год | E17: =E136*$E$81 -> 0 | F17: =F136*$E$81 -> 12 | G17: =G136*$E$81 -> 148 | H17: =H136*$E$81 -> 12 | I17: =I136*$E$81 -> 14 | J17: =J136*$E$81 -> 160 | K17: =K136*$E$81 -> 12 | L17: =L136*$E$81 -> 148 | ... N17: =N136*$E$81 -> 0
B18: Сервис ТО (авто) = трудозатраты ТО × ставка | C18: тыс/год | E18: =E15*$E$77/1000 -> 27.321 | F18: =F15*$E$77/1000 -> 27.321 | G18: =G15*$E$77/1000 -> 27.321 | H18: =H15*$E$77/1000 -> 27.321 | I18: =I15*$E$77/1000 -> 27.321 | J18: =J15*$E$77/1000 -> 27.321 | K18: =K15*$E$77/1000 -> 27.321 | L18: =L15*$E$77/1000 -> 27.321 | ... N18: =N15*$E$77/1000 -> 27.321
B19: Сервис текущих ремонтов (авто) | C19: тыс/год | E19: =E16*$E$77/1000 -> 0 | F19: =F16*$E$77/1000 -> 0 | G19: =G16*$E$77/1000 -> 0 | H19: =H16*$E$77/1000 -> 0 | I19: =I16*$E$77/1000 -> 0 | J19: =J16*$E$77/1000 -> 0 | K19: =K16*$E$77/1000 -> 0 | L19: =L16*$E$77/1000 -> 0 | ... N19: =N16*$E$77/1000 -> 0
B20: Сервис капитальных ремонтов (цех, авто) | C20: тыс/год | E20: =E17*$E$77/1000 -> 0 | F20: =F17*$E$77/1000 -> 0.6 | G20: =G17*$E$77/1000 -> 7.4 | H20: =H17*$E$77/1000 -> 0.6 | I20: =I17*$E$77/1000 -> 0.7 | J20: =J17*$E$77/1000 -> 8 | K20: =K17*$E$77/1000 -> 0.6 | L20: =L17*$E$77/1000 -> 7.4 | ... N20: =N17*$E$77/1000 -> 0
B21: ИТОГО ТОиР (авто) → «Данные по годам» | C21: тыс/год | E21: =E12+E13+E14+E18+E19+E20 -> 178.32392 | F21: =F12+F13+F14+F18+F19+F20 -> 1228.3601 | G21: =G12+G13+G14+G18+G19+G20 -> 7633.767 | H21: =H12+H13+H14+H18+H19+H20 -> 3263.7619 | I21: =I12+I13+I14+I18+I19+I20 -> 2517.1322 | J21: =J12+J13+J14+J18+J19+J20 -> 8727.2864 | K21: =K12+K13+K14+K18+K19+K20 -> 3263.7619 | L21: =L12+L13+L14+L18+L19+L20 -> 7633.767 | ... N21: =N12+N13+N14+N18+N19+N20 -> 178.32392
B22: Удельный расход ДТ | C22: кг/час | E22: 102 | F22: 102 | G22: 102 | H22: 102 | I22: 102 | J22: 102 | K22: 102 | L22: 102 | M22: 102 | N22: 102
B23: Расходники на ковш | C23: руб/м³ | E23: 0.87 | F23: 0.87 | G23: 0.87 | H23: 0.87 | I23: 0.87 | J23: 0.87 | K23: 0.87 | L23: 0.87 | M23: 0.87 | N23: 0.87
B24: РАСЧЁТ ТО (по интервалам обслуживания), ПО ГОДАМ
B25: Наработка по годам | C25: м/час | E25: 7000 | F25: 7000 | G25: 7000 | H25: 7000 | I25: 7000 | J25: 7000 | K25: 7000 | L25: 7000 | M25: 7000 | N25: 7000
B26: Вид ТО | C26: интервал | D26: длит.простоя | E26: персонал
B27: ТО-1 | C27: 500 | D27: 10.2 | E27: 2
B28: ТО-2 | C28: 1000 | D28: 9.4 | E28: 2
B29: ТО-3 | C29: 2000 | D29: 12.4 | E29: 2
B30: ТО-4 | C30: 4000 | D30: 7.8 | E30: 2
B31: ТО-5 | C31: 5000 | D31: 5.4 | E31: 2
B32: ТО-1: простои, ч/год | C32: #,##0 | E32: =(E$25/$C27)*$D27 -> 142.8 | F32: =(F$25/$C27)*$D27 -> 142.8 | G32: =(G$25/$C27)*$D27 -> 142.8 | H32: =(H$25/$C27)*$D27 -> 142.8 | I32: =(I$25/$C27)*$D27 -> 142.8 | J32: =(J$25/$C27)*$D27 -> 142.8 | K32: =(K$25/$C27)*$D27 -> 142.8 | L32: =(L$25/$C27)*$D27 -> 142.8 | ... N32: =(N$25/$C27)*$D27 -> 142.8
B33: ТО-2: простои, ч/год | C33: #,##0 | E33: =(E$25/$C28)*$D28 -> 65.8 | F33: =(F$25/$C28)*$D28 -> 65.8 | G33: =(G$25/$C28)*$D28 -> 65.8 | H33: =(H$25/$C28)*$D28 -> 65.8 | I33: =(I$25/$C28)*$D28 -> 65.8 | J33: =(J$25/$C28)*$D28 -> 65.8 | K33: =(K$25/$C28)*$D28 -> 65.8 | L33: =(L$25/$C28)*$D28 -> 65.8 | ... N33: =(N$25/$C28)*$D28 -> 65.8
B34: ТО-3: простои, ч/год | C34: #,##0 | E34: =(E$25/$C29)*$D29 -> 43.4 | F34: =(F$25/$C29)*$D29 -> 43.4 | G34: =(G$25/$C29)*$D29 -> 43.4 | H34: =(H$25/$C29)*$D29 -> 43.4 | I34: =(I$25/$C29)*$D29 -> 43.4 | J34: =(J$25/$C29)*$D29 -> 43.4 | K34: =(K$25/$C29)*$D29 -> 43.4 | L34: =(L$25/$C29)*$D29 -> 43.4 | ... N34: =(N$25/$C29)*$D29 -> 43.4
B35: ТО-4: простои, ч/год | C35: #,##0 | E35: =(E$25/$C30)*$D30 -> 13.65 | F35: =(F$25/$C30)*$D30 -> 13.65 | G35: =(G$25/$C30)*$D30 -> 13.65 | H35: =(H$25/$C30)*$D30 -> 13.65 | I35: =(I$25/$C30)*$D30 -> 13.65 | J35: =(J$25/$C30)*$D30 -> 13.65 | K35: =(K$25/$C30)*$D30 -> 13.65 | L35: =(L$25/$C30)*$D30 -> 13.65 | ... N35: =(N$25/$C30)*$D30 -> 13.65
B36: ТО-5: простои, ч/год | C36: #,##0 | E36: =(E$25/$C31)*$D31 -> 7.56 | F36: =(F$25/$C31)*$D31 -> 7.56 | G36: =(G$25/$C31)*$D31 -> 7.56 | H36: =(H$25/$C31)*$D31 -> 7.56 | I36: =(I$25/$C31)*$D31 -> 7.56 | J36: =(J$25/$C31)*$D31 -> 7.56 | K36: =(K$25/$C31)*$D31 -> 7.56 | L36: =(L$25/$C31)*$D31 -> 7.56 | ... N36: =(N$25/$C31)*$D31 -> 7.56
B37: Итого простои ТО, ч/год | C37: ч/год | E37: =SUM(E32:E36) -> 273.21 | F37: =SUM(F32:F36) -> 273.21 | G37: =SUM(G32:G36) -> 273.21 | H37: =SUM(H32:H36) -> 273.21 | I37: =SUM(I32:I36) -> 273.21 | J37: =SUM(J32:J36) -> 273.21 | K37: =SUM(K32:K36) -> 273.21 | L37: =SUM(L32:L36) -> 273.21 | ... N37: =SUM(N32:N36) -> 273.21
B38: ТО-1: ч·часы/год | C38: #,##0 | E38: =E32*$E27 -> 285.6 | F38: =F32*$E27 -> 285.6 | G38: =G32*$E27 -> 285.6 | H38: =H32*$E27 -> 285.6 | I38: =I32*$E27 -> 285.6 | J38: =J32*$E27 -> 285.6 | K38: =K32*$E27 -> 285.6 | L38: =L32*$E27 -> 285.6 | ... N38: =N32*$E27 -> 285.6
B39: ТО-2: ч·часы/год | C39: #,##0 | E39: =E33*$E28 -> 131.6 | F39: =F33*$E28 -> 131.6 | G39: =G33*$E28 -> 131.6 | H39: =H33*$E28 -> 131.6 | I39: =I33*$E28 -> 131.6 | J39: =J33*$E28 -> 131.6 | K39: =K33*$E28 -> 131.6 | L39: =L33*$E28 -> 131.6 | ... N39: =N33*$E28 -> 131.6
B40: ТО-3: ч·часы/год | C40: #,##0 | E40: =E34*$E29 -> 86.8 | F40: =F34*$E29 -> 86.8 | G40: =G34*$E29 -> 86.8 | H40: =H34*$E29 -> 86.8 | I40: =I34*$E29 -> 86.8 | J40: =J34*$E29 -> 86.8 | K40: =K34*$E29 -> 86.8 | L40: =L34*$E29 -> 86.8 | ... N40: =N34*$E29 -> 86.8
B41: ТО-4: ч·часы/год | C41: #,##0 | E41: =E35*$E30 -> 27.3 | F41: =F35*$E30 -> 27.3 | G41: =G35*$E30 -> 27.3 | H41: =H35*$E30 -> 27.3 | I41: =I35*$E30 -> 27.3 | J41: =J35*$E30 -> 27.3 | K41: =K35*$E30 -> 27.3 | L41: =L35*$E30 -> 27.3 | ... N41: =N35*$E30 -> 27.3
B42: ТО-5: ч·часы/год | C42: #,##0 | E42: =E36*$E31 -> 15.12 | F42: =F36*$E31 -> 15.12 | G42: =G36*$E31 -> 15.12 | H42: =H36*$E31 -> 15.12 | I42: =I36*$E31 -> 15.12 | J42: =J36*$E31 -> 15.12 | K42: =K36*$E31 -> 15.12 | L42: =L36*$E31 -> 15.12 | ... N42: =N36*$E31 -> 15.12
B43: Итого ч·часы ТО, ч-час/год | C43: ч-час | E43: =SUM(E38:E42) -> 546.42 | F43: =SUM(F38:F42) -> 546.42 | G43: =SUM(G38:G42) -> 546.42 | H43: =SUM(H38:H42) -> 546.42 | I43: =SUM(I38:I42) -> 546.42 | J43: =SUM(J38:J42) -> 546.42 | K43: =SUM(K38:K42) -> 546.42 | L43: =SUM(L38:L42) -> 546.42 | ... N43: =SUM(N38:N42) -> 546.42
B45: КАТАЛОГ ЗАПЧАСТЕЙ ТО (заполняет подрядчик), ПО ГОДАМ
B46: Наименование | C46: цена за ед | D46: кол-во/ТО | E46: год 1 | F46: год 2 | G46: год 3 | H46: год 4 | I46: год 5 | J46: год 6 | K46: год 7 | L46: год 8 | M46: год 9 | N46: год 10 | P46: № ТО
B47: Масляный фильтр | C47: 114.83 | D47: 4 | E47: =(E$25/INDEX($C$27:$C$31,$P47))*D47*C47/1000 -> 6.43048 | F47: =(F$25/INDEX($C$27:$C$31,$P47))*D47*C47/1000 -> 6.43048 | G47: =(G$25/INDEX($C$27:$C$31,$P47))*D47*C47/1000 -> 6.43048 | H47: =(H$25/INDEX($C$27:$C$31,$P47))*D47*C47/1000 -> 6.43048 | I47: =(I$25/INDEX($C$27:$C$31,$P47))*D47*C47/1000 -> 6.43048 | J47: =(J$25/INDEX($C$27:$C$31,$P47))*D47*C47/1000 -> 6.43048 | K47: =(K$25/INDEX($C$27:$C$31,$P47))*D47*C47/1000 -> 6.43048 | L47: =(L$25/INDEX($C$27:$C$31,$P47))*D47*C47/1000 -> 6.43048 | M47: =(M$25/INDEX($C$27:$C$31,$P47))*D47*C47/1000 -> 6.43048 | N47: =(N$25/INDEX($C$27:$C$31,$P47))*D47*C47/1000 -> 6.43048 | P47: 1
B48: Топливный фильтр | C48: 141.33 | D48: 2 | E48: =(E$25/INDEX($C$27:$C$31,$P48))*D48*C48/1000 -> 3.95724 | F48: =(F$25/INDEX($C$27:$C$31,$P48))*D48*C48/1000 -> 3.95724 | G48: =(G$25/INDEX($C$27:$C$31,$P48))*D48*C48/1000 -> 3.95724 | H48: =(H$25/INDEX($C$27:$C$31,$P48))*D48*C48/1000 -> 3.95724 | I48: =(I$25/INDEX($C$27:$C$31,$P48))*D48*C48/1000 -> 3.95724 | J48: =(J$25/INDEX($C$27:$C$31,$P48))*D48*C48/1000 -> 3.95724 | K48: =(K$25/INDEX($C$27:$C$31,$P48))*D48*C48/1000 -> 3.95724 | L48: =(L$25/INDEX($C$27:$C$31,$P48))*D48*C48/1000 -> 3.95724 | M48: =(M$25/INDEX($C$27:$C$31,$P48))*D48*C48/1000 -> 3.95724 | N48: =(N$25/INDEX($C$27:$C$31,$P48))*D48*C48/1000 -> 3.95724 | P48: 1
B49: Масло ДВС | C49: 6.87 | D49: 130 | E49: =(E$25/INDEX($C$27:$C$31,$P49))*D49*C49/1000 -> 12.5034 | F49: =(F$25/INDEX($C$27:$C$31,$P49))*D49*C49/1000 -> 12.5034 | G49: =(G$25/INDEX($C$27:$C$31,$P49))*D49*C49/1000 -> 12.5034 | H49: =(H$25/INDEX($C$27:$C$31,$P49))*D49*C49/1000 -> 12.5034 | I49: =(I$25/INDEX($C$27:$C$31,$P49))*D49*C49/1000 -> 12.5034 | J49: =(J$25/INDEX($C$27:$C$31,$P49))*D49*C49/1000 -> 12.5034 | K49: =(K$25/INDEX($C$27:$C$31,$P49))*D49*C49/1000 -> 12.5034 | L49: =(L$25/INDEX($C$27:$C$31,$P49))*D49*C49/1000 -> 12.5034 | M49: =(M$25/INDEX($C$27:$C$31,$P49))*D49*C49/1000 -> 12.5034 | N49: =(N$25/INDEX($C$27:$C$31,$P49))*D49*C49/1000 -> 12.5034 | P49: 1
B50: Фильтр управляющего контура | C50: 126 | D50: 1 | E50: =(E$25/INDEX($C$27:$C$31,$P50))*D50*C50/1000 -> 1.764 | F50: =(F$25/INDEX($C$27:$C$31,$P50))*D50*C50/1000 -> 1.764 | G50: =(G$25/INDEX($C$27:$C$31,$P50))*D50*C50/1000 -> 1.764 | H50: =(H$25/INDEX($C$27:$C$31,$P50))*D50*C50/1000 -> 1.764 | I50: =(I$25/INDEX($C$27:$C$31,$P50))*D50*C50/1000 -> 1.764 | J50: =(J$25/INDEX($C$27:$C$31,$P50))*D50*C50/1000 -> 1.764 | K50: =(K$25/INDEX($C$27:$C$31,$P50))*D50*C50/1000 -> 1.764 | L50: =(L$25/INDEX($C$27:$C$31,$P50))*D50*C50/1000 -> 1.764 | M50: =(M$25/INDEX($C$27:$C$31,$P50))*D50*C50/1000 -> 1.764 | N50: =(N$25/INDEX($C$27:$C$31,$P50))*D50*C50/1000 -> 1.764 | P50: 1
B51: Сливной фильтр | C51: 30.67 | D51: 2 | E51: =(E$25/INDEX($C$27:$C$31,$P51))*D51*C51/1000 -> 0.85876 | F51: =(F$25/INDEX($C$27:$C$31,$P51))*D51*C51/1000 -> 0.85876 | G51: =(G$25/INDEX($C$27:$C$31,$P51))*D51*C51/1000 -> 0.85876 | H51: =(H$25/INDEX($C$27:$C$31,$P51))*D51*C51/1000 -> 0.85876 | I51: =(I$25/INDEX($C$27:$C$31,$P51))*D51*C51/1000 -> 0.85876 | J51: =(J$25/INDEX($C$27:$C$31,$P51))*D51*C51/1000 -> 0.85876 | K51: =(K$25/INDEX($C$27:$C$31,$P51))*D51*C51/1000 -> 0.85876 | L51: =(L$25/INDEX($C$27:$C$31,$P51))*D51*C51/1000 -> 0.85876 | M51: =(M$25/INDEX($C$27:$C$31,$P51))*D51*C51/1000 -> 0.85876 | N51: =(N$25/INDEX($C$27:$C$31,$P51))*D51*C51/1000 -> 0.85876 | P51: 1
B52: Сливной фильтр насоса | C52: 201 | D52: 3 | E52: =(E$25/INDEX($C$27:$C$31,$P52))*D52*C52/1000 -> 8.442 | F52: =(F$25/INDEX($C$27:$C$31,$P52))*D52*C52/1000 -> 8.442 | G52: =(G$25/INDEX($C$27:$C$31,$P52))*D52*C52/1000 -> 8.442 | H52: =(H$25/INDEX($C$27:$C$31,$P52))*D52*C52/1000 -> 8.442 | I52: =(I$25/INDEX($C$27:$C$31,$P52))*D52*C52/1000 -> 8.442 | J52: =(J$25/INDEX($C$27:$C$31,$P52))*D52*C52/1000 -> 8.442 | K52: =(K$25/INDEX($C$27:$C$31,$P52))*D52*C52/1000 -> 8.442 | L52: =(L$25/INDEX($C$27:$C$31,$P52))*D52*C52/1000 -> 8.442 | M52: =(M$25/INDEX($C$27:$C$31,$P52))*D52*C52/1000 -> 8.442 | N52: =(N$25/INDEX($C$27:$C$31,$P52))*D52*C52/1000 -> 8.442 | P52: 1
B53: Смазка | C53: 12.24 | D53: 200 | E53: =(E$25/INDEX($C$27:$C$31,$P53))*D53*C53/1000 -> 34.272 | F53: =(F$25/INDEX($C$27:$C$31,$P53))*D53*C53/1000 -> 34.272 | G53: =(G$25/INDEX($C$27:$C$31,$P53))*D53*C53/1000 -> 34.272 | H53: =(H$25/INDEX($C$27:$C$31,$P53))*D53*C53/1000 -> 34.272 | I53: =(I$25/INDEX($C$27:$C$31,$P53))*D53*C53/1000 -> 34.272 | J53: =(J$25/INDEX($C$27:$C$31,$P53))*D53*C53/1000 -> 34.272 | K53: =(K$25/INDEX($C$27:$C$31,$P53))*D53*C53/1000 -> 34.272 | L53: =(L$25/INDEX($C$27:$C$31,$P53))*D53*C53/1000 -> 34.272 | M53: =(M$25/INDEX($C$27:$C$31,$P53))*D53*C53/1000 -> 34.272 | N53: =(N$25/INDEX($C$27:$C$31,$P53))*D53*C53/1000 -> 34.272 | P53: 1
B54: Топливный фильтр (ТО-2) | C54: 80.17 | D54: 2 | E54: =(E$25/INDEX($C$27:$C$31,$P54))*D54*C54/1000 -> 1.12238 | F54: =(F$25/INDEX($C$27:$C$31,$P54))*D54*C54/1000 -> 1.12238 | G54: =(G$25/INDEX($C$27:$C$31,$P54))*D54*C54/1000 -> 1.12238 | H54: =(H$25/INDEX($C$27:$C$31,$P54))*D54*C54/1000 -> 1.12238 | I54: =(I$25/INDEX($C$27:$C$31,$P54))*D54*C54/1000 -> 1.12238 | J54: =(J$25/INDEX($C$27:$C$31,$P54))*D54*C54/1000 -> 1.12238 | K54: =(K$25/INDEX($C$27:$C$31,$P54))*D54*C54/1000 -> 1.12238 | L54: =(L$25/INDEX($C$27:$C$31,$P54))*D54*C54/1000 -> 1.12238 | M54: =(M$25/INDEX($C$27:$C$31,$P54))*D54*C54/1000 -> 1.12238 | N54: =(N$25/INDEX($C$27:$C$31,$P54))*D54*C54/1000 -> 1.12238 | P54: 2
B55: Фильтр сапуна топл.бака | C55: 19.17 | D55: 1 | E55: =(E$25/INDEX($C$27:$C$31,$P55))*D55*C55/1000 -> 0.13419 | F55: =(F$25/INDEX($C$27:$C$31,$P55))*D55*C55/1000 -> 0.13419 | G55: =(G$25/INDEX($C$27:$C$31,$P55))*D55*C55/1000 -> 0.13419 | H55: =(H$25/INDEX($C$27:$C$31,$P55))*D55*C55/1000 -> 0.13419 | I55: =(I$25/INDEX($C$27:$C$31,$P55))*D55*C55/1000 -> 0.13419 | J55: =(J$25/INDEX($C$27:$C$31,$P55))*D55*C55/1000 -> 0.13419 | K55: =(K$25/INDEX($C$27:$C$31,$P55))*D55*C55/1000 -> 0.13419 | L55: =(L$25/INDEX($C$27:$C$31,$P55))*D55*C55/1000 -> 0.13419 | M55: =(M$25/INDEX($C$27:$C$31,$P55))*D55*C55/1000 -> 0.13419 | N55: =(N$25/INDEX($C$27:$C$31,$P55))*D55*C55/1000 -> 0.13419 | P55: 2
B56: Фильтр сапуна гидробака | C56: 19.17 | D56: 2 | E56: =(E$25/INDEX($C$27:$C$31,$P56))*D56*C56/1000 -> 0.26838 | F56: =(F$25/INDEX($C$27:$C$31,$P56))*D56*C56/1000 -> 0.26838 | G56: =(G$25/INDEX($C$27:$C$31,$P56))*D56*C56/1000 -> 0.26838 | H56: =(H$25/INDEX($C$27:$C$31,$P56))*D56*C56/1000 -> 0.26838 | I56: =(I$25/INDEX($C$27:$C$31,$P56))*D56*C56/1000 -> 0.26838 | J56: =(J$25/INDEX($C$27:$C$31,$P56))*D56*C56/1000 -> 0.26838 | K56: =(K$25/INDEX($C$27:$C$31,$P56))*D56*C56/1000 -> 0.26838 | L56: =(L$25/INDEX($C$27:$C$31,$P56))*D56*C56/1000 -> 0.26838 | M56: =(M$25/INDEX($C$27:$C$31,$P56))*D56*C56/1000 -> 0.26838 | N56: =(N$25/INDEX($C$27:$C$31,$P56))*D56*C56/1000 -> 0.26838 | P56: 2
B57: Гидравлический фильтр | C57: 344.33 | D57: 3 | E57: =(E$25/INDEX($C$27:$C$31,$P57))*D57*C57/1000 -> 7.23093 | F57: =(F$25/INDEX($C$27:$C$31,$P57))*D57*C57/1000 -> 7.23093 | G57: =(G$25/INDEX($C$27:$C$31,$P57))*D57*C57/1000 -> 7.23093 | H57: =(H$25/INDEX($C$27:$C$31,$P57))*D57*C57/1000 -> 7.23093 | I57: =(I$25/INDEX($C$27:$C$31,$P57))*D57*C57/1000 -> 7.23093 | J57: =(J$25/INDEX($C$27:$C$31,$P57))*D57*C57/1000 -> 7.23093 | K57: =(K$25/INDEX($C$27:$C$31,$P57))*D57*C57/1000 -> 7.23093 | L57: =(L$25/INDEX($C$27:$C$31,$P57))*D57*C57/1000 -> 7.23093 | M57: =(M$25/INDEX($C$27:$C$31,$P57))*D57*C57/1000 -> 7.23093 | N57: =(N$25/INDEX($C$27:$C$31,$P57))*D57*C57/1000 -> 7.23093 | P57: 2
B58: О-кольцо | C58: 24.5 | D58: 3 | E58: =(E$25/INDEX($C$27:$C$31,$P58))*D58*C58/1000 -> 0.5145 | F58: =(F$25/INDEX($C$27:$C$31,$P58))*D58*C58/1000 -> 0.5145 | G58: =(G$25/INDEX($C$27:$C$31,$P58))*D58*C58/1000 -> 0.5145 | H58: =(H$25/INDEX($C$27:$C$31,$P58))*D58*C58/1000 -> 0.5145 | I58: =(I$25/INDEX($C$27:$C$31,$P58))*D58*C58/1000 -> 0.5145 | J58: =(J$25/INDEX($C$27:$C$31,$P58))*D58*C58/1000 -> 0.5145 | K58: =(K$25/INDEX($C$27:$C$31,$P58))*D58*C58/1000 -> 0.5145 | L58: =(L$25/INDEX($C$27:$C$31,$P58))*D58*C58/1000 -> 0.5145 | M58: =(M$25/INDEX($C$27:$C$31,$P58))*D58*C58/1000 -> 0.5145 | N58: =(N$25/INDEX($C$27:$C$31,$P58))*D58*C58/1000 -> 0.5145 | P58: 2
... B73: Гидравлическое масло | C73: 6.43 | D73: 1300 | E73: =(E$25/INDEX($C$27:$C$31,$P73))*D73*C73/1000 -> 11.7026 | F73: =(F$25/INDEX($C$27:$C$31,$P73))*D73*C73/1000 -> 11.7026 | G73: =(G$25/INDEX($C$27:$C$31,$P73))*D73*C73/1000 -> 11.7026 | H73: =(H$25/INDEX($C$27:$C$31,$P73))*D73*C73/1000 -> 11.7026 | I73: =(I$25/INDEX($C$27:$C$31,$P73))*D73*C73/1000 -> 11.7026 | J73: =(J$25/INDEX($C$27:$C$31,$P73))*D73*C73/1000 -> 11.7026 | K73: =(K$25/INDEX($C$27:$C$31,$P73))*D73*C73/1000 -> 11.7026 | L73: =(L$25/INDEX($C$27:$C$31,$P73))*D73*C73/1000 -> 11.7026 | M73: =(M$25/INDEX($C$27:$C$31,$P73))*D73*C73/1000 -> 11.7026 | N73: =(N$25/INDEX($C$27:$C$31,$P73))*D73*C73/1000 -> 11.7026 | P73: 5
B74: Корректировка (поглощения/прочее) | E74: 0 | F74: 0 | G74: 0 | H74: 0 | I74: 0 | J74: 0 | K74: 0 | L74: 0 | M74: 0 | N74: 0
B75: ИТОГО затраты на запчасти ТО, тыс/год | E75: =SUM(E47:E74) -> 107.51972 | F75: =SUM(F47:F74) -> 107.51972 | G75: =SUM(G47:G74) -> 107.51972 | H75: =SUM(H47:H74) -> 107.51972 | I75: =SUM(I47:I74) -> 107.51972 | J75: =SUM(J47:J74) -> 107.51972 | K75: =SUM(K47:K74) -> 107.51972 | L75: =SUM(L47:L74) -> 107.51972 | ... N75: =SUM(N47:N74) -> 107.51972
B77: Ставка сервиса | C77: вал/ч·час | E77: 50
B79: РАСЧЁТ РЕМОНТОВ (из списков по периодичности замены узлов)
B80: Простои в текущих + капитальных ремонтах | C80: ч/год | E80: 786.13 | F80: 1924.36 | G80: 1682.92 | H80: 2228.84 | I80: 2239.02 | J80: 1794.52 | K80: 2025.05 | L80: 1519.78 | M80: 2468.19 | N80: 1663.35
B81: Коэффициент поглощения (0–1; 1=как у поставщика) | C81: коэф. | E81: 1
B83: ТЕКУЩИЕ РЕМОНТЫ — ЗАТРАТЫ НА ЗЧ (по ресурсу замены)
B84: Наименование | C84: стоим.замены,тыс | D84: ресурс, м/ч | E84: год 1 | F84: год 2 | G84: год 3 | H84: год 4 | I84: год 5 | J84: год 6 | K84: год 7 | L84: год 8 | M84: год 9 | N84: год 10
B86: ИТОГО | E86: =SUM(E85:E85) -> 0 | F86: =SUM(F85:F85) -> 0 | G86: =SUM(G85:G85) -> 0 | H86: =SUM(H85:H85) -> 0 | I86: =SUM(I85:I85) -> 0 | J86: =SUM(J85:J85) -> 0 | K86: =SUM(K85:K85) -> 0 | L86: =SUM(L85:L85) -> 0 | ... N86: =SUM(N85:N85) -> 0
B88: ТЕКУЩИЕ РЕМОНТЫ — ТРУДОЗАТРАТЫ (по ресурсу замены)
B89: Наименование | C89: нормо-час/событие | D89: ресурс, м/ч | E89: год 1 | F89: год 2 | G89: год 3 | H89: год 4 | I89: год 5 | J89: год 6 | K89: год 7 | L89: год 8 | M89: год 9 | N89: год 10
B91: ИТОГО | E91: =SUM(E90:E90) -> 0 | F91: =SUM(F90:F90) -> 0 | G91: =SUM(G90:G90) -> 0 | H91: =SUM(H90:H90) -> 0 | I91: =SUM(I90:I90) -> 0 | J91: =SUM(J90:J90) -> 0 | K91: =SUM(K90:K90) -> 0 | L91: =SUM(L90:L90) -> 0 | ... N91: =SUM(N90:N90) -> 0
B93: КАПИТАЛЬНЫЕ РЕМОНТЫ (ЦЕХ) — ЗАТРАТЫ НА ЗЧ (по ресурсу до замены узла)
B94: Наименование | C94: стоим.замены,тыс | D94: ресурс, м/ч | E94: год 1 | F94: год 2 | G94: год 3 | H94: год 4 | I94: год 5 | J94: год 6 | K94: год 7 | L94: год 8 | M94: год 9 | N94: год 10
B95: ДВС | C95: 1540.5749 | D95: 18000 | E95: =(INT($E$25*1/$D95)-INT($E$25*(1-1)/$D95))*$C95 -> 0 | F95: =(INT($E$25*2/$D95)-INT($E$25*(2-1)/$D95))*$C95 -> 0 | G95: =(INT($E$25*3/$D95)-INT($E$25*(3-1)/$D95))*$C95 -> 1540.5749 | H95: =(INT($E$25*4/$D95)-INT($E$25*(4-1)/$D95))*$C95 -> 0 | I95: =(INT($E$25*5/$D95)-INT($E$25*(5-1)/$D95))*$C95 -> 0 | J95: =(INT($E$25*6/$D95)-INT($E$25*(6-1)/$D95))*$C95 -> 1540.5749 | K95: =(INT($E$25*7/$D95)-INT($E$25*(7-1)/$D95))*$C95 -> 0 | L95: =(INT($E$25*8/$D95)-INT($E$25*(8-1)/$D95))*$C95 -> 1540.5749 | M95: =(INT($E$25*9/$D95)-INT($E$25*(9-1)/$D95))*$C95 -> 0 | N95: =(INT($E$25*10/$D95)-INT($E$25*(10-1)/$D95))*$C95 -> 0
B96: МУФТА РПН | C96: 54.7854 | D96: 18000 | E96: =(INT($E$25*1/$D96)-INT($E$25*(1-1)/$D96))*$C96 -> 0 | F96: =(INT($E$25*2/$D96)-INT($E$25*(2-1)/$D96))*$C96 -> 0 | G96: =(INT($E$25*3/$D96)-INT($E$25*(3-1)/$D96))*$C96 -> 54.7854 | H96: =(INT($E$25*4/$D96)-INT($E$25*(4-1)/$D96))*$C96 -> 0 | I96: =(INT($E$25*5/$D96)-INT($E$25*(5-1)/$D96))*$C96 -> 0 | J96: =(INT($E$25*6/$D96)-INT($E$25*(6-1)/$D96))*$C96 -> 54.7854 | K96: =(INT($E$25*7/$D96)-INT($E$25*(7-1)/$D96))*$C96 -> 0 | L96: =(INT($E$25*8/$D96)-INT($E$25*(8-1)/$D96))*$C96 -> 54.7854 | M96: =(INT($E$25*9/$D96)-INT($E$25*(9-1)/$D96))*$C96 -> 0 | N96: =(INT($E$25*10/$D96)-INT($E$25*(10-1)/$D96))*$C96 -> 0
B97: ПОДУШКИ ОПОРЫ ДВС | C97: 5.4114 | D97: 18000 | E97: =(INT($E$25*1/$D97)-INT($E$25*(1-1)/$D97))*$C97 -> 0 | F97: =(INT($E$25*2/$D97)-INT($E$25*(2-1)/$D97))*$C97 -> 0 | G97: =(INT($E$25*3/$D97)-INT($E$25*(3-1)/$D97))*$C97 -> 5.4114 | H97: =(INT($E$25*4/$D97)-INT($E$25*(4-1)/$D97))*$C97 -> 0 | I97: =(INT($E$25*5/$D97)-INT($E$25*(5-1)/$D97))*$C97 -> 0 | J97: =(INT($E$25*6/$D97)-INT($E$25*(6-1)/$D97))*$C97 -> 5.4114 | K97: =(INT($E$25*7/$D97)-INT($E$25*(7-1)/$D97))*$C97 -> 0 | L97: =(INT($E$25*8/$D97)-INT($E$25*(8-1)/$D97))*$C97 -> 5.4114 | M97: =(INT($E$25*9/$D97)-INT($E$25*(9-1)/$D97))*$C97 -> 0 | N97: =(INT($E$25*10/$D97)-INT($E$25*(10-1)/$D97))*$C97 -> 0
B98: ЦИЛИНДР СТРЕЛЫ 2 шт | C98: 114.7671 | D98: 12000 | E98: =(INT($E$25*1/$D98)-INT($E$25*(1-1)/$D98))*$C98 -> 0 | F98: =(INT($E$25*2/$D98)-INT($E$25*(2-1)/$D98))*$C98 -> 114.7671 | G98: =(INT($E$25*3/$D98)-INT($E$25*(3-1)/$D98))*$C98 -> 0 | H98: =(INT($E$25*4/$D98)-INT($E$25*(4-1)/$D98))*$C98 -> 114.7671 | I98: =(INT($E$25*5/$D98)-INT($E$25*(5-1)/$D98))*$C98 -> 0 | J98: =(INT($E$25*6/$D98)-INT($E$25*(6-1)/$D98))*$C98 -> 114.7671 | K98: =(INT($E$25*7/$D98)-INT($E$25*(7-1)/$D98))*$C98 -> 114.7671 | L98: =(INT($E$25*8/$D98)-INT($E$25*(8-1)/$D98))*$C98 -> 0 | M98: =(INT($E$25*9/$D98)-INT($E$25*(9-1)/$D98))*$C98 -> 114.7671 | N98: =(INT($E$25*10/$D98)-INT($E$25*(10-1)/$D98))*$C98 -> 0
B99: ЦИЛИНДР КОВША | C99: 21.049 | D99: 12000 | E99: =(INT($E$25*1/$D99)-INT($E$25*(1-1)/$D99))*$C99 -> 0 | F99: =(INT($E$25*2/$D99)-INT($E$25*(2-1)/$D99))*$C99 -> 21.049 | G99: =(INT($E$25*3/$D99)-INT($E$25*(3-1)/$D99))*$C99 -> 0 | H99: =(INT($E$25*4/$D99)-INT($E$25*(4-1)/$D99))*$C99 -> 21.049 | I99: =(INT($E$25*5/$D99)-INT($E$25*(5-1)/$D99))*$C99 -> 0 | J99: =(INT($E$25*6/$D99)-INT($E$25*(6-1)/$D99))*$C99 -> 21.049 | K99: =(INT($E$25*7/$D99)-INT($E$25*(7-1)/$D99))*$C99 -> 21.049 | L99: =(INT($E$25*8/$D99)-INT($E$25*(8-1)/$D99))*$C99 -> 0 | M99: =(INT($E$25*9/$D99)-INT($E$25*(9-1)/$D99))*$C99 -> 21.049 | N99: =(INT($E$25*10/$D99)-INT($E$25*(10-1)/$D99))*$C99 -> 0
B100: ЦИЛИНДР РУКОЯТИ | C100: 21.2862 | D100: 12000 | E100: =(INT($E$25*1/$D100)-INT($E$25*(1-1)/$D100))*$C100 -> 0 | F100: =(INT($E$25*2/$D100)-INT($E$25*(2-1)/$D100))*$C100 -> 21.2862 | G100: =(INT($E$25*3/$D100)-INT($E$25*(3-1)/$D100))*$C100 -> 0 | H100: =(INT($E$25*4/$D100)-INT($E$25*(4-1)/$D100))*$C100 -> 21.2862 | I100: =(INT($E$25*5/$D100)-INT($E$25*(5-1)/$D100))*$C100 -> 0 | J100: =(INT($E$25*6/$D100)-INT($E$25*(6-1)/$D100))*$C100 -> 21.2862 | K100: =(INT($E$25*7/$D100)-INT($E$25*(7-1)/$D100))*$C100 -> 21.2862 | L100: =(INT($E$25*8/$D100)-INT($E$25*(8-1)/$D100))*$C100 -> 0 | M100: =(INT($E$25*9/$D100)-INT($E$25*(9-1)/$D100))*$C100 -> 21.2862 | N100: =(INT($E$25*10/$D100)-INT($E$25*(10-1)/$D100))*$C100 -> 0
B101: ЦЕНТРАЛЬНЫЙ КОЛЛЕКТОР | C101: 4.8888 | D101: 12000 | E101: =(INT($E$25*1/$D101)-INT($E$25*(1-1)/$D101))*$C101 -> 0 | F101: =(INT($E$25*2/$D101)-INT($E$25*(2-1)/$D101))*$C101 -> 4.8888 | G101: =(INT($E$25*3/$D101)-INT($E$25*(3-1)/$D101))*$C101 -> 0 | H101: =(INT($E$25*4/$D101)-INT($E$25*(4-1)/$D101))*$C101 -> 4.8888 | I101: =(INT($E$25*5/$D101)-INT($E$25*(5-1)/$D101))*$C101 -> 0 | J101: =(INT($E$25*6/$D101)-INT($E$25*(6-1)/$D101))*$C101 -> 4.8888 | K101: =(INT($E$25*7/$D101)-INT($E$25*(7-1)/$D101))*$C101 -> 4.8888 | L101: =(INT($E$25*8/$D101)-INT($E$25*(8-1)/$D101))*$C101 -> 0 | M101: =(INT($E$25*9/$D101)-INT($E$25*(9-1)/$D101))*$C101 -> 4.8888 | N101: =(INT($E$25*10/$D101)-INT($E$25*(10-1)/$D101))*$C101 -> 0
B102: ГИДРОРАСПРЕДЕЛИТЕЛЬ ОСНОВНОЙ (3шт) | C102: 2035.4018 | D102: 24000 | E102: =(INT($E$25*1/$D102)-INT($E$25*(1-1)/$D102))*$C102 -> 0 | F102: =(INT($E$25*2/$D102)-INT($E$25*(2-1)/$D102))*$C102 -> 0 | G102: =(INT($E$25*3/$D102)-INT($E$25*(3-1)/$D102))*$C102 -> 0 | H102: =(INT($E$25*4/$D102)-INT($E$25*(4-1)/$D102))*$C102 -> 2035.4018 | I102: =(INT($E$25*5/$D102)-INT($E$25*(5-1)/$D102))*$C102 -> 0 | J102: =(INT($E$25*6/$D102)-INT($E$25*(6-1)/$D102))*$C102 -> 0 | K102: =(INT($E$25*7/$D102)-INT($E$25*(7-1)/$D102))*$C102 -> 2035.4018 | L102: =(INT($E$25*8/$D102)-INT($E$25*(8-1)/$D102))*$C102 -> 0 | M102: =(INT($E$25*9/$D102)-INT($E$25*(9-1)/$D102))*$C102 -> 0 | N102: =(INT($E$25*10/$D102)-INT($E$25*(10-1)/$D102))*$C102 -> 0
B103: РВД РАБОЧЕГО ОБОРУДОВАНИЯ | C103: 97.097 | D103: 12000 | E103: =(INT($E$25*1/$D103)-INT($E$25*(1-1)/$D103))*$C103 -> 0 | F103: =(INT($E$25*2/$D103)-INT($E$25*(2-1)/$D103))*$C103 -> 97.097 | G103: =(INT($E$25*3/$D103)-INT($E$25*(3-1)/$D103))*$C103 -> 0 | H103: =(INT($E$25*4/$D103)-INT($E$25*(4-1)/$D103))*$C103 -> 97.097 | I103: =(INT($E$25*5/$D103)-INT($E$25*(5-1)/$D103))*$C103 -> 0 | J103: =(INT($E$25*6/$D103)-INT($E$25*(6-1)/$D103))*$C103 -> 97.097 | K103: =(INT($E$25*7/$D103)-INT($E$25*(7-1)/$D103))*$C103 -> 97.097 | L103: =(INT($E$25*8/$D103)-INT($E$25*(8-1)/$D103))*$C103 -> 0 | M103: =(INT($E$25*9/$D103)-INT($E$25*(9-1)/$D103))*$C103 -> 97.097 | N103: =(INT($E$25*10/$D103)-INT($E$25*(10-1)/$D103))*$C103 -> 0
B104: РАДИАТОР ГИДРАВЛИЧЕСКИЙ | C104: 835.3987 | D104: 18000 | E104: =(INT($E$25*1/$D104)-INT($E$25*(1-1)/$D104))*$C104 -> 0 | F104: =(INT($E$25*2/$D104)-INT($E$25*(2-1)/$D104))*$C104 -> 0 | G104: =(INT($E$25*3/$D104)-INT($E$25*(3-1)/$D104))*$C104 -> 835.3987 | H104: =(INT($E$25*4/$D104)-INT($E$25*(4-1)/$D104))*$C104 -> 0 | I104: =(INT($E$25*5/$D104)-INT($E$25*(5-1)/$D104))*$C104 -> 0 | J104: =(INT($E$25*6/$D104)-INT($E$25*(6-1)/$D104))*$C104 -> 835.3987 | K104: =(INT($E$25*7/$D104)-INT($E$25*(7-1)/$D104))*$C104 -> 0 | L104: =(INT($E$25*8/$D104)-INT($E$25*(8-1)/$D104))*$C104 -> 835.3987 | M104: =(INT($E$25*9/$D104)-INT($E$25*(9-1)/$D104))*$C104 -> 0 | N104: =(INT($E$25*10/$D104)-INT($E$25*(10-1)/$D104))*$C104 -> 0
B105: РАДИАТОР ДВС | C105: 523.8867 | D105: 18000 | E105: =(INT($E$25*1/$D105)-INT($E$25*(1-1)/$D105))*$C105 -> 0 | F105: =(INT($E$25*2/$D105)-INT($E$25*(2-1)/$D105))*$C105 -> 0 | G105: =(INT($E$25*3/$D105)-INT($E$25*(3-1)/$D105))*$C105 -> 523.8867 | H105: =(INT($E$25*4/$D105)-INT($E$25*(4-1)/$D105))*$C105 -> 0 | I105: =(INT($E$25*5/$D105)-INT($E$25*(5-1)/$D105))*$C105 -> 0 | J105: =(INT($E$25*6/$D105)-INT($E$25*(6-1)/$D105))*$C105 -> 523.8867 | K105: =(INT($E$25*7/$D105)-INT($E$25*(7-1)/$D105))*$C105 -> 0 | L105: =(INT($E$25*8/$D105)-INT($E$25*(8-1)/$D105))*$C105 -> 523.8867 | M105: =(INT($E$25*9/$D105)-INT($E$25*(9-1)/$D105))*$C105 -> 0 | N105: =(INT($E$25*10/$D105)-INT($E$25*(10-1)/$D105))*$C105 -> 0
