Workbook

Sheet Методика
B1: МЕТОДИКА: АННУИТЕТ ЗАТРАТ (РУБ/ПОГ.М) НА ВЛАДЕНИЕ БУРОВЫМИ СТАНКАМИ
B2: Пост-налоговый погодовой дисконтированный аннуитет жизненного цикла.
C4: 1. НАЗНАЧЕНИЕ
C5: Экономическое сравнение буровых станков одного класса по удельному аннуитету затрат (руб/пог.м пробуренной скважины, а также руб/м³ взорванной горной массы) за полный срок эксплуатации. Метрика корректно сопоставляет станки с разной ценой, производительностью и структурой затрат. Лучший вариант — минимум руб/пог.м.
C6: 2. ПРОИЗВОДИТЕЛЬНОСТЬ (методика бурения из файла «W час»)
C7: Теоретическая скорость бурения = (0,1 × мощность вращателя) / (2,73^(0,017 × крепость породы) × диаметр_заряда²); диаметр заряда = диаметр долота × коэффициент разбура. Время цикла скважины = бурение + продувка + наращивание + подъём става + разбор + переезд. Скважин/смену = смена / время цикла. Часовая производительность (п.м/час) = скважин/смену × средняя глубина / смена. КИО = КТГ × (1 − простои_смены/(60 × смена)); эффективное время = КФВ × КИО. Годовой объём бурения (тыс.пог.м) = часовая × эффективное время; объём взрывания (тыс.м³) = бурение × выход м³/пог.м.
C8: 3. ПОГОДОВОЙ ДЕНЕЖНЫЙ ПОТОК (10 лет)
C9: Для каждого года считаются: топливо/энергия (эфф.время × расход × цена), ТОиР и сервис (задаются ПО ГОДАМ на листах «Поставщик N» — ТО, текущие и капитальные ремонты; годы капремонтов дают всплеск затрат), буровой инструмент (долота, штанги), расходники, персонал, транспортный налог. Добавляются амортизация (НУ) и налог на прибыль (щит). Операционный поток = база + налог − амортизация. Инвестиции — в год 0, остаточная стоимость — в конце срока.
C10: 4. АННУИТЕТ (ЯДРО)
C11: Потоки дисконтируются и преобразуются в эквивалентный годовой платёж: Аннуитет = NPV затрат / Σ(дисконт-факторов). Инвестиционный аннуитет = (Цена − дисконт. остаточная стоимость) / Σ(дисконт-факторов). Операционный аннуитет — приведённые эксплуатационные затраты после налога. Общий = инвестиционный + операционный. Удельный аннуитет (руб/пог.м) = общий аннуитет / средний годовой объём бурения (пог.м); руб/м³ = руб/пог.м / выход м³ с 1 пог.м.
C12: 5. ПОРЯДОК РАБОТЫ
C13: «Параметры» → «Ввод данных» (цена, физика бурения: мощность вращателя, диаметр, скорость СПО; персонал) → листы «Поставщик 1…5»: по каждой машине задаются КТГ, простои и затраты ТОиР по годам, расход ДТ, буровой инструмент — КТГ и ИТОГО ТОиР считаются автоматически. Сводка «Данные по годам» тянет итоги сама → авторасчёт «Производительность», «Денежный поток», «Расчёт аннуитета» → «Дашборд», «Сравнение», «Аналитика», «Чувствительность». Правки — в листах «Поставщик N» и «Ввод данных».
C14: 6. ДОПУЩЕНИЯ
C15: • Станки сравниваются в одном классе и одной задаче; разница в производительности учтена через руб/пог.м и руб/м³.
... C22: зелёные ячейки — итоговые показатели / лучший вариант

Sheet Дашборд
B1: ИТОГОВЫЙ ДАШБОРД — СРАВНЕНИЕ БУРОВЫХ СТАНКОВ
B2: Ключевые показатели и графики. Данные обновляются автоматически.
B4: КЛЮЧЕВЫЕ ПОКАЗАТЕЛИ
B5: Лучший вариант | C5: Мин. аннуитет, руб/пог.м | D5: Мин. NPV владения, тыс.руб | E5: Разброс аннуитета, руб/пог.м
B6: =INDEX('Ввод данных'!D7:H7,MATCH(MIN('Расчёт аннуитета'!D30:H30),'Расчёт аннуитета'!D30:H30,0)) -> Sunward SWDRT270SM | C6: =MIN('Расчёт аннуитета'!D30:H30) -> 744.1213 | D6: =MIN('Расчёт аннуитета'!D16:H16) -> 492152.25 | E6: =MAX('Расчёт аннуитета'!D30:H30)-MIN('Расчёт аннуитета'!D30:H30) -> 328.88571
B8: РЕЙТИНГ ПО УДЕЛЬНОМУ АННУИТЕТУ (руб/пог.м)
B9: Место | C9: Буровой станок | G9: руб/пог.м | I9: руб/м³
B10: 1 | C10: =INDEX('Ввод данных'!D7:H7,MATCH(SMALL('Расчёт аннуитета'!D30:H30,1),'Расчёт аннуитета'!D30:H30,0)) -> Sunward SWDRT270SM | G10: =SMALL('Расчёт аннуитета'!D30:H30,1) -> 744.1213 | I10: =INDEX('Расчёт аннуитета'!$D$32:$H$32,MATCH(SMALL('Расчёт аннуитета'!D30:H30,1),'Расчёт аннуитета'!D30:H30,0)) -> 15.04339
B11: 2 | C11: =INDEX('Ввод данных'!D7:H7,MATCH(SMALL('Расчёт аннуитета'!D30:H30,2),'Расчёт аннуитета'!D30:H30,0)) -> YANGZI DR75 (аналог Epiroc DM75) | G11: =SMALL('Расчёт аннуитета'!D30:H30,2) -> 802.33746 | I11: =INDEX('Расчёт аннуитета'!$D$32:$H$32,MATCH(SMALL('Расчёт аннуитета'!D30:H30,2),'Расчёт аннуитета'!D30:H30,0)) -> 16.220307
B12: 3 | C12: =INDEX('Ввод данных'!D7:H7,MATCH(SMALL('Расчёт аннуитета'!D30:H30,3),'Расчёт аннуитета'!D30:H30,0)) -> Sunward SWDRT250SM | G12: =SMALL('Расчёт аннуитета'!D30:H30,3) -> 831.8363 | I12: =INDEX('Расчёт аннуитета'!$D$32:$H$32,MATCH(SMALL('Расчёт аннуитета'!D30:H30,3),'Расчёт аннуитета'!D30:H30,0)) -> 16.816664
B13: 4 | C13: =INDEX('Ввод данных'!D7:H7,MATCH(SMALL('Расчёт аннуитета'!D30:H30,4),'Расчёт аннуитета'!D30:H30,0)) -> Sunward SWDRT270B | G13: =SMALL('Расчёт аннуитета'!D30:H30,4) -> 904.32091 | I13: =INDEX('Расчёт аннуитета'!$D$32:$H$32,MATCH(SMALL('Расчёт аннуитета'!D30:H30,4),'Расчёт аннуитета'!D30:H30,0)) -> 18.282036
B14: 5 | C14: =INDEX('Ввод данных'!D7:H7,MATCH(SMALL('Расчёт аннуитета'!D30:H30,5),'Расчёт аннуитета'!D30:H30,0)) -> HIFO 75D (аналог DM75) | G14: =SMALL('Расчёт аннуитета'!D30:H30,5) -> 1073.007 | I14: =INDEX('Расчёт аннуитета'!$D$32:$H$32,MATCH(SMALL('Расчёт аннуитета'!D30:H30,5),'Расчёт аннуитета'!D30:H30,0)) -> 21.692247

Sheet Выводы
B1: ВЫВОДЫ: СРАВНЕНИЕ ДВУХ ВЕРСИЙ И ПРИЧИНЫ РАЗНИЦЫ В АННУИТЕТЕ
B2: Класс 250–270 мм (дизель), карьер «Сухой Лог». Сопоставление одноклассников; сравнение с корпоративными файлами 000_БСЛ-2027.
B4: 1. Общий аннуитет по версиям (руб/м³ взорванной горной массы) — меньше = лучше
B5: Станок | C5: ПОСТАВЩИК | D5: ПРОИЗВОДИТЕЛЬ | E5: Δ (пр−пост) | F5: Δ, % | G5: Ориентир 000_БСЛ
B6: YANGZI DR75 | C6: 20.8 | D6: 16.22 | E6: -4.58 | F6: -0.22019231 | G6: 21.09 / 16.47
B7: Sunward SWDRT250SM | C7: 17.4 | D7: 16.82 | E7: -0.58 | F7: -0.033333333 | G7: 17.93 / 17.29
B8: Sunward SWDRT270SM | C8: 15.58 | D8: 15.04 | E8: -0.54 | F8: -0.03465982 | G8: 16.05 / 15.47
B9: Sunward SWDRT270B | C9: 16.98 | D9: 18.28 | E9: 1.3 | F9: 0.07656066 | G9: 17.51 / 18.51
B10: HIFO 75D | C10: 21.73 | D10: 21.69 | E10: -0.04 | F10: -0.0018407731 | G10: 21.98 / 21.98
B11: Ориентир 000_БСЛ = поставщик / производитель (руб/м³).
B29: 2. Причины разницы версий (что именно меняется у одноклассника)
B30: Станок | C30: Срок службы | D30: КТГ средний | E30: ТОиР, млн руб/год | F30: Главный драйвер Δ аннуитета
B31: YANGZI DR75 | C31: 10 → 12 | D31: 0.86 → 0.91 | E31: 50.3 → 28.4 | F31: срок службы 10→12 лет и ТОиР −44% (28,4 vs 50,3 млн руб) → минус ≈4,6 руб/м³
B32: Sunward SWDRT250SM | C32: 10 → 12 | D32: 0.86 → 0.86 | E32: 50.1 → 49.0 | F32: срок службы 10→12 лет; ТОиР почти без изменений → минус ≈0,6 руб/м³
B33: Sunward SWDRT270SM | C33: 10 → 12 | D33: 0.86 → 0.86 | E33: 50.1 → 49.0 | F33: срок службы 10→12 лет; ТОиР почти без изменений → минус ≈0,6 руб/м³
B34: Sunward SWDRT270B | C34: 10 → 12 | D34: 0.86 → 0.90 | E34: 50.1 → 69.6 | F34: срок службы 10→12 лет, НО ТОиР +39% (69,6 vs 50,1 млн руб) → плюс ≈1,0 руб/м³
B35: HIFO 75D | C35: 10 → 10 | D35: 0.86 → 0.86 | E35: 50.3 → 50.3 | F35: все допущения идентичны (10 лет, КТГ 0,86, ТОиР 50,3 млн) → без изменений
B37: 3. Выводы
B38: • Обе версии считают ОДИН класс станков (250–270 мм, дизель) — сравнение только одноклассников. Разница между версиями — это разница ДОПУЩЕНИЙ, а не самих машин: физика бурения, цены и объёмы у обеих версий одинаковы.
B39: • ВЕРСИЯ «ПОСТАВЩИК» — консервативный единый норматив: срок 10 лет у всех, КТГ 0,86 у всех, ТОиР усреднён ≈50 млн руб/год. Годится для быстрого отсева и «защиты снизу».
B40: • ВЕРСИЯ «ПРОИЗВОДИТЕЛЬ» — паспортные данные: срок службы 12 лет (кроме HIFO — 10), фактический КТГ (0,90–0,91 у DR75/270B) и ДИФФЕРЕНЦИРОВАННЫЙ ТОиР по узловому ресурсу. Точнее отражает экономику владения.
B41: • Ключевой драйвер разницы — ТОиР и срок службы, а НЕ производительность: у DR75 переход к паспорту снижает аннуитет на ≈4,6 руб/м³ (−22%) за счёт низкого ТОиР 28 млн и ресурса 12 лет; у 270B, наоборот, аннуитет РАСТЁТ на ≈1,0 руб/м³ из-за высокого паспортного ТОиР 69,6 млн руб/год.
B42: • Срок службы 10→12 лет влияет в основном на ИНВЕСТИЦИОННЫЙ аннуитет (CAPEX распределяется на больший объём), операционный аннуитет от срока почти не зависит — поэтому эффект срока умеренный и одинаков по знаку у всех.
B43: • HIFO 75D в обеих версиях идентичен (10 лет, КТГ 0,86, ТОиР 50,3 млн) — контрольная точка: аннуитет 21,7–22,0 руб/м³ совпадает.
B44: • Итоговый рейтинг устойчив: лучшие — Sunward 270SM и 270B; DR75 сильно зависит от того, чьим данным по ТОиР доверять.
B45: 4. Методические расхождения с корпоративным файлом (учтены)
B46: • Долота, штанги и расходники в файлах 000_БСЛ-2027 НЕ котировались ни одним поставщиком (строки = 0). В модели они также обнулены — иначе частичные данные ТКП только по DR75 завышали бы аннуитет одного станка и делали сравнение несимметричным.
B47: • ТОиР калиброван «коэффициентом калибровки» под целевой уровень корпоративного файла (тыс.руб/год) отдельно для каждой версии; детальный узловой каталог (ресурс в м/ч) взят по HIFO 75D как классовому шаблону.
B48: • Расхождение модели с ориентиром 000_БСЛ — в пределах ≈1–3 руб/м³ (2–4%): источник — незначительная разница выхода м³/пог.м (49,5 в модели vs 47,4 в файле) и профиля дисконтирования «рваного» графика капремонтов. Ранжирование и знак межверсионной разницы полностью совпадают.
B49: • Транспортный налог и долота/штанги = 0 (нет данных); при получении котировок заменить в жёлтых ячейках листа «Ввод данных».

Sheet Параметры
B1: ГЛОБАЛЬНЫЕ ПАРАМЕТРЫ МОДЕЛИ
B2: Единые допущения для всех вариантов. Жёлтые ячейки — ввод.
B4: Финансовые допущения
B5: Параметр | C5: Значение | D5: Ед. | E5: Комментарий
B6: Ставка дисконтирования (WACC) | C6: 0.12 | D6: %/год | E6: Стоимость капитала для приведения к текущей стоимости
B7: Налог на прибыль | C7: 0.25 | D7: % | E7: Формирует налоговый щит на затраты и амортизацию
B8: Срок эксплуатации (горизонт) | C8: 10 | D8: лет | E8: Фиксирован = 10 лет в погодовом движке
B9: Срок амортизации (налоговый учёт) | C9: 5.083 | D9: лет | E9: Линейная; 61 мес ≈ 5,08 года (как в исходной модели)
B10: Цена дизельного топлива | C10: 66.019 | D10: тыс.руб/т | E10: СЛ 2025: 1 274 749,9 тыс.руб / 19 308,86 т
B11: Цена электроэнергии | C11: 5.133 | D11: руб/кВт·ч | E11: Для электрических станков (СЛ 2025)
B13: Эскалация цен (реальный/номинальный рост)
B14: Параметр | C14: Значение | D14: Ед. | E14: Комментарий
B15: Эскалация цены топлива/энергии | C15: 0 | D15: %/год | E15: 0 = данные уже с учётом инфляции
B16: Эскалация ЗЧ/инструмента/расходников | C16: 0 | D16: %/год | E16: ТОиР задаётся по годам напрямую
B17: Эскалация оплаты труда | C17: 0 | D17: %/год | E17: Рост ФОТ экипажей
B19: Курсы валют
B20: Параметр | C20: Значение | D20: Ед. | E20: Комментарий
B21: Курс юаня (CNY) | C21: 11 | D21: руб | E21: Для оборудования из Китая
B22: Курс доллара (USD) | C22: 80 | D22: руб
B23: Курс евро (EUR) | C23: 90 | D23: руб
B25: Параметры производительности (карьер / буровзрывные работы)
B26: Параметр | C26: Значение | D26: Ед. | E26: Комментарий
B27: Календарный фонд времени | C27: 8760 | D27: час/год | E27: 24 ч × 365 дн
B28: Длительность смены | C28: 12 | D28: час | E28: Для пересчёта простоев и производительности
B29: Предел прочности породы на сжатие | C29: 130 | D29: МПа | E29: Влияет на скорость бурения (крепость f)
B30: Коэффициент разбура | C30: 1.05 | D30: коэф. | E30: Диаметр заряда = диаметр долота × k_разбура
B31: Средняя глубина скважин | C31: 16.16 | D31: м | E31: (гл.руда×доля + гл.вскрыша×доля); из «W час»
B32: КПД скорости подъёма става | C32: 0.8 | D32: коэф. | E32: Фактическая скорость = паспортная × КПД
B33: Время продувки скважины | C33: 2 | D33: мин | E33: Часть цикла бурения одной скважины
B34: Время переезда между скважинами | C34: 2.5 | D34: мин | E34: Часть цикла бурения одной скважины
B35: Выход горной массы с 1 пог.м скважины | C35: 49.465 | D35: м³/пог.м | E35: Для пересчёта руб/пог.м → руб/м³ (сетка БВР)
B37: Расчётные финансовые коэффициенты
B38: Параметр | C38: Значение | D38: Ед. | E38: Комментарий
B39: Коэф. аннуитета Σдиск.факторов (r, N) | C39: =IF('Параметры'!C6=0,'Параметры'!C8,(1-(1+'Параметры'!C6)^-'Параметры'!C8)/'Параметры'!C6) -> 5.650223 | D39: коэф. | E39: Сумма дисконт-факторов за срок службы
B40: Коэф. приведённой амортизации | C40: =(1/'Параметры'!C9)*((1-(1+'Параметры'!C6)^-INT('Параметры'!C9))/'Параметры'!C6+('Параметры'!C9-INT('Параметры'!C9))*(1+'Параметры'!C6)^-(INT('Параметры'!C9)+1)) -> 0.71745555 | D40: коэф. | E40: Приведённая амортизация на 1 руб. цены (налог. щит)
B42: Легенда: | D42: — ввод данных
D43: — расчётные показатели

Sheet Ввод данных
B1: ВВОД ИСХОДНЫХ ДАННЫХ ПО БУРОВЫМ СТАНКАМ
B2: Сравнение до 5 машин одного класса. Пример: станки класса 250–270 мм (дизель), карьер «Сухой Лог».
B4: Показатель | C4: Ед. | D4: Станок 1 | E4: Станок 2 | F4: Станок 3 | G4: Станок 4 | H4: Станок 5 | K4: Пояснение
B6: A. ИДЕНТИФИКАЦИЯ
B7: Наименование / модель | C7: — | D7: YANGZI DR75 (аналог Epiroc DM75) | E7: Sunward SWDRT250SM | F7: Sunward SWDRT270SM | G7: Sunward SWDRT270B | H7: HIFO 75D (аналог DM75) | K7: Название варианта
B8: Поставщик | C8: — | D8: Огунвей | E8: Стройкомпозит-Н | F8: Стройкомпозит-Н | G8: Огунвей | H8: Майнинг Солюшнс
B9: Двигатель / привод | C9: — | D9: Cummins QSK19 | E9: CAT C27 | F9: CAT C27 | G9: CAT C27 | H9: CAT C27
B10: B. СТОИМОСТЬ И ОСТАТОЧНАЯ ЦЕНА
B11: Цена за единицу | C11: тыс.вал. | D11: 207820 | E11: 138793 | F11: 147750 | G11: 206000 | H11: 236876 | K11: ⚠ В файле поставщика цена не указана — ОЦЕНКА, уточнить
B12: Валюта цены | C12: — | D12: RUB | E12: RUB | F12: RUB | G12: RUB | H12: RUB | K12: CNY / USD / EUR / RUB
B13: Монтаж, доставка, ПНР | C13: тыс.руб | D13: 0 | E13: 0 | F13: 0 | G13: 0 | H13: 0 | K13: Дополнительно к цене
B14: Остаточная стоимость | C14: % от цены | D14: 0 | E14: 0 | F14: 0 | G14: 0 | H14: 0 | K14: Реализация в конце срока (0 = не учитывать)
B15: C. ПРОИЗВОДИТЕЛЬНОСТЬ (физика бурения — лист «W час»)
B16: Мощность вращателя (в расчёте) | C16: кВт | D16: 136 | E16: 148.3 | F16: 173.4 | G16: 173.4 | H16: 136 | K16: Ключевой драйвер скорости бурения
B17: Диаметр долота (в расчёте) | C17: м | D17: 0.267 | E17: 0.267 | F17: 0.267 | G17: 0.267 | H17: 0.267 | K17: Диаметр заряда = диаметр × k_разбура
B18: Скорость подъёма става | C18: м/мин | D18: 51.5 | E18: 60 | F18: 45 | G18: 45 | H18: 51.5 | K18: Влияет на время СПО
B19: Время наращивания/разбора става | C19: мин | D19: 1.5 | E19: 1.5 | F19: 1.5 | G19: 1.5 | H19: 1.5 | K19: На одну операцию
B20: Кол-во операций свинчивания | C20: ед. | D20: 1 | E20: 1 | F20: 1 | G20: 1 | H20: 1 | K20: Штанг на скважину − 1
B21: D. ПРОЧИЕ ГОДОВЫЕ ЗАТРАТЫ И ПАРАМЕТРЫ
B22: Расходы на персонал (экипаж) | C22: тыс.руб/год | D22: 15710 | E22: 15710 | F22: 15710 | G22: 15710 | H22: 15710 | K22: ФОТ+отчисления+прочее на 1 машину
B23: Мощность двигателя (транспортный налог) | C23: л.с. | D23: 800 | E23: 800 | F23: 800 | G23: 800 | H23: 811.69 | K23: × ставку налога (руб/л.с.)
B24: ℹ КТГ, простои, затраты на ТОиР (ТО/ТР/капремонты/сервис), удельный расход ДТ, буровой инструмент и расходники задаются ПО ГОДАМ на листах «Поставщик 1…5». Сводка — на листе «Данные по годам».

Sheet Поставщик 1
B1: ДАННЫЕ ПОСТАВЩИКА — ВАРИАНТ 1 (ТО и Ремонты — модель по узлам)
B2: Жёлтое — ввод. Зелёное — авто (снизу вверх). ИТОГО ТОиР = (ЗЧ ТО + ЗЧ тек.+кап.ремонтов + сервис) × коэф.калибровки; тянется в «Данные по годам».
B4: Буровой станок: | E4: ='Ввод данных'!D7 -> YANGZI DR75 (аналог Epiroc DM75)
B5: Валюта затрат ТОиР: | D5: EUR
B6: Показатель | C6: Ед. | E6: год 1 | F6: год 2 | G6: год 3 | H6: год 4 | I6: год 5 | J6: год 6 | K6: год 7 | L6: год 8 | M6: год 9 | N6: год 10
B7: СВОДКА ПО ГОДАМ (зелёное — авто снизу вверх; тянется в расчёт)
B8: Простои на ТО (авто из интервалов) | C8: ч/год | E8: =E40 -> 636.37233 | F8: =F40 -> 636.37233 | G8: =G40 -> 636.37233 | H8: =H40 -> 636.37233 | I8: =I40 -> 636.37233 | J8: =J40 -> 636.37233 | K8: =K40 -> 636.37233 | L8: =L40 -> 636.37233 | ... N8: =N40 -> 636.37233
B9: Простои в ремонтах (справочно) | C9: ч/год | E9: 200 | F9: 300 | G9: 200 | H9: 300 | I9: 600 | J9: 300 | K9: 900 | L9: 300 | M9: 200 | N9: 900
B10: Ежесменный осмотр (20 мин/смену), справочно | C10: ч/год | E10: =('Параметры'!C27-E8-E9)/'Параметры'!C28*20/60 -> 220.10077 | F10: =('Параметры'!C27-F8-F9)/'Параметры'!C28*20/60 -> 217.32299 | G10: =('Параметры'!C27-G8-G9)/'Параметры'!C28*20/60 -> 220.10077 | H10: =('Параметры'!C27-H8-H9)/'Параметры'!C28*20/60 -> 217.32299 | I10: =('Параметры'!C27-I8-I9)/'Параметры'!C28*20/60 -> 208.98966 | J10: =('Параметры'!C27-J8-J9)/'Параметры'!C28*20/60 -> 217.32299 | K10: =('Параметры'!C27-K8-K9)/'Параметры'!C28*20/60 -> 200.65632 | L10: =('Параметры'!C27-L8-L9)/'Параметры'!C28*20/60 -> 217.32299 | M10: =('Параметры'!C27-M8-M9)/'Параметры'!C28*20/60 -> 220.10077 | N10: =('Параметры'!C27-N8-N9)/'Параметры'!C28*20/60 -> 200.65632
B11: КТГ (техготовность, ВВОД) → «Данные по годам» | C11: коэф. | E11: 0.9309 | F11: 0.9172 | G11: 0.9309 | H11: 0.9172 | I11: 0.8865 | J11: 0.9172 | K11: 0.8506 | L11: 0.9198 | M11: 0.9283 | N11: 0.8532
B12: Затраты на ЗЧ ТО (авто из каталога) | C12: тыс.вал/г | E12: =E85 -> 136.07379 | F12: =F85 -> 136.07379 | G12: =G85 -> 136.07379 | H12: =H85 -> 136.07379 | I12: =I85 -> 136.07379 | J12: =J85 -> 136.07379 | K12: =K85 -> 136.07379 | L12: =L85 -> 136.07379 | ... N12: =N85 -> 136.07379
B13: Затраты на ЗЧ текущих ремонтов (по ресурсу) | C13: тыс.вал/г | E13: =E105 -> 4.50682 | F13: =F105 -> 60.10984 | G13: =G105 -> 145.1624 | H13: =H105 -> 60.10984 | I13: =I105 -> 144.82518 | J13: =J105 -> 67.22701 | K13: =K105 -> 145.21432 | L13: =L105 -> 60.05792 | ... N13: =N105 -> 105.58931
B14: Затраты на ЗЧ капремонтов (по ресурсу) | C14: тыс.вал/г | E14: =E188 -> 7.38238 | F14: =F188 -> 204.26495 | G14: =G188 -> 438.81584 | H14: =H188 -> 434.86339 | I14: =I188 -> 610.36746 | J14: =J188 -> 366.36175 | K14: =K188 -> 590.25823 | L14: =L188 -> 224.66392 | ... N14: =N188 -> 283.30237
B15: Трудозатраты ТО (авто) | C15: ч-час/г | E15: =E47 -> 636.37233 | F15: =F47 -> 636.37233 | G15: =G47 -> 636.37233 | H15: =H47 -> 636.37233 | I15: =I47 -> 636.37233 | J15: =J47 -> 636.37233 | K15: =K47 -> 636.37233 | L15: =L47 -> 636.37233 | ... N15: =N47 -> 636.37233
B16: Трудозатраты текущих ремонтов (авто) | C16: ч-час/г | E16: =E125 -> 48.4 | F16: =F125 -> 174.3 | G16: =G125 -> 228.3 | H16: =H125 -> 174.3 | I16: =I125 -> 220.4 | J16: =J125 -> 255.8 | K16: =K125 -> 226.3 | L16: =L125 -> 176.3 | ... N16: =N125 -> 365.3
B17: Трудозатраты капремонтов (авто) | C17: ч-час/г | E17: =E251 -> 36.6 | F17: =F251 -> 192.66 | G17: =G251 -> 330.45 | H17: =H251 -> 188.56 | I17: =I251 -> 267.75 | J17: =J251 -> 319.96 | K17: =K251 -> 300.71 | L17: =L251 -> 155.4 | ... N17: =N251 -> 102.4
B18: Сервис (трудозатраты ТО+ТР+КР) | C18: тыс.вал/г | E18: =(E15+E16+E17)*$E$23/1000 -> 41.762927 | F18: =(F15+F16+F17)*$E$23/1000 -> 58.086639 | G18: =(G15+G16+G17)*$E$23/1000 -> 69.190076 | H18: =(H15+H16+H17)*$E$23/1000 -> 57.849275 | I18: =(I15+I16+I17)*$E$23/1000 -> 65.102779 | J18: =(J15+J16+J17)*$E$23/1000 -> 70.174848 | K18: =(K15+K16+K17)*$E$23/1000 -> 67.352529 | L18: =(L15+L16+L17)*$E$23/1000 -> 56.045307 | ... N18: =(N15+N16+N17)*$E$23/1000 -> 63.918853
B19: Коэффициент калибровки ИТОГО под ТКП | C19: коэф. | E19: 0.4943
B20: ИТОГО ТОиР → «Данные по годам» | C20: тыс.вал/г | E20: =(E12+E13+E14+E18)*$E$19 -> 93.78152 | F20: =(F12+F13+F14+F18)*$E$19 -> 226.65396 | G20: =(G12+G13+G14+G18)*$E$19 -> 390.12237 | H20: =(H12+H13+H14+H18)*$E$19 -> 340.52144 | I20: =(I12+I13+I14+I18)*$E$19 -> 472.7333 | J20: =(J12+J13+J14+J18)*$E$19 -> 316.27162 | K20: =(K12+K13+K14+K18)*$E$19 -> 464.09771 | L20: =(L12+L13+L14+L18)*$E$19 -> 235.70247 | ... N20: =(N12+N13+N14+N18)*$E$19 -> 291.08552
B21: Удельный расход ДТ / энергии | C21: кг(кВт)/час | E21: 74.75 | F21: 74.75 | G21: 74.75 | H21: 74.75 | I21: 74.75 | J21: 74.75 | K21: 74.75 | L21: 74.75 | M21: 74.75 | N21: 74.75
B23: Ставка сервиса | C23: вал/ч·час | E23: 57.893718
B24: РАСЧЁТ ТО (по интервалам обслуживания), ПО ГОДАМ
B25: Наработка по годам | C25: м/час | E25: 7000 | F25: 7000 | G25: 7000 | H25: 7000 | I25: 7000 | J25: 7000 | K25: 7000 | L25: 7000 | M25: 7000 | N25: 7000
B26: Вид ТО | C26: интервал, м/ч | D26: простой/ТО, ч | E26: персонал
B27: ТО-1 | C27: 250 | D27: 10.9 | E27: 1
B28: ТО-2 | C28: 500 | D28: 13.5 | E28: 1
B29: ТО-3 | C29: 1000 | D29: 12.43 | E29: 1
B30: ТО-4 | C30: 2000 | D30: 5.67 | E30: 1
B31: ТО-5 | C31: 3000 | D31: 10.06 | E31: 1
B32: ТО-6 | C32: 5000 | D32: 8.46 | E32: 1
B34: ТО-1: простои, ч/год | C34: ч | E34: =E$25/$C27*$D27 -> 305.2 | F34: =F$25/$C27*$D27 -> 305.2 | G34: =G$25/$C27*$D27 -> 305.2 | H34: =H$25/$C27*$D27 -> 305.2 | I34: =I$25/$C27*$D27 -> 305.2 | J34: =J$25/$C27*$D27 -> 305.2 | K34: =K$25/$C27*$D27 -> 305.2 | L34: =L$25/$C27*$D27 -> 305.2 | ... N34: =N$25/$C27*$D27 -> 305.2
B35: ТО-2: простои, ч/год | C35: ч | E35: =E$25/$C28*$D28 -> 189 | F35: =F$25/$C28*$D28 -> 189 | G35: =G$25/$C28*$D28 -> 189 | H35: =H$25/$C28*$D28 -> 189 | I35: =I$25/$C28*$D28 -> 189 | J35: =J$25/$C28*$D28 -> 189 | K35: =K$25/$C28*$D28 -> 189 | L35: =L$25/$C28*$D28 -> 189 | ... N35: =N$25/$C28*$D28 -> 189
B36: ТО-3: простои, ч/год | C36: ч | E36: =E$25/$C29*$D29 -> 87.01 | F36: =F$25/$C29*$D29 -> 87.01 | G36: =G$25/$C29*$D29 -> 87.01 | H36: =H$25/$C29*$D29 -> 87.01 | I36: =I$25/$C29*$D29 -> 87.01 | J36: =J$25/$C29*$D29 -> 87.01 | K36: =K$25/$C29*$D29 -> 87.01 | L36: =L$25/$C29*$D29 -> 87.01 | ... N36: =N$25/$C29*$D29 -> 87.01
B37: ТО-4: простои, ч/год | C37: ч | E37: =E$25/$C30*$D30 -> 19.845 | F37: =F$25/$C30*$D30 -> 19.845 | G37: =G$25/$C30*$D30 -> 19.845 | H37: =H$25/$C30*$D30 -> 19.845 | I37: =I$25/$C30*$D30 -> 19.845 | J37: =J$25/$C30*$D30 -> 19.845 | K37: =K$25/$C30*$D30 -> 19.845 | L37: =L$25/$C30*$D30 -> 19.845 | ... N37: =N$25/$C30*$D30 -> 19.845
B38: ТО-5: простои, ч/год | C38: ч | E38: =E$25/$C31*$D31 -> 23.473333 | F38: =F$25/$C31*$D31 -> 23.473333 | G38: =G$25/$C31*$D31 -> 23.473333 | H38: =H$25/$C31*$D31 -> 23.473333 | I38: =I$25/$C31*$D31 -> 23.473333 | J38: =J$25/$C31*$D31 -> 23.473333 | K38: =K$25/$C31*$D31 -> 23.473333 | L38: =L$25/$C31*$D31 -> 23.473333 | ... N38: =N$25/$C31*$D31 -> 23.473333
B39: ТО-6: простои, ч/год | C39: ч | E39: =E$25/$C32*$D32 -> 11.844 | F39: =F$25/$C32*$D32 -> 11.844 | G39: =G$25/$C32*$D32 -> 11.844 | H39: =H$25/$C32*$D32 -> 11.844 | I39: =I$25/$C32*$D32 -> 11.844 | J39: =J$25/$C32*$D32 -> 11.844 | K39: =K$25/$C32*$D32 -> 11.844 | L39: =L$25/$C32*$D32 -> 11.844 | ... N39: =N$25/$C32*$D32 -> 11.844
B40: Итого простои ТО | E40: =SUM(E34:E39) -> 636.37233 | F40: =SUM(F34:F39) -> 636.37233 | G40: =SUM(G34:G39) -> 636.37233 | H40: =SUM(H34:H39) -> 636.37233 | I40: =SUM(I34:I39) -> 636.37233 | J40: =SUM(J34:J39) -> 636.37233 | K40: =SUM(K34:K39) -> 636.37233 | L40: =SUM(L34:L39) -> 636.37233 | ... N40: =SUM(N34:N39) -> 636.37233
B41: ТО-1: чел-часы/год | C41: ч-час | E41: =E34*$E27 -> 305.2 | F41: =F34*$E27 -> 305.2 | G41: =G34*$E27 -> 305.2 | H41: =H34*$E27 -> 305.2 | I41: =I34*$E27 -> 305.2 | J41: =J34*$E27 -> 305.2 | K41: =K34*$E27 -> 305.2 | L41: =L34*$E27 -> 305.2 | ... N41: =N34*$E27 -> 305.2
B42: ТО-2: чел-часы/год | C42: ч-час | E42: =E35*$E28 -> 189 | F42: =F35*$E28 -> 189 | G42: =G35*$E28 -> 189 | H42: =H35*$E28 -> 189 | I42: =I35*$E28 -> 189 | J42: =J35*$E28 -> 189 | K42: =K35*$E28 -> 189 | L42: =L35*$E28 -> 189 | ... N42: =N35*$E28 -> 189
B43: ТО-3: чел-часы/год | C43: ч-час | E43: =E36*$E29 -> 87.01 | F43: =F36*$E29 -> 87.01 | G43: =G36*$E29 -> 87.01 | H43: =H36*$E29 -> 87.01 | I43: =I36*$E29 -> 87.01 | J43: =J36*$E29 -> 87.01 | K43: =K36*$E29 -> 87.01 | L43: =L36*$E29 -> 87.01 | ... N43: =N36*$E29 -> 87.01
B44: ТО-4: чел-часы/год | C44: ч-час | E44: =E37*$E30 -> 19.845 | F44: =F37*$E30 -> 19.845 | G44: =G37*$E30 -> 19.845 | H44: =H37*$E30 -> 19.845 | I44: =I37*$E30 -> 19.845 | J44: =J37*$E30 -> 19.845 | K44: =K37*$E30 -> 19.845 | L44: =L37*$E30 -> 19.845 | ... N44: =N37*$E30 -> 19.845
B45: ТО-5: чел-часы/год | C45: ч-час | E45: =E38*$E31 -> 23.473333 | F45: =F38*$E31 -> 23.473333 | G45: =G38*$E31 -> 23.473333 | H45: =H38*$E31 -> 23.473333 | I45: =I38*$E31 -> 23.473333 | J45: =J38*$E31 -> 23.473333 | K45: =K38*$E31 -> 23.473333 | L45: =L38*$E31 -> 23.473333 | ... N45: =N38*$E31 -> 23.473333
B46: ТО-6: чел-часы/год | C46: ч-час | E46: =E39*$E32 -> 11.844 | F46: =F39*$E32 -> 11.844 | G46: =G39*$E32 -> 11.844 | H46: =H39*$E32 -> 11.844 | I46: =I39*$E32 -> 11.844 | J46: =J39*$E32 -> 11.844 | K46: =K39*$E32 -> 11.844 | L46: =L39*$E32 -> 11.844 | ... N46: =N39*$E32 -> 11.844
B47: Итого чел-часы ТО | E47: =SUM(E41:E46) -> 636.37233 | F47: =SUM(F41:F46) -> 636.37233 | G47: =SUM(G41:G46) -> 636.37233 | H47: =SUM(H41:H46) -> 636.37233 | I47: =SUM(I41:I46) -> 636.37233 | J47: =SUM(J41:J46) -> 636.37233 | K47: =SUM(K41:K46) -> 636.37233 | L47: =SUM(L41:L46) -> 636.37233 | ... N47: =SUM(N41:N46) -> 636.37233
B49: КАТАЛОГ ЗАПЧАСТЕЙ ТО (заполняет подрядчик), ПО ГОДАМ
B50: Наименование | C50: цена за ед | D50: кол-во/ТО | P50: № ТО
B51: Моторное масло | C51: 6.77 | D51: 70 | E51: =E$25/INDEX($C$27:$C$32,$P51)*D51*C51/1000 -> 13.2692 | F51: =F$25/INDEX($C$27:$C$32,$P51)*D51*C51/1000 -> 13.2692 | G51: =G$25/INDEX($C$27:$C$32,$P51)*D51*C51/1000 -> 13.2692 | H51: =H$25/INDEX($C$27:$C$32,$P51)*D51*C51/1000 -> 13.2692 | I51: =I$25/INDEX($C$27:$C$32,$P51)*D51*C51/1000 -> 13.2692 | J51: =J$25/INDEX($C$27:$C$32,$P51)*D51*C51/1000 -> 13.2692 | K51: =K$25/INDEX($C$27:$C$32,$P51)*D51*C51/1000 -> 13.2692 | L51: =L$25/INDEX($C$27:$C$32,$P51)*D51*C51/1000 -> 13.2692 | M51: =M$25/INDEX($C$27:$C$32,$P51)*D51*C51/1000 -> 13.2692 | N51: =N$25/INDEX($C$27:$C$32,$P51)*D51*C51/1000 -> 13.2692 | P51: 1
B52: Масляный фильтр двигателя | C52: 75.788 | D52: 2 | E52: =E$25/INDEX($C$27:$C$32,$P52)*D52*C52/1000 -> 4.244128 | F52: =F$25/INDEX($C$27:$C$32,$P52)*D52*C52/1000 -> 4.244128 | G52: =G$25/INDEX($C$27:$C$32,$P52)*D52*C52/1000 -> 4.244128 | H52: =H$25/INDEX($C$27:$C$32,$P52)*D52*C52/1000 -> 4.244128 | I52: =I$25/INDEX($C$27:$C$32,$P52)*D52*C52/1000 -> 4.244128 | J52: =J$25/INDEX($C$27:$C$32,$P52)*D52*C52/1000 -> 4.244128 | K52: =K$25/INDEX($C$27:$C$32,$P52)*D52*C52/1000 -> 4.244128 | L52: =L$25/INDEX($C$27:$C$32,$P52)*D52*C52/1000 -> 4.244128 | M52: =M$25/INDEX($C$27:$C$32,$P52)*D52*C52/1000 -> 4.244128 | N52: =N$25/INDEX($C$27:$C$32,$P52)*D52*C52/1000 -> 4.244128 | P52: 1
B53: Охлаждающая жидкость | C53: 4.368 | D53: 3 | E53: =E$25/INDEX($C$27:$C$32,$P53)*D53*C53/1000 -> 0.366912 | F53: =F$25/INDEX($C$27:$C$32,$P53)*D53*C53/1000 -> 0.366912 | G53: =G$25/INDEX($C$27:$C$32,$P53)*D53*C53/1000 -> 0.366912 | H53: =H$25/INDEX($C$27:$C$32,$P53)*D53*C53/1000 -> 0.366912 | I53: =I$25/INDEX($C$27:$C$32,$P53)*D53*C53/1000 -> 0.366912 | J53: =J$25/INDEX($C$27:$C$32,$P53)*D53*C53/1000 -> 0.366912 | K53: =K$25/INDEX($C$27:$C$32,$P53)*D53*C53/1000 -> 0.366912 | L53: =L$25/INDEX($C$27:$C$32,$P53)*D53*C53/1000 -> 0.366912 | M53: =M$25/INDEX($C$27:$C$32,$P53)*D53*C53/1000 -> 0.366912 | N53: =N$25/INDEX($C$27:$C$32,$P53)*D53*C53/1000 -> 0.366912 | P53: 1
B54: Воздушный фильтр первичный | C54: 51.588 | D54: 3 | E54: =E$25/INDEX($C$27:$C$32,$P54)*D54*C54/1000 -> 4.333392 | F54: =F$25/INDEX($C$27:$C$32,$P54)*D54*C54/1000 -> 4.333392 | G54: =G$25/INDEX($C$27:$C$32,$P54)*D54*C54/1000 -> 4.333392 | H54: =H$25/INDEX($C$27:$C$32,$P54)*D54*C54/1000 -> 4.333392 | I54: =I$25/INDEX($C$27:$C$32,$P54)*D54*C54/1000 -> 4.333392 | J54: =J$25/INDEX($C$27:$C$32,$P54)*D54*C54/1000 -> 4.333392 | K54: =K$25/INDEX($C$27:$C$32,$P54)*D54*C54/1000 -> 4.333392 | L54: =L$25/INDEX($C$27:$C$32,$P54)*D54*C54/1000 -> 4.333392 | M54: =M$25/INDEX($C$27:$C$32,$P54)*D54*C54/1000 -> 4.333392 | N54: =N$25/INDEX($C$27:$C$32,$P54)*D54*C54/1000 -> 4.333392 | P54: 1
B55: Воздушный фильтр вторичный | C55: 37.65 | D55: 3 | E55: =E$25/INDEX($C$27:$C$32,$P55)*D55*C55/1000 -> 3.1626 | F55: =F$25/INDEX($C$27:$C$32,$P55)*D55*C55/1000 -> 3.1626 | G55: =G$25/INDEX($C$27:$C$32,$P55)*D55*C55/1000 -> 3.1626 | H55: =H$25/INDEX($C$27:$C$32,$P55)*D55*C55/1000 -> 3.1626 | I55: =I$25/INDEX($C$27:$C$32,$P55)*D55*C55/1000 -> 3.1626 | J55: =J$25/INDEX($C$27:$C$32,$P55)*D55*C55/1000 -> 3.1626 | K55: =K$25/INDEX($C$27:$C$32,$P55)*D55*C55/1000 -> 3.1626 | L55: =L$25/INDEX($C$27:$C$32,$P55)*D55*C55/1000 -> 3.1626 | M55: =M$25/INDEX($C$27:$C$32,$P55)*D55*C55/1000 -> 3.1626 | N55: =N$25/INDEX($C$27:$C$32,$P55)*D55*C55/1000 -> 3.1626 | P55: 1
B56: Фильтр системы охл. ДВС | C56: 27.113 | D56: 2 | E56: =E$25/INDEX($C$27:$C$32,$P56)*D56*C56/1000 -> 1.518328 | F56: =F$25/INDEX($C$27:$C$32,$P56)*D56*C56/1000 -> 1.518328 | G56: =G$25/INDEX($C$27:$C$32,$P56)*D56*C56/1000 -> 1.518328 | H56: =H$25/INDEX($C$27:$C$32,$P56)*D56*C56/1000 -> 1.518328 | I56: =I$25/INDEX($C$27:$C$32,$P56)*D56*C56/1000 -> 1.518328 | J56: =J$25/INDEX($C$27:$C$32,$P56)*D56*C56/1000 -> 1.518328 | K56: =K$25/INDEX($C$27:$C$32,$P56)*D56*C56/1000 -> 1.518328 | L56: =L$25/INDEX($C$27:$C$32,$P56)*D56*C56/1000 -> 1.518328 | M56: =M$25/INDEX($C$27:$C$32,$P56)*D56*C56/1000 -> 1.518328 | N56: =N$25/INDEX($C$27:$C$32,$P56)*D56*C56/1000 -> 1.518328 | P56: 1
B57: Топливный фильтр первичный | C57: 65.662 | D57: 1 | E57: =E$25/INDEX($C$27:$C$32,$P57)*D57*C57/1000 -> 1.838536 | F57: =F$25/INDEX($C$27:$C$32,$P57)*D57*C57/1000 -> 1.838536 | G57: =G$25/INDEX($C$27:$C$32,$P57)*D57*C57/1000 -> 1.838536 | H57: =H$25/INDEX($C$27:$C$32,$P57)*D57*C57/1000 -> 1.838536 | I57: =I$25/INDEX($C$27:$C$32,$P57)*D57*C57/1000 -> 1.838536 | J57: =J$25/INDEX($C$27:$C$32,$P57)*D57*C57/1000 -> 1.838536 | K57: =K$25/INDEX($C$27:$C$32,$P57)*D57*C57/1000 -> 1.838536 | L57: =L$25/INDEX($C$27:$C$32,$P57)*D57*C57/1000 -> 1.838536 | M57: =M$25/INDEX($C$27:$C$32,$P57)*D57*C57/1000 -> 1.838536 | N57: =N$25/INDEX($C$27:$C$32,$P57)*D57*C57/1000 -> 1.838536 | P57: 1
B58: Топливный фильтр вторичный | C58: 127.662 | D58: 1 | E58: =E$25/INDEX($C$27:$C$32,$P58)*D58*C58/1000 -> 3.574536 | F58: =F$25/INDEX($C$27:$C$32,$P58)*D58*C58/1000 -> 3.574536 | G58: =G$25/INDEX($C$27:$C$32,$P58)*D58*C58/1000 -> 3.574536 | H58: =H$25/INDEX($C$27:$C$32,$P58)*D58*C58/1000 -> 3.574536 | I58: =I$25/INDEX($C$27:$C$32,$P58)*D58*C58/1000 -> 3.574536 | J58: =J$25/INDEX($C$27:$C$32,$P58)*D58*C58/1000 -> 3.574536 | K58: =K$25/INDEX($C$27:$C$32,$P58)*D58*C58/1000 -> 3.574536 | L58: =L$25/INDEX($C$27:$C$32,$P58)*D58*C58/1000 -> 3.574536 | M58: =M$25/INDEX($C$27:$C$32,$P58)*D58*C58/1000 -> 3.574536 | N58: =N$25/INDEX($C$27:$C$32,$P58)*D58*C58/1000 -> 3.574536 | P58: 1
B59: Влагоотделитель | C59: 14.612 | D59: 2 | E59: =E$25/INDEX($C$27:$C$32,$P59)*D59*C59/1000 -> 0.818272 | F59: =F$25/INDEX($C$27:$C$32,$P59)*D59*C59/1000 -> 0.818272 | G59: =G$25/INDEX($C$27:$C$32,$P59)*D59*C59/1000 -> 0.818272 | H59: =H$25/INDEX($C$27:$C$32,$P59)*D59*C59/1000 -> 0.818272 | I59: =I$25/INDEX($C$27:$C$32,$P59)*D59*C59/1000 -> 0.818272 | J59: =J$25/INDEX($C$27:$C$32,$P59)*D59*C59/1000 -> 0.818272 | K59: =K$25/INDEX($C$27:$C$32,$P59)*D59*C59/1000 -> 0.818272 | L59: =L$25/INDEX($C$27:$C$32,$P59)*D59*C59/1000 -> 0.818272 | M59: =M$25/INDEX($C$27:$C$32,$P59)*D59*C59/1000 -> 0.818272 | N59: =N$25/INDEX($C$27:$C$32,$P59)*D59*C59/1000 -> 0.818272 | P59: 1
B60: Консистентная смазка | C60: 10.752 | D60: 2 | E60: =E$25/INDEX($C$27:$C$32,$P60)*D60*C60/1000 -> 0.602112 | F60: =F$25/INDEX($C$27:$C$32,$P60)*D60*C60/1000 -> 0.602112 | G60: =G$25/INDEX($C$27:$C$32,$P60)*D60*C60/1000 -> 0.602112 | H60: =H$25/INDEX($C$27:$C$32,$P60)*D60*C60/1000 -> 0.602112 | I60: =I$25/INDEX($C$27:$C$32,$P60)*D60*C60/1000 -> 0.602112 | J60: =J$25/INDEX($C$27:$C$32,$P60)*D60*C60/1000 -> 0.602112 | K60: =K$25/INDEX($C$27:$C$32,$P60)*D60*C60/1000 -> 0.602112 | L60: =L$25/INDEX($C$27:$C$32,$P60)*D60*C60/1000 -> 0.602112 | M60: =M$25/INDEX($C$27:$C$32,$P60)*D60*C60/1000 -> 0.602112 | N60: =N$25/INDEX($C$27:$C$32,$P60)*D60*C60/1000 -> 0.602112 | P60: 1
B61: Сапун гидробака | C61: 18.025 | D61: 2 | E61: =E$25/INDEX($C$27:$C$32,$P61)*D61*C61/1000 -> 0.5047 | F61: =F$25/INDEX($C$27:$C$32,$P61)*D61*C61/1000 -> 0.5047 | G61: =G$25/INDEX($C$27:$C$32,$P61)*D61*C61/1000 -> 0.5047 | H61: =H$25/INDEX($C$27:$C$32,$P61)*D61*C61/1000 -> 0.5047 | I61: =I$25/INDEX($C$27:$C$32,$P61)*D61*C61/1000 -> 0.5047 | J61: =J$25/INDEX($C$27:$C$32,$P61)*D61*C61/1000 -> 0.5047 | K61: =K$25/INDEX($C$27:$C$32,$P61)*D61*C61/1000 -> 0.5047 | L61: =L$25/INDEX($C$27:$C$32,$P61)*D61*C61/1000 -> 0.5047 | M61: =M$25/INDEX($C$27:$C$32,$P61)*D61*C61/1000 -> 0.5047 | N61: =N$25/INDEX($C$27:$C$32,$P61)*D61*C61/1000 -> 0.5047 | P61: 2
B62: Фильтра системы пылеподавления | C62: 58.9 | D62: 9 | E62: =E$25/INDEX($C$27:$C$32,$P62)*D62*C62/1000 -> 7.4214 | F62: =F$25/INDEX($C$27:$C$32,$P62)*D62*C62/1000 -> 7.4214 | G62: =G$25/INDEX($C$27:$C$32,$P62)*D62*C62/1000 -> 7.4214 | H62: =H$25/INDEX($C$27:$C$32,$P62)*D62*C62/1000 -> 7.4214 | I62: =I$25/INDEX($C$27:$C$32,$P62)*D62*C62/1000 -> 7.4214 | J62: =J$25/INDEX($C$27:$C$32,$P62)*D62*C62/1000 -> 7.4214 | K62: =K$25/INDEX($C$27:$C$32,$P62)*D62*C62/1000 -> 7.4214 | L62: =L$25/INDEX($C$27:$C$32,$P62)*D62*C62/1000 -> 7.4214 | M62: =M$25/INDEX($C$27:$C$32,$P62)*D62*C62/1000 -> 7.4214 | N62: =N$25/INDEX($C$27:$C$32,$P62)*D62*C62/1000 -> 7.4214 | P62: 2
... B83: Охлаждающая жидкость | C83: 3.122 | D83: 190 | E83: =E$25/INDEX($C$27:$C$32,$P83)*D83*C83/1000 -> 0.830452 | F83: =F$25/INDEX($C$27:$C$32,$P83)*D83*C83/1000 -> 0.830452 | G83: =G$25/INDEX($C$27:$C$32,$P83)*D83*C83/1000 -> 0.830452 | H83: =H$25/INDEX($C$27:$C$32,$P83)*D83*C83/1000 -> 0.830452 | I83: =I$25/INDEX($C$27:$C$32,$P83)*D83*C83/1000 -> 0.830452 | J83: =J$25/INDEX($C$27:$C$32,$P83)*D83*C83/1000 -> 0.830452 | K83: =K$25/INDEX($C$27:$C$32,$P83)*D83*C83/1000 -> 0.830452 | L83: =L$25/INDEX($C$27:$C$32,$P83)*D83*C83/1000 -> 0.830452 | M83: =M$25/INDEX($C$27:$C$32,$P83)*D83*C83/1000 -> 0.830452 | N83: =N$25/INDEX($C$27:$C$32,$P83)*D83*C83/1000 -> 0.830452 | P83: 6
B84: Корректировка (прочее) | E84: 0 | F84: 0 | G84: 0 | H84: 0 | I84: 0 | J84: 0 | K84: 0 | L84: 0 | M84: 0 | N84: 0
B85: ИТОГО ЗЧ ТО, тыс.вал/год | E85: =SUM(E51:E84) -> 136.07379 | F85: =SUM(F51:F84) -> 136.07379 | G85: =SUM(G51:G84) -> 136.07379 | H85: =SUM(H51:H84) -> 136.07379 | I85: =SUM(I51:I84) -> 136.07379 | J85: =SUM(J51:J84) -> 136.07379 | K85: =SUM(K51:K84) -> 136.07379 | L85: =SUM(L51:L84) -> 136.07379 | ... N85: =SUM(N51:N84) -> 136.07379
B87: ТЕКУЩИЕ РЕМОНТЫ — ЗАТРАТЫ НА ЗЧ (по ресурсу)
B88: Наименование | C88: стоим.замены,вал | D88: ресурс, м/ч | E88: год 1 | F88: год 2 | G88: год 3 | H88: год 4 | I88: год 5 | J88: год 6 | K88: год 7 | L88: год 8 | M88: год 9 | N88: год 10
B89: ENG (двигатель капремонт) | C89: 98848.48 | D89: 15000 | E89: =(INT($E$25*1/$D89)-INT($E$25*(1-1)/$D89))*$C89/1000 -> 0 | F89: =(INT($E$25*2/$D89)-INT($E$25*(2-1)/$D89))*$C89/1000 -> 0 | G89: =(INT($E$25*3/$D89)-INT($E$25*(3-1)/$D89))*$C89/1000 -> 98.84848 | H89: =(INT($E$25*4/$D89)-INT($E$25*(4-1)/$D89))*$C89/1000 -> 0 | I89: =(INT($E$25*5/$D89)-INT($E$25*(5-1)/$D89))*$C89/1000 -> 98.84848 | J89: =(INT($E$25*6/$D89)-INT($E$25*(6-1)/$D89))*$C89/1000 -> 0 | K89: =(INT($E$25*7/$D89)-INT($E$25*(7-1)/$D89))*$C89/1000 -> 98.84848 | L89: =(INT($E$25*8/$D89)-INT($E$25*(8-1)/$D89))*$C89/1000 -> 0 | M89: =(INT($E$25*9/$D89)-INT($E$25*(9-1)/$D89))*$C89/1000 -> 98.84848 | N89: =(INT($E$25*10/$D89)-INT($E$25*(10-1)/$D89))*$C89/1000 -> 0
B90: AIREND Seal LP (Компрессор ремкомплект | C90: 32894 | D90: 16000 | E90: =(INT($E$25*1/$D90)-INT($E$25*(1-1)/$D90))*$C90/1000 -> 0 | F90: =(INT($E$25*2/$D90)-INT($E$25*(2-1)/$D90))*$C90/1000 -> 0 | G90: =(INT($E$25*3/$D90)-INT($E$25*(3-1)/$D90))*$C90/1000 -> 32.894 | H90: =(INT($E$25*4/$D90)-INT($E$25*(4-1)/$D90))*$C90/1000 -> 0 | I90: =(INT($E$25*5/$D90)-INT($E$25*(5-1)/$D90))*$C90/1000 -> 32.894 | J90: =(INT($E$25*6/$D90)-INT($E$25*(6-1)/$D90))*$C90/1000 -> 0 | K90: =(INT($E$25*7/$D90)-INT($E$25*(7-1)/$D90))*$C90/1000 -> 32.894 | L90: =(INT($E$25*8/$D90)-INT($E$25*(8-1)/$D90))*$C90/1000 -> 0 | M90: =(INT($E$25*9/$D90)-INT($E$25*(9-1)/$D90))*$C90/1000 -> 0 | N90: =(INT($E$25*10/$D90)-INT($E$25*(10-1)/$D90))*$C90/1000 -> 32.894
B91: ROTARYHEAD (Ремкомплект вращателя | C91: 46638 | D91: 13000 | E91: =(INT($E$25*1/$D91)-INT($E$25*(1-1)/$D91))*$C91/1000 -> 0 | F91: =(INT($E$25*2/$D91)-INT($E$25*(2-1)/$D91))*$C91/1000 -> 46.638 | G91: =(INT($E$25*3/$D91)-INT($E$25*(3-1)/$D91))*$C91/1000 -> 0 | H91: =(INT($E$25*4/$D91)-INT($E$25*(4-1)/$D91))*$C91/1000 -> 46.638 | I91: =(INT($E$25*5/$D91)-INT($E$25*(5-1)/$D91))*$C91/1000 -> 0 | J91: =(INT($E$25*6/$D91)-INT($E$25*(6-1)/$D91))*$C91/1000 -> 46.638 | K91: =(INT($E$25*7/$D91)-INT($E$25*(7-1)/$D91))*$C91/1000 -> 0 | L91: =(INT($E$25*8/$D91)-INT($E$25*(8-1)/$D91))*$C91/1000 -> 46.638 | M91: =(INT($E$25*9/$D91)-INT($E$25*(9-1)/$D91))*$C91/1000 -> 0 | N91: =(INT($E$25*10/$D91)-INT($E$25*(10-1)/$D91))*$C91/1000 -> 46.638
B92: KIT, SEAL (ремкомплект к цилиндру пода | C92: 4240.92 | D92: 7450 | E92: =(INT($E$25*1/$D92)-INT($E$25*(1-1)/$D92))*$C92/1000 -> 0 | F92: =(INT($E$25*2/$D92)-INT($E$25*(2-1)/$D92))*$C92/1000 -> 4.24092 | G92: =(INT($E$25*3/$D92)-INT($E$25*(3-1)/$D92))*$C92/1000 -> 4.24092 | H92: =(INT($E$25*4/$D92)-INT($E$25*(4-1)/$D92))*$C92/1000 -> 4.24092 | I92: =(INT($E$25*5/$D92)-INT($E$25*(5-1)/$D92))*$C92/1000 -> 4.24092 | J92: =(INT($E$25*6/$D92)-INT($E$25*(6-1)/$D92))*$C92/1000 -> 4.24092 | K92: =(INT($E$25*7/$D92)-INT($E$25*(7-1)/$D92))*$C92/1000 -> 4.24092 | L92: =(INT($E$25*8/$D92)-INT($E$25*(8-1)/$D92))*$C92/1000 -> 4.24092 | M92: =(INT($E$25*9/$D92)-INT($E$25*(9-1)/$D92))*$C92/1000 -> 4.24092 | N92: =(INT($E$25*10/$D92)-INT($E$25*(10-1)/$D92))*$C92/1000 -> 4.24092
B93: SEAL KIT,CYLINDER (ремкомплект к цил.д | C93: 4242.92 | D93: 7450 | E93: =(INT($E$25*1/$D93)-INT($E$25*(1-1)/$D93))*$C93/1000 -> 0 | F93: =(INT($E$25*2/$D93)-INT($E$25*(2-1)/$D93))*$C93/1000 -> 4.24292 | G93: =(INT($E$25*3/$D93)-INT($E$25*(3-1)/$D93))*$C93/1000 -> 4.24292 | H93: =(INT($E$25*4/$D93)-INT($E$25*(4-1)/$D93))*$C93/1000 -> 4.24292 | I93: =(INT($E$25*5/$D93)-INT($E$25*(5-1)/$D93))*$C93/1000 -> 4.24292 | J93: =(INT($E$25*6/$D93)-INT($E$25*(6-1)/$D93))*$C93/1000 -> 4.24292 | K93: =(INT($E$25*7/$D93)-INT($E$25*(7-1)/$D93))*$C93/1000 -> 4.24292 | L93: =(INT($E$25*8/$D93)-INT($E$25*(8-1)/$D93))*$C93/1000 -> 4.24292 | M93: =(INT($E$25*9/$D93)-INT($E$25*(9-1)/$D93))*$C93/1000 -> 4.24292 | N93: =(INT($E$25*10/$D93)-INT($E$25*(10-1)/$D93))*$C93/1000 -> 4.24292
B94: KIT, SEAL (ремкомплект к цилиндру п. м | C94: 3464.48 | D94: 6000 | E94: =(INT($E$25*1/$D94)-INT($E$25*(1-1)/$D94))*$C94/1000 -> 3.46448 | F94: =(INT($E$25*2/$D94)-INT($E$25*(2-1)/$D94))*$C94/1000 -> 3.46448 | G94: =(INT($E$25*3/$D94)-INT($E$25*(3-1)/$D94))*$C94/1000 -> 3.46448 | H94: =(INT($E$25*4/$D94)-INT($E$25*(4-1)/$D94))*$C94/1000 -> 3.46448 | I94: =(INT($E$25*5/$D94)-INT($E$25*(5-1)/$D94))*$C94/1000 -> 3.46448 | J94: =(INT($E$25*6/$D94)-INT($E$25*(6-1)/$D94))*$C94/1000 -> 6.92896 | K94: =(INT($E$25*7/$D94)-INT($E$25*(7-1)/$D94))*$C94/1000 -> 3.46448 | L94: =(INT($E$25*8/$D94)-INT($E$25*(8-1)/$D94))*$C94/1000 -> 3.46448 | M94: =(INT($E$25*9/$D94)-INT($E$25*(9-1)/$D94))*$C94/1000 -> 3.46448 | N94: =(INT($E$25*10/$D94)-INT($E$25*(10-1)/$D94))*$C94/1000 -> 3.46448
B95: SEAL KIT (ремкомплектгидроцилиндр мех. | C95: 237.18 | D95: 6000 | E95: =(INT($E$25*1/$D95)-INT($E$25*(1-1)/$D95))*$C95/1000 -> 0.23718 | F95: =(INT($E$25*2/$D95)-INT($E$25*(2-1)/$D95))*$C95/1000 -> 0.23718 | G95: =(INT($E$25*3/$D95)-INT($E$25*(3-1)/$D95))*$C95/1000 -> 0.23718 | H95: =(INT($E$25*4/$D95)-INT($E$25*(4-1)/$D95))*$C95/1000 -> 0.23718 | I95: =(INT($E$25*5/$D95)-INT($E$25*(5-1)/$D95))*$C95/1000 -> 0.23718 | J95: =(INT($E$25*6/$D95)-INT($E$25*(6-1)/$D95))*$C95/1000 -> 0.47436 | K95: =(INT($E$25*7/$D95)-INT($E$25*(7-1)/$D95))*$C95/1000 -> 0.23718 | L95: =(INT($E$25*8/$D95)-INT($E$25*(8-1)/$D95))*$C95/1000 -> 0.23718 | M95: =(INT($E$25*9/$D95)-INT($E$25*(9-1)/$D95))*$C95/1000 -> 0.23718 | N95: =(INT($E$25*10/$D95)-INT($E$25*(10-1)/$D95))*$C95/1000 -> 0.23718
B96: KIT,SEAL (ремкомплект цилиндра ключа) | C96: 102.66 | D96: 4000 | E96: =(INT($E$25*1/$D96)-INT($E$25*(1-1)/$D96))*$C96/1000 -> 0.10266 | F96: =(INT($E$25*2/$D96)-INT($E$25*(2-1)/$D96))*$C96/1000 -> 0.20532 | G96: =(INT($E$25*3/$D96)-INT($E$25*(3-1)/$D96))*$C96/1000 -> 0.20532 | H96: =(INT($E$25*4/$D96)-INT($E$25*(4-1)/$D96))*$C96/1000 -> 0.20532 | I96: =(INT($E$25*5/$D96)-INT($E$25*(5-1)/$D96))*$C96/1000 -> 0.10266 | J96: =(INT($E$25*6/$D96)-INT($E$25*(6-1)/$D96))*$C96/1000 -> 0.20532 | K96: =(INT($E$25*7/$D96)-INT($E$25*(7-1)/$D96))*$C96/1000 -> 0.20532 | L96: =(INT($E$25*8/$D96)-INT($E$25*(8-1)/$D96))*$C96/1000 -> 0.20532 | M96: =(INT($E$25*9/$D96)-INT($E$25*(9-1)/$D96))*$C96/1000 -> 0.10266 | N96: =(INT($E$25*10/$D96)-INT($E$25*(10-1)/$D96))*$C96/1000 -> 0.20532
B97: SEAL KIT (ремкомплект цилиндра мех.зам | C97: 110.66 | D97: 4000 | E97: =(INT($E$25*1/$D97)-INT($E$25*(1-1)/$D97))*$C97/1000 -> 0.11066 | F97: =(INT($E$25*2/$D97)-INT($E$25*(2-1)/$D97))*$C97/1000 -> 0.22132 | G97: =(INT($E$25*3/$D97)-INT($E$25*(3-1)/$D97))*$C97/1000 -> 0.22132 | H97: =(INT($E$25*4/$D97)-INT($E$25*(4-1)/$D97))*$C97/1000 -> 0.22132 | I97: =(INT($E$25*5/$D97)-INT($E$25*(5-1)/$D97))*$C97/1000 -> 0.11066 | J97: =(INT($E$25*6/$D97)-INT($E$25*(6-1)/$D97))*$C97/1000 -> 0.22132 | K97: =(INT($E$25*7/$D97)-INT($E$25*(7-1)/$D97))*$C97/1000 -> 0.22132 | L97: =(INT($E$25*8/$D97)-INT($E$25*(8-1)/$D97))*$C97/1000 -> 0.22132 | M97: =(INT($E$25*9/$D97)-INT($E$25*(9-1)/$D97))*$C97/1000 -> 0.11066 | N97: =(INT($E$25*10/$D97)-INT($E$25*(10-1)/$D97))*$C97/1000 -> 0.22132
B98: SEAL KIT (ремкомплект к гидроцил.стопо | C98: 92.04 | D98: 5000 | E98: =(INT($E$25*1/$D98)-INT($E$25*(1-1)/$D98))*$C98/1000 -> 0.09204 | F98: =(INT($E$25*2/$D98)-INT($E$25*(2-1)/$D98))*$C98/1000 -> 0.09204 | G98: =(INT($E$25*3/$D98)-INT($E$25*(3-1)/$D98))*$C98/1000 -> 0.18408 | H98: =(INT($E$25*4/$D98)-INT($E$25*(4-1)/$D98))*$C98/1000 -> 0.09204 | I98: =(INT($E$25*5/$D98)-INT($E$25*(5-1)/$D98))*$C98/1000 -> 0.18408 | J98: =(INT($E$25*6/$D98)-INT($E$25*(6-1)/$D98))*$C98/1000 -> 0.09204 | K98: =(INT($E$25*7/$D98)-INT($E$25*(7-1)/$D98))*$C98/1000 -> 0.09204 | L98: =(INT($E$25*8/$D98)-INT($E$25*(8-1)/$D98))*$C98/1000 -> 0.18408 | M98: =(INT($E$25*9/$D98)-INT($E$25*(9-1)/$D98))*$C98/1000 -> 0.09204 | N98: =(INT($E$25*10/$D98)-INT($E$25*(10-1)/$D98))*$C98/1000 -> 0.18408
B99: SEAL KIT (ремкомплект гидроцил.фартука | C99: 123.9 | D99: 4000 | E99: =(INT($E$25*1/$D99)-INT($E$25*(1-1)/$D99))*$C99/1000 -> 0.1239 | F99: =(INT($E$25*2/$D99)-INT($E$25*(2-1)/$D99))*$C99/1000 -> 0.2478 | G99: =(INT($E$25*3/$D99)-INT($E$25*(3-1)/$D99))*$C99/1000 -> 0.2478 | H99: =(INT($E$25*4/$D99)-INT($E$25*(4-1)/$D99))*$C99/1000 -> 0.2478 | I99: =(INT($E$25*5/$D99)-INT($E$25*(5-1)/$D99))*$C99/1000 -> 0.1239 | J99: =(INT($E$25*6/$D99)-INT($E$25*(6-1)/$D99))*$C99/1000 -> 0.2478 | K99: =(INT($E$25*7/$D99)-INT($E$25*(7-1)/$D99))*$C99/1000 -> 0.2478 | L99: =(INT($E$25*8/$D99)-INT($E$25*(8-1)/$D99))*$C99/1000 -> 0.2478 | M99: =(INT($E$25*9/$D99)-INT($E$25*(9-1)/$D99))*$C99/1000 -> 0.1239 | N99: =(INT($E$25*10/$D99)-INT($E$25*(10-1)/$D99))*$C99/1000 -> 0.2478
B100: Ремонт системы смазки | C100: 143.96 | D100: 12000 | E100: =(INT($E$25*1/$D100)-INT($E$25*(1-1)/$D100))*$C100/1000 -> 0 | F100: =(INT($E$25*2/$D100)-INT($E$25*(2-1)/$D100))*$C100/1000 -> 0.14396 | G100: =(INT($E$25*3/$D100)-INT($E$25*(3-1)/$D100))*$C100/1000 -> 0 | H100: =(INT($E$25*4/$D100)-INT($E$25*(4-1)/$D100))*$C100/1000 -> 0.14396 | I100: =(INT($E$25*5/$D100)-INT($E$25*(5-1)/$D100))*$C100/1000 -> 0 | J100: =(INT($E$25*6/$D100)-INT($E$25*(6-1)/$D100))*$C100/1000 -> 0.14396 | K100: =(INT($E$25*7/$D100)-INT($E$25*(7-1)/$D100))*$C100/1000 -> 0.14396 | L100: =(INT($E$25*8/$D100)-INT($E$25*(8-1)/$D100))*$C100/1000 -> 0 | M100: =(INT($E$25*9/$D100)-INT($E$25*(9-1)/$D100))*$C100/1000 -> 0.14396 | N100: =(INT($E$25*10/$D100)-INT($E$25*(10-1)/$D100))*$C100/1000 -> 0
... B104: Инспекция металлоконструкций | C104: 12637.39 | D104: 65000 | E104: =(INT($E$25*1/$D104)-INT($E$25*(1-1)/$D104))*$C104/1000 -> 0 | F104: =(INT($E$25*2/$D104)-INT($E$25*(2-1)/$D104))*$C104/1000 -> 0 | G104: =(INT($E$25*3/$D104)-INT($E$25*(3-1)/$D104))*$C104/1000 -> 0 | H104: =(INT($E$25*4/$D104)-INT($E$25*(4-1)/$D104))*$C104/1000 -> 0 | I104: =(INT($E$25*5/$D104)-INT($E$25*(5-1)/$D104))*$C104/1000 -> 0 | J104: =(INT($E$25*6/$D104)-INT($E$25*(6-1)/$D104))*$C104/1000 -> 0 | K104: =(INT($E$25*7/$D104)-INT($E$25*(7-1)/$D104))*$C104/1000 -> 0 | L104: =(INT($E$25*8/$D104)-INT($E$25*(8-1)/$D104))*$C104/1000 -> 0 | M104: =(INT($E$25*9/$D104)-INT($E$25*(9-1)/$D104))*$C104/1000 -> 0 | N104: =(INT($E$25*10/$D104)-INT($E$25*(10-1)/$D104))*$C104/1000 -> 12.63739
B105: ИТОГО | E105: =SUM(E89:E104) -> 4.50682 | F105: =SUM(F89:F104) -> 60.10984 | G105: =SUM(G89:G104) -> 145.1624 | H105: =SUM(H89:H104) -> 60.10984 | I105: =SUM(I89:I104) -> 144.82518 | J105: =SUM(J89:J104) -> 67.22701 | K105: =SUM(K89:K104) -> 145.21432 | L105: =SUM(L89:L104) -> 60.05792 | ... N105: =SUM(N89:N104) -> 105.58931
B107: ТЕКУЩИЕ РЕМОНТЫ — ТРУДОЗАТРАТЫ (по ресурсу)
B108: Наименование | C108: нормо-час/событие | D108: ресурс, м/ч | E108: год 1 | F108: год 2 | G108: год 3 | H108: год 4 | I108: год 5 | J108: год 6 | K108: год 7 | L108: год 8 | M108: год 9 | N108: год 10
B109: ENG (двигатель капремонт) | C109: 56 | D109: 15000 | E109: =(INT($E$25*1/$D109)-INT($E$25*(1-1)/$D109))*$C109 -> 0 | F109: =(INT($E$25*2/$D109)-INT($E$25*(2-1)/$D109))*$C109 -> 0 | G109: =(INT($E$25*3/$D109)-INT($E$25*(3-1)/$D109))*$C109 -> 56 | H109: =(INT($E$25*4/$D109)-INT($E$25*(4-1)/$D109))*$C109 -> 0 | I109: =(INT($E$25*5/$D109)-INT($E$25*(5-1)/$D109))*$C109 -> 56 | J109: =(INT($E$25*6/$D109)-INT($E$25*(6-1)/$D109))*$C109 -> 0 | K109: =(INT($E$25*7/$D109)-INT($E$25*(7-1)/$D109))*$C109 -> 56 | L109: =(INT($E$25*8/$D109)-INT($E$25*(8-1)/$D109))*$C109 -> 0 | M109: =(INT($E$25*9/$D109)-INT($E$25*(9-1)/$D109))*$C109 -> 56 | N109: =(INT($E$25*10/$D109)-INT($E$25*(10-1)/$D109))*$C109 -> 0
B110: AIREND Seal LP (Компрессор ремкомплект | C110: 4 | D110: 16000 | E110: =(INT($E$25*1/$D110)-INT($E$25*(1-1)/$D110))*$C110 -> 0 | F110: =(INT($E$25*2/$D110)-INT($E$25*(2-1)/$D110))*$C110 -> 0 | G110: =(INT($E$25*3/$D110)-INT($E$25*(3-1)/$D110))*$C110 -> 4 | H110: =(INT($E$25*4/$D110)-INT($E$25*(4-1)/$D110))*$C110 -> 0 | I110: =(INT($E$25*5/$D110)-INT($E$25*(5-1)/$D110))*$C110 -> 4 | J110: =(INT($E$25*6/$D110)-INT($E$25*(6-1)/$D110))*$C110 -> 0 | K110: =(INT($E$25*7/$D110)-INT($E$25*(7-1)/$D110))*$C110 -> 4 | L110: =(INT($E$25*8/$D110)-INT($E$25*(8-1)/$D110))*$C110 -> 0 | M110: =(INT($E$25*9/$D110)-INT($E$25*(9-1)/$D110))*$C110 -> 0 | N110: =(INT($E$25*10/$D110)-INT($E$25*(10-1)/$D110))*$C110 -> 4
B111: ROTARYHEAD (Ремкомплект вращателя | C111: 8 | D111: 13000 | E111: =(INT($E$25*1/$D111)-INT($E$25*(1-1)/$D111))*$C111 -> 0 | F111: =(INT($E$25*2/$D111)-INT($E$25*(2-1)/$D111))*$C111 -> 8 | G111: =(INT($E$25*3/$D111)-INT($E$25*(3-1)/$D111))*$C111 -> 0 | H111: =(INT($E$25*4/$D111)-INT($E$25*(4-1)/$D111))*$C111 -> 8 | I111: =(INT($E$25*5/$D111)-INT($E$25*(5-1)/$D111))*$C111 -> 0 | J111: =(INT($E$25*6/$D111)-INT($E$25*(6-1)/$D111))*$C111 -> 8 | K111: =(INT($E$25*7/$D111)-INT($E$25*(7-1)/$D111))*$C111 -> 0 | L111: =(INT($E$25*8/$D111)-INT($E$25*(8-1)/$D111))*$C111 -> 8 | M111: =(INT($E$25*9/$D111)-INT($E$25*(9-1)/$D111))*$C111 -> 0 | N111: =(INT($E$25*10/$D111)-INT($E$25*(10-1)/$D111))*$C111 -> 8
B112: KIT, SEAL (ремкомплект к цилиндру пода | C112: 36 | D112: 7450 | E112: =(INT($E$25*1/$D112)-INT($E$25*(1-1)/$D112))*$C112 -> 0 | F112: =(INT($E$25*2/$D112)-INT($E$25*(2-1)/$D112))*$C112 -> 36 | G112: =(INT($E$25*3/$D112)-INT($E$25*(3-1)/$D112))*$C112 -> 36 | H112: =(INT($E$25*4/$D112)-INT($E$25*(4-1)/$D112))*$C112 -> 36 | I112: =(INT($E$25*5/$D112)-INT($E$25*(5-1)/$D112))*$C112 -> 36 | J112: =(INT($E$25*6/$D112)-INT($E$25*(6-1)/$D112))*$C112 -> 36 | K112: =(INT($E$25*7/$D112)-INT($E$25*(7-1)/$D112))*$C112 -> 36 | L112: =(INT($E$25*8/$D112)-INT($E$25*(8-1)/$D112))*$C112 -> 36 | M112: =(INT($E$25*9/$D112)-INT($E$25*(9-1)/$D112))*$C112 -> 36 | N112: =(INT($E$25*10/$D112)-INT($E$25*(10-1)/$D112))*$C112 -> 36
B113: SEAL KIT,CYLINDER (ремкомплект к цил.д | C113: 72 | D113: 7450 | E113: =(INT($E$25*1/$D113)-INT($E$25*(1-1)/$D113))*$C113 -> 0 | F113: =(INT($E$25*2/$D113)-INT($E$25*(2-1)/$D113))*$C113 -> 72 | G113: =(INT($E$25*3/$D113)-INT($E$25*(3-1)/$D113))*$C113 -> 72 | H113: =(INT($E$25*4/$D113)-INT($E$25*(4-1)/$D113))*$C113 -> 72 | I113: =(INT($E$25*5/$D113)-INT($E$25*(5-1)/$D113))*$C113 -> 72 | J113: =(INT($E$25*6/$D113)-INT($E$25*(6-1)/$D113))*$C113 -> 72 | K113: =(INT($E$25*7/$D113)-INT($E$25*(7-1)/$D113))*$C113 -> 72 | L113: =(INT($E$25*8/$D113)-INT($E$25*(8-1)/$D113))*$C113 -> 72 | M113: =(INT($E$25*9/$D113)-INT($E$25*(9-1)/$D113))*$C113 -> 72 | N113: =(INT($E$25*10/$D113)-INT($E$25*(10-1)/$D113))*$C113 -> 72
B114: KIT, SEAL (ремкомплект к цилиндру п. м | C114: 28 | D114: 6000 | E114: =(INT($E$25*1/$D114)-INT($E$25*(1-1)/$D114))*$C114 -> 28 | F114: =(INT($E$25*2/$D114)-INT($E$25*(2-1)/$D114))*$C114 -> 28 | G114: =(INT($E$25*3/$D114)-INT($E$25*(3-1)/$D114))*$C114 -> 28 | H114: =(INT($E$25*4/$D114)-INT($E$25*(4-1)/$D114))*$C114 -> 28 | I114: =(INT($E$25*5/$D114)-INT($E$25*(5-1)/$D114))*$C114 -> 28 | J114: =(INT($E$25*6/$D114)-INT($E$25*(6-1)/$D114))*$C114 -> 56 | K114: =(INT($E$25*7/$D114)-INT($E$25*(7-1)/$D114))*$C114 -> 28 | L114: =(INT($E$25*8/$D114)-INT($E$25*(8-1)/$D114))*$C114 -> 28 | M114: =(INT($E$25*9/$D114)-INT($E$25*(9-1)/$D114))*$C114 -> 28 | N114: =(INT($E$25*10/$D114)-INT($E$25*(10-1)/$D114))*$C114 -> 28
B115: SEAL KIT (ремкомплектгидроцилиндр мех. | C115: 3.5 | D115: 6000 | E115: =(INT($E$25*1/$D115)-INT($E$25*(1-1)/$D115))*$C115 -> 3.5 | F115: =(INT($E$25*2/$D115)-INT($E$25*(2-1)/$D115))*$C115 -> 3.5 | G115: =(INT($E$25*3/$D115)-INT($E$25*(3-1)/$D115))*$C115 -> 3.5 | H115: =(INT($E$25*4/$D115)-INT($E$25*(4-1)/$D115))*$C115 -> 3.5 | I115: =(INT($E$25*5/$D115)-INT($E$25*(5-1)/$D115))*$C115 -> 3.5 | J115: =(INT($E$25*6/$D115)-INT($E$25*(6-1)/$D115))*$C115 -> 7 | K115: =(INT($E$25*7/$D115)-INT($E$25*(7-1)/$D115))*$C115 -> 3.5 | L115: =(INT($E$25*8/$D115)-INT($E$25*(8-1)/$D115))*$C115 -> 3.5 | M115: =(INT($E$25*9/$D115)-INT($E$25*(9-1)/$D115))*$C115 -> 3.5 | N115: =(INT($E$25*10/$D115)-INT($E$25*(10-1)/$D115))*$C115 -> 3.5
B116: KIT,SEAL (ремкомплект цилиндра ключа) | C116: 3.5 | D116: 4000 | E116: =(INT($E$25*1/$D116)-INT($E$25*(1-1)/$D116))*$C116 -> 3.5 | F116: =(INT($E$25*2/$D116)-INT($E$25*(2-1)/$D116))*$C116 -> 7 | G116: =(INT($E$25*3/$D116)-INT($E$25*(3-1)/$D116))*$C116 -> 7 | H116: =(INT($E$25*4/$D116)-INT($E$25*(4-1)/$D116))*$C116 -> 7 | I116: =(INT($E$25*5/$D116)-INT($E$25*(5-1)/$D116))*$C116 -> 3.5 | J116: =(INT($E$25*6/$D116)-INT($E$25*(6-1)/$D116))*$C116 -> 7 | K116: =(INT($E$25*7/$D116)-INT($E$25*(7-1)/$D116))*$C116 -> 7 | L116: =(INT($E$25*8/$D116)-INT($E$25*(8-1)/$D116))*$C116 -> 7 | M116: =(INT($E$25*9/$D116)-INT($E$25*(9-1)/$D116))*$C116 -> 3.5 | N116: =(INT($E$25*10/$D116)-INT($E$25*(10-1)/$D116))*$C116 -> 7
B117: SEAL KIT (ремкомплект цилиндра мех.зам | C117: 3.5 | D117: 4000 | E117: =(INT($E$25*1/$D117)-INT($E$25*(1-1)/$D117))*$C117 -> 3.5 | F117: =(INT($E$25*2/$D117)-INT($E$25*(2-1)/$D117))*$C117 -> 7 | G117: =(INT($E$25*3/$D117)-INT($E$25*(3-1)/$D117))*$C117 -> 7 | H117: =(INT($E$25*4/$D117)-INT($E$25*(4-1)/$D117))*$C117 -> 7 | I117: =(INT($E$25*5/$D117)-INT($E$25*(5-1)/$D117))*$C117 -> 3.5 | J117: =(INT($E$25*6/$D117)-INT($E$25*(6-1)/$D117))*$C117 -> 7 | K117: =(INT($E$25*7/$D117)-INT($E$25*(7-1)/$D117))*$C117 -> 7 | L117: =(INT($E$25*8/$D117)-INT($E$25*(8-1)/$D117))*$C117 -> 7 | M117: =(INT($E$25*9/$D117)-INT($E$25*(9-1)/$D117))*$C117 -> 3.5 | N117: =(INT($E$25*10/$D117)-INT($E$25*(10-1)/$D117))*$C117 -> 7
B118: SEAL KIT (ремкомплект к гидроцил.стопо | C118: 4 | D118: 5000 | E118: =(INT($E$25*1/$D118)-INT($E$25*(1-1)/$D118))*$C118 -> 4 | F118: =(INT($E$25*2/$D118)-INT($E$25*(2-1)/$D118))*$C118 -> 4 | G118: =(INT($E$25*3/$D118)-INT($E$25*(3-1)/$D118))*$C118 -> 8 | H118: =(INT($E$25*4/$D118)-INT($E$25*(4-1)/$D118))*$C118 -> 4 | I118: =(INT($E$25*5/$D118)-INT($E$25*(5-1)/$D118))*$C118 -> 8 | J118: =(INT($E$25*6/$D118)-INT($E$25*(6-1)/$D118))*$C118 -> 4 | K118: =(INT($E$25*7/$D118)-INT($E$25*(7-1)/$D118))*$C118 -> 4 | L118: =(INT($E$25*8/$D118)-INT($E$25*(8-1)/$D118))*$C118 -> 8 | M118: =(INT($E$25*9/$D118)-INT($E$25*(9-1)/$D118))*$C118 -> 4 | N118: =(INT($E$25*10/$D118)-INT($E$25*(10-1)/$D118))*$C118 -> 8
B119: SEAL KIT (ремкомплект гидроцил.фартука | C119: 0.9 | D119: 4000 | E119: =(INT($E$25*1/$D119)-INT($E$25*(1-1)/$D119))*$C119 -> 0.9 | F119: =(INT($E$25*2/$D119)-INT($E$25*(2-1)/$D119))*$C119 -> 1.8 | G119: =(INT($E$25*3/$D119)-INT($E$25*(3-1)/$D119))*$C119 -> 1.8 | H119: =(INT($E$25*4/$D119)-INT($E$25*(4-1)/$D119))*$C119 -> 1.8 | I119: =(INT($E$25*5/$D119)-INT($E$25*(5-1)/$D119))*$C119 -> 0.9 | J119: =(INT($E$25*6/$D119)-INT($E$25*(6-1)/$D119))*$C119 -> 1.8 | K119: =(INT($E$25*7/$D119)-INT($E$25*(7-1)/$D119))*$C119 -> 1.8 | L119: =(INT($E$25*8/$D119)-INT($E$25*(8-1)/$D119))*$C119 -> 1.8 | M119: =(INT($E$25*9/$D119)-INT($E$25*(9-1)/$D119))*$C119 -> 0.9 | N119: =(INT($E$25*10/$D119)-INT($E$25*(10-1)/$D119))*$C119 -> 1.8
B120: Ремонт системы смазки | C120: 2 | D120: 12000 | E120: =(INT($E$25*1/$D120)-INT($E$25*(1-1)/$D120))*$C120 -> 0 | F120: =(INT($E$25*2/$D120)-INT($E$25*(2-1)/$D120))*$C120 -> 2 | G120: =(INT($E$25*3/$D120)-INT($E$25*(3-1)/$D120))*$C120 -> 0 | H120: =(INT($E$25*4/$D120)-INT($E$25*(4-1)/$D120))*$C120 -> 2 | I120: =(INT($E$25*5/$D120)-INT($E$25*(5-1)/$D120))*$C120 -> 0 | J120: =(INT($E$25*6/$D120)-INT($E$25*(6-1)/$D120))*$C120 -> 2 | K120: =(INT($E$25*7/$D120)-INT($E$25*(7-1)/$D120))*$C120 -> 2 | L120: =(INT($E$25*8/$D120)-INT($E$25*(8-1)/$D120))*$C120 -> 0 | M120: =(INT($E$25*9/$D120)-INT($E$25*(9-1)/$D120))*$C120 -> 2 | N120: =(INT($E$25*10/$D120)-INT($E$25*(10-1)/$D120))*$C120 -> 0
... B124: Инспекция металлоконструкций | C124: 185 | D124: 65000 | E124: =(INT($E$25*1/$D124)-INT($E$25*(1-1)/$D124))*$C124 -> 0 | F124: =(INT($E$25*2/$D124)-INT($E$25*(2-1)/$D124))*$C124 -> 0 | G124: =(INT($E$25*3/$D124)-INT($E$25*(3-1)/$D124))*$C124 -> 0 | H124: =(INT($E$25*4/$D124)-INT($E$25*(4-1)/$D124))*$C124 -> 0 | I124: =(INT($E$25*5/$D124)-INT($E$25*(5-1)/$D124))*$C124 -> 0 | J124: =(INT($E$25*6/$D124)-INT($E$25*(6-1)/$D124))*$C124 -> 0 | K124: =(INT($E$25*7/$D124)-INT($E$25*(7-1)/$D124))*$C124 -> 0 | L124: =(INT($E$25*8/$D124)-INT($E$25*(8-1)/$D124))*$C124 -> 0 | M124: =(INT($E$25*9/$D124)-INT($E$25*(9-1)/$D124))*$C124 -> 0 | N124: =(INT($E$25*10/$D124)-INT($E$25*(10-1)/$D124))*$C124 -> 185
B125: ИТОГО | E125: =SUM(E109:E124) -> 48.4 | F125: =SUM(F109:F124) -> 174.3 | G125: =SUM(G109:G124) -> 228.3 | H125: =SUM(H109:H124) -> 174.3 | I125: =SUM(I109:I124) -> 220.4 | J125: =SUM(J109:J124) -> 255.8 | K125: =SUM(K109:K124) -> 226.3 | L125: =SUM(L109:L124) -> 176.3 | ... N125: =SUM(N109:N124) -> 365.3
B127: КАПИТАЛЬНЫЕ РЕМОНТЫ — ЗАТРАТЫ НА ЗЧ (по ресурсу до замены узла)
B128: Наименование | C128: стоим.замены,вал | D128: ресурс, м/ч | E128: год 1 | F128: год 2 | G128: год 3 | H128: год 4 | I128: год 5 | J128: год 6 | K128: год 7 | L128: год 8 | M128: год 9 | N128: год 10
B129: PUMP,P7,9A CONT (главный насос) | C129: 37124 | D129: 12000 | E129: =(INT($E$25*1/$D129)-INT($E$25*(1-1)/$D129))*$C129/1000 -> 0 | F129: =(INT($E$25*2/$D129)-INT($E$25*(2-1)/$D129))*$C129/1000 -> 37.124 | G129: =(INT($E$25*3/$D129)-INT($E$25*(3-1)/$D129))*$C129/1000 -> 0 | H129: =(INT($E$25*4/$D129)-INT($E$25*(4-1)/$D129))*$C129/1000 -> 37.124 | I129: =(INT($E$25*5/$D129)-INT($E$25*(5-1)/$D129))*$C129/1000 -> 0 | J129: =(INT($E$25*6/$D129)-INT($E$25*(6-1)/$D129))*$C129/1000 -> 37.124 | K129: =(INT($E$25*7/$D129)-INT($E$25*(7-1)/$D129))*$C129/1000 -> 37.124 | L129: =(INT($E$25*8/$D129)-INT($E$25*(8-1)/$D129))*$C129/1000 -> 0 | M129: =(INT($E$25*9/$D129)-INT($E$25*(9-1)/$D129))*$C129/1000 -> 37.124 | N129: =(INT($E$25*10/$D129)-INT($E$25*(10-1)/$D129))*$C129/1000 -> 0
B130: DRIVE SHAFT & BEARING (вал и подшипник | C130: 1226.17 | D130: 11000 | E130: =(INT($E$25*1/$D130)-INT($E$25*(1-1)/$D130))*$C130/1000 -> 0 | F130: =(INT($E$25*2/$D130)-INT($E$25*(2-1)/$D130))*$C130/1000 -> 1.22617 | G130: =(INT($E$25*3/$D130)-INT($E$25*(3-1)/$D130))*$C130/1000 -> 0 | H130: =(INT($E$25*4/$D130)-INT($E$25*(4-1)/$D130))*$C130/1000 -> 1.22617 | I130: =(INT($E$25*5/$D130)-INT($E$25*(5-1)/$D130))*$C130/1000 -> 1.22617 | J130: =(INT($E$25*6/$D130)-INT($E$25*(6-1)/$D130))*$C130/1000 -> 0 | K130: =(INT($E$25*7/$D130)-INT($E$25*(7-1)/$D130))*$C130/1000 -> 1.22617 | L130: =(INT($E$25*8/$D130)-INT($E$25*(8-1)/$D130))*$C130/1000 -> 1.22617 | M130: =(INT($E$25*9/$D130)-INT($E$25*(9-1)/$D130))*$C130/1000 -> 0 | N130: =(INT($E$25*10/$D130)-INT($E$25*(10-1)/$D130))*$C130/1000 -> 1.22617
B131: STROKER,9A ELECTROHYD (сервоприв.) | C131: 18096.84 | D131: 12000 | E131: =(INT($E$25*1/$D131)-INT($E$25*(1-1)/$D131))*$C131/1000 -> 0 | F131: =(INT($E$25*2/$D131)-INT($E$25*(2-1)/$D131))*$C131/1000 -> 18.09684 | G131: =(INT($E$25*3/$D131)-INT($E$25*(3-1)/$D131))*$C131/1000 -> 0 | H131: =(INT($E$25*4/$D131)-INT($E$25*(4-1)/$D131))*$C131/1000 -> 18.09684 | I131: =(INT($E$25*5/$D131)-INT($E$25*(5-1)/$D131))*$C131/1000 -> 0 | J131: =(INT($E$25*6/$D131)-INT($E$25*(6-1)/$D131))*$C131/1000 -> 18.09684 | K131: =(INT($E$25*7/$D131)-INT($E$25*(7-1)/$D131))*$C131/1000 -> 18.09684 | L131: =(INT($E$25*8/$D131)-INT($E$25*(8-1)/$D131))*$C131/1000 -> 0 | M131: =(INT($E$25*9/$D131)-INT($E$25*(9-1)/$D131))*$C131/1000 -> 18.09684 | N131: =(INT($E$25*10/$D131)-INT($E$25*(10-1)/$D131))*$C131/1000 -> 0
B132: PUMP,TRIPLE (лопастной насос) | C132: 6929.74 | D132: 8000 | E132: =(INT($E$25*1/$D132)-INT($E$25*(1-1)/$D132))*$C132/1000 -> 0 | F132: =(INT($E$25*2/$D132)-INT($E$25*(2-1)/$D132))*$C132/1000 -> 6.92974 | G132: =(INT($E$25*3/$D132)-INT($E$25*(3-1)/$D132))*$C132/1000 -> 6.92974 | H132: =(INT($E$25*4/$D132)-INT($E$25*(4-1)/$D132))*$C132/1000 -> 6.92974 | I132: =(INT($E$25*5/$D132)-INT($E$25*(5-1)/$D132))*$C132/1000 -> 6.92974 | J132: =(INT($E$25*6/$D132)-INT($E$25*(6-1)/$D132))*$C132/1000 -> 6.92974 | K132: =(INT($E$25*7/$D132)-INT($E$25*(7-1)/$D132))*$C132/1000 -> 6.92974 | L132: =(INT($E$25*8/$D132)-INT($E$25*(8-1)/$D132))*$C132/1000 -> 6.92974 | M132: =(INT($E$25*9/$D132)-INT($E$25*(9-1)/$D132))*$C132/1000 -> 0 | N132: =(INT($E$25*10/$D132)-INT($E$25*(10-1)/$D132))*$C132/1000 -> 6.92974
B133: VALVE,ASSEMBLY,6 SPOOL (сборка расп.кл | C133: 19766.43 | D133: 25000 | E133: =(INT($E$25*1/$D133)-INT($E$25*(1-1)/$D133))*$C133/1000 -> 0 | F133: =(INT($E$25*2/$D133)-INT($E$25*(2-1)/$D133))*$C133/1000 -> 0 | G133: =(INT($E$25*3/$D133)-INT($E$25*(3-1)/$D133))*$C133/1000 -> 0 | H133: =(INT($E$25*4/$D133)-INT($E$25*(4-1)/$D133))*$C133/1000 -> 19.76643 | I133: =(INT($E$25*5/$D133)-INT($E$25*(5-1)/$D133))*$C133/1000 -> 0 | J133: =(INT($E$25*6/$D133)-INT($E$25*(6-1)/$D133))*$C133/1000 -> 0 | K133: =(INT($E$25*7/$D133)-INT($E$25*(7-1)/$D133))*$C133/1000 -> 0 | L133: =(INT($E$25*8/$D133)-INT($E$25*(8-1)/$D133))*$C133/1000 -> 19.76643 | M133: =(INT($E$25*9/$D133)-INT($E$25*(9-1)/$D133))*$C133/1000 -> 0 | N133: =(INT($E$25*10/$D133)-INT($E$25*(10-1)/$D133))*$C133/1000 -> 0
...

Sheet Поставщик 2
B1: ДАННЫЕ ПОСТАВЩИКА — ВАРИАНТ 2 (ТО и Ремонты — модель по узлам)
B2: Жёлтое — ввод. Зелёное — авто (снизу вверх). ИТОГО ТОиР = (ЗЧ ТО + ЗЧ тек.+кап.ремонтов + сервис) × коэф.калибровки; тянется в «Данные по годам».
B4: Буровой станок: | E4: ='Ввод данных'!E7 -> Sunward SWDRT250SM
B5: Валюта затрат ТОиР: | D5: EUR
B6: Показатель | C6: Ед. | E6: год 1 | F6: год 2 | G6: год 3 | H6: год 4 | I6: год 5 | J6: год 6 | K6: год 7 | L6: год 8 | M6: год 9 | N6: год 10
B7: СВОДКА ПО ГОДАМ (зелёное — авто снизу вверх; тянется в расчёт)
B8: Простои на ТО (авто из интервалов) | C8: ч/год | E8: =E40 -> 636.37233 | F8: =F40 -> 636.37233 | G8: =G40 -> 636.37233 | H8: =H40 -> 636.37233 | I8: =I40 -> 636.37233 | J8: =J40 -> 636.37233 | K8: =K40 -> 636.37233 | L8: =L40 -> 636.37233 | ... N8: =N40 -> 636.37233
B9: Простои в ремонтах (справочно) | C9: ч/год | E9: 425.645 | F9: 690.645 | G9: 870.645 | H9: 605.645 | I9: 690.645 | J9: 890.645 | K9: 720.645 | L9: 690.645 | M9: 830.645 | N9: 790.645
B10: Ежесменный осмотр (20 мин/смену), справочно | C10: ч/год | E10: =('Параметры'!C27-E8-E9)/'Параметры'!C28*20/60 -> 213.83285 | F10: =('Параметры'!C27-F8-F9)/'Параметры'!C28*20/60 -> 206.47174 | G10: =('Параметры'!C27-G8-G9)/'Параметры'!C28*20/60 -> 201.47174 | H10: =('Параметры'!C27-H8-H9)/'Параметры'!C28*20/60 -> 208.83285 | I10: =('Параметры'!C27-I8-I9)/'Параметры'!C28*20/60 -> 206.47174 | J10: =('Параметры'!C27-J8-J9)/'Параметры'!C28*20/60 -> 200.91619 | K10: =('Параметры'!C27-K8-K9)/'Параметры'!C28*20/60 -> 205.63841 | L10: =('Параметры'!C27-L8-L9)/'Параметры'!C28*20/60 -> 206.47174 | M10: =('Параметры'!C27-M8-M9)/'Параметры'!C28*20/60 -> 202.58285 | N10: =('Параметры'!C27-N8-N9)/'Параметры'!C28*20/60 -> 203.69396
B11: КТГ (техготовность, ВВОД) → «Данные по годам» | C11: коэф. | E11: 0.8948 | F11: 0.8654 | G11: 0.8454 | H11: 0.8748 | I11: 0.8654 | J11: 0.8432 | K11: 0.8621 | L11: 0.8654 | M11: 0.8498 | N11: 0.8543
B12: Затраты на ЗЧ ТО (авто из каталога) | C12: тыс.вал/г | E12: =E85 -> 136.07379 | F12: =F85 -> 136.07379 | G12: =G85 -> 136.07379 | H12: =H85 -> 136.07379 | I12: =I85 -> 136.07379 | J12: =J85 -> 136.07379 | K12: =K85 -> 136.07379 | L12: =L85 -> 136.07379 | ... N12: =N85 -> 136.07379
B13: Затраты на ЗЧ текущих ремонтов (по ресурсу) | C13: тыс.вал/г | E13: =E105 -> 4.50682 | F13: =F105 -> 60.10984 | G13: =G105 -> 145.1624 | H13: =H105 -> 60.10984 | I13: =I105 -> 144.82518 | J13: =J105 -> 67.22701 | K13: =K105 -> 145.21432 | L13: =L105 -> 60.05792 | ... N13: =N105 -> 105.58931
B14: Затраты на ЗЧ капремонтов (по ресурсу) | C14: тыс.вал/г | E14: =E188 -> 7.38238 | F14: =F188 -> 204.26495 | G14: =G188 -> 438.81584 | H14: =H188 -> 434.86339 | I14: =I188 -> 610.36746 | J14: =J188 -> 366.36175 | K14: =K188 -> 590.25823 | L14: =L188 -> 224.66392 | ... N14: =N188 -> 283.30237
B15: Трудозатраты ТО (авто) | C15: ч-час/г | E15: =E47 -> 636.37233 | F15: =F47 -> 636.37233 | G15: =G47 -> 636.37233 | H15: =H47 -> 636.37233 | I15: =I47 -> 636.37233 | J15: =J47 -> 636.37233 | K15: =K47 -> 636.37233 | L15: =L47 -> 636.37233 | ... N15: =N47 -> 636.37233
B16: Трудозатраты текущих ремонтов (авто) | C16: ч-час/г | E16: =E125 -> 48.4 | F16: =F125 -> 174.3 | G16: =G125 -> 228.3 | H16: =H125 -> 174.3 | I16: =I125 -> 220.4 | J16: =J125 -> 255.8 | K16: =K125 -> 226.3 | L16: =L125 -> 176.3 | ... N16: =N125 -> 365.3
B17: Трудозатраты капремонтов (авто) | C17: ч-час/г | E17: =E251 -> 36.6 | F17: =F251 -> 192.66 | G17: =G251 -> 330.45 | H17: =H251 -> 188.56 | I17: =I251 -> 267.75 | J17: =J251 -> 319.96 | K17: =K251 -> 300.71 | L17: =L251 -> 155.4 | ... N17: =N251 -> 102.4
B18: Сервис (трудозатраты ТО+ТР+КР) | C18: тыс.вал/г | E18: =(E15+E16+E17)*$E$23/1000 -> 41.762927 | F18: =(F15+F16+F17)*$E$23/1000 -> 58.086639 | G18: =(G15+G16+G17)*$E$23/1000 -> 69.190076 | H18: =(H15+H16+H17)*$E$23/1000 -> 57.849275 | I18: =(I15+I16+I17)*$E$23/1000 -> 65.102779 | J18: =(J15+J16+J17)*$E$23/1000 -> 70.174848 | K18: =(K15+K16+K17)*$E$23/1000 -> 67.352529 | L18: =(L15+L16+L17)*$E$23/1000 -> 56.045307 | ... N18: =(N15+N16+N17)*$E$23/1000 -> 63.918853
B19: Коэффициент калибровки ИТОГО под ТКП | C19: коэф. | E19: 0.8536
B20: ИТОГО ТОиР → «Данные по годам» | C20: тыс.вал/г | E20: =(E12+E13+E14+E18)*$E$19 -> 161.95004 | F20: =(F12+F13+F14+F18)*$E$19 -> 391.40566 | G20: =(G12+G13+G14+G18)*$E$19 -> 673.69706 | H20: =(H12+H13+H14+H18)*$E$19 -> 588.04188 | I20: =(I12+I13+I14+I18)*$E$19 -> 816.35676 | J20: =(J12+J13+J14+J18)*$E$19 -> 546.1652 | K20: =(K12+K13+K14+K18)*$E$19 -> 801.44407 | L20: =(L12+L13+L14+L18)*$E$19 -> 407.03142 | ... N20: =(N12+N13+N14+N18)*$E$19 -> 502.67166
B21: Удельный расход ДТ / энергии | C21: кг(кВт)/час | E21: 75.15 | F21: 75.15 | G21: 75.15 | H21: 75.15 | I21: 75.15 | J21: 75.15 | K21: 75.15 | L21: 75.15 | M21: 75.15 | N21: 75.15
B23: Ставка сервиса | C23: вал/ч·час | E23: 57.893718
B24: РАСЧЁТ ТО (по интервалам обслуживания), ПО ГОДАМ
B25: Наработка по годам | C25: м/час | E25: 7000 | F25: 7000 | G25: 7000 | H25: 7000 | I25: 7000 | J25: 7000 | K25: 7000 | L25: 7000 | M25: 7000 | N25: 7000
B26: Вид ТО | C26: интервал, м/ч | D26: простой/ТО, ч | E26: персонал
B27: ТО-1 | C27: 250 | D27: 10.9 | E27: 1
B28: ТО-2 | C28: 500 | D28: 13.5 | E28: 1
B29: ТО-3 | C29: 1000 | D29: 12.43 | E29: 1
B30: ТО-4 | C30: 2000 | D30: 5.67 | E30: 1
B31: ТО-5 | C31: 3000 | D31: 10.06 | E31: 1
B32: ТО-6 | C32: 5000 | D32: 8.46 | E32: 1
B34: ТО-1: простои, ч/год | C34: ч | E34: =E$25/$C27*$D27 -> 305.2 | F34: =F$25/$C27*$D27 -> 305.2 | G34: =G$25/$C27*$D27 -> 305.2 | H34: =H$25/$C27*$D27 -> 305.2 | I34: =I$25/$C27*$D27 -> 305.2 | J34: =J$25/$C27*$D27 -> 305.2 | K34: =K$25/$C27*$D27 -> 305.2 | L34: =L$25/$C27*$D27 -> 305.2 | ... N34: =N$25/$C27*$D27 -> 305.2
B35: ТО-2: простои, ч/год | C35: ч | E35: =E$25/$C28*$D28 -> 189 | F35: =F$25/$C28*$D28 -> 189 | G35: =G$25/$C28*$D28 -> 189 | H35: =H$25/$C28*$D28 -> 189 | I35: =I$25/$C28*$D28 -> 189 | J35: =J$25/$C28*$D28 -> 189 | K35: =K$25/$C28*$D28 -> 189 | L35: =L$25/$C28*$D28 -> 189 | ... N35: =N$25/$C28*$D28 -> 189
B36: ТО-3: простои, ч/год | C36: ч | E36: =E$25/$C29*$D29 -> 87.01 | F36: =F$25/$C29*$D29 -> 87.01 | G36: =G$25/$C29*$D29 -> 87.01 | H36: =H$25/$C29*$D29 -> 87.01 | I36: =I$25/$C29*$D29 -> 87.01 | J36: =J$25/$C29*$D29 -> 87.01 | K36: =K$25/$C29*$D29 -> 87.01 | L36: =L$25/$C29*$D29 -> 87.01 | ... N36: =N$25/$C29*$D29 -> 87.01
B37: ТО-4: простои, ч/год | C37: ч | E37: =E$25/$C30*$D30 -> 19.845 | F37: =F$25/$C30*$D30 -> 19.845 | G37: =G$25/$C30*$D30 -> 19.845 | H37: =H$25/$C30*$D30 -> 19.845 | I37: =I$25/$C30*$D30 -> 19.845 | J37: =J$25/$C30*$D30 -> 19.845 | K37: =K$25/$C30*$D30 -> 19.845 | L37: =L$25/$C30*$D30 -> 19.845 | ... N37: =N$25/$C30*$D30 -> 19.845
B38: ТО-5: простои, ч/год | C38: ч | E38: =E$25/$C31*$D31 -> 23.473333 | F38: =F$25/$C31*$D31 -> 23.473333 | G38: =G$25/$C31*$D31 -> 23.473333 | H38: =H$25/$C31*$D31 -> 23.473333 | I38: =I$25/$C31*$D31 -> 23.473333 | J38: =J$25/$C31*$D31 -> 23.473333 | K38: =K$25/$C31*$D31 -> 23.473333 | L38: =L$25/$C31*$D31 -> 23.473333 | ... N38: =N$25/$C31*$D31 -> 23.473333
B39: ТО-6: простои, ч/год | C39: ч | E39: =E$25/$C32*$D32 -> 11.844 | F39: =F$25/$C32*$D32 -> 11.844 | G39: =G$25/$C32*$D32 -> 11.844 | H39: =H$25/$C32*$D32 -> 11.844 | I39: =I$25/$C32*$D32 -> 11.844 | J39: =J$25/$C32*$D32 -> 11.844 | K39: =K$25/$C32*$D32 -> 11.844 | L39: =L$25/$C32*$D32 -> 11.844 | ... N39: =N$25/$C32*$D32 -> 11.844
B40: Итого простои ТО | E40: =SUM(E34:E39) -> 636.37233 | F40: =SUM(F34:F39) -> 636.37233 | G40: =SUM(G34:G39) -> 636.37233 | H40: =SUM(H34:H39) -> 636.37233 | I40: =SUM(I34:I39) -> 636.37233 | J40: =SUM(J34:J39) -> 636.37233 | K40: =SUM(K34:K39) -> 636.37233 | L40: =SUM(L34:L39) -> 636.37233 | ... N40: =SUM(N34:N39) -> 636.37233
B41: ТО-1: чел-часы/год | C41: ч-час | E41: =E34*$E27 -> 305.2 | F41: =F34*$E27 -> 305.2 | G41: =G34*$E27 -> 305.2 | H41: =H34*$E27 -> 305.2 | I41: =I34*$E27 -> 305.2 | J41: =J34*$E27 -> 305.2 | K41: =K34*$E27 -> 305.2 | L41: =L34*$E27 -> 305.2 | ... N41: =N34*$E27 -> 305.2
B42: ТО-2: чел-часы/год | C42: ч-час | E42: =E35*$E28 -> 189 | F42: =F35*$E28 -> 189 | G42: =G35*$E28 -> 189 | H42: =H35*$E28 -> 189 | I42: =I35*$E28 -> 189 | J42: =J35*$E28 -> 189 | K42: =K35*$E28 -> 189 | L42: =L35*$E28 -> 189 | ... N42: =N35*$E28 -> 189
B43: ТО-3: чел-часы/год | C43: ч-час | E43: =E36*$E29 -> 87.01 | F43: =F36*$E29 -> 87.01 | G43: =G36*$E29 -> 87.01 | H43: =H36*$E29 -> 87.01 | I43: =I36*$E29 -> 87.01 | J43: =J36*$E29 -> 87.01 | K43: =K36*$E29 -> 87.01 | L43: =L36*$E29 -> 87.01 | ... N43: =N36*$E29 -> 87.01
B44: ТО-4: чел-часы/год | C44: ч-час | E44: =E37*$E30 -> 19.845 | F44: =F37*$E30 -> 19.845 | G44: =G37*$E30 -> 19.845 | H44: =H37*$E30 -> 19.845 | I44: =I37*$E30 -> 19.845 | J44: =J37*$E30 -> 19.845 | K44: =K37*$E30 -> 19.845 | L44: =L37*$E30 -> 19.845 | ... N44: =N37*$E30 -> 19.845
B45: ТО-5: чел-часы/год | C45: ч-час | E45: =E38*$E31 -> 23.473333 | F45: =F38*$E31 -> 23.473333 | G45: =G38*$E31 -> 23.473333 | H45: =H38*$E31 -> 23.473333 | I45: =I38*$E31 -> 23.473333 | J45: =J38*$E31 -> 23.473333 | K45: =K38*$E31 -> 23.473333 | L45: =L38*$E31 -> 23.473333 | ... N45: =N38*$E31 -> 23.473333
B46: ТО-6: чел-часы/год | C46: ч-час | E46: =E39*$E32 -> 11.844 | F46: =F39*$E32 -> 11.844 | G46: =G39*$E32 -> 11.844 | H46: =H39*$E32 -> 11.844 | I46: =I39*$E32 -> 11.844 | J46: =J39*$E32 -> 11.844 | K46: =K39*$E32 -> 11.844 | L46: =L39*$E32 -> 11.844 | ... N46: =N39*$E32 -> 11.844
B47: Итого чел-часы ТО | E47: =SUM(E41:E46) -> 636.37233 | F47: =SUM(F41:F46) -> 636.37233 | G47: =SUM(G41:G46) -> 636.37233 | H47: =SUM(H41:H46) -> 636.37233 | I47: =SUM(I41:I46) -> 636.37233 | J47: =SUM(J41:J46) -> 636.37233 | K47: =SUM(K41:K46) -> 636.37233 | L47: =SUM(L41:L46) -> 636.37233 | ... N47: =SUM(N41:N46) -> 636.37233
B49: КАТАЛОГ ЗАПЧАСТЕЙ ТО (заполняет подрядчик), ПО ГОДАМ
B50: Наименование | C50: цена за ед | D50: кол-во/ТО | P50: № ТО
B51: Моторное масло | C51: 6.77 | D51: 70 | E51: =E$25/INDEX($C$27:$C$32,$P51)*D51*C51/1000 -> 13.2692 | F51: =F$25/INDEX($C$27:$C$32,$P51)*D51*C51/1000 -> 13.2692 | G51: =G$25/INDEX($C$27:$C$32,$P51)*D51*C51/1000 -> 13.2692 | H51: =H$25/INDEX($C$27:$C$32,$P51)*D51*C51/1000 -> 13.2692 | I51: =I$25/INDEX($C$27:$C$32,$P51)*D51*C51/1000 -> 13.2692 | J51: =J$25/INDEX($C$27:$C$32,$P51)*D51*C51/1000 -> 13.2692 | K51: =K$25/INDEX($C$27:$C$32,$P51)*D51*C51/1000 -> 13.2692 | L51: =L$25/INDEX($C$27:$C$32,$P51)*D51*C51/1000 -> 13.2692 | M51: =M$25/INDEX($C$27:$C$32,$P51)*D51*C51/1000 -> 13.2692 | N51: =N$25/INDEX($C$27:$C$32,$P51)*D51*C51/1000 -> 13.2692 | P51: 1
B52: Масляный фильтр двигателя | C52: 75.788 | D52: 2 | E52: =E$25/INDEX($C$27:$C$32,$P52)*D52*C52/1000 -> 4.244128 | F52: =F$25/INDEX($C$27:$C$32,$P52)*D52*C52/1000 -> 4.244128 | G52: =G$25/INDEX($C$27:$C$32,$P52)*D52*C52/1000 -> 4.244128 | H52: =H$25/INDEX($C$27:$C$32,$P52)*D52*C52/1000 -> 4.244128 | I52: =I$25/INDEX($C$27:$C$32,$P52)*D52*C52/1000 -> 4.244128 | J52: =J$25/INDEX($C$27:$C$32,$P52)*D52*C52/1000 -> 4.244128 | K52: =K$25/INDEX($C$27:$C$32,$P52)*D52*C52/1000 -> 4.244128 | L52: =L$25/INDEX($C$27:$C$32,$P52)*D52*C52/1000 -> 4.244128 | M52: =M$25/INDEX($C$27:$C$32,$P52)*D52*C52/1000 -> 4.244128 | N52: =N$25/INDEX($C$27:$C$32,$P52)*D52*C52/1000 -> 4.244128 | P52: 1
B53: Охлаждающая жидкость | C53: 4.368 | D53: 3 | E53: =E$25/INDEX($C$27:$C$32,$P53)*D53*C53/1000 -> 0.366912 | F53: =F$25/INDEX($C$27:$C$32,$P53)*D53*C53/1000 -> 0.366912 | G53: =G$25/INDEX($C$27:$C$32,$P53)*D53*C53/1000 -> 0.366912 | H53: =H$25/INDEX($C$27:$C$32,$P53)*D53*C53/1000 -> 0.366912 | I53: =I$25/INDEX($C$27:$C$32,$P53)*D53*C53/1000 -> 0.366912 | J53: =J$25/INDEX($C$27:$C$32,$P53)*D53*C53/1000 -> 0.366912 | K53: =K$25/INDEX($C$27:$C$32,$P53)*D53*C53/1000 -> 0.366912 | L53: =L$25/INDEX($C$27:$C$32,$P53)*D53*C53/1000 -> 0.366912 | M53: =M$25/INDEX($C$27:$C$32,$P53)*D53*C53/1000 -> 0.366912 | N53: =N$25/INDEX($C$27:$C$32,$P53)*D53*C53/1000 -> 0.366912 | P53: 1
B54: Воздушный фильтр первичный | C54: 51.588 | D54: 3 | E54: =E$25/INDEX($C$27:$C$32,$P54)*D54*C54/1000 -> 4.333392 | F54: =F$25/INDEX($C$27:$C$32,$P54)*D54*C54/1000 -> 4.333392 | G54: =G$25/INDEX($C$27:$C$32,$P54)*D54*C54/1000 -> 4.333392 | H54: =H$25/INDEX($C$27:$C$32,$P54)*D54*C54/1000 -> 4.333392 | I54: =I$25/INDEX($C$27:$C$32,$P54)*D54*C54/1000 -> 4.333392 | J54: =J$25/INDEX($C$27:$C$32,$P54)*D54*C54/1000 -> 4.333392 | K54: =K$25/INDEX($C$27:$C$32,$P54)*D54*C54/1000 -> 4.333392 | L54: =L$25/INDEX($C$27:$C$32,$P54)*D54*C54/1000 -> 4.333392 | M54: =M$25/INDEX($C$27:$C$32,$P54)*D54*C54/1000 -> 4.333392 | N54: =N$25/INDEX($C$27:$C$32,$P54)*D54*C54/1000 -> 4.333392 | P54: 1
B55: Воздушный фильтр вторичный | C55: 37.65 | D55: 3 | E55: =E$25/INDEX($C$27:$C$32,$P55)*D55*C55/1000 -> 3.1626 | F55: =F$25/INDEX($C$27:$C$32,$P55)*D55*C55/1000 -> 3.1626 | G55: =G$25/INDEX($C$27:$C$32,$P55)*D55*C55/1000 -> 3.1626 | H55: =H$25/INDEX($C$27:$C$32,$P55)*D55*C55/1000 -> 3.1626 | I55: =I$25/INDEX($C$27:$C$32,$P55)*D55*C55/1000 -> 3.1626 | J55: =J$25/INDEX($C$27:$C$32,$P55)*D55*C55/1000 -> 3.1626 | K55: =K$25/INDEX($C$27:$C$32,$P55)*D55*C55/1000 -> 3.1626 | L55: =L$25/INDEX($C$27:$C$32,$P55)*D55*C55/1000 -> 3.1626 | M55: =M$25/INDEX($C$27:$C$32,$P55)*D55*C55/1000 -> 3.1626 | N55: =N$25/INDEX($C$27:$C$32,$P55)*D55*C55/1000 -> 3.1626 | P55: 1
B56: Фильтр системы охл. ДВС | C56: 27.113 | D56: 2 | E56: =E$25/INDEX($C$27:$C$32,$P56)*D56*C56/1000 -> 1.518328 | F56: =F$25/INDEX($C$27:$C$32,$P56)*D56*C56/1000 -> 1.518328 | G56: =G$25/INDEX($C$27:$C$32,$P56)*D56*C56/1000 -> 1.518328 | H56: =H$25/INDEX($C$27:$C$32,$P56)*D56*C56/1000 -> 1.518328 | I56: =I$25/INDEX($C$27:$C$32,$P56)*D56*C56/1000 -> 1.518328 | J56: =J$25/INDEX($C$27:$C$32,$P56)*D56*C56/1000 -> 1.518328 | K56: =K$25/INDEX($C$27:$C$32,$P56)*D56*C56/1000 -> 1.518328 | L56: =L$25/INDEX($C$27:$C$32,$P56)*D56*C56/1000 -> 1.518328 | M56: =M$25/INDEX($C$27:$C$32,$P56)*D56*C56/1000 -> 1.518328 | N56: =N$25/INDEX($C$27:$C$32,$P56)*D56*C56/1000 -> 1.518328 | P56: 1
B57: Топливный фильтр первичный | C57: 65.662 | D57: 1 | E57: =E$25/INDEX($C$27:$C$32,$P57)*D57*C57/1000 -> 1.838536 | F57: =F$25/INDEX($C$27:$C$32,$P57)*D57*C57/1000 -> 1.838536 | G57: =G$25/INDEX($C$27:$C$32,$P57)*D57*C57/1000 -> 1.838536 | H57: =H$25/INDEX($C$27:$C$32,$P57)*D57*C57/1000 -> 1.838536 | I57: =I$25/INDEX($C$27:$C$32,$P57)*D57*C57/1000 -> 1.838536 | J57: =J$25/INDEX($C$27:$C$32,$P57)*D57*C57/1000 -> 1.838536 | K57: =K$25/INDEX($C$27:$C$32,$P57)*D57*C57/1000 -> 1.838536 | L57: =L$25/INDEX($C$27:$C$32,$P57)*D57*C57/1000 -> 1.838536 | M57: =M$25/INDEX($C$27:$C$32,$P57)*D57*C57/1000 -> 1.838536 | N57: =N$25/INDEX($C$27:$C$32,$P57)*D57*C57/1000 -> 1.838536 | P57: 1
B58: Топливный фильтр вторичный | C58: 127.662 | D58: 1 | E58: =E$25/INDEX($C$27:$C$32,$P58)*D58*C58/1000 -> 3.574536 | F58: =F$25/INDEX($C$27:$C$32,$P58)*D58*C58/1000 -> 3.574536 | G58: =G$25/INDEX($C$27:$C$32,$P58)*D58*C58/1000 -> 3.574536 | H58: =H$25/INDEX($C$27:$C$32,$P58)*D58*C58/1000 -> 3.574536 | I58: =I$25/INDEX($C$27:$C$32,$P58)*D58*C58/1000 -> 3.574536 | J58: =J$25/INDEX($C$27:$C$32,$P58)*D58*C58/1000 -> 3.574536 | K58: =K$25/INDEX($C$27:$C$32,$P58)*D58*C58/1000 -> 3.574536 | L58: =L$25/INDEX($C$27:$C$32,$P58)*D58*C58/1000 -> 3.574536 | M58: =M$25/INDEX($C$27:$C$32,$P58)*D58*C58/1000 -> 3.574536 | N58: =N$25/INDEX($C$27:$C$32,$P58)*D58*C58/1000 -> 3.574536 | P58: 1
B59: Влагоотделитель | C59: 14.612 | D59: 2 | E59: =E$25/INDEX($C$27:$C$32,$P59)*D59*C59/1000 -> 0.818272 | F59: =F$25/INDEX($C$27:$C$32,$P59)*D59*C59/1000 -> 0.818272 | G59: =G$25/INDEX($C$27:$C$32,$P59)*D59*C59/1000 -> 0.818272 | H59: =H$25/INDEX($C$27:$C$32,$P59)*D59*C59/1000 -> 0.818272 | I59: =I$25/INDEX($C$27:$C$32,$P59)*D59*C59/1000 -> 0.818272 | J59: =J$25/INDEX($C$27:$C$32,$P59)*D59*C59/1000 -> 0.818272 | K59: =K$25/INDEX($C$27:$C$32,$P59)*D59*C59/1000 -> 0.818272 | L59: =L$25/INDEX($C$27:$C$32,$P59)*D59*C59/1000 -> 0.818272 | M59: =M$25/INDEX($C$27:$C$32,$P59)*D59*C59/1000 -> 0.818272 | N59: =N$25/INDEX($C$27:$C$32,$P59)*D59*C59/1000 -> 0.818272 | P59: 1
B60: Консистентная смазка | C60: 10.752 | D60: 2 | E60: =E$25/INDEX($C$27:$C$32,$P60)*D60*C60/1000 -> 0.602112 | F60: =F$25/INDEX($C$27:$C$32,$P60)*D60*C60/1000 -> 0.602112 | G60: =G$25/INDEX($C$27:$C$32,$P60)*D60*C60/1000 -> 0.602112 | H60: =H$25/INDEX($C$27:$C$32,$P60)*D60*C60/1000 -> 0.602112 | I60: =I$25/INDEX($C$27:$C$32,$P60)*D60*C60/1000 -> 0.602112 | J60: =J$25/INDEX($C$27:$C$32,$P60)*D60*C60/1000 -> 0.602112 | K60: =K$25/INDEX($C$27:$C$32,$P60)*D60*C60/1000 -> 0.602112 | L60: =L$25/INDEX($C$27:$C$32,$P60)*D60*C60/1000 -> 0.602112 | M60: =M$25/INDEX($C$27:$C$32,$P60)*D60*C60/1000 -> 0.602112 | N60: =N$25/INDEX($C$27:$C$32,$P60)*D60*C60/1000 -> 0.602112 | P60: 1
B61: Сапун гидробака | C61: 18.025 | D61: 2 | E61: =E$25/INDEX($C$27:$C$32,$P61)*D61*C61/1000 -> 0.5047 | F61: =F$25/INDEX($C$27:$C$32,$P61)*D61*C61/1000 -> 0.5047 | G61: =G$25/INDEX($C$27:$C$32,$P61)*D61*C61/1000 -> 0.5047 | H61: =H$25/INDEX($C$27:$C$32,$P61)*D61*C61/1000 -> 0.5047 | I61: =I$25/INDEX($C$27:$C$32,$P61)*D61*C61/1000 -> 0.5047 | J61: =J$25/INDEX($C$27:$C$32,$P61)*D61*C61/1000 -> 0.5047 | K61: =K$25/INDEX($C$27:$C$32,$P61)*D61*C61/1000 -> 0.5047 | L61: =L$25/INDEX($C$27:$C$32,$P61)*D61*C61/1000 -> 0.5047 | M61: =M$25/INDEX($C$27:$C$32,$P61)*D61*C61/1000 -> 0.5047 | N61: =N$25/INDEX($C$27:$C$32,$P61)*D61*C61/1000 -> 0.5047 | P61: 2
B62: Фильтра системы пылеподавления | C62: 58.9 | D62: 9 | E62: =E$25/INDEX($C$27:$C$32,$P62)*D62*C62/1000 -> 7.4214 | F62: =F$25/INDEX($C$27:$C$32,$P62)*D62*C62/1000 -> 7.4214 | G62: =G$25/INDEX($C$27:$C$32,$P62)*D62*C62/1000 -> 7.4214 | H62: =H$25/INDEX($C$27:$C$32,$P62)*D62*C62/1000 -> 7.4214 | I62: =I$25/INDEX($C$27:$C$32,$P62)*D62*C62/1000 -> 7.4214 | J62: =J$25/INDEX($C$27:$C$32,$P62)*D62*C62/1000 -> 7.4214 | K62: =K$25/INDEX($C$27:$C$32,$P62)*D62*C62/1000 -> 7.4214 | L62: =L$25/INDEX($C$27:$C$32,$P62)*D62*C62/1000 -> 7.4214 | M62: =M$25/INDEX($C$27:$C$32,$P62)*D62*C62/1000 -> 7.4214 | N62: =N$25/INDEX($C$27:$C$32,$P62)*D62*C62/1000 -> 7.4214 | P62: 2
... B83: Охлаждающая жидкость | C83: 3.122 | D83: 190 | E83: =E$25/INDEX($C$27:$C$32,$P83)*D83*C83/1000 -> 0.830452 | F83: =F$25/INDEX($C$27:$C$32,$P83)*D83*C83/1000 -> 0.830452 | G83: =G$25/INDEX($C$27:$C$32,$P83)*D83*C83/1000 -> 0.830452 | H83: =H$25/INDEX($C$27:$C$32,$P83)*D83*C83/1000 -> 0.830452 | I83: =I$25/INDEX($C$27:$C$32,$P83)*D83*C83/1000 -> 0.830452 | J83: =J$25/INDEX($C$27:$C$32,$P83)*D83*C83/1000 -> 0.830452 | K83: =K$25/INDEX($C$27:$C$32,$P83)*D83*C83/1000 -> 0.830452 | L83: =L$25/INDEX($C$27:$C$32,$P83)*D83*C83/1000 -> 0.830452 | M83: =M$25/INDEX($C$27:$C$32,$P83)*D83*C83/1000 -> 0.830452 | N83: =N$25/INDEX($C$27:$C$32,$P83)*D83*C83/1000 -> 0.830452 | P83: 6
B84: Корректировка (прочее) | E84: 0 | F84: 0 | G84: 0 | H84: 0 | I84: 0 | J84: 0 | K84: 0 | L84: 0 | M84: 0 | N84: 0
B85: ИТОГО ЗЧ ТО, тыс.вал/год | E85: =SUM(E51:E84) -> 136.07379 | F85: =SUM(F51:F84) -> 136.07379 | G85: =SUM(G51:G84) -> 136.07379 | H85: =SUM(H51:H84) -> 136.07379 | I85: =SUM(I51:I84) -> 136.07379 | J85: =SUM(J51:J84) -> 136.07379 | K85: =SUM(K51:K84) -> 136.07379 | L85: =SUM(L51:L84) -> 136.07379 | ... N85: =SUM(N51:N84) -> 136.07379
B87: ТЕКУЩИЕ РЕМОНТЫ — ЗАТРАТЫ НА ЗЧ (по ресурсу)
B88: Наименование | C88: стоим.замены,вал | D88: ресурс, м/ч | E88: год 1 | F88: год 2 | G88: год 3 | H88: год 4 | I88: год 5 | J88: год 6 | K88: год 7 | L88: год 8 | M88: год 9 | N88: год 10
B89: ENG (двигатель капремонт) | C89: 98848.48 | D89: 15000 | E89: =(INT($E$25*1/$D89)-INT($E$25*(1-1)/$D89))*$C89/1000 -> 0 | F89: =(INT($E$25*2/$D89)-INT($E$25*(2-1)/$D89))*$C89/1000 -> 0 | G89: =(INT($E$25*3/$D89)-INT($E$25*(3-1)/$D89))*$C89/1000 -> 98.84848 | H89: =(INT($E$25*4/$D89)-INT($E$25*(4-1)/$D89))*$C89/1000 -> 0 | I89: =(INT($E$25*5/$D89)-INT($E$25*(5-1)/$D89))*$C89/1000 -> 98.84848 | J89: =(INT($E$25*6/$D89)-INT($E$25*(6-1)/$D89))*$C89/1000 -> 0 | K89: =(INT($E$25*7/$D89)-INT($E$25*(7-1)/$D89))*$C89/1000 -> 98.84848 | L89: =(INT($E$25*8/$D89)-INT($E$25*(8-1)/$D89))*$C89/1000 -> 0 | M89: =(INT($E$25*9/$D89)-INT($E$25*(9-1)/$D89))*$C89/1000 -> 98.84848 | N89: =(INT($E$25*10/$D89)-INT($E$25*(10-1)/$D89))*$C89/1000 -> 0
B90: AIREND Seal LP (Компрессор ремкомплект | C90: 32894 | D90: 16000 | E90: =(INT($E$25*1/$D90)-INT($E$25*(1-1)/$D90))*$C90/1000 -> 0 | F90: =(INT($E$25*2/$D90)-INT($E$25*(2-1)/$D90))*$C90/1000 -> 0 | G90: =(INT($E$25*3/$D90)-INT($E$25*(3-1)/$D90))*$C90/1000 -> 32.894 | H90: =(INT($E$25*4/$D90)-INT($E$25*(4-1)/$D90))*$C90/1000 -> 0 | I90: =(INT($E$25*5/$D90)-INT($E$25*(5-1)/$D90))*$C90/1000 -> 32.894 | J90: =(INT($E$25*6/$D90)-INT($E$25*(6-1)/$D90))*$C90/1000 -> 0 | K90: =(INT($E$25*7/$D90)-INT($E$25*(7-1)/$D90))*$C90/1000 -> 32.894 | L90: =(INT($E$25*8/$D90)-INT($E$25*(8-1)/$D90))*$C90/1000 -> 0 | M90: =(INT($E$25*9/$D90)-INT($E$25*(9-1)/$D90))*$C90/1000 -> 0 | N90: =(INT($E$25*10/$D90)-INT($E$25*(10-1)/$D90))*$C90/1000 -> 32.894
B91: ROTARYHEAD (Ремкомплект вращателя | C91: 46638 | D91: 13000 | E91: =(INT($E$25*1/$D91)-INT($E$25*(1-1)/$D91))*$C91/1000 -> 0 | F91: =(INT($E$25*2/$D91)-INT($E$25*(2-1)/$D91))*$C91/1000 -> 46.638 | G91: =(INT($E$25*3/$D91)-INT($E$25*(3-1)/$D91))*$C91/1000 -> 0 | H91: =(INT($E$25*4/$D91)-INT($E$25*(4-1)/$D91))*$C91/1000 -> 46.638 | I91: =(INT($E$25*5/$D91)-INT($E$25*(5-1)/$D91))*$C91/1000 -> 0 | J91: =(INT($E$25*6/$D91)-INT($E$25*(6-1)/$D91))*$C91/1000 -> 46.638 | K91: =(INT($E$25*7/$D91)-INT($E$25*(7-1)/$D91))*$C91/1000 -> 0 | L91: =(INT($E$25*8/$D91)-INT($E$25*(8-1)/$D91))*$C91/1000 -> 46.638 | M91: =(INT($E$25*9/$D91)-INT($E$25*(9-1)/$D91))*$C91/1000 -> 0 | N91: =(INT($E$25*10/$D91)-INT($E$25*(10-1)/$D91))*$C91/1000 -> 46.638
B92: KIT, SEAL (ремкомплект к цилиндру пода | C92: 4240.92 | D92: 7450 | E92: =(INT($E$25*1/$D92)-INT($E$25*(1-1)/$D92))*$C92/1000 -> 0 | F92: =(INT($E$25*2/$D92)-INT($E$25*(2-1)/$D92))*$C92/1000 -> 4.24092 | G92: =(INT($E$25*3/$D92)-INT($E$25*(3-1)/$D92))*$C92/1000 -> 4.24092 | H92: =(INT($E$25*4/$D92)-INT($E$25*(4-1)/$D92))*$C92/1000 -> 4.24092 | I92: =(INT($E$25*5/$D92)-INT($E$25*(5-1)/$D92))*$C92/1000 -> 4.24092 | J92: =(INT($E$25*6/$D92)-INT($E$25*(6-1)/$D92))*$C92/1000 -> 4.24092 | K92: =(INT($E$25*7/$D92)-INT($E$25*(7-1)/$D92))*$C92/1000 -> 4.24092 | L92: =(INT($E$25*8/$D92)-INT($E$25*(8-1)/$D92))*$C92/1000 -> 4.24092 | M92: =(INT($E$25*9/$D92)-INT($E$25*(9-1)/$D92))*$C92/1000 -> 4.24092 | N92: =(INT($E$25*10/$D92)-INT($E$25*(10-1)/$D92))*$C92/1000 -> 4.24092
B93: SEAL KIT,CYLINDER (ремкомплект к цил.д | C93: 4242.92 | D93: 7450 | E93: =(INT($E$25*1/$D93)-INT($E$25*(1-1)/$D93))*$C93/1000 -> 0 | F93: =(INT($E$25*2/$D93)-INT($E$25*(2-1)/$D93))*$C93/1000 -> 4.24292 | G93: =(INT($E$25*3/$D93)-INT($E$25*(3-1)/$D93))*$C93/1000 -> 4.24292 | H93: =(INT($E$25*4/$D93)-INT($E$25*(4-1)/$D93))*$C93/1000 -> 4.24292 | I93: =(INT($E$25*5/$D93)-INT($E$25*(5-1)/$D93))*$C93/1000 -> 4.24292 | J93: =(INT($E$25*6/$D93)-INT($E$25*(6-1)/$D93))*$C93/1000 -> 4.24292 | K93: =(INT($E$25*7/$D93)-INT($E$25*(7-1)/$D93))*$C93/1000 -> 4.24292 | L93: =(INT($E$25*8/$D93)-INT($E$25*(8-1)/$D93))*$C93/1000 -> 4.24292 | M93: =(INT($E$25*9/$D93)-INT($E$25*(9-1)/$D93))*$C93/1000 -> 4.24292 | N93: =(INT($E$25*10/$D93)-INT($E$25*(10-1)/$D93))*$C93/1000 -> 4.24292
B94: KIT, SEAL (ремкомплект к цилиндру п. м | C94: 3464.48 | D94: 6000 | E94: =(INT($E$25*1/$D94)-INT($E$25*(1-1)/$D94))*$C94/1000 -> 3.46448 | F94: =(INT($E$25*2/$D94)-INT($E$25*(2-1)/$D94))*$C94/1000 -> 3.46448 | G94: =(INT($E$25*3/$D94)-INT($E$25*(3-1)/$D94))*$C94/1000 -> 3.46448 | H94: =(INT($E$25*4/$D94)-INT($E$25*(4-1)/$D94))*$C94/1000 -> 3.46448 | I94: =(INT($E$25*5/$D94)-INT($E$25*(5-1)/$D94))*$C94/1000 -> 3.46448 | J94: =(INT($E$25*6/$D94)-INT($E$25*(6-1)/$D94))*$C94/1000 -> 6.92896 | K94: =(INT($E$25*7/$D94)-INT($E$25*(7-1)/$D94))*$C94/1000 -> 3.46448 | L94: =(INT($E$25*8/$D94)-INT($E$25*(8-1)/$D94))*$C94/1000 -> 3.46448 | M94: =(INT($E$25*9/$D94)-INT($E$25*(9-1)/$D94))*$C94/1000 -> 3.46448 | N94: =(INT($E$25*10/$D94)-INT($E$25*(10-1)/$D94))*$C94/1000 -> 3.46448
B95: SEAL KIT (ремкомплектгидроцилиндр мех. | C95: 237.18 | D95: 6000 | E95: =(INT($E$25*1/$D95)-INT($E$25*(1-1)/$D95))*$C95/1000 -> 0.23718 | F95: =(INT($E$25*2/$D95)-INT($E$25*(2-1)/$D95))*$C95/1000 -> 0.23718 | G95: =(INT($E$25*3/$D95)-INT($E$25*(3-1)/$D95))*$C95/1000 -> 0.23718 | H95: =(INT($E$25*4/$D95)-INT($E$25*(4-1)/$D95))*$C95/1000 -> 0.23718 | I95: =(INT($E$25*5/$D95)-INT($E$25*(5-1)/$D95))*$C95/1000 -> 0.23718 | J95: =(INT($E$25*6/$D95)-INT($E$25*(6-1)/$D95))*$C95/1000 -> 0.47436 | K95: =(INT($E$25*7/$D95)-INT($E$25*(7-1)/$D95))*$C95/1000 -> 0.23718 | L95: =(INT($E$25*8/$D95)-INT($E$25*(8-1)/$D95))*$C95/1000 -> 0.23718 | M95: =(INT($E$25*9/$D95)-INT($E$25*(9-1)/$D95))*$C95/1000 -> 0.23718 | N95: =(INT($E$25*10/$D95)-INT($E$25*(10-1)/$D95))*$C95/1000 -> 0.23718
B96: KIT,SEAL (ремкомплект цилиндра ключа) | C96: 102.66 | D96: 4000 | E96: =(INT($E$25*1/$D96)-INT($E$25*(1-1)/$D96))*$C96/1000 -> 0.10266 | F96: =(INT($E$25*2/$D96)-INT($E$25*(2-1)/$D96))*$C96/1000 -> 0.20532 | G96: =(INT($E$25*3/$D96)-INT($E$25*(3-1)/$D96))*$C96/1000 -> 0.20532 | H96: =(INT($E$25*4/$D96)-INT($E$25*(4-1)/$D96))*$C96/1000 -> 0.20532 | I96: =(INT($E$25*5/$D96)-INT($E$25*(5-1)/$D96))*$C96/1000 -> 0.10266 | J96: =(INT($E$25*6/$D96)-INT($E$25*(6-1)/$D96))*$C96/1000 -> 0.20532 | K96: =(INT($E$25*7/$D96)-INT($E$25*(7-1)/$D96))*$C96/1000 -> 0.20532 | L96: =(INT($E$25*8/$D96)-INT($E$25*(8-1)/$D96))*$C96/1000 -> 0.20532 | M96: =(INT($E$25*9/$D96)-INT($E$25*(9-1)/$D96))*$C96/1000 -> 0.10266 | N96: =(INT($E$25*10/$D96)-INT($E$25*(10-1)/$D96))*$C96/1000 -> 0.20532
B97: SEAL KIT (ремкомплект цилиндра мех.зам | C97: 110.66 | D97: 4000 | E97: =(INT($E$25*1/$D97)-INT($E$25*(1-1)/$D97))*$C97/1000 -> 0.11066 | F97: =(INT($E$25*2/$D97)-INT($E$25*(2-1)/$D97))*$C97/1000 -> 0.22132 | G97: =(INT($E$25*3/$D97)-INT($E$25*(3-1)/$D97))*$C97/1000 -> 0.22132 | H97: =(INT($E$25*4/$D97)-INT($E$25*(4-1)/$D97))*$C97/1000 -> 0.22132 | I97: =(INT($E$25*5/$D97)-INT($E$25*(5-1)/$D97))*$C97/1000 -> 0.11066 | J97: =(INT($E$25*6/$D97)-INT($E$25*(6-1)/$D97))*$C97/1000 -> 0.22132 | K97: =(INT($E$25*7/$D97)-INT($E$25*(7-1)/$D97))*$C97/1000 -> 0.22132 | L97: =(INT($E$25*8/$D97)-INT($E$25*(8-1)/$D97))*$C97/1000 -> 0.22132 | M97: =(INT($E$25*9/$D97)-INT($E$25*(9-1)/$D97))*$C97/1000 -> 0.11066 | N97: =(INT($E$25*10/$D97)-INT($E$25*(10-1)/$D97))*$C97/1000 -> 0.22132
B98: SEAL KIT (ремкомплект к гидроцил.стопо | C98: 92.04 | D98: 5000 | E98: =(INT($E$25*1/$D98)-INT($E$25*(1-1)/$D98))*$C98/1000 -> 0.09204 | F98: =(INT($E$25*2/$D98)-INT($E$25*(2-1)/$D98))*$C98/1000 -> 0.09204 | G98: =(INT($E$25*3/$D98)-INT($E$25*(3-1)/$D98))*$C98/1000 -> 0.18408 | H98: =(INT($E$25*4/$D98)-INT($E$25*(4-1)/$D98))*$C98/1000 -> 0.09204 | I98: =(INT($E$25*5/$D98)-INT($E$25*(5-1)/$D98))*$C98/1000 -> 0.18408 | J98: =(INT($E$25*6/$D98)-INT($E$25*(6-1)/$D98))*$C98/1000 -> 0.09204 | K98: =(INT($E$25*7/$D98)-INT($E$25*(7-1)/$D98))*$C98/1000 -> 0.09204 | L98: =(INT($E$25*8/$D98)-INT($E$25*(8-1)/$D98))*$C98/1000 -> 0.18408 | M98: =(INT($E$25*9/$D98)-INT($E$25*(9-1)/$D98))*$C98/1000 -> 0.09204 | N98: =(INT($E$25*10/$D98)-INT($E$25*(10-1)/$D98))*$C98/1000 -> 0.18408
B99: SEAL KIT (ремкомплект гидроцил.фартука | C99: 123.9 | D99: 4000 | E99: =(INT($E$25*1/$D99)-INT($E$25*(1-1)/$D99))*$C99/1000 -> 0.1239 | F99: =(INT($E$25*2/$D99)-INT($E$25*(2-1)/$D99))*$C99/1000 -> 0.2478 | G99: =(INT($E$25*3/$D99)-INT($E$25*(3-1)/$D99))*$C99/1000 -> 0.2478 | H99: =(INT($E$25*4/$D99)-INT($E$25*(4-1)/$D99))*$C99/1000 -> 0.2478 | I99: =(INT($E$25*5/$D99)-INT($E$25*(5-1)/$D99))*$C99/1000 -> 0.1239 | J99: =(INT($E$25*6/$D99)-INT($E$25*(6-1)/$D99))*$C99/1000 -> 0.2478 | K99: =(INT($E$25*7/$D99)-INT($E$25*(7-1)/$D99))*$C99/1000 -> 0.2478 | L99: =(INT($E$25*8/$D99)-INT($E$25*(8-1)/$D99))*$C99/1000 -> 0.2478 | M99: =(INT($E$25*9/$D99)-INT($E$25*(9-1)/$D99))*$C99/1000 -> 0.1239 | N99: =(INT($E$25*10/$D99)-INT($E$25*(10-1)/$D99))*$C99/1000 -> 0.2478
B100: Ремонт системы смазки | C100: 143.96 | D100: 12000 | E100: =(INT($E$25*1/$D100)-INT($E$25*(1-1)/$D100))*$C100/1000 -> 0 | F100: =(INT($E$25*2/$D100)-INT($E$25*(2-1)/$D100))*$C100/1000 -> 0.14396 | G100: =(INT($E$25*3/$D100)-INT($E$25*(3-1)/$D100))*$C100/1000 -> 0 | H100: =(INT($E$25*4/$D100)-INT($E$25*(4-1)/$D100))*$C100/1000 -> 0.14396 | I100: =(INT($E$25*5/$D100)-INT($E$25*(5-1)/$D100))*$C100/1000 -> 0 | J100: =(INT($E$25*6/$D100)-INT($E$25*(6-1)/$D100))*$C100/1000 -> 0.14396 | K100: =(INT($E$25*7/$D100)-INT($E$25*(7-1)/$D100))*$C100/1000 -> 0.14396 | L100: =(INT($E$25*8/$D100)-INT($E$25*(8-1)/$D100))*$C100/1000 -> 0 | M100: =(INT($E$25*9/$D100)-INT($E$25*(9-1)/$D100))*$C100/1000 -> 0.14396 | N100: =(INT($E$25*10/$D100)-INT($E$25*(10-1)/$D100))*$C100/1000 -> 0
... B104: Инспекция металлоконструкций | C104: 12637.39 | D104: 65000 | E104: =(INT($E$25*1/$D104)-INT($E$25*(1-1)/$D104))*$C104/1000 -> 0 | F104: =(INT($E$25*2/$D104)-INT($E$25*(2-1)/$D104))*$C104/1000 -> 0 | G104: =(INT($E$25*3/$D104)-INT($E$25*(3-1)/$D104))*$C104/1000 -> 0 | H104: =(INT($E$25*4/$D104)-INT($E$25*(4-1)/$D104))*$C104/1000 -> 0 | I104: =(INT($E$25*5/$D104)-INT($E$25*(5-1)/$D104))*$C104/1000 -> 0 | J104: =(INT($E$25*6/$D104)-INT($E$25*(6-1)/$D104))*$C104/1000 -> 0 | K104: =(INT($E$25*7/$D104)-INT($E$25*(7-1)/$D104))*$C104/1000 -> 0 | L104: =(INT($E$25*8/$D104)-INT($E$25*(8-1)/$D104))*$C104/1000 -> 0 | M104: =(INT($E$25*9/$D104)-INT($E$25*(9-1)/$D104))*$C104/1000 -> 0 | N104: =(INT($E$25*10/$D104)-INT($E$25*(10-1)/$D104))*$C104/1000 -> 12.63739
B105: ИТОГО | E105: =SUM(E89:E104) -> 4.50682 | F105: =SUM(F89:F104) -> 60.10984 | G105: =SUM(G89:G104) -> 145.1624 | H105: =SUM(H89:H104) -> 60.10984 | I105: =SUM(I89:I104) -> 144.82518 | J105: =SUM(J89:J104) -> 67.22701 | K105: =SUM(K89:K104) -> 145.21432 | L105: =SUM(L89:L104) -> 60.05792 | ... N105: =SUM(N89:N104) -> 105.58931
B107: ТЕКУЩИЕ РЕМОНТЫ — ТРУДОЗАТРАТЫ (по ресурсу)
B108: Наименование | C108: нормо-час/событие | D108: ресурс, м/ч | E108: год 1 | F108: год 2 | G108: год 3 | H108: год 4 | I108: год 5 | J108: год 6 | K108: год 7 | L108: год 8 | M108: год 9 | N108: год 10
B109: ENG (двигатель капремонт) | C109: 56 | D109: 15000 | E109: =(INT($E$25*1/$D109)-INT($E$25*(1-1)/$D109))*$C109 -> 0 | F109: =(INT($E$25*2/$D109)-INT($E$25*(2-1)/$D109))*$C109 -> 0 | G109: =(INT($E$25*3/$D109)-INT($E$25*(3-1)/$D109))*$C109 -> 56 | H109: =(INT($E$25*4/$D109)-INT($E$25*(4-1)/$D109))*$C109 -> 0 | I109: =(INT($E$25*5/$D109)-INT($E$25*(5-1)/$D109))*$C109 -> 56 | J109: =(INT($E$25*6/$D109)-INT($E$25*(6-1)/$D109))*$C109 -> 0 | K109: =(INT($E$25*7/$D109)-INT($E$25*(7-1)/$D109))*$C109 -> 56 | L109: =(INT($E$25*8/$D109)-INT($E$25*(8-1)/$D109))*$C109 -> 0 | M109: =(INT($E$25*9/$D109)-INT($E$25*(9-1)/$D109))*$C109 -> 56 | N109: =(INT($E$25*10/$D109)-INT($E$25*(10-1)/$D109))*$C109 -> 0
B110: AIREND Seal LP (Компрессор ремкомплект | C110: 4 | D110: 16000 | E110: =(INT($E$25*1/$D110)-INT($E$25*(1-1)/$D110))*$C110 -> 0 | F110: =(INT($E$25*2/$D110)-INT($E$25*(2-1)/$D110))*$C110 -> 0 | G110: =(INT($E$25*3/$D110)-INT($E$25*(3-1)/$D110))*$C110 -> 4 | H110: =(INT($E$25*4/$D110)-INT($E$25*(4-1)/$D110))*$C110 -> 0 | I110: =(INT($E$25*5/$D110)-INT($E$25*(5-1)/$D110))*$C110 -> 4 | J110: =(INT($E$25*6/$D110)-INT($E$25*(6-1)/$D110))*$C110 -> 0 | K110: =(INT($E$25*7/$D110)-INT($E$25*(7-1)/$D110))*$C110 -> 4 | L110: =(INT($E$25*8/$D110)-INT($E$25*(8-1)/$D110))*$C110 -> 0 | M110: =(INT($E$25*9/$D110)-INT($E$25*(9-1)/$D110))*$C110 -> 0 | N110: =(INT($E$25*10/$D110)-INT($E$25*(10-1)/$D110))*$C110 -> 4
B111: ROTARYHEAD (Ремкомплект вращателя | C111: 8 | D111: 13000 | E111: =(INT($E$25*1/$D111)-INT($E$25*(1-1)/$D111))*$C111 -> 0 | F111: =(INT($E$25*2/$D111)-INT($E$25*(2-1)/$D111))*$C111 -> 8 | G111: =(INT($E$25*3/$D111)-INT($E$25*(3-1)/$D111))*$C111 -> 0 | H111: =(INT($E$25*4/$D111)-INT($E$25*(4-1)/$D111))*$C111 -> 8 | I111: =(INT($E$25*5/$D111)-INT($E$25*(5-1)/$D111))*$C111 -> 0 | J111: =(INT($E$25*6/$D111)-INT($E$25*(6-1)/$D111))*$C111 -> 8 | K111: =(INT($E$25*7/$D111)-INT($E$25*(7-1)/$D111))*$C111 -> 0 | L111: =(INT($E$25*8/$D111)-INT($E$25*(8-1)/$D111))*$C111 -> 8 | M111: =(INT($E$25*9/$D111)-INT($E$25*(9-1)/$D111))*$C111 -> 0 | N111: =(INT($E$25*10/$D111)-INT($E$25*(10-1)/$D111))*$C111 -> 8
B112: KIT, SEAL (ремкомплект к цилиндру пода | C112: 36 | D112: 7450 | E112: =(INT($E$25*1/$D112)-INT($E$25*(1-1)/$D112))*$C112 -> 0 | F112: =(INT($E$25*2/$D112)-INT($E$25*(2-1)/$D112))*$C112 -> 36 | G112: =(INT($E$25*3/$D112)-INT($E$25*(3-1)/$D112))*$C112 -> 36 | H112: =(INT($E$25*4/$D112)-INT($E$25*(4-1)/$D112))*$C112 -> 36 | I112: =(INT($E$25*5/$D112)-INT($E$25*(5-1)/$D112))*$C112 -> 36 | J112: =(INT($E$25*6/$D112)-INT($E$25*(6-1)/$D112))*$C112 -> 36 | K112: =(INT($E$25*7/$D112)-INT($E$25*(7-1)/$D112))*$C112 -> 36 | L112: =(INT($E$25*8/$D112)-INT($E$25*(8-1)/$D112))*$C112 -> 36 | M112: =(INT($E$25*9/$D112)-INT($E$25*(9-1)/$D112))*$C112 -> 36 | N112: =(INT($E$25*10/$D112)-INT($E$25*(10-1)/$D112))*$C112 -> 36
B113: SEAL KIT,CYLINDER (ремкомплект к цил.д | C113: 72 | D113: 7450 | E113: =(INT($E$25*1/$D113)-INT($E$25*(1-1)/$D113))*$C113 -> 0 | F113: =(INT($E$25*2/$D113)-INT($E$25*(2-1)/$D113))*$C113 -> 72 | G113: =(INT($E$25*3/$D113)-INT($E$25*(3-1)/$D113))*$C113 -> 72 | H113: =(INT($E$25*4/$D113)-INT($E$25*(4-1)/$D113))*$C113 -> 72 | I113: =(INT($E$25*5/$D113)-INT($E$25*(5-1)/$D113))*$C113 -> 72 | J113: =(INT($E$25*6/$D113)-INT($E$25*(6-1)/$D113))*$C113 -> 72 | K113: =(INT($E$25*7/$D113)-INT($E$25*(7-1)/$D113))*$C113 -> 72 | L113: =(INT($E$25*8/$D113)-INT($E$25*(8-1)/$D113))*$C113 -> 72 | M113: =(INT($E$25*9/$D113)-INT($E$25*(9-1)/$D113))*$C113 -> 72 | N113: =(INT($E$25*10/$D113)-INT($E$25*(10-1)/$D113))*$C113 -> 72
B114: KIT, SEAL (ремкомплект к цилиндру п. м | C114: 28 | D114: 6000 | E114: =(INT($E$25*1/$D114)-INT($E$25*(1-1)/$D114))*$C114 -> 28 | F114: =(INT($E$25*2/$D114)-INT($E$25*(2-1)/$D114))*$C114 -> 28 | G114: =(INT($E$25*3/$D114)-INT($E$25*(3-1)/$D114))*$C114 -> 28 | H114: =(INT($E$25*4/$D114)-INT($E$25*(4-1)/$D114))*$C114 -> 28 | I114: =(INT($E$25*5/$D114)-INT($E$25*(5-1)/$D114))*$C114 -> 28 | J114: =(INT($E$25*6/$D114)-INT($E$25*(6-1)/$D114))*$C114 -> 56 | K114: =(INT($E$25*7/$D114)-INT($E$25*(7-1)/$D114))*$C114 -> 28 | L114: =(INT($E$25*8/$D114)-INT($E$25*(8-1)/$D114))*$C114 -> 28 | M114: =(INT($E$25*9/$D114)-INT($E$25*(9-1)/$D114))*$C114 -> 28 | N114: =(INT($E$25*10/$D114)-INT($E$25*(10-1)/$D114))*$C114 -> 28
B115: SEAL KIT (ремкомплектгидроцилиндр мех. | C115: 3.5 | D115: 6000 | E115: =(INT($E$25*1/$D115)-INT($E$25*(1-1)/$D115))*$C115 -> 3.5 | F115: =(INT($E$25*2/$D115)-INT($E$25*(2-1)/$D115))*$C115 -> 3.5 | G115: =(INT($E$25*3/$D115)-INT($E$25*(3-1)/$D115))*$C115 -> 3.5 | H115: =(INT($E$25*4/$D115)-INT($E$25*(4-1)/$D115))*$C115 -> 3.5 | I115: =(INT($E$25*5/$D115)-INT($E$25*(5-1)/$D115))*$C115 -> 3.5 | J115: =(INT($E$25*6/$D115)-INT($E$25*(6-1)/$D115))*$C115 -> 7 | K115: =(INT($E$25*7/$D115)-INT($E$25*(7-1)/$D115))*$C115 -> 3.5 | L115: =(INT($E$25*8/$D115)-INT($E$25*(8-1)/$D115))*$C115 -> 3.5 | M115: =(INT($E$25*9/$D115)-INT($E$25*(9-1)/$D115))*$C115 -> 3.5 | N115: =(INT($E$25*10/$D115)-INT($E$25*(10-1)/$D115))*$C115 -> 3.5
B116: KIT,SEAL (ремкомплект цилиндра ключа) | C116: 3.5 | D116: 4000 | E116: =(INT($E$25*1/$D116)-INT($E$25*(1-1)/$D116))*$C116 -> 3.5 | F116: =(INT($E$25*2/$D116)-INT($E$25*(2-1)/$D116))*$C116 -> 7 | G116: =(INT($E$25*3/$D116)-INT($E$25*(3-1)/$D116))*$C116 -> 7 | H116: =(INT($E$25*4/$D116)-INT($E$25*(4-1)/$D116))*$C116 -> 7 | I116: =(INT($E$25*5/$D116)-INT($E$25*(5-1)/$D116))*$C116 -> 3.5 | J116: =(INT($E$25*6/$D116)-INT($E$25*(6-1)/$D116))*$C116 -> 7 | K116: =(INT($E$25*7/$D116)-INT($E$25*(7-1)/$D116))*$C116 -> 7 | L116: =(INT($E$25*8/$D116)-INT($E$25*(8-1)/$D116))*$C116 -> 7 | M116: =(INT($E$25*9/$D116)-INT($E$25*(9-1)/$D116))*$C116 -> 3.5 | N116: =(INT($E$25*10/$D116)-INT($E$25*(10-1)/$D116))*$C116 -> 7
B117: SEAL KIT (ремкомплект цилиндра мех.зам | C117: 3.5 | D117: 4000 | E117: =(INT($E$25*1/$D117)-INT($E$25*(1-1)/$D117))*$C117 -> 3.5 | F117: =(INT($E$25*2/$D117)-INT($E$25*(2-1)/$D117))*$C117 -> 7 | G117: =(INT($E$25*3/$D117)-INT($E$25*(3-1)/$D117))*$C117 -> 7 | H117: =(INT($E$25*4/$D117)-INT($E$25*(4-1)/$D117))*$C117 -> 7 | I117: =(INT($E$25*5/$D117)-INT($E$25*(5-1)/$D117))*$C117 -> 3.5 | J117: =(INT($E$25*6/$D117)-INT($E$25*(6-1)/$D117))*$C117 -> 7 | K117: =(INT($E$25*7/$D117)-INT($E$25*(7-1)/$D117))*$C117 -> 7 | L117: =(INT($E$25*8/$D117)-INT($E$25*(8-1)/$D117))*$C117 -> 7 | M117: =(INT($E$25*9/$D117)-INT($E$25*(9-1)/$D117))*$C117 -> 3.5 | N117: =(INT($E$25*10/$D117)-INT($E$25*(10-1)/$D117))*$C117 -> 7
B118: SEAL KIT (ремкомплект к гидроцил.стопо | C118: 4 | D118: 5000 | E118: =(INT($E$25*1/$D118)-INT($E$25*(1-1)/$D118))*$C118 -> 4 | F118: =(INT($E$25*2/$D118)-INT($E$25*(2-1)/$D118))*$C118 -> 4 | G118: =(INT($E$25*3/$D118)-INT($E$25*(3-1)/$D118))*$C118 -> 8 | H118: =(INT($E$25*4/$D118)-INT($E$25*(4-1)/$D118))*$C118 -> 4 | I118: =(INT($E$25*5/$D118)-INT($E$25*(5-1)/$D118))*$C118 -> 8 | J118: =(INT($E$25*6/$D118)-INT($E$25*(6-1)/$D118))*$C118 -> 4 | K118: =(INT($E$25*7/$D118)-INT($E$25*(7-1)/$D118))*$C118 -> 4 | L118: =(INT($E$25*8/$D118)-INT($E$25*(8-1)/$D118))*$C118 -> 8 | M118: =(INT($E$25*9/$D118)-INT($E$25*(9-1)/$D118))*$C118 -> 4 | N118: =(INT($E$25*10/$D118)-INT($E$25*(10-1)/$D118))*$C118 -> 8
B119: SEAL KIT (ремкомплект гидроцил.фартука | C119: 0.9 | D119: 4000 | E119: =(INT($E$25*1/$D119)-INT($E$25*(1-1)/$D119))*$C119 -> 0.9 | F119: =(INT($E$25*2/$D119)-INT($E$25*(2-1)/$D119))*$C119 -> 1.8 | G119: =(INT($E$25*3/$D119)-INT($E$25*(3-1)/$D119))*$C119 -> 1.8 | H119: =(INT($E$25*4/$D119)-INT($E$25*(4-1)/$D119))*$C119 -> 1.8 | I119: =(INT($E$25*5/$D119)-INT($E$25*(5-1)/$D119))*$C119 -> 0.9 | J119: =(INT($E$25*6/$D119)-INT($E$25*(6-1)/$D119))*$C119 -> 1.8 | K119: =(INT($E$25*7/$D119)-INT($E$25*(7-1)/$D119))*$C119 -> 1.8 | L119: =(INT($E$25*8/$D119)-INT($E$25*(8-1)/$D119))*$C119 -> 1.8 | M119: =(INT($E$25*9/$D119)-INT($E$25*(9-1)/$D119))*$C119 -> 0.9 | N119: =(INT($E$25*10/$D119)-INT($E$25*(10-1)/$D119))*$C119 -> 1.8
B120: Ремонт системы смазки | C120: 2 | D120: 12000 | E120: =(INT($E$25*1/$D120)-INT($E$25*(1-1)/$D120))*$C120 -> 0 | F120: =(INT($E$25*2/$D120)-INT($E$25*(2-1)/$D120))*$C120 -> 2 | G120: =(INT($E$25*3/$D120)-INT($E$25*(3-1)/$D120))*$C120 -> 0 | H120: =(INT($E$25*4/$D120)-INT($E$25*(4-1)/$D120))*$C120 -> 2 | I120: =(INT($E$25*5/$D120)-INT($E$25*(5-1)/$D120))*$C120 -> 0 | J120: =(INT($E$25*6/$D120)-INT($E$25*(6-1)/$D120))*$C120 -> 2 | K120: =(INT($E$25*7/$D120)-INT($E$25*(7-1)/$D120))*$C120 -> 2 | L120: =(INT($E$25*8/$D120)-INT($E$25*(8-1)/$D120))*$C120 -> 0 | M120: =(INT($E$25*9/$D120)-INT($E$25*(9-1)/$D120))*$C120 -> 2 | N120: =(INT($E$25*10/$D120)-INT($E$25*(10-1)/$D120))*$C120 -> 0
... B124: Инспекция металлоконструкций | C124: 185 | D124: 65000 | E124: =(INT($E$25*1/$D124)-INT($E$25*(1-1)/$D124))*$C124 -> 0 | F124: =(INT($E$25*2/$D124)-INT($E$25*(2-1)/$D124))*$C124 -> 0 | G124: =(INT($E$25*3/$D124)-INT($E$25*(3-1)/$D124))*$C124 -> 0 | H124: =(INT($E$25*4/$D124)-INT($E$25*(4-1)/$D124))*$C124 -> 0 | I124: =(INT($E$25*5/$D124)-INT($E$25*(5-1)/$D124))*$C124 -> 0 | J124: =(INT($E$25*6/$D124)-INT($E$25*(6-1)/$D124))*$C124 -> 0 | K124: =(INT($E$25*7/$D124)-INT($E$25*(7-1)/$D124))*$C124 -> 0 | L124: =(INT($E$25*8/$D124)-INT($E$25*(8-1)/$D124))*$C124 -> 0 | M124: =(INT($E$25*9/$D124)-INT($E$25*(9-1)/$D124))*$C124 -> 0 | N124: =(INT($E$25*10/$D124)-INT($E$25*(10-1)/$D124))*$C124 -> 185
B125: ИТОГО | E125: =SUM(E109:E124) -> 48.4 | F125: =SUM(F109:F124) -> 174.3 | G125: =SUM(G109:G124) -> 228.3 | H125: =SUM(H109:H124) -> 174.3 | I125: =SUM(I109:I124) -> 220.4 | J125: =SUM(J109:J124) -> 255.8 | K125: =SUM(K109:K124) -> 226.3 | L125: =SUM(L109:L124) -> 176.3 | ... N125: =SUM(N109:N124) -> 365.3
B127: КАПИТАЛЬНЫЕ РЕМОНТЫ — ЗАТРАТЫ НА ЗЧ (по ресурсу до замены узла)
B128: Наименование | C128: стоим.замены,вал | D128: ресурс, м/ч | E128: год 1 | F128: год 2 | G128: год 3 | H128: год 4 | I128: год 5 | J128: год 6 | K128: год 7 | L128: год 8 | M128: год 9 | N128: год 10
B129: PUMP,P7,9A CONT (главный насос) | C129: 37124 | D129: 12000 | E129: =(INT($E$25*1/$D129)-INT($E$25*(1-1)/$D129))*$C129/1000 -> 0 | F129: =(INT($E$25*2/$D129)-INT($E$25*(2-1)/$D129))*$C129/1000 -> 37.124 | G129: =(INT($E$25*3/$D129)-INT($E$25*(3-1)/$D129))*$C129/1000 -> 0 | H129: =(INT($E$25*4/$D129)-INT($E$25*(4-1)/$D129))*$C129/1000 -> 37.124 | I129: =(INT($E$25*5/$D129)-INT($E$25*(5-1)/$D129))*$C129/1000 -> 0 | J129: =(INT($E$25*6/$D129)-INT($E$25*(6-1)/$D129))*$C129/1000 -> 37.124 | K129: =(INT($E$25*7/$D129)-INT($E$25*(7-1)/$D129))*$C129/1000 -> 37.124 | L129: =(INT($E$25*8/$D129)-INT($E$25*(8-1)/$D129))*$C129/1000 -> 0 | M129: =(INT($E$25*9/$D129)-INT($E$25*(9-1)/$D129))*$C129/1000 -> 37.124 | N129: =(INT($E$25*10/$D129)-INT($E$25*(10-1)/$D129))*$C129/1000 -> 0
B130: DRIVE SHAFT & BEARING (вал и подшипник | C130: 1226.17 | D130: 11000 | E130: =(INT($E$25*1/$D130)-INT($E$25*(1-1)/$D130))*$C130/1000 -> 0 | F130: =(INT($E$25*2/$D130)-INT($E$25*(2-1)/$D130))*$C130/1000 -> 1.22617 | G130: =(INT($E$25*3/$D130)-INT($E$25*(3-1)/$D130))*$C130/1000 -> 0 | H130: =(INT($E$25*4/$D130)-INT($E$25*(4-1)/$D130))*$C130/1000 -> 1.22617 | I130: =(INT($E$25*5/$D130)-INT($E$25*(5-1)/$D130))*$C130/1000 -> 1.22617 | J130: =(INT($E$25*6/$D130)-INT($E$25*(6-1)/$D130))*$C130/1000 -> 0 | K130: =(INT($E$25*7/$D130)-INT($E$25*(7-1)/$D130))*$C130/1000 -> 1.22617 | L130: =(INT($E$25*8/$D130)-INT($E$25*(8-1)/$D130))*$C130/1000 -> 1.22617 | M130: =(INT($E$25*9/$D130)-INT($E$25*(9-1)/$D130))*$C130/1000 -> 0 | N130: =(INT($E$25*10/$D130)-INT($E$25*(10-1)/$D130))*$C130/1000 -> 1.22617
B131: STROKER,9A ELECTROHYD (сервоприв.) | C131: 18096.84 | D131: 12000 | E131: =(INT($E$25*1/$D131)-INT($E$25*(1-1)/$D131))*$C131/1000 -> 0 | F131: =(INT($E$25*2/$D131)-INT($E$25*(2-1)/$D131))*$C131/1000 -> 18.09684 | G131: =(INT($E$25*3/$D131)-INT($E$25*(3-1)/$D131))*$C131/1000 -> 0 | H131: =(INT($E$25*4/$D131)-INT($E$25*(4-1)/$D131))*$C131/1000 -> 18.09684 | I131: =(INT($E$25*5/$D131)-INT($E$25*(5-1)/$D131))*$C131/1000 -> 0 | J131: =(INT($E$25*6/$D131)-INT($E$25*(6-1)/$D131))*$C131/1000 -> 18.09684 | K131: =(INT($E$25*7/$D131)-INT($E$25*(7-1)/$D131))*$C131/1000 -> 18.09684 | L131: =(INT($E$25*8/$D131)-INT($E$25*(8-1)/$D131))*$C131/1000 -> 0 | M131: =(INT($E$25*9/$D131)-INT($E$25*(9-1)/$D131))*$C131/1000 -> 18.09684 | N131: =(INT($E$25*10/$D131)-INT($E$25*(10-1)/$D131))*$C131/1000 -> 0
B132: PUMP,TRIPLE (лопастной насос) | C132: 6929.74 | D132: 8000 | E132: =(INT($E$25*1/$D132)-INT($E$25*(1-1)/$D132))*$C132/1000 -> 0 | F132: =(INT($E$25*2/$D132)-INT($E$25*(2-1)/$D132))*$C132/1000 -> 6.92974 | G132: =(INT($E$25*3/$D132)-INT($E$25*(3-1)/$D132))*$C132/1000 -> 6.92974 | H132: =(INT($E$25*4/$D132)-INT($E$25*(4-1)/$D132))*$C132/1000 -> 6.92974 | I132: =(INT($E$25*5/$D132)-INT($E$25*(5-1)/$D132))*$C132/1000 -> 6.92974 | J132: =(INT($E$25*6/$D132)-INT($E$25*(6-1)/$D132))*$C132/1000 -> 6.92974 | K132: =(INT($E$25*7/$D132)-INT($E$25*(7-1)/$D132))*$C132/1000 -> 6.92974 | L132: =(INT($E$25*8/$D132)-INT($E$25*(8-1)/$D132))*$C132/1000 -> 6.92974 | M132: =(INT($E$25*9/$D132)-INT($E$25*(9-1)/$D132))*$C132/1000 -> 0 | N132: =(INT($E$25*10/$D132)-INT($E$25*(10-1)/$D132))*$C132/1000 -> 6.92974
B133: VALVE,ASSEMBLY,6 SPOOL (сборка расп.кл | C133: 19766.43 | D133: 25000 | E133: =(INT($E$25*1/$D133)-INT($E$25*(1-1)/$D133))*$C133/1000 -> 0 | F133: =(INT($E$25*2/$D133)-INT($E$25*(2-1)/$D133))*$C133/1000 -> 0 | G133: =(INT($E$25*3/$D133)-INT($E$25*(3-1)/$D133))*$C133/1000 -> 0 | H133: =(INT($E$25*4/$D133)-INT($E$25*(4-1)/$D133))*$C133/1000 -> 19.76643 | I133: =(INT($E$25*5/$D133)-INT($E$25*(5-1)/$D133))*$C133/1000 -> 0 | J133: =(INT($E$25*6/$D133)-INT($E$25*(6-1)/$D133))*$C133/1000 -> 0 | K133: =(INT($E$25*7/$D133)-INT($E$25*(7-1)/$D133))*$C133/1000 -> 0 | L133: =(INT($E$25*8/$D133)-INT($E$25*(8-1)/$D133))*$C133/1000 -> 19.76643 | M133: =(INT($E$25*9/$D133)-INT($E$25*(9-1)/$D133))*$C133/1000 -> 0 | N133: =(INT($E$25*10/$D133)-INT($E$25*(10-1)/$D133))*$C133/1000 -> 0
...

Sheet Поставщик 3
B1: ДАННЫЕ ПОСТАВЩИКА — ВАРИАНТ 3 (ТО и Ремонты — модель по узлам)
B2: Жёлтое — ввод. Зелёное — авто (снизу вверх). ИТОГО ТОиР = (ЗЧ ТО + ЗЧ тек.+кап.ремонтов + сервис) × коэф.калибровки; тянется в «Данные по годам».
B4: Буровой станок: | E4: ='Ввод данных'!F7 -> Sunward SWDRT270SM
B5: Валюта затрат ТОиР: | D5: EUR
B6: Показатель | C6: Ед. | E6: год 1 | F6: год 2 | G6: год 3 | H6: год 4 | I6: год 5 | J6: год 6 | K6: год 7 | L6: год 8 | M6: год 9 | N6: год 10
B7: СВОДКА ПО ГОДАМ (зелёное — авто снизу вверх; тянется в расчёт)
B8: Простои на ТО (авто из интервалов) | C8: ч/год | E8: =E40 -> 636.37233 | F8: =F40 -> 636.37233 | G8: =G40 -> 636.37233 | H8: =H40 -> 636.37233 | I8: =I40 -> 636.37233 | J8: =J40 -> 636.37233 | K8: =K40 -> 636.37233 | L8: =L40 -> 636.37233 | ... N8: =N40 -> 636.37233
B9: Простои в ремонтах (справочно) | C9: ч/год | E9: 425.645 | F9: 690.645 | G9: 870.645 | H9: 605.645 | I9: 690.645 | J9: 890.645 | K9: 720.645 | L9: 690.645 | M9: 830.645 | N9: 790.645
B10: Ежесменный осмотр (20 мин/смену), справочно | C10: ч/год | E10: =('Параметры'!C27-E8-E9)/'Параметры'!C28*20/60 -> 213.83285 | F10: =('Параметры'!C27-F8-F9)/'Параметры'!C28*20/60 -> 206.47174 | G10: =('Параметры'!C27-G8-G9)/'Параметры'!C28*20/60 -> 201.47174 | H10: =('Параметры'!C27-H8-H9)/'Параметры'!C28*20/60 -> 208.83285 | I10: =('Параметры'!C27-I8-I9)/'Параметры'!C28*20/60 -> 206.47174 | J10: =('Параметры'!C27-J8-J9)/'Параметры'!C28*20/60 -> 200.91619 | K10: =('Параметры'!C27-K8-K9)/'Параметры'!C28*20/60 -> 205.63841 | L10: =('Параметры'!C27-L8-L9)/'Параметры'!C28*20/60 -> 206.47174 | M10: =('Параметры'!C27-M8-M9)/'Параметры'!C28*20/60 -> 202.58285 | N10: =('Параметры'!C27-N8-N9)/'Параметры'!C28*20/60 -> 203.69396
B11: КТГ (техготовность, ВВОД) → «Данные по годам» | C11: коэф. | E11: 0.8948 | F11: 0.8654 | G11: 0.8454 | H11: 0.8748 | I11: 0.8654 | J11: 0.8432 | K11: 0.8621 | L11: 0.8654 | M11: 0.8498 | N11: 0.8543
B12: Затраты на ЗЧ ТО (авто из каталога) | C12: тыс.вал/г | E12: =E85 -> 136.07379 | F12: =F85 -> 136.07379 | G12: =G85 -> 136.07379 | H12: =H85 -> 136.07379 | I12: =I85 -> 136.07379 | J12: =J85 -> 136.07379 | K12: =K85 -> 136.07379 | L12: =L85 -> 136.07379 | ... N12: =N85 -> 136.07379
B13: Затраты на ЗЧ текущих ремонтов (по ресурсу) | C13: тыс.вал/г | E13: =E105 -> 4.50682 | F13: =F105 -> 60.10984 | G13: =G105 -> 145.1624 | H13: =H105 -> 60.10984 | I13: =I105 -> 144.82518 | J13: =J105 -> 67.22701 | K13: =K105 -> 145.21432 | L13: =L105 -> 60.05792 | ... N13: =N105 -> 105.58931
B14: Затраты на ЗЧ капремонтов (по ресурсу) | C14: тыс.вал/г | E14: =E188 -> 7.38238 | F14: =F188 -> 204.26495 | G14: =G188 -> 438.81584 | H14: =H188 -> 434.86339 | I14: =I188 -> 610.36746 | J14: =J188 -> 366.36175 | K14: =K188 -> 590.25823 | L14: =L188 -> 224.66392 | ... N14: =N188 -> 283.30237
B15: Трудозатраты ТО (авто) | C15: ч-час/г | E15: =E47 -> 636.37233 | F15: =F47 -> 636.37233 | G15: =G47 -> 636.37233 | H15: =H47 -> 636.37233 | I15: =I47 -> 636.37233 | J15: =J47 -> 636.37233 | K15: =K47 -> 636.37233 | L15: =L47 -> 636.37233 | ... N15: =N47 -> 636.37233
B16: Трудозатраты текущих ремонтов (авто) | C16: ч-час/г | E16: =E125 -> 48.4 | F16: =F125 -> 174.3 | G16: =G125 -> 228.3 | H16: =H125 -> 174.3 | I16: =I125 -> 220.4 | J16: =J125 -> 255.8 | K16: =K125 -> 226.3 | L16: =L125 -> 176.3 | ... N16: =N125 -> 365.3
B17: Трудозатраты капремонтов (авто) | C17: ч-час/г | E17: =E251 -> 36.6 | F17: =F251 -> 192.66 | G17: =G251 -> 330.45 | H17: =H251 -> 188.56 | I17: =I251 -> 267.75 | J17: =J251 -> 319.96 | K17: =K251 -> 300.71 | L17: =L251 -> 155.4 | ... N17: =N251 -> 102.4
B18: Сервис (трудозатраты ТО+ТР+КР) | C18: тыс.вал/г | E18: =(E15+E16+E17)*$E$23/1000 -> 41.762927 | F18: =(F15+F16+F17)*$E$23/1000 -> 58.086639 | G18: =(G15+G16+G17)*$E$23/1000 -> 69.190076 | H18: =(H15+H16+H17)*$E$23/1000 -> 57.849275 | I18: =(I15+I16+I17)*$E$23/1000 -> 65.102779 | J18: =(J15+J16+J17)*$E$23/1000 -> 70.174848 | K18: =(K15+K16+K17)*$E$23/1000 -> 67.352529 | L18: =(L15+L16+L17)*$E$23/1000 -> 56.045307 | ... N18: =(N15+N16+N17)*$E$23/1000 -> 63.918853
B19: Коэффициент калибровки ИТОГО под ТКП | C19: коэф. | E19: 0.8536
B20: ИТОГО ТОиР → «Данные по годам» | C20: тыс.вал/г | E20: =(E12+E13+E14+E18)*$E$19 -> 161.95004 | F20: =(F12+F13+F14+F18)*$E$19 -> 391.40566 | G20: =(G12+G13+G14+G18)*$E$19 -> 673.69706 | H20: =(H12+H13+H14+H18)*$E$19 -> 588.04188 | I20: =(I12+I13+I14+I18)*$E$19 -> 816.35676 | J20: =(J12+J13+J14+J18)*$E$19 -> 546.1652 | K20: =(K12+K13+K14+K18)*$E$19 -> 801.44407 | L20: =(L12+L13+L14+L18)*$E$19 -> 407.03142 | ... N20: =(N12+N13+N14+N18)*$E$19 -> 502.67166
B21: Удельный расход ДТ / энергии | C21: кг(кВт)/час | E21: 76.92 | F21: 76.92 | G21: 76.92 | H21: 76.92 | I21: 76.92 | J21: 76.92 | K21: 76.92 | L21: 76.92 | M21: 76.92 | N21: 76.92
B23: Ставка сервиса | C23: вал/ч·час | E23: 57.893718
B24: РАСЧЁТ ТО (по интервалам обслуживания), ПО ГОДАМ
B25: Наработка по годам | C25: м/час | E25: 7000 | F25: 7000 | G25: 7000 | H25: 7000 | I25: 7000 | J25: 7000 | K25: 7000 | L25: 7000 | M25: 7000 | N25: 7000
B26: Вид ТО | C26: интервал, м/ч | D26: простой/ТО, ч | E26: персонал
B27: ТО-1 | C27: 250 | D27: 10.9 | E27: 1
B28: ТО-2 | C28: 500 | D28: 13.5 | E28: 1
B29: ТО-3 | C29: 1000 | D29: 12.43 | E29: 1
B30: ТО-4 | C30: 2000 | D30: 5.67 | E30: 1
B31: ТО-5 | C31: 3000 | D31: 10.06 | E31: 1
B32: ТО-6 | C32: 5000 | D32: 8.46 | E32: 1
B34: ТО-1: простои, ч/год | C34: ч | E34: =E$25/$C27*$D27 -> 305.2 | F34: =F$25/$C27*$D27 -> 305.2 | G34: =G$25/$C27*$D27 -> 305.2 | H34: =H$25/$C27*$D27 -> 305.2 | I34: =I$25/$C27*$D27 -> 305.2 | J34: =J$25/$C27*$D27 -> 305.2 | K34: =K$25/$C27*$D27 -> 305.2 | L34: =L$25/$C27*$D27 -> 305.2 | ... N34: =N$25/$C27*$D27 -> 305.2
B35: ТО-2: простои, ч/год | C35: ч | E35: =E$25/$C28*$D28 -> 189 | F35: =F$25/$C28*$D28 -> 189 | G35: =G$25/$C28*$D28 -> 189 | H35: =H$25/$C28*$D28 -> 189 | I35: =I$25/$C28*$D28 -> 189 | J35: =J$25/$C28*$D28 -> 189 | K35: =K$25/$C28*$D28 -> 189 | L35: =L$25/$C28*$D28 -> 189 | ... N35: =N$25/$C28*$D28 -> 189
B36: ТО-3: простои, ч/год | C36: ч | E36: =E$25/$C29*$D29 -> 87.01 | F36: =F$25/$C29*$D29 -> 87.01 | G36: =G$25/$C29*$D29 -> 87.01 | H36: =H$25/$C29*$D29 -> 87.01 | I36: =I$25/$C29*$D29 -> 87.01 | J36: =J$25/$C29*$D29 -> 87.01 | K36: =K$25/$C29*$D29 -> 87.01 | L36: =L$25/$C29*$D29 -> 87.01 | ... N36: =N$25/$C29*$D29 -> 87.01
B37: ТО-4: простои, ч/год | C37: ч | E37: =E$25/$C30*$D30 -> 19.845 | F37: =F$25/$C30*$D30 -> 19.845 | G37: =G$25/$C30*$D30 -> 19.845 | H37: =H$25/$C30*$D30 -> 19.845 | I37: =I$25/$C30*$D30 -> 19.845 | J37: =J$25/$C30*$D30 -> 19.845 | K37: =K$25/$C30*$D30 -> 19.845 | L37: =L$25/$C30*$D30 -> 19.845 | ... N37: =N$25/$C30*$D30 -> 19.845
B38: ТО-5: простои, ч/год | C38: ч | E38: =E$25/$C31*$D31 -> 23.473333 | F38: =F$25/$C31*$D31 -> 23.473333 | G38: =G$25/$C31*$D31 -> 23.473333 | H38: =H$25/$C31*$D31 -> 23.473333 | I38: =I$25/$C31*$D31 -> 23.473333 | J38: =J$25/$C31*$D31 -> 23.473333 | K38: =K$25/$C31*$D31 -> 23.473333 | L38: =L$25/$C31*$D31 -> 23.473333 | ... N38: =N$25/$C31*$D31 -> 23.473333
B39: ТО-6: простои, ч/год | C39: ч | E39: =E$25/$C32*$D32 -> 11.844 | F39: =F$25/$C32*$D32 -> 11.844 | G39: =G$25/$C32*$D32 -> 11.844 | H39: =H$25/$C32*$D32 -> 11.844 | I39: =I$25/$C32*$D32 -> 11.844 | J39: =J$25/$C32*$D32 -> 11.844 | K39: =K$25/$C32*$D32 -> 11.844 | L39: =L$25/$C32*$D32 -> 11.844 | ... N39: =N$25/$C32*$D32 -> 11.844
B40: Итого простои ТО | E40: =SUM(E34:E39) -> 636.37233 | F40: =SUM(F34:F39) -> 636.37233 | G40: =SUM(G34:G39) -> 636.37233 | H40: =SUM(H34:H39) -> 636.37233 | I40: =SUM(I34:I39) -> 636.37233 | J40: =SUM(J34:J39) -> 636.37233 | K40: =SUM(K34:K39) -> 636.37233 | L40: =SUM(L34:L39) -> 636.37233 | ... N40: =SUM(N34:N39) -> 636.37233
B41: ТО-1: чел-часы/год | C41: ч-час | E41: =E34*$E27 -> 305.2 | F41: =F34*$E27 -> 305.2 | G41: =G34*$E27 -> 305.2 | H41: =H34*$E27 -> 305.2 | I41: =I34*$E27 -> 305.2 | J41: =J34*$E27 -> 305.2 | K41: =K34*$E27 -> 305.2 | L41: =L34*$E27 -> 305.2 | ... N41: =N34*$E27 -> 305.2
B42: ТО-2: чел-часы/год | C42: ч-час | E42: =E35*$E28 -> 189 | F42: =F35*$E28 -> 189 | G42: =G35*$E28 -> 189 | H42: =H35*$E28 -> 189 | I42: =I35*$E28 -> 189 | J42: =J35*$E28 -> 189 | K42: =K35*$E28 -> 189 | L42: =L35*$E28 -> 189 | ... N42: =N35*$E28 -> 189
B43: ТО-3: чел-часы/год | C43: ч-час | E43: =E36*$E29 -> 87.01 | F43: =F36*$E29 -> 87.01 | G43: =G36*$E29 -> 87.01 | H43: =H36*$E29 -> 87.01 | I43: =I36*$E29 -> 87.01 | J43: =J36*$E29 -> 87.01 | K43: =K36*$E29 -> 87.01 | L43: =L36*$E29 -> 87.01 | ... N43: =N36*$E29 -> 87.01
B44: ТО-4: чел-часы/год | C44: ч-час | E44: =E37*$E30 -> 19.845 | F44: =F37*$E30 -> 19.845 | G44: =G37*$E30 -> 19.845 | H44: =H37*$E30 -> 19.845 | I44: =I37*$E30 -> 19.845 | J44: =J37*$E30 -> 19.845 | K44: =K37*$E30 -> 19.845 | L44: =L37*$E30 -> 19.845 | ... N44: =N37*$E30 -> 19.845
B45: ТО-5: чел-часы/год | C45: ч-час | E45: =E38*$E31 -> 23.473333 | F45: =F38*$E31 -> 23.473333 | G45: =G38*$E31 -> 23.473333 | H45: =H38*$E31 -> 23.473333 | I45: =I38*$E31 -> 23.473333 | J45: =J38*$E31 -> 23.473333 | K45: =K38*$E31 -> 23.473333 | L45: =L38*$E31 -> 23.473333 | ... N45: =N38*$E31 -> 23.473333
B46: ТО-6: чел-часы/год | C46: ч-час | E46: =E39*$E32 -> 11.844 | F46: =F39*$E32 -> 11.844 | G46: =G39*$E32 -> 11.844 | H46: =H39*$E32 -> 11.844 | I46: =I39*$E32 -> 11.844 | J46: =J39*$E32 -> 11.844 | K46: =K39*$E32 -> 11.844 | L46: =L39*$E32 -> 11.844 | ... N46: =N39*$E32 -> 11.844
B47: Итого чел-часы ТО | E47: =SUM(E41:E46) -> 636.37233 | F47: =SUM(F41:F46) -> 636.37233 | G47: =SUM(G41:G46) -> 636.37233 | H47: =SUM(H41:H46) -> 636.37233 | I47: =SUM(I41:I46) -> 636.37233 | J47: =SUM(J41:J46) -> 636.37233 | K47: =SUM(K41:K46) -> 636.37233 | L47: =SUM(L41:L46) -> 636.37233 | ... N47: =SUM(N41:N46) -> 636.37233
B49: КАТАЛОГ ЗАПЧАСТЕЙ ТО (заполняет подрядчик), ПО ГОДАМ
B50: Наименование | C50: цена за ед | D50: кол-во/ТО | P50: № ТО
B51: Моторное масло | C51: 6.77 | D51: 70 | E51: =E$25/INDEX($C$27:$C$32,$P51)*D51*C51/1000 -> 13.2692 | F51: =F$25/INDEX($C$27:$C$32,$P51)*D51*C51/1000 -> 13.2692 | G51: =G$25/INDEX($C$27:$C$32,$P51)*D51*C51/1000 -> 13.2692 | H51: =H$25/INDEX($C$27:$C$32,$P51)*D51*C51/1000 -> 13.2692 | I51: =I$25/INDEX($C$27:$C$32,$P51)*D51*C51/1000 -> 13.2692 | J51: =J$25/INDEX($C$27:$C$32,$P51)*D51*C51/1000 -> 13.2692 | K51: =K$25/INDEX($C$27:$C$32,$P51)*D51*C51/1000 -> 13.2692 | L51: =L$25/INDEX($C$27:$C$32,$P51)*D51*C51/1000 -> 13.2692 | M51: =M$25/INDEX($C$27:$C$32,$P51)*D51*C51/1000 -> 13.2692 | N51: =N$25/INDEX($C$27:$C$32,$P51)*D51*C51/1000 -> 13.2692 | P51: 1
B52: Масляный фильтр двигателя | C52: 75.788 | D52: 2 | E52: =E$25/INDEX($C$27:$C$32,$P52)*D52*C52/1000 -> 4.244128 | F52: =F$25/INDEX($C$27:$C$32,$P52)*D52*C52/1000 -> 4.244128 | G52: =G$25/INDEX($C$27:$C$32,$P52)*D52*C52/1000 -> 4.244128 | H52: =H$25/INDEX($C$27:$C$32,$P52)*D52*C52/1000 -> 4.244128 | I52: =I$25/INDEX($C$27:$C$32,$P52)*D52*C52/1000 -> 4.244128 | J52: =J$25/INDEX($C$27:$C$32,$P52)*D52*C52/1000 -> 4.244128 | K52: =K$25/INDEX($C$27:$C$32,$P52)*D52*C52/1000 -> 4.244128 | L52: =L$25/INDEX($C$27:$C$32,$P52)*D52*C52/1000 -> 4.244128 | M52: =M$25/INDEX($C$27:$C$32,$P52)*D52*C52/1000 -> 4.244128 | N52: =N$25/INDEX($C$27:$C$32,$P52)*D52*C52/1000 -> 4.244128 | P52: 1
B53: Охлаждающая жидкость | C53: 4.368 | D53: 3 | E53: =E$25/INDEX($C$27:$C$32,$P53)*D53*C53/1000 -> 0.366912 | F53: =F$25/INDEX($C$27:$C$32,$P53)*D53*C53/1000 -> 0.366912 | G53: =G$25/INDEX($C$27:$C$32,$P53)*D53*C53/1000 -> 0.366912 | H53: =H$25/INDEX($C$27:$C$32,$P53)*D53*C53/1000 -> 0.366912 | I53: =I$25/INDEX($C$27:$C$32,$P53)*D53*C53/1000 -> 0.366912 | J53: =J$25/INDEX($C$27:$C$32,$P53)*D53*C53/1000 -> 0.366912 | K53: =K$25/INDEX($C$27:$C$32,$P53)*D53*C53/1000 -> 0.366912 | L53: =L$25/INDEX($C$27:$C$32,$P53)*D53*C53/1000 -> 0.366912 | M53: =M$25/INDEX($C$27:$C$32,$P53)*D53*C53/1000 -> 0.366912 | N53: =N$25/INDEX($C$27:$C$32,$P53)*D53*C53/1000 -> 0.366912 | P53: 1
B54: Воздушный фильтр первичный | C54: 51.588 | D54: 3 | E54: =E$25/INDEX($C$27:$C$32,$P54)*D54*C54/1000 -> 4.333392 | F54: =F$25/INDEX($C$27:$C$32,$P54)*D54*C54/1000 -> 4.333392 | G54: =G$25/INDEX($C$27:$C$32,$P54)*D54*C54/1000 -> 4.333392 | H54: =H$25/INDEX($C$27:$C$32,$P54)*D54*C54/1000 -> 4.333392 | I54: =I$25/INDEX($C$27:$C$32,$P54)*D54*C54/1000 -> 4.333392 | J54: =J$25/INDEX($C$27:$C$32,$P54)*D54*C54/1000 -> 4.333392 | K54: =K$25/INDEX($C$27:$C$32,$P54)*D54*C54/1000 -> 4.333392 | L54: =L$25/INDEX($C$27:$C$32,$P54)*D54*C54/1000 -> 4.333392 | M54: =M$25/INDEX($C$27:$C$32,$P54)*D54*C54/1000 -> 4.333392 | N54: =N$25/INDEX($C$27:$C$32,$P54)*D54*C54/1000 -> 4.333392 | P54: 1
B55: Воздушный фильтр вторичный | C55: 37.65 | D55: 3 | E55: =E$25/INDEX($C$27:$C$32,$P55)*D55*C55/1000 -> 3.1626 | F55: =F$25/INDEX($C$27:$C$32,$P55)*D55*C55/1000 -> 3.1626 | G55: =G$25/INDEX($C$27:$C$32,$P55)*D55*C55/1000 -> 3.1626 | H55: =H$25/INDEX($C$27:$C$32,$P55)*D55*C55/1000 -> 3.1626 | I55: =I$25/INDEX($C$27:$C$32,$P55)*D55*C55/1000 -> 3.1626 | J55: =J$25/INDEX($C$27:$C$32,$P55)*D55*C55/1000 -> 3.1626 | K55: =K$25/INDEX($C$27:$C$32,$P55)*D55*C55/1000 -> 3.1626 | L55: =L$25/INDEX($C$27:$C$32,$P55)*D55*C55/1000 -> 3.1626 | M55: =M$25/INDEX($C$27:$C$32,$P55)*D55*C55/1000 -> 3.1626 | N55: =N$25/INDEX($C$27:$C$32,$P55)*D55*C55/1000 -> 3.1626 | P55: 1
B56: Фильтр системы охл. ДВС | C56: 27.113 | D56: 2 | E56: =E$25/INDEX($C$27:$C$32,$P56)*D56*C56/1000 -> 1.518328 | F56: =F$25/INDEX($C$27:$C$32,$P56)*D56*C56/1000 -> 1.518328 | G56: =G$25/INDEX($C$27:$C$32,$P56)*D56*C56/1000 -> 1.518328 | H56: =H$25/INDEX($C$27:$C$32,$P56)*D56*C56/1000 -> 1.518328 | I56: =I$25/INDEX($C$27:$C$32,$P56)*D56*C56/1000 -> 1.518328 | J56: =J$25/INDEX($C$27:$C$32,$P56)*D56*C56/1000 -> 1.518328 | K56: =K$25/INDEX($C$27:$C$32,$P56)*D56*C56/1000 -> 1.518328 | L56: =L$25/INDEX($C$27:$C$32,$P56)*D56*C56/1000 -> 1.518328 | M56: =M$25/INDEX($C$27:$C$32,$P56)*D56*C56/1000 -> 1.518328 | N56: =N$25/INDEX($C$27:$C$32,$P56)*D56*C56/1000 -> 1.518328 | P56: 1
B57: Топливный фильтр первичный | C57: 65.662 | D57: 1 | E57: =E$25/INDEX($C$27:$C$32,$P57)*D57*C57/1000 -> 1.838536 | F57: =F$25/INDEX($C$27:$C$32,$P57)*D57*C57/1000 -> 1.838536 | G57: =G$25/INDEX($C$27:$C$32,$P57)*D57*C57/1000 -> 1.838536 | H57: =H$25/INDEX($C$27:$C$32,$P57)*D57*C57/1000 -> 1.838536 | I57: =I$25/INDEX($C$27:$C$32,$P57)*D57*C57/1000 -> 1.838536 | J57: =J$25/INDEX($C$27:$C$32,$P57)*D57*C57/1000 -> 1.838536 | K57: =K$25/INDEX($C$27:$C$32,$P57)*D57*C57/1000 -> 1.838536 | L57: =L$25/INDEX($C$27:$C$32,$P57)*D57*C57/1000 -> 1.838536 | M57: =M$25/INDEX($C$27:$C$32,$P57)*D57*C57/1000 -> 1.838536 | N57: =N$25/INDEX($C$27:$C$32,$P57)*D57*C57/1000 -> 1.838536 | P57: 1
B58: Топливный фильтр вторичный | C58: 127.662 | D58: 1 | E58: =E$25/INDEX($C$27:$C$32,$P58)*D58*C58/1000 -> 3.574536 | F58: =F$25/INDEX($C$27:$C$32,$P58)*D58*C58/1000 -> 3.574536 | G58: =G$25/INDEX($C$27:$C$32,$P58)*D58*C58/1000 -> 3.574536 | H58: =H$25/INDEX($C$27:$C$32,$P58)*D58*C58/1000 -> 3.574536 | I58: =I$25/INDEX($C$27:$C$32,$P58)*D58*C58/1000 -> 3.574536 | J58: =J$25/INDEX($C$27:$C$32,$P58)*D58*C58/1000 -> 3.574536 | K58: =K$25/INDEX($C$27:$C$32,$P58)*D58*C58/1000 -> 3.574536 | L58: =L$25/INDEX($C$27:$C$32,$P58)*D58*C58/1000 -> 3.574536 | M58: =M$25/INDEX($C$27:$C$32,$P58)*D58*C58/1000 -> 3.574536 | N58: =N$25/INDEX($C$27:$C$32,$P58)*D58*C58/1000 -> 3.574536 | P58: 1
B59: Влагоотделитель | C59: 14.612 | D59: 2 | E59: =E$25/INDEX($C$27:$C$32,$P59)*D59*C59/1000 -> 0.818272 | F59: =F$25/INDEX($C$27:$C$32,$P59)*D59*C59/1000 -> 0.818272 | G59: =G$25/INDEX($C$27:$C$32,$P59)*D59*C59/1000 -> 0.818272 | H59: =H$25/INDEX($C$27:$C$32,$P59)*D59*C59/1000 -> 0.818272 | I59: =I$25/INDEX($C$27:$C$32,$P59)*D59*C59/1000 -> 0.818272 | J59: =J$25/INDEX($C$27:$C$32,$P59)*D59*C59/1000 -> 0.818272 | K59: =K$25/INDEX($C$27:$C$32,$P59)*D59*C59/1000 -> 0.818272 | L59: =L$25/INDEX($C$27:$C$32,$P59)*D59*C59/1000 -> 0.818272 | M59: =M$25/INDEX($C$27:$C$32,$P59)*D59*C59/1000 -> 0.818272 | N59: =N$25/INDEX($C$27:$C$32,$P59)*D59*C59/1000 -> 0.818272 | P59: 1
B60: Консистентная смазка | C60: 10.752 | D60: 2 | E60: =E$25/INDEX($C$27:$C$32,$P60)*D60*C60/1000 -> 0.602112 | F60: =F$25/INDEX($C$27:$C$32,$P60)*D60*C60/1000 -> 0.602112 | G60: =G$25/INDEX($C$27:$C$32,$P60)*D60*C60/1000 -> 0.602112 | H60: =H$25/INDEX($C$27:$C$32,$P60)*D60*C60/1000 -> 0.602112 | I60: =I$25/INDEX($C$27:$C$32,$P60)*D60*C60/1000 -> 0.602112 | J60: =J$25/INDEX($C$27:$C$32,$P60)*D60*C60/1000 -> 0.602112 | K60: =K$25/INDEX($C$27:$C$32,$P60)*D60*C60/1000 -> 0.602112 | L60: =L$25/INDEX($C$27:$C$32,$P60)*D60*C60/1000 -> 0.602112 | M60: =M$25/INDEX($C$27:$C$32,$P60)*D60*C60/1000 -> 0.602112 | N60: =N$25/INDEX($C$27:$C$32,$P60)*D60*C60/1000 -> 0.602112 | P60: 1
B61: Сапун гидробака | C61: 18.025 | D61: 2 | E61: =E$25/INDEX($C$27:$C$32,$P61)*D61*C61/1000 -> 0.5047 | F61: =F$25/INDEX($C$27:$C$32,$P61)*D61*C61/1000 -> 0.5047 | G61: =G$25/INDEX($C$27:$C$32,$P61)*D61*C61/1000 -> 0.5047 | H61: =H$25/INDEX($C$27:$C$32,$P61)*D61*C61/1000 -> 0.5047 | I61: =I$25/INDEX($C$27:$C$32,$P61)*D61*C61/1000 -> 0.5047 | J61: =J$25/INDEX($C$27:$C$32,$P61)*D61*C61/1000 -> 0.5047 | K61: =K$25/INDEX($C$27:$C$32,$P61)*D61*C61/1000 -> 0.5047 | L61: =L$25/INDEX($C$27:$C$32,$P61)*D61*C61/1000 -> 0.5047 | M61: =M$25/INDEX($C$27:$C$32,$P61)*D61*C61/1000 -> 0.5047 | N61: =N$25/INDEX($C$27:$C$32,$P61)*D61*C61/1000 -> 0.5047 | P61: 2
B62: Фильтра системы пылеподавления | C62: 58.9 | D62: 9 | E62: =E$25/INDEX($C$27:$C$32,$P62)*D62*C62/1000 -> 7.4214 | F62: =F$25/INDEX($C$27:$C$32,$P62)*D62*C62/1000 -> 7.4214 | G62: =G$25/INDEX($C$27:$C$32,$P62)*D62*C62/1000 -> 7.4214 | H62: =H$25/INDEX($C$27:$C$32,$P62)*D62*C62/1000 -> 7.4214 | I62: =I$25/INDEX($C$27:$C$32,$P62)*D62*C62/1000 -> 7.4214 | J62: =J$25/INDEX($C$27:$C$32,$P62)*D62*C62/1000 -> 7.4214 | K62: =K$25/INDEX($C$27:$C$32,$P62)*D62*C62/1000 -> 7.4214 | L62: =L$25/INDEX($C$27:$C$32,$P62)*D62*C62/1000 -> 7.4214 | M62: =M$25/INDEX($C$27:$C$32,$P62)*D62*C62/1000 -> 7.4214 | N62: =N$25/INDEX($C$27:$C$32,$P62)*D62*C62/1000 -> 7.4214 | P62: 2
... B83: Охлаждающая жидкость | C83: 3.122 | D83: 190 | E83: =E$25/INDEX($C$27:$C$32,$P83)*D83*C83/1000 -> 0.830452 | F83: =F$25/INDEX($C$27:$C$32,$P83)*D83*C83/1000 -> 0.830452 | G83: =G$25/INDEX($C$27:$C$32,$P83)*D83*C83/1000 -> 0.830452 | H83: =H$25/INDEX($C$27:$C$32,$P83)*D83*C83/1000 -> 0.830452 | I83: =I$25/INDEX($C$27:$C$32,$P83)*D83*C83/1000 -> 0.830452 | J83: =J$25/INDEX($C$27:$C$32,$P83)*D83*C83/1000 -> 0.830452 | K83: =K$25/INDEX($C$27:$C$32,$P83)*D83*C83/1000 -> 0.830452 | L83: =L$25/INDEX($C$27:$C$32,$P83)*D83*C83/1000 -> 0.830452 | M83: =M$25/INDEX($C$27:$C$32,$P83)*D83*C83/1000 -> 0.830452 | N83: =N$25/INDEX($C$27:$C$32,$P83)*D83*C83/1000 -> 0.830452 | P83: 6
B84: Корректировка (прочее) | E84: 0 | F84: 0 | G84: 0 | H84: 0 | I84: 0 | J84: 0 | K84: 0 | L84: 0 | M84: 0 | N84: 0
B85: ИТОГО ЗЧ ТО, тыс.вал/год | E85: =SUM(E51:E84) -> 136.07379 | F85: =SUM(F51:F84) -> 136.07379 | G85: =SUM(G51:G84) -> 136.07379 | H85: =SUM(H51:H84) -> 136.07379 | I85: =SUM(I51:I84) -> 136.07379 | J85: =SUM(J51:J84) -> 136.07379 | K85: =SUM(K51:K84) -> 136.07379 | L85: =SUM(L51:L84) -> 136.07379 | ... N85: =SUM(N51:N84) -> 136.07379
B87: ТЕКУЩИЕ РЕМОНТЫ — ЗАТРАТЫ НА ЗЧ (по ресурсу)
B88: Наименование | C88: стоим.замены,вал | D88: ресурс, м/ч | E88: год 1 | F88: год 2 | G88: год 3 | H88: год 4 | I88: год 5 | J88: год 6 | K88: год 7 | L88: год 8 | M88: год 9 | N88: год 10
B89: ENG (двигатель капремонт) | C89: 98848.48 | D89: 15000 | E89: =(INT($E$25*1/$D89)-INT($E$25*(1-1)/$D89))*$C89/1000 -> 0 | F89: =(INT($E$25*2/$D89)-INT($E$25*(2-1)/$D89))*$C89/1000 -> 0 | G89: =(INT($E$25*3/$D89)-INT($E$25*(3-1)/$D89))*$C89/1000 -> 98.84848 | H89: =(INT($E$25*4/$D89)-INT($E$25*(4-1)/$D89))*$C89/1000 -> 0 | I89: =(INT($E$25*5/$D89)-INT($E$25*(5-1)/$D89))*$C89/1000 -> 98.84848 | J89: =(INT($E$25*6/$D89)-INT($E$25*(6-1)/$D89))*$C89/1000 -> 0 | K89: =(INT($E$25*7/$D89)-INT($E$25*(7-1)/$D89))*$C89/1000 -> 98.84848 | L89: =(INT($E$25*8/$D89)-INT($E$25*(8-1)/$D89))*$C89/1000 -> 0 | M89: =(INT($E$25*9/$D89)-INT($E$25*(9-1)/$D89))*$C89/1000 -> 98.84848 | N89: =(INT($E$25*10/$D89)-INT($E$25*(10-1)/$D89))*$C89/1000 -> 0
B90: AIREND Seal LP (Компрессор ремкомплект | C90: 32894 | D90: 16000 | E90: =(INT($E$25*1/$D90)-INT($E$25*(1-1)/$D90))*$C90/1000 -> 0 | F90: =(INT($E$25*2/$D90)-INT($E$25*(2-1)/$D90))*$C90/1000 -> 0 | G90: =(INT($E$25*3/$D90)-INT($E$25*(3-1)/$D90))*$C90/1000 -> 32.894 | H90: =(INT($E$25*4/$D90)-INT($E$25*(4-1)/$D90))*$C90/1000 -> 0 | I90: =(INT($E$25*5/$D90)-INT($E$25*(5-1)/$D90))*$C90/1000 -> 32.894 | J90: =(INT($E$25*6/$D90)-INT($E$25*(6-1)/$D90))*$C90/1000 -> 0 | K90: =(INT($E$25*7/$D90)-INT($E$25*(7-1)/$D90))*$C90/1000 -> 32.894 | L90: =(INT($E$25*8/$D90)-INT($E$25*(8-1)/$D90))*$C90/1000 -> 0 | M90: =(INT($E$25*9/$D90)-INT($E$25*(9-1)/$D90))*$C90/1000 -> 0 | N90: =(INT($E$25*10/$D90)-INT($E$25*(10-1)/$D90))*$C90/1000 -> 32.894
B91: ROTARYHEAD (Ремкомплект вращателя | C91: 46638 | D91: 13000 | E91: =(INT($E$25*1/$D91)-INT($E$25*(1-1)/$D91))*$C91/1000 -> 0 | F91: =(INT($E$25*2/$D91)-INT($E$25*(2-1)/$D91))*$C91/1000 -> 46.638 | G91: =(INT($E$25*3/$D91)-INT($E$25*(3-1)/$D91))*$C91/1000 -> 0 | H91: =(INT($E$25*4/$D91)-INT($E$25*(4-1)/$D91))*$C91/1000 -> 46.638 | I91: =(INT($E$25*5/$D91)-INT($E$25*(5-1)/$D91))*$C91/1000 -> 0 | J91: =(INT($E$25*6/$D91)-INT($E$25*(6-1)/$D91))*$C91/1000 -> 46.638 | K91: =(INT($E$25*7/$D91)-INT($E$25*(7-1)/$D91))*$C91/1000 -> 0 | L91: =(INT($E$25*8/$D91)-INT($E$25*(8-1)/$D91))*$C91/1000 -> 46.638 | M91: =(INT($E$25*9/$D91)-INT($E$25*(9-1)/$D91))*$C91/1000 -> 0 | N91: =(INT($E$25*10/$D91)-INT($E$25*(10-1)/$D91))*$C91/1000 -> 46.638
B92: KIT, SEAL (ремкомплект к цилиндру пода | C92: 4240.92 | D92: 7450 | E92: =(INT($E$25*1/$D92)-INT($E$25*(1-1)/$D92))*$C92/1000 -> 0 | F92: =(INT($E$25*2/$D92)-INT($E$25*(2-1)/$D92))*$C92/1000 -> 4.24092 | G92: =(INT($E$25*3/$D92)-INT($E$25*(3-1)/$D92))*$C92/1000 -> 4.24092 | H92: =(INT($E$25*4/$D92)-INT($E$25*(4-1)/$D92))*$C92/1000 -> 4.24092 | I92: =(INT($E$25*5/$D92)-INT($E$25*(5-1)/$D92))*$C92/1000 -> 4.24092 | J92: =(INT($E$25*6/$D92)-INT($E$25*(6-1)/$D92))*$C92/1000 -> 4.24092 | K92: =(INT($E$25*7/$D92)-INT($E$25*(7-1)/$D92))*$C92/1000 -> 4.24092 | L92: =(INT($E$25*8/$D92)-INT($E$25*(8-1)/$D92))*$C92/1000 -> 4.24092 | M92: =(INT($E$25*9/$D92)-INT($E$25*(9-1)/$D92))*$C92/1000 -> 4.24092 | N92: =(INT($E$25*10/$D92)-INT($E$25*(10-1)/$D92))*$C92/1000 -> 4.24092
B93: SEAL KIT,CYLINDER (ремкомплект к цил.д | C93: 4242.92 | D93: 7450 | E93: =(INT($E$25*1/$D93)-INT($E$25*(1-1)/$D93))*$C93/1000 -> 0 | F93: =(INT($E$25*2/$D93)-INT($E$25*(2-1)/$D93))*$C93/1000 -> 4.24292 | G93: =(INT($E$25*3/$D93)-INT($E$25*(3-1)/$D93))*$C93/1000 -> 4.24292 | H93: =(INT($E$25*4/$D93)-INT($E$25*(4-1)/$D93))*$C93/1000 -> 4.24292 | I93: =(INT($E$25*5/$D93)-INT($E$25*(5-1)/$D93))*$C93/1000 -> 4.24292 | J93: =(INT($E$25*6/$D93)-INT($E$25*(6-1)/$D93))*$C93/1000 -> 4.24292 | K93: =(INT($E$25*7/$D93)-INT($E$25*(7-1)/$D93))*$C93/1000 -> 4.24292 | L93: =(INT($E$25*8/$D93)-INT($E$25*(8-1)/$D93))*$C93/1000 -> 4.24292 | M93: =(INT($E$25*9/$D93)-INT($E$25*(9-1)/$D93))*$C93/1000 -> 4.24292 | N93: =(INT($E$25*10/$D93)-INT($E$25*(10-1)/$D93))*$C93/1000 -> 4.24292
B94: KIT, SEAL (ремкомплект к цилиндру п. м | C94: 3464.48 | D94: 6000 | E94: =(INT($E$25*1/$D94)-INT($E$25*(1-1)/$D94))*$C94/1000 -> 3.46448 | F94: =(INT($E$25*2/$D94)-INT($E$25*(2-1)/$D94))*$C94/1000 -> 3.46448 | G94: =(INT($E$25*3/$D94)-INT($E$25*(3-1)/$D94))*$C94/1000 -> 3.46448 | H94: =(INT($E$25*4/$D94)-INT($E$25*(4-1)/$D94))*$C94/1000 -> 3.46448 | I94: =(INT($E$25*5/$D94)-INT($E$25*(5-1)/$D94))*$C94/1000 -> 3.46448 | J94: =(INT($E$25*6/$D94)-INT($E$25*(6-1)/$D94))*$C94/1000 -> 6.92896 | K94: =(INT($E$25*7/$D94)-INT($E$25*(7-1)/$D94))*$C94/1000 -> 3.46448 | L94: =(INT($E$25*8/$D94)-INT($E$25*(8-1)/$D94))*$C94/1000 -> 3.46448 | M94: =(INT($E$25*9/$D94)-INT($E$25*(9-1)/$D94))*$C94/1000 -> 3.46448 | N94: =(INT($E$25*10/$D94)-INT($E$25*(10-1)/$D94))*$C94/1000 -> 3.46448
B95: SEAL KIT (ремкомплектгидроцилиндр мех. | C95: 237.18 | D95: 6000 | E95: =(INT($E$25*1/$D95)-INT($E$25*(1-1)/$D95))*$C95/1000 -> 0.23718 | F95: =(INT($E$25*2/$D95)-INT($E$25*(2-1)/$D95))*$C95/1000 -> 0.23718 | G95: =(INT($E$25*3/$D95)-INT($E$25*(3-1)/$D95))*$C95/1000 -> 0.23718 | H95: =(INT($E$25*4/$D95)-INT($E$25*(4-1)/$D95))*$C95/1000 -> 0.23718 | I95: =(INT($E$25*5/$D95)-INT($E$25*(5-1)/$D95))*$C95/1000 -> 0.23718 | J95: =(INT($E$25*6/$D95)-INT($E$25*(6-1)/$D95))*$C95/1000 -> 0.47436 | K95: =(INT($E$25*7/$D95)-INT($E$25*(7-1)/$D95))*$C95/1000 -> 0.23718 | L95: =(INT($E$25*8/$D95)-INT($E$25*(8-1)/$D95))*$C95/1000 -> 0.23718 | M95: =(INT($E$25*9/$D95)-INT($E$25*(9-1)/$D95))*$C95/1000 -> 0.23718 | N95: =(INT($E$25*10/$D95)-INT($E$25*(10-1)/$D95))*$C95/1000 -> 0.23718
B96: KIT,SEAL (ремкомплект цилиндра ключа) | C96: 102.66 | D96: 4000 | E96: =(INT($E$25*1/$D96)-INT($E$25*(1-1)/$D96))*$C96/1000 -> 0.10266 | F96: =(INT($E$25*2/$D96)-INT($E$25*(2-1)/$D96))*$C96/1000 -> 0.20532 | G96: =(INT($E$25*3/$D96)-INT($E$25*(3-1)/$D96))*$C96/1000 -> 0.20532 | H96: =(INT($E$25*4/$D96)-INT($E$25*(4-1)/$D96))*$C96/1000 -> 0.20532 | I96: =(INT($E$25*5/$D96)-INT($E$25*(5-1)/$D96))*$C96/1000 -> 0.10266 | J96: =(INT($E$25*6/$D96)-INT($E$25*(6-1)/$D96))*$C96/1000 -> 0.20532 | K96: =(INT($E$25*7/$D96)-INT($E$25*(7-1)/$D96))*$C96/1000 -> 0.20532 | L96: =(INT($E$25*8/$D96)-INT($E$25*(8-1)/$D96))*$C96/1000 -> 0.20532 | M96: =(INT($E$25*9/$D96)-INT($E$25*(9-1)/$D96))*$C96/1000 -> 0.10266 | N96: =(INT($E$25*10/$D96)-INT($E$25*(10-1)/$D96))*$C96/1000 -> 0.20532
B97: SEAL KIT (ремкомплект цилиндра мех.зам | C97: 110.66 | D97: 4000 | E97: =(INT($E$25*1/$D97)-INT($E$25*(1-1)/$D97))*$C97/1000 -> 0.11066 | F97: =(INT($E$25*2/$D97)-INT($E$25*(2-1)/$D97))*$C97/1000 -> 0.22132 | G97: =(INT($E$25*3/$D97)-INT($E$25*(3-1)/$D97))*$C97/1000 -> 0.22132 | H97: =(INT($E$25*4/$D97)-INT($E$25*(4-1)/$D97))*$C97/1000 -> 0.22132 | I97: =(INT($E$25*5/$D97)-INT($E$25*(5-1)/$D97))*$C97/1000 -> 0.11066 | J97: =(INT($E$25*6/$D97)-INT($E$25*(6-1)/$D97))*$C97/1000 -> 0.22132 | K97: =(INT($E$25*7/$D97)-INT($E$25*(7-1)/$D97))*$C97/1000 -> 0.22132 | L97: =(INT($E$25*8/$D97)-INT($E$25*(8-1)/$D97))*$C97/1000 -> 0.22132 | M97: =(INT($E$25*9/$D97)-INT($E$25*(9-1)/$D97))*$C97/1000 -> 0.11066 | N97: =(INT($E$25*10/$D97)-INT($E$25*(10-1)/$D97))*$C97/1000 -> 0.22132
B98: SEAL KIT (ремкомплект к гидроцил.стопо | C98: 92.04 | D98: 5000 | E98: =(INT($E$25*1/$D98)-INT($E$25*(1-1)/$D98))*$C98/1000 -> 0.09204 | F98: =(INT($E$25*2/$D98)-INT($E$25*(2-1)/$D98))*$C98/1000 -> 0.09204 | G98: =(INT($E$25*3/$D98)-INT($E$25*(3-1)/$D98))*$C98/1000 -> 0.18408 | H98: =(INT($E$25*4/$D98)-INT($E$25*(4-1)/$D98))*$C98/1000 -> 0.09204 | I98: =(INT($E$25*5/$D98)-INT($E$25*(5-1)/$D98))*$C98/1000 -> 0.18408 | J98: =(INT($E$25*6/$D98)-INT($E$25*(6-1)/$D98))*$C98/1000 -> 0.09204 | K98: =(INT($E$25*7/$D98)-INT($E$25*(7-1)/$D98))*$C98/1000 -> 0.09204 | L98: =(INT($E$25*8/$D98)-INT($E$25*(8-1)/$D98))*$C98/1000 -> 0.18408 | M98: =(INT($E$25*9/$D98)-INT($E$25*(9-1)/$D98))*$C98/1000 -> 0.09204 | N98: =(INT($E$25*10/$D98)-INT($E$25*(10-1)/$D98))*$C98/1000 -> 0.18408
B99: SEAL KIT (ремкомплект гидроцил.фартука | C99: 123.9 | D99: 4000 | E99: =(INT($E$25*1/$D99)-INT($E$25*(1-1)/$D99))*$C99/1000 -> 0.1239 | F99: =(INT($E$25*2/$D99)-INT($E$25*(2-1)/$D99))*$C99/1000 -> 0.2478 | G99: =(INT($E$25*3/$D99)-INT($E$25*(3-1)/$D99))*$C99/1000 -> 0.2478 | H99: =(INT($E$25*4/$D99)-INT($E$25*(4-1)/$D99))*$C99/1000 -> 0.2478 | I99: =(INT($E$25*5/$D99)-INT($E$25*(5-1)/$D99))*$C99/1000 -> 0.1239 | J99: =(INT($E$25*6/$D99)-INT($E$25*(6-1)/$D99))*$C99/1000 -> 0.2478 | K99: =(INT($E$25*7/$D99)-INT($E$25*(7-1)/$D99))*$C99/1000 -> 0.2478 | L99: =(INT($E$25*8/$D99)-INT($E$25*(8-1)/$D99))*$C99/1000 -> 0.2478 | M99: =(INT($E$25*9/$D99)-INT($E$25*(9-1)/$D99))*$C99/1000 -> 0.1239 | N99: =(INT($E$25*10/$D99)-INT($E$25*(10-1)/$D99))*$C99/1000 -> 0.2478
B100: Ремонт системы смазки | C100: 143.96 | D100: 12000 | E100: =(INT($E$25*1/$D100)-INT($E$25*(1-1)/$D100))*$C100/1000 -> 0 | F100: =(INT($E$25*2/$D100)-INT($E$25*(2-1)/$D100))*$C100/1000 -> 0.14396 | G100: =(INT($E$25*3/$D100)-INT($E$25*(3-1)/$D100))*$C100/1000 -> 0 | H100: =(INT($E$25*4/$D100)-INT($E$25*(4-1)/$D100))*$C100/1000 -> 0.14396 | I100: =(INT($E$25*5/$D100)-INT($E$25*(5-1)/$D100))*$C100/1000 -> 0 | J100: =(INT($E$25*6/$D100)-INT($E$25*(6-1)/$D100))*$C100/1000 -> 0.14396 | K100: =(INT($E$25*7/$D100)-INT($E$25*(7-1)/$D100))*$C100/1000 -> 0.14396 | L100: =(INT($E$25*8/$D100)-INT($E$25*(8-1)/$D100))*$C100/1000 -> 0 | M100: =(INT($E$25*9/$D100)-INT($E$25*(9-1)/$D100))*$C100/1000 -> 0.14396 | N100: =(INT($E$25*10/$D100)-INT($E$25*(10-1)/$D100))*$C100/1000 -> 0
... B104: Инспекция металлоконструкций | C104: 12637.39 | D104: 65000 | E104: =(INT($E$25*1/$D104)-INT($E$25*(1-1)/$D104))*$C104/1000 -> 0 | F104: =(INT($E$25*2/$D104)-INT($E$25*(2-1)/$D104))*$C104/1000 -> 0 | G104: =(INT($E$25*3/$D104)-INT($E$25*(3-1)/$D104))*$C104/1000 -> 0 | H104: =(INT($E$25*4/$D104)-INT($E$25*(4-1)/$D104))*$C104/1000 -> 0 | I104: =(INT($E$25*5/$D104)-INT($E$25*(5-1)/$D104))*$C104/1000 -> 0 | J104: =(INT($E$25*6/$D104)-INT($E$25*(6-1)/$D104))*$C104/1000 -> 0 | K104: =(INT($E$25*7/$D104)-INT($E$25*(7-1)/$D104))*$C104/1000 -> 0 | L104: =(INT($E$25*8/$D104)-INT($E$25*(8-1)/$D104))*$C104/1000 -> 0 | M104: =(INT($E$25*9/$D104)-INT($E$25*(9-1)/$D104))*$C104/1000 -> 0 | N104: =(INT($E$25*10/$D104)-INT($E$25*(10-1)/$D104))*$C104/1000 -> 12.63739
B105: ИТОГО | E105: =SUM(E89:E104) -> 4.50682 | F105: =SUM(F89:F104) -> 60.10984 | G105: =SUM(G89:G104) -> 145.1624 | H105: =SUM(H89:H104) -> 60.10984 | I105: =SUM(I89:I104) -> 144.82518 | J105: =SUM(J89:J104) -> 67.22701 | K105: =SUM(K89:K104) -> 145.21432 | L105: =SUM(L89:L104) -> 60.05792 | ... N105: =SUM(N89:N104) -> 105.58931
B107: ТЕКУЩИЕ РЕМОНТЫ — ТРУДОЗАТРАТЫ (по ресурсу)
B108: Наименование | C108: нормо-час/событие | D108: ресурс, м/ч | E108: год 1 | F108: год 2 | G108: год 3 | H108: год 4 | I108: год 5 | J108: год 6 | K108: год 7 | L108: год 8 | M108: год 9 | N108: год 10
B109: ENG (двигатель капремонт) | C109: 56 | D109: 15000 | E109: =(INT($E$25*1/$D109)-INT($E$25*(1-1)/$D109))*$C109 -> 0 | F109: =(INT($E$25*2/$D109)-INT($E$25*(2-1)/$D109))*$C109 -> 0 | G109: =(INT($E$25*3/$D109)-INT($E$25*(3-1)/$D109))*$C109 -> 56 | H109: =(INT($E$25*4/$D109)-INT($E$25*(4-1)/$D109))*$C109 -> 0 | I109: =(INT($E$25*5/$D109)-INT($E$25*(5-1)/$D109))*$C109 -> 56 | J109: =(INT($E$25*6/$D109)-INT($E$25*(6-1)/$D109))*$C109 -> 0 | K109: =(INT($E$25*7/$D109)-INT($E$25*(7-1)/$D109))*$C109 -> 56 | L109: =(INT($E$25*8/$D109)-INT($E$25*(8-1)/$D109))*$C109 -> 0 | M109: =(INT($E$25*9/$D109)-INT($E$25*(9-1)/$D109))*$C109 -> 56 | N109: =(INT($E$25*10/$D109)-INT($E$25*(10-1)/$D109))*$C109 -> 0
B110: AIREND Seal LP (Компрессор ремкомплект | C110: 4 | D110: 16000 | E110: =(INT($E$25*1/$D110)-INT($E$25*(1-1)/$D110))*$C110 -> 0 | F110: =(INT($E$25*2/$D110)-INT($E$25*(2-1)/$D110))*$C110 -> 0 | G110: =(INT($E$25*3/$D110)-INT($E$25*(3-1)/$D110))*$C110 -> 4 | H110: =(INT($E$25*4/$D110)-INT($E$25*(4-1)/$D110))*$C110 -> 0 | I110: =(INT($E$25*5/$D110)-INT($E$25*(5-1)/$D110))*$C110 -> 4 | J110: =(INT($E$25*6/$D110)-INT($E$25*(6-1)/$D110))*$C110 -> 0 | K110: =(INT($E$25*7/$D110)-INT($E$25*(7-1)/$D110))*$C110 -> 4 | L110: =(INT($E$25*8/$D110)-INT($E$25*(8-1)/$D110))*$C110 -> 0 | M110: =(INT($E$25*9/$D110)-INT($E$25*(9-1)/$D110))*$C110 -> 0 | N110: =(INT($E$25*10/$D110)-INT($E$25*(10-1)/$D110))*$C110 -> 4
B111: ROTARYHEAD (Ремкомплект вращателя | C111: 8 | D111: 13000 | E111: =(INT($E$25*1/$D111)-INT($E$25*(1-1)/$D111))*$C111 -> 0 | F111: =(INT($E$25*2/$D111)-INT($E$25*(2-1)/$D111))*$C111 -> 8 | G111: =(INT($E$25*3/$D111)-INT($E$25*(3-1)/$D111))*$C111 -> 0 | H111: =(INT($E$25*4/$D111)-INT($E$25*(4-1)/$D111))*$C111 -> 8 | I111: =(INT($E$25*5/$D111)-INT($E$25*(5-1)/$D111))*$C111 -> 0 | J111: =(INT($E$25*6/$D111)-INT($E$25*(6-1)/$D111))*$C111 -> 8 | K111: =(INT($E$25*7/$D111)-INT($E$25*(7-1)/$D111))*$C111 -> 0 | L111: =(INT($E$25*8/$D111)-INT($E$25*(8-1)/$D111))*$C111 -> 8 | M111: =(INT($E$25*9/$D111)-INT($E$25*(9-1)/$D111))*$C111 -> 0 | N111: =(INT($E$25*10/$D111)-INT($E$25*(10-1)/$D111))*$C111 -> 8
B112: KIT, SEAL (ремкомплект к цилиндру пода | C112: 36 | D112: 7450 | E112: =(INT($E$25*1/$D112)-INT($E$25*(1-1)/$D112))*$C112 -> 0 | F112: =(INT($E$25*2/$D112)-INT($E$25*(2-1)/$D112))*$C112 -> 36 | G112: =(INT($E$25*3/$D112)-INT($E$25*(3-1)/$D112))*$C112 -> 36 | H112: =(INT($E$25*4/$D112)-INT($E$25*(4-1)/$D112))*$C112 -> 36 | I112: =(INT($E$25*5/$D112)-INT($E$25*(5-1)/$D112))*$C112 -> 36 | J112: =(INT($E$25*6/$D112)-INT($E$25*(6-1)/$D112))*$C112 -> 36 | K112: =(INT($E$25*7/$D112)-INT($E$25*(7-1)/$D112))*$C112 -> 36 | L112: =(INT($E$25*8/$D112)-INT($E$25*(8-1)/$D112))*$C112 -> 36 | M112: =(INT($E$25*9/$D112)-INT($E$25*(9-1)/$D112))*$C112 -> 36 | N112: =(INT($E$25*10/$D112)-INT($E$25*(10-1)/$D112))*$C112 -> 36
B113: SEAL KIT,CYLINDER (ремкомплект к цил.д | C113: 72 | D113: 7450 | E113: =(INT($E$25*1/$D113)-INT($E$25*(1-1)/$D113))*$C113 -> 0 | F113: =(INT($E$25*2/$D113)-INT($E$25*(2-1)/$D113))*$C113 -> 72 | G113: =(INT($E$25*3/$D113)-INT($E$25*(3-1)/$D113))*$C113 -> 72 | H113: =(INT($E$25*4/$D113)-INT($E$25*(4-1)/$D113))*$C113 -> 72 | I113: =(INT($E$25*5/$D113)-INT($E$25*(5-1)/$D113))*$C113 -> 72 | J113: =(INT($E$25*6/$D113)-INT($E$25*(6-1)/$D113))*$C113 -> 72 | K113: =(INT($E$25*7/$D113)-INT($E$25*(7-1)/$D113))*$C113 -> 72 | L113: =(INT($E$25*8/$D113)-INT($E$25*(8-1)/$D113))*$C113 -> 72 | M113: =(INT($E$25*9/$D113)-INT($E$25*(9-1)/$D113))*$C113 -> 72 | N113: =(INT($E$25*10/$D113)-INT($E$25*(10-1)/$D113))*$C113 -> 72
B114: KIT, SEAL (ремкомплект к цилиндру п. м | C114: 28 | D114: 6000 | E114: =(INT($E$25*1/$D114)-INT($E$25*(1-1)/$D114))*$C114 -> 28 | F114: =(INT($E$25*2/$D114)-INT($E$25*(2-1)/$D114))*$C114 -> 28 | G114: =(INT($E$25*3/$D114)-INT($E$25*(3-1)/$D114))*$C114 -> 28 | H114: =(INT($E$25*4/$D114)-INT($E$25*(4-1)/$D114))*$C114 -> 28 | I114: =(INT($E$25*5/$D114)-INT($E$25*(5-1)/$D114))*$C114 -> 28 | J114: =(INT($E$25*6/$D114)-INT($E$25*(6-1)/$D114))*$C114 -> 56 | K114: =(INT($E$25*7/$D114)-INT($E$25*(7-1)/$D114))*$C114 -> 28 | L114: =(INT($E$25*8/$D114)-INT($E$25*(8-1)/$D114))*$C114 -> 28 | M114: =(INT($E$25*9/$D114)-INT($E$25*(9-1)/$D114))*$C114 -> 28 | N114: =(INT($E$25*10/$D114)-INT($E$25*(10-1)/$D114))*$C114 -> 28
B115: SEAL KIT (ремкомплектгидроцилиндр мех. | C115: 3.5 | D115: 6000 | E115: =(INT($E$25*1/$D115)-INT($E$25*(1-1)/$D115))*$C115 -> 3.5 | F115: =(INT($E$25*2/$D115)-INT($E$25*(2-1)/$D115))*$C115 -> 3.5 | G115: =(INT($E$25*3/$D115)-INT($E$25*(3-1)/$D115))*$C115 -> 3.5 | H115: =(INT($E$25*4/$D115)-INT($E$25*(4-1)/$D115))*$C115 -> 3.5 | I115: =(INT($E$25*5/$D115)-INT($E$25*(5-1)/$D115))*$C115 -> 3.5 | J115: =(INT($E$25*6/$D115)-INT($E$25*(6-1)/$D115))*$C115 -> 7 | K115: =(INT($E$25*7/$D115)-INT($E$25*(7-1)/$D115))*$C115 -> 3.5 | L115: =(INT($E$25*8/$D115)-INT($E$25*(8-1)/$D115))*$C115 -> 3.5 | M115: =(INT($E$25*9/$D115)-INT($E$25*(9-1)/$D115))*$C115 -> 3.5 | N115: =(INT($E$25*10/$D115)-INT($E$25*(10-1)/$D115))*$C115 -> 3.5
B116: KIT,SEAL (ремкомплект цилиндра ключа) | C116: 3.5 | D116: 4000 | E116: =(INT($E$25*1/$D116)-INT($E$25*(1-1)/$D116))*$C116 -> 3.5 | F116: =(INT($E$25*2/$D116)-INT($E$25*(2-1)/$D116))*$C116 -> 7 | G116: =(INT($E$25*3/$D116)-INT($E$25*(3-1)/$D116))*$C116 -> 7 | H116: =(INT($E$25*4/$D116)-INT($E$25*(4-1)/$D116))*$C116 -> 7 | I116: =(INT($E$25*5/$D116)-INT($E$25*(5-1)/$D116))*$C116 -> 3.5 | J116: =(INT($E$25*6/$D116)-INT($E$25*(6-1)/$D116))*$C116 -> 7 | K116: =(INT($E$25*7/$D116)-INT($E$25*(7-1)/$D116))*$C116 -> 7 | L116: =(INT($E$25*8/$D116)-INT($E$25*(8-1)/$D116))*$C116 -> 7 | M116: =(INT($E$25*9/$D116)-INT($E$25*(9-1)/$D116))*$C116 -> 3.5 | N116: =(INT($E$25*10/$D116)-INT($E$25*(10-1)/$D116))*$C116 -> 7
B117: SEAL KIT (ремкомплект цилиндра мех.зам | C117: 3.5 | D117: 4000 | E117: =(INT($E$25*1/$D117)-INT($E$25*(1-1)/$D117))*$C117 -> 3.5 | F117: =(INT($E$25*2/$D117)-INT($E$25*(2-1)/$D117))*$C117 -> 7 | G117: =(INT($E$25*3/$D117)-INT($E$25*(3-1)/$D117))*$C117 -> 7 | H117: =(INT($E$25*4/$D117)-INT($E$25*(4-1)/$D117))*$C117 -> 7 | I117: =(INT($E$25*5/$D117)-INT($E$25*(5-1)/$D117))*$C117 -> 3.5 | J117: =(INT($E$25*6/$D117)-INT($E$25*(6-1)/$D117))*$C117 -> 7 | K117: =(INT($E$25*7/$D117)-INT($E$25*(7-1)/$D117))*$C117 -> 7 | L117: =(INT($E$25*8/$D117)-INT($E$25*(8-1)/$D117))*$C117 -> 7 | M117: =(INT($E$25*9/$D117)-INT($E$25*(9-1)/$D117))*$C117 -> 3.5 | N117: =(INT($E$25*10/$D117)-INT($E$25*(10-1)/$D117))*$C117 -> 7
B118: SEAL KIT (ремкомплект к гидроцил.стопо | C118: 4 | D118: 5000 | E118: =(INT($E$25*1/$D118)-INT($E$25*(1-1)/$D118))*$C118 -> 4 | F118: =(INT($E$25*2/$D118)-INT($E$25*(2-1)/$D118))*$C118 -> 4 | G118: =(INT($E$25*3/$D118)-INT($E$25*(3-1)/$D118))*$C118 -> 8 | H118: =(INT($E$25*4/$D118)-INT($E$25*(4-1)/$D118))*$C118 -> 4 | I118: =(INT($E$25*5/$D118)-INT($E$25*(5-1)/$D118))*$C118 -> 8 | J118: =(INT($E$25*6/$D118)-INT($E$25*(6-1)/$D118))*$C118 -> 4 | K118: =(INT($E$25*7/$D118)-INT($E$25*(7-1)/$D118))*$C118 -> 4 | L118: =(INT($E$25*8/$D118)-INT($E$25*(8-1)/$D118))*$C118 -> 8 | M118: =(INT($E$25*9/$D118)-INT($E$25*(9-1)/$D118))*$C118 -> 4 | N118: =(INT($E$25*10/$D118)-INT($E$25*(10-1)/$D118))*$C118 -> 8
B119: SEAL KIT (ремкомплект гидроцил.фартука | C119: 0.9 | D119: 4000 | E119: =(INT($E$25*1/$D119)-INT($E$25*(1-1)/$D119))*$C119 -> 0.9 | F119: =(INT($E$25*2/$D119)-INT($E$25*(2-1)/$D119))*$C119 -> 1.8 | G119: =(INT($E$25*3/$D119)-INT($E$25*(3-1)/$D119))*$C119 -> 1.8 | H119: =(INT($E$25*4/$D119)-INT($E$25*(4-1)/$D119))*$C119 -> 1.8 | I119: =(INT($E$25*5/$D119)-INT($E$25*(5-1)/$D119))*$C119 -> 0.9 | J119: =(INT($E$25*6/$D119)-INT($E$25*(6-1)/$D119))*$C119 -> 1.8 | K119: =(INT($E$25*7/$D119)-INT($E$25*(7-1)/$D119))*$C119 -> 1.8 | L119: =(INT($E$25*8/$D119)-INT($E$25*(8-1)/$D119))*$C119 -> 1.8 | M119: =(INT($E$25*9/$D119)-INT($E$25*(9-1)/$D119))*$C119 -> 0.9 | N119: =(INT($E$25*10/$D119)-INT($E$25*(10-1)/$D119))*$C119 -> 1.8
B120: Ремонт системы смазки | C120: 2 | D120: 12000 | E120: =(INT($E$25*1/$D120)-INT($E$25*(1-1)/$D120))*$C120 -> 0 | F120: =(INT($E$25*2/$D120)-INT($E$25*(2-1)/$D120))*$C120 -> 2 | G120: =(INT($E$25*3/$D120)-INT($E$25*(3-1)/$D120))*$C120 -> 0 | H120: =(INT($E$25*4/$D120)-INT($E$25*(4-1)/$D120))*$C120 -> 2 | I120: =(INT($E$25*5/$D120)-INT($E$25*(5-1)/$D120))*$C120 -> 0 | J120: =(INT($E$25*6/$D120)-INT($E$25*(6-1)/$D120))*$C120 -> 2 | K120: =(INT($E$25*7/$D120)-INT($E$25*(7-1)/$D120))*$C120 -> 2 | L120: =(INT($E$25*8/$D120)-INT($E$25*(8-1)/$D120))*$C120 -> 0 | M120: =(INT($E$25*9/$D120)-INT($E$25*(9-1)/$D120))*$C120 -> 2 | N120: =(INT($E$25*10/$D120)-INT($E$25*(10-1)/$D120))*$C120 -> 0
... B124: Инспекция металлоконструкций | C124: 185 | D124: 65000 | E124: =(INT($E$25*1/$D124)-INT($E$25*(1-1)/$D124))*$C124 -> 0 | F124: =(INT($E$25*2/$D124)-INT($E$25*(2-1)/$D124))*$C124 -> 0 | G124: =(INT($E$25*3/$D124)-INT($E$25*(3-1)/$D124))*$C124 -> 0 | H124: =(INT($E$25*4/$D124)-INT($E$25*(4-1)/$D124))*$C124 -> 0 | I124: =(INT($E$25*5/$D124)-INT($E$25*(5-1)/$D124))*$C124 -> 0 | J124: =(INT($E$25*6/$D124)-INT($E$25*(6-1)/$D124))*$C124 -> 0 | K124: =(INT($E$25*7/$D124)-INT($E$25*(7-1)/$D124))*$C124 -> 0 | L124: =(INT($E$25*8/$D124)-INT($E$25*(8-1)/$D124))*$C124 -> 0 | M124: =(INT($E$25*9/$D124)-INT($E$25*(9-1)/$D124))*$C124 -> 0 | N124: =(INT($E$25*10/$D124)-INT($E$25*(10-1)/$D124))*$C124 -> 185
B125: ИТОГО | E125: =SUM(E109:E124) -> 48.4 | F125: =SUM(F109:F124) -> 174.3 | G125: =SUM(G109:G124) -> 228.3 | H125: =SUM(H109:H124) -> 174.3 | I125: =SUM(I109:I124) -> 220.4 | J125: =SUM(J109:J124) -> 255.8 | K125: =SUM(K109:K124) -> 226.3 | L125: =SUM(L109:L124) -> 176.3 | ... N125: =SUM(N109:N124) -> 365.3
B127: КАПИТАЛЬНЫЕ РЕМОНТЫ — ЗАТРАТЫ НА ЗЧ (по ресурсу до замены узла)
B128: Наименование | C128: стоим.замены,вал | D128: ресурс, м/ч | E128: год 1 | F128: год 2 | G128: год 3 | H128: год 4 | I128: год 5 | J128: год 6 | K128: год 7 | L128: год 8 | M128: год 9 | N128: год 10
B129: PUMP,P7,9A CONT (главный насос) | C129: 37124 | D129: 12000 | E129: =(INT($E$25*1/$D129)-INT($E$25*(1-1)/$D129))*$C129/1000 -> 0 | F129: =(INT($E$25*2/$D129)-INT($E$25*(2-1)/$D129))*$C129/1000 -> 37.124 | G129: =(INT($E$25*3/$D129)-INT($E$25*(3-1)/$D129))*$C129/1000 -> 0 | H129: =(INT($E$25*4/$D129)-INT($E$25*(4-1)/$D129))*$C129/1000 -> 37.124 | I129: =(INT($E$25*5/$D129)-INT($E$25*(5-1)/$D129))*$C129/1000 -> 0 | J129: =(INT($E$25*6/$D129)-INT($E$25*(6-1)/$D129))*$C129/1000 -> 37.124 | K129: =(INT($E$25*7/$D129)-INT($E$25*(7-1)/$D129))*$C129/1000 -> 37.124 | L129: =(INT($E$25*8/$D129)-INT($E$25*(8-1)/$D129))*$C129/1000 -> 0 | M129: =(INT($E$25*9/$D129)-INT($E$25*(9-1)/$D129))*$C129/1000 -> 37.124 | N129: =(INT($E$25*10/$D129)-INT($E$25*(10-1)/$D129))*$C129/1000 -> 0
B130: DRIVE SHAFT & BEARING (вал и подшипник | C130: 1226.17 | D130: 11000 | E130: =(INT($E$25*1/$D130)-INT($E$25*(1-1)/$D130))*$C130/1000 -> 0 | F130: =(INT($E$25*2/$D130)-INT($E$25*(2-1)/$D130))*$C130/1000 -> 1.22617 | G130: =(INT($E$25*3/$D130)-INT($E$25*(3-1)/$D130))*$C130/1000 -> 0 | H130: =(INT($E$25*4/$D130)-INT($E$25*(4-1)/$D130))*$C130/1000 -> 1.22617 | I130: =(INT($E$25*5/$D130)-INT($E$25*(5-1)/$D130))*$C130/1000 -> 1.22617 | J130: =(INT($E$25*6/$D130)-INT($E$25*(6-1)/$D130))*$C130/1000 -> 0 | K130: =(INT($E$25*7/$D130)-INT($E$25*(7-1)/$D130))*$C130/1000 -> 1.22617 | L130: =(INT($E$25*8/$D130)-INT($E$25*(8-1)/$D130))*$C130/1000 -> 1.22617 | M130: =(INT($E$25*9/$D130)-INT($E$25*(9-1)/$D130))*$C130/1000 -> 0 | N130: =(INT($E$25*10/$D130)-INT($E$25*(10-1)/$D130))*$C130/1000 -> 1.22617
B131: STROKER,9A ELECTROHYD (сервоприв.) | C131: 18096.84 | D131: 12000 | E131: =(INT($E$25*1/$D131)-INT($E$25*(1-1)/$D131))*$C131/1000 -> 0 | F131: =(INT($E$25*2/$D131)-INT($E$25*(2-1)/$D131))*$C131/1000 -> 18.09684 | G131: =(INT($E$25*3/$D131)-INT($E$25*(3-1)/$D131))*$C131/1000 -> 0 | H131: =(INT($E$25*4/$D131)-INT($E$25*(4-1)/$D131))*$C131/1000 -> 18.09684 | I131: =(INT($E$25*5/$D131)-INT($E$25*(5-1)/$D131))*$C131/1000 -> 0 | J131: =(INT($E$25*6/$D131)-INT($E$25*(6-1)/$D131))*$C131/1000 -> 18.09684 | K131: =(INT($E$25*7/$D131)-INT($E$25*(7-1)/$D131))*$C131/1000 -> 18.09684 | L131: =(INT($E$25*8/$D131)-INT($E$25*(8-1)/$D131))*$C131/1000 -> 0 | M131: =(INT($E$25*9/$D131)-INT($E$25*(9-1)/$D131))*$C131/1000 -> 18.09684 | N131: =(INT($E$25*10/$D131)-INT($E$25*(10-1)/$D131))*$C131/1000 -> 0
B132: PUMP,TRIPLE (лопастной насос) | C132: 6929.74 | D132: 8000 | E132: =(INT($E$25*1/$D132)-INT($E$25*(1-1)/$D132))*$C132/1000 -> 0 | F132: =(INT($E$25*2/$D132)-INT($E$25*(2-1)/$D132))*$C132/1000 -> 6.92974 | G132: =(INT($E$25*3/$D132)-INT($E$25*(3-1)/$D132))*$C132/1000 -> 6.92974 | H132: =(INT($E$25*4/$D132)-INT($E$25*(4-1)/$D132))*$C132/1000 -> 6.92974 | I132: =(INT($E$25*5/$D132)-INT($E$25*(5-1)/$D132))*$C132/1000 -> 6.92974 | J132: =(INT($E$25*6/$D132)-INT($E$25*(6-1)/$D132))*$C132/1000 -> 6.92974 | K132: =(INT($E$25*7/$D132)-INT($E$25*(7-1)/$D132))*$C132/1000 -> 6.92974 | L132: =(INT($E$25*8/$D132)-INT($E$25*(8-1)/$D132))*$C132/1000 -> 6.92974 | M132: =(INT($E$25*9/$D132)-INT($E$25*(9-1)/$D132))*$C132/1000 -> 0 | N132: =(INT($E$25*10/$D132)-INT($E$25*(10-1)/$D132))*$C132/1000 -> 6.92974
B133: VALVE,ASSEMBLY,6 SPOOL (сборка расп.кл | C133: 19766.43 | D133: 25000 | E133: =(INT($E$25*1/$D133)-INT($E$25*(1-1)/$D133))*$C133/1000 -> 0 | F133: =(INT($E$25*2/$D133)-INT($E$25*(2-1)/$D133))*$C133/1000 -> 0 | G133: =(INT($E$25*3/$D133)-INT($E$25*(3-1)/$D133))*$C133/1000 -> 0 | H133: =(INT($E$25*4/$D133)-INT($E$25*(4-1)/$D133))*$C133/1000 -> 19.76643 | I133: =(INT($E$25*5/$D133)-INT($E$25*(5-1)/$D133))*$C133/1000 -> 0 | J133: =(INT($E$25*6/$D133)-INT($E$25*(6-1)/$D133))*$C133/1000 -> 0 | K133: =(INT($E$25*7/$D133)-INT($E$25*(7-1)/$D133))*$C133/1000 -> 0 | L133: =(INT($E$25*8/$D133)-INT($E$25*(8-1)/$D133))*$C133/1000 -> 19.76643 | M133: =(INT($E$25*9/$D133)-INT($E$25*(9-1)/$D133))*$C133/1000 -> 0 | N133: =(INT($E$25*10/$D133)-INT($E$25*(10-1)/$D133))*$C133/1000 -> 0
...

Sheet Поставщик 4
B1: ДАННЫЕ ПОСТАВЩИКА — ВАРИАНТ 4 (ТО и Ремонты — модель по узлам)
B2: Жёлтое — ввод. Зелёное — авто (снизу вверх). ИТОГО ТОиР = (ЗЧ ТО + ЗЧ тек.+кап.ремонтов + сервис) × коэф.калибровки; тянется в «Данные по годам».
B4: Буровой станок: | E4: ='Ввод данных'!G7 -> Sunward SWDRT270B
B5: Валюта затрат ТОиР: | D5: EUR
B6: Показатель | C6: Ед. | E6: год 1 | F6: год 2 | G6: год 3 | H6: год 4 | I6: год 5 | J6: год 6 | K6: год 7 | L6: год 8 | M6: год 9 | N6: год 10
B7: СВОДКА ПО ГОДАМ (зелёное — авто снизу вверх; тянется в расчёт)
B8: Простои на ТО (авто из интервалов) | C8: ч/год | E8: =E40 -> 636.37233 | F8: =F40 -> 636.37233 | G8: =G40 -> 636.37233 | H8: =H40 -> 636.37233 | I8: =I40 -> 636.37233 | J8: =J40 -> 636.37233 | K8: =K40 -> 636.37233 | L8: =L40 -> 636.37233 | ... N8: =N40 -> 636.37233
B9: Простои в ремонтах (справочно) | C9: ч/год | E9: 109.67 | F9: 109.67 | G9: 109.67 | H9: 109.67 | I9: 109.67 | J9: 109.67 | K9: 109.67 | L9: 109.67 | M9: 109.67 | N9: 109.67
B10: Ежесменный осмотр (20 мин/смену), справочно | C10: ч/год | E10: =('Параметры'!C27-E8-E9)/'Параметры'!C28*20/60 -> 222.60994 | F10: =('Параметры'!C27-F8-F9)/'Параметры'!C28*20/60 -> 222.60994 | G10: =('Параметры'!C27-G8-G9)/'Параметры'!C28*20/60 -> 222.60994 | H10: =('Параметры'!C27-H8-H9)/'Параметры'!C28*20/60 -> 222.60994 | I10: =('Параметры'!C27-I8-I9)/'Параметры'!C28*20/60 -> 222.60994 | J10: =('Параметры'!C27-J8-J9)/'Параметры'!C28*20/60 -> 222.60994 | K10: =('Параметры'!C27-K8-K9)/'Параметры'!C28*20/60 -> 222.60994 | L10: =('Параметры'!C27-L8-L9)/'Параметры'!C28*20/60 -> 222.60994 | M10: =('Параметры'!C27-M8-M9)/'Параметры'!C28*20/60 -> 222.60994 | N10: =('Параметры'!C27-N8-N9)/'Параметры'!C28*20/60 -> 222.60994
B11: КТГ (техготовность, ВВОД) → «Данные по годам» | C11: коэф. | E11: 0.93 | F11: 0.93 | G11: 0.92 | H11: 0.92 | I11: 0.87 | J11: 0.9 | K11: 0.85 | L11: 0.9 | M11: 0.9 | N11: 0.85
B12: Затраты на ЗЧ ТО (авто из каталога) | C12: тыс.вал/г | E12: =E85 -> 136.07379 | F12: =F85 -> 136.07379 | G12: =G85 -> 136.07379 | H12: =H85 -> 136.07379 | I12: =I85 -> 136.07379 | J12: =J85 -> 136.07379 | K12: =K85 -> 136.07379 | L12: =L85 -> 136.07379 | ... N12: =N85 -> 136.07379
B13: Затраты на ЗЧ текущих ремонтов (по ресурсу) | C13: тыс.вал/г | E13: =E105 -> 4.50682 | F13: =F105 -> 60.10984 | G13: =G105 -> 145.1624 | H13: =H105 -> 60.10984 | I13: =I105 -> 144.82518 | J13: =J105 -> 67.22701 | K13: =K105 -> 145.21432 | L13: =L105 -> 60.05792 | ... N13: =N105 -> 105.58931
B14: Затраты на ЗЧ капремонтов (по ресурсу) | C14: тыс.вал/г | E14: =E188 -> 7.38238 | F14: =F188 -> 204.26495 | G14: =G188 -> 438.81584 | H14: =H188 -> 434.86339 | I14: =I188 -> 610.36746 | J14: =J188 -> 366.36175 | K14: =K188 -> 590.25823 | L14: =L188 -> 224.66392 | ... N14: =N188 -> 283.30237
B15: Трудозатраты ТО (авто) | C15: ч-час/г | E15: =E47 -> 636.37233 | F15: =F47 -> 636.37233 | G15: =G47 -> 636.37233 | H15: =H47 -> 636.37233 | I15: =I47 -> 636.37233 | J15: =J47 -> 636.37233 | K15: =K47 -> 636.37233 | L15: =L47 -> 636.37233 | ... N15: =N47 -> 636.37233
B16: Трудозатраты текущих ремонтов (авто) | C16: ч-час/г | E16: =E125 -> 48.4 | F16: =F125 -> 174.3 | G16: =G125 -> 228.3 | H16: =H125 -> 174.3 | I16: =I125 -> 220.4 | J16: =J125 -> 255.8 | K16: =K125 -> 226.3 | L16: =L125 -> 176.3 | ... N16: =N125 -> 365.3
B17: Трудозатраты капремонтов (авто) | C17: ч-час/г | E17: =E251 -> 36.6 | F17: =F251 -> 192.66 | G17: =G251 -> 330.45 | H17: =H251 -> 188.56 | I17: =I251 -> 267.75 | J17: =J251 -> 319.96 | K17: =K251 -> 300.71 | L17: =L251 -> 155.4 | ... N17: =N251 -> 102.4
B18: Сервис (трудозатраты ТО+ТР+КР) | C18: тыс.вал/г | E18: =(E15+E16+E17)*$E$23/1000 -> 41.762927 | F18: =(F15+F16+F17)*$E$23/1000 -> 58.086639 | G18: =(G15+G16+G17)*$E$23/1000 -> 69.190076 | H18: =(H15+H16+H17)*$E$23/1000 -> 57.849275 | I18: =(I15+I16+I17)*$E$23/1000 -> 65.102779 | J18: =(J15+J16+J17)*$E$23/1000 -> 70.174848 | K18: =(K15+K16+K17)*$E$23/1000 -> 67.352529 | L18: =(L15+L16+L17)*$E$23/1000 -> 56.045307 | ... N18: =(N15+N16+N17)*$E$23/1000 -> 63.918853
B19: Коэффициент калибровки ИТОГО под ТКП | C19: коэф. | E19: 1.2133
B20: ИТОГО ТОиР → «Данные по годам» | C20: тыс.вал/г | E20: =(E12+E13+E14+E18)*$E$19 -> 230.19445 | F20: =(F12+F13+F14+F18)*$E$19 -> 556.34078 | G20: =(G12+G13+G14+G18)*$E$19 -> 957.58744 | H20: =(H12+H13+H14+H18)*$E$19 -> 835.83787 | I20: =(I12+I13+I14+I18)*$E$19 -> 1160.3628 | J20: =(J12+J13+J14+J18)*$E$19 -> 776.31471 | K20: =(K12+K13+K14+K18)*$E$19 -> 1139.166 | L20: =(L12+L13+L14+L18)*$E$19 -> 578.55111 | ... N20: =(N12+N13+N14+N18)*$E$19 -> 714.49335
B21: Удельный расход ДТ / энергии | C21: кг(кВт)/час | E21: 76.87 | F21: 76.87 | G21: 76.87 | H21: 76.87 | I21: 76.87 | J21: 76.87 | K21: 76.87 | L21: 76.87 | M21: 76.87 | N21: 76.87
B23: Ставка сервиса | C23: вал/ч·час | E23: 57.893718
B24: РАСЧЁТ ТО (по интервалам обслуживания), ПО ГОДАМ
B25: Наработка по годам | C25: м/час | E25: 7000 | F25: 7000 | G25: 7000 | H25: 7000 | I25: 7000 | J25: 7000 | K25: 7000 | L25: 7000 | M25: 7000 | N25: 7000
B26: Вид ТО | C26: интервал, м/ч | D26: простой/ТО, ч | E26: персонал
B27: ТО-1 | C27: 250 | D27: 10.9 | E27: 1
B28: ТО-2 | C28: 500 | D28: 13.5 | E28: 1
B29: ТО-3 | C29: 1000 | D29: 12.43 | E29: 1
B30: ТО-4 | C30: 2000 | D30: 5.67 | E30: 1
B31: ТО-5 | C31: 3000 | D31: 10.06 | E31: 1
B32: ТО-6 | C32: 5000 | D32: 8.46 | E32: 1
B34: ТО-1: простои, ч/год | C34: ч | E34: =E$25/$C27*$D27 -> 305.2 | F34: =F$25/$C27*$D27 -> 305.2 | G34: =G$25/$C27*$D27 -> 305.2 | H34: =H$25/$C27*$D27 -> 305.2 | I34: =I$25/$C27*$D27 -> 305.2 | J34: =J$25/$C27*$D27 -> 305.2 | K34: =K$25/$C27*$D27 -> 305.2 | L34: =L$25/$C27*$D27 -> 305.2 | ... N34: =N$25/$C27*$D27 -> 305.2
B35: ТО-2: простои, ч/год | C35: ч | E35: =E$25/$C28*$D28 -> 189 | F35: =F$25/$C28*$D28 -> 189 | G35: =G$25/$C28*$D28 -> 189 | H35: =H$25/$C28*$D28 -> 189 | I35: =I$25/$C28*$D28 -> 189 | J35: =J$25/$C28*$D28 -> 189 | K35: =K$25/$C28*$D28 -> 189 | L35: =L$25/$C28*$D28 -> 189 | ... N35: =N$25/$C28*$D28 -> 189
B36: ТО-3: простои, ч/год | C36: ч | E36: =E$25/$C29*$D29 -> 87.01 | F36: =F$25/$C29*$D29 -> 87.01 | G36: =G$25/$C29*$D29 -> 87.01 | H36: =H$25/$C29*$D29 -> 87.01 | I36: =I$25/$C29*$D29 -> 87.01 | J36: =J$25/$C29*$D29 -> 87.01 | K36: =K$25/$C29*$D29 -> 87.01 | L36: =L$25/$C29*$D29 -> 87.01 | ... N36: =N$25/$C29*$D29 -> 87.01
B37: ТО-4: простои, ч/год | C37: ч | E37: =E$25/$C30*$D30 -> 19.845 | F37: =F$25/$C30*$D30 -> 19.845 | G37: =G$25/$C30*$D30 -> 19.845 | H37: =H$25/$C30*$D30 -> 19.845 | I37: =I$25/$C30*$D30 -> 19.845 | J37: =J$25/$C30*$D30 -> 19.845 | K37: =K$25/$C30*$D30 -> 19.845 | L37: =L$25/$C30*$D30 -> 19.845 | ... N37: =N$25/$C30*$D30 -> 19.845
B38: ТО-5: простои, ч/год | C38: ч | E38: =E$25/$C31*$D31 -> 23.473333 | F38: =F$25/$C31*$D31 -> 23.473333 | G38: =G$25/$C31*$D31 -> 23.473333 | H38: =H$25/$C31*$D31 -> 23.473333 | I38: =I$25/$C31*$D31 -> 23.473333 | J38: =J$25/$C31*$D31 -> 23.473333 | K38: =K$25/$C31*$D31 -> 23.473333 | L38: =L$25/$C31*$D31 -> 23.473333 | ... N38: =N$25/$C31*$D31 -> 23.473333
B39: ТО-6: простои, ч/год | C39: ч | E39: =E$25/$C32*$D32 -> 11.844 | F39: =F$25/$C32*$D32 -> 11.844 | G39: =G$25/$C32*$D32 -> 11.844 | H39: =H$25/$C32*$D32 -> 11.844 | I39: =I$25/$C32*$D32 -> 11.844 | J39: =J$25/$C32*$D32 -> 11.844 | K39: =K$25/$C32*$D32 -> 11.844 | L39: =L$25/$C32*$D32 -> 11.844 | ... N39: =N$25/$C32*$D32 -> 11.844
B40: Итого простои ТО | E40: =SUM(E34:E39) -> 636.37233 | F40: =SUM(F34:F39) -> 636.37233 | G40: =SUM(G34:G39) -> 636.37233 | H40: =SUM(H34:H39) -> 636.37233 | I40: =SUM(I34:I39) -> 636.37233 | J40: =SUM(J34:J39) -> 636.37233 | K40: =SUM(K34:K39) -> 636.37233 | L40: =SUM(L34:L39) -> 636.37233 | ... N40: =SUM(N34:N39) -> 636.37233
B41: ТО-1: чел-часы/год | C41: ч-час | E41: =E34*$E27 -> 305.2 | F41: =F34*$E27 -> 305.2 | G41: =G34*$E27 -> 305.2 | H41: =H34*$E27 -> 305.2 | I41: =I34*$E27 -> 305.2 | J41: =J34*$E27 -> 305.2 | K41: =K34*$E27 -> 305.2 | L41: =L34*$E27 -> 305.2 | ... N41: =N34*$E27 -> 305.2
B42: ТО-2: чел-часы/год | C42: ч-час | E42: =E35*$E28 -> 189 | F42: =F35*$E28 -> 189 | G42: =G35*$E28 -> 189 | H42: =H35*$E28 -> 189 | I42: =I35*$E28 -> 189 | J42: =J35*$E28 -> 189 | K42: =K35*$E28 -> 189 | L42: =L35*$E28 -> 189 | ... N42: =N35*$E28 -> 189
B43: ТО-3: чел-часы/год | C43: ч-час | E43: =E36*$E29 -> 87.01 | F43: =F36*$E29 -> 87.01 | G43: =G36*$E29 -> 87.01 | H43: =H36*$E29 -> 87.01 | I43: =I36*$E29 -> 87.01 | J43: =J36*$E29 -> 87.01 | K43: =K36*$E29 -> 87.01 | L43: =L36*$E29 -> 87.01 | ... N43: =N36*$E29 -> 87.01
B44: ТО-4: чел-часы/год | C44: ч-час | E44: =E37*$E30 -> 19.845 | F44: =F37*$E30 -> 19.845 | G44: =G37*$E30 -> 19.845 | H44: =H37*$E30 -> 19.845 | I44: =I37*$E30 -> 19.845 | J44: =J37*$E30 -> 19.845 | K44: =K37*$E30 -> 19.845 | L44: =L37*$E30 -> 19.845 | ... N44: =N37*$E30 -> 19.845
B45: ТО-5: чел-часы/год | C45: ч-час | E45: =E38*$E31 -> 23.473333 | F45: =F38*$E31 -> 23.473333 | G45: =G38*$E31 -> 23.473333 | H45: =H38*$E31 -> 23.473333 | I45: =I38*$E31 -> 23.473333 | J45: =J38*$E31 -> 23.473333 | K45: =K38*$E31 -> 23.473333 | L45: =L38*$E31 -> 23.473333 | ... N45: =N38*$E31 -> 23.473333
B46: ТО-6: чел-часы/год | C46: ч-час | E46: =E39*$E32 -> 11.844 | F46: =F39*$E32 -> 11.844 | G46: =G39*$E32 -> 11.844 | H46: =H39*$E32 -> 11.844 | I46: =I39*$E32 -> 11.844 | J46: =J39*$E32 -> 11.844 | K46: =K39*$E32 -> 11.844 | L46: =L39*$E32 -> 11.844 | ... N46: =N39*$E32 -> 11.844
B47: Итого чел-часы ТО | E47: =SUM(E41:E46) -> 636.37233 | F47: =SUM(F41:F46) -> 636.37233 | G47: =SUM(G41:G46) -> 636.37233 | H47: =SUM(H41:H46) -> 636.37233 | I47: =SUM(I41:I46) -> 636.37233 | J47: =SUM(J41:J46) -> 636.37233 | K47: =SUM(K41:K46) -> 636.37233 | L47: =SUM(L41:L46) -> 636.37233 | ... N47: =SUM(N41:N46) -> 636.37233
B49: КАТАЛОГ ЗАПЧАСТЕЙ ТО (заполняет подрядчик), ПО ГОДАМ
B50: Наименование | C50: цена за ед | D50: кол-во/ТО | P50: № ТО
B51: Моторное масло | C51: 6.77 | D51: 70 | E51: =E$25/INDEX($C$27:$C$32,$P51)*D51*C51/1000 -> 13.2692 | F51: =F$25/INDEX($C$27:$C$32,$P51)*D51*C51/1000 -> 13.2692 | G51: =G$25/INDEX($C$27:$C$32,$P51)*D51*C51/1000 -> 13.2692 | H51: =H$25/INDEX($C$27:$C$32,$P51)*D51*C51/1000 -> 13.2692 | I51: =I$25/INDEX($C$27:$C$32,$P51)*D51*C51/1000 -> 13.2692 | J51: =J$25/INDEX($C$27:$C$32,$P51)*D51*C51/1000 -> 13.2692 | K51: =K$25/INDEX($C$27:$C$32,$P51)*D51*C51/1000 -> 13.2692 | L51: =L$25/INDEX($C$27:$C$32,$P51)*D51*C51/1000 -> 13.2692 | M51: =M$25/INDEX($C$27:$C$32,$P51)*D51*C51/1000 -> 13.2692 | N51: =N$25/INDEX($C$27:$C$32,$P51)*D51*C51/1000 -> 13.2692 | P51: 1
B52: Масляный фильтр двигателя | C52: 75.788 | D52: 2 | E52: =E$25/INDEX($C$27:$C$32,$P52)*D52*C52/1000 -> 4.244128 | F52: =F$25/INDEX($C$27:$C$32,$P52)*D52*C52/1000 -> 4.244128 | G52: =G$25/INDEX($C$27:$C$32,$P52)*D52*C52/1000 -> 4.244128 | H52: =H$25/INDEX($C$27:$C$32,$P52)*D52*C52/1000 -> 4.244128 | I52: =I$25/INDEX($C$27:$C$32,$P52)*D52*C52/1000 -> 4.244128 | J52: =J$25/INDEX($C$27:$C$32,$P52)*D52*C52/1000 -> 4.244128 | K52: =K$25/INDEX($C$27:$C$32,$P52)*D52*C52/1000 -> 4.244128 | L52: =L$25/INDEX($C$27:$C$32,$P52)*D52*C52/1000 -> 4.244128 | M52: =M$25/INDEX($C$27:$C$32,$P52)*D52*C52/1000 -> 4.244128 | N52: =N$25/INDEX($C$27:$C$32,$P52)*D52*C52/1000 -> 4.244128 | P52: 1
B53: Охлаждающая жидкость | C53: 4.368 | D53: 3 | E53: =E$25/INDEX($C$27:$C$32,$P53)*D53*C53/1000 -> 0.366912 | F53: =F$25/INDEX($C$27:$C$32,$P53)*D53*C53/1000 -> 0.366912 | G53: =G$25/INDEX($C$27:$C$32,$P53)*D53*C53/1000 -> 0.366912 | H53: =H$25/INDEX($C$27:$C$32,$P53)*D53*C53/1000 -> 0.366912 | I53: =I$25/INDEX($C$27:$C$32,$P53)*D53*C53/1000 -> 0.366912 | J53: =J$25/INDEX($C$27:$C$32,$P53)*D53*C53/1000 -> 0.366912 | K53: =K$25/INDEX($C$27:$C$32,$P53)*D53*C53/1000 -> 0.366912 | L53: =L$25/INDEX($C$27:$C$32,$P53)*D53*C53/1000 -> 0.366912 | M53: =M$25/INDEX($C$27:$C$32,$P53)*D53*C53/1000 -> 0.366912 | N53: =N$25/INDEX($C$27:$C$32,$P53)*D53*C53/1000 -> 0.366912 | P53: 1
B54: Воздушный фильтр первичный | C54: 51.588 | D54: 3 | E54: =E$25/INDEX($C$27:$C$32,$P54)*D54*C54/1000 -> 4.333392 | F54: =F$25/INDEX($C$27:$C$32,$P54)*D54*C54/1000 -> 4.333392 | G54: =G$25/INDEX($C$27:$C$32,$P54)*D54*C54/1000 -> 4.333392 | H54: =H$25/INDEX($C$27:$C$32,$P54)*D54*C54/1000 -> 4.333392 | I54: =I$25/INDEX($C$27:$C$32,$P54)*D54*C54/1000 -> 4.333392 | J54: =J$25/INDEX($C$27:$C$32,$P54)*D54*C54/1000 -> 4.333392 | K54: =K$25/INDEX($C$27:$C$32,$P54)*D54*C54/1000 -> 4.333392 | L54: =L$25/INDEX($C$27:$C$32,$P54)*D54*C54/1000 -> 4.333392 | M54: =M$25/INDEX($C$27:$C$32,$P54)*D54*C54/1000 -> 4.333392 | N54: =N$25/INDEX($C$27:$C$32,$P54)*D54*C54/1000 -> 4.333392 | P54: 1
B55: Воздушный фильтр вторичный | C55: 37.65 | D55: 3 | E55: =E$25/INDEX($C$27:$C$32,$P55)*D55*C55/1000 -> 3.1626 | F55: =F$25/INDEX($C$27:$C$32,$P55)*D55*C55/1000 -> 3.1626 | G55: =G$25/INDEX($C$27:$C$32,$P55)*D55*C55/1000 -> 3.1626 | H55: =H$25/INDEX($C$27:$C$32,$P55)*D55*C55/1000 -> 3.1626 | I55: =I$25/INDEX($C$27:$C$32,$P55)*D55*C55/1000 -> 3.1626 | J55: =J$25/INDEX($C$27:$C$32,$P55)*D55*C55/1000 -> 3.1626 | K55: =K$25/INDEX($C$27:$C$32,$P55)*D55*C55/1000 -> 3.1626 | L55: =L$25/INDEX($C$27:$C$32,$P55)*D55*C55/1000 -> 3.1626 | M55: =M$25/INDEX($C$27:$C$32,$P55)*D55*C55/1000 -> 3.1626 | N55: =N$25/INDEX($C$27:$C$32,$P55)*D55*C55/1000 -> 3.1626 | P55: 1
B56: Фильтр системы охл. ДВС | C56: 27.113 | D56: 2 | E56: =E$25/INDEX($C$27:$C$32,$P56)*D56*C56/1000 -> 1.518328 | F56: =F$25/INDEX($C$27:$C$32,$P56)*D56*C56/1000 -> 1.518328 | G56: =G$25/INDEX($C$27:$C$32,$P56)*D56*C56/1000 -> 1.518328 | H56: =H$25/INDEX($C$27:$C$32,$P56)*D56*C56/1000 -> 1.518328 | I56: =I$25/INDEX($C$27:$C$32,$P56)*D56*C56/1000 -> 1.518328 | J56: =J$25/INDEX($C$27:$C$32,$P56)*D56*C56/1000 -> 1.518328 | K56: =K$25/INDEX($C$27:$C$32,$P56)*D56*C56/1000 -> 1.518328 | L56: =L$25/INDEX($C$27:$C$32,$P56)*D56*C56/1000 -> 1.518328 | M56: =M$25/INDEX($C$27:$C$32,$P56)*D56*C56/1000 -> 1.518328 | N56: =N$25/INDEX($C$27:$C$32,$P56)*D56*C56/1000 -> 1.518328 | P56: 1
B57: Топливный фильтр первичный | C57: 65.662 | D57: 1 | E57: =E$25/INDEX($C$27:$C$32,$P57)*D57*C57/1000 -> 1.838536 | F57: =F$25/INDEX($C$27:$C$32,$P57)*D57*C57/1000 -> 1.838536 | G57: =G$25/INDEX($C$27:$C$32,$P57)*D57*C57/1000 -> 1.838536 | H57: =H$25/INDEX($C$27:$C$32,$P57)*D57*C57/1000 -> 1.838536 | I57: =I$25/INDEX($C$27:$C$32,$P57)*D57*C57/1000 -> 1.838536 | J57: =J$25/INDEX($C$27:$C$32,$P57)*D57*C57/1000 -> 1.838536 | K57: =K$25/INDEX($C$27:$C$32,$P57)*D57*C57/1000 -> 1.838536 | L57: =L$25/INDEX($C$27:$C$32,$P57)*D57*C57/1000 -> 1.838536 | M57: =M$25/INDEX($C$27:$C$32,$P57)*D57*C57/1000 -> 1.838536 | N57: =N$25/INDEX($C$27:$C$32,$P57)*D57*C57/1000 -> 1.838536 | P57: 1
B58: Топливный фильтр вторичный | C58: 127.662 | D58: 1 | E58: =E$25/INDEX($C$27:$C$32,$P58)*D58*C58/1000 -> 3.574536 | F58: =F$25/INDEX($C$27:$C$32,$P58)*D58*C58/1000 -> 3.574536 | G58: =G$25/INDEX($C$27:$C$32,$P58)*D58*C58/1000 -> 3.574536 | H58: =H$25/INDEX($C$27:$C$32,$P58)*D58*C58/1000 -> 3.574536 | I58: =I$25/INDEX($C$27:$C$32,$P58)*D58*C58/1000 -> 3.574536 | J58: =J$25/INDEX($C$27:$C$32,$P58)*D58*C58/1000 -> 3.574536 | K58: =K$25/INDEX($C$27:$C$32,$P58)*D58*C58/1000 -> 3.574536 | L58: =L$25/INDEX($C$27:$C$32,$P58)*D58*C58/1000 -> 3.574536 | M58: =M$25/INDEX($C$27:$C$32,$P58)*D58*C58/1000 -> 3.574536 | N58: =N$25/INDEX($C$27:$C$32,$P58)*D58*C58/1000 -> 3.574536 | P58: 1
B59: Влагоотделитель | C59: 14.612 | D59: 2 | E59: =E$25/INDEX($C$27:$C$32,$P59)*D59*C59/1000 -> 0.818272 | F59: =F$25/INDEX($C$27:$C$32,$P59)*D59*C59/1000 -> 0.818272 | G59: =G$25/INDEX($C$27:$C$32,$P59)*D59*C59/1000 -> 0.818272 | H59: =H$25/INDEX($C$27:$C$32,$P59)*D59*C59/1000 -> 0.818272 | I59: =I$25/INDEX($C$27:$C$32,$P59)*D59*C59/1000 -> 0.818272 | J59: =J$25/INDEX($C$27:$C$32,$P59)*D59*C59/1000 -> 0.818272 | K59: =K$25/INDEX($C$27:$C$32,$P59)*D59*C59/1000 -> 0.818272 | L59: =L$25/INDEX($C$27:$C$32,$P59)*D59*C59/1000 -> 0.818272 | M59: =M$25/INDEX($C$27:$C$32,$P59)*D59*C59/1000 -> 0.818272 | N59: =N$25/INDEX($C$27:$C$32,$P59)*D59*C59/1000 -> 0.818272 | P59: 1
B60: Консистентная смазка | C60: 10.752 | D60: 2 | E60: =E$25/INDEX($C$27:$C$32,$P60)*D60*C60/1000 -> 0.602112 | F60: =F$25/INDEX($C$27:$C$32,$P60)*D60*C60/1000 -> 0.602112 | G60: =G$25/INDEX($C$27:$C$32,$P60)*D60*C60/1000 -> 0.602112 | H60: =H$25/INDEX($C$27:$C$32,$P60)*D60*C60/1000 -> 0.602112 | I60: =I$25/INDEX($C$27:$C$32,$P60)*D60*C60/1000 -> 0.602112 | J60: =J$25/INDEX($C$27:$C$32,$P60)*D60*C60/1000 -> 0.602112 | K60: =K$25/INDEX($C$27:$C$32,$P60)*D60*C60/1000 -> 0.602112 | L60: =L$25/INDEX($C$27:$C$32,$P60)*D60*C60/1000 -> 0.602112 | M60: =M$25/INDEX($C$27:$C$32,$P60)*D60*C60/1000 -> 0.602112 | N60: =N$25/INDEX($C$27:$C$32,$P60)*D60*C60/1000 -> 0.602112 | P60: 1
B61: Сапун гидробака | C61: 18.025 | D61: 2 | E61: =E$25/INDEX($C$27:$C$32,$P61)*D61*C61/1000 -> 0.5047 | F61: =F$25/INDEX($C$27:$C$32,$P61)*D61*C61/1000 -> 0.5047 | G61: =G$25/INDEX($C$27:$C$32,$P61)*D61*C61/1000 -> 0.5047 | H61: =H$25/INDEX($C$27:$C$32,$P61)*D61*C61/1000 -> 0.5047 | I61: =I$25/INDEX($C$27:$C$32,$P61)*D61*C61/1000 -> 0.5047 | J61: =J$25/INDEX($C$27:$C$32,$P61)*D61*C61/1000 -> 0.5047 | K61: =K$25/INDEX($C$27:$C$32,$P61)*D61*C61/1000 -> 0.5047 | L61: =L$25/INDEX($C$27:$C$32,$P61)*D61*C61/1000 -> 0.5047 | M61: =M$25/INDEX($C$27:$C$32,$P61)*D61*C61/1000 -> 0.5047 | N61: =N$25/INDEX($C$27:$C$32,$P61)*D61*C61/1000 -> 0.5047 | P61: 2
B62: Фильтра системы пылеподавления | C62: 58.9 | D62: 9 | E62: =E$25/INDEX($C$27:$C$32,$P62)*D62*C62/1000 -> 7.4214 | F62: =F$25/INDEX($C$27:$C$32,$P62)*D62*C62/1000 -> 7.4214 | G62: =G$25/INDEX($C$27:$C$32,$P62)*D62*C62/1000 -> 7.4214 | H62: =H$25/INDEX($C$27:$C$32,$P62)*D62*C62/1000 -> 7.4214 | I62: =I$25/INDEX($C$27:$C$32,$P62)*D62*C62/1000 -> 7.4214 | J62: =J$25/INDEX($C$27:$C$32,$P62)*D62*C62/1000 -> 7.4214 | K62: =K$25/INDEX($C$27:$C$32,$P62)*D62*C62/1000 -> 7.4214 | L62: =L$25/INDEX($C$27:$C$32,$P62)*D62*C62/1000 -> 7.4214 | M62: =M$25/INDEX($C$27:$C$32,$P62)*D62*C62/1000 -> 7.4214 | N62: =N$25/INDEX($C$27:$C$32,$P62)*D62*C62/1000 -> 7.4214 | P62: 2
... B83: Охлаждающая жидкость | C83: 3.122 | D83: 190 | E83: =E$25/INDEX($C$27:$C$32,$P83)*D83*C83/1000 -> 0.830452 | F83: =F$25/INDEX($C$27:$C$32,$P83)*D83*C83/1000 -> 0.830452 | G83: =G$25/INDEX($C$27:$C$32,$P83)*D83*C83/1000 -> 0.830452 | H83: =H$25/INDEX($C$27:$C$32,$P83)*D83*C83/1000 -> 0.830452 | I83: =I$25/INDEX($C$27:$C$32,$P83)*D83*C83/1000 -> 0.830452 | J83: =J$25/INDEX($C$27:$C$32,$P83)*D83*C83/1000 -> 0.830452 | K83: =K$25/INDEX($C$27:$C$32,$P83)*D83*C83/1000 -> 0.830452 | L83: =L$25/INDEX($C$27:$C$32,$P83)*D83*C83/1000 -> 0.830452 | M83: =M$25/INDEX($C$27:$C$32,$P83)*D83*C83/1000 -> 0.830452 | N83: =N$25/INDEX($C$27:$C$32,$P83)*D83*C83/1000 -> 0.830452 | P83: 6
B84: Корректировка (прочее) | E84: 0 | F84: 0 | G84: 0 | H84: 0 | I84: 0 | J84: 0 | K84: 0 | L84: 0 | M84: 0 | N84: 0
B85: ИТОГО ЗЧ ТО, тыс.вал/год | E85: =SUM(E51:E84) -> 136.07379 | F85: =SUM(F51:F84) -> 136.07379 | G85: =SUM(G51:G84) -> 136.07379 | H85: =SUM(H51:H84) -> 136.07379 | I85: =SUM(I51:I84) -> 136.07379 | J85: =SUM(J51:J84) -> 136.07379 | K85: =SUM(K51:K84) -> 136.07379 | L85: =SUM(L51:L84) -> 136.07379 | ... N85: =SUM(N51:N84) -> 136.07379
B87: ТЕКУЩИЕ РЕМОНТЫ — ЗАТРАТЫ НА ЗЧ (по ресурсу)
B88: Наименование | C88: стоим.замены,вал | D88: ресурс, м/ч | E88: год 1 | F88: год 2 | G88: год 3 | H88: год 4 | I88: год 5 | J88: год 6 | K88: год 7 | L88: год 8 | M88: год 9 | N88: год 10
B89: ENG (двигатель капремонт) | C89: 98848.48 | D89: 15000 | E89: =(INT($E$25*1/$D89)-INT($E$25*(1-1)/$D89))*$C89/1000 -> 0 | F89: =(INT($E$25*2/$D89)-INT($E$25*(2-1)/$D89))*$C89/1000 -> 0 | G89: =(INT($E$25*3/$D89)-INT($E$25*(3-1)/$D89))*$C89/1000 -> 98.84848 | H89: =(INT($E$25*4/$D89)-INT($E$25*(4-1)/$D89))*$C89/1000 -> 0 | I89: =(INT($E$25*5/$D89)-INT($E$25*(5-1)/$D89))*$C89/1000 -> 98.84848 | J89: =(INT($E$25*6/$D89)-INT($E$25*(6-1)/$D89))*$C89/1000 -> 0 | K89: =(INT($E$25*7/$D89)-INT($E$25*(7-1)/$D89))*$C89/1000 -> 98.84848 | L89: =(INT($E$25*8/$D89)-INT($E$25*(8-1)/$D89))*$C89/1000 -> 0 | M89: =(INT($E$25*9/$D89)-INT($E$25*(9-1)/$D89))*$C89/1000 -> 98.84848 | N89: =(INT($E$25*10/$D89)-INT($E$25*(10-1)/$D89))*$C89/1000 -> 0
B90: AIREND Seal LP (Компрессор ремкомплект | C90: 32894 | D90: 16000 | E90: =(INT($E$25*1/$D90)-INT($E$25*(1-1)/$D90))*$C90/1000 -> 0 | F90: =(INT($E$25*2/$D90)-INT($E$25*(2-1)/$D90))*$C90/1000 -> 0 | G90: =(INT($E$25*3/$D90)-INT($E$25*(3-1)/$D90))*$C90/1000 -> 32.894 | H90: =(INT($E$25*4/$D90)-INT($E$25*(4-1)/$D90))*$C90/1000 -> 0 | I90: =(INT($E$25*5/$D90)-INT($E$25*(5-1)/$D90))*$C90/1000 -> 32.894 | J90: =(INT($E$25*6/$D90)-INT($E$25*(6-1)/$D90))*$C90/1000 -> 0 | K90: =(INT($E$25*7/$D90)-INT($E$25*(7-1)/$D90))*$C90/1000 -> 32.894 | L90: =(INT($E$25*8/$D90)-INT($E$25*(8-1)/$D90))*$C90/1000 -> 0 | M90: =(INT($E$25*9/$D90)-INT($E$25*(9-1)/$D90))*$C90/1000 -> 0 | N90: =(INT($E$25*10/$D90)-INT($E$25*(10-1)/$D90))*$C90/1000 -> 32.894
B91: ROTARYHEAD (Ремкомплект вращателя | C91: 46638 | D91: 13000 | E91: =(INT($E$25*1/$D91)-INT($E$25*(1-1)/$D91))*$C91/1000 -> 0 | F91: =(INT($E$25*2/$D91)-INT($E$25*(2-1)/$D91))*$C91/1000 -> 46.638 | G91: =(INT($E$25*3/$D91)-INT($E$25*(3-1)/$D91))*$C91/1000 -> 0 | H91: =(INT($E$25*4/$D91)-INT($E$25*(4-1)/$D91))*$C91/1000 -> 46.638 | I91: =(INT($E$25*5/$D91)-INT($E$25*(5-1)/$D91))*$C91/1000 -> 0 | J91: =(INT($E$25*6/$D91)-INT($E$25*(6-1)/$D91))*$C91/1000 -> 46.638 | K91: =(INT($E$25*7/$D91)-INT($E$25*(7-1)/$D91))*$C91/1000 -> 0 | L91: =(INT($E$25*8/$D91)-INT($E$25*(8-1)/$D91))*$C91/1000 -> 46.638 | M91: =(INT($E$25*9/$D91)-INT($E$25*(9-1)/$D91))*$C91/1000 -> 0 | N91: =(INT($E$25*10/$D91)-INT($E$25*(10-1)/$D91))*$C91/1000 -> 46.638
B92: KIT, SEAL (ремкомплект к цилиндру пода | C92: 4240.92 | D92: 7450 | E92: =(INT($E$25*1/$D92)-INT($E$25*(1-1)/$D92))*$C92/1000 -> 0 | F92: =(INT($E$25*2/$D92)-INT($E$25*(2-1)/$D92))*$C92/1000 -> 4.24092 | G92: =(INT($E$25*3/$D92)-INT($E$25*(3-1)/$D92))*$C92/1000 -> 4.24092 | H92: =(INT($E$25*4/$D92)-INT($E$25*(4-1)/$D92))*$C92/1000 -> 4.24092 | I92: =(INT($E$25*5/$D92)-INT($E$25*(5-1)/$D92))*$C92/1000 -> 4.24092 | J92: =(INT($E$25*6/$D92)-INT($E$25*(6-1)/$D92))*$C92/1000 -> 4.24092 | K92: =(INT($E$25*7/$D92)-INT($E$25*(7-1)/$D92))*$C92/1000 -> 4.24092 | L92: =(INT($E$25*8/$D92)-INT($E$25*(8-1)/$D92))*$C92/1000 -> 4.24092 | M92: =(INT($E$25*9/$D92)-INT($E$25*(9-1)/$D92))*$C92/1000 -> 4.24092 | N92: =(INT($E$25*10/$D92)-INT($E$25*(10-1)/$D92))*$C92/1000 -> 4.24092
B93: SEAL KIT,CYLINDER (ремкомплект к цил.д | C93: 4242.92 | D93: 7450 | E93: =(INT($E$25*1/$D93)-INT($E$25*(1-1)/$D93))*$C93/1000 -> 0 | F93: =(INT($E$25*2/$D93)-INT($E$25*(2-1)/$D93))*$C93/1000 -> 4.24292 | G93: =(INT($E$25*3/$D93)-INT($E$25*(3-1)/$D93))*$C93/1000 -> 4.24292 | H93: =(INT($E$25*4/$D93)-INT($E$25*(4-1)/$D93))*$C93/1000 -> 4.24292 | I93: =(INT($E$25*5/$D93)-INT($E$25*(5-1)/$D93))*$C93/1000 -> 4.24292 | J93: =(INT($E$25*6/$D93)-INT($E$25*(6-1)/$D93))*$C93/1000 -> 4.24292 | K93: =(INT($E$25*7/$D93)-INT($E$25*(7-1)/$D93))*$C93/1000 -> 4.24292 | L93: =(INT($E$25*8/$D93)-INT($E$25*(8-1)/$D93))*$C93/1000 -> 4.24292 | M93: =(INT($E$25*9/$D93)-INT($E$25*(9-1)/$D93))*$C93/1000 -> 4.24292 | N93: =(INT($E$25*10/$D93)-INT($E$25*(10-1)/$D93))*$C93/1000 -> 4.24292
B94: KIT, SEAL (ремкомплект к цилиндру п. м | C94: 3464.48 | D94: 6000 | E94: =(INT($E$25*1/$D94)-INT($E$25*(1-1)/$D94))*$C94/1000 -> 3.46448 | F94: =(INT($E$25*2/$D94)-INT($E$25*(2-1)/$D94))*$C94/1000 -> 3.46448 | G94: =(INT($E$25*3/$D94)-INT($E$25*(3-1)/$D94))*$C94/1000 -> 3.46448 | H94: =(INT($E$25*4/$D94)-INT($E$25*(4-1)/$D94))*$C94/1000 -> 3.46448 | I94: =(INT($E$25*5/$D94)-INT($E$25*(5-1)/$D94))*$C94/1000 -> 3.46448 | J94: =(INT($E$25*6/$D94)-INT($E$25*(6-1)/$D94))*$C94/1000 -> 6.92896 | K94: =(INT($E$25*7/$D94)-INT($E$25*(7-1)/$D94))*$C94/1000 -> 3.46448 | L94: =(INT($E$25*8/$D94)-INT($E$25*(8-1)/$D94))*$C94/1000 -> 3.46448 | M94: =(INT($E$25*9/$D94)-INT($E$25*(9-1)/$D94))*$C94/1000 -> 3.46448 | N94: =(INT($E$25*10/$D94)-INT($E$25*(10-1)/$D94))*$C94/1000 -> 3.46448
B95: SEAL KIT (ремкомплектгидроцилиндр мех. | C95: 237.18 | D95: 6000 | E95: =(INT($E$25*1/$D95)-INT($E$25*(1-1)/$D95))*$C95/1000 -> 0.23718 | F95: =(INT($E$25*2/$D95)-INT($E$25*(2-1)/$D95))*$C95/1000 -> 0.23718 | G95: =(INT($E$25*3/$D95)-INT($E$25*(3-1)/$D95))*$C95/1000 -> 0.23718 | H95: =(INT($E$25*4/$D95)-INT($E$25*(4-1)/$D95))*$C95/1000 -> 0.23718 | I95: =(INT($E$25*5/$D95)-INT($E$25*(5-1)/$D95))*$C95/1000 -> 0.23718 | J95: =(INT($E$25*6/$D95)-INT($E$25*(6-1)/$D95))*$C95/1000 -> 0.47436 | K95: =(INT($E$25*7/$D95)-INT($E$25*(7-1)/$D95))*$C95/1000 -> 0.23718 | L95: =(INT($E$25*8/$D95)-INT($E$25*(8-1)/$D95))*$C95/1000 -> 0.23718 | M95: =(INT($E$25*9/$D95)-INT($E$25*(9-1)/$D95))*$C95/1000 -> 0.23718 | N95: =(INT($E$25*10/$D95)-INT($E$25*(10-1)/$D95))*$C95/1000 -> 0.23718
B96: KIT,SEAL (ремкомплект цилиндра ключа) | C96: 102.66 | D96: 4000 | E96: =(INT($E$25*1/$D96)-INT($E$25*(1-1)/$D96))*$C96/1000 -> 0.10266 | F96: =(INT($E$25*2/$D96)-INT($E$25*(2-1)/$D96))*$C96/1000 -> 0.20532 | G96: =(INT($E$25*3/$D96)-INT($E$25*(3-1)/$D96))*$C96/1000 -> 0.20532 | H96: =(INT($E$25*4/$D96)-INT($E$25*(4-1)/$D96))*$C96/1000 -> 0.20532 | I96: =(INT($E$25*5/$D96)-INT($E$25*(5-1)/$D96))*$C96/1000 -> 0.10266 | J96: =(INT($E$25*6/$D96)-INT($E$25*(6-1)/$D96))*$C96/1000 -> 0.20532 | K96: =(INT($E$25*7/$D96)-INT($E$25*(7-1)/$D96))*$C96/1000 -> 0.20532 | L96: =(INT($E$25*8/$D96)-INT($E$25*(8-1)/$D96))*$C96/1000 -> 0.20532 | M96: =(INT($E$25*9/$D96)-INT($E$25*(9-1)/$D96))*$C96/1000 -> 0.10266 | N96: =(INT($E$25*10/$D96)-INT($E$25*(10-1)/$D96))*$C96/1000 -> 0.20532
B97: SEAL KIT (ремкомплект цилиндра мех.зам | C97: 110.66 | D97: 4000 | E97: =(INT($E$25*1/$D97)-INT($E$25*(1-1)/$D97))*$C97/1000 -> 0.11066 | F97: =(INT($E$25*2/$D97)-INT($E$25*(2-1)/$D97))*$C97/1000 -> 0.22132 | G97: =(INT($E$25*3/$D97)-INT($E$25*(3-1)/$D97))*$C97/1000 -> 0.22132 | H97: =(INT($E$25*4/$D97)-INT($E$25*(4-1)/$D97))*$C97/1000 -> 0.22132 | I97: =(INT($E$25*5/$D97)-INT($E$25*(5-1)/$D97))*$C97/1000 -> 0.11066 | J97: =(INT($E$25*6/$D97)-INT($E$25*(6-1)/$D97))*$C97/1000 -> 0.22132 | K97: =(INT($E$25*7/$D97)-INT($E$25*(7-1)/$D97))*$C97/1000 -> 0.22132 | L97: =(INT($E$25*8/$D97)-INT($E$25*(8-1)/$D97))*$C97/1000 -> 0.22132 | M97: =(INT($E$25*9/$D97)-INT($E$25*(9-1)/$D97))*$C97/1000 -> 0.11066 | N97: =(INT($E$25*10/$D97)-INT($E$25*(10-1)/$D97))*$C97/1000 -> 0.22132
B98: SEAL KIT (ремкомплект к гидроцил.стопо | C98: 92.04 | D98: 5000 | E98: =(INT($E$25*1/$D98)-INT($E$25*(1-1)/$D98))*$C98/1000 -> 0.09204 | F98: =(INT($E$25*2/$D98)-INT($E$25*(2-1)/$D98))*$C98/1000 -> 0.09204 | G98: =(INT($E$25*3/$D98)-INT($E$25*(3-1)/$D98))*$C98/1000 -> 0.18408 | H98: =(INT($E$25*4/$D98)-INT($E$25*(4-1)/$D98))*$C98/1000 -> 0.09204 | I98: =(INT($E$25*5/$D98)-INT($E$25*(5-1)/$D98))*$C98/1000 -> 0.18408 | J98: =(INT($E$25*6/$D98)-INT($E$25*(6-1)/$D98))*$C98/1000 -> 0.09204 | K98: =(INT($E$25*7/$D98)-INT($E$25*(7-1)/$D98))*$C98/1000 -> 0.09204 | L98: =(INT($E$25*8/$D98)-INT($E$25*(8-1)/$D98))*$C98/1000 -> 0.18408 | M98: =(INT($E$25*9/$D98)-INT($E$25*(9-1)/$D98))*$C98/1000 -> 0.09204 | N98: =(INT($E$25*10/$D98)-INT($E$25*(10-1)/$D98))*$C98/1000 -> 0.18408
B99: SEAL KIT (ремкомплект гидроцил.фартука | C99: 123.9 | D99: 4000 | E99: =(INT($E$25*1/$D99)-INT($E$25*(1-1)/$D99))*$C99/1000 -> 0.1239 | F99: =(INT($E$25*2/$D99)-INT($E$25*(2-1)/$D99))*$C99/1000 -> 0.2478 | G99: =(INT($E$25*3/$D99)-INT($E$25*(3-1)/$D99))*$C99/1000 -> 0.2478 | H99: =(INT($E$25*4/$D99)-INT($E$25*(4-1)/$D99))*$C99/1000 -> 0.2478 | I99: =(INT($E$25*5/$D99)-INT($E$25*(5-1)/$D99))*$C99/1000 -> 0.1239 | J99: =(INT($E$25*6/$D99)-INT($E$25*(6-1)/$D99))*$C99/1000 -> 0.2478 | K99: =(INT($E$25*7/$D99)-INT($E$25*(7-1)/$D99))*$C99/1000 -> 0.2478 | L99: =(INT($E$25*8/$D99)-INT($E$25*(8-1)/$D99))*$C99/1000 -> 0.2478 | M99: =(INT($E$25*9/$D99)-INT($E$25*(9-1)/$D99))*$C99/1000 -> 0.1239 | N99: =(INT($E$25*10/$D99)-INT($E$25*(10-1)/$D99))*$C99/1000 -> 0.2478
B100: Ремонт системы смазки | C100: 143.96 | D100: 12000 | E100: =(INT($E$25*1/$D100)-INT($E$25*(1-1)/$D100))*$C100/1000 -> 0 | F100: =(INT($E$25*2/$D100)-INT($E$25*(2-1)/$D100))*$C100/1000 -> 0.14396 | G100: =(INT($E$25*3/$D100)-INT($E$25*(3-1)/$D100))*$C100/1000 -> 0 | H100: =(INT($E$25*4/$D100)-INT($E$25*(4-1)/$D100))*$C100/1000 -> 0.14396 | I100: =(INT($E$25*5/$D100)-INT($E$25*(5-1)/$D100))*$C100/1000 -> 0 | J100: =(INT($E$25*6/$D100)-INT($E$25*(6-1)/$D100))*$C100/1000 -> 0.14396 | K100: =(INT($E$25*7/$D100)-INT($E$25*(7-1)/$D100))*$C100/1000 -> 0.14396 | L100: =(INT($E$25*8/$D100)-INT($E$25*(8-1)/$D100))*$C100/1000 -> 0 | M100: =(INT($E$25*9/$D100)-INT($E$25*(9-1)/$D100))*$C100/1000 -> 0.14396 | N100: =(INT($E$25*10/$D100)-INT($E$25*(10-1)/$D100))*$C100/1000 -> 0
... B104: Инспекция металлоконструкций | C104: 12637.39 | D104: 65000 | E104: =(INT($E$25*1/$D104)-INT($E$25*(1-1)/$D104))*$C104/1000 -> 0 | F104: =(INT($E$25*2/$D104)-INT($E$25*(2-1)/$D104))*$C104/1000 -> 0 | G104: =(INT($E$25*3/$D104)-INT($E$25*(3-1)/$D104))*$C104/1000 -> 0 | H104: =(INT($E$25*4/$D104)-INT($E$25*(4-1)/$D104))*$C104/1000 -> 0 | I104: =(INT($E$25*5/$D104)-INT($E$25*(5-1)/$D104))*$C104/1000 -> 0 | J104: =(INT($E$25*6/$D104)-INT($E$25*(6-1)/$D104))*$C104/1000 -> 0 | K104: =(INT($E$25*7/$D104)-INT($E$25*(7-1)/$D104))*$C104/1000 -> 0 | L104: =(INT($E$25*8/$D104)-INT($E$25*(8-1)/$D104))*$C104/1000 -> 0 | M104: =(INT($E$25*9/$D104)-INT($E$25*(9-1)/$D104))*$C104/1000 -> 0 | N104: =(INT($E$25*10/$D104)-INT($E$25*(10-1)/$D104))*$C104/1000 -> 12.63739
B105: ИТОГО | E105: =SUM(E89:E104) -> 4.50682 | F105: =SUM(F89:F104) -> 60.10984 | G105: =SUM(G89:G104) -> 145.1624 | H105: =SUM(H89:H104) -> 60.10984 | I105: =SUM(I89:I104) -> 144.82518 | J105: =SUM(J89:J104) -> 67.22701 | K105: =SUM(K89:K104) -> 145.21432 | L105: =SUM(L89:L104) -> 60.05792 | ... N105: =SUM(N89:N104) -> 105.58931
B107: ТЕКУЩИЕ РЕМОНТЫ — ТРУДОЗАТРАТЫ (по ресурсу)
B108: Наименование | C108: нормо-час/событие | D108: ресурс, м/ч | E108: год 1 | F108: год 2 | G108: год 3 | H108: год 4 | I108: год 5 | J108: год 6 | K108: год 7 | L108: год 8 | M108: год 9 | N108: год 10
B109: ENG (двигатель капремонт) | C109: 56 | D109: 15000 | E109: =(INT($E$25*1/$D109)-INT($E$25*(1-1)/$D109))*$C109 -> 0 | F109: =(INT($E$25*2/$D109)-INT($E$25*(2-1)/$D109))*$C109 -> 0 | G109: =(INT($E$25*3/$D109)-INT($E$25*(3-1)/$D109))*$C109 -> 56 | H109: =(INT($E$25*4/$D109)-INT($E$25*(4-1)/$D109))*$C109 -> 0 | I109: =(INT($E$25*5/$D109)-INT($E$25*(5-1)/$D109))*$C109 -> 56 | J109: =(INT($E$25*6/$D109)-INT($E$25*(6-1)/$D109))*$C109 -> 0 | K109: =(INT($E$25*7/$D109)-INT($E$25*(7-1)/$D109))*$C109 -> 56 | L109: =(INT($E$25*8/$D109)-INT($E$25*(8-1)/$D109))*$C109 -> 0 | M109: =(INT($E$25*9/$D109)-INT($E$25*(9-1)/$D109))*$C109 -> 56 | N109: =(INT($E$25*10/$D109)-INT($E$25*(10-1)/$D109))*$C109 -> 0
B110: AIREND Seal LP (Компрессор ремкомплект | C110: 4 | D110: 16000 | E110: =(INT($E$25*1/$D110)-INT($E$25*(1-1)/$D110))*$C110 -> 0 | F110: =(INT($E$25*2/$D110)-INT($E$25*(2-1)/$D110))*$C110 -> 0 | G110: =(INT($E$25*3/$D110)-INT($E$25*(3-1)/$D110))*$C110 -> 4 | H110: =(INT($E$25*4/$D110)-INT($E$25*(4-1)/$D110))*$C110 -> 0 | I110: =(INT($E$25*5/$D110)-INT($E$25*(5-1)/$D110))*$C110 -> 4 | J110: =(INT($E$25*6/$D110)-INT($E$25*(6-1)/$D110))*$C110 -> 0 | K110: =(INT($E$25*7/$D110)-INT($E$25*(7-1)/$D110))*$C110 -> 4 | L110: =(INT($E$25*8/$D110)-INT($E$25*(8-1)/$D110))*$C110 -> 0 | M110: =(INT($E$25*9/$D110)-INT($E$25*(9-1)/$D110))*$C110 -> 0 | N110: =(INT($E$25*10/$D110)-INT($E$25*(10-1)/$D110))*$C110 -> 4
B111: ROTARYHEAD (Ремкомплект вращателя | C111: 8 | D111: 13000 | E111: =(INT($E$25*1/$D111)-INT($E$25*(1-1)/$D111))*$C111 -> 0 | F111: =(INT($E$25*2/$D111)-INT($E$25*(2-1)/$D111))*$C111 -> 8 | G111: =(INT($E$25*3/$D111)-INT($E$25*(3-1)/$D111))*$C111 -> 0 | H111: =(INT($E$25*4/$D111)-INT($E$25*(4-1)/$D111))*$C111 -> 8 | I111: =(INT($E$25*5/$D111)-INT($E$25*(5-1)/$D111))*$C111 -> 0 | J111: =(INT($E$25*6/$D111)-INT($E$25*(6-1)/$D111))*$C111 -> 8 | K111: =(INT($E$25*7/$D111)-INT($E$25*(7-1)/$D111))*$C111 -> 0 | L111: =(INT($E$25*8/$D111)-INT($E$25*(8-1)/$D111))*$C111 -> 8 | M111: =(INT($E$25*9/$D111)-INT($E$25*(9-1)/$D111))*$C111 -> 0 | N111: =(INT($E$25*10/$D111)-INT($E$25*(10-1)/$D111))*$C111 -> 8
B112: KIT, SEAL (ремкомплект к цилиндру пода | C112: 36 | D112: 7450 | E112: =(INT($E$25*1/$D112)-INT($E$25*(1-1)/$D112))*$C112 -> 0 | F112: =(INT($E$25*2/$D112)-INT($E$25*(2-1)/$D112))*$C112 -> 36 | G112: =(INT($E$25*3/$D112)-INT($E$25*(3-1)/$D112))*$C112 -> 36 | H112: =(INT($E$25*4/$D112)-INT($E$25*(4-1)/$D112))*$C112 -> 36 | I112: =(INT($E$25*5/$D112)-INT($E$25*(5-1)/$D112))*$C112 -> 36 | J112: =(INT($E$25*6/$D112)-INT($E$25*(6-1)/$D112))*$C112 -> 36 | K112: =(INT($E$25*7/$D112)-INT($E$25*(7-1)/$D112))*$C112 -> 36 | L112: =(INT($E$25*8/$D112)-INT($E$25*(8-1)/$D112))*$C112 -> 36 | M112: =(INT($E$25*9/$D112)-INT($E$25*(9-1)/$D112))*$C112 -> 36 | N112: =(INT($E$25*10/$D112)-INT($E$25*(10-1)/$D112))*$C112 -> 36
B113: SEAL KIT,CYLINDER (ремкомплект к цил.д | C113: 72 | D113: 7450 | E113: =(INT($E$25*1/$D113)-INT($E$25*(1-1)/$D113))*$C113 -> 0 | F113: =(INT($E$25*2/$D113)-INT($E$25*(2-1)/$D113))*$C113 -> 72 | G113: =(INT($E$25*3/$D113)-INT($E$25*(3-1)/$D113))*$C113 -> 72 | H113: =(INT($E$25*4/$D113)-INT($E$25*(4-1)/$D113))*$C113 -> 72 | I113: =(INT($E$25*5/$D113)-INT($E$25*(5-1)/$D113))*$C113 -> 72 | J113: =(INT($E$25*6/$D113)-INT($E$25*(6-1)/$D113))*$C113 -> 72 | K113: =(INT($E$25*7/$D113)-INT($E$25*(7-1)/$D113))*$C113 -> 72 | L113: =(INT($E$25*8/$D113)-INT($E$25*(8-1)/$D113))*$C113 -> 72 | M113: =(INT($E$25*9/$D113)-INT($E$25*(9-1)/$D113))*$C113 -> 72 | N113: =(INT($E$25*10/$D113)-INT($E$25*(10-1)/$D113))*$C113 -> 72
B114: KIT, SEAL (ремкомплект к цилиндру п. м | C114: 28 | D114: 6000 | E114: =(INT($E$25*1/$D114)-INT($E$25*(1-1)/$D114))*$C114 -> 28 | F114: =(INT($E$25*2/$D114)-INT($E$25*(2-1)/$D114))*$C114 -> 28 | G114: =(INT($E$25*3/$D114)-INT($E$25*(3-1)/$D114))*$C114 -> 28 | H114: =(INT($E$25*4/$D114)-INT($E$25*(4-1)/$D114))*$C114 -> 28 | I114: =(INT($E$25*5/$D114)-INT($E$25*(5-1)/$D114))*$C114 -> 28 | J114: =(INT($E$25*6/$D114)-INT($E$25*(6-1)/$D114))*$C114 -> 56 | K114: =(INT($E$25*7/$D114)-INT($E$25*(7-1)/$D114))*$C114 -> 28 | L114: =(INT($E$25*8/$D114)-INT($E$25*(8-1)/$D114))*$C114 -> 28 | M114: =(INT($E$25*9/$D114)-INT($E$25*(9-1)/$D114))*$C114 -> 28 | N114: =(INT($E$25*10/$D114)-INT($E$25*(10-1)/$D114))*$C114 -> 28
B115: SEAL KIT (ремкомплектгидроцилиндр мех. | C115: 3.5 | D115: 6000 | E115: =(INT($E$25*1/$D115)-INT($E$25*(1-1)/$D115))*$C115 -> 3.5 | F115: =(INT($E$25*2/$D115)-INT($E$25*(2-1)/$D115))*$C115 -> 3.5 | G115: =(INT($E$25*3/$D115)-INT($E$25*(3-1)/$D115))*$C115 -> 3.5 | H115: =(INT($E$25*4/$D115)-INT($E$25*(4-1)/$D115))*$C115 -> 3.5 | I115: =(INT($E$25*5/$D115)-INT($E$25*(5-1)/$D115))*$C115 -> 3.5 | J115: =(INT($E$25*6/$D115)-INT($E$25*(6-1)/$D115))*$C115 -> 7 | K115: =(INT($E$25*7/$D115)-INT($E$25*(7-1)/$D115))*$C115 -> 3.5 | L115: =(INT($E$25*8/$D115)-INT($E$25*(8-1)/$D115))*$C115 -> 3.5 | M115: =(INT($E$25*9/$D115)-INT($E$25*(9-1)/$D115))*$C115 -> 3.5 | N115: =(INT($E$25*10/$D115)-INT($E$25*(10-1)/$D115))*$C115 -> 3.5
B116: KIT,SEAL (ремкомплект цилиндра ключа) | C116: 3.5 | D116: 4000 | E116: =(INT($E$25*1/$D116)-INT($E$25*(1-1)/$D116))*$C116 -> 3.5 | F116: =(INT($E$25*2/$D116)-INT($E$25*(2-1)/$D116))*$C116 -> 7 | G116: =(INT($E$25*3/$D116)-INT($E$25*(3-1)/$D116))*$C116 -> 7 | H116: =(INT($E$25*4/$D116)-INT($E$25*(4-1)/$D116))*$C116 -> 7 | I116: =(INT($E$25*5/$D116)-INT($E$25*(5-1)/$D116))*$C116 -> 3.5 | J116: =(INT($E$25*6/$D116)-INT($E$25*(6-1)/$D116))*$C116 -> 7 | K116: =(INT($E$25*7/$D116)-INT($E$25*(7-1)/$D116))*$C116 -> 7 | L116: =(INT($E$25*8/$D116)-INT($E$25*(8-1)/$D116))*$C116 -> 7 | M116: =(INT($E$25*9/$D116)-INT($E$25*(9-1)/$D116))*$C116 -> 3.5 | N116: =(INT($E$25*10/$D116)-INT($E$25*(10-1)/$D116))*$C116 -> 7
B117: SEAL KIT (ремкомплект цилиндра мех.зам | C117: 3.5 | D117: 4000 | E117: =(INT($E$25*1/$D117)-INT($E$25*(1-1)/$D117))*$C117 -> 3.5 | F117: =(INT($E$25*2/$D117)-INT($E$25*(2-1)/$D117))*$C117 -> 7 | G117: =(INT($E$25*3/$D117)-INT($E$25*(3-1)/$D117))*$C117 -> 7 | H117: =(INT($E$25*4/$D117)-INT($E$25*(4-1)/$D117))*$C117 -> 7 | I117: =(INT($E$25*5/$D117)-INT($E$25*(5-1)/$D117))*$C117 -> 3.5 | J117: =(INT($E$25*6/$D117)-INT($E$25*(6-1)/$D117))*$C117 -> 7 | K117: =(INT($E$25*7/$D117)-INT($E$25*(7-1)/$D117))*$C117 -> 7 | L117: =(INT($E$25*8/$D117)-INT($E$25*(8-1)/$D117))*$C117 -> 7 | M117: =(INT($E$25*9/$D117)-INT($E$25*(9-1)/$D117))*$C117 -> 3.5 | N117: =(INT($E$25*10/$D117)-INT($E$25*(10-1)/$D117))*$C117 -> 7
B118: SEAL KIT (ремкомплект к гидроцил.стопо | C118: 4 | D118: 5000 | E118: =(INT($E$25*1/$D118)-INT($E$25*(1-1)/$D118))*$C118 -> 4 | F118: =(INT($E$25*2/$D118)-INT($E$25*(2-1)/$D118))*$C118 -> 4 | G118: =(INT($E$25*3/$D118)-INT($E$25*(3-1)/$D118))*$C118 -> 8 | H118: =(INT($E$25*4/$D118)-INT($E$25*(4-1)/$D118))*$C118 -> 4 | I118: =(INT($E$25*5/$D118)-INT($E$25*(5-1)/$D118))*$C118 -> 8 | J118: =(INT($E$25*6/$D118)-INT($E$25*(6-1)/$D118))*$C118 -> 4 | K118: =(INT($E$25*7/$D118)-INT($E$25*(7-1)/$D118))*$C118 -> 4 | L118: =(INT($E$25*8/$D118)-INT($E$25*(8-1)/$D118))*$C118 -> 8 | M118: =(INT($E$25*9/$D118)-INT($E$25*(9-1)/$D118))*$C118 -> 4 | N118: =(INT($E$25*10/$D118)-INT($E$25*(10-1)/$D118))*$C118 -> 8
B119: SEAL KIT (ремкомплект гидроцил.фартука | C119: 0.9 | D119: 4000 | E119: =(INT($E$25*1/$D119)-INT($E$25*(1-1)/$D119))*$C119 -> 0.9 | F119: =(INT($E$25*2/$D119)-INT($E$25*(2-1)/$D119))*$C119 -> 1.8 | G119: =(INT($E$25*3/$D119)-INT($E$25*(3-1)/$D119))*$C119 -> 1.8 | H119: =(INT($E$25*4/$D119)-INT($E$25*(4-1)/$D119))*$C119 -> 1.8 | I119: =(INT($E$25*5/$D119)-INT($E$25*(5-1)/$D119))*$C119 -> 0.9 | J119: =(INT($E$25*6/$D119)-INT($E$25*(6-1)/$D119))*$C119 -> 1.8 | K119: =(INT($E$25*7/$D119)-INT($E$25*(7-1)/$D119))*$C119 -> 1.8 | L119: =(INT($E$25*8/$D119)-INT($E$25*(8-1)/$D119))*$C119 -> 1.8 | M119: =(INT($E$25*9/$D119)-INT($E$25*(9-1)/$D119))*$C119 -> 0.9 | N119: =(INT($E$25*10/$D119)-INT($E$25*(10-1)/$D119))*$C119 -> 1.8
B120: Ремонт системы смазки | C120: 2 | D120: 12000 | E120: =(INT($E$25*1/$D120)-INT($E$25*(1-1)/$D120))*$C120 -> 0 | F120: =(INT($E$25*2/$D120)-INT($E$25*(2-1)/$D120))*$C120 -> 2 | G120: =(INT($E$25*3/$D120)-INT($E$25*(3-1)/$D120))*$C120 -> 0 | H120: =(INT($E$25*4/$D120)-INT($E$25*(4-1)/$D120))*$C120 -> 2 | I120: =(INT($E$25*5/$D120)-INT($E$25*(5-1)/$D120))*$C120 -> 0 | J120: =(INT($E$25*6/$D120)-INT($E$25*(6-1)/$D120))*$C120 -> 2 | K120: =(INT($E$25*7/$D120)-INT($E$25*(7-1)/$D120))*$C120 -> 2 | L120: =(INT($E$25*8/$D120)-INT($E$25*(8-1)/$D120))*$C120 -> 0 | M120: =(INT($E$25*9/$D120)-INT($E$25*(9-1)/$D120))*$C120 -> 2 | N120: =(INT($E$25*10/$D120)-INT($E$25*(10-1)/$D120))*$C120 -> 0
... B124: Инспекция металлоконструкций | C124: 185 | D124: 65000 | E124: =(INT($E$25*1/$D124)-INT($E$25*(1-1)/$D124))*$C124 -> 0 | F124: =(INT($E$25*2/$D124)-INT($E$25*(2-1)/$D124))*$C124 -> 0 | G124: =(INT($E$25*3/$D124)-INT($E$25*(3-1)/$D124))*$C124 -> 0 | H124: =(INT($E$25*4/$D124)-INT($E$25*(4-1)/$D124))*$C124 -> 0 | I124: =(INT($E$25*5/$D124)-INT($E$25*(5-1)/$D124))*$C124 -> 0 | J124: =(INT($E$25*6/$D124)-INT($E$25*(6-1)/$D124))*$C124 -> 0 | K124: =(INT($E$25*7/$D124)-INT($E$25*(7-1)/$D124))*$C124 -> 0 | L124: =(INT($E$25*8/$D124)-INT($E$25*(8-1)/$D124))*$C124 -> 0 | M124: =(INT($E$25*9/$D124)-INT($E$25*(9-1)/$D124))*$C124 -> 0 | N124: =(INT($E$25*10/$D124)-INT($E$25*(10-1)/$D124))*$C124 -> 185
B125: ИТОГО | E125: =SUM(E109:E124) -> 48.4 | F125: =SUM(F109:F124) -> 174.3 | G125: =SUM(G109:G124) -> 228.3 | H125: =SUM(H109:H124) -> 174.3 | I125: =SUM(I109:I124) -> 220.4 | J125: =SUM(J109:J124) -> 255.8 | K125: =SUM(K109:K124) -> 226.3 | L125: =SUM(L109:L124) -> 176.3 | ... N125: =SUM(N109:N124) -> 365.3
B127: КАПИТАЛЬНЫЕ РЕМОНТЫ — ЗАТРАТЫ НА ЗЧ (по ресурсу до замены узла)
B128: Наименование | C128: стоим.замены,вал | D128: ресурс, м/ч | E128: год 1 | F128: год 2 | G128: год 3 | H128: год 4 | I128: год 5 | J128: год 6 | K128: год 7 | L128: год 8 | M128: год 9 | N128: год 10
B129: PUMP,P7,9A CONT (главный насос) | C129: 37124 | D129: 12000 | E129: =(INT($E$25*1/$D129)-INT($E$25*(1-1)/$D129))*$C129/1000 -> 0 | F129: =(INT($E$25*2/$D129)-INT($E$25*(2-1)/$D129))*$C129/1000 -> 37.124 | G129: =(INT($E$25*3/$D129)-INT($E$25*(3-1)/$D129))*$C129/1000 -> 0 | H129: =(INT($E$25*4/$D129)-INT($E$25*(4-1)/$D129))*$C129/1000 -> 37.124 | I129: =(INT($E$25*5/$D129)-INT($E$25*(5-1)/$D129))*$C129/1000 -> 0 | J129: =(INT($E$25*6/$D129)-INT($E$25*(6-1)/$D129))*$C129/1000 -> 37.124 | K129: =(INT($E$25*7/$D129)-INT($E$25*(7-1)/$D129))*$C129/1000 -> 37.124 | L129: =(INT($E$25*8/$D129)-INT($E$25*(8-1)/$D129))*$C129/1000 -> 0 | M129: =(INT($E$25*9/$D129)-INT($E$25*(9-1)/$D129))*$C129/1000 -> 37.124 | N129: =(INT($E$25*10/$D129)-INT($E$25*(10-1)/$D129))*$C129/1000 -> 0
B130: DRIVE SHAFT & BEARING (вал и подшипник | C130: 1226.17 | D130: 11000 | E130: =(INT($E$25*1/$D130)-INT($E$25*(1-1)/$D130))*$C130/1000 -> 0 | F130: =(INT($E$25*2/$D130)-INT($E$25*(2-1)/$D130))*$C130/1000 -> 1.22617 | G130: =(INT($E$25*3/$D130)-INT($E$25*(3-1)/$D130))*$C130/1000 -> 0 | H130: =(INT($E$25*4/$D130)-INT($E$25*(4-1)/$D130))*$C130/1000 -> 1.22617 | I130: =(INT($E$25*5/$D130)-INT($E$25*(5-1)/$D130))*$C130/1000 -> 1.22617 | J130: =(INT($E$25*6/$D130)-INT($E$25*(6-1)/$D130))*$C130/1000 -> 0 | K130: =(INT($E$25*7/$D130)-INT($E$25*(7-1)/$D130))*$C130/1000 -> 1.22617 | L130: =(INT($E$25*8/$D130)-INT($E$25*(8-1)/$D130))*$C130/1000 -> 1.22617 | M130: =(INT($E$25*9/$D130)-INT($E$25*(9-1)/$D130))*$C130/1000 -> 0 | N130: =(INT($E$25*10/$D130)-INT($E$25*(10-1)/$D130))*$C130/1000 -> 1.22617
B131: STROKER,9A ELECTROHYD (сервоприв.) | C131: 18096.84 | D131: 12000 | E131: =(INT($E$25*1/$D131)-INT($E$25*(1-1)/$D131))*$C131/1000 -> 0 | F131: =(INT($E$25*2/$D131)-INT($E$25*(2-1)/$D131))*$C131/1000 -> 18.09684 | G131: =(INT($E$25*3/$D131)-INT($E$25*(3-1)/$D131))*$C131/1000 -> 0 | H131: =(INT($E$25*4/$D131)-INT($E$25*(4-1)/$D131))*$C131/1000 -> 18.09684 | I131: =(INT($E$25*5/$D131)-INT($E$25*(5-1)/$D131))*$C131/1000 -> 0 | J131: =(INT($E$25*6/$D131)-INT($E$25*(6-1)/$D131))*$C131/1000 -> 18.09684 | K131: =(INT($E$25*7/$D131)-INT($E$25*(7-1)/$D131))*$C131/1000 -> 18.09684 | L131: =(INT($E$25*8/$D131)-INT($E$25*(8-1)/$D131))*$C131/1000 -> 0 | M131: =(INT($E$25*9/$D131)-INT($E$25*(9-1)/$D131))*$C131/1000 -> 18.09684 | N131: =(INT($E$25*10/$D131)-INT($E$25*(10-1)/$D131))*$C131/1000 -> 0
B132: PUMP,TRIPLE (лопастной насос) | C132: 6929.74 | D132: 8000 | E132: =(INT($E$25*1/$D132)-INT($E$25*(1-1)/$D132))*$C132/1000 -> 0 | F132: =(INT($E$25*2/$D132)-INT($E$25*(2-1)/$D132))*$C132/1000 -> 6.92974 | G132: =(INT($E$25*3/$D132)-INT($E$25*(3-1)/$D132))*$C132/1000 -> 6.92974 | H132: =(INT($E$25*4/$D132)-INT($E$25*(4-1)/$D132))*$C132/1000 -> 6.92974 | I132: =(INT($E$25*5/$D132)-INT($E$25*(5-1)/$D132))*$C132/1000 -> 6.92974 | J132: =(INT($E$25*6/$D132)-INT($E$25*(6-1)/$D132))*$C132/1000 -> 6.92974 | K132: =(INT($E$25*7/$D132)-INT($E$25*(7-1)/$D132))*$C132/1000 -> 6.92974 | L132: =(INT($E$25*8/$D132)-INT($E$25*(8-1)/$D132))*$C132/1000 -> 6.92974 | M132: =(INT($E$25*9/$D132)-INT($E$25*(9-1)/$D132))*$C132/1000 -> 0 | N132: =(INT($E$25*10/$D132)-INT($E$25*(10-1)/$D132))*$C132/1000 -> 6.92974
B133: VALVE,ASSEMBLY,6 SPOOL (сборка расп.кл | C133: 19766.43 | D133: 25000 | E133: =(INT($E$25*1/$D133)-INT($E$25*(1-1)/$D133))*$C133/1000 -> 0 | F133: =(INT($E$25*2/$D133)-INT($E$25*(2-1)/$D133))*$C133/1000 -> 0 | G133: =(INT($E$25*3/$D133)-INT($E$25*(3-1)/$D133))*$C133/1000 -> 0 | H133: =(INT($E$25*4/$D133)-INT($E$25*(4-1)/$D133))*$C133/1000 -> 19.76643 | I133: =(INT($E$25*5/$D133)-INT($E$25*(5-1)/$D133))*$C133/1000 -> 0 | J133: =(INT($E$25*6/$D133)-INT($E$25*(6-1)/$D133))*$C133/1000 -> 0 | K133: =(INT($E$25*7/$D133)-INT($E$25*(7-1)/$D133))*$C133/1000 -> 0 | L133: =(INT($E$25*8/$D133)-INT($E$25*(8-1)/$D133))*$C133/1000 -> 19.76643 | M133: =(INT($E$25*9/$D133)-INT($E$25*(9-1)/$D133))*$C133/1000 -> 0 | N133: =(INT($E$25*10/$D133)-INT($E$25*(10-1)/$D133))*$C133/1000 -> 0
...

Sheet Поставщик 5
B1: ДАННЫЕ ПОСТАВЩИКА — ВАРИАНТ 5 (ТО и Ремонты — модель по узлам)
B2: Жёлтое — ввод. Зелёное — авто (снизу вверх). ИТОГО ТОиР = (ЗЧ ТО + ЗЧ тек.+кап.ремонтов + сервис) × коэф.калибровки; тянется в «Данные по годам».
B4: Буровой станок: | E4: ='Ввод данных'!H7 -> HIFO 75D (аналог DM75)
B5: Валюта затрат ТОиР: | D5: EUR
B6: Показатель | C6: Ед. | E6: год 1 | F6: год 2 | G6: год 3 | H6: год 4 | I6: год 5 | J6: год 6 | K6: год 7 | L6: год 8 | M6: год 9 | N6: год 10
B7: СВОДКА ПО ГОДАМ (зелёное — авто снизу вверх; тянется в расчёт)
B8: Простои на ТО (авто из интервалов) | C8: ч/год | E8: =E40 -> 636.37233 | F8: =F40 -> 636.37233 | G8: =G40 -> 636.37233 | H8: =H40 -> 636.37233 | I8: =I40 -> 636.37233 | J8: =J40 -> 636.37233 | K8: =K40 -> 636.37233 | L8: =L40 -> 636.37233 | ... N8: =N40 -> 636.37233
B9: Простои в ремонтах (справочно) | C9: ч/год | E9: 85 | F9: 315.66 | G9: 423.65 | H9: 333.06 | I9: 283.55 | J9: 510.36 | K9: 398.41 | L9: 274.9 | M9: 438.21 | N9: 436.2
B10: Ежесменный осмотр (20 мин/смену), справочно | C10: ч/год | E10: =('Параметры'!C27-E8-E9)/'Параметры'!C28*20/60 -> 223.29521 | F10: =('Параметры'!C27-F8-F9)/'Параметры'!C28*20/60 -> 216.88799 | G10: =('Параметры'!C27-G8-G9)/'Параметры'!C28*20/60 -> 213.88827 | H10: =('Параметры'!C27-H8-H9)/'Параметры'!C28*20/60 -> 216.40466 | I10: =('Параметры'!C27-I8-I9)/'Параметры'!C28*20/60 -> 217.77994 | J10: =('Параметры'!C27-J8-J9)/'Параметры'!C28*20/60 -> 211.47966 | K10: =('Параметры'!C27-K8-K9)/'Параметры'!C28*20/60 -> 214.58938 | L10: =('Параметры'!C27-L8-L9)/'Параметры'!C28*20/60 -> 218.02021 | M10: =('Параметры'!C27-M8-M9)/'Параметры'!C28*20/60 -> 213.48382 | N10: =('Параметры'!C27-N8-N9)/'Параметры'!C28*20/60 -> 213.53966
B11: КТГ (техготовность, ВВОД) → «Данные по годам» | C11: коэф. | E11: 0.8932 | F11: 0.867 | G11: 0.8536 | H11: 0.8651 | I11: 0.8702 | J11: 0.8443 | K11: 0.8584 | L11: 0.8706 | M11: 0.8529 | N11: 0.8527
B12: Затраты на ЗЧ ТО (авто из каталога) | C12: тыс.вал/г | E12: =E85 -> 136.07379 | F12: =F85 -> 136.07379 | G12: =G85 -> 136.07379 | H12: =H85 -> 136.07379 | I12: =I85 -> 136.07379 | J12: =J85 -> 136.07379 | K12: =K85 -> 136.07379 | L12: =L85 -> 136.07379 | ... N12: =N85 -> 136.07379
B13: Затраты на ЗЧ текущих ремонтов (по ресурсу) | C13: тыс.вал/г | E13: =E105 -> 4.50682 | F13: =F105 -> 60.10984 | G13: =G105 -> 145.1624 | H13: =H105 -> 60.10984 | I13: =I105 -> 144.82518 | J13: =J105 -> 67.22701 | K13: =K105 -> 145.21432 | L13: =L105 -> 60.05792 | ... N13: =N105 -> 105.58931
B14: Затраты на ЗЧ капремонтов (по ресурсу) | C14: тыс.вал/г | E14: =E188 -> 7.38238 | F14: =F188 -> 204.26495 | G14: =G188 -> 438.81584 | H14: =H188 -> 434.86339 | I14: =I188 -> 610.36746 | J14: =J188 -> 366.36175 | K14: =K188 -> 590.25823 | L14: =L188 -> 224.66392 | ... N14: =N188 -> 283.30237
B15: Трудозатраты ТО (авто) | C15: ч-час/г | E15: =E47 -> 636.37233 | F15: =F47 -> 636.37233 | G15: =G47 -> 636.37233 | H15: =H47 -> 636.37233 | I15: =I47 -> 636.37233 | J15: =J47 -> 636.37233 | K15: =K47 -> 636.37233 | L15: =L47 -> 636.37233 | ... N15: =N47 -> 636.37233
B16: Трудозатраты текущих ремонтов (авто) | C16: ч-час/г | E16: =E125 -> 48.4 | F16: =F125 -> 174.3 | G16: =G125 -> 228.3 | H16: =H125 -> 174.3 | I16: =I125 -> 220.4 | J16: =J125 -> 255.8 | K16: =K125 -> 226.3 | L16: =L125 -> 176.3 | ... N16: =N125 -> 365.3
B17: Трудозатраты капремонтов (авто) | C17: ч-час/г | E17: =E251 -> 36.6 | F17: =F251 -> 192.66 | G17: =G251 -> 330.45 | H17: =H251 -> 188.56 | I17: =I251 -> 267.75 | J17: =J251 -> 319.96 | K17: =K251 -> 300.71 | L17: =L251 -> 155.4 | ... N17: =N251 -> 102.4
B18: Сервис (трудозатраты ТО+ТР+КР) | C18: тыс.вал/г | E18: =(E15+E16+E17)*$E$23/1000 -> 41.762927 | F18: =(F15+F16+F17)*$E$23/1000 -> 58.086639 | G18: =(G15+G16+G17)*$E$23/1000 -> 69.190076 | H18: =(H15+H16+H17)*$E$23/1000 -> 57.849275 | I18: =(I15+I16+I17)*$E$23/1000 -> 65.102779 | J18: =(J15+J16+J17)*$E$23/1000 -> 70.174848 | K18: =(K15+K16+K17)*$E$23/1000 -> 67.352529 | L18: =(L15+L16+L17)*$E$23/1000 -> 56.045307 | ... N18: =(N15+N16+N17)*$E$23/1000 -> 63.918853
B19: Коэффициент калибровки ИТОГО под ТКП | C19: коэф. | E19: 0.8756
B20: ИТОГО ТОиР → «Данные по годам» | C20: тыс.вал/г | E20: =(E12+E13+E14+E18)*$E$19 -> 166.12401 | F20: =(F12+F13+F14+F18)*$E$19 -> 401.49344 | G20: =(G12+G13+G14+G18)*$E$19 -> 691.06039 | H20: =(H12+H13+H14+H18)*$E$19 -> 603.19759 | I20: =(I12+I13+I14+I18)*$E$19 -> 837.39688 | J20: =(J12+J13+J14+J18)*$E$19 -> 560.24162 | K20: =(K12+K13+K14+K18)*$E$19 -> 822.09985 | L20: =(L12+L13+L14+L18)*$E$19 -> 417.52192 | ... N20: =(N12+N13+N14+N18)*$E$19 -> 515.62711
B21: Удельный расход ДТ / энергии | C21: кг(кВт)/час | E21: 75.89 | F21: 75.89 | G21: 75.89 | H21: 75.89 | I21: 75.89 | J21: 75.89 | K21: 75.89 | L21: 75.89 | M21: 75.89 | N21: 75.89
B23: Ставка сервиса | C23: вал/ч·час | E23: 57.893718
B24: РАСЧЁТ ТО (по интервалам обслуживания), ПО ГОДАМ
B25: Наработка по годам | C25: м/час | E25: 7000 | F25: 7000 | G25: 7000 | H25: 7000 | I25: 7000 | J25: 7000 | K25: 7000 | L25: 7000 | M25: 7000 | N25: 7000
B26: Вид ТО | C26: интервал, м/ч | D26: простой/ТО, ч | E26: персонал
B27: ТО-1 | C27: 250 | D27: 10.9 | E27: 1
B28: ТО-2 | C28: 500 | D28: 13.5 | E28: 1
B29: ТО-3 | C29: 1000 | D29: 12.43 | E29: 1
B30: ТО-4 | C30: 2000 | D30: 5.67 | E30: 1
B31: ТО-5 | C31: 3000 | D31: 10.06 | E31: 1
B32: ТО-6 | C32: 5000 | D32: 8.46 | E32: 1
B34: ТО-1: простои, ч/год | C34: ч | E34: =E$25/$C27*$D27 -> 305.2 | F34: =F$25/$C27*$D27 -> 305.2 | G34: =G$25/$C27*$D27 -> 305.2 | H34: =H$25/$C27*$D27 -> 305.2 | I34: =I$25/$C27*$D27 -> 305.2 | J34: =J$25/$C27*$D27 -> 305.2 | K34: =K$25/$C27*$D27 -> 305.2 | L34: =L$25/$C27*$D27 -> 305.2 | ... N34: =N$25/$C27*$D27 -> 305.2
B35: ТО-2: простои, ч/год | C35: ч | E35: =E$25/$C28*$D28 -> 189 | F35: =F$25/$C28*$D28 -> 189 | G35: =G$25/$C28*$D28 -> 189 | H35: =H$25/$C28*$D28 -> 189 | I35: =I$25/$C28*$D28 -> 189 | J35: =J$25/$C28*$D28 -> 189 | K35: =K$25/$C28*$D28 -> 189 | L35: =L$25/$C28*$D28 -> 189 | ... N35: =N$25/$C28*$D28 -> 189
B36: ТО-3: простои, ч/год | C36: ч | E36: =E$25/$C29*$D29 -> 87.01 | F36: =F$25/$C29*$D29 -> 87.01 | G36: =G$25/$C29*$D29 -> 87.01 | H36: =H$25/$C29*$D29 -> 87.01 | I36: =I$25/$C29*$D29 -> 87.01 | J36: =J$25/$C29*$D29 -> 87.01 | K36: =K$25/$C29*$D29 -> 87.01 | L36: =L$25/$C29*$D29 -> 87.01 | ... N36: =N$25/$C29*$D29 -> 87.01
B37: ТО-4: простои, ч/год | C37: ч | E37: =E$25/$C30*$D30 -> 19.845 | F37: =F$25/$C30*$D30 -> 19.845 | G37: =G$25/$C30*$D30 -> 19.845 | H37: =H$25/$C30*$D30 -> 19.845 | I37: =I$25/$C30*$D30 -> 19.845 | J37: =J$25/$C30*$D30 -> 19.845 | K37: =K$25/$C30*$D30 -> 19.845 | L37: =L$25/$C30*$D30 -> 19.845 | ... N37: =N$25/$C30*$D30 -> 19.845
B38: ТО-5: простои, ч/год | C38: ч | E38: =E$25/$C31*$D31 -> 23.473333 | F38: =F$25/$C31*$D31 -> 23.473333 | G38: =G$25/$C31*$D31 -> 23.473333 | H38: =H$25/$C31*$D31 -> 23.473333 | I38: =I$25/$C31*$D31 -> 23.473333 | J38: =J$25/$C31*$D31 -> 23.473333 | K38: =K$25/$C31*$D31 -> 23.473333 | L38: =L$25/$C31*$D31 -> 23.473333 | ... N38: =N$25/$C31*$D31 -> 23.473333
B39: ТО-6: простои, ч/год | C39: ч | E39: =E$25/$C32*$D32 -> 11.844 | F39: =F$25/$C32*$D32 -> 11.844 | G39: =G$25/$C32*$D32 -> 11.844 | H39: =H$25/$C32*$D32 -> 11.844 | I39: =I$25/$C32*$D32 -> 11.844 | J39: =J$25/$C32*$D32 -> 11.844 | K39: =K$25/$C32*$D32 -> 11.844 | L39: =L$25/$C32*$D32 -> 11.844 | ... N39: =N$25/$C32*$D32 -> 11.844
B40: Итого простои ТО | E40: =SUM(E34:E39) -> 636.37233 | F40: =SUM(F34:F39) -> 636.37233 | G40: =SUM(G34:G39) -> 636.37233 | H40: =SUM(H34:H39) -> 636.37233 | I40: =SUM(I34:I39) -> 636.37233 | J40: =SUM(J34:J39) -> 636.37233 | K40: =SUM(K34:K39) -> 636.37233 | L40: =SUM(L34:L39) -> 636.37233 | ... N40: =SUM(N34:N39) -> 636.37233
B41: ТО-1: чел-часы/год | C41: ч-час | E41: =E34*$E27 -> 305.2 | F41: =F34*$E27 -> 305.2 | G41: =G34*$E27 -> 305.2 | H41: =H34*$E27 -> 305.2 | I41: =I34*$E27 -> 305.2 | J41: =J34*$E27 -> 305.2 | K41: =K34*$E27 -> 305.2 | L41: =L34*$E27 -> 305.2 | ... N41: =N34*$E27 -> 305.2
B42: ТО-2: чел-часы/год | C42: ч-час | E42: =E35*$E28 -> 189 | F42: =F35*$E28 -> 189 | G42: =G35*$E28 -> 189 | H42: =H35*$E28 -> 189 | I42: =I35*$E28 -> 189 | J42: =J35*$E28 -> 189 | K42: =K35*$E28 -> 189 | L42: =L35*$E28 -> 189 | ... N42: =N35*$E28 -> 189
B43: ТО-3: чел-часы/год | C43: ч-час | E43: =E36*$E29 -> 87.01 | F43: =F36*$E29 -> 87.01 | G43: =G36*$E29 -> 87.01 | H43: =H36*$E29 -> 87.01 | I43: =I36*$E29 -> 87.01 | J43: =J36*$E29 -> 87.01 | K43: =K36*$E29 -> 87.01 | L43: =L36*$E29 -> 87.01 | ... N43: =N36*$E29 -> 87.01
B44: ТО-4: чел-часы/год | C44: ч-час | E44: =E37*$E30 -> 19.845 | F44: =F37*$E30 -> 19.845 | G44: =G37*$E30 -> 19.845 | H44: =H37*$E30 -> 19.845 | I44: =I37*$E30 -> 19.845 | J44: =J37*$E30 -> 19.845 | K44: =K37*$E30 -> 19.845 | L44: =L37*$E30 -> 19.845 | ... N44: =N37*$E30 -> 19.845
B45: ТО-5: чел-часы/год | C45: ч-час | E45: =E38*$E31 -> 23.473333 | F45: =F38*$E31 -> 23.473333 | G45: =G38*$E31 -> 23.473333 | H45: =H38*$E31 -> 23.473333 | I45: =I38*$E31 -> 23.473333 | J45: =J38*$E31 -> 23.473333 | K45: =K38*$E31 -> 23.473333 | L45: =L38*$E31 -> 23.473333 | ... N45: =N38*$E31 -> 23.473333
B46: ТО-6: чел-часы/год | C46: ч-час | E46: =E39*$E32 -> 11.844 | F46: =F39*$E32 -> 11.844 | G46: =G39*$E32 -> 11.844 | H46: =H39*$E32 -> 11.844 | I46: =I39*$E32 -> 11.844 | J46: =J39*$E32 -> 11.844 | K46: =K39*$E32 -> 11.844 | L46: =L39*$E32 -> 11.844 | ... N46: =N39*$E32 -> 11.844
B47: Итого чел-часы ТО | E47: =SUM(E41:E46) -> 636.37233 | F47: =SUM(F41:F46) -> 636.37233 | G47: =SUM(G41:G46) -> 636.37233 | H47: =SUM(H41:H46) -> 636.37233 | I47: =SUM(I41:I46) -> 636.37233 | J47: =SUM(J41:J46) -> 636.37233 | K47: =SUM(K41:K46) -> 636.37233 | L47: =SUM(L41:L46) -> 636.37233 | ... N47: =SUM(N41:N46) -> 636.37233
B49: КАТАЛОГ ЗАПЧАСТЕЙ ТО (заполняет подрядчик), ПО ГОДАМ
B50: Наименование | C50: цена за ед | D50: кол-во/ТО | P50: № ТО
